Workbook
Name _1B.05.M.010.0010: #REF!
Name _1B.05.M.010.0050: #REF!
Name _1B.05.M.0100.0010: #REF!
Name _1B.05.M.020.0010: #REF!
Name _1B.05.M.020.0020: #REF!
Name _1B.05.M.020.0030: #REF!
Name _1B.05.M.020.0040: #REF!
Name _1B.05.M.030.0010: #REF!
Name _1B.05.M.030.0020: #REF!
Name _1B.05.M.040.0010: #REF!
Name _1B.05.M.050.0010: #REF!
Name _1B.05.M.050.0020: #REF!
Name _1B.05.M.050.0030: #REF!
Name _1B.05.M.060.0020: #REF!
Name _1B.05.M.060.0100: #REF!
Name _1B.05.M.070.0010: #REF!
Name _1B.05.M.070.0020: #REF!
Name _1B.05.M.070.0030: #REF!
Name _1B.05.M.070.0040: #REF!
Name _1B.05.M.070.0050: #REF!
Name _1B.05.M.080.0010: #REF!
Name _1B.05.M.090.0010: #REF!
Name _1B.09.P.010.0010: #REF!
Name _1B.09.P.010.0020: #REF!
Name _1B.09.P.010.0030: #REF!
Name _1B.09.P.010.0040: #REF!
Name _1B.09.P.010.0050: #REF!
Name _1B.09.P.010.0060: #REF!
Name _1B.09.P.010.0070: #REF!
Name _1B.09.P.020.0010: #REF!
Name _1B.09.P.020.0020: #REF!
Name _1B.09.P.020.0030: #REF!
Name _1B.09.P.020.0040: #REF!
Name _1B.09.P.020.0050: #REF!
Name _1B.09.P.020.0060: #REF!
Name _1B.09.P.020.0070: #REF!
Name _1B.09.P.020.0080: #REF!
Name _1B.09.P.020.0090: #REF!
Name _1B.09.P.020.0100: #REF!
Name _1B.09.P.020.0110: #REF!
Name _1B.09.P.020.0120: #REF!
Name _1B.09.P.020.0130: #REF!
Name _1B.09.P.020.0140: #REF!
Name _1B.09.P.020.0150: #REF!
Name _1B.09.P.030.0010: #REF!
Name _1B.09.P.030.0020: #REF!
Name _1B.09.P.030.0030: #REF!
Name _1B.09.P.030.0040: #REF!
Name _1B.09.P.030.0050: #REF!
Name _1B.09.P.030.0060: #REF!
Name _1B.09.P.040.0010: #REF!
Name _1B.09.P.040.0020: #REF!
Name _1B.09.P.040.0030: #REF!
Name _1B.09.P.050.0010: #REF!
Name _1B.09.P.050.0020: #REF!
Name _1B.09.P.060.0010: #REF!
Name _1B.09.P.060.0020: #REF!
Name _1B.09.P.060.0030: #REF!
Name _1B.09.P.060.0040: #REF!
Name _1B.09.P.060.0050: #REF!

Sheet Weekly Progress Report
A1: MODON - Weekly Progress Report - Construction Projects | M1: Dashboard 20-Oct-2026 | AB1: Report No. | AC1: ='General Information'!L2 -> 47.857143 | AF1: Data Date | AG1: ='General Information'!L1 -> 46315
A2: Contract General Information | G2: Key Dates | M2: Cost Summary (SR) | U2: Performance Summary | AA2: Project Scope
A3: Project Name | B3: ='General Information'!C3 -> INFRASTRUCTURE DEVELOPMENT FOR INDUSTRIAL CITY 1 IN JEDDAH | G3: Contract Award | H3: ='General Information'!C12 -> 45963 | I3: Contract Award (Hijri) | J3: ='General Information'!C16 -> 45963 | K3: Revised Completion | L3: ='General Information'!C20 -> 46709 | M3: Original Contract Value | O3: ='Invoice Log'!E3 -> 86782345 | Q3: O&M Value (if any) | S3: ='[36]Invoice Log'!I3 -> 0 | T3: EAC | U3: Plan Value | V3: =K28 -> 0.53183049 | W3: Phys. Plan Value | X3: =W28 -> 0.4698619 | Y3: Quality Score | Z3: ='Quality '!AC11 -> 0.85206897 | AA3: The Scope of Works for the INFRASTRUCTURE DEVELOPMENT FOR INDUSTRIAL CITY 1 IN JEDDAH. This construction works includes but not limited to the followings: (Road works - Storm network - Sewer Network - Potable water network - TSE network - Electrical works - Fence - Bridge - Landscape works)
A4: Project ID | B4: ='General Information'!C4 -> JDH1-02-003 | D4: Stage | E4: ='General Information'!C7 -> Construction | G4: Contract Sign | H4: ='General Information'!C13 -> 45974 | I4: Contract Sign (Hijri) | J4: ='General Information'!C17 -> 45974 | K4: Committed Completion | L4: ='General Information'!C21 -> 46709 | M4: Revised Contract Value | O4: ='Invoice Log'!E4 -> 86782345 | P4: EAC | Q4: Submitted Invoices (Gross Value) | S4: ='Invoice Log'!F33 -> 44851849 | U4: Earn Value | V4: =L28 -> 0.78721045 | W4: Phys. Earn Value | X4: =X28 -> 0.72612176 | Z4: =REPT("¢",IF(INT(+Z3*10)>5,5,INT(+Z3*10)))&REPT("£",IF(INT(+Z3*10)>5,0,5-INT(+Z3*10)))&CHAR(10)&REPT("¢",+IF(INT(+Z3*10)>5,-5+INT(+Z3*10),0))&REPT("£",IF(INT(+Z3*10)>5,10-INT(+Z3*10),5)) -> ¢¢¢¢¢ ¢¢¢££
A5: Contractor | B5: ='General Information'!C5 -> Al Enjaz Company for Trading and Contracting | D5: Status | E5: ='General Information'!C8 -> Active | G5: Site Handover | H5: ='General Information'!C14 -> 45980 | I5: Site Handover (Hijri) | J5: ='General Information'!C18 -> 45980 | K5: Forecast Completion | L5: ='General Information'!C22 -> 46893 | M5: Estimate At Completion Value | O5: ='Invoice Log'!E5 -> 86782345 | P5: =+#REF!+#REF!+O5 -> #REF! | Q5: Penalities | S5: ='Invoice Log'!M6 -> 0 | U5: Variance | V5: =V4-V3 -> 0.25537996 | W5: Variance | X5: =X4-X3 -> 0.25625986 | Y5: Safety Score | Z5: =HSE!AE6 -> 0.77173913
A6: Consultant | B6: ='General Information'!C6 -> Saudi Arabia Consulting Engineering Company "EGIS" | D6: Modon PM | E6: ='General Information'!C9 -> Engr.Abdallah Aljulayfi | G6: Original Completion | H6: ='General Information'!C15 -> 46709 | I6: Original Completion (Hijri) | J6: ='General Information'!C19 -> 46709 | K6: Variance | L6: ='General Information'!C23 -> -184 | M6: Potential Changes | O6: =O4-O5 -> 0 | Q6: FIR Value (Todate) | S6: =MAX('Invoice Ammount FIR'!C3:C46) -> 57162747 | U6: FIR % | V6: =S6/O4 -> 0.65869097 | W6: Invoiced % | X6: =S4/O4 -> 0.5168315 | Z6: =REPT("¢",IF(INT(+Z5*10)>5,5,INT(+Z5*10)))&REPT("£",IF(INT(+Z5*10)>5,0,5-INT(+Z5*10)))&CHAR(10)&REPT("¢",+IF(INT(+Z5*10)>5,-5+INT(+Z5*10),0))&REPT("£",IF(INT(+Z5*10)>5,10-INT(+Z5*10),5)) -> ¢¢¢¢¢ ¢¢£££
A8: Progress Overview
A9: Earned Value Progress (SAR) | O9: Physical Progress (Effort) | AA9: Earned Value Progress (%)
A10: WBS | C10: BOQ Value (SAR) | D10: % Wt. | E10: Weekly (SAR) | G10: To Date (SAR) | O10: Budgeted | P10: % Wt. | Q10: Weekly Physical Progress | U10: To Date Physical Progress
E11: Planned | F11: Earned | G11: Original Plan | H11: Revised Planned | I11: Earned | J11: Original Plan % | K11: Revised Planned % | L11: Earned % | M11: Variance | N11: SPI | O11: (Manhours) | Q11: Planned | R11: Earned | S11: Plan % | T11: Earned % | U11: Planned | V11: Earned | W11: Plan % | X11: Earned % | Y11: Variance | Z11: SPI
C12: =Progress!C7 -> 0 | D12: =Progress!D7 -> 0 | E12: =Progress!E18 -> 88958.71 | F12: =Progress!F18 -> 0 | G12: =Progress!G18 -> 2119815.9 | H12: =Progress!H18 -> 2208774.6 | I12: =Progress!I18 -> 5352415.6 | J12: =IFERROR(IF(ISBLANK(G12),"",G12/C12),0) -> 0 | K12: =IFERROR(IF(ISBLANK(H12),"",H12/C12),0) -> 0 | L12: =IFERROR(IF(ISBLANK(I12),"",I12/C12),0) -> 0 | M12: =IFERROR(L12-K12,"") -> 0 | N12: =IFERROR(L12/K12,"") | P12: =IF(ISBLANK(O12),"",O12/$O$28)
A13: =Progress!A7 -> Mobilization | C13: =Progress!C7 -> 0 | D13: =Progress!D7 -> 0 | E13: =Progress!E7 -> 0 | F13: =Progress!F7 -> 0 | G13: =Progress!G7 -> 0 | H13: =Progress!H7 -> 0 | I13: =Progress!I7 -> 0 | J13: =IFERROR(IF(ISBLANK(G13),"",G13/C13),0) -> 0 | K13: =IFERROR(IF(ISBLANK(H13),"",H13/C13),0) -> 0 | L13: =IFERROR(IF(ISBLANK(I13),"",I13/C13),0) -> 0 | M13: =IFERROR(L13-K13,"") -> 0 | N13: =IFERROR(L13/K13,"") | O13: =Progress!L7 -> 20050 | P13: =IF(ISBLANK(O13),"",O13/$O$28) -> 0.028059176 | Q13: =Progress!N7 -> 0 | R13: =Progress!O7 -> 0 | S13: =IFERROR(IF(ISBLANK(Q13),"",Q13/O13),0) -> 0 | T13: =IFERROR(IF(ISBLANK(R13),"",R13/O13),0) -> 0 | U13: =Progress!P7 -> 20050 | V13: =Progress!Q7 -> 20050 | W13: =IFERROR(IF(ISBLANK(U13),"",U13/O13),0) -> 1 | X13: =IFERROR(IF(ISBLANK(V13),"",V13/O13),0) -> 1 | Y13: =IFERROR(X13-W13,"") -> 0 | Z13: =IFERROR(X13/W13,"") -> 1
A14: =Progress!A8 -> Engineering | C14: =Progress!C8 -> 2601460.4 | D14: =Progress!D8 -> 0.029976839 | E14: =Progress!E8 -> 0 | F14: =Progress!F8 -> 0 | G14: =Progress!G8 -> 2601460.4 | H14: =Progress!H8 -> 2601460.4 | I14: =Progress!I8 -> 2579200.4 | J14: =IFERROR(IF(ISBLANK(G14),"",G14/C14),0) -> 1 | K14: =IFERROR(IF(ISBLANK(H14),"",H14/C14),0) -> 1 | L14: =IFERROR(IF(ISBLANK(I14),"",I14/C14),0) -> 0.99144327 | M14: =IFERROR(L14-K14,"") -> -0.0085567322 | N14: =IFERROR(L14/K14,"") -> 0.99144327 | O14: =Progress!L8 -> 33415 | P14: =IF(ISBLANK(O14),"",O14/$O$28) -> 0.046762961 | Q14: =Progress!N8 -> 0 | R14: =Progress!O8 -> 0 | S14: =IFERROR(IF(ISBLANK(Q14),"",Q14/O14),0) -> 0 | T14: =IFERROR(IF(ISBLANK(R14),"",R14/O14),0) -> 0 | U14: =Progress!P8 -> 33415 | V14: =Progress!Q8 -> 33009.2 | W14: =IFERROR(IF(ISBLANK(U14),"",U14/O14),0) -> 1 | X14: =IFERROR(IF(ISBLANK(V14),"",V14/O14),0) -> 0.98785575 | Y14: =IFERROR(X14-W14,"") -> -0.012144247 | Z14: =IFERROR(X14/W14,"") -> 0.98785575
A15: =Progress!A9 -> Procurement | C15: =Progress!C9 -> 17355662 | D15: =Progress!D9 -> 0.1999907 | E15: =Progress!E9 -> 26504 | F15: =Progress!F9 -> 208500 | G15: =Progress!G9 -> 13492073 | H15: =Progress!H9 -> 13518577 | I15: =Progress!I9 -> 15737880 | J15: =IFERROR(IF(ISBLANK(G15),"",G15/C15),0) -> 0.7773874 | K15: =IFERROR(IF(ISBLANK(H15),"",H15/C15),0) -> 0.77891451 | L15: =IFERROR(IF(ISBLANK(I15),"",I15/C15),0) -> 0.9067865 | M15: =IFERROR(L15-K15,"") -> 0.12787199 | N15: =IFERROR(L15/K15,"") -> 1.1641669 | O15: =Progress!L9 -> 82413.81 | P15: =IF(ISBLANK(O15),"",O15/$O$28) -> 0.11533484 | Q15: =Progress!N9 -> 0 | R15: =Progress!O9 -> 0 | S15: =IFERROR(IF(ISBLANK(Q15),"",Q15/O15),0) -> 0 | T15: =IFERROR(IF(ISBLANK(R15),"",R15/O15),0) -> 0 | U15: =Progress!P9 -> 35843.52 | V15: =Progress!Q9 -> 65032.49 | W15: =IFERROR(IF(ISBLANK(U15),"",U15/O15),0) -> 0.43492128 | X15: =IFERROR(IF(ISBLANK(V15),"",V15/O15),0) -> 0.789097 | Y15: =IFERROR(X15-W15,"") -> 0.35417571 | Z15: =IFERROR(X15/W15,"") -> 1.8143444
A16: =Progress!A10 -> Construction | C16: =Progress!C10 -> 58147531 | D16: =Progress!D10 -> 0.67003872 | E16: =Progress!E10 -> 394580.51 | F16: =Progress!F10 -> 190111.17 | G16: =Progress!G10 -> 29638879 | H16: =Progress!H10 -> 30033459 | I16: =Progress!I10 -> 44572325 | J16: =IFERROR(IF(ISBLANK(G16),"",G16/C16),0) -> 0.50971861 | K16: =IFERROR(IF(ISBLANK(H16),"",H16/C16),0) -> 0.51650446 | L16: =IFERROR(IF(ISBLANK(I16),"",I16/C16),0) -> 0.76653857 | M16: =IFERROR(L16-K16,"") -> 0.2500341 | N16: =IFERROR(L16/K16,"") -> 1.4840889 | O16: =Progress!L10 -> 545268.46 | P16: =IF(ISBLANK(O16),"",O16/$O$28) -> 0.76308147 | Q16: =Progress!N10 -> 5590.01 | R16: =Progress!O10 -> 1907.14 | S16: =IFERROR(IF(ISBLANK(Q16),"",Q16/O16),0) -> 0.010251849 | T16: =IFERROR(IF(ISBLANK(R16),"",R16/O16),0) -> 0.0034976166 | U16: =Progress!P10 -> 246436.59 | V16: =Progress!Q10 -> 390120.29 | W16: =IFERROR(IF(ISBLANK(U16),"",U16/O16),0) -> 0.4519546 | X16: =IFERROR(IF(ISBLANK(V16),"",V16/O16),0) -> 0.71546462 | Y16: =IFERROR(X16-W16,"") -> 0.26351001 | Z16: =IFERROR(X16/W16,"") -> 1.5830453
A17: =Progress!A11 -> Site Demolition | C17: =Progress!C11 -> 279942.75 | D17: =Progress!D11 -> 0.003225803 | E17: =Progress!E11 -> 0 | F17: =Progress!F11 -> 0 | G17: =Progress!G11 -> 279942.75 | H17: =Progress!H11 -> 279942.75 | I17: =Progress!I11 -> 279942.75 | J17: =IFERROR(IF(ISBLANK(G17),"",G17/C17),0) -> 1 | K17: =IFERROR(IF(ISBLANK(H17),"",H17/C17),0) -> 1 | L17: =IFERROR(IF(ISBLANK(I17),"",I17/C17),0) -> 1 | M17: =IFERROR(L17-K17,"") -> 0 | N17: =IFERROR(L17/K17,"") -> 1 | O17: =Progress!L11 -> 7350 | P17: =IF(ISBLANK(O17),"",O17/$O$28) -> 0.010286032 | Q17: =Progress!N11 -> 0 | R17: =Progress!O11 -> 0 | S17: =IFERROR(IF(ISBLANK(Q17),"",Q17/O17),0) -> 0 | T17: =IFERROR(IF(ISBLANK(R17),"",R17/O17),0) -> 0 | U17: =Progress!P11 -> 7350 | V17: =Progress!Q11 -> 7350 | W17: =IFERROR(IF(ISBLANK(U17),"",U17/O17),0) -> 1 | X17: =IFERROR(IF(ISBLANK(V17),"",V17/O17),0) -> 1 | Y17: =IFERROR(X17-W17,"") -> 0 | Z17: =IFERROR(X17/W17,"") -> 1
A18: =Progress!A12 -> Roads & Meduim Voltage | C18: =Progress!C12 -> 11810039 | D18: =Progress!D12 -> 0.13608803 | E18: =Progress!E12 -> 0 | F18: =Progress!F12 -> 0 | G18: =Progress!G12 -> 11810039 | H18: =Progress!H12 -> 11810039 | I18: =Progress!I12 -> 8650438.8 | J18: =IFERROR(IF(ISBLANK(G18),"",G18/C18),0) -> 1 | K18: =IFERROR(IF(ISBLANK(H18),"",H18/C18),0) -> 1 | L18: =IFERROR(IF(ISBLANK(I18),"",I18/C18),0) -> 0.7324649 | M18: =IFERROR(L18-K18,"") -> -0.2675351 | N18: =IFERROR(L18/K18,"") -> 0.7324649 | O18: =Progress!L12 -> 100175 | P18: =IF(ISBLANK(O18),"",O18/$O$28) -> 0.14019092 | Q18: =Progress!N12 -> 0 | R18: =Progress!O12 -> 0 | S18: =IFERROR(IF(ISBLANK(Q18),"",Q18/O18),0) -> 0 | T18: =IFERROR(IF(ISBLANK(R18),"",R18/O18),0) -> 0 | U18: =Progress!P12 -> 100175 | V18: =Progress!Q12 -> 73591 | W18: =IFERROR(IF(ISBLANK(U18),"",U18/O18),0) -> 1 | X18: =IFERROR(IF(ISBLANK(V18),"",V18/O18),0) -> 0.73462441 | Y18: =IFERROR(X18-W18,"") -> -0.26537559 | Z18: =IFERROR(X18/W18,"") -> 0.73462441
A19: =Progress!A13 -> Deep Infrastructure network | C19: =Progress!C13 -> 10009830 | D19: =Progress!D13 -> 0.11534409 | E19: =Progress!E13 -> 10082.82 | F19: =Progress!F13 -> 7209.5 | G19: =Progress!G13 -> 9958787.2 | H19: =Progress!H13 -> 9968870 | I19: =Progress!I13 -> 9750710.5 | J19: =IFERROR(IF(ISBLANK(G19),"",G19/C19),0) -> 0.99490071 | K19: =IFERROR(IF(ISBLANK(H19),"",H19/C19),0) -> 0.99590801 | L19: =IFERROR(IF(ISBLANK(I19),"",I19/C19),0) -> 0.97411348 | M19: =IFERROR(L19-K19,"") -> -0.021794529 | N19: =IFERROR(L19/K19,"") -> 0.97811592 | O19: =Progress!L13 -> 54025 | P19: =IF(ISBLANK(O19),"",O19/$O$28) -> 0.075605834 | Q19: =Progress!N13 -> 0 | R19: =Progress!O13 -> 0 | S19: =IFERROR(IF(ISBLANK(Q19),"",Q19/O19),0) -> 0 | T19: =IFERROR(IF(ISBLANK(R19),"",R19/O19),0) -> 0 | U19: =Progress!P13 -> 54025 | V19: =Progress!Q13 -> 51820.5 | W19: =IFERROR(IF(ISBLANK(U19),"",U19/O19),0) -> 1 | X19: =IFERROR(IF(ISBLANK(V19),"",V19/O19),0) -> 0.95919482 | Y19: =IFERROR(X19-W19,"") -> -0.040805183 | Z19: =IFERROR(X19/W19,"") -> 0.95919482
A20: =Progress!A14 -> Shallow infrastructure network | C20: =Progress!C14 -> 12539076 | D20: =Progress!D14 -> 0.14448879 | E20: =Progress!E14 -> 209087.15 | F20: =Progress!F14 -> 99253.79 | G20: =Progress!G14 -> 2810927.8 | H20: =Progress!H14 -> 3020015 | I20: =Progress!I14 -> 10453768 | J20: =IFERROR(IF(ISBLANK(G20),"",G20/C20),0) -> 0.22417344 | K20: =IFERROR(IF(ISBLANK(H20),"",H20/C20),0) -> 0.24084828 | L20: =IFERROR(IF(ISBLANK(I20),"",I20/C20),0) -> 0.83369524 | M20: =IFERROR(L20-K20,"") -> 0.59284696 | N20: =IFERROR(L20/K20,"") -> 3.4614955 | O20: =Progress!L14 -> 198577.38 | P20: =IF(ISBLANK(O20),"",O20/$O$28) -> 0.27790113 | Q20: =Progress!N14 -> 4687.15 | R20: =Progress!O14 -> 1717.15 | S20: =IFERROR(IF(ISBLANK(Q20),"",Q20/O20),0) -> 0.023603645 | T20: =IFERROR(IF(ISBLANK(R20),"",R20/O20),0) -> 0.0086472588 | U20: =Progress!P14 -> 43207.03 | V20: =Progress!Q14 -> 154727.25 | W20: =IFERROR(IF(ISBLANK(U20),"",U20/O20),0) -> 0.21758284 | X20: =IFERROR(IF(ISBLANK(V20),"",V20/O20),0) -> 0.77917863 | Y20: =IFERROR(X20-W20,"") -> 0.56159579 | Z20: =IFERROR(X20/W20,"") -> 3.5810666
A21: =Progress!A15 -> Bridge | C21: =Progress!C15 -> 2513307 | D21: =Progress!D15 -> 0.02896104 | E21: =Progress!E15 -> 15291.43 | F21: =Progress!F15 -> 0 | G21: =Progress!G15 -> 1320006.9 | H21: =Progress!H15 -> 1335298.3 | I21: =Progress!I15 -> 1830342.9 | J21: =IFERROR(IF(ISBLANK(G21),"",G21/C21),0) -> 0.52520718 | K21: =IFERROR(IF(ISBLANK(H21),"",H21/C21),0) -> 0.53129137 | L21: =IFERROR(IF(ISBLANK(I21),"",I21/C21),0) -> 0.72826077 | M21: =IFERROR(L21-K21,"") -> 0.1969694 | N21: =IFERROR(L21/K21,"") -> 1.3707371 | O21: =Progress!L15 -> 14022.14 | P21: =IF(ISBLANK(O21),"",O21/$O$28) -> 0.019623426 | Q21: =Progress!N15 -> 171.43 | R21: =Progress!O15 -> 0 | S21: =IFERROR(IF(ISBLANK(Q21),"",Q21/O21),0) -> 0.012225666 | T21: =IFERROR(IF(ISBLANK(R21),"",R21/O21),0) -> 0 | U21: =Progress!P15 -> 7721.43 | V21: =Progress!Q15 -> 12207.14 | W21: =IFERROR(IF(ISBLANK(U21),"",U21/O21),0) -> 0.55065989 | X21: =IFERROR(IF(ISBLANK(V21),"",V21/O21),0) -> 0.87056184 | Y21: =IFERROR(X21-W21,"") -> 0.31990196 | Z21: =IFERROR(X21/W21,"") -> 1.5809429
A22: =Progress!A16 -> Outside Boundary Area (Tie-in Lines) | C22: =Progress!C16 -> 2681726.3 | D22: =Progress!D16 -> 0.030901749 | E22: =Progress!E16 -> 71160.39 | F22: =Progress!F16 -> 0 | G22: =Progress!G16 -> 1339359.5 | H22: =Progress!H16 -> 1410519.9 | I22: =Progress!I16 -> 2663147.2 | J22: =IFERROR(IF(ISBLANK(G22),"",G22/C22),0) -> 0.4994393 | K22: =IFERROR(IF(ISBLANK(H22),"",H22/C22),0) -> 0.52597459 | L22: =IFERROR(IF(ISBLANK(I22),"",I22/C22),0) -> 0.99307196 | M22: =IFERROR(L22-K22,"") -> 0.46709737 | N22: =IFERROR(L22/K22,"") -> 1.8880607 | O22: =Progress!L16 -> 19949.2 | P22: =IF(ISBLANK(O22),"",O22/$O$28) -> 0.02791811 | Q22: =Progress!N16 -> 681.43 | R22: =Progress!O16 -> 0 | S22: =IFERROR(IF(ISBLANK(Q22),"",Q22/O22),0) -> 0.034158262 | T22: =IFERROR(IF(ISBLANK(R22),"",R22/O22),0) -> 0 | U22: =Progress!P16 -> 9933.13 | V22: =Progress!Q16 -> 19885.03 | W22: =IFERROR(IF(ISBLANK(U22),"",U22/O22),0) -> 0.49792122 | X22: =IFERROR(IF(ISBLANK(V22),"",V22/O22),0) -> 0.99678333 | Y22: =IFERROR(X22-W22,"") -> 0.49886211 | Z22: =IFERROR(X22/W22,"") -> 2.0018896
A23: =Progress!A17 -> Roads Finishing | C23: =Progress!C17 -> 8138565 | D23: =Progress!D17 -> 0.093781345 | E23: =Progress!E17 -> 0 | F23: =Progress!F17 -> 83647.88 | G23: =Progress!G17 -> 0 | H23: =Progress!H17 -> 0 | I23: =Progress!I17 -> 5591559.2 | J23: =IFERROR(IF(ISBLANK(G23),"",G23/C23),0) -> 0 | K23: =IFERROR(IF(ISBLANK(H23),"",H23/C23),0) -> 0 | L23: =IFERROR(IF(ISBLANK(I23),"",I23/C23),0) -> 0.68704485 | M23: =IFERROR(L23-K23,"") -> 0.68704485 | N23: =IFERROR(L23/K23,"") | O23: =Progress!L17 -> 65951.79 | P23: =IF(ISBLANK(O23),"",O23/$O$28) -> 0.092296901 | Q23: =Progress!N17 -> 0 | R23: =Progress!O17 -> 190 | S23: =IFERROR(IF(ISBLANK(Q23),"",Q23/O23),0) -> 0 | T23: =IFERROR(IF(ISBLANK(R23),"",R23/O23),0) -> 0.0028808922 | U23: =Progress!P17 -> 0 | V23: =Progress!Q17 -> 45112.37 | W23: =IFERROR(IF(ISBLANK(U23),"",U23/O23),0) -> 0 | X23: =IFERROR(IF(ISBLANK(V23),"",V23/O23),0) -> 0.6840204 | Y23: =IFERROR(X23-W23,"") -> 0.6840204 | Z23: =IFERROR(X23/W23,"")
A24: =Progress!A18 -> Fence and Gate | C24: =Progress!C18 -> 8127691.9 | D24: =Progress!D18 -> 0.093656053 | E24: =Progress!E18 -> 88958.71 | F24: =Progress!F18 -> 0 | G24: =Progress!G18 -> 2119815.9 | H24: =Progress!H18 -> 2208774.6 | I24: =Progress!I18 -> 5352415.6 | J24: =IFERROR(IF(ISBLANK(G24),"",G24/C24),0) -> 0.26081401 | K24: =IFERROR(IF(ISBLANK(H24),"",H24/C24),0) -> 0.27175914 | L24: =IFERROR(IF(ISBLANK(I24),"",I24/C24),0) -> 0.65854066 | M24: =IFERROR(L24-K24,"") -> 0.38678151 | N24: =IFERROR(L24/K24,"") -> 2.4232511 | O24: =Progress!L18 -> 43715 | P24: =IF(ISBLANK(O24),"",O24/$O$28) -> 0.0611774 | Q24: =Progress!N18 -> 50 | R24: =Progress!O18 -> 0 | S24: =IFERROR(IF(ISBLANK(Q24),"",Q24/O24),0) -> 0.0011437722 | T24: =IFERROR(IF(ISBLANK(R24),"",R24/O24),0) -> 0 | U24: =Progress!P18 -> 24025 | V24: =Progress!Q18 -> 25427 | W24: =IFERROR(IF(ISBLANK(U24),"",U24/O24),0) -> 0.54958252 | X24: =IFERROR(IF(ISBLANK(V24),"",V24/O24),0) -> 0.58165389 | Y24: =IFERROR(X24-W24,"") -> 0.032071371 | Z24: =IFERROR(X24/W24,"") -> 1.0583559
... A27: =Progress!A21 -> Project Close-out | C27: =Progress!C21 -> 0 | D27: =Progress!D21 -> 0 | E27: =Progress!E21 -> 0 | F27: =Progress!F21 -> 0 | G27: =Progress!G21 -> 0 | H27: =Progress!H21 -> 0 | I27: =Progress!I21 -> 0 | J27: =IFERROR(IF(ISBLANK(G27),"",G27/C27),0) -> 0 | K27: =IFERROR(IF(ISBLANK(H27),"",H27/C27),0) -> 0 | L27: =IFERROR(IF(ISBLANK(I27),"",I27/C27),0) -> 0 | M27: =IFERROR(L27-K27,"") -> 0 | N27: =IFERROR(L27/K27,"") | O27: =Progress!L21 -> 13364 | P27: =IF(ISBLANK(O27),"",O27/$O$28) -> 0.018702385 | Q27: =Progress!N21 -> 0 | R27: =Progress!O21 -> 0 | S27: =IFERROR(IF(ISBLANK(Q27),"",Q27/O27),0) -> 0 | T27: =IFERROR(IF(ISBLANK(R27),"",R27/O27),0) -> 0 | U27: =Progress!P21 -> 0 | V27: =Progress!Q21 -> 0 | W27: =IFERROR(IF(ISBLANK(U27),"",U27/O27),0) -> 0 | X27: =IFERROR(IF(ISBLANK(V27),"",V27/O27),0) -> 0 | Y27: =IFERROR(X27-W27,"") -> 0 | Z27: =IFERROR(X27/W27,"")
B28: Total | C28: =Progress!C25 -> 86782345 | D28: =Progress!D25 -> 1 | E28: =SUM(E12:E22) -> 815665.01 | F28: =SUM(F12:F22) -> 505074.46 | G28: =Progress!G25 -> 45732412 | H28: =Progress!H25 -> 46153497 | I28: =Progress!I25 -> 68315969 | J28: =IFERROR(IF(ISBLANK(G28),"",G28/C28),0) -> 0.5269783 | K28: =IFERROR(IF(ISBLANK(H28),"",H28/C28),0) -> 0.53183049 | L28: =I28/C28 -> 0.78721045 | M28: =+L28-K28 -> 0.25537996 | N28: =L28/K28 -> 1.4801905 | O28: =Progress!L25 -> 714561.26 | P28: =Progress!M25 -> 1 | Q28: =Progress!N25 -> 5590.01 | R28: =Progress!O25 -> 1907.15 | S28: =IFERROR(IF(ISBLANK(Q28),"",Q28/O28),0) -> 0.0078229962 | T28: =IFERROR(IF(ISBLANK(R28),"",R28/O28),0) -> 0.0026689804 | U28: =Progress!P25 -> 335745.11 | V28: =Progress!Q25 -> 518858.48 | W28: =IFERROR(IF(ISBLANK(U28),"",U28/O28),0) -> 0.4698619 | X28: =IFERROR(IF(ISBLANK(V28),"",V28/O28),0) -> 0.72612176 | Y28: =+X28-W28 -> 0.25625986 | Z28: =X28/W28 -> 1.545394
AA29: Construction Milestones
AA30: Item No. | AB30: Milestones | AD30: Original (Baseline) | AE30: Latest Plan | AF30: Forecast | AG30: Status | AH30: Days Change
AA31: =+Milestones!A4 -> 1 | AB31: =+Milestones!B4 -> Project Finish | AD31: =+Milestones!D4 -> 46886 | AE31: =+Milestones!E4 -> 46893 | AF31: =+Milestones!E4 -> 46893 | AG31: =+Milestones!F4 -> F | AH31: =+Milestones!G4 -> -7
Z32: =+Milestones!#REF! -> #REF! | AA32: =+Milestones!A5 -> 2 | AB32: =+Milestones!B5 -> Project Start | AD32: =+Milestones!D5 -> 45980 | AE32: =+Milestones!E5 -> 45980 | AF32: =+Milestones!E5 -> 45980 | AG32: =+Milestones!F5 -> A | AH32: =+Milestones!G5 -> 0
Z33: =+Milestones!#REF! -> #REF! | AA33: =+Milestones!A6 -> 3 | AB33: =+Milestones!B6 -> Finish Mobilization | AD33: =+Milestones!D6 -> 46085 | AE33: =+Milestones!E6 -> 46085 | AF33: =+Milestones!E6 -> 46085 | AG33: =+Milestones!F6 -> A | AH33: =+Milestones!G6 -> 0
Z34: =+Milestones!#REF! -> #REF! | AA34: =+Milestones!A7 -> 4 | AB34: =+Milestones!B7 -> Finish Baseline Time Schedule | AD34: =+Milestones!D7 -> 46009 | AE34: =+Milestones!E7 -> 46009 | AF34: =+Milestones!E7 -> 46009 | AG34: =+Milestones!F7 -> A | AH34: =+Milestones!G7 -> 0
Z35: =+Milestones!#REF! -> #REF! | AA35: =+Milestones!A8 -> 5 | AB35: =+Milestones!B8 -> Finish Submission and Approval for Shop Drawings, Method of Statement, Prequalification and Materials | AD35: =+Milestones!D8 -> 46326 | AE35: =+Milestones!E8 -> 46333 | AF35: =+Milestones!E8 -> 46333 | AG35: =+Milestones!F8 -> F | AH35: =+Milestones!G8 -> -7
Z36: =+Milestones!#REF! -> #REF! | AA36: =+Milestones!A9 -> 6 | AB36: =+Milestones!B9 -> Finish PO for Short Lead Item & Long Lead Item | AD36: =+Milestones!D9 -> 46320 | AE36: =+Milestones!E9 -> 46327 | AF36: =+Milestones!E9 -> 46327 | AG36: =+Milestones!F9 -> F | AH36: =+Milestones!G9 -> -7
G37: 20000000 | Z37: =+Milestones!#REF! -> #REF! | AA37: =+Milestones!A10 -> 7 | AB37: =+Milestones!B10 -> Completion of Roads & Meduim Voltage | AD37: =+Milestones!D10 -> 46398 | AE37: =+Milestones!E10 -> 46405 | AF37: =+Milestones!E10 -> 46405 | AG37: =+Milestones!F10 -> F | AH37: =+Milestones!G10 -> -7
AA38: =+Milestones!A11 -> 8 | AB38: =+Milestones!B11 -> Completion of Deep infrastructure network | AD38: =+Milestones!D11 -> 46550 | AE38: =+Milestones!E11 -> 46557 | AF38: =+Milestones!E11 -> 46557 | AG38: =+Milestones!F11 -> F | AH38: =+Milestones!G11 -> -7
AA39: =+Milestones!A12 -> 9 | AB39: =+Milestones!B12 -> Completion of Shallow infrastructure network | AD39: =+Milestones!D12 -> 46656 | AE39: =+Milestones!E12 -> 46663 | AF39: =+Milestones!E12 -> 46663 | AG39: =+Milestones!F12 -> F | AH39: =+Milestones!G12 -> -7
Z40: =+Milestones!#REF! -> #REF! | AA40: =+Milestones!A13 -> 10 | AB40: =+Milestones!B13 -> Completion all Works | AD40: =+Milestones!D13 -> 46886 | AE40: =+Milestones!E13 -> 46893 | AF40: =+Milestones!E13 -> 46893 | AG40: =+Milestones!F13 -> F | AH40: =+Milestones!G13 -> -7
Z41: =+Milestones!#REF! -> #REF!
Z42: =+Milestones!#REF! -> #REF!
Z43: =+Milestones!#REF! -> #REF!
Z44: =+Milestones!#REF! -> #REF!
G45: 20000000 | Z45: =+Milestones!#REF! -> #REF!
Z48: =+Milestones!#REF! -> #REF!
Z49: =+Milestones!#REF! -> #REF!
A65: Performance overview
A66: Submittals Status | L66: Quality | W66: Safety
A67: Shop Drawings | L67: Quality Reports | W67: Safety Statistics | AE67: Proactive Vs Reactive Actions Taken
A68: Item Per WBS | C68: Total | D68: Total Submitted Drawings | I68: Remaining | J68: Pending | K68: Total Submittals | L68: Quality Reports | N68: Issued | O68: Closed | P68: Pending | Q68: Avg. Closing (Days) | R68: Pending | W68: Category | X68: Item | Z68: This Week | AB68: This Month | AC68: Year to Date | AD68: Cumulative
D69: A | E69: B | F69: C | G69: D | H69: Processed | R69: 0-10 Days | S69: 11-20 Days | T69: 21-30 Days | U69: 31-60 Days | V69: > 60 Days
A70: Roads | C70: ='Quality-Stat '!D13 -> 268 | D70: ='Quality-Stat '!E13 -> 2 | E70: ='Quality-Stat '!F13 -> 266 | F70: ='Quality-Stat '!G13 -> 0 | G70: ='Quality-Stat '!H13 -> 0 | H70: ='Quality-Stat '!I13 -> 268 | I70: ='Quality-Stat '!J13 -> 0 | J70: ='Quality-Stat '!K13 -> 0 | K70: ='Quality-Stat '!L13 -> 268 | W70: General | X70: Total Hours Worked | Z70: ='HSE-Stat '!D4 -> 9216 | AB70: ='HSE-Stat '!E4 -> 26112 | AC70: ='HSE-Stat '!F4 -> 438898 | AD70: ='HSE-Stat '!G4 -> 465010 | AG70: Proactive | AH70: =+SUM(AD81:AD85) -> 212
A71: General | C71: ='Quality-Stat '!D14 -> 11 | D71: ='Quality-Stat '!E14 -> 0 | E71: ='Quality-Stat '!F14 -> 11 | F71: ='Quality-Stat '!G14 -> 0 | G71: ='Quality-Stat '!H14 -> 0 | H71: ='Quality-Stat '!I14 -> 11 | I71: ='Quality-Stat '!J14 -> 0 | J71: ='Quality-Stat '!K14 -> 0 | K71: ='Quality-Stat '!L14 -> 11 | L71: Non Conformance (NCR) | N71: ='Quality-Stat '!D5 -> 16 | O71: ='Quality-Stat '!I5 -> 16 | P71: ='Quality-Stat '!J5 -> 0 | X71: Safe Hours Worked | Z71: ='HSE-Stat '!D5 -> 9216 | AB71: ='HSE-Stat '!E5 -> 26112 | AC71: ='HSE-Stat '!F5 -> 438898 | AD71: ='HSE-Stat '!G5 -> 465010 | AG71: Reactive | AH71: =SUM(AD72:AD80) -> 0
A72: Structural | C72: ='Quality-Stat '!D15 -> 590 | D72: ='Quality-Stat '!E15 -> 2 | E72: ='Quality-Stat '!F15 -> 588 | F72: ='Quality-Stat '!G15 -> 0 | G72: ='Quality-Stat '!H15 -> 109 | H72: ='Quality-Stat '!I15 -> 480 | I72: ='Quality-Stat '!J15 -> 0 | J72: ='Quality-Stat '!K15 -> 0 | K72: ='Quality-Stat '!L15 -> 590 | L72: Site Instruction (SIR) | N72: ='Quality-Stat '!D6 -> 21 | O72: ='Quality-Stat '!I6 -> 21 | P72: ='Quality-Stat '!J6 -> 0 | W72: Reactive | X72: LTI | Z72: ='HSE-Stat '!D6 -> 0 | AB72: ='HSE-Stat '!E6 -> 0 | AC72: ='HSE-Stat '!F6 -> 0 | AD72: ='HSE-Stat '!G6 -> 0
A73: Architectural | C73: ='Quality-Stat '!D16 -> 2 | D73: ='Quality-Stat '!E16 -> 0 | E73: ='Quality-Stat '!F16 -> 2 | F73: ='Quality-Stat '!G16 -> 0 | G73: ='Quality-Stat '!H16 -> 0 | H73: ='Quality-Stat '!I16 -> 2 | I73: ='Quality-Stat '!J16 -> 0 | J73: ='Quality-Stat '!K16 -> 0 | K73: ='Quality-Stat '!L16 -> 2 | L73: Material Inspection (MIR) | N73: ='Quality-Stat '!D7 -> 100 | O73: ='Quality-Stat '!I7 -> 100 | P73: ='Quality-Stat '!J7 -> 0 | X73: MTC (Healed w/o Disability) | Z73: ='HSE-Stat '!D7 -> 0 | AB73: ='HSE-Stat '!E7 -> 0 | AC73: ='HSE-Stat '!F7 -> 0 | AD73: ='HSE-Stat '!G7 -> 0
A74: Mechanical | C74: ='Quality-Stat '!D17 -> 336 | D74: ='Quality-Stat '!E17 -> 2 | E74: ='Quality-Stat '!F17 -> 397 | F74: ='Quality-Stat '!G17 -> 0 | G74: ='Quality-Stat '!H17 -> 1 | H74: ='Quality-Stat '!I17 -> 264 | I74: ='Quality-Stat '!J17 -> 0 | J74: ='Quality-Stat '!K17 -> 65 | K74: ='Quality-Stat '!L17 -> 406 | L74: Field Inspection (FIR) | N74: ='Quality-Stat '!D8 -> 5477 | O74: ='Quality-Stat '!I8 -> 5427 | P74: ='Quality-Stat '!J8 -> 0 | X74: MTC (Healed w/ Disability) | Z74: ='HSE-Stat '!D8 -> 0 | AB74: ='HSE-Stat '!E8 -> 0 | AC74: ='HSE-Stat '!F8 -> 0 | AD74: ='HSE-Stat '!G8 -> 0
A75: Electrical | C75: ='Quality-Stat '!D18 -> 220 | D75: ='Quality-Stat '!E18 -> 3 | E75: ='Quality-Stat '!F18 -> 214 | F75: ='Quality-Stat '!G18 -> 0 | G75: ='Quality-Stat '!H18 -> 0 | H75: ='Quality-Stat '!I18 -> 220 | I75: ='Quality-Stat '!J18 -> 0 | J75: ='Quality-Stat '!K18 -> 0 | K75: ='Quality-Stat '!L18 -> 220 | L75: Key Submittals Approval Status | X75: Near Miss | Z75: ='HSE-Stat '!D9 -> 0 | AB75: ='HSE-Stat '!E9 -> 0 | AC75: ='HSE-Stat '!F9 -> 0 | AD75: ='HSE-Stat '!G9 -> 0
A76: TOTAL | C76: =SUM(C70:C75) -> 1427 | D76: =SUM(D70:D75) -> 9 | E76: =SUM(E70:E75) -> 1478 | F76: =SUM(F70:F75) -> 0 | G76: =SUM(G70:G75) -> 110 | H76: =SUM(H70:H75) -> 1245 | I76: =SUM(I70:I75) -> 0 | J76: =SUM(J70:J75) -> 65 | K76: =SUM(K70:K75) -> 1497 | L76: 1 Quality Plan Approval | O76: ='General Information'!C27 -> 46062 | Q76: 6 Baseline Approval | U76: ='General Information'!C39 -> 46009 | X76: First Aid Cases | Z76: ='HSE-Stat '!D10 -> 0 | AB76: ='HSE-Stat '!E10 -> 0 | AC76: ='HSE-Stat '!F10 -> 0 | AD76: ='HSE-Stat '!G10 -> 0 | AE76: Total Hours Worked Vs Safe Hours Worked
A77: Material Approval | L77: 2 Quality Plan Last Up | O77: ='General Information'!C28 -> - | Q77: 7 No of Approved Version of Schedule | U77: ='General Information'!C40 -> 1 | X77: Fatality | Z77: ='HSE-Stat '!D11 -> 0 | AB77: ='HSE-Stat '!E11 -> 0 | AC77: ='HSE-Stat '!F11 -> 0 | AD77: ='HSE-Stat '!G11 -> 0
A78: Item Per WBS | C78: Total | D78: Total Submitted Material | I78: Remaining to approve | J78: Pending | K78: Total Submittals | L78: 3 Safety Plan Approval | O78: ='General Information'!C31 -> 46056 | Q78: 8 Last Approved Schedule | U78: ='General Information'!C41 -> - | X78: Fire Incident Cases | Z78: ='HSE-Stat '!D12 -> 0 | AB78: ='HSE-Stat '!E12 -> 0 | AC78: ='HSE-Stat '!F12 -> 0 | AD78: ='HSE-Stat '!G12 -> 0
D79: A | E79: B | F79: C | G79: D | H79: Processed | I79: with Designer | L79: 4 Safety Plan Last Up | O79: ='General Information'!C32 -> - | Q79: 9 BOQ Approval Date | U79: ='General Information'!C44 -> 45980 | X79: Vehicle Incident | Z79: ='HSE-Stat '!D13 -> 0 | AB79: ='HSE-Stat '!E13 -> 0 | AC79: ='HSE-Stat '!F13 -> 0 | AD79: ='HSE-Stat '!G13 -> 0
A80: Civil /Structural /Architectural | C80: ='Quality-Stat '!D25 -> 95 | D80: ='Quality-Stat '!E25 -> 2 | E80: ='Quality-Stat '!F25 -> 90 | F80: ='Quality-Stat '!G25 -> 0 | G80: ='Quality-Stat '!H25 -> 1 | H80: ='Quality-Stat '!I25 -> 92 | I80: ='Quality-Stat '!J25 -> 0 | J80: ='Quality-Stat '!K25 -> 0 | K80: ='Quality-Stat '!L25 -> 95 | L80: 5 Construction Plan Approval | O80: ='General Information'!C48 -> 46058 | Q80: 10 No of Approved Version of BOQ | U80: ='General Information'!C45 -> 0 | X80: Property Damages | Z80: ='HSE-Stat '!D14 -> 0 | AB80: ='HSE-Stat '!E14 -> 0 | AC80: ='HSE-Stat '!F14 -> 0 | AD80: ='HSE-Stat '!G14 -> 0
A81: Mechanical | C81: ='Quality-Stat '!D26 -> 33 | D81: ='Quality-Stat '!E26 -> 2 | E81: ='Quality-Stat '!F26 -> 33 | F81: ='Quality-Stat '!G26 -> 0 | G81: ='Quality-Stat '!H26 -> 0 | H81: ='Quality-Stat '!I26 -> 33 | I81: ='Quality-Stat '!J26 -> 0 | J81: ='Quality-Stat '!K26 -> 0 | K81: ='Quality-Stat '!L26 -> 33 | L81: Invoices Summary | W81: Proactive | X81: Induction Training | Z81: ='HSE-Stat '!D15 -> 0 session | AB81: ='HSE-Stat '!E15 -> 0 session | AC81: ='HSE-Stat '!F15 -> 63 | AD81: ='HSE-Stat '!G15 -> 63
A82: Electrical | C82: ='Quality-Stat '!D27 -> 22 | D82: ='Quality-Stat '!E27 -> 0 | E82: ='Quality-Stat '!F27 -> 16 | F82: ='Quality-Stat '!G27 -> 0 | G82: ='Quality-Stat '!H27 -> 6 | H82: ='Quality-Stat '!I27 -> 16 | I82: ='Quality-Stat '!J27 -> 0 | J82: ='Quality-Stat '!K27 -> 0 | K82: ='Quality-Stat '!L27 -> 22 | L82: Total Submitted Invoices | N82: ='Invoice Log'!U3 -> 6 | O82: Submitted Invoices (SAR) | R82: ='Invoice Log'!Y3 -> 44851849 | T82: Contract Value (SR) | U82: =O4 -> 86782345 | X82: No.of Internal Training | Z82: ='HSE-Stat '!D16 -> 0session | AB82: ='HSE-Stat '!E16 -> 0 session | AC82: ='HSE-Stat '!F16 -> 61 | AD82: ='HSE-Stat '!G16 -> 61
L83: PM Approved Invoices | N83: ='Invoice Log'!U5 -> 7 | O83: PM Approved Invoices (SAR) | R83: ='Invoice Log'!Y5 -> 51579627 | T83: Planned Value (SR) | U83: =H28 -> 46153497 | X83: No.of Internal Audit | Z83: ='HSE-Stat '!D17 -> 0 | AB83: ='HSE-Stat '!E17 -> 0 | AC83: ='HSE-Stat '!F17 -> 0 | AD83: ='HSE-Stat '!G17 -> 0
L84: No of Paid Invoices | N84: ='Invoice Log'!U6 -> 6 | O84: Paid Invoices (SAR) | R84: ='Invoice Log'!Y6 -> 48055958 | T84: Earned Value (SR) | U84: =I28 -> 68315969 | X84: No. of Toolbox Talks | Z84: ='HSE-Stat '!D18 -> 0 sessions | AB84: ='HSE-Stat '!E18 -> 0 sessions | AC84: ='HSE-Stat '!F18 -> 88 | AD84: ='HSE-Stat '!G18 -> 88
A85: TOTAL | C85: =SUM(C80:C84) -> 150 | D85: =SUM(D80:D84) -> 4 | E85: =SUM(E80:E84) -> 139 | F85: =SUM(F80:F84) -> 0 | G85: =SUM(G80:G84) -> 7 | H85: =SUM(H80:H84) -> 141 | I85: =SUM(I80:I84) -> 0 | J85: =SUM(J80:J84) -> 0 | K85: =SUM(K80:K84) -> 150 | L85: No of Pending Invoices | N85: =+N82-N84 -> 0 | O85: Last Submitted Period | R85: ='Invoice Log'!AB3 -> 46294 | T85: Submitted (SAR) | U85: =R82 -> 44851849 | X85: Safety Awards/Incentives | Z85: ='HSE-Stat '!D19 -> 0 | AB85: ='HSE-Stat '!E19 -> 0 | AC85: ='HSE-Stat '!F19 -> 0 | AD85: ='HSE-Stat '!G19 -> 0
A86: Procurement Summary | L86: Advance Payment % | N86: ='Invoice Log'!M3 -> 0 | O86: Advance Payment (SAR) | R86: ='Invoice Log'!Q3 -> 0 | T86: PM Approved (SAR) | U86: =R83 -> 51579627 | W86: Latest Contract Change Order Log
A87: Item Per WBS | C87: Total Materials | D87: Total Number of P.O. | E87: Actual P.O. To Date | F87: Remaining P.O | G87: Material on Site | H87: Remaining Materials | I87: Material Delivery Completion (Date) | L87: Retention % | N87: ='Invoice Log'!M4 -> 0 | O87: Retention (SAR) | R87: ='Invoice Log'!Q4 -> 0 | T87: Total Paid (SAR) | U87: =R84 -> 48055958
D88: A | E88: B | F88: C | G88: D | H88: Processed | L88: Deduction / Penalties % | N88: ='Invoice Log'!M5 -> 0 | O88: Deduction / Penalties (SAR) | R88: ='Invoice Log'!M6 -> 0 | W88: CCO No. | X88: Date Added | Y88: Description of Change | AD88: Status | AE88: Cost | AF88: Sch Impact (Months) | AG88: Date Approved | AH88: Duration
A89: Civil /Structural /Architectural | C89: ='Quality-Stat '!D33 -> 31 | D89: ='Quality-Stat '!E33 -> 31 | E89: ='Quality-Stat '!F33 -> 31 | F89: ='Quality-Stat '!G33 -> 0 | G89: ='Quality-Stat '!H33 -> 28 | H89: ='Quality-Stat '!I33 -> 3 | I89: 46526 | L89: Resources at Site
A90: Mechanical | C90: ='Quality-Stat '!D34 -> 19 | D90: ='Quality-Stat '!E34 -> 19 | E90: ='Quality-Stat '!F34 -> 19 | F90: ='Quality-Stat '!G34 -> 0 | G90: ='Quality-Stat '!H34 -> 19 | H90: ='Quality-Stat '!I34 -> 0 | I90: 46567 | L90: Head Count - Manual | P90: Head Count - Non Manual | T90: Total Head Count | W90: =CCO!A3 -> - | X90: =CCO!B3 -> - | Y90: =CCO!C3 -> - | AD90: =CCO!D3 -> - | AE90: =CCO!E3 -> - | AF90: =CCO!F3 -> - | AG90: =CCO!G3 -> - | AH90: =CCO!H3 -> -
A91: Electrical | C91: ='Quality-Stat '!D35 -> 63 | D91: ='Quality-Stat '!E35 -> 63 | E91: ='Quality-Stat '!F35 -> 58 | F91: ='Quality-Stat '!G35 -> 5 | G91: ='Quality-Stat '!H35 -> 58 | H91: ='Quality-Stat '!I35 -> 5 | I91: 46457 | L91: Planned | M91: Actual | N91: Next Month Forecast | O91: Saudi Staff | P91: Planned | Q91: Actual | R91: Next Month Forecast | S91: Saudi Staff | T91: Total Plan | U91: Total Actual | V91: Variance
L92: =Manpower!A24 -> 148 | M92: =Manpower!B24 -> 130 | N92: =Manpower!F24 -> 187 | O92: =Manpower!H24 -> 0 | P92: =Manpower!A20 -> 22 | Q92: =Manpower!B20 -> 48 | R92: =Manpower!F20 -> 40 | S92: =Manpower!H20 -> 6 | T92: =L92+P92 -> 170 | U92: =M92+Q92 -> 178 | V92: =+U92-T92 -> 8
L93: Manpower Breakdown by Trade | S93: Major Equipment
A94: TOTAL | C94: =SUM(C89:C93) -> 113 | D94: =SUM(D89:D93) -> 113 | E94: =SUM(E89:E93) -> 108 | F94: =SUM(F89:F93) -> 5 | G94: =SUM(G89:G93) -> 105 | H94: =SUM(H89:H93) -> 8 | I94: =MAX(I89:K91) -> 46567 | L94: Key Trade | M94: Planned | N94: Actual | S94: Type | T94: Planned | U94: Actual | V94: Idle
A95: =Schedule!A1 -> Primavera P6 Schedule Status | L95: =+Manpower!N23 -> Labor | M95: =Manpower!N24 -> 40 | N95: =Manpower!N25 -> 17 | S95: =+Manpower!$B$49 -> Excavator | T95: =+Manpower!B50 -> 3 | U95: =+Manpower!B51 -> 4 | V95: =+Manpower!B52 -> 0
A96: =Schedule!A2 -> Project Activities Overview | L96: =+Manpower!P23 -> Skilled Labor | M96: =Manpower!P24 -> 26 | N96: =Manpower!P25 -> 30 | S96: =+Manpower!$D$49 -> Bulldozer | T96: =+Manpower!D50 -> 2 | U96: =+Manpower!D51 -> 1 | V96: =+Manpower!D52 -> 0 | W96: Major Quantity Trackers
A97: =Schedule!A3 -> Schedule Statistics | F97: =Schedule!F3 -> Active Schedule Activities | L97: =+Manpower!R23 -> Driver / Operator | M97: =+Manpower!R24 -> 60 | N97: =Manpower!R25 -> 48 | S97: =+Manpower!$F$49 -> Grader | T97: =+Manpower!F50 -> 4 | U97: =+Manpower!F51 -> 1 | V97: =+Manpower!F52 -> 0 | W97: BOQ N0. | X97: Item Description | AC97: Total Qty | AD97: Measu Unit | AE97: Plan to Date | AF97: Act to Date | AG97: Remaining | AH97: Variance
A98: =Schedule!A4 -> Total Act. | B98: =Schedule!B4 -> Not Started | C98: =Schedule!C4 -> In Progress | D98: =Schedule!D4 -> Completed | E98: =Schedule!E4 -> % | F98: =Schedule!F4 -> Active | G98: =Schedule!G4 -> Ahead | H98: =Schedule!H4 -> On | ... K98: =Schedule!K4 -> 0 | L98: =+Manpower!T23 -> Carpenter | M98: =Manpower!T24 -> 5 | N98: =Manpower!T25 -> 6 | S98: =+Manpower!$H$49 -> Road Roller | T98: =+Manpower!H50 -> 3 | U98: =+Manpower!H51 -> 3 | V98: =+Manpower!H52 -> 0 | W98: ='Major Quantities'!A3 -> 31 22 00.02 | X98: ='Major Quantities'!B3 -> Parcrels Excavation for cuttings (all types of soil) | AC98: ='Major Quantities'!C3 -> 123555 | AD98: ='Major Quantities'!D3 -> m3 | AE98: ='Major Quantities'!E3 -> 123555 | AF98: ='Major Quantities'!F3 -> 123555 | AG98: ='Major Quantities'!G3 -> 0 | AH98: ='Major Quantities'!H3 -> 0
A99: =Schedule!A5 -> 1905 | B99: =Schedule!B5 -> 423 | C99: =Schedule!C5 -> 204 | D99: =Schedule!D5 -> 1278 | E99: =Schedule!E5 -> 0.67086614 | F99: =Schedule!F5 -> 204 | G99: =Schedule!G5 -> 91 | H99: =Schedule!H5 -> 0 | ... J99: =Schedule!J5 -> -22 | L99: =+Manpower!V23 -> Steel Fixer | M99: =+Manpower!V24 -> 5 | N99: =+Manpower!V25 -> 9 | S99: =+Manpower!$J$49 -> Crane | T99: =+Manpower!J50 -> 2 | U99: =+Manpower!J51 -> 1 | V99: =+Manpower!J52 -> 0 | W99: ='Major Quantities'!A6 -> 31 22 00.05 | X99: ='Major Quantities'!B6 -> Subgrade | AC99: ='Major Quantities'!C6 -> 34693.65 | AD99: ='Major Quantities'!D6 -> m3 | AE99: ='Major Quantities'!E6 -> 34693.65 | AF99: ='Major Quantities'!F6 -> 34693.65 | AG99: ='Major Quantities'!G6 -> 0 | AH99: ='Major Quantities'!H6 -> 0
A100: =Schedule!A6 -> Critical Path Activities | D100: =Schedule!D6 -> Free Float Management (Total) | H100: =Schedule!H6 -> Failed Start Activities | L100: =+Manpower!X23 -> Mason | M100: =+Manpower!X24 -> 2 | N100: =+Manpower!X25 -> 0 | S100: =+Manpower!$L$49 -> Aggregate paver | T100: =+Manpower!L50 -> 0 | U100: =+Manpower!L51 -> 0 | V100: =+Manpower!L52 -> 0 | W100: ='Major Quantities'!A8 -> 32 11 26.01 | X100: ='Major Quantities'!B8 -> Bituminous base course (Grading I - Class A), including Prime Coat (MC1) according to drawings | AC100: ='Major Quantities'!C8 -> 8290 | AD100: ='Major Quantities'!D8 -> m3 | AE100: ='Major Quantities'!E8 -> 8290 | AF100: ='Major Quantities'!F8 -> 8290 | AG100: ='Major Quantities'!G8 -> 0 | AH100: ='Major Quantities'!H8 -> 0
D101: =Schedule!D7 -> Greater Than 14 Days | F101: =Schedule!F7 -> Less Than 14 Days | L101: =Manpower!Z23 -> Plumber | M101: =Manpower!Z24 -> 8 | N101: =Manpower!Z25 -> 7 | S101: =+Manpower!$N$49 -> Other | T101: =+Manpower!N50 -> 28 | U101: =+Manpower!N51 -> 10 | V101: =+Manpower!N52 -> 0 | W101: ='Major Quantities'!A9 -> 32 12 16.01 | X101: ='Major Quantities'!B9 -> Bituminous concrete wearing course, (Grading I - Class A), including tack coat (RC2) according to drawings. | AC101: ='Major Quantities'!C9 -> 5920 | AD101: ='Major Quantities'!D9 -> m3 | AE101: ='Major Quantities'!E9 -> 0 | AF101: ='Major Quantities'!F9 -> 2074 | AG101: ='Major Quantities'!G9 -> 3846 | AH101: ='Major Quantities'!H9 -> 2074
A102: =Schedule!A8 -> Last Week | B102: =Schedule!B8 -> This Week | C102: =Schedule!C8 -> Diff | D102: =Schedule!D8 -> Last Week | E102: =Schedule!E8 -> This Week | F102: =Schedule!F8 -> Last Week | G102: =Schedule!G8 -> This Week | H102: =Schedule!H8 -> Last Week | ... K102: =Schedule!K8 -> 0 | L102: Total | M102: =Manpower!AF24 -> 148 | N102: =Manpower!AF25 -> 130 | S102: Total | T102: =SUM(T95:T101) -> 42 | U102: =SUM(U95:U101) -> 20 | V102: =SUM(V95:V101) -> 0 | W102: ='Major Quantities'!A10 -> 33 42 11 | X102: ='Major Quantities'!B10 -> GRP Pipes for Storm network | AC102: ='Major Quantities'!C10 -> 5650 | AD102: ='Major Quantities'!D10 -> m | AE102: ='Major Quantities'!E10 -> 5650 | AF102: ='Major Quantities'!F10 -> 5650 | AG102: ='Major Quantities'!G10 -> 0 | AH102: ='Major Quantities'!H10 -> 0
A103: =Schedule!A9 -> 460 | B103: =Schedule!B9 -> 457 | C103: =Schedule!C9 -> 3 | D103: =Schedule!D9 -> 71 | E103: =Schedule!E9 -> 68 | F103: =Schedule!F9 -> 1834 | G103: =Schedule!G9 -> 1837 | H103: =Schedule!H9 -> 107 | ... J103: =Schedule!J9 -> -6 | Q103: Top Issues and Risks
A104: Testing And Commissioning
Q105: Top 5 Issues
A106: Item | B106: Planned Start Date | D106: Planned Finish Date | F106: Forecast Start Date | H106: Forecast Finish Date | J106: Actual Start Date | L106: Actual Finish Date | M106: % Completed | N106: Open Comments | O106: Closed Comments | P106: Issue No | R106: Date Identified | S106: Issue Description | V106: Responsible | X106: Action Taken | AC106: Mitigation | AF106: Current Status | AG106: Expected/Actual Closure | AH106: Duration Elapsed
A107: =Testing!A3 -> Test for Irrigation and Landscape | B107: =IF(Testing!B3=""," ",Testing!B3) -> 46679 | D107: =IF(Testing!C3=""," ",Testing!C3) -> 46686 | F107: =IF(Testing!D3=""," ",Testing!D3) -> 46807 | H107: =IF(Testing!E3=""," ",Testing!E3) -> 46814 | J107: =IF(Testing!F3=""," ",Testing!F3) | L107: =IF(Testing!G3=""," ",Testing!G3) | M107: =IF(Testing!H3=""," ",Testing!H3) | N107: =IF(Testing!I3=""," ",Testing!I3) | O107: =IF(Testing!J3=""," ",Testing!J3) | P107: =IF(+Issues!B11="","",+Issues!B11) -> 1 | R107: =IF(+Issues!C11="","",+Issues!C11) -> 46006 | S107: =IF(+Issues!D11="","",+Issues!D11) -> Update of Aggrement between MODON and SEC for Medium Voltage | V107: =IF(+Issues!E11="","",+Issues!E11) -> Owner | X107: =IF(+Issues!F11="","",+Issues!F11) -> 1. MODON contacted with SEC for getting Electric Source and it is under Process from SEC 2. Enjazco waiting for responding on Lettter No. (2818) 13.01.2026 | AF107: =IF(+Issues!H11="","",+Issues!H11) -> Open | AG107: =IF(+Issues!I11="","",+Issues!I11) -> 46021
A108: =Testing!A4 -> Test for Earthing System | B108: =IF(Testing!B4=""," ",Testing!B4) -> 46680 | D108: =IF(Testing!C4=""," ",Testing!C4) -> 46686 | F108: =IF(Testing!D4=""," ",Testing!D4) -> 46736 | H108: =IF(Testing!E4=""," ",Testing!E4) -> 46743 | J108: =IF(Testing!F4=""," ",Testing!F4) -> 46235 | L108: =IF(Testing!G4=""," ",Testing!G4) | M108: =IF(Testing!H4=""," ",Testing!H4) -> 0.3 | N108: =IF(Testing!I4=""," ",Testing!I4) | O108: =IF(Testing!J4=""," ",Testing!J4) | P108: =IF(+Issues!B12="","",+Issues!B12) -> 2 | R108: =IF(+Issues!C12="","",+Issues!C12) -> 45986 | S108: =IF(+Issues!D12="","",+Issues!D12) -> Permits from (SEC - STC - NWC) for allowing Construction works for Tie-in Lines (Sewer Line - TSE Line - Potable Water Line) | V108: =IF(+Issues!E12="","",+Issues!E12) -> Contractor | X108: =IF(+Issues!F12="","",+Issues!F12) -> Coordination done with all Servse Providers (STC - NWC - SEC (HV)) | AF108: =IF(+Issues!H12="","",+Issues!H12) -> closed | AG108: =IF(+Issues!I12="","",+Issues!I12) -> 46063
A109: =Testing!A5 -> Test for CCTV feeding system and GSM | B109: =IF(Testing!B5=""," ",Testing!B5) -> 46673 | D109: =IF(Testing!C5=""," ",Testing!C5) -> 46679 | F109: =IF(Testing!D5=""," ",Testing!D5) -> 46729 | H109: =IF(Testing!E5=""," ",Testing!E5) -> 46736 | J109: =IF(Testing!F5=""," ",Testing!F5) -> 46235 | L109: =IF(Testing!G5=""," ",Testing!G5) | M109: =IF(Testing!H5=""," ",Testing!H5) -> 0.35 | N109: =IF(Testing!I5=""," ",Testing!I5) | O109: =IF(Testing!J5=""," ",Testing!J5) | P109: =IF(+Issues!B13="","",+Issues!B13) -> 3 | R109: =IF(+Issues!C13="","",+Issues!C13) | S109: =IF(+Issues!D13="","",+Issues!D13) -> Supplier Approval not included in Vendor List :: Pre-Qualification for Post Tension Works, Bearings and Expansion Joints Scope NOT IN VENDOR LIST Emirates Elite Trading Co. (ECO) Freyssinet Menard Saudi Arabia Ltd AL-BUNYAN EST. LT | V109: =IF(+Issues!E13="","",+Issues!E13) -> Owner | X109: =IF(+Issues!F13="","",+Issues!F13) -> PQD Submitted to Egis For Approval | AF109: =IF(+Issues!H13="","",+Issues!H13) -> closed | AG109: =IF(+Issues!J13="","",+Issues!J13)
A110: =Testing!A6 -> Test for Telecommunications Work | B110: =IF(Testing!B6=""," ",Testing!B6) -> 46666 | D110: =IF(Testing!C6=""," ",Testing!C6) -> 46672 | F110: =IF(Testing!D6=""," ",Testing!D6) -> 46722 | H110: =IF(Testing!E6=""," ",Testing!E6) -> 46729 | J110: =IF(Testing!F6=""," ",Testing!F6) -> 46235 | L110: =IF(Testing!G6=""," ",Testing!G6) | M110: =IF(Testing!H6=""," ",Testing!H6) -> 0.3 | N110: =IF(Testing!I6=""," ",Testing!I6) | O110: =IF(Testing!J6=""," ",Testing!J6) | P110: =IF(+Issues!B14="","",+Issues!B14) -> 4 | R110: =IF(+Issues!C14="","",+Issues!C14) | S110: =IF(+Issues!D14="","",+Issues!D14) | V110: =IF(+Issues!E14="","",+Issues!E14) | X110: =IF(+Issues!F14="","",+Issues!F14) | AF110: =IF(+Issues!H14="","",+Issues!H14) | AG110: =IF(+Issues!J14="","",+Issues!J14)
A111: =Testing!A7 -> Test for Road Lighting | B111: =IF(Testing!B7=""," ",Testing!B7) -> 46659 | D111: =IF(Testing!C7=""," ",Testing!C7) -> 46665 | F111: =IF(Testing!D7=""," ",Testing!D7) -> 46715 | H111: =IF(Testing!E7=""," ",Testing!E7) -> 46722 | J111: =IF(Testing!F7=""," ",Testing!F7) -> 46235 | L111: =IF(Testing!G7=""," ",Testing!G7) | M111: =IF(Testing!H7=""," ",Testing!H7) -> 0.3 | N111: =IF(Testing!I7=""," ",Testing!I7) | O111: =IF(Testing!J7=""," ",Testing!J7) | R111: =IF(+Issues!C15="","",+Issues!C15) | S111: =IF(+Issues!D15="","",+Issues!D15) | V111: =IF(+Issues!E15="","",+Issues!E15) | X111: =IF(+Issues!F15="","",+Issues!F15) | AF111: =IF(+Issues!H15="","",+Issues!H15) | AG111: =IF(+Issues!J15="","",+Issues!J15)
A112: =Testing!A8 -> Test for Electrical Network | B112: =IF(Testing!B8=""," ",Testing!B8) -> 46641 | D112: =IF(Testing!C8=""," ",Testing!C8) -> 46649 | F112: =IF(Testing!D8=""," ",Testing!D8) -> 46701 | H112: =IF(Testing!E8=""," ",Testing!E8) -> 46711 | J112: =IF(Testing!F8=""," ",Testing!F8) -> 46235 | L112: =IF(Testing!G8=""," ",Testing!G8) | M112: =IF(Testing!H8=""," ",Testing!H8) -> 0.3 | N112: =IF(Testing!I8=""," ",Testing!I8) | O112: =IF(Testing!J8=""," ",Testing!J8) | R112: =IF(+Issues!C16="","",+Issues!C16) | S112: =IF(+Issues!D16="","",+Issues!D16) | V112: =IF(+Issues!E16="","",+Issues!E16) | X112: =IF(+Issues!F16="","",+Issues!F16) | AF112: =IF(+Issues!H16="","",+Issues!H16) | AG112: =IF(+Issues!J16="","",+Issues!J16)
A113: =Testing!A9 -> Test for Road Works | B113: =IF(Testing!B9=""," ",Testing!B9) -> 46603 | D113: =IF(Testing!C9=""," ",Testing!C9) -> 46611 | F113: =IF(Testing!D9=""," ",Testing!D9) -> 46676 | H113: =IF(Testing!E9=""," ",Testing!E9) -> 46684 | J113: =IF(Testing!F9=""," ",Testing!F9) -> 46235 | L113: =IF(Testing!G9=""," ",Testing!G9) | M113: =IF(Testing!H9=""," ",Testing!H9) -> 0.7 | N113: =IF(Testing!I9=""," ",Testing!I9) | O113: =IF(Testing!J9=""," ",Testing!J9) | R113: =IF(+Issues!C17="","",+Issues!C17) | S113: =IF(+Issues!D17="","",+Issues!D17) | V113: =IF(+Issues!E17="","",+Issues!E17) | X113: =IF(+Issues!F17="","",+Issues!F17) | AF113: =IF(+Issues!H17="","",+Issues!H17) | AG113: =IF(+Issues!J17="","",+Issues!J17)
A114: =Testing!A10 -> Test for Fence & Gate | B114: =IF(Testing!B10=""," ",Testing!B10) -> 46679 | D114: =IF(Testing!C10=""," ",Testing!C10) -> 46685 | F114: =IF(Testing!D10=""," ",Testing!D10) -> 15-Jun-26 A | H114: =IF(Testing!E10=""," ",Testing!E10) -> 46695 | J114: =IF(Testing!F10=""," ",Testing!F10) -> 46188 | L114: =IF(Testing!G10=""," ",Testing!G10) | M114: =IF(Testing!H10=""," ",Testing!H10) -> 0.6 | N114: =IF(Testing!I10=""," ",Testing!I10) | O114: =IF(Testing!J10=""," ",Testing!J10) | R114: =IF(+Issues!C18="","",+Issues!C18) | S114: =IF(+Issues!D18="","",+Issues!D18) | V114: =IF(+Issues!E18="","",+Issues!E18) | X114: =IF(+Issues!F18="","",+Issues!F18) | AF114: =IF(+Issues!H18="","",+Issues!H18) | AG114: =IF(+Issues!J18="","",+Issues!J18)
A115: =Testing!A11 -> Test for Bridge Work | B115: =IF(Testing!B11=""," ",Testing!B11) -> 46631 | D115: =IF(Testing!C11=""," ",Testing!C11) -> 46639 | F115: =IF(Testing!D11=""," ",Testing!D11) -> 15-Jun-26 A | H115: =IF(Testing!E11=""," ",Testing!E11) -> 46701 | J115: =IF(Testing!F11=""," ",Testing!F11) -> 46188 | L115: =IF(Testing!G11=""," ",Testing!G11) | M115: =IF(Testing!H11=""," ",Testing!H11) -> 0.7 | N115: =IF(Testing!I11=""," ",Testing!I11) | O115: =IF(Testing!J11=""," ",Testing!J11) | R115: =IF(+Issues!C19="","",+Issues!C19) | S115: =IF(+Issues!D19="","",+Issues!D19) | V115: =IF(+Issues!E19="","",+Issues!E19) | X115: =IF(+Issues!F19="","",+Issues!F19) | AF115: =IF(+Issues!H19="","",+Issues!H19) | AG115: =IF(+Issues!J19="","",+Issues!J19)
A116: =Testing!A12 -> Test for Stormwater Utilities | B116: =IF(Testing!B12=""," ",Testing!B12) -> 46622 | D116: =IF(Testing!C12=""," ",Testing!C12) -> 46630 | F116: =IF(Testing!D12=""," ",Testing!D12) -> 15-Jun-26 A | H116: =IF(Testing!E12=""," ",Testing!E12) -> 46695 | J116: =IF(Testing!F12=""," ",Testing!F12) -> 46188 | L116: =IF(Testing!G12=""," ",Testing!G12) | M116: =IF(Testing!H12=""," ",Testing!H12) -> 0.7 | N116: =IF(Testing!I12=""," ",Testing!I12) | O116: =IF(Testing!J12=""," ",Testing!J12) | R116: =IF(+Issues!C20="","",+Issues!C20) | S116: =IF(+Issues!D20="","",+Issues!D20) | V116: =IF(+Issues!E20="","",+Issues!E20) | X116: =IF(+Issues!F20="","",+Issues!F20) | AF116: =IF(+Issues!H20="","",+Issues!H20) | AG116: =IF(+Issues!J20="","",+Issues!J20)
A117: =Testing!A13 -> Test for Sanitary Sewerage | B117: =IF(Testing!B13=""," ",Testing!B13) -> 46613 | D117: =IF(Testing!C13=""," ",Testing!C13) -> 46621 | F117: =IF(Testing!D13=""," ",Testing!D13) -> 15-Jun-26 A | H117: =IF(Testing!E13=""," ",Testing!E13) -> 46690 | J117: =IF(Testing!F13=""," ",Testing!F13) -> 46188 | L117: =IF(Testing!G13=""," ",Testing!G13) | M117: =IF(Testing!H13=""," ",Testing!H13) -> 0.75 | N117: =IF(Testing!I13=""," ",Testing!I13) | O117: =IF(Testing!J13=""," ",Testing!J13) | P117: =IF(+Issues!B21="","",+Issues!B21) | R117: =IF(+Issues!C21="","",+Issues!C21) | S117: =IF(+Issues!D21="","",+Issues!D21) | V117: =IF(+Issues!E21="","",+Issues!E21) | X117: =IF(+Issues!F21="","",+Issues!F21) | AF117: =IF(+Issues!H21="","",+Issues!H21) | AG117: =IF(+Issues!J21="","",+Issues!J21)
A118: =Testing!A14 -> Test for TSE Network | B118: =IF(Testing!B14=""," ",Testing!B14) -> 46650 | D118: =IF(Testing!C14=""," ",Testing!C14) -> 46658 | F118: =IF(Testing!D14=""," ",Testing!D14) -> 15-Jun-26 A | H118: =IF(Testing!E14=""," ",Testing!E14) -> 46715 | J118: =IF(Testing!F14=""," ",Testing!F14) -> 46188 | L118: =IF(Testing!G14=""," ",Testing!G14) | M118: =IF(Testing!H14=""," ",Testing!H14) -> 0.75 | N118: =IF(Testing!I14=""," ",Testing!I14) | O118: =IF(Testing!J14=""," ",Testing!J14) | P118: =IF(+Issues!B22="","",+Issues!B22) | R118: =IF(+Issues!C22="","",+Issues!C22) | S118: =IF(+Issues!D22="","",+Issues!D22) | V118: =IF(+Issues!E22="","",+Issues!E22) | X118: =IF(+Issues!F22="","",+Issues!F22) | AF118: =IF(+Issues!H22="","",+Issues!H22) | AG118: =IF(+Issues!J22="","",+Issues!J22)
A119: =Testing!A15 -> Test for Public Water Utility Distribution | B119: =IF(Testing!B15=""," ",Testing!B15) -> 46613 | D119: =IF(Testing!C15=""," ",Testing!C15) -> 46621 | F119: =IF(Testing!D15=""," ",Testing!D15) -> 15-Jun-26 A | H119: =IF(Testing!E15=""," ",Testing!E15) -> 46690 | J119: =IF(Testing!F15=""," ",Testing!F15) -> 46188 | L119: =IF(Testing!G15=""," ",Testing!G15) | M119: =IF(Testing!H15=""," ",Testing!H15) -> 0.75 | N119: =IF(Testing!I15=""," ",Testing!I15) | O119: =IF(Testing!J15=""," ",Testing!J15) | P119: =IF(+Issues!B23="","",+Issues!B23) | R119: =IF(+Issues!C23="","",+Issues!C23) | S119: =IF(+Issues!D23="","",+Issues!D23) | V119: =IF(+Issues!E23="","",+Issues!E23) | X119: =IF(+Issues!F23="","",+Issues!F23) | AF119: =IF(+Issues!H23="","",+Issues!H23) | AG119: =IF(+Issues!J23="","",+Issues!J23)
P120: =IF(+Issues!B24="","",+Issues!B24) | R120: =IF(+Issues!C24="","",+Issues!C24) | S120: =IF(+Issues!D24="","",+Issues!D24) | V120: =IF(+Issues!E24="","",+Issues!E24) | X120: =IF(+Issues!F24="","",+Issues!F24) | AF120: =IF(+Issues!H24="","",+Issues!H24) | AG120: =IF(+Issues!J24="","",+Issues!J24)

Sheet General Information
A1: Weekly Progress Report - Construction Projects | K1: Data Date | L1: 46315
A2: Contract General Information | K2: Week No. | L2: =(L1-C14)/7 -> 47.857143
A3: Project Name | C3: INFRASTRUCTURE DEVELOPMENT FOR INDUSTRIAL CITY 1 IN JEDDAH
A4: Project ID | C4: JDH1-02-003
A5: Contractor | C5: Al Enjaz Company for Trading and Contracting
A6: Consultant | C6: Saudi Arabia Consulting Engineering Company "EGIS"
A7: Stage | C7: Construction
A8: Status | C8: Active
A9: Modon PM | C9: Engr.Abdallah Aljulayfi
A11: Key Dates
A12: Contract Award Date | C12: 45963
A13: Contract Sign Date | C13: 45974
A14: Site Handover Date | C14: 45980
A15: Original Completion | C15: 46709
A16: Contract Award Date (Hijri) | C16: =C12 -> 45963
A17: Contract Sign Date (Hijri) | C17: =C13 -> 45974
A18: Site Handover Date (Hijri) | C18: =C14 -> 45980
A19: Original Completion (Hijri) | C19: =C15 -> 46709
A20: Revised Completion Date | C20: 46709
A21: Committed Completion Date | C21: 46709
A22: Forecast Completion | C22: 46893
A23: Variance | C23: =C20-C22 -> -184
A25: Key Project Submittals | C25: Submission Date | D25: Days taken to approve orginal plan from site handover date
A26: Quality Plan submission | C26: 45986 | D26: =C26-C14 -> 6
A27: Quality Plan approval | C27: 46062
A28: Quality Plan Last Update | C28: -
A30: Safety Plan submission | C30: 46001 | D30: =C30-C14 -> 21
A31: Safety Plan approval | C31: 46056
A32: Safety Plan Last Update | C32: -
A34: Risk Management Plan submission | C34: 46006 | D34: =C34-C14 -> 26
A35: Risk Management Plan approval | C35: 46009
A36: Risk Management Plan Last Update | C36: -
A38: Baseline Schedule submission | C38: 46007 | D38: =C38-C14 -> 27
A39: Baseline Schedule approval | C39: 46009
A40: No of Schedule Versions | C40: 1
A41: Last Revised Schedule Approval Date | C41: -
A43: BOQ submission | C43: 45980 | D43: =C43-C14 -> 0
A44: BOQ approval | C44: 45980
A45: No of Approved Version of BOQ
A47: Execution Plan submission | C47: 45986 | D47: =C47-C14 -> 6
A48: Execution Plan Approval | C48: 46058

Sheet Progress
A1: Project Scope Statement
A4: Earned Value Progress (SAR) | L4: Physical Progress (Effort)
A5: WBS | C5: BOQ Value (SAR) | D5: % Wt. | E5: Weekly (SAR) | H5: To Date (SAR) | J5: Actual % | L5: Budgeted | M5: % Wt. | N5: Weekly Physical Progress | P5: To Date Physical Progress | T5: Last Week Cost (SAR) | V5: Last Week Physical Progress
E6: Planned | F6: Earned | G6: Original Plan | H6: Planned | I6: Earned | L6: (Manhours) | N6: Planned | O6: Earned | P6: Planned | Q6: Earned | S6: 5508011 | T6: Planned | U6: Earned | V6: Planned | W6: Earned
A7: Mobilization | C7: 0 | E7: =H7-T7 -> 0 | F7: =I7-U7 -> 0 | G7: 0 | H7: =E39 -> 0 | I7: =F39 -> 0 | J7: =I7/$C$25 -> 0 | L7: 20050 | M7: =L7/$L$25 -> 0.028059176 | N7: =P7-V7 -> 0 | O7: =Q7-W7 -> 0 | P7: =H39 -> 20050 | Q7: =I39 -> 20050 | S7: 0 | T7: 0 | U7: 0 | V7: 20050 | W7: 20050
A8: Engineering | C8: 2601460.4 | D8: =C8/$C$25 -> 0.029976839 | E8: =H8-T8 -> 0 | F8: =I8-U8 -> 0 | G8: 2601460.4 | H8: =E40 -> 2601460.4 | I8: =F40 -> 2579200.4 | J8: =I8/$C$25 -> 0.029720335 | L8: 33415 | M8: =L8/$L$25 -> 0.046762961 | N8: =P8-V8 -> 0 | O8: =Q8-W8 -> 0 | P8: 33415 | Q8: 33009.2 | S8: 0 | T8: 2601460.4 | U8: 2579200.4 | V8: 33415 | W8: 33009.2
A9: Procurement | C9: 17355662 | D9: =C9/$C$25 -> 0.1999907 | E9: =H9-T9 -> 26504 | F9: =I9-U9 -> 208500 | G9: 13492073 | H9: =E41 -> 13518577 | I9: =F41 -> 15737880 | J9: =I9/$C$25 -> 0.18134887 | L9: 82413.81 | M9: =L9/$L$25 -> 0.11533484 | N9: =P9-V9 -> 0 | O9: =Q9-W9 -> 0 | P9: 35843.52 | Q9: 65032.49 | S9: 1889863.4 | T9: 13492073 | U9: 15529380 | V9: 35843.52 | W9: 65032.49
A10: Construction | C10: 58147531 | D10: =C10/$C$25 -> 0.67003872 | E10: =H10-T10 -> 394580.51 | F10: =I10-U10 -> 190111.17 | G10: 29638879 | H10: =E42 -> 30033459 | I10: =F42 -> 44572325 | J10: =I10/$C$25 -> 0.51361052 | L10: 545268.46 | M10: =L10/$L$25 -> 0.76308147 | N10: =P10-V10 -> 5590.01 | O10: =Q10-W10 -> 1907.14 | P10: =H42 -> 246436.59 | Q10: =I42 -> 390120.29 | S10: 1520807.4 | T10: 29638879 | U10: 44382214 | V10: 240846.58 | W10: 388213.15
A11: Site Demolition | C11: 279942.75 | D11: =C11/$C$25 -> 0.003225803 | E11: =H11-T11 -> 0 | F11: =I11-U11 -> 0 | G11: 279942.75 | H11: =E43 -> 279942.75 | I11: =F43 -> 279942.75 | J11: =I11/$C$25 -> 0.003225803 | L11: 7350 | M11: =L11/$L$25 -> 0.010286032 | N11: =P11-V11 -> 0 | O11: =Q11-W11 -> 0 | P11: =H43 -> 7350 | Q11: =I43 -> 7350 | S11: 2097340.2 | T11: 279942.75 | U11: 279942.75 | V11: 7350 | W11: 7350
A12: Roads & Meduim Voltage | C12: 11810039 | D12: =C12/$C$25 -> 0.13608803 | E12: =H12-T12 -> 0 | F12: =I12-U12 -> 0 | G12: 11810039 | H12: =E44 -> 11810039 | I12: =F44 -> 8650438.8 | J12: =I12/$C$25 -> 0.099679708 | L12: 100175 | M12: =L12/$L$25 -> 0.14019092 | N12: =P12-V12 -> 0 | O12: =Q12-W12 -> 0 | P12: =H44 -> 100175 | Q12: =I44 -> 73591 | S12: 957625.34 | T12: 11810039 | U12: 8650438.8 | V12: 100175 | W12: 73591
A13: Deep Infrastructure network | C13: 10009830 | D13: =C13/$C$25 -> 0.11534409 | E13: =H13-T13 -> 10082.82 | F13: =I13-U13 -> 7209.5 | G13: 9958787.2 | H13: =E45 -> 9968870 | I13: =F45 -> 9750710.5 | J13: =I13/$C$25 -> 0.11235823 | L13: 54025 | M13: =L13/$L$25 -> 0.075605834 | N13: =P13-V13 -> 0 | O13: =Q13-W13 -> 0 | P13: =H45 -> 54025 | Q13: =I45 -> 51820.5 | S13: 583145.23 | T13: 9958787.2 | U13: 9743501 | V13: 54025 | W13: 51820.5
A14: Shallow infrastructure network | C14: 12539076 | D14: =C14/$C$25 -> 0.14448879 | E14: =H14-T14 -> 209087.15 | F14: =I14-U14 -> 99253.79 | G14: 2810927.8 | H14: =E46 -> 3020015 | I14: =F46 -> 10453768 | J14: =I14/$C$25 -> 0.12045962 | L14: 198577.38 | M14: =L14/$L$25 -> 0.27790113 | N14: =P14-V14 -> 4687.15 | O14: =Q14-W14 -> 1717.15 | P14: =H46 -> 43207.03 | Q14: =I46 -> 154727.25 | S14: 556569.64 | T14: 2810927.8 | U14: 10354514 | V14: 38519.88 | W14: 153010.1
A15: Bridge | C15: 2513307 | D15: =C15/$C$25 -> 0.02896104 | E15: =H15-T15 -> 15291.43 | F15: =I15-U15 -> 0 | G15: 1320006.9 | H15: =E47 -> 1335298.3 | I15: =F47 -> 1830342.9 | J15: =I15/$C$25 -> 0.02109119 | L15: 14022.14 | M15: =L15/$L$25 -> 0.019623426 | N15: =P15-V15 -> 171.43 | O15: =Q15-W15 -> 0 | P15: =H47 -> 7721.43 | Q15: =I47 -> 12207.14 | S15: 0 | T15: 1320006.9 | U15: 1830342.9 | V15: 7550 | W15: 12207.14
A16: Outside Boundary Area (Tie-in Lines) | C16: 2681726.3 | D16: =C16/$C$25 -> 0.030901749 | E16: =H16-T16 -> 71160.39 | F16: =I16-U16 -> 0 | G16: 1339359.5 | H16: =E48 -> 1410519.9 | I16: =F48 -> 2663147.2 | J16: =I16/$C$25 -> 0.030687661 | L16: 19949.2 | M16: =L16/$L$25 -> 0.02791811 | N16: =P16-V16 -> 681.43 | O16: =Q16-W16 -> 0 | P16: =H48 -> 9933.13 | Q16: =I48 -> 19885.03 | S16: 0 | T16: 1339359.5 | U16: 2663147.2 | V16: 9251.7 | W16: 19885.03
A17: Roads Finishing | C17: 8138565 | D17: =C17/$C$25 -> 0.093781345 | E17: =H17-T17 -> 0 | F17: =I17-U17 -> 83647.88 | G17: 0 | H17: =E49 -> 0 | I17: =F49 -> 5591559.2 | J17: =I17/$C$25 -> 0.06443199 | L17: 65951.79 | M17: =L17/$L$25 -> 0.092296901 | N17: =P17-V17 -> 0 | O17: =Q17-W17 -> 190 | P17: =H49 -> 0 | Q17: =I49 -> 45112.37 | T17: 0 | U17: 5507911.3 | V17: 0 | W17: 44922.37
A18: Fence and Gate | C18: 8127691.9 | D18: =C18/$C$25 -> 0.093656053 | E18: =H18-T18 -> 88958.71 | F18: =I18-U18 -> 0 | G18: 2119815.9 | H18: =E50 -> 2208774.6 | I18: =F50 -> 5352415.6 | J18: =I18/$C$25 -> 0.061676319 | L18: 43715 | M18: =L18/$L$25 -> 0.0611774 | N18: =P18-V18 -> 50 | O18: =Q18-W18 -> 0 | P18: =H50 -> 24025 | Q18: =I50 -> 25427 | T18: 2119815.9 | U18: 5352415.6 | V18: 23975 | W18: 25427
A19: Roundabout & Landscape | C19: 2047352.9 | D19: =C19/$C$25 -> 0.023591814 | E19: =H19-T19 -> 0 | F19: =I19-U19 -> 0 | G19: 0 | H19: =E51 -> 0 | I19: =F51 -> 0 | J19: =I19/$C$25 -> 0 | L19: 41502.94 | M19: =L19/$L$25 -> 0.05808171 | N19: =P19-V19 -> 0 | O19: =Q19-W19 -> 0 | P19: =H51 -> 0 | Q19: =I51 -> 0 | T19: 0 | U19: 0 | V19: 0 | W19: 0
A20: Testing & Commissioning | C20: 8677691.2 | D20: =C20/$C$25 -> 0.09999374 | E20: =H20-T20 -> 0 | F20: =I20-U20 -> 0 | G20: 0 | H20: =E52 -> 0 | I20: =F52 -> 5426563.3 | J20: =I20/$C$25 -> 0.062530729 | L20: 20050 | M20: =L20/$L$25 -> 0.028059176 | N20: =P20-V20 -> 0 | O20: =Q20-W20 -> 0 | P20: =H52 -> 0 | Q20: =I52 -> 10646.5 | T20: 0 | U20: 5426563.3 | V20: 0 | W20: 10646.5
A21: Project Close-out | C21: 0 | D21: 0 | E21: =H21-T21 -> 0 | F21: =I21-U21 -> 0 | G21: 0 | H21: =E53 -> 0 | I21: =F53 -> 0 | J21: =I21/$C$25 -> 0 | L21: 13364 | M21: =L21/$L$25 -> 0.018702385 | N21: =P21-V21 -> 0 | O21: =Q21-W21 -> 0 | P21: =H53 -> 0 | Q21: =I53 -> 0 | T21: 0 | U21: 0 | V21: 0 | W21: 0
E22: =H22-T22 -> 0 | F22: =I22-U22 -> 0 | N22: =P22-V22 -> 0 | O22: =Q22-W22 -> 0
E23: =H23-T23 -> 0 | F23: =I23-U23 -> 0 | N23: =P23-V23 -> 0 | O23: =Q23-W23 -> 0
E24: =H24-T24 -> 0 | F24: =I24-U24 -> 0 | N24: =P24-V24 -> 0 | O24: =Q24-W24 -> 0
B25: Total | C25: =C7+C8+C9+C11+C12+C13+C14+C15+C16+C17+C18+C19+C20+C21 -> 86782345 | D25: =D7+D8+D9+D11+D12+D13+D14+D15+D16+D17+D18+D19+D20+D21 -> 1 | E25: =E7+E8+E9+E11+E12+E13+E14+E15+E16+E17+E18+E19+E20+E21 -> 421084.5 | F25: =F7+F8+F9+F11+F12+F13+F14+F15+F16+F17+F18+F19+F20+F21 -> 398611.17 | G25: =G7+G8+G9+G11+G12+G13+G14+G15+G16+G17+G18+G19+G20+G21 -> 45732412 | H25: =H7+H8+H9+H11+H12+H13+H14+H15+H16+H17+H18+H19+H20+H21 -> 46153497 | I25: =I7+I8+I9+I11+I12+I13+I14+I15+I16+I17+I18+I19+I20+I21 -> 68315969 | J25: =I25/$C$25 -> 0.78721045 | L25: =L7+L8+L9+L11+L12+L13+L14+L15+L16+L17+L18+L19+L20+L21 -> 714561.26 | M25: =M7+M8+M9+M11+M12+M13+M14+M15+M16+M17+M18+M19+M20+M21 -> 1 | N25: =N7+N8+N9+N11+N12+N13+N14+N15+N16+N17+N18+N19+N20+N21 -> 5590.01 | O25: =O7+O8+O9+O11+O12+O13+O14+O15+O16+O17+O18+O19+O20+O21 -> 1907.15 | P25: =P7+P8+P9+P11+P12+P13+P14+P15+P16+P17+P18+P19+P20+P21 -> 335745.11 | Q25: =Q7+Q8+Q9+Q11+Q12+Q13+Q14+Q15+Q16+Q17+Q18+Q19+Q20+Q21 -> 518858.48 | T25: =T7+T8+T9+T11+T12+T13+T14+T15+T16+T17+T18+T19+T20+T21 -> 45732412 | U25: =U7+U8+U9+U11+U12+U13+U14+U15+U16+U17+U18+U19+U20+U21 -> 67917358 | V25: =V7+V8+V9+V11+V12+V13+V14+V15+V16+V17+V18+V19+V20+V21 -> 330155.1 | W25: =W7+W8+W9+W11+W12+W13+W14+W15+W16+W17+W18+W19+W20+W21 -> 516951.33
G26: =G25/C25 -> 0.5269783 | H26: =H25/C25 -> 0.53183049 | I26: =I25/C25 -> 0.78721045 | P26: =P25/L25 -> 0.4698619 | Q26: =Q25/L25 -> 0.72612176
I27: =H26-I26 -> -0.25537996
A36: Activity ID | B36: Activity Name | C36: Original Duration | D36: Budgeted Total Cost | E36: Planned Value Cost | F36: Earned Value Cost | G36: Budgeted Labor Units | H36: Planned Value Labor Units | I36: Earned Value Labor Units
A37: JDH1-02-003 - Infrastructure Development For Industrial City 1 In Jeddah - Update - 20.10.2026 | C37: 763 | D37: 86782345 | E37: 46153497 | F37: 68315969 | G37: 714561.27 | H37: 347982.15 | I37: 528822.75 | J37: 461520.15 | K37: =I37-J37 -> 67302.6
A38: Milestones | C38: 763 | D38: 0 | E38: 0 | F38: 0 | G38: 0 | H38: 0 | I38: 0 | J38: 0 | K38: =I38-J38 -> 0
A39: Mobilization | C39: 112 | D39: 0 | E39: 0 | F39: 0 | G39: 20050 | H39: 20050 | I39: 20050 | J39: 20050 | K39: =I39-J39 -> 0
A40: Engineering | C40: 287 | D40: 2601460.4 | E40: 2601460.4 | F40: 2579200.4 | G40: 33415 | H40: 33415 | I40: 33009.2 | J40: 33009.2 | K40: =I40-J40 -> 0
A41: Procurement | C41: 502 | D41: 17355662 | E41: 13518577 | F41: 15737880 | G41: 82413.81 | H41: 48080.56 | I41: 74996.76 | J41: 65032.49 | K41: =I41-J41 -> 9964.27
A42: Construction | C42: 710 | D42: 58147531 | E42: 30033459 | F42: 44572325 | G42: 545268.46 | H42: 246436.59 | I42: 390120.29 | J42: 339660.46 | K42: =I42-J42 -> 50459.83
A43: Site Demolition | C43: 93 | D43: 279942.75 | E43: 279942.75 | F43: 279942.75 | G43: 7350 | H43: 7350 | I43: 7350 | J43: 7350 | K43: =I43-J43 -> 0
A44: Roads & Meduim Voltage | C44: 423 | D44: 11810039 | E44: 11810039 | F44: 8650438.8 | G44: 100175 | H44: 100175 | I44: 73591 | J44: 72812.5 | K44: =I44-J44 -> 778.5
A45: Deep Infrastructure network | C45: 277 | D45: 10009830 | E45: 9968870 | F45: 9750710.5 | G45: 54025 | H45: 54025 | I45: 51820.5 | J45: 51617.5 | K45: =I45-J45 -> 203
A46: Shallow infrastructure network | C46: 433 | D46: 12539076 | E46: 3020015 | F46: 10453768 | G46: 198577.38 | H46: 43207.03 | I46: 154727.25 | J46: 126285.02 | K46: =I46-J46 -> 28442.23
A47: Bridge | C47: 452 | D47: 2513307 | E47: 1335298.3 | F47: 1830342.9 | G47: 14022.14 | H47: 7721.43 | I47: 12207.14 | J47: 11391.07 | K47: =I47-J47 -> 816.07
A48: Outside Boundary Area (Tie-in Lines) | C48: 419 | D48: 2681726.3 | E48: 1410519.9 | F48: 2663147.2 | G48: 19949.2 | H48: 9933.13 | I48: 19885.03 | J48: 17900.29 | K48: =I48-J48 -> 1984.74
... A53: Project Close-out | C53: 145 | D53: 0 | E53: 0 | F53: 0 | G53: 13364 | H53: 0 | I53: 0 | J53: 0 | K53: =I53-J53 -> 0
F74: Activity ID | G74: Activity Name | H74: Original Duration | I74: BL Project Start | J74: BL Project Finish | L74: Start | M74: Finish | N74: Planned Value Cost | O74: Actual Total Cost | P74: Earned Value Cost | Q74: Schedule % Complete | R74: Performance % Complete | S74: Budgeted Total Cost | U74: Actual Labor Units | V74: Earned Value Labor Units | W74: Total Float
F75: Construction of 32 RBF's (900m2) in Jeddah 2 Industrial City | H75: 359 | I75: 45774 | J75: 46198 | L75: 26-Apr-25 A | M75: 46204 | N75: 26937517 | O75: 26297180 | P75: 26898067 | Q75: 0.3827 | R75: 0.3821 | S75: 70392244 | U75: 19616 | V75: 19774.6 | W75: -5

Sheet Weekly Photos
V1: ='[37]General Information'!K1 -> Data Date | W1: ='General Information'!L1 -> 46315
B2: L01 - Installation of Telecom Pipes | L2: Curbstone works
B21: L01 - Backfilling of Telecom Pipes | L21: Interlock works
B41: Interlock works | L41: Installation of street lights fuse box of local 1
B60: Installation of Light Poles | L60: Excavation of irrigation main pipes in plot no 10 for landscaping

Sheet Major Quantities
A1: BOQ Number | B1: Description of Item | C1: Total Quantity | D1: Unit of Measurement | E1: Plan To Date | F1: Actual To Date | G1: Remaining Total | H1: Variance
A2: 31 22 00.01 | B2: Excavation for Roadway, fences and bridge, cuttings including dump locations (all types of soil) | C2: 116177.4 | D2: m3 | E2: =C2*1 -> 116177.4 | F2: =C2*1 -> 116177.4 | G2: =C2-F2 -> 0 | H2: =F2-E2 -> 0
A3: 31 22 00.02 | B3: Parcrels Excavation for cuttings (all types of soil) | C3: 123555 | D3: m3 | E3: =C3*1 -> 123555 | F3: =1*C3 -> 123555 | G3: =C3-F3 -> 0 | H3: =F3-E3 -> 0
A4: 31 22 00.03 | B4: Embankments to the roads , fences and bridge. | C4: 80919.7 | D4: m3 | E4: =1*C4 -> 80919.7 | F4: =1*C4 -> 80919.7 | G4: =C4-F4 -> 0 | H4: =F4-E4 -> 0
A5: 31 22 00.04 | B5: Embankments to the parcels | C5: 94645 | D5: m3 | E5: =1*C5 -> 94645 | F5: =0.998*C5 -> 94455.71 | G5: =C5-F5 -> 189.29 | H5: =F5-E5 -> -189.29
A6: 31 22 00.05 | B6: Subgrade | C6: 34693.65 | D6: m3 | E6: =1*C6 -> 34693.65 | F6: =1*C6 -> 34693.65 | G6: =C6-F6 -> 0 | H6: =F6-E6 -> 0
A7: 32 11 23.01 | B7: Aggregate base course | C7: 23129.1 | D7: m3 | E7: =1*C7 -> 23129.1 | F7: =1*C7 -> 23129.1 | G7: =C7-F7 -> 0 | H7: =F7-E7 -> 0
A8: 32 11 26.01 | B8: Bituminous base course (Grading I - Class A), including Prime Coat (MC1) according to drawings | C8: 8290 | D8: m3 | E8: =1*C8 -> 8290 | F8: =C8*1 -> 8290 | G8: =C8-F8 -> 0 | H8: =F8-E8 -> 0
A9: 32 12 16.01 | B9: Bituminous concrete wearing course, (Grading I - Class A), including tack coat (RC2) according to drawings. | C9: 5920 | D9: m3 | E9: 0 | F9: 2074 | G9: =C9-F9 -> 3846 | H9: =F9-E9 -> 2074
A10: 33 42 11 | B10: GRP Pipes for Storm network | C10: 5650 | D10: m | E10: =1*C10 -> 5650 | F10: 5650 | G10: =C10-F10 -> 0 | H10: =F10-E10 -> 0 | J10: =F10/C10 -> 1
A11: 33 14 13 | B11: High Density Polyethylene pipes PE 100 SDR 11 (PN 16 Bars) | C11: =4575+738.28+3182+3580 -> 12075.28 | D11: m | E11: =0.578*C11 -> 6979.5118 | F11: 12075 | G11: =C11-F11 -> 0.28 | H11: =F11-E11 -> 5095.4882 | J11: =F11/C11 -> 0.99997681
A12: 33 14 13 | B12: High Density Polyethylene pipes PE 100 SDR 11 (PN 16 Bars) | C12: 8722 | D12: m | E12: =0.733*C12 -> 6393.226 | F12: 8700 | G12: =C12-F12 -> 22 | H12: =F12-E12 -> 2306.774 | J12: =F12/C12 -> 0.99747764
A13: 33 31 00 | B13: Glass Reinforced Plastic (GRP) for Sewer network | C13: 6244 | D13: m | E13: =1*C13 -> 6244 | F13: 6244 | G13: =C13-F13 -> 0 | H13: =F13-E13 -> 0 | J13: =F13/C13 -> 1
G14: =C14-F14 -> 0 | H14: =F14-E14 -> 0
G15: =C15-F15 -> 0 | H15: =F15-E15 -> 0
G16: =C16-F16 -> 0 | H16: =F16-E16 -> 0
G17: =C17-F17 -> 0 | H17: =F17-E17 -> 0
G18: =C18-F18 -> 0 | H18: =F18-E18 -> 0
G19: =C19-F19 -> 0 | H19: =F19-E19 -> 0

Sheet Quality  
B2: QC OBSERVATIONS CHECKLIST
B6: Project No. | E6: JDH1-02-003 | K6: OBS No. | O6: ='General Information'!L2 -> 47.857143 | U6: Inspection Day: | X6: ='General Information'!L1 -> 46315
B8: Project | E8: INFRASTRUCTURE DEVELOPMENT FOR INDUSTRIAL CITY 1 IN JEDDAH | O8: Contractor: | U8: Al Enjaz Company for Trading and Contracting
O9: Consultant: | U9: EGIS Saudi ARABIA CONSULTANT ENGINEERING COMPANY
B11: 4 | D11: Excellent | G11: Quality Management System is being practiced and applies to MODON System | Z11: 90 - 100 | AB11: QC Overall Score | AC11: =Q50 -> 0.85206897 | AN11: =SUM(Z11:Z14) -> 0 | AO11: 100 | AP11: 0.22883295
B12: 3 | D12: Good | G12: Evidence of compliance with plans and procedures. | Z12: 80 - 89 | AN12: =SUM(Y11:Y15) -> 0 | AO12: 89 | AP12: 0.20366133
B13: 2 | D13: Average | G13: Indication level of compliance with standards but there is room for improvement | Z13: 70 - 79 | AO13: 79 | AP13: 0.18077803
B14: 1 | D14: Improve | G14: Quality and Control is NOT being managed effectively. Needs Improvement | Z14: ≤ 69 | AO14: 69 | AP14: 0.15789474
B15: 0 | D15: N/A | G15: Item was not applicable or this item was not reviewed during the inspection. | Z15: Zero | AO15: 100 | AP15: 0.22883295
B17: No. | C17: Topic | K17: E (4) | L17: G (3) | M17: A (2) | N17: I (1) | O17: N/A (0) | Q17: No. | R17: Topic | Z17: E (4) | AA17: G (3) | AB17: A (2) | AC17: I (1) | AD17: N/A (0) | AO17: =SUM(AO11:AO16) -> 437
K18: 1 | L18: 0.89 | M18: 0.79 | N18: 0.69 | O18: 1 | Z18: 1 | AA18: 0.89 | AB18: 0.79 | AC18: 0.69 | AD18: 1 | AF18: =SUM(AF19:AG47)/COUNT(AF19:AG47) -> 0.85206897
B19: 1 | C19: Control of Access to Site/Office | L19: 1 | N19: 0 | Q19: 30 | R19: QC of Excavation | AB19: 1 | AC19: 0 | AD19: 0 | AF19: =SUMPRODUCT($K$18:$O$18,K19:O19) -> 0.89 | AG19: =SUMPRODUCT($Z$18:$AD$18,Z19:AD19) -> 0.79 | AV19: Item Count | AW19: Score | AX19: Distributtion
B20: 2 | C20: Document Control Administration | L20: 1 | M20: 0 | N20: 0 | Q20: 31 | R20: QC of Roads/Round about | AB20: 1 | AC20: 0 | AD20: 0 | AF20: =SUMPRODUCT($K$18:$O$18,K20:O20) -> 0.89 | AG20: =SUMPRODUCT($Z$18:$AD$18,Z20:AD20) -> 0.79 | AX20: Overall | AY20: Relevant
B21: 3 | C21: Project Documents and Progress | L21: 1 | M21: 0 | N21: 0 | Q21: 32 | R21: QC of Interlock & Curbstone | AB21: 1 | AF21: =SUMPRODUCT($K$18:$O$18,K21:O21) -> 0.89 | AG21: =SUMPRODUCT($Z$18:$AD$18,Z21:AD21) -> 0.79 | AM21: 4 | AN21: =58 -> 58 | AO21: counts | AQ21: 4 | AR21: Excellent | AV21: =SUM(Z19:Z47,K19:K47) -> 0 | AW21: =AQ21*AV21 -> 0 | AX21: =AV21/$AV$26 -> 0 | AY21: =AV21/SUM($AV$21:$AV$24) -> 0
B22: 4 | C22: Contractor's Quality Plan/CM (Updated and Reviewed) | M22: 1 | Q22: 33 | R22: Layers/Backfilling Sampling | AB22: 1 | AC22: 0 | AD22: 0 | AF22: =SUMPRODUCT($K$18:$O$18,K22:O22) -> 0.79 | AG22: =SUMPRODUCT($Z$18:$AD$18,Z22:AD22) -> 0.79 | AM22: 3 | AN22: =58 -> 58 | AO22: counts | AQ22: 3 | AR22: Good | AV22: =SUM(L19:L47,AA19:AA47) -> 15 | AW22: =AQ22*AV22 -> 45 | AX22: =AV22/$AV$26 -> 0.25862069 | AY22: =AV22/SUM($AV$21:$AV$24) -> 0.3125
B23: 5 | C23: MS Log and Paperwork | M23: 1 | Q23: 34 | R23: Pump Stations Units | AD23: 1 | AF23: =SUMPRODUCT($K$18:$O$18,K23:O23) -> 0.79 | AG23: =SUMPRODUCT($Z$18:$AD$18,Z23:AD23) -> 1 | AM23: 2 | AN23: =58 -> 58 | AO23: counts | AQ23: 2 | AR23: Average | AV23: =SUM(M19:M47,AB19:AB47) -> 33 | AW23: =AQ23*AV23 -> 66 | AX23: =AV23/$AV$26 -> 0.56896552 | AY23: =AV23/SUM($AV$21:$AV$24) -> 0.6875
B24: 6 | C24: RFI, FIR, & MIR Procedure | M24: 1 | N24: 0 | Q24: 35 | R24: Quality of Form Work | AB24: 1 | AD24: 0 | AF24: =SUMPRODUCT($K$18:$O$18,K24:O24) -> 0.79 | AG24: =SUMPRODUCT($Z$18:$AD$18,Z24:AD24) -> 0.79 | AM24: 1 | AN24: =58 -> 58 | AO24: counts | AQ24: 1 | AR24: Improve | AV24: =SUM(N19:N47,AC19:AC47) -> 0 | AW24: =AQ24*AV24 -> 0 | AX24: =AV24/$AV$26 -> 0 | AY24: =AV24/SUM($AV$21:$AV$24) -> 0
B25: 7 | C25: RFI, FIR, & MIR Inventory system | L25: 1 | M25: 0 | N25: 0 | Q25: 36 | R25: Design Change List | AD25: 1 | AF25: =SUMPRODUCT($K$18:$O$18,K25:O25) -> 0.89 | AG25: =SUMPRODUCT($Z$18:$AD$18,Z25:AD25) -> 1 | AM25: 0 | AN25: =58 -> 58 | AO25: counts | AQ25: 0 | AR25: N/A | AV25: =SUM(O19:O47,AD19:AD47) -> 10 | AW25: =AQ25*AV25 -> 0 | AX25: =AV25/$AV$26 -> 0.17241379 | AY25: -
B26: 8 | C26: NCRs Control & Procedure | M26: 1 | N26: 0 | Q26: 37 | R26: Quality of Concrete Placing | AB26: 1 | AC26: 0 | AD26: 0 | AF26: =SUMPRODUCT($K$18:$O$18,K26:O26) -> 0.79 | AG26: =SUMPRODUCT($Z$18:$AD$18,Z26:AD26) -> 0.79 | AR26: Total | AV26: =SUM(AV21:AV25) -> 58 | AW26: =SUM(AW21:AW25) -> 111 | AX26: =SUM(AX21:AX25) -> 1 | AY26: =SUM(AY21:AY25) -> 1
B27: 9 | C27: NCR Log | L27: 1 | M27: 0 | N27: 0 | Q27: 38 | R27: Concrete Surface Finishing | AB27: 1 | AD27: 0 | AF27: =SUMPRODUCT($K$18:$O$18,K27:O27) -> 0.89 | AG27: =SUMPRODUCT($Z$18:$AD$18,Z27:AD27) -> 0.79
B28: 10 | C28: MODON Standard* | M28: 1 | N28: 0 | Q28: 39 | R28: Pedestals/Columns/Beams Alignment | AB28: 1 | AD28: 0 | AF28: =SUMPRODUCT($K$18:$O$18,K28:O28) -> 0.79 | AG28: =SUMPRODUCT($Z$18:$AD$18,Z28:AD28) -> 0.79 | AV28: Maz Score Available: | AW28: =SUM(AV21:AV24)*AQ21 -> 192 | AX28: <- Excludes N/A items
B29: 11 | C29: Project Risk Plan/Management* | M29: 1 | N29: 0 | Q29: 40 | R29: Siporex Lifting & Unloading | AD29: 1 | AF29: =SUMPRODUCT($K$18:$O$18,K29:O29) -> 0.79 | AG29: =SUMPRODUCT($Z$18:$AD$18,Z29:AD29) -> 1
B30: 12 | C30: Monthly Quality Reports* | L30: 1 | M30: 0 | N30: 0 | O30: 0 | Q30: 41 | R30: Siporex Quality Pre-installation | AD30: 1 | AF30: =SUMPRODUCT($K$18:$O$18,K30:O30) -> 0.89 | AG30: =SUMPRODUCT($Z$18:$AD$18,Z30:AD30) -> 1
B31: 13 | C31: ITP | M31: 1 | Q31: 42 | R31: Siporex Finishing Quality | AD31: 1 | AF31: =SUMPRODUCT($K$18:$O$18,K31:O31) -> 0.79 | AG31: =SUMPRODUCT($Z$18:$AD$18,Z31:AD31) -> 1 | AR31: Total Score | AW31: Percentage (%)
B32: 14 | C32: MODON Weekly Report | L32: 1 | M32: 0 | Q32: 43 | R32: Roads / Parking Markings | AB32: 1 | AF32: =SUMPRODUCT($K$18:$O$18,K32:O32) -> 0.89 | AG32: =SUMPRODUCT($Z$18:$AD$18,Z32:AD32) -> 0.79 | AN32: =MAX(AN21:AN25) -> 58 | AR32: =AW26 -> 111 | AW32: =SUM(100/AR34*AR32) -> 57.8125 | AY32: %
B33: 15 | C33: Design Change Official Paperwork* | L33: 1 | Q33: 44 | R33: QC of Finishing Outdoors | AB33: 1 | AF33: =SUMPRODUCT($K$18:$O$18,K33:O33) -> 0.89 | AG33: =SUMPRODUCT($Z$18:$AD$18,Z33:AD33) -> 0.79 | AR33: Max Score Available | BP33: 31
B34: 16 | C34: Design Change was Applied* | L34: 1 | Q34: 45 | R34: Quality of Finishing Indoors | AD34: 1 | AF34: =SUMPRODUCT($K$18:$O$18,K34:O34) -> 0.89 | AG34: =SUMPRODUCT($Z$18:$AD$18,Z34:AD34) -> 1 | AR34: =AW28 -> 192 | BP34: 32
B35: 17 | C35: Material List | L35: 1 | M35: 0 | O35: 0 | Q35: 46 | R35: Stairs Quality | AD35: 1 | AF35: =SUMPRODUCT($K$18:$O$18,K35:O35) -> 0.89 | AG35: =SUMPRODUCT($Z$18:$AD$18,Z35:AD35) -> 1 | BP35: 33
B36: 18 | C36: Pending Material Status | L36: 1 | M36: 0 | Q36: 47 | R36: Tanks Method Statement Work | AD36: 1 | AF36: =SUMPRODUCT($K$18:$O$18,K36:O36) -> 0.89 | AG36: =SUMPRODUCT($Z$18:$AD$18,Z36:AD36) -> 1 | BP36: 34
B37: 19 | C37: Lifting Plan* | M37: 1 | Q37: 48 | R37: Electric Rooms | AB37: 1 | AF37: =SUMPRODUCT($K$18:$O$18,K37:O37) -> 0.79 | AG37: =SUMPRODUCT($Z$18:$AD$18,Z37:AD37) -> 0.79 | BP37: 35
B38: 20 | C38: DWG Log | L38: 1 | Q38: 49 | R38: QC of MCC/ATS Plant Units | AB38: 0 | AD38: 1 | AF38: =SUMPRODUCT($K$18:$O$18,K38:O38) -> 0.89 | AG38: =SUMPRODUCT($Z$18:$AD$18,Z38:AD38) -> 1 | BP38: 36
B39: 21 | C39: Invoice Status | L39: 1 | Q39: 50 | R39: Qualified Subcontractor | AB39: 1 | AD39: 0 | AF39: =SUMPRODUCT($K$18:$O$18,K39:O39) -> 0.89 | AG39: =SUMPRODUCT($Z$18:$AD$18,Z39:AD39) -> 0.79 | BP39: 37
B40: 22 | C40: Site Handover Letter | O40: 1 | Q40: 51 | R40: Scaffold/Ladders/Slope/Bridge Compliance | AB40: 1 | AF40: =SUMPRODUCT($K$18:$O$18,K40:O40) -> 1 | AG40: =SUMPRODUCT($Z$18:$AD$18,Z40:AD40) -> 0.79 | BP40: 38
B41: 23 | C41: Material Testing Results & Certification | L41: 1 | M41: 0 | Q41: 52 | R41: Protection Applied to Completed Work | AB41: 1 | AD41: 0 | AF41: =SUMPRODUCT($K$18:$O$18,K41:O41) -> 0.89 | AG41: =SUMPRODUCT($Z$18:$AD$18,Z41:AD41) -> 0.79
B42: 24 | C42: As Build Drawings Status* | M42: 1 | Q42: 53 | R42: Storage Management in/out Control | AB42: 1 | AC42: 0 | AF42: =SUMPRODUCT($K$18:$O$18,K42:O42) -> 0.79 | AG42: =SUMPRODUCT($Z$18:$AD$18,Z42:AD42) -> 0.79
B43: 25 | C43: Calibrated Lab Tools & Equipment | L43: 1 | M43: 0 | O43: 0 | Q43: 54 | R43: Material Control | AB43: 1 | AC43: 0 | AD43: 0 | AF43: =SUMPRODUCT($K$18:$O$18,K43:O43) -> 0.89 | AG43: =SUMPRODUCT($Z$18:$AD$18,Z43:AD43) -> 0.79
B44: 26 | C44: Storage Inventory System | M44: 1 | Q44: 55 | R44: Manholes Storing and Quality | AB44: 1 | AC44: 0 | AD44: 0 | AF44: =SUMPRODUCT($K$18:$O$18,K44:O44) -> 0.79 | AG44: =SUMPRODUCT($Z$18:$AD$18,Z44:AD44) -> 0.79
B45: 27 | C45: Logistics Plan | M45: 1 | Q45: 56 | R45: Reinforced Steel Quality | AB45: 1 | AC45: 0 | AD45: 0 | AF45: =SUMPRODUCT($K$18:$O$18,K45:O45) -> 0.79 | AG45: =SUMPRODUCT($Z$18:$AD$18,Z45:AD45) -> 0.79
B46: 28 | C46: Project Progress Planview | M46: 1 | Q46: 57 | R46: Safety Overview | AB46: 1 | AC46: 0 | AD46: 0 | AF46: =SUMPRODUCT($K$18:$O$18,K46:O46) -> 0.79 | AG46: =SUMPRODUCT($Z$18:$AD$18,Z46:AD46) -> 0.79
B47: 29 | C47: Sufficient Number of QC Inspectors | M47: 1 | Q47: 58 | R47: Waste Management Control | AB47: 1 | AD47: 0 | AF47: =SUMPRODUCT($K$18:$O$18,K47:O47) -> 0.79 | AG47: =SUMPRODUCT($Z$18:$AD$18,Z47:AD47) -> 0.79
I49: Score
M50: *QC % | Q50: =AF18 -> 0.85206897
B52: Prepared by: | G52: Imtiyaz Khan | Q52: Issued to PM: | V52: Engr.Abdallah Aljulayfi
B54: *QC Observations refer only to the practices and documentation observed at time of inspection. The responsibility of the CM and Contractor is to ensure that aspects of Quality are suitably managed. *Scores are a reflection of the general site conditions based upon the findings at the time of the walk through *If Applicable

Sheet Quality-Stat  
A1: Quality Reports
A2: Item | D2: Issued | E2: A | F2: B | G2: C | H2: D | I2: Approved
J3: Remaining | K3: Submittals With Consultant | L3: Total Submittals
A5: Non Conforomance Report (NCR) | D5: 16 | E5: 0 | F5: 16 | G5: 0 | H5: 0 | I5: 16 | J5: 0 | K5: =-D515 -> 0 | L5: 16
A6: Site Instruction (SI) | D6: 21 | E6: 0 | F6: 21 | G6: 0 | H6: 0 | I6: 21 | J6: 0 | K6: 0 | L6: 21
A7: Material Inspection Report (MIR) | D7: 100 | E7: 100 | F7: 0 | G7: 0 | H7: 0 | I7: 100 | J7: 0 | K7: 0 | L7: 100
A8: Field Inspection Report (FIR) | D8: 5477 | E8: 905 | F8: 4522 | G8: 5 | H8: 0 | I8: 5427 | J8: 0 | K8: 45 | L8: 5477
A10: Shop Drawings
A11: Item Per WBS | D11: Total IFC | E11: Total Drawings Submitted | J11: Remaining Drawings | K11: Pending | L11: Total Submittals
E12: A | F12: B | G12: C | H12: D | I12: Processed | J12: with Designer | K12: Submittals With Consultant
A13: Roads | D13: 268 | E13: 2 | F13: 266 | G13: 0 | H13: 0 | I13: 268 | K13: 0 | L13: 268
A14: General | D14: 11 | E14: 0 | F14: 11 | G14: 0 | H14: 0 | I14: 11 | K14: 0 | L14: 11
A15: Structural | D15: 590 | E15: 2 | F15: 588 | G15: 0 | H15: 109 | I15: 480 | K15: 0 | L15: 590
A16: Architectural | D16: 2 | E16: 0 | F16: 2 | G16: 0 | H16: 0 | I16: 2 | K16: 0 | L16: 2
A17: Mechanical | C17: Mechanical | D17: 336 | E17: 2 | F17: 397 | G17: 0 | H17: 1 | I17: 264 | K17: 65 | L17: 406
A18: Electrical | C18: Electrical | D18: 220 | E18: 3 | F18: 214 | G18: 0 | H18: 0 | I18: 220 | K18: 0 | L18: 220
A19: TOTAL | D19: =SUM(D13:D18) -> 1427 | E19: =SUM(E13:E18) -> 9 | F19: =SUM(F13:F18) -> 1478 | G19: =SUM(G13:G18) -> 0 | H19: =SUM(H13:H18) -> 110 | I19: =SUM(I13:I18) -> 1245 | K19: =SUM(K13:K18) -> 65 | L19: =SUM(L13:L18) -> 1497
A22: Material Approval
A23: Item Per WBS | D23: Total | E23: Total Materials Submitted | J23: Remaining to approve | K23: Pending | L23: Total Submittals
E24: A | F24: B | G24: C | H24: D | I24: Processed | J24: with Designer | K24: Submittals With Consultant
A25: Civil /Structural /Architectural | D25: 95 | E25: 2 | F25: 90 | G25: 0 | H25: 1 | I25: 92 | K25: 0 | L25: 95
A26: Mechanical | C26: Mechanical | D26: 33 | E26: 2 | F26: 33 | G26: 0 | H26: 0 | I26: 33 | K26: 0 | L26: 33
A27: Electrical | C27: Electrical | D27: 22 | E27: 0 | F27: 16 | G27: 0 | H27: 6 | I27: 16 | K27: 0 | L27: 22
A28: TOTAL | D28: =SUM(D25:D27) -> 150 | E28: =SUM(E25:E27) -> 4 | F28: =SUM(F25:F27) -> 139 | G28: =SUM(G25:G27) -> 0 | H28: =SUM(H25:H27) -> 7 | I28: =SUM(I25:I27) -> 141 | K28: =SUM(K25:K27) -> 0 | L28: =SUM(L25:L27) -> 150
A30: Procurement Summary
A31: Item Per WBS | D31: Total Materials | E31: Total Number of P.O. | F31: Actual P.O. To Date | G31: Remaining P.O | H31: Actual Material on Site | I31: Remaining Materials | J31: Material Delivery Completion (Date)
E32: A | F32: B | G32: C | H32: D | I32: Processed
A33: Civil /Structural /Architectural | D33: 31 | E33: 31 | F33: 31 | G33: =D33-F33 -> 0 | H33: 28 | I33: =D33-H33 -> 3 | J33: 46526
A34: Mechanical | C34: Mechanical | D34: 19 | E34: 19 | F34: 19 | G34: =D34-F34 -> 0 | H34: 19 | I34: =D34-H34 -> 0 | J34: 46567
A35: Electrical | C35: Electrical | D35: 63 | E35: 63 | F35: 58 | G35: =D35-F35 -> 5 | H35: 58 | I35: =D35-H35 -> 5 | J35: 46457
A36: TOTAL | D36: =SUM(D33:D35) -> 113 | E36: =SUM(E33:E35) -> 113 | F36: =SUM(F33:F35) -> 108 | G36: =SUM(G33:G35) -> 5 | H36: =SUM(H33:H35) -> 105 | I36: =SUM(I33:I35) -> 8
A38: Consultant Quality Inspections / Observations (Weekly Basis) | I38: Overall Average | J38: =AVERAGE(E45:E827) -> 0.82810617 | L38: Average Closing | M38: =AVERAGE(G45:G116) -> 2.3414634
A39: Week Number | B39: Date of Audit | C39: Date Issued | D39: Numbers Of Comments | E39: Quality Score | F39: Date Closed | G39: Closure Duration | I39: This Week Score | J39: ='Quality '!AC11 -> 0.85206897 | L39: Average Number of Comments Per Audit | M39: =AVERAGE(D45:D116) -> 3.0731707
A40: Week-1 | B40: 45986
A41: Week-2 | B41: =B40+7 -> 45993
A42: Week-3 | B42: =B41+7 -> 46000
A43: Week-4 | B43: =B42+7 -> 46007
A44: Week-5 | B44: =B43+7 -> 46014
A45: Week-6 | B45: =B44+7 -> 46021 | C45: 46018 | D45: 3 | E45: 0.8 | F45: 46019 | G45: =F45-C45 -> 1
A46: Week-7 | B46: =B45+7 -> 46028 | C46: 46024 | D46: 2 | E46: 0.7 | F46: 46026 | G46: =F46-C46 -> 2
A47: Week-8 | B47: =B46+7 -> 46035 | C47: 46031 | D47: 4 | E47: 0.72 | F47: 46033 | G47: =F47-C47 -> 2
A48: Week-9 | B48: =B47+7 -> 46042 | C48: 46037 | D48: 6 | E48: 0.75 | F48: 46040 | G48: =F48-C48 -> 3
A49: Week-10 | B49: =B48+7 -> 46049 | C49: 46043 | D49: 4 | E49: 0.75 | F49: 46046 | G49: =F49-C49 -> 3
A50: Week-11 | B50: =B49+7 -> 46056 | C50: 46053 | D50: 2 | E50: 0.8 | F50: 46055 | G50: =F50-C50 -> 2
A51: Week-12 | B51: =B50+7 -> 46063 | C51: 46059 | D51: 5 | E51: 0.75 | F51: 46062 | G51: =F51-C51 -> 3
A52: Week-13 | B52: =B51+7 -> 46070 | C52: 46065 | D52: 4 | E52: 0.8 | F52: 46068 | G52: =F52-C52 -> 3
A53: Week-14 | B53: =B52+7 -> 46077 | C53: 46074 | D53: 3 | E53: 0.81 | F53: 46076 | G53: =F53-C53 -> 2
A54: Week-15 | B54: =B53+7 -> 46084 | C54: 46079 | D54: 4 | E54: 0.72 | F54: 46082 | G54: =F54-C54 -> 3
A55: Week-16 | B55: =B54+7 -> 46091 | C55: 46088 | D55: 3 | E55: 0.8 | F55: 46089 | G55: =F55-C55 -> 1
A56: Week-17 | B56: =B55+7 -> 46098 | C56: 46093 | D56: 4 | E56: 0.8 | F56: 46096 | G56: =F56-C56 -> 3
A57: Week-18 | B57: =B56+7 -> 46105
A58: Week-19 | B58: =B57+7 -> 46112 | C58: 46110 | D58: 1 | E58: 0.85 | F58: 46111 | G58: =F58-C58 -> 1
A59: Week-20 | B59: =B58+7 -> 46119 | C59: 46116 | D59: 2 | E59: 0.85 | F59: 46117 | G59: =F59-C59 -> 1
A60: Week-21 | B60: =B59+7 -> 46126 | C60: 46123 | D60: 1 | E60: 0.85 | F60: 46124 | G60: =F60-C60 -> 1
A61: Week-22 | B61: =B60+7 -> 46133 | C61: 46129 | D61: 3 | E61: 0.88 | F61: 46131 | G61: =F61-C61 -> 2
A62: Week-23 | B62: =B61+7 -> 46140 | C62: 46136 | D62: 3 | E62: 0.8 | F62: 46138 | G62: =F62-C62 -> 2
A63: Week-24 | B63: =B62+7 -> 46147 | C63: 46144 | D63: 3 | E63: 0.86 | F63: 46145 | G63: =F63-C63 -> 1
A64: Week-25 | B64: =B63+7 -> 46154 | C64: 46151 | D64: 2 | E64: 0.86 | F64: 46152 | G64: =F64-C64 -> 1
A65: Week-26 | B65: =B64+7 -> 46161 | C65: 46158 | D65: 2 | E65: 0.86 | F65: 46159 | G65: =F65-C65 -> 1
A66: Week-27 | B66: =B65+7 -> 46168
A67: Week-28 | B67: =B66+7 -> 46175 | C67: 46172 | D67: 1 | E67: 0.86 | F67: 46173 | G67: =F67-C67 -> 1
A68: Week-29 | B68: =B67+7 -> 46182 | C68: 46178 | D68: 1 | E68: 0.86 | F68: 46180 | G68: =F68-C68 -> 2
A69: Week-30 | B69: =B68+7 -> 46189 | C69: 46187 | D69: 3 | E69: 0.86 | F69: 46189 | G69: =F69-C69 -> 2
A70: Week-31 | B70: 46196 | C70: 46193 | D70: 4 | E70: 0.84 | F70: 46195 | G70: 2
A71: Week-32 | B71: 46203 | C71: 46200 | D71: 3 | E71: 0.85 | F71: 46202 | G71: 2
A72: Week-33 | B72: 46210 | C72: 46205 | D72: 4 | E72: 0.84 | F72: 46208 | G72: 3
A73: Week-34 | B73: 46215 | C73: 46214 | D73: 3 | E73: 0.85 | F73: 46215 | G73: 2
A74: Week-35 | B74: 46224 | C74: 46221 | D74: 4 | E74: 0.84 | F74: 46223 | G74: 2
A75: Week-36 | B75: 46231 | C75: 46226 | D75: 5 | E75: 0.84 | F75: 46230 | G75: 4
A76: Week-37 | B76: 46238 | C76: 46233 | D76: 4 | E76: 0.85 | F76: 46237 | G76: 4
A77: Week-38 | B77: 46245 | C77: 46240 | D77: 3 | E77: 0.86 | F77: 46244 | G77: 4
A78: Week-39 | B78: 46252 | C78: 46249 | D78: 3 | E78: 0.86 | F78: 46251 | G78: 2
A79: Week-40 | B79: 46259 | C79: 46254 | D79: 4 | E79: 0.85 | F79: 46258 | G79: 4
A80: Week-41 | B80: 46266 | C80: 46263 | D80: 3 | E80: 0.86 | F80: 46265 | G80: 3
A81: Week-42 | B81: 46273 | C81: 46268 | D81: 3 | E81: 0.86 | F81: 46272 | G81: 3
... A83: Week-44 | B83: 46287 | C83: 46282 | D83: 4 | E83: 0.85 | F83: 46286 | G83: 4
A84: Week-45 | B84: 46291 | C84: 46285 | D84: 1 | E84: =AVERAGE(E67:E83) -> 0.85235294 | F84: 46290 | G84: 1
A85: Week-46 | B85: 46301 | C85: 46294 | D85: 3 | E85: 0.86 | F85: 46300 | G85: 3
A86: Week-47 | B86: 46308 | C86: 46303 | D86: 3 | E86: 0.87 | F86: 46307 | G86: 3
A87: Week-48 | B87: 46315 | C87: 46310 | D87: 3 | E87: 0.87 | F87: 46314 | G87: 4

Sheet HSE
B1: MODON HSE Site Inspection Report
B2: Date | E2: ='General Information'!L1 -> 46315 | L2: Inspected By: | T2: Raef M. M.
B4: Project ID. | E4: JDH01-02-003 | L4: Report No. | P4: ='General Information'!L2 -> 47.857143 | W4: MODON PM Name | Y4: Engr.Abdallah Aljulayfi
B6: Project Name: | E6: INFRASTRUCTURE DEVELOPMENT FOR INDUSTRIAL CITY 1 IN JEDDAH | L6: Contractor: | R6: Al Enjaz Company for Trading and Contracting | X6: Safety Performance | AA6: =IF(W29>0,3,IF(L29>6,2,IF(D29>0,2,1)*1)*1) -> 3 | AE6: =(((COUNTIF(L13:Q25,"1")+COUNTIF(AC13:AH25,"1"))*AR13)+(COUNTIF(L13:Q25,"2")+COUNTIF(AC13:AH25,"2"))*AR14+(COUNTIF(L13:Q25,"3")+COUNTIF(AC13:AH25,"3"))*AR15)/((COUNT(L13:Q25)+COUNT(AC13:AH25))*100) -> 0.77173913
B8: Inspections are a snapshot in time and refer only to the practices and documentation observed at the time of the Inspection. It remains the responsibility of the Consultant and Contractor to ensure that all aspects of Health & Safety are suitably managed.
B9: 1 | D9: Good Practice | H9: 2 | I9: Need Improvement | T9: 3 | U9: Fail (Life Threatening Activity) / Comliance with Plan & Procedures | X9: N/A | Y9: Atcitty Not Applicable for this Site Inspection Report
B11: No. | C11: Topic | K11: Wt. | L11: HSE Compliance | S11: No. | T11: Topic | AB11: Wt. | AC11: HSE Compliance
B13: 1 | C13: Access and Egress - (General access to site, segregated from vehicles, / Overhead protection, while entering into the building /Adequate lighting provided when dark or overnight work) | K13: 0.05 | L13: 1 | S13: 14 | T13: Work at Height - (PPE/Fall Protection(Same level, above and blow) / Training / Fall restraint / competency /Safe access & egress to and from work at height / Ladders / Openings (floor/shafts/Provision of emergency rescue) | AB13: 0.05 | AC13: N/A | AP13: 1 | AR13: 100 | AU13: 1
B14: 2 | C14: Traffic Management - (Loading/unloading/sheeting/temp. routes/speed/parking/competence) | K14: 0.03 | L14: 1 | S14: 15 | T14: Scaffolding - (Temp. Scaffolding Work-platform (All types) - qualified scaffolder / Inspection / Tagged / Safe Access/egress / PTW/Falsework & Formwork) | AB14: 0.04 | AC14: N/A | AP14: 2 | AR14: 75 | AU14: 2
B15: 3 | C15: Site Signage - (Project Notice Board & General Signage) | K15: 0.02 | L15: 1 | S15: 16 | T15: Mobile Elevated Work platform (MEWP) - (PTW/competence requirements/conditions/inspections/tagged/training/Full-body harness) | AB15: 0.04 | AC15: N/A | AP15: 3 | AR15: 0 | AU15: 3
B16: 4 | C16: PPE Compliance - (Use, storage, stock, handling & checks - Head, Foot, Eye, Hearing) | K16: 0.05 | L16: 2 | S16: 17 | T16: Excavation & Trenches - (PTW/Edge protection/buffer zone/Slope/Benching/Shoring/Geo-tech report/Atmospheric hazards/Acess&egress/Emergency management / MS&RA/H.E) | AB16: 0.03 | AC16: 2 | AU16: N/A
B17: 5 | C17: Housekeeping - (Material correctly stored/Rubbish cleaned & removed daily/slips & trips hazards) | K17: 0.03 | L17: 2 | S17: 18 | T17: Confined Space - (PTW/Training/competence/Emergency Management/MS & RA/Safe access/egress) | AB17: 0.05 | AC17: 2
B18: 6 | C18: Storage of Materials - (Transporting, storage, training and use - Combustible / Flammable / Hazardous substances (COSHH) | L18: 2 | S18: 19 | T18: Fire Protection - (Flammable/Oxy. LPG /Combustible separated/FE's/Flashback arrestor/Sparks & slags/Smoking area/PTW/Generators/MS & RA/Emergency Management) | AC18: 2 | AL18: Red | AM18: Serious injury or death (immediately)
B19: 7 | C19: Site Waste Management - (Hazardous waste /Combustible waste / Human waste / Construction waste - asphalt, cable, timber, paving roof sheeting tiles, plastic & bricks) | L19: 2 | S19: 20 | T19: Health & Welfare - (Adequate drinking water/shaded - eating & rest area/washing & sanitary facilities/Certified FA/FA Box & Stock/adequate toilets/Ambulance) | AC19: 1 | AL19: Yellow | AM19: Minor or near miss (3 days to comply)
B20: 8 | C20: Health Surveillance - (Expose to excessive noise/vibration/dust/silica/CO/cement/radiation/extreme weather condition) | K20: 0.03 | L20: 1 | S20: 21 | T20: Environmental Incident Measures - (Spill/ Leakage / Concrete wash / vehicle & eqpts. wash / waste disposal/Sewers and drains/emissions/Emergency Management/Training/site run-off water) | AB20: 0.05 | AC20: 2 | AL20: Green | AM20: No issues
B21: 9 | C21: Electrical Safety - (Electrical qualified /RCD/GFCI/Industrial Cocket/LOTO/Cable-overhung or buried/Cords in good condition/current inspection tag) | K21: 0.05 | L21: 2 | S21: 22 | T21: HSE Communications & Meetings - (Schedule HSE Meetings/Safety Committee meetings/Alerts / Lesson learned/Safety Bulletin contains latest HSE KPI) | AB21: 0.05 | AC21: 3
B22: 10 | C22: Tools & Equipment - (Includes, powered, hydraulic & pneumatic/Guards in place/Properly stored/RCD Protection/Earthed/Good condition & tagged) | K22: 0.03 | L22: 2 | S22: 23 | T22: HSE Plan & Associated Procedures - (Approved updated HSE Plan/ CEMP/HAZComm/Procedures/Standards/Project Safety Risk Register) | AB22: 0.03 | AC22: 1 | AL22: 26 points > 4 minors then is it’s a serious issue
B23: 11 | C23: Manual Handling - (Lifting/loading/pulling/pushing/twisting/awkward posture/repetitive task/frequent and prolong physical effort/Reasonable practicable use of mechanical aid) | K23: 0.03 | L23: 2 | S23: 24 | T23: Health, Safety & Environment Incident reporting - (Review of HSE Statistics, Reporting of Unsafe Act & Conditions/ Reporting of Near Miss incident/Reporting of FA cases/Record MT cases) | AB23: 0.03 | AC23: 1
B24: 12 | C24: Vehicle and mobile equipment / Plant - (dumpers; excavators, cranes, piling rigs, grader, roller, loaders/condition/KSA License/certification) | K24: 0.05 | L24: 2 | S24: 25 | T24: HSE Awareness, Training & Competence - (Policy /Objective & targets/Information, training/Climatic condition awareness/Reponses in emergency situation/ Safety Behavior Observation) | AB24: 0.04 | AC24: 1
B25: 13 | C25: Lifting Operations & Rigging - (Lifting Plan/Lifting devices & gears/PTW/Condition/3rd party certification/bank-man/rigger/slingers/man-basket/inspection record/tagged) | L25: 2 | S25: 26 | T25: Project Leadership Site Tours - (Provide evidence of proactive safety performance/Deficient discovered discussed/Positive feedback/Workers resolving safety issues) | AC25: 3
B27: Prepared by: | G27: =T2 -> Raef M. M. | S27: Sent to MODON PM: | X27: Engr.Abdallah Aljulayfi
B28: Safety Results
B29: 1 | D29: =COUNTIF(L13:Q26,"1")+COUNTIF(AB13:AG26,"1") -> 8 | I29: 2 | L29: =COUNTIF(L13:Q26,"2")+COUNTIF(AB13:AG26,"2") -> 13 | U29: 3 | W29: =COUNTIF(L13:Q26,"3")+COUNTIF(AB13:AG26,"3") -> 2

Sheet HSE-Stat 
A1: Safety Statistics
A3: Category | B3: Item | D3: This Week | E3: This Month | F3: Year to Date | G3: Cumulative
A4: Category | B4: Total Hours Worked | D4: 9216 | E4: 26112 | F4: 438898 | G4: =E4+F4 -> 465010
B5: Safe Hours Worked | D5: 9216 | E5: 26112 | F5: 438898 | G5: =E5+F5 -> 465010
B6: LTI | D6: 0 | E6: 0 | F6: 0 | G6: 0
B7: MTC (Healed w/o Disability) | D7: 0 | E7: 0 | F7: 0 | G7: 0
B8: MTC (Healed w/ Disability) | D8: 0 | E8: 0 | F8: 0 | G8: 0
B9: Near Miss | D9: 0 | E9: 0 | F9: 0 | G9: 0
B10: First Aid Cases | D10: 0 | E10: 0 | F10: 0 | G10: 0
B11: Fatality | D11: 0 | E11: 0 | F11: 0 | G11: 0
B12: Fire Incident Cases | D12: 0 | E12: 0 | F12: 0 | G12: 0
B13: Vehicle Incident | D13: 0 | E13: 0 | F13: 0 | G13: 0
B14: Property Damages | D14: 0 | E14: 0 | F14: 0 | G14: 0
A15: Proactive | B15: Induction Training | D15: 0 session | E15: 0 session | F15: 63 | G15: 63
B16: No.of Internal Training | D16: 0session | E16: 0 session | F16: 61 | G16: 61
B17: No.of Internal Audit | D17: 0 | E17: 0 | F17: 0 | G17: 0
B18: No. of Toolbox Talks | D18: 0 sessions | E18: 0 sessions | F18: 88 | G18: 88
B19: Safety Awards/Incentives | D19: 0 | E19: 0 | F19: 0 | G19: 0
I20: Category | J20: Item | L20: This Week | M20: This Month | N20: Year to Date | O20: Cumulative
A22: Consultant Safety Inspection (Weekly Basis) | I22: Overall Average | J22: =AVERAGE(E24:E303) -> 0.7302439
A23: Week Number | B23: Date of Audit | C23: Date Issued | D23: Numbers Of Comments | E23: Overall Score | F23: Date Closed | G23: Closure Duration | I23: This Week Score | J23: =HSE!AE6 -> 0.77173913
A24: Week-1 | B24: 45986
A25: Week-2 | B25: =B24+7 -> 45993
A26: Week-3 | B26: =B25+7 -> 46000
A27: Week-4 | B27: =B26+7 -> 46007
A28: Week-5 | B28: =B27+7 -> 46014
A29: Week-6 | B29: =B28+7 -> 46021 | C29: 46018 | D29: 2 | E29: 0.8 | F29: 46019 | G29: =F29-C29 -> 1
A30: Week-7 | B30: =B29+7 -> 46028 | C30: 46024 | D30: 2 | E30: 0.48 | F30: 46026 | G30: =F30-C30 -> 2
A31: Week-8 | B31: =B30+7 -> 46035 | C31: 46031 | D31: 2 | E31: 0.48 | F31: 46033 | G31: =F31-C31 -> 2
A32: Week-9 | B32: =B31+7 -> 46042 | C32: 46037 | D32: 1 | E32: 0.6 | F32: 46040 | G32: =F32-C32 -> 3
A33: Week-10 | B33: =B32+7 -> 46049 | C33: 46043 | D33: 2 | E33: 0.6 | F33: 46046 | G33: =F33-C33 -> 3
A34: Week-11 | B34: =B33+7 -> 46056 | C34: 46053 | D34: 1 | E34: 0.6 | F34: 46055 | G34: =F34-C34 -> 2
A35: Week-12 | B35: =B34+7 -> 46063 | C35: 46059 | D35: 1 | E35: 0.72 | F35: 46062 | G35: =F35-C35 -> 3
A36: Week-13 | B36: =B35+7 -> 46070 | C36: 46065 | D36: 1 | E36: 0.72 | F36: 46068 | G36: =F36-C36 -> 3
A37: Week-14 | B37: =B36+7 -> 46077 | C37: 46074 | D37: 2 | E37: 0.72 | F37: 46076 | G37: =F37-C37 -> 2
A38: Week-15 | B38: =B37+7 -> 46084 | C38: 46079 | D38: 1 | E38: 0.72 | F38: 46082 | G38: =F38-C38 -> 3
A39: Week-16 | B39: =B38+7 -> 46091 | C39: 46088 | D39: 2 | E39: 0.72 | F39: 46089 | G39: =F39-C39 -> 1
A40: Week-17 | B40: =B39+7 -> 46098 | C40: 46093 | D40: 2 | E40: 0.72 | F40: 46096 | G40: =F40-C40 -> 3
A41: Week-18 | B41: =B40+7 -> 46105
A42: Week-19 | B42: =B41+7 -> 46112 | C42: 46110 | D42: 2 | E42: 0.72 | F42: 46111 | G42: =F42-C42 -> 1
A43: Week-20 | B43: =B42+7 -> 46119 | C43: 46116 | D43: 2 | E43: 0.73 | F43: 46117 | G43: =F43-C43 -> 1
A44: Week-21 | B44: =B43+7 -> 46126 | C44: 46123 | D44: 2 | E44: 0.73 | F44: 46124 | G44: =F44-C44 -> 1
A45: Week-22 | B45: =B44+7 -> 46133 | C45: 46129 | D45: 1 | E45: 0.73 | F45: 46131 | G45: =F45-C45 -> 2
A46: Week-23 | B46: =B45+7 -> 46140 | C46: 46136 | D46: 3 | E46: 0.73 | F46: 46138 | G46: =F46-C46 -> 2
A47: Week-24 | B47: =B46+7 -> 46147 | C47: 46144 | D47: 2 | E47: 0.75 | F47: 46145 | G47: =F47-C47 -> 1
A48: Week-25 | B48: =B47+7 -> 46154 | C48: 46151 | D48: 1 | E48: 0.75 | F48: 46152 | G48: =F48-C48 -> 1
A49: Week-26 | B49: =B48+7 -> 46161 | C49: 46158 | D49: 2 | E49: 0.73 | F49: 46159 | G49: =F49-C49 -> 1
A50: Week-27 | B50: =B49+7 -> 46168
A51: Week-28 | B51: =B50+7 -> 46175 | C51: 46172 | D51: 3 | E51: 0.73 | F51: 46173 | G51: =F51-C51 -> 1
A52: Week-29 | B52: =B51+7 -> 46182 | C52: 46178 | D52: 1 | E52: 0.76 | F52: 46180 | G52: =F52-C52 -> 2
A53: Week-30 | B53: =B52+7 -> 46189 | C53: 46187 | D53: 2 | E53: 0.76 | F53: 46189 | G53: =F53-C53 -> 2
A54: Week-31 | B54: 46196 | C54: 46194 | D54: 4 | E54: 0.64 | F54: 46193 | G54: 3
A55: Week-32 | B55: 46203 | C55: 46201 | D55: 3 | E55: 0.64 | F55: 46202 | G55: 2
A56: Week-33 | B56: 46210 | C56: 46208 | D56: 2 | E56: 0.7 | F56: 46209 | G56: 2
A57: Week-34 | B57: 46217 | C57: 46215 | D57: 3 | E57: 0.75 | F57: 46216 | G57: 3
A58: Week-35 | B58: 46224 | C58: 46222 | D58: 3 | E58: 0.75 | F58: 46223 | G58: 3
A59: Week-36 | B59: 46231 | C59: 46229 | D59: 2 | E59: 0.69 | F59: 46230 | G59: 2
A60: Week-37 | B60: 46238 | C60: 46236 | D60: 3 | E60: 0.69 | F60: 46237 | G60: 2
A61: Week-38 | B61: 46245 | C61: 46243 | D61: 2 | E61: 0.72 | F61: 46244 | G61: 2
A62: Week-39 | B62: 46252 | C62: 46250 | D62: 2 | E62: 0.84 | F62: 46251 | G62: 2
A63: Week-40 | B63: 46259 | C63: 46257 | D63: 2 | E63: 0.84 | F63: 46258 | G63: 2
A64: Week-41 | B64: 46266 | C64: 46264 | D64: 3 | E64: 0.84 | F64: 46265 | G64: 2
A65: Week-42 | B65: 46273 | C65: 46271 | D65: 2 | E65: 0.86 | F65: 46272 | G65: 2
... A71: Week-48 | B71: 46315 | C71: 46313 | D71: 2 | E71: 0.77 | F71: 46312 | G71: 2
A72: Week-49
A73: Week-50
A74: Week-51
A75: Week-52
A76: Week-53
A77: Week-54
A78: Week-55
A79: Week-56
A80: Week-57
A81: Week-58
A82: Week-59
A83: Week-60
... A109: Week-86

Sheet Invoice Log
B1: Weekly Progress Report - Invoice Log | AJ1: Y
B2: Project Value | L2: Payment Status | T2: Invoices Summary | AD2: Average Invoices durations | AJ2: N
B3: Original Contract Value | E3: 86782345 | G3: O&M Value | I3: 0 | K3: Advance Payment % | M3: 0 | O3: Advance Payment (SAR) | Q3: =E3*M3 -> 0 | S3: No of Submitted Invoices | U3: =MAX($C$9:$C$32) -> 6 | W3: Submitted Invoices (SAR) | Y3: =SUM(F9:F32) -> 44851849 | AA3: Submiited Invoice Peroid | AB3: =MAX(L9:L32) -> 46294 | AC3: CM / PgM Average Approval duration | AE3: =IFERROR(AVERAGE(P9:P33),0) -> 0.42857143 | AF3: Average Invoice Value | AG3: =IFERROR(AVERAGE(F9:F32),0) -> 6407407.1
B4: Revised Contract Value | E4: 86782345 | G4: Revised O&M Value | I4: 0 | K4: Retention % | M4: 0 | O4: Retention (SAR) | Q4: =E3*M4 -> 0 | S4: No of Approved Invoices (CM) | U4: =COUNTIF($N$9:$N$33,"Y") -> 7 | W4: Approved Invoices (CM) (SAR) | Y4: =SUMIF($N$9:$N$32,"Y",$J$9:$J$32) -> 51579627 | AC4: MODON PM & Accounts Average Approval duration | AE4: =IFERROR(AVERAGE(W9:W33),0) -> 15.833333
B5: Estimate At Completion Value | E5: 86782345 | G5: Submitted Invoices (Gross Value) | I5: =SUM(F9:F32) -> 44851849 | K5: Penalties and deduction % | M5: =IFERROR(I6/E3,0) -> 0 | O5: AP Recovery (SAR) | Q5: =SUM(G9:G32) -> 0 | S5: No of Approved Invoices (PM) | U5: =COUNTIF($R$9:$R$33,"Y") -> 7 | W5: Approved Invoices (PM) (SAR) | Y5: =SUMIF($R$9:$R$32,"Y",$J$9:$J$32) -> 51579627 | AA5: Invoice Submitted Compared to Contract Value | AB5: =Y3/E4 -> 0.5168315 | AC5: Payments Average Duration | AE5: =IFERROR(AVERAGE(AA9:AA33),0) -> 36.833333
B6: Potential Changes | E6: =E4-E5 -> 0 | G6: Total Deduction | I6: =G33+H33+I33 -> 0 | K6: Penalties and deduction (SAR) | M6: =SUM(I9:I32) -> 0 | O6: Retention Cumulative (SAR) | Q6: =SUM(H9:H32) -> 0 | S6: No of Paid Invoices | U6: =COUNTA(X9:X33) -> 6 | W6: Paid Invoices (SAR) | Y6: =SUM(Y9:Y32) -> 48055958 | AC6: Invoices Average total Duration | AE6: =IFERROR(AVERAGE(AC9:AC33),"") -> 37.5
B7: Invoice Reference | F7: Invoice Value | K7: Period Covered | N7: CM / PgM Approval Timeline | R7: Modon PM & Accounts Approval | Y7: Payment Status | AD7: Total Invoice Duration | AE7: Remarks
B8: # | C8: Invoice No. | D8: Doc Control reference | E8: Submittal Rev. # | F8: Gross Value | G8: AP Recovery | H8: Retention | I8: Deduction / Penalties | J8: Amount (net) | K8: Start Date | L8: End Date | M8: Date to CM / PgM | N8: CM / PgM Approval (Yes/No) | O8: CM / PgM Reply Date | P8: Days Elapsed | Q8: Date to PM | R8: PM Approval (Yes/No) | S8: PM Reply Date | T8: Date to Accounts | U8: Accounts Approval (Yes/No) | V8: Accounts Approval Date | W8: Days Elapsed | X8: Date Paid | Y8: Amount Paid | Z8: Paid % | AA8: Payment Period (d) | AB8: Amount Pending
B9: 1 | C9: 1 | D9: JDH1-02-003-ENJ-TS9-1-COM-INV-0027-01 | E9: 0 | F9: 1992643.8 | G9: =IF(ISBLANK(F9),"",-F9*$M$3) -> 0 | H9: =IF(ISBLANK(F9),"",-F9*$M$4) -> 0 | I9: 0 | J9: =IF(ISBLANK(F9),"",SUM(F9:I9)+F9*0.15) -> 2291540.4 | K9: 45980 | L9: 46047 | M9: 46050 | N9: Y | O9: 46050 | P9: =IF(ISBLANK(O9),"",O9-M9) -> 0 | Q9: 46051 | R9: Y | S9: 46053 | T9: 46063 | U9: Y | V9: 46063 | W9: =IF(ISBLANK(V9),"",V9-Q9) -> 12 | X9: 46152 | Y9: =IF(ISBLANK(X9),"",J9) -> 2291540.4 | Z9: =IF(ISBLANK(X9),"",Y9/J9) -> 1 | AA9: =IF(ISBLANK(V9),"",X9-V9) -> 89 | AB9: =IF(ISBLANK(X9),"",(J9-Y9)) -> 0 | AC9: =IF(ISBLANK(X9),"",X9-M10) -> 40
B10: 2 | C10: 2 | D10: JDH1-02-003-ENJ-TS9-1-COM-INV-0043-01 | E10: 0 | F10: 5438490 | G10: =IF(ISBLANK(F10),"",-F10*$M$3) -> 0 | H10: =IF(ISBLANK(F10),"",-F10*$M$4) -> 0 | I10: 0 | J10: =IF(ISBLANK(F10),"",SUM(F10:I10)+F10*0.15) -> 6254263.5 | K10: 46048 | L10: 46111 | M10: 46112 | N10: Y | O10: 46113 | P10: =IF(ISBLANK(O10),"",O10-M10) -> 1 | Q10: 46113 | R10: Y | S10: 46113 | T10: 46116 | U10: Y | V10: 46117 | W10: =IF(ISBLANK(V10),"",V10-Q10) -> 4 | X10: 46177 | Y10: =IF(ISBLANK(X10),"",J10) -> 6254263.5 | Z10: =IF(ISBLANK(X10),"",Y10/J10) -> 1 | AA10: =IF(ISBLANK(V10),"",X10-V10) -> 60 | AB10: =IF(ISBLANK(X10),"",(J10-Y10)) -> 0 | AC10: =IF(ISBLANK(X10),"",X10-M11) -> 29 | AG10: format if no, make shaded
B11: 3 | C11: 3 | D11: JDH1-02-003-ENJ-TS9-1-COM-INV-0055-00 | E11: 0 | F11: 6962016.4 | G11: =IF(ISBLANK(F11),"",-F11*$M$3) -> 0 | H11: =IF(ISBLANK(F11),"",-F11*$M$4) -> 0 | I11: 0 | J11: =IF(ISBLANK(F11),"",SUM(F11:I11)+F11*0.15) -> 8006318.8 | K11: 46112 | L11: 46148 | M11: 46148 | N11: Y | O11: 46149 | P11: =IF(ISBLANK(O11),"",O11-M11) -> 1 | Q11: 46149 | R11: Y | S11: 46150 | T11: 46150 | U11: Y | V11: 46203 | W11: =IF(ISBLANK(V11),"",V11-Q11) -> 54 | X11: 46208 | Y11: =IF(ISBLANK(X11),"",J11) -> 8006318.8 | Z11: =IF(ISBLANK(X11),"",Y11/J11) -> 1 | AA11: =IF(ISBLANK(V11),"",X11-V11) -> 5 | AB11: =IF(ISBLANK(X11),"",(J11-Y11)) -> 0 | AC11: =IF(ISBLANK(X11),"",X11-M11) -> 60
B12: 4 | C12: 4 | D12: JDH1-02-003-ENJ-TS9-1-COM-INV-0068-00 | E12: 0 | F12: =12538359.91-5102.38 -> 12533258 | G12: =IF(ISBLANK(F12),"",-F12*$M$3) -> 0 | H12: =IF(ISBLANK(F12),"",-F12*$M$4) -> 0 | I12: 0 | J12: =IF(ISBLANK(F12),"",SUM(F12:I12)+F12*0.15) -> 14413246 | K12: 46149 | L12: 46193 | M12: 46202 | N12: Y | O12: 46202 | P12: =IF(ISBLANK(O12),"",O12-M12) -> 0 | Q12: 46202 | R12: Y | S12: 46203 | T12: 46208 | U12: Y | V12: 46210 | W12: =IF(ISBLANK(V12),"",V12-Q12) -> 8 | X12: 46239 | Y12: =IF(ISBLANK(X12),"",J12) -> 14413246 | Z12: =IF(ISBLANK(X12),"",Y12/J12) -> 1 | AA12: =IF(ISBLANK(V12),"",X12-V12) -> 29 | AB12: =IF(ISBLANK(X12),"",(J12-Y12)) -> 0 | AC12: =IF(ISBLANK(X12),"",X12-M12) -> 37
B13: 5 | C13: 5 | D13: JDH1-02-003-ENJ-TS9-1-COM-INV-0078-00 | E13: 0 | F13: 9833283.9 | G13: =IF(ISBLANK(F13),"",-F13*$M$3) -> 0 | H13: =IF(ISBLANK(F13),"",-F13*$M$4) -> 0 | I13: 0 | J13: =IF(ISBLANK(F13),"",SUM(F13:I13)+F13*0.15) -> 11308276 | K13: 46194 | L13: 46233 | M13: 46233 | N13: Y | O13: 46233 | P13: =IF(ISBLANK(O13),"",O13-M13) -> 0 | Q13: 46235 | R13: Y | S13: 46236 | T13: 46239 | U13: Y | V13: 46239 | W13: =IF(ISBLANK(V13),"",V13-Q13) -> 4 | X13: 46264 | Y13: =IF(ISBLANK(X13),"",J13) -> 11308276 | Z13: =IF(ISBLANK(X13),"",Y13/J13) -> 1 | AA13: =IF(ISBLANK(V13),"",X13-V13) -> 25 | AB13: =IF(ISBLANK(X13),"",(J13-Y13)) -> 0 | AC13: =IF(ISBLANK(X13),"",X13-M13) -> 31
B14: 6 | C14: 6 | D14: JDH1-02-003-ENJ-TS9-1-COM-INV-0088-00 | E14: 0 | F14: 5028097.6 | G14: =IF(ISBLANK(F14),"",-F14*$M$3) -> 0 | H14: =IF(ISBLANK(F14),"",-F14*$M$4) -> 0 | I14: 0 | J14: =IF(ISBLANK(F14),"",SUM(F14:I14)+F14*0.15) -> 5782312.3 | K14: 46234 | L14: 46264 | M14: 46264 | N14: Y | O14: 46264 | P14: =IF(ISBLANK(O14),"",O14-M14) -> 0 | Q14: 46266 | R14: Y | S14: 46268 | T14: 46270 | U14: Y | V14: 46279 | W14: =IF(ISBLANK(V14),"",V14-Q14) -> 13 | X14: 46292 | Y14: =IF(ISBLANK(X14),"",J14) -> 5782312.3 | Z14: =IF(ISBLANK(X14),"",Y14/J14) -> 1 | AA14: =IF(ISBLANK(V14),"",X14-V14) -> 13 | AB14: =IF(ISBLANK(X14),"",(J14-Y14)) -> 0 | AC14: =IF(ISBLANK(X14),"",X14-M14) -> 28
B15: 7 | D15: JDH1-02-003-ENJ-TS9-1-COM-INV-0098-00 | E15: 0 | F15: 3064060.1 | G15: =IF(ISBLANK(F15),"",-F15*$M$3) -> 0 | H15: =IF(ISBLANK(F15),"",-F15*$M$4) -> 0 | I15: 0 | J15: =IF(ISBLANK(F15),"",SUM(F15:I15)+F15*0.15) -> 3523669.2 | K15: 46265 | L15: 46294 | M15: 46294 | N15: Y | O15: 46295 | P15: =IF(ISBLANK(O15),"",O15-M15) -> 1 | Q15: 46298 | R15: Y | S15: 46298 | T15: 46301 | W15: =IF(ISBLANK(V15),"",V15-Q15) | Y15: =IF(ISBLANK(X15),"",J15) | Z15: =IF(ISBLANK(X15),"",Y15/J15) | AA15: =IF(ISBLANK(V15),"",X15-V15) | AB15: =IF(ISBLANK(X15),"",(J15-Y15)) | AC15: =IF(ISBLANK(X15),"",X15-M15)
B16: 8 | G16: =IF(ISBLANK(F16),"",-F16*$M$3) | H16: =IF(ISBLANK(F16),"",-F16*$M$4) | J16: =IF(ISBLANK(F16),"",SUM(F16:I16)+F16*0.15) | P16: =IF(ISBLANK(O16),"",O16-M16) | W16: =IF(ISBLANK(V16),"",V16-Q16) | Y16: =IF(ISBLANK(X16),"",J16) | Z16: =IF(ISBLANK(X16),"",Y16/J16) | AA16: =IF(ISBLANK(V16),"",X16-V16) | AB16: =IF(ISBLANK(X16),"",(J16-Y16)) | AC16: =IF(ISBLANK(X16),"",X16-M16)
B17: 9 | J17: =IF(ISBLANK(F17),"",SUM(F17:I17)+F17*0.15)
B18: 10 | J18: =IF(ISBLANK(F18),"",SUM(F18:I18)+F18*0.15)
B19: 11 | J19: =IF(ISBLANK(F19),"",SUM(F19:I19)+F19*0.15)
B20: 12 | J20: =IF(ISBLANK(F20),"",SUM(F20:I20)+F20*0.15) | P20: =IF(ISBLANK(O20),"",O20-M20) | W20: =IF(ISBLANK(V20),"",V20-Q20) | Y20: =IF(ISBLANK(X20),"",J20) | Z20: =IF(ISBLANK(X20),"",Y20/J20) | AA20: =IF(ISBLANK(V20),"",X20-V20) | AB20: =IF(ISBLANK(X20),"",(J20-Y20)) | AC20: =IF(ISBLANK(X20),"",X20-M20)
B21: 13 | J21: =IF(ISBLANK(F21),"",SUM(F21:I21)+F21*0.15) | P21: =IF(ISBLANK(O21),"",O21-M21) | W21: =IF(ISBLANK(V21),"",V21-Q21) | Y21: =IF(ISBLANK(X21),"",J21) | Z21: =IF(ISBLANK(X21),"",Y21/J21) | AA21: =IF(ISBLANK(V21),"",X21-V21) | AB21: =IF(ISBLANK(X21),"",(J21-Y21)) | AC21: =IF(ISBLANK(X21),"",X21-M21)
B22: 14 | J22: =IF(ISBLANK(F22),"",SUM(F22:I22)+F22*0.15) | P22: =IF(ISBLANK(O22),"",O22-M22) | W22: =IF(ISBLANK(V22),"",V22-Q22) | Y22: =IF(ISBLANK(X22),"",J22) | Z22: =IF(ISBLANK(X22),"",Y22/J22) | AA22: =IF(ISBLANK(V22),"",X22-V22) | AB22: =IF(ISBLANK(X22),"",(J22-Y22)) | AC22: =IF(ISBLANK(X22),"",X22-M22)
B23: 15 | J23: =IF(ISBLANK(F23),"",SUM(F23:I23)+F23*0.15) | P23: =IF(ISBLANK(O23),"",O23-M23) | W23: =IF(ISBLANK(V23),"",V23-Q23) | Y23: =IF(ISBLANK(X23),"",J23) | Z23: =IF(ISBLANK(X23),"",Y23/J23) | AA23: =IF(ISBLANK(V23),"",X23-V23) | AB23: =IF(ISBLANK(X23),"",(J23-Y23)) | AC23: =IF(ISBLANK(X23),"",X23-M23)
B24: 16 | J24: =IF(ISBLANK(F24),"",SUM(F24:I24)+F24*0.15) | P24: =IF(ISBLANK(O24),"",O24-M24) | W24: =IF(ISBLANK(V24),"",V24-Q24) | Y24: =IF(ISBLANK(X24),"",J24) | Z24: =IF(ISBLANK(X24),"",Y24/J24) | AA24: =IF(ISBLANK(V24),"",X24-V24) | AB24: =IF(ISBLANK(X24),"",(J24-Y24)) | AC24: =IF(ISBLANK(X24),"",X24-M24)
B25: 17 | J25: =IF(ISBLANK(F25),"",SUM(F25:I25)+F25*0.15) | P25: =IF(ISBLANK(O25),"",O25-M25) | W25: =IF(ISBLANK(V25),"",V25-Q25) | Y25: =IF(ISBLANK(X25),"",J25) | Z25: =IF(ISBLANK(X25),"",Y25/J25) | AA25: =IF(ISBLANK(V25),"",X25-V25) | AB25: =IF(ISBLANK(X25),"",(J25-Y25)) | AC25: =IF(ISBLANK(X25),"",X25-M25)
B26: 18 | J26: =IF(ISBLANK(F26),"",SUM(F26:I26)+F26*0.15) | P26: =IF(ISBLANK(O26),"",O26-M26) | W26: =IF(ISBLANK(V26),"",V26-Q26) | Y26: =IF(ISBLANK(X26),"",J26) | Z26: =IF(ISBLANK(X26),"",Y26/J26) | AA26: =IF(ISBLANK(V26),"",X26-V26) | AB26: =IF(ISBLANK(X26),"",(J26-Y26)) | AC26: =IF(ISBLANK(X26),"",X26-M26)
B27: 19 | J27: =IF(ISBLANK(F27),"",SUM(F27:I27)+F27*0.15) | P27: =IF(ISBLANK(O27),"",O27-M27) | W27: =IF(ISBLANK(V27),"",V27-Q27) | Y27: =IF(ISBLANK(X27),"",J27) | Z27: =IF(ISBLANK(X27),"",Y27/J27) | AA27: =IF(ISBLANK(V27),"",X27-V27) | AB27: =IF(ISBLANK(X27),"",(J27-Y27))
B28: 20 | G28: =IF(ISBLANK(F28),"",-F28*$M$3) | H28: =IF(ISBLANK(F28),"",-F28*$M$4) | J28: =IF(ISBLANK(F28),"",SUM(F28:I28)+F28*0.15) | P28: =IF(ISBLANK(O28),"",O28-M28) | W28: =IF(ISBLANK(V28),"",V28-Q28) | Y28: =IF(ISBLANK(X28),"",J28) | Z28: =IF(ISBLANK(X28),"",Y28/J28) | AA28: =IF(ISBLANK(V28),"",X28-V28) | AB28: =IF(ISBLANK(X28),"",(J28-Y28)) | AC28: =IF(ISBLANK(X28),"",X28-M28)
B29: 21 | G29: =IF(ISBLANK(F29),"",-F29*$M$3) | H29: =IF(ISBLANK(F29),"",-F29*$M$4) | J29: =IF(ISBLANK(F29),"",SUM(F29:I29)+F29*0.15) | P29: =IF(ISBLANK(O29),"",O29-M29) | W29: =IF(ISBLANK(V29),"",V29-Q29) | Y29: =IF(ISBLANK(X29),"",J29) | Z29: =IF(ISBLANK(X29),"",Y29/J29) | AA29: =IF(ISBLANK(V29),"",X29-V29) | AB29: =IF(ISBLANK(X29),"",(J29-Y29)) | AC29: =IF(ISBLANK(X29),"",X29-M29)
B30: 22 | G30: =IF(ISBLANK(F30),"",-F30*$M$3) | H30: =IF(ISBLANK(F30),"",-F30*$M$4) | J30: =IF(ISBLANK(F30),"",SUM(F30:I30)+F30*0.15) | P30: =IF(ISBLANK(O30),"",O30-M30) | W30: =IF(ISBLANK(V30),"",V30-Q30) | Y30: =IF(ISBLANK(X30),"",J30) | Z30: =IF(ISBLANK(X30),"",Y30/J30) | AA30: =IF(ISBLANK(V30),"",X30-V30) | AB30: =IF(ISBLANK(X30),"",(J30-Y30)) | AC30: =IF(ISBLANK(X30),"",X30-M30)
B31: 23 | G31: =IF(ISBLANK(F31),"",-F31*$M$3) | H31: =IF(ISBLANK(F31),"",-F31*$M$4) | J31: =IF(ISBLANK(F31),"",SUM(F31:I31)+F31*0.15) | P31: =IF(ISBLANK(O31),"",O31-M31) | W31: =IF(ISBLANK(V31),"",V31-Q31) | Y31: =IF(ISBLANK(X31),"",J31) | Z31: =IF(ISBLANK(X31),"",Y31/J31) | AA31: =IF(ISBLANK(V31),"",X31-V31) | AB31: =IF(ISBLANK(X31),"",(J31-Y31)) | AC31: =IF(ISBLANK(X31),"",X31-M31)
B32: 24 | G32: =IF(ISBLANK(F32),"",-F32*$M$3) | H32: =IF(ISBLANK(F32),"",-F32*$M$4) | J32: =IF(ISBLANK(F32),"",SUM(F32:I32)+F32*0.15) | P32: =IF(ISBLANK(O32),"",O32-M32) | W32: =IF(ISBLANK(V32),"",V32-Q32) | Y32: =IF(ISBLANK(X32),"",J32) | Z32: =IF(ISBLANK(X32),"",Y32/J32) | AA32: =IF(ISBLANK(V32),"",X32-V32) | AB32: =IF(ISBLANK(X32),"",(J32-Y32)) | AC32: =IF(ISBLANK(X32),"",X32-M32)
E33: TOTAL | F33: =SUM(F9:F32) -> 44851849 | G33: =SUM(G9:G32) -> 0 | H33: =SUM(H9:H32) -> 0 | I33: =SUM(I9:I32) -> 0 | J33: =SUM(J9:J32) -> 51579627 | P33: =IF(ISBLANK(O33),"",O33-M33) | W33: =IF(ISBLANK(V33),"",V33-Q33) | Y33: =SUM(Y9:Y32) -> 48055958 | AA33: =IF(ISBLANK(X33),"",X33-V33) | AB33: =SUM(AB9:AB32) -> 0 | AC33: =IF(ISBLANK(X33),"",X33-M33)
F37: =F33/0.9 -> 49835388

Sheet Invoice Ammount FIR
E1: ='Weekly Progress Report'!$C$28 -> 86782345
A2: SL. | B2: date of FIR | C2: TOTAL AMOUNT | D2: Total Amount % (as per FIR)
A3: 1 | B3: 46014 | C3: 0 | D3: =C3/$E$1 -> 0
A4: 2 | B4: 46021 | C4: 1342209.6 | D4: =C4/$E$1 -> 0.01546639 | G4: weekly invoice
A5: 3 | B5: 46026 | C5: 1548711.5 | D5: =C5/$E$1 -> 0.017845928
A6: 4 | B6: 46033 | C6: 2161553.6 | D6: =C6/$E$1 -> 0.024907757
A7: 5 | B7: 46040 | C7: 2438279.8 | D7: =C7/$E$1 -> 0.028096496
A8: 6 | B8: 46047 | C8: 3413204.4 | D8: =C8/$E$1 -> 0.039330631
A9: 7 | B9: 46055 | C9: 4999723.1 | D9: =C9/$E$1 -> 0.057612215
A10: 8 | B10: 46061 | C10: 6264074.7 | D10: =C10/$E$1 -> 0.072181441
A11: 9 | B11: 46068 | C11: 7612053.4 | D11: =C11/$E$1 -> 0.087714309
A12: 10 | B12: 46077 | C12: 8630947.8 | D12: =C12/$E$1 -> 0.099455112
A13: 11 | B13: 46084 | C13: 9629665.6 | D13: =C13/$E$1 -> 0.11096342
A14: 12 | B14: 46090 | C14: 10832960 | D14: =C14/$E$1 -> 0.12482907
A15: 13 | B15: 46097 | C15: 12485173 | D15: =C15/$E$1 -> 0.14386766
A16: 14 | B16: 46105 | C16: 13373012 | D16: =C16/$E$1 -> 0.1540983
... A46: 44 | B46: 46315 | C46: 57162747 | D46: =C46/$E$1 -> 0.65869097

Sheet CCO
A1: CONTRACT CHANGE ORDER (CCO)
A2: CCO No. | B2: Date Added | C2: Description of Change | D2: Status | E2: SR | F2: Sch Impact (Months) | G2: Date Approved | H2: Duration (days)
A3: - | B3: - | C3: - | D3: - | E3: - | F3: - | G3: - | H3: -

Sheet Procurement
A2: Sr. NO. | B2: Project ID | C2: ACT#inP6 | D2: Item Description | E2: Discipline | F2: (Long \Short) Lead Items | G2: BOQ. No. | H2: Unit | I2: Quantity | J2: Proc. Qty | K2: Required P.O Date | L2: Date of Pur. Order Issued | M2: Purchase Order No. | N2: Supplier | O2: Supplier Phone | P2: Method of Shipping | Q2: Required on Job | R2: E.D.A. to Site | S2: A.D.A. to Site | T2: Lead Time | U2: Approval Status | V2: Completion Rate | W2: The Impact (BOQ Cost) | X2: Remarks
A3: 1
A4: 2 | B4: JDH1-02-003 | C4: Road - Civil | E4: Road - Civil | F4: Short
A5: =A4+1 -> 3 | B5: JDH1-02-003 | C5: CON-LEG101-PR-1390 | D5: Steel Reinforcement | E5: CIVIL | F5: Short | G5: 03 45 00.03 | H5: ton | I5: 126 | J5: 126 | K5: 46021 | L5: 46006 | M5: P116327 | N5: BRC | O5: 599556849 | P5: Local | Q5: 46046 | S5: 46007 | T5: Short | U5: Approved | V5: 1 | X5: Delivered Done | Y5: =IF(AND(L5="",K5<TODAY()),"Delay","") | AA5: =IF(K5<'General Information'!$L$1,1,0) -> 1
A6: =A5+1 -> 4 | B6: JDH1-02-003 | C6: CON-LEG101-PR-1420 | D6: Ready Mixed Concrete | E6: CIVIL | F6: Short | G6: 03 30 00 | H6: m³ | I6: =4037+798 -> 4835 | J6: =4037+798 -> 4835 | K6: 46027 | N6: Enjazco & Al Arabia Construction | P6: Local | Q6: 46070 | S6: 46012 | T6: Short | U6: Approved | V6: 1 | X6: Delivered Done | Y6: =IF(AND(L6="",K6<TODAY()),"Delay","") -> Delay | AA6: =IF(K6<'General Information'!$L$1,1,0) -> 1
A7: =A6+1 -> 5 | B7: JDH1-02-003 | C7: CON-LEG101-PR-3990 | D7: Backfilling Materials | E7: Roads | F7: Short | G7: 31 22 00 | H7: m³ | I7: 234480 | J7: 234480 | K7: 46030 | N7: Enjazco | P7: Local | Q7: 46079 | S7: 45992 | T7: Short | U7: Approved | V7: 1 | X7: Delivered Done | Y7: =IF(AND(L7="",K7<TODAY()),"Delay","") -> Delay | AA7: =IF(K7<'General Information'!$L$1,1,0) -> 1
A8: =A7+1 -> 6 | B8: JDH1-02-003 | C8: CON-LEG101-PR-1470 | D8: Aggregate Base Course | E8: Roads | F8: Short | G8: 32 11 23.01 | H8: m³ | I8: 24870 | J8: 224870 | K8: 46033 | L8: 46029 | N8: Enjazco | P8: Local | Q8: 46184 | R8: 46068 | S8: 46037 | T8: Short | U8: Approved | V8: 1 | X8: Delivered Done | Y8: =IF(AND(L8="",K8<TODAY()),"Delay","") | AA8: =IF(K8<'General Information'!$L$1,1,0) -> 1
A9: =A8+1 -> 7 | B9: JDH1-02-003 | C9: CON-LEG101-PR-1520 | D9: Precast Concrete Kerb | E9: CIVIL | F9: Short | G9: 32 14 13 | H9: m | I9: 59990 | J9: 59990 | K9: 46037 | N9: Enjazco | P9: Local | Q9: 46368 | R9: 46174 | T9: Short | U9: Approved | V9: 1 | X9: Delivered Done | Y9: =IF(AND(L9="",K9<TODAY()),"Delay","") -> Delay | AA9: =IF(K9<'General Information'!$L$1,1,0) -> 1
A10: =A9+1 -> 8 | B10: JDH1-02-003 | C10: CON-LEG101-PR-1550 | D10: Interlocking Block Pavers | E10: CIVIL | F10: Short | G10: 32 14 13.13 | H10: m2 | I10: 57905 | K10: 46037 | P10: Local | Q10: 46368 | T10: Short | U10: Approved | V10: 1 | X10: Delivered Done | Y10: =IF(AND(L10="",K10<TODAY()),"Delay","") -> Delay | AA10: =IF(K10<'General Information'!$L$1,1,0) -> 1
A11: =A10+1 -> 9 | B11: JDH1-02-003 | C11: CON-LEG101-PR-1440 | D11: Water Proofing | E11: CIVIL | F11: Short | G11: 07 00 00.01 | H11: m2 | I11: 19530 | J11: 19530 | K11: 46033 | L11: 46025 | M11: P117746 | N11: Saleh Sunaid | O11: 0506506735 | P11: Local | Q11: 46096 | R11: 46037 | S11: 46027 | T11: Short | U11: Approved | V11: 1 | X11: Delivered Done | Y11: =IF(AND(L11="",K11<TODAY()),"Delay","") | AA11: =IF(K11<'General Information'!$L$1,1,0) -> 1
A12: =A11+1 -> 10 | B12: JDH1-02-003 | C12: CON-LEG101-PR-1580 | D12: Pavement Markings | E12: Roads | F12: Short | G12: 32 17 23 | H12: m2 | I12: 3780 | K12: 46039 | P12: Local | Q12: 46481 | T12: Short | U12: Approved | V12: 1 | X12: Delivered Done | Y12: =IF(AND(L12="",K12<TODAY()),"Delay","") -> Delay | AA12: =IF(K12<'General Information'!$L$1,1,0) -> 1
A13: =A12+1 -> 11 | B13: JDH1-02-003 | C13: CON-LEG101-PR-1500 | D13: Bituminous Base Course | E13: Roads | F13: Short | G13: 32 11 26.01 | H13: m3 | I13: 8290 | J13: 8290 | K13: 46039 | L13: 46023 | N13: ENJAZCO | P13: Local | Q13: 46209 | R13: 46209 | T13: Short | U13: Approved | V13: 1 | X13: Delivered Done | Y13: =IF(AND(L13="",K13<TODAY()),"Delay","") | AA13: =IF(K13<'General Information'!$L$1,1,0) -> 1
A14: =A13+1 -> 12 | B14: JDH1-02-003 | C14: CON-LEG101-PR-1500 | D14: Bituminous Wearing Course | E14: Roads | F14: Short | G14: 32 12 16.01 | H14: m3 | I14: 5920 | J14: 5920 | K14: 46039 | L14: 46023 | N14: ENJAZCO | P14: Local | Q14: 46488 | R14: 46341 | S14: 46294 | T14: Short | U14: Approved | V14: 1 | X14: Delivered Done | Y14: =IF(AND(L14="",K14<TODAY()),"Delay","") | AA14: =IF(K14<'General Information'!$L$1,1,0) -> 1
A15: =A14+1 -> 13 | B15: JDH1-02-003 | C15: CON-LEG101-PR-1610 | D15: Traffic Signs | E15: Roads | F15: Long | G15: 10 14 53 | H15: Nos | I15: 261 | J15: 261 | K15: 46039 | L15: 46016 | M15: P117196 | N15: AL-HARAMAIN | O15: 055 892 8861 | P15: Local | Q15: 46385 | R15: 46295 | T15: Long | U15: Approved | V15: 1 | X15: Delivered Done | Y15: =IF(AND(L15="",K15<TODAY()),"Delay","") | Z15: تحويل عتد م.اسلام عبدالسميع | AA15: =IF(K15<'General Information'!$L$1,1,0) -> 1
A16: =A15+1 -> 14 | B16: JDH1-02-003 | C16: CON-LEG101-PR-2000 | D16: Metal Fence | E16: CIVIL | F16: Long | G16: 32 31 13.04 | H16: m | I16: 3356 | J16: 1623 | K16: 46028 | L16: 46018 | M16: P117265 | N16: BRC | O16: 0583880333 | P16: Local | Q16: 46139 | R16: 46139 | T16: Long | U16: Approved | V16: 1 | X16: Delivered Done | Y16: =IF(AND(L16="",K16<TODAY()),"Delay","") | AA16: =IF(K16<'General Information'!$L$1,1,0) -> 1
A17: =A16+1 -> 15 | B17: JDH1-02-003 | C17: CON-LEG101-PR-2030 | D17: Gates | E17: CIVIL | F17: Long | G17: 32 31 13.01 | H17: Nos | I17: 6 | J17: 6 | K17: 46034 | L17: 46018 | M17: P117265 | N17: BRC | O17: 0583880333 | P17: Local | Q17: 46243 | R17: 46188 | T17: Long | U17: N/A | V17: 0 | X17: N/A | Y17: =IF(AND(L17="",K17<TODAY()),"Delay","") | AA17: =IF(K17<'General Information'!$L$1,1,0) -> 1
A18: =A17+1 -> 16 | B18: JDH1-02-003 | C18: CON-LEG101-PR-2610 | D18: Paint On Cement Plaster | E18: CIVIL | F18: Long | G18: 09 91 00.01 | H18: m2 | I18: 4062 | J18: 4062 | K18: 46040 | L18: 46035 | M18: P118432 | N18: DCP | O18: 0507862088 | P18: Local | Q18: 46168 | R18: 46047 | T18: Long | U18: Approved | V18: 1 | X18: Delivered Done | Y18: =IF(AND(L18="",K18<TODAY()),"Delay","") | AA18: =IF(K18<'General Information'!$L$1,1,0) -> 1
A19: =A18+1 -> 17 | B19: JDH1-02-003 | C19: CON-LEG101-PR-3000 | D19: agricultural soil | E19: CIVIL | F19: Long | G19: 32 90 00.01 | H19: m2 | I19: 9115 | K19: 46040 | P19: Local | Q19: 46632 | T19: Long | X19: PO ISSUED | Y19: =IF(AND(L19="",K19<TODAY()),"Delay","") -> Delay | AA19: =IF(K19<'General Information'!$L$1,1,0) -> 1
A20: =A19+1 -> 18 | B20: JDH1-02-003 | D20: SH-01, Golden daisy bush euryops pectinatus | E20: CIVIL | F20: Short | G20: 32 90 00.01 | H20: m2 | I20: 9115 | K20: 46040 | P20: Local | Q20: 46644 | T20: Short | U20: Approved | V20: 1 | X20: Delivered Done | Y20: =IF(AND(L20="",K20<TODAY()),"Delay","") -> Delay | AA20: =IF(K20<'General Information'!$L$1,1,0) -> 1
A21: =A20+1 -> 19 | B21: JDH1-02-003 | C21: CON-LEG101-PR-2140 | D21: Prestressing Strands | E21: CIVIL | F21: Long | G21: 03 45 00.02 | H21: ton | I21: 24 | J21: 24 | K21: 46035 | L21: 46065 | P21: Local | Q21: 46146 | T21: Long | U21: Approved | V21: 1 | X21: Delivered Done | Y21: =IF(AND(L21="",K21<TODAY()),"Delay","") | Z21: تحويل عتد م.اسلام عبدالسميع | AA21: =IF(K21<'General Information'!$L$1,1,0) -> 1
A22: =A21+1 -> 20 | B22: JDH1-02-003 | C22: CON-LEG101-PR-2200 | D22: Bridge Bearings | E22: CIVIL | F22: Long | G22: 14 70 00.01 | H22: Nos | I22: 14 | J22: 14 | K22: 46039 | L22: 46065 | M22: P121188 | N22: AL-Bunyan | O22: 533251336 | P22: Local | Q22: 46191 | R22: 46097 | T22: Long | U22: Approved | V22: 1 | X22: Delivered Done | Y22: =IF(AND(L22="",K22<TODAY()),"Delay","") | AA22: =IF(K22<'General Information'!$L$1,1,0) -> 1
A23: =A22+1 -> 21 | B23: JDH1-02-003 | C23: CON-LEG101-PR-2390 | D23: Bridge Gully (Scupper) drainage | E23: CIVIL | F23: Long | G23: 33 44 00.01 | H23: Nos | I23: 3 | K23: 46039 | P23: Local | Q23: 46238 | T23: Long | V23: 1 | X23: Delivered Done | Y23: =IF(AND(L23="",K23<TODAY()),"Delay","") -> Delay | Z23: تحويل عتد م.اسلام عبدالسميع | AA23: =IF(K23<'General Information'!$L$1,1,0) -> 1
A24: =A23+1 -> 22 | B24: JDH1-02-003 | C24: CON-LEG101-PR-2170 | D24: New Jersey | E24: CIVIL | F24: Long | G24: 13 14 32.01 | H24: m | I24: 96 | K24: 46039 | P24: Local | Q24: 46289 | T24: Long | U24: Approved | V24: 1 | X24: Delivered Done | Y24: =IF(AND(L24="",K24<TODAY()),"Delay","") -> Delay | Z24: تحويل عتد م.اسلام عبدالسميع | AA24: =IF(K24<'General Information'!$L$1,1,0) -> 1
A25: =A24+1 -> 23 | B25: JDH1-02-003 | C25: CON-LEG101-PR-2230 | D25: Expansion Joints | E25: CIVIL | F25: Long | G25: 07 95 13.01 | H25: m | I25: 28 | J25: 28 | K25: 46039 | L25: 46065 | N25: AL BUNYAN EST LTD | P25: Local | Q25: 46383 | T25: Long | U25: Approved | V25: 1 | X25: Delivered Done | Y25: =IF(AND(L25="",K25<TODAY()),"Delay","") | Z25: تحويل عتد م.اسلام عبدالسميع | AA25: =IF(K25<'General Information'!$L$1,1,0) -> 1
A26: =A25+1 -> 24 | B26: JDH1-02-003 | C26: CON-LEG101-PR-2280 | D26: Guard Rail | E26: CIVIL | F26: Long | G26: 05 50 00.01 | H26: m | I26: 80 | K26: 46039 | P26: Local | Q26: 46412 | T26: Long | U26: Approved | X26: PO ISSUED | Y26: =IF(AND(L26="",K26<TODAY()),"Delay","") -> Delay | Z26: تحويل عتد م.اسلام عبدالسميع | AA26: =IF(K26<'General Information'!$L$1,1,0) -> 1
A27: =A26+1 -> 25 | B27: JDH1-02-003 | C27: CON-LEG101-PR-2360 | D27: Logo MODON | E27: CIVIL | F27: Long | G27: 10 14 23.01 | H27: Nos | I27: 2 | J27: 2 | K27: 46039 | P27: Local | Q27: 46510 | S27: 46275 | T27: Long | U27: Approved | V27: 1 | X27: Delivered Done | Y27: =IF(AND(L27="",K27<TODAY()),"Delay","") -> Delay | Z27: تحويل عتد م.اسلام عبدالسميع | AA27: =IF(K27<'General Information'!$L$1,1,0) -> 1
A28: =A27+1 -> 26 | B28: JDH1-02-003 | C28: CON-LEG101-PR-2320 | D28: GRP Panel | E28: CIVIL | F28: Long | G28: 06 64 00.01 | H28: m2 | I28: 235 | K28: 46039 | P28: Local | Q28: 46490 | T28: Long | X28: PO ISSUED | Y28: =IF(AND(L28="",K28<TODAY()),"Delay","") -> Delay | Z28: تحويل عتد م.اسلام عبدالسميع | AA28: =IF(K28<'General Information'!$L$1,1,0) -> 1
A29: =A28+1 -> 27 | B29: JDH1-02-003 | D29: Membrane waterproofing | E29: CIVIL | F29: Short | G29: 07 13 26.01 | H29: m2 | I29: 644 | J29: 644 | K29: 46039 | L29: 46025 | M29: P117746 | N29: Saleh Sunaid | O29: 0506506735 | P29: Local | Q29: 46412 | R29: 46054 | S29: 46016 | T29: Short | U29: Approved | V29: 1 | X29: Delivered Done | Y29: =IF(AND(L29="",K29<TODAY()),"Delay","") | AA29: =IF(K29<'General Information'!$L$1,1,0) -> 1
A30: =A29+1 -> 28 | B30: JDH1-02-003 | D30: Protective Coating for Concrete Surfaces | E30: CIVIL | F30: Short | G30: 09 96 00.01 | H30: m2 | I30: 1874 | J30: 1874 | K30: 46039 | N30: ENJAZCO | P30: Local | Q30: 46412 | R30: 46266 | T30: Short | U30: Approved | V30: 1 | X30: Delivered Done | Y30: =IF(AND(L30="",K30<TODAY()),"Delay","") -> Delay | AA30: =IF(K30<'General Information'!$L$1,1,0) -> 1
A31: =A30+1 -> 29 | B31: JDH1-02-003 | C31: CON-LEG101-PR-3010 | D31: Curbs and edging | E31: CIVIL | F31: Short | G31: 32 14 13.05 | H31: m | I31: 340 | J31: 340 | K31: 46040 | N31: ENJAZCO | P31: Local | Q31: 46392 | R31: 46266 | T31: Short | U31: Approved | V31: 1 | X31: Delivered Done | Y31: =IF(AND(L31="",K31<TODAY()),"Delay","") -> Delay | AA31: =IF(K31<'General Information'!$L$1,1,0) -> 1
A32: =A31+1 -> 30 | B32: JDH1-02-003 | AA32: =IF(K32<'General Information'!$L$1,1,0) -> 1
A33: =A32+1 -> 31 | B33: JDH1-02-003 | C33: MECHANICAL | AA33: =IF(K33<'General Information'!$L$1,1,0) -> 1
A34: =A33+1 -> 32 | B34: JDH1-02-003 | C34: CON-LEG101-PR-1700 | D34: GRP Pipes for Sewer network | E34: MECHANICAL | F34: Long | G34: 33 31 00 | H34: m | I34: 6737 | J34: 6737 | K34: 46025 | L34: 46008 | M34: P117065 | N34: Tarek Nagadi & Almunif | O34: 0500195198 | P34: Local | Q34: 46135 | R34: 46019 | S34: 46019 | T34: Long | U34: Approved | V34: 1 | X34: Delivered Done | Y34: =IF(AND(L34="",K34<TODAY()),"Delay","") | AA34: =IF(K34<'General Information'!$L$1,1,0) -> 1
A35: =A34+1 -> 33 | B35: JDH1-02-003 | C35: CON-LEG101-PR-1730 | D35: Fiberglass Manholes for Sewer network | E35: MECHANICAL | F35: Long | G35: 33 05 76 | H35: m | I35: 122 | J35: 122 | K35: 46033 | L35: 46385 | M35: P117477 | N35: Tarek Nagadi & Almunif | O35: 0500195198 | P35: Local | Q35: 46144 | R35: 46032 | S35: 46044 | T35: Long | U35: Approved | V35: 1 | X35: Delivered Done | Y35: =IF(AND(L35="",K35<TODAY()),"Delay","") | AA35: =IF(K35<'General Information'!$L$1,1,0) -> 1
A36: =A35+1 -> 34 | B36: JDH1-02-003 | C36: CON-LEG101-PR-1670 | D36: HDPE Pipe (PN 16) for TSE | E36: MECHANICAL | F36: Long | G36: 33 14 13 | H36: m | I36: 9424 | J36: 9424 | K36: 46030 | L36: 46023 | M36: P117621 | N36: Neproplast | O36: 0557128534 | P36: Local | Q36: 46165 | R36: 46029 | T36: Long | U36: Approved | V36: 1 | X36: Delivered Done | Y36: =IF(AND(L36="",K36<TODAY()),"Delay","") | AA36: =IF(K36<'General Information'!$L$1,1,0) -> 1
A37: =A36+1 -> 35 | B37: JDH1-02-003 | C37: CON-LEG101-PR-1360 | D37: Valves for TSE | E37: MECHANICAL | F37: Long | G37: 33 14 19 | H37: Nos | I37: 142 | J37: 142 | K37: 46041 | L37: 46050 | M37: P119667 | N37: SPS | O37: 0505275340 | P37: Local | Q37: 46198 | R37: 46068 | S37: 46056 | T37: Long | U37: Approved | V37: 1 | X37: Delivered Done | Y37: =IF(AND(L37="",K37<TODAY()),"Delay","") | AA37: =IF(K37<'General Information'!$L$1,1,0) -> 1
A38: =A37+1 -> 36 | B38: JDH1-02-003 | C38: CON-LEG101-PR-2440 | D38: Fire Hydrant | E38: MECHANICAL | F38: Long | G38: 33 14 19.15 | H38: Nos | I38: 89 | J38: 89 | K38: 46036 | L38: 46050 | M38: P119667 | N38: SPS | O38: 0505275340 | P38: Local | Q38: 46252 | R38: 46068 | S38: 46056 | T38: Long | U38: Approved | V38: 1 | X38: Delivered Done | Y38: =IF(AND(L38="",K38<TODAY()),"Delay","") | AA38: =IF(K38<'General Information'!$L$1,1,0) -> 1
A39: =A37+1 -> 36 | B39: JDH1-02-003 | C39: CON-LEG101-PR-1790 | D39: GRP Pipes for Storm network | E39: MECHANICAL | F39: Long | G39: 33 42 11 | H39: m | I39: 5939 | J39: 5939 | K39: 46025 | L39: 46000 | N39: Tarek Nagadi & Almunif | O39: 0507779468 | P39: Local | Q39: 46134 | R39: 46007 | S39: 46007 | T39: Long | U39: Approved | V39: 1 | X39: Delivered Done | Y39: =IF(AND(L39="",K39<TODAY()),"Delay","") | Z39: تحويل عند م اسلام عبدالسميع | AA39: =IF(K39<'General Information'!$L$1,1,0) -> 1
A40: =A39+1 -> 37 | B40: JDH1-02-003 | C40: CON-LEG101-PR-1760 | D40: UPVC Pipes | E40: MECHANICAL | F40: Long | G40: 33 42 11 | H40: m | I40: 3127 | J40: 3127 | K40: 46025 | L40: 46374 | M40: P116662 | N40: Al-Munif | O40: 0507775269 | P40: Local | Q40: 46135 | R40: 46052 | S40: 46053 | T40: Long | U40: Approved | V40: 1 | X40: Delivered Done | Y40: =IF(AND(L40="",K40<TODAY()),"Delay","") | AA40: =IF(K40<'General Information'!$L$1,1,0) -> 1
A41: =A38+1 -> 37 | B41: JDH1-02-003 | C41: CON-LEG101-PR-1820 | D41: Inlet Manholes for Storm network | E41: MECHANICAL | F41: Long | G41: 33 05 13 | H41: Nos | I41: 130 | J41: 130 | K41: 46035 | L41: 46013 | M41: P116883 | N41: Tarek Nagadi & Saudi Land | O41: 0553455856 | P41: Local | Q41: 46140 | R41: 46019 | S41: 46019 | T41: Long | U41: Approved | V41: 1 | X41: Delivered Done | Y41: =IF(AND(L41="",K41<TODAY()),"Delay","") | AA41: =IF(K41<'General Information'!$L$1,1,0) -> 1
A42: =A40+1 -> 38 | B42: JDH1-02-003 | C42: CON-LEG101-PR-1850 | D42: Concrete chambers | E42: MECHANICAL | F42: Long | G42: 33 05 13.08 | H42: Nos | I42: 180 | J42: 180 | K42: 46041 | L42: 46043 | M42: P119137 | N42: Tarek Nagadi | O42: 0500195198 | P42: Local | Q42: 46163 | R42: 46068 | S42: 46053 | T42: Long | U42: Approved | V42: 1 | X42: Delivered Done | Y42: =IF(AND(L42="",K42<TODAY()),"Delay","") | AA42: =IF(K42<'General Information'!$L$1,1,0) -> 1
A43: =A42+1 -> 39 | B43: JDH1-02-003 | C43: CON-LEG101-PR-1640 | D43: HDPE Pipe (PN 16) for Ptable Water | E43: MECHANICAL | F43: Long | G43: 33 14 13 | H43: m | I43: 10852 | J43: 10852 | K43: 46032 | L43: 46023 | M43: P117621 | N43: Neproplast | O43: 0557128534 | P43: Local | Q43: 46142 | R43: 46026 | S43: 46026 | T43: Long | U43: Approved | V43: 1 | X43: Delivered Done | Y43: =IF(AND(L43="",K43<TODAY()),"Delay","") | AA43: =IF(K43<'General Information'!$L$1,1,0) -> 1
A44: =A43+1 -> 40 | B44: JDH1-02-003 | C44: CON-LEG101-PR-1330 | D44: Valves for Ptable Water | E44: MECHANICAL | F44: Long | G44: 33 14 19 | H44: Nos | I44: 108 | J44: 108 | K44: 46036 | L44: 46050 | M44: P119667 | N44: SPS | O44: 0505275340 | P44: Local | Q44: 46228 | R44: 46068 | S44: 46056 | T44: Long | U44: Approved | V44: 1 | X44: Delivered Done | Y44: =IF(AND(L44="",K44<TODAY()),"Delay","") | AA44: =IF(K44<'General Information'!$L$1,1,0) -> 1
A45: =A44+1 -> 41 | B45: JDH1-02-003 | C45: CON-LEG101-PR-2960 | D45: Electrical Solenoid Valve | E45: MECHANICAL | F45: Long | G45: 32 84 00.04 | H45: Nos | I45: 8 | K45: 46040 | P45: Local | Q45: 46404 | S45: 46310 | T45: Long | U45: Approved | V45: 1 | X45: Delivered Done | Y45: =IF(AND(L45="",K45<TODAY()),"Delay","") -> Delay | AA45: =IF(K45<'General Information'!$L$1,1,0) -> 1
A46: =A45+1 -> 42 | B46: JDH1-02-003 | C46: CON-LEG101-PR-2970 | D46: Quick coupler valve | E46: MECHANICAL | F46: Long | G46: 32 84 00.06 | H46: Nos | I46: 8 | K46: 46040 | P46: Local | Q46: 46424 | S46: 46310 | T46: Long | U46: Approved | V46: 1 | X46: Delivered Done | AA46: =IF(K46<'General Information'!$L$1,1,0) -> 1
A47: =A46+1 -> 43 | B47: JDH1-02-003 | C47: CON-LEG101-PR-3100 | D47: Flush valve | E47: MECHANICAL | F47: Long | G47: 32 84 00.07 | H47: Nos | I47: 50 | K47: 46040 | P47: Local | Q47: 46449 | S47: 46310 | T47: Long | U47: Approved | V47: 1 | X47: Delivered Done | AA47: =IF(K47<'General Information'!$L$1,1,0) -> 1
A48: =A47+1 -> 44 | B48: JDH1-02-003 | C48: CON-LEG101-PR-2980 | D48: Irrigation controller | E48: MECHANICAL | F48: Long | G48: 32 84 00.09 | H48: Nos | I48: 1 | K48: 46040 | P48: Local | Q48: 46473 | S48: 46310 | T48: Long | U48: Approved | V48: 1 | X48: Delivered Done | AA48: =IF(K48<'General Information'!$L$1,1,0) -> 1
A49: =A48+1 -> 45 | B49: JDH1-02-003 | C49: CON-LEG101-PR-3140 | D49: Decoder for valve | E49: MECHANICAL | F49: Long | G49: 32 84 00.10 | H49: Nos | I49: 8 | K49: 46040 | P49: Local | Q49: 46499 | S49: 46310 | T49: Long | U49: Approved | V49: 1 | X49: Delivered Done | AA49: =IF(K49<'General Information'!$L$1,1,0) -> 1
A50: =A49+1 -> 46 | B50: JDH1-02-003 | C50: CON-LEG101-PR-2990 | D50: Decoder Cables | E50: MECHANICAL | F50: Long | G50: 32 84 00.11 | H50: m | I50: 3225 | K50: 46040 | P50: Local | Q50: 46404 | S50: 46310 | T50: Long | U50: Approved | V50: 1 | X50: Delivered Done | AA50: =IF(K50<'General Information'!$L$1,1,0) -> 1
A51: =A50+1 -> 47 | B51: JDH1-02-003 | C51: CON-LEG101-PR-2820 | D51: Single station decoder | E51: MECHANICAL | F51: Long | G51: 32 84 00.10 | H51: Nos | I51: 8 | K51: 46041 | P51: Local | Q51: 46540 | S51: 46310 | T51: Long | U51: Approved | V51: 1 | X51: Delivered Done | AA51: =IF(K51<'General Information'!$L$1,1,0) -> 1
A52: =A51+1 -> 48 | B52: JDH1-02-003 | C52: CON-LEG101-PR-2750 | D52: Decoder cables 12 AWG | E52: MECHANICAL | F52: Long | G52: 32 84 00.11 | H52: m | I52: 3225 | K52: 46041 | P52: Local | Q52: 46548 | S52: 46310 | T52: Long | U52: Approved | V52: 1 | X52: Delivered Done | AA52: =IF(K52<'General Information'!$L$1,1,0) -> 1
A53: =A52+1 -> 49 | B53: JDH1-02-003 | C53: ELECTRICAL | AA53: =IF(K53<'General Information'!$L$1,1,0) -> 1
A54: =A53+1 -> 50 | B54: JDH1-02-003 | C54: CON-LEG101-PR-3160 | D54: Pipe for Duct | E54: ELECTRICAL | F54: Long | G54: 33 71 19 | H54: m | I54: 700 | K54: 46028 | P54: Local | Q54: 46292 | T54: Long | U54: Approved | V54: 1 | X54: Delivered Done | Y54: =IF(AND(L54="",K54<TODAY()),"Delay","") -> Delay | AA54: =IF(K54<'General Information'!$L$1,1,0) -> 1
A55: =A54+1 -> 51 | B55: JDH1-02-003 | C55: CON-LEG101-PR-3190 | D55: Low Voltage Cables | E55: ELECTRICAL | F55: Long | G55: 26 05 19 | H55: m | I55: 39240 | K55: 46037 | P55: Local | Q55: 46324 | T55: Long | U55: Approved | V55: 1 | X55: Delivered Done | Y55: =IF(AND(L55="",K55<TODAY()),"Delay","") -> Delay | AA55: =IF(K55<'General Information'!$L$1,1,0) -> 1
A56: =A55+1 -> 52 | B56: JDH1-02-003 | C56: CON-LEG101-PR-3200 | D56: Manhole | E56: ELECTRICAL | F56: Long | G56: 33 71 19.13 | H56: Nos | I56: 77 | K56: 46040 | P56: Local | Q56: 46342 | T56: Long | U56: Approved | V56: 1 | X56: Delivered Done | Y56: =IF(AND(L56="",K56<TODAY()),"Delay","") -> Delay | AA56: =IF(K56<'General Information'!$L$1,1,0) -> 1
A57: =A56+1 -> 53 | B57: JDH1-02-003 | C57: CON-LEG101-PR-1260 | D57: Pipe for Duct | E57: ELECTRICAL | F57: Long | G57: 33 71 19 | H57: m | I57: 500 | K57: 46028 | P57: Local | Q57: 46160 | T57: Long | U57: Approved | V57: 1 | X57: Delivered Done | Y57: =IF(AND(L57="",K57<TODAY()),"Delay","") -> Delay | AA57: =IF(K57<'General Information'!$L$1,1,0) -> 1
A58: =A57+1 -> 54 | B58: JDH1-02-003 | C58: CON-LEG101-PR-1240 | D58: Cable Termination & Joints | E58: ELECTRICAL | F58: Long | G58: 26 05 13.16 | H58: Nos | I58: 64 | K58: 46036 | P58: Local | Q58: 46186 | T58: Long | U58: Approved | X58: PO in Delay | Y58: =IF(AND(L58="",K58<TODAY()),"Delay","") -> Delay | AA58: =IF(K58<'General Information'!$L$1,1,0) -> 1
A59: =A58+1 -> 55 | B59: JDH1-02-003 | C59: CON-LEG101-PR-1250 | D59: Earthing System | E59: ELECTRICAL | F59: Long | G59: 26 05 26 | H59: Nos | I59: 70 | K59: 46036 | P59: Local | Q59: 46231 | T59: Long | U59: Approved | V59: 1 | X59: Delivered Done | Y59: =IF(AND(L59="",K59<TODAY()),"Delay","") -> Delay | Z59: Material Submite 2-10-2025 | AA59: =IF(K59<'General Information'!$L$1,1,0) -> 1
A60: =A59+1 -> 56 | B60: JDH1-02-003 | C60: CON-LEG101-PR-1000 | D60: Medium Voltage Cable | E60: ELECTRICAL | F60: Long | G60: 26 05 13.16.01 | H60: m | I60: 14500 | K60: 46040 | P60: Local | Q60: 46152 | T60: Long | U60: Approved | X60: PO in Delay | Y60: =IF(AND(L60="",K60<TODAY()),"Delay","") -> Delay | Z60: Material Submite 2-10-2025 | AA60: =IF(K60<'General Information'!$L$1,1,0) -> 1
A61: =A60+1 -> 57 | B61: JDH1-02-003 | C61: CON-LEG101-PR-1010 | D61: Street Lighting Sub-station | E61: ELECTRICAL | F61: Long | G61: 26 11 16.01 | H61: Nos | I61: 4 | K61: 46040 | P61: Local | Q61: 46260 | T61: Long | U61: Approved | X61: PO ISSUED | Y61: =IF(AND(L61="",K61<TODAY()),"Delay","") -> Delay | AA61: =IF(K61<'General Information'!$L$1,1,0) -> 1
A62: =A61+1 -> 58 | B62: JDH1-02-003 | C62: CON-LEG101-PR-1020 | D62: Low Voltage Cables | E62: ELECTRICAL | F62: Long | G62: 26 05 19 | H62: m | I62: 6115 | K62: 46034 | P62: Local | Q62: 46278 | T62: Long | U62: Approved | V62: 1 | X62: Delivered Done | Y62: =IF(AND(L62="",K62<TODAY()),"Delay","") -> Delay | AA62: =IF(K62<'General Information'!$L$1,1,0) -> 1
A63: =A62+1 -> 59 | B63: JDH1-02-003 | C63: CON-LEG101-PR-2480 | D63: Ring Main Unit | E63: ELECTRICAL | F63: Long | G63: 26 11 16.02 | H63: Nos | I63: 4 | K63: 46040 | P63: Local | Q63: 46315 | T63: Long | U63: Under Review | X63: PO in Delay | Y63: =IF(AND(L63="",K63<TODAY()),"Delay","") -> Delay | AA63: =IF(K63<'General Information'!$L$1,1,0) -> 1
A64: =A63+1 -> 60 | B64: JDH1-02-003 | C64: CON-LEG101-PR-1030 | D64: Lighting poles | E64: ELECTRICAL | F64: Long | G64: 26 56 19.01 | H64: Nos | I64: 443 | J64: 443 | K64: 46039 | L64: 46069 | M64: P121189 | N64: Al-Babtain | O64: 564587728 | P64: Local | Q64: 46261 | R64: 46142 | T64: Long | U64: Approved | V64: 1 | X64: Delivered Done | Y64: =IF(AND(L64="",K64<TODAY()),"Delay","") | AA64: =IF(K64<'General Information'!$L$1,1,0) -> 1
A65: =A64+1 -> 61 | B65: JDH1-02-003 | C65: CON-LEG101-PR-2520 | D65: Lighting panels | E65: ELECTRICAL | F65: Long | G65: 26 27 33 .01 | H65: Nos | I65: 4 | K65: 46041 | P65: Local | Q65: 46321 | T65: Long | U65: Approved | V65: 1 | X65: Delivered Done | Y65: =IF(AND(L65="",K65<TODAY()),"Delay","") -> Delay | AA65: =IF(K65<'General Information'!$L$1,1,0) -> 1
A66: =A65+1 -> 62 | B66: JDH1-02-003 | C66: CON-LEG101-PR-1040 | D66: Street Lighting Luminaire | E66: ELECTRICAL | F66: Long | G66: 26 56 19.02 | H66: Nos | I66: 443 | J66: 443 | K66: 46039 | L66: 46069 | M66: P121189 | N66: Al-Babtain | O66: 564587728 | P66: Local | Q66: 46261 | R66: 46142 | T66: Long | U66: Approved | V66: 1 | X66: Delivered Done | Y66: =IF(AND(L66="",K66<TODAY()),"Delay","") | AA66: =IF(K66<'General Information'!$L$1,1,0) -> 1
A67: =A65+1 -> 62 | B67: JDH1-02-003 | C67: CON-LEG101-PR-1050 | D67: KWHM | E67: ELECTRICAL | F67: Long | G67: 04 20 00.01 | H67: Nos | I67: 4 | K67: 46039 | P67: Local | Q67: 46420 | T67: Long | U67: Approved | V67: 1 | X67: Delivered Done | Y67: =IF(AND(L67="",K67<TODAY()),"Delay","") -> Delay | AA67: =IF(K67<'General Information'!$L$1,1,0) -> 1
A68: =A66+1 -> 63 | B68: JDH1-02-003 | C68: CON-LEG101-PR-1060 | D68: Feeder Piller | E68: ELECTRICAL | F68: Long | G68: 26 24 16.01 | H68: Nos | I68: 10 | K68: 46041 | P68: Local | Q68: 46321 | T68: Long | U68: Approved | V68: 1 | X68: Delivered Done | Y68: =IF(AND(L68="",K68<TODAY()),"Delay","") -> Delay | AA68: =IF(K68<'General Information'!$L$1,1,0) -> 1
A69: =A68+1 -> 64 | B69: JDH1-02-003 | C69: CON-LEG101-PR-1070 | D69: Street Lighting Panels | E69: ELECTRICAL | F69: Long | G69: 26 24 16 | H69: Nos | I69: 4 | K69: 46039 | P69: Local | Q69: 46321 | T69: Long | U69: Approved | V69: 1 | X69: Delivered Done | Y69: =IF(AND(L69="",K69<TODAY()),"Delay","") -> Delay | AA69: =IF(K69<'General Information'!$L$1,1,0) -> 1
A70: =A69+1 -> 65 | B70: JDH1-02-003 | C70: CON-LEG101-PR-3270 | D70: LED Screen 43" (24/7 operation) with Ethernet decoders | E70: ELECTRICAL | F70: Long | G70: 28 20 00.04 | H70: Nos | I70: 4 | K70: 46040 | P70: Local | Q70: 46362 | T70: Long | U70: Approved | V70: 1 | X70: Delivered Done | Y70: =IF(AND(L70="",K70<TODAY()),"Delay","") -> Delay | AA70: =IF(K70<'General Information'!$L$1,1,0) -> 1
A71: =A70+1 -> 66 | B71: JDH1-02-003 | C71: CON-LEG101-PR-3740 | D71: Network Video Recorder 4k 64 Channel | E71: ELECTRICAL | F71: Long | G71: 28 20 00.05 | H71: Nos | I71: 1 | K71: 46040 | P71: Local | Q71: 46426 | T71: Long | U71: Approved | V71: 1 | X71: Delivered Done | Y71: =IF(AND(L71="",K71<TODAY()),"Delay","") -> Delay | AA71: =IF(K71<'General Information'!$L$1,1,0) -> 1
A72: =A71+1 -> 67 | B72: JDH1-02-003 | C72: CON-LEG101-PR-3770 | D72: Keypad | E72: ELECTRICAL | F72: Long | G72: 28 20 00.06 | H72: Nos | I72: 1 | K72: 46040 | P72: Local | Q72: 46433 | T72: Long | U72: Approved | V72: 1 | X72: Delivered Done | Y72: =IF(AND(L72="",K72<TODAY()),"Delay","") -> Delay | AA72: =IF(K72<'General Information'!$L$1,1,0) -> 1
A73: =A72+1 -> 68 | B73: JDH1-02-003 | C73: CON-LEG101-PR-3300 | D73: Fiber Optic Patch Panel 12 port | E73: ELECTRICAL | F73: Long | G73: 27 10 00.01 | H73: Nos | I73: 2 | K73: 46037 | P73: Local | Q73: 46309 | T73: Long | U73: Approved | V73: 1 | X73: Delivered Done | Y73: =IF(AND(L73="",K73<TODAY()),"Delay","") -> Delay | AA73: =IF(K73<'General Information'!$L$1,1,0) -> 1
A74: =A73+1 -> 69 | B74: JDH1-02-003 | C74: CON-LEG101-PR-3310 | D74: Modular Industrial Switches for main pole | E74: ELECTRICAL | F74: Long | G74: 27 20 00.01 | H74: Nos | I74: 1 | K74: 46041 | P74: Local | Q74: 46338 | T74: Long | U74: Approved | V74: 1 | X74: Delivered Done | Y74: =IF(AND(L74="",K74<TODAY()),"Delay","") -> Delay | AA74: =IF(K74<'General Information'!$L$1,1,0) -> 1
A75: =A74+1 -> 70 | B75: JDH1-02-003 | C75: CON-LEG101-PR-3380 | D75: 8POE ports Industrial Switches for remote poles | E75: ELECTRICAL | F75: Long | G75: 27 20 00.02 | H75: Nos | I75: 6 | K75: 46040 | P75: Local | Q75: 46306 | T75: Long | U75: Approved | V75: 1 | X75: Delivered Done | Y75: =IF(AND(L75="",K75<TODAY()),"Delay","") -> Delay | AA75: =IF(K75<'General Information'!$L$1,1,0) -> 1
A76: =A75+1 -> 71 | B76: JDH1-02-003 | C76: CON-LEG101-PR-3420 | D76: Core Switch | E76: ELECTRICAL | F76: Long | G76: 27 20 00.03 | H76: Nos | I76: 2 | K76: 46040 | P76: Local | Q76: 46373 | T76: Long | U76: Approved | V76: 1 | X76: Delivered Done | Y76: =IF(AND(L76="",K76<TODAY()),"Delay","") -> Delay | AA76: =IF(K76<'General Information'!$L$1,1,0) -> 1
A77: =A76+1 -> 72 | B77: JDH1-02-003 | C77: CON-LEG101-PR-3460 | D77: Access Switch 48 port | E77: ELECTRICAL | F77: Long | G77: 27 20 00.04 | H77: Nos | I77: 2 | K77: 46040 | P77: Local | Q77: 46382 | T77: Long | U77: Approved | V77: 1 | X77: Delivered Done | Y77: =IF(AND(L77="",K77<TODAY()),"Delay","") -> Delay | AA77: =IF(K77<'General Information'!$L$1,1,0) -> 1
A78: =A77+1 -> 73 | B78: JDH1-02-003 | C78: CON-LEG101-PR-3500 | D78: Server | E78: ELECTRICAL | F78: Long | G78: 27 42 00.01 | H78: Nos | I78: 3 | K78: 46040 | P78: Local | Q78: 46321 | T78: Long | U78: Approved | V78: 1 | X78: Delivered Done | Y78: =IF(AND(L78="",K78<TODAY()),"Delay","") -> Delay | AA78: =IF(K78<'General Information'!$L$1,1,0) -> 1
A79: =A78+1 -> 74 | B79: JDH1-02-003 | C79: CON-LEG101-PR-3540 | D79: Stand rack 42U- 19" | E79: ELECTRICAL | F79: Long | G79: 27 42 00.02 | H79: Nos | I79: 2 | K79: 46041 | P79: Local | Q79: 46408 | T79: Long | U79: Approved | V79: 1 | X79: Delivered Done | Y79: =IF(AND(L79="",K79<TODAY()),"Delay","") -> Delay | AA79: =IF(K79<'General Information'!$L$1,1,0) -> 1
A80: =A79+1 -> 75 | B80: JDH1-02-003 | C80: CON-LEG101-PR-3580 | D80: IP Outdoor CCTV POE Camera,5 MP, Metal Housing | E80: ELECTRICAL | F80: Long | G80: 28 20 00.01 | H80: Nos | I80: 28 | K80: 46040 | P80: Local | Q80: 46321 | T80: Long | U80: Approved | V80: 1 | X80: Delivered Done | Y80: =IF(AND(L80="",K80<TODAY()),"Delay","") -> Delay | AA80: =IF(K80<'General Information'!$L$1,1,0) -> 1
A81: =A80+1 -> 76 | B81: JDH1-02-003 | C81: CON-LEG101-PR-3640 | D81: Outdoor PTZ with IR, HDTV 1080 and 31x optical, 12x digital | E81: ELECTRICAL | F81: Long | G81: 28 20 00.02 | H81: Nos | I81: 7 | K81: 46040 | P81: Local | Q81: 46345 | T81: Long | U81: Approved | V81: 1 | X81: Delivered Done | AA81: =IF(K81<'General Information'!$L$1,1,0) -> 1
A82: =A81+1 -> 77 | B82: JDH1-02-003 | C82: CON-LEG101-PR-3680 | D82: Security workstation with 1 x 19" LED screen | E82: ELECTRICAL | F82: Long | G82: 28 20 00.03 | H82: Nos | I82: 1 | K82: 46040 | P82: Local | Q82: 46411 | T82: Long | U82: Approved | V82: 1 | X82: Delivered Done | AA82: =IF(K82<'General Information'!$L$1,1,0) -> 1
A83: =A82+1 -> 78 | B83: JDH1-02-003 | C83: CON-LEG101-PR-3720 | D83: Horizontal Power Distribution Unit (min 8 outlets) | E83: ELECTRICAL | F83: Long | G83: 28 20 00.04 | H83: Nos | I83: 4 | K83: 46040 | P83: Local | Q83: 46422 | T83: Long | U83: Approved | V83: 1 | X83: Delivered Done | AA83: =IF(K83<'General Information'!$L$1,1,0) -> 1
A84: =A83+1 -> 79 | B84: JDH1-02-003 | C84: CON-LEG101-PR-3820 | D84: 35 Meters mono pole with Double Platform for Access Points | E84: ELECTRICAL | F84: Long | G84: 26 33 54.01 | H84: Nos | I84: 1 | K84: 46040 | P84: Local | Q84: 46422 | T84: Long | U84: Approved | V84: 1 | X84: Delivered Done | AA84: =IF(K84<'General Information'!$L$1,1,0) -> 1
A85: =A84+1 -> 80 | B85: JDH1-02-003 | C85: CON-LEG101-PR-3860 | D85: 25 Meters pole for CCTV Cameras | E85: ELECTRICAL | F85: Long | G85: 26 33 54.02 | H85: Nos | I85: 6 | K85: 46040 | P85: Local | Q85: 46338 | T85: Long | U85: Approved | V85: 1 | X85: Delivered Done | AA85: =IF(K85<'General Information'!$L$1,1,0) -> 1
A86: =A85+1 -> 81 | B86: JDH1-02-003 | C86: CON-LEG101-PR-3900 | D86: Short Range wireless point to point wireless bridge | E86: ELECTRICAL | F86: Long | G86: 26 33 55.01 | H86: Nos | I86: 12 | K86: 46040 | P86: Local | Q86: 46338 | T86: Long | U86: Approved | V86: 1 | X86: Delivered Done | AA86: =IF(K86<'General Information'!$L$1,1,0) -> 1
R64383: #REF!
A1048480: Y

Sheet Issues
M3: ='General Information'!L1 -> 46315 | N3: Status | O3: Responsibility
N4: Open | O4: Contractor
N5: Closed | O5: Consultant
O6: Modon
O7: Third Party
O8: Other
B9: Issue Log
B10: Issue No | C10: Date Identified | D10: Issue Description | E10: Responsibility | F10: Action Taken | H10: Current Status | I10: Expected/Actual Closure | J10: Duration Elapsed
B11: 1 | C11: 46006 | D11: Update of Aggrement between MODON and SEC for Medium Voltage | E11: Owner | F11: 1. MODON contacted with SEC for getting Electric Source and it is under Process from SEC 2. Enjazco waiting for responding on Lettter No. (2818) 13.01.2026 | H11: Open | I11: 46021 | L11: Owner
B12: 2 | C12: 45986 | D12: Permits from (SEC - STC - NWC) for allowing Construction works for Tie-in Lines (Sewer Line - TSE Line - Potable Water Line) | E12: Contractor | F12: Coordination done with all Servse Providers (STC - NWC - SEC (HV)) | H12: closed | I12: 46063 | L12: Contractor
B13: 3 | D13: Supplier Approval not included in Vendor List :: Pre-Qualification for Post Tension Works, Bearings and Expansion Joints Scope NOT IN VENDOR LIST Emirates Elite Trading Co. (ECO) Freyssinet Menard Saudi Arabia Ltd AL-BUNYAN EST. LT | E13: Owner | F13: PQD Submitted to Egis For Approval | H13: closed | L13: Consultant
B14: 4
B15: 5
B16: 6
B17: 7
B18: 8
B19: 9
B20: 10
B59: 48
B60: 49
B61: 50
B62: 13 | D62: MV Network | H62: Open

Sheet Milestones
A1: Project Name
A2: Item No. | B2: Milestones | C2: Original (Baseline) | D2: Latest | E2: Forecast | G2: Days Change
D3: 129.42857 | E3: =(E4-E5)/7 -> 130.42857 | G3: =(D3-E3)*7 -> -7
A4: 1 | B4: Project Finish | C4: 46709 | D4: 46886 | E4: =O23 -> 46893 | F4: F | G4: =(D4-E4) -> -7
A5: 2 | B5: Project Start | C5: 45980 | D5: 45980 | E5: 45980 | F5: A | G5: =(D5-E5) -> 0
A6: 3 | B6: Finish Mobilization | C6: 45972 | D6: 46085 | E6: =O26 -> 46085 | F6: A | G6: =(D6-E6) -> 0
A7: 4 | B7: Finish Baseline Time Schedule | C7: 46009 | D7: 46009 | E7: =O28 -> 46009 | F7: A | G7: =D7-E7 -> 0
A8: 5 | B8: Finish Submission and Approval for Shop Drawings, Method of Statement, Prequalification and Materials | C8: 46041 | D8: 46326 | E8: =O30 -> 46333 | F8: F | G8: =D8-E8 -> -7
A9: 6 | B9: Finish PO for Short Lead Item & Long Lead Item | C9: 46041 | D9: 46320 | E9: =O32 -> 46327 | F9: F | G9: =D9-E9 -> -7
A10: 7 | B10: Completion of Roads & Meduim Voltage | C10: 46282 | D10: 46398 | E10: =O34 -> 46405 | F10: F | G10: =D10-E10 -> -7
A11: 8 | B11: Completion of Deep infrastructure network | C11: 46344 | D11: 46550 | E11: =O35 -> 46557 | F11: F | G11: =D11-E11 -> -7
A12: 9 | B12: Completion of Shallow infrastructure network | C12: 46464 | D12: 46656 | E12: =O36 -> 46663 | F12: F | G12: =D12-E12 -> -7
A13: 10 | B13: Completion all Works | C13: 46709 | D13: 46886 | E13: =O37 -> 46893 | F13: F | G13: =D13-E13 -> -7
B18: Activity ID | C18: Activity Name | D18: Original Duration | E18: Activity Status | F18: Activity % Complete | G18: Physical % Complete | H18: Duration % Complete | I18: Units % Complete | J18: Schedule % Complete | K18: Performance % Complete | L18: BL Project Start | M18: BL Project Finish | N18: Start | O18: Finish | P18: Budgeted Total Cost | Q18: Planned Value Cost | R18: Earned Value Cost | S18: Actual Total Cost | T18: Budgeted Labor Units | U18: Planned Value Labor Units | V18: Earned Value Labor Units | W18: Actual Labor Units | X18: Total Float | Y18: Auto Compute Actuals
B19: JDH1-02-003 - Infrastructure Development For Industrial City 1 In Jeddah - Update - 20.10.2026 | D19: 763 | H19: 0.3644 | I19: 0.7424 | J19: 0.532 | K19: 0.7874 | L19: 45980 | M19: 46709 | N19: 19-Nov-25 A | O19: 46893 | P19: 86782345 | Q19: 46153497 | R19: 68315969 | S19: 68315984 | T19: 714561.27 | U19: 347982.15 | V19: 528822.75 | W19: 531335.8 | X19: -157
B20: Milestones | D20: 763 | H20: 0.3764 | I20: 0 | J20: 0 | K20: 0 | L20: 45980 | M20: 46709 | N20: 19-Nov-25 A | O20: 46893 | P20: 0 | Q20: 0 | R20: 0 | S20: 0 | T20: 0 | U20: 0 | V20: 0 | W20: 0 | X20: -157
B21: Key Milestones | D21: 763 | H21: 1 | I21: 0 | J21: 0 | K21: 0 | L21: 45980 | M21: 46709 | N21: 19-Nov-25 A | O21: 46893 | P21: 0 | Q21: 0 | R21: 0 | S21: 0 | T21: 0 | U21: 0 | V21: 0 | W21: 0 | X21: -157
B22: CON-LEG101-MS-1090 | C22: Project Commencement Date | D22: 0 | E22: Completed | F22: 1 | G22: 1 | H22: 1 | I22: 0 | J22: 1 | K22: 1 | L22: 45980 | N22: 19-Nov-25 A | P22: 0 | Q22: 0 | R22: 0 | S22: 0 | T22: 0 | U22: 0 | V22: 0 | W22: 0 | Y22: No
B23: CON-LEG101-MS-1000 | C23: Project Completion Date | D23: 0 | E23: Not Started | F23: 0 | G23: 0 | H23: 0 | I23: 0 | J23: 0 | K23: 0 | M23: 46709 | O23: 46893 | P23: 0 | Q23: 0 | R23: 0 | S23: 0 | T23: 0 | U23: 0 | V23: 0 | W23: 0 | X23: -157 | Y23: No
B24: Contractual Milestone | D24: 733 | H24: 0.3509 | I24: 0 | J24: 0 | K24: 0 | L24: 46009 | M24: 46709 | N24: 18-Dec-25 A | O24: 46893 | P24: 0 | Q24: 0 | R24: 0 | S24: 0 | T24: 0 | U24: 0 | V24: 0 | W24: 0 | X24: -157
B25: Mobilization | D25: 0 | H25: 0 | I25: 0 | J25: 0 | K25: 0 | L25: 46009 | M25: 46009 | N25: 04-Mar-26 A | O25: 04-Mar-26 A | P25: 0 | Q25: 0 | R25: 0 | S25: 0 | T25: 0 | U25: 0 | V25: 0 | W25: 0
B26: CON-LEG101-MS-1070 | C26: Finish Mobilization | D26: 0 | E26: Completed | F26: 1 | G26: 1 | H26: 1 | I26: 0 | J26: 1 | K26: 1 | M26: 46009 | O26: 46085 | P26: 0 | Q26: 0 | R26: 0 | S26: 0 | T26: 0 | U26: 0 | V26: 0 | W26: 0 | Y26: No
B27: Time Schedule | D27: 0 | H27: 0 | I27: 0 | J27: 0 | K27: 0 | L27: 46009 | M27: 46009 | N27: 18-Dec-25 A | O27: 46009 | P27: 0 | Q27: 0 | R27: 0 | S27: 0 | T27: 0 | U27: 0 | V27: 0 | W27: 0
B28: CON-LEG101-MS-1080 | C28: Finish Baseline Time Schedule | D28: 0 | E28: Completed | F28: 1 | G28: 1 | H28: 1 | I28: 0 | J28: 1 | K28: 1 | M28: 46009 | O28: 46009 | P28: 0 | Q28: 0 | R28: 0 | S28: 0 | T28: 0 | U28: 0 | V28: 0 | W28: 0 | Y28: No
B29: Engineering | D29: 0 | H29: 0 | I29: 0 | J29: 0 | K29: 0 | L29: 46041 | M29: 46041 | N29: 46333 | O29: 46333 | P29: 0 | Q29: 0 | R29: 0 | S29: 0 | T29: 0 | U29: 0 | V29: 0 | W29: 0 | X29: -55
B30: CON-LEG101-MS-1060 | C30: Finish Submission and Approval for Shop Drawings, Method of Statement, Prequalification and Materials | D30: 0 | E30: Not Started | F30: 0 | G30: 0 | H30: 0 | I30: 0 | J30: 1 | K30: 0 | M30: 46041 | O30: 46333 | P30: 0 | Q30: 0 | R30: 0 | S30: 0 | T30: 0 | U30: 0 | V30: 0 | W30: 0 | X30: -55 | Y30: No
B31: Procurement | D31: 0 | H31: 0 | I31: 0 | J31: 0 | K31: 0 | L31: 46041 | M31: 46041 | N31: 46327 | O31: 46327 | P31: 0 | Q31: 0 | R31: 0 | S31: 0 | T31: 0 | U31: 0 | V31: 0 | W31: 0 | X31: -49
B32: CON-LEG101-MS-1100 | C32: Finish PO for Short Lead Item & Long Lead Item | D32: 0 | E32: Not Started | F32: 0 | G32: 0 | H32: 0 | I32: 0 | J32: 1 | K32: 0 | M32: 46041 | O32: 46327 | P32: 0 | Q32: 0 | R32: 0 | S32: 0 | T32: 0 | U32: 0 | V32: 0 | W32: 0 | X32: -49 | Y32: No
B33: Construction | D33: 408 | H33: 0 | I33: 0 | J33: 0 | K33: 0 | L33: 46282 | M33: 46709 | N33: 46405 | O33: 46893 | P33: 0 | Q33: 0 | R33: 0 | S33: 0 | T33: 0 | U33: 0 | V33: 0 | W33: 0 | X33: -157
B34: CON-LEG101-MS-1130 | C34: Completion of Deep infrastructure network | D34: 0 | E34: Not Started | F34: 0 | G34: 0 | H34: 0 | I34: 0 | J34: 0 | K34: 0 | M34: 46344 | O34: 46405 | P34: 0 | Q34: 0 | R34: 0 | S34: 0 | T34: 0 | U34: 0 | V34: 0 | W34: 0 | X34: 43 | Y34: No
B35: CON-LEG101-MS-1120 | C35: Completion of Roads & Meduim Voltage | D35: 0 | E35: Not Started | F35: 0 | G35: 0 | H35: 0 | I35: 0 | J35: 1 | K35: 0 | M35: 46282 | O35: 46557 | P35: 0 | Q35: 0 | R35: 0 | S35: 0 | T35: 0 | U35: 0 | V35: 0 | W35: 0 | X35: -106 | Y35: No
B36: CON-LEG101-MS-1140 | C36: Completion of Shallow infrastructure network | D36: 0 | E36: Not Started | F36: 0 | G36: 0 | H36: 0 | I36: 0 | J36: 0 | K36: 0 | M36: 46464 | O36: 46663 | P36: 0 | Q36: 0 | R36: 0 | S36: 0 | T36: 0 | U36: 0 | V36: 0 | W36: 0 | X36: -42 | Y36: No
B37: CON-LEG101-MS-1150 | C37: Completion all Works | D37: 0 | E37: Not Started | F37: 0 | G37: 0 | H37: 0 | I37: 0 | J37: 0 | K37: 0 | M37: 46709 | O37: 46893 | P37: 0 | Q37: 0 | R37: 0 | S37: 0 | T37: 0 | U37: 0 | V37: 0 | W37: 0 | X37: -157 | Y37: No
B38: Monitoring and Control Milestone | D38: 260 | H38: 0 | I38: 0 | J38: 0 | K38: 0 | L38: 46511 | M38: 46678 | N38: 46558 | O38: 46861 | P38: 0 | Q38: 0 | R38: 0 | S38: 0 | T38: 0 | U38: 0 | V38: 0 | W38: 0 | X38: -153
B39: Mobilization | D39: 112 | H39: 1 | I39: 1 | J39: 0 | K39: 0 | L39: 45980 | M39: 46009 | N39: 19-Nov-25 A | O39: 04-Mar-26 A | P39: 0 | Q39: 0 | R39: 0 | S39: 0 | T39: 20050 | U39: 20050 | V39: 20050 | W39: 20050
B40: Engineering | D40: 287 | H40: 0.9477 | I40: 0.9879 | J40: 1 | K40: 0.9914 | L40: 45987 | M40: 46041 | N40: 01-Dec-25 A | O40: 46333 | P40: 2601460.4 | Q40: 2601460.4 | R40: 2579200.4 | S40: 2579202.4 | T40: 33415 | U40: 33415 | V40: 33009.2 | W40: 33009.2 | X40: -55
B41: Procurement | D41: 502 | H41: 0.4995 | I41: 0.91 | J41: 0.7789 | K41: 0.9068 | L41: 46019 | M41: 46644 | N41: 25-Nov-25 A | O41: 46620 | P41: 17355662 | Q41: 13518577 | R41: 15737880 | S41: 15737880 | T41: 82413.81 | U41: 48080.56 | V41: 74996.76 | W41: 74996.78 | X41: 30
B42: Construction | D42: 710 | H42: 0.3549 | I42: 0.7242 | J42: 0.5167 | K42: 0.7669 | L42: 46011 | M42: 46678 | N42: 20-Nov-25 A | O42: 46861 | P42: 58147531 | Q42: 30033459 | R42: 44572325 | S42: 44572338 | T42: 545268.46 | U42: 246436.59 | V42: 390120.29 | W42: 392633.33 | X42: -153
B43: Testing & Commissioning | D43: 167 | H43: 0.239 | I43: 0.531 | J43: 0 | K43: 0.6253 | L43: 46603 | M43: 46686 | N43: 15-Jun-26 A | O43: 46869 | P43: 8677691.2 | Q43: 0 | R43: 5426563.3 | S43: 5426563.3 | T43: 20050 | U43: 0 | V43: 10646.5 | W43: 10646.5 | X43: -157
B44: Project Close-out | D44: 145 | H44: 0 | I44: 0 | J44: 0 | K44: 0 | L44: 46613 | M44: 46709 | N44: 46725 | O44: 46893 | P44: 0 | Q44: 0 | R44: 0 | S44: 0 | T44: 13364 | U44: 0 | V44: 0 | W44: 0 | X44: -157

Sheet EV-Chart Data
B2: Baseline Plan | E2: Revised / Recovery Plan | H2: Earned Value | K2: Gross Paid Value | N2: Forecast | Q2: Actual/Fcst vs Plan
A3: Month | B3: Monthly | C3: Cum | D3: % | E3: Monthly | F3: Cum | G3: % | H3: Monthly | I3: Cum | J3: % | K3: Monthly | L3: Cum | M3: % | N3: Monthly | O3: C um | Q3: Month | R3: Cum
A4: 45991 | C4: =B4 -> 0 | D4: =C4/$C$27 -> 0 | H4: =I4 -> 204246.48 | I4: 204246.48 | J4: =I4/$C$27 -> 0.0023535488 | K4: 0 | L4: =K4 -> 0 | M4: =L4/$C$27 -> 0 | Q4: =(H4+N4)-B4 -> 204246.48 | R4: =Q4 -> 204246.48 | T4: Actuals thru previous month
A5: =A4+31 -> 46022 | B5: 945885.87 | C5: =C4+B5 -> 945885.87 | D5: =C5/$C$27 -> 0.01089952 | H5: =I5-I4 -> 4365181.2 | I5: 4569427.7 | J5: =I5/$C$27 -> 0.052653886 | K5: 0 | L5: =L4+K5 -> 0 | M5: =L5/$C$27 -> 0 | Q5: =(H5+N5)-B5 -> 3419295.3 | R5: =Q5+R4 -> 3623541.8
A6: =A5+28 -> 46050 | B6: 2527898.4 | C6: =C5+B6 -> 3473784.2 | D6: =C6/$C$27 -> 0.040028698 | H6: =I6-I5 -> 7095979.2 | I6: 11665407 | J6: =I6/$C$27 -> 0.13442143 | K6: 0 | L6: =L5+K6 -> 0 | M6: =L6/$C$27 -> 0 | Q6: =(H6+N6)-B6 -> 4568080.8 | R6: =Q6+R5 -> 8191622.6
A7: =A6+31 -> 46081 | B7: 2865444.2 | C7: =C6+B7 -> 6339228.4 | D7: =C7/$C$27 -> 0.073047444 | H7: =I7-I6 -> 6859828.3 | I7: 18525235 | J7: =I7/$C$27 -> 0.21346779 | K7: 0 | L7: =L6+K7 -> 0 | M7: =L7/$C$27 -> 0 | Q7: =(H7+N7)-B7 -> 3994384.1 | R7: =Q7+R6 -> 12186007
A8: =A7+31 -> 46112 | B8: 778518.31 | C8: =C7+B8 -> 7117746.8 | D8: =C8/$C$27 -> 0.082018373 | H8: =I8-I7 -> 5417836.6 | I8: 23943072 | J8: =I8/$C$27 -> 0.27589796 | K8: 0 | L8: =L7+K8 -> 0 | M8: =L8/$C$27 -> 0 | Q8: =(H8+N8)-B8 -> 4639318.3 | R8: =Q8+R7 -> 16825325 | T8: Forecast current and future months
A9: =A8+30 -> 46142 | B9: 6018470.8 | C9: =C8+B9 -> 13136218 | D9: =C9/$C$27 -> 0.1513697 | H9: =I9-I8 -> 9609746.1 | I9: 33552818 | J9: =I9/$C$27 -> 0.38663184 | K9: 0 | L9: =L8+K9 -> 0 | M9: =L9/$C$27 -> 0 | Q9: =(H9+N9)-B9 -> 3591275.4 | R9: =Q9+R8 -> 20416600
A10: =A9+31 -> 46173 | B10: 5115924.7 | C10: =C9+B10 -> 18252142 | D10: =C10/$C$27 -> 0.21032092 | H10: =I10-I9 -> 6579364.9 | I10: 40132183 | J10: =I10/$C$27 -> 0.4624464 | K10: 0 | L10: =L9+K10 -> 0 | M10: =L10/$C$27 -> 0 | Q10: =(H10+N10)-B10 -> 1463440.2 | R10: =Q10+R9 -> 21880041
A11: =A10+30 -> 46203 | B11: 6349563.3 | C11: =C10+B11 -> 24601705 | D11: =C11/$C$27 -> 0.28348745 | H11: =I11-I10 -> 6399095.8 | I11: 46531279 | J11: =I11/$C$27 -> 0.5361837 | K11: 0 | L11: =L10+K11 -> 0 | M11: =L11/$C$27 -> 0 | Q11: =(H11+N11)-B11 -> 49532.51 | R11: =Q11+R10 -> 21929573
A12: =A11+31 -> 46234 | B12: 5904651.3 | C12: =C11+B12 -> 30506357 | D12: =C12/$C$27 -> 0.35152722 | H12: =I12-I11 -> 7824666.8 | I12: 54355945 | J12: =I12/$C$27 -> 0.62634797 | K12: 0 | L12: =L11+K12 -> 0 | M12: =L12/$C$27 -> 0 | Q12: =(H12+N12)-B12 -> 1920015.4 | R12: =Q12+R11 -> 23849589
A13: =A12+31 -> 46265 | B13: 7367495 | C13: =C12+B13 -> 37873852 | D13: =C13/$C$27 -> 0.43642347 | H13: =I13-I12 -> 8165098.4 | I13: 62521044 | J13: =I13/$C$27 -> 0.72043506 | K13: 0 | L13: =L12+K13 -> 0 | M13: =L13/$C$27 -> 0 | Q13: =(H13+N13)-B13 -> 797603.45 | R13: =Q13+R12 -> 24647192
A14: =A13+30 -> 46295 | B14: 6675161.8 | C14: =C13+B14 -> 44549014 | D14: =C14/$C$27 -> 0.5133419 | H14: =I14-I13 -> 3874944.4 | I14: 66395988 | J14: =I14/$C$27 -> 0.76508636 | K14: 0 | L14: =L13+K14 -> 0 | M14: =L14/$C$27 -> 0 | Q14: =(H14+N14)-B14 -> -2800217.4 | R14: =Q14+R13 -> 21846975
A15: =A14+31 -> 46326 | B15: 2226357.7 | C15: =C14+B15 -> 46775371 | D15: =C15/$C$27 -> 0.5389964 | H15: =I15-I14 -> 1919980.6 | I15: 68315969 | J15: =I15/$C$27 -> 0.78721045 | L15: =L14+K15 -> 0 | M15: =L15/$C$27 -> 0 | N15: 381926.64 | O15: =N15+I15 -> 68697895 | P15: =O15/$C$27 -> 0.79161142 | Q15: =(H15+N15)-B15 -> 75549.56 | R15: =Q15+R14 -> 21922524
A16: =A15+30 -> 46356 | B16: 5664986.4 | C16: =C15+B16 -> 52440358 | D16: =C16/$C$27 -> 0.6042745 | N16: =604137.18+199800 -> 803937.18 | O16: =N16+O15 -> 69501833 | P16: =O16/$C$27 -> 0.80087526
A17: =A16+31 -> 46387 | B17: 4709802.4 | C17: =C16+B17 -> 57150160 | D17: =C17/$C$27 -> 0.65854593 | N17: 650999.88 | O17: =N17+O16 -> 70152833 | P17: =O17/$C$27 -> 0.80837678
A18: =A17+31 -> 46418 | B18: 2450893 | C18: =C17+B18 -> 59601053 | D18: =C18/$C$27 -> 0.68678777 | N18: 1419963.8 | O18: =N18+O17 -> 71572796 | P18: =O18/$C$27 -> 0.82473914
A19: =A18+28 -> 46446 | B19: 2606967.7 | C19: =C18+B19 -> 62208021 | D19: =C19/$C$27 -> 0.71682807 | N19: 240430.02 | O19: =N19+O18 -> 71813226 | P19: =O19/$C$27 -> 0.82750963
A20: =A19+31 -> 46477 | B20: 3761453.3 | C20: =C19+B20 -> 65969474 | D20: =C20/$C$27 -> 0.7601716 | N20: =1604803.38-398611.17 -> 1206192.2 | O20: =N20+O19 -> 73019419 | P20: =O20/$C$27 -> 0.84140869
A21: =A20+30 -> 46507 | B21: 2318874.6 | C21: =C20+B21 -> 68288349 | D21: =C21/$C$27 -> 0.78689218 | N21: 1005171.1 | O21: =N21+O20 -> 74024590 | P21: =O21/$C$27 -> 0.85299135
A22: =A21+31 -> 46538 | B22: 2398376.1 | C22: =C21+B22 -> 70686725 | D22: =C22/$C$27 -> 0.81452886 | N22: 1460265.7 | O22: =N22+O21 -> 75484855 | P22: =O22/$C$27 -> 0.86981811 | U22: Extended Duration
A23: =A22+30 -> 46568 | B23: 3208784.2 | C23: =C22+B23 -> 73895509 | D23: =C23/$C$27 -> 0.85150394 | N23: 1135063.4 | O23: =N23+O22 -> 76619919 | P23: =O23/$C$27 -> 0.88289754
A24: =A23+31 -> 46599 | B24: 1687613.5 | C24: =C23+B24 -> 75583122 | D24: =C24/$C$27 -> 0.87095045 | N24: =1657215.9-228000 -> 1429215.9 | O24: =N24+O23 -> 78049135 | P24: =O24/$C$27 -> 0.89936651
A25: =A24+31 -> 46630 | B25: 5271091.4 | C25: =C24+B25 -> 80854214 | D25: =C25/$C$27 -> 0.93168967 | N25: 1091632.2 | O25: =N25+O24 -> 79140767 | P25: =O25/$C$27 -> 0.91194548
A26: =A25+30 -> 46660 | B26: 2475992.5 | C26: =C25+B26 -> 83330206 | D26: =C26/$C$27 -> 0.96022073 | N26: 1044925.6 | O26: =N26+O25 -> 80185692 | P26: =O26/$C$27 -> 0.92398624
A27: =A26+31 -> 46691 | B27: 3452138.5 | C27: =C26+B27 -> 86782345 | D27: =C27/$C$27 -> 1 | N27: 1438294.1 | O27: =N27+O26 -> 81623987 | P27: =O27/$C$27 -> 0.94055982
A28: 46721 | N28: 2453576.3 | O28: =N28+O27 -> 84077563 | P28: =O28/$C$27 -> 0.96883258 | AE28: Spreadsheet Field | AF28: 45748 | AG28: 45778 | AH28: 45809 | AI28: 45839 | AJ28: 45870 | AK28: 45901 | AL28: 45931 | AM28: 45962 | AN28: 45992 | AO28: 46023 | AP28: 46054 | AQ28: 46082 | AR28: 46113 | AS28: 46143 | AT28: 46174 | AU28: 46204
A29: 46751 | N29: =1718691.7-559790.28 -> 1158901.4 | O29: =N29+O28 -> 85236464 | P29: =O29/$C$27 -> 0.98218669 | AE29: Cum BL1 Total Cost | AG29: 806595.32 | AH29: 1076993.7 | AI29: 1646314.3 | AJ29: 4103352.1 | AK29: 11057032 | AL29: 26957436 | AM29: 35047131 | AN29: 43482280 | AO29: 49721626 | AP29: 55541495 | AQ29: 58609253 | AR29: 59458608 | AS29: 62416852 | AT29: 70392954 | AU29: 70392954
A30: 46782 | N30: 437078.56 | O30: =N30+O29 -> 85673543 | P30: =O30/$C$27 -> 0.98722319 | AE30: Cum Actual Total Cost | AF30: 531360 | AG30: 1562095.1 | AH30: 4086192.6 | AI30: 6155575.8 | AJ30: 8202527.2 | AK30: 15434173 | AL30: 25435681 | AM30: 28628682 | AN30: 28628682 | AO30: 28628682 | AP30: 28628682 | AQ30: 28628682 | AR30: 28628682 | AS30: 28628682 | AT30: 28628682 | AU30: 28628682
A31: 46812 | N31: 156512.77 | O31: =N31+O30 -> 85830056 | P31: =O31/$C$27 -> 0.9890267 | AE31: BL1 Labor Units | AF31: 356 | AG31: 1721 | AH31: 872 | AI31: 1877 | AJ31: 3382 | AK31: 4485 | AL31: 4819 | AM31: 7855 | AN31: 6939 | AO31: 5176 | AP31: 6559 | AQ31: 5583 | AR31: 2552 | AS31: 2519 | AT31: 3446
A32: 46842 | N32: 568388.81 | O32: =N32+O31 -> 86398444 | P32: =O32/$C$27 -> 0.99557629 | AE32: Actual Labor Units | AF32: 1172.65 | AG32: 3628.34 | AH32: 1840.31 | AI32: 3196.17 | AJ32: 3048.04 | AK32: 3613.71 | AL32: 2936.9 | AM32: 961.48
A33: 46873 | N33: =383885.26+15 -> 383900.26 | O33: =N33+O32 -> 86782345 | P33: =O33/$C$27 -> 1 | AE33: BL1 Total Cost | AG33: 806595.32 | AH33: 270398.36 | AI33: 569320.64 | AJ33: 2457037.8 | AK33: 6953679.8 | AL33: 15900404 | AM33: 8089694.7 | AN33: 8435149 | AO33: 6239346.5 | AP33: 5819868.7 | AQ33: 3067757.8 | AR33: 849355.53 | AS33: 2958243.3 | AT33: 7976102.2
AE34: Actual Total Cost | AF34: 531360 | AG34: 1030735.1 | AH34: 2524097.5 | AI34: 2069383.2 | AJ34: 2046951.4 | AK34: 7231645.4 | AL34: 10001509 | AM34: 3193000.9
AE35: Cum BL1 Labor Units | AF35: 356 | AG35: 2077 | AH35: 2949 | AI35: 4826 | AJ35: 8208 | AK35: 12693 | AL35: 17512 | AM35: 25367 | AN35: 32306 | AO35: 37482 | AP35: 44041 | AQ35: 49624 | AR35: 52176 | AS35: 54695 | AT35: 58141 | AU35: 58141
AE36: Cum Actual Labor Units | AF36: 1172.65 | AG36: 4800.99 | AH36: 6641.3 | AI36: 9837.47 | AJ36: 12885.51 | AK36: 16499.22 | AL36: 19436.12 | AM36: 20397.6 | AN36: 20397.6 | AO36: 20397.6 | AP36: 20397.6 | AQ36: 20397.6 | AR36: 20397.6 | AS36: 20397.6 | AT36: 20397.6 | AU36: 20397.6
AE37: Remaining Labor Units | AM37: 6319.8 | AN37: 7300.2 | AO37: 7381.4 | AP37: 5360 | AQ37: 3410 | AR37: 1327 | AS37: 1731 | AT37: 4507 | AU37: 369
AE38: Remaining Total Cost | AM38: 20117547 | AN38: 7464473.5 | AO38: 8885195 | AP38: 3858005.2 | AQ38: 1683332.3 | AR38: 351955.75 | AS38: 1819272.1 | AT38: 8935913.6 | AU38: 425432
B39: UPDATE ONLY YELLOW PORTION FROM PRIMAVERA EXPORT, IF NEEDED, EXTEND YELLOW PORTION BASED ON SCHEDULE.
O44: =C27-O33 -> 0

Sheet Physical-Chart Data
B2: Baseline Plan | E2: Revised / Recovery Plan | H2: Earned Effort % | K2: Forecast | N2: Achieved/Fcst vs Plan
A3: Week | B3: Monthly Effort | C3: Cum Effort | D3: Plan Wt.% | E3: MonthlyEffort | F3: Cum Effort | G3: Plan Wt.% | H3: Monthly Wt. | I3: Cum Wt. | J3: Achieved Wt.% | K3: Monthly Wt. | L3: Cum Wt. | M3: Wt.% | N3: Monthly Wt. | O3: Cum Wt.
A4: 45991 | B4: 5359.95 | C4: =B4 -> 5359.95 | D4: =C4/$C$28 -> 0.0075010365 | E4: 5359.95 | F4: =E4 -> 5359.95 | G4: =F4/$C$28 -> 0.0075010365 | H4: =I4 -> 11192.02 | I4: 11192.02 | J4: =I4/$F$28 -> 0.015662786 | N4: =H4-E4 -> 5832.07 | O4: =N4 -> 5832.07 | Q4: Actuals thru previous month
A5: =A4+31 -> 46022 | B5: 29813.84 | C5: =B5+C4 -> 35173.79 | D5: =C5/$C$28 -> 0.049224318 | E5: 29813.84 | F5: =E5+F4 -> 35173.79 | G5: =F5/$C$28 -> 0.049224318 | H5: =I5-I4 -> 48070.98 | I5: 59263 | J5: =I5/$F$28 -> 0.082936207 | N5: =(K5+H5)-E5 -> 18257.14 | O5: =O4+N5 -> 24089.21
A6: =A5+28 -> 46050 | B6: 29643.7 | C6: =B6+C5 -> 64817.49 | D6: =C6/$C$28 -> 0.090709495 | E6: 29643.7 | F6: =E6+F5 -> 64817.49 | G6: =F6/$C$28 -> 0.090709495 | H6: =I6-I5 -> 51804.67 | I6: 111067.67 | J6: =I6/$F$28 -> 0.15543478 | N6: =(K6+H6)-E6 -> 22160.97 | O6: =O5+N6 -> 46250.18
A7: =A6+31 -> 46081 | B7: 24392.64 | C7: =B7+C6 -> 89210.13 | D7: =C7/$C$28 -> 0.12484602 | E7: 24392.64 | F7: =E7+F6 -> 89210.13 | G7: =F7/$C$28 -> 0.12484602 | H7: =I7-I6 -> 42988.56 | I7: 154056.23 | J7: =I7/$F$28 -> 0.21559556 | N7: =(K7+H7)-E7 -> 18595.92 | O7: =O6+N7 -> 64846.1
A8: =A7+31 -> 46112 | B8: 18781.31 | C8: =B8+C7 -> 107991.44 | D8: =C8/$C$28 -> 0.15112972 | E8: 18781.31 | F8: =E8+F7 -> 107991.44 | G8: =F8/$C$28 -> 0.15112972 | H8: =I8-I7 -> 41993.23 | I8: 196049.46 | J8: =I8/$F$28 -> 0.27436341 | N8: =(K8+H8)-E8 -> 23211.92 | O8: =O7+N8 -> 88058.02 | Q8: Forecast current and future months
A9: =A8+30 -> 46142 | B9: 29373.61 | C9: =B9+C8 -> 137365.05 | D9: =C9/$C$28 -> 0.19223691 | E9: 29373.61 | F9: =E9+F8 -> 137365.05 | G9: =F9/$C$28 -> 0.19223691 | H9: =I9-I8 -> 64055.99 | I9: 260105.45 | J9: =I9/$F$28 -> 0.36400721 | N9: =(K9+H9)-E9 -> 34682.38 | O9: =O8+N9 -> 122740.4
A10: =A9+31 -> 46173 | B10: 24568.1 | C10: =B10+C9 -> 161933.15 | D10: =C10/$C$28 -> 0.22661899 | E10: 24568.1 | F10: =E10+F9 -> 161933.15 | G10: =F10/$C$28 -> 0.22661899 | H10: =I10-I9 -> 43582.96 | I10: 303688.41 | J10: =I10/$F$28 -> 0.42499983 | N10: =(K10+H10)-E10 -> 19014.86 | O10: =O9+N10 -> 141755.26
A11: =A10+30 -> 46203 | B11: 33732.43 | C11: =B11+C10 -> 195665.58 | D11: =C11/$C$28 -> 0.27382618 | E11: 33732.43 | F11: =E11+F10 -> 195665.58 | G11: =F11/$C$28 -> 0.27382618 | H11: =I11-I10 -> 43961.59 | I11: 347650 | J11: =I11/$F$28 -> 0.48652232 | N11: =(K11+H11)-E11 -> 10229.16 | O11: =O10+N11 -> 151984.42
A12: =A11+31 -> 46234 | B12: 36781.76 | C12: =B12+C11 -> 232447.34 | D12: =C12/$C$28 -> 0.32530079 | E12: 36781.76 | F12: =E12+F11 -> 232447.34 | G12: =F12/$C$28 -> 0.32530079 | H12: =I12-I11 -> 77155.64 | I12: 424805.64 | J12: =I12/$F$28 -> 0.59449857 | N12: =(K12+H12)-E12 -> 40373.88 | O12: =O11+N12 -> 192358.3
A13: =A12+31 -> 46265 | B13: 47939.59 | C13: =B13+C12 -> 280386.93 | D13: =C13/$C$28 -> 0.39239034 | E13: 47939.59 | F13: =E13+F12 -> 280386.93 | G13: =F13/$C$28 -> 0.39239034 | H13: =I13-I12 -> 62683.37 | I13: 487489.01 | J13: =I13/$F$28 -> 0.68222145 | N13: =(K13+H13)-E13 -> 14743.78 | O13: =O12+N13 -> 207102.08 | X13: Spreadsheet Field | Y13: 45748 | Z13: 45778 | AA13: 45809 | AB13: 45839 | AC13: 45870 | AD13: 45901 | AE13: 45931 | AF13: 45962 | AG13: 45992 | AH13: 46023 | AI13: 46054 | AJ13: 46082 | AK13: 46113 | AL13: 46143 | AM13: 46174 | AN13: 46204
A14: =A13+30 -> 46295 | B14: 50083.47 | C14: =B14+C13 -> 330470.4 | D14: =C14/$C$28 -> 0.46248016 | E14: 50083.47 | F14: =E14+F13 -> 330470.4 | G14: =F14/$C$28 -> 0.46248016 | H14: =I14-I13 -> 22015.45 | I14: 509504.46 | J14: =I14/$F$28 -> 0.71303119 | N14: =(K14+H14)-E14 -> -28068.02 | O14: =O13+N14 -> 179034.06 | X14: Cum BL1 Total Cost | Z14: 806595.32 | AA14: 1076993.7 | AB14: 1646314.3 | AC14: 4103352.1 | AD14: 11057032 | AE14: 26957436 | AF14: 35047131 | AG14: 43482280 | AH14: 49721626 | AI14: 55541495 | AJ14: 58609253 | AK14: 59458608 | AL14: 62416852 | AM14: 70392954 | AN14: 70392954
A15: =A14+31 -> 46326 | B15: 31644.5 | C15: =B15+C14 -> 362114.9 | D15: =C15/$C$28 -> 0.50676538 | E15: 31644.5 | F15: =E15+F14 -> 362114.9 | G15: =F15/$C$28 -> 0.50676538 | H15: =I15-I14 -> 19318.29 | I15: 528822.75 | J15: =I15/$F$28 -> 0.74006637 | K15: 7295.11 | L15: =K15+I15 -> 536117.86 | M15: =L15/$C$28 -> 0.75027559 | N15: =(K15+H15)-E15 -> -5031.1 | O15: =O14+N15 -> 174002.96 | X15: Cum Actual Total Cost | Y15: 531360 | Z15: 1562095.1 | AA15: 4086192.6 | AB15: 6155575.8 | AC15: 8206784.5 | AD15: 15457052 | AE15: 25654616 | AF15: 27792679 | AG15: 27792679 | AH15: 27792679 | AI15: 27792679 | AJ15: 27792679 | AK15: 27792679 | AL15: 27792679 | AM15: 27792679 | AN15: 27792679
A16: =A15+30 -> 46356 | B16: 39701.82 | C16: =B16+C15 -> 401816.72 | D16: =C16/$C$28 -> 0.56232649 | E16: 39701.82 | F16: =E16+F15 -> 401816.72 | G16: =F16/$C$28 -> 0.56232649 | K16: 7399.83 | L16: =K16+L15 -> 543517.69 | M16: =L16/$C$28 -> 0.76063135 | X16: BL1 Labor Units | Y16: 356 | Z16: 1721 | AA16: 872 | AB16: 1877 | AC16: 3382 | AD16: 4485 | AE16: 4819 | AF16: 7855 | AG16: 6939 | AH16: 5176 | AI16: 6559 | AJ16: 5583 | AK16: 2552 | AL16: 2519 | AM16: 3446
A17: =A16+31 -> 46387 | B17: 46326.66 | C17: =B17+C16 -> 448143.38 | D17: =C17/$C$28 -> 0.62715881 | E17: 46326.66 | F17: =E17+F16 -> 448143.38 | G17: =F17/$C$28 -> 0.62715881 | K17: 7325.68 | L17: =K17+L16 -> 550843.37 | M17: =L17/$C$28 -> 0.77088335 | X17: Actual Labor Units | Y17: 1172.65 | Z17: 3628.34 | AA17: 1840.31 | AB17: 3196.17 | AC17: 3049.07 | AD17: 3618.81 | AE17: 3018.25 | AF17: 672.41
A18: =A17+31 -> 46418 | B18: 41440.12 | C18: =B18+C17 -> 489583.5 | D18: =C18/$C$28 -> 0.6851526 | E18: 41440.12 | F18: =E18+F17 -> 489583.5 | G18: =F18/$C$28 -> 0.6851526 | K18: 7608.29 | L18: =K18+L17 -> 558451.66 | M18: =L18/$C$28 -> 0.78153085 | X18: BL1 Total Cost | Z18: 806595.32 | AA18: 270398.36 | AB18: 569320.64 | AC18: 2457037.8 | AD18: 6953679.8 | AE18: 15900404 | AF18: 8089694.7 | AG18: 8435149 | AH18: 6239346.5 | AI18: 5819868.7 | AJ18: 3067757.8 | AK18: 849355.53 | AL18: 2958243.3 | AM18: 7976102.2
A19: =A18+28 -> 46446 | B19: 30567.53 | C19: =B19+C18 -> 520151.03 | D19: =C19/$C$28 -> 0.72793064 | E19: 30567.53 | F19: =E19+F18 -> 520151.03 | G19: =F19/$C$28 -> 0.72793064 | K19: =2311.93+5144.88 -> 7456.81 | L19: =K19+L18 -> 565908.47 | M19: =L19/$C$28 -> 0.79196636 | X19: Actual Total Cost | Y19: 531360 | Z19: 1030735.1 | AA19: 2524097.5 | AB19: 2069383.2 | AC19: 2051208.6 | AD19: 7250267.7 | AE19: 10197564 | AF19: 2138062.8
A20: =A19+31 -> 46477 | B20: 34520.87 | C20: =B20+C19 -> 554671.9 | D20: =C20/$C$28 -> 0.77624122 | E20: 34520.87 | F20: =E20+F19 -> 554671.9 | G20: =F20/$C$28 -> 0.77624122 | K20: 11660.64 | L20: =K20+L19 -> 577569.11 | M20: =L20/$C$28 -> 0.80828496 | X20: Cum BL1 Labor Units | Y20: 356 | Z20: 2077 | AA20: 2949 | AB20: 4826 | AC20: 8208 | AD20: 12693 | AE20: 17512 | AF20: 25367 | AG20: 32306 | AH20: 37482 | AI20: 44041 | AJ20: 49624 | AK20: 52176 | AL20: 54695 | AM20: 58141 | AN20: 58141
A21: =A20+30 -> 46507 | B21: 21773.44 | C21: =B21+C20 -> 576445.34 | D21: =C21/$C$28 -> 0.80671229 | E21: 21773.44 | F21: =E21+F20 -> 576445.34 | G21: =F21/$C$28 -> 0.80671229 | K21: 7775.23 | L21: =K21+L20 -> 585344.34 | M21: =L21/$C$28 -> 0.81916608 | X21: Cum Actual Labor Units | Y21: 1172.65 | Z21: 4800.99 | AA21: 6641.3 | AB21: 9837.47 | AC21: 12886.54 | AD21: 16505.35 | AE21: 19523.59 | AF21: 20196 | AG21: 20196 | AH21: 20196 | AI21: 20196 | AJ21: 20196 | AK21: 20196 | AL21: 20196 | AM21: 20196 | AN21: 20196
A22: =A21+31 -> 46538 | B22: 30753.45 | C22: =B22+C21 -> 607198.79 | D22: =C22/$C$28 -> 0.84975051 | E22: 30753.45 | F22: =E22+F21 -> 607198.79 | G22: =F22/$C$28 -> 0.84975051 | K22: 12741.9 | L22: =K22+L21 -> 598086.24 | M22: =L22/$C$28 -> 0.83699786 | R22: Extended Duration | X22: Remaining Labor Units | AF22: 7196.2 | AG22: 7175.2 | AH22: 7414.6 | AI22: 5123 | AJ22: 3302 | AK22: 1098 | AL22: 2019 | AM22: 4579
A23: =A22+30 -> 46568 | B23: 28626.94 | C23: =B23+C22 -> 635825.73 | D23: =C23/$C$28 -> 0.88981278 | E23: 28626.94 | F23: =E23+F22 -> 635825.73 | G23: =F23/$C$28 -> 0.88981278 | K23: =15895.2-146.71 -> 15748.49 | L23: =K23+L22 -> 613834.73 | M23: =L23/$C$28 -> 0.85903725 | X23: Remaining Total Cost | AF23: 21185774 | AG23: 8002967.6 | AH23: 8606824.2 | AI23: 3474097.5 | AJ23: 1572072.1 | AK23: 273706.67 | AL23: 2370642.2 | AM23: 8801345.6
A24: =A23+31 -> 46599 | B24: 17130.27 | C24: =B24+C23 -> 652956 | D24: =C24/$C$28 -> 0.91378591 | E24: 17130.27 | F24: =E24+F23 -> 652956 | G24: =F24/$C$28 -> 0.91378591 | K24: 11432.82 | L24: =K24+L23 -> 625267.55 | M24: =L24/$C$28 -> 0.87503702
A25: =A24+31 -> 46630 | B25: 17971.29 | C25: =B25+C24 -> 670927.29 | D25: =C25/$C$28 -> 0.93893601 | E25: 17971.29 | F25: =E25+F24 -> 670927.29 | G25: =F25/$C$28 -> 0.93893601 | K25: 10852.09 | L25: =K25+L24 -> 636119.64 | M25: =L25/$C$28 -> 0.89022409
A26: =A25+30 -> 46660 | B26: 21052.53 | C26: =B26+C25 -> 691979.82 | D26: =C26/$C$28 -> 0.96839819 | E26: 21052.53 | F26: =E26+F25 -> 691979.82 | G26: =F26/$C$28 -> 0.96839819 | K26: 7628.93 | L26: =K26+L25 -> 643748.57 | M26: =L26/$C$28 -> 0.90090048
A27: =A26+31 -> 46691 | B27: 16945.56 | C27: =B27+C26 -> 708925.38 | D27: =C27/$C$28 -> 0.99211282 | E27: 16945.56 | F27: =E27+F26 -> 708925.38 | G27: =F27/$C$28 -> 0.99211282 | K27: =15100.17-1014.72 -> 14085.45 | L27: =K27+L26 -> 657834.02 | M27: =L27/$C$28 -> 0.9206125
A28: 46721 | B28: 5635.87 | C28: =B28+C27 -> 714561.25 | D28: =C28/$C$28 -> 1 | E28: 5635.87 | F28: =E28+F27 -> 714561.25 | G28: =F28/$C$28 -> 1 | K28: 9976.84 | L28: =K28+L27 -> 667810.86 | M28: =L28/$C$28 -> 0.93457469
A29: 46751 | K29: 20381.37 | L29: =K29+L28 -> 688192.23 | M29: =L29/$C$28 -> 0.96309761
A30: 46782 | K30: 14328.06 | L30: =K30+L29 -> 702520.29 | M30: =L30/$C$28 -> 0.98314916
A31: 46812 | K31: 3785.45 | L31: =K31+L30 -> 706305.74 | M31: =L31/$C$28 -> 0.98844674
A32: 46842 | K32: 2961.8 | L32: =K32+L31 -> 709267.54 | M32: =L32/$C$28 -> 0.99259166
A33: 46873 | K33: 5293.71 | L33: =K33+L32 -> 714561.25 | M33: =L33/$C$28 -> 1
B39: UPDATE ONLY YELLOW PORTION FROM PRIMAVERA EXPORT, IF NEEDED, EXTEND YELLOW PORTION BASED ON SCHEDULE.
K43: =L33-C28 -> 0

Sheet LOOK AHEAD 
A1: مستهدف الربع
A2: # | B2: القطاع | C2: المبادرة | D2: Project ID | E2: اسم المشروع | F2: مدير المشروع | G2: المقاول | H2: بداية المشروع | I2: نهاية المشروع التعاقدية | J2: مدة المشروع (أشهر) | K2: نهاية المشروع المتوقعة/ الالتزام | L2: قيمة المشروع | M2: المخطط /الفعلي | N2: Mobilization المخطط | O2: Mobilization المنفذ | P2: Procurement (Long Lead Items) توريد المواد طويلة الأجل (المخطط) | Q2: Procurement (Long Lead Items) توريد المواد طويلة الأجل (المنفذ) | R2: Civil Work الأعمال المدنيه (المخطط) | S2: Civil Work الأعمال المدنيه (المنفذ) | T2: Mechnical Work أعمال الميكانيكا (المخطط) | U2: Mechnical Work أعمال الميكانيكا (المنفذ) | V2: Mechnical Work أعمال الكهرباء (المخطط) | W2: Mechnical Work أعمال الكهرباء (المنفذ) | X2: تأثير التأخير (إن وجد) على المبادرات في الربع | Y2: نسبة الانجاز المستهدفة بنهاية الربع | Z2: نسبة الانجاز المحققة بنهاية الربع | AA2: مجموع المبالغ المفوترة المستهدفة بنهاية الربع | AB2: مجموع المبالغ المفوترة المحققة بنهاية الربع | AC2: نهاية المشروع المتوقعة
A3: 1 | B3: الغربي | C3: - | D3: ='Weekly Progress Report'!B4 -> JDH1-02-003 | E3: ='Weekly Progress Report'!B3 -> INFRASTRUCTURE DEVELOPMENT FOR INDUSTRIAL CITY 1 IN JEDDAH | F3: م. رضا المنشاوي | G3: ='Weekly Progress Report'!$B$5 -> Al Enjaz Company for Trading and Contracting | H3: ='Weekly Progress Report'!H5 -> 45980 | I3: ='Weekly Progress Report'!H6 -> 46709 | J3: 24 | K3: 46356 | L3: ='Weekly Progress Report'!C28 -> 86782345 | M3: المخطط=53.18% الفعلى =78.72% | N3: 1 | O3: 1 | P3: 1. توريد مواسير شبكة السيول 100% 2. توريد مواسير شبكة الصرف الصحي 100% 3. توريد مواسير شبكة مياه الشرب 100% 4. توريد مواسير شبكة الري 100% 5. توريد مناهل السيول والصرف الصحي 100% 6. توريد مصايد الامطار 100% 7. توريد كابلات الجهد المنخفض 100% توريد أعمدة الانارة والكشافات 100 % 9. توريد مناهل الاتصالات 100% 10. توريد مواد شبكة الكاميرات والمراقبة 30% 11- توريد كابلات الجهد المتوسط 50% 12- توريد مواد الكوبري 100% 13. توريد حديد السور 100% | Q3: 1. جاري توريد مواسير شبكة السيول حيث تم توريد100 % 2- تم توريد مناهل السيول حيث تم وصول100% 3- تم توريد مواسير الصرف الصحي بنسبة 100% 4- تم توريد مواسير المياه حوالي 100% 5- تم توريد مواسير مياه شبكة الري بنسبة 100% 6- تم توريد مناهل الصرف الصحي بنسبة 100% 7- تم توريد مصايد السيول بنسبة 100% 8 - تم توريد محابس القفل والفراشة لشبكة المياه والري بنسبة 100% 9- توريد طفايات الحريق بنسبة100% 10 - تم توريد كابلات الجهد المنخفض 100% 11 - جاري توريد مناهل الاتصالات والكهرباء 12 - توريد حديد السور بنسبة 100% 13 - توريد اعمدة الانارة والكشافات بنسبة 100% | R3: 1. انهاء اعمال إزالة المباني والاسوار 2. الانتهاء من اعمال قطع الاراضى 100% 3. الانتهاء من اعمال ردم الأراضي 100% 4. اعمال قطع الطرق 100% 5. اعمال ردم الطرق 100% 6. اعمال الحفر للسور 100% 7. اعمال خرسانات الاساسات للسور 80% 8. اعمال حفر الكوبري 100% 9. أعمال الخوازيق للكوبري 100% اعمال الانتهاء من خرسانات الكوبري 100% تركيب حديد للسور بنسبة 70% | S3: 1. انهاء اعمال إزالة المباني والاسوار 100% 2. الانتهاء من اعمال قطع الاراضى 100% 3. الانتهاء من اعمال ردم الأراضي 99.8% 4. اعمال قطع الطرق 100% 5. اعمال ردم الطرق 100% 6. اعمال الحفر للسور100% 7. اعمال خرسانات الاساسات للسور 100% 8- اعمال Subgrade 100% 9- اعمال حفر وصب الخوازيق للكوبري بنسبة 100% 10- تم صب 100% من Abutment of Bridge - اعمال صب واعمال تسليجح لزوم جردرات الكوبري 100% - تركيب حديد السور بنسبة 83% - جاري اعمال الاسفلت الطبقة الاولى 100% - جاري اعمال البردورات 89% - اعمال الانترلوك بنسبة 79.82% - أعمال الاسفلت الطبقة السطحية بنسبة 43% | T3: 1- تنفيذ شبكة السيول بنسبة 70% 2- تنفيذ شبكة الصرف الصحي بنسبة70% اعمال تنفيذ شبكة المياه 60% اعمال تنفيذ شبكة الري بنسبة 70% | U3: 1- تم حفر وتركيب واختبار مواسير شبكة السيول56244 م.ط بنسبة 100% 2- انتهاء تركيب اعمال مواسير شبكة الصرف الصحي بطول 6244 م.ط 3. انتهاء اعمال حفر واعمال لحام مواسير شبكة مياه الشرب بطول 12075 م.ط 4- جاري اعمال حفر واعمال لحام مواسير شبكة الري بطول 8633 م.ط 5- تم الانتهاء من تركيب طفايات الحريق 100% 6- تم تركيب عدد 156 محبس لشبكة المياه والري 7- جاري اعمال والتشطيب لغرف شبكة المياه والري | V3: 1- اعمال دكتات الكهرباء والاتصالات بنسبة 75% 2- اعمال مناهل الاتصالات بنسبة 40% اعمال شبكة الجهد المتوسط بنسبة 25% اعمال قواعد أعمدة الانارة 100% | W3: 1- اعمال الدكتات بنسبة 100% 2- جاري اعمال حفر مناهل الاتصالات80% 3- تم اعمال صب قواعد أعمدة الانارة بنسبة100% 4- جاري تركيب أعمدة الانارة بعدد 370 عمود 5 - اعمال حفر وتمديد كابلات الجهد المنخفض بطول 13900 م 6- تركيب عدد 7 أعمدة لنظام CCTV | X3: ضرورة انهاء اتفاقية شبكة الجهد المتوسط من قبل مدن مع شركة الكهرباء وذلك لتأخر بدء التوريد والعمل بالموقع | Y3: 0.75 | Z3: =Progress!I26 -> 0.78721045 | AA3: =Y3*86782345 -> 65086759 | AB3: 44851849 | AC3: 46356

Sheet Schedule
A1: Primavera P6 Schedule Status | P1: ='General Information'!$K$1 -> Data Date | Q1: ='General Information'!$L$1 -> 46315
A2: Project Activities Overview
A3: Schedule Statistics | F3: Active Schedule Activities
A4: Total Act. | B4: Not Started | C4: In Progress | D4: Completed | E4: % | F4: Active | G4: Ahead | H4: On | I4: Behind | J4: Flag
A5: 1905 | B5: 423 | C5: 204 | D5: 1278 | E5: =D5/A5 -> 0.67086614 | F5: =C5 -> 204 | G5: =F5-I5-H5 -> 91 | H5: 0 | I5: =I9 -> 113 | J5: =+G5+H5-I5 -> -22
A6: Critical Path Activities | D6: Free Float Management (Total) | H6: Failed Start Activities
D7: Greater Than 14 Days | F7: Less Than 14 Days
A8: Last Week | B8: This Week | C8: Diff | D8: Last Week | E8: This Week | F8: Last Week | G8: This Week | H8: Last Week | I8: This Week | J8: Flag
A9: 460 | B9: 457 | C9: =A9-B9 -> 3 | D9: 71 | E9: 68 | F9: 1834 | G9: =A5-E9 -> 1837 | H9: 107 | I9: 113 | J9: =H9-I9 -> -6

Sheet Manpower
A1: Head-Count ( Non Manual)
A2: MONTHS | B2: 45991 | C2: 46022 | D2: 46050 | E2: 46081 | F2: 46112 | G2: 46142 | H2: 46173 | I2: 46203 | J2: 46234 | K2: 46265 | L2: 46295 | M2: 46326 | N2: 46356 | O2: 46387 | P2: 46418 | Q2: 46446 | R2: 46477 | S2: 46507 | T2: 46538 | U2: 46568 | V2: 46599 | W2: 46630 | X2: 46660 | Y2: 46691 | Z2: 46721 | AM2: non direct
A3: Plan - Monthly | B3: 20 | C3: 20 | D3: 21 | E3: 21 | F3: 22 | G3: 22 | H3: 22 | I3: 22 | J3: 22 | K3: 22 | L3: 22 | M3: 22 | N3: 21 | O3: 21 | P3: 21 | Q3: 20 | R3: 20 | S3: 20 | T3: 20 | U3: 20 | V3: 20 | W3: 20 | X3: 20 | Y3: 20 | Z3: 14
A4: Planned - Cumulative | B4: =B3 -> 20 | C4: =B4+C3 -> 40 | D4: =C4+D3 -> 61 | E4: =D4+E3 -> 82 | F4: =E4+F3 -> 104 | G4: =F4+G3 -> 126 | H4: =G4+H3 -> 148 | I4: =H4+I3 -> 170 | J4: =I4+J3 -> 192 | ... Z4: =Y4+Z3 -> 515
A5: Actual - Monthly | B5: 30 | C5: 40 | D5: 54 | E5: 54 | F5: 52 | G5: 52 | H5: 52 | I5: 52 | J5: 52 | K5: 52 | L5: 47 | M5: 48 | AM5: daily report
A6: Actual Cumulative | B6: =B5 -> 30 | C6: =B6+C5 -> 70 | D6: =C6+D5 -> 124 | E6: =D6+E5 -> 178 | F6: =E6+F5 -> 230 | G6: =F6+G5 -> 282 | H6: =G6+H5 -> 334 | I6: =H6+I5 -> 386 | J6: =I6+J5 -> 438 | ... M6: =L6+M5 -> 585
A7: Forecast - Monthly | N7: 40 | O7: 35 | P7: 21 | Q7: 20 | R7: 20 | S7: 20 | T7: 20 | U7: 20 | V7: 20 | W7: 20 | X7: 20 | Y7: 20 | Z7: 14
A8: Saudi Monthly - Actual
A9: Head-Count (Manual) | AM9: direct
A10: MONTHS | B10: 45991 | C10: 46022 | D10: 46050 | E10: 46081 | F10: 46112 | G10: 46142 | H10: 46173 | I10: 46203 | J10: 46234 | K10: 46265 | L10: 46295 | M10: 46326 | N10: 46356 | O10: 46387 | P10: 46418 | Q10: 46446 | R10: 46477 | S10: 46507 | T10: 46538 | U10: 46568 | V10: 46599 | W10: 46630 | X10: 46660 | Y10: 46691 | Z10: 46721
A11: Plan - Monthly | B11: 22.681923 | C11: 102.05447 | D11: 87.996587 | E11: 117.27236 | F11: 90.29476 | G11: 139.49615 | H11: 114.85697 | I11: 159.56149 | J11: 177.34923 | K11: 228.71635 | L11: 239.47976 | M11: 148.25019 | N11: 186.51038 | O11: 216.85923 | P11: 196.86745 | Q11: 144.49875 | R11: 168.55101 | S11: 109.75317 | T11: 146.73245 | U11: 136.75452 | V11: 82.861827 | W11: 52.513269 | X11: 64.71851 | Y11: 17.514615 | Z11: 17.427885
A12: Planned - Cumulative | B12: =B11 -> 22.681923 | C12: =B12+C11 -> 124.73639 | D12: =C12+D11 -> 212.73298 | E12: =D12+E11 -> 330.00534 | F12: =E12+F11 -> 420.3001 | G12: =F12+G11 -> 559.79625 | H12: =G12+H11 -> 674.65322 | I12: =H12+I11 -> 834.21471 | J12: =I12+J11 -> 1011.5639 | ... Z12: =Y12+Z11 -> 3169.5733
A13: Actual - Monthly | B13: 35 | C13: 93 | D13: 148 | E13: 140 | F13: 134 | G13: 155 | H13: 192 | I13: 196 | J13: 194 | K13: 196 | L13: 135 | M13: 130 | AM13: daily report | AQ13: =W2-V2 -> 31
A14: Actual Cumulative | B14: =B13 -> 35 | C14: =B14+C13 -> 128 | D14: =C14+D13 -> 276 | E14: =D14+E13 -> 416 | F14: =E14+F13 -> 550 | G14: =F14+G13 -> 705 | H14: =G14+H13 -> 897 | I14: =H14+I13 -> 1093 | J14: =I14+J13 -> 1287 | ... M14: =L14+M13 -> 1748
A15: Forecast - Monthly | N15: 186.51038 | O15: 216.85923 | P15: 196.86745 | Q15: 144.49875 | R15: 168.55101 | S15: 109.75317 | T15: 146.73245 | U15: 136.75452 | V15: 82.861827 | W15: 52.513269 | X15: 64.71851 | Y15: 17.514615 | Z15: 17.427885
A16: Saudi - Actual
A18: Head-Count (Non-Manual) | AG18: Month | AI18: =EOMONTH('General Information'!$L$1,0) -> 46326 | AM18: =EOMONTH(AI18,1) -> 46356
A19: Planned | B19: Actual | D19: Variance | F19: Forecast Next Month | H19: Saudi Staff
A20: 22 | B20: 48 | D20: =B20-A20 -> 26 | F20: 40 | H20: 6
A22: Head-Count (Manual) | L22: Man Power by Trade
A23: Planned | B23: Actual | D23: Variance | F23: Forecast Next Month | H23: Saudi Staff | L23: Key Trade | N23: Labor | P23: Skilled Labor | R23: Driver / Operator | T23: Carpenter | V23: Steel Fixer | X23: Mason | Z23: Plumber | AB23: Electrician | AD23: Others | AF23: Total
A24: 148 | B24: 130 | D24: =B24-A24 -> -18 | F24: 187 | H24: 0 | L24: Plan | N24: 40 | P24: 26 | R24: 60 | T24: 5 | V24: 5 | X24: 2 | Z24: 8 | AB24: 2 | AD24: 0 | AF24: =SUM(N24:AE24) -> 148
L25: Actual | N25: 17 | P25: 30 | R25: 48 | T25: 6 | V25: 9 | X25: 0 | Z25: 7 | AB25: 13 | AD25: 0 | AF25: =SUM(N25:AE25) -> 130
A32: Equipment
A33: MONTHS | B33: 45991 | C33: 46022 | D33: 46050 | E33: 46081 | F33: 46112 | G33: 46142 | H33: 46173 | I33: 46203 | J33: 46234 | K33: 46265 | L33: 46295 | M33: 46326 | N33: 46356 | O33: 46387 | P33: 46418 | Q33: 46446 | R33: 46477 | S33: 46507 | T33: 46538 | U33: 46568 | V33: 46599 | W33: 46630 | X33: 46660 | Y33: 46691 | Z33: 46721
A34: Plan - Monthly | B34: 0 | C34: 3.6263942 | D34: 11.868077 | E34: 18.949519 | F34: 14.19399 | G34: 29.798365 | H34: 29.590721 | I34: 53.21375 | J34: 55.926827 | K34: 77.144904 | L34: 89.068173 | M34: 59.690048 | N34: 55.820673 | O34: 58.884038 | P34: 55.691827 | Q34: 43.872596 | R34: 46.043606 | S34: 19.948413 | T34: 25.574663 | U34: 19.375817 | V34: 12.954375 | W34: 17.604904 | X34: 22.761106 | Y34: 4.8529808
A35: Planned - Cumulative | B35: =B34 -> 0 | C35: =B35+C34 -> 3.6263942 | D35: =C35+D34 -> 15.494471 | E35: =D35+E34 -> 34.44399 | F35: =E35+F34 -> 48.637981 | G35: =F35+G34 -> 78.436346 | H35: =G35+H34 -> 108.02707 | I35: =H35+I34 -> 161.24082 | J35: =I35+J34 -> 217.16764 | ... Y35: =X35+Y34 -> 826.45577
A36: Actual - Monthly | B36: 20 | C36: 52 | D36: 83 | E36: 75 | F36: 69 | G36: 69 | H36: 94 | I36: 98 | J36: 96 | K36: 98 | L36: 54 | M36: 48
A37: Actual Cumulative | B37: =B36 -> 20 | C37: =B37+C36 -> 72 | D37: =C37+D36 -> 155 | E37: =D37+E36 -> 230 | F37: =E37+F36 -> 299 | G37: =F37+G36 -> 368 | H37: =G37+H36 -> 462 | I37: =H37+I36 -> 560 | J37: 564 | K37: 564 | L37: 564 | M37: 564
A38: Forecast - Monthly | N38: 55.820673 | O38: 58.884038 | P38: 55.691827 | Q38: 43.872596 | R38: 46.043606 | S38: 19.948413 | T38: 25.574663 | U38: 19.375817 | V38: 12.954375 | W38: 17.604904 | X38: 22.761106 | Y38: 4.8529808
A41: Equipment Count
A42: Planned | B42: Actual | D42: Idle | F42: Variance | H42: Forecast Next Month
A43: 60 | B43: 48 | D43: =O52 -> 0 | F43: =B43-A43 -> -12 | H43: 56
A49: Type | B49: Excavator | C49: Loader | D49: Bulldozer | E49: Water Tanker | F49: Grader | G49: Truck | H49: Road Roller | I49: Asphalt Paver | J49: Crane | K49: Bobcat | L49: Aggregate paver | M49: Compactor | N49: Other | O49: Total
A50: Plan | B50: 3 | C50: 3 | D50: 2 | E50: 3 | F50: 4 | G50: 12 | H50: 3 | I50: 0 | J50: 2 | K50: 0 | L50: 0 | M50: 0 | N50: 28 | O50: =SUM(B50:N50) -> 60
A51: Actual | B51: 4 | C51: 3 | D51: 1 | E51: 6 | F51: 1 | G51: 9 | H51: 3 | I51: 2 | J51: 1 | K51: 5 | L51: 0 | M51: 3 | N51: 10 | O51: =SUM(B51:N51) -> 48
A52: Idle | B52: 0 | C52: 0 | D52: 0 | E52: 0 | F52: 0 | G52: 0 | H52: 0 | I52: 0 | J52: 0 | K52: 0 | L52: 0 | M52: 0 | N52: 0 | O52: =SUM(B52:N52) -> 0

Sheet Conclusion
A1: مشروع تطوير البنية التحتية بالمدينة الصناعية الاولى بجدة JDH1-02-003
A2: معلومات المشروع | F2: نطاق المشروع | L2: موقع المشروع
A3: المقاول | B3: شركة الانجاز للتجارة والمقاولات | C3: الاستشاري | D3: شركة ايجيس السعودية للاستشارات | F3: البند | G3: الكمية الكلية | H3: الكمية المنفذة | I3: الكمية المتبقية | J3: نسبة المنفذ
A4: تاريخ استلام الموقع | B4: 45980 | C4: مدة التنفيذ | D4: 24 شهرًا ميلاديًا | F4: اعمال الازالة | G4: 1 | H4: 1 | I4: =G4-H4 -> 0 | J4: =H4 -> 1
A5: بداية العقد | B5: من تاريخ استلام الموقع | C5: قيمة العقد (شامل ضريبة القيمة المضافة) | D5: {='Weekly Progress Report'!$O$5:$P$5} -> 86782345 | E5: #REF! | F5: الطرق و المواقف | G5: 1 | H5: 0.8228 | I5: =G5-H5 -> 0.1772 | J5: =H5 -> 0.8228
A6: نسبة الإنجاز المخطط له | B6: ='Weekly Progress Report'!$V$3 -> 0.53183049 | C6: نسبة الإنجاز الفعلي | D6: ='Weekly Progress Report'!$V$4 -> 0.78721045 | F6: الاعمال الكهربائية | G6: 1 | H6: 0.5604 | I6: =G6-H6 -> 0.4396 | J6: =H6 -> 0.5604
F7: اعمال شبكة مياه الشرب | G7: 1 | H7: 0.9472 | I7: =G7-H7 -> 0.0528 | J7: =H7 -> 0.9472
F8: اعمال شبكة مياه الري | G8: 1 | H8: 0.9545 | I8: =G8-H8 -> 0.0455 | J8: =H8 -> 0.9545
A9: ملخص جدول الكميات | F9: اعمال شبكة السيول | G9: 1 | H9: 0.9778 | I9: =G9-H9 -> 0.0222 | J9: =H9 -> 0.9778
A10: مكونات المشروع | C10: التكلفة (غير شامل ضريبة القيمة المضافة) | D10: النسبة الاجمالية | F10: اعمال شبكة الصرف الصحي | G10: 1 | H10: 0.9704 | I10: =G10-H10 -> 0.0296 | J10: =H10 -> 0.9704 | Q10: 20865877 | R10: =Q10*(1-0.0212) -> 20423520
A11: الطرق و المواقف | C11: 21303539 | D11: =C11/$D$5 -> 0.24548241 | F11: اعمال الاسوار والبوابات | G11: 1 | H11: 0.6585 | I11: =G11-H11 -> 0.3415 | J11: =H11 -> 0.6585 | L11: تقدم أعمال layout | Q11: 10508920 | R11: =Q11*(1-0.0212) -> 10286131
A12: الاعمال الكهربائية | C12: 15060436 | D12: =C12/$D$5 -> 0.17354263 | F12: اعمال الكوبري | G12: 1 | H12: 0.7283 | I12: =G12-H12 -> 0.2717 | J12: =H12 -> 0.7283 | Q12: 23728460 | R12: =Q12*(1-0.0212) -> 23225417
A13: اعمال شبكة مياه الشرب | C13: 8476992.4 | D13: =C13/$D$5 -> 0.097681071 | F13: اعمال الاند سكيب | G13: 1 | H13: 0 | I13: =G13-H13 -> 1 | J13: =H13 -> 0 | Q13: 7970089 | R13: =Q13*(1-0.0212) -> 7801123.1
A14: اعمال شبكة مياه الري | C14: 7038125.4 | D14: =C14/$D$5 -> 0.08110089 | F14: ملخص التوريدات | Q14: 8842925 | R14: =Q14*(1-0.0212) -> 8655455
A15: اعمال شبكة السيول | C15: 14055612 | D15: =C15/$D$5 -> 0.16196396 | F15: البند | G15: الكمية الكلية | H15: الكمية المورده | I15: الكمية المتبقية | J15: نسبة التوريد
A16: اعمال شبكة الصرف الصحي | C16: 6688000.6 | D16: =C16/$D$5 -> 0.077066374 | F16: Steel Reinforcement | G16: 126 | H16: 126 | I16: =G16-H16 -> 0 | J16: =IFERROR(H16/G16,0) -> 1
A17: اعمال الاسوار والبوابات | C17: 7099976.2 | D17: =C17/$D$5 -> 0.081813602 | F17: Precast Concrete Kerb | G17: 59990 | H17: 59990 | I17: =G17-H17 -> 0 | J17: =IFERROR(H17/G17,0) -> 1
A18: اعمال الكوبري | C18: 3909548.3 | D18: =C18/$D$5 -> 0.045050042 | F18: Interlocking Block Pavers | G18: 57905 | H18: =G18*1 -> 57905 | I18: =G18-H18 -> 0 | J18: =IFERROR(H18/G18,0) -> 1 | U18: 5041
A19: اعمال الاند سكيب | C19: 3150114.8 | D19: =C19/$D$5 -> 0.036299028 | F19: Metal Fence | G19: 2295 | H19: 2295 | I19: =G19-H19 -> 0 | J19: =IFERROR(H19/G19,0) -> 1 | U19: 12075.28
A20: الإجمالي للمشروع | C20: =SUM(C11:C19) -> 86782345 | D20: =C20/$D$5 -> 1 | F20: GRP Pipes for Sewer network | G20: 6244 | H20: 6244 | I20: =G20-H20 -> 0 | J20: =IFERROR(H20/G20,0) -> 1 | U20: 8502
A21: معالم البرنامج الزمني | F21: Fiberglass Manholes for Sewer network | G21: 122 | H21: 122 | I21: =G21-H21 -> 0 | J21: =IFERROR(H21/G21,0) -> 1 | U21: 5775.1
A22: البند | C22: التاريخ حسب الجدول الزمني | D22: ملاحظة | F22: GRP Pipes for Storm network | G22: 5650 | H22: 5650 | I22: =G22-H22 -> 0 | J22: =IFERROR(H22/G22,0) -> 1
A23: نهاية الشروع | C23: 46709 | F23: Inlet Manholes for Storm network | G23: 130 | H23: 130 | I23: =G23-H23 -> 0 | J23: =IFERROR(H23/G23,0) -> 1
A24: بداية المشروع | C24: 45980 | D24: تم البدء | F24: Concrete chambers | G24: 189 | H24: 189 | I24: =G24-H24 -> 0 | J24: =IFERROR(H24/G24,0) -> 1
A25: تجهيزات الموقع. | C25: 46009 | D25: تم الانتهاء | F25: HDPE Pipe (PN 16) for Ptable Water | G25: 12075 | H25: 12075 | I25: =G25-H25 -> 0 | J25: =IFERROR(H25/G25,0) -> 1
A26: تقديم خطة العمل والبرنامج الزمني | C26: 46009 | D26: تم الانتهاء | F26: HDPE Pipe (PN 16) for TSE | G26: 8722 | H26: 8722 | I26: =G26-H26 -> 0 | J26: =IFERROR(H26/G26,0) -> 1
A27: تقديم واعتماد المخططات والمواد | C27: 46041 | D27: جاري التنفيذ | F27: التحديات والعوائق
A28: الانتهاء من اصدار جميع أوامر الشراء | C28: 46041 | D28: جاري التنفيذ | F28: في انتظار تحديث اتفاقية الكهرباء بين مدن والشركة السعودية للكهرباء بخصوص شبكة الجهد المتوسط
A29: الانتهاء من نطاق أعمال الطرق والجهد المتوسط | C29: 46282 | D29: جاري التنفيذ
A30: الانتهاء من نطاق أعمال الشبكات العميقة | C30: 46344 | D30: جاري التنفيذ
A31: الانتهاء من نطاق جميع أعمال الشبكات | C31: 46464 | D31: جاري التنفيذ
A32: الانتهاء من كامل الأعمال | C32: 46709 | D32: لم يبدأ

Sheet Testing
A1: Testing and Commissioning
A2: Item | B2: Planned Start Date | C2: Planned Finish Date | D2: Forecast Start Date | E2: Forecast Finish Date | F2: Actual Start Date | G2: Actual Finish Date | H2: % Completed | I2: Open Comments | J2: Closed Comments
A3: Test for Irrigation and Landscape | B3: =K25 -> 46679 | C3: =L25 -> 46686 | D3: =M25 -> 46807 | E3: =N25 -> 46814
A4: Test for Earthing System | B4: =K26 -> 46680 | C4: =L26 -> 46686 | D4: =M26 -> 46736 | E4: =N26 -> 46743 | F4: 46235 | H4: 0.3
A5: Test for CCTV feeding system and GSM | B5: =K27 -> 46673 | C5: =L27 -> 46679 | D5: =M27 -> 46729 | E5: =N27 -> 46736 | F5: 46235 | H5: 0.35
A6: Test for Telecommunications Work | B6: =K28 -> 46666 | C6: =L28 -> 46672 | D6: =M28 -> 46722 | E6: =N28 -> 46729 | F6: 46235 | H6: 0.3
A7: Test for Road Lighting | B7: =K29 -> 46659 | C7: =L29 -> 46665 | D7: =M29 -> 46715 | E7: =N29 -> 46722 | F7: 46235 | H7: 0.3
A8: Test for Electrical Network | B8: =K30 -> 46641 | C8: =L30 -> 46649 | D8: =M30 -> 46701 | E8: =N30 -> 46711 | F8: 46235 | H8: 0.3
A9: Test for Road Works | B9: =K31 -> 46603 | C9: =L31 -> 46611 | D9: =M31 -> 46676 | E9: =N31 -> 46684 | F9: 46235 | H9: 0.7
A10: Test for Fence & Gate | B10: =K32 -> 46679 | C10: =L32 -> 46685 | D10: =M32 -> 15-Jun-26 A | E10: =N32 -> 46695 | F10: 46188 | H10: 0.6
A11: Test for Bridge Work | B11: =K33 -> 46631 | C11: =L33 -> 46639 | D11: =M33 -> 15-Jun-26 A | E11: =N33 -> 46701 | F11: 46188 | H11: 0.7
A12: Test for Stormwater Utilities | B12: =K34 -> 46622 | C12: =L34 -> 46630 | D12: =M34 -> 15-Jun-26 A | E12: =N34 -> 46695 | F12: 46188 | H12: 0.7
A13: Test for Sanitary Sewerage | B13: =K35 -> 46613 | C13: =L35 -> 46621 | D13: =M35 -> 15-Jun-26 A | E13: =N35 -> 46690 | F13: 46188 | H13: 0.75
A14: Test for TSE Network | B14: =K36 -> 46650 | C14: =L36 -> 46658 | D14: =M36 -> 15-Jun-26 A | E14: =N36 -> 46715 | F14: 46188 | H14: 0.75
A15: Test for Public Water Utility Distribution | B15: =K37 -> 46613 | C15: =L37 -> 46621 | D15: =M37 -> 15-Jun-26 A | E15: =N37 -> 46690 | F15: 46188 | H15: 0.75
A24: Activity ID | B24: Activity Name | C24: Original Duration | D24: Activity Status | E24: Activity % Complete | F24: Physical % Complete | G24: Duration % Complete | H24: Schedule % Complete | I24: Units % Complete | J24: Performance % Complete | K24: BL Project Start | L24: BL Project Finish | M24: Start | N24: Finish | O24: Budgeted Total Cost | P24: Planned Value Cost | Q24: Earned Value Cost | R24: Actual Total Cost | S24: Budgeted Labor Units | T24: Planned Value Labor Units | U24: Earned Value Labor Units | V24: Actual Labor Units | W24: Total Float | X24: Auto Compute Actuals
A25: CON-LEG101-TC-1090 | B25: Test for Irrigation and Landscape | C25: 7 | D25: Not Started | E25: 0 | F25: 0 | G25: 0 | H25: 0 | I25: 0 | J25: 0 | K25: 46679 | L25: 46686 | M25: 46807 | N25: 46814 | O25: 305575 | P25: 0 | Q25: 0 | R25: 0 | S25: 1570 | T25: 0 | U25: 0 | V25: 0 | W25: -110 | X25: No
A26: CON-LEG101-TC-1120 | B26: Test for Earthing System | C26: 6 | D26: Not Started | E26: 0 | F26: 0 | G26: 0 | H26: 0 | I26: 0 | J26: 0 | K26: 46680 | L26: 46686 | M26: 46736 | N26: 46743 | O26: 16600 | P26: 0 | Q26: 0 | R26: 0 | S26: 1570 | T26: 0 | U26: 0 | V26: 0 | W26: -49 | X26: No
A27: CON-LEG101-TC-1070 | B27: Test for CCTV feeding system and GSM | C27: 6 | D27: Not Started | E27: 0 | F27: 0 | G27: 0 | H27: 0 | I27: 0 | J27: 0 | K27: 46673 | L27: 46679 | M27: 46729 | N27: 46736 | O27: 249750 | P27: 0 | Q27: 0 | R27: 0 | S27: 1570 | T27: 0 | U27: 0 | V27: 0 | W27: -49 | X27: No
A28: CON-LEG101-TC-1000 | B28: Test for Telecommunications Work | C28: 6 | D28: Not Started | E28: 0 | F28: 0 | G28: 0 | H28: 0 | I28: 0 | J28: 0 | K28: 46666 | L28: 46672 | M28: 46722 | N28: 46729 | O28: 341181 | P28: 0 | Q28: 0 | R28: 0 | S28: 1210 | T28: 0 | U28: 0 | V28: 0 | W28: -49 | X28: No
A29: CON-LEG101-TC-1100 | B29: Test for Road Lighting | C29: 6 | D29: Not Started | E29: 0 | F29: 0 | G29: 0 | H29: 0 | I29: 0 | J29: 0 | K29: 46659 | L29: 46665 | M29: 46715 | N29: 46722 | O29: 477615 | P29: 0 | Q29: 0 | R29: 0 | S29: 1570 | T29: 0 | U29: 0 | V29: 0 | W29: -49 | X29: No
A30: CON-LEG101-TC-1010 | B30: Test for Electrical Network | C30: 8 | D30: Not Started | E30: 0 | F30: 0 | G30: 0 | H30: 0 | I30: 0 | J30: 0 | K30: 46641 | L30: 46649 | M30: 46701 | N30: 46711 | O30: 418189 | P30: 0 | Q30: 0 | R30: 0 | S30: 1570 | T30: 0 | U30: 0 | V30: 0 | W30: -49 | X30: No
A31: CON-LEG101-TC-1110 | B31: Test for Road Works | C31: 8 | D31: Not Started | E31: 0 | F31: 0 | G31: 0 | H31: 0 | I31: 0 | J31: 0 | K31: 46603 | L31: 46611 | M31: 46676 | N31: 46684 | O31: 2658716.5 | P31: 0 | Q31: 0 | R31: 0 | S31: 1570 | T31: 0 | U31: 0 | V31: 0 | W31: -50 | X31: No
A32: CON-LEG101-TC-1080 | B32: Test for Fence & Gate | C32: 6 | D32: In Progress | E32: 0.4 | F32: 0.4 | G32: 0.4 | H32: 0 | I32: 0.4 | J32: 0.4 | K32: 46679 | L32: 46685 | M32: 15-Jun-26 A | N32: 46695 | O32: 1179417 | P32: 0 | Q32: 471766.8 | R32: 471766.8 | S32: 1570 | T32: 0 | U32: 628 | V32: 628 | W32: -9 | X32: No
A33: CON-LEG101-TC-1060 | B33: Test for Bridge Work | C33: 8 | D33: In Progress | E33: 0.4 | F33: 0.4 | G33: 0.4 | H33: 0 | I33: 0.4 | J33: 0.4 | K33: 46631 | L33: 46639 | M33: 15-Jun-26 A | N33: 46701 | O33: 345044.7 | P33: 0 | Q33: 138017.88 | R33: 138017.88 | S33: 1570 | T33: 0 | U33: 628 | V33: 628 | W33: -49 | X33: No
A34: CON-LEG101-TC-1050 | B34: Test for Stormwater Utilities | C34: 8 | D34: In Progress | E34: 0.4 | F34: 0.4 | G34: 0.4 | H34: 0 | I34: 0.4 | J34: 0.4 | K34: 46622 | L34: 46630 | M34: 15-Jun-26 A | N34: 46695 | O34: 1041566 | P34: 0 | Q34: 416626.4 | R34: 416626.4 | S34: 1570 | T34: 0 | U34: 628 | V34: 628 | W34: -49 | X34: No
A35: CON-LEG101-TC-1040 | B35: Test for Sanitary Sewerage | C35: 8 | D35: In Progress | E35: 0.4 | F35: 0.4 | G35: 0.4 | H35: 0 | I35: 0.4 | J35: 0.4 | K35: 46613 | L35: 46621 | M35: 15-Jun-26 A | N35: 46690 | O35: 568550 | P35: 0 | Q35: 227420 | R35: 227420 | S35: 1570 | T35: 0 | U35: 628 | V35: 628 | W35: -49 | X35: No
A36: CON-LEG101-TC-1030 | B36: Test for TSE Network | C36: 7 | D36: In Progress | E36: 0.4 | F36: 0.4 | G36: 0.4 | H36: 0 | I36: 0.4 | J36: 0.4 | K36: 46650 | L36: 46658 | M36: 15-Jun-26 A | N36: 46715 | O36: 581275 | P36: 0 | Q36: 232510 | R36: 232510 | S36: 1570 | T36: 0 | U36: 628 | V36: 628 | W36: -49 | X36: No
A37: CON-LEG101-TC-1020 | B37: Test for Public Water Utility Distribution | C37: 8 | D37: In Progress | E37: 0.4 | F37: 0.4 | G37: 0.4 | H37: 0 | I37: 0.4 | J37: 0.4 | K37: 46613 | L37: 46621 | M37: 15-Jun-26 A | N37: 46690 | O37: 494212 | P37: 0 | Q37: 197684.8 | R37: 197684.8 | S37: 1570 | T37: 0 | U37: 628 | V37: 628 | W37: -49 | X37: No

Sheet Codes
C3: Status List
C4: Approved | E4: Y
C5: Pending | E5: N | K5: (Manhours)
C6: Potential | K6: (Mandays)
C10: Phase | D10: Stage | F10: Stage | H10: Status | J10: Score
J11: Low | K11: Contractor | L11: Active
C12: Launch | D12: LOA | F12: LOA | H12: Active | J12: Medium | K12: CM | L12: Expired
C13: Launch | D13: Kick-off Meeting | F13: Kick-off Meeting | H13: On Hold | J13: High | K13: PgM | L13: Occurred
C14: Launch | D14: Site Handover | H14: Terminated | K14: Modon | L14: Pending
C15: Launch | D15: Mobilization | F15: Mobilization | G15: Initial staff and equipment in place, ready to start production | H15: Terminated, Closed | K15: Other
C16: Execution | D16: Construction | F16: Execution | G16: Tender Documents Issued | H16: Substantial Complete | I16: Initial Handover done at site
C17: Execution | D17: T&C | G17: Responses to the OCS completed | H17: Complete | I17: Initial Handover Signed
C18: Execution | D18: Initial Handover | F18: Closeout | G18: Design close-out process complete | H18: Closed | I18: Final Handover done at Site
D19: Warranty Period
D20: Final Handover
B41: Project Status Score
B42: Elements | E42: Max | F42: Score | G42: Planned | H42: Actual | I42: Remarks
B43: SPI (Physical Effort) | E43: 1 | F43: =IFERROR('Weekly Progress Report'!$Z$28,1) -> 1.545394 | G43: No Entry Required
B44: SPI (Cost) | E44: 1 | F44: =IFERROR('Weekly Progress Report'!$N$28,1) -> 1.4801905 | G44: No Entry Required
B45: On Schedule -Active | E45: 1 | F45: =IFERROR(('Weekly Progress Report'!G99+'Weekly Progress Report'!H99)/'Weekly Progress Report'!F99,1) -> 0.44607843 | G45: No Entry Required | K45: =12/20 -> 0.6
B46: Manpower Availability | E46: 1 | F46: =IFERROR('Weekly Progress Report'!N102/'Weekly Progress Report'!M102,1) -> 0.87837838 | G46: No Entry Required
B47: Major Equipment Availability | E47: 1 | F47: =IFERROR('Weekly Progress Report'!U102/'Weekly Progress Report'!T102,1) -> 0.47619048 | G47: No Entry Required
B48: Billing % Compared to Planned | E48: 1 | F48: =IFERROR('Weekly Progress Report'!R84/'Weekly Progress Report'!R82,1) -> 1.0714376 | G48: No Entry Required
