Workbook
Name _1B.05.M.010.0010: #REF!
Name _1B.05.M.010.0010: #REF!
Name _1B.05.M.010.0010: #REF!
Name _1B.05.M.010.0050: #REF!
Name _1B.05.M.010.0050: #REF!
Name _1B.05.M.010.0050: #REF!
Name _1B.05.M.0100.0010: #REF!
Name _1B.05.M.0100.0010: #REF!
Name _1B.05.M.020.0010: #REF!
Name _1B.05.M.020.0010: #REF!
Name _1B.05.M.020.0020: #REF!
Name _1B.05.M.020.0020: #REF!
Name _1B.05.M.020.0030: #REF!
Name _1B.05.M.020.0030: #REF!
Name _1B.05.M.020.0040: #REF!
Name _1B.05.M.020.0040: #REF!
Name _1B.05.M.030.0010: #REF!
Name _1B.05.M.030.0010: #REF!
Name _1B.05.M.030.0020: #REF!
Name _1B.05.M.030.0020: #REF!
Name _1B.05.M.040.0010: #REF!
Name _1B.05.M.040.0010: #REF!
Name _1B.05.M.050.0010: #REF!
Name _1B.05.M.050.0010: #REF!
Name _1B.05.M.050.0020: #REF!
Name _1B.05.M.050.0020: #REF!
Name _1B.05.M.050.0030: #REF!
Name _1B.05.M.050.0030: #REF!
Name _1B.05.M.060.0020: #REF!
Name _1B.05.M.060.0020: #REF!
Name _1B.05.M.060.0100: #REF!
Name _1B.05.M.060.0100: #REF!
Name _1B.05.M.070.0010: #REF!
Name _1B.05.M.070.0010: #REF!
Name _1B.05.M.070.0020: #REF!
Name _1B.05.M.070.0020: #REF!
Name _1B.05.M.070.0030: #REF!
Name _1B.05.M.070.0030: #REF!
Name _1B.05.M.070.0040: #REF!
Name _1B.05.M.070.0040: #REF!
Name _1B.05.M.070.0050: #REF!
Name _1B.05.M.070.0050: #REF!
Name _1B.05.M.080.0010: #REF!
Name _1B.05.M.080.0010: #REF!
Name _1B.05.M.090.0010: #REF!
Name _1B.05.M.090.0010: #REF!
Name _1B.09.P.010.0010: #REF!
Name _1B.09.P.010.0010: #REF!
Name _1B.09.P.010.0020: #REF!
Name _1B.09.P.010.0020: #REF!
Name _1B.09.P.010.0030: #REF!
Name _1B.09.P.010.0030: #REF!
Name _1B.09.P.010.0040: #REF!
Name _1B.09.P.010.0040: #REF!
Name _1B.09.P.010.0050: #REF!
Name _1B.09.P.010.0050: #REF!
Name _1B.09.P.010.0060: #REF!
Name _1B.09.P.010.0060: #REF!
Name _1B.09.P.010.0070: #REF!
Name _1B.09.P.010.0070: #REF!

Sheet DB
A1: ='Weekly Progress Report'!$A$1 -> MODON - Weekly Progress Report - Construction Projects
B2: ='Weekly Progress Report'!$A$2 -> Contract General Information | J2: ='Weekly Progress Report'!G2 -> Key Dates | U2: ='Weekly Progress Report'!$M$2 -> Cost Summary (SR) | AD2: ='Weekly Progress Report'!$U$2 -> Performance Summary | AP2: ='Weekly Progress Report'!A56 -> Shop Drawings | AT2: ='Weekly Progress Report'!A65 -> Material Approval | AW2: ='Weekly Progress Report'!A74 -> Procurement Summary | BD2: ='Weekly Progress Report'!L56 -> Quality Reports | BT2: ='Weekly Progress Report'!L64 -> Key Submittals Approval Status | CD2: ='Weekly Progress Report'!L70 -> Invoices Summary | CR2: ='Weekly Progress Report'!L78 -> Resources at Site | CY2: ='Weekly Progress Report'!W56 -> Safety Statistics | FK2: ='Weekly Progress Report'!A83 -> Primavera P6 Schedule Status | FS2: ='Weekly Progress Report'!A92 -> Weekly Prgoress Photos
A3: ='Weekly Progress Report'!AF1 -> Data Date | B3: ='Weekly Progress Report'!A3 -> Project Name | C3: ='Weekly Progress Report'!A4 -> Project ID | D3: ='Weekly Progress Report'!A5 -> Contractor | E3: ='Weekly Progress Report'!A6 -> Consultant | F3: ='Weekly Progress Report'!D4 -> Stage | G3: ='Weekly Progress Report'!D5 -> Status | H3: ='Weekly Progress Report'!D6 -> Modon PM | I3: ='Weekly Progress Report'!AA2 -> Project Scope | J3: ='Weekly Progress Report'!G3 -> Contract Award | K3: ='Weekly Progress Report'!G4 -> Contract Sign | L3: ='Weekly Progress Report'!G5 -> Site Handover | M3: ='Weekly Progress Report'!G6 -> Original Completion | N3: ='Weekly Progress Report'!$I$3 -> Contract Award (Hijri) | O3: ='Weekly Progress Report'!$I$4 -> Contract Sign (Hijri) | P3: ='Weekly Progress Report'!$I$5 -> Site Handover (Hijri) | Q3: ='Weekly Progress Report'!$I$6 -> Original Completion (Hijri) | R3: ='Weekly Progress Report'!$K$3 -> Revised Completion | S3: ='Weekly Progress Report'!$K$4 -> Committed Completion | T3: ='Weekly Progress Report'!$K$5 -> Forecast Completion | U3: ='Weekly Progress Report'!$M$3 -> Original Contract Value | V3: ='Weekly Progress Report'!$M$4 -> Revised Contract Value | W3: ='Weekly Progress Report'!$M$5 -> Estimate At Completion Value | X3: ='Weekly Progress Report'!$M$6 -> Potential Changes | Y3: ='Weekly Progress Report'!$Q$3 -> O&M Value (if any) | Z3: ='Weekly Progress Report'!$Q$4 -> Submitted Invoices (Gross Value) | AA3: ='Weekly Progress Report'!$Q$5 -> Penalities | AB3: ='Weekly Progress Report'!$Q$6 -> FIR Value (Todate) | AC3: Original Plan Value | AD3: ='Weekly Progress Report'!$U$3 -> Plan Value | AE3: ='Weekly Progress Report'!$U$4 -> Earn Value | AF3: ='Weekly Progress Report'!$W$3 -> Phys. Plan Value | AG3: ='Weekly Progress Report'!$W$4 -> Phys. Earn Value | AH3: ='Weekly Progress Report'!$Y$3 -> Quality Score | AI3: ='Weekly Progress Report'!$Y$5 -> Safety Score | AJ3: Weekly PV (SAR) | AK3: Weekly EV (SAR) | AL3: Weekly PV % | AM3: Weekly PV % | AN3: Weekly Phys PV% | AO3: Weekly Phys PV% | AP3: Total SD Planned | AQ3: SD Remaining | AR3: SD Pending | AS3: Total SD Submittals | AT3: Planned Materials Approv | AU3: Material Pending Approval | AV3: Materila Total Submittals | AW3: ='Weekly Progress Report'!C75 -> Total Materials | AX3: ='Weekly Progress Report'!D75 -> Total Number of P.O. | AY3: ='Weekly Progress Report'!E75 -> Actual P.O. To Date | AZ3: ='Weekly Progress Report'!F75 -> Remaining P.O | BA3: ='Weekly Progress Report'!G75 -> Material on Site | BB3: ='Weekly Progress Report'!H75 -> Remaining Materials | BC3: ='Weekly Progress Report'!I75 -> Material Delivery Completion (Date) | BD3: ="NCR "&'Weekly Progress Report'!N57 -> NCR Issued | BE3: ="NCR "&'Weekly Progress Report'!O57 -> NCR Closed | BF3: ="NCR "&'Weekly Progress Report'!P57 -> NCR Pending | BG3: ="NCR "&'Weekly Progress Report'!Q57 -> NCR Avg. Closing (Days) | BH3: ="SIR "&'Weekly Progress Report'!N57 -> SIR Issued | BI3: ="SIR "&'Weekly Progress Report'!O57 -> SIR Closed | BJ3: ="SIR "&'Weekly Progress Report'!P57 -> SIR Pending | BK3: ="SIR "&'Weekly Progress Report'!Q57 -> SIR Avg. Closing (Days) | BL3: ="MIR "&'Weekly Progress Report'!N57 -> MIR Issued | BM3: ="MIR "&'Weekly Progress Report'!O57 -> MIR Closed | BN3: ="MIR "&'Weekly Progress Report'!P57 -> MIR Pending | BO3: ="MIR "&'Weekly Progress Report'!Q57 -> MIR Avg. Closing (Days) | BP3: ="FIR "&'Weekly Progress Report'!N57 -> FIR Issued | BQ3: ="FIR "&'Weekly Progress Report'!O57 -> FIR Closed | BR3: ="FIR "&'Weekly Progress Report'!P57 -> FIR Pending | BS3: ="FIR "&'Weekly Progress Report'!Q57 -> FIR Avg. Closing (Days) | BT3: ='Weekly Progress Report'!L65 -> 1 Quality Plan Approval | BU3: ='Weekly Progress Report'!L66 -> 2 Quality Plan Last Up | BV3: ='Weekly Progress Report'!L67 -> 3 Safety Plan Approval | BW3: ='Weekly Progress Report'!L68 -> 4 Safety Plan Last Up | BX3: ='Weekly Progress Report'!L69 -> 5 Construction Plan Approval | BY3: ='Weekly Progress Report'!Q65 -> 6 Baseline Approval | BZ3: ='Weekly Progress Report'!Q66 -> 7 No of Approved Version of Schedule | CA3: ='Weekly Progress Report'!Q67 -> 8 Last Approved Schedule | CB3: ='Weekly Progress Report'!Q68 -> 9 BOQ Approval Date | CC3: ='Weekly Progress Report'!Q69 -> 10 No of Approved Version of BOQ | CD3: ='Weekly Progress Report'!L71 -> Total Submitted Invoices | CE3: ='Weekly Progress Report'!L72 -> PM Approved Invoices | CF3: ='Weekly Progress Report'!L73 -> No of Paid Invoices | CG3: ='Weekly Progress Report'!L74 -> No of Pending Invoices | CH3: ='Weekly Progress Report'!L75 -> Advance Payment % | CI3: ='Weekly Progress Report'!L76 -> Retention % | CJ3: ='Weekly Progress Report'!L77 -> Deduction / Penalties % | CK3: ='Weekly Progress Report'!O71 -> Submitted Invoices (SAR) | CL3: ='Weekly Progress Report'!O72 -> PM Approved Invoices (SAR) | CM3: ='Weekly Progress Report'!O73 -> Paid Invoices (SAR) | CN3: ='Weekly Progress Report'!O74 -> Last Submitted Period | CO3: ='Weekly Progress Report'!O75 -> Advance Payment (SAR) | CP3: ='Weekly Progress Report'!O76 -> Retention (SAR) | CQ3: ='Weekly Progress Report'!O77 -> Deduction / Penalties (SAR) | CR3: Planned Head Count | CS3: Actual Head Count | CT3: Saudi Staff | CU3: Labor Planned | CV3: Labor Actual | CW3: Equipment Planned | CX3: Equipment Actual | CY3: ="This Week "&'Weekly Progress Report'!X59 -> This Week Total Hours Worked | CZ3: ="This Week "&'Weekly Progress Report'!X60 -> This Week Safe Hours Worked | DA3: ="This Week "&'Weekly Progress Report'!X61 -> This Week LTI | DB3: ="This Week "&'Weekly Progress Report'!X62 -> This Week MTC (Healed w/o Disability) | DC3: ="This Week "&'Weekly Progress Report'!X63 -> This Week MTC (Healed w/ Disability) | DD3: ="This Week "&'Weekly Progress Report'!X64 -> This Week Near Miss | DE3: ="This Week "&'Weekly Progress Report'!X65 -> This Week First Aid Cases | DF3: ="This Week "&'Weekly Progress Report'!X66 -> This Week Fatality | DG3: ="This Week "&'Weekly Progress Report'!X67 -> This Week Fire Incident Cases | DH3: ="This Week "&'Weekly Progress Report'!X68 -> This Week Vehicle Incident | DI3: ="This Week "&'Weekly Progress Report'!X69 -> This Week Property Damages | DJ3: ="This Week "&'Weekly Progress Report'!X70 -> This Week Induction Training | DK3: ="This Week "&'Weekly Progress Report'!X71 -> This Week No.of Internal Training | DL3: ="This Week "&'Weekly Progress Report'!X72 -> This Week No.of Internal Audit | DM3: ="This Week "&'Weekly Progress Report'!X73 -> This Week No. of Toolbox Talks | DN3: ="This Week "&'Weekly Progress Report'!X74 -> This Week Safety Awards/Incentives | DO3: ="This Month "&'Weekly Progress Report'!X59 -> This Month Total Hours Worked | DP3: ="This Month "&'Weekly Progress Report'!X60 -> This Month Safe Hours Worked | DQ3: ="This Month "&'Weekly Progress Report'!X61 -> This Month LTI | DR3: ="This Month "&'Weekly Progress Report'!X62 -> This Month MTC (Healed w/o Disability) | DS3: ="This Month "&'Weekly Progress Report'!X63 -> This Month MTC (Healed w/ Disability) | DT3: ="This Month "&'Weekly Progress Report'!X64 -> This Month Near Miss | DU3: ="This Month "&'Weekly Progress Report'!X65 -> This Month First Aid Cases | DV3: ="This Month "&'Weekly Progress Report'!X66 -> This Month Fatality | DW3: ="This Month "&'Weekly Progress Report'!X67 -> This Month Fire Incident Cases | DX3: ="This Month "&'Weekly Progress Report'!X68 -> This Month Vehicle Incident | DY3: ="This Month "&'Weekly Progress Report'!X69 -> This Month Property Damages | DZ3: ="This Month "&'Weekly Progress Report'!X70 -> This Month Induction Training | EA3: ="This Month "&'Weekly Progress Report'!X71 -> This Month No.of Internal Training | EB3: ="This Month "&'Weekly Progress Report'!X72 -> This Month No.of Internal Audit | EC3: ="This Month "&'Weekly Progress Report'!X73 -> This Month No. of Toolbox Talks | ED3: ="This Month "&'Weekly Progress Report'!X74 -> This Month Safety Awards/Incentives | EE3: ="YTD "&'Weekly Progress Report'!X59 -> YTD Total Hours Worked | EF3: ="YTD "&'Weekly Progress Report'!X60 -> YTD Safe Hours Worked | EG3: ="YTD "&'Weekly Progress Report'!X61 -> YTD LTI | EH3: ="YTD "&'Weekly Progress Report'!X62 -> YTD MTC (Healed w/o Disability) | EI3: ="YTD "&'Weekly Progress Report'!X63 -> YTD MTC (Healed w/ Disability) | EJ3: ="YTD "&'Weekly Progress Report'!X64 -> YTD Near Miss | EK3: ="YTD "&'Weekly Progress Report'!X65 -> YTD First Aid Cases | EL3: ="YTD "&'Weekly Progress Report'!X66 -> YTD Fatality | EM3: ="YTD "&'Weekly Progress Report'!X67 -> YTD Fire Incident Cases | EN3: ="YTD "&'Weekly Progress Report'!X68 -> YTD Vehicle Incident | EO3: ="YTD "&'Weekly Progress Report'!X69 -> YTD Property Damages | EP3: ="YTD "&'Weekly Progress Report'!X70 -> YTD Induction Training | EQ3: ="YTD "&'Weekly Progress Report'!X71 -> YTD No.of Internal Training | ER3: ="YTD "&'Weekly Progress Report'!X72 -> YTD No.of Internal Audit | ES3: ="YTD "&'Weekly Progress Report'!X73 -> YTD No. of Toolbox Talks | ET3: ="YTD "&'Weekly Progress Report'!X74 -> YTD Safety Awards/Incentives | EU3: ="Cum "&'Weekly Progress Report'!X59 -> Cum Total Hours Worked | EV3: ="Cum "&'Weekly Progress Report'!X60 -> Cum Safe Hours Worked | EW3: ="Cum "&'Weekly Progress Report'!X61 -> Cum LTI | EX3: ="Cum "&'Weekly Progress Report'!X62 -> Cum MTC (Healed w/o Disability) | EY3: ="Cum "&'Weekly Progress Report'!X63 -> Cum MTC (Healed w/ Disability) | EZ3: ="Cum "&'Weekly Progress Report'!X64 -> Cum Near Miss | FA3: ="Cum "&'Weekly Progress Report'!X65 -> Cum First Aid Cases | FB3: ="Cum "&'Weekly Progress Report'!X66 -> Cum Fatality | FC3: ="Cum "&'Weekly Progress Report'!X67 -> Cum Fire Incident Cases | FD3: ="Cum "&'Weekly Progress Report'!X68 -> Cum Vehicle Incident | FE3: ="Cum "&'Weekly Progress Report'!X69 -> Cum Property Damages | FF3: ="Cum "&'Weekly Progress Report'!X70 -> Cum Induction Training | FG3: ="Cum "&'Weekly Progress Report'!X71 -> Cum No.of Internal Training | FH3: ="Cum "&'Weekly Progress Report'!X72 -> Cum No.of Internal Audit | FI3: ="Cum "&'Weekly Progress Report'!X73 -> Cum No. of Toolbox Talks | FJ3: ="Cum "&'Weekly Progress Report'!X74 -> Cum Safety Awards/Incentives | FK3: ='Weekly Progress Report'!A86 -> Total Act. | FL3: ='Weekly Progress Report'!B86 -> Not Started | FM3: ='Weekly Progress Report'!C86 -> In Progress | FN3: ='Weekly Progress Report'!D86 -> Completed | FO3: Critical Path Act.Last Week | FP3: Critical Path Act.This Week | FQ3: Failed start Last Week | FR3: Failed start This Week | FS3: ='Weekly Progress Report'!B94 -> 0 | FT3: ='Weekly Progress Report'!D94 -> 0 | FU3: ='Weekly Progress Report'!F94 -> 0 | FV3: ='Weekly Progress Report'!H94 -> 0 | FW3: ='Weekly Progress Report'!J94 -> 0 | FX3: ='Weekly Progress Report'!L94 -> 0 | FY3: ='Weekly Progress Report'!N94 -> 0 | FZ3: ='Weekly Progress Report'!O94 -> 0 | GA3: ='Weekly Progress Report'!P94 -> 0
A4: ='Weekly Progress Report'!AG1 -> 46308 | B4: ='Weekly Progress Report'!B3 -> Construction of Industrial Units for Artisans in Najran | C4: ='Weekly Progress Report'!B4 -> NJR1-05-005 | D4: ='Weekly Progress Report'!B5 -> Labenat Al Bena | E4: ='Weekly Progress Report'!B6 -> EGIS | F4: ='Weekly Progress Report'!E4 -> Construction | G4: ='Weekly Progress Report'!E5 -> Active | H4: ='Weekly Progress Report'!E6 -> Eng. Ahmed Kotbi | I4: ='Weekly Progress Report'!AA3 -> The project scope covers the construction of the Low Process RBF Unit, Outside Mosque, Pump Shed, and GRP Water Tank, including site preparation works (demolition, excavation, and backfilling), concrete and masonry works, thermal and waterproofing systems, installation of doors and windows, finishing works, and specialties. It also includes pre-engineered structures, mechanical systems (sanitary, water supply, HVAC, and firefighting), and electrical systems such as substations, distribution networks, lighting, power, telecom, fire alarm, and solar power. | J4: ='Weekly Progress Report'!H3 -> 46047 | K4: ='Weekly Progress Report'!H4 -> 46065 | L4: ='Weekly Progress Report'!H5 -> 46084 | M4: ='Weekly Progress Report'!H6 -> 46389 | N4: ='Weekly Progress Report'!$J$3 -> 46047 | O4: ='Weekly Progress Report'!$J$4 -> 46065 | P4: ='Weekly Progress Report'!$J$5 -> 46084 | Q4: ='Weekly Progress Report'!$J$6 -> 46389 | R4: ='Weekly Progress Report'!$L$3 -> 46389 | S4: ='Weekly Progress Report'!$L$4 -> 46310 | T4: ='Weekly Progress Report'!$L$5 -> 46310 | U4: ='Weekly Progress Report'!$O$3 -> 9554134 | V4: ='Weekly Progress Report'!$O$4 -> 9554134 | W4: ='Weekly Progress Report'!$O$5 -> 9554134 | X4: ='Weekly Progress Report'!$O$6 -> 0 | Y4: ='Weekly Progress Report'!$S$3 -> 0 | Z4: ='Weekly Progress Report'!$S$4 -> 7935744 | AA4: ='Weekly Progress Report'!$S$5 -> -20000 | AB4: ='Weekly Progress Report'!$S$6 -> 9266829.7 | AC4: ='Weekly Progress Report'!$J$27 -> 0.9999999 | AD4: ='Weekly Progress Report'!$V$3 -> 0.75185056 | AE4: ='Weekly Progress Report'!$V$4 -> 0.96947719 | AF4: ='Weekly Progress Report'!$X$3 -> 0.78657431 | AG4: ='Weekly Progress Report'!$X$4 -> 0.96524679 | AH4: ='Weekly Progress Report'!$Z$3 -> 0.88775862 | AI4: ='Weekly Progress Report'!$Z$5 -> 0.83 | AJ4: ='Weekly Progress Report'!$E$27 -> 381787 | AK4: ='Weekly Progress Report'!$F$27 -> 218625 | AL4: =AJ4/V4 -> 0.039960398 | AM4: =AK4/V4 -> 0.022882765 | AN4: ='Weekly Progress Report'!S27 -> 0.031469017 | AO4: ='Weekly Progress Report'!T27 -> 0.0079315264 | AP4: ='Weekly Progress Report'!C64 -> 93 | AQ4: ='Weekly Progress Report'!I64 -> 0 | AR4: ='Weekly Progress Report'!J64 -> 0 | AS4: ='Weekly Progress Report'!K64 -> 93 | AT4: ='Weekly Progress Report'!C73 -> 95 | AU4: ='Weekly Progress Report'!J73 -> 0 | AV4: ='Weekly Progress Report'!K73 -> 95 | AW4: ='Weekly Progress Report'!C82 -> 95 | AX4: ='Weekly Progress Report'!D82 -> 95 | AY4: ='Weekly Progress Report'!E82 -> 95 | AZ4: ='Weekly Progress Report'!F82 -> 0 | BA4: ='Weekly Progress Report'!G82 -> 95 | BB4: ='Weekly Progress Report'!H82 -> 0 | BC4: ='Weekly Progress Report'!I82 -> 46274 | BD4: ='Weekly Progress Report'!N60 -> 17 | BE4: ='Weekly Progress Report'!O60 -> 17 | BF4: ='Weekly Progress Report'!P60 -> 0 | BG4: ='Weekly Progress Report'!Q60 -> 3 | BH4: ='Weekly Progress Report'!N61 -> 18 | BI4: ='Weekly Progress Report'!O61 -> 18 | BJ4: ='Weekly Progress Report'!P61 -> 0 | BK4: ='Weekly Progress Report'!Q61 -> 3 | BL4: ='Weekly Progress Report'!N62 -> 64 | BM4: ='Weekly Progress Report'!O62 -> 64 | BN4: ='Weekly Progress Report'!P62 -> 0 | BO4: ='Weekly Progress Report'!Q62 -> 3 | BP4: ='Weekly Progress Report'!N63 -> 407 | BQ4: ='Weekly Progress Report'!O63 -> 407 | BR4: ='Weekly Progress Report'!P63 -> 0 | BS4: ='Weekly Progress Report'!Q63 -> 3 | BT4: ='Weekly Progress Report'!O65 -> 46134 | BU4: ='Weekly Progress Report'!O66 -> 46134 | BV4: ='Weekly Progress Report'!O67 -> 46130 | BW4: ='Weekly Progress Report'!O68 -> 46130 | BX4: ='Weekly Progress Report'!O69 -> 46114 | BY4: ='Weekly Progress Report'!U65 -> 46113 | BZ4: ='Weekly Progress Report'!U66 -> 0 | CA4: ='Weekly Progress Report'!U67 -> 46113 | CB4: ='Weekly Progress Report'!U68 -> N/A | CC4: ='Weekly Progress Report'!U69 -> 0 | CD4: ='Weekly Progress Report'!N71 -> 6 | CE4: ='Weekly Progress Report'!N72 -> 6 | CF4: ='Weekly Progress Report'!N73 -> 4 | CG4: ='Weekly Progress Report'!N74 -> 2 | CH4: ='Weekly Progress Report'!N75 -> 0 | CI4: ='Weekly Progress Report'!N76 -> 0 | CJ4: ='Weekly Progress Report'!N77 -> 0.0020933347 | CK4: ='Weekly Progress Report'!R71 -> 7935744 | CL4: ='Weekly Progress Report'!R72 -> 7935744 | CM4: ='Weekly Progress Report'!R73 -> 4460610 | CN4: ='Weekly Progress Report'!R74 -> 46295 | CO4: ='Weekly Progress Report'!R75 -> 0 | CP4: ='Weekly Progress Report'!R76 -> 0 | CQ4: ='Weekly Progress Report'!R77 -> -20000 | CR4: ='Weekly Progress Report'!L81 -> 13 | CS4: ='Weekly Progress Report'!M81 -> 14 | CT4: ='Weekly Progress Report'!O81 -> 0 | CU4: ='Weekly Progress Report'!P81 -> 119 | CV4: ='Weekly Progress Report'!Q81 -> 21 | CW4: ='Weekly Progress Report'!T91 -> 34 | CX4: ='Weekly Progress Report'!U91 -> 8 | CY4: ='Weekly Progress Report'!Z59 -> 1920 | CZ4: ='Weekly Progress Report'!Z60 -> 2040 | DA4: ='Weekly Progress Report'!Z61 -> 0 | DB4: ='Weekly Progress Report'!Z62 -> 0 | DC4: ='Weekly Progress Report'!Z63 -> 0 | DD4: ='Weekly Progress Report'!Z64 -> 0 | DE4: ='Weekly Progress Report'!Z65 -> 0 | DF4: ='Weekly Progress Report'!Z66 -> 0 | DG4: ='Weekly Progress Report'!Z67 -> 0 | DH4: ='Weekly Progress Report'!Z68 -> 0 | DI4: ='Weekly Progress Report'!Z69 -> 0 | DJ4: ='Weekly Progress Report'!Z70 -> 1 | DK4: ='Weekly Progress Report'!Z71 -> 0 | DL4: ='Weekly Progress Report'!Z72 -> 0 | DM4: ='Weekly Progress Report'!Z73 -> 1 | DN4: ='Weekly Progress Report'!Z74 -> 1 | DO4: ='Weekly Progress Report'!AB59 -> 3960 | DP4: ='Weekly Progress Report'!AB60 -> 3960 | DQ4: ='Weekly Progress Report'!AB61 -> 0 | DR4: ='Weekly Progress Report'!AB62 -> 0 | DS4: ='Weekly Progress Report'!AB63 -> 0 | DT4: ='Weekly Progress Report'!AB64 -> 0 | DU4: ='Weekly Progress Report'!AB65 -> 0 | DV4: ='Weekly Progress Report'!AB66 -> 0 | DW4: ='Weekly Progress Report'!AB67 -> 0 | DX4: ='Weekly Progress Report'!AB68 -> 0 | DY4: ='Weekly Progress Report'!AB69 -> 0 | DZ4: ='Weekly Progress Report'!AB70 -> 1 | EA4: ='Weekly Progress Report'!AB71 -> 0 | EB4: ='Weekly Progress Report'!AB72 -> 0 | EC4: ='Weekly Progress Report'!AB73 -> 2 | ED4: ='Weekly Progress Report'!AB74 -> 1 | EE4: ='Weekly Progress Report'!AC59 -> 82166 | EF4: ='Weekly Progress Report'!AC60 -> 82166 | EG4: ='Weekly Progress Report'!AC61 -> 0 | EH4: ='Weekly Progress Report'!AC62 -> 0 | EI4: ='Weekly Progress Report'!AC63 -> 0 | EJ4: ='Weekly Progress Report'!AC64 -> 2 | EK4: ='Weekly Progress Report'!AC65 -> 1 | EL4: ='Weekly Progress Report'!AC66 -> 0 | EM4: ='Weekly Progress Report'!AC67 -> 1 | EN4: ='Weekly Progress Report'!AC68 -> 0 | EO4: ='Weekly Progress Report'!AC69 -> 0 | EP4: ='Weekly Progress Report'!AC70 -> 49 | EQ4: ='Weekly Progress Report'!AC71 -> 4 | ER4: ='Weekly Progress Report'!AC72 -> 1 | ES4: ='Weekly Progress Report'!AC73 -> 27 | ET4: ='Weekly Progress Report'!AC74 -> 3 | EU4: ='Weekly Progress Report'!AD59 -> 82166 | EV4: ='Weekly Progress Report'!AD60 -> 82166 | EW4: ='Weekly Progress Report'!AD61 -> 0 | EX4: ='Weekly Progress Report'!AD62 -> 0 | EY4: ='Weekly Progress Report'!AD63 -> 0 | EZ4: ='Weekly Progress Report'!AD64 -> 2 | FA4: ='Weekly Progress Report'!AD65 -> 1 | FB4: ='Weekly Progress Report'!AD66 -> 0 | FC4: ='Weekly Progress Report'!AD67 -> 1 | FD4: ='Weekly Progress Report'!AD68 -> 0 | FE4: ='Weekly Progress Report'!AD69 -> 0 | FF4: ='Weekly Progress Report'!AD70 -> 49 | FG4: ='Weekly Progress Report'!AD71 -> 4 | FH4: ='Weekly Progress Report'!AD72 -> 1 | FI4: ='Weekly Progress Report'!AD73 -> 27 | FJ4: ='Weekly Progress Report'!AD74 -> 3 | FK4: ='Weekly Progress Report'!A87 -> 1462 | FL4: ='Weekly Progress Report'!B87 -> 22 | FM4: ='Weekly Progress Report'!C87 -> 30 | FN4: ='Weekly Progress Report'!D87 -> 1410 | FO4: ='Weekly Progress Report'!A91 -> 0 | FP4: ='Weekly Progress Report'!B91 -> 0 | FQ4: ='Weekly Progress Report'!H91 -> 13 | FR4: ='Weekly Progress Report'!I91 -> 9 | FS4: ='Weekly Progress Report'!B99 -> 0 | FT4: ='Weekly Progress Report'!D99 -> 0 | FU4: ='Weekly Progress Report'!F99 -> 0 | FV4: ='Weekly Progress Report'!H99 -> 0 | FW4: ='Weekly Progress Report'!J99 -> 0 | FX4: ='Weekly Progress Report'!L99 -> 0 | FY4: ='Weekly Progress Report'!N99 -> 0 | FZ4: ='Weekly Progress Report'!O99 -> 0 | GA4: ='Weekly Progress Report'!P99 -> 0

Sheet Weekly Progress Report
A1: MODON - Weekly Progress Report - Construction Projects | AF1: Data Date | AG1: ='General Information'!L1 -> 46308
A2: Contract General Information | G2: Key Dates | M2: Cost Summary (SR) | U2: Performance Summary | AA2: Project Scope
A3: Project Name | B3: ='General Information'!C3 -> Construction of Industrial Units for Artisans in Najran | G3: Contract Award | H3: ='General Information'!C12 -> 46047 | I3: Contract Award (Hijri) | J3: ='General Information'!C16 -> 46047 | K3: Revised Completion | L3: ='General Information'!C20 -> 46389 | M3: Original Contract Value | O3: ='Invoice Log'!E3 -> 9554134 | Q3: O&M Value (if any) | S3: ='Invoice Log'!I3 -> 0 | T3: EAC | U3: Plan Value | V3: =K27 -> 0.75185056 | W3: Phys. Plan Value | X3: =W27 -> 0.78657431 | Y3: Quality Score | Z3: ='Quality-Stat'!J43 -> 0.88775862 | AA3: =+Progress!B1 -> The project scope covers the construction of the Low Process RBF Unit, Outside Mosque, Pump Shed, and GRP Water Tank, including site preparation works (demolition, excavation, and backfilling), concrete and masonry works, thermal and waterproofing systems, installation of doors and windows, finishing works, and specialties. It also includes pre-engineered structures, mechanical systems (sanitary, water supply, HVAC, and firefighting), and electrical systems such as substations, distribution networks, lighting, power, telecom, fire alarm, and solar power.
A4: Project ID | B4: ='General Information'!C4 -> NJR1-05-005 | D4: Stage | E4: ='General Information'!C7 -> Construction | G4: Contract Sign | H4: ='General Information'!C13 -> 46065 | I4: Contract Sign (Hijri) | J4: ='General Information'!C17 -> 46065 | K4: Committed Completion | L4: ='General Information'!C21 -> 46310 | M4: Revised Contract Value | O4: ='Invoice Log'!E4 -> 9554134 | P4: EAC | Q4: Submitted Invoices (Gross Value) | S4: ='Invoice Log'!I5 -> 7935744 | U4: Earn Value | V4: =L27 -> 0.96947719 | W4: Phys. Earn Value | X4: =X27 -> 0.96524679 | Z4: =REPT("¢",IF(INT(+Z3*10)>5,5,INT(+Z3*10)))&REPT("£",IF(INT(+Z3*10)>5,0,5-INT(+Z3*10)))&CHAR(10)&REPT("¢",+IF(INT(+Z3*10)>5,-5+INT(+Z3*10),0))&REPT("£",IF(INT(+Z3*10)>5,10-INT(+Z3*10),5)) -> ¢¢¢¢¢ ¢¢¢££
A5: Contractor | B5: ='General Information'!C5 -> Labenat Al Bena | D5: Status | E5: ='General Information'!C8 -> Active | G5: Site Handover | H5: ='General Information'!C14 -> 46084 | I5: Site Handover (Hijri) | J5: ='General Information'!C18 -> 46084 | K5: Forecast Completion | L5: ='General Information'!C22 -> 46310 | M5: Estimate At Completion Value | O5: ='Invoice Log'!E5 -> 9554134 | P5: =+#REF!+#REF!+O5 -> #REF! | Q5: Penalities | S5: ='Invoice Log'!I6 -> -20000 | U5: Variance | V5: =V4-V3 -> 0.21762663 | W5: Variance | X5: =Y27 -> 0.17867248 | Y5: Safety Score | Z5: =HSE!AE6 -> 0.83
A6: Consultant | B6: ='General Information'!C6 -> EGIS | D6: Modon PM | E6: ='General Information'!C9 -> Eng. Ahmed Kotbi | G6: Original Completion | H6: ='General Information'!C15 -> 46389 | I6: Original Completion (Hijri) | J6: ='General Information'!C19 -> 46389 | K6: Variance | L6: ='General Information'!C23 -> 79 | M6: Potential Changes | O6: =O4-O5 -> 0 | Q6: FIR Value (Todate) | S6: ='FIR Summary'!H17 -> 9266829.7 | U6: SPI | V6: =V4/V3 -> 1.2894546 | W6: SPI | X6: =X4/X3 -> 1.2271527 | Z6: =REPT("¢",IF(INT(+Z5*10)>5,5,INT(+Z5*10)))&REPT("£",IF(INT(+Z5*10)>5,0,5-INT(+Z5*10)))&CHAR(10)&REPT("¢",+IF(INT(+Z5*10)>5,-5+INT(+Z5*10),0))&REPT("£",IF(INT(+Z5*10)>5,10-INT(+Z5*10),5)) -> ¢¢¢¢¢ ¢¢¢££
A8: Progress Overview
A9: Earned Value Progress (SAR) | O9: Physical Progress (Effort) | AA9: Earned Value Progress (%)
A10: WBS | C10: BOQ Value (SAR) | D10: % Wt. | E10: Weekly (SAR) | G10: To Date (SAR) | O10: Budgeted | P10: % Wt. | Q10: Weekly Physical Progress | U10: To Date Physical Progress
E11: Planned | F11: Earned | G11: Crushed Planned | H11: Original Plan | I11: Earned | J11: Crushed Plan % | K11: Original Plan % | L11: Earned % | M11: Variance | N11: SPI | O11: (Manhours) | Q11: Planned | R11: Earned | S11: Plan % | T11: Earned % | U11: Planned | V11: Earned | W11: Plan % | X11: Earned % | Y11: Variance | Z11: SPI
A12: =+Progress!A7 -> MOBILIZATION | C12: =+Progress!C7 -> 0 | D12: =IF(ISBLANK(C12),"",C12/$C$27) -> 0 | E12: =+Progress!E7 -> 0 | F12: =+Progress!F7 -> 0 | G12: =Progress!G7 -> 0 | H12: =+Progress!H7 -> 0 | I12: =+Progress!I7 -> 0 | J12: =IFERROR(IF(ISBLANK(G12),"",G12/C12),0) -> 0 | K12: =IFERROR(IF(ISBLANK(H12),"",H12/C12),0) -> 0 | L12: =IFERROR(IF(ISBLANK(I12),"",I12/C12),0) -> 0 | M12: =IFERROR(L12-K12,"") -> 0 | N12: =IFERROR(L12/K12,"") | O12: =+Progress!K7 -> 8972.8 | P12: =IF(ISBLANK(O12),"",O12/$O$27) -> 0.04 | Q12: =+Progress!M7 -> 0 | R12: =+Progress!N7 -> 0 | S12: =IFERROR(IF(ISBLANK(Q12),"",Q12/O12),0) -> 0 | T12: =IFERROR(IF(ISBLANK(R12),"",R12/O12),0) -> 0 | U12: =+Progress!O7 -> 8972.8 | V12: =+Progress!P7 -> 8972.8 | W12: =IFERROR(IF(ISBLANK(U12),"",U12/O12),0) -> 1 | X12: =IFERROR(IF(ISBLANK(V12),"",V12/O12),0) -> 1 | Y12: =IFERROR(X12-W12,"") -> 0 | Z12: =IFERROR(X12/W12,"") -> 1
A13: =+Progress!A8 -> ENGINEERING | C13: =Progress!C8 -> 281825.22 | D13: =IF(ISBLANK(C13),"",C13/$C$27) -> 0.029497725 | E13: =+Progress!E8 -> 0 | F13: =+Progress!F8 -> 0 | G13: =Progress!G8 -> 281825 | H13: =+Progress!H8 -> 281825 | I13: =+Progress!I8 -> 281825 | J13: =IFERROR(IF(ISBLANK(G13),"",G13/C13),0) -> 0.99999922 | K13: =IFERROR(IF(ISBLANK(H13),"",H13/C13),0) -> 0.99999922 | L13: =IFERROR(IF(ISBLANK(I13),"",I13/C13),0) -> 0.99999922 | M13: =IFERROR(L13-K13,"") -> 0 | N13: =IFERROR(L13/K13,"") -> 1 | O13: =+Progress!K8 -> 8972.8 | P13: =IF(ISBLANK(O13),"",O13/$O$27) -> 0.04 | Q13: =+Progress!M8 -> 0 | R13: =+Progress!N8 -> 0 | S13: =IFERROR(IF(ISBLANK(Q13),"",Q13/O13),0) -> 0 | T13: =IFERROR(IF(ISBLANK(R13),"",R13/O13),0) -> 0 | U13: =+Progress!O8 -> 8972.8 | V13: =+Progress!P8 -> 8972.8 | W13: =IFERROR(IF(ISBLANK(U13),"",U13/O13),0) -> 1 | X13: =IFERROR(IF(ISBLANK(V13),"",V13/O13),0) -> 1 | Y13: =IFERROR(X13-W13,"") -> 0 | Z13: =IFERROR(X13/W13,"") -> 1
A14: =+Progress!A9 -> PROCUREMENT | C14: =Progress!C9 -> 2536427 | D14: =IF(ISBLANK(C14),"",C14/$C$27) -> 0.26547953 | E14: =+Progress!E9 -> 152357 | F14: =+Progress!F9 -> 0 | G14: =Progress!G9 -> 2536427 | H14: =+Progress!H9 -> 2457598 | I14: =+Progress!I9 -> 2536427 | J14: =IFERROR(IF(ISBLANK(G14),"",G14/C14),0) -> 1 | K14: =IFERROR(IF(ISBLANK(H14),"",H14/C14),0) -> 0.96892125 | L14: =IFERROR(IF(ISBLANK(I14),"",I14/C14),0) -> 1 | M14: =IFERROR(L14-K14,"") -> 0.031078758 | N14: =IFERROR(L14/K14,"") -> 1.0320756 | O14: =+Progress!K9 -> 26918.4 | P14: =IF(ISBLANK(O14),"",O14/$O$27) -> 0.12 | Q14: =+Progress!M9 -> 171.13 | R14: =+Progress!N9 -> 0 | S14: =IFERROR(IF(ISBLANK(Q14),"",Q14/O14),0) -> 0.0063573615 | T14: =IFERROR(IF(ISBLANK(R14),"",R14/O14),0) -> 0 | U14: =+Progress!O9 -> 26338.75 | V14: =+Progress!P9 -> 26918.4 | W14: =IFERROR(IF(ISBLANK(U14),"",U14/O14),0) -> 0.9784664 | X14: =IFERROR(IF(ISBLANK(V14),"",V14/O14),0) -> 1 | Y14: =IFERROR(X14-W14,"") -> 0.021533598 | Z14: =IFERROR(X14/W14,"") -> 1.0220075
A15: =Progress!A11 -> Site Works | C15: =Progress!C11 -> 682299 | D15: =IF(ISBLANK(C15),"",C15/$C$27) -> 0.071414008 | E15: =Progress!E11 -> 48693 | F15: =Progress!F11 -> 0 | G15: =Progress!G11 -> 682299 | H15: =Progress!H11 -> 189310 | I15: =Progress!I11 -> 682299 | J15: =IFERROR(IF(ISBLANK(G15),"",G15/C15),0) -> 1 | K15: =IFERROR(IF(ISBLANK(H15),"",H15/C15),0) -> 0.277459 | L15: =IFERROR(IF(ISBLANK(I15),"",I15/C15),0) -> 1 | M15: =IFERROR(L15-K15,"") -> 0.722541 | N15: =IFERROR(L15/K15,"") -> 3.6041361 | O15: =Progress!K11 -> 10600 | P15: =IF(ISBLANK(O15),"",O15/$O$27) -> 0.047253923 | Q15: =Progress!M11 -> 1552 | R15: =Progress!N11 -> 0 | S15: =IFERROR(IF(ISBLANK(Q15),"",Q15/O15),0) -> 0.14641509 | T15: =IFERROR(IF(ISBLANK(R15),"",R15/O15),0) -> 0 | U15: =Progress!O11 -> 5528 | V15: =Progress!P11 -> 10600 | W15: =IFERROR(IF(ISBLANK(U15),"",U15/O15),0) -> 0.52150943 | X15: =IFERROR(IF(ISBLANK(V15),"",V15/O15),0) -> 1 | Y15: =IFERROR(X15-W15,"") -> 0.47849057 | Z15: =IFERROR(X15/W15,"") -> 1.9175109
A16: =Progress!A12 -> Concrete | C16: =Progress!C12 -> 508590 | D16: =IF(ISBLANK(C16),"",C16/$C$27) -> 0.053232454 | E16: =Progress!E12 -> 0 | F16: =Progress!F12 -> 0 | G16: =Progress!G12 -> 508590 | H16: =Progress!H12 -> 508590 | I16: =Progress!I12 -> 508590 | J16: =IFERROR(IF(ISBLANK(G16),"",G16/C16),0) -> 1 | K16: =IFERROR(IF(ISBLANK(H16),"",H16/C16),0) -> 1 | L16: =IFERROR(IF(ISBLANK(I16),"",I16/C16),0) -> 1 | M16: =IFERROR(L16-K16,"") -> 0 | N16: =IFERROR(L16/K16,"") -> 1 | O16: =Progress!K12 -> 38936 | P16: =IF(ISBLANK(O16),"",O16/$O$27) -> 0.17357347 | Q16: =Progress!M12 -> 0 | R16: =Progress!N12 -> 0 | S16: =IFERROR(IF(ISBLANK(Q16),"",Q16/O16),0) -> 0 | T16: =IFERROR(IF(ISBLANK(R16),"",R16/O16),0) -> 0 | U16: =Progress!O12 -> 38936 | V16: =Progress!P12 -> 38936 | W16: =IFERROR(IF(ISBLANK(U16),"",U16/O16),0) -> 1 | X16: =IFERROR(IF(ISBLANK(V16),"",V16/O16),0) -> 1 | Y16: =IFERROR(X16-W16,"") -> 0 | Z16: =IFERROR(X16/W16,"") -> 1 | AJ16: 0
A17: =Progress!A13 -> Masonry Work | C17: =Progress!C13 -> 25032 | D17: =IF(ISBLANK(C17),"",C17/$C$27) -> 0.0026200177 | E17: =Progress!E13 -> 699 | F17: =Progress!F13 -> 0 | G17: =Progress!G13 -> 25032 | H17: =Progress!H13 -> 25032 | I17: =Progress!I13 -> 25032 | J17: =IFERROR(IF(ISBLANK(G17),"",G17/C17),0) -> 1 | K17: =IFERROR(IF(ISBLANK(H17),"",H17/C17),0) -> 1 | L17: =IFERROR(IF(ISBLANK(I17),"",I17/C17),0) -> 1 | M17: =IFERROR(L17-K17,"") -> 0 | N17: =IFERROR(L17/K17,"") -> 1 | O17: =Progress!K13 -> 4992 | P17: =IF(ISBLANK(O17),"",O17/$O$27) -> 0.022253923 | Q17: =Progress!M13 -> 384 | R17: =Progress!N13 -> 0 | S17: =IFERROR(IF(ISBLANK(Q17),"",Q17/O17),0) -> 0.076923077 | T17: =IFERROR(IF(ISBLANK(R17),"",R17/O17),0) -> 0 | U17: =Progress!O13 -> 4992 | V17: =Progress!P13 -> 4992 | W17: =IFERROR(IF(ISBLANK(U17),"",U17/O17),0) -> 1 | X17: =IFERROR(IF(ISBLANK(V17),"",V17/O17),0) -> 1 | Y17: =IFERROR(X17-W17,"") -> 0 | Z17: =IFERROR(X17/W17,"") -> 1 | AJ17: 0
A18: =Progress!A14 -> Metal Works | C18: =Progress!C14 -> 43560 | D18: =IF(ISBLANK(C18),"",C18/$C$27) -> 0.0045592829 | E18: =Progress!E14 -> 2160 | F18: =Progress!F14 -> 0 | G18: =Progress!G14 -> 43560 | H18: =Progress!H14 -> 8640 | I18: =Progress!I14 -> 43560 | J18: =IFERROR(IF(ISBLANK(G18),"",G18/C18),0) -> 1 | K18: =IFERROR(IF(ISBLANK(H18),"",H18/C18),0) -> 0.19834711 | L18: =IFERROR(IF(ISBLANK(I18),"",I18/C18),0) -> 1 | M18: =IFERROR(L18-K18,"") -> 0.80165289 | N18: =IFERROR(L18/K18,"") -> 5.0416667 | O18: =Progress!K14 -> 1288 | P18: =IF(ISBLANK(O18),"",O18/$O$27) -> 0.0057417974 | Q18: =Progress!M14 -> 96 | R18: =Progress!N14 -> 0 | S18: =IFERROR(IF(ISBLANK(Q18),"",Q18/O18),0) -> 0.074534161 | T18: =IFERROR(IF(ISBLANK(R18),"",R18/O18),0) -> 0 | U18: =Progress!O14 -> 384 | V18: =Progress!P14 -> 1288 | W18: =IFERROR(IF(ISBLANK(U18),"",U18/O18),0) -> 0.29813665 | X18: =IFERROR(IF(ISBLANK(V18),"",V18/O18),0) -> 1 | Y18: =IFERROR(X18-W18,"") -> 0.70186335 | Z18: =IFERROR(X18/W18,"") -> 3.3541667
A19: =Progress!A15 -> Thermal & Moisture Protection | C19: =Progress!C15 -> 114132 | D19: =IF(ISBLANK(C19),"",C19/$C$27) -> 0.011945824 | E19: =Progress!E15 -> 2911 | F19: =Progress!F15 -> 0 | G19: =Progress!G15 -> 114132 | H19: =Progress!H15 -> 104262 | I19: =Progress!I15 -> 114132 | J19: =IFERROR(IF(ISBLANK(G19),"",G19/C19),0) -> 1 | K19: =IFERROR(IF(ISBLANK(H19),"",H19/C19),0) -> 0.91352119 | L19: =IFERROR(IF(ISBLANK(I19),"",I19/C19),0) -> 1 | M19: =IFERROR(L19-K19,"") -> 0.086478814 | N19: =IFERROR(L19/K19,"") -> 1.0946654 | O19: =Progress!K15 -> 5984 | P19: =IF(ISBLANK(O19),"",O19/$O$27) -> 0.026676177 | Q19: =Progress!M15 -> 560 | R19: =Progress!N15 -> 0 | S19: =IFERROR(IF(ISBLANK(Q19),"",Q19/O19),0) -> 0.093582888 | T19: =IFERROR(IF(ISBLANK(R19),"",R19/O19),0) -> 0 | U19: =Progress!O15 -> 4880 | V19: =Progress!P15 -> 5984 | W19: =IFERROR(IF(ISBLANK(U19),"",U19/O19),0) -> 0.81550802 | X19: =IFERROR(IF(ISBLANK(V19),"",V19/O19),0) -> 1 | Y19: =IFERROR(X19-W19,"") -> 0.18449198 | Z19: =IFERROR(X19/W19,"") -> 1.2262295
A20: =Progress!A16 -> Doors and Windows | C20: =Progress!C16 -> 198780 | D20: =IF(ISBLANK(C20),"",C20/$C$27) -> 0.020805653 | E20: =Progress!E16 -> 63746 | F20: =Progress!F16 -> 0 | G20: =Progress!G16 -> 198780 | H20: =Progress!H16 -> 150146 | I20: =Progress!I16 -> 198780 | J20: =IFERROR(IF(ISBLANK(G20),"",G20/C20),0) -> 1 | K20: =IFERROR(IF(ISBLANK(H20),"",H20/C20),0) -> 0.75533756 | L20: =IFERROR(IF(ISBLANK(I20),"",I20/C20),0) -> 1 | M20: =IFERROR(L20-K20,"") -> 0.24466244 | N20: =IFERROR(L20/K20,"") -> 1.3239114 | O20: =Progress!K16 -> 8048 | P20: =IF(ISBLANK(O20),"",O20/$O$27) -> 0.035877318 | Q20: =Progress!M16 -> 1432 | R20: =Progress!N16 -> 0 | S20: =IFERROR(IF(ISBLANK(Q20),"",Q20/O20),0) -> 0.17793241 | T20: =IFERROR(IF(ISBLANK(R20),"",R20/O20),0) -> 0 | U20: =Progress!O16 -> 2584 | V20: =Progress!P16 -> 8048 | W20: =IFERROR(IF(ISBLANK(U20),"",U20/O20),0) -> 0.32107356 | X20: =IFERROR(IF(ISBLANK(V20),"",V20/O20),0) -> 1 | Y20: =IFERROR(X20-W20,"") -> 0.67892644 | Z20: =IFERROR(X20/W20,"") -> 3.1145511
A21: =Progress!A17 -> Finishes | C21: =Progress!C17 -> 173460 | D21: =IF(ISBLANK(C21),"",C21/$C$27) -> 0.018155492 | E21: =Progress!E17 -> 3633 | F21: =Progress!F17 -> 0 | G21: =Progress!G17 -> 173460 | H21: =Progress!H17 -> 14069 | I21: =Progress!I17 -> 173460 | J21: =IFERROR(IF(ISBLANK(G21),"",G21/C21),0) -> 1 | K21: =IFERROR(IF(ISBLANK(H21),"",H21/C21),0) -> 0.081108036 | L21: =IFERROR(IF(ISBLANK(I21),"",I21/C21),0) -> 1 | M21: =IFERROR(L21-K21,"") -> 0.91889196 | N21: =IFERROR(L21/K21,"") -> 12.329234 | O21: =Progress!K17 -> 11200 | P21: =IF(ISBLANK(O21),"",O21/$O$27) -> 0.049928673 | Q21: =Progress!M17 -> 480 | R21: =Progress!N17 -> 0 | S21: =IFERROR(IF(ISBLANK(Q21),"",Q21/O21),0) -> 0.042857143 | T21: =IFERROR(IF(ISBLANK(R21),"",R21/O21),0) -> 0 | U21: =Progress!O17 -> 2560 | V21: =Progress!P17 -> 11200 | W21: =IFERROR(IF(ISBLANK(U21),"",U21/O21),0) -> 0.22857143 | X21: =IFERROR(IF(ISBLANK(V21),"",V21/O21),0) -> 1 | Y21: =IFERROR(X21-W21,"") -> 0.77142857 | Z21: =IFERROR(X21/W21,"") -> 4.375
A22: =Progress!A18 -> Specialties | C22: =Progress!C18 -> 27450 | D22: =IF(ISBLANK(C22),"",C22/$C$27) -> 0.0028731018 | E22: =Progress!E18 -> 0 | F22: =Progress!F18 -> 0 | G22: =Progress!G18 -> 27450 | H22: =Progress!H18 -> 0 | I22: =Progress!I18 -> 27450 | J22: =IFERROR(IF(ISBLANK(G22),"",G22/C22),0) -> 1 | K22: =IFERROR(IF(ISBLANK(H22),"",H22/C22),0) -> 0 | L22: =IFERROR(IF(ISBLANK(I22),"",I22/C22),0) -> 1 | M22: =IFERROR(L22-K22,"") -> 1 | N22: =IFERROR(L22/K22,"") | O22: =Progress!K18 -> 1392 | P22: =IF(ISBLANK(O22),"",O22/$O$27) -> 0.0062054208 | Q22: =Progress!M18 -> 0 | R22: =Progress!N18 -> 0 | S22: =IFERROR(IF(ISBLANK(Q22),"",Q22/O22),0) -> 0 | T22: =IFERROR(IF(ISBLANK(R22),"",R22/O22),0) -> 0 | U22: =Progress!O18 -> 0 | V22: =Progress!P18 -> 1392 | W22: =IFERROR(IF(ISBLANK(U22),"",U22/O22),0) -> 0 | X22: =IFERROR(IF(ISBLANK(V22),"",V22/O22),0) -> 1 | Y22: =IFERROR(X22-W22,"") -> 1 | Z22: =IFERROR(X22/W22,"")
A23: =Progress!A19 -> Pre Engineered Structure | C23: =Progress!C19 -> 1223640 | D23: =IF(ISBLANK(C23),"",C23/$C$27) -> 0.1280744 | E23: =Progress!E19 -> 0 | F23: =Progress!F19 -> 0 | G23: =Progress!G19 -> 1223640 | H23: =Progress!H19 -> 1223640 | I23: =Progress!I19 -> 1188960 | J23: =IFERROR(IF(ISBLANK(G23),"",G23/C23),0) -> 1 | K23: =IFERROR(IF(ISBLANK(I23),"",I23/C23),0) -> 0.97165833 | L23: =IFERROR(IF(ISBLANK(I23),"",I23/C23),0) -> 0.97165833 | M23: =IFERROR(L23-K23,"") -> 0 | N23: =IFERROR(L23/K23,"") -> 1 | O23: =Progress!K19 -> 18224 | P23: =IF(ISBLANK(O23),"",O23/$O$27) -> 0.081241084 | Q23: =Progress!M19 -> 0 | R23: =Progress!N19 -> 0 | S23: =IFERROR(IF(ISBLANK(Q23),"",Q23/O23),0) -> 0 | T23: =IFERROR(IF(ISBLANK(R23),"",R23/O23),0) -> 0 | U23: =Progress!O19 -> 18224 | V23: =Progress!P19 -> 16640 | W23: =IFERROR(IF(ISBLANK(U23),"",U23/O23),0) -> 1 | X23: =IFERROR(IF(ISBLANK(V23),"",V23/O23),0) -> 0.91308165 | Y23: =IFERROR(X23-W23,"") -> -0.086918349 | Z23: =IFERROR(X23/W23,"") -> 0.91308165
A24: =Progress!A20 -> Mechanical Work | C24: =Progress!C20 -> 1175904 | D24: =IF(ISBLANK(C24),"",C24/$C$27) -> 0.12307803 | E24: =Progress!E20 -> 6048 | F24: =Progress!F20 -> 201600 | G24: =Progress!G20 -> 1175904 | H24: =Progress!H20 -> 1099852 | I24: =Progress!I20 -> 1175904 | J24: =IFERROR(IF(ISBLANK(G24),"",G24/C24),0) -> 1 | K24: =IFERROR(IF(ISBLANK(I24),"",I24/C24),0) -> 1 | L24: =IFERROR(IF(ISBLANK(I24),"",I24/C24),0) -> 1 | M24: =IFERROR(L24-K24,"") -> 0 | N24: =IFERROR(L24/K24,"") -> 1 | O24: =Progress!K20 -> 29328 | P24: =IF(ISBLANK(O24),"",O24/$O$27) -> 0.1307418 | Q24: =Progress!M20 -> 592 | R24: =Progress!N20 -> 1152 | S24: =IFERROR(IF(ISBLANK(Q24),"",Q24/O24),0) -> 0.020185488 | T24: =IFERROR(IF(ISBLANK(R24),"",R24/O24),0) -> 0.039279869 | U24: =Progress!O20 -> 24816 | V24: =Progress!P20 -> 29328 | W24: =IFERROR(IF(ISBLANK(U24),"",U24/O24),0) -> 0.84615385 | X24: =IFERROR(IF(ISBLANK(V24),"",V24/O24),0) -> 1 | Y24: =IFERROR(X24-W24,"") -> 0.15384615 | Z24: =IFERROR(X24/W24,"") -> 1.1818182
A25: =Progress!A21 -> Electrical Work | C25: =Progress!C21 -> 1607621.4 | D25: =IF(ISBLANK(C25),"",C25/$C$27) -> 0.16826448 | E25: =Progress!E21 -> 101540 | F25: =Progress!F21 -> 15744 | G25: =Progress!G21 -> 1607621 | H25: =Progress!H21 -> 1120317 | I25: =Progress!I21 -> 1581472 | J25: =IFERROR(IF(ISBLANK(G25),"",G25/C25),0) -> 0.99999975 | K25: =IFERROR(IF(ISBLANK(I25),"",I25/C25),0) -> 0.98373411 | L25: =IFERROR(IF(ISBLANK(I25),"",I25/C25),0) -> 0.98373411 | M25: =IFERROR(L25-K25,"") -> 0 | N25: =IFERROR(L25/K25,"") -> 1 | O25: =Progress!K21 -> 41144 | P25: =IF(ISBLANK(O25),"",O25/$O$27) -> 0.18341655 | Q25: =Progress!M21 -> 1792 | R25: =Progress!N21 -> 537.6 | S25: =IFERROR(IF(ISBLANK(Q25),"",Q25/O25),0) -> 0.043554346 | T25: =IFERROR(IF(ISBLANK(R25),"",R25/O25),0) -> 0.013066304 | U25: =Progress!O21 -> 29256 | V25: =Progress!P21 -> 40090.56 | W25: =IFERROR(IF(ISBLANK(U25),"",U25/O25),0) -> 0.71106358 | X25: =IFERROR(IF(ISBLANK(V25),"",V25/O25),0) -> 0.97439627 | Y25: =IFERROR(X25-W25,"") -> 0.26333269 | Z25: =IFERROR(X25/W25,"") -> 1.3703363
A26: =Progress!A23 -> Close-Out | C26: =Progress!C23 -> 955413.4 | D26: =IF(ISBLANK(C26),"",C26/$C$27) -> 0.1 | E26: =Progress!E23 -> 0 | F26: =Progress!F23 -> 1281 | G26: =Progress!G23 -> 955413 | H26: =Progress!H23 -> 0 | I26: =Progress!I23 -> 724624 | J26: =IFERROR(IF(ISBLANK(G26),"",G26/C26),0) -> 0.99999958 | K26: =IFERROR(IF(ISBLANK(I26),"",I26/C26),0) -> 0.75844027 | L26: =IFERROR(IF(ISBLANK(I26),"",I26/C26),0) -> 0.75844027 | M26: =IFERROR(L26-K26,"") -> 0 | N26: =IFERROR(L26/K26,"") -> 1 | O26: =Progress!K22 -> 8320 | P26: =IF(ISBLANK(O26),"",O26/$O$27) -> 0.037089872 | Q26: =Progress!M23 -> 0 | R26: =Progress!N23 -> 89.6 | S26: =IFERROR(IF(ISBLANK(Q26),"",Q26/O26),0) -> 0 | T26: =IFERROR(IF(ISBLANK(R26),"",R26/O26),0) -> 0.010769231 | U26: =Progress!O23 -> 0 | V26: =Progress!P23 -> 3161.6 | W26: =IFERROR(IF(ISBLANK(U26),"",U26/O26),0) -> 0 | X26: =IFERROR(IF(ISBLANK(V26),"",V26/O26),0) -> 0.38 | Y26: =IFERROR(X26-W26,"") -> 0.38 | Z26: =IFERROR(X26/W26,"")
B27: Total | C27: =SUM(C12:C26) -> 9554134 | D27: =SUM(D12:D26) -> 1 | E27: =SUM(E12:E26) -> 381787 | F27: =SUM(F12:F26) -> 218625 | G27: =SUM(G12:G26) -> 9554133 | H27: =SUM(H12:H26) -> 7183281 | I27: =SUM(I12:I26) -> 9262515 | J27: =IFERROR(IF(ISBLANK(G27),"",G27/C27),0) -> 0.9999999 | K27: =IFERROR(IF(ISBLANK(H27),"",H27/C27),0) -> 0.75185056 | L27: =IFERROR(IF(ISBLANK(I27),"",I27/C27),0) -> 0.96947719 | M27: =+L27-K27 -> 0.21762663 | N27: =L27/K27 -> 1.2894546 | O27: =SUM(O12:O26) -> 224320 | P27: =SUM(P12:P26) -> 1 | Q27: =SUM(Q12:Q26) -> 7059.13 | R27: =SUM(R12:R26) -> 1779.2 | S27: =IFERROR(IF(ISBLANK(Q27),"",Q27/O27),0) -> 0.031469017 | T27: =IFERROR(IF(ISBLANK(R27),"",R27/O27),0) -> 0.0079315264 | U27: =SUM(U12:U26) -> 176444.35 | V27: =SUM(V12:V26) -> 216524.16 | W27: =IFERROR(IF(ISBLANK(U27),"",U27/O27),0) -> 0.78657431 | X27: =IFERROR(IF(ISBLANK(V27),"",V27/O27),0) -> 0.96524679 | Y27: =+X27-W27 -> 0.17867248 | Z27: =X27/W27 -> 1.2271527
AA28: Construction Milestones
AA29: Item No. | AB29: Milestones | AD29: Original (Baseline) | AE29: Latest Plan | AF29: Forecast | AG29: Status | AH29: Days Change
AA30: =+Milestones!A4 -> 1 | AB30: =+Milestones!B4 -> Award Date | AD30: =+Milestones!C4 -> 46047 | AE30: =+Milestones!D4 -> 46047 | AF30: =+Milestones!E4 -> 46047 | AG30: =+Milestones!F4 -> A | AH30: =+Milestones!G4 -> 0
AA31: =+Milestones!A5 -> 2 | AB31: =+Milestones!B5 -> Contract Sign Date | AD31: =+Milestones!C5 -> 46065 | AE31: =+Milestones!D5 -> 46065 | AF31: =+Milestones!E5 -> 46065 | AG31: =+Milestones!F5 -> A | AH31: =+Milestones!G5 -> 0
AA32: =+Milestones!A6 -> 3 | AB32: =+Milestones!B6 -> Site Handover Date | AD32: =+Milestones!C6 -> 46084 | AE32: =+Milestones!D6 -> 46084 | AF32: =+Milestones!E6 -> 46084 | AG32: =+Milestones!F6 -> A | AH32: =+Milestones!G6 -> 0
AA33: =+Milestones!A7 -> 4 | AB33: =+Milestones!B7 -> Complete Mobilization | AD33: =+Milestones!C7 -> 45747 | AE33: =+Milestones!D7 -> 45747 | AF33: =+Milestones!E7 -> 45747 | AG33: =+Milestones!F7 -> A | AH33: =+Milestones!G7 -> 0
AA34: =+Milestones!A8 -> 5 | AB34: =+Milestones!B8 -> Complete existing condition survey, submission of Final Reports | AD34: =+Milestones!C8 -> 45747 | AE34: =+Milestones!D8 -> 45747 | AF34: =+Milestones!E8 -> 45747 | AG34: =+Milestones!F8 -> A | AH34: =+Milestones!G8 -> 0
AA35: =+Milestones!A9 -> 6 | AB35: =+Milestones!B9 -> Completion of Long Lead Procurement and Material Delivery | AD35: =+Milestones!C9 -> 46322 | AE35: =+Milestones!D9 -> 46322 | AF35: =+Milestones!E9 -> 46322 | AG35: =+Milestones!F9 -> A | AH35: =+Milestones!G9 -> 0
AA36: =+Milestones!A10 -> 7 | AB36: =+Milestones!B10 -> Completion of Short Lead Procurement and Material Delivery | AD36: =+Milestones!C10 -> 46324 | AE36: =+Milestones!D10 -> 46270 | AF36: =+Milestones!E10 -> 46270 | AG36: =+Milestones!F10 -> A | AH36: =+Milestones!G10 -> 0
AA37: =+Milestones!A11 -> 8 | AB37: =+Milestones!B11 -> Complete All Warehouse | AD37: =+Milestones!C11 -> 46355 | AE37: =+Milestones!D11 -> 46298 | AF37: =+Milestones!E11 -> 46298 | AG37: =+Milestones!F11 -> A | AH37: =+Milestones!G11 -> 0
AA38: =+Milestones!A12 -> 9 | AB38: =+Milestones!B12 -> Complete All Outside Mosque (Prayer Room) | AD38: =+Milestones!C12 -> 46361 | AE38: =+Milestones!D12 -> 46295 | AF38: =+Milestones!E12 -> 46295 | AG38: =+Milestones!F12 -> A | AH38: =+Milestones!G12 -> 0
A54: Performance overview
A55: Submittals Status | L55: Quality | W55: Safety
A56: Shop Drawings | L56: Quality Reports | W56: Safety Statistics | AE56: Proactive Vs Reactive Actions Taken
A57: Item Per WBS | C57: Total | D57: Total Submitted Drawings | I57: Remaining | J57: Pending | K57: Total Submittals | L57: Quality Reports | N57: Issued | O57: Closed | P57: Pending | Q57: Avg. Closing (Days) | R57: Pending | W57: Category | X57: Item | Z57: This Week | AB57: This Month | AC57: Year to Date | AD57: Cumulative
D58: A | E58: B | F58: C | G58: D | H58: Processed | R58: 0-10 Days | S58: 11-20 Days | T58: 21-30 Days | U58: 31-60 Days | V58: > 60 Days
A59: ='Quality-Stat'!$A$13 -> Structural | C59: =IF('Quality-Stat'!D13="","",'Quality-Stat'!D13) -> 19 | D59: =IF('Quality-Stat'!E13="","",'Quality-Stat'!E13) -> 19 | E59: =IF('Quality-Stat'!F13="","",'Quality-Stat'!F13) -> 0 | F59: =IF('Quality-Stat'!G13="","",'Quality-Stat'!G13) -> 0 | G59: =IF('Quality-Stat'!H13="","",'Quality-Stat'!H13) | H59: =IF('Quality-Stat'!I13="","",'Quality-Stat'!I13) -> 19 | I59: =IF('Quality-Stat'!J13="","",'Quality-Stat'!J13) -> 0 | J59: =IF('Quality-Stat'!K13="","",'Quality-Stat'!K13) -> 0 | K59: =IF('Quality-Stat'!L13="","",'Quality-Stat'!L13) -> 19 | W59: General | X59: ='[35]HSE-Stat'!B4 -> Total Hours Worked | Z59: ='HSE-Stat'!D4 -> 1920 | AB59: ='HSE-Stat'!E4 -> 3960 | AC59: ='HSE-Stat'!F4 -> 82166 | AD59: ='HSE-Stat'!G4 -> 82166 | AG59: Proactive | AH59: =+SUM(AD70:AD74) -> 0
A60: ='Quality-Stat'!$A$14 -> Architectural | C60: =IF('Quality-Stat'!D14="","",'Quality-Stat'!D14) -> 15 | D60: =IF('Quality-Stat'!E14="","",'Quality-Stat'!E14) -> 15 | E60: =IF('Quality-Stat'!F14="","",'Quality-Stat'!F14) -> 0 | F60: =IF('Quality-Stat'!G14="","",'Quality-Stat'!G14) -> 0 | G60: =IF('Quality-Stat'!H14="","",'Quality-Stat'!H14) | H60: =IF('Quality-Stat'!I14="","",'Quality-Stat'!I14) -> 15 | I60: =IF('Quality-Stat'!J14="","",'Quality-Stat'!J14) -> 0 | J60: =IF('Quality-Stat'!K14="","",'Quality-Stat'!K14) -> 0 | K60: =IF('Quality-Stat'!L14="","",'Quality-Stat'!L14) -> 15 | L60: Non Conformance (NCR) | N60: ='Quality-Stat'!C5 -> 17 | O60: ='Quality-Stat'!D5 -> 17 | P60: ='Quality-Stat'!E5 -> 0 | Q60: ='Quality-Stat'!F5 -> 3 | R60: ='Quality-Stat'!G5 -> 0 | S60: ='Quality-Stat'!H5 -> 0 | T60: ='Quality-Stat'!I5 -> 0 | U60: ='Quality-Stat'!J5 -> 0 | V60: ='Quality-Stat'!K5 -> 0 | X60: ='[35]HSE-Stat'!B5 -> Safe Hours Worked | Z60: ='HSE-Stat'!D5 -> 2040 | AB60: ='HSE-Stat'!E5 -> 3960 | AC60: ='HSE-Stat'!F5 -> 82166 | AD60: ='HSE-Stat'!G5 -> 82166 | AG60: Reactive | AH60: =SUM(AD61:AD69) -> 4
A61: ='Quality-Stat'!$A$15 -> Mechanical, Electrical , & External Infra | C61: =IF('Quality-Stat'!D15="","",'Quality-Stat'!D15) -> 47 | D61: =IF('Quality-Stat'!E15="","",'Quality-Stat'!E15) -> 47 | E61: =IF('Quality-Stat'!F15="","",'Quality-Stat'!F15) -> 0 | F61: =IF('Quality-Stat'!G15="","",'Quality-Stat'!G15) -> 0 | G61: =IF('Quality-Stat'!H15="","",'Quality-Stat'!H15) | H61: =IF('Quality-Stat'!I15="","",'Quality-Stat'!I15) -> 47 | I61: =IF('Quality-Stat'!J15="","",'Quality-Stat'!J15) -> 0 | J61: =IF('Quality-Stat'!K15="","",'Quality-Stat'!K15) -> 0 | K61: =IF('Quality-Stat'!L15="","",'Quality-Stat'!L15) -> 47 | L61: Site Instruction (SIR) | N61: ='Quality-Stat'!C6 -> 18 | O61: ='Quality-Stat'!D6 -> 18 | P61: ='Quality-Stat'!E6 -> 0 | Q61: ='Quality-Stat'!F6 -> 3 | R61: ='Quality-Stat'!G6 -> 0 | S61: ='Quality-Stat'!H6 -> 0 | T61: ='Quality-Stat'!I6 -> 0 | U61: ='Quality-Stat'!J6 -> 0 | V61: ='Quality-Stat'!K6 -> 0 | W61: Reactive | X61: ='[35]HSE-Stat'!B6 -> LTI | Z61: ='[36]HSE-Stat'!D6 -> 0 | AB61: ='[36]HSE-Stat'!E6 -> 0 | AC61: ='[36]HSE-Stat'!F6 -> 0 | AD61: ='[36]HSE-Stat'!G6 -> 0
A62: ='Quality-Stat'!A16:C16 -> Road | C62: =IF('Quality-Stat'!D16="","",'Quality-Stat'!D16) -> 12 | D62: =IF('Quality-Stat'!E16="","",'Quality-Stat'!E16) -> 12 | E62: =IF('Quality-Stat'!F16="","",'Quality-Stat'!F16) -> 0 | F62: =IF('Quality-Stat'!G16="","",'Quality-Stat'!G16) -> 0 | G62: =IF('Quality-Stat'!H16="","",'Quality-Stat'!H16) | H62: =IF('Quality-Stat'!I16="","",'Quality-Stat'!I16) -> 12 | I62: =IF('Quality-Stat'!J16="","",'Quality-Stat'!J16) -> 0 | J62: =IF('Quality-Stat'!K16="","",'Quality-Stat'!K16) -> 0 | K62: =IF('Quality-Stat'!L16="","",'Quality-Stat'!L16) -> 12 | L62: Material Inspection (MIR) | N62: ='Quality-Stat'!C7 -> 64 | O62: ='Quality-Stat'!D7 -> 64 | P62: ='Quality-Stat'!E7 -> 0 | Q62: ='Quality-Stat'!F6 -> 3 | R62: ='Quality-Stat'!G7 -> 0 | S62: ='Quality-Stat'!H7 -> 0 | T62: ='Quality-Stat'!I7 -> 0 | U62: ='Quality-Stat'!J7 -> 0 | V62: ='Quality-Stat'!K7 -> 0 | X62: ='[35]HSE-Stat'!B7 -> MTC (Healed w/o Disability) | Z62: ='[36]HSE-Stat'!D7 -> 0 | AB62: ='[36]HSE-Stat'!E7 -> 0 | AC62: ='[36]HSE-Stat'!F7 -> 0 | AD62: ='[36]HSE-Stat'!G7 -> 0
C63: =IF('Quality-Stat'!D18="","",'Quality-Stat'!D18) | D63: =IF('Quality-Stat'!E18="","",'Quality-Stat'!E18) | E63: =IF('Quality-Stat'!F18="","",'Quality-Stat'!F18) | F63: =IF('Quality-Stat'!G18="","",'Quality-Stat'!G18) | G63: =IF('Quality-Stat'!H18="","",'Quality-Stat'!H18) | H63: =IF('Quality-Stat'!I18="","",'Quality-Stat'!I18) | I63: =IF('Quality-Stat'!J18="","",'Quality-Stat'!J18) | J63: =IF('Quality-Stat'!K18="","",'Quality-Stat'!K18) | K63: =IF('Quality-Stat'!L18="","",'Quality-Stat'!L18) | L63: Field Inspection (FIR) | N63: ='Quality-Stat'!C8 -> 407 | O63: ='Quality-Stat'!D8 -> 407 | P63: ='Quality-Stat'!E8 -> 0 | Q63: ='Quality-Stat'!F7 -> 3 | R63: ='Quality-Stat'!G8 -> 0 | S63: ='Quality-Stat'!H8 -> 0 | T63: ='Quality-Stat'!I8 -> 0 | U63: ='Quality-Stat'!J8 -> 0 | V63: ='Quality-Stat'!K8 -> 0 | X63: ='[35]HSE-Stat'!B8 -> MTC (Healed w/ Disability) | Z63: ='[36]HSE-Stat'!D8 -> 0 | AB63: ='[36]HSE-Stat'!E8 -> 0 | AC63: ='[36]HSE-Stat'!F8 -> 0 | AD63: ='[36]HSE-Stat'!G8 -> 0
A64: TOTAL | C64: =SUM(C59:C63) -> 93 | D64: =SUM(D59:D63) -> 93 | E64: =SUM(E59:E63) -> 0 | F64: =SUM(F59:F63) -> 0 | G64: =SUM(G59:G63) -> 0 | H64: =SUM(H59:H63) -> 93 | I64: =SUM(I59:I63) -> 0 | J64: =SUM(J59:J63) -> 0 | K64: =SUM(K59:K63) -> 93 | L64: Key Submittals Approval Status | X64: ='[35]HSE-Stat'!B9 -> Near Miss | Z64: 0 | AB64: 0 | AC64: ='[36]HSE-Stat'!F9 -> 2 | AD64: ='[36]HSE-Stat'!G9 -> 2
A65: Material Approval | L65: 1 Quality Plan Approval | O65: ='General Information'!C27 -> 46134 | Q65: 6 Baseline Approval | U65: ='General Information'!C39 -> 46113 | X65: ='[35]HSE-Stat'!B10 -> First Aid Cases | Z65: ='[36]HSE-Stat'!D10 -> 0 | AB65: ='[36]HSE-Stat'!E10 -> 0 | AC65: ='[36]HSE-Stat'!F10 -> 1 | AD65: ='[36]HSE-Stat'!G10 -> 1 | AE65: Total Hours Worked Vs Safe Hours Worked
A66: Item Per WBS | C66: Total | D66: Total Submitted Material | I66: Remaining to approve | J66: Pending | K66: Total Submittals | L66: 2 Quality Plan Last Up | O66: ='General Information'!C28 -> 46134 | Q66: 7 No of Approved Version of Schedule | U66: ='General Information'!C40 -> 0 | X66: ='[35]HSE-Stat'!B11 -> Fatality | Z66: ='[36]HSE-Stat'!D11 -> 0 | AB66: ='[36]HSE-Stat'!E11 -> 0 | AC66: ='[36]HSE-Stat'!F11 -> 0 | AD66: ='[36]HSE-Stat'!G11 -> 0
D67: A | E67: B | F67: C | G67: D | H67: Processed | I67: with Designer | L67: 3 Safety Plan Approval | O67: ='General Information'!C31 -> 46130 | Q67: 8 Last Approved Schedule | U67: ='General Information'!C41 -> 46113 | X67: ='[35]HSE-Stat'!B12 -> Fire Incident Cases | Z67: ='[36]HSE-Stat'!D12 -> 0 | AB67: ='[36]HSE-Stat'!E12 -> 0 | AC67: ='[36]HSE-Stat'!F12 -> 1 | AD67: ='[36]HSE-Stat'!G12 -> 1
A68: ='Quality-Stat'!$A$25 -> Earthworks | C68: =IF('Quality-Stat'!D25="","",'Quality-Stat'!D25) -> 8 | D68: =IF('Quality-Stat'!E25="","",'Quality-Stat'!E25) -> 8 | E68: =IF('Quality-Stat'!F25="","",'Quality-Stat'!F25) -> 0 | F68: =IF('Quality-Stat'!G25="","",'Quality-Stat'!G25) | G68: =IF('Quality-Stat'!H25="","",'Quality-Stat'!H25) | H68: =IF('Quality-Stat'!I25="","",'Quality-Stat'!I25) -> 8 | I68: =IF('Quality-Stat'!J25="","",'Quality-Stat'!J25) -> 0 | J68: =IF('Quality-Stat'!K25="","",'Quality-Stat'!K25) -> 0 | K68: =IF('Quality-Stat'!L25="","",'Quality-Stat'!L25) -> 8 | L68: 4 Safety Plan Last Up | O68: ='General Information'!C32 -> 46130 | Q68: 9 BOQ Approval Date | U68: ='General Information'!C44 -> N/A | X68: ='[35]HSE-Stat'!B13 -> Vehicle Incident | Z68: ='[36]HSE-Stat'!D13 -> 0 | AB68: ='[36]HSE-Stat'!E13 -> 0 | AC68: ='[36]HSE-Stat'!F13 -> 0 | AD68: ='[36]HSE-Stat'!G13 -> 0
A69: ='Quality-Stat'!$A$26 -> Structural | C69: =IF('Quality-Stat'!D26="","",'Quality-Stat'!D26) -> 14 | D69: =IF('Quality-Stat'!E26="","",'Quality-Stat'!E26) -> 14 | E69: =IF('Quality-Stat'!F26="","",'Quality-Stat'!F26) -> 0 | F69: =IF('Quality-Stat'!G26="","",'Quality-Stat'!G26) | G69: =IF('Quality-Stat'!H26="","",'Quality-Stat'!H26) | H69: =IF('Quality-Stat'!I26="","",'Quality-Stat'!I26) -> 14 | I69: =IF('Quality-Stat'!J26="","",'Quality-Stat'!J26) -> 0 | J69: =IF('Quality-Stat'!K26="","",'Quality-Stat'!K26) -> 0 | K69: =IF('Quality-Stat'!L26="","",'Quality-Stat'!L26) -> 14 | L69: 5 Construction Plan Approval | O69: ='General Information'!C48 -> 46114 | Q69: 10 No of Approved Version of BOQ | U69: ='General Information'!C45 -> 0 | X69: ='[35]HSE-Stat'!B14 -> Property Damages | Z69: ='[36]HSE-Stat'!D14 -> 0 | AB69: ='[36]HSE-Stat'!E14 -> 0 | AC69: ='[36]HSE-Stat'!F14 -> 0 | AD69: ='[36]HSE-Stat'!G14 -> 0
A70: ='Quality-Stat'!$A$27 -> Architectural | C70: =IF('Quality-Stat'!D27="","",'Quality-Stat'!D27) -> 23 | D70: =IF('Quality-Stat'!E27="","",'Quality-Stat'!E27) -> 23 | E70: =IF('Quality-Stat'!F27="","",'Quality-Stat'!F27) -> 0 | F70: =IF('Quality-Stat'!G27="","",'Quality-Stat'!G27) | G70: =IF('Quality-Stat'!H27="","",'Quality-Stat'!H27) | H70: =IF('Quality-Stat'!I27="","",'Quality-Stat'!I27) -> 23 | I70: =IF('Quality-Stat'!J27="","",'Quality-Stat'!J27) -> 0 | J70: =IF('Quality-Stat'!K27="","",'Quality-Stat'!K27) -> 0 | K70: =IF('Quality-Stat'!L27="","",'Quality-Stat'!L27) -> 23 | L70: Invoices Summary | W70: Proactive | X70: ='[35]HSE-Stat'!B15 -> Induction Training | Z70: ='HSE-Stat'!D15 -> 1 | AB70: ='HSE-Stat'!E15 -> 1 | AC70: ='HSE-Stat'!F15 -> 49 | AD70: ='HSE-Stat'!G15 -> 49
A71: ='Quality-Stat'!$A$28:$C$28 -> Mechanical | C71: =IF('Quality-Stat'!D28="","",'Quality-Stat'!D28) -> 28 | D71: =IF('Quality-Stat'!E28="","",'Quality-Stat'!E28) -> 28 | E71: =IF('Quality-Stat'!F28="","",'Quality-Stat'!F28) -> 0 | F71: =IF('Quality-Stat'!G28="","",'Quality-Stat'!G28) | G71: =IF('Quality-Stat'!H28="","",'Quality-Stat'!H28) | H71: =IF('Quality-Stat'!I28="","",'Quality-Stat'!I28) -> 28 | I71: =IF('Quality-Stat'!J28="","",'Quality-Stat'!J28) -> 0 | J71: =IF('Quality-Stat'!K28="","",'Quality-Stat'!K28) -> 0 | K71: =IF('Quality-Stat'!L28="","",'Quality-Stat'!L28) -> 28 | L71: Total Submitted Invoices | N71: ='Invoice Log'!U3 -> 6 | O71: Submitted Invoices (SAR) | R71: ='Invoice Log'!Y3 -> 7935744 | T71: Contract Value (SR) | U71: =O4 -> 9554134 | X71: ='[35]HSE-Stat'!B16 -> No.of Internal Training | Z71: ='HSE-Stat'!D16 -> 0 | AB71: ='HSE-Stat'!E16 -> 0 | AC71: ='HSE-Stat'!F16 -> 4 | AD71: ='HSE-Stat'!G16 -> 4
A72: ='Quality-Stat'!$A$29:$C$29 -> Electrical | C72: =IF('Quality-Stat'!D29="","",'Quality-Stat'!D29) -> 22 | D72: =IF('Quality-Stat'!E29="","",'Quality-Stat'!E29) -> 22 | E72: =IF('Quality-Stat'!F29="","",'Quality-Stat'!F29) -> 0 | F72: =IF('Quality-Stat'!G29="","",'Quality-Stat'!G29) | G72: =IF('Quality-Stat'!H29="","",'Quality-Stat'!H29) | H72: =IF('Quality-Stat'!I29="","",'Quality-Stat'!I29) -> 22 | I72: =IF('Quality-Stat'!J29="","",'Quality-Stat'!J29) -> 0 | J72: =IF('Quality-Stat'!K29="","",'Quality-Stat'!K29) -> 0 | K72: =IF('Quality-Stat'!L29="","",'Quality-Stat'!L29) -> 22 | L72: PM Approved Invoices | N72: ='Invoice Log'!U5 -> 6 | O72: PM Approved Invoices (SAR) | R72: ='Invoice Log'!Y5 -> 7935744 | T72: Planned Value (SR) | U72: =H27 -> 7183281 | X72: ='[35]HSE-Stat'!B17 -> No.of Internal Audit | Z72: ='HSE-Stat'!D17 -> 0 | AB72: ='HSE-Stat'!E17 -> 0 | AC72: ='HSE-Stat'!F17 -> 1 | AD72: ='HSE-Stat'!G17 -> 1
A73: TOTAL | C73: =SUM(C68:C72) -> 95 | D73: =SUM(D68:D72) -> 95 | E73: =SUM(E68:E72) -> 0 | F73: =SUM(F68:F72) -> 0 | G73: =SUM(G68:G72) -> 0 | H73: =SUM(H68:H72) -> 95 | I73: =SUM(I68:I72) -> 0 | J73: =SUM(J68:J72) -> 0 | K73: =SUM(K68:K72) -> 95 | L73: No of Paid Invoices | N73: ='Invoice Log'!U6 -> 4 | O73: Paid Invoices (SAR) | R73: ='Invoice Log'!Y6 -> 4460610 | T73: Earned Value (SR) | U73: =I27 -> 9262515 | X73: ='[35]HSE-Stat'!B18 -> No. of Toolbox Talks | Z73: ='HSE-Stat'!D18 -> 1 | AB73: ='HSE-Stat'!E18 -> 2 | AC73: ='HSE-Stat'!F18 -> 27 | AD73: ='HSE-Stat'!G18 -> 27
A74: Procurement Summary | L74: No of Pending Invoices | N74: =N72-N73 -> 2 | O74: Last Submitted Period | R74: ='Invoice Log'!AB3 -> 46295 | T74: Submitted (SAR) | U74: =R71 -> 7935744 | X74: ='[35]HSE-Stat'!B19 -> Safety Awards/Incentives | Z74: ='HSE-Stat'!D19 -> 1 | AB74: ='HSE-Stat'!E19 -> 1 | AC74: ='HSE-Stat'!F19 -> 3 | AD74: ='HSE-Stat'!G19 -> 3
A75: Item Per WBS | C75: Total Materials | D75: Total Number of P.O. | E75: Actual P.O. To Date | F75: Remaining P.O | G75: Material on Site | H75: Remaining Materials | I75: Material Delivery Completion (Date) | L75: Advance Payment % | N75: ='Invoice Log'!M3 -> 0 | O75: Advance Payment (SAR) | R75: ='Invoice Log'!Q3 -> 0 | T75: PM Approved (SAR) | U75: =R72 -> 7935744 | W75: Latest Contract Change Order Log
D76: A | E76: B | F76: C | G76: D | H76: Processed | L76: Retention % | N76: ='Invoice Log'!M4 -> 0 | O76: Retention (SAR) | R76: ='Invoice Log'!Q4 -> 0 | T76: Total Paid (SAR) | U76: =R73 -> 4460610
A77: ='Quality-Stat'!$A$35 -> Earthworks | C77: =IF('Quality-Stat'!D35="","",'Quality-Stat'!D35) -> 8 | D77: =IF('Quality-Stat'!E35="","",'Quality-Stat'!E35) -> 8 | E77: =IF('Quality-Stat'!F35="","",'Quality-Stat'!F35) -> 8 | F77: =IF('Quality-Stat'!G35="","",'Quality-Stat'!G35) -> 0 | G77: =IF('Quality-Stat'!H35="","",'Quality-Stat'!H35) -> 8 | H77: =IF('Quality-Stat'!I35="","",'Quality-Stat'!I35) -> 0 | I77: ='Quality-Stat'!J35 -> 46270 | L77: Deduction / Penalties % | N77: ='Invoice Log'!M5 -> 0.0020933347 | O77: Deduction / Penalties (SAR) | R77: ='Invoice Log'!M6 -> -20000 | W77: CCO No. | X77: Date Added | Y77: Description of Change | AD77: Status | AE77: Cost | AF77: Sch Impact (Months) | AG77: Date Approved | AH77: Duration
A78: ='Quality-Stat'!$A$36 -> Structural | C78: =IF('Quality-Stat'!D36="","",'Quality-Stat'!D36) -> 14 | D78: =IF('Quality-Stat'!E36="","",'Quality-Stat'!E36) -> 14 | E78: =IF('Quality-Stat'!F36="","",'Quality-Stat'!F36) -> 14 | F78: =IF('Quality-Stat'!G36="","",'Quality-Stat'!G36) -> 0 | G78: =IF('Quality-Stat'!H36="","",'Quality-Stat'!H36) -> 14 | H78: =IF('Quality-Stat'!I36="","",'Quality-Stat'!I36) -> 0 | I78: ='Quality-Stat'!J36 -> 46228 | L78: Resources at Site
A79: ='Quality-Stat'!$A$37 -> Architectural | C79: =IF('Quality-Stat'!D37="","",'Quality-Stat'!D37) -> 23 | D79: =IF('Quality-Stat'!E37="","",'Quality-Stat'!E37) -> 23 | E79: =IF('Quality-Stat'!F37="","",'Quality-Stat'!F37) -> 23 | F79: =IF('Quality-Stat'!G37="","",'Quality-Stat'!G37) -> 0 | G79: =IF('Quality-Stat'!H37="","",'Quality-Stat'!H37) -> 23 | H79: =IF('Quality-Stat'!I37="","",'Quality-Stat'!I37) -> 0 | I79: ='Quality-Stat'!J37 -> 46270 | L79: Head Count - Non Manual | P79: Head Count - Manual | T79: Total Head Count | W79: =CCO!A3 -> 0 | X79: =CCO!B3 -> 0 | Y79: =CCO!C3 -> 0 | AD79: =CCO!D3 -> 0 | AE79: =CCO!E3 -> 0 | AF79: =CCO!F3 -> 0 | AG79: =CCO!G3 -> 0 | AH79: =CCO!H3 -> 0
A80: ='Quality-Stat'!$A$38:$C$38 -> Mechanical | C80: =IF('Quality-Stat'!D38="","",'Quality-Stat'!D38) -> 28 | D80: =IF('Quality-Stat'!E38="","",'Quality-Stat'!E38) -> 28 | E80: =IF('Quality-Stat'!F38="","",'Quality-Stat'!F38) -> 28 | F80: =IF('Quality-Stat'!G38="","",'Quality-Stat'!G38) -> 0 | G80: =IF('Quality-Stat'!H38="","",'Quality-Stat'!H38) -> 28 | H80: =IF('Quality-Stat'!I38="","",'Quality-Stat'!I38) -> 0 | I80: ='Quality-Stat'!J38 -> 46274 | L80: Planned | M80: Actual | N80: Next Month Forecast | O80: Saudi Staff | P80: Planned | Q80: Actual | R80: Next Month Forecast | S80: Saudi Staff | T80: Total Plan | U80: Total Actual | V80: Variance
A81: ='Quality-Stat'!$A$39:$C$39 -> Electrical | C81: =IF('Quality-Stat'!D39="","",'Quality-Stat'!D39) -> 22 | D81: =IF('Quality-Stat'!E39="","",'Quality-Stat'!E39) -> 22 | E81: =IF('Quality-Stat'!F39="","",'Quality-Stat'!F39) -> 22 | F81: =IF('Quality-Stat'!G39="","",'Quality-Stat'!G39) -> 0 | G81: =IF('Quality-Stat'!H39="","",'Quality-Stat'!H39) -> 22 | H81: =IF('Quality-Stat'!I39="","",'Quality-Stat'!I39) -> 0 | I81: ='Quality-Stat'!J39 -> 46233 | L81: =Manpower!A20 -> 13 | M81: 14 | N81: =Manpower!F20 -> 13 | O81: 0 | P81: =M91 -> 119 | Q81: =N91 -> 21 | R81: 56 | S81: 0 | T81: =L81+P81 -> 132 | U81: =M81+Q81 -> 35 | V81: =+U81-T81 -> -97 | W81: =CCO!A4 | X81: =CCO!B4 -> 0 | Y81: =CCO!C4 -> 0 | AD81: =IF(CCO!D4="","",CCO!D4) | AE81: =CCO!E4 -> 0 | AF81: =CCO!F4 -> 0 | AG81: =CCO!G4 -> 0 | AH81: =CCO!H4 -> 0
A82: TOTAL | C82: =IF('Quality-Stat'!D40="","",'Quality-Stat'!D40) -> 95 | D82: =IF('Quality-Stat'!E40="","",'Quality-Stat'!E40) -> 95 | E82: =IF('Quality-Stat'!F40="","",'Quality-Stat'!F40) -> 95 | F82: =IF('Quality-Stat'!G40="","",'Quality-Stat'!G40) -> 0 | G82: =IF('Quality-Stat'!H40="","",'Quality-Stat'!H40) -> 95 | H82: =IF('Quality-Stat'!I40="","",'Quality-Stat'!I40) -> 0 | I82: =MAX(I77:I81) -> 46274 | L82: Manpower Breakdown by Trade | S82: Major Equipment
A83: =Schedule!A1 -> Primavera P6 Schedule Status | L83: Key Trade | M83: Planned | N83: Actual | S83: Type | T83: Planned | U83: Actual | V83: Idle | W83: =CCO!A5 | X83: =CCO!B5 -> 0 | Y83: =CCO!C5 -> 0 | AD83: =IF(CCO!D5="","",CCO!D5) | AE83: =CCO!E5 -> 0 | AF83: =CCO!F5 -> 0 | AG83: =CCO!G5 -> 0 | AH83: =CCO!H5 -> 0
A84: =Schedule!A2 -> Project Activities Overview | L84: =+Manpower!N23 -> General Labor | M84: =Manpower!N24 -> 10 | N84: =Manpower!N25 -> 5 | S84: =+Manpower!$B$49 -> Excavator | T84: =+Manpower!B50 -> 2 | U84: =+Manpower!B51 -> 0 | V84: =+Manpower!B52 -> 0
A85: =Schedule!A3 -> Schedule Statistics | F85: =Schedule!F3 -> Active Schedule Activities | L85: =+Manpower!P23 -> Carpenter | M85: =+Manpower!P24 -> 4 | N85: =+Manpower!P25 -> 0 | S85: =+Manpower!$D$49 -> Grader | T85: =+Manpower!D50 -> 0 | U85: =+Manpower!D51 -> 0 | V85: =+Manpower!D52 -> 0 | W85: Major Quantity Trackers
A86: =Schedule!A4 -> Total Act. | B86: =Schedule!B4 -> Not Started | C86: =Schedule!C4 -> In Progress | D86: =Schedule!D4 -> Completed | E86: =Schedule!E4 -> % | F86: =Schedule!F4 -> Active | G86: =Schedule!G4 -> Ahead | H86: =Schedule!H4 -> On | ... K86: =Schedule!K4 -> 0 | L86: =+Manpower!R23 -> Steel Fixer | M86: =+Manpower!R24 -> 5 | N86: =+Manpower!R25 -> 0 | S86: =+Manpower!$F$49 -> Loader | T86: =+Manpower!F50 -> 1 | U86: =+Manpower!F51 -> 1 | V86: =+Manpower!F52 -> 0 | W86: BOQ N0. | X86: Item Description | AC86: Total Qty | AD86: Measu Unit | AE86: Plan to Date | AF86: Act to Date | AG86: Remaining | AH86: Variance
A87: =Schedule!A5 -> 1462 | B87: =Schedule!B5 -> 22 | C87: =Schedule!C5 -> 30 | D87: =Schedule!D5 -> 1410 | E87: =Schedule!E5 -> 0.96443228 | F87: =Schedule!F5 -> 30 | G87: =Schedule!G5 -> 0 | H87: =Schedule!H5 -> 30 | ... J87: =Schedule!J5 -> 30 | L87: =+Manpower!T23 -> Concreting Labor | M87: =+Manpower!T24 -> 2 | N87: =+Manpower!T25 -> 0 | S87: =+Manpower!$H$49 -> Skid Loader | T87: =+Manpower!H50 -> 4 | U87: =+Manpower!H51 -> 1 | V87: =+Manpower!H52 -> 0 | W87: ='Major Quantities'!A2 -> 2.1.6 | X87: ='Major Quantities'!B2 -> Backfill Material | AC87: ='Major Quantities'!C2 -> 2615 | AD87: ='Major Quantities'!D2 -> m3 | AE87: ='Major Quantities'!E2 -> 2615 | AF87: ='Major Quantities'!F2 -> 2615 | AG87: ='Major Quantities'!G2 -> 0 | AH87: ='Major Quantities'!H2 -> 0
A88: =Schedule!A6 -> Critical Path Activities | D88: =Schedule!D6 -> Free Float Management (Total) | H88: =Schedule!H6 -> Failed Start Activities | L88: =+Manpower!V23 -> Mason | M88: =+Manpower!V24 -> 6 | N88: =+Manpower!V25 -> 0 | S88: =+Manpower!$J$49 -> Dump Truck | T88: =+Manpower!J50 -> 3 | U88: =+Manpower!J51 -> 0 | V88: =+Manpower!J52 -> 0 | W88: ='Major Quantities'!A3 -> 2.2.1 | X88: ='Major Quantities'!B3 -> Bituminous wearing course asphalt layer | AC88: ='Major Quantities'!C3 -> 217 | AD88: ='Major Quantities'!D3 -> m3 | AE88: ='Major Quantities'!E3 -> 0 | AF88: ='Major Quantities'!F3 -> 217 | AG88: ='Major Quantities'!G3 -> 0 | AH88: ='Major Quantities'!H3 -> 217
D89: =Schedule!D7 -> Greater Than 14 Days | F89: =Schedule!F7 -> Less Than 14 Days | L89: =+Manpower!X23 -> Operator | M89: =+Manpower!X24 -> 15 | N89: =+Manpower!X25 -> 3 | S89: =+Manpower!$L$49 -> Water Tank Truck | T89: =+Manpower!L50 -> 2 | U89: =+Manpower!L51 -> 1 | V89: =+Manpower!L52 -> 0 | W89: ='Major Quantities'!A4 -> 2.2.2 | X89: ='Major Quantities'!B4 -> Bituminous base course asphalt layer | AC89: ='Major Quantities'!C4 -> 304 | AD89: ='Major Quantities'!D4 -> m3 | AE89: ='Major Quantities'!E4 -> 0 | AF89: ='Major Quantities'!F4 -> 304 | AG89: ='Major Quantities'!G4 -> 0 | AH89: ='Major Quantities'!H4 -> 304
A90: =Schedule!A8 -> Last Week | B90: =Schedule!B8 -> This Week | C90: =Schedule!C8 -> Diff | D90: =Schedule!D8 -> Last Week | E90: =Schedule!E8 -> This Week | F90: =Schedule!F8 -> Last Week | G90: =Schedule!G8 -> This Week | H90: =Schedule!H8 -> Last Week | ... K90: =Schedule!K8 -> 0 | L90: =+Manpower!Z23 -> Others | M90: =+Manpower!Z24 -> 77 | N90: =+Manpower!Z25 -> 13 | S90: =+Manpower!$N$49 -> Other | T90: =+Manpower!N50 -> 22 | U90: =+Manpower!N51 -> 5 | V90: =+Manpower!N52 -> 0 | W90: ='Major Quantities'!A5 -> 2.2.3 | X90: ='Major Quantities'!B5 -> Base course layer | AC90: ='Major Quantities'!C5 -> 867 | AD90: ='Major Quantities'!D5 -> m3 | AE90: ='Major Quantities'!E5 -> 57.8289 | AF90: ='Major Quantities'!F5 -> 867 | AG90: ='Major Quantities'!G5 -> 0 | AH90: ='Major Quantities'!H5 -> 809.1711
A91: =Schedule!A9 -> 0 | B91: =Schedule!B9 -> 0 | C91: =Schedule!C9 -> 0 | D91: =Schedule!D9 -> 2 | E91: =Schedule!E9 -> 2 | F91: =Schedule!F9 -> 2 | G91: =Schedule!G9 -> 2 | H91: =Schedule!H9 -> 13 | ... J91: =Schedule!J9 -> 4 | L91: Total | M91: =SUM(M84:M90) -> 119 | N91: =SUM(N84:N90) -> 21 | S91: Total | T91: =SUM(T84:T90) -> 34 | U91: =SUM(U84:U90) -> 8 | V91: =SUM(V84:V90) -> 0 | W91: ='Major Quantities'!A6 -> 2.2.4 | X91: ='Major Quantities'!B6 -> Subgrade material | AC91: ='Major Quantities'!C6 -> 1300 | AD91: ='Major Quantities'!D6 -> m3 | AE91: ='Major Quantities'!E6 -> 1300 | AF91: ='Major Quantities'!F6 -> 1300 | AG91: ='Major Quantities'!G6 -> 0 | AH91: ='Major Quantities'!H6 -> 0
A92: Weekly Prgoress Photos | Q92: Top Issues and Risks
A94: Refer to the Weekly Photo Sheet | Q94: Issue No | R94: Date Identified | S94: Issue Description | W94: Responsible | X94: Action Taken | AA94: Mitigation | AF94: Current Status | AG94: Expected/Actual Closure | AH94: Duration Elapsed
Q95: =IF(+Issues!B11="","",+Issues!B11) -> 1 | R95: =IF(+Issues!C11="","",+Issues!C11) | S95: =IF(+Issues!D11="","",+Issues!D11) | W95: =IF(+Issues!E11="","",+Issues!E11) | X95: =IF(+Issues!F11="","",+Issues!F11) | AF95: =IF(+Issues!H11="","",+Issues!H11) | AG95: =IF(+Issues!I11="","",+Issues!I11) | AH95: =IF(+Issues!J11="","",+Issues!J11) -> 46308
Q96: =IF(+Issues!B12="","",+Issues!B12) -> 2 | R96: =IF(+Issues!C12="","",+Issues!C12) | S96: =IF(+Issues!D12="","",+Issues!D12) | W96: =IF(+Issues!E12="","",+Issues!E12) | X96: =IF(+Issues!F12="","",+Issues!F12) | AF96: =IF(+Issues!H12="","",+Issues!H12) | AG96: =IF(+Issues!I12="","",+Issues!I12) | AH96: =IF(+Issues!J12="","",+Issues!J12) -> 46308
Q97: =IF(+Issues!B13="","",+Issues!B13) -> 3 | R97: =IF(+Issues!C13="","",+Issues!C13) | S97: =IF(+Issues!D13="","",+Issues!D13) | W97: =IF(+Issues!E13="","",+Issues!E13) | X97: =IF(+Issues!F13="","",+Issues!F13) | AF97: =IF(+Issues!H13="","",+Issues!H13) | AG97: =IF(+Issues!I13="","",+Issues!I13) | AH97: =IF(+Issues!J13="","",+Issues!J13) -> 46308
Q98: =IF(+Issues!B14="","",+Issues!B14) -> 4 | R98: =IF(+Issues!C14="","",+Issues!C14) | S98: =IF(+Issues!D14="","",+Issues!D14) | W98: =IF(+Issues!E14="","",+Issues!E14) | X98: =IF(+Issues!F14="","",+Issues!F14) | AF98: =IF(+Issues!H14="","",+Issues!H14) | AG98: =IF(+Issues!I14="","",+Issues!I14) | AH98: =IF(+Issues!J14="","",+Issues!J14) -> 46308
Q99: =IF(+Issues!B15="","",+Issues!B15) -> 5 | R99: =IF(+Issues!C15="","",+Issues!C15) | S99: =IF(+Issues!D15="","",+Issues!D15) | W99: =IF(+Issues!E15="","",+Issues!E15) | X99: =IF(+Issues!F15="","",+Issues!F15) | AF99: =IF(+Issues!H15="","",+Issues!H15) | AG99: =IF(+Issues!I15="","",+Issues!I15) | AH99: =IF(+Issues!J15="","",+Issues!J15) -> 46308

Sheet General Information
A1: Weekly Progress Report - Construction Projects | K1: Data Date | L1: 46308
A2: Contract General Information
A3: Project Name | C3: Construction of Industrial Units for Artisans in Najran
A4: Project ID | C4: NJR1-05-005
A5: Contractor | C5: Labenat Al Bena
A6: Consultant | C6: EGIS
A7: Stage | C7: Construction
A8: Status | C8: Active
A9: Modon PM | C9: Eng. Ahmed Kotbi
A11: Key Dates
A12: Contract Award Date | C12: =Milestones!C4 -> 46047
A13: Contract Sign Date | C13: =Milestones!C5 -> 46065
A14: Site Handover Date | C14: =Milestones!C6 -> 46084
A15: Original Completion | C15: =Milestones!C15 -> 46389
A16: Contract Award Date (Hijri) | C16: =C12 -> 46047
A17: Contract Sign Date (Hijri) | C17: =C13 -> 46065
A18: Site Handover Date (Hijri) | C18: =C14 -> 46084
A19: Original Completion (Hijri) | C19: =C15 -> 46389
A20: Revised Completion Date | C20: =Milestones!D15 -> 46389
A21: Committed Completion Date | C21: =Milestones!E15 -> 46310
A22: Forecast Completion | C22: =Milestones!E15 -> 46310
A23: Variance | C23: =C20-C22 -> 79
A25: Key Project Submittals | C25: Submission Date | D25: Days taken to approve orginal plan from site handover date
A26: Quality Plan submission | C26: 46128 | D26: =C26-C14 -> 44
A27: Quality Plan approval | C27: 46134
A28: Quality Plan Last Update | C28: 46134
A30: Safety Plan submission | C30: 46117 | D30: =C30-C14 -> 33
A31: Safety Plan approval | C31: 46130
A32: Safety Plan Last Update | C32: 46130
A34: Risk Management Plan submission | C34: 46155 | D34: =C34-C14 -> 71
A35: Risk Management Plan approval | C35: 46167
A36: Risk Management Plan Last Update | C36: 46167
A38: Baseline Schedule submission | C38: 46113 | D38: =C38-C14 -> 29
A39: Baseline Schedule approval | C39: 46113
A40: No of Schedule Versions | C40: 0
A41: Last Recovery Schedule Approval Date | C41: 46113
A43: BOQ submission | C43: =C14 -> 46084 | D43: =C43-C19 -> -305
A44: BOQ approval | C44: N/A | E44: There is one revision of BOQ submitted
A45: No of Approved Version of BOQ | C45: 0
A47: Construction Plan submission | C47: 46114 | D47: =C47-C14 -> 30
A48: Construction Plan Approval | C48: 46114

Sheet PV-PH
E4: Tuesday | F4: Tuesday | G4: Tuesday | H4: Tuesday | I4: Tuesday | J4: Tuesday | K4: Tuesday | L4: Tuesday | M4: Tuesday | N4: Tuesday | O4: Tuesday | P4: Tuesday | Q4: Tuesday | R4: Tuesday | S4: Tuesday | T4: Tuesday | U4: Tuesday | V4: Tuesday | W4: Tuesday | X4: Tuesday | Y4: Tuesday | Z4: Tuesday | AA4: Tuesday | AB4: Tuesday | AC4: Tuesday | AD4: Tuesday | AE4: Tuesday | AF4: Tuesday | AG4: Tuesday | AH4: Tuesday | AI4: Tuesday | AJ4: Tuesday | AK4: Tuesday | AL4: Tuesday | AM4: Tuesday | AN4: Tuesday | AO4: Tuesday | AP4: Tuesday | AQ4: Tuesday | AR4: Tuesday | AS4: Tuesday | AT4: Tuesday | AU4: Tuesday | AV4: Tuesday | AW4: Tuesday | AX4: Tuesday | AY4: Tuesday | AZ4: Tuesday | BA4: Tuesday | BB4: Tuesday | BC4: Tuesday | BD4: Tuesday
E5: =E6 -> 45300 | F5: =F6 -> 45307 | G5: =G6 -> 45314 | H5: =H6 -> 45321 | I5: =I6 -> 45328 | J5: =J6 -> 45335 | K5: =K6 -> 45342 | L5: =L6 -> 45349 | ... BD5: =BD6 -> 45657
B6: Activity ID | C6: Budgeted Units | D6: Spreadsheet Field | E6: 45300 | F6: 45307 | G6: 45314 | H6: 45321 | I6: 45328 | J6: 45335 | K6: 45342 | L6: 45349 | M6: 45356 | N6: 45363 | O6: 45370 | P6: 45377 | Q6: 45384 | R6: 45391 | S6: 45398 | T6: 45405 | U6: 45412 | V6: 45419 | W6: 45426 | X6: 45433 | Y6: 45440 | Z6: 45447 | AA6: 45454 | AB6: 45461 | AC6: 45468 | AD6: 45475 | AE6: 45482 | AF6: 45489 | AG6: 45496 | AH6: 45503 | AI6: 45510 | AJ6: 45517 | AK6: 45524 | AL6: 45531 | AM6: 45538 | AN6: 45545 | AO6: 45552 | AP6: 45559 | AQ6: 45566 | AR6: 45573 | AS6: 45580 | AT6: 45587 | AU6: 45594 | AV6: 45601 | AW6: 45608 | AX6: 45615 | AY6: 45622 | AZ6: 45629 | BA6: 45636 | BB6: 45643 | BC6: 45650 | BD6: 45657
B7: Project: HAL1-05-1 Civil Defense Fire Station in Hail Industrial City | C7: 220460.02 | D7: Budgeted Units | E7: =E8 -> 255.34 | F7: =F8-E8 -> 533.36 | G7: =G8-F8 -> 831.16 | H7: =H8-G8 -> 2077.87 | I7: =I8-H8 -> 2245.69 | J7: =J8-I8 -> 1087.72 | K7: =K8-J8 -> 1210.9 | L7: =L8-K8 -> 888.95 | M7: =M8-L8 -> 1077.11 | ... BD7: =BD8-BC8 -> 4056.33
B8: Project: HAL1-05-1 Civil Defense Fire Station in Hail Industrial City | C8: 220460.02 | D8: Cum Budgeted Units | E8: 255.34 | F8: 788.7 | G8: 1619.86 | H8: 3697.73 | I8: 5943.42 | J8: 7031.14 | K8: 8242.04 | L8: 9130.99 | M8: 10208.1 | N8: 11381.53 | O8: 12793.76 | P8: 14373.94 | Q8: 16376.73 | R8: 17684.7 | S8: 18685.95 | T8: 20449.72 | U8: 22408.53 | V8: 26223.73 | W8: 30933.46 | X8: 35121.81 | Y8: 39534.02 | Z8: 44758.71 | AA8: 49842.92 | AB8: 51760.8 | AC8: 59081.04 | AD8: 63023.99 | AE8: 67887.31 | AF8: 73180.87 | AG8: 81643.94 | AH8: 99223.69 | AI8: 118314.53 | AJ8: 128622.04 | AK8: 133738.93 | AL8: 137361.8 | AM8: 139381.34 | AN8: 142958.41 | AO8: 147374.26 | AP8: 152520 | AQ8: 161471.54 | AR8: 168527.25 | AS8: 172440.36 | AT8: 180991.98 | AU8: 187776.76 | AV8: 197084.19 | AW8: 201472.02 | AX8: 208589.52 | AY8: 209414.52 | AZ8: 209672.02 | BA8: 210165.22 | BB8: 210650.82 | BC8: 211705.36 | BD8: 215761.69
B9: WBS: HAL1-05-1.2 MOBILIZATION | C9: 3445.8 | D9: Budgeted Units | E9: =E10 -> 147.78 | F9: =F10-E10 -> 295.56 | G9: =G10-F10 -> 511.56 | H9: =H10-G10 -> 1259.34 | I9: =I10-H10 -> 1231.56 | J9: =J10-I10 -> 0 | K9: =K10-J10 -> 0 | L9: =L10-K10 -> 0 | M9: =M10-L10 -> 0 | ... BD9: =BD10-BC10 -> 0
B10: WBS: HAL1-05-1.2 MOBILIZATION | C10: 3445.8 | D10: Cum Budgeted Units | E10: 147.78 | F10: 443.34 | G10: 954.9 | H10: 2214.24 | I10: 3445.8 | J10: 3445.8 | K10: 3445.8 | L10: 3445.8 | M10: 3445.8 | N10: 3445.8 | O10: 3445.8 | P10: 3445.8 | Q10: 3445.8 | R10: 3445.8 | S10: 3445.8 | T10: 3445.8 | U10: 3445.8 | V10: 3445.8 | W10: 3445.8 | X10: 3445.8 | Y10: 3445.8 | Z10: 3445.8 | AA10: 3445.8 | AB10: 3445.8 | AC10: 3445.8 | AD10: 3445.8 | AE10: 3445.8 | AF10: 3445.8 | AG10: 3445.8 | AH10: 3445.8 | AI10: 3445.8 | AJ10: 3445.8 | AK10: 3445.8 | AL10: 3445.8 | AM10: 3445.8 | AN10: 3445.8 | AO10: 3445.8 | AP10: 3445.8 | AQ10: 3445.8 | AR10: 3445.8 | AS10: 3445.8 | AT10: 3445.8 | AU10: 3445.8 | AV10: 3445.8 | AW10: 3445.8 | AX10: 3445.8 | AY10: 3445.8 | AZ10: 3445.8 | BA10: 3445.8 | BB10: 3445.8 | BC10: 3445.8 | BD10: 3445.8
B11: WBS: HAL1-05-1.7 SITE | C11: 66611.78 | D11: Budgeted Units | E11: =E12 -> 22.08 | F11: =F12-E12 -> 46.22 | G11: =G12-F12 -> 55.61 | H11: =H12-G12 -> 163.79 | I11: =I12-H12 -> 240.88 | J11: =J12-I12 -> 350.73 | K11: =K12-J12 -> 366.06 | L11: =L12-K12 -> 157.13 | M11: =M12-L12 -> 268.48 | ... BD11: =BD12-BC12 -> 0
B12: WBS: HAL1-05-1.7 SITE | C12: 66611.78 | D12: Cum Budgeted Units | E12: 22.08 | F12: 68.3 | G12: 123.91 | H12: 287.7 | I12: 528.58 | J12: 879.31 | K12: 1245.37 | L12: 1402.5 | M12: 1670.98 | N12: 1878.94 | O12: 1932.17 | P12: 1935.95 | Q12: 2076.79 | R12: 2172.1 | S12: 2284.56 | T12: 2558.02 | U12: 3091.03 | V12: 4406.94 | W12: 6292.79 | X12: 8347.05 | Y12: 9983.23 | Z12: 11275.75 | AA12: 12225.03 | AB12: 12552.93 | AC12: 13681.42 | AD12: 14996.13 | AE12: 16434.3 | AF12: 17785.21 | AG12: 19054.07 | AH12: 28098.78 | AI12: 37613.83 | AJ12: 41436.65 | AK12: 41936.91 | AL12: 42693.59 | AM12: 43386.61 | AN12: 44314.27 | AO12: 45261.28 | AP12: 45706.33 | AQ12: 46519.29 | AR12: 47168.38 | AS12: 47897.78 | AT12: 50434.06 | AU12: 51791.35 | AV12: 56267.61 | AW12: 59290.78 | AX12: 65081.78 | AY12: 65081.78 | AZ12: 65201.78 | BA12: 65694.98 | BB12: 66180.58 | BC12: 66611.78 | BD12: 66611.78
B13: WBS: HAL1-05-1.7.1 Engineering | C13: 1607.2 | D13: Budgeted Units | E13: =E14 -> 22.08 | F13: =F14-E14 -> 46.22 | G13: =G14-F14 -> 55.61 | H13: =H14-G14 -> 163.79 | I13: =I14-H14 -> 240.88 | J13: =J14-I14 -> 229.01 | K13: =K14-J14 -> 244.35 | L13: =L14-K14 -> 116.56 | M13: =M14-L14 -> 241.48 | ... BD13: =BD14-BC14 -> 0
B14: WBS: HAL1-05-1.7.1 Engineering | C14: 1607.2 | D14: Cum Budgeted Units | E14: 22.08 | F14: 68.3 | G14: 123.91 | H14: 287.7 | I14: 528.58 | J14: 757.59 | K14: 1001.94 | L14: 1118.5 | M14: 1359.98 | N14: 1540.95 | O14: 1582.66 | P14: 1582.66 | Q14: 1592.88 | R14: 1601.06 | S14: 1604.74 | T14: 1607.2 | U14: 1607.2 | V14: 1607.2 | W14: 1607.2 | X14: 1607.2 | Y14: 1607.2 | Z14: 1607.2 | AA14: 1607.2 | AB14: 1607.2 | AC14: 1607.2 | AD14: 1607.2 | AE14: 1607.2 | AF14: 1607.2 | AG14: 1607.2 | AH14: 1607.2 | AI14: 1607.2 | AJ14: 1607.2 | AK14: 1607.2 | AL14: 1607.2 | AM14: 1607.2 | AN14: 1607.2 | AO14: 1607.2 | AP14: 1607.2 | AQ14: 1607.2 | AR14: 1607.2 | AS14: 1607.2 | AT14: 1607.2 | AU14: 1607.2 | AV14: 1607.2 | AW14: 1607.2 | AX14: 1607.2 | AY14: 1607.2 | AZ14: 1607.2 | BA14: 1607.2 | BB14: 1607.2 | BC14: 1607.2 | BD14: 1607.2
B15: WBS: HAL1-05-1.7.2 Procurement | C15: 7653.58 | D15: Budgeted Units | E15: =E16 -> 0 | F15: =F16-E16 -> 0 | G15: =G16-F16 -> 0 | H15: =H16-G16 -> 0 | I15: =I16-H16 -> 0 | J15: =J16-I16 -> 0 | K15: =K16-J16 -> 0 | L15: =L16-K16 -> 0 | M15: =M16-L16 -> 27 | ... BD15: =BD16-BC16 -> 0
B16: WBS: HAL1-05-1.7.2 Procurement | C16: 7653.58 | D16: Cum Budgeted Units | M16: 27 | N16: 53.99 | O16: 65.51 | P16: 69.29 | Q16: 199.91 | R16: 287.04 | S16: 322.48 | T16: 373.49 | U16: 409.83 | V16: 459.74 | W16: 527.93 | X16: 659.18 | Y16: 703.7 | Z16: 777.89 | AA16: 824.67 | AB16: 851.4 | AC16: 978.39 | AD16: 1177.8 | AE16: 1308.55 | AF16: 1449.79 | AG16: 1711.98 | AH16: 1777.5 | AI16: 1794.3 | AJ16: 2430.12 | AK16: 2436.38 | AL16: 2456.39 | AM16: 2496.41 | AN16: 2512.07 | AO16: 2619.08 | AP16: 2632.13 | AQ16: 2965.09 | AR16: 3134.18 | AS16: 3143.58 | AT16: 4911.87 | AU16: 5126.15 | AV16: 7653.58 | AW16: 7653.58 | AX16: 7653.58 | AY16: 7653.58 | AZ16: 7653.58 | BA16: 7653.58 | BB16: 7653.58 | BC16: 7653.58 | BD16: 7653.58
B17: WBS: HAL1-05-1.7.3 Construction | C17: 57351 | D17: Budgeted Units | E17: =E18 -> 0 | F17: =F18-E18 -> 0 | G17: =G18-F18 -> 0 | H17: =H18-G18 -> 0 | I17: =I18-H18 -> 0 | J17: =J18-I18 -> 121.71 | K17: =K18-J18 -> 121.72 | L17: =L18-K18 -> 40.57 | M17: =M18-L18 -> 0 | ... BD17: =BD18-BC18 -> 0
B18: WBS: HAL1-05-1.7.3 Construction | C18: 57351 | D18: Cum Budgeted Units | J18: 121.71 | K18: 243.43 | L18: 284 | M18: 284 | N18: 284 | O18: 284 | P18: 284 | Q18: 284 | R18: 284 | S18: 357.33 | T18: 577.33 | U18: 1074 | V18: 2340 | W18: 4157.67 | X18: 6080.67 | Y18: 7672.33 | Z18: 8890.67 | AA18: 9793.17 | AB18: 10094.33 | AC18: 11095.83 | AD18: 12211.13 | AE18: 13518.56 | AF18: 14728.22 | AG18: 15734.89 | AH18: 24714.08 | AI18: 34212.33 | AJ18: 37399.33 | AK18: 37893.33 | AL18: 38630 | AM18: 39283 | AN18: 40195 | AO18: 41035 | AP18: 41467 | AQ18: 41947 | AR18: 42427 | AS18: 43147 | AT18: 43915 | AU18: 45058 | AV18: 47006.83 | AW18: 50030 | AX18: 55821 | AY18: 55821 | AZ18: 55941 | BA18: 56434.2 | BB18: 56919.8 | BC18: 57351 | BD18: 57351
B19: WBS: HAL1-05-1.8 MAIN BUILDING | C19: 86348.45 | D19: Budgeted Units | E19: =E20 -> 43.76 | F19: =F20-E20 -> 106.12 | G19: =G20-F20 -> 162.97 | H19: =H20-G20 -> 403.24 | I19: =I20-H20 -> 538.92 | J19: =J20-I20 -> 523.51 | K19: =K20-J20 -> 627.47 | L19: =L20-K20 -> 570.49 | M19: =M20-L20 -> 708.78 | ... BD19: =BD20-BC20 -> 0
B20: WBS: HAL1-05-1.8 MAIN BUILDING | C20: 86348.45 | D20: Cum Budgeted Units | E20: 43.76 | F20: 149.88 | G20: 312.85 | H20: 716.09 | I20: 1255.01 | J20: 1778.52 | K20: 2405.99 | L20: 2976.48 | M20: 3685.26 | N20: 4381.79 | O20: 4910.18 | P20: 5342.23 | Q20: 5674.68 | R20: 6031.27 | S20: 6307.46 | T20: 6658.3 | U20: 7241.47 | V20: 8485.4 | W20: 9239.56 | X20: 10073.28 | Y20: 11610.58 | Z20: 14033.99 | AA20: 16345.19 | AB20: 17031.9 | AC20: 19442.03 | AD20: 20252.43 | AE20: 21318.82 | AF20: 22858.1 | AG20: 27631.5 | AH20: 34063.19 | AI20: 39051.74 | AJ20: 43859.87 | AK20: 45224.45 | AL20: 46298.39 | AM20: 47552.29 | AN20: 49890.61 | AO20: 51969.6 | AP20: 54716.65 | AQ20: 62082.85 | AR20: 67916.4 | AS20: 70520.11 | AT20: 74007.45 | AU20: 78863.61 | AV20: 82694.78 | AW20: 84059.45 | AX20: 85385.95 | AY20: 86210.95 | AZ20: 86348.45 | BA20: 86348.45 | BB20: 86348.45 | BC20: 86348.45 | BD20: 86348.45
B21: WBS: HAL1-05-1.8.1 Engineering | C21: 3103.98 | D21: Budgeted Units | E21: =E22 -> 43.76 | F21: =F22-E22 -> 106.12 | G21: =G22-F22 -> 162.97 | H21: =H22-G22 -> 376.24 | I21: =I22-H22 -> 474.59 | J21: =J22-I22 -> 456.81 | K21: =K22-J22 -> 535.94 | L21: =L22-K22 -> 358.45 | M21: =M22-L22 -> 235.35 | ... BD21: =BD22-BC22 -> 0
B22: WBS: HAL1-05-1.8.1 Engineering | C22: 3103.98 | D22: Cum Budgeted Units | E22: 43.76 | F22: 149.88 | G22: 312.85 | H22: 689.09 | I22: 1163.68 | J22: 1620.49 | K22: 2156.43 | L22: 2514.88 | M22: 2750.23 | N22: 2879.05 | O22: 2923.01 | P22: 2988.45 | Q22: 3050.81 | R22: 3091.71 | S22: 3099.07 | T22: 3103.98 | U22: 3103.98 | V22: 3103.98 | W22: 3103.98 | X22: 3103.98 | Y22: 3103.98 | Z22: 3103.98 | AA22: 3103.98 | AB22: 3103.98 | AC22: 3103.98 | AD22: 3103.98 | AE22: 3103.98 | AF22: 3103.98 | AG22: 3103.98 | AH22: 3103.98 | AI22: 3103.98 | AJ22: 3103.98 | AK22: 3103.98 | AL22: 3103.98 | AM22: 3103.98 | AN22: 3103.98 | AO22: 3103.98 | AP22: 3103.98 | AQ22: 3103.98 | AR22: 3103.98 | AS22: 3103.98 | AT22: 3103.98 | AU22: 3103.98 | AV22: 3103.98 | AW22: 3103.98 | AX22: 3103.98 | AY22: 3103.98 | AZ22: 3103.98 | BA22: 3103.98 | BB22: 3103.98 | BC22: 3103.98 | BD22: 3103.98
B23: WBS: HAL1-05-1.8.2 Procurement | C23: 11205.47 | D23: Budgeted Units | E23: =E24 -> 0 | F23: =F24-E24 -> 0 | G23: =G24-F24 -> 0 | H23: =H24-G24 -> 27 | I23: =I24-H24 -> 64.32 | J23: =J24-I24 -> 66.71 | K23: =K24-J24 -> 91.53 | L23: =L24-K24 -> 20.04 | M23: =M24-L24 -> 9.43 | ... BD23: =BD24-BC24 -> 0
B24: WBS: HAL1-05-1.8.2 Procurement | C24: 11205.47 | D24: Cum Budgeted Units | H24: 27 | I24: 91.32 | J24: 158.03 | K24: 249.56 | L24: 269.6 | M24: 279.03 | N24: 306.73 | O24: 316.17 | P24: 337.78 | Q24: 426.15 | R24: 515.56 | S24: 582.39 | T24: 664.32 | U24: 739.22 | V24: 1010.36 | W24: 1287.59 | X24: 1614.3 | Y24: 1924.6 | Z24: 2328.01 | AA24: 2619.22 | AB24: 2723.42 | AC24: 3386.05 | AD24: 3705.65 | AE24: 4252.85 | AF24: 5024.13 | AG24: 5355.53 | AH24: 5777.21 | AI24: 6123.02 | AJ24: 7153.7 | AK24: 7487.8 | AL24: 7888.42 | AM24: 8338.32 | AN24: 9745.13 | AO24: 10340.62 | AP24: 11205.47 | AQ24: 11205.47 | AR24: 11205.47 | AS24: 11205.47 | AT24: 11205.47 | AU24: 11205.47 | AV24: 11205.47 | AW24: 11205.47 | AX24: 11205.47 | AY24: 11205.47 | AZ24: 11205.47 | BA24: 11205.47 | BB24: 11205.47 | BC24: 11205.47 | BD24: 11205.47
B25: WBS: HAL1-05-1.8.3 Construction | C25: 72039 | D25: Budgeted Units | E25: =E26 -> 0 | F25: =F26-E26 -> 0 | G25: =G26-F26 -> 0 | H25: =H26-G26 -> 0 | I25: =I26-H26 -> 0 | J25: =J26-I26 -> 0 | K25: =K26-J26 -> 0 | L25: =L26-K26 -> 192 | M25: =M26-L26 -> 464 | ... BD25: =BD26-BC26 -> 0
B26: WBS: HAL1-05-1.8.3 Construction | C26: 72039 | D26: Cum Budgeted Units | L26: 192 | M26: 656 | N26: 1196 | O26: 1671 | P26: 2016 | Q26: 2197.71 | R26: 2424 | S26: 2626 | T26: 2890 | U26: 3398.27 | V26: 4371.07 | W26: 4848 | X26: 5355 | Y26: 6582 | Z26: 8602 | AA26: 10622 | AB26: 11204.5 | AC26: 12952 | AD26: 13442.8 | AE26: 13962 | AF26: 14730 | AG26: 19172 | AH26: 25182 | AI26: 29824.74 | AJ26: 33602.19 | AK26: 34632.67 | AL26: 35306 | AM26: 36110 | AN26: 37041.5 | AO26: 38525 | AP26: 40407.2 | AQ26: 47773.4 | AR26: 53606.95 | AS26: 56210.67 | AT26: 59698 | AU26: 64554.17 | AV26: 68385.33 | AW26: 69750 | AX26: 71076.5 | AY26: 71901.5 | AZ26: 72039 | BA26: 72039 | BB26: 72039 | BC26: 72039 | BD26: 72039
B27: WBS: HAL1-05-1.9 SERVICE BUILDING | C27: 19120.97 | D27: Budgeted Units | E27: =E28 -> 29.44 | F27: =F28-E28 -> 60.94 | G27: =G28-F28 -> 70.34 | H27: =H28-G28 -> 158.67 | I27: =I28-H28 -> 149.48 | J27: =J28-I28 -> 116.96 | K27: =K28-J28 -> 123.3 | L27: =L28-K28 -> 69.93 | M27: =M28-L28 -> 33.13 | ... BD27: =BD28-BC28 -> 0
B28: WBS: HAL1-05-1.9 SERVICE BUILDING | C28: 19120.97 | D28: Cum Budgeted Units | E28: 29.44 | F28: 90.38 | G28: 160.72 | H28: 319.39 | I28: 468.87 | J28: 585.83 | K28: 709.13 | L28: 779.06 | M28: 812.19 | N28: 952.27 | O28: 1276.27 | P28: 1468.27 | Q28: 1768.01 | R28: 2054.49 | S28: 2197.06 | T28: 2532.2 | U28: 2855.76 | V28: 3114.05 | W28: 3462.54 | X28: 3753.03 | Y28: 4465.77 | Z28: 4835.42 | AA28: 5403.42 | AB28: 5583 | AC28: 6684.08 | AD28: 6754.27 | AE28: 7695.34 | AF28: 8936.37 | AG28: 10498.83 | AH28: 11791.82 | AI28: 13802.77 | AJ28: 15113.97 | AK28: 16401.43 | AL28: 17303.47 | AM28: 17331.65 | AN28: 17359.84 | AO28: 17826.97 | AP28: 19120.97 | AQ28: 19120.97 | AR28: 19120.97 | AS28: 19120.97 | AT28: 19120.97 | AU28: 19120.97 | AV28: 19120.97 | AW28: 19120.97 | AX28: 19120.97 | AY28: 19120.97 | AZ28: 19120.97 | BA28: 19120.97 | BB28: 19120.97 | BC28: 19120.97 | BD28: 19120.97
B29: WBS: HAL1-05-1.9.1 Engineering | C29: 834.27 | D29: Budgeted Units | E29: =E30 -> 29.44 | F29: =F30-E30 -> 60.94 | G29: =G30-F30 -> 70.34 | H29: =H30-G30 -> 158.67 | I29: =I30-H30 -> 149.48 | J29: =J30-I30 -> 116.96 | K29: =K30-J30 -> 123.3 | L29: =L30-K30 -> 69.93 | M29: =M30-L30 -> 33.13 | ... BD29: =BD30-BC30 -> 0
B30: WBS: HAL1-05-1.9.1 Engineering | C30: 834.27 | D30: Cum Budgeted Units | E30: 29.44 | F30: 90.38 | G30: 160.72 | H30: 319.39 | I30: 468.87 | J30: 585.83 | K30: 709.13 | L30: 779.06 | M30: 812.19 | N30: 834.27 | O30: 834.27 | P30: 834.27 | Q30: 834.27 | R30: 834.27 | S30: 834.27 | T30: 834.27 | U30: 834.27 | V30: 834.27 | W30: 834.27 | X30: 834.27 | Y30: 834.27 | Z30: 834.27 | AA30: 834.27 | AB30: 834.27 | AC30: 834.27 | AD30: 834.27 | AE30: 834.27 | AF30: 834.27 | AG30: 834.27 | AH30: 834.27 | AI30: 834.27 | AJ30: 834.27 | AK30: 834.27 | AL30: 834.27 | AM30: 834.27 | AN30: 834.27 | AO30: 834.27 | AP30: 834.27 | AQ30: 834.27 | AR30: 834.27 | AS30: 834.27 | AT30: 834.27 | AU30: 834.27 | AV30: 834.27 | AW30: 834.27 | AX30: 834.27 | AY30: 834.27 | AZ30: 834.27 | BA30: 834.27 | BB30: 834.27 | BC30: 834.27 | BD30: 834.27
B31: WBS: HAL1-05-1.9.2 Procurement | C31: 2520.7 | D31: Budgeted Units | E31: =E32 -> 0 | F31: =F32-E32 -> 0 | G31: =G32-F32 -> 0 | H31: =H32-G32 -> 0 | I31: =I32-H32 -> 0 | J31: =J32-I32 -> 0 | K31: =K32-J32 -> 0 | L31: =L32-K32 -> 0 | M31: =M32-L32 -> 0 | ... BD31: =BD32-BC32 -> 0
B32: WBS: HAL1-05-1.9.2 Procurement | C32: 2520.7 | D32: Cum Budgeted Units | Q32: 53.99 | R32: 80.02 | S32: 104.39 | T32: 167.26 | U32: 222.29 | V32: 307.78 | W32: 393.27 | X32: 472.76 | Y32: 549.25 | Z32: 641.4 | AA32: 783.15 | AB32: 810.73 | AC32: 1059.81 | AD32: 1130 | AE32: 1303.07 | AF32: 1728.1 | AG32: 1930.56 | AH32: 1975.55 | AI32: 2290.5 | AJ32: 2290.5 | AK32: 2290.5 | AL32: 2295.2 | AM32: 2323.38 | AN32: 2351.57 | AO32: 2520.7 | AP32: 2520.7 | AQ32: 2520.7 | AR32: 2520.7 | AS32: 2520.7 | AT32: 2520.7 | AU32: 2520.7 | AV32: 2520.7 | AW32: 2520.7 | AX32: 2520.7 | AY32: 2520.7 | AZ32: 2520.7 | BA32: 2520.7 | BB32: 2520.7 | BC32: 2520.7 | BD32: 2520.7
B33: WBS: HAL1-05-1.9.3 Construction | C33: 15766 | D33: Budgeted Units | E33: =E34 -> 0 | F33: =F34-E34 -> 0 | G33: =G34-F34 -> 0 | H33: =H34-G34 -> 0 | I33: =I34-H34 -> 0 | J33: =J34-I34 -> 0 | K33: =K34-J34 -> 0 | L33: =L34-K34 -> 0 | M33: =M34-L34 -> 0 | ... BD33: =BD34-BC34 -> 0
B34: WBS: HAL1-05-1.9.3 Construction | C34: 15766 | D34: Cum Budgeted Units | N34: 118 | O34: 442 | P34: 634 | Q34: 879.75 | R34: 1140.2 | S34: 1258.4 | T34: 1530.67 | U34: 1799.2 | V34: 1972 | W34: 2235 | X34: 2446 | Y34: 3082.25 | Z34: 3359.75 | AA34: 3786 | AB34: 3938 | AC34: 4790 | AD34: 4790 | AE34: 5558 | AF34: 6374 | AG34: 7734 | AH34: 8982 | AI34: 10678 | AJ34: 11989.2 | AK34: 13276.67 | AL34: 14174 | AM34: 14174 | AN34: 14174 | AO34: 14472 | AP34: 15766 | AQ34: 15766 | AR34: 15766 | AS34: 15766 | AT34: 15766 | AU34: 15766 | AV34: 15766 | AW34: 15766 | AX34: 15766 | AY34: 15766 | AZ34: 15766 | BA34: 15766 | BB34: 15766 | BC34: 15766 | BD34: 15766
B35: WBS: HAL1-05-1.10 GUARD ROOM 1 | C35: 9829.32 | D35: Budgeted Units | E35: =E36 -> 6.13 | F35: =F36-E36 -> 12.27 | G35: =G36-F36 -> 12.27 | H35: =H36-G36 -> 28.22 | I35: =I36-H36 -> 28.22 | J35: =J36-I36 -> 46.62 | K35: =K36-J36 -> 44.98 | L35: =L36-K36 -> 54.4 | M35: =M36-L36 -> 29.44 | ... BD35: =BD36-BC36 -> 0
B36: WBS: HAL1-05-1.10 GUARD ROOM 1 | C36: 9829.32 | D36: Cum Budgeted Units | E36: 6.13 | F36: 18.4 | G36: 30.67 | H36: 58.89 | I36: 87.11 | J36: 133.73 | K36: 178.71 | L36: 233.11 | M36: 262.55 | N36: 310.18 | O36: 498.18 | P36: 874.18 | Q36: 1295.18 | R36: 1454.18 | S36: 1598.18 | T36: 1790.18 | U36: 2005.68 | V36: 2442.17 | W36: 3081.49 | X36: 3388.14 | Y36: 3635.61 | Z36: 4006.08 | AA36: 4438.39 | AB36: 4600.05 | AC36: 5215.03 | AD36: 5542 | AE36: 5868.98 | AF36: 6243.95 | AG36: 6450.93 | AH36: 6633.9 | AI36: 7922.83 | AJ36: 8076.81 | AK36: 9200.69 | AL36: 9572.87 | AM36: 9597.93 | AN36: 9622.98 | AO36: 9821.32 | AP36: 9829.32 | AQ36: 9829.32 | AR36: 9829.32 | AS36: 9829.32 | AT36: 9829.32 | AU36: 9829.32 | AV36: 9829.32 | AW36: 9829.32 | AX36: 9829.32 | AY36: 9829.32 | AZ36: 9829.32 | BA36: 9829.32 | BB36: 9829.32 | BC36: 9829.32 | BD36: 9829.32
B37: WBS: HAL1-05-1.10.1 Engineering | C37: 282.18 | D37: Budgeted Units | E37: =E38 -> 6.13 | F37: =F38-E38 -> 12.27 | G37: =G38-F38 -> 12.27 | H37: =H38-G38 -> 28.22 | I37: =I38-H38 -> 28.22 | J37: =J38-I38 -> 46.62 | K37: =K38-J38 -> 44.98 | L37: =L38-K38 -> 54.4 | M37: =M38-L38 -> 29.44 | ... BD37: =BD38-BC38 -> 0
B38: WBS: HAL1-05-1.10.1 Engineering | C38: 282.18 | D38: Cum Budgeted Units | E38: 6.13 | F38: 18.4 | G38: 30.67 | H38: 58.89 | I38: 87.11 | J38: 133.73 | K38: 178.71 | L38: 233.11 | M38: 262.55 | N38: 282.18 | O38: 282.18 | P38: 282.18 | Q38: 282.18 | R38: 282.18 | S38: 282.18 | T38: 282.18 | U38: 282.18 | V38: 282.18 | W38: 282.18 | X38: 282.18 | Y38: 282.18 | Z38: 282.18 | AA38: 282.18 | AB38: 282.18 | AC38: 282.18 | AD38: 282.18 | AE38: 282.18 | AF38: 282.18 | AG38: 282.18 | AH38: 282.18 | AI38: 282.18 | AJ38: 282.18 | AK38: 282.18 | AL38: 282.18 | AM38: 282.18 | AN38: 282.18 | AO38: 282.18 | AP38: 282.18 | AQ38: 282.18 | AR38: 282.18 | AS38: 282.18 | AT38: 282.18 | AU38: 282.18 | AV38: 282.18 | AW38: 282.18 | AX38: 282.18 | AY38: 282.18 | AZ38: 282.18 | BA38: 282.18 | BB38: 282.18 | BC38: 282.18 | BD38: 282.18
B39: WBS: HAL1-05-1.10.2 Procurement | C39: 2877.14 | D39: Budgeted Units | E39: =E40 -> 0 | F39: =F40-E40 -> 0 | G39: =G40-F40 -> 0 | H39: =H40-G40 -> 0 | I39: =I40-H40 -> 0 | J39: =J40-I40 -> 0 | K39: =K40-J40 -> 0 | L39: =L40-K40 -> 0 | M39: =M40-L40 -> 0 | ... BD39: =BD40-BC40 -> 0
B40: WBS: HAL1-05-1.10.2 Procurement | C40: 2877.14 | D40: Cum Budgeted Units | V40: 53.99 | W40: 107.98 | X40: 227.96 | Y40: 380.93 | Z40: 527.9 | AA40: 662.88 | AB40: 707.87 | AC40: 842.85 | AD40: 977.82 | AE40: 1112.8 | AF40: 1247.77 | AG40: 1382.75 | AH40: 1517.72 | AI40: 1922.65 | AJ40: 2012.63 | AK40: 2672.52 | AL40: 2676.69 | AM40: 2701.75 | AN40: 2726.8 | AO40: 2877.14 | AP40: 2877.14 | AQ40: 2877.14 | AR40: 2877.14 | AS40: 2877.14 | AT40: 2877.14 | AU40: 2877.14 | AV40: 2877.14 | AW40: 2877.14 | AX40: 2877.14 | AY40: 2877.14 | AZ40: 2877.14 | BA40: 2877.14 | BB40: 2877.14 | BC40: 2877.14 | BD40: 2877.14
B41: WBS: HAL1-05-1.10.3 Construction | C41: 6670 | D41: Budgeted Units | E41: =E42 -> 0 | F41: =F42-E42 -> 0 | G41: =G42-F42 -> 0 | H41: =H42-G42 -> 0 | I41: =I42-H42 -> 0 | J41: =J42-I42 -> 0 | K41: =K42-J42 -> 0 | L41: =L42-K42 -> 0 | M41: =M42-L42 -> 0 | ... BD41: =BD42-BC42 -> 0
B42: WBS: HAL1-05-1.10.3 Construction | C42: 6670 | D42: Cum Budgeted Units | N42: 28 | O42: 216 | P42: 592 | Q42: 1013 | R42: 1172 | S42: 1316 | T42: 1508 | U42: 1723.5 | V42: 2106 | W42: 2691.33 | X42: 2878 | Y42: 2972.5 | Z42: 3196 | AA42: 3493.33 | AB42: 3610 | AC42: 4090 | AD42: 4282 | AE42: 4474 | AF42: 4714 | AG42: 4786 | AH42: 4834 | AI42: 5718 | AJ42: 5782 | AK42: 6246 | AL42: 6614 | AM42: 6614 | AN42: 6614 | AO42: 6662 | AP42: 6670 | AQ42: 6670 | AR42: 6670 | AS42: 6670 | AT42: 6670 | AU42: 6670 | AV42: 6670 | AW42: 6670 | AX42: 6670 | AY42: 6670 | AZ42: 6670 | BA42: 6670 | BB42: 6670 | BC42: 6670 | BD42: 6670
B43: WBS: HAL1-05-1.11 GUARD ROOM 2 | C43: 6730.54 | D43: Budgeted Units | E43: =E44 -> 2.45 | F43: =F44-E44 -> 4.91 | G43: =G44-F44 -> 4.91 | H43: =H44-G44 -> 7.36 | I43: =I44-H44 -> 4.91 | J43: =J44-I44 -> 0 | K43: =K44-J44 -> 0 | L43: =L44-K44 -> 0 | M43: =M44-L44 -> 0 | ... BD43: =BD44-BC44 -> 0
B44: WBS: HAL1-05-1.11 GUARD ROOM 2 | C44: 6730.54 | D44: Cum Budgeted Units | E44: 2.45 | F44: 7.36 | G44: 12.27 | H44: 19.63 | I44: 24.54 | J44: 24.54 | K44: 24.54 | L44: 24.54 | M44: 24.54 | N44: 70.54 | O44: 276.54 | P44: 652.54 | Q44: 1073.54 | R44: 1232.54 | S44: 1376.54 | T44: 1568.54 | U44: 1784.04 | V44: 2166.54 | W44: 2751.87 | X44: 2938.54 | Y44: 3033.04 | Z44: 3256.54 | AA44: 3553.87 | AB44: 3670.54 | AC44: 4150.54 | AD44: 4342.54 | AE44: 4534.54 | AF44: 4742.54 | AG44: 4846.54 | AH44: 4894.54 | AI44: 5778.54 | AJ44: 5842.54 | AK44: 6306.54 | AL44: 6674.54 | AM44: 6674.54 | AN44: 6674.54 | AO44: 6722.54 | AP44: 6730.54 | AQ44: 6730.54 | AR44: 6730.54 | AS44: 6730.54 | AT44: 6730.54 | AU44: 6730.54 | AV44: 6730.54 | AW44: 6730.54 | AX44: 6730.54 | AY44: 6730.54 | AZ44: 6730.54 | BA44: 6730.54 | BB44: 6730.54 | BC44: 6730.54 | BD44: 6730.54
B45: WBS: HAL1-05-1.11.1 Engineering | C45: 24.54 | D45: Budgeted Units | E45: =E46 -> 2.45 | F45: =F46-E46 -> 4.91 | G45: =G46-F46 -> 4.91 | H45: =H46-G46 -> 7.36 | I45: =I46-H46 -> 4.91 | J45: =J46-I46 -> 0 | K45: =K46-J46 -> 0 | L45: =L46-K46 -> 0 | M45: =M46-L46 -> 0 | ... BD45: =BD46-BC46 -> 0
B46: WBS: HAL1-05-1.11.1 Engineering | C46: 24.54 | D46: Cum Budgeted Units | E46: 2.45 | F46: 7.36 | G46: 12.27 | H46: 19.63 | I46: 24.54 | J46: 24.54 | K46: 24.54 | L46: 24.54 | M46: 24.54 | N46: 24.54 | O46: 24.54 | P46: 24.54 | Q46: 24.54 | R46: 24.54 | S46: 24.54 | T46: 24.54 | U46: 24.54 | V46: 24.54 | W46: 24.54 | X46: 24.54 | Y46: 24.54 | Z46: 24.54 | AA46: 24.54 | AB46: 24.54 | AC46: 24.54 | AD46: 24.54 | AE46: 24.54 | AF46: 24.54 | AG46: 24.54 | AH46: 24.54 | AI46: 24.54 | AJ46: 24.54 | AK46: 24.54 | AL46: 24.54 | AM46: 24.54 | AN46: 24.54 | AO46: 24.54 | AP46: 24.54 | AQ46: 24.54 | AR46: 24.54 | AS46: 24.54 | AT46: 24.54 | AU46: 24.54 | AV46: 24.54 | AW46: 24.54 | AX46: 24.54 | AY46: 24.54 | AZ46: 24.54 | BA46: 24.54 | BB46: 24.54 | BC46: 24.54 | BD46: 24.54
B47: WBS: HAL1-05-1.11.3 Construction | C47: 6706 | D47: Budgeted Units | E47: =E48 -> 0 | F47: =F48-E48 -> 0 | G47: =G48-F48 -> 0 | H47: =H48-G48 -> 0 | I47: =I48-H48 -> 0 | J47: =J48-I48 -> 0 | K47: =K48-J48 -> 0 | L47: =L48-K48 -> 0 | M47: =M48-L48 -> 0 | ... BD47: =BD48-BC48 -> 0
B48: WBS: HAL1-05-1.11.3 Construction | C48: 6706 | D48: Cum Budgeted Units | N48: 46 | O48: 252 | P48: 628 | Q48: 1049 | R48: 1208 | S48: 1352 | T48: 1544 | U48: 1759.5 | V48: 2142 | W48: 2727.33 | X48: 2914 | Y48: 3008.5 | Z48: 3232 | AA48: 3529.33 | AB48: 3646 | AC48: 4126 | AD48: 4318 | AE48: 4510 | AF48: 4718 | AG48: 4822 | AH48: 4870 | AI48: 5754 | AJ48: 5818 | AK48: 6282 | AL48: 6650 | AM48: 6650 | AN48: 6650 | AO48: 6698 | AP48: 6706 | AQ48: 6706 | AR48: 6706 | AS48: 6706 | AT48: 6706 | AU48: 6706 | AV48: 6706 | AW48: 6706 | AX48: 6706 | AY48: 6706 | AZ48: 6706 | BA48: 6706 | BB48: 6706 | BC48: 6706 | BD48: 6706
B49: WBS: HAL1-05-1.12 PUMP ROOM | C49: 18995.17 | D49: Budgeted Units | E49: =E50 -> 3.68 | F49: =F50-E50 -> 7.36 | G49: =G50-F50 -> 13.5 | H49: =H50-G50 -> 57.25 | I49: =I50-H50 -> 51.73 | J49: =J50-I50 -> 49.9 | K49: =K50-J50 -> 49.08 | L49: =L50-K50 -> 37.01 | M49: =M50-L50 -> 37.28 | ... BD49: =BD50-BC50 -> 0
B50: WBS: HAL1-05-1.12 PUMP ROOM | C50: 18995.17 | D50: Cum Budgeted Units | E50: 3.68 | F50: 11.04 | G50: 24.54 | H50: 81.79 | I50: 133.52 | J50: 183.42 | K50: 232.5 | L50: 269.51 | M50: 306.79 | N50: 342.02 | O50: 454.62 | P50: 654.98 | Q50: 1042.74 | R50: 1294.32 | S50: 1476.36 | T50: 1896.68 | U50: 1984.76 | V50: 2162.83 | W50: 2659.4 | X50: 3175.98 | Y50: 3359.98 | Z50: 3905.13 | AA50: 4431.21 | AB50: 4876.59 | AC50: 6462.15 | AD50: 7690.82 | AE50: 8589.52 | AF50: 9168.9 | AG50: 9716.27 | AH50: 10295.65 | AI50: 10699.02 | AJ50: 10846.4 | AK50: 11223.1 | AL50: 11373.15 | AM50: 11392.52 | AN50: 11650.37 | AO50: 12326.75 | AP50: 12970.39 | AQ50: 13742.77 | AR50: 14315.84 | AS50: 14895.84 | AT50: 17423.84 | AU50: 17995.17 | AV50: 18995.17 | AW50: 18995.17 | AX50: 18995.17 | AY50: 18995.17 | AZ50: 18995.17 | BA50: 18995.17 | BB50: 18995.17 | BC50: 18995.17 | BD50: 18995.17
B51: WBS: HAL1-05-1.12.1 Engineering | C51: 220.84 | D51: Budgeted Units | E51: =E52 -> 3.68 | F51: =F52-E52 -> 7.36 | G51: =G52-F52 -> 13.5 | H51: =H52-G52 -> 57.25 | I51: =I52-H52 -> 51.73 | J51: =J52-I52 -> 36.4 | K51: =K52-J52 -> 22.08 | L51: =L52-K52 -> 14.52 | M51: =M52-L52 -> 8.18 | ... BD51: =BD52-BC52 -> 0
B52: WBS: HAL1-05-1.12.1 Engineering | C52: 220.84 | D52: Cum Budgeted Units | E52: 3.68 | F52: 11.04 | G52: 24.54 | H52: 81.79 | I52: 133.52 | J52: 169.92 | K52: 192 | L52: 206.52 | M52: 214.7 | N52: 220.84 | O52: 220.84 | P52: 220.84 | Q52: 220.84 | R52: 220.84 | S52: 220.84 | T52: 220.84 | U52: 220.84 | V52: 220.84 | W52: 220.84 | X52: 220.84 | Y52: 220.84 | Z52: 220.84 | AA52: 220.84 | AB52: 220.84 | AC52: 220.84 | AD52: 220.84 | AE52: 220.84 | AF52: 220.84 | AG52: 220.84 | AH52: 220.84 | AI52: 220.84 | AJ52: 220.84 | AK52: 220.84 | AL52: 220.84 | AM52: 220.84 | AN52: 220.84 | AO52: 220.84 | AP52: 220.84 | AQ52: 220.84 | AR52: 220.84 | AS52: 220.84 | AT52: 220.84 | AU52: 220.84 | AV52: 220.84 | AW52: 220.84 | AX52: 220.84 | AY52: 220.84 | AZ52: 220.84 | BA52: 220.84 | BB52: 220.84 | BC52: 220.84 | BD52: 220.84
B53: WBS: HAL1-05-1.12.2 Procurement | C53: 2197.34 | D53: Budgeted Units | E53: =E54 -> 0 | F53: =F54-E54 -> 0 | G53: =G54-F54 -> 0 | H53: =H54-G54 -> 0 | I53: =I54-H54 -> 0 | J53: =J54-I54 -> 13.5 | K53: =K54-J54 -> 26.99 | L53: =L54-K54 -> 22.5 | M53: =M54-L54 -> 29.09 | ... BD53: =BD54-BC54 -> 0
B54: WBS: HAL1-05-1.12.2 Procurement | C54: 2197.34 | D54: Cum Budgeted Units | J54: 13.5 | K54: 40.49 | L54: 62.99 | M54: 92.08 | N54: 121.18 | O54: 205.78 | P54: 318.14 | Q54: 402.9 | R54: 432.48 | S54: 447.27 | T54: 476.85 | U54: 506.42 | V54: 563 | W54: 619.57 | X54: 668.14 | Y54: 712.72 | Z54: 757.29 | AA54: 806.04 | AB54: 1028.75 | AC54: 1474.31 | AD54: 1532.31 | AE54: 1551.69 | AF54: 1571.06 | AG54: 1590.44 | AH54: 1609.81 | AI54: 1629.19 | AJ54: 1648.56 | AK54: 1667.93 | AL54: 1687.31 | AM54: 1706.68 | AN54: 1868.53 | AO54: 1872.91 | AP54: 1876.56 | AQ54: 1880.93 | AR54: 2197.34 | AS54: 2197.34 | AT54: 2197.34 | AU54: 2197.34 | AV54: 2197.34 | AW54: 2197.34 | AX54: 2197.34 | AY54: 2197.34 | AZ54: 2197.34 | BA54: 2197.34 | BB54: 2197.34 | BC54: 2197.34 | BD54: 2197.34
B55: WBS: HAL1-05-1.12.3 Construction | C55: 16577 | D55: Budgeted Units | E55: =E56 -> 0 | F55: =F56-E56 -> 0 | G55: =G56-F56 -> 0 | H55: =H56-G56 -> 0 | I55: =I56-H56 -> 0 | J55: =J56-I56 -> 0 | K55: =K56-J56 -> 0 | L55: =L56-K56 -> 0 | M55: =M56-L56 -> 0 | ... BD55: =BD56-BC56 -> 0
B56: WBS: HAL1-05-1.12.3 Construction | C56: 16577 | D56: Cum Budgeted Units | O56: 28 | P56: 116 | Q56: 419 | R56: 641 | S56: 808.25 | T56: 1199 | U56: 1257.5 | V56: 1379 | W56: 1819 | X56: 2287 | Y56: 2426.43 | Z56: 2927 | AA56: 3404.33 | AB56: 3627 | AC56: 4767 | AD56: 5937.67 | AE56: 6817 | AF56: 7377 | AG56: 7905 | AH56: 8465 | AI56: 8849 | AJ56: 8977 | AK56: 9334.33 | AL56: 9465 | AM56: 9465 | AN56: 9561 | AO56: 10233 | AP56: 10873 | AQ56: 11641 | AR56: 11897.67 | AS56: 12477.67 | AT56: 15005.67 | AU56: 15577 | AV56: 16577 | AW56: 16577 | AX56: 16577 | AY56: 16577 | AZ56: 16577 | BA56: 16577 | BB56: 16577 | BC56: 16577 | BD56: 16577
B57: WBS: HAL1-05-1.6 CLOSEOUT | C57: 9378 | D57: Budgeted Units | E57: =E58 -> 0 | F57: =F58-E58 -> 0 | G57: =G58-F58 -> 0 | H57: =H58-G58 -> 0 | I57: =I58-H58 -> 0 | J57: =J58-I58 -> 0 | K57: =K58-J58 -> 0 | L57: =L58-K58 -> 0 | M57: =M58-L58 -> 0 | ... BD57: =BD58-BC58 -> 4056.34
B58: WBS: HAL1-05-1.6 CLOSEOUT | C58: 9378 | D58: Cum Budgeted Units | BC58: 623.33 | BD58: 4679.67

Sheet PV
H3: 33 | I3: Tuesday | J3: Tuesday | K3: Tuesday | L3: Tuesday | M3: Tuesday | N3: Tuesday | O3: Tuesday | P3: Tuesday | Q3: Tuesday | R3: Tuesday | S3: Tuesday | T3: Tuesday | U3: Tuesday | V3: Tuesday | W3: Tuesday | X3: Tuesday | Y3: Tuesday | Z3: Tuesday | AA3: Tuesday | AB3: Tuesday | AC3: Tuesday | AD3: Tuesday | AE3: Tuesday | AF3: Tuesday | AG3: Tuesday | AH3: Tuesday | AI3: Tuesday | AJ3: Tuesday | AK3: Tuesday | AL3: Tuesday | AM3: Tuesday | AN3: Tuesday | AO3: Tuesday | AP3: Tuesday | AQ3: Tuesday | AR3: Tuesday | AS3: Tuesday | AT3: Tuesday | AU3: Tuesday | AV3: Tuesday | AW3: Tuesday | AX3: Tuesday | AY3: Tuesday | AZ3: Tuesday | BA3: Tuesday | BB3: Tuesday | BC3: Tuesday | BD3: Tuesday | BE3: Tuesday | BF3: Tuesday | BG3: Tuesday
H4: 33 | I4: =I5 -> 45307 | J4: =J5 -> 45314 | K4: =K5 -> 45321 | L4: =L5 -> 45328 | M4: =M5 -> 45335 | N4: =N5 -> 45342 | O4: =O5 -> 45349 | P4: =P5 -> 45356 | ... BG4: =BG5 -> 45657
C5: Activity ID | D5: Budgeted Total Cost | E5: Budgeted Labor Units | F5: Start | G5: Finish | H5: Spreadsheet Field | I5: 45307 | J5: 45314 | K5: 45321 | L5: 45328 | M5: 45335 | N5: 45342 | O5: 45349 | P5: 45356 | Q5: 45363 | R5: 45370 | S5: 45377 | T5: 45384 | U5: 45391 | V5: 45398 | W5: 45405 | X5: 45412 | Y5: 45419 | Z5: 45426 | AA5: 45433 | AB5: 45440 | AC5: 45447 | AD5: 45454 | AE5: 45461 | AF5: 45468 | AG5: 45475 | AH5: 45482 | AI5: 45489 | AJ5: 45496 | AK5: 45503 | AL5: 45510 | AM5: 45517 | AN5: 45524 | AO5: 45531 | AP5: 45538 | AQ5: 45545 | AR5: 45552 | AS5: 45559 | AT5: 45566 | AU5: 45573 | AV5: 45580 | AW5: 45587 | AX5: 45594 | AY5: 45601 | AZ5: 45608 | BA5: 45615 | BB5: 45622 | BC5: 45629 | BD5: 45636 | BE5: 45643 | BF5: 45650 | BG5: 45657
C6: Civil Defense Fire Station in Hail Industrial City | D6: 11141855 | E6: 220460.02 | F6: 45298 | G6: 45663 | H6: Planned Value Cost | I6: =I7 -> 15390 | J6: =J7-I7 -> 1485 | K6: =K7-J7 -> 11831.4 | L6: =L7-K7 -> 22422.42 | M6: =M7-L7 -> 28755.46 | N6: =N7-M7 -> 18674.21 | O6: =O7-N7 -> 13885.71 | P6: =P7-O7 -> 13329 | Q6: =Q7-P7 -> 62496 | ... BG6: =BG7-BF7 -> 557092.75
C7: Civil Defense Fire Station in Hail Industrial City | D7: 11141855 | E7: 220460.02 | F7: 45298 | G7: 45663 | H7: Cum Planned Value Cost | I7: 15390 | J7: 16875 | K7: 28706.4 | L7: 51128.82 | M7: 79884.28 | N7: 98558.49 | O7: 112444.2 | P7: 125773.2 | Q7: 188269.2 | R7: 246850.2 | S7: 290320.2 | T7: 316101.47 | U7: 337055.76 | V7: 367890.66 | W7: 445728.36 | X7: 555757.05 | Y7: 686278.2 | Z7: 794909.4 | AA7: 955513.95 | AB7: 1261263.1 | AC7: 1509896 | AD7: 1775729 | AE7: 1861664.9 | AF7: 2110934 | AG7: 2364630.9 | AH7: 2715992.5 | AI7: 3282584 | AJ7: 3915947.4 | AK7: 4425904 | AL7: 4884667.9 | AM7: 5434522.6 | AN7: 5992148.1 | AO7: 6274382.9 | AP7: 6412629.6 | AQ7: 6529175.9 | AR7: 6815477.2 | AS7: 7111800.4 | AT7: 7486780.1 | AU7: 7916868.2 | AV7: 8379220.2 | AW7: 8868575.9 | AX7: 9266080.7 | AY7: 9421873.7 | AZ7: 9646250.8 | BA7: 9806867.6 | BB7: 9918459.7 | BC7: 9965183.4 | BD7: 9983986.2 | BE7: 10001190 | BF7: 10120518 | BG7: 10677611
C8: PROJECT MILESTONES | D8: 0 | E8: 0 | F8: 45298 | G8: 45663 | H8: Planned Value Cost | I8: =I9 -> 0 | J8: =J9-I9 -> 0 | K8: =K9-J9 -> 0 | L8: =L9-K9 -> 0 | M8: =M9-L9 -> 0 | N8: =N9-M9 -> 0 | O8: =O9-N9 -> 0 | P8: =P9-O9 -> 0 | Q8: =Q9-P9 -> 0 | ... BG8: =BG9-BF9 -> 0
C9: PROJECT MILESTONES | D9: 0 | E9: 0 | F9: 45298 | G9: 45663 | H9: Cum Planned Value Cost
C10: MOBILIZATION | D10: 0 | E10: 3445.8 | F10: 45298 | G10: 45328 | H10: Planned Value Cost | I10: =I11 -> 0 | J10: =J11-I11 -> 0 | K10: =K11-J11 -> 0 | L10: =L11-K11 -> 0 | M10: =M11-L11 -> 0 | N10: =N11-M11 -> 0 | O10: =O11-N11 -> 0 | P10: =P11-O11 -> 0 | Q10: =Q11-P11 -> 0 | ... BG10: =BG11-BF11 -> 0
C11: MOBILIZATION | D11: 0 | E11: 3445.8 | F11: 45298 | G11: 45328 | H11: Cum Planned Value Cost
C12: SITE | D12: 2802577.5 | E12: 66611.78 | F12: 45298 | G12: 45649 | H12: Planned Value Cost | I12: =I13 -> 0 | J12: =J13-I13 -> 1485 | K12: =K13-J13 -> 8910 | L12: =L13-K13 -> 4894.02 | M12: =M13-L13 -> 19991.26 | N12: =N13-M13 -> 18674.21 | O12: =O13-N13 -> 5785.71 | P12: =P13-O13 -> 0 | Q12: =Q13-P13 -> 0 | ... BG12: =BG13-BF13 -> 0
C13: SITE | D13: 2802577.5 | E13: 66611.78 | F13: 45298 | G13: 45649 | H13: Cum Planned Value Cost | J13: 1485 | K13: 10395 | L13: 15289.02 | M13: 35280.28 | N13: 53954.49 | O13: 59740.2 | P13: 59740.2 | Q13: 59740.2 | R13: 59740.2 | S13: 59740.2 | T13: 59740.2 | U13: 59740.2 | V13: 63377.1 | W13: 74287.8 | X13: 130944.15 | Y13: 187552.8 | Z13: 250465.8 | AA13: 323361 | AB13: 386193.75 | AC13: 490517.1 | AD13: 578876.43 | AE13: 591135.36 | AF13: 630207.16 | AG13: 781799.7 | AH13: 957993.75 | AI13: 1125247.9 | AJ13: 1265665.9 | AK13: 1364204.1 | AL13: 1393907.7 | AM13: 1455875.6 | AN13: 1601487.9 | AO13: 1729296.9 | AP13: 1808395.2 | AQ13: 1842616.8 | AR13: 1886930.6 | AS13: 1902021.7 | AT13: 1916979.1 | AU13: 1931936.5 | AV13: 2063618.7 | AW13: 2218645.9 | AX13: 2341287.1 | AY13: 2430953.3 | AZ13: 2624518.8 | BA13: 2711966.4 | BB13: 2711966.4 | BC13: 2740091.4 | BD13: 2758894.2 | BE13: 2776097.9 | BF13: 2802577.5 | BG13: 2802577.5
C14: Engineering | D14: 19240.2 | E14: 1607.2 | F14: 45298 | G14: 45400 | H14: Planned Value Cost | I14: =I15 -> 0 | J14: =J15-I15 -> 1485 | K14: =K15-J15 -> 8910 | L14: =L15-K15 -> 4894.02 | M14: =M15-L15 -> 2634.12 | N14: =N15-M15 -> 1317.06 | O14: =O15-N15 -> 0 | P14: =P15-O15 -> 0 | Q14: =Q15-P15 -> 0 | ... BG14: =BG15-BF15 -> 0
C15: Engineering | D15: 19240.2 | E15: 1607.2 | F15: 45298 | G15: 45400 | H15: Cum Planned Value Cost | J15: 1485 | K15: 10395 | L15: 15289.02 | M15: 17923.14 | N15: 19240.2 | O15: 19240.2 | P15: 19240.2 | Q15: 19240.2 | R15: 19240.2 | S15: 19240.2 | T15: 19240.2 | U15: 19240.2 | V15: 19240.2 | W15: 19240.2 | X15: 19240.2 | Y15: 19240.2 | Z15: 19240.2 | AA15: 19240.2 | AB15: 19240.2 | AC15: 19240.2 | AD15: 19240.2 | AE15: 19240.2 | AF15: 19240.2 | AG15: 19240.2 | AH15: 19240.2 | AI15: 19240.2 | AJ15: 19240.2 | AK15: 19240.2 | AL15: 19240.2 | AM15: 19240.2 | AN15: 19240.2 | AO15: 19240.2 | AP15: 19240.2 | AQ15: 19240.2 | AR15: 19240.2 | AS15: 19240.2 | AT15: 19240.2 | AU15: 19240.2 | AV15: 19240.2 | AW15: 19240.2 | AX15: 19240.2 | AY15: 19240.2 | AZ15: 19240.2 | BA15: 19240.2 | BB15: 19240.2 | BC15: 19240.2 | BD15: 19240.2 | BE15: 19240.2 | BF15: 19240.2 | BG15: 19240.2
C16: Procurement | D16: 128268 | E16: 7653.58 | F16: 45350 | G16: 45600 | H16: Planned Value Cost | I16: =I17 -> 0 | J16: =J17-I17 -> 0 | K16: =K17-J17 -> 0 | L16: =L17-K17 -> 0 | M16: =M17-L17 -> 0 | N16: =N17-M17 -> 0 | O16: =O17-N17 -> 0 | P16: =P17-O17 -> 0 | Q16: =Q17-P17 -> 0 | ... BG16: =BG17-BF17 -> 0
C17: Procurement | D17: 128268 | E17: 7653.58 | F17: 45350 | G17: 45600 | H17: Cum Planned Value Cost | AG17: 99000 | AH17: 99000 | AI17: 99000 | AJ17: 128268 | AK17: 128268 | AL17: 128268 | AM17: 128268 | AN17: 128268 | AO17: 128268 | AP17: 128268 | AQ17: 128268 | AR17: 128268 | AS17: 128268 | AT17: 128268 | AU17: 128268 | AV17: 128268 | AW17: 128268 | AX17: 128268 | AY17: 128268 | AZ17: 128268 | BA17: 128268 | BB17: 128268 | BC17: 128268 | BD17: 128268 | BE17: 128268 | BF17: 128268 | BG17: 128268
C18: Construction | D18: 2655069.3 | E18: 57351 | F18: 45329 | G18: 45649 | H18: Planned Value Cost | I18: =I19 -> 0 | J18: =J19-I19 -> 0 | K18: =K19-J19 -> 0 | L18: =L19-K19 -> 0 | M18: =M19-L19 -> 17357.14 | N18: =N19-M19 -> 17357.15 | O18: =O19-N19 -> 5785.71 | P18: =P19-O19 -> 0 | Q18: =Q19-P19 -> 0 | ... BG18: =BG19-BF19 -> 0
C19: Construction | D19: 2655069.3 | E19: 57351 | F19: 45329 | G19: 45649 | H19: Cum Planned Value Cost | M19: 17357.14 | N19: 34714.29 | O19: 40500 | P19: 40500 | Q19: 40500 | R19: 40500 | S19: 40500 | T19: 40500 | U19: 40500 | V19: 44136.9 | W19: 55047.6 | X19: 111703.95 | Y19: 168312.6 | Z19: 231225.6 | AA19: 304120.8 | AB19: 366953.55 | AC19: 471276.9 | AD19: 559636.23 | AE19: 571895.16 | AF19: 610966.96 | AG19: 663559.5 | AH19: 839753.55 | AI19: 1007007.8 | AJ19: 1118157.8 | AK19: 1216695.9 | AL19: 1246399.5 | AM19: 1308367.4 | AN19: 1453979.7 | AO19: 1581788.7 | AP19: 1660887 | AQ19: 1695108.6 | AR19: 1739422.4 | AS19: 1754513.5 | AT19: 1769470.9 | AU19: 1784428.3 | AV19: 1916110.5 | AW19: 2071137.7 | AX19: 2193778.9 | AY19: 2283445.1 | AZ19: 2477010.6 | BA19: 2564458.2 | BB19: 2564458.2 | BC19: 2592583.2 | BD19: 2611386 | BE19: 2628589.7 | BF19: 2655069.3 | BG19: 2655069.3
C20: MAIN BUILDING | D20: 4439875.5 | E20: 86348.45 | F20: 45298 | G20: 45623 | H20: Planned Value Cost | I20: =I21 -> 15390 | J20: =J21-I21 -> 0 | K20: =K21-J21 -> 0 | L20: =L21-K21 -> 0 | M20: =M21-L21 -> 0 | N20: =N21-M21 -> 0 | O20: =O21-N21 -> 8100 | P20: =P21-O21 -> 13329 | Q20: =Q21-P21 -> 57375 | ... BG20: =BG21-BF21 -> 0
C21: MAIN BUILDING | D21: 4439875.5 | E21: 86348.45 | F21: 45298 | G21: 45623 | H21: Cum Planned Value Cost | I21: 15390 | J21: 15390 | K21: 15390 | L21: 15390 | M21: 15390 | N21: 15390 | O21: 23490 | P21: 36819 | Q21: 94194 | R21: 135706.5 | S21: 145494 | T21: 155061 | U21: 161694 | V21: 180864 | W21: 231894 | X21: 268656.6 | Y21: 326901.9 | Z21: 351584.1 | AA21: 421504.65 | AB21: 618036.3 | AC21: 728961.3 | AD21: 839886.3 | AE21: 843148.8 | AF21: 852936.3 | AG21: 890493.3 | AH21: 925599.6 | AI21: 1154164.5 | AJ21: 1451542 | AK21: 1751004.6 | AL21: 1999839.7 | AM21: 2272269.5 | AN21: 2355234.2 | AO21: 2389883 | AP21: 2449031.4 | AQ21: 2525159.6 | AR21: 2712948.7 | AS21: 2939569.2 | AT21: 3275975.5 | AU21: 3538446.2 | AV21: 3751815.9 | AW21: 3961680.5 | AX21: 4144626.1 | AY21: 4205703.9 | AZ21: 4236515.5 | BA21: 4309684.7 | BB21: 4421276.8 | BC21: 4439875.5 | BD21: 4439875.5 | BE21: 4439875.5 | BF21: 4439875.5 | BG21: 4439875.5
C22: Engineering | D22: 15390 | E22: 3103.98 | F22: 45298 | G22: 45400 | H22: Planned Value Cost | I22: =I23 -> 15390 | J22: =J23-I23 -> 0 | K22: =K23-J23 -> 0 | L22: =L23-K23 -> 0 | M22: =M23-L23 -> 0 | N22: =N23-M23 -> 0 | O22: =O23-N23 -> 0 | P22: =P23-O23 -> 0 | Q22: =Q23-P23 -> 0 | ... BG22: =BG23-BF23 -> 0
C23: Engineering | D23: 15390 | E23: 3103.98 | F23: 45298 | G23: 45400 | H23: Cum Planned Value Cost | I23: 15390 | J23: 15390 | K23: 15390 | L23: 15390 | M23: 15390 | N23: 15390 | O23: 15390 | P23: 15390 | Q23: 15390 | R23: 15390 | S23: 15390 | T23: 15390 | U23: 15390 | V23: 15390 | W23: 15390 | X23: 15390 | Y23: 15390 | Z23: 15390 | AA23: 15390 | AB23: 15390 | AC23: 15390 | AD23: 15390 | AE23: 15390 | AF23: 15390 | AG23: 15390 | AH23: 15390 | AI23: 15390 | AJ23: 15390 | AK23: 15390 | AL23: 15390 | AM23: 15390 | AN23: 15390 | AO23: 15390 | AP23: 15390 | AQ23: 15390 | AR23: 15390 | AS23: 15390 | AT23: 15390 | AU23: 15390 | AV23: 15390 | AW23: 15390 | AX23: 15390 | AY23: 15390 | AZ23: 15390 | BA23: 15390 | BB23: 15390 | BC23: 15390 | BD23: 15390 | BE23: 15390 | BF23: 15390 | BG23: 15390
C24: Procurement | D24: 138510 | E24: 11205.47 | F24: 45319 | G24: 45559 | H24: Planned Value Cost | I24: =I25 -> 0 | J24: =J25-I25 -> 0 | K24: =K25-J25 -> 0 | L24: =L25-K25 -> 0 | M24: =M25-L25 -> 0 | N24: =N25-M25 -> 0 | O24: =O25-N25 -> 0 | P24: =P25-O25 -> 0 | Q24: =Q25-P25 -> 0 | ... BG24: =BG25-BF25 -> 0
C25: Procurement | D25: 138510 | E25: 11205.47 | F25: 45319 | G25: 45559 | H25: Cum Planned Value Cost | AI25: 138510 | AJ25: 138510 | AK25: 138510 | AL25: 138510 | AM25: 138510 | AN25: 138510 | AO25: 138510 | AP25: 138510 | AQ25: 138510 | AR25: 138510 | AS25: 138510 | AT25: 138510 | AU25: 138510 | AV25: 138510 | AW25: 138510 | AX25: 138510 | AY25: 138510 | AZ25: 138510 | BA25: 138510 | BB25: 138510 | BC25: 138510 | BD25: 138510 | BE25: 138510 | BF25: 138510 | BG25: 138510
C26: Construction | D26: 4285975.5 | E26: 72039 | F26: 45347 | G26: 45623 | H26: Planned Value Cost | I26: =I27 -> 0 | J26: =J27-I27 -> 0 | K26: =K27-J27 -> 0 | L26: =L27-K27 -> 0 | M26: =M27-L27 -> 0 | N26: =N27-M27 -> 0 | O26: =O27-N27 -> 8100 | P26: =P27-O27 -> 13329 | Q26: =Q27-P27 -> 57375 | ... BG26: =BG27-BF27 -> 0
C27: Construction | D27: 4285975.5 | E27: 72039 | F27: 45347 | G27: 45623 | H27: Cum Planned Value Cost | O27: 8100 | P27: 21429 | Q27: 78804 | R27: 120316.5 | S27: 130104 | T27: 139671 | U27: 146304 | V27: 165474 | W27: 216504 | X27: 253266.6 | Y27: 311511.9 | Z27: 336194.1 | AA27: 406114.65 | AB27: 602646.3 | AC27: 713571.3 | AD27: 824496.3 | AE27: 827758.8 | AF27: 837546.3 | AG27: 875103.3 | AH27: 910209.6 | AI27: 1000264.5 | AJ27: 1297642 | AK27: 1597104.6 | AL27: 1845939.7 | AM27: 2118369.5 | AN27: 2201334.2 | AO27: 2235983 | AP27: 2295131.4 | AQ27: 2371259.6 | AR27: 2559048.7 | AS27: 2785669.2 | AT27: 3122075.5 | AU27: 3384546.2 | AV27: 3597915.9 | AW27: 3807780.5 | AX27: 3990726.1 | AY27: 4051803.9 | AZ27: 4082615.5 | BA27: 4155784.7 | BB27: 4267376.8 | BC27: 4285975.5 | BD27: 4285975.5 | BE27: 4285975.5 | BF27: 4285975.5 | BG27: 4285975.5
C28: SERVICE BUILDING | D28: 1307801.7 | E28: 19120.97 | F28: 45298 | G28: 45559 | H28: Planned Value Cost | I28: =I29 -> 0 | J28: =J29-I29 -> 0 | K28: =K29-J29 -> 0 | L28: =L29-K29 -> 0 | M28: =M29-L29 -> 0 | N28: =N29-M29 -> 0 | O28: =O29-N29 -> 0 | P28: =P29-O29 -> 0 | Q28: =Q29-P29 -> 4824 | ... BG28: =BG29-BF29 -> 0
C29: SERVICE BUILDING | D29: 1307801.7 | E29: 19120.97 | F29: 45298 | G29: 45559 | H29: Cum Planned Value Cost | Q29: 4824 | R29: 19876.5 | S29: 43501.5 | T29: 51517.13 | U29: 58266 | V29: 61776 | W29: 67914 | X29: 76392 | Y29: 85869 | Z29: 91498.5 | AA29: 99975.3 | AB29: 138146.17 | AC29: 152827.43 | AD29: 186268.05 | AE29: 198665.55 | AF29: 234249.3 | AG29: 234249.3 | AH29: 280068.3 | AI29: 318317.1 | AJ29: 425841.6 | AK29: 504903.15 | AL29: 648778.2 | AM29: 857777.4 | AN29: 1139684.4 | AO29: 1231286.4 | AP29: 1231286.4 | AQ29: 1231286.4 | AR29: 1261649.2 | AS29: 1307801.7 | AT29: 1307801.7 | AU29: 1307801.7 | AV29: 1307801.7 | AW29: 1307801.7 | AX29: 1307801.7 | AY29: 1307801.7 | AZ29: 1307801.7 | BA29: 1307801.7 | BB29: 1307801.7 | BC29: 1307801.7 | BD29: 1307801.7 | BE29: 1307801.7 | BF29: 1307801.7 | BG29: 1307801.7
C30: Engineering | D30: 0 | E30: 834.27 | F30: 45298 | G30: 45361 | H30: Planned Value Cost | I30: =I31 -> 0 | J30: =J31-I31 -> 0 | K30: =K31-J31 -> 0 | L30: =L31-K31 -> 0 | M30: =M31-L31 -> 0 | N30: =N31-M31 -> 0 | O30: =O31-N31 -> 0 | P30: =P31-O31 -> 0 | Q30: =Q31-P31 -> 0 | ... BG30: =BG31-BF31 -> 0
C31: Engineering | D31: 0 | E31: 834.27 | F31: 45298 | G31: 45361 | H31: Cum Planned Value Cost
C32: Procurement | D32: 0 | E32: 2520.7 | F32: 45378 | G32: 45550 | H32: Planned Value Cost | I32: =I33 -> 0 | J32: =J33-I33 -> 0 | K32: =K33-J33 -> 0 | L32: =L33-K33 -> 0 | M32: =M33-L33 -> 0 | N32: =N33-M33 -> 0 | O32: =O33-N33 -> 0 | P32: =P33-O33 -> 0 | Q32: =Q33-P33 -> 0 | ... BG32: =BG33-BF33 -> 0
C33: Procurement | D33: 0 | E33: 2520.7 | F33: 45378 | G33: 45550 | H33: Cum Planned Value Cost
C34: Construction | D34: 1307801.7 | E34: 15766 | F34: 45357 | G34: 45559 | H34: Planned Value Cost | I34: =I35 -> 0 | J34: =J35-I35 -> 0 | K34: =K35-J35 -> 0 | L34: =L35-K35 -> 0 | M34: =M35-L35 -> 0 | N34: =N35-M35 -> 0 | O34: =O35-N35 -> 0 | P34: =P35-O35 -> 0 | Q34: =Q35-P35 -> 4824 | ... BG34: =BG35-BF35 -> 0
C35: Construction | D35: 1307801.7 | E35: 15766 | F35: 45357 | G35: 45559 | H35: Cum Planned Value Cost | Q35: 4824 | R35: 19876.5 | S35: 43501.5 | T35: 51517.13 | U35: 58266 | V35: 61776 | W35: 67914 | X35: 76392 | Y35: 85869 | Z35: 91498.5 | AA35: 99975.3 | AB35: 138146.17 | AC35: 152827.43 | AD35: 186268.05 | AE35: 198665.55 | AF35: 234249.3 | AG35: 234249.3 | AH35: 280068.3 | AI35: 318317.1 | AJ35: 425841.6 | AK35: 504903.15 | AL35: 648778.2 | AM35: 857777.4 | AN35: 1139684.4 | AO35: 1231286.4 | AP35: 1231286.4 | AQ35: 1231286.4 | AR35: 1261649.2 | AS35: 1307801.7 | AT35: 1307801.7 | AU35: 1307801.7 | AV35: 1307801.7 | AW35: 1307801.7 | AX35: 1307801.7 | AY35: 1307801.7 | AZ35: 1307801.7 | BA35: 1307801.7 | BB35: 1307801.7 | BC35: 1307801.7 | BD35: 1307801.7 | BE35: 1307801.7 | BF35: 1307801.7 | BG35: 1307801.7
C36: GUARD ROOM 1 | D36: 127414.8 | E36: 9829.32 | F36: 45298 | G36: 45553 | H36: Planned Value Cost | I36: =I37 -> 0 | J36: =J37-I37 -> 0 | K36: =K37-J37 -> 0 | L36: =L37-K37 -> 0 | M36: =M37-L37 -> 0 | N36: =N37-M37 -> 0 | O36: =O37-N37 -> 0 | P36: =P37-O37 -> 0 | Q36: =Q37-P37 -> 148.5 | ... BG36: =BG37-BF37 -> 0
C37: GUARD ROOM 1 | D37: 127414.8 | E37: 9829.32 | F37: 45298 | G37: 45553 | H37: Cum Planned Value Cost | Q37: 148.5 | R37: 931.5 | S37: 5431.5 | T37: 7033.32 | U37: 7444.53 | V37: 8814.78 | W37: 12928.98 | X37: 17046 | Y37: 19746 | Z37: 25084.5 | AA37: 26824.5 | AB37: 30404.7 | AC37: 35178.3 | AD37: 45678.9 | AE37: 48771.9 | AF37: 63657.9 | AG37: 69191.1 | AH37: 71626.5 | AI37: 78055.2 | AJ37: 78473.7 | AK37: 79113.9 | AL37: 92810.7 | AM37: 94433.1 | AN37: 108476.55 | AO37: 119520 | AP37: 119520 | AQ37: 119520 | AR37: 126726.3 | AS37: 127414.8 | AT37: 127414.8 | AU37: 127414.8 | AV37: 127414.8 | AW37: 127414.8 | AX37: 127414.8 | AY37: 127414.8 | AZ37: 127414.8 | BA37: 127414.8 | BB37: 127414.8 | BC37: 127414.8 | BD37: 127414.8 | BE37: 127414.8 | BF37: 127414.8 | BG37: 127414.8
C38: Engineering | D38: 0 | E38: 282.18 | F38: 45298 | G38: 45361 | H38: Planned Value Cost | I38: =I39 -> 0 | J38: =J39-I39 -> 0 | K38: =K39-J39 -> 0 | L38: =L39-K39 -> 0 | M38: =M39-L39 -> 0 | N38: =N39-M39 -> 0 | O38: =O39-N39 -> 0 | P38: =P39-O39 -> 0 | Q38: =Q39-P39 -> 0 | ... BG38: =BG39-BF39 -> 0
C39: Engineering | D39: 0 | E39: 282.18 | F39: 45298 | G39: 45361 | H39: Cum Planned Value Cost
C40: Procurement | D40: 0 | E40: 2877.14 | F40: 45413 | G40: 45550 | H40: Planned Value Cost | I40: =I41 -> 0 | J40: =J41-I41 -> 0 | K40: =K41-J41 -> 0 | L40: =L41-K41 -> 0 | M40: =M41-L41 -> 0 | N40: =N41-M41 -> 0 | O40: =O41-N41 -> 0 | P40: =P41-O41 -> 0 | Q40: =Q41-P41 -> 0 | ... BG40: =BG41-BF41 -> 0
C41: Procurement | D41: 0 | E41: 2877.14 | F41: 45413 | G41: 45550 | H41: Cum Planned Value Cost
C42: Construction | D42: 127414.8 | E42: 6670 | F42: 45362 | G42: 45553 | H42: Planned Value Cost | I42: =I43 -> 0 | J42: =J43-I43 -> 0 | K42: =K43-J43 -> 0 | L42: =L43-K43 -> 0 | M42: =M43-L43 -> 0 | N42: =N43-M43 -> 0 | O42: =O43-N43 -> 0 | P42: =P43-O43 -> 0 | Q42: =Q43-P43 -> 148.5 | ... BG42: =BG43-BF43 -> 0
C43: Construction | D43: 127414.8 | E43: 6670 | F43: 45362 | G43: 45553 | H43: Cum Planned Value Cost | Q43: 148.5 | R43: 931.5 | S43: 5431.5 | T43: 7033.32 | U43: 7444.53 | V43: 8814.78 | W43: 12928.98 | X43: 17046 | Y43: 19746 | Z43: 25084.5 | AA43: 26824.5 | AB43: 30404.7 | AC43: 35178.3 | AD43: 45678.9 | AE43: 48771.9 | AF43: 63657.9 | AG43: 69191.1 | AH43: 71626.5 | AI43: 78055.2 | AJ43: 78473.7 | AK43: 79113.9 | AL43: 92810.7 | AM43: 94433.1 | AN43: 108476.55 | AO43: 119520 | AP43: 119520 | AQ43: 119520 | AR43: 126726.3 | AS43: 127414.8 | AT43: 127414.8 | AU43: 127414.8 | AV43: 127414.8 | AW43: 127414.8 | AX43: 127414.8 | AY43: 127414.8 | AZ43: 127414.8 | BA43: 127414.8 | BB43: 127414.8 | BC43: 127414.8 | BD43: 127414.8 | BE43: 127414.8 | BF43: 127414.8 | BG43: 127414.8
C44: GUARD ROOM 2 | D44: 135848.7 | E44: 6730.54 | F44: 45298 | G44: 45553 | H44: Planned Value Cost | I44: =I45 -> 0 | J44: =J45-I45 -> 0 | K44: =K45-J45 -> 0 | L44: =L45-K45 -> 0 | M44: =M45-L45 -> 0 | N44: =N45-M45 -> 0 | O44: =O45-N45 -> 0 | P44: =P45-O45 -> 0 | Q44: =Q45-P45 -> 148.5 | ... BG44: =BG45-BF45 -> 0
C45: GUARD ROOM 2 | D45: 135848.7 | E45: 6730.54 | F45: 45298 | G45: 45553 | H45: Cum Planned Value Cost | Q45: 148.5 | R45: 931.5 | S45: 5431.5 | T45: 7033.32 | U45: 7444.53 | V45: 8814.78 | W45: 12502.08 | X45: 15765.3 | Y45: 18586.8 | Z45: 24046.8 | AA45: 25786.8 | AB45: 29367 | AC45: 38822.4 | AD45: 48658.8 | AE45: 51832.8 | AF45: 66718.8 | AG45: 72333 | AH45: 74696.4 | AI45: 79906.2 | AJ45: 80508.6 | AK45: 81181.8 | AL45: 92825.1 | AM45: 96100.5 | AN45: 114935.4 | AO45: 127770.3 | AP45: 127770.3 | AQ45: 127770.3 | AR45: 135206.1 | AS45: 135848.7 | AT45: 135848.7 | AU45: 135848.7 | AV45: 135848.7 | AW45: 135848.7 | AX45: 135848.7 | AY45: 135848.7 | AZ45: 135848.7 | BA45: 135848.7 | BB45: 135848.7 | BC45: 135848.7 | BD45: 135848.7 | BE45: 135848.7 | BF45: 135848.7 | BG45: 135848.7
C46: Engineering | D46: 0 | E46: 24.54 | F46: 45298 | G46: 45326 | H46: Planned Value Cost | I46: =I47 -> 0 | J46: =J47-I47 -> 0 | K46: =K47-J47 -> 0 | L46: =L47-K47 -> 0 | M46: =M47-L47 -> 0 | N46: =N47-M47 -> 0 | O46: =O47-N47 -> 0 | P46: =P47-O47 -> 0 | Q46: =Q47-P47 -> 0 | ... BG46: =BG47-BF47 -> 0
C47: Engineering | D47: 0 | E47: 24.54 | F47: 45298 | G47: 45326 | H47: Cum Planned Value Cost
C48: Construction | D48: 135848.7 | E48: 6706 | F48: 45362 | G48: 45553 | H48: Planned Value Cost | I48: =I49 -> 0 | J48: =J49-I49 -> 0 | K48: =K49-J49 -> 0 | L48: =L49-K49 -> 0 | M48: =M49-L49 -> 0 | N48: =N49-M49 -> 0 | O48: =O49-N49 -> 0 | P48: =P49-O49 -> 0 | Q48: =Q49-P49 -> 148.5 | ... BG48: =BG49-BF49 -> 0
C49: Construction | D49: 135848.7 | E49: 6706 | F49: 45362 | G49: 45553 | H49: Cum Planned Value Cost | Q49: 148.5 | R49: 931.5 | S49: 5431.5 | T49: 7033.32 | U49: 7444.53 | V49: 8814.78 | W49: 12502.08 | X49: 15765.3 | Y49: 18586.8 | Z49: 24046.8 | AA49: 25786.8 | AB49: 29367 | AC49: 38822.4 | AD49: 48658.8 | AE49: 51832.8 | AF49: 66718.8 | AG49: 72333 | AH49: 74696.4 | AI49: 79906.2 | AJ49: 80508.6 | AK49: 81181.8 | AL49: 92825.1 | AM49: 96100.5 | AN49: 114935.4 | AO49: 127770.3 | AP49: 127770.3 | AQ49: 127770.3 | AR49: 135206.1 | AS49: 135848.7 | AT49: 135848.7 | AU49: 135848.7 | AV49: 135848.7 | AW49: 135848.7 | AX49: 135848.7 | AY49: 135848.7 | AZ49: 135848.7 | BA49: 135848.7 | BB49: 135848.7 | BC49: 135848.7 | BD49: 135848.7 | BE49: 135848.7 | BF49: 135848.7 | BG49: 135848.7
C50: PUMP ROOM | D50: 1214151.3 | E50: 18995.17 | F50: 45298 | G50: 45600 | H50: Planned Value Cost | I50: =I51 -> 0 | J50: =J51-I51 -> 0 | K50: =K51-J51 -> 2921.4 | L50: =L51-K51 -> 17528.4 | M50: =M51-L51 -> 8764.2 | N50: =N51-M51 -> 0 | O50: =O51-N51 -> 0 | P50: =P51-O51 -> 0 | Q50: =Q51-P51 -> 0 | ... BG50: =BG51-BF51 -> 0
C51: PUMP ROOM | D51: 1214151.3 | E51: 18995.17 | F51: 45298 | G51: 45600 | H51: Cum Planned Value Cost | K51: 2921.4 | L51: 20449.8 | M51: 29214 | N51: 29214 | O51: 29214 | P51: 29214 | Q51: 29214 | R51: 29664 | S51: 30721.5 | T51: 35716.5 | U51: 42466.5 | V51: 44244 | W51: 46201.5 | X51: 46953 | Y51: 47621.7 | Z51: 52229.7 | AA51: 58061.7 | AB51: 59115.21 | AC51: 63589.5 | AD51: 76360.5 | AE51: 128110.5 | AF51: 263164.5 | AG51: 316564.5 | AH51: 406008 | AI51: 526893 | AJ51: 613915.5 | AK51: 645496.5 | AL51: 656506.5 | AM51: 658066.5 | AN51: 672329.7 | AO51: 676626.3 | AP51: 676626.3 | AQ51: 682822.8 | AR51: 692016.3 | AS51: 699144.3 | AT51: 722760.3 | AU51: 875420.3 | AV51: 992720.3 | AW51: 1117184.3 | AX51: 1209102.3 | AY51: 1214151.3 | AZ51: 1214151.3 | BA51: 1214151.3 | BB51: 1214151.3 | BC51: 1214151.3 | BD51: 1214151.3 | BE51: 1214151.3 | BF51: 1214151.3 | BG51: 1214151.3
C52: Engineering | D52: 29214 | E52: 220.84 | F52: 45298 | G52: 45362 | H52: Planned Value Cost | I52: =I53 -> 0 | J52: =J53-I53 -> 0 | K52: =K53-J53 -> 2921.4 | L52: =L53-K53 -> 17528.4 | M52: =M53-L53 -> 8764.2 | N52: =N53-M53 -> 0 | O52: =O53-N53 -> 0 | P52: =P53-O53 -> 0 | Q52: =Q53-P53 -> 0 | ... BG52: =BG53-BF53 -> 0
C53: Engineering | D53: 29214 | E53: 220.84 | F53: 45298 | G53: 45362 | H53: Cum Planned Value Cost | K53: 2921.4 | L53: 20449.8 | M53: 29214 | N53: 29214 | O53: 29214 | P53: 29214 | Q53: 29214 | R53: 29214 | S53: 29214 | T53: 29214 | U53: 29214 | V53: 29214 | W53: 29214 | X53: 29214 | Y53: 29214 | Z53: 29214 | AA53: 29214 | AB53: 29214 | AC53: 29214 | AD53: 29214 | AE53: 29214 | AF53: 29214 | AG53: 29214 | AH53: 29214 | AI53: 29214 | AJ53: 29214 | AK53: 29214 | AL53: 29214 | AM53: 29214 | AN53: 29214 | AO53: 29214 | AP53: 29214 | AQ53: 29214 | AR53: 29214 | AS53: 29214 | AT53: 29214 | AU53: 29214 | AV53: 29214 | AW53: 29214 | AX53: 29214 | AY53: 29214 | AZ53: 29214 | BA53: 29214 | BB53: 29214 | BC53: 29214 | BD53: 29214 | BE53: 29214 | BF53: 29214 | BG53: 29214
C54: Procurement | D54: 262926 | E54: 2197.34 | F54: 45333 | G54: 45572 | H54: Planned Value Cost | I54: =I55 -> 0 | J54: =J55-I55 -> 0 | K54: =K55-J55 -> 0 | L54: =L55-K55 -> 0 | M54: =M55-L55 -> 0 | N54: =N55-M55 -> 0 | O54: =O55-N55 -> 0 | P54: =P55-O55 -> 0 | Q54: =Q55-P55 -> 0 | ... BG54: =BG55-BF55 -> 0
C55: Procurement | D55: 262926 | E55: 2197.34 | F55: 45333 | G55: 45572 | H55: Cum Planned Value Cost | AE55: 45522 | AF55: 136566 | AG55: 136566 | AH55: 136566 | AI55: 136566 | AJ55: 136566 | AK55: 136566 | AL55: 136566 | AM55: 136566 | AN55: 136566 | AO55: 136566 | AP55: 136566 | AQ55: 136566 | AR55: 136566 | AS55: 136566 | AT55: 136566 | AU55: 262926 | AV55: 262926 | AW55: 262926 | AX55: 262926 | AY55: 262926 | AZ55: 262926 | BA55: 262926 | BB55: 262926 | BC55: 262926 | BD55: 262926 | BE55: 262926 | BF55: 262926 | BG55: 262926
C56: Construction | D56: 922011.3 | E56: 16577 | F56: 45369 | G56: 45600 | H56: Planned Value Cost | I56: =I57 -> 0 | J56: =J57-I57 -> 0 | K56: =K57-J57 -> 0 | L56: =L57-K57 -> 0 | M56: =M57-L57 -> 0 | N56: =N57-M57 -> 0 | O56: =O57-N57 -> 0 | P56: =P57-O57 -> 0 | Q56: =Q57-P57 -> 0 | ... BG56: =BG57-BF57 -> 0
C57: Construction | D57: 922011.3 | E57: 16577 | F57: 45369 | G57: 45600 | H57: Cum Planned Value Cost | R57: 450 | S57: 1507.5 | T57: 6502.5 | U57: 13252.5 | V57: 15030 | W57: 16987.5 | X57: 17739 | Y57: 18407.7 | Z57: 23015.7 | AA57: 28847.7 | AB57: 29901.21 | AC57: 34375.5 | AD57: 47146.5 | AE57: 53374.5 | AF57: 97384.5 | AG57: 150784.5 | AH57: 240228 | AI57: 361113 | AJ57: 448135.5 | AK57: 479716.5 | AL57: 490726.5 | AM57: 492286.5 | AN57: 506549.7 | AO57: 510846.3 | AP57: 510846.3 | AQ57: 517042.8 | AR57: 526236.3 | AS57: 533364.3 | AT57: 556980.3 | AU57: 583280.3 | AV57: 700580.3 | AW57: 825044.3 | AX57: 916962.3 | AY57: 922011.3 | AZ57: 922011.3 | BA57: 922011.3 | BB57: 922011.3 | BC57: 922011.3 | BD57: 922011.3 | BE57: 922011.3 | BF57: 922011.3 | BG57: 922011.3
C58: CLOSEOUT | D58: 1114185.5 | E58: 9378 | F58: 45650 | G58: 45663 | H58: Planned Value Cost | I58: =I59 -> 0 | J58: =J59-I59 -> 0 | K58: =K59-J59 -> 0 | L58: =L59-K59 -> 0 | M58: =M59-L59 -> 0 | N58: =N59-M59 -> 0 | O58: =O59-N59 -> 0 | P58: =P59-O59 -> 0 | Q58: =Q59-P59 -> 0 | ... BG58: =BG59-BF59 -> 557092.75
C59: CLOSEOUT | D59: 1114185.5 | E59: 9378 | F59: 45650 | G59: 45663 | H59: Cum Planned Value Cost | BF59: 92848.79 | BG59: 649941.54
C60: Testing & Commissioning | D60: 1114185.5 | E60: 7480 | F60: 45650 | G60: 45663 | H60: Planned Value Cost | I60: =I61 -> 0 | J60: =J61-I61 -> 0 | K60: =K61-J61 -> 0 | L60: =L61-K61 -> 0 | M60: =M61-L61 -> 0 | N60: =N61-M61 -> 0 | O60: =O61-N61 -> 0 | P60: =P61-O61 -> 0 | Q60: =Q61-P61 -> 0 | ... BG60: =BG61-BF61 -> 557092.75
C61: Testing & Commissioning | D61: 1114185.5 | E61: 7480 | F61: 45650 | G61: 45663 | H61: Cum Planned Value Cost | BF61: 92848.79 | BG61: 649941.54
C62: Site Work | D62: 311397.5 | E62: 800 | F62: 45650 | G62: 45663 | H62: Planned Value Cost | I62: =I63 -> 0 | J62: =J63-I63 -> 0 | K62: =K63-J63 -> 0 | L62: =L63-K63 -> 0 | M62: =M63-L63 -> 0 | N62: =N63-M63 -> 0 | O62: =O63-N63 -> 0 | P62: =P63-O63 -> 0 | Q62: =Q63-P63 -> 0 | ... BG62: =BG63-BF63 -> 155698.75
C63: Site Work | D63: 311397.5 | E63: 800 | F63: 45650 | G63: 45663 | H63: Cum Planned Value Cost | BF63: 25949.79 | BG63: 181648.54
C64: Main Building | D64: 493319.5 | E64: 2200 | F64: 45650 | G64: 45663 | H64: Planned Value Cost | I64: =I65 -> 0 | J64: =J65-I65 -> 0 | K64: =K65-J65 -> 0 | L64: =L65-K65 -> 0 | M64: =M65-L65 -> 0 | N64: =N65-M65 -> 0 | O64: =O65-N65 -> 0 | P64: =P65-O65 -> 0 | Q64: =Q65-P65 -> 0 | ... BG64: =BG65-BF65 -> 246659.75
C65: Main Building | D65: 493319.5 | E65: 2200 | F65: 45650 | G65: 45663 | H65: Cum Planned Value Cost | BF65: 41109.96 | BG65: 287769.71
C66: Service Building | D66: 145311.3 | E66: 1800 | F66: 45650 | G66: 45663 | H66: Planned Value Cost | I66: =I67 -> 0 | J66: =J67-I67 -> 0 | K66: =K67-J67 -> 0 | L66: =L67-K67 -> 0 | M66: =M67-L67 -> 0 | N66: =N67-M67 -> 0 | O66: =O67-N67 -> 0 | P66: =P67-O67 -> 0 | Q66: =Q67-P67 -> 0 | ... BG66: =BG67-BF67 -> 72655.65
C67: Service Building | D67: 145311.3 | E67: 1800 | F67: 45650 | G67: 45663 | H67: Cum Planned Value Cost | BF67: 12109.28 | BG67: 84764.93
C68: Guard Room 1 | D68: 14157.2 | E68: 940.5 | F68: 45650 | G68: 45663 | H68: Planned Value Cost | I68: =I69 -> 0 | J68: =J69-I69 -> 0 | K68: =K69-J69 -> 0 | L68: =L69-K69 -> 0 | M68: =M69-L69 -> 0 | N68: =N69-M69 -> 0 | O68: =O69-N69 -> 0 | P68: =P69-O69 -> 0 | Q68: =Q69-P69 -> 0 | ... BG68: =BG69-BF69 -> 7078.6
C69: Guard Room 1 | D69: 14157.2 | E69: 940.5 | F69: 45650 | G69: 45663 | H69: Cum Planned Value Cost | BF69: 1179.77 | BG69: 8258.37
C70: Guard Room 2 | D70: 15094.3 | E70: 939.5 | F70: 45650 | G70: 45663 | H70: Planned Value Cost | I70: =I71 -> 0 | J70: =J71-I71 -> 0 | K70: =K71-J71 -> 0 | L70: =L71-K71 -> 0 | M70: =M71-L71 -> 0 | N70: =N71-M71 -> 0 | O70: =O71-N71 -> 0 | P70: =P71-O71 -> 0 | Q70: =Q71-P71 -> 0 | ... BG70: =BG71-BF71 -> 7547.15
C71: Guard Room 2 | D71: 15094.3 | E71: 939.5 | F71: 45650 | G71: 45663 | H71: Cum Planned Value Cost | BF71: 1257.86 | BG71: 8805.01
C72: Pump Room | D72: 134905.7 | E72: 800 | F72: 45650 | G72: 45663 | H72: Planned Value Cost | I72: =I73 -> 0 | J72: =J73-I73 -> 0 | K72: =K73-J73 -> 0 | L72: =L73-K73 -> 0 | M72: =M73-L73 -> 0 | N72: =N73-M73 -> 0 | O72: =O73-N73 -> 0 | P72: =P73-O73 -> 0 | Q72: =Q73-P73 -> 0 | ... BG72: =BG73-BF73 -> 67452.85
C73: Pump Room | D73: 134905.7 | E73: 800 | F73: 45650 | G73: 45663 | H73: Cum Planned Value Cost | BF73: 11242.14 | BG73: 78694.99
C74: Engineering | D74: 0 | E74: 0 | F74: 45650 | G74: 45656 | H74: Planned Value Cost | I74: =I75 -> 0 | J74: =J75-I75 -> 0 | K74: =K75-J75 -> 0 | L74: =L75-K75 -> 0 | M74: =M75-L75 -> 0 | N74: =N75-M75 -> 0 | O74: =O75-N75 -> 0 | P74: =P75-O75 -> 0 | Q74: =Q75-P75 -> 0 | ... BG74: =BG75-BF75 -> 0
C75: Engineering | D75: 0 | E75: 0 | F75: 45650 | G75: 45656 | H75: Cum Planned Value Cost
C76: Demobilization | D76: 0 | E76: 1898 | F76: 45657 | G76: 45663 | H76: Planned Value Cost | I76: =I77 -> 0 | J76: =J77-I77 -> 0 | K76: =K77-J77 -> 0 | L76: =L77-K77 -> 0 | M76: =M77-L77 -> 0 | N76: =N77-M77 -> 0 | O76: =O77-N77 -> 0 | P76: =P77-O77 -> 0 | Q76: =Q77-P77 -> 0 | ... BG76: =BG77-BF77 -> 0
C77: Demobilization | D77: 0 | E77: 1898 | F77: 45657 | G77: 45663 | H77: Cum Planned Value Cost
L78: =L79-#REF! -> #REF! | M78: =M79-F79 -> 0 | N78: =N79-G79 -> 0 | O78: =O79-H79 -> 0
L79: =L80-#REF! -> #REF! | M79: =M80-F80 -> 0 | N79: =N80-G80 -> 0 | O79: =O80-H80 -> 0
L80: =L81-#REF! -> #REF! | M80: =M81-F81 -> 0 | N80: =N81-G81 -> 0 | O80: =O81-H81 -> 0
L81: =L82-#REF! -> #REF! | M81: =M82-F82 -> 0 | N81: =N82-G82 -> 0 | O81: =O82-H82 -> 0
L82: =L83-#REF! -> #REF! | M82: =M83-F83 -> 0 | N82: =N83-G83 -> 0 | O82: =O83-H83 -> 0

Sheet Progress
A1: Project Scope Statement | B1: The project scope covers the construction of the Low Process RBF Unit, Outside Mosque, Pump Shed, and GRP Water Tank, including site preparation works (demolition, excavation, and backfilling), concrete and masonry works, thermal and waterproofing systems, installation of doors and windows, finishing works, and specialties. It also includes pre-engineered structures, mechanical systems (sanitary, water supply, HVAC, and firefighting), and electrical systems such as substations, distribution networks, lighting, power, telecom, fire alarm, and solar power. | S1: ='General Information'!$K$1 -> Data Date | T1: ='General Information'!L1 -> 46308
A4: Earned Value Progress (SAR) | K4: Physical Progress (Effort)
A5: WBS | C5: BOQ Value (SAR) | D5: % Wt. | E5: Weekly (SAR) | G5: To Date (SAR) | K5: Budgeted | L5: % Wt. | M5: Weekly Physical Progress | O5: To Date Physical Progress
E6: Planned | F6: Earned | G6: Crushed | H6: Planned | I6: Earned | K6: (Manhours) | M6: Planned | N6: Earned | O6: Planned | P6: Earned
A7: MOBILIZATION | D7: =IF(ISBLANK(C7),"",C7/$C$24) | E7: 0 | F7: 0 | K7: 8972.8 | L7: =IF(ISBLANK(K7),"",K7/$K$24) -> 0.04 | M7: 0 | N7: 0 | O7: 8972.8 | P7: 8972.8
A8: ENGINEERING | C8: 281825.22 | D8: =IF(ISBLANK(C8),"",C8/$C$24) -> 0.029497725 | E8: 0 | F8: 0 | G8: 281825 | H8: 281825 | I8: 281825 | K8: 8972.8 | L8: =IF(ISBLANK(K8),"",K8/$K$24) -> 0.04 | M8: 0 | N8: 0 | O8: 8972.8 | P8: 8972.8
A9: PROCUREMENT | C9: 2536427 | D9: =IF(ISBLANK(C9),"",C9/$C$24) -> 0.26547953 | E9: 152357 | F9: 0 | G9: 2536427 | H9: 2457598 | I9: 2536427 | K9: 26918.4 | L9: =IF(ISBLANK(K9),"",K9/$K$24) -> 0.12 | M9: 171.13 | N9: 0 | O9: 26338.75 | P9: 26918.4
A10: CONSTRUCTION | C10: =SUM(C11:C21) -> 5780468.4 | D10: =IF(ISBLANK(C10),"",C10/$C$24) -> 0.60502275 | E10: =SUM(E11:E21) -> 229430 | F10: =SUM(F11:F21) -> 217344 | G10: =SUM(G11:G21) -> 5780468 | H10: =SUM(H11:H21) -> 4443858 | I10: =SUM(I11:I21) -> 5719639 | K10: =SUM(K11:K21) -> 171136 | L10: =IF(ISBLANK(K10),"",K10/$K$24) -> 0.76291013 | M10: =SUM(M11:M21) -> 6888 | N10: =SUM(N11:N21) -> 1689.6 | O10: =SUM(O11:O21) -> 132160 | P10: =SUM(P11:P21) -> 168498.56
A11: Site Works | C11: 682299 | D11: =IF(ISBLANK(C11),"",C11/$C$24) -> 0.071414008 | E11: 48693 | F11: 0 | G11: 682299 | H11: 189310 | I11: 682299 | K11: 10600 | L11: =IF(ISBLANK(K11),"",K11/$K$24) -> 0.047253923 | M11: 1552 | N11: 0 | O11: 5528 | P11: 10600
A12: Concrete | C12: 508590 | D12: =IF(ISBLANK(C12),"",C12/$C$24) -> 0.053232454 | E12: 0 | F12: 0 | G12: 508590 | H12: 508590 | I12: 508590 | K12: 38936 | L12: =IF(ISBLANK(K12),"",K12/$K$24) -> 0.17357347 | M12: 0 | N12: 0 | O12: 38936 | P12: 38936
A13: Masonry Work | C13: 25032 | D13: =IF(ISBLANK(C13),"",C13/$C$24) -> 0.0026200177 | E13: 699 | F13: 0 | G13: 25032 | H13: 25032 | I13: 25032 | K13: 4992 | L13: =IF(ISBLANK(K13),"",K13/$K$24) -> 0.022253923 | M13: 384 | N13: 0 | O13: 4992 | P13: 4992
A14: Metal Works | C14: 43560 | D14: =IF(ISBLANK(C14),"",C14/$C$24) -> 0.0045592829 | E14: 2160 | F14: 0 | G14: 43560 | H14: 8640 | I14: 43560 | K14: 1288 | L14: =IF(ISBLANK(K14),"",K14/$K$24) -> 0.0057417974 | M14: 96 | N14: 0 | O14: 384 | P14: 1288
A15: Thermal & Moisture Protection | C15: 114132 | D15: =IF(ISBLANK(C15),"",C15/$C$24) -> 0.011945824 | E15: 2911 | F15: 0 | G15: 114132 | H15: 104262 | I15: 114132 | K15: 5984 | L15: =IF(ISBLANK(K15),"",K15/$K$24) -> 0.026676177 | M15: 560 | N15: 0 | O15: 4880 | P15: 5984
A16: Doors and Windows | C16: 198780 | D16: =IF(ISBLANK(C16),"",C16/$C$24) -> 0.020805653 | E16: 63746 | F16: 0 | G16: 198780 | H16: 150146 | I16: 198780 | K16: 8048 | L16: =IF(ISBLANK(K16),"",K16/$K$24) -> 0.035877318 | M16: 1432 | N16: 0 | O16: 2584 | P16: 8048
A17: Finishes | C17: 173460 | D17: =IF(ISBLANK(C17),"",C17/$C$24) -> 0.018155492 | E17: 3633 | F17: 0 | G17: 173460 | H17: 14069 | I17: 173460 | K17: 11200 | L17: =IF(ISBLANK(K17),"",K17/$K$24) -> 0.049928673 | M17: 480 | N17: 0 | O17: 2560 | P17: 11200
A18: Specialties | C18: 27450 | D18: =IF(ISBLANK(C18),"",C18/$C$24) -> 0.0028731018 | E18: 0 | F18: 0 | G18: 27450 | H18: 0 | I18: 27450 | K18: 1392 | L18: =IF(ISBLANK(K18),"",K18/$K$24) -> 0.0062054208 | M18: 0 | N18: 0 | O18: 0 | P18: 1392
A19: Pre Engineered Structure | C19: 1223640 | D19: =IF(ISBLANK(C19),"",C19/$C$24) -> 0.1280744 | E19: 0 | F19: 0 | G19: 1223640 | H19: 1223640 | I19: 1188960 | K19: 18224 | L19: =IF(ISBLANK(K19),"",K19/$K$24) -> 0.081241084 | M19: 0 | N19: 0 | O19: 18224 | P19: 16640
A20: Mechanical Work | C20: 1175904 | D20: =IF(ISBLANK(C20),"",C20/$C$24) -> 0.12307803 | E20: 6048 | F20: 201600 | G20: 1175904 | H20: 1099852 | I20: 1175904 | K20: 29328 | L20: =IF(ISBLANK(K20),"",K20/$K$24) -> 0.1307418 | M20: 592 | N20: 1152 | O20: 24816 | P20: 29328
A21: Electrical Work | C21: 1607621.4 | D21: =IF(ISBLANK(C21),"",C21/$C$24) -> 0.16826448 | E21: 101540 | F21: 15744 | G21: 1607621 | H21: 1120317 | I21: 1581472 | K21: 41144 | L21: =IF(ISBLANK(K21),"",K21/$K$24) -> 0.18341655 | M21: 1792 | N21: 537.6 | O21: 29256 | P21: 40090.56
A22: Close-Out | C22: =C23 -> 955413.4 | D22: =IF(ISBLANK(C22),"",C22/$C$24) -> 0.1 | E22: =E23 -> 0 | F22: =F23 -> 1281 | G22: =G23 -> 955413 | H22: =H23 -> 0 | I22: =I23 -> 724624 | K22: =K23 -> 8320 | L22: =IF(ISBLANK(K22),"",K22/$K$24) -> 0.037089872 | M22: =M23 -> 0 | N22: =N23 -> 89.6 | O22: =O23 -> 0 | P22: =P23 -> 3161.6
A23: Close-Out | C23: 955413.4 | D23: =IF(ISBLANK(C23),"",C23/$C$24) -> 0.1 | E23: 0 | F23: 1281 | G23: 955413 | H23: 0 | I23: 724624 | K23: 8320 | L23: =IF(ISBLANK(K23),"",K23/$K$24) -> 0.037089872 | M23: 0 | N23: 89.6 | O23: 0 | P23: 3161.6
B24: Total | C24: =C8+C9+C10+C22 -> 9554134 | D24: =D8+D9+D10+D22 -> 1 | E24: =E7+E8+E9+E10+E22 -> 381787 | F24: =F7+F8+F9+F10+F22 -> 218625 | G24: =G7+G8+G9+G10+G22 -> 9554133 | H24: =H7+H8+H9+H10+H22 -> 7183281 | I24: =I7+I8+I9+I10+I22 -> 9262515 | K24: =K7+K8+K9+K10+K22 -> 224320 | L24: =L7+L8+L9+L10+L22 -> 1 | M24: =M7+M8+M9+M10+M22 -> 7059.13 | N24: =N7+N8+N9+N10+N22 -> 1779.2 | O24: =O7+O8+O9+O10+O22 -> 176444.35 | P24: =P7+P8+P9+P10+P22 -> 216524.16
E25: =E24/$C$24 -> 0.039960398 | F25: =F24/$C$24 -> 0.022882765 | G25: =G24/$C$24 -> 0.9999999 | H25: =H24/$C$24 -> 0.75185056 | I25: =I24/$C$24 -> 0.96947719 | M25: =M24/$K$24 -> 0.031469017 | N25: =N24/$K$24 -> 0.0079315264 | O25: =O24/$K$24 -> 0.78657431 | P25: =P24/$K$24 -> 0.96524679
LT63: 623.33 | LU63: 1246.67 | LV63: 1870 | LW63: 1870 | LX63: 2493.33 | LY63: 3116.67 | LZ63: 3740 | MA63: 4363.33 | MB63: 4986.67 | MC63: 5610 | MD63: 5610 | ME63: 6233.33 | MF63: 6856.67 | MG63: 7480
MA65: 316.33 | MB65: 316.33 | MC65: 316.33 | ME65: 316.33 | MF65: 316.33 | MG65: 316.33
MA66: 316.33 | MB66: 632.67 | MC66: 949 | MD66: 949 | ME66: 1265.33 | MF66: 1581.67 | MG66: 1898

Sheet Weekly Photos
B1: Date | C1: ='Weekly Progress Report'!AG1 -> 46308
B4: Pump Room Works
B23: Pump Room Works
B42: Pump Room Works

Sheet FIR Summary
A2: Project Name | C2: Construction Of Industrial Units For Artisans In Najran
A3: Project ID | C3: cv | E3: Project Budget | F3: 9554134 | I3: 266865
A4: Date Pariod | C4: Start Date | D4: 46300 | E4: To | F4: Data Date | G4: 46306
A6: BOQ Item # | B6: BOQ Description | C6: FIR # | D6: Date | E6: FIR Description | F6: Unit Rate | G6: Current Period Quantity | H6: Total (SR) | I6: Comments
A8: 9.1.2 | B8: Supply and install carpet rolls to prayer room including all the accessories to complete the work with approved quality by the Client as shown in the drawings and specifications | C8: NJR1-05-005-LBC-TS9-1-ARC-FIR--0062-00 | D8: 46295 | E8: Supply and install carpet rolls to prayer room including all the accessories to complete the work with approved quality by the Client as shown in the drawings and specifications | F8: 330 | G8: 51.6 | H8: 17028
A9: 9.1.6 | B9: Supply and install wood skirt 100mm height as shown in the drawings and specifications | C9: NJR1-05-005-LBC-TS9-1-ARC-FIR--0063-00 | D9: 46295 | E9: Supply and install wood skirt 100mm height as shown in the drawings and specifications | F9: 35 | G9: 38.2 | H9: 1337
A10: 11.1.5 | B10: Installation pump shed and leak test | C10: NJR1-05-005-LBC-TS9-1-CVL-FIR--0154-00 | D10: 46295 | E10: Installation pump shed and leak test | F10: 35000 | G10: 0.5 | H10: 17500
A11: 15.1.1 | B11: Installing, Testing & Commissioning: fire pump sequence | C11: NJR1-05-005-LBC-TS9-1-MECH-FIR-0059-00 | D11: 46298 | E11: Installing, Testing & Commissioning: fire pump sequence | F11: 420000 | G11: 0.55 | H11: 231000
H12: 0
H13: 0
A15: Total Period Amount | H15: 266865
A16: Previous weekly reports amount | H16: 8999964.7
A17: Accomulative Amount | H17: 9266829.7

Sheet Quality
B2: QC OBSERVATIONS CHECKLIST
B6: Project No. | E6: ='General Information'!C4 -> NJR1-05-005 | K6: OBS No. | O6: =ROUNDUP(BC6/7,0)-4 -> 29 | U6: Inspection Day: | X6: ='General Information'!L1 -> 46308 | BC6: =(X6-Milestones!C6+1) -> 225
B8: Project | E8: ='General Information'!C3 -> Construction of Industrial Units for Artisans in Najran | O8: Contractor: Consultant: | U8: LABENAT AL BENA EGIS
B10: 4 | D10: Excellent | G10: Quality Management System is being practiced and applies to MODON System | Z10: 90 - 100 | AB10: QC Overall Score | AC10: =Q49 -> 0.88775862 | AN10: =SUM(Z10:Z13) -> 0 | AO10: 100 | AP10: 0.22883295
B11: 3 | D11: Good | G11: Evidence of compliance with plans and procedures. | Z11: 80 - 89 | AN11: =SUM(Y10:Y14) -> 0 | AO11: 89 | AP11: 0.20366133
B12: 2 | D12: Average | G12: Indication level of compliance with standards but there is room for improvement | Z12: 70 - 79 | AO12: 79 | AP12: 0.18077803
B13: 1 | D13: Improve | G13: Quality and Control is NOT being managed effectively. Needs Improvement | Z13: ≤ 69 | AO13: 69 | AP13: 0.15789474
B14: 0 | D14: N/A | G14: Item was not applicable or this item was not reviewed during the inspection. | Z14: Zero | AO14: 100 | AP14: 0.22883295
B16: No. | C16: Topic | K16: E (4) | L16: G (3) | M16: A (2) | N16: I (1) | O16: N/A (0) | Q16: No. | R16: Topic | Z16: E (4) | AA16: G (3) | AB16: A (2) | AC16: I (1) | AD16: N/A (0) | AO16: =SUM(AO10:AO15) -> 437
K17: 1 | L17: 0.89 | M17: 0.79 | N17: 0.69 | O17: 1 | Z17: 1 | AA17: 0.89 | AB17: 0.79 | AC17: 0.69 | AD17: 1 | AF17: =SUM(AF18:AG46)/COUNT(AF18:AG46) -> 0.88775862
B18: 1 | C18: Control of Access to Site/Office | L18: 1 | M18: 0 | N18: 0 | Q18: 30 | R18: QC of Excavation | Z18: 0 | AA18: 1 | AF18: =SUMPRODUCT($K$17:$O$17,K18:O18) -> 0.89 | AG18: =SUMPRODUCT($Z$17:$AD$17,Z18:AD18) -> 0.89 | AV18: Item Count | AW18: Score | AX18: Distributtion
B19: 2 | C19: Document Control Administration | L19: 0 | M19: 1 | Q19: 31 | R19: QC of Roads/Round about | AD19: 1 | AF19: =SUMPRODUCT($K$17:$O$17,K19:O19) -> 0.79 | AG19: =SUMPRODUCT($Z$17:$AD$17,Z19:AD19) -> 1 | AX19: Overall | AY19: Relevant
B20: 3 | C20: Project Documents and Progress | L20: 1 | Q20: 32 | R20: QC of Interlock & Curbstone | AD20: 1 | AF20: =SUMPRODUCT($K$17:$O$17,K20:O20) -> 0.89 | AG20: =SUMPRODUCT($Z$17:$AD$17,Z20:AD20) -> 1 | AM20: 4 | AN20: =58 -> 58 | AO20: counts | AQ20: 4 | AR20: Excellent | AV20: =SUM(Z18:Z46,K18:K46) -> 0 | AW20: =AQ20*AV20 -> 0 | AX20: =AV20/$AV$25 -> 0 | AY20: =AV20/SUM($AV$20:$AV$23) -> 0
B21: 4 | C21: Contractor's Quality Plan/CM (Updated and Reviewed) | L21: 1 | Q21: 33 | R21: Layers/Backfilling Sampling | Z21: 0 | AA21: 1 | AB21: 0 | AC21: 0 | AF21: =SUMPRODUCT($K$17:$O$17,K21:O21) -> 0.89 | AG21: =SUMPRODUCT($Z$17:$AD$17,Z21:AD21) -> 0.89 | AM21: 3 | AN21: =58 -> 58 | AO21: counts | AQ21: 3 | AR21: Good | AV21: =SUM(L18:L46,AA18:AA46) -> 28 | AW21: =AQ21*AV21 -> 84 | AX21: =AV21/$AV$25 -> 0.48275862 | AY21: =AV21/SUM($AV$20:$AV$23) -> 0.68292683
B22: 5 | C22: MS Log and Paperwork | L22: 1 | Q22: 34 | R22: Pump Stations Units | AB22: 1 | AD22: 0 | AF22: =SUMPRODUCT($K$17:$O$17,K22:O22) -> 0.89 | AG22: =SUMPRODUCT($Z$17:$AD$17,Z22:AD22) -> 0.79 | AM22: 2 | AN22: =58 -> 58 | AO22: counts | AQ22: 2 | AR22: Average | AV22: =SUM(M18:M46,AB18:AB46) -> 6 | AW22: =AQ22*AV22 -> 12 | AX22: =AV22/$AV$25 -> 0.10344828 | AY22: =AV22/SUM($AV$20:$AV$23) -> 0.14634146 | BC22: NB: Insert 1, or 0 in the required cell only.
B23: 6 | C23: RFI, FIR, & MIR Procedure | L23: 1 | Q23: 35 | R23: Quality of Form Work | AA23: 1 | AB23: 0 | AC23: 0 | AD23: 0 | AF23: =SUMPRODUCT($K$17:$O$17,K23:O23) -> 0.89 | AG23: =SUMPRODUCT($Z$17:$AD$17,Z23:AD23) -> 0.89 | AM23: 1 | AN23: =58 -> 58 | AO23: counts | AQ23: 1 | AR23: Improve | AV23: =SUM(N18:N46,AC18:AC46) -> 7 | AW23: =AQ23*AV23 -> 7 | AX23: =AV23/$AV$25 -> 0.12068966 | AY23: =AV23/SUM($AV$20:$AV$23) -> 0.17073171
B24: 7 | C24: RFI, FIR, & MIR Inventory system | L24: 1 | Q24: 36 | R24: Design Change List | AD24: 1 | AF24: =SUMPRODUCT($K$17:$O$17,K24:O24) -> 0.89 | AG24: =SUMPRODUCT($Z$17:$AD$17,Z24:AD24) -> 1 | AM24: 0 | AN24: =58 -> 58 | AO24: counts | AQ24: 0 | AR24: N/A | AV24: =SUM(O18:O46,AD18:AD46) -> 17 | AW24: =AQ24*AV24 -> 0 | AX24: =AV24/$AV$25 -> 0.29310345 | AY24: -
B25: 8 | C25: NCRs Control & Procedure | L25: 1 | Q25: 37 | R25: Quality of Concrete Placing | AA25: 1 | AB25: 0 | AD25: 0 | AF25: =SUMPRODUCT($K$17:$O$17,K25:O25) -> 0.89 | AG25: =SUMPRODUCT($Z$17:$AD$17,Z25:AD25) -> 0.89 | AR25: Total | AV25: =SUM(AV20:AV24) -> 58 | AW25: =SUM(AW20:AW24) -> 103 | AX25: =SUM(AX20:AX24) -> 1 | AY25: =SUM(AY20:AY24) -> 1
B26: 9 | C26: NCR Log | L26: 1 | Q26: 38 | R26: Concrete Surface Finishing | AB26: 1 | AD26: 0 | AF26: =SUMPRODUCT($K$17:$O$17,K26:O26) -> 0.89 | AG26: =SUMPRODUCT($Z$17:$AD$17,Z26:AD26) -> 0.79
B27: 10 | C27: MODON Standard* | L27: 1 | M27: 0 | Q27: 39 | R27: Pedestals/Columns/Beams Alignment | AA27: 1 | AD27: 0 | AF27: =SUMPRODUCT($K$17:$O$17,K27:O27) -> 0.89 | AG27: =SUMPRODUCT($Z$17:$AD$17,Z27:AD27) -> 0.89 | AV27: Maz Score Available: | AW27: =SUM(AV20:AV23)*AQ20 -> 164 | AX27: <- Excludes N/A items
B28: 11 | C28: Project Risk Plan/Management* | L28: 1 | M28: 0 | N28: 0 | Q28: 40 | R28: Siporex Lifting & Unloading | AD28: 1 | AF28: =SUMPRODUCT($K$17:$O$17,K28:O28) -> 0.89 | AG28: =SUMPRODUCT($Z$17:$AD$17,Z28:AD28) -> 1
B29: 12 | C29: Monthly Quality Reports* | L29: 1 | M29: 0 | O29: 0 | Q29: 41 | R29: Siporex Quality Pre-installation | AD29: 1 | AF29: =SUMPRODUCT($K$17:$O$17,K29:O29) -> 0.89 | AG29: =SUMPRODUCT($Z$17:$AD$17,Z29:AD29) -> 1
B30: 13 | C30: ITP | L30: 1 | M30: 0 | Q30: 42 | R30: Siporex Finishing Quality | AD30: 1 | AF30: =SUMPRODUCT($K$17:$O$17,K30:O30) -> 0.89 | AG30: =SUMPRODUCT($Z$17:$AD$17,Z30:AD30) -> 1 | AR30: Total Score | AW30: Percentage (%)
B31: 14 | C31: MODON Weekly Report | L31: 1 | Q31: 43 | R31: Roads / Parking Markings | AD31: 1 | AF31: =SUMPRODUCT($K$17:$O$17,K31:O31) -> 0.89 | AG31: =SUMPRODUCT($Z$17:$AD$17,Z31:AD31) -> 1 | AN31: =MAX(AN20:AN24) -> 58 | AR31: =AW25 -> 103 | AW31: =SUM(100/AR33*AR31) -> 62.804878 | AY31: %
B32: 15 | C32: Design Change Official Paperwork* | L32: 0 | O32: 1 | Q32: 44 | R32: QC of Finishing Outdoors | AD32: 1 | AF32: =SUMPRODUCT($K$17:$O$17,K32:O32) -> 1 | AG32: =SUMPRODUCT($Z$17:$AD$17,Z32:AD32) -> 1 | AR32: Max Score Available | BP32: 31
B33: 16 | C33: Design Change was Applied* | L33: 0 | O33: 1 | Q33: 45 | R33: Quality of Finishing Indoors | AD33: 1 | AF33: =SUMPRODUCT($K$17:$O$17,K33:O33) -> 1 | AG33: =SUMPRODUCT($Z$17:$AD$17,Z33:AD33) -> 1 | AR33: =AW27 -> 164 | BP33: 32
B34: 17 | C34: Material List | L34: 0 | M34: 1 | Q34: 46 | R34: Stairs Quality | AD34: 1 | AF34: =SUMPRODUCT($K$17:$O$17,K34:O34) -> 0.79 | AG34: =SUMPRODUCT($Z$17:$AD$17,Z34:AD34) -> 1 | BP34: 33
B35: 18 | C35: Pending Material Status | L35: 1 | Q35: 47 | R35: Tanks Method Statement Work | AC35: 1 | AD35: 0 | AF35: =SUMPRODUCT($K$17:$O$17,K35:O35) -> 0.89 | AG35: =SUMPRODUCT($Z$17:$AD$17,Z35:AD35) -> 0.69 | BP35: 34
B36: 19 | C36: Lifting Plan* | L36: 1 | Q36: 48 | R36: Electric Rooms | AD36: 1 | AF36: =SUMPRODUCT($K$17:$O$17,K36:O36) -> 0.89 | AG36: =SUMPRODUCT($Z$17:$AD$17,Z36:AD36) -> 1 | BP36: 35
B37: 20 | C37: DWG Log | L37: 1 | Q37: 49 | R37: QC of MCC/ATS Plant Units | AD37: 1 | AF37: =SUMPRODUCT($K$17:$O$17,K37:O37) -> 0.89 | AG37: =SUMPRODUCT($Z$17:$AD$17,Z37:AD37) -> 1 | BP37: 36
B38: 21 | C38: Invoice Status | L38: 1 | O38: 0 | Q38: 50 | R38: Qualified Subcontractor | AA38: 0 | AC38: 1 | AF38: =SUMPRODUCT($K$17:$O$17,K38:O38) -> 0.89 | AG38: =SUMPRODUCT($Z$17:$AD$17,Z38:AD38) -> 0.69 | BP38: 37
B39: 22 | C39: Site Handover Letter | L39: 0 | O39: 1 | Q39: 51 | R39: Scaffold/Ladders/Slope/Bridge Compliance | AC39: 1 | AD39: 0 | AF39: =SUMPRODUCT($K$17:$O$17,K39:O39) -> 1 | AG39: =SUMPRODUCT($Z$17:$AD$17,Z39:AD39) -> 0.69 | BP39: 38
B40: 23 | C40: Material Testing Results & Certification | L40: 0 | M40: 1 | N40: 0 | Q40: 52 | R40: Protection Applied to Completed Work | Z40: 0 | AA40: 0 | AB40: 1 | AF40: =SUMPRODUCT($K$17:$O$17,K40:O40) -> 0.79 | AG40: =SUMPRODUCT($Z$17:$AD$17,Z40:AD40) -> 0.79
B41: 24 | C41: As Build Drawings Status* | O41: 1 | Q41: 53 | R41: Storage Management in/out Control | Z41: 0 | AA41: 1 | AF41: =SUMPRODUCT($K$17:$O$17,K41:O41) -> 1 | AG41: =SUMPRODUCT($Z$17:$AD$17,Z41:AD41) -> 0.89
B42: 25 | C42: Calibrated Lab Tools & Equipment | L42: 0 | N42: 1 | Q42: 54 | R42: Material Control | AA42: 1 | AB42: 0 | AF42: =SUMPRODUCT($K$17:$O$17,K42:O42) -> 0.69 | AG42: =SUMPRODUCT($Z$17:$AD$17,Z42:AD42) -> 0.89
B43: 26 | C43: Storage Inventory System | L43: 0 | N43: 1 | O43: 0 | Q43: 55 | R43: Manholes Storing and Quality | AD43: 1 | AF43: =SUMPRODUCT($K$17:$O$17,K43:O43) -> 0.69 | AG43: =SUMPRODUCT($Z$17:$AD$17,Z43:AD43) -> 1
B44: 27 | C44: Logistics Plan | L44: 0 | N44: 1 | Q44: 56 | R44: Reinforced Steel Quality | AA44: 1 | AD44: 0 | AF44: =SUMPRODUCT($K$17:$O$17,K44:O44) -> 0.69 | AG44: =SUMPRODUCT($Z$17:$AD$17,Z44:AD44) -> 0.89
B45: 28 | C45: Project Progress Planview | L45: 1 | Q45: 57 | R45: Safety Overview | Z45: 0 | AA45: 1 | AB45: 0 | AF45: =SUMPRODUCT($K$17:$O$17,K45:O45) -> 0.89 | AG45: =SUMPRODUCT($Z$17:$AD$17,Z45:AD45) -> 0.89
B46: 29 | C46: Sufficient Number of QC Inspectors | L46: 0 | N46: 1 | Q46: 58 | R46: Waste Management Control | Z46: 0 | AA46: 1 | AB46: 0 | AF46: =SUMPRODUCT($K$17:$O$17,K46:O46) -> 0.69 | AG46: =SUMPRODUCT($Z$17:$AD$17,Z46:AD46) -> 0.89
O47: 0
I48: Score
M49: *QC % | Q49: =AF17 -> 0.88775862
B51: Prepared by: | Q51: Issued to PM: | V51: ='General Information'!C9 -> Eng. Ahmed Kotbi
B53: *QC Observations refer only to the practices and documentation observed at time of inspection. The responsibility of the CM and Contractor is to ensure that aspects of Quality are suitably managed. *Scores are a reflection of the general site conditions based upon the findings at the time of the walk through *If Applicable

Sheet Quality-Stat
A1: Quality Reports
A2: Item | C2: Issued | D2: Closed | E2: Pending | F2: Avg. Closing (Days) | G2: Pending
G3: 0-10 Days | H3: 11-20 Days | I3: 21-30 Days | J3: 31-60 Days | K3: > 60 Days
A5: Non Conforomance Report (NCR) | C5: 17 | D5: 17 | E5: =+C5-D5 -> 0 | F5: 3 | G5: 0 | H5: 0 | I5: 0 | J5: 0 | K5: 0
A6: Site Instruction (SI) | C6: 18 | D6: 18 | E6: =+C6-D6 -> 0 | F6: 3 | G6: 0 | H6: 0 | I6: 0 | J6: 0 | K6: 0
A7: Material Inspection Report (MIR) | C7: 64 | D7: 64 | E7: =+C7-D7 -> 0 | F7: 3 | G7: 0 | H7: 0 | I7: 0 | J7: 0 | K7: 0
A8: Field Inspection Report (FIR) | C8: 407 | D8: 407 | E8: =+C8-D8 -> 0 | F8: 3 | G8: 0 | H8: 0 | I8: 0 | J8: 0 | K8: 0
A10: Shop Drawings
A11: Item Per WBS | D11: Total Planned | E11: Total Drawings Submitted | J11: Remaining Drawings | K11: Pending | L11: Total Submittals
E12: A | F12: B | G12: C | H12: D | I12: Approved | J12: with Designer | K12: Submittals With Consultant
A13: Structural | D13: 19 | E13: 19 | F13: 0 | G13: 0 | I13: =SUM(E13:F13) -> 19 | J13: =D13-I13 -> 0 | K13: 0 | L13: =SUM(E13:H13)+K13 -> 19
A14: Architectural | D14: 15 | E14: 15 | F14: 0 | G14: 0 | I14: =SUM(E14:F14) -> 15 | J14: =D14-I14 -> 0 | K14: 0 | L14: =SUM(E14:H14)+K14 -> 15
A15: Mechanical, Electrical , & External Infra | D15: 47 | E15: 47 | F15: 0 | G15: 0 | I15: =SUM(E15:F15) -> 47 | J15: =D15-I15 -> 0 | K15: 0 | L15: =SUM(E15:H15)+K15 -> 47
A16: Road | D16: 12 | E16: 12 | F16: 0 | G16: 0 | I16: =SUM(E16:F16) -> 12 | J16: =D16-I16 -> 0 | K16: 0 | L16: =SUM(E16:H16)+K16 -> 12
A19: TOTAL | D19: =SUM(D13:D18) -> 93 | E19: =SUM(E13:E18) -> 93 | F19: =SUM(F13:F18) -> 0 | G19: =SUM(G13:G18) -> 0 | H19: =SUM(H13:H18) -> 0 | I19: =SUM(I13:I18) -> 93 | J19: =SUM(J13:J18) -> 0 | K19: =SUM(K13:K18) -> 0 | L19: =SUM(L13:L18) -> 93
A22: Material Approval
A23: Item Per WBS | D23: Total Planned | E23: Total Materials Submitted | J23: Remaining to approve | K23: Pending | L23: Total Submittals
E24: A | F24: B | G24: C | H24: D | I24: Approved | J24: with Designer | K24: Submittals With Consultant
A25: Earthworks | D25: 8 | E25: 8 | F25: 0 | I25: =SUM(E25:F25) -> 8 | J25: =D25-I25 -> 0 | K25: 0 | L25: =SUM(E25:H25)+K25 -> 8
A26: Structural | D26: 14 | E26: 14 | F26: 0 | I26: =SUM(E26:F26) -> 14 | J26: =D26-I26 -> 0 | K26: 0 | L26: =SUM(E26:H26)+K26 -> 14
A27: Architectural | D27: 23 | E27: 23 | F27: 0 | I27: =SUM(E27:F27) -> 23 | J27: =D27-I27 -> 0 | K27: 0 | L27: =SUM(E27:H27)+K27 -> 23
A28: Mechanical | D28: 28 | E28: 28 | F28: 0 | I28: =SUM(E28:F28) -> 28 | J28: =D28-I28 -> 0 | K28: 0 | L28: =SUM(E28:H28)+K28 -> 28
A29: Electrical | D29: 22 | E29: 22 | F29: 0 | I29: =SUM(E29:F29) -> 22 | J29: =D29-I29 -> 0 | K29: 0 | L29: =SUM(E29:H29)+K29 -> 22
A30: TOTAL | D30: =SUM(D25:D29) -> 95 | E30: =SUM(E25:E29) -> 95 | F30: =SUM(F25:F29) -> 0 | G30: =SUM(G25:G29) -> 0 | H30: =SUM(H25:H29) -> 0 | I30: =SUM(I25:I29) -> 95 | J30: =SUM(J25:J29) -> 0 | K30: =SUM(K25:K29) -> 0 | L30: =SUM(L25:L29) -> 95
A32: Procurement Summary
A33: Item Per WBS | D33: Total Materials Planned | E33: Total Number of P.O. | F33: Actual P.O. To Date | G33: Remaining P.O | H33: Actual Material on Site | I33: Remaining Materials | J33: Material Delivery Completion (Date)
E34: A | F34: B | G34: C | H34: D | I34: Processed
A35: Earthworks | D35: 8 | E35: =+D35 -> 8 | F35: 8 | G35: =E35-F35 -> 0 | H35: 8 | I35: =+E35-H35 -> 0 | J35: 46270
A36: Structural | D36: 14 | E36: =+D36 -> 14 | F36: 14 | G36: =E36-F36 -> 0 | H36: 14 | I36: =+E36-H36 -> 0 | J36: 46228
A37: Architectural | D37: 23 | E37: =+D37 -> 23 | F37: 23 | G37: 0 | H37: 23 | I37: =+E37-H37 -> 0 | J37: 46270
A38: Mechanical | D38: 28 | E38: =+D38 -> 28 | F38: 28 | G38: =E38-F38 -> 0 | H38: 28 | I38: =+E38-H38 -> 0 | J38: 46274
A39: Electrical | D39: 22 | E39: =+D39 -> 22 | F39: 22 | G39: =E39-F39 -> 0 | H39: 22 | I39: =+E39-H39 -> 0 | J39: 46233
A40: TOTAL | D40: =SUM(D35:D39) -> 95 | E40: =SUM(E35:E39) -> 95 | F40: =SUM(F35:F39) -> 95 | G40: =SUM(G35:G39) -> 0 | H40: =SUM(H35:H39) -> 95 | I40: =SUM(I35:I39) -> 0 | J40: =MAX(J35:J39) -> 46274
A42: Consultant Quality Inspections / Observations (Weekly Basis) | I42: Overall Average | J42: =AVERAGE(E44:E118) -> 0.88775862 | L42: Average Closing | M42: =AVERAGE(G44:G118) -> 1
A43: Week Number | B43: Date of Audit | C43: Date Issued | D43: Numbers Of Comments | E43: Quality Score | F43: Date Closed | G43: Closure Duration | I43: This Week Score | J43: =Quality!AC10 -> 0.88775862 | L43: Average Number of Comments Per Audit | M43: =AVERAGE(D44:D118) -> 0
A44: Week-1 | B44: 46118 | C44: 46118 | D44: 0 | E44: 0.88775862 | F44: =C44+1 -> 46119 | G44: =F44-C44 -> 1
A45: Week-2 | B45: 46125 | C45: =B45 -> 46125 | D45: 0 | E45: 0.88775862 | F45: =C45+1 -> 46126 | G45: =F45-C45 -> 1
A46: Week-3 | B46: 46132 | C46: =B46 -> 46132 | D46: 0 | E46: 0.88775862 | F46: =C46+1 -> 46133 | G46: =F46-C46 -> 1
A47: Week-4 | B47: 46139 | C47: =B47 -> 46139 | D47: 0 | E47: 0.88775862 | F47: =C47+1 -> 46140 | G47: =F47-C47 -> 1
A48: Week-5 | B48: 46146 | C48: =B48 -> 46146 | D48: 0 | E48: 0.88775862 | F48: =C48+1 -> 46147 | G48: =F48-C48 -> 1
A49: Week-6 | B49: 46153 | C49: =B49 -> 46153 | D49: 0 | E49: 0.88775862 | F49: =C49+1 -> 46154 | G49: =F49-C49 -> 1
A50: Week-7 | B50: 46160 | C50: =B50 -> 46160 | D50: 0 | E50: 0.88775862 | F50: =C50+1 -> 46161 | G50: =F50-C50 -> 1
A51: Week-8 | B51: 46166 | C51: =B51 -> 46166 | D51: 0 | E51: 0.88775862 | F51: =C51+1 -> 46167 | G51: =F51-C51 -> 1
A52: Week-9 | B52: 46174 | C52: =B52 -> 46174 | D52: 0 | E52: 0.88775862 | F52: =C52+1 -> 46175 | G52: =F52-C52 -> 1
A53: Week-10 | B53: 46181 | C53: =B53 -> 46181 | D53: 0 | E53: 0.88775862 | F53: =C53+1 -> 46182 | G53: =F53-C53 -> 1
A54: Week-11 | B54: 46188 | C54: =B54 -> 46188 | D54: 0 | E54: 0.88775862 | F54: =C54+1 -> 46189 | G54: =F54-C54 -> 1
A55: Week-12 | B55: 46195 | C55: =B55 -> 46195 | D55: 0 | E55: 0.88775862 | F55: =C55+1 -> 46196 | G55: =F55-C55 -> 1
A56: Week-13 | B56: 46202 | C56: =B56 -> 46202 | D56: 0 | E56: 0.88775862 | F56: =C56+1 -> 46203 | G56: =F56-C56 -> 1
... A65: Week-22 | B65: 46265 | C65: =B65 -> 46265 | D65: 0 | E65: 0.88775862 | F65: =C65+1 -> 46266 | G65: =F65-C65 -> 1
A66: Week-23 | B66: 46272 | C66: =B66 -> 46272 | D66: 0 | E66: =E65 -> 0.88775862 | F66: =C66+1 -> 46273 | G66: =F66-C66 -> 1
A67: Week-24 | B67: 46279 | C67: =B67 -> 46279 | D67: 0 | E67: =E66 -> 0.88775862 | F67: =C67+1 -> 46280 | G67: =F67-C67 -> 1
A68: Week-25 | B68: 46286 | C68: =B68 -> 46286 | D68: 0 | E68: =E67 -> 0.88775862 | F68: =C68+1 -> 46287 | G68: =F68-C68 -> 1
A69: Week-26 | B69: 46293 | C69: =B69 -> 46293 | D69: 0 | E69: =E68 -> 0.88775862 | F69: =C69+1 -> 46294 | G69: =F69-C69 -> 1
A70: Week-27 | B70: 46300 | C70: =B70 -> 46300 | D70: 0 | E70: =E69 -> 0.88775862 | F70: =C70+1 -> 46301 | G70: =F70-C70 -> 1
A71: Week-28 | B71: 46307 | C71: =B71 -> 46307 | D71: 0 | E71: =E70 -> 0.88775862 | F71: =C71+1 -> 46308 | G71: =F71-C71 -> 1
A72: Week-29
A73: Week-30
A74: Week-31
A75: Week-32
A76: Week-33
A77: Week-34
A78: Week-35
A79: Week-36
A80: Week-37
A81: Week-38
A82: Week-39
A83: Week-40
... A118: Week-75

Sheet HSE
B1: MODON HSE Site Inspection Report
B2: Date | E2: 46307 | L2: Inspected By:
B4: Project ID. | E4: NJR1-05-005 | L4: Report No. | P4: 29 | W4: MODON PM Name | Y4: Eng. Ahmed Kotbi
B6: Project Name: | E6: Construction of Industrial Units for Artisans in Najran | L6: Contractor: | R6: Labenat Al Bena | X6: Safety Performance | AA6: 2 | AE6: 0.83
B8: Inspections are a snapshot in time and refer only to the practices and documentation observed at the time of the Inspection. It remains the responsibility of the Consultant and Contractor to ensure that all aspects of Health & Safety are suitably managed.
B9: 1 | D9: Good Practice | H9: 2 | I9: Need Improvement | T9: 3 | U9: Fail (Life Threatening Activity) / Comliance with Plan & Procedures | X9: N/A | Y9: Atcitty Not Applicable for this Site Inspection Report
B11: No. | C11: Topic | K11: Wt. | L11: HSE Compliance | S11: No. | T11: Topic | AB11: Wt. | AC11: HSE Compliance
B13: 1 | C13: Access and Egress - (General access to site, segregated from vehicles, / Overhead protection, while entering into the building /Adequate lighting provided when dark or overnight work) | K13: 0.05 | L13: 1 | S13: 14 | T13: Work at Height - (PPE/Fall Protection(Same level, above and blow) / Training / Fall restraint / competency /Safe access & egress to and from work at height / Ladders / Openings (floor/shafts/Provision of emergency rescue) | AB13: 0.05 | AC13: N/A | AP13: 1 | AR13: 100 | AU13: 1
B14: 2 | C14: Traffic Management - (Loading/unloading/sheeting/temp. routes/speed/parking/competence) | K14: 0.03 | L14: 1 | S14: 15 | T14: Scaffolding - (Temp. Scaffolding Work-platform (All types) - qualified scaffolder / Inspection / Tagged / Safe Access/egress / PTW/Falsework & Formwork) | AB14: 0.04 | AC14: N/A | AP14: 2 | AR14: 75 | AU14: 2
B15: 3 | C15: Site Signage - (Project Notice Board & General Signage) | K15: 0.02 | L15: 1 | S15: 16 | T15: Mobile Elevated Work platform (MEWP) - (PTW/competence requirements/conditions/inspections/tagged/training/Full-body harness) | AB15: 0.04 | AC15: N/A | AP15: 3 | AR15: 0 | AU15: 3
B16: 4 | C16: PPE Compliance - (Use, storage, stock, handling & checks - Head, Foot, Eye, Hearing) | K16: 0.05 | L16: 2 | S16: 17 | T16: Excavation & Trenches - (PTW/Edge protection/buffer zone/Slope/Benching/Shoring/Geo-tech report/Atmospheric hazards/Acess&egress/Emergency management / MS&RA/H.E) | AB16: 0.03 | AC16: N/A | AU16: N/A
B17: 5 | C17: Housekeeping - (Material correctly stored/Rubbish cleaned & removed daily/slips & trips hazards) | K17: 0.03 | L17: 2 | S17: 18 | T17: Confined Space - (PTW/Training/competence/Emergency Management/MS & RA/Safe access/egress) | AB17: 0.05 | AC17: N/A
B18: 6 | C18: Storage of Materials - (Transporting, storage, training and use - Combustible / Flammable / Hazardous substances (COSHH) | L18: 2 | S18: 19 | T18: Fire Protection - (Flammable/Oxy. LPG /Combustible separated/FE's/Flashback arrestor/Sparks & slags/Smoking area/PTW/Generators/MS & RA/Emergency Management) | AC18: 1 | AL18: Red | AM18: Serious injury or death (immediately)
B19: 7 | C19: Site Waste Management - (Hazardous waste /Combustible waste / Human waste / Construction waste - asphalt, cable, timber, paving roof sheeting tiles, plastic & bricks) | L19: 2 | S19: 20 | T19: Health & Welfare - (Adequate drinking water/shaded - eating & rest area/washing & sanitary facilities/Certified FA/FA Box & Stock/adequate toilets/Ambulance) | AC19: 2 | AL19: Yellow | AM19: Minor or near miss (3 days to comply)
B20: 8 | C20: Health Surveillance - (Expose to excessive noise/vibration/dust/silica/CO/cement/radiation/extreme weather condition) | K20: 0.03 | L20: 1 | S20: 21 | T20: Environmental Incident Measures - (Spill/ Leakage / Concrete wash / vehicle & eqpts. wash / waste disposal/Sewers and drains/emissions/Emergency Management/Training/site run-off water) | AB20: 0.05 | AC20: 1 | AL20: Green | AM20: No issues
B21: 9 | C21: Electrical Safety - (Electrical qualified /RCD/GFCI/Industrial Cocket/LOTO/Cable-overhung or buried/Cords in good condition/current inspection tag) | K21: 0.05 | L21: 2 | S21: 22 | T21: HSE Communications & Meetings - (Schedule HSE Meetings/Safety Committee meetings/Alerts / Lesson learned/Safety Bulletin contains latest HSE KPI) | AB21: 0.05 | AC21: 2
B22: 10 | C22: Tools & Equipment - (Includes, powered, hydraulic & pneumatic/Guards in place/Properly stored/RCD Protection/Earthed/Good condition & tagged) | K22: 0.03 | L22: 2 | S22: 23 | T22: HSE Plan & Associated Procedures - (Approved updated HSE Plan/ CEMP/HAZComm/Procedures/Standards/Project Safety Risk Register) | AB22: 0.03 | AC22: 2 | AL22: 26 points > 4 minors then is it’s a serious issue
B23: 11 | C23: Manual Handling - (Lifting/loading/pulling/pushing/twisting/awkward posture/repetitive task/frequent and prolong physical effort/Reasonable practicable use of mechanical aid) | K23: 0.03 | L23: 1 | S23: 24 | T23: Health, Safety & Environment Incident reporting - (Review of HSE Statistics, Reporting of Unsafe Act & Conditions/ Reporting of Near Miss incident/Reporting of FA cases/Record MT cases) | AB23: 0.03 | AC23: 2
B24: 12 | C24: Vehicle and mobile equipment / Plant - (dumpers; excavators, cranes, piling rigs, grader, roller, loaders/condition/KSA License/certification) | K24: 0.05 | L24: 1 | S24: 25 | T24: HSE Awareness, Training & Competence - (Policy /Objective & targets/Information, training/Climatic condition awareness/Reponses in emergency situation/ Safety Behavior Observation) | AB24: 0.04 | AC24: 1
B25: 13 | C25: Lifting Operations & Rigging - (Lifting Plan/Lifting devices & gears/PTW/Condition/3rd party certification/bank-man/rigger/slingers/man-basket/inspection record/tagged) | L25: N/A | S25: 26 | T25: Project Leadership Site Tours - (Provide evidence of proactive safety performance/Deficient discovered discussed/Positive feedback/Workers resolving safety issues) | AC25: 1
B27: Prepared by: | G27: =U2 -> 0 | S27: Sent to MODON PM: | X27: =Y4 -> Eng. Ahmed Kotbi
B28: Safety Results
B29: 1 | D29: =COUNTIF(L13:Q26,"1")+COUNTIF(AB13:AG26,"1") -> 10 | I29: 2 | L29: =COUNTIF(L13:Q26,"2")+COUNTIF(AB13:AG26,"2") -> 10 | U29: 3 | W29: =COUNTIF(L13:Q26,"3")+COUNTIF(AB13:AG26,"3") -> 0

Sheet HSE-Stat
A1: Safety Statistics
A3: Category | B3: Item | D3: This Week | E3: This Month | F3: Year to Date | G3: Cumulative
A4: Category | B4: Total Hours Worked | D4: 1920 | E4: 3960 | F4: 82166 | G4: 82166
B5: Safe Hours Worked | D5: 2040 | E5: 3960 | F5: 82166 | G5: 82166
A6: Reactive | B6: LTI | D6: 0 | E6: 0 | F6: 0 | G6: 0
B7: MTC (Healed w/o Disability) | D7: 0 | E7: 0 | F7: 0 | G7: 0
B8: MTC (Healed w/ Disability) | D8: 0 | E8: 0 | F8: 0 | G8: 0
B9: Near Miss | D9: 0 | E9: 0 | F9: 9 | G9: 0
B10: First Aid Cases | D10: 0 | E10: 2 | F10: 2 | G10: 2
B11: Fatality | D11: 0 | E11: 0 | F11: 0 | G11: 0
B12: Fire Incident Cases | D12: 0 | E12: 0 | F12: 0 | G12: 0
B13: Vehicle Incident | D13: 0 | E13: 0 | F13: 0 | G13: 0
B14: Property Damages | D14: 0 | E14: 0 | F14: 0 | G14: 0
A15: Proactive | B15: Induction Training | D15: 1 | E15: 1 | F15: 49 | G15: 49
B16: No.of Internal Training | D16: 0 | E16: 0 | F16: 4 | G16: 4
B17: No.of Internal Audit | D17: 0 | E17: 0 | F17: 1 | G17: 1
B18: No. of Toolbox Talks | D18: 1 | E18: 2 | F18: 27 | G18: 27
B19: Safety Awards/Incentives | D19: 1 | E19: 1 | F19: 3 | G19: 3
I20: Category | J20: Item | L20: This Week | M20: This Month | N20: Year to Date | O20: Cumulative
A22: Consultant Safety Inspection (Weekly Basis) | I22: Overall Average | J22: 0.82
A23: Week Number | B23: Date of Audit | C23: Date Issued | D23: Numbers Of Comments | E23: Overall Score | F23: Date Closed | G23: Closure Duration | I23: This Week Score | J23: 0.83
A24: Week-1 | B24: 46118 | C24: =B24 -> 46118 | D24: 0 | E24: 0.84090909 | F24: =C24+1 -> 46119 | G24: =F24-C24 -> 1
A25: Week-2 | B25: 46125 | C25: =B25 -> 46125 | D25: 0 | E25: 0.84090909 | F25: =C25+1 -> 46126 | G25: =F25-C25 -> 1
A26: Week-3 | B26: 46132 | C26: =B26 -> 46132 | D26: 0 | E26: 0.84090909 | F26: =C26+1 -> 46133 | G26: =F26-C26 -> 1
A27: Week-4 | B27: 46139 | C27: =B27 -> 46139 | D27: 0 | E27: 0.84090909 | F27: =C27+1 -> 46140 | G27: =F27-C27 -> 1
A28: Week-5 | B28: 46146 | C28: =B28 -> 46146 | D28: 0 | E28: 0.84090909 | F28: =C28+1 -> 46147 | G28: =F28-C28 -> 1
A29: Week-6 | B29: 46153 | C29: =B29 -> 46153 | D29: 0 | E29: 0.84090909 | F29: =C29+1 -> 46154 | G29: =F29-C29 -> 1
A30: Week-7 | B30: 46160 | C30: =B30 -> 46160 | D30: 0 | E30: 0.84090909 | F30: =C30+1 -> 46161 | G30: =F30-C30 -> 1
A31: Week-8 | B31: 46166 | C31: =B31 -> 46166 | D31: 0 | E31: 0.84090909 | F31: =C31+1 -> 46167 | G31: =F31-C31 -> 1
A32: Week-9 | B32: 46174 | C32: =B32 -> 46174 | D32: 0 | E32: 0.84090909 | F32: =C32+1 -> 46175 | G32: =F32-C32 -> 1
A33: Week-10 | B33: 46181 | C33: =B33 -> 46181 | D33: 0 | E33: 0.84090909 | F33: =C33+1 -> 46182 | G33: =F33-C33 -> 1
A34: Week-11 | B34: 46188 | C34: =B34 -> 46188 | D34: 0 | E34: 0.84090909 | F34: =C34+1 -> 46189 | G34: =F34-C34 -> 1
A35: Week-12 | B35: 46195 | C35: =B35 -> 46195 | D35: 0 | E35: 0.84090909 | F35: =C35+1 -> 46196 | G35: =F35-C35 -> 1
... A37: Week-14 | B37: 46209 | C37: =B37 -> 46209 | D37: 0 | E37: 0.84090909 | F37: =C37+1 -> 46210 | G37: =F37-C37 -> 1
A38: Week-15 | B38: 46216 | C38: 46216 | D38: 0 | E38: 0.82 | F38: 46216 | G38: 1
A39: Week-16 | B39: 46223 | C39: 46223 | D39: 0 | E39: 0.83 | F39: =C39+1 -> 46224 | G39: 1
A40: Week-17 | B40: 46230 | C40: 46230 | D40: 0 | E40: 0.83 | F40: =C40+1 -> 46231 | G40: 1
A41: Week-18 | B41: 46237 | C41: =B41 -> 46237 | D41: 0 | E41: 0.83 | F41: =C41+1 -> 46238 | G41: 1
A42: Week-19 | B42: 46244 | C42: =B42 -> 46244 | D42: 0 | E42: 0.83 | F42: =C42+1 -> 46245 | G42: 1
A43: Week-20 | B43: 46251 | C43: =B43 -> 46251 | D43: 0 | E43: 0.83 | F43: =C43+1 -> 46252 | G43: 1
A44: Week-21 | B44: 46258 | C44: =B44 -> 46258 | D44: 0 | E44: 0.83 | F44: =C44+1 -> 46259 | G44: 1
A45: Week-22 | B45: 46265 | C45: =B45 -> 46265 | D45: 0 | E45: 0.83 | F45: =C45+1 -> 46266 | G45: 1
A46: Week-23 | B46: 46272 | C46: =B46 -> 46272 | D46: 0 | E46: 0.83 | F46: =C46+1 -> 46273 | G46: 1
A47: Week-24 | B47: 46279 | C47: =B47 -> 46279 | D47: 0 | E47: 0.83 | F47: =C47+1 -> 46280 | G47: 1
A48: Week-25 | B48: 46286 | C48: =B48 -> 46286 | D48: 0 | E48: 0.83 | F48: =C48+1 -> 46287 | G48: 1
A49: Week-26 | B49: 46293 | C49: =B49 -> 46293 | D49: 0 | E49: 0.83 | F49: =C49+1 -> 46294 | G49: 1
A50: Week-27 | B50: 46300 | C50: =B50 -> 46300 | D50: 0 | E50: 0.83 | F50: =C50+1 -> 46301 | G50: 1
A51: Week-28 | B51: 46307 | C51: =B51 -> 46307 | D51: 0 | E51: 0.83 | F51: =C51+1 -> 46308 | G51: 1
A52: Week-29
A53: Week-30
A54: Week-31
A55: Week-32
A56: Week-33
A57: Week-34
A58: Week-35
A59: Week-36
A60: Week-37
A61: Week-38
A62: Week-39
A63: Week-40
... A98: Week-75

Sheet Major Quantities
A1: BOQ Number | B1: Description of Item | C1: Total Quantity | D1: Unit of Measurement | E1: Plan To Date | F1: Actual To Date | G1: Remaining Total | H1: Variance
A2: 2.1.6 | B2: Backfill Material | C2: 2615 | D2: m3 | E2: =C2 -> 2615 | F2: =C2*1 -> 2615 | G2: =C2-F2 -> 0 | H2: =F2-E2 -> 0
A3: 2.2.1 | B3: Bituminous wearing course asphalt layer | C3: 217 | D3: m3 | F3: 217 | G3: =C3-F3 -> 0 | H3: =F3-E3 -> 217
A4: 2.2.2 | B4: Bituminous base course asphalt layer | C4: 304 | D4: m3 | F4: 304 | G4: =C4-F4 -> 0 | H4: =F4-E4 -> 304
A5: 2.2.3 | B5: Base course layer | C5: 867 | D5: m3 | E5: =C5*0.0667 -> 57.8289 | F5: =C5 -> 867 | G5: =C5-F5 -> 0 | H5: =F5-E5 -> 809.1711
A6: 2.2.4 | B6: Subgrade material | C6: 1300 | D6: m3 | E6: =C6*1 -> 1300 | F6: =C6 -> 1300 | G6: =C6-F6 -> 0 | H6: =F6-E6 -> 0
A7: 2.2.7.1 | B7: Interlocking block pavers | C7: 1326 | D7: m2 | F7: =C7*100% -> 1326 | G7: =C7-F7 -> 0 | H7: =F7-E7 -> 1326
A8: 2.3.8 | B8: Precast concrete curbstone | C8: 1294 | D8: Lm | E8: =C8*0.4658 -> 602.7452 | F8: =C8*1 -> 1294 | G8: =C8-F8 -> 0 | H8: =F8-E8 -> 691.2548
A9: 3.2 | B9: Reinforced concrete | C9: 449 | D9: m3 | E9: =C9*1 -> 449 | F9: =C9 -> 449 | G9: =C9-F9 -> 0 | H9: =F9-E9 -> 0
A10: 3.3 | B10: 150 mm thk concrete floor slab on grade | C10: 307 | D10: m3 | E10: =C10 -> 307 | F10: =C10 -> 307 | G10: =C10-F10 -> 0 | H10: =F10-E10 -> 0
A11: 3.4 | B11: Autoclaved aerated panel for slabs, external and internal walls and parapet | C11: 55 | D11: m2 | E11: =C11*1 -> 55 | F11: =C11 -> 55 | G11: =C11-F11 -> 0 | H11: =F11-E11 -> 0
A12: 4.1 | B12: Concrete Masonry Unit | C12: 444 | D12: m2 | E12: =C12*0.9721 -> 431.6124 | F12: =C12 -> 444 | G12: =C12-F12 -> 0 | H12: =F12-E12 -> 12.3876
A13: 15.1.2.1 | B13: 200 mm Ø HDPE Fire Fighting | C13: 48 | D13: Lm | E13: =C13 -> 48 | F13: =E13 -> 48 | G13: =C13-F13 -> 0 | H13: =F13-E13 -> 0
A14: 15.1.2.2 | B14: 150 mm Ø HDPE Fire Fighting | C14: 200 | D14: Lm | E14: =C14 -> 200 | F14: =C14*1 -> 200 | G14: =C14-F14 -> 0 | H14: =F14-E14 -> 0
A15: 15.2.2.1 | B15: 100 mm Ø HDPE Water Supply | C15: 20 | D15: Lm | E15: =C15*1 -> 20 | F15: =C15*1 -> 20 | G15: =C15-F15 -> 0 | H15: =F15-E15 -> 0
A16: 15.2.2.2 | B16: 90 mm Ø HDPE Water Supply | C16: 235 | D16: Lm | E16: =C16 -> 235 | F16: =C16*1 -> 235 | G16: =C16-F16 -> 0 | H16: =F16-E16 -> 0
A17: 15.2.2.3 | B17: 63 mm Ø HDPE Water Supply | C17: 8 | D17: Lm | E17: =C17*1 -> 8 | F17: =C17*1 -> 8 | G17: =C17-F17 -> 0 | H17: =F17-E17 -> 0
A18: 15.2.2.4 | B18: 50 mm Ø HDPE Water Supply | C18: 40 | D18: Lm | E18: =C18*1 -> 40 | F18: =C18*1 -> 40 | G18: =C18-F18 -> 0 | H18: =F18-E18 -> 0
A19: 15.3.2.1 | B19: 110 mm Pipe sewer upvc pipe | C19: 105 | D19: Lm | E19: =C19*1 -> 105 | F19: =C19 -> 105 | G19: =C19-F19 -> 0 | H19: =F19-E19 -> 0
A20: 15.3.2.2 | B20: 160 mm Pipe sewer upvc pipe | C20: 75 | D20: Lm | E20: =C20*1 -> 75 | F20: =C20 -> 75 | G20: =C20-F20 -> 0 | H20: =F20-E20 -> 0
A21: 15.4.1.1 | B21: 8" Ø Fire Fighting HDPE Pipes | C21: 15 | D21: Lm | E21: =C21*1 -> 15 | F21: =C21 -> 15 | G21: =C21-F21 -> 0 | H21: =F21-E21 -> 0
A22: 15.5.1.1 | B22: 63 mm Ø HDPE pipes Water Supply | C22: 40 | D22: Lm | E22: =C22*1 -> 40 | F22: =C22 -> 40 | G22: =C22-F22 -> 0 | H22: =F22-E22 -> 0
A23: 15.6.1.1 | B23: Ø 4" uPVC Pipe Sewer & Drainage | C23: 168 | D23: Lm | E23: =C23 -> 168 | F23: =C23*1 -> 168 | G23: =C23-F23 -> 0 | H23: =F23-E23 -> 0
A24: 15.6.1.2 | B24: Ø 3" uPVC Pipe Sewer & Drainage | C24: 30 | D24: Lm | E24: =C24 -> 30 | F24: =C24*1 -> 30 | G24: =C24-F24 -> 0 | H24: =F24-E24 -> 0
A25: 15.6.1.3 | B25: Ø 2" uPVC Pipe Sewer & Drainage | C25: 132 | D25: Lm | E25: =C25 -> 132 | F25: =C25*1 -> 132 | G25: =C25-F25 -> 0 | H25: =F25-E25 -> 0
A26: 15.6.1.4 | B26: Ø 1" uPVC Pipe Sewer & Drainage | C26: 180 | D26: Lm | E26: =C26 -> 180 | F26: =C26*1 -> 180 | G26: =C26-F26 -> 0 | H26: =F26-E26 -> 0
A27: 16.6.1 | B27: 4C x 185 mm2 +1C x 95mm2 Low voltage cables | C27: 120 | D27: Lm | E27: =C27*0.6667 -> 80.004 | F27: 120 | G27: =C27-F27 -> 0 | H27: =F27-E27 -> 39.996
A28: 16.6.2 | B28: 4C x 120 mm2 +1C x 70mm2 Low voltage cables | C28: 75 | D28: Lm | E28: =C28*0.6667 -> 50.0025 | F28: 75 | G28: =C28-F28 -> 0 | H28: =F28-E28 -> 24.9975

Sheet Risk Register
B2: Department: | K2: Status Date: | L2: ='General Information'!L1 -> 46308
B3: Program
B4: Project: | E4: ='General Information'!C3 -> Construction of Industrial Units for Artisans in Najran
B5: Project No.: | E5: ='General Information'!C4 -> NJR1-05-005
B6: Project Location: | E6: Najran, Saudi Arabia
R8: Before Treatment | AC8: Post Treatment
B9: Risk Data | H9: Category | K9: Risk Description | N9: Risk Control Dates | P9: Risk Manageability | Q9: Risk Proximity | R9: Most Likely | U9: Risk Owner | V9: Risk Response & Treatment Action | Z9: Treatment Control Dates | AC9: Most Likely | AF9: Treatment Status
B10: Risk ID | C10: Region | D10: Section / Group | E10: City | F10: Project ID | G10: Risk Status | H10: T/O/I | I10: Internal / External Level1 | J10: Category | K10: Cause / Source | L10: Risk | M10: Consequence / Effect | N10: Identified | O10: Closed | R10: Liklihood | S10: Impact | T10: Risk Score | V10: Risk Response Strategy | W10: Treatment Action | X10: Treatment Action Description | Y10: Treatment Action Owner | Z10: Start | AA10: Due | AB10: Closed | AC10: Liklihood | AD10: Impact | AE10: Risk Score
T13: =IF(AND(R13="Very Low",S13="Low"),"L1",IF(AND(R13="Low",S13="Low"),"L4",IF(OR(AND(R13="Very Low",S13="Low"),AND(R13="Low",S13="Very Low")),"L2",IF(OR(AND(R13="Medium",S13="Very Low"),AND(R13="Very Low",S13="Medium")),"L3",IF(OR(AND(R13="High",S13="Very Low"),AND(R13="Very Low",S13="High")),"L4",IF(OR(AND(R13="Very High",S13="Very Low"),AND(R13="Very Low",S13="Very High")),"M5",IF(OR(AND(R13="Low",S13="Medium"),AND(R13="Medium",S13="Low")),"M6",IF(OR(AND(R13="High",S13="Low"),AND(R13="Low",S13="High")),"M8",IF(AND(R13="Medium",S13="Medium"),"M9",IF(OR(AND(R13="Very High",S13="Low"),AND(R13="Low",S13="Very High")),"M10",IF(OR(AND(R13="High",S13="Medium"),AND(R13="Medium",S13="High")),"M12",IF(OR(AND(R13="Very High",S13="Medium"),AND(R13="Medium",S13="Very High")),"H15",IF(AND(R13="High",S13="High"),"H16",IF(OR(AND(R13="Very High",S13="High"),AND(R13="High",S13="Very High")),"H20",IF(AND(R13="Very High",S13="Very High"),"H25","")))))))))))))))
T14: =IF(AND(R14="Very Low",S14="Low"),"L1",IF(AND(R14="Low",S14="Low"),"L4",IF(OR(AND(R14="Very Low",S14="Low"),AND(R14="Low",S14="Very Low")),"L2",IF(OR(AND(R14="Medium",S14="Very Low"),AND(R14="Very Low",S14="Medium")),"L3",IF(OR(AND(R14="High",S14="Very Low"),AND(R14="Very Low",S14="High")),"L4",IF(OR(AND(R14="Very High",S14="Very Low"),AND(R14="Very Low",S14="Very High")),"M5",IF(OR(AND(R14="Low",S14="Medium"),AND(R14="Medium",S14="Low")),"M6",IF(OR(AND(R14="High",S14="Low"),AND(R14="Low",S14="High")),"M8",IF(AND(R14="Medium",S14="Medium"),"M9",IF(OR(AND(R14="Very High",S14="Low"),AND(R14="Low",S14="Very High")),"M10",IF(OR(AND(R14="High",S14="Medium"),AND(R14="Medium",S14="High")),"M12",IF(OR(AND(R14="Very High",S14="Medium"),AND(R14="Medium",S14="Very High")),"H15",IF(AND(R14="High",S14="High"),"H16",IF(OR(AND(R14="Very High",S14="High"),AND(R14="High",S14="Very High")),"H20",IF(AND(R14="Very High",S14="Very High"),"H25",""))))))))))))))) | AE14: =IF(AND(AC14="Very Low",AD14="Low"),"L1",IF(AND(AC14="Low",AD14="Low"),"L4",IF(OR(AND(AC14="Very Low",AD14="Low"),AND(AC14="Low",AD14="Very Low")),"L2",IF(OR(AND(AC14="Medium",AD14="Very Low"),AND(AC14="Very Low",AD14="Medium")),"L3",IF(OR(AND(AC14="High",AD14="Very Low"),AND(AC14="Very Low",AD14="High")),"L4",IF(OR(AND(AC14="Very High",AD14="Very Low"),AND(AC14="Very Low",AD14="Very High")),"M5",IF(OR(AND(AC14="Low",AD14="Medium"),AND(AC14="Medium",AD14="Low")),"M6",IF(OR(AND(AC14="High",AD14="Low"),AND(AC14="Low",AD14="High")),"M8",IF(AND(AC14="Medium",AD14="Medium"),"M9",IF(OR(AND(AC14="Very High",AD14="Low"),AND(AC14="Low",AD14="Very High")),"M10",IF(OR(AND(AC14="High",AD14="Medium"),AND(AC14="Medium",AD14="High")),"M12",IF(OR(AND(AC14="Very High",AD14="Medium"),AND(AC14="Medium",AD14="Very High")),"H15",IF(AND(AC14="High",AD14="High"),"H16",IF(OR(AND(AC14="Very High",AD14="High"),AND(AC14="High",AD14="Very High")),"H20",IF(AND(AC14="Very High",AD14="Very High"),"H25","")))))))))))))))
B18: NOTES:
B19: Risk Status: 1.Open, 2.Closed, or 3.Realized
B20: T/O/I: 1.Threat, 2.Opportunity, or 3.Issue
B22: Category (select 1):
B23: 1. Political
B24: 2. Legal, Regulatory, Compliance
B25: 3. Funding, Finance, Budget
B26: 4. Management, Governance, Policies, KPI, Performance
B27: 5. Human Resources
B28: 6. Stakeholders, Authorities, Approvals, Permits
B29: 7. Requirements, Specifications, Scope, Procurement, Contract
B30: 8. Process, Tools, Technique, Technology
... B46: Risk Level/Score: Likelihood x Highest Impact (Safety, Cost, Schedule, Environment, Quality, or Reputation. See Risk Scoring Matrix tab)

Sheet EV-Chart Data
B1: 9554134 | E1: 9554134 | K1: 0.85
B2: Baseline Plan (Original Plan) | E2: Baseline Plan (Crushed) | H2: Earned Value | K2: Gross Paid Value | N2: Forecast | Q2: Actual/Fcst vs Plan
A3: Month | B3: Monthly | C3: Cum | D3: % | E3: Monthly | F3: Cum | G3: % | H3: Monthly | I3: Cum | J3: % | K3: Monthly | L3: Cum | M3: % | N3: Monthly | O3: C um | Q3: Month | R3: Cum
A4: 46084 | B4: 134128.43 | C4: =B4 -> 134128.43 | D4: 0 | E4: 152202 | F4: =E4 -> 152202 | G4: 0 | I4: =H4 -> 0 | J4: =IF($E$1="",I4/$B$1,I4/$E$1) -> 0 | K4: 0 | L4: 0 | M4: 0 | Q4: =H4-E4 -> -152202 | R4: =Q4 -> -152202 | T4: Actuals thru previous month
A5: =EOMONTH(A4,1) -> 46142 | B5: 638522.06 | C5: =C4+B5 -> 772650.49 | D5: =C5/$B$1 -> 0.080870803 | E5: 692767 | F5: =F4+E5 -> 844969 | G5: =F5/$E$1 -> 0.088440145 | H5: 771218 | I5: 771218 | J5: 0.080720869 | K5: 0 | L5: 0 | M5: 0 | Q5: =H5-E5 -> 78451 | R5: =Q5+R4 -> -73751
A6: =EOMONTH(A5,1) -> 46173 | B6: 488657.03 | C6: =C5+B6 -> 1261307.5 | D6: =C6/$B$1 -> 0.13201694 | E6: 727104 | F6: =F5+E6 -> 1572073 | G6: =F6/$E$1 -> 0.16454375 | H6: =I6-I5 -> 652117 | I6: 1423335 | J6: =IF($E$1="",I6/$B$1,I6/$E$1) -> 0.14897583 | K6: 0 | L6: 0 | M6: 0 | Q6: =H6-E6 -> -74987 | R6: =Q6+R5 -> -148738 | T6: Forecast current and future months
A7: =EOMONTH(A6,1) -> 46203 | B7: 1356793.2 | C7: =C6+B7 -> 2618100.8 | D7: =C7/$B$1 -> 0.27402805 | E7: 1870539 | F7: =F6+E7 -> 3442612 | G7: =F7/$E$1 -> 0.36032695 | H7: =I7-I6 -> 2117547 | I7: 3540882 | J7: =IF($E$1="",I7/$B$1,I7/$E$1) -> 0.37061255 | K7: ='Invoice Log'!Y9 -> 180835 | L7: =K7 -> 180835 | M7: =IF($E$1="",L7/$B$1,L7/$E$1) -> 0.018927409 | Q7: =N7-E7 -> -1870539 | R7: =Q7+R6 -> -2019277
A8: =EOMONTH(A7,1) -> 46234 | B8: 2212825.2 | C8: =C7+B8 -> 4830925.9 | D8: =C8/$B$1 -> 0.50563724 | E8: 2737145 | F8: =F7+E8 -> 6179757 | G8: =F8/$E$1 -> 0.64681498 | H8: =I8-I7 -> 2201031 | I8: 5741913 | J8: =IF($E$1="",I8/$B$1,I8/$E$1) -> 0.60098728 | K8: ='Invoice Log'!Y10+'Invoice Log'!Y11 -> 1725541 | L8: =K8+L7 -> 1906376 | M8: =IF($E$1="",L8/$B$1,L8/$E$1) -> 0.19953415 | Q8: =N8-E8 -> -2737145 | R8: =Q8+R7 -> -4756422
A9: =EOMONTH(A8,1) -> 46265 | B9: 1046425.8 | C9: =C8+B9 -> 5877351.7 | D9: =C9/$B$1 -> 0.6151632 | E9: 2128922 | F9: =F8+E9 -> 8308679 | G9: =F9/$E$1 -> 0.86964229 | H9: 1921737.6 | I9: =I8+H9 -> 7663650.6 | J9: =IF($E$1="",I9/$B$1,I9/$E$1) -> 0.80212927 | K9: 2554234 | L9: =K9+L8 -> 4460610 | M9: =IF($E$1="",L9/$B$1,L9/$E$1) -> 0.46687748 | Q9: =N9-E9 -> -2128922 | R9: =Q9+R8 -> -6885344
A10: =EOMONTH(A9,1) -> 46295 | B10: 675374.23 | C10: =C9+B10 -> 6552725.9 | D10: =C10/$B$1 -> 0.68585242 | E10: 1245455 | F10: =F9+E10 -> 9554134 | G10: =F10/$E$1 -> 1 | H10: =I10-I9 -> 1281933.8 | I10: 8945584.3 | J10: =IF($E$1="",I10/$B$1,I10/$E$1) -> 0.93630509 | K10: 0 | L10: =K10+L9 -> 4460610 | M10: =IF($E$1="",L10/$B$1,L10/$E$1) -> 0.46687748 | Q10: =N10-E10 -> -1245455 | R10: =Q10+R9 -> -8130799
A11: =EOMONTH(A10,1) -> 46326 | B11: 1305544.6 | C11: =C10+B11 -> 7858270.5 | D11: =C11/$B$1 -> 0.82249951 | H11: =I11-I10 -> 316930.66 | I11: =Progress!I24 -> 9262515 | J11: =IF($E$1="",I11/$B$1,I11/$E$1) -> 0.96947719 | N11: =O11-I11 -> 291619 | O11: =E1 -> 9554134 | P11: =O11/$E$1 -> 1 | Q11: =N11-E11 -> 291619 | R11: =Q11+R10 -> -7839180 | U11: Extended Duration
A12: =EOMONTH(A11,1) -> 46356 | B12: 714502.65 | C12: =C11+B12 -> 8572773.1 | D12: =C12/$B$1 -> 0.89728416
A13: =EOMONTH(A12,1) -> 46387 | B13: 981360.86 | C13: =C12+B13 -> 9554134 | D13: =C13/$B$1 -> 1
A14: =EOMONTH(A13,1) -> 46418 | O14: =O11-E1 -> 0
A15: =EOMONTH(A14,1) -> 46446
A16: =EOMONTH(A15,1) -> 46477
A17: =EOMONTH(A16,1) -> 46507
A18: =EOMONTH(A17,1) -> 46538
B38: UPDATE ONLY YELLOW PORTION FROM PRIMAVERA EXPORT, IF NEEDED, EXTEND YELLOW PORTION BASED ON SCHEDULE.

Sheet Physical-Chart Data
B1: 224320 | E1: 241519.85
B2: Baseline Plan (Original Plan) | E2: Baseline Plan (Crushed) | H2: Earned Effort % | K2: Forecast | N2: Achieved/Fcst vs Plan
A3: Week | B3: Monthly Effort | C3: Cum Effort | D3: Plan Wt.% | E3: Weekly Effort | F3: Cum Effort | G3: Plan Wt.% | H3: Weekly Wt. | I3: Cum Wt. | J3: Achieved Wt.% | K3: Monthly Wt. | L3: Cum Wt. | M3: Wt.% | N3: Weekly Wt. | O3: Cum Wt.
A4: 46084 | B4: 14673.48 | C4: =B4 -> 14673.48 | D4: 0 | E4: 16022.45 | F4: =E4 -> 16022.45 | G4: 0 | I4: =H4 -> 0 | J4: =IF($E$1="",I4/$B$1,I4/$E$1) -> 0 | N4: =H4-E4 -> -16022.45 | O4: =N4 -> -16022.45 | Q4: Actuals thru previous month
A5: =EOMONTH(A4,1) -> 46142 | B5: 10034.32 | C5: =C4+B5 -> 24707.8 | D5: =C5/$B$1 -> 0.11014533 | E5: 12975.86 | F5: =F4+E5 -> 28998.31 | G5: =F5/$E$1 -> 0.12006595 | H5: =I5-I4 -> 26134.04 | I5: 26134.04 | J5: =IF($E$1="",I5/$B$1,I5/$E$1) -> 0.10820659 | N5: =H5-E5 -> 13158.18 | O5: =N5+O4 -> -2864.27
A6: =EOMONTH(A5,1) -> 46173 | B6: 17663.63 | C6: =C5+B6 -> 42371.43 | D6: =C6/$B$1 -> 0.18888833 | E6: 26862.13 | F6: =F5+E6 -> 55860.44 | G6: =F6/$E$1 -> 0.23128716 | H6: =I6-I5 -> 23650.35 | I6: 49784.39 | J6: =IF($E$1="",I6/$B$1,I6/$E$1) -> 0.2061296 | N6: =H6-E6 -> -3211.78 | O6: =N6+O5 -> -6076.05 | Q6: Forecast current and future months
A7: =EOMONTH(A6,1) -> 46203 | B7: 19366.49 | C7: =C6+B7 -> 61737.92 | D7: =C7/$B$1 -> 0.27522254 | E7: 44046.04 | F7: =F6+E7 -> 99906.48 | G7: =F7/$E$1 -> 0.41365743 | H7: =I7-I6 -> 51190.05 | I7: 100974.44 | J7: =IF($E$1="",I7/$B$1,I7/$E$1) -> 0.41807926 | N7: =K7-E7 -> -44046.04 | O7: =N7+O6 -> -50122.09
A8: =EOMONTH(A7,1) -> 46234 | B8: 46535.41 | C8: =C7+B8 -> 108273.33 | D8: =C8/$B$1 -> 0.48267355 | E8: 64090.97 | F8: =F7+E8 -> 163997.45 | G8: =F8/$E$1 -> 0.67902266 | H8: =I8-I7 -> 49570.01 | I8: 150544.45 | J8: =IF($E$1="",I8/$B$1,I8/$E$1) -> 0.62332123 | N8: =K8-E8 -> -64090.97 | O8: =N8+O7 -> -114213.06
A9: =EOMONTH(A8,1) -> 46265 | B9: 28434.85 | C9: =C8+B9 -> 136708.18 | D9: =C9/$B$1 -> 0.60943376 | E9: 64388.65 | F9: =F8+E9 -> 228386.1 | G9: =F9/$E$1 -> 0.94562041 | H9: 42830.35 | I9: =I8+H9 -> 193374.8 | J9: =IF($E$1="",I9/$B$1,I9/$E$1) -> 0.800658 | N9: =K9-E9 -> -64388.65 | O9: =N9+O8 -> -178601.71
A10: =EOMONTH(A9,1) -> 46295 | B10: 26122.93 | C10: =C9+B10 -> 162831.11 | D10: =C10/$B$1 -> 0.72588762 | E10: 13133.75 | F10: =F9+E10 -> 241519.85 | G10: =F10/$E$1 -> 1 | H10: =I10-I9 -> 20196.94 | I10: 213571.74 | J10: =IF($E$1="",I10/$B$1,I10/$E$1) -> 0.88428235 | N10: =K10-E10 -> -13133.75 | O10: =N10+O9 -> -191735.46
A11: =EOMONTH(A10,1) -> 46326 | B11: 32096.85 | C11: =C10+B11 -> 194927.96 | D11: =C11/$B$1 -> 0.86897272 | H11: =I11-I10 -> 2952.42 | I11: =Progress!P24 -> 216524.16 | J11: =IF($E$1="",I11/$B$1,I11/$E$1) -> 0.89650668 | K11: =L11-I11 -> 24995.69 | L11: =E1 -> 241519.85 | M11: =L11/$E$1 -> 1 | N11: =K11-E11 -> 24995.69 | O11: =N11+O10 -> -166739.77 | R11: Extended Duration
A12: =EOMONTH(A11,1) -> 46356 | B12: 19376 | C12: =C11+B12 -> 214303.96 | D12: =C12/$B$1 -> 0.95534932
A13: =EOMONTH(A12,1) -> 46387 | B13: 10016.04 | C13: =C12+B13 -> 224320 | D13: =C13/$B$1 -> 1
A14: =EOMONTH(A13,1) -> 46418
A15: =EOMONTH(A14,1) -> 46446
A16: =EOMONTH(A15,1) -> 46477
A17: =EOMONTH(A16,1) -> 46507
A18: =EOMONTH(A17,1) -> 46538
A19: =EOMONTH(A18,1) -> 46568
A20: =EOMONTH(A19,1) -> 46599
A21: =EOMONTH(A20,1) -> 46630
A22: =EOMONTH(A21,1) -> 46660
A23: =EOMONTH(A22,1) -> 46691
A24: =EOMONTH(A23,1) -> 46721
A25: =EOMONTH(A24,1) -> 46752
... A35: =EOMONTH(A34,1) -> 47057
B38: UPDATE ONLY YELLOW PORTION FROM PRIMAVERA EXPORT, IF NEEDED, EXTEND YELLOW PORTION BASED ON SCHEDULE.

Sheet Invoice Log
B1: Weekly Progress Report - Invoice Log | AJ1: Y
B2: Project Value | K2: Payment Status | S2: Invoices Summary | AC2: Average Invoices durations | AJ2: N
B3: Original Contract Value | E3: =Progress!C24 -> 9554134 | G3: O&M Value | I3: 0 | J3: EAC | K3: Advance Payment % | M3: 0 | O3: Advance Payment (SAR) | Q3: =E3*M3 -> 0 | S3: No of Submitted Invoices | U3: =MAX($C$9:$C$31) -> 6 | W3: Submitted Invoices (SAR) | Y3: =SUM(F9:F31) -> 7935744 | AA3: Submiited Invoice Peroid | AB3: =MAX(L9:L31) -> 46295 | AC3: CM / PgM Average Approval duration | AE3: =AVERAGE(P9:P32) -> 0 | AG3: Average Invoice Value | AH3: =AVERAGE(F9:F31) -> 1322624
B4: Revised Contract Value | D4: 21100000 | E4: =E3 -> 9554134 | G4: Revised O&M Value | I4: 0 | J4: =+#REF!+#REF!+I4 -> #REF! | K4: Retention % | M4: 0 | O4: Retention (SAR) | Q4: =E3*M4 -> 0 | S4: No of Approved Invoices (CM) | U4: =COUNTIF($N$9:$N$32,"Y") -> 6 | W4: Approved Invoices (CM) (SAR) | Y4: =SUMIF($N$9:$N$31,"Y",$F$9:$F$31) -> 7935744 | AC4: MODON PM & Accounts Average Approval duration | AE4: =AVERAGE(W9:W32) -> 0
B5: Estimate At Completion Value | D5: 20900000 | E5: =E4 -> 9554134 | F5: =+#REF!+#REF!+E5 -> #REF! | G5: Submitted Invoices (Gross Value) | I5: =F32 -> 7935744 | K5: Penalties and deduction % | M5: =ABS(M6/E3) -> 0.0020933347 | O5: AP Recovery (SAR) | Q5: =SUM(G9:G31) -> 0 | S5: No of Approved Invoices (PM) | U5: =COUNTIF($R$9:$R$32,"Y") -> 6 | W5: Approved Invoices (PM) (SAR) | Y5: =SUMIF($R$9:$R$31,"Y",$F$9:$F$31) -> 7935744 | AA5: Invoice Submitted Compared to Contract Value | AB5: =Y3/E4 -> 0.8306084 | AC5: Payments Average Duration | AE5: =AVERAGE(AA9:AA32) -> 26.75
B6: Potential Changes | D6: =D4-D5 -> 200000 | E6: =E4-E5 -> 0 | G6: Total Deduction | I6: =M6+Q6+Q5 -> -20000 | K6: Penalties and deduction (SAR) | M6: =SUM(I9:I31) -> -20000 | O6: Retention Cumulative (SAR) | Q6: =SUM(H9:H31) -> 0 | S6: No of Paid Invoices | U6: =COUNTA(X9:X32) -> 4 | W6: Paid Invoices (SAR) | Y6: =SUM(Y9:Y31) -> 4460610 | AC6: Invoices Average total Duration | AE6: =IFERROR(AVERAGE(AC9:AC32),"") -> 26.75
B7: Invoice Reference | F7: Invoice Value | K7: Period Covered | M7: CM / PgM Approval Timeline | Q7: Modon PM & Accounts Approval | X7: Payment Status | AC7: Total Invoice Duration | AD7: Remarks
B8: # | C8: Invoice No. | D8: Doc Control reference | E8: Submittal Rev. # | F8: Gross Value | G8: AP Recovery | H8: Retention | I8: Deduction / Penalties | J8: Amount (net) + VAT 15% | K8: Start Date | L8: End Date | M8: Date to CM / PgM | N8: CM / PgM Approval (Yes/No) | O8: CM / PgM Reply Date | P8: Days Elapsed | Q8: Date to PM | R8: PM Approval (Yes/No) | S8: PM Reply Date | T8: Date to Accounts | U8: Accounts Approval (Yes/No) | V8: Accounts Approval Date | W8: Days Elapsed | X8: Date Paid | Y8: Amount Paid | Z8: Paid % | AA8: Payment Period (d) | AB8: Amount Pending
B9: 1 | C9: 1 | D9: NJR1-01-007-LBC-TS9-1-PRW-IPC-0001-00 | F9: 180835 | G9: =IF(ISBLANK(F9),"",-F9*$M$3) -> 0 | H9: =IF(ISBLANK(F9),"",-F9*$M$4) -> 0 | I9: 0 | J9: =IF(ISBLANK(F9),"",(SUM(F9:I9)+(F9+G9)*0.15)) -> 207960.25 | K9: 46084 | L9: 46142 | M9: 46146 | N9: Y | O9: =M9 -> 46146 | P9: =IF(ISBLANK(O9),"",O9-M9) -> 0 | Q9: =O9 -> 46146 | R9: Y | S9: =Q9 -> 46146 | T9: =S9 -> 46146 | U9: Y | V9: =T9 -> 46146 | W9: =IF(ISBLANK(V9),"",V9-T9) -> 0 | X9: 46177 | Y9: =F9 -> 180835 | Z9: 0 | AA9: =IF(ISBLANK(X9),"",X9-V9) -> 31 | AB9: =IF(ISBLANK(Y9),"",(F9-Y9)) -> 0 | AC9: =IF(ISBLANK(X9),"",X9-M9) -> 31 | AH9: format if no, make shaded
B10: 2 | C10: 2 | D10: NJR1-05-005-LBC-TS9-1-PRW-IPC-0002-00 | F10: 318233 | G10: =IF(ISBLANK(F10),"",-F10*$M$3) -> 0 | H10: =IF(ISBLANK(F10),"",-F10*$M$4) -> 0 | I10: 0 | J10: =IF(ISBLANK(F10),"",(SUM(F10:I10)+(F10+G10)*0.15)) -> 365967.95 | K10: 46143 | L10: 46173 | M10: 46179 | N10: Y | O10: =M10 -> 46179 | P10: =IF(ISBLANK(O10),"",O10-M10) -> 0 | Q10: =O10 -> 46179 | R10: Y | S10: =Q10 -> 46179 | T10: =S10 -> 46179 | U10: Y | V10: =T10 -> 46179 | W10: =IF(ISBLANK(V10),"",V10-T10) -> 0 | X10: 46210 | Y10: =F10 -> 318233 | Z10: 0 | AA10: =IF(ISBLANK(X10),"",X10-V10) -> 31 | AB10: =IF(ISBLANK(Y10),"",(F10-Y10)) -> 0 | AC10: =IF(ISBLANK(X10),"",X10-M10) -> 31
B11: 3 | C11: 3 | D11: NJR1-05-005-LBC-TS9-1-PRW-IPC-0003-00 | F11: 1407308 | G11: =IF(ISBLANK(F11),"",-F11*$M$3) -> 0 | H11: =IF(ISBLANK(F11),"",-F11*$M$4) -> 0 | I11: 0 | J11: =IF(ISBLANK(F11),"",(SUM(F11:I11)+(F11+G11)*0.15))+1 -> 1618405.2 | K11: 46174 | L11: 46203 | M11: 46203 | N11: Y | O11: =M11 -> 46203 | P11: =IF(ISBLANK(O11),"",O11-M11) -> 0 | Q11: =O11 -> 46203 | R11: Y | S11: =Q11 -> 46203 | T11: =S11 -> 46203 | U11: Y | V11: =T11 -> 46203 | W11: =IF(ISBLANK(V11),"",V11-T11) -> 0 | X11: 46225 | Y11: =F11 -> 1407308 | Z11: 0 | AA11: =IF(ISBLANK(X11),"",X11-V11) -> 22 | AB11: =IF(ISBLANK(Y11),"",(F11-Y11)) -> 0 | AC11: =IF(ISBLANK(X11),"",X11-M11) -> 22
B12: 4 | C12: 4 | D12: NJR1-05-005-LBC-TS9-1-PRW-IPC-0004-00 | F12: 2554234 | G12: =IF(ISBLANK(F12),"",-F12*$M$3) -> 0 | H12: =IF(ISBLANK(F12),"",-F12*$M$4) -> 0 | I12: 0 | J12: =IF(ISBLANK(F12),"",(SUM(F12:I12)+(F12+G12)*0.15))+1 -> 2937370.1 | K12: 46204 | L12: 46234 | M12: 46235 | N12: Y | O12: =M12 -> 46235 | P12: =IF(ISBLANK(O12),"",O12-M12) -> 0 | Q12: =O12 -> 46235 | R12: Y | S12: =Q12 -> 46235 | T12: =S12 -> 46235 | U12: Y | V12: =T12 -> 46235 | W12: =IF(ISBLANK(V12),"",V12-T12) -> 0 | X12: 46258 | Y12: 2554234 | Z12: 0 | AA12: =IF(ISBLANK(X12),"",X12-V12) -> 23 | AB12: =IF(ISBLANK(Y12),"",(F12-Y12)) -> 0 | AC12: =IF(ISBLANK(X12),"",X12-M12) -> 23
B13: 5 | C13: 5 | D13: NJR1-05-005-LBC-TS9-1-PRW-IPC-0005-00 | F13: 2044391 | G13: =IF(ISBLANK(F13),"",-F13*$M$3) -> 0 | H13: =IF(ISBLANK(F13),"",-F13*$M$4) -> 0 | I13: -20000 | J13: =IF(ISBLANK(F13),"",(SUM(F13:I13)+(F13+G13)*0.15))-1 -> 2331048.6 | K13: 46235 | L13: 46265 | M13: 46266 | N13: Y | O13: =M13 -> 46266 | P13: =IF(ISBLANK(O13),"",O13-M13) -> 0 | Q13: =O13 -> 46266 | R13: Y | S13: =Q13 -> 46266 | T13: =S13 -> 46266 | U13: Y | V13: =T13 -> 46266 | W13: =IF(ISBLANK(V13),"",V13-T13) -> 0 | Y13: 0 | Z13: 0 | AA13: =IF(ISBLANK(X13),"",X13-V13) | AB13: =IF(ISBLANK(Y13),"",(F13-Y13)) -> 2044391 | AC13: =IF(ISBLANK(X13),"",X13-M13)
B14: 6 | C14: 6 | D14: NJR1-05-005-LBC-TS9-1-PRW-IPC-0006-00 | F14: 1430743 | G14: =IF(ISBLANK(F14),"",-F14*$M$3) -> 0 | H14: =IF(ISBLANK(F14),"",-F14*$M$4) -> 0 | I14: 0 | J14: =IF(ISBLANK(F14),"",(SUM(F14:I14)+(F14+G14)*0.15)) -> 1645354.4 | K14: 46266 | L14: 46295 | M14: 46305 | N14: Y | O14: =M14 -> 46305 | P14: =IF(ISBLANK(O14),"",O14-M14) -> 0 | Q14: =O14 -> 46305 | R14: Y | S14: =Q14 -> 46305 | T14: =S14 -> 46305 | U14: Y | V14: =T14 -> 46305 | W14: =IF(ISBLANK(V14),"",V14-T14) -> 0 | Y14: 0 | Z14: 0 | AA14: =IF(ISBLANK(X14),"",X14-V14) | AB14: =IF(ISBLANK(Y14),"",(F14-Y14)) -> 1430743 | AC14: =IF(ISBLANK(X14),"",X14-M14)
B15: 7
B16: 8
B17: 9
B18: 10
B19: 11
B20: 12
B21: 13
B22: 14
B23: 15
B24: 16
B25: 17
B26: 18
B27: 19 | G27: =IF(ISBLANK(F27),"",-F27*$M$3) | H27: =IF(ISBLANK(F27),"",-F27*$M$4) | J27: =IF(ISBLANK(F27),"",(SUM(F27:I27)+(F27+G27)*0.15)) | P27: =IF(ISBLANK(O27),"",O27-M27) | W27: =IF(ISBLANK(V27),"",V27-Q27) | Z27: =IF(ISBLANK(Y27),"",Y27/F27) | AA27: =IF(ISBLANK(X27),"",X27-V27) | AB27: =IF(ISBLANK(Y27),"",(F27-Y27)) | AC27: =IF(ISBLANK(X27),"",X27-M27)
B28: 20 | G28: =IF(ISBLANK(F28),"",-F28*$M$3) | H28: =IF(ISBLANK(F28),"",-F28*$M$4) | J28: =IF(ISBLANK(F28),"",(SUM(F28:I28)+(F28+G28)*0.15)) | P28: =IF(ISBLANK(O28),"",O28-M28) | W28: =IF(ISBLANK(V28),"",V28-Q28) | Z28: =IF(ISBLANK(Y28),"",Y28/F28) | AA28: =IF(ISBLANK(X28),"",X28-V28) | AB28: =IF(ISBLANK(Y28),"",(F28-Y28)) | AC28: =IF(ISBLANK(X28),"",X28-M28)
B29: 21 | G29: =IF(ISBLANK(F29),"",-F29*$M$3) | H29: =IF(ISBLANK(F29),"",-F29*$M$4) | J29: =IF(ISBLANK(F29),"",(SUM(F29:I29)+(F29+G29)*0.15)) | P29: =IF(ISBLANK(O29),"",O29-M29) | W29: =IF(ISBLANK(V29),"",V29-Q29) | Z29: =IF(ISBLANK(Y29),"",Y29/F29) | AA29: =IF(ISBLANK(X29),"",X29-V29) | AB29: =IF(ISBLANK(Y29),"",(F29-Y29)) | AC29: =IF(ISBLANK(X29),"",X29-M29)
B30: 22 | G30: =IF(ISBLANK(F30),"",-F30*$M$3) | H30: =IF(ISBLANK(F30),"",-F30*$M$4) | J30: =IF(ISBLANK(F30),"",(SUM(F30:I30)+(F30+G30)*0.15)) | P30: =IF(ISBLANK(O30),"",O30-M30) | W30: =IF(ISBLANK(V30),"",V30-Q30) | Z30: =IF(ISBLANK(Y30),"",Y30/F30) | AA30: =IF(ISBLANK(X30),"",X30-V30) | AB30: =IF(ISBLANK(Y30),"",(F30-Y30)) | AC30: =IF(ISBLANK(X30),"",X30-M30)
B31: 23 | G31: =IF(ISBLANK(F31),"",-F31*$M$3) | H31: =IF(ISBLANK(F31),"",-F31*$M$4) | J31: =IF(ISBLANK(F31),"",(SUM(F31:I31)+(F31+G31)*0.15)) | P31: =IF(ISBLANK(O31),"",O31-M31) | W31: =IF(ISBLANK(V31),"",V31-Q31) | Z31: =IF(ISBLANK(Y31),"",Y31/F31) | AA31: =IF(ISBLANK(X31),"",X31-V31) | AB31: =IF(ISBLANK(Y31),"",(F31-Y31)) | AC31: =IF(ISBLANK(X31),"",X31-M31)
E32: TOTAL | F32: =SUM(F9:F31) -> 7935744 | G32: =SUM(G9:G31) -> 0 | H32: =SUM(H9:H31) -> 0 | I32: =SUM(I9:I31) -> -20000 | J32: =SUM(J9:J31) -> 9106106.6 | P32: =IF(ISBLANK(O32),"",O32-M32) | W32: =IF(ISBLANK(V32),"",V32-Q32) | Y32: =SUM(Y9:Y31) -> 4460610 | AA32: =IF(ISBLANK(X32),"",X32-V32) | AB32: =SUM(AB9:AB31) -> 3475134 | AC32: =IF(ISBLANK(X32),"",X32-M32)

Sheet Procurement
B1: MATERIALS DELIVERY
B2: Project Name : Construction of Industrial Units for Artisans in Najran
B3: Project ID : NJR1-05-005 | F3: Date : | M3: Date as of : | N3: 46193 | X3: 46229
A5: Sr. NO. | B5: Project ID | C5: ACT # in P6 | D5: Item Description | E5: Discipline | F5: (Long \Short) Lead Items | G5: BOQ. No. | H5: Unit | I5: Quantity | J5: Proc. Qty | K5: Required P.O Date | L5: Date of Pur. Order Issued | M5: Purchase Order No. | N5: Supplier | O5: Supplier Phone | P5: Method of Shipping | Q5: Required on Job | R5: E.D.A. to Site | S5: A.D.A. to Site | T5: Lead Time | U5: Approval Status | V5: The Impact (BOQ Cost) | W5: Completion Rate | X5: Remarks
A6: 1 | B6: NJR1-05-005 | C6: NJR1-MS-LL-CO-PS-100 | D6: Autoclaved aerated panel (ACC Blocks) | E6: Concrete Work | F6: Long Lead | G6: 3.4 | H6: m2 | I6: 55 | J6: =I6 -> 55 | K6: 46158 | L6: 46183 | M6: Najran Workshop - - Modon / 37 /2026 | N6: Siporex | O6: + 966 11 498 1800 | P6: Land | Q6: =R6+3 -> 46261 | R6: 46258 | S6: 46225 | T6: =S6-L6 -> 42 | U6: Approved | V6: 16500 | W6: 1 | X6: Delivered | Y6: 1 | Z6: Structural
A7: 2 | B7: NJR1-05-005 | C7: NJR1-MS-LL-DW-PS-100 | D7: Roll up shutter door | E7: Doors & Windows Work | F7: Long Lead | G7: 8.1.1 | H7: Nos. | I7: 12 | J7: 12 | K7: 46158 | L7: 46111 | M7: Najran Workshop - - Modon / 9 /2026 | N7: Randa Automatic Doors Factory | O7: + 966 11 474 8881 | P7: Land | Q7: =R7+3 -> 46297 | R7: 46294 | S7: 46217 | T7: =S7-L7 -> 106 | U7: Approved | V7: 240000 | W7: 1 | X7: Delivered | Y7: 1 | Z7: Architectural
A8: 3 | B8: NJR1-05-005 | C8: NJR1-MS-LL-DW-PS-110 | D8: Steel door | E8: Doors & Windows Work | F8: Long Lead | G8: 8.1.2 | H8: Sets | I8: 12 | J8: =I8 -> 12 | K8: 46158 | L8: 46159 | M8: Najran Workshop - - Modon / 28 /2026 | N8: Architectural Doors | O8: +966 1 499 0113 | P8: Land | Q8: =R8+3 -> 46284 | R8: 46281 | S8: 46207 | T8: =S8-L8 -> 48 | U8: Approved | V8: 36000 | W8: 1 | X8: Delivered | Y8: 1 | Z8: Architectural | AA8: to date delivred
A9: 4 | B9: NJR1-05-005 | C9: NJR1-MS-LL-DW-PS-120 | D9: Galvanized steel door | E9: Doors & Windows Work | F9: Long Lead | G9: 8.1.3 | H9: Sets | I9: 2 | J9: 2 | K9: 46158 | L9: 46159 | M9: Najran Workshop - - Modon / 28 /2026 | N9: Architectural Doors | O9: +966 1 499 0113 | P9: Land | Q9: =R9+3 -> 46284 | R9: 46281 | S9: 46207 | T9: =S9-L9 -> 48 | U9: Approved | V9: 6000 | W9: 1 | X9: Delivered | Y9: 1 | Z9: Architectural
A10: 5 | B10: NJR1-05-005 | C10: NJR1-MS-LL-DW-PS-130 | D10: Solid wood door | E10: Doors & Windows Work | F10: Long Lead | G10: 8.1.4 | H10: Sets | I10: 2 | J10: =I10 -> 2 | K10: 46158 | L10: 46159 | M10: Najran Workshop - - Modon / 28 /2026 | N10: Architectural Doors | O10: +966 1 499 0113 | P10: Land | Q10: =R10+3 -> 46297 | R10: 46294 | S10: 46207 | T10: =S10-L10 -> 48 | U10: Approved | V10: 7000 | W10: 1 | X10: Delivered | Z10: Architectural
A11: 6 | B11: NJR1-05-005 | C11: NJR1-MS-LL-DW-PS-140 | D11: Aluminum framed double glazed windows | E11: Doors & Windows Work | F11: Long Lead | G11: 8.2.1 | H11: Nos. | I11: 14 | J11: =I11 -> 14 | K11: 46158 | L11: 46139 | M11: Issued | N11: Labenat Albena Company | O11: +966 53 269 4871 | P11: Land | Q11: =R11+3 -> 46297 | R11: 46294 | S11: 46235 | T11: =S11-L11 -> 96 | U11: Approved | V11: 19200 | W11: 1 | X11: Delivered | Z11: Architectural
A12: 7 | B12: NJR1-05-005 | C12: NJR1-MS-LL-DW-PS-150 | D12: Glass and aluminum door | E12: Doors & Windows Work | F12: Long Lead | G12: 8.3.1 | H12: Nos. | I12: 1 | J12: =I12 -> 1 | K12: 46158 | L12: 46139 | M12: Issued | N12: Labenat Albena Company | O12: +966 53 269 4871 | P12: Land | Q12: =R12+3 -> 46297 | R12: 46294 | S12: 46235 | T12: =S12-L12 -> 96 | U12: Approved | V12: 7500 | W12: 1 | X12: Delivered | Z12: Architectural
A13: 8 | B13: NJR1-05-005 | C13: NJR1-MS-LL-PR-PS-100 | D13: RBF Steel Structure | E13: Pre Engineered Structure Work | F13: Long Lead | G13: 11.1.1 | H13: Nos. | I13: 1 | J13: 1 | K13: 46118 | L13: 46107 | M13: by Contract | N13: Arabian International Company(aic) | O13: +966 92 000 3343 | P13: Land | Q13: =R13+3 -> 46186 | R13: 46183 | S13: 46187 | T13: =S13-L13 -> 80 | U13: Approved | V13: 1700000 | W13: 1 | X13: Delivered | Y13: 1 | Z13: Structural
A14: 9 | B14: NJR1-05-005 | C14: NJR1-MS-LL-PR-PS-110 | D14: Sandwich Panel | E14: Pre Engineered Structure Work | F14: Long Lead | G14: 11.1.1 | H14: Nos. | I14: 1 | J14: 1 | K14: 46118 | L14: 46127 | M14: Najran Workshop - - Modon /10 /2026 | N14: BCOMS | O14: +966 13 812 4571 | P14: Land | Q14: =R14+3 -> 46186 | R14: 46183 | S14: 46218 | T14: =S14-L14 -> 91 | U14: Approved | V14: 1700000 | W14: 1 | X14: Delivered | Y14: 1 | Z14: Structural
A15: 10 | B15: NJR1-05-005 | C15: NJR1-MS-LL-PR-PS-120 | D15: Pump Shed | E15: Pre Engineered Structure Work | F15: Long Lead | G15: 11.1.5 | H15: Item | I15: 1 | J15: =I15 -> 1 | K15: 46118 | L15: 46107 | M15: by Contract | N15: Arabian International Company(aic) | O15: +966 92 000 3343 | P15: Land | Q15: =R15+3 -> 46186 | R15: 46183 | S15: 46175 | T15: =S15-L15 -> 68 | U15: Approved | V15: 35000 | W15: 1 | X15: Delivered | Y15: 1 | Z15: Structural
A16: 11 | B16: NJR1-05-005 | C16: NJR1-MS-LL-FF-PS-100 | D16: Fire Pump system | E16: Mechanical Works | F16: Long Lead | G16: 15.1.1 | H16: Item | I16: 1 | J16: 1 | K16: 46121 | L16: 46148 | M16: Najran Workshop - - Modon /19 /2026 | N16: Saudi Mechanical Industries Co. | O16: +966 11 265 1979 | P16: Land | Q16: =R16+3 -> 46207 | R16: 46204 | S16: 46298 | T16: =S16-L16 -> 150 | U16: Approved | V16: 420000 | W16: 1 | X16: Delivered | Z16: Mechanical
A17: 12 | B17: NJR1-05-005 | C17: NJR1-MS-LL-WS-PS-100 | D17: Facility water storage tanks (GRP Tank) | E17: Mechanical Works | F17: Long Lead | G17: 15.2.8.1 | H17: Nos. | I17: 1 | J17: 1 | K17: 46121 | L17: 46132 | M17: Najran Workshop - - Modon /12 /2026 | N17: Pipeco | O17: +966 54 734 5295 | P17: Land | Q17: =R17+3 -> 46207 | R17: 46204 | S17: 46242 | T17: =S17-L17 -> 110 | U17: Approved | V17: 500000 | W17: 1 | X17: Delivered | Z17: Mechanical
A18: 13 | B18: NJR1-05-005 | C18: NJR1-MS-LL-EE-PS-100 | D18: Street lighting network | E18: Electrical Works | F18: Long Lead | G18: 16.3 | H18: Ls | I18: 1 | J18: =I18 -> 1 | K18: 46128 | L18: 46156 | M18: Najran Workshop - - Modon /26 /2026 | N18: Pan Light Factory | O18: +966 53 269 4871 | P18: Land | Q18: =R18+3 -> 46243 | R18: 46240 | S18: 46222 | T18: =S18-L18 -> 66 | U18: Approved | V18: 211600 | W18: 1 | X18: Delivered | Y18: 1 | Z18: Electrical
