Workbook
Name _1B.05.M.010.0010: #REF!
Name _1B.05.M.010.0010: #REF!
Name _1B.05.M.010.0050: #REF!
Name _1B.05.M.010.0050: #REF!
Name _1B.05.M.0100.0010: #REF!
Name _1B.05.M.020.0010: #REF!
Name _1B.05.M.020.0020: #REF!
Name _1B.05.M.020.0030: #REF!
Name _1B.05.M.020.0040: #REF!
Name _1B.05.M.030.0010: #REF!
Name _1B.05.M.030.0020: #REF!
Name _1B.05.M.040.0010: #REF!
Name _1B.05.M.050.0010: #REF!
Name _1B.05.M.050.0020: #REF!
Name _1B.05.M.050.0030: #REF!
Name _1B.05.M.060.0020: #REF!
Name _1B.05.M.060.0100: #REF!
Name _1B.05.M.070.0010: #REF!
Name _1B.05.M.070.0020: #REF!
Name _1B.05.M.070.0030: #REF!
Name _1B.05.M.070.0040: #REF!
Name _1B.05.M.070.0050: #REF!
Name _1B.05.M.080.0010: #REF!
Name _1B.05.M.090.0010: #REF!
Name _1B.09.P.010.0010: #REF!
Name _1B.09.P.010.0020: #REF!
Name _1B.09.P.010.0030: #REF!
Name _1B.09.P.010.0040: #REF!
Name _1B.09.P.010.0050: #REF!
Name _1B.09.P.010.0060: #REF!
Name _1B.09.P.010.0070: #REF!
Name _1B.09.P.020.0010: #REF!
Name _1B.09.P.020.0020: #REF!
Name _1B.09.P.020.0030: #REF!
Name _1B.09.P.020.0040: #REF!
Name _1B.09.P.020.0050: #REF!
Name _1B.09.P.020.0060: #REF!
Name _1B.09.P.020.0070: #REF!
Name _1B.09.P.020.0080: #REF!
Name _1B.09.P.020.0090: #REF!
Name _1B.09.P.020.0100: #REF!
Name _1B.09.P.020.0110: #REF!
Name _1B.09.P.020.0120: #REF!
Name _1B.09.P.020.0130: #REF!
Name _1B.09.P.020.0140: #REF!
Name _1B.09.P.020.0150: #REF!
Name _1B.09.P.030.0010: #REF!
Name _1B.09.P.030.0020: #REF!
Name _1B.09.P.030.0030: #REF!
Name _1B.09.P.030.0040: #REF!
Name _1B.09.P.030.0050: #REF!
Name _1B.09.P.030.0060: #REF!
Name _1B.09.P.040.0010: #REF!
Name _1B.09.P.040.0020: #REF!
Name _1B.09.P.040.0030: #REF!
Name _1B.09.P.050.0010: #REF!
Name _1B.09.P.050.0020: #REF!
Name _1B.09.P.060.0010: #REF!
Name _1B.09.P.060.0020: #REF!
Name _1B.09.P.060.0030: #REF!

Sheet DB
A1: ='Weekly Progress Report'!#REF! -> #REF!
B2: ='Weekly Progress Report'!#REF! -> #REF! | J2: ='Weekly Progress Report'!F2 -> Key Dates | U2: ='Weekly Progress Report'!$L$2 -> Cost Summary (SR) | AD2: ='Weekly Progress Report'!$T$2 -> Performance Summary | AP2: ='Weekly Progress Report'!#REF! -> #REF! | AT2: ='Weekly Progress Report'!#REF! -> #REF! | AW2: ='Weekly Progress Report'!#REF! -> #REF! | BD2: ='Weekly Progress Report'!K51 -> Quality Reports | BT2: ='Weekly Progress Report'!K59 -> Key Submittals Approval Status | CD2: ='Weekly Progress Report'!K65 -> Invoices Summary | CR2: ='Weekly Progress Report'!K73 -> Resources at Site | CY2: ='Weekly Progress Report'!V51 -> Safety Statistics | FK2: ='Weekly Progress Report'!#REF! -> #REF! | FS2: ='Weekly Progress Report'!#REF! -> #REF!
A3: ='Weekly Progress Report'!AE1 -> Data Date | B3: ='Weekly Progress Report'!#REF! -> #REF! | C3: ='Weekly Progress Report'!#REF! -> #REF! | D3: ='Weekly Progress Report'!#REF! -> #REF! | E3: ='Weekly Progress Report'!#REF! -> #REF! | F3: ='Weekly Progress Report'!C4 -> Stage | G3: ='Weekly Progress Report'!C5 -> Status | H3: ='Weekly Progress Report'!C6 -> Modon PM | I3: ='Weekly Progress Report'!Z2 -> Project Scope | J3: ='Weekly Progress Report'!F3 -> Contract Award | K3: ='Weekly Progress Report'!F4 -> Contract Sign | L3: ='Weekly Progress Report'!F5 -> Site Handover | M3: ='Weekly Progress Report'!F6 -> Original Completion | N3: ='Weekly Progress Report'!$H$3 -> Contract Award (Hijri) | O3: ='Weekly Progress Report'!$H$4 -> Contract Sign (Hijri) | P3: ='Weekly Progress Report'!$H$5 -> Site Handover (Hijri) | Q3: ='Weekly Progress Report'!$H$6 -> Original Completion (Hijri) | R3: ='Weekly Progress Report'!$J$3 -> Revised Completion | S3: ='Weekly Progress Report'!$J$4 -> Committed Completion | T3: ='Weekly Progress Report'!$J$5 -> Forecast Completion | U3: ='Weekly Progress Report'!$L$3 -> Original Contract Value | V3: ='Weekly Progress Report'!$L$4 -> Revised Contract Value | W3: ='Weekly Progress Report'!$L$5 -> Estimate At Completion Value | X3: ='Weekly Progress Report'!$L$6 -> Potential Changes | Y3: ='Weekly Progress Report'!$P$3 -> O&M Value (if any) | Z3: ='Weekly Progress Report'!$P$4 -> Submitted Invoices (Gross Value) | AA3: ='Weekly Progress Report'!$P$5 -> Penalities | AB3: ='Weekly Progress Report'!$P$6 -> FIR Value (Todate) | AC3: Original Plan Value | AD3: ='Weekly Progress Report'!$T$3 -> Plan Value | AE3: ='Weekly Progress Report'!$T$4 -> Earn Value | AF3: ='Weekly Progress Report'!$V$3 -> Phys. Plan Value | AG3: ='Weekly Progress Report'!$V$4 -> Phys. Earn Value | AH3: ='Weekly Progress Report'!$X$3 -> Quality Score | AI3: ='Weekly Progress Report'!$X$5 -> Safety Score | AJ3: Weekly PV (SAR) | AK3: Weekly EV (SAR) | AL3: Weekly PV % | AM3: Weekly PV % | AN3: Weekly Phys PV% | AO3: Weekly Phys PV% | AP3: Total SD Planned | AQ3: SD Remaining | AR3: SD Pending | AS3: Total SD Submittals | AT3: Planned Materials Approv | AU3: Material Pending Approval | AV3: Materila Total Submittals | AW3: ='Weekly Progress Report'!B70 -> Total Materials | AX3: ='Weekly Progress Report'!C70 -> Total Number of P.O. | AY3: ='Weekly Progress Report'!D70 -> Actual P.O. To Date | AZ3: ='Weekly Progress Report'!E70 -> Remaining P.O | BA3: ='Weekly Progress Report'!F70 -> Material on Site | BB3: ='Weekly Progress Report'!G70 -> Remaining Materials | BC3: ='Weekly Progress Report'!H70 -> Material Delivery Completion (Date) | BD3: ="NCR "&'Weekly Progress Report'!M52 -> NCR Issued | BE3: ="NCR "&'Weekly Progress Report'!N52 -> NCR Closed | BF3: ="NCR "&'Weekly Progress Report'!O52 -> NCR Pending | BG3: ="NCR "&'Weekly Progress Report'!P52 -> NCR Avg. Closing (Days) | BH3: ="SIR "&'Weekly Progress Report'!M52 -> SIR Issued | BI3: ="SIR "&'Weekly Progress Report'!N52 -> SIR Closed | BJ3: ="SIR "&'Weekly Progress Report'!O52 -> SIR Pending | BK3: ="SIR "&'Weekly Progress Report'!P52 -> SIR Avg. Closing (Days) | BL3: ="MIR "&'Weekly Progress Report'!M52 -> MIR Issued | BM3: ="MIR "&'Weekly Progress Report'!N52 -> MIR Closed | BN3: ="MIR "&'Weekly Progress Report'!O52 -> MIR Pending | BO3: ="MIR "&'Weekly Progress Report'!P52 -> MIR Avg. Closing (Days) | BP3: ="FIR "&'Weekly Progress Report'!M52 -> FIR Issued | BQ3: ="FIR "&'Weekly Progress Report'!N52 -> FIR Closed | BR3: ="FIR "&'Weekly Progress Report'!O52 -> FIR Pending | BS3: ="FIR "&'Weekly Progress Report'!P52 -> FIR Avg. Closing (Days) | BT3: ='Weekly Progress Report'!K60 -> 1 Quality Plan Approval | BU3: ='Weekly Progress Report'!K61 -> 2 Quality Plan Last Up | BV3: ='Weekly Progress Report'!K62 -> 3 Safety Plan Approval | BW3: ='Weekly Progress Report'!K63 -> 4 Safety Plan Last Up | BX3: ='Weekly Progress Report'!K64 -> 5 Execution Plan Approval | BY3: ='Weekly Progress Report'!P60 -> 6 Baseline Approval | BZ3: ='Weekly Progress Report'!P61 -> 7 No of Approved Version of Schedule | CA3: ='Weekly Progress Report'!P62 -> 8 Last Approved Schedule | CB3: ='Weekly Progress Report'!P63 -> 9 BOQ Approval Date | CC3: ='Weekly Progress Report'!P64 -> 10 No of Approved Version of BOQ | CD3: ='Weekly Progress Report'!K66 -> Total Submitted Invoices | CE3: ='Weekly Progress Report'!K67 -> PM Approved Invoices | CF3: ='Weekly Progress Report'!K68 -> No of Paid Invoices | CG3: ='Weekly Progress Report'!K69 -> No of Pending Invoices | CH3: ='Weekly Progress Report'!K70 -> Advance Payment % | CI3: ='Weekly Progress Report'!K71 -> Retention % | CJ3: ='Weekly Progress Report'!K72 -> Deduction / Penalties % | CK3: ='Weekly Progress Report'!N66 -> Submitted Invoices (SAR) | CL3: ='Weekly Progress Report'!N67 -> PM Approved Invoices (SAR) | CM3: ='Weekly Progress Report'!N68 -> Paid Invoices (SAR) | CN3: ='Weekly Progress Report'!N69 -> Last Submitted Period | CO3: ='Weekly Progress Report'!N70 -> Advance Payment (SAR) | CP3: ='Weekly Progress Report'!N71 -> Retention (SAR) | CQ3: ='Weekly Progress Report'!N72 -> Deduction / Penalties (SAR) | CR3: Planned Head Count | CS3: Actual Head Count | CT3: Saudi Staff | CU3: Labor Planned | CV3: Labor Actual | CW3: Equipment Planned | CX3: Equipment Actual | CY3: ="This Week "&'Weekly Progress Report'!W54 -> This Week Total Hours Worked | CZ3: ="This Week "&'Weekly Progress Report'!W55 -> This Week Safe Hours Worked | DA3: ="This Week "&'Weekly Progress Report'!W56 -> This Week LTI | DB3: ="This Week "&'Weekly Progress Report'!W57 -> This Week MTC (Healed w/o Disability) | DC3: ="This Week "&'Weekly Progress Report'!W58 -> This Week MTC (Healed w/ Disability) | DD3: ="This Week "&'Weekly Progress Report'!W59 -> This Week Near Miss | DE3: ="This Week "&'Weekly Progress Report'!W60 -> This Week First Aid Cases | DF3: ="This Week "&'Weekly Progress Report'!W61 -> This Week Fatality | DG3: ="This Week "&'Weekly Progress Report'!W62 -> This Week Fire Incident Cases | DH3: ="This Week "&'Weekly Progress Report'!W63 -> This Week Vehicle Incident | DI3: ="This Week "&'Weekly Progress Report'!W64 -> This Week Property Damages | DJ3: ="This Week "&'Weekly Progress Report'!W65 -> This Week Induction Training | DK3: ="This Week "&'Weekly Progress Report'!W66 -> This Week No.of Internal Training | DL3: ="This Week "&'Weekly Progress Report'!W67 -> This Week No.of Internal Audit | DM3: ="This Week "&'Weekly Progress Report'!W68 -> This Week No. of Toolbox Talks | DN3: ="This Week "&'Weekly Progress Report'!W69 -> This Week Safety Awards/Incentives | DO3: ="This Month "&'Weekly Progress Report'!W54 -> This Month Total Hours Worked | DP3: ="This Month "&'Weekly Progress Report'!W55 -> This Month Safe Hours Worked | DQ3: ="This Month "&'Weekly Progress Report'!W56 -> This Month LTI | DR3: ="This Month "&'Weekly Progress Report'!W57 -> This Month MTC (Healed w/o Disability) | DS3: ="This Month "&'Weekly Progress Report'!W58 -> This Month MTC (Healed w/ Disability) | DT3: ="This Month "&'Weekly Progress Report'!W59 -> This Month Near Miss | DU3: ="This Month "&'Weekly Progress Report'!W60 -> This Month First Aid Cases | DV3: ="This Month "&'Weekly Progress Report'!W61 -> This Month Fatality | DW3: ="This Month "&'Weekly Progress Report'!W62 -> This Month Fire Incident Cases | DX3: ="This Month "&'Weekly Progress Report'!W63 -> This Month Vehicle Incident | DY3: ="This Month "&'Weekly Progress Report'!W64 -> This Month Property Damages | DZ3: ="This Month "&'Weekly Progress Report'!W65 -> This Month Induction Training | EA3: ="This Month "&'Weekly Progress Report'!W66 -> This Month No.of Internal Training | EB3: ="This Month "&'Weekly Progress Report'!W67 -> This Month No.of Internal Audit | EC3: ="This Month "&'Weekly Progress Report'!W68 -> This Month No. of Toolbox Talks | ED3: ="This Month "&'Weekly Progress Report'!W69 -> This Month Safety Awards/Incentives | EE3: ="YTD "&'Weekly Progress Report'!W54 -> YTD Total Hours Worked | EF3: ="YTD "&'Weekly Progress Report'!W55 -> YTD Safe Hours Worked | EG3: ="YTD "&'Weekly Progress Report'!W56 -> YTD LTI | EH3: ="YTD "&'Weekly Progress Report'!W57 -> YTD MTC (Healed w/o Disability) | EI3: ="YTD "&'Weekly Progress Report'!W58 -> YTD MTC (Healed w/ Disability) | EJ3: ="YTD "&'Weekly Progress Report'!W59 -> YTD Near Miss | EK3: ="YTD "&'Weekly Progress Report'!W60 -> YTD First Aid Cases | EL3: ="YTD "&'Weekly Progress Report'!W61 -> YTD Fatality | EM3: ="YTD "&'Weekly Progress Report'!W62 -> YTD Fire Incident Cases | EN3: ="YTD "&'Weekly Progress Report'!W63 -> YTD Vehicle Incident | EO3: ="YTD "&'Weekly Progress Report'!W64 -> YTD Property Damages | EP3: ="YTD "&'Weekly Progress Report'!W65 -> YTD Induction Training | EQ3: ="YTD "&'Weekly Progress Report'!W66 -> YTD No.of Internal Training | ER3: ="YTD "&'Weekly Progress Report'!W67 -> YTD No.of Internal Audit | ES3: ="YTD "&'Weekly Progress Report'!W68 -> YTD No. of Toolbox Talks | ET3: ="YTD "&'Weekly Progress Report'!W69 -> YTD Safety Awards/Incentives | EU3: ="Cum "&'Weekly Progress Report'!W54 -> Cum Total Hours Worked | EV3: ="Cum "&'Weekly Progress Report'!W55 -> Cum Safe Hours Worked | EW3: ="Cum "&'Weekly Progress Report'!W56 -> Cum LTI | EX3: ="Cum "&'Weekly Progress Report'!W57 -> Cum MTC (Healed w/o Disability) | EY3: ="Cum "&'Weekly Progress Report'!W58 -> Cum MTC (Healed w/ Disability) | EZ3: ="Cum "&'Weekly Progress Report'!W59 -> Cum Near Miss | FA3: ="Cum "&'Weekly Progress Report'!W60 -> Cum First Aid Cases | FB3: ="Cum "&'Weekly Progress Report'!W61 -> Cum Fatality | FC3: ="Cum "&'Weekly Progress Report'!W62 -> Cum Fire Incident Cases | FD3: ="Cum "&'Weekly Progress Report'!W63 -> Cum Vehicle Incident | FE3: ="Cum "&'Weekly Progress Report'!W64 -> Cum Property Damages | FF3: ="Cum "&'Weekly Progress Report'!W65 -> Cum Induction Training | FG3: ="Cum "&'Weekly Progress Report'!W66 -> Cum No.of Internal Training | FH3: ="Cum "&'Weekly Progress Report'!W67 -> Cum No.of Internal Audit | FI3: ="Cum "&'Weekly Progress Report'!W68 -> Cum No. of Toolbox Talks | FJ3: ="Cum "&'Weekly Progress Report'!W69 -> Cum Safety Awards/Incentives | FK3: ='Weekly Progress Report'!#REF! -> #REF! | FL3: ='Weekly Progress Report'!A81 -> Not Started | FM3: ='Weekly Progress Report'!B81 -> In Progress | FN3: ='Weekly Progress Report'!C81 -> Completed | FO3: Critical Path Act.Last Week | FP3: Critical Path Act.This Week | FQ3: Failed start Last Week | FR3: Failed start This Week | FS3: ='Weekly Progress Report'!A89 -> 0 | FT3: ='Weekly Progress Report'!C89 -> 0 | FU3: ='Weekly Progress Report'!E89 -> 0 | FV3: ='Weekly Progress Report'!G89 -> 0 | FW3: ='Weekly Progress Report'!I89 -> 0 | FX3: ='Weekly Progress Report'!K89 -> 0 | FY3: ='Weekly Progress Report'!M89 -> 0 | FZ3: ='Weekly Progress Report'!N89 -> 0 | GA3: ='Weekly Progress Report'!O89 -> 0
A4: ='Weekly Progress Report'!AF1 -> 46308 | B4: ='Weekly Progress Report'!A3 -> Completion of Infrastructure Works in The Second Industrial City in Makkah Al-Mukarramah | C4: ='Weekly Progress Report'!A4 -> MKH2-02-003 | D4: ='Weekly Progress Report'!A5 -> Al Enjaz Trading & Contracting Co. | E4: ='Weekly Progress Report'!A6 -> Saudi Arabia Consulting Engineering Company "EGIS" | F4: ='Weekly Progress Report'!D4 -> Construction | G4: ='Weekly Progress Report'!D5 -> Active | H4: ='Weekly Progress Report'!D6 -> Engr. Abdallah Aljulaifi | I4: ='Weekly Progress Report'!Z3 -> Completion of Infrastruture in The Second Industrial City in Makkah (The project includes construction of Roads works ; Box Culvert ; Open Drain Channels and Dike Walls ; Street Lightings and Low Voltage Cables ,concrete ducts at road crossing) | J4: ='Weekly Progress Report'!G3 -> 46054 | K4: ='Weekly Progress Report'!G4 -> 46061 | L4: ='Weekly Progress Report'!G5 -> 46068 | M4: ='Weekly Progress Report'!G6 -> 46613 | N4: ='Weekly Progress Report'!$I$3 -> 01/02/1447 | O4: ='Weekly Progress Report'!$I$4 -> 08/02/1447 | P4: ='Weekly Progress Report'!$I$5 -> 15/02/1447 | Q4: ='Weekly Progress Report'!$I$6 -> 14/08/1447 | R4: ='Weekly Progress Report'!$K$3 -> 46613 | S4: ='Weekly Progress Report'!$K$4 -> 46613 | T4: ='Weekly Progress Report'!$K$5 -> 46642 | U4: ='Weekly Progress Report'!$N$3 -> 52025516 | V4: ='Weekly Progress Report'!$N$4 -> 52025516 | W4: ='Weekly Progress Report'!$N$5 -> 52025516 | X4: ='Weekly Progress Report'!$N$6 -> 0 | Y4: ='Weekly Progress Report'!$R$3 -> 0 | Z4: ='Weekly Progress Report'!$R$4 -> 29797667 | AA4: ='Weekly Progress Report'!$R$5 -> 2000 | AB4: ='Weekly Progress Report'!$R$6 -> 40071158 | AC4: ='Weekly Progress Report'!$I$21 -> 0.55242619 | AD4: ='Weekly Progress Report'!$U$3 -> 0.55242619 | AE4: ='Weekly Progress Report'!$U$4 -> 0.77077089 | AF4: ='Weekly Progress Report'!$W$3 -> 0.48663588 | AG4: ='Weekly Progress Report'!$W$4 -> 0.79311926 | AH4: ='Weekly Progress Report'!$Y$3 -> 0.9012069 | AI4: ='Weekly Progress Report'!$Y$5 -> 0.86363636 | AJ4: ='Weekly Progress Report'!$D$21 -> 642969.32 | AK4: ='Weekly Progress Report'!$E$21 -> 916464.08 | AL4: =AJ4/V4 -> 0.01235873 | AM4: =AK4/V4 -> 0.017615665 | AN4: ='Weekly Progress Report'!R21 -> 0.016004089 | AO4: ='Weekly Progress Report'!S21 -> 0.013478729 | AP4: ='Weekly Progress Report'!B59 -> 36 | AQ4: ='Weekly Progress Report'!H59 -> 8 | AR4: ='Weekly Progress Report'!I59 -> 8 | AS4: ='Weekly Progress Report'!J59 -> 36 | AT4: ='Weekly Progress Report'!B68 -> 65 | AU4: ='Weekly Progress Report'!I68 -> 0 | AV4: ='Weekly Progress Report'!J68 -> 65 | AW4: ='Weekly Progress Report'!B77 -> 18 | AX4: ='Weekly Progress Report'!C77 -> 18 | AY4: ='Weekly Progress Report'!D77 -> 18 | AZ4: ='Weekly Progress Report'!E77 -> 0 | BA4: ='Weekly Progress Report'!F77 -> 17 | BB4: ='Weekly Progress Report'!G77 -> 1 | BC4: ='Weekly Progress Report'!H77 -> 46336 | BD4: ='Weekly Progress Report'!M55 -> 2 | BE4: ='Weekly Progress Report'!N55 -> 2 | BF4: ='Weekly Progress Report'!O55 -> 0 | BG4: ='Weekly Progress Report'!P55 -> 3 | BH4: ='Weekly Progress Report'!M56 -> 25 | BI4: ='Weekly Progress Report'!N56 -> 24 | BJ4: ='Weekly Progress Report'!O56 -> 1 | BK4: ='Weekly Progress Report'!P56 -> 3 | BL4: ='Weekly Progress Report'!M57 -> 31 | BM4: ='Weekly Progress Report'!N57 -> 31 | BN4: ='Weekly Progress Report'!O57 -> 0 | BO4: ='Weekly Progress Report'!P57 -> 5 | BP4: ='Weekly Progress Report'!M58 -> 910 | BQ4: ='Weekly Progress Report'!N58 -> 901 | BR4: ='Weekly Progress Report'!O58 -> 9 | BS4: ='Weekly Progress Report'!P58 -> 4 | BT4: ='Weekly Progress Report'!N60 -> 46110 | BU4: ='Weekly Progress Report'!N61 -> 46110 | BV4: ='Weekly Progress Report'!N62 -> 46090 | BW4: ='Weekly Progress Report'!N63 -> 46090 | BX4: ='Weekly Progress Report'!N64 -> 46072 | BY4: ='Weekly Progress Report'!T60 -> 45717 | BZ4: ='Weekly Progress Report'!T61 -> 1 | CA4: ='Weekly Progress Report'!T62 -> 45717 | CB4: ='Weekly Progress Report'!T63 -> 0 | CC4: ='Weekly Progress Report'!T64 -> 0 | CD4: ='Weekly Progress Report'!M66 -> 0 | CE4: ='Weekly Progress Report'!M67 -> 7 | CF4: ='Weekly Progress Report'!M68 -> 6 | CG4: ='Weekly Progress Report'!M69 -> 1 | CH4: ='Weekly Progress Report'!M70 -> 0 | CI4: ='Weekly Progress Report'!M71 -> 0 | CJ4: ='Weekly Progress Report'!M72 -> 3.8442675e-05 | CK4: ='Weekly Progress Report'!Q66 -> 34267317 | CL4: ='Weekly Progress Report'!Q67 -> 34269317 | CM4: ='Weekly Progress Report'!Q68 -> 31459715 | CN4: ='Weekly Progress Report'!Q69 -> 0 | CO4: ='Weekly Progress Report'!Q70 -> 0 | CP4: ='Weekly Progress Report'!Q71 -> 0 | CQ4: ='Weekly Progress Report'!Q72 -> 2000 | CR4: ='Weekly Progress Report'!K76 -> 12 | CS4: ='Weekly Progress Report'!L76 -> 27 | CT4: ='Weekly Progress Report'!N76 -> 0 | CU4: ='Weekly Progress Report'!O76 -> 105 | CV4: ='Weekly Progress Report'!P76 -> 119 | CW4: ='Weekly Progress Report'!S86 -> 50 | CX4: ='Weekly Progress Report'!T86 -> 64 | CY4: ='Weekly Progress Report'!Y54 -> 7560 | CZ4: ='Weekly Progress Report'!Y55 -> 7560 | DA4: ='Weekly Progress Report'!Y56 -> 0 | DB4: ='Weekly Progress Report'!Y57 -> 0 | DC4: ='Weekly Progress Report'!Y58 -> 0 | DD4: ='Weekly Progress Report'!Y59 -> 0 | DE4: ='Weekly Progress Report'!Y60 -> 0 | DF4: ='Weekly Progress Report'!Y61 -> 0 | DG4: ='Weekly Progress Report'!Y62 -> 0 | DH4: ='Weekly Progress Report'!Y63 -> 0 | DI4: ='Weekly Progress Report'!Y64 -> 0 | DJ4: ='Weekly Progress Report'!Y65 -> 0 | DK4: ='Weekly Progress Report'!Y66 -> 2 | DL4: ='Weekly Progress Report'!Y67 -> 0 | DM4: ='Weekly Progress Report'!Y68 -> 1 | DN4: ='Weekly Progress Report'!Y69 -> 0 | DO4: ='Weekly Progress Report'!AA54 -> 15120 | DP4: ='Weekly Progress Report'!AA55 -> 15120 | DQ4: ='Weekly Progress Report'!AA56 -> 0 | DR4: ='Weekly Progress Report'!AA57 -> 0 | DS4: ='Weekly Progress Report'!AA58 -> 0 | DT4: ='Weekly Progress Report'!AA59 -> 1 | DU4: ='Weekly Progress Report'!AA60 -> 0 | DV4: ='Weekly Progress Report'!AA61 -> 0 | DW4: ='Weekly Progress Report'!AA62 -> 0 | DX4: ='Weekly Progress Report'!AA63 -> 0 | DY4: ='Weekly Progress Report'!AA64 -> 0 | DZ4: ='Weekly Progress Report'!AA65 -> 0 | EA4: ='Weekly Progress Report'!AA66 -> 3 | EB4: ='Weekly Progress Report'!AA67 -> 2 | EC4: ='Weekly Progress Report'!AA68 -> 2 | ED4: ='Weekly Progress Report'!AA69 -> 0 | EE4: ='Weekly Progress Report'!AB54 -> 192100 | EF4: ='Weekly Progress Report'!AB55 -> 192100 | EG4: ='Weekly Progress Report'!AB56 -> 0 | EH4: ='Weekly Progress Report'!AB57 -> 0 | EI4: ='Weekly Progress Report'!AB58 -> 0 | EJ4: ='Weekly Progress Report'!AB59 -> 1 | EK4: ='Weekly Progress Report'!AB60 -> 0 | EL4: ='Weekly Progress Report'!AB61 -> 0 | EM4: ='Weekly Progress Report'!AB62 -> 0 | EN4: ='Weekly Progress Report'!AB63 -> 0 | EO4: ='Weekly Progress Report'!AB64 -> 0 | EP4: ='Weekly Progress Report'!AB65 -> 12 | EQ4: ='Weekly Progress Report'!AB66 -> 38 | ER4: ='Weekly Progress Report'!AB67 -> 2 | ES4: ='Weekly Progress Report'!AB68 -> 50 | ET4: ='Weekly Progress Report'!AB69 -> 0 | EU4: ='Weekly Progress Report'!AC54 -> 192100 | EV4: ='Weekly Progress Report'!AC55 -> 192100 | EW4: ='Weekly Progress Report'!AC56 -> 0 | EX4: ='Weekly Progress Report'!AC57 -> 0 | EY4: ='Weekly Progress Report'!AC58 -> 0 | EZ4: ='Weekly Progress Report'!AC59 -> 1 | FA4: ='Weekly Progress Report'!AC60 -> 0 | FB4: ='Weekly Progress Report'!AC61 -> 0 | FC4: ='Weekly Progress Report'!AC62 -> 0 | FD4: ='Weekly Progress Report'!AC63 -> 0 | FE4: ='Weekly Progress Report'!AC64 -> 0 | FF4: ='Weekly Progress Report'!AC65 -> 12 | FG4: ='Weekly Progress Report'!AC66 -> 38 | FH4: ='Weekly Progress Report'!AC67 -> 2 | FI4: ='Weekly Progress Report'!AC68 -> 50 | FJ4: ='Weekly Progress Report'!AC69 -> 0 | FK4: ='Weekly Progress Report'!#REF! -> #REF! | FL4: ='Weekly Progress Report'!A82 -> 57 | FM4: ='Weekly Progress Report'!B82 -> 32 | FN4: ='Weekly Progress Report'!C82 -> 310 | FO4: ='Weekly Progress Report'!#REF! -> #REF! | FP4: ='Weekly Progress Report'!A86 -> 66 | FQ4: ='Weekly Progress Report'!G86 -> 8 | FR4: ='Weekly Progress Report'!H86 -> 8 | FS4: ='Weekly Progress Report'!A94 -> 0 | FT4: ='Weekly Progress Report'!C94 -> 0 | FU4: ='Weekly Progress Report'!E94 -> 0 | FV4: ='Weekly Progress Report'!G94 -> 0 | FW4: ='Weekly Progress Report'!I94 -> 0 | FX4: ='Weekly Progress Report'!K94 -> 0 | FY4: ='Weekly Progress Report'!M94 -> 0 | FZ4: ='Weekly Progress Report'!N94 -> 0 | GA4: ='Weekly Progress Report'!O94 -> 0

Sheet Weekly Progress Report
AC1: =+HSE!L4 -> Report No. | AD1: ='General Information'!O1 -> 35 | AE1: Data Date | AF1: ='General Information'!L1 -> 46308
F2: Key Dates | L2: Cost Summary (SR) | T2: Performance Summary | Z2: Project Scope
A3: ='General Information'!C3 -> Completion of Infrastructure Works in The Second Industrial City in Makkah Al-Mukarramah | F3: Contract Award | G3: ='General Information'!C12 -> 46054 | H3: Contract Award (Hijri) | I3: ='General Information'!C16 -> 01/02/1447 | J3: Revised Completion | K3: ='General Information'!C20 -> 46613 | L3: Original Contract Value | N3: ='Invoice Log'!E3 -> 52025516 | P3: O&M Value (if any) | R3: ='Invoice Log'!I3 -> 0 | S3: EAC | T3: Plan Value | U3: =J21 -> 0.55242619 | V3: Phys. Plan Value | W3: =V21 -> 0.48663588 | X3: Quality Score | Y3: =Quality!AC10 -> 0.9012069 | Z3: =+Progress!A1 -> Completion of Infrastruture in The Second Industrial City in Makkah (The project includes construction of Roads works ; Box Culvert ; Open Drain Channels and Dike Walls ; Street Lightings and Low Voltage Cables ,concrete ducts at road crossing)
A4: ='General Information'!C4 -> MKH2-02-003 | C4: Stage | D4: ='General Information'!C7 -> Construction | F4: Contract Sign | G4: ='General Information'!C13 -> 46061 | H4: Contract Sign (Hijri) | I4: ='General Information'!C17 -> 08/02/1447 | J4: Committed Completion | K4: ='General Information'!C21 -> 46613 | L4: Revised Contract Value | N4: ='Invoice Log'!E4 -> 52025516 | O4: EAC | P4: Submitted Invoices (Gross Value) | R4: =+'Invoice Log'!F59 -> 29797667 | T4: Earn Value | U4: =K21 -> 0.77077089 | V4: Phys. Earn Value | W4: =W21 -> 0.79311926 | Y4: =REPT("¢",IF(INT(+Y3*10)>5,5,INT(+Y3*10)))&REPT("£",IF(INT(+Y3*10)>5,0,5-INT(+Y3*10)))&CHAR(10)&REPT("¢",+IF(INT(+Y3*10)>5,-5+INT(+Y3*10),0))&REPT("£",IF(INT(+Y3*10)>5,10-INT(+Y3*10),5)) -> ¢¢¢¢¢ ¢¢¢¢£
A5: ='General Information'!C5 -> Al Enjaz Trading & Contracting Co. | C5: Status | D5: ='General Information'!C8 -> Active | F5: Site Handover | G5: ='General Information'!C14 -> 46068 | H5: Site Handover (Hijri) | I5: ='General Information'!C18 -> 15/02/1447 | J5: Forecast Completion | K5: ='General Information'!C22 -> 46642 | L5: Estimate At Completion Value | N5: ='Invoice Log'!E5 -> 52025516 | O5: =+#REF!+#REF!+N5 -> #REF! | P5: Penalities | R5: ='Invoice Log'!M6 -> 2000 | T5: Variance | U5: =U4-U3 -> 0.2183447 | V5: Variance | W5: =W4-W3 -> 0.30648338 | X5: Safety Score | Y5: ='HSE-Stat'!J23 -> 0.86363636
A6: ='General Information'!C6 -> Saudi Arabia Consulting Engineering Company "EGIS" | C6: Modon PM | D6: ='General Information'!C9 -> Engr. Abdallah Aljulaifi | F6: Original Completion | G6: ='General Information'!C15 -> 46613 | H6: Original Completion (Hijri) | I6: ='General Information'!C19 -> 14/08/1447 | J6: Variance | K6: ='General Information'!C23 -> -29 | L6: Potential Changes | N6: =N4-N5 -> 0 | P6: FIR Value (Todate) | R6: =+'FIR summary '!K2 -> 40071158 | T6: FIR % | U6: =R6/N4 -> 0.77022124 | V6: Invoiced % | W6: =R4/N4 -> 0.57275102 | Y6: =REPT("¢",IF(INT(+Y5*10)>5,5,INT(+Y5*10)))&REPT("£",IF(INT(+Y5*10)>5,0,5-INT(+Y5*10)))&CHAR(10)&REPT("¢",+IF(INT(+Y5*10)>5,-5+INT(+Y5*10),0))&REPT("£",IF(INT(+Y5*10)>5,10-INT(+Y5*10),5)) -> ¢¢¢¢¢ ¢¢¢££
N9: Physical Progress (Effort) | Z9: Earned Value Progress (%)
B10: BOQ Value (SAR) | C10: % Wt. | D10: Weekly (SAR) | F10: To Date (SAR) | N10: Budgeted | O10: % Wt. | P10: Weekly Physical Progress | T10: To Date Physical Progress
D11: Planned | E11: Earned | F11: Original Plan | G11: Revised Planned | H11: Earned | I11: Original Plan % | J11: Revised Planned % | K11: Earned % | L11: Variance | M11: SPI | N11: (Manhours) | P11: Planned | Q11: Earned | R11: Plan % | S11: Earned % | T11: Planned | U11: Earned | V11: Plan % | W11: Earned % | X11: Variance | Y11: SPI
B12: =+Progress!B7 -> 0 | C12: =IF(ISBLANK(B12),"",B12/$B$21) -> 0 | D12: =+Progress!D7 -> 0 | E12: =+Progress!E7 -> - | F12: =+Progress!F7 -> 0 | G12: =+Progress!G7 -> 0 | H12: =+Progress!H7 -> - | I12: =IFERROR(IF(ISBLANK(F12),"",F12/B12),0) -> 0 | J12: =IFERROR(IF(ISBLANK(G12),"",G12/B12),0) -> 0 | K12: =IFERROR(IF(ISBLANK(H12),"",H12/B12),0) -> 0 | L12: =IFERROR(K12-J12,"") -> 0 | M12: =IFERROR(K12/J12,"") | N12: =+Progress!J7 -> 14738 | O12: =IF(ISBLANK(N12),"",N12/$N$21) -> 0.029894584 | P12: =+Progress!L7 -> 0 | Q12: =+Progress!M7 -> 0 | R12: =IFERROR(IF(ISBLANK(P12),"",P12/N12),0) -> 0 | S12: =IFERROR(IF(ISBLANK(Q12),"",Q12/N12),0) -> 0 | T12: =+Progress!N7 -> 14738 | U12: =+Progress!O7 -> 14738 | V12: =IFERROR(IF(ISBLANK(T12),"",T12/N12),0) -> 1 | W12: =IFERROR(IF(ISBLANK(U12),"",U12/N12),0) -> 1 | X12: =IFERROR(W12-V12,"") -> 0 | Y12: =IFERROR(W12/V12,"") -> 1
B13: =+Progress!B9 -> 1560765.5 | C13: =IF(ISBLANK(B13),"",B13/$B$21) -> 0.03 | D13: =+Progress!D9 -> 0 | E13: =+Progress!E9 -> 0 | F13: =+Progress!F9 -> 1560765.5 | G13: =+Progress!G9 -> 1560765.5 | H13: =+Progress!H9 -> 1560765.5 | I13: =IFERROR(IF(ISBLANK(F13),"",F13/B13),0) -> 1 | J13: =IFERROR(IF(ISBLANK(G13),"",G13/B13),0) -> 1 | K13: =IFERROR(IF(ISBLANK(H13),"",H13/B13),0) -> 1 | L13: =IFERROR(K13-J13,"") -> 0 | M13: =IFERROR(K13/J13,"") -> 1 | N13: =+Progress!J9 -> 24562 | O13: =IF(ISBLANK(N13),"",N13/$N$21) -> 0.049821602 | P13: =+Progress!L9 -> 0 | Q13: =+Progress!M9 -> 0 | R13: =IFERROR(IF(ISBLANK(P13),"",P13/N13),0) -> 0 | S13: =IFERROR(IF(ISBLANK(Q13),"",Q13/N13),0) -> 0 | T13: =+Progress!N9 -> 24562 | U13: =+Progress!O9 -> 24562 | V13: =IFERROR(IF(ISBLANK(T13),"",T13/N13),0) -> 1 | W13: =IFERROR(IF(ISBLANK(U13),"",U13/N13),0) -> 1 | X13: =IFERROR(W13-V13,"") -> 0 | Y13: =IFERROR(W13/V13,"") -> 1
B14: =+Progress!B11 -> 10405103 | C14: =IF(ISBLANK(B14),"",B14/$B$21) -> 0.2 | D14: =+Progress!D11 -> 0 | E14: =+Progress!E11 -> 25502.7 | F14: =+Progress!F11 -> 10405103 | G14: =+Progress!G11 -> 10405103 | H14: =+Progress!H11 -> 10060817 | I14: =IFERROR(IF(ISBLANK(F14),"",F14/B14),0) -> 1 | J14: =IFERROR(IF(ISBLANK(G14),"",G14/B14),0) -> 1 | K14: =IFERROR(IF(ISBLANK(H14),"",H14/B14),0) -> 0.96691177 | L14: =IFERROR(K14-J14,"") -> -0.03308823 | M14: =IFERROR(K14/J14,"") -> 0.96691177 | N14: =+Progress!J11 -> 58936 | O14: =IF(ISBLANK(N14),"",N14/$N$21) -> 0.11954588 | P14: =+Progress!L11 -> 0 | Q14: =+Progress!M11 -> 152 | R14: =IFERROR(IF(ISBLANK(P14),"",P14/N14),0) -> 0 | S14: =IFERROR(IF(ISBLANK(Q14),"",Q14/N14),0) -> 0.0025790688 | T14: =+Progress!N11 -> 58936 | U14: =+Progress!O11 -> 53310 | V14: =IFERROR(IF(ISBLANK(T14),"",T14/N14),0) -> 1 | W14: =IFERROR(IF(ISBLANK(U14),"",U14/N14),0) -> 0.90454052 | X14: =IFERROR(W14-V14,"") -> -0.095459481 | Y14: =IFERROR(W14/V14,"") -> 0.90454052
B15: =+Progress!B13 -> 18062898 | C15: =IF(ISBLANK(B15),"",B15/$B$21) -> 0.34719305 | D15: =+Progress!D13 -> 470222.41 | E15: =+Progress!E13 -> 846741.38 | F15: =+Progress!F13 -> 10120548 | G15: =+Progress!G13 -> 10120548 | H15: =+Progress!H13 -> 13145824 | I15: =IFERROR(IF(ISBLANK(F15),"",F15/B15),0) -> 0.56029481 | J15: =IFERROR(IF(ISBLANK(G15),"",G15/B15),0) -> 0.56029481 | K15: =IFERROR(IF(ISBLANK(H15),"",H15/B15),0) -> 0.72778047 | L15: =IFERROR(K15-J15,"") -> 0.16748566 | M15: =IFERROR(K15/J15,"") -> 1.2989242 | N15: =+Progress!J13 -> 118380 | O15: =IF(ISBLANK(N15),"",N15/$N$21) -> 0.24012219 | P15: =+Progress!L13 -> 3390 | Q15: =+Progress!M13 -> 5197 | R15: =IFERROR(IF(ISBLANK(P15),"",P15/N15),0) -> 0.028636594 | S15: =IFERROR(IF(ISBLANK(Q15),"",Q15/N15),0) -> 0.043900997 | T15: =+Progress!N13 -> 55810 | U15: =+Progress!O13 -> 69355 | V15: =IFERROR(IF(ISBLANK(T15),"",T15/N15),0) -> 0.47144788 | W15: =IFERROR(IF(ISBLANK(U15),"",U15/N15),0) -> 0.58586755 | X15: =IFERROR(W15-V15,"") -> 0.11441967 | Y15: =IFERROR(W15/V15,"") -> 1.2426984
B16: =+Progress!B15 -> 2353781.9 | C16: =IF(ISBLANK(B16),"",B16/$B$21) -> 0.045242836 | D16: =+Progress!D15 -> 51053.04 | E16: =+Progress!E15 -> 44220 | F16: =+Progress!F15 -> 291254.26 | G16: =+Progress!G15 -> 291254.26 | H16: =+Progress!H15 -> 1886038.2 | I16: =IFERROR(IF(ISBLANK(F16),"",F16/B16),0) -> 0.12373885 | J16: =IFERROR(IF(ISBLANK(G16),"",G16/B16),0) -> 0.12373885 | K16: =IFERROR(IF(ISBLANK(H16),"",H16/B16),0) -> 0.80127993 | L16: =IFERROR(K16-J16,"") -> 0.67754108 | M16: =IFERROR(K16/J16,"") -> 6.4755728 | N16: =+Progress!J15 -> 41030 | O16: =IF(ISBLANK(N16),"",N16/$N$21) -> 0.083225321 | P16: =+Progress!L15 -> 1320 | Q16: =+Progress!M15 -> 1296 | R16: =IFERROR(IF(ISBLANK(P16),"",P16/N16),0) -> 0.032171582 | S16: =IFERROR(IF(ISBLANK(Q16),"",Q16/N16),0) -> 0.031586644 | T16: =+Progress!N15 -> 9100 | U16: =+Progress!O15 -> 29080 | V16: =IFERROR(IF(ISBLANK(T16),"",T16/N16),0) -> 0.22178893 | W16: =IFERROR(IF(ISBLANK(U16),"",U16/N16),0) -> 0.7087497 | X16: =IFERROR(W16-V16,"") -> 0.48696076 | Y16: =IFERROR(W16/V16,"") -> 3.1956044
B17: =+Progress!B17 -> 189275 | C17: =IF(ISBLANK(B17),"",B17/$B$21) -> 0.0036381186 | D17: =+Progress!D17 -> 0 | E17: =+Progress!E17 -> 0 | F17: =+Progress!F17 -> 189275 | G17: =+Progress!G17 -> 189275 | H17: =+Progress!H17 -> 155775 | I17: =IFERROR(IF(ISBLANK(F17),"",F17/B17),0) -> 1 | J17: =IFERROR(IF(ISBLANK(G17),"",G17/B17),0) -> 1 | K17: =IFERROR(IF(ISBLANK(H17),"",H17/B17),0) -> 0.82300885 | L17: =IFERROR(K17-J17,"") -> -0.17699115 | M17: =IFERROR(K17/J17,"") -> 0.82300885 | N17: =+Progress!J17 -> 6490 | O17: =IF(ISBLANK(N17),"",N17/$N$21) -> 0.013164327 | P17: =+Progress!L17 -> 0 | Q17: =+Progress!M17 -> 0 | R17: =IFERROR(IF(ISBLANK(P17),"",P17/N17),0) -> 0 | S17: =IFERROR(IF(ISBLANK(Q17),"",Q17/N17),0) -> 0 | T17: =+Progress!N17 -> 6490 | U17: =+Progress!O17 -> 4390 | V17: =IFERROR(IF(ISBLANK(T17),"",T17/N17),0) -> 1 | W17: =IFERROR(IF(ISBLANK(U17),"",U17/N17),0) -> 0.67642527 | X17: =IFERROR(W17-V17,"") -> -0.32357473 | Y17: =IFERROR(W17/V17,"") -> 0.67642527
B18: =+Progress!B19 -> 3959941.2 | C18: =IF(ISBLANK(B18),"",B18/$B$21) -> 0.076115366 | D18: =+Progress!D19 -> 0 | E18: =+Progress!E19 -> 0 | F18: =+Progress!F19 -> 3959941.2 | G18: =+Progress!G19 -> 3959941.2 | H18: =+Progress!H19 -> 3959941.2 | I18: =IFERROR(IF(ISBLANK(F18),"",F18/B18),0) -> 1 | J18: =IFERROR(IF(ISBLANK(G18),"",G18/B18),0) -> 1 | K18: =IFERROR(IF(ISBLANK(H18),"",H18/B18),0) -> 1 | L18: =IFERROR(K18-J18,"") -> 0 | M18: =IFERROR(K18/J18,"") -> 1 | N18: =+Progress!J19 -> 17395 | O18: =IF(ISBLANK(N18),"",N18/$N$21) -> 0.035284047 | P18: =+Progress!L19 -> 0 | Q18: =+Progress!M19 -> 0 | R18: =IFERROR(IF(ISBLANK(P18),"",P18/N18),0) -> 0 | S18: =IFERROR(IF(ISBLANK(Q18),"",Q18/N18),0) -> 0 | T18: =+Progress!N19 -> 17395 | U18: =+Progress!O19 -> 17395 | V18: =IFERROR(IF(ISBLANK(T18),"",T18/N18),0) -> 1 | W18: =IFERROR(IF(ISBLANK(U18),"",U18/N18),0) -> 1 | X18: =IFERROR(W18-V18,"") -> 0 | Y18: =IFERROR(W18/V18,"") -> 1
B19: =+Progress!B21 -> 10291200 | C19: =IF(ISBLANK(B19),"",B19/$B$21) -> 0.19781063 | D19: =+Progress!D21 -> 121693.87 | E19: =+Progress!E21 -> 0 | F19: =+Progress!F21 -> 2213370.7 | G19: =+Progress!G21 -> 2213370.7 | H19: =+Progress!H21 -> 9330592.4 | I19: =IFERROR(IF(ISBLANK(F19),"",F19/B19),0) -> 0.21507411 | J19: =IFERROR(IF(ISBLANK(G19),"",G19/B19),0) -> 0.21507411 | K19: =IFERROR(IF(ISBLANK(H19),"",H19/B19),0) -> 0.90665737 | L19: =IFERROR(K19-J19,"") -> 0.69158326 | M19: =IFERROR(K19/J19,"") -> 4.2155579 | N19: =+Progress!J21 -> 185220 | O19: =IF(ISBLANK(N19),"",N19/$N$21) -> 0.37570056 | P19: =+Progress!L21 -> 3180 | Q19: =+Progress!M21 -> 0 | R19: =IFERROR(IF(ISBLANK(P19),"",P19/N19),0) -> 0.017168772 | S19: =IFERROR(IF(ISBLANK(Q19),"",Q19/N19),0) -> 0 | T19: =+Progress!N21 -> 52880 | U19: =+Progress!O21 -> 178177 | V19: =IFERROR(IF(ISBLANK(T19),"",T19/N19),0) -> 0.28549833 | W19: =IFERROR(IF(ISBLANK(U19),"",U19/N19),0) -> 0.96197495 | X19: =IFERROR(W19-V19,"") -> 0.67647662 | Y19: =IFERROR(W19/V19,"") -> 3.3694592
B20: =+Progress!B23 -> 5202551.6 | C20: =IF(ISBLANK(B20),"",B20/$B$21) -> 0.1 | D20: =+Progress!D23 -> 0 | E20: =+Progress!E23 -> 0 | F20: =+Progress!F23 -> 0 | G20: =+Progress!G23 -> 0 | H20: =+Progress!H23 -> 0 | I20: =IFERROR(IF(ISBLANK(F20),"",F20/B20),0) -> 0 | J20: =IFERROR(IF(ISBLANK(G20),"",G20/B20),0) -> 0 | K20: =IFERROR(IF(ISBLANK(H20),"",H20/B20),0) -> 0 | L20: =IFERROR(K20-J20,"") -> 0 | M20: =IFERROR(K20/J20,"") | N20: =+Progress!J23 -> 14740 | O20: =IF(ISBLANK(N20),"",N20/$N$21) -> 0.029898641 | P20: =+Progress!L23 -> 0 | Q20: =+Progress!M23 -> 0 | R20: =IFERROR(IF(ISBLANK(P20),"",P20/N20),0) -> 0 | S20: =IFERROR(IF(ISBLANK(Q20),"",Q20/N20),0) -> 0 | T20: =+Progress!N23 -> 0 | U20: =+Progress!O23 -> 0 | V20: =IFERROR(IF(ISBLANK(T20),"",T20/N20),0) -> 0 | W20: =IFERROR(IF(ISBLANK(U20),"",U20/N20),0) -> 0 | X20: =IFERROR(W20-V20,"") -> 0 | Y20: =IFERROR(W20/V20,"")
A21: Total | B21: =SUM(B12:B20) -> 52025516 | C21: =SUM(C12:C20) -> 1 | D21: =SUM(D12:D20) -> 642969.32 | E21: =SUM(E12:E20) -> 916464.08 | F21: =SUM(F12:F20) -> 28740258 | G21: =SUM(G12:G20) -> 28740258 | H21: =SUM(H12:H20) -> 40099753 | I21: =IFERROR(IF(ISBLANK(F21),"",F21/B21),0) -> 0.55242619 | J21: =IFERROR(IF(ISBLANK(G21),"",G21/B21),0) -> 0.55242619 | K21: =IFERROR(IF(ISBLANK(H21),"",H21/B21),0) -> 0.77077089 | L21: =+K21-J21 -> 0.2183447 | M21: =K21/J21 -> 1.3952468 | N21: 492999 | O21: =SUM(O12:O20) -> 0.97665715 | P21: =SUM(P12:P20) -> 7890 | Q21: =SUM(Q12:Q20) -> 6645 | R21: =IFERROR(IF(ISBLANK(P21),"",P21/N21),0) -> 0.016004089 | S21: =IFERROR(IF(ISBLANK(Q21),"",Q21/N21),0) -> 0.013478729 | T21: =SUM(T12:T20) -> 239911 | U21: =SUM(U12:U20) -> 391007 | V21: =IFERROR(IF(ISBLANK(T21),"",T21/N21),0) -> 0.48663588 | W21: =IFERROR(IF(ISBLANK(U21),"",U21/N21),0) -> 0.79311926 | X21: =+W21-V21 -> 0.30648338 | Y21: =W21/V21 -> 1.6298002
Z22: Construction Milestones
Z23: Item No. | AA23: Milestones | AC23: Original (Baseline) | AD23: Latest Plan | AE23: Forecast | AF23: Status | AG23: Days Change
Z24: =+Milestones!A4 -> 1 | AA24: =+Milestones!B4 -> Project Commencement Date | AC24: =+Milestones!C4 -> 46068 | AD24: =+Milestones!D4 -> 46068 | AE24: =+Milestones!E4 -> 46068 | AF24: =+Milestones!F4 -> A | AG24: =+Milestones!G4 -> 0
Z25: =+Milestones!A5 -> 2 | AA25: =+Milestones!B5 -> Project Kick Off Meeting/NTP | AC25: =+Milestones!C5 -> 46068 | AD25: =+Milestones!D5 -> 46068 | AE25: =+Milestones!E5 -> 46068 | AF25: =+Milestones!F5 -> A | AG25: =+Milestones!G5 -> 0
Z26: =+Milestones!A6 -> 3 | AA26: =+Milestones!B6 -> Project Completion | AC26: =+Milestones!C6 -> 46613 | AD26: =+Milestones!D6 -> 46613 | AE26: =+Milestones!E6 -> 46642 | AF26: =+Milestones!F6 -> F | AG26: =+Milestones!G6 -> -29
Z27: =+Milestones!A7 -> 4 | AA27: =+Milestones!B7 -> Completion of Mobilization | AC27: =+Milestones!C7 -> 46095 | AD27: =+Milestones!D7 -> 46095 | AE27: =+Milestones!E7 -> 46179 | AF27: =+Milestones!F7 -> A | AG27: =+Milestones!G7 -> -84
Z28: =+Milestones!A10 -> 7 | AA28: =+Milestones!B10 -> Completion of Long lead Materials Delivery | AC28: =+Milestones!C10 -> 46250 | AD28: =+Milestones!D10 -> 46250 | AE28: =+Milestones!E10 -> 46263 | AF28: =+Milestones!F10 -> A | AG28: =+Milestones!G10 -> -13
Z29: =+Milestones!A11 -> 8 | AA29: =+Milestones!B11 -> Completion of Road Works | AC29: =+Milestones!C11 -> 46370 | AD29: =+Milestones!D11 -> 46370 | AE29: =+Milestones!E11 -> 46412 | AF29: =+Milestones!F11 -> F | AG29: =+Milestones!G11 -> -42
Z30: =+Milestones!A12 -> 9 | AA30: =+Milestones!B12 -> Completion of Open Drain Channel | AC30: =+Milestones!C12 -> 46552 | AD30: =+Milestones!D12 -> 46552 | AE30: =+Milestones!E12 -> 46581 | AF30: =+Milestones!F12 -> F | AG30: =+Milestones!G12 -> -29
Z31: =+Milestones!A13 -> 10 | AA31: =+Milestones!B13 -> Completion of All Works | AC31: =+Milestones!C13 -> 46613 | AD31: =+Milestones!D13 -> 46613 | AE31: =+Milestones!E13 -> 46642 | AF31: =+Milestones!F13 -> F | AG31: =+Milestones!G13 -> -29
Z32: =+Milestones!A14 -> 11 | AA32: =+Milestones!B14 -> Final Handover | AC32: =+Milestones!C14 -> 46613 | AD32: =+Milestones!D14 -> 46613 | AE32: =+Milestones!E14 -> 46642 | AF32: =+Milestones!F14 -> F | AG32: =+Milestones!G14 -> -29
K50: Quality | V50: Safety
K51: Quality Reports | V51: Safety Statistics | AD51: Proactive Vs Reactive Actions Taken
B52: Total | C52: Total Submitted Drawings | H52: Remaining | I52: Pending | J52: Total Submittals | K52: Quality Reports | M52: Issued | N52: Closed | O52: Pending | P52: Avg. Closing (Days) | Q52: Pending | V52: Category | W52: Item | Y52: This Week | AA52: This Month | AB52: Year to Date | AC52: Cumulative
C53: A | D53: B | E53: C | F53: D | G53: Processed | Q53: 0-10 Days | R53: 11-20 Days | S53: 21-30 Days | T53: 31-60 Days | U53: > 60 Days
B54: =IF('Quality-Stat'!D13="","",'Quality-Stat'!D13) -> 0 | C54: =IF('Quality-Stat'!E13="","",'Quality-Stat'!E13) -> 0 | D54: =IF('Quality-Stat'!F13="","",'Quality-Stat'!F13) -> 0 | E54: =IF('Quality-Stat'!G13="","",'Quality-Stat'!G13) -> 0 | F54: =IF('Quality-Stat'!H13="","",'Quality-Stat'!H13) -> 0 | G54: =IF('Quality-Stat'!I13="","",'Quality-Stat'!I13) -> 0 | H54: =IF('Quality-Stat'!J13="","",'Quality-Stat'!J13) -> 0 | I54: =IF('Quality-Stat'!K13="","",'Quality-Stat'!K13) -> 0 | J54: =IF('Quality-Stat'!L13="","",'Quality-Stat'!L13) -> 0 | V54: General | W54: ='HSE-Stat'!B4 -> Total Hours Worked | Y54: ='HSE-Stat'!D4 -> 7560 | AA54: ='HSE-Stat'!E4 -> 15120 | AB54: ='HSE-Stat'!F4 -> 192100 | AC54: ='HSE-Stat'!G4 -> 192100 | AF54: Proactive | AG54: =+SUM(AC65:AC69) -> 102
B55: =IF('Quality-Stat'!D14="","",'Quality-Stat'!D14) -> 25 | C55: =IF('Quality-Stat'!E14="","",'Quality-Stat'!E14) -> 0 | D55: =IF('Quality-Stat'!F14="","",'Quality-Stat'!F14) -> 17 | E55: =IF('Quality-Stat'!G14="","",'Quality-Stat'!G14) -> 0 | F55: =IF('Quality-Stat'!H14="","",'Quality-Stat'!H14) -> 0 | G55: =IF('Quality-Stat'!I14="","",'Quality-Stat'!I14) -> 17 | H55: =IF('Quality-Stat'!J14="","",'Quality-Stat'!J14) -> 8 | I55: =IF('Quality-Stat'!K14="","",'Quality-Stat'!K14) -> 8 | J55: =IF('Quality-Stat'!L14="","",'Quality-Stat'!L14) -> 25 | K55: Non Conformance (NCR) | M55: ='Quality-Stat'!D5 -> 2 | N55: ='Quality-Stat'!E5 -> 2 | O55: ='Quality-Stat'!F5 -> 0 | P55: ='Quality-Stat'!G5 -> 3 | Q55: ='Quality-Stat'!H5 -> 0 | R55: ='Quality-Stat'!I5 -> 0 | S55: ='Quality-Stat'!J5 -> 0 | T55: ='Quality-Stat'!K5 -> 0 | U55: ='Quality-Stat'!L5 -> 0 | W55: ='HSE-Stat'!B5 -> Safe Hours Worked | Y55: ='HSE-Stat'!D5 -> 7560 | AA55: ='HSE-Stat'!E5 -> 15120 | AB55: ='HSE-Stat'!F5 -> 192100 | AC55: ='HSE-Stat'!G5 -> 192100 | AF55: Reactive | AG55: =SUM(AC56:AC64) -> 1
B56: =IF('Quality-Stat'!D15="","",'Quality-Stat'!D15) -> 0 | C56: =IF('Quality-Stat'!E15="","",'Quality-Stat'!E15) -> 0 | D56: =IF('Quality-Stat'!F15="","",'Quality-Stat'!F15) -> 0 | E56: =IF('Quality-Stat'!G15="","",'Quality-Stat'!G15) -> 0 | F56: =IF('Quality-Stat'!H15="","",'Quality-Stat'!H15) -> 0 | G56: =IF('Quality-Stat'!I15="","",'Quality-Stat'!I15) -> 0 | H56: =IF('Quality-Stat'!J15="","",'Quality-Stat'!J15) -> 0 | I56: =IF('Quality-Stat'!K15="","",'Quality-Stat'!K15) -> 0 | J56: =IF('Quality-Stat'!L15="","",'Quality-Stat'!L15) -> 0 | K56: Site Instruction (SIR/SOR) | M56: ='Quality-Stat'!D6 -> 25 | N56: ='Quality-Stat'!E6 -> 24 | O56: ='Quality-Stat'!F6 -> 1 | P56: ='Quality-Stat'!G6 -> 3 | Q56: ='Quality-Stat'!H6 -> 1 | R56: ='Quality-Stat'!I6 -> 0 | S56: ='Quality-Stat'!J6 -> 0 | T56: ='Quality-Stat'!K6 -> 0 | U56: ='Quality-Stat'!L6 -> 0 | V56: Reactive | W56: ='HSE-Stat'!B6 -> LTI | Y56: ='HSE-Stat'!D6 -> 0 | AA56: ='HSE-Stat'!E6 -> 0 | AB56: ='HSE-Stat'!F6 -> 0 | AC56: ='HSE-Stat'!G6 -> 0
B57: =IF('Quality-Stat'!D16="","",'Quality-Stat'!D16) -> 0 | C57: =IF('Quality-Stat'!E16="","",'Quality-Stat'!E16) -> 0 | D57: =IF('Quality-Stat'!F16="","",'Quality-Stat'!F16) -> 0 | E57: =IF('Quality-Stat'!G16="","",'Quality-Stat'!G16) -> 0 | F57: =IF('Quality-Stat'!H16="","",'Quality-Stat'!H16) -> 0 | G57: =IF('Quality-Stat'!I16="","",'Quality-Stat'!I16) -> 0 | H57: =IF('Quality-Stat'!J16="","",'Quality-Stat'!J16) -> 0 | I57: =IF('Quality-Stat'!K16="","",'Quality-Stat'!K16) -> 0 | J57: =IF('Quality-Stat'!L16="","",'Quality-Stat'!L16) -> 0 | K57: Material Inspection (MRIR) | M57: ='Quality-Stat'!D7 -> 31 | N57: ='Quality-Stat'!E7 -> 31 | O57: ='Quality-Stat'!F7 -> 0 | P57: ='Quality-Stat'!G7 -> 5 | Q57: ='Quality-Stat'!H7 -> 0 | R57: ='Quality-Stat'!I7 -> 0 | S57: ='Quality-Stat'!J7 -> 0 | T57: ='Quality-Stat'!K7 -> 0 | U57: ='Quality-Stat'!L7 -> 0 | W57: ='HSE-Stat'!B7 -> MTC (Healed w/o Disability) | Y57: ='HSE-Stat'!D7 -> 0 | AA57: ='HSE-Stat'!E7 -> 0 | AB57: ='HSE-Stat'!F7 -> 0 | AC57: ='HSE-Stat'!G7 -> 0
B58: =IF('Quality-Stat'!D17="","",'Quality-Stat'!D17) -> 11 | C58: =IF('Quality-Stat'!E17="","",'Quality-Stat'!E17) -> 0 | D58: =IF('Quality-Stat'!F17="","",'Quality-Stat'!F17) -> 11 | E58: =IF('Quality-Stat'!G17="","",'Quality-Stat'!G17) -> 0 | F58: =IF('Quality-Stat'!H17="","",'Quality-Stat'!H17) -> 0 | G58: =IF('Quality-Stat'!I17="","",'Quality-Stat'!I17) -> 11 | H58: =IF('Quality-Stat'!J17="","",'Quality-Stat'!J17) -> 0 | I58: =IF('Quality-Stat'!K17="","",'Quality-Stat'!K17) -> 0 | J58: =IF('Quality-Stat'!L17="","",'Quality-Stat'!L17) -> 11 | K58: Field Inspection (FIR) | M58: ='Quality-Stat'!D8 -> 910 | N58: ='Quality-Stat'!E8 -> 901 | O58: ='Quality-Stat'!F8 -> 9 | P58: ='Quality-Stat'!G8 -> 4 | Q58: ='Quality-Stat'!H8 -> 2 | R58: ='Quality-Stat'!I8 -> 0 | S58: ='Quality-Stat'!J8 -> 0 | T58: ='Quality-Stat'!K8 -> 0 | U58: ='Quality-Stat'!L8 -> 0 | W58: ='HSE-Stat'!B8 -> MTC (Healed w/ Disability) | Y58: ='HSE-Stat'!D8 -> 0 | AA58: ='HSE-Stat'!E8 -> 0 | AB58: ='HSE-Stat'!F8 -> 0 | AC58: ='HSE-Stat'!G8 -> 0
B59: =SUM(B54:B58) -> 36 | C59: =SUM(C54:C58) -> 0 | D59: =SUM(D54:D58) -> 28 | E59: =SUM(E54:E58) -> 0 | F59: =SUM(F54:F58) -> 0 | G59: =SUM(G54:G58) -> 28 | H59: =SUM(H54:H58) -> 8 | I59: =SUM(I54:I58) -> 8 | J59: =SUM(J54:J58) -> 36 | K59: Key Submittals Approval Status | W59: ='HSE-Stat'!B9 -> Near Miss | Y59: ='HSE-Stat'!D9 -> 0 | AA59: ='HSE-Stat'!E9 -> 1 | AB59: ='HSE-Stat'!F9 -> 1 | AC59: ='HSE-Stat'!G9 -> 1
K60: 1 Quality Plan Approval | N60: =+'General Information'!C27 -> 46110 | P60: 6 Baseline Approval | T60: ='General Information'!C39 -> 45717 | W60: ='HSE-Stat'!B10 -> First Aid Cases | Y60: ='HSE-Stat'!D10 -> 0 | AA60: ='HSE-Stat'!E10 -> 0 | AB60: ='HSE-Stat'!F10 -> 0 | AC60: ='HSE-Stat'!G10 -> 0 | AD60: Total Hours Worked Vs Safe Hours Worked
B61: Total | C61: Total Submitted Material | H61: Remaining to approve | I61: Pending | J61: Total Submittals | K61: 2 Quality Plan Last Up | N61: =+'General Information'!C28 -> 46110 | P61: 7 No of Approved Version of Schedule | T61: ='General Information'!C40 -> 1 | W61: ='HSE-Stat'!B11 -> Fatality | Y61: ='HSE-Stat'!D11 -> 0 | AA61: ='HSE-Stat'!E11 -> 0 | AB61: ='HSE-Stat'!F11 -> 0 | AC61: ='HSE-Stat'!G11 -> 0
C62: A | D62: B | E62: C | F62: D | G62: Processed | H62: with Designer | K62: 3 Safety Plan Approval | N62: =+'General Information'!C31 -> 46090 | P62: 8 Last Approved Schedule | T62: ='General Information'!C41 -> 45717 | W62: ='HSE-Stat'!B12 -> Fire Incident Cases | Y62: ='HSE-Stat'!D12 -> 0 | AA62: ='HSE-Stat'!E12 -> 0 | AB62: ='HSE-Stat'!F12 -> 0 | AC62: ='HSE-Stat'!G12 -> 0
B63: =IF('Quality-Stat'!D30="","",'Quality-Stat'!D30) -> 0 | C63: =IF('Quality-Stat'!E30="","",'Quality-Stat'!E30) -> 0 | D63: =IF('Quality-Stat'!F30="","",'Quality-Stat'!F30) -> 0 | E63: =IF('Quality-Stat'!G30="","",'Quality-Stat'!G30) -> 0 | F63: =IF('Quality-Stat'!H30="","",'Quality-Stat'!H30) -> 0 | G63: =IF('Quality-Stat'!I30="","",'Quality-Stat'!I30) -> 0 | H63: =IF('Quality-Stat'!J30="","",'Quality-Stat'!J30) -> 0 | I63: =IF('Quality-Stat'!K30="","",'Quality-Stat'!K30) -> 0 | J63: =IF('Quality-Stat'!L30="","",'Quality-Stat'!L30) -> 0 | K63: 4 Safety Plan Last Up | N63: =+'General Information'!C32 -> 46090 | P63: 9 BOQ Approval Date | T63: =+'General Information'!C44 -> 0 | W63: ='HSE-Stat'!B13 -> Vehicle Incident | Y63: ='HSE-Stat'!D13 -> 0 | AA63: ='HSE-Stat'!E13 -> 0 | AB63: ='HSE-Stat'!F13 -> 0 | AC63: ='HSE-Stat'!G13 -> 0
B64: =IF('Quality-Stat'!D31="","",'Quality-Stat'!D31) -> 15 | C64: =IF('Quality-Stat'!E31="","",'Quality-Stat'!E31) -> 0 | D64: =IF('Quality-Stat'!F31="","",'Quality-Stat'!F31) -> 14 | E64: =IF('Quality-Stat'!G31="","",'Quality-Stat'!G31) -> 0 | F64: =IF('Quality-Stat'!H31="","",'Quality-Stat'!H31) -> 1 | G64: =IF('Quality-Stat'!I31="","",'Quality-Stat'!I31) -> 14 | H64: =IF('Quality-Stat'!J31="","",'Quality-Stat'!J31) -> 0 | I64: =IF('Quality-Stat'!K31="","",'Quality-Stat'!K31) -> 0 | J64: =IF('Quality-Stat'!L31="","",'Quality-Stat'!L31) -> 15 | K64: 5 Execution Plan Approval | N64: =+'General Information'!C48 -> 46072 | P64: 10 No of Approved Version of BOQ | T64: ='General Information'!C45 -> 0 | W64: ='HSE-Stat'!B14 -> Property Damages | Y64: ='HSE-Stat'!D14 -> 0 | AA64: ='HSE-Stat'!E14 -> 0 | AB64: ='HSE-Stat'!F14 -> 0 | AC64: ='HSE-Stat'!G14 -> 0
B65: =IF('Quality-Stat'!D32="","",'Quality-Stat'!D32) -> 33 | C65: =IF('Quality-Stat'!E32="","",'Quality-Stat'!E32) -> 0 | D65: =IF('Quality-Stat'!F32="","",'Quality-Stat'!F32) -> 32 | E65: =IF('Quality-Stat'!G32="","",'Quality-Stat'!G32) -> 0 | F65: =IF('Quality-Stat'!H32="","",'Quality-Stat'!H32) -> 1 | G65: =IF('Quality-Stat'!I32="","",'Quality-Stat'!I32) -> 32 | H65: =IF('Quality-Stat'!J32="","",'Quality-Stat'!J32) -> 0 | I65: =IF('Quality-Stat'!K32="","",'Quality-Stat'!K32) -> 0 | J65: =IF('Quality-Stat'!L32="","",'Quality-Stat'!L32) -> 33 | K65: Invoices Summary | V65: Proactive | W65: ='HSE-Stat'!B15 -> Induction Training | Y65: ='HSE-Stat'!D15 -> 0 | AA65: ='HSE-Stat'!E15 -> 0 | AB65: ='HSE-Stat'!F15 -> 12 | AC65: ='HSE-Stat'!G15 -> 12
B66: =IF('Quality-Stat'!D33="","",'Quality-Stat'!D33) -> 0 | C66: =IF('Quality-Stat'!E33="","",'Quality-Stat'!E33) -> 0 | D66: =IF('Quality-Stat'!F33="","",'Quality-Stat'!F33) -> 0 | E66: =IF('Quality-Stat'!G33="","",'Quality-Stat'!G33) -> 0 | F66: =IF('Quality-Stat'!H33="","",'Quality-Stat'!H33) -> 0 | G66: =IF('Quality-Stat'!I33="","",'Quality-Stat'!I33) -> 0 | H66: =IF('Quality-Stat'!J33="","",'Quality-Stat'!J33) -> 0 | I66: =IF('Quality-Stat'!K33="","",'Quality-Stat'!K33) -> 0 | J66: =IF('Quality-Stat'!L33="","",'Quality-Stat'!L33) -> 0 | K66: Total Submitted Invoices | M66: ='Invoice Log'!U3 -> 0 | N66: Submitted Invoices (SAR) | Q66: ='Invoice Log'!Y3 -> 34267317 | S66: Contract Value (SR) | T66: =N4 -> 52025516 | W66: ='HSE-Stat'!B16 -> No.of Internal Training | Y66: ='HSE-Stat'!D16 -> 2 | AA66: ='HSE-Stat'!E16 -> 3 | AB66: ='HSE-Stat'!F16 -> 38 | AC66: ='HSE-Stat'!G16 -> 38
B67: =IF('Quality-Stat'!D34="","",'Quality-Stat'!D34) -> 17 | C67: =IF('Quality-Stat'!E34="","",'Quality-Stat'!E34) -> 0 | D67: =IF('Quality-Stat'!F34="","",'Quality-Stat'!F34) -> 17 | E67: =IF('Quality-Stat'!G34="","",'Quality-Stat'!G34) -> 0 | F67: =IF('Quality-Stat'!H34="","",'Quality-Stat'!H34) -> 0 | G67: =IF('Quality-Stat'!I34="","",'Quality-Stat'!I34) -> 17 | H67: =IF('Quality-Stat'!J34="","",'Quality-Stat'!J34) -> 0 | I67: =IF('Quality-Stat'!K34="","",'Quality-Stat'!K34) -> 0 | J67: =IF('Quality-Stat'!L34="","",'Quality-Stat'!L34) -> 17 | K67: PM Approved Invoices | M67: ='Invoice Log'!U5 -> 7 | N67: PM Approved Invoices (SAR) | Q67: ='Invoice Log'!Y5 -> 34269317 | S67: Planned Value (SR) | T67: =G21 -> 28740258 | W67: ='HSE-Stat'!B17 -> No.of Internal Audit | Y67: ='HSE-Stat'!D17 -> 0 | AA67: ='HSE-Stat'!E17 -> 2 | AB67: ='HSE-Stat'!F17 -> 2 | AC67: ='HSE-Stat'!G17 -> 2
B68: =SUM(B63:B67) -> 65 | C68: =SUM(C63:C67) -> 0 | D68: =SUM(D63:D67) -> 63 | E68: =SUM(E63:E67) -> 0 | F68: =SUM(F63:F67) -> 2 | G68: =SUM(G63:G67) -> 63 | H68: =SUM(H63:H67) -> 0 | I68: =SUM(I63:I67) -> 0 | J68: =SUM(J63:J67) -> 65 | K68: No of Paid Invoices | M68: ='Invoice Log'!U6 -> 6 | N68: Paid Invoices (SAR) | Q68: ='Invoice Log'!Y6 -> 31459715 | S68: Earned Value (SR) | T68: =H21 -> 40099753 | W68: ='HSE-Stat'!B18 -> No. of Toolbox Talks | Y68: ='HSE-Stat'!D18 -> 1 | AA68: ='HSE-Stat'!E18 -> 2 | AB68: ='HSE-Stat'!F18 -> 50 | AC68: ='HSE-Stat'!G18 -> 50
K69: No of Pending Invoices | M69: =M67-M68 -> 1 | N69: Last Submitted Period | S69: Submitted (SAR) | T69: =Q66 -> 34267317 | W69: ='HSE-Stat'!B19 -> Safety Awards/Incentives | Y69: ='HSE-Stat'!D19 -> 0 | AA69: ='HSE-Stat'!E19 -> 0 | AB69: ='HSE-Stat'!F19 -> 0 | AC69: ='HSE-Stat'!G19 -> 0
B70: Total Materials | C70: Total Number of P.O. | D70: Actual P.O. To Date | E70: Remaining P.O | F70: Material on Site | G70: Remaining Materials | H70: Material Delivery Completion (Date) | K70: Advance Payment % | M70: ='Invoice Log'!M3 -> 0 | N70: Advance Payment (SAR) | Q70: ='Invoice Log'!Q3 -> 0 | S70: PM Approved (SAR) | T70: =Q67 -> 34269317 | V70: Latest Contract Change Order Log
C71: A | D71: B | E71: C | F71: D | G71: Processed | K71: Retention % | M71: ='Invoice Log'!M4 -> 0 | N71: Retention (SAR) | Q71: ='Invoice Log'!Q4 -> 0 | S71: Total Paid (SAR) | T71: =Q68 -> 31459715
B72: =IF('Quality-Stat'!D40="","",'Quality-Stat'!D40) -> 0 | C72: =IF('Quality-Stat'!E40="","",'Quality-Stat'!E40) -> 0 | D72: =IF('Quality-Stat'!F40="","",'Quality-Stat'!F40) | E72: =IF('Quality-Stat'!G40="","",'Quality-Stat'!G40) -> 0 | F72: =IF('Quality-Stat'!H40="","",'Quality-Stat'!H40) -> 0 | G72: =IF('Quality-Stat'!I40="","",'Quality-Stat'!I40) -> 0 | H72: ='Quality-Stat'!J40 -> 0 | K72: Deduction / Penalties % | M72: ='Invoice Log'!M5 -> 3.8442675e-05 | N72: Deduction / Penalties (SAR) | Q72: ='Invoice Log'!M6 -> 2000 | V72: CCO No. | W72: Date Added | X72: Description of Change | AC72: Status | AD72: Cost | AE72: Sch Impact (Months) | AF72: Date Approved | AG72: Duration
B73: =IF('Quality-Stat'!D41="","",'Quality-Stat'!D41) -> 9 | C73: =IF('Quality-Stat'!E41="","",'Quality-Stat'!E41) -> 9 | D73: =IF('Quality-Stat'!F41="","",'Quality-Stat'!F41) -> 9 | E73: =IF('Quality-Stat'!G41="","",'Quality-Stat'!G41) -> 0 | F73: =IF('Quality-Stat'!H41="","",'Quality-Stat'!H41) -> 8 | G73: =IF('Quality-Stat'!I41="","",'Quality-Stat'!I41) -> 1 | H73: ='Quality-Stat'!J41 -> 46336 | K73: Resources at Site
B74: =IF('Quality-Stat'!D42="","",'Quality-Stat'!D42) -> 2 | C74: =IF('Quality-Stat'!E42="","",'Quality-Stat'!E42) -> 2 | D74: =IF('Quality-Stat'!F42="","",'Quality-Stat'!F42) -> 2 | E74: =IF('Quality-Stat'!G42="","",'Quality-Stat'!G42) -> 0 | F74: =IF('Quality-Stat'!H42="","",'Quality-Stat'!H42) -> 2 | G74: =IF('Quality-Stat'!I42="","",'Quality-Stat'!I42) -> 0 | H74: ='Quality-Stat'!J42 -> 46172 | K74: Head Count - Non Manual | O74: Head Count - Manual | S74: Total Head Count | V74: =CCO!A3 -> 0 | W74: =CCO!B3 -> 0 | X74: =CCO!C3 -> 0 | AC74: =CCO!D3 -> 0 | AD74: =CCO!E3 -> 0 | AE74: =CCO!F3 -> 0 | AF74: =CCO!G3 -> 0 | AG74: =CCO!H3 -> 0
B75: =IF('Quality-Stat'!D43="","",'Quality-Stat'!D43) -> 0 | C75: =IF('Quality-Stat'!E43="","",'Quality-Stat'!E43) -> 0 | D75: =IF('Quality-Stat'!F43="","",'Quality-Stat'!F43) -> 0 | E75: =IF('Quality-Stat'!G43="","",'Quality-Stat'!G43) -> 0 | F75: =IF('Quality-Stat'!H43="","",'Quality-Stat'!H43) -> 0 | G75: =IF('Quality-Stat'!I43="","",'Quality-Stat'!I43) -> 0 | H75: ='Quality-Stat'!J43 -> 0 | K75: Planned | L75: Actual | M75: Next Month Forecast | N75: Saudi Staff | O75: Planned | P75: Actual | Q75: Next Month Forecast | R75: Saudi Staff | S75: Total Plan | T75: Total Actual | U75: Variance
B76: =IF('Quality-Stat'!D44="","",'Quality-Stat'!D44) -> 7 | C76: =IF('Quality-Stat'!E44="","",'Quality-Stat'!E44) -> 7 | D76: =IF('Quality-Stat'!F44="","",'Quality-Stat'!F44) -> 7 | E76: =IF('Quality-Stat'!G44="","",'Quality-Stat'!G44) -> 0 | F76: =IF('Quality-Stat'!H44="","",'Quality-Stat'!H44) -> 7 | G76: =IF('Quality-Stat'!I44="","",'Quality-Stat'!I44) -> 0 | H76: ='Quality-Stat'!J44 -> 46263 | K76: =Manpower!A20 -> 12 | L76: =Manpower!B20 -> 27 | M76: =Manpower!F20 -> 12 | N76: =Manpower!H20 -> 0 | O76: =L86 -> 105 | P76: =M86 -> 119 | Q76: =Manpower!F24 -> 137 | R76: =Manpower!H24 -> 0 | S76: =K76+O76 -> 117 | T76: =L76+P76 -> 146 | U76: =+T76-S76 -> 29 | V76: =CCO!A4 | W76: =CCO!B4 | X76: =CCO!C4 | AC76: =IF(CCO!D4="","",CCO!D4) | AD76: =CCO!E4 | AE76: =CCO!F4 | AF76: =CCO!G4 | AG76: =CCO!H4
B77: =IF('Quality-Stat'!D45="","",'Quality-Stat'!D45) -> 18 | C77: =IF('Quality-Stat'!E45="","",'Quality-Stat'!E45) -> 18 | D77: =IF('Quality-Stat'!F45="","",'Quality-Stat'!F45) -> 18 | E77: =IF('Quality-Stat'!G45="","",'Quality-Stat'!G45) -> 0 | F77: =IF('Quality-Stat'!H45="","",'Quality-Stat'!H45) -> 17 | G77: =IF('Quality-Stat'!I45="","",'Quality-Stat'!I45) -> 1 | H77: =MAX(H72:H76) -> 46336 | K77: Manpower Breakdown by Trade | R77: Major Equipment
K78: Key Trade | L78: Planned | M78: Actual | R78: Type | S78: Planned | T78: Actual | U78: Idle | V78: =CCO!A5 | W78: =CCO!B5 | X78: =CCO!C5 | AC78: =IF(CCO!D5="","",CCO!D5) | AD78: =CCO!E5 | AE78: =CCO!F5 | AF78: =CCO!G5 | AG78: =CCO!H5
K79: =+Manpower!N23 -> General Labor | L79: =Manpower!N24 -> 60 | M79: =Manpower!N25 -> 57 | R79: =+Manpower!$B$49 -> Excavator | S79: =+Manpower!B50 -> 5 | T79: =+Manpower!B51 -> 13 | U79: =+Manpower!B52 -> 0
E80: =Schedule!F3 -> Active Schedule Activities | K80: =+Manpower!P23 -> Carpenter | L80: =Manpower!P24 -> 1 | M80: =Manpower!P25 -> 0 | R80: =+Manpower!$D$49 -> Loader | S80: =+Manpower!D50 -> 5 | T80: =+Manpower!D51 -> 5 | U80: =+Manpower!D52 -> 0 | V80: Major Quantity Trackers
A81: =Schedule!B4 -> Not Started | B81: =Schedule!C4 -> In Progress | C81: =Schedule!D4 -> Completed | D81: =Schedule!E4 -> % | E81: =Schedule!F4 -> Active | F81: =Schedule!G4 -> Ahead | G81: =Schedule!H4 -> On | H81: =Schedule!I4 -> Behind | ... J81: =Schedule!K4 -> 0 | K81: =+Manpower!R23 -> Plumber | L81: =+Manpower!R24 -> 0 | M81: =Manpower!R25 -> 0 | R81: =+Manpower!$F$49 -> Dozer | S81: =+Manpower!F50 -> 2 | T81: =+Manpower!F51 -> 7 | U81: =+Manpower!F52 -> 0 | V81: BOQ N0. | W81: Item Description | AB81: Total Qty | AC81: Measu Unit | AD81: Plan to Date | AE81: Act to Date | AF81: Remaining | AG81: Variance
A82: =Schedule!B5 -> 57 | B82: =Schedule!C5 -> 32 | C82: =Schedule!D5 -> 310 | D82: =Schedule!E5 -> 0.77694236 | E82: =Schedule!F5 -> 32 | F82: =Schedule!G5 -> 27 | G82: =Schedule!H5 -> 0 | H82: =Schedule!I5 -> 5 | I82: =Schedule!J5 -> 22 | K82: =+Manpower!T23 -> Operator | L82: =Manpower!T24 -> 20 | M82: =Manpower!T25 -> 36 | R82: =+Manpower!$H$49 -> Dump Truck | S82: =+Manpower!H50 -> 17 | T82: =+Manpower!H51 -> 20 | U82: =+Manpower!H52 -> 0 | V82: ='Major Quantities'!A2 -> B1.31 22 00.01 | W82: ='Major Quantities'!B2 -> Roadway Excavation for cuttings (all types of soil) | AB82: ='Major Quantities'!C2 -> 537044.15 | AC82: ='Major Quantities'!D2 -> m³ | AD82: ='Major Quantities'!E2 -> 537044.15 | AE82: ='Major Quantities'!F2 -> 508798.76 | AF82: ='Major Quantities'!G2 -> 28245.398 | AG82: ='Major Quantities'!H2 -> -28245.398
C83: =Schedule!D6 -> Free Float Management (Total) | G83: =Schedule!H6 -> Failed Start Activities | K83: =+Manpower!V23 -> Steel Fixer | L83: =+Manpower!V24 -> 2 | M83: =+Manpower!V25 -> 0 | R83: =+Manpower!$J$49 -> Crane | S83: =+Manpower!J50 -> 0 | T83: =+Manpower!J51 -> 2 | U83: =+Manpower!J52 -> 0 | V83: ='Major Quantities'!A3 -> B1.31 22 00.02 | W83: ='Major Quantities'!B3 -> Embankments to the ROW with common / suitable excavated material or with suitable imported material | AB83: ='Major Quantities'!C3 -> 438396.6 | AC83: ='Major Quantities'!D3 -> m³ | AD83: ='Major Quantities'!E3 -> 438396.6 | AE83: ='Major Quantities'!F3 -> 434601.61 | AF83: ='Major Quantities'!G3 -> 3794.996 | AG83: ='Major Quantities'!H3 -> -3794.996
C84: =Schedule!D7 -> Greater Than 14 Days | E84: =Schedule!F7 -> Less Than 14 Days | K84: =+Manpower!X23 -> Mason | L84: =+Manpower!X24 -> 2 | M84: =+Manpower!X25 -> 0 | R84: =+Manpower!$L$49 -> Grader | S84: =+Manpower!L50 -> 4 | T84: =+Manpower!L51 -> 3 | U84: =+Manpower!L52 -> 0 | V84: ='Major Quantities'!A4 -> B1.31 22 00.05 | W84: ='Major Quantities'!B4 -> Subgrade | AB84: ='Major Quantities'!C4 -> 21604 | AC84: ='Major Quantities'!D4 -> m³ | AD84: ='Major Quantities'!E4 -> 0 | AE84: ='Major Quantities'!F4 -> 0 | AF84: ='Major Quantities'!G4 -> 21604 | AG84: ='Major Quantities'!H4 -> 0
A85: =Schedule!B8 -> This Week | B85: =Schedule!C8 -> Diff | C85: =Schedule!D8 -> Last Week | D85: =Schedule!E8 -> This Week | E85: =Schedule!F8 -> Last Week | F85: =Schedule!G8 -> This Week | G85: =Schedule!H8 -> Last Week | H85: =Schedule!I8 -> This Week | ... J85: =Schedule!K8 -> 0 | K85: =+Manpower!Z23 -> Others | L85: =+Manpower!Z24 -> 20 | M85: =+Manpower!Z25 -> 26 | R85: =+Manpower!$N$49 -> Other | S85: =+Manpower!N50 -> 17 | T85: =+Manpower!N51 -> 14 | U85: =+Manpower!N52 -> 0 | V85: ='Major Quantities'!A5 -> B1.32 11 23.01 | W85: ='Major Quantities'!B5 -> Aggregate base course | AB85: ='Major Quantities'!C5 -> 14403 | AC85: ='Major Quantities'!D5 -> m³ | AD85: ='Major Quantities'!E5 -> 0 | AE85: ='Major Quantities'!F5 -> 0 | AF85: ='Major Quantities'!G5 -> 14403 | AG85: ='Major Quantities'!H5 -> 0
A86: =Schedule!B9 -> 66 | B86: =Schedule!C9 -> 1 | C86: =Schedule!D9 -> 7 | D86: =Schedule!E9 -> 6 | E86: =Schedule!F9 -> 89 | F86: =Schedule!G9 -> 83 | G86: =Schedule!H9 -> 8 | H86: =Schedule!I9 -> 8 | I86: =Schedule!J9 -> 0 | K86: Total | L86: =SUM(L79:L85) -> 105 | M86: =SUM(M79:M85) -> 119 | R86: Total | S86: =SUM(S79:S85) -> 50 | T86: =SUM(T79:T85) -> 64 | U86: =SUM(U79:U85) -> 0 | V86: ='Major Quantities'!A6 -> B1.32 11 26.01 | W86: ='Major Quantities'!B6 -> Bituminous base course (Grading I - Class A), including Prime Coat (MC1) and tack coat (RC2) (if any) | AB86: ='Major Quantities'!C6 -> 7129 | AC86: ='Major Quantities'!D6 -> m³ | AD86: ='Major Quantities'!E6 -> 0 | AE86: ='Major Quantities'!F6 -> 0 | AF86: ='Major Quantities'!G6 -> 7129 | AG86: ='Major Quantities'!H6 -> 0
P87: Top Issues and Risks
E88: ='Weekly Photos'!L23 -> RIP-RAP Works for Dike Wall 1 | K88: ='Weekly Photos'!B4 -> Cutting Works for Collector 9 | P88: Top 5 Issues
P89: Issue No | Q89: Date Identified | R89: Issue Description | V89: Responsible | W89: Action Taken | Z89: Mitigation | AE89: Current Status | AF89: Expected/Actual Closure | AG89: Duration Elapsed
P90: =IF(+Issues!B11="","",+Issues!B11) -> 1 | Q90: =IF(+Issues!C11="","",+Issues!C11) | R90: =IF(+Issues!D11="","",+Issues!D11) | V90: =IF(+Issues!E11="","",+Issues!E11) | W90: =IF(+Issues!F11="","",+Issues!F11) | AE90: =IF(+Issues!H11="","",+Issues!H11) | AF90: =IF(+Issues!I11="","",+Issues!I11) | AG90: =IF(+Issues!J11="","",+Issues!J11) -> 0
P91: =IF(+Issues!B12="","",+Issues!B12) -> 2 | Q91: =IF(+Issues!C12="","",+Issues!C12) | R91: =IF(+Issues!D12="","",+Issues!D12) | V91: =IF(+Issues!E12="","",+Issues!E12) | W91: =IF(+Issues!F12="","",+Issues!F12) | AE91: =IF(+Issues!H12="","",+Issues!H12) | AF91: =IF(+Issues!I12="","",+Issues!I12) | AG91: =IF(+Issues!J12="","",+Issues!J12) -> 0
P92: =IF(+Issues!B13="","",+Issues!B13) -> 3 | Q92: =IF(+Issues!C13="","",+Issues!C13) | R92: =IF(+Issues!D13="","",+Issues!D13) | V92: =IF(+Issues!E13="","",+Issues!E13) | W92: =IF(+Issues!F13="","",+Issues!F13) | AE92: =IF(+Issues!H13="","",+Issues!H13) | AF92: =IF(+Issues!I13="","",+Issues!I13) | AG92: =IF(+Issues!J13="","",+Issues!J13) -> 0
P93: =IF(+Issues!B14="","",+Issues!B14) -> 4 | Q93: =IF(+Issues!C14="","",+Issues!C14) | R93: =IF(+Issues!D14="","",+Issues!D14) | V93: =IF(+Issues!E14="","",+Issues!E14) | W93: =IF(+Issues!F14="","",+Issues!F14) | AE93: =IF(+Issues!H14="","",+Issues!H14) | AF93: =IF(+Issues!I14="","",+Issues!I14) | AG93: =IF(+Issues!J14="","",+Issues!J14) -> 0
P94: =IF(+Issues!B15="","",+Issues!B15) -> 5 | Q94: =IF(+Issues!C15="","",+Issues!C15) | R94: =IF(+Issues!D15="","",+Issues!D15) | V94: =IF(+Issues!E15="","",+Issues!E15) | W94: =IF(+Issues!F15="","",+Issues!F15) | AE94: =IF(+Issues!H15="","",+Issues!H15) | AF94: =IF(+Issues!I15="","",+Issues!I15) | AG94: =IF(+Issues!J15="","",+Issues!J15)

Sheet FIR summary 
A1: Project Name | C1: =+'General Information'!C3:I3 -> Completion of Infrastructure Works in The Second Industrial City in Makkah Al-Mukarramah | F1: Total FIR Amount | I1: =+Total -> 944735.5 | J1: Cum Previous FIR up to 29-09-2026 | K1: Cum up To Date FRI
A2: Project ID | C2: =+'General Information'!C4:I4 -> MKH2-02-003 | E2: Project Budget | F2: 52025516 | J2: 38688025 | K2: =J2+438397.58+944735.5 -> 40071158
A3: Date Period | C3: =+F3-6 -> 46302 | E3: To | F3: ='General Information'!L1 -> 46308
A5: BOQ Item # | B5: BOQ Description | C5: FIR # | D5: FIR DATE | E5: FIR Description | F5: Unit | G5: Unit Rate | H5: Current Pariod Quantity | I5: Total (SR)
A6: ROAD WORKS | K6: =+K2/52025516 -> 0.77022124
A7: B1.31 05 05.01 | B7: Removal of existing curbstone | F7: m | G7: 30 | I7: =+H7*G7 -> 0
A8: B1.31 05 05.02 | B8: Milling of the existing asphalt layer | F8: m² | G8: 10 | I8: =+H8*G8 -> 0
A9: B1.31 05 05.03 | B9: Removal of the existing asphalt layers (up to base course layer) | F9: m² | G9: 35 | I9: =+H9*G9 -> 0
A10: B1.31 05 05.08 | B10: Removal of the existing signages | F10: nr | G10: 5000 | I10: =+H10*G10 -> 0
A11: B1.31 05 05.11 | B11: Removal of the existing Street Lighting Poles | F11: nr | G11: 2500 | I11: =+H11*G11 -> 0
A12: B1.31 22 00.01 | B12: Roadway Excavation for cuttings (all types of soil) | F12: m3 | G12: 20 | I12: =+H12*G12 -> 0
F13: m3 | G13: 20 | I13: =+H13*G13 -> 0
A14: B1.31 22 00.02 | B14: Embankments to the ROW with common / suitable excavated material or with suitable imported material | F14: m3 | G14: 18 | I14: =+H14*G14 -> 0
F15: m3 | G15: 18 | I15: =+H15*G15 -> 0
A16: B1.31 22 00.03 | B16: Subgrade | F16: m3 | G16: 22 | I16: =+H16*G16 -> 0
F17: m3 | G17: 22 | I17: =+H17*G17 -> 0
A18: B1.32 11 23.01 | B18: Aggregate base course | F18: m3 | G18: 50 | I18: =+H18*G18 -> 0
F19: m3 | G19: 50 | I19: =+H19*G19 -> 0
A20: B1.32 11 26.01 | B20: Bituminous base course (Grading I - Class A), including Prime Coat (MC1) and tack coat (RC2) (if any) | F20: m3 | G20: 560 | I20: =+H20*G20 -> 0
F21: m3 | G21: 560 | I21: =+H21*G21 -> 0
A22: B1.32 12 16.01 | B22: Bituminous concrete wearing course, (Grading I - Class A), including tack coat (RC2) | C22: MKH2-02-003-ENJ-TS9-1-CVL-FIR-0772-00 | D22: 14/09/2026 | E22: Pavement of BWC at Sta 0+150 to 0+180 (Asphalt and Compaction) at BOX CULVERT 2 | F22: m3 | G22: 580 | H22: 35.63 | I22: =+H22*G22 -> 20665.4
A23: B1.32 14 13.01 | B23: Precast Concrete Kerb, Type K1-A | C23: MKH2-02-003-ENJ-TS9-1-CVL-FIR-0782-00 | D23: 46304 | E23: Interlock Block Paver for Sidewalk 60mm Thickness at Arterial Road 03 L/S Station 2+740 to 3+020 (Sand filling and compaction) | F23: m | G23: 60 | H23: 504 | I23: =+H23*G23 -> 30240
F24: m | G24: 60 | I24: =+H24*G24 -> 0
A25: B1.32 14 13.02 | B25: Precast Concrete Kerb, Type K4 | C25: MKH2-02-003-ENJ-TS9-1-CVL-FIR-0804-00 | D25: 16/09/2026 | E25: CASTING OF CONCRET CURB STONE (K4) FOR ART 04 2 STA (0+510 - 1+060) L/S SHOULDER | F25: m | G25: 60 | H25: 642.76 | I25: =+H25*G25 -> 38565.6
A26: B1.32 14 13.03 | B26: Precast Concrete Kerb, Type K1-B | C26: MKH2-02-003-ENJ-TS9-1-CVL-FIR-0784-01 | D26: 27/09/2026 | E26: CASTING OF CONCRET CURB STONE (K1-B) FOR ART 03 )ROUND ABOUT 05 L/S | F26: m | G26: 55 | H26: 89.2 | I26: =+H26*G26 -> 4906
C27: MKH2-02-003-ENJ-TS9-1-CVL-FIR-0787-00 | D27: 17/09/2026 | E27: CASTING OF CONCRET CURB STONE (K1-B) FOR ART 03 )ROUND ABOUT 05 R/S | F27: m | G27: 55 | H27: 87 | I27: =+H27*G27 -> 4785
A28: B1.32 14 13.13.01 | B28: 60mm thick - Interlocking block pavers for sidewalk/footpath | C28: MKH2-02-003-ENJ-TS9-1-CVL-FIR-0783-00 | D28: 15/09/2026 | E28: CASTING OF CONCRET CURB STONE (K1-A) FOR ART 03 AT STA (0+510 - 1+060) L SHOULDER | F28: m2 | G28: 70 | H28: 553.7 | I28: =+H28*G28 -> 38759
C29: MKH2-02-003-ENJ-TS9-1-CVL-FIR-0796-00 | D29: 17/09/2026 | E29: CASTING OF CONCRET CURB STONE (K1-A) FOR ART 03 AT STA (0+420 - 1+060) R SHOULDER | F29: m2 | G29: 70 | H29: 762.6 | I29: =+H29*G29 -> 53382
C30: MKH2-02-003-ENJ-TS9-1-CVL-FIR-0778-00 | D30: 46304 | E30: Interlock Block Paver for Side Walk 60mm Thickness at Arterial Road 03 L/S Station 3+100 to 3+720 (Sand filling and compaction) | F30: m2 | G30: 70 | H30: 1116 | I30: =+H30*G30 -> 78120
C31: MKH2-02-003-ENJ-TS9-1-CVL-FIR-0801-00 | D31: 14/09/2026 | E31: Interlock Block Paver for Sidewalk 60mm Thickness at Arterial Road 03 L&R ( BOX CULVERT 2) Station 0+150 to 0+180 (Sand filling and compaction) | F31: m2 | G31: 70 | H31: 185.56 | I31: =+H31*G31 -> 12989.2
C32: MKH2-02-003-ENJ-TS9-1-CVL-FIR-0805-00 | D32: 17/09/2026 | E32: Interlock Block Paver for Sidewalk 60mm Thickness at Arterial Road 03 L/S Station 2+600 to 2+740 (Sand filling and compaction) | F32: m2 | G32: 70 | H32: 279.86 | I32: =+H32*G32 -> 19590.2
C33: MKH2-02-003-ENJ-TS9-1-CVL-FIR-0818-00 | D33: 20/09/2026 | E33: Interlock Block Paver for Sidewalk 60mm Thickness at ROUND ABOUT 04 AT ROAD 03 L/S (Sand filling and compaction) | F33: m2 | G33: 70 | H33: 220.16 | I33: =+H33*G33 -> 15411.2
C34: MKH2-02-003-ENJ-TS9-1-CVL-FIR-0857-00 | D34: 30/09/2026 | E34: Installation of Interlock Block Paver for Side Walk 60mm Thickness at Arterial Road 03 L/S Station 3+080 to 3+100 | F34: m2 | G34: 70 | H34: 37.49 | I34: =+H34*G34 -> 2624.3
C35: MKH2-02-003-ENJ-TS9-1-CVL-FIR-0858-00 | D35: 28/09/2026 | E35: Interlock Block Paver for Side Walk 60mm Thickness at Arterial Road 03 L/S Station 3+816 to 3+840 (Sand filling and compaction) | F35: m2 | G35: 70 | H35: 43.6 | I35: =+H35*G35 -> 3052
C36: MKH2-02-003-ENJ-TS9-1-CVL-FIR-0868-00 | D36: 30/09/2026 | E36: INSULLATION Interlock Block Paver for Side Walk 60mm Thickness at Arterial Road 03 L/S Station 3+720 to 3+760 | F36: m2 | G36: 70 | H36: 62.43 | I36: =+H36*G36 -> 4370.1
F37: m2 | G37: 70 | I37: =+H37*G37 -> 0
A38: B1.32 17 23.01 | B38: Retroreflective Thermoplastic White paiting and traffic lines | F38: m² | G38: 36 | I38: =+H38*G38 -> 0
A39: B1.32 17 23.02 | B39: Retroreflective Thermoplastic Yellow paiting and traffic lines | F39: m² | G39: 36 | I39: =+H39*G39 -> 0
A40: B1.10 14 53.01 | B40: Traffic signs, ground mounted, Sheet Alumenium, (breakaway)Single post, with all accessories | F40: Unit | G40: 1700 | I40: =+H40*G40 -> 0
A41: B1.10 14 53.02 | B41: Set of traffic signals at intersection , the set include 4 signals,TSCP, controller, support and automatic traffic violation detection system (Saher) with all components and all necessary civil and electrical works to complete the works as per drawings and specifications. . | F41: Unit | G41: 750000 | I41: =+H41*G41 -> 0
A42: ELECTRICAL WORKS | I42: =+H42*G42 -> 0
A43: B2.26 05 19.01 | B43: Cable, Copper 4Cx16mm2 +1Cx10mm2 CU/XLPE/SWA/PVC | F43: m | G43: 70 | I43: =+H43*G43 -> 0
F44: m | G44: 70 | I44: =+H44*G44 -> 0
A45: B2.26 05 19.02 | B45: Cable, Copper 4Cx50mm2 +1Cx25mm2 CU/XLPE/SWA/PVC | F45: m | G45: 175 | I45: =+H45*G45 -> 0
A46: B2.26 05 19.03 | B46: Cable, Copper 4Cx95mm2 +1Cx50mm2 CU/XLPE/SWA/PVC | F46: m | G46: 270 | I46: =+H46*G46 -> 0
A47: B2.26 56 19.01 | B47: Lighting poles with 2 arms, height of ( 16 ) meters, including the power distribution box, cables , and RCC foundation. | F47: Unit | G47: 8000 | I47: =+H47*G47 -> 0
A48: B2.26 56 19.02 | B48: Lighting poles with 1 arm, height of ( 10 ) meters, including the power distribution box, cables , and RCC foundation. | F48: Unit | G48: 6400 | I48: =+H48*G48 -> 0
F49: Unit | G49: 6400 | I49: =+H49*G49 -> 0
A50: B2.26.56.19.04 | B50: Street Lighting( LED) Luminaire of Output ≥ 36385 lumen complete with control gear and lamp, (262) WATT. | F50: Unit | G50: 1600 | I50: =+H50*G50 -> 0
F51: Unit | G51: 1600 | I51: =+H51*G51 -> 0
A52: B2.26.56.19.05 | B52: Street Lighting( LED) Luminaire of Output ≥ 16784 lumen complete with control gear and lamp, (107) WATT. | F52: Unit | G52: 2000 | I52: =+H52*G52 -> 0
A53: B2.26 05 26.01 | B53: Including earthing of lighting poles ,masts. feeder pillars , unit substations, L.V feeders and KWH meter. | F53: Unit | G53: 1500 | I53: =+H53*G53 -> 0
A54: B2.33 71 19.01 | B54: Road crossing ducts, 2 ways (2 x 150mm PVC) | F54: m | G54: 300 | I54: =+H54*G54 -> 0
F55: m | G55: 300 | I55: =+H55*G55 -> 0 | K55: =+K2/52025516 -> 0.77022124
A56: B2.33 71 19.02 | B56: Road crossing ducts, 4 ways (4 x 150mm PVC) | F56: m | G56: 400 | I56: =+H56*G56 -> 0
F57: m | G57: 400 | I57: =+H57*G57 -> 0
A58: B2.33 71 19.02 | B58: Road crossing ducts, 6 ways (6 x 150mm PVC) | F58: m | G58: 650 | I58: =+H58*G58 -> 0
A59: B2.33 71 19.13.01 | B59: Drawpit with medium duty steel cover, size600x600x1000mm | F59: Unit | G59: 6000 | I59: =+H59*G59 -> 0
A60: B2.33 71 19.13.02 | B60: Drawpit with medium duty steel cover, size 900x900x1200mm | F60: Unit | G60: 12000 | I60: =+H60*G60 -> 0
A61: B2.26 24 16.01 | B61: Street Lighting panels | F61: Unit | G61: 28000 | I61: =+H61*G61 -> 0
A62: B2.26 24 16.02 | B62: Feeder pillars | F62: Unit | G62: 30000 | I62: =+H62*G62 -> 0
A63: B2.26 24 16.03 | B63: Supply and installation of KWH meter mounting frame including concrete block for installation of KWH meter according to the standards and specifications of SEC. | F63: Unit | G63: 12000 | I63: =+H63*G63 -> 0
A64: STORM WATER DRAINAGE | I64: =+H64*G64 -> 0
A65: B6.31 22 00.01 | B65: Excavation in (all types of soil) including all the required backfilling | F65: m3 | G65: 30 | I65: =+H65*G65 -> 0
A66: B6.03 30 00.01 | B66: Plain Concrete for box culvert | C66: MKH2-02-003-ENJ-TS9-1-CVL-FIR-0766-00 | D66: 14/09/2026 | E66: Checking coordinates and elevations for formworks and pouring lean concrete for box culvert 04 | F66: m3 | G66: 450 | H66: 24.82 | I66: =+H66*G66 -> 11169
F67: m3 | G67: 450 | I67: =+H67*G67 -> 0
A68: B6.03 30 00.02 | B68: Concrete for box culvert including bitumenous coating (Steel Reinforcement is measured separately) | C68: MKH2-02-003-ENJ-TS9-1-CVL-FIR-0800-00 | D68: 20/09/2026 | E68: checking coordinates and elevations for formworks and pouring concrete grade 35 mpa for base slab of box culvert 04 | F68: m3 | G68: 900 | H68: 85.68 | I68: =+H68*G68 -> 77112
C69: MKH2-02-003-ENJ-TS9-1-CVL-FIR-0825-00 | D69: 26/09/2026 | E69: checking coordinates and elevations for formworks and pouring concrete grade 35 mpa for outer and inner walls for box culvert 04 | F69: m3 | G69: 900 | H69: 22.44 | I69: =+H69*G69 -> 20196
A70: B6.03 30 00.03 | B70: Steel Reinforcement for box culverts as per drawings and the Engineer's instructions | C70: MKH2-02-003-ENJ-TS9-1-CVL-FIR-0799-00 | D70: 15/09/2026 | E70: checking reinforcement for base slab for box culvert 04 | F70: ton | G70: 4200 | H70: 18.95 | I70: =+H70*G70 -> 79590
C71: MKH2-02-003-ENJ-TS9-1-CVL-FIR-0869-00 | D71: 28/09/2026 | E71: checking reinforcement for top slab for box culvert 04 | F71: ton | G71: 4200 | H71: 8.88 | I71: =+H71*G71 -> 37296
A72: B6.31 22 00.04 | B72: Channel excavation in all type of soil for any depth including levelling, compaction and disposal of surplus material | F72: m³ | G72: 25 | I72: =+H72*G72 -> 0
F73: m³ | G73: 25 | I73: =+H73*G73 -> 0
A74: B6.31 22 00.05 | B74: embankments to the Channel Berms ,with suitable and approved imported material,from borrow pits, as showin in drawings. | C74: MKH2-02-003-ENJ-TS9-1-CVL-FIR-0780-00 | D74: 46304 | E74: Replacement of Sand with granular material 30cm for open channel 3C from station 1+460 TO 1+543.50 RS | F74: m³ | G74: 20 | H74: 154.03 | I74: =+H74*G74 -> 3080.6
C75: MKH2-02-003-ENJ-TS9-1-CVL-FIR-0781-00 | D75: 46304 | E75: Replacement of Sand with granular material 30cm for open channel 3C from station 1+680 TO 1+740 RS | F75: m³ | G75: 20 | H75: 119.21 | I75: =+H75*G75 -> 2384.2
C76: MKH2-02-003-ENJ-TS9-1-CVL-FIR-0802-00 | D76: 17/09/2026 | E76: Replacement of Sand with granular material 30cm for open channel 3C from station 0+750 TO 0+800 L/R | F76: m³ | G76: 20 | H76: 123.88 | I76: =+H76*G76 -> 2477.6
C77: MKH2-02-003-ENJ-TS9-1-CVL-FIR-0803-00 | D77: 17/09/2026 | E77: Replacement of Sand with granular material 30cm for open channel 3C from station 1+460 TO 1+543 LS | F77: m³ | G77: 20 | H77: 119.21 | I77: =+H77*G77 -> 2384.2
C78: MKH2-02-003-ENJ-TS9-1-CVL-FIR-0819-00 | D78: 20/09/2026 | E78: Field Inspection Request for Backfill 6th Layer at DIKE WALL 2 Station. 0+200 TO 0+240 | F78: m³ | G78: 20 | H78: 1268.41 | I78: =+H78*G78 -> 25368.2
C79: MKH2-02-003-ENJ-TS9-1-CVL-FIR-0851-00 | D79: 26/09/2026 | E79: Field Inspection Request for BACKFILL TOE at DIKE WALL 1 Station. 0+110 TO 0+147 | F79: m³ | G79: 20 | H79: 129.8 | I79: =+H79*G79 -> 2596
F80: m³ | G80: 20 | I80: =+H80*G80 -> 0
A81: B6.31 25 00.02 | B81: Finished grouted riprap as per drawings | F81: m² | G81: 90 | I81: =+H81*G81 -> 0
C82: MKH2-02-003-ENJ-TS9-1-CVL-FIR-0762-00 | D82: 46212 | E82: Checking Grouting and finishing of joints For Rip Rap Stones for Open Channel 3C from Sta. 0+280 to Sta.0+540 (Right Side) | F82: m² | G82: 90 | H82: 2202.76 | I82: =+H82*G82 -> 198248.4
C83: MKH2-02-003-ENJ-TS9-1-CVL-FIR-0789-00 | D83: 13/09/2026 | E83: Checking Grouting and finishing of joints For Rip Rap Stones for Open Channel 3C from Sta. 0+000 to Sta.0+080 (Left Side) | F83: m² | G83: 90 | H83: 489.71 | I83: =+H83*G83 -> 44073.9
C84: MKH2-02-003-ENJ-TS9-1-CVL-FIR-0791-00 | D84: 13/09/2026 | E84: Checking Grouting and finishing of joints For Rip Rap Stones for Open Channel 3C from Sta. 0+000 to Sta.0+060 (Right Side) | F84: m² | G84: 90 | H84: 508.33 | I84: =+H84*G84 -> 45749.7
C85: MKH2-02-003-ENJ-TS9-1-CVL-FIR-0795-00 | D85: 17/09/2026 | E85: Checking Grouting and finihings of joints for Dike Wall-2 from Sta. 0+400 to Sta.0+489.12 | F85: m² | G85: 90 | H85: 728.33 | I85: =+H85*G85 -> 65549.7
B86: Finished grouted riprap as per drawings | F86: m² | G86: 90 | I86: =+H86*G86 -> 0
A87: Total Pariod Amount | I87: =SUM(I6:I86) -> 944735.5

Sheet General Information
A1: Weekly Progress Report - Construction Projects | K1: Data Date | L1: 46308 | N1: Report No. | O1: =ROUNDUP(((L1-C14)/7),0) -> 35
A2: Contract General Information
A3: Project Name | C3: Completion of Infrastructure Works in The Second Industrial City in Makkah Al-Mukarramah
A4: Project ID | C4: MKH2-02-003
A5: Contractor | C5: Al Enjaz Trading & Contracting Co.
A6: Consultant | C6: Saudi Arabia Consulting Engineering Company "EGIS"
A7: Stage | C7: Construction
A8: Status | C8: Active
A9: Modon PM | C9: Engr. Abdallah Aljulaifi
A11: Key Dates
A12: Contract Award Date | C12: 46054
A13: Contract Sign Date | C13: 46061
A14: Site Handover Date | C14: 46068
A15: Original Completion | C15: 46613
A16: Contract Award Date (Hijri) | C16: 01/02/1447
A17: Contract Sign Date (Hijri) | C17: 08/02/1447
A18: Site Handover Date (Hijri) | C18: 15/02/1447
A19: Original Completion (Hijri) | C19: 14/08/1447
A20: Revised Completion Date | C20: 46613
A21: Committed Completion Date | C21: 46613
A22: Forecast Completion | C22: 46642
A23: Variance | C23: =C20-C22 -> -29
A25: Key Project Submittals | C25: Submission Date | D25: Days taken to approve orginal plan from site handover date
A26: Quality Plan submission | C26: 46076 | D26: =C26-C14 -> 8
A27: Quality Plan approval | C27: 46110
A28: Quality Plan Last Update | C28: 46110
A30: Safety Plan submission | C30: 46085 | D30: =C30-C14 -> 17
A31: Safety Plan approval | C31: 46090
A32: Safety Plan Last Update | C32: 46090
A34: Risk Management Plan submission | C34: 46076 | D34: =C34-C14 -> 8
A35: Risk Management Plan approval | C35: 46078
A36: Risk Management Plan Last Update | C36: 46078
A38: Baseline Schedule submission | C38: 46070 | D38: =C38-C14 -> 2
A39: Baseline Schedule approval | C39: 45717
A40: No of Schedule Versions | C40: 1
A41: Last Recovery Schedule Approval Date | C41: 45717
A43: BOQ submission | C43: 46231 | D43: =C43-C14 -> 163
A44: BOQ approval
A45: No of Approved Version of BOQ
A47: Project Execution Plan submission | C47: 46072 | D47: =C47-C14 -> 4
A48: Execution Plan Approval | C48: 46072

Sheet Progress
A1: Completion of Infrastruture in The Second Industrial City in Makkah (The project includes construction of Roads works ; Box Culvert ; Open Drain Channels and Dike Walls ; Street Lightings and Low Voltage Cables ,concrete ducts at road crossing) | R1: ='General Information'!$K$1 -> Data Date | S1: ='General Information'!L1 -> 46308
A4: Earned Value Progress (SAR) | J4: Physical Progress (Effort)
B5: BOQ Value (SAR) | C5: % Wt. | D5: Weekly (SAR) | G5: To Date (SAR) | J5: Budgeted | K5: % Wt. | L5: Weekly Physical Progress | N5: To Date Physical Progress
D6: Planned | E6: Earned | F6: Original Plan | G6: Planned | H6: Earned | J6: (Manhours) | L6: Planned | M6: Earned | N6: Planned | O6: Earned
A7: Mobilization | B7: =SUBTOTAL(9,B8:B8) -> 0 | C7: =IF(ISBLANK(B7),"",B7/$B$27) -> 0 | D7: =SUBTOTAL(9,D8:D8) -> 0 | E7: - | F7: =SUBTOTAL(9,F8:F8) -> 0 | G7: =SUBTOTAL(9,G8:G8) -> 0 | H7: - | J7: =SUBTOTAL(9,J8:J8) -> 14738 | K7: =IF(ISBLANK(J7),"",J7/$J$27) -> 0.029894584 | L7: =SUBTOTAL(9,L8:L8) -> 0 | M7: =SUBTOTAL(9,M8:M8) -> 0 | N7: =SUBTOTAL(9,N8:N8) -> 14738 | O7: =SUBTOTAL(9,O8:O8) -> 14738
B8: 0 | C8: =IF(ISBLANK(B8),"",B8/$B$27) -> 0 | D8: =+'Progress (2)'!I4 -> 0 | E8: =+'Progress (2)'!J4 -> 916464.08 | F8: =+'Progress (2)'!K4 -> 0 | G8: =+'Progress (2)'!L4 -> 0 | H8: =+'Progress (2)'!M4 -> 40099753 | J8: 14738 | K8: =IF(ISBLANK(J8),"",J8/$J$27) -> 0.029894584 | L8: =+'Progress (2)'!O4 -> 0 | M8: =+'Progress (2)'!P4 -> 0 | N8: =+'Progress (2)'!Q4 -> 14738 | O8: =+'Progress (2)'!R4 -> 14738
A9: Engineering | B9: =SUBTOTAL(9,B10:B10) -> 1560765.5 | C9: =IF(ISBLANK(B9),"",B9/$B$27) -> 0.03 | D9: =SUBTOTAL(9,D10:D10) -> 0 | E9: =SUBTOTAL(9,E10:E10) -> 0 | F9: =SUBTOTAL(9,F10:F10) -> 1560765.5 | G9: =SUBTOTAL(9,G10:G10) -> 1560765.5 | H9: =SUBTOTAL(9,H10:H10) -> 1560765.5 | J9: =SUBTOTAL(9,J10:J10) -> 24562 | K9: =IF(ISBLANK(J9),"",J9/$J$27) -> 0.049821602 | L9: =SUBTOTAL(9,L10:L10) -> 0 | M9: =SUBTOTAL(9,M10:M10) -> 0 | N9: =SUBTOTAL(9,N10:N10) -> 24562 | O9: =SUBTOTAL(9,O10:O10) -> 24562
B10: 1560765.5 | C10: =IF(ISBLANK(B10),"",B10/$B$27) -> 0.03 | D10: =+'Progress (2)'!I5 -> 0 | E10: =+'Progress (2)'!J5 -> 0 | F10: =+'Progress (2)'!K5 -> 1560765.5 | G10: =+'Progress (2)'!L5 -> 1560765.5 | H10: =+'Progress (2)'!M5 -> 1560765.5 | J10: 24562 | K10: =IF(ISBLANK(J10),"",J10/$J$27) -> 0.049821602 | L10: =+'Progress (2)'!O5 -> 0 | M10: =+'Progress (2)'!P5 -> 0 | N10: =+'Progress (2)'!Q5 -> 24562 | O10: =+'Progress (2)'!R5 -> 24562
A11: Procurement | B11: =SUBTOTAL(9,B12:B12) -> 10405103 | C11: =IF(ISBLANK(B11),"",B11/$B$27) -> 0.2 | D11: =SUBTOTAL(9,D12:D12) -> 0 | E11: =SUBTOTAL(9,E12:E12) -> 25502.7 | F11: =SUBTOTAL(9,F12:F12) -> 10405103 | G11: =SUBTOTAL(9,G12:G12) -> 10405103 | H11: =SUBTOTAL(9,H12:H12) -> 10060817 | J11: =SUBTOTAL(9,J12:J12) -> 58936 | K11: =IF(ISBLANK(J11),"",J11/$J$27) -> 0.11954588 | L11: =SUBTOTAL(9,L12:L12) -> 0 | M11: =SUBTOTAL(9,M12:M12) -> 152 | N11: =SUBTOTAL(9,N12:N12) -> 58936 | O11: =SUBTOTAL(9,O12:O12) -> 53310
B12: 10405103 | C12: =IF(ISBLANK(B12),"",B12/$B$27) -> 0.2 | D12: =+'Progress (2)'!I6 -> 0 | E12: =+'Progress (2)'!J6 -> 25502.7 | F12: =+'Progress (2)'!K6 -> 10405103 | G12: =+'Progress (2)'!L6 -> 10405103 | H12: =+'Progress (2)'!M6 -> 10060817 | J12: 58936 | K12: =IF(ISBLANK(J12),"",J12/$J$27) -> 0.11954588 | L12: =+'Progress (2)'!O6 -> 0 | M12: =+'Progress (2)'!P6 -> 152 | N12: =+'Progress (2)'!Q6 -> 58936 | O12: =+'Progress (2)'!R6 -> 53310
A13: Road Works | B13: =SUBTOTAL(9,B14:B14) -> 18062898 | C13: =IF(ISBLANK(B13),"",B13/$B$27) -> 0.34719305 | D13: =SUBTOTAL(9,D14:D14) -> 470222.41 | E13: =SUBTOTAL(9,E14:E14) -> 846741.38 | F13: =SUBTOTAL(9,F14:F14) -> 10120548 | G13: =SUBTOTAL(9,G14:G14) -> 10120548 | H13: =SUBTOTAL(9,H14:H14) -> 13145824 | J13: =SUBTOTAL(9,J14:J14) -> 118380 | K13: =IF(ISBLANK(J13),"",J13/$J$27) -> 0.24012219 | L13: =SUBTOTAL(9,L14:L14) -> 3390 | M13: =SUBTOTAL(9,M14:M14) -> 5197 | N13: =SUBTOTAL(9,N14:N14) -> 55810 | O13: =SUBTOTAL(9,O14:O14) -> 69355
B14: 18062898 | C14: =IF(ISBLANK(B14),"",B14/$B$27) -> 0.34719305 | D14: =+'Progress (2)'!I7 -> 470222.41 | E14: =+'Progress (2)'!J7 -> 846741.38 | F14: =+'Progress (2)'!K7 -> 10120548 | G14: =+'Progress (2)'!L7 -> 10120548 | H14: =+'Progress (2)'!M7 -> 13145824 | J14: 118380 | K14: =IF(ISBLANK(J14),"",J14/$J$27) -> 0.24012219 | L14: =+'Progress (2)'!O7 -> 3390 | M14: =+'Progress (2)'!P7 -> 5197 | N14: =+'Progress (2)'!Q7 -> 55810 | O14: =+'Progress (2)'!R7 -> 69355
A15: Electricity Works | B15: =SUBTOTAL(9,B16:B16) -> 2353781.9 | C15: =IF(ISBLANK(B15),"",B15/$B$27) -> 0.045242836 | D15: =SUBTOTAL(9,D16:D16) -> 51053.04 | E15: =SUBTOTAL(9,E16:E16) -> 44220 | F15: =SUBTOTAL(9,F16:F16) -> 291254.26 | G15: =SUBTOTAL(9,G16:G16) -> 291254.26 | H15: =SUBTOTAL(9,H16:H16) -> 1886038.2 | J15: =SUBTOTAL(9,J16:J16) -> 41030 | K15: =IF(ISBLANK(J15),"",J15/$J$27) -> 0.083225321 | L15: =SUBTOTAL(9,L16:L16) -> 1320 | M15: =SUBTOTAL(9,M16:M16) -> 1296 | N15: =SUBTOTAL(9,N16:N16) -> 9100 | O15: =SUBTOTAL(9,O16:O16) -> 29080
B16: 2353781.9 | C16: =IF(ISBLANK(B16),"",B16/$B$27) -> 0.045242836 | D16: =+'Progress (2)'!I8 -> 51053.04 | E16: =+'Progress (2)'!J8 -> 44220 | F16: =+'Progress (2)'!K8 -> 291254.26 | G16: =+'Progress (2)'!L8 -> 291254.26 | H16: =+'Progress (2)'!M8 -> 1886038.2 | J16: 41030 | K16: =IF(ISBLANK(J16),"",J16/$J$27) -> 0.083225321 | L16: =+'Progress (2)'!O8 -> 1320 | M16: =+'Progress (2)'!P8 -> 1296 | N16: =+'Progress (2)'!Q8 -> 9100 | O16: =+'Progress (2)'!R8 -> 29080
A17: Demolision | B17: =SUBTOTAL(9,B18:B18) -> 189275 | C17: =IF(ISBLANK(B17),"",B17/$B$27) -> 0.0036381186 | D17: =SUBTOTAL(9,D18:D18) -> 0 | E17: =SUBTOTAL(9,E18:E18) -> 0 | F17: =SUBTOTAL(9,F18:F18) -> 189275 | G17: =SUBTOTAL(9,G18:G18) -> 189275 | H17: =SUBTOTAL(9,H18:H18) -> 155775 | J17: =SUBTOTAL(9,J18:J18) -> 6490 | K17: =IF(ISBLANK(J17),"",J17/$J$27) -> 0.013164327 | L17: =SUBTOTAL(9,L18:L18) -> 0 | M17: =SUBTOTAL(9,M18:M18) -> 0 | N17: =SUBTOTAL(9,N18:N18) -> 6490 | O17: =SUBTOTAL(9,O18:O18) -> 4390
B18: 189275 | C18: =IF(ISBLANK(B18),"",B18/$B$27) -> 0.0036381186 | D18: =+'Progress (2)'!I9 -> 0 | E18: =+'Progress (2)'!J9 -> 0 | F18: =+'Progress (2)'!K9 -> 189275 | G18: =+'Progress (2)'!L9 -> 189275 | H18: =+'Progress (2)'!M9 -> 155775 | J18: 6490 | K18: =IF(ISBLANK(J18),"",J18/$J$27) -> 0.013164327 | L18: =+'Progress (2)'!O9 -> 0 | M18: =+'Progress (2)'!P9 -> 0 | N18: =+'Progress (2)'!Q9 -> 6490 | O18: =+'Progress (2)'!R9 -> 4390
A19: Box Culvert | B19: =SUBTOTAL(9,B20:B20) -> 3959941.2 | C19: =IF(ISBLANK(B19),"",B19/$B$27) -> 0.076115366 | D19: =SUBTOTAL(9,D20:D20) -> 0 | E19: =SUBTOTAL(9,E20:E20) -> 0 | F19: =SUBTOTAL(9,F20:F20) -> 3959941.2 | G19: =SUBTOTAL(9,G20:G20) -> 3959941.2 | H19: =SUBTOTAL(9,H20:H20) -> 3959941.2 | J19: =SUBTOTAL(9,J20:J20) -> 17395 | K19: =IF(ISBLANK(J19),"",J19/$J$27) -> 0.035284047 | L19: =SUBTOTAL(9,L20:L20) -> 0 | M19: =SUBTOTAL(9,M20:M20) -> 0 | N19: =SUBTOTAL(9,N20:N20) -> 17395 | O19: =SUBTOTAL(9,O20:O20) -> 17395
B20: 3959941.2 | C20: =IF(ISBLANK(B20),"",B20/$B$27) -> 0.076115366 | D20: =+'Progress (2)'!I10 -> 0 | E20: =+'Progress (2)'!J10 -> 0 | F20: =+'Progress (2)'!K10 -> 3959941.2 | G20: =+'Progress (2)'!L10 -> 3959941.2 | H20: =+'Progress (2)'!M10 -> 3959941.2 | J20: 17395 | K20: =IF(ISBLANK(J20),"",J20/$J$27) -> 0.035284047 | L20: =+'Progress (2)'!O10 -> 0 | M20: =+'Progress (2)'!P10 -> 0 | N20: =+'Progress (2)'!Q10 -> 17395 | O20: =+'Progress (2)'!R10 -> 17395
A21: Open Channel | B21: =SUBTOTAL(9,B22:B22) -> 10291200 | C21: =IF(ISBLANK(B21),"",B21/$B$27) -> 0.19781063 | D21: =SUBTOTAL(9,D22:D22) -> 121693.87 | E21: =SUBTOTAL(9,E22:E22) -> 0 | F21: =SUBTOTAL(9,F22:F22) -> 2213370.7 | G21: =SUBTOTAL(9,G22:G22) -> 2213370.7 | H21: =SUBTOTAL(9,H22:H22) -> 9330592.4 | J21: =SUBTOTAL(9,J22:J22) -> 185220 | K21: =IF(ISBLANK(J21),"",J21/$J$27) -> 0.37570056 | L21: =SUBTOTAL(9,L22:L22) -> 3180 | M21: =SUBTOTAL(9,M22:M22) -> 0 | N21: =SUBTOTAL(9,N22:N22) -> 52880 | O21: =SUBTOTAL(9,O22:O22) -> 178177
B22: 10291200 | C22: =IF(ISBLANK(B22),"",B22/$B$27) -> 0.19781063 | D22: =+'Progress (2)'!I11 -> 121693.87 | E22: =+'Progress (2)'!J11 -> 0 | F22: =+'Progress (2)'!K11 -> 2213370.7 | G22: =+'Progress (2)'!L11 -> 2213370.7 | H22: =+'Progress (2)'!M11 -> 9330592.4 | J22: 185220 | K22: =IF(ISBLANK(J22),"",J22/$J$27) -> 0.37570056 | L22: =+'Progress (2)'!O11 -> 3180 | M22: =+'Progress (2)'!P11 -> 0 | N22: =+'Progress (2)'!Q11 -> 52880 | O22: =+'Progress (2)'!R11 -> 178177
A23: Testing & Commissioning | B23: =SUBTOTAL(9,B24:B24) -> 5202551.6 | C23: =IF(ISBLANK(B23),"",B23/$B$27) -> 0.1 | D23: =SUBTOTAL(9,D24:D24) -> 0 | E23: =SUBTOTAL(9,E24:E24) -> 0 | F23: =SUBTOTAL(9,F24:F24) -> 0 | G23: =SUBTOTAL(9,G24:G24) -> 0 | H23: =SUBTOTAL(9,H24:H24) -> 0 | J23: =SUBTOTAL(9,J24:J24) -> 14740 | K23: =IF(ISBLANK(J23),"",J23/$J$27) -> 0.029898641 | L23: =SUBTOTAL(9,L24:L24) -> 0 | M23: =SUBTOTAL(9,M24:M24) -> 0 | N23: =SUBTOTAL(9,N24:N24) -> 0 | O23: =SUBTOTAL(9,O24:O24) -> 0
B24: 5202551.6 | C24: =IF(ISBLANK(B24),"",B24/$B$27) -> 0.1 | D24: =+'Progress (2)'!I12 -> 0 | E24: =+'Progress (2)'!J12 -> 0 | F24: =+'Progress (2)'!K12 -> 0 | G24: =+'Progress (2)'!L12 -> 0 | H24: =+'Progress (2)'!M12 -> 0 | J24: 14740 | K24: =IF(ISBLANK(J24),"",J24/$J$27) -> 0.029898641 | L24: =+'Progress (2)'!O12 -> 0 | M24: =+'Progress (2)'!P12 -> 0 | N24: =+'Progress (2)'!Q12 -> 0 | O24: =+'Progress (2)'!R12 -> 0
B25: - | C25: 0 | D25: =SUBTOTAL(9,D26:D26) -> 0 | E25: =SUBTOTAL(9,E26:E26) -> 0 | F25: =SUBTOTAL(9,F26:F26) -> 0 | G25: =SUBTOTAL(9,G26:G26) -> 0 | H25: =SUBTOTAL(9,H26:H26) -> 0 | J25: =SUBTOTAL(9,J26:J26) -> 9820 | K25: =IF(ISBLANK(J25),"",J25/$J$27) -> 0.019918905 | L25: =SUBTOTAL(9,L26:L26) -> 0 | M25: =SUBTOTAL(9,M26:M26) -> 0 | N25: =SUBTOTAL(9,N26:N26) -> 0 | O25: =SUBTOTAL(9,O26:O26) -> 0
B26: - | C26: 0 | D26: =+'Progress (2)'!I14 -> 0 | E26: =+'Progress (2)'!J14 -> 0 | F26: =+'Progress (2)'!K14 -> 0 | G26: =+'Progress (2)'!L14 -> 0 | H26: =+'Progress (2)'!M14 -> 0 | J26: 9820 | K26: =IF(ISBLANK(J26),"",J26/$J$27) -> 0.019918905 | L26: =+'Progress (2)'!O14 -> 0 | M26: =+'Progress (2)'!P14 -> 0 | N26: =+'Progress (2)'!Q14 -> 0 | O26: =+'Progress (2)'!R14 -> 0
A27: Total | B27: =+SUM(B9,B11,B13,B15,B17,B19,B21,B23) -> 52025516 | C27: =+SUM(C9,C11,C13,C15,C17,C19,C21,C23) -> 1 | D27: =+SUM(D7,D9,D11,D13,D15,D17,D19,D21,D23) -> 642969.32 | E27: =+SUM(E7,E9,E11,E13,E15,E17,E19,E21,E23) -> 916464.08 | F27: =+SUM(F7,F9,F11,F13,F15,F17,F19,F21,F23) -> 28740258 | G27: =+SUM(G7,G9,G11,G13,G15,G17,G19,G21,G23) -> 28740258 | H27: =+SUM(H7,H9,H11,H13,H15,H17,H19,H21,H23) -> 40099753 | I27: =+SUM(I9,I11,I13,I15,I17,I19,I21,I23) -> 0 | J27: 492999 | K27: =+SUM(K7,K9,K11,K13,K15,K17,K19,K21,K23,K25) -> 0.99657606 | L27: =+SUM(L7,L9,L11,L13,L15,L17,L19,L21,L23,L25) -> 7890 | M27: =+SUM(M7,M9,M11,M13,M15,M17,M19,M21,M23,M25) -> 6645 | N27: =+SUM(N7,N9,N11,N13,N15,N17,N19,N21,N23,N25) -> 239911 | O27: =+SUM(O7,O9,O11,O13,O15,O17,O19,O21,O23,O25) -> 391007
D28: =D27/$B$27 -> 0.01235873 | E28: =E27/$B$27 -> 0.017615665 | F28: =F27/$B$27 -> 0.55242619 | G28: =G27/$B$27 -> 0.55242619 | H28: =H27/$B$27 -> 0.77077089 | L28: =L27/$J$27 -> 0.016004089 | M28: =M27/$J$27 -> 0.013478729 | N28: =N27/$J$27 -> 0.48663588 | O28: =O27/$J$27 -> 0.79311926

Sheet Progress (2)
A1: CM This Week | I1: This Week | K1: CM | O1: This Week | Q1: CM
A2: Activity ID | B2: Planned Value Cost | C2: Earned Value Cost | D2: Planned Value Labor Units | E2: Earned Value Labor Units | F2: Schedule % Complete | G2: Performance % Complete | H2: Activity ID | I2: Planned Value Cost | J2: Earned Value Cost | K2: CM Original Plan | L2: CM Planned | M2: CM Earned | O2: Planned Value Labor Units | P2: Earned Value Labor Units | Q2: CM Planned Value Labor Units | R2: CM Earned Value Labor Units
A3: Total | B3: =+B35 -> 28740258 | C3: 2319038.9 | D3: =+D35 -> 239911 | E3: =+E35 -> 391007 | F3: =+F35 -> 0.5524 | G3: =+G35 -> 0.7708 | H3: Total | I3: =+B3-B16 -> 642969.31 | J3: =+C3-C16 -> 0 | K3: =B35 -> 28740258 | L3: =+B3 -> 28740258 | M3: =+C3 -> 2319038.9 | O3: =+D3-D16 -> 7890 | P3: =+E3-E16 -> 6646 | Q3: =+D3 -> 239911 | R3: =+E3 -> 391007
A4: Mobilization | B4: =+B36 -> 0 | C4: =+C35 -> 40099753 | D4: =+D36 -> 14738 | E4: =+E36 -> 14738 | F4: =+F36 -> 0 | G4: =+G36 -> 0 | H4: Mobilization | I4: =+B4-B17 -> 0 | J4: =+C4-C17 -> 916464.08 | K4: =B36 -> 0 | L4: =+B4 -> 0 | M4: =+C4 -> 40099753 | O4: =+D4-D17 -> 0 | P4: =+E4-E17 -> 0 | Q4: =+D4 -> 14738 | R4: =+E4 -> 14738
A5: Engineering | B5: =+B37 -> 1560765.5 | C5: =+C37 -> 1560765.5 | D5: =+D37 -> 24562 | E5: =+E37 -> 24562 | F5: =+F37 -> 1 | G5: =+G37 -> 1 | H5: Engineering | I5: =+B5-B18 -> 0 | J5: =+C5-C18 -> 0 | K5: =B37 -> 1560765.5 | L5: =+B5 -> 1560765.5 | M5: =+C5 -> 1560765.5 | O5: =+D5-D18 -> 0 | P5: =+E5-E18 -> 0 | Q5: =+D5 -> 24562 | R5: =+E5 -> 24562
A6: Procuments | B6: =+B38 -> 10405103 | C6: =+C38 -> 10060817 | D6: =+D38 -> 58936 | E6: =+E38 -> 53310 | F6: =+F38 -> 1 | G6: =+G38 -> 0.9669 | H6: Procuments | I6: =+B6-B19 -> 0 | J6: =+C6-C19 -> 25502.7 | K6: =B38 -> 10405103 | L6: =+B6 -> 10405103 | M6: =+C6 -> 10060817 | O6: =+D6-D19 -> 0 | P6: =+E6-E19 -> 152 | Q6: =+D6 -> 58936 | R6: =+E6 -> 53310
A7: Road Works | B7: =+B39 -> 10120548 | C7: =+C39 -> 13145824 | D7: =+D39 -> 55810 | E7: =+E39 -> 69355 | F7: =+F39 -> 2.699 | G7: =+G39 -> 3.2506 | H7: Road Works | I7: =+B7-B20 -> 470222.41 | J7: =+C7-C20 -> 846741.38 | K7: =B39 -> 10120548 | L7: =+B7 -> 10120548 | M7: =+C7 -> 13145824 | O7: =+D7-D20 -> 3390 | P7: =+E7-E20 -> 5197 | Q7: =+D7 -> 55810 | R7: =+E7 -> 69355
A8: Electrical Works | B8: =+B40 -> 291254.26 | C8: =+C40 -> 1886038.2 | D8: =+D40 -> 9100 | E8: =+E40 -> 29080 | F8: =+F40 -> 0.2487 | G8: =+G40 -> 2.2185 | H8: Electrical Works | I8: =+B8-B21 -> 51053.04 | J8: =+C8-C21 -> 44220 | K8: =B40 -> 291254.26 | L8: =+B8 -> 291254.26 | M8: =+C8 -> 1886038.2 | O8: =+D8-D21 -> 1320 | P8: =+E8-E21 -> 1296 | Q8: =+D8 -> 9100 | R8: =+E8 -> 29080
A9: Demolition Works | B9: =+B41 -> 189275 | C9: =+C41 -> 155775 | D9: =+D41 -> 6490 | E9: =+E41 -> 4390 | F9: =+F41 -> 1 | G9: =+G41 -> 0.823 | H9: Demolition Works | I9: =+B9-B22 -> 0 | J9: =+C9-C22 -> 0 | K9: =B41 -> 189275 | L9: =+B9 -> 189275 | M9: =+C9 -> 155775 | O9: =+D9-D22 -> 0 | P9: =+E9-E22 -> 0 | Q9: =+D9 -> 6490 | R9: =+E9 -> 4390
A10: Box Culvert | B10: =+B42 -> 3959941.2 | C10: =+C42 -> 3959941.2 | D10: =+D42 -> 17395 | E10: =+E42 -> 17395 | F10: =+F42 -> 2 | G10: =+G42 -> 2 | H10: Box Culvert | I10: =+B10-B23 -> 0 | J10: =+C10-C23 -> 0 | K10: =B42 -> 3959941.2 | L10: =+B10 -> 3959941.2 | M10: =+C10 -> 3959941.2 | O10: =+D10-D23 -> 0 | P10: =+E10-E23 -> 0 | Q10: =+D10 -> 17395 | R10: =+E10 -> 17395
A11: Open Drain Channel | B11: =+B43 -> 2213370.7 | C11: =+C43 -> 9330592.4 | D11: =+D43 -> 52880 | E11: =+E43 -> 178177 | F11: =+F43 -> 0.2151 | G11: =+G43 -> 0.9067 | H11: Open Drain Channel | I11: =+B11-B24 -> 121693.87 | J11: =+C11-C24 -> 0 | K11: =B43 -> 2213370.7 | L11: =+B11 -> 2213370.7 | M11: =+C11 -> 9330592.4 | O11: =+D11-D24 -> 3180 | P11: =+E11-E24 -> 0 | Q11: =+D11 -> 52880 | R11: =+E11 -> 178177
A12: Testing and Commissioning | B12: =+B44 -> 0 | C12: =+C44 -> 0 | D12: =+D44 -> 0 | E12: =+E44 -> 0 | F12: =+F44 -> 0 | G12: =+G44 -> 0 | H12: Testing and Commissioning | I12: =+B12-B25 -> 0 | J12: =+C12-C25 -> 0 | K12: =B44 -> 0 | L12: =+B12 -> 0 | M12: =+C12 -> 0 | O12: =+D12-D25 -> 0 | P12: =+E12-E25 -> 0 | Q12: =+D12 -> 0 | R12: =+E12 -> 0
A13: No Construction | B13: 0 | C13: 0 | D13: 0 | E13: 0 | F13: 0 | G13: 0 | H13: No Construction | I13: =+B13-B26 -> 0 | J13: =+C13-C26 -> 0 | K13: =B45 -> 0 | L13: =+B13 -> 0 | M13: =+C13 -> 0 | O13: =+D13-D26 -> 0 | P13: =+E13-E26 -> 0 | Q13: =+D13 -> 0 | R13: =+E13 -> 0
A14: CM Last Week
A15: Activity ID | B15: Planned Value Cost | C15: Earned Value Cost | D15: Planned Value Labor Units | E15: Earned Value Labor Units | F15: Schedule % Complete | G15: Performance % Complete
A16: Total | B16: 28097288 | C16: 2319038.9 | D16: 232021 | E16: 384361 | F16: 0.5401 | G16: 0.7532
A17: Mobilization | B17: 0 | C17: 39183289 | D17: 14738 | E17: 14738 | F17: 0 | G17: 0
A18: Engineering | B18: 1560765.5 | C18: 1560765.5 | D18: 24562 | E18: 24562 | F18: 1 | G18: 1
A19: Procuments | B19: 10405103 | C19: 10035314 | D19: 58936 | E19: 53158 | F19: 1 | G19: 0.9645
A20: Road Works | B20: 9650325.4 | C20: 12299083 | D20: 52420 | E20: 64158 | F20: 2.6101 | G20: 2.7739
A21: Electrical Works | B21: 240201.22 | C21: 1841818.2 | D21: 7780 | E21: 27784 | F21: 0.2038 | G21: 2.1706
A22: Demolition Works | B22: 189275 | C22: 155775 | D22: 6490 | E22: 4390 | F22: 1 | G22: 0.823
A23: Box Culvert | B23: 3959941.2 | C23: 3959941.2 | D23: 17395 | E23: 17395 | F23: 2 | G23: 2
A24: Open Drain Channel | B24: 2091676.8 | C24: 9330592.4 | D24: 49700 | E24: 178177 | F24: 0.2032 | G24: 0.9067
A25: Testing and Commissioning | B25: 0 | C25: 0 | D25: 0 | E25: 0 | F25: 0 | G25: 0
A26: No Construction | B26: 0 | C26: 0 | D26: 0 | E26: 0 | F26: 0 | G26: 0
A34: Activity ID | B34: Planned Value Cost | C34: Earned Value Cost | D34: Planned Value Labor Units | E34: Earned Value Labor Units | F34: Schedule % Complete | G34: Performance % Complete
A35: Total | B35: =+AF51 -> 28740258 | C35: =+AG51 -> 40099753 | D35: =+AD51 -> 239911 | E35: =+AE51 -> 391007 | F35: =+AA51 -> 0.5524 | G35: =+AB51 -> 0.7708
A36: Mobilization | B36: =AF53 -> 0 | C36: =AG53 -> 0 | D36: =AD53 -> 14738 | E36: =AE53 -> 14738 | F36: =AA53 -> 0 | G36: =AB53 -> 0
A37: Engineering | B37: =AF54 -> 1560765.5 | C37: =AG54 -> 1560765.5 | D37: =AD54 -> 24562 | E37: =AE54 -> 24562 | F37: =AA54 -> 1 | G37: =AB54 -> 1
A38: Procuments | B38: =AF55 -> 10405103 | C38: =AG55 -> 10060817 | D38: =AD55 -> 58936 | E38: =AE55 -> 53310 | F38: =AA55 -> 1 | G38: =AB55 -> 0.9669
A39: Road Works | B39: =AF61+AF66+AF69+AF70+AF71+AF73+AF76 -> 10120548 | C39: =AG61+AG66+AG69+AG70+AG71+AG73+AG76 -> 13145824 | D39: =AD61+AD66+AD69+AD70+AD71+AD73+AD76 -> 55810 | E39: =AE61+AE66+AE69+AE70+AE71++AE73+AE76 -> 69355 | F39: =AA61+AA66+AA69+AA70+AA71+AA73+AA76 -> 2.699 | G39: =AB61+AB66+AB69+AB70+AB71+AB73+AB76 -> 3.2506
A40: Electrical Works | B40: =AF62+AF67+AF74+AF77 -> 291254.26 | C40: =AG62+AG67+AG74+AG77 -> 1886038.2 | D40: =AD62+AD67+AD74+AD77 -> 9100 | E40: =AE62+AE67+AE74+AE77 -> 29080 | F40: =AA62+AA67+AA74+AA77 -> 0.2487 | G40: =AB62+AB67+AB74+AB77 -> 2.2185
A41: Demolition Works | B41: =AF78 -> 189275 | C41: =AG78 -> 155775 | D41: =AD78 -> 6490 | E41: =AE78 -> 4390 | F41: =AA78 -> 1 | G41: =AB78 -> 0.823
A42: Box Culvert | B42: =AF59+AF64 -> 3959941.2 | C42: =AG59+AG64 -> 3959941.2 | D42: =AD59+AD64 -> 17395 | E42: =AE59+AE64 -> 17395 | F42: =AA59+AA64 -> 2 | G42: =AB59+AB64 -> 2
A43: Open Drain Channel | B43: =AF79 -> 2213370.7 | C43: =AG79 -> 9330592.4 | D43: =AD79 -> 52880 | E43: =AE79 -> 178177 | F43: =AA79 -> 0.2151 | G43: =AB79 -> 0.9067
A44: Testing and Commissioning | B44: =AF80 -> 0 | C44: =AG80 -> 0 | D44: =AD80 -> 0 | E44: =AE80 -> 0 | F44: =AA80 -> 0 | G44: =AB80 -> 0
A45: No Construction
T50: Activity ID | U50: Activity Name | V50: Original Duration | W50: Start | X50: Finish | Y50: Total Float | Z50: Budgeted Total Cost | AA50: Schedule % Complete | AB50: Performance % Complete | AC50: Budgeted Labor Units | AD50: Planned Value Labor Units | AE50: Earned Value Labor Units | AF50: Planned Value Cost | AG50: Earned Value Cost
T51: MKH2-02-003 - Completion of Infrastructure Works at the Second Industrial City in Makkah UP 32 | V51: 478 | W51: 15-Feb-26 A | X51: 46642 | Y51: -25 | Z51: 52025516 | AA51: 0.5524 | AB51: 0.7708 | AC51: 491311 | AD51: 239911 | AE51: 391007 | AF51: 28740258 | AG51: 40099753
T52: KEY MILESTONES | V52: 478 | W52: 15-Feb-26 A | X52: 46642 | Y52: -25 | Z52: 0 | AA52: 0 | AB52: 0 | AC52: 0 | AD52: 0 | AE52: 0 | AF52: 0 | AG52: 0
T53: MOBILIZATION | V53: 99 | W53: 15-Feb-26 A | X53: 06-Jun-26 A | Z53: 0 | AA53: 0 | AB53: 0 | AC53: 14738 | AD53: 14738 | AE53: 14738 | AF53: 0 | AG53: 0
T54: ENGINEERING | V54: 133 | W54: 17-Feb-26 A | X54: 22-Jul-26 A | Z54: 1560765.5 | AA54: 1 | AB54: 1 | AC54: 24562 | AD54: 24562 | AE54: 24562 | AF54: 1560765.5 | AG54: 1560765.5
T55: PROCUREMENT | V55: 198 | W55: 10-Mar-26 A | X55: 46383 | Y55: -16 | Z55: 10405103 | AA55: 1 | AB55: 0.9669 | AC55: 58936 | AD55: 58936 | AE55: 53310 | AF55: 10405103 | AG55: 10060817
T56: CONSTRUCTION PHASE | V56: 396 | W56: 18-Feb-26 A | X56: 46582 | Y56: -16 | Z56: 34857096 | AA56: 0.4812 | AB56: 0.817 | AC56: 368515 | AD56: 141675 | AE56: 298396 | AF56: 16774389 | AG56: 28478171
T57: ROADS | V57: 379 | W57: 18-Feb-26 A | X57: 46582 | Y57: -16 | Z57: 24376621 | AA57: 0.5896 | AB57: 0.7791 | AC57: 176805 | AD57: 82305 | AE57: 115830 | AF57: 14371743 | AG57: 18991803
T58: ARTERIAL-03 (2+510 to 4+267.54) | V58: 295 | W58: 18-Feb-26 A | X58: 46460 | Y58: 24 | Z58: 11737666 | AA58: 0.7248 | AB58: 0.9162 | AC58: 62760 | AD58: 45870 | AE58: 56850 | AF58: 8507174 | AG58: 10754187
T59: Box Culvert - 1 | V59: 105 | W59: 04-Mar-26 A | X59: 22-Aug-26 A | Z59: 2986578.6 | AA59: 1 | AB59: 1 | AC59: 13850 | AD59: 13850 | AE59: 13850 | AF59: 2986578.6 | AG59: 2986578.6
T60: ARTERIAL-03-ROAD | V60: 289 | W60: 18-Feb-26 A | X60: 46460 | Y60: 24 | Z60: 8751087.5 | AA60: 0.6308 | AB60: 0.8876 | AC60: 48910 | AD60: 32020 | AE60: 43000 | AF60: 5520595.4 | AG60: 7767607.9
T61: ROADS & ROUNDABOUT | V61: 289 | W61: 18-Feb-26 A | X61: 46460 | Y61: 18 | Z61: 7533911.9 | AA61: 0.6958 | AB61: 0.8695 | AC61: 33030 | AD61: 24440 | AE61: 27120 | AF61: 5242434.9 | AG61: 6550432.3
T62: ELECTRICAL | V62: 142 | W62: 01-Apr-26 A | X62: 10-Oct-26 A | Z62: 1217175.6 | AA62: 0.2285 | AB62: 1 | AC62: 15880 | AD62: 7580 | AE62: 15880 | AF62: 278160.55 | AG62: 1217175.6
T63: ARTERIAL-04 (0+000 to 1+0.83) | V63: 338 | W63: 10-Mar-26 A | X63: 46538 | Y63: -9 | Z63: 7559557.3 | AA63: 0.5335 | AB63: 0.8446 | AC63: 39845 | AD63: 16065 | AE63: 31694 | AF63: 4033142.2 | AG63: 6384977.5
T64: Box Culvert - 2 | V64: 134 | W64: 25-Mar-26 A | X64: 05-Aug-26 A | Z64: 973362.6 | AA64: 1 | AB64: 1 | AC64: 3545 | AD64: 3545 | AE64: 3545 | AF64: 973362.6 | AG64: 973362.6
T65: ARTERIAL-04-ROAD | V65: 304 | W65: 10-Mar-26 A | X65: 46538 | Y65: -9 | Z65: 6586194.7 | AA65: 0.4646 | AB65: 0.8217 | AC65: 36300 | AD65: 12520 | AE65: 28149 | AF65: 3059779.6 | AG65: 5411614.9
T66: ROADS | V66: 260 | W66: 10-Mar-26 A | X66: 46497 | Y66: -9 | Z66: 5938291.3 | AA66: 0.5131 | AB66: 0.811 | AC66: 23180 | AD66: 11000 | AE66: 16461 | AF66: 3046685.9 | AG66: 4815747.7
T67: ELECTRICAL WORKS (MKH2-01-007-DAR-TS8-0-SL-DWG-1010-00) | V67: 221 | W67: 03-Jun-26 A | X67: 46538 | Y67: -9 | Z67: 647903.4 | AA67: 0.0202 | AB67: 0.9197 | AC67: 13120 | AD67: 1520 | AE67: 11688 | AF67: 13093.71 | AG67: 595867.18
T68: CONNECTION TO 5th RING ROAD (IF-0+000 to 1+258) | V68: 240 | W68: 22-Sep-26 A | X68: 46582 | Y68: -16 | Z68: 3573515.8 | AA68: 0.4399 | AB68: 0.4031 | AC68: 23370 | AD68: 9730 | AE68: 9315 | AF68: 1571835.2 | AG68: 1440380.9
T69: EARTHWORKS & SITE GRADING | V69: 76 | W69: 22-Sep-26 A | X69: 46354 | Y69: -21 | Z69: 1604369.7 | AA69: 0.9797 | AB69: 0.8609 | AC69: 10500 | AD69: 9730 | AE69: 8883 | AF69: 1571835.2 | AG69: 1381233.2
T70: ASPHALT WORKS | V70: 124 | W70: 08-Oct-26 A | X70: 46527 | Y70: -16 | Z70: 1405325 | AA70: 0 | AB70: 0.0421 | AC70: 10830 | AD70: 0 | AE70: 432 | AF70: 0 | AG70: 59147.6
T71: FINISHING WORKS | V71: 47 | W71: 46529 | X71: 46582 | Y71: -16 | Z71: 563821.08 | AA71: 0 | AB71: 0 | AC71: 2040 | AD71: 0 | AE71: 0 | AF71: 0 | AG71: 0
T72: RAMP-2-IN (0+000 to 0+400) | V72: 238 | W72: 05-Aug-26 A | X72: 46557 | Y72: -25 | Z72: 752969.25 | AA72: 0.1752 | AB72: 0.2094 | AC72: 27080 | AD72: 6650 | AE72: 8214 | AF72: 131938.12 | AG72: 157644.58
T73: ROADS | V73: 178 | W73: 05-Aug-26 A | X73: 46483 | Y73: 11 | Z73: 508589.34 | AA73: 0.2594 | AB73: 0.31 | AC73: 20450 | AD73: 6650 | AE73: 8214 | AF73: 131938.12 | AG73: 157644.58
T74: ELECTRICAL WORKS (MKH2-01-007-DAR-TS8-0-SL-DWG-1010-00) | V74: 83 | W74: 46454 | X74: 46557 | Y74: -25 | Z74: 244379.92 | AA74: 0 | AB74: 0 | AC74: 6630 | AD74: 0 | AE74: 0 | AF74: 0 | AG74: 0
T75: RAMP-2-OUT (0+398 to 0+000) | V75: 181 | W75: 05-Aug-26 A | X75: 46511 | Y75: 11 | Z75: 752912.29 | AA75: 0.1695 | AB75: 0.3382 | AC75: 23750 | AD75: 3990 | AE75: 9757 | AF75: 127653.69 | AG75: 254614
T76: ROADS | V76: 177 | W76: 05-Aug-26 A | X76: 46506 | Y76: -5 | Z76: 508589.34 | AA76: 0.251 | AB76: 0.3571 | AC76: 18350 | AD76: 3990 | AE76: 8245 | AF76: 127653.69 | AG76: 181618.62
T77: ELECTRICAL WORKS (MKH2-01-007-DAR-TS8-0-SL-DWG-1010-00) | V77: 146 | W77: 10-Sep-26 A | X77: 46511 | Y77: 11 | Z77: 244322.95 | AA77: 0 | AB77: 0.2988 | AC77: 5400 | AD77: 0 | AE77: 1512 | AF77: 0 | AG77: 72995.39
T78: DEMOLISHING WORKS | V78: 122 | W78: 08-Apr-26 A | X78: 46324 | Y78: 136 | Z78: 189275 | AA78: 1 | AB78: 0.823 | AC78: 6490 | AD78: 6490 | AE78: 4390 | AF78: 189275 | AG78: 155775
T79: Open Drain Channels | V79: 366 | W79: 14-Mar-26 A | X79: 46581 | Y79: -25 | Z79: 10291200 | AA79: 0.2151 | AB79: 0.9067 | AC79: 185220 | AD79: 52880 | AE79: 178177 | AF79: 2213370.7 | AG79: 9330592.4
T80: TESTING & COMMISSIONING | V80: 71 | W80: 46508 | X80: 46593 | Y80: -19 | Z80: 5202551.6 | AA80: 0 | AB80: 0 | AC80: 14740 | AD80: 0 | AE80: 0 | AF80: 0 | AG80: 0
T81: PROJECT CLOSEOUT & DEMOBILIZATION | V81: 107 | W81: 46515 | X81: 46642 | Y81: -25 | Z81: 0 | AA81: 0 | AB81: 0 | AC81: 9820 | AD81: 0 | AE81: 0 | AF81: 0 | AG81: 0

Sheet Weekly Photos
B1: Date | C1: ='Weekly Progress Report'!AF1 -> 46308
B4: Cutting Works for Collector 9 | L4: Installation of Interlock Block works for Arterial 4
B23: ABC Works for Non-Muslim Road | L23: RIP-RAP Works for Dike Wall 1

Sheet Quality
B2: QC OBSERVATIONS CHECKLIST
BB4: ='General Information'!C14 -> 46068
B6: Project No. | E6: ='General Information'!C4 -> MKH2-02-003 | K6: OBS No. | O6: ='General Information'!O1 -> 35 | U6: Inspection Day: | X6: ='General Information'!L1 -> 46308
B8: Project | E8: ='General Information'!C3 -> Completion of Infrastructure Works in The Second Industrial City in Makkah Al-Mukarramah | O8: Contractor: Consultant: | U8: ='General Information'!C5&" "&'General Information'!C6 -> Al Enjaz Trading & Contracting Co. Saudi Arabia Consulting Engineering Company "EGIS"
B10: 4 | D10: Excellent | G10: Quality Management System is being practiced and applies to MODON System | Z10: 90 - 100 | AB10: QC Overall Score | AC10: =Q49 -> 0.9012069 | AN10: =SUM(Z10:Z13) -> 0 | AO10: 100 | AP10: 0.22883295
B11: 3 | D11: Good | G11: Evidence of compliance with plans and procedures. | Z11: 80 - 89 | AN11: =SUM(Y10:Y14) -> 0 | AO11: 89 | AP11: 0.20366133
B12: 2 | D12: Average | G12: Indication level of compliance with standards but there is room for improvement | Z12: 70 - 79 | AO12: 79 | AP12: 0.18077803
B13: 1 | D13: Improve | G13: Quality and Control is NOT being managed effectively. Needs Improvement | Z13: ≤ 69 | AO13: 69 | AP13: 0.15789474
B14: 0 | D14: N/A | G14: Item was not applicable or this item was not reviewed during the inspection. | Z14: Zero | AO14: 100 | AP14: 0.22883295
B16: No. | C16: Topic | K16: E (4) | L16: G (3) | M16: A (2) | N16: I (1) | O16: N/A (0) | Q16: No. | R16: Topic | Z16: E (4) | AA16: G (3) | AB16: A (2) | AC16: I (1) | AD16: N/A (0) | AO16: =SUM(AO10:AO15) -> 437
K17: 1 | L17: 0.89 | M17: 0.79 | N17: 0.69 | O17: 1 | Z17: 1 | AA17: 0.89 | AB17: 0.79 | AC17: 0.69 | AD17: 1 | AF17: =SUM(AF18:AG46)/COUNT(AF18:AG46) -> 0.9012069
B18: 1 | C18: Control of Access to Site/Office | L18: 1 | Q18: 30 | R18: QC of Excavation | AA18: 1 | AF18: =SUMPRODUCT($K$17:$O$17,K18:O18) -> 0.89 | AG18: =SUMPRODUCT($Z$17:$AD$17,Z18:AD18) -> 0.89 | AV18: Item Count | AW18: Score | AX18: Distributtion
B19: 2 | C19: Document Control Administration | L19: 1 | Q19: 31 | R19: QC of Roads/Round about | AA19: 1 | AF19: =SUMPRODUCT($K$17:$O$17,K19:O19) -> 0.89 | AG19: =SUMPRODUCT($Z$17:$AD$17,Z19:AD19) -> 0.89 | AX19: Overall | AY19: Relevant
B20: 3 | C20: Project Documents and Progress | L20: 1 | Q20: 32 | R20: QC of Interlock & Curbstone | AA20: 1 | AF20: =SUMPRODUCT($K$17:$O$17,K20:O20) -> 0.89 | AG20: =SUMPRODUCT($Z$17:$AD$17,Z20:AD20) -> 0.89 | AM20: 4 | AN20: =58 -> 58 | AO20: counts | AQ20: 4 | AR20: Excellent | AV20: =SUM(Z18:Z46,K18:K46) -> 0 | AW20: =AQ20*AV20 -> 0 | AX20: =AV20/$AV$25 -> 0 | AY20: =AV20/SUM($AV$20:$AV$23) -> 0
B21: 4 | C21: Contractor's Quality Plan/CM (Updated and Reviewed) | L21: 1 | Q21: 33 | R21: Layers/Backfilling Sampling | AA21: 1 | AF21: =SUMPRODUCT($K$17:$O$17,K21:O21) -> 0.89 | AG21: =SUMPRODUCT($Z$17:$AD$17,Z21:AD21) -> 0.89 | AM21: 3 | AN21: =58 -> 58 | AO21: counts | AQ21: 3 | AR21: Good | AV21: =SUM(L18:L46,AA18:AA46) -> 34 | AW21: =AQ21*AV21 -> 102 | AX21: =AV21/$AV$25 -> 0.5862069 | AY21: =AV21/SUM($AV$20:$AV$23) -> 0.79069767
B22: 5 | C22: MS Log and Paperwork | L22: 1 | Q22: 34 | R22: Pump Stations Units | AD22: 1 | AF22: =SUMPRODUCT($K$17:$O$17,K22:O22) -> 0.89 | AG22: =SUMPRODUCT($Z$17:$AD$17,Z22:AD22) -> 1 | AM22: 2 | AN22: =58 -> 58 | AO22: counts | AQ22: 2 | AR22: Average | AV22: =SUM(M18:M46,AB18:AB46) -> 8 | AW22: =AQ22*AV22 -> 16 | AX22: =AV22/$AV$25 -> 0.13793103 | AY22: =AV22/SUM($AV$20:$AV$23) -> 0.18604651 | BC22: NB: Insert 1, or 0 in the required cell only.
B23: 6 | C23: RFI, FIR, & MIR Procedure | L23: 1 | Q23: 35 | R23: Quality of Form Work | AA23: 1 | AF23: =SUMPRODUCT($K$17:$O$17,K23:O23) -> 0.89 | AG23: =SUMPRODUCT($Z$17:$AD$17,Z23:AD23) -> 0.89 | AM23: 1 | AN23: =58 -> 58 | AO23: counts | AQ23: 1 | AR23: Improve | AV23: =SUM(N18:N46,AC18:AC46) -> 1 | AW23: =AQ23*AV23 -> 1 | AX23: =AV23/$AV$25 -> 0.017241379 | AY23: =AV23/SUM($AV$20:$AV$23) -> 0.023255814
B24: 7 | C24: RFI, FIR, & MIR Inventory system | L24: 1 | Q24: 36 | R24: Design Change List | AD24: 1 | AF24: =SUMPRODUCT($K$17:$O$17,K24:O24) -> 0.89 | AG24: =SUMPRODUCT($Z$17:$AD$17,Z24:AD24) -> 1 | AM24: 0 | AN24: =58 -> 58 | AO24: counts | AQ24: 0 | AR24: N/A | AV24: =SUM(O18:O46,AD18:AD46) -> 15 | AW24: =AQ24*AV24 -> 0 | AX24: =AV24/$AV$25 -> 0.25862069 | AY24: -
B25: 8 | C25: NCRs Control & Procedure | L25: 1 | Q25: 37 | R25: Quality of Concrete Placing | AA25: 1 | AF25: =SUMPRODUCT($K$17:$O$17,K25:O25) -> 0.89 | AG25: =SUMPRODUCT($Z$17:$AD$17,Z25:AD25) -> 0.89 | AR25: Total | AV25: =SUM(AV20:AV24) -> 58 | AW25: =SUM(AW20:AW24) -> 119 | AX25: =SUM(AX20:AX24) -> 1 | AY25: =SUM(AY20:AY24) -> 1
B26: 9 | C26: NCR Log | L26: 1 | Q26: 38 | R26: Concrete Surface Finishing | AA26: 1 | AF26: =SUMPRODUCT($K$17:$O$17,K26:O26) -> 0.89 | AG26: =SUMPRODUCT($Z$17:$AD$17,Z26:AD26) -> 0.89
B27: 10 | C27: MODON Standard* | L27: 1 | Q27: 39 | R27: Pedestals/Columns/Beams Alignment | AD27: 1 | AF27: =SUMPRODUCT($K$17:$O$17,K27:O27) -> 0.89 | AG27: =SUMPRODUCT($Z$17:$AD$17,Z27:AD27) -> 1 | AV27: Maz Score Available: | AW27: =SUM(AV20:AV23)*AQ20 -> 172 | AX27: <- Excludes N/A items
B28: 11 | C28: Project Risk Plan/Management* | M28: 1 | Q28: 40 | R28: Siporex Lifting & Unloading | AD28: 1 | AF28: =SUMPRODUCT($K$17:$O$17,K28:O28) -> 0.79 | AG28: =SUMPRODUCT($Z$17:$AD$17,Z28:AD28) -> 1
B29: 12 | C29: Monthly Quality Reports* | L29: 1 | Q29: 41 | R29: Siporex Quality Pre-installation | AD29: 1 | AF29: =SUMPRODUCT($K$17:$O$17,K29:O29) -> 0.89 | AG29: =SUMPRODUCT($Z$17:$AD$17,Z29:AD29) -> 1
B30: 13 | C30: ITP | L30: 1 | Q30: 42 | R30: Siporex Finishing Quality | AD30: 1 | AF30: =SUMPRODUCT($K$17:$O$17,K30:O30) -> 0.89 | AG30: =SUMPRODUCT($Z$17:$AD$17,Z30:AD30) -> 1 | AR30: Total Score | AW30: Percentage (%)
B31: 14 | C31: MODON Weekly Report | L31: 1 | Q31: 43 | R31: Roads / Parking Markings | AB31: 1 | AF31: =SUMPRODUCT($K$17:$O$17,K31:O31) -> 0.89 | AG31: =SUMPRODUCT($Z$17:$AD$17,Z31:AD31) -> 0.79 | AN31: =MAX(AN20:AN24) -> 58 | AR31: =AW25 -> 119 | AW31: =SUM(100/AR33*AR31) -> 69.186047 | AY31: %
B32: 15 | C32: Design Change Official Paperwork* | O32: 1 | Q32: 44 | R32: QC of Finishing Outdoors | AB32: 1 | AF32: =SUMPRODUCT($K$17:$O$17,K32:O32) -> 1 | AG32: =SUMPRODUCT($Z$17:$AD$17,Z32:AD32) -> 0.79 | AR32: Max Score Available | BP32: 31
B33: 16 | C33: Design Change was Applied* | O33: 1 | Q33: 45 | R33: Quality of Finishing Indoors | AD33: 1 | AF33: =SUMPRODUCT($K$17:$O$17,K33:O33) -> 1 | AG33: =SUMPRODUCT($Z$17:$AD$17,Z33:AD33) -> 1 | AR33: =AW27 -> 172 | BP33: 32
B34: 17 | C34: Material List | L34: 1 | Q34: 46 | R34: Stairs Quality | AD34: 1 | AF34: =SUMPRODUCT($K$17:$O$17,K34:O34) -> 0.89 | AG34: =SUMPRODUCT($Z$17:$AD$17,Z34:AD34) -> 1 | BP34: 33
B35: 18 | C35: Pending Material Status | L35: 1 | Q35: 47 | R35: Tanks Method Statement Work | AD35: 1 | AF35: =SUMPRODUCT($K$17:$O$17,K35:O35) -> 0.89 | AG35: =SUMPRODUCT($Z$17:$AD$17,Z35:AD35) -> 1 | BP35: 34
B36: 19 | C36: Lifting Plan* | M36: 1 | Q36: 48 | R36: Electric Rooms | AD36: 1 | AF36: =SUMPRODUCT($K$17:$O$17,K36:O36) -> 0.79 | AG36: =SUMPRODUCT($Z$17:$AD$17,Z36:AD36) -> 1 | BP36: 35
B37: 20 | C37: DWG Log | L37: 1 | Q37: 49 | R37: QC of MCC/ATS Plant Units | AD37: 1 | AF37: =SUMPRODUCT($K$17:$O$17,K37:O37) -> 0.89 | AG37: =SUMPRODUCT($Z$17:$AD$17,Z37:AD37) -> 1 | BP37: 36
B38: 21 | C38: Invoice Status | M38: 1 | Q38: 50 | R38: Qualified Subcontractor | AA38: 1 | AF38: =SUMPRODUCT($K$17:$O$17,K38:O38) -> 0.79 | AG38: =SUMPRODUCT($Z$17:$AD$17,Z38:AD38) -> 0.89 | BP38: 37
B39: 22 | C39: Site Handover Letter | O39: 1 | Q39: 51 | R39: Scaffold/Ladders/Slope/Bridge Compliance | AB39: 1 | AF39: =SUMPRODUCT($K$17:$O$17,K39:O39) -> 1 | AG39: =SUMPRODUCT($Z$17:$AD$17,Z39:AD39) -> 0.79 | BP39: 38
B40: 23 | C40: Material Testing Results & Certification | L40: 1 | Q40: 52 | R40: Protection Applied to Completed Work | AC40: 1 | AF40: =SUMPRODUCT($K$17:$O$17,K40:O40) -> 0.89 | AG40: =SUMPRODUCT($Z$17:$AD$17,Z40:AD40) -> 0.69
B41: 24 | C41: As Build Drawings Status* | M41: 1 | Q41: 53 | R41: Storage Management in/out Control | AA41: 1 | AF41: =SUMPRODUCT($K$17:$O$17,K41:O41) -> 0.79 | AG41: =SUMPRODUCT($Z$17:$AD$17,Z41:AD41) -> 0.89
B42: 25 | C42: Calibrated Lab Tools & Equipment | L42: 1 | Q42: 54 | R42: Material Control | AA42: 1 | AF42: =SUMPRODUCT($K$17:$O$17,K42:O42) -> 0.89 | AG42: =SUMPRODUCT($Z$17:$AD$17,Z42:AD42) -> 0.89
B43: 26 | C43: Storage Inventory System | L43: 1 | Q43: 55 | R43: Manholes Storing and Quality | AD43: 1 | AF43: =SUMPRODUCT($K$17:$O$17,K43:O43) -> 0.89 | AG43: =SUMPRODUCT($Z$17:$AD$17,Z43:AD43) -> 1
B44: 27 | C44: Logistics Plan | M44: 1 | Q44: 56 | R44: Reinforced Steel Quality | AA44: 1 | AF44: =SUMPRODUCT($K$17:$O$17,K44:O44) -> 0.79 | AG44: =SUMPRODUCT($Z$17:$AD$17,Z44:AD44) -> 0.89
B45: 28 | C45: Project Progress Planview | L45: 1 | Q45: 57 | R45: Safety Overview | AA45: 1 | AF45: =SUMPRODUCT($K$17:$O$17,K45:O45) -> 0.89 | AG45: =SUMPRODUCT($Z$17:$AD$17,Z45:AD45) -> 0.89
B46: 29 | C46: Sufficient Number of QC Inspectors | L46: 1 | Q46: 58 | R46: Waste Management Control | AA46: 1 | AF46: =SUMPRODUCT($K$17:$O$17,K46:O46) -> 0.89 | AG46: =SUMPRODUCT($Z$17:$AD$17,Z46:AD46) -> 0.89
I48: Score
M49: *QC % | Q49: =AF17 -> 0.9012069
B51: Prepared by: | G51: Waleed Mahmoud | Q51: Issued to PM: | V51: Engr. Abdallah Aljulaifi
B53: *QC Observations refer only to the practices and documentation observed at time of inspection. The responsibility of the CM and Contractor is to ensure that aspects of Quality are suitably managed. *Scores are a reflection of the general site conditions based upon the findings at the time of the walk through *If Applicable

Sheet Quality-Stat
A1: Quality Reports
A2: Item | D2: Issued | E2: Closed | F2: Pending | G2: Avg. Closing (Days) | H2: Pending
H3: 0-10 Days | I3: 11-20 Days | J3: 21-30 Days | K3: 31-60 Days | L3: > 60 Days
A5: Non Conforomance Report (NCR) | D5: 2 | E5: 2 | F5: =+D5-E5 -> 0 | G5: 3 | H5: 0 | I5: 0 | J5: 0 | K5: 0 | L5: 0
A6: Site Instruction (SIR/SOR) | D6: 25 | E6: 24 | F6: =+D6-E6 -> 1 | G6: 3 | H6: 1 | I6: 0 | J6: 0 | K6: 0 | L6: 0
A7: Material Inspection Report (MRIR) | D7: 31 | E7: 31 | F7: =+D7-E7 -> 0 | G7: 5 | H7: 0 | I7: 0 | J7: 0 | K7: 0 | L7: 0
A8: Field Inspection Report (FIR) | D8: 910 | E8: 901 | F8: =+D8-E8 -> 9 | G8: 4 | H8: 2 | I8: 0 | J8: 0 | K8: 0 | L8: 0
A10: Shop Drawings
A11: Item Per WBS | D11: Total Planned | E11: Total Drawings Submitted | J11: Remaining Drawings | K11: Pending | L11: Total Submittals
E12: A | F12: B | G12: C | H12: D | I12: Processed | J12: with Designer | K12: Submittals With Consultant
A13: General | D13: 0 | E13: 0 | F13: 0 | G13: 0 | H13: 0 | I13: 0 | J13: =D13-I13 -> 0 | K13: 0 | L13: =E13+F13+G13+H13+K13+J13 -> 0 | M13: =+I13/D13 -> #DIV/0! | N13: =+L13/D13 -> #DIV/0! | R13: =+D13 -> 0 | S13: =+E13 -> 0 | T13: =+F13 -> 0 | U13: =+G13 -> 0 | V13: =+H13 -> 0 | W13: =+I13 -> 0 | X13: =+J1+3 -> 3 | Y13: =+K13 -> 0
A14: Road Works | D14: 25 | E14: 0 | F14: 17 | G14: 0 | H14: 0 | I14: 17 | J14: =D14-I14 -> 8 | K14: 8 | L14: =E14+F14+G14+H14+K14 -> 25 | M14: =+I14/D14 -> 0.68 | N14: =+L14/D14 -> 1 | R14: =+D14+D15 -> 25 | S14: =+E14+E15 -> 0 | T14: =+F14+F15 -> 17 | U14: =+G14+G15 -> 0 | V14: =+H14+H15 -> 0 | W14: =+I14+I15 -> 17 | X14: =+J14+J15 -> 8 | Y14: =+K14+K15 -> 8
A15: Civil | D15: 0 | E15: 0 | F15: 0 | G15: 0 | H15: 0 | I15: 0 | J15: =D15-I15 -> 0 | K15: 0 | L15: =E15+F15+G15+H15+K15+J15 -> 0 | R15: =+D16 -> 0 | S15: =+E16 -> 0 | T15: =+F16 -> 0 | U15: =+G16 -> 0 | V15: =+H16 -> 0 | W15: =+I16 -> 0 | X15: =+J16 -> 0 | Y15: =+K16 -> 0
A16: Mechanical | D16: 0 | E16: 0 | F16: 0 | G16: 0 | H16: 0 | I16: =E16+F16+G16+H16+K16 -> 0 | J16: =D16-I16 -> 0 | K16: 0 | L16: =E16+F16+G16+H16+K16+J16 -> 0 | M16: =+I16/D16 -> #DIV/0! | N16: =+L16/D16 -> #DIV/0! | R16: =+D17 -> 11 | S16: =+E17 -> 0 | T16: =+F17 -> 11 | U16: =+G17 -> 0 | V16: =+H17 -> 0 | W16: =+I17 -> 11 | X16: =+J17 -> 0 | Y16: =+K17 -> 0
A17: Electrical | D17: 11 | E17: 0 | F17: 11 | G17: 0 | H17: 0 | I17: =E17+F17+G17+H17+K17 -> 11 | J17: =D17-I17 -> 0 | K17: 0 | L17: =E17+F17+G17+H17+K17 -> 11 | M17: =+I17/D17 -> 1 | N17: =+L17/D17 -> 1 | R17: =+D35 -> 65 | S17: =+E35 -> 0 | T17: =+F35 -> 63 | U17: =+G35 -> 0 | V17: =+H35 -> 2 | W17: =+I35 -> 63 | X17: =+J35 -> 0 | Y17: =+K35 -> 0
A18: Telecom | D18: 0 | E18: 0 | F18: 0 | G18: 0 | I18: =E18+F18+G18+H18+K18 -> 0 | J18: =D18-I18 -> 0 | K18: 0 | L18: =E18+F18+G18+H18+K18+J18 -> 0 | M18: =+I18/D18 -> #DIV/0!
A19: Potable | D19: 0 | E19: 0 | F19: 0 | G19: 0 | H19: 0 | I19: =E19+F19+G19+H19+K19 -> 0 | J19: =D19-I19 -> 0 | K19: 0 | L19: =E19+F19+G19+H19+K19+J19 -> 0
A20: Sewer | D20: 0 | E20: 0 | F20: 0 | G20: 0 | H20: 0 | I20: =E20+F20+G20+H20+K20 -> 0 | J20: =D20-I20 -> 0 | L20: =E20+F20+G20+H20+K20+J20 -> 0
A21: Irrigation | D21: 0 | E21: 0 | F21: 0 | G21: 0 | H21: 0 | I21: 0 | J21: =D21-I21 -> 0 | K21: 0 | L21: =E21+F21+G21+H21+K21+J21 -> 0
A22: Strom | D22: 21 | E22: 1 | F22: 19 | G22: 0 | H22: 1 | I22: =+E22+F22+G22 -> 20 | J22: 0 | K22: 0 | L22: =E22+F22+G22+H22+K22+J22 -> 21 | M22: =+I22/D22 -> 0.95238095
A23: Enviromental | D23: 0 | E23: 0 | F23: 0 | G23: 0 | H23: 0 | I23: =E23+F23+G23+H23+K23 -> 0 | J23: =D23-I23 -> 0 | L23: =E23+F23+G23+H23+K23+J23 -> 0
A24: TOTAL | D24: =SUM(D13:D23) -> 57 | E24: =SUM(E13:E23) -> 1 | F24: =SUM(F13:F23) -> 47 | G24: =SUM(G13:G23) -> 0 | H24: =SUM(H13:H23) -> 1 | I24: =SUM(I13:I23) -> 48 | J24: =SUM(J13:J23) -> 8 | K24: =SUM(K13:K23) -> 8 | L24: =SUM(L13:L23) -> 57 | M24: =+I24/D24 -> 0.84210526 | N24: =+L24/D24 -> 1
I25: =+I24/D24 -> 0.84210526
A27: Material Approval
A28: Item Per WBS | D28: Total Planned | E28: Total Materials Submitted | J28: Remaining | K28: Pending | L28: Total Submittals
E29: A | F29: B | G29: C | H29: D | I29: Approved | J29: with Designer | K29: Submittals With Consultant
A30: General | D30: 0 | E30: 0 | F30: 0 | G30: 0 | H30: 0 | I30: 0 | J30: =+D30-L30 -> 0 | K30: 0 | L30: =+E30+F30+G30+H30+K30 -> 0
A31: Road Works | D31: 15 | E31: 0 | F31: 14 | G31: 0 | H31: 1 | I31: =+E31+F31 -> 14 | J31: =+D31-L31 -> 0 | K31: 0 | L31: =+E31+F31+G31+H31+K31 -> 15
A32: Civil | D32: 33 | E32: 0 | F32: 32 | G32: 0 | H32: 1 | I32: =+E32+F32 -> 32 | J32: =+D32-L32 -> 0 | K32: 0 | L32: =+E32+F32+G32+H32+K32 -> 33
A33: Mechanical | D33: 0 | E33: 0 | F33: 0 | G33: 0 | H33: 0 | I33: 0 | J33: =+D33-L33 -> 0 | K33: 0 | L33: =+E33+F33+G33+H33+K33 -> 0
A34: Electrical | D34: 17 | E34: 0 | F34: 17 | G34: 0 | H34: 0 | I34: 17 | J34: =+D34-L34 -> 0 | K34: 0 | L34: =+E34+F34+G34+H34+K34 -> 17
A35: TOTAL | D35: =SUM(D30:D34) -> 65 | E35: =SUM(E30:E34) -> 0 | F35: =SUM(F30:F34) -> 63 | G35: =SUM(G30:G34) -> 0 | H35: =SUM(H30:H34) -> 2 | I35: =SUM(I30:I34) -> 63 | J35: =SUM(J30:J34) -> 0 | K35: =SUM(K30:K34) -> 0 | L35: =SUM(L30:L34) -> 65 | N35: =+L35/D35 -> 1
A37: Procurement Summary
A38: Item Per WBS | D38: Total Materials Planned | E38: Total Number of P.O. | F38: Actual P.O. To Date | G38: Remaining P.O | H38: Actual Material on Site | I38: Remaining Materials | J38: Material Delivery Completion (Date)
E39: A | F39: B | G39: C | H39: D | I39: Processed
A40: General | D40: 0 | E40: 0 | G40: 0 | H40: 0 | I40: 0
A41: Road Works | D41: 9 | E41: 9 | F41: 9 | G41: =+E41-F41 -> 0 | H41: 8 | I41: =+D41-H41 -> 1 | J41: 46336
A42: Civil | D42: 2 | E42: 2 | F42: 2 | G42: 0 | H42: 2 | I42: =+D42-H42 -> 0 | J42: 46172
A43: Mechanical | D43: 0 | E43: 0 | F43: 0 | G43: 0 | H43: 0 | I43: =+D43-H43 -> 0
A44: Electrical | D44: 7 | E44: 7 | F44: 7 | G44: =+E44-F44 -> 0 | H44: 7 | I44: =+D44-H44 -> 0 | J44: 46263
A45: TOTAL | D45: =SUM(D40:D44) -> 18 | E45: =SUM(E40:E44) -> 18 | F45: =SUM(F40:F44) -> 18 | G45: =SUM(G40:G44) -> 0 | H45: =SUM(H40:H44) -> 17 | I45: =SUM(I40:I44) -> 1 | J45: =MAX(J40:J44) -> 46336
A47: Consultant Quality Inspections / Observations (Weekly Basis) | I47: Overall Average | J47: =AVERAGE(E49:E123) -> 0.84522903 | L47: Average Closing | M47: =AVERAGE(G49:G123) -> 1.75
A48: Week Number | B48: Date of Audit | C48: Date Issued | D48: Numbers Of Comments | E48: Quality Score | F48: Date Closed | G48: Closure Duration | I48: This Week Score | J48: =Quality!AC10 -> 0.9012069 | L48: Average Number of Comments Per Audit | M48: =AVERAGE(D49:D123) -> 2.8064516
A49: Week-1
A50: Week-2
A51: Week-3
A52: Week-4 | B52: 46091 | C52: 46090 | D52: 3 | E52: 0.8 | F52: 46091 | G52: =F52-C52 -> 1
A53: Week-5 | B53: 46098 | C53: 46097 | D53: 3 | E53: 0.8 | F53: 46099 | G53: =F53-C53 -> 2
A54: Week-6 | B54: 46105 | C54: 46104 | D54: 2 | E54: 0.75 | F54: 46105 | G54: =F54-C54 -> 1
A55: Week-7 | B55: 46112 | C55: 46111 | D55: 3 | E55: 0.78 | F55: 46112 | G55: =F55-C55 -> 1
A56: Week-8 | B56: 46119 | C56: 46118 | D56: 3 | E56: 0.78 | F56: 46120 | G56: =F56-C56 -> 2
A57: Week-9 | B57: 46126 | C57: 46124 | D57: 2 | E57: 0.75 | F57: 46127 | G57: =F57-C57 -> 3
A58: Week-10 | B58: 46133 | C58: 46131 | D58: 3 | E58: 0.79 | F58: 46133 | G58: =F58-C58 -> 2
A59: Week-11 | B59: 46140 | C59: 46138 | D59: 2 | E59: 0.8 | F59: 46138 | G59: =F59-C59 -> 0
A60: Week-12 | B60: 46147 | C60: 46145 | D60: 3 | E60: 0.78 | F60: 46146 | G60: =F60-C60 -> 1
A61: Week-13 | B61: 46154 | C61: 46152 | D61: 4 | E61: 0.79 | F61: 46154 | G61: =F61-C61 -> 2
A62: Week-14 | B62: 46161 | C62: 46159 | D62: 3 | E62: 0.79 | F62: 46161 | G62: =F62-C62 -> 2
A63: Week-15 | B63: 46168 | C63: 46166 | D63: 3 | E63: 0.8 | F63: 46168 | G63: =F63-C63 -> 2
A64: Week-16 | G64: =F64-C64 -> 0
A65: Week-17 | B65: 46182 | C65: 46179 | D65: 3 | E65: 0.8 | F65: 46180 | G65: =F65-C65 -> 1
A66: Week-18 | B66: 46189 | C66: 46186 | D66: 3 | E66: 0.85 | F66: 46188 | G66: =F66-C66 -> 2
A67: Week-19 | B67: 46196 | C67: 46193 | D67: 3 | E67: 0.85 | F67: 46196 | G67: =F67-C67 -> 3
A68: Week-20 | B68: 46203 | C68: 46200 | D68: 3 | E68: 0.87 | F68: 46201 | G68: =F68-C68 -> 1
A69: Week-21 | B69: 46210 | C69: 46207 | D69: 3 | E69: 0.875 | F69: 46207 | G69: =F69-C69 -> 0
A70: Week-22 | B70: 46217 | C70: 46216 | D70: 3 | E70: 0.875 | F70: 46217 | G70: =F70-C70 -> 1
A71: Week-23 | B71: 46224 | C71: 46221 | D71: 3 | E71: 0.89 | F71: 46223 | G71: =F71-C71 -> 2
A72: Week-24 | B72: 46231 | C72: 46229 | D72: 3 | E72: 0.892 | F72: 46232 | G72: =F72-C72 -> 3
A73: Week-25 | B73: 46238 | C73: 46236 | D73: 2 | E73: 0.893 | F73: 46239 | G73: =F73-C73 -> 3
A74: Week-26 | B74: 46245 | C74: 46243 | D74: 4 | E74: 0.897 | F74: 46244 | G74: =F74-C74 -> 1
A75: Week-27 | B75: 46252 | C75: 46247 | D75: 3 | E75: 0.899 | F75: 46250 | G75: =F75-C75 -> 3
A76: Week-28 | B76: 46259 | C76: 46255 | D76: 2 | E76: 0.8995 | F76: 46257 | G76: =F76-C76 -> 2
... A83: Week-35 | B83: 46308 | C83: 46303 | D83: 2 | E83: 0.9012 | F83: 46305 | G83: =F83-C83 -> 2
A84: Week-36
A85: Week-37
A86: Week-38
A87: Week-39
A88: Week-40
A89: Week-41
A90: Week-42
A91: Week-43
A92: Week-44
A93: Week-45
A94: Week-46
A95: Week-47
... A123: Week-75

Sheet HSE
B1: MODON HSE Site Inspection Report
B2: Date: | E2: ='General Information'!L1 -> 46308 | L2: Inspected By: | U2: =G27 -> Waleed Mahmoud
B4: Project ID. | E4: ='General Information'!C4 -> MKH2-02-003 | L4: Report No. | P4: ='General Information'!O1 -> 35 | W4: MODON PM Name | Y4: Engr. Abdallah Aljulaifi
B6: Project Name: | E6: ='General Information'!C3 -> Completion of Infrastructure Works in The Second Industrial City in Makkah Al-Mukarramah | L6: Contractor: | R6: ='General Information'!C5 -> Al Enjaz Trading & Contracting Co. | X6: Safety Performance | AA6: =IF(W29>0,3,IF(L29>6,2,IF(D29>9,1,1)*1)*1) -> 2 | AE6: =(((COUNTIF(L13:Q25,"1")+COUNTIF(AC13:AH25,"1"))*AR13)+(COUNTIF(L13:Q25,"2")+COUNTIF(AC13:AH25,"2"))*AR14+(COUNTIF(L13:Q25,"3")+COUNTIF(AC13:AH25,"3"))*AR15)/((COUNT(L13:Q25)+COUNT(AC13:AH25))*100) -> 0.86363636
B8: Inspections are a snapshot in time and refer only to the practices and documentation observed at the time of the Inspection. It remains the responsibility of the Consultant and Contractor to ensure that all aspects of Health & Safety are suitably managed.
B9: 1 | D9: Good Practice | H9: 2 | I9: Need Improvement | T9: 3 | U9: Fail (Life Threatening Activity) / Comliance with Plan & Procedures | X9: N/A | Y9: Atcitty Not Applicable for this Site Inspection Report
B11: No. | C11: Topic | K11: Wt. | L11: HSE Compliance | S11: No. | T11: Topic | AB11: Wt. | AC11: HSE Compliance
B13: 1 | C13: Access and Egress - (General access to site, segregated from vehicles, / Overhead protection, while entering into the building /Adequate lighting provided when dark or overnight work) | K13: 0.05 | L13: 2 | S13: 14 | T13: Work at Height - (PPE/Fall Protection(Same level, above and blow) / Training / Fall restraint / competency /Safe access & egress to and from work at height / Ladders / Openings (floor/shafts/Provision of emergency rescue) | AB13: 0.05 | AC13: N/A | AP13: 1 | AR13: 100 | AU13: 1
B14: 2 | C14: Traffic Management - (Loading/unloading/sheeting/temp. routes/speed/parking/competence) | K14: 0.03 | L14: 2 | S14: 15 | T14: Scaffolding - (Temp. Scaffolding Work-platform (All types) - qualified scaffolder / Inspection / Tagged / Safe Access/egress / PTW/Falsework & Formwork) | AB14: 0.04 | AC14: N/A | AP14: 2 | AR14: 75 | AU14: 2
B15: 3 | C15: Site Signage - (Project Notice Board & General Signage) | K15: 0.02 | L15: 1 | S15: 16 | T15: Mobile Elevated Work platform (MEWP) - (PTW/competence requirements/conditions/inspections/tagged/training/Full-body harness) | AB15: 0.04 | AC15: N/A | AP15: 3 | AR15: 0 | AU15: 3
B16: 4 | C16: PPE Compliance - (Use, storage, stock, handling & checks - Head, Foot, Eye, Hearing) | K16: 0.05 | L16: 1 | S16: 17 | T16: Excavation & Trenches - (PTW/Edge protection/buffer zone/Slope/Benching/Shoring/Geo-tech report/Atmospheric hazards/Acess&egress/Emergency management / MS&RA/H.E) | AB16: 0.03 | AC16: 2 | AU16: N/A
B17: 5 | C17: Housekeeping - (Material correctly stored/Rubbish cleaned & removed daily/slips & trips hazards) | K17: 0.03 | L17: 1 | S17: 18 | T17: Confined Space - (PTW/Training/competence/Emergency Management/MS & RA/Safe access/egress) | AB17: 0.05 | AC17: N/A
B18: 6 | C18: Storage of Materials - (Transporting, storage, training and use - Combustible / Flammable / Hazardous substances (COSHH) | L18: 2 | S18: 19 | T18: Fire Protection - (Flammable/Oxy. LPG /Combustible separated/FE's/Flashback arrestor/Sparks & slags/Smoking area/PTW/Generators/MS & RA/Emergency Management) | AC18: 1 | AL18: Red | AM18: Serious injury or death (immediately)
B19: 7 | C19: Site Waste Management - (Hazardous waste /Combustible waste / Human waste / Construction waste - asphalt, cable, timber, paving roof sheeting tiles, plastic & bricks) | L19: 2 | S19: 20 | T19: Health & Welfare - (Adequate drinking water/shaded - eating & rest area/washing & sanitary facilities/Certified FA/FA Box & Stock/adequate toilets/Ambulance) | AC19: 2 | AL19: Yellow | AM19: Minor or near miss (3 days to comply)
B20: 8 | C20: Health Surveillance - (Expose to excessive noise/vibration/dust/silica/CO/cement/radiation/extreme weather condition) | K20: 0.03 | L20: 1 | S20: 21 | T20: Environmental Incident Measures - (Spill/ Leakage / Concrete wash / vehicle & eqpts. wash / waste disposal/Sewers and drains/emissions/Emergency Management/Training/site run-off water) | AB20: 0.05 | AC20: 2 | AL20: Green | AM20: No issues
B21: 9 | C21: Electrical Safety - (Electrical qualified /RCD/GFCI/Industrial Cocket/LOTO/Cable-overhung or buried/Cords in good condition/current inspection tag) | K21: 0.05 | L21: 1 | S21: 22 | T21: HSE Communications & Meetings - (Schedule HSE Meetings/Safety Committee meetings/Alerts / Lesson learned/Safety Bulletin contains latest HSE KPI) | AB21: 0.05 | AC21: 1
B22: 10 | C22: Tools & Equipment - (Includes, powered, hydraulic & pneumatic/Guards in place/Properly stored/RCD Protection/Earthed/Good condition & tagged) | K22: 0.03 | L22: 2 | S22: 23 | T22: HSE Plan & Associated Procedures - (Approved updated HSE Plan/ CEMP/HAZComm/Procedures/Standards/Project Safety Risk Register) | AB22: 0.03 | AC22: 2 | AL22: 26 points > 4 minors then is it’s a serious issue
B23: 11 | C23: Manual Handling - (Lifting/loading/pulling/pushing/twisting/awkward posture/repetitive task/frequent and prolong physical effort/Reasonable practicable use of mechanical aid) | K23: 0.03 | L23: 2 | S23: 24 | T23: Health, Safety & Environment Incident reporting - (Review of HSE Statistics, Reporting of Unsafe Act & Conditions/ Reporting of Near Miss incident/Reporting of FA cases/Record MT cases) | AB23: 0.03 | AC23: 2
B24: 12 | C24: Vehicle and mobile equipment / Plant - (dumpers; excavators, cranes, piling rigs, grader, roller, loaders/condition/KSA License/certification) | K24: 0.05 | L24: 2 | S24: 25 | T24: HSE Awareness, Training & Competence - (Policy /Objective & targets/Information, training/Climatic condition awareness/Reponses in emergency situation/ Safety Behavior Observation) | AB24: 0.04 | AC24: 1
B25: 13 | C25: Lifting Operations & Rigging - (Lifting Plan/Lifting devices & gears/PTW/Condition/3rd party certification/bank-man/rigger/slingers/man-basket/inspection record/tagged) | L25: 1 | S25: 26 | T25: Project Leadership Site Tours - (Provide evidence of proactive safety performance/Deficient discovered discussed/Positive feedback/Workers resolving safety issues) | AC25: 1
B27: Prepared by: | G27: Waleed Mahmoud | S27: Sent to MODON PM: | X27: Engr. Abdallah Aljulaifi
B28: Safety Results
B29: 1 | D29: =COUNTIF(L13:Q26,"1")+COUNTIF(AB13:AG26,"1") -> 10 | I29: 2 | L29: =COUNTIF(L13:Q26,"2")+COUNTIF(AB13:AG26,"2") -> 12 | U29: 3 | W29: =COUNTIF(L13:Q26,"3")+COUNTIF(AB13:AG26,"3") -> 0

Sheet HSE-Stat
A1: Safety Statistics | K1: 18400
A3: Category | B3: Item | D3: This Week | E3: This Month | F3: Year to Date | G3: Cumulative
A4: Category | B4: Total Hours Worked | D4: 7560 | E4: 15120 | F4: 192100 | G4: 192100
B5: Safe Hours Worked | D5: 7560 | E5: 15120 | F5: 192100 | G5: 192100
A6: Reactive | B6: LTI | D6: 0 | E6: 0 | F6: 0 | G6: 0
B7: MTC (Healed w/o Disability) | D7: 0 | E7: 0 | F7: 0 | G7: 0
B8: MTC (Healed w/ Disability) | D8: 0 | E8: 0 | F8: 0 | G8: 0
B9: Near Miss | D9: 0 | E9: 1 | F9: 1 | G9: 1
B10: First Aid Cases | D10: 0 | E10: 0 | F10: 0 | G10: 0
B11: Fatality | D11: 0 | E11: 0 | F11: 0 | G11: 0
B12: Fire Incident Cases | D12: 0 | E12: 0 | F12: 0 | G12: 0
B13: Vehicle Incident | D13: 0 | E13: 0 | F13: 0 | G13: 0
B14: Property Damages | D14: 0 | E14: 0 | F14: 0 | G14: 0
A15: Proactive | B15: Induction Training | D15: 0 | E15: 0 | F15: 12 | G15: 12
B16: No.of Internal Training | D16: 2 | E16: 3 | F16: 38 | G16: 38
B17: No.of Internal Audit | D17: 0 | E17: 2 | F17: 2 | G17: 2
B18: No. of Toolbox Talks | D18: 1 | E18: 2 | F18: 50 | G18: 50
B19: Safety Awards/Incentives | D19: 0 | E19: 0 | F19: 0 | G19: 0
I20: Category | J20: Item | L20: This Week | M20: This Month | N20: Year to Date | O20: Cumulative
A22: Consultant Safety Inspection (Weekly Basis) | I22: Overall Average | J22: =AVERAGE(E24:E95) -> 0.85137419
A23: Week Number | B23: Date of Audit | C23: Date Issued | D23: Numbers Of Comments | E23: Overall Score | F23: Date Closed | G23: Closure Duration | I23: This Week Score | J23: =HSE!AE6 -> 0.86363636
A24: Week-1
A25: Week-2
A26: Week-3
A27: Week-4 | B27: 46091 | C27: 46090 | D27: 3 | E27: 0.85 | F27: 46090 | G27: =F27-C27 -> 0
A28: Week-5 | B28: 46098 | C28: 46097 | D28: 3 | E28: 0.85 | F28: 46097 | G28: =F28-C28 -> 0
A29: Week-6 | B29: 46105 | C29: 46104 | D29: 2 | E29: 0.85 | F29: 46104 | G29: =F29-C29 -> 0
A30: Week-7 | B30: 46112 | C30: 46111 | D30: 3 | E30: 0.85 | F30: 46111 | G30: =F30-C30 -> 0
A31: Week-8 | B31: 46119 | C31: 46118 | D31: 3 | E31: 0.85 | F31: 46118 | G31: =F31-C31 -> 0
A32: Week-9 | B32: 46126 | C32: 46124 | D32: 2 | E32: 0.85 | F32: 46124 | G32: =F32-C32 -> 0
A33: Week-10 | B33: 46133 | C33: 46131 | D33: 3 | E33: 0.85 | F33: 46131 | G33: =F33-C33 -> 0
A34: Week-11 | B34: 46140 | C34: 46138 | D34: 2 | E34: 0.85 | F34: 46138 | G34: =F34-C34 -> 0
A35: Week-12 | B35: 46147 | C35: 46145 | D35: 3 | E35: 0.85 | F35: 46145 | G35: =F35-C35 -> 0
A36: Week-13 | B36: 46154 | C36: 46152 | D36: 4 | E36: 0.85 | F36: 46152 | G36: =F36-C36 -> 0
A37: Week-14 | B37: 46161 | C37: 46159 | D37: 3 | E37: 0.85 | F37: 46159 | G37: =F37-C37 -> 0
A38: Week-15 | B38: 46168 | C38: 46166 | D38: 3 | E38: 0.85 | F38: 46166 | G38: =F38-C38 -> 0
A39: Week-16 | G39: =F39-C39 -> 0
A40: Week-17 | B40: 46182 | C40: 46179 | D40: 3 | E40: 0.85 | F40: 46179 | G40: =F40-C40 -> 0
A41: Week-18 | B41: 46189 | C41: 46186 | D41: 3 | E41: 0.85 | F41: 46186 | G41: =F41-C41 -> 0
A42: Week-19 | B42: 46196 | C42: 46193 | D42: 3 | E42: 0.85 | F42: 46193 | G42: =F42-C42 -> 0
A43: Week-20 | B43: 46203 | C43: 46200 | D43: 3 | E43: 0.85 | F43: 46200 | G43: =F43-C43 -> 0
A44: Week-21 | B44: 46210 | C44: 46207 | D44: 3 | E44: 0.85 | F44: 46207 | G44: =F44-C44 -> 0
A45: Week-22 | B45: 46217 | C45: 46216 | D45: 3 | E45: 0.85 | F45: 46216 | G45: =F45-C45 -> 0
A46: Week-23 | B46: 46224 | C46: 46221 | D46: 3 | E46: 0.85 | F46: 46221 | G46: =F46-C46 -> 0
A47: Week-24 | B47: 46231 | C47: 46229 | D47: 3 | E47: 0.85 | F47: 46229 | G47: =F47-C47 -> 0
A48: Week-25 | B48: 46238 | C48: 46236 | D48: 2 | E48: 0.85 | F48: 46236 | G48: =F48-C48 -> 0
A49: Week-26 | B49: 46245 | C49: 46243 | D49: 1 | E49: 0.85 | F49: 46243 | G49: =F49-C49 -> 0
A50: Week-27 | B50: 46252 | C50: 46247 | D50: 2 | E50: 0.8409 | F50: 46249 | G50: =F50-C50 -> 2
A51: Week-28 | B51: 46259 | C51: 46253 | D51: 6 | E51: 0.8295 | F51: 46257 | G51: =F51-C51 -> 4
... A58: Week-35 | B58: 46308 | C58: 46303 | D58: 4 | E58: 0.8636 | F58: 46308 | G58: =F58-C58 -> 5
A59: Week-36
A60: Week-37
A61: Week-38
A62: Week-39
A63: Week-40
A64: Week-41
A65: Week-42
A66: Week-43
A67: Week-44
A68: Week-45
A69: Week-46
A70: Week-47
... A95: Week-72

Sheet Risk Register
B2: Department: | K2: Status Date:
B3: Program | K3: ='General Information'!L1 -> 46308
B4: Project: | E4: ='General Information'!C3 -> Completion of Infrastructure Works in The Second Industrial City in Makkah Al-Mukarramah
B5: Project No.: | E5: ='General Information'!C4 -> MKH2-02-003
B6: Project Location: | E6: MAKKAH 2nd INDUSTRIAL CITY
R8: Before Treatment | AC8: Post Treatment
B9: Risk Data | H9: Category | K9: Risk Description | N9: Risk Control Dates | P9: Risk Manageability | Q9: Risk Proximity | R9: Most Likely | U9: Risk Owner | V9: Risk Response & Treatment Action | Z9: Treatment Control Dates | AC9: Most Likely | AF9: Treatment Status
B10: Risk ID | C10: Region | D10: Section / Group | E10: City | F10: Project ID | G10: Risk Status | H10: T/O/I | I10: Internal/External | J10: Category | K10: Cause / Source | L10: Risk | M10: Consequence / Effect | N10: Identified | O10: Closed | R10: Liklihood | S10: Impact | T10: Risk Score | V10: Risk Response Strategy | W10: Treatment Action | X10: Treatment Acton Description | Y10: Treatment Action Owner | Z10: Start | AA10: Due | AB10: Closed | AC10: Liklihood | AD10: Impact | AE10: Risk Score
B11: MKH2-02-003-00 | C11: Western | D11: Western | E11: Makkah | F11: MKH2-02-003 | G11: Close | H11: Threat | I11: Internal | J11: Design / Planning | K11: Delay in Designing of Channels | L11: Design revision for Open Channel 3A issued by MODON | M11: Delay in Construction Works | N11: 46119 | O11: Closed | P11: Hard | Q11: Imminent | R11: High | S11: Very High | T11: =IF(AND(R11="Very Low",S11="Low"),"L1",IF(AND(R11="Low",S11="Low"),"L4",IF(OR(AND(R11="Very Low",S11="Low"),AND(R11="Low",S11="Very Low")),"L2",IF(OR(AND(R11="Medium",S11="Very Low"),AND(R11="Very Low",S11="Medium")),"L3",IF(OR(AND(R11="High",S11="Very Low"),AND(R11="Very Low",S11="High")),"L4",IF(OR(AND(R11="Very High",S11="Very Low"),AND(R11="Very Low",S11="Very High")),"M5",IF(OR(AND(R11="Low",S11="Medium"),AND(R11="Medium",S11="Low")),"M6",IF(OR(AND(R11="High",S11="Low"),AND(R11="Low",S11="High")),"M8",IF(AND(R11="Medium",S11="Medium"),"M9",IF(OR(AND(R11="Very High",S11="Low"),AND(R11="Low",S11="Very High")),"M10",IF(OR(AND(R11="High",S11="Medium"),AND(R11="Medium",S11="High")),"M12",IF(OR(AND(R11="Very High",S11="Medium"),AND(R11="Medium",S11="Very High")),"H15",IF(AND(R11="High",S11="High"),"H16",IF(OR(AND(R11="Very High",S11="High"),AND(R11="High",S11="Very High")),"H20",IF(AND(R11="Very High",S11="Very High"),"H25",""))))))))))))))) -> H20 | U11: Contractor/MODON | V11: Treat | W11: Mitigation | Y11: Contractor/MODON | Z11: 46119 | AB11: 46131 | AC11: High | AD11: High | AE11: =IF(AND(AC11="Very Low",AD11="Low"),"L1",IF(AND(AC11="Low",AD11="Low"),"L4",IF(OR(AND(AC11="Very Low",AD11="Low"),AND(AC11="Low",AD11="Very Low")),"L2",IF(OR(AND(AC11="Medium",AD11="Very Low"),AND(AC11="Very Low",AD11="Medium")),"L3",IF(OR(AND(AC11="High",AD11="Very Low"),AND(AC11="Very Low",AD11="High")),"L4",IF(OR(AND(AC11="Very High",AD11="Very Low"),AND(AC11="Very Low",AD11="Very High")),"M5",IF(OR(AND(AC11="Low",AD11="Medium"),AND(AC11="Medium",AD11="Low")),"M6",IF(OR(AND(AC11="High",AD11="Low"),AND(AC11="Low",AD11="High")),"M8",IF(AND(AC11="Medium",AD11="Medium"),"M9",IF(OR(AND(AC11="Very High",AD11="Low"),AND(AC11="Low",AD11="Very High")),"M10",IF(OR(AND(AC11="High",AD11="Medium"),AND(AC11="Medium",AD11="High")),"M12",IF(OR(AND(AC11="Very High",AD11="Medium"),AND(AC11="Medium",AD11="Very High")),"H15",IF(AND(AC11="High",AD11="High"),"H16",IF(OR(AND(AC11="Very High",AD11="High"),AND(AC11="High",AD11="Very High")),"H20",IF(AND(AC11="Very High",AD11="Very High"),"H25",""))))))))))))))) -> H16 | AF11: Close
B12: MKH2-02-003-01 | C12: Western | D12: Western | E12: Makkah | F12: MKH2-02-003 | G12: Close | H12: Threat | I12: Internal | J12: Safety / Quality | K12: Delay in Designing of Culvert No. 3 | L12: Construction of additional culvert, Number 3, at the Northern Entrance of the Al-Badad | M12: Delay in Construction Works | N12: 46119 | P12: Hard | Q12: Imminent | R12: High | S12: High | T12: =IF(AND(R12="Very Low",S12="Low"),"L1",IF(AND(R12="Low",S12="Low"),"L4",IF(OR(AND(R12="Very Low",S12="Low"),AND(R12="Low",S12="Very Low")),"L2",IF(OR(AND(R12="Medium",S12="Very Low"),AND(R12="Very Low",S12="Medium")),"L3",IF(OR(AND(R12="High",S12="Very Low"),AND(R12="Very Low",S12="High")),"L4",IF(OR(AND(R12="Very High",S12="Very Low"),AND(R12="Very Low",S12="Very High")),"M5",IF(OR(AND(R12="Low",S12="Medium"),AND(R12="Medium",S12="Low")),"M6",IF(OR(AND(R12="High",S12="Low"),AND(R12="Low",S12="High")),"M8",IF(AND(R12="Medium",S12="Medium"),"M9",IF(OR(AND(R12="Very High",S12="Low"),AND(R12="Low",S12="Very High")),"M10",IF(OR(AND(R12="High",S12="Medium"),AND(R12="Medium",S12="High")),"M12",IF(OR(AND(R12="Very High",S12="Medium"),AND(R12="Medium",S12="Very High")),"H15",IF(AND(R12="High",S12="High"),"H16",IF(OR(AND(R12="Very High",S12="High"),AND(R12="High",S12="Very High")),"H20",IF(AND(R12="Very High",S12="Very High"),"H25",""))))))))))))))) -> H16 | U12: Contractor/MODON | V12: Treat | W12: Mitigation | Y12: Contractor/MODON | Z12: 46119 | AC12: High | AD12: High | AE12: =IF(AND(AC12="Very Low",AD12="Low"),"L1",IF(AND(AC12="Low",AD12="Low"),"L4",IF(OR(AND(AC12="Very Low",AD12="Low"),AND(AC12="Low",AD12="Very Low")),"L2",IF(OR(AND(AC12="Medium",AD12="Very Low"),AND(AC12="Very Low",AD12="Medium")),"L3",IF(OR(AND(AC12="High",AD12="Very Low"),AND(AC12="Very Low",AD12="High")),"L4",IF(OR(AND(AC12="Very High",AD12="Very Low"),AND(AC12="Very Low",AD12="Very High")),"M5",IF(OR(AND(AC12="Low",AD12="Medium"),AND(AC12="Medium",AD12="Low")),"M6",IF(OR(AND(AC12="High",AD12="Low"),AND(AC12="Low",AD12="High")),"M8",IF(AND(AC12="Medium",AD12="Medium"),"M9",IF(OR(AND(AC12="Very High",AD12="Low"),AND(AC12="Low",AD12="Very High")),"M10",IF(OR(AND(AC12="High",AD12="Medium"),AND(AC12="Medium",AD12="High")),"M12",IF(OR(AND(AC12="Very High",AD12="Medium"),AND(AC12="Medium",AD12="Very High")),"H15",IF(AND(AC12="High",AD12="High"),"H16",IF(OR(AND(AC12="Very High",AD12="High"),AND(AC12="High",AD12="Very High")),"H20",IF(AND(AC12="Very High",AD12="Very High"),"H25",""))))))))))))))) -> H16 | AF12: Close
B13: MKH2-02-003-02 | C13: Western | D13: Western | E13: Makkah | F13: MKH2-02-003 | G13: Close | H13: Threat | I13: External | J13: Authorities / Permits | K13: Delay in Receiving perrmit for work in Makkah I Hajj Period | L13: Delay in Receiving perrmit for work in Makkah I Hajj Period | M13: Delay in Construction Works | N13: 46126 | O13: Closed | P13: Hard | Q13: Imminent | R13: High | S13: High | T13: =IF(AND(R13="Very Low",S13="Low"),"L1",IF(AND(R13="Low",S13="Low"),"L4",IF(OR(AND(R13="Very Low",S13="Low"),AND(R13="Low",S13="Very Low")),"L2",IF(OR(AND(R13="Medium",S13="Very Low"),AND(R13="Very Low",S13="Medium")),"L3",IF(OR(AND(R13="High",S13="Very Low"),AND(R13="Very Low",S13="High")),"L4",IF(OR(AND(R13="Very High",S13="Very Low"),AND(R13="Very Low",S13="Very High")),"M5",IF(OR(AND(R13="Low",S13="Medium"),AND(R13="Medium",S13="Low")),"M6",IF(OR(AND(R13="High",S13="Low"),AND(R13="Low",S13="High")),"M8",IF(AND(R13="Medium",S13="Medium"),"M9",IF(OR(AND(R13="Very High",S13="Low"),AND(R13="Low",S13="Very High")),"M10",IF(OR(AND(R13="High",S13="Medium"),AND(R13="Medium",S13="High")),"M12",IF(OR(AND(R13="Very High",S13="Medium"),AND(R13="Medium",S13="Very High")),"H15",IF(AND(R13="High",S13="High"),"H16",IF(OR(AND(R13="Very High",S13="High"),AND(R13="High",S13="Very High")),"H20",IF(AND(R13="Very High",S13="Very High"),"H25",""))))))))))))))) -> H16 | U13: Contractor | V13: Treat | W13: Mitigate | Y13: Contractor | Z13: 46126 | AB13: 46131 | AC13: High | AD13: High | AE13: =IF(AND(AC13="Very Low",AD13="Low"),"L1",IF(AND(AC13="Low",AD13="Low"),"L4",IF(OR(AND(AC13="Very Low",AD13="Low"),AND(AC13="Low",AD13="Very Low")),"L2",IF(OR(AND(AC13="Medium",AD13="Very Low"),AND(AC13="Very Low",AD13="Medium")),"L3",IF(OR(AND(AC13="High",AD13="Very Low"),AND(AC13="Very Low",AD13="High")),"L4",IF(OR(AND(AC13="Very High",AD13="Very Low"),AND(AC13="Very Low",AD13="Very High")),"M5",IF(OR(AND(AC13="Low",AD13="Medium"),AND(AC13="Medium",AD13="Low")),"M6",IF(OR(AND(AC13="High",AD13="Low"),AND(AC13="Low",AD13="High")),"M8",IF(AND(AC13="Medium",AD13="Medium"),"M9",IF(OR(AND(AC13="Very High",AD13="Low"),AND(AC13="Low",AD13="Very High")),"M10",IF(OR(AND(AC13="High",AD13="Medium"),AND(AC13="Medium",AD13="High")),"M12",IF(OR(AND(AC13="Very High",AD13="Medium"),AND(AC13="Medium",AD13="Very High")),"H15",IF(AND(AC13="High",AD13="High"),"H16",IF(OR(AND(AC13="Very High",AD13="High"),AND(AC13="High",AD13="Very High")),"H20",IF(AND(AC13="Very High",AD13="Very High"),"H25",""))))))))))))))) -> H16 | AF13: Close
B14: MKH2-02-003-03 | C14: Western | D14: Western | E14: Makkah | F14: MKH2-02-003 | G14: Close | H14: Threat | I14: Internal | J14: Authorities / Permits | K14: No permission for Non-Muslim workers to work in Hajj Period | L14: No permission for Non-Muslim workers to work in Hajj Period | M14: Delay in Construction Works | N14: 46126 | P14: Moderate | Q14: Imminent | R14: Medium | S14: Medium | T14: =IF(AND(R14="Very Low",S14="Low"),"L1",IF(AND(R14="Low",S14="Low"),"L4",IF(OR(AND(R14="Very Low",S14="Low"),AND(R14="Low",S14="Very Low")),"L2",IF(OR(AND(R14="Medium",S14="Very Low"),AND(R14="Very Low",S14="Medium")),"L3",IF(OR(AND(R14="High",S14="Very Low"),AND(R14="Very Low",S14="High")),"L4",IF(OR(AND(R14="Very High",S14="Very Low"),AND(R14="Very Low",S14="Very High")),"M5",IF(OR(AND(R14="Low",S14="Medium"),AND(R14="Medium",S14="Low")),"M6",IF(OR(AND(R14="High",S14="Low"),AND(R14="Low",S14="High")),"M8",IF(AND(R14="Medium",S14="Medium"),"M9",IF(OR(AND(R14="Very High",S14="Low"),AND(R14="Low",S14="Very High")),"M10",IF(OR(AND(R14="High",S14="Medium"),AND(R14="Medium",S14="High")),"M12",IF(OR(AND(R14="Very High",S14="Medium"),AND(R14="Medium",S14="Very High")),"H15",IF(AND(R14="High",S14="High"),"H16",IF(OR(AND(R14="Very High",S14="High"),AND(R14="High",S14="Very High")),"H20",IF(AND(R14="Very High",S14="Very High"),"H25",""))))))))))))))) -> M9 | U14: Contractor | V14: Treat | W14: Mitigate | Y14: Contractor | Z14: 46126 | AC14: Medium | AD14: Medium | AE14: =IF(AND(AC14="Very Low",AD14="Low"),"L1",IF(AND(AC14="Low",AD14="Low"),"L4",IF(OR(AND(AC14="Very Low",AD14="Low"),AND(AC14="Low",AD14="Very Low")),"L2",IF(OR(AND(AC14="Medium",AD14="Very Low"),AND(AC14="Very Low",AD14="Medium")),"L3",IF(OR(AND(AC14="High",AD14="Very Low"),AND(AC14="Very Low",AD14="High")),"L4",IF(OR(AND(AC14="Very High",AD14="Very Low"),AND(AC14="Very Low",AD14="Very High")),"M5",IF(OR(AND(AC14="Low",AD14="Medium"),AND(AC14="Medium",AD14="Low")),"M6",IF(OR(AND(AC14="High",AD14="Low"),AND(AC14="Low",AD14="High")),"M8",IF(AND(AC14="Medium",AD14="Medium"),"M9",IF(OR(AND(AC14="Very High",AD14="Low"),AND(AC14="Low",AD14="Very High")),"M10",IF(OR(AND(AC14="High",AD14="Medium"),AND(AC14="Medium",AD14="High")),"M12",IF(OR(AND(AC14="Very High",AD14="Medium"),AND(AC14="Medium",AD14="Very High")),"H15",IF(AND(AC14="High",AD14="High"),"H16",IF(OR(AND(AC14="Very High",AD14="High"),AND(AC14="High",AD14="Very High")),"H20",IF(AND(AC14="Very High",AD14="Very High"),"H25",""))))))))))))))) -> M9 | AF14: Close
B15: MKH2-02-003-04 | C15: Western | D15: Western | E15: Makkah | F15: MKH2-02-003 | G15: Open | H15: Threat | I15: Internal | J15: Design / Planning | K15: Delay in Designing of Culvert No. 4 | L15: Construction of additional culvert, Number 4, at the RAMP2-IN | M15: Delay in Construction Works | N15: 46193 | P15: Moderate | Q15: Imminent | R15: Very High | S15: Very High | T15: =IF(AND(R15="Very Low",S15="Low"),"L1",IF(AND(R15="Low",S15="Low"),"L4",IF(OR(AND(R15="Very Low",S15="Low"),AND(R15="Low",S15="Very Low")),"L2",IF(OR(AND(R15="Medium",S15="Very Low"),AND(R15="Very Low",S15="Medium")),"L3",IF(OR(AND(R15="High",S15="Very Low"),AND(R15="Very Low",S15="High")),"L4",IF(OR(AND(R15="Very High",S15="Very Low"),AND(R15="Very Low",S15="Very High")),"M5",IF(OR(AND(R15="Low",S15="Medium"),AND(R15="Medium",S15="Low")),"M6",IF(OR(AND(R15="High",S15="Low"),AND(R15="Low",S15="High")),"M8",IF(AND(R15="Medium",S15="Medium"),"M9",IF(OR(AND(R15="Very High",S15="Low"),AND(R15="Low",S15="Very High")),"M10",IF(OR(AND(R15="High",S15="Medium"),AND(R15="Medium",S15="High")),"M12",IF(OR(AND(R15="Very High",S15="Medium"),AND(R15="Medium",S15="Very High")),"H15",IF(AND(R15="High",S15="High"),"H16",IF(OR(AND(R15="Very High",S15="High"),AND(R15="High",S15="Very High")),"H20",IF(AND(R15="Very High",S15="Very High"),"H25",""))))))))))))))) -> H25 | U15: Contractor/MODON | V15: Treat | W15: Mitigate | Y15: Contractor/MODON | AC15: Very High | AD15: Very High | AE15: =IF(AND(AC15="Very Low",AD15="Low"),"L1",IF(AND(AC15="Low",AD15="Low"),"L4",IF(OR(AND(AC15="Very Low",AD15="Low"),AND(AC15="Low",AD15="Very Low")),"L2",IF(OR(AND(AC15="Medium",AD15="Very Low"),AND(AC15="Very Low",AD15="Medium")),"L3",IF(OR(AND(AC15="High",AD15="Very Low"),AND(AC15="Very Low",AD15="High")),"L4",IF(OR(AND(AC15="Very High",AD15="Very Low"),AND(AC15="Very Low",AD15="Very High")),"M5",IF(OR(AND(AC15="Low",AD15="Medium"),AND(AC15="Medium",AD15="Low")),"M6",IF(OR(AND(AC15="High",AD15="Low"),AND(AC15="Low",AD15="High")),"M8",IF(AND(AC15="Medium",AD15="Medium"),"M9",IF(OR(AND(AC15="Very High",AD15="Low"),AND(AC15="Low",AD15="Very High")),"M10",IF(OR(AND(AC15="High",AD15="Medium"),AND(AC15="Medium",AD15="High")),"M12",IF(OR(AND(AC15="Very High",AD15="Medium"),AND(AC15="Medium",AD15="Very High")),"H15",IF(AND(AC15="High",AD15="High"),"H16",IF(OR(AND(AC15="Very High",AD15="High"),AND(AC15="High",AD15="Very High")),"H20",IF(AND(AC15="Very High",AD15="Very High"),"H25",""))))))))))))))) -> H25 | AF15: Close
B16: MKH2-02-003-05 | C16: Eastern | D16: Western | E16: Makkah | F16: MKH2-02-003 | G16: Open | H16: Threat | I16: Internal | J16: Scope / Requirments / Contractual | K16: Scope Change | L16: Addition works in Collector 9 | M16: Delay in Construction Works | N16: 46196 | P16: Moderate | Q16: Imminent | R16: High | S16: Low | T16: =IF(AND(R16="Very Low",S16="Low"),"L1",IF(AND(R16="Low",S16="Low"),"L4",IF(OR(AND(R16="Very Low",S16="Low"),AND(R16="Low",S16="Very Low")),"L2",IF(OR(AND(R16="Medium",S16="Very Low"),AND(R16="Very Low",S16="Medium")),"L3",IF(OR(AND(R16="High",S16="Very Low"),AND(R16="Very Low",S16="High")),"L4",IF(OR(AND(R16="Very High",S16="Very Low"),AND(R16="Very Low",S16="Very High")),"M5",IF(OR(AND(R16="Low",S16="Medium"),AND(R16="Medium",S16="Low")),"M6",IF(OR(AND(R16="High",S16="Low"),AND(R16="Low",S16="High")),"M8",IF(AND(R16="Medium",S16="Medium"),"M9",IF(OR(AND(R16="Very High",S16="Low"),AND(R16="Low",S16="Very High")),"M10",IF(OR(AND(R16="High",S16="Medium"),AND(R16="Medium",S16="High")),"M12",IF(OR(AND(R16="Very High",S16="Medium"),AND(R16="Medium",S16="Very High")),"H15",IF(AND(R16="High",S16="High"),"H16",IF(OR(AND(R16="Very High",S16="High"),AND(R16="High",S16="Very High")),"H20",IF(AND(R16="Very High",S16="Very High"),"H25",""))))))))))))))) -> M8 | U16: Contractor | V16: Treat | W16: Mitigate | Y16: Contractor/MODON | AC16: Medium | AD16: Medium | AE16: =IF(AND(AC16="Very Low",AD16="Low"),"L1",IF(AND(AC16="Low",AD16="Low"),"L4",IF(OR(AND(AC16="Very Low",AD16="Low"),AND(AC16="Low",AD16="Very Low")),"L2",IF(OR(AND(AC16="Medium",AD16="Very Low"),AND(AC16="Very Low",AD16="Medium")),"L3",IF(OR(AND(AC16="High",AD16="Very Low"),AND(AC16="Very Low",AD16="High")),"L4",IF(OR(AND(AC16="Very High",AD16="Very Low"),AND(AC16="Very Low",AD16="Very High")),"M5",IF(OR(AND(AC16="Low",AD16="Medium"),AND(AC16="Medium",AD16="Low")),"M6",IF(OR(AND(AC16="High",AD16="Low"),AND(AC16="Low",AD16="High")),"M8",IF(AND(AC16="Medium",AD16="Medium"),"M9",IF(OR(AND(AC16="Very High",AD16="Low"),AND(AC16="Low",AD16="Very High")),"M10",IF(OR(AND(AC16="High",AD16="Medium"),AND(AC16="Medium",AD16="High")),"M12",IF(OR(AND(AC16="Very High",AD16="Medium"),AND(AC16="Medium",AD16="Very High")),"H15",IF(AND(AC16="High",AD16="High"),"H16",IF(OR(AND(AC16="Very High",AD16="High"),AND(AC16="High",AD16="Very High")),"H20",IF(AND(AC16="Very High",AD16="Very High"),"H25",""))))))))))))))) -> M9 | AF16: Open
B17: MKH2-02-003-06 | C17: Western | D17: Western | E17: Makkah | F17: MKH2-02-003 | G17: Open | H17: Threat | I17: Internal | J17: Scope / Requirments / Contractual | K17: Scope Change | L17: Construction of Road 52 | M17: Delay in Construction Works | N17: 46196 | P17: Moderate | Q17: Imminent | R17: High | S17: Very High | T17: =IF(AND(R17="Very Low",S17="Low"),"L1",IF(AND(R17="Low",S17="Low"),"L4",IF(OR(AND(R17="Very Low",S17="Low"),AND(R17="Low",S17="Very Low")),"L2",IF(OR(AND(R17="Medium",S17="Very Low"),AND(R17="Very Low",S17="Medium")),"L3",IF(OR(AND(R17="High",S17="Very Low"),AND(R17="Very Low",S17="High")),"L4",IF(OR(AND(R17="Very High",S17="Very Low"),AND(R17="Very Low",S17="Very High")),"M5",IF(OR(AND(R17="Low",S17="Medium"),AND(R17="Medium",S17="Low")),"M6",IF(OR(AND(R17="High",S17="Low"),AND(R17="Low",S17="High")),"M8",IF(AND(R17="Medium",S17="Medium"),"M9",IF(OR(AND(R17="Very High",S17="Low"),AND(R17="Low",S17="Very High")),"M10",IF(OR(AND(R17="High",S17="Medium"),AND(R17="Medium",S17="High")),"M12",IF(OR(AND(R17="Very High",S17="Medium"),AND(R17="Medium",S17="Very High")),"H15",IF(AND(R17="High",S17="High"),"H16",IF(OR(AND(R17="Very High",S17="High"),AND(R17="High",S17="Very High")),"H20",IF(AND(R17="Very High",S17="Very High"),"H25",""))))))))))))))) -> H20 | U17: Contractor/MODON | V17: Terminate | W17: Mitigate | Y17: Contractor/MODON | AC17: Very High | AD17: Very High | AE17: =IF(AND(AC17="Very Low",AD17="Low"),"L1",IF(AND(AC17="Low",AD17="Low"),"L4",IF(OR(AND(AC17="Very Low",AD17="Low"),AND(AC17="Low",AD17="Very Low")),"L2",IF(OR(AND(AC17="Medium",AD17="Very Low"),AND(AC17="Very Low",AD17="Medium")),"L3",IF(OR(AND(AC17="High",AD17="Very Low"),AND(AC17="Very Low",AD17="High")),"L4",IF(OR(AND(AC17="Very High",AD17="Very Low"),AND(AC17="Very Low",AD17="Very High")),"M5",IF(OR(AND(AC17="Low",AD17="Medium"),AND(AC17="Medium",AD17="Low")),"M6",IF(OR(AND(AC17="High",AD17="Low"),AND(AC17="Low",AD17="High")),"M8",IF(AND(AC17="Medium",AD17="Medium"),"M9",IF(OR(AND(AC17="Very High",AD17="Low"),AND(AC17="Low",AD17="Very High")),"M10",IF(OR(AND(AC17="High",AD17="Medium"),AND(AC17="Medium",AD17="High")),"M12",IF(OR(AND(AC17="Very High",AD17="Medium"),AND(AC17="Medium",AD17="Very High")),"H15",IF(AND(AC17="High",AD17="High"),"H16",IF(OR(AND(AC17="Very High",AD17="High"),AND(AC17="High",AD17="Very High")),"H20",IF(AND(AC17="Very High",AD17="Very High"),"H25",""))))))))))))))) -> H25 | AF17: Open
B18: MKH2-02-003-07 | C18: Western | D18: Western | E18: Makkah | F18: MKH2-02-003 | G18: Open | H18: Threat | I18: Internal | J18: Scope / Requirments / Contractual | K18: Scope Change | L18: Construction of Al Gloud Road | M18: Delay in Construction Works | N18: 46196 | P18: Moderate | Q18: Imminent | R18: High | S18: High | T18: =IF(AND(R18="Very Low",S18="Low"),"L1",IF(AND(R18="Low",S18="Low"),"L4",IF(OR(AND(R18="Very Low",S18="Low"),AND(R18="Low",S18="Very Low")),"L2",IF(OR(AND(R18="Medium",S18="Very Low"),AND(R18="Very Low",S18="Medium")),"L3",IF(OR(AND(R18="High",S18="Very Low"),AND(R18="Very Low",S18="High")),"L4",IF(OR(AND(R18="Very High",S18="Very Low"),AND(R18="Very Low",S18="Very High")),"M5",IF(OR(AND(R18="Low",S18="Medium"),AND(R18="Medium",S18="Low")),"M6",IF(OR(AND(R18="High",S18="Low"),AND(R18="Low",S18="High")),"M8",IF(AND(R18="Medium",S18="Medium"),"M9",IF(OR(AND(R18="Very High",S18="Low"),AND(R18="Low",S18="Very High")),"M10",IF(OR(AND(R18="High",S18="Medium"),AND(R18="Medium",S18="High")),"M12",IF(OR(AND(R18="Very High",S18="Medium"),AND(R18="Medium",S18="Very High")),"H15",IF(AND(R18="High",S18="High"),"H16",IF(OR(AND(R18="Very High",S18="High"),AND(R18="High",S18="Very High")),"H20",IF(AND(R18="Very High",S18="Very High"),"H25",""))))))))))))))) -> H16 | U18: Contractor/MODON | V18: Treat | W18: Mitigate | Y18: Contractor/MODON | AC18: Medium | AD18: Medium | AE18: =IF(AND(AC18="Very Low",AD18="Low"),"L1",IF(AND(AC18="Low",AD18="Low"),"L4",IF(OR(AND(AC18="Very Low",AD18="Low"),AND(AC18="Low",AD18="Very Low")),"L2",IF(OR(AND(AC18="Medium",AD18="Very Low"),AND(AC18="Very Low",AD18="Medium")),"L3",IF(OR(AND(AC18="High",AD18="Very Low"),AND(AC18="Very Low",AD18="High")),"L4",IF(OR(AND(AC18="Very High",AD18="Very Low"),AND(AC18="Very Low",AD18="Very High")),"M5",IF(OR(AND(AC18="Low",AD18="Medium"),AND(AC18="Medium",AD18="Low")),"M6",IF(OR(AND(AC18="High",AD18="Low"),AND(AC18="Low",AD18="High")),"M8",IF(AND(AC18="Medium",AD18="Medium"),"M9",IF(OR(AND(AC18="Very High",AD18="Low"),AND(AC18="Low",AD18="Very High")),"M10",IF(OR(AND(AC18="High",AD18="Medium"),AND(AC18="Medium",AD18="High")),"M12",IF(OR(AND(AC18="Very High",AD18="Medium"),AND(AC18="Medium",AD18="Very High")),"H15",IF(AND(AC18="High",AD18="High"),"H16",IF(OR(AND(AC18="Very High",AD18="High"),AND(AC18="High",AD18="Very High")),"H20",IF(AND(AC18="Very High",AD18="Very High"),"H25",""))))))))))))))) -> M9 | AF18: Close
H19: Threat | I19: Internal | J19: Safety / Quality | N19: 45986 | P19: Ease | Q19: Med Term | R19: High | S19: High | T19: =IF(AND(R19="Very Low",S19="Low"),"L1",IF(AND(R19="Low",S19="Low"),"L4",IF(OR(AND(R19="Very Low",S19="Low"),AND(R19="Low",S19="Very Low")),"L2",IF(OR(AND(R19="Medium",S19="Very Low"),AND(R19="Very Low",S19="Medium")),"L3",IF(OR(AND(R19="High",S19="Very Low"),AND(R19="Very Low",S19="High")),"L4",IF(OR(AND(R19="Very High",S19="Very Low"),AND(R19="Very Low",S19="Very High")),"M5",IF(OR(AND(R19="Low",S19="Medium"),AND(R19="Medium",S19="Low")),"M6",IF(OR(AND(R19="High",S19="Low"),AND(R19="Low",S19="High")),"M8",IF(AND(R19="Medium",S19="Medium"),"M9",IF(OR(AND(R19="Very High",S19="Low"),AND(R19="Low",S19="Very High")),"M10",IF(OR(AND(R19="High",S19="Medium"),AND(R19="Medium",S19="High")),"M12",IF(OR(AND(R19="Very High",S19="Medium"),AND(R19="Medium",S19="Very High")),"H15",IF(AND(R19="High",S19="High"),"H16",IF(OR(AND(R19="Very High",S19="High"),AND(R19="High",S19="Very High")),"H20",IF(AND(R19="Very High",S19="Very High"),"H25",""))))))))))))))) -> H16 | U19: Contractor | V19: Treat | W19: Mitigate | AC19: Medium | AD19: Medium | AE19: =IF(AND(AC19="Very Low",AD19="Low"),"L1",IF(AND(AC19="Low",AD19="Low"),"L4",IF(OR(AND(AC19="Very Low",AD19="Low"),AND(AC19="Low",AD19="Very Low")),"L2",IF(OR(AND(AC19="Medium",AD19="Very Low"),AND(AC19="Very Low",AD19="Medium")),"L3",IF(OR(AND(AC19="High",AD19="Very Low"),AND(AC19="Very Low",AD19="High")),"L4",IF(OR(AND(AC19="Very High",AD19="Very Low"),AND(AC19="Very Low",AD19="Very High")),"M5",IF(OR(AND(AC19="Low",AD19="Medium"),AND(AC19="Medium",AD19="Low")),"M6",IF(OR(AND(AC19="High",AD19="Low"),AND(AC19="Low",AD19="High")),"M8",IF(AND(AC19="Medium",AD19="Medium"),"M9",IF(OR(AND(AC19="Very High",AD19="Low"),AND(AC19="Low",AD19="Very High")),"M10",IF(OR(AND(AC19="High",AD19="Medium"),AND(AC19="Medium",AD19="High")),"M12",IF(OR(AND(AC19="Very High",AD19="Medium"),AND(AC19="Medium",AD19="Very High")),"H15",IF(AND(AC19="High",AD19="High"),"H16",IF(OR(AND(AC19="Very High",AD19="High"),AND(AC19="High",AD19="Very High")),"H20",IF(AND(AC19="Very High",AD19="Very High"),"H25",""))))))))))))))) -> M9 | AF19: Open
H20: Threat | I20: Internal | J20: Safety / Quality | N20: 45986 | P20: Ease | Q20: Med Term | R20: Medium | S20: High | T20: =IF(AND(R20="Very Low",S20="Low"),"L1",IF(AND(R20="Low",S20="Low"),"L4",IF(OR(AND(R20="Very Low",S20="Low"),AND(R20="Low",S20="Very Low")),"L2",IF(OR(AND(R20="Medium",S20="Very Low"),AND(R20="Very Low",S20="Medium")),"L3",IF(OR(AND(R20="High",S20="Very Low"),AND(R20="Very Low",S20="High")),"L4",IF(OR(AND(R20="Very High",S20="Very Low"),AND(R20="Very Low",S20="Very High")),"M5",IF(OR(AND(R20="Low",S20="Medium"),AND(R20="Medium",S20="Low")),"M6",IF(OR(AND(R20="High",S20="Low"),AND(R20="Low",S20="High")),"M8",IF(AND(R20="Medium",S20="Medium"),"M9",IF(OR(AND(R20="Very High",S20="Low"),AND(R20="Low",S20="Very High")),"M10",IF(OR(AND(R20="High",S20="Medium"),AND(R20="Medium",S20="High")),"M12",IF(OR(AND(R20="Very High",S20="Medium"),AND(R20="Medium",S20="Very High")),"H15",IF(AND(R20="High",S20="High"),"H16",IF(OR(AND(R20="Very High",S20="High"),AND(R20="High",S20="Very High")),"H20",IF(AND(R20="Very High",S20="Very High"),"H25",""))))))))))))))) -> M12 | U20: Contractor | V20: Treat | W20: Mitigate | AC20: Medium | AD20: Medium | AE20: =IF(AND(AC20="Very Low",AD20="Low"),"L1",IF(AND(AC20="Low",AD20="Low"),"L4",IF(OR(AND(AC20="Very Low",AD20="Low"),AND(AC20="Low",AD20="Very Low")),"L2",IF(OR(AND(AC20="Medium",AD20="Very Low"),AND(AC20="Very Low",AD20="Medium")),"L3",IF(OR(AND(AC20="High",AD20="Very Low"),AND(AC20="Very Low",AD20="High")),"L4",IF(OR(AND(AC20="Very High",AD20="Very Low"),AND(AC20="Very Low",AD20="Very High")),"M5",IF(OR(AND(AC20="Low",AD20="Medium"),AND(AC20="Medium",AD20="Low")),"M6",IF(OR(AND(AC20="High",AD20="Low"),AND(AC20="Low",AD20="High")),"M8",IF(AND(AC20="Medium",AD20="Medium"),"M9",IF(OR(AND(AC20="Very High",AD20="Low"),AND(AC20="Low",AD20="Very High")),"M10",IF(OR(AND(AC20="High",AD20="Medium"),AND(AC20="Medium",AD20="High")),"M12",IF(OR(AND(AC20="Very High",AD20="Medium"),AND(AC20="Medium",AD20="Very High")),"H15",IF(AND(AC20="High",AD20="High"),"H16",IF(OR(AND(AC20="Very High",AD20="High"),AND(AC20="High",AD20="Very High")),"H20",IF(AND(AC20="Very High",AD20="Very High"),"H25",""))))))))))))))) -> M9 | AF20: Open
H21: Threat | I21: External | J21: Design / Planning | N21: 45986 | P21: Ease | Q21: Med Term | R21: High | S21: High | T21: =IF(AND(R21="Very Low",S21="Low"),"L1",IF(AND(R21="Low",S21="Low"),"L4",IF(OR(AND(R21="Very Low",S21="Low"),AND(R21="Low",S21="Very Low")),"L2",IF(OR(AND(R21="Medium",S21="Very Low"),AND(R21="Very Low",S21="Medium")),"L3",IF(OR(AND(R21="High",S21="Very Low"),AND(R21="Very Low",S21="High")),"L4",IF(OR(AND(R21="Very High",S21="Very Low"),AND(R21="Very Low",S21="Very High")),"M5",IF(OR(AND(R21="Low",S21="Medium"),AND(R21="Medium",S21="Low")),"M6",IF(OR(AND(R21="High",S21="Low"),AND(R21="Low",S21="High")),"M8",IF(AND(R21="Medium",S21="Medium"),"M9",IF(OR(AND(R21="Very High",S21="Low"),AND(R21="Low",S21="Very High")),"M10",IF(OR(AND(R21="High",S21="Medium"),AND(R21="Medium",S21="High")),"M12",IF(OR(AND(R21="Very High",S21="Medium"),AND(R21="Medium",S21="Very High")),"H15",IF(AND(R21="High",S21="High"),"H16",IF(OR(AND(R21="Very High",S21="High"),AND(R21="High",S21="Very High")),"H20",IF(AND(R21="Very High",S21="Very High"),"H25",""))))))))))))))) -> H16 | U21: Saudi Electricity Company (SEC) | V21: Transfer | W21: Mitigate | AC21: Very High | AD21: Very High | AE21: =IF(AND(AC21="Very Low",AD21="Low"),"L1",IF(AND(AC21="Low",AD21="Low"),"L4",IF(OR(AND(AC21="Very Low",AD21="Low"),AND(AC21="Low",AD21="Very Low")),"L2",IF(OR(AND(AC21="Medium",AD21="Very Low"),AND(AC21="Very Low",AD21="Medium")),"L3",IF(OR(AND(AC21="High",AD21="Very Low"),AND(AC21="Very Low",AD21="High")),"L4",IF(OR(AND(AC21="Very High",AD21="Very Low"),AND(AC21="Very Low",AD21="Very High")),"M5",IF(OR(AND(AC21="Low",AD21="Medium"),AND(AC21="Medium",AD21="Low")),"M6",IF(OR(AND(AC21="High",AD21="Low"),AND(AC21="Low",AD21="High")),"M8",IF(AND(AC21="Medium",AD21="Medium"),"M9",IF(OR(AND(AC21="Very High",AD21="Low"),AND(AC21="Low",AD21="Very High")),"M10",IF(OR(AND(AC21="High",AD21="Medium"),AND(AC21="Medium",AD21="High")),"M12",IF(OR(AND(AC21="Very High",AD21="Medium"),AND(AC21="Medium",AD21="Very High")),"H15",IF(AND(AC21="High",AD21="High"),"H16",IF(OR(AND(AC21="Very High",AD21="High"),AND(AC21="High",AD21="Very High")),"H20",IF(AND(AC21="Very High",AD21="Very High"),"H25",""))))))))))))))) -> H25 | AF21: Open
H22: Threat | I22: Internal | J22: Design / Planning | N22: 45986 | P22: Moderate | Q22: Med Term | R22: Very High | S22: Very High | T22: =IF(AND(R22="Very Low",S22="Low"),"L1",IF(AND(R22="Low",S22="Low"),"L4",IF(OR(AND(R22="Very Low",S22="Low"),AND(R22="Low",S22="Very Low")),"L2",IF(OR(AND(R22="Medium",S22="Very Low"),AND(R22="Very Low",S22="Medium")),"L3",IF(OR(AND(R22="High",S22="Very Low"),AND(R22="Very Low",S22="High")),"L4",IF(OR(AND(R22="Very High",S22="Very Low"),AND(R22="Very Low",S22="Very High")),"M5",IF(OR(AND(R22="Low",S22="Medium"),AND(R22="Medium",S22="Low")),"M6",IF(OR(AND(R22="High",S22="Low"),AND(R22="Low",S22="High")),"M8",IF(AND(R22="Medium",S22="Medium"),"M9",IF(OR(AND(R22="Very High",S22="Low"),AND(R22="Low",S22="Very High")),"M10",IF(OR(AND(R22="High",S22="Medium"),AND(R22="Medium",S22="High")),"M12",IF(OR(AND(R22="Very High",S22="Medium"),AND(R22="Medium",S22="Very High")),"H15",IF(AND(R22="High",S22="High"),"H16",IF(OR(AND(R22="Very High",S22="High"),AND(R22="High",S22="Very High")),"H20",IF(AND(R22="Very High",S22="Very High"),"H25",""))))))))))))))) -> H25 | U22: Contractor / Modon | V22: Terminate | W22: Mitigate | AC22: Very High | AD22: Very High | AE22: =IF(AND(AC22="Very Low",AD22="Low"),"L1",IF(AND(AC22="Low",AD22="Low"),"L4",IF(OR(AND(AC22="Very Low",AD22="Low"),AND(AC22="Low",AD22="Very Low")),"L2",IF(OR(AND(AC22="Medium",AD22="Very Low"),AND(AC22="Very Low",AD22="Medium")),"L3",IF(OR(AND(AC22="High",AD22="Very Low"),AND(AC22="Very Low",AD22="High")),"L4",IF(OR(AND(AC22="Very High",AD22="Very Low"),AND(AC22="Very Low",AD22="Very High")),"M5",IF(OR(AND(AC22="Low",AD22="Medium"),AND(AC22="Medium",AD22="Low")),"M6",IF(OR(AND(AC22="High",AD22="Low"),AND(AC22="Low",AD22="High")),"M8",IF(AND(AC22="Medium",AD22="Medium"),"M9",IF(OR(AND(AC22="Very High",AD22="Low"),AND(AC22="Low",AD22="Very High")),"M10",IF(OR(AND(AC22="High",AD22="Medium"),AND(AC22="Medium",AD22="High")),"M12",IF(OR(AND(AC22="Very High",AD22="Medium"),AND(AC22="Medium",AD22="Very High")),"H15",IF(AND(AC22="High",AD22="High"),"H16",IF(OR(AND(AC22="Very High",AD22="High"),AND(AC22="High",AD22="Very High")),"H20",IF(AND(AC22="Very High",AD22="Very High"),"H25",""))))))))))))))) -> H25 | AF22: Open
T23: =IF(AND(R23="Very Low",S23="Low"),"L1",IF(AND(R23="Low",S23="Low"),"L4",IF(OR(AND(R23="Very Low",S23="Low"),AND(R23="Low",S23="Very Low")),"L2",IF(OR(AND(R23="Medium",S23="Very Low"),AND(R23="Very Low",S23="Medium")),"L3",IF(OR(AND(R23="High",S23="Very Low"),AND(R23="Very Low",S23="High")),"L4",IF(OR(AND(R23="Very High",S23="Very Low"),AND(R23="Very Low",S23="Very High")),"M5",IF(OR(AND(R23="Low",S23="Medium"),AND(R23="Medium",S23="Low")),"M6",IF(OR(AND(R23="High",S23="Low"),AND(R23="Low",S23="High")),"M8",IF(AND(R23="Medium",S23="Medium"),"M9",IF(OR(AND(R23="Very High",S23="Low"),AND(R23="Low",S23="Very High")),"M10",IF(OR(AND(R23="High",S23="Medium"),AND(R23="Medium",S23="High")),"M12",IF(OR(AND(R23="Very High",S23="Medium"),AND(R23="Medium",S23="Very High")),"H15",IF(AND(R23="High",S23="High"),"H16",IF(OR(AND(R23="Very High",S23="High"),AND(R23="High",S23="Very High")),"H20",IF(AND(R23="Very High",S23="Very High"),"H25",""))))))))))))))) | AE23: =IF(AND(AC23="Very Low",AD23="Low"),"L1",IF(AND(AC23="Low",AD23="Low"),"L4",IF(OR(AND(AC23="Very Low",AD23="Low"),AND(AC23="Low",AD23="Very Low")),"L2",IF(OR(AND(AC23="Medium",AD23="Very Low"),AND(AC23="Very Low",AD23="Medium")),"L3",IF(OR(AND(AC23="High",AD23="Very Low"),AND(AC23="Very Low",AD23="High")),"L4",IF(OR(AND(AC23="Very High",AD23="Very Low"),AND(AC23="Very Low",AD23="Very High")),"M5",IF(OR(AND(AC23="Low",AD23="Medium"),AND(AC23="Medium",AD23="Low")),"M6",IF(OR(AND(AC23="High",AD23="Low"),AND(AC23="Low",AD23="High")),"M8",IF(AND(AC23="Medium",AD23="Medium"),"M9",IF(OR(AND(AC23="Very High",AD23="Low"),AND(AC23="Low",AD23="Very High")),"M10",IF(OR(AND(AC23="High",AD23="Medium"),AND(AC23="Medium",AD23="High")),"M12",IF(OR(AND(AC23="Very High",AD23="Medium"),AND(AC23="Medium",AD23="Very High")),"H15",IF(AND(AC23="High",AD23="High"),"H16",IF(OR(AND(AC23="Very High",AD23="High"),AND(AC23="High",AD23="Very High")),"H20",IF(AND(AC23="Very High",AD23="Very High"),"H25","")))))))))))))))
T24: =IF(AND(R24="Very Low",S24="Low"),"L1",IF(AND(R24="Low",S24="Low"),"L4",IF(OR(AND(R24="Very Low",S24="Low"),AND(R24="Low",S24="Very Low")),"L2",IF(OR(AND(R24="Medium",S24="Very Low"),AND(R24="Very Low",S24="Medium")),"L3",IF(OR(AND(R24="High",S24="Very Low"),AND(R24="Very Low",S24="High")),"L4",IF(OR(AND(R24="Very High",S24="Very Low"),AND(R24="Very Low",S24="Very High")),"M5",IF(OR(AND(R24="Low",S24="Medium"),AND(R24="Medium",S24="Low")),"M6",IF(OR(AND(R24="High",S24="Low"),AND(R24="Low",S24="High")),"M8",IF(AND(R24="Medium",S24="Medium"),"M9",IF(OR(AND(R24="Very High",S24="Low"),AND(R24="Low",S24="Very High")),"M10",IF(OR(AND(R24="High",S24="Medium"),AND(R24="Medium",S24="High")),"M12",IF(OR(AND(R24="Very High",S24="Medium"),AND(R24="Medium",S24="Very High")),"H15",IF(AND(R24="High",S24="High"),"H16",IF(OR(AND(R24="Very High",S24="High"),AND(R24="High",S24="Very High")),"H20",IF(AND(R24="Very High",S24="Very High"),"H25",""))))))))))))))) | AE24: =IF(AND(AC24="Very Low",AD24="Low"),"L1",IF(AND(AC24="Low",AD24="Low"),"L4",IF(OR(AND(AC24="Very Low",AD24="Low"),AND(AC24="Low",AD24="Very Low")),"L2",IF(OR(AND(AC24="Medium",AD24="Very Low"),AND(AC24="Very Low",AD24="Medium")),"L3",IF(OR(AND(AC24="High",AD24="Very Low"),AND(AC24="Very Low",AD24="High")),"L4",IF(OR(AND(AC24="Very High",AD24="Very Low"),AND(AC24="Very Low",AD24="Very High")),"M5",IF(OR(AND(AC24="Low",AD24="Medium"),AND(AC24="Medium",AD24="Low")),"M6",IF(OR(AND(AC24="High",AD24="Low"),AND(AC24="Low",AD24="High")),"M8",IF(AND(AC24="Medium",AD24="Medium"),"M9",IF(OR(AND(AC24="Very High",AD24="Low"),AND(AC24="Low",AD24="Very High")),"M10",IF(OR(AND(AC24="High",AD24="Medium"),AND(AC24="Medium",AD24="High")),"M12",IF(OR(AND(AC24="Very High",AD24="Medium"),AND(AC24="Medium",AD24="Very High")),"H15",IF(AND(AC24="High",AD24="High"),"H16",IF(OR(AND(AC24="Very High",AD24="High"),AND(AC24="High",AD24="Very High")),"H20",IF(AND(AC24="Very High",AD24="Very High"),"H25","")))))))))))))))
T25: =IF(AND(R25="Very Low",S25="Low"),"L1",IF(AND(R25="Low",S25="Low"),"L4",IF(OR(AND(R25="Very Low",S25="Low"),AND(R25="Low",S25="Very Low")),"L2",IF(OR(AND(R25="Medium",S25="Very Low"),AND(R25="Very Low",S25="Medium")),"L3",IF(OR(AND(R25="High",S25="Very Low"),AND(R25="Very Low",S25="High")),"L4",IF(OR(AND(R25="Very High",S25="Very Low"),AND(R25="Very Low",S25="Very High")),"M5",IF(OR(AND(R25="Low",S25="Medium"),AND(R25="Medium",S25="Low")),"M6",IF(OR(AND(R25="High",S25="Low"),AND(R25="Low",S25="High")),"M8",IF(AND(R25="Medium",S25="Medium"),"M9",IF(OR(AND(R25="Very High",S25="Low"),AND(R25="Low",S25="Very High")),"M10",IF(OR(AND(R25="High",S25="Medium"),AND(R25="Medium",S25="High")),"M12",IF(OR(AND(R25="Very High",S25="Medium"),AND(R25="Medium",S25="Very High")),"H15",IF(AND(R25="High",S25="High"),"H16",IF(OR(AND(R25="Very High",S25="High"),AND(R25="High",S25="Very High")),"H20",IF(AND(R25="Very High",S25="Very High"),"H25",""))))))))))))))) | AE25: =IF(AND(AC25="Very Low",AD25="Low"),"L1",IF(AND(AC25="Low",AD25="Low"),"L4",IF(OR(AND(AC25="Very Low",AD25="Low"),AND(AC25="Low",AD25="Very Low")),"L2",IF(OR(AND(AC25="Medium",AD25="Very Low"),AND(AC25="Very Low",AD25="Medium")),"L3",IF(OR(AND(AC25="High",AD25="Very Low"),AND(AC25="Very Low",AD25="High")),"L4",IF(OR(AND(AC25="Very High",AD25="Very Low"),AND(AC25="Very Low",AD25="Very High")),"M5",IF(OR(AND(AC25="Low",AD25="Medium"),AND(AC25="Medium",AD25="Low")),"M6",IF(OR(AND(AC25="High",AD25="Low"),AND(AC25="Low",AD25="High")),"M8",IF(AND(AC25="Medium",AD25="Medium"),"M9",IF(OR(AND(AC25="Very High",AD25="Low"),AND(AC25="Low",AD25="Very High")),"M10",IF(OR(AND(AC25="High",AD25="Medium"),AND(AC25="Medium",AD25="High")),"M12",IF(OR(AND(AC25="Very High",AD25="Medium"),AND(AC25="Medium",AD25="Very High")),"H15",IF(AND(AC25="High",AD25="High"),"H16",IF(OR(AND(AC25="Very High",AD25="High"),AND(AC25="High",AD25="Very High")),"H20",IF(AND(AC25="Very High",AD25="Very High"),"H25","")))))))))))))))
T26: =IF(AND(R26="Very Low",S26="Low"),"L1",IF(AND(R26="Low",S26="Low"),"L4",IF(OR(AND(R26="Very Low",S26="Low"),AND(R26="Low",S26="Very Low")),"L2",IF(OR(AND(R26="Medium",S26="Very Low"),AND(R26="Very Low",S26="Medium")),"L3",IF(OR(AND(R26="High",S26="Very Low"),AND(R26="Very Low",S26="High")),"L4",IF(OR(AND(R26="Very High",S26="Very Low"),AND(R26="Very Low",S26="Very High")),"M5",IF(OR(AND(R26="Low",S26="Medium"),AND(R26="Medium",S26="Low")),"M6",IF(OR(AND(R26="High",S26="Low"),AND(R26="Low",S26="High")),"M8",IF(AND(R26="Medium",S26="Medium"),"M9",IF(OR(AND(R26="Very High",S26="Low"),AND(R26="Low",S26="Very High")),"M10",IF(OR(AND(R26="High",S26="Medium"),AND(R26="Medium",S26="High")),"M12",IF(OR(AND(R26="Very High",S26="Medium"),AND(R26="Medium",S26="Very High")),"H15",IF(AND(R26="High",S26="High"),"H16",IF(OR(AND(R26="Very High",S26="High"),AND(R26="High",S26="Very High")),"H20",IF(AND(R26="Very High",S26="Very High"),"H25",""))))))))))))))) | AE26: =IF(AND(AC26="Very Low",AD26="Low"),"L1",IF(AND(AC26="Low",AD26="Low"),"L4",IF(OR(AND(AC26="Very Low",AD26="Low"),AND(AC26="Low",AD26="Very Low")),"L2",IF(OR(AND(AC26="Medium",AD26="Very Low"),AND(AC26="Very Low",AD26="Medium")),"L3",IF(OR(AND(AC26="High",AD26="Very Low"),AND(AC26="Very Low",AD26="High")),"L4",IF(OR(AND(AC26="Very High",AD26="Very Low"),AND(AC26="Very Low",AD26="Very High")),"M5",IF(OR(AND(AC26="Low",AD26="Medium"),AND(AC26="Medium",AD26="Low")),"M6",IF(OR(AND(AC26="High",AD26="Low"),AND(AC26="Low",AD26="High")),"M8",IF(AND(AC26="Medium",AD26="Medium"),"M9",IF(OR(AND(AC26="Very High",AD26="Low"),AND(AC26="Low",AD26="Very High")),"M10",IF(OR(AND(AC26="High",AD26="Medium"),AND(AC26="Medium",AD26="High")),"M12",IF(OR(AND(AC26="Very High",AD26="Medium"),AND(AC26="Medium",AD26="Very High")),"H15",IF(AND(AC26="High",AD26="High"),"H16",IF(OR(AND(AC26="Very High",AD26="High"),AND(AC26="High",AD26="Very High")),"H20",IF(AND(AC26="Very High",AD26="Very High"),"H25","")))))))))))))))
T27: =IF(AND(R27="Very Low",S27="Low"),"L1",IF(AND(R27="Low",S27="Low"),"L4",IF(OR(AND(R27="Very Low",S27="Low"),AND(R27="Low",S27="Very Low")),"L2",IF(OR(AND(R27="Medium",S27="Very Low"),AND(R27="Very Low",S27="Medium")),"L3",IF(OR(AND(R27="High",S27="Very Low"),AND(R27="Very Low",S27="High")),"L4",IF(OR(AND(R27="Very High",S27="Very Low"),AND(R27="Very Low",S27="Very High")),"M5",IF(OR(AND(R27="Low",S27="Medium"),AND(R27="Medium",S27="Low")),"M6",IF(OR(AND(R27="High",S27="Low"),AND(R27="Low",S27="High")),"M8",IF(AND(R27="Medium",S27="Medium"),"M9",IF(OR(AND(R27="Very High",S27="Low"),AND(R27="Low",S27="Very High")),"M10",IF(OR(AND(R27="High",S27="Medium"),AND(R27="Medium",S27="High")),"M12",IF(OR(AND(R27="Very High",S27="Medium"),AND(R27="Medium",S27="Very High")),"H15",IF(AND(R27="High",S27="High"),"H16",IF(OR(AND(R27="Very High",S27="High"),AND(R27="High",S27="Very High")),"H20",IF(AND(R27="Very High",S27="Very High"),"H25",""))))))))))))))) | AE27: =IF(AND(AC27="Very Low",AD27="Low"),"L1",IF(AND(AC27="Low",AD27="Low"),"L4",IF(OR(AND(AC27="Very Low",AD27="Low"),AND(AC27="Low",AD27="Very Low")),"L2",IF(OR(AND(AC27="Medium",AD27="Very Low"),AND(AC27="Very Low",AD27="Medium")),"L3",IF(OR(AND(AC27="High",AD27="Very Low"),AND(AC27="Very Low",AD27="High")),"L4",IF(OR(AND(AC27="Very High",AD27="Very Low"),AND(AC27="Very Low",AD27="Very High")),"M5",IF(OR(AND(AC27="Low",AD27="Medium"),AND(AC27="Medium",AD27="Low")),"M6",IF(OR(AND(AC27="High",AD27="Low"),AND(AC27="Low",AD27="High")),"M8",IF(AND(AC27="Medium",AD27="Medium"),"M9",IF(OR(AND(AC27="Very High",AD27="Low"),AND(AC27="Low",AD27="Very High")),"M10",IF(OR(AND(AC27="High",AD27="Medium"),AND(AC27="Medium",AD27="High")),"M12",IF(OR(AND(AC27="Very High",AD27="Medium"),AND(AC27="Medium",AD27="Very High")),"H15",IF(AND(AC27="High",AD27="High"),"H16",IF(OR(AND(AC27="Very High",AD27="High"),AND(AC27="High",AD27="Very High")),"H20",IF(AND(AC27="Very High",AD27="Very High"),"H25","")))))))))))))))
T28: =IF(AND(R28="Very Low",S28="Low"),"L1",IF(AND(R28="Low",S28="Low"),"L4",IF(OR(AND(R28="Very Low",S28="Low"),AND(R28="Low",S28="Very Low")),"L2",IF(OR(AND(R28="Medium",S28="Very Low"),AND(R28="Very Low",S28="Medium")),"L3",IF(OR(AND(R28="High",S28="Very Low"),AND(R28="Very Low",S28="High")),"L4",IF(OR(AND(R28="Very High",S28="Very Low"),AND(R28="Very Low",S28="Very High")),"M5",IF(OR(AND(R28="Low",S28="Medium"),AND(R28="Medium",S28="Low")),"M6",IF(OR(AND(R28="High",S28="Low"),AND(R28="Low",S28="High")),"M8",IF(AND(R28="Medium",S28="Medium"),"M9",IF(OR(AND(R28="Very High",S28="Low"),AND(R28="Low",S28="Very High")),"M10",IF(OR(AND(R28="High",S28="Medium"),AND(R28="Medium",S28="High")),"M12",IF(OR(AND(R28="Very High",S28="Medium"),AND(R28="Medium",S28="Very High")),"H15",IF(AND(R28="High",S28="High"),"H16",IF(OR(AND(R28="Very High",S28="High"),AND(R28="High",S28="Very High")),"H20",IF(AND(R28="Very High",S28="Very High"),"H25",""))))))))))))))) | AE28: =IF(AND(AC28="Very Low",AD28="Low"),"L1",IF(AND(AC28="Low",AD28="Low"),"L4",IF(OR(AND(AC28="Very Low",AD28="Low"),AND(AC28="Low",AD28="Very Low")),"L2",IF(OR(AND(AC28="Medium",AD28="Very Low"),AND(AC28="Very Low",AD28="Medium")),"L3",IF(OR(AND(AC28="High",AD28="Very Low"),AND(AC28="Very Low",AD28="High")),"L4",IF(OR(AND(AC28="Very High",AD28="Very Low"),AND(AC28="Very Low",AD28="Very High")),"M5",IF(OR(AND(AC28="Low",AD28="Medium"),AND(AC28="Medium",AD28="Low")),"M6",IF(OR(AND(AC28="High",AD28="Low"),AND(AC28="Low",AD28="High")),"M8",IF(AND(AC28="Medium",AD28="Medium"),"M9",IF(OR(AND(AC28="Very High",AD28="Low"),AND(AC28="Low",AD28="Very High")),"M10",IF(OR(AND(AC28="High",AD28="Medium"),AND(AC28="Medium",AD28="High")),"M12",IF(OR(AND(AC28="Very High",AD28="Medium"),AND(AC28="Medium",AD28="Very High")),"H15",IF(AND(AC28="High",AD28="High"),"H16",IF(OR(AND(AC28="Very High",AD28="High"),AND(AC28="High",AD28="Very High")),"H20",IF(AND(AC28="Very High",AD28="Very High"),"H25","")))))))))))))))
T29: =IF(AND(R29="Very Low",S29="Low"),"L1",IF(AND(R29="Low",S29="Low"),"L4",IF(OR(AND(R29="Very Low",S29="Low"),AND(R29="Low",S29="Very Low")),"L2",IF(OR(AND(R29="Medium",S29="Very Low"),AND(R29="Very Low",S29="Medium")),"L3",IF(OR(AND(R29="High",S29="Very Low"),AND(R29="Very Low",S29="High")),"L4",IF(OR(AND(R29="Very High",S29="Very Low"),AND(R29="Very Low",S29="Very High")),"M5",IF(OR(AND(R29="Low",S29="Medium"),AND(R29="Medium",S29="Low")),"M6",IF(OR(AND(R29="High",S29="Low"),AND(R29="Low",S29="High")),"M8",IF(AND(R29="Medium",S29="Medium"),"M9",IF(OR(AND(R29="Very High",S29="Low"),AND(R29="Low",S29="Very High")),"M10",IF(OR(AND(R29="High",S29="Medium"),AND(R29="Medium",S29="High")),"M12",IF(OR(AND(R29="Very High",S29="Medium"),AND(R29="Medium",S29="Very High")),"H15",IF(AND(R29="High",S29="High"),"H16",IF(OR(AND(R29="Very High",S29="High"),AND(R29="High",S29="Very High")),"H20",IF(AND(R29="Very High",S29="Very High"),"H25",""))))))))))))))) | AE29: =IF(AND(AC29="Very Low",AD29="Low"),"L1",IF(AND(AC29="Low",AD29="Low"),"L4",IF(OR(AND(AC29="Very Low",AD29="Low"),AND(AC29="Low",AD29="Very Low")),"L2",IF(OR(AND(AC29="Medium",AD29="Very Low"),AND(AC29="Very Low",AD29="Medium")),"L3",IF(OR(AND(AC29="High",AD29="Very Low"),AND(AC29="Very Low",AD29="High")),"L4",IF(OR(AND(AC29="Very High",AD29="Very Low"),AND(AC29="Very Low",AD29="Very High")),"M5",IF(OR(AND(AC29="Low",AD29="Medium"),AND(AC29="Medium",AD29="Low")),"M6",IF(OR(AND(AC29="High",AD29="Low"),AND(AC29="Low",AD29="High")),"M8",IF(AND(AC29="Medium",AD29="Medium"),"M9",IF(OR(AND(AC29="Very High",AD29="Low"),AND(AC29="Low",AD29="Very High")),"M10",IF(OR(AND(AC29="High",AD29="Medium"),AND(AC29="Medium",AD29="High")),"M12",IF(OR(AND(AC29="Very High",AD29="Medium"),AND(AC29="Medium",AD29="Very High")),"H15",IF(AND(AC29="High",AD29="High"),"H16",IF(OR(AND(AC29="Very High",AD29="High"),AND(AC29="High",AD29="Very High")),"H20",IF(AND(AC29="Very High",AD29="Very High"),"H25","")))))))))))))))
T30: =IF(AND(R30="Very Low",S30="Low"),"L1",IF(AND(R30="Low",S30="Low"),"L4",IF(OR(AND(R30="Very Low",S30="Low"),AND(R30="Low",S30="Very Low")),"L2",IF(OR(AND(R30="Medium",S30="Very Low"),AND(R30="Very Low",S30="Medium")),"L3",IF(OR(AND(R30="High",S30="Very Low"),AND(R30="Very Low",S30="High")),"L4",IF(OR(AND(R30="Very High",S30="Very Low"),AND(R30="Very Low",S30="Very High")),"M5",IF(OR(AND(R30="Low",S30="Medium"),AND(R30="Medium",S30="Low")),"M6",IF(OR(AND(R30="High",S30="Low"),AND(R30="Low",S30="High")),"M8",IF(AND(R30="Medium",S30="Medium"),"M9",IF(OR(AND(R30="Very High",S30="Low"),AND(R30="Low",S30="Very High")),"M10",IF(OR(AND(R30="High",S30="Medium"),AND(R30="Medium",S30="High")),"M12",IF(OR(AND(R30="Very High",S30="Medium"),AND(R30="Medium",S30="Very High")),"H15",IF(AND(R30="High",S30="High"),"H16",IF(OR(AND(R30="Very High",S30="High"),AND(R30="High",S30="Very High")),"H20",IF(AND(R30="Very High",S30="Very High"),"H25",""))))))))))))))) | AE30: =IF(AND(AC30="Very Low",AD30="Low"),"L1",IF(AND(AC30="Low",AD30="Low"),"L4",IF(OR(AND(AC30="Very Low",AD30="Low"),AND(AC30="Low",AD30="Very Low")),"L2",IF(OR(AND(AC30="Medium",AD30="Very Low"),AND(AC30="Very Low",AD30="Medium")),"L3",IF(OR(AND(AC30="High",AD30="Very Low"),AND(AC30="Very Low",AD30="High")),"L4",IF(OR(AND(AC30="Very High",AD30="Very Low"),AND(AC30="Very Low",AD30="Very High")),"M5",IF(OR(AND(AC30="Low",AD30="Medium"),AND(AC30="Medium",AD30="Low")),"M6",IF(OR(AND(AC30="High",AD30="Low"),AND(AC30="Low",AD30="High")),"M8",IF(AND(AC30="Medium",AD30="Medium"),"M9",IF(OR(AND(AC30="Very High",AD30="Low"),AND(AC30="Low",AD30="Very High")),"M10",IF(OR(AND(AC30="High",AD30="Medium"),AND(AC30="Medium",AD30="High")),"M12",IF(OR(AND(AC30="Very High",AD30="Medium"),AND(AC30="Medium",AD30="Very High")),"H15",IF(AND(AC30="High",AD30="High"),"H16",IF(OR(AND(AC30="Very High",AD30="High"),AND(AC30="High",AD30="Very High")),"H20",IF(AND(AC30="Very High",AD30="Very High"),"H25","")))))))))))))))
T31: =IF(AND(R31="Very Low",S31="Low"),"L1",IF(AND(R31="Low",S31="Low"),"L4",IF(OR(AND(R31="Very Low",S31="Low"),AND(R31="Low",S31="Very Low")),"L2",IF(OR(AND(R31="Medium",S31="Very Low"),AND(R31="Very Low",S31="Medium")),"L3",IF(OR(AND(R31="High",S31="Very Low"),AND(R31="Very Low",S31="High")),"L4",IF(OR(AND(R31="Very High",S31="Very Low"),AND(R31="Very Low",S31="Very High")),"M5",IF(OR(AND(R31="Low",S31="Medium"),AND(R31="Medium",S31="Low")),"M6",IF(OR(AND(R31="High",S31="Low"),AND(R31="Low",S31="High")),"M8",IF(AND(R31="Medium",S31="Medium"),"M9",IF(OR(AND(R31="Very High",S31="Low"),AND(R31="Low",S31="Very High")),"M10",IF(OR(AND(R31="High",S31="Medium"),AND(R31="Medium",S31="High")),"M12",IF(OR(AND(R31="Very High",S31="Medium"),AND(R31="Medium",S31="Very High")),"H15",IF(AND(R31="High",S31="High"),"H16",IF(OR(AND(R31="Very High",S31="High"),AND(R31="High",S31="Very High")),"H20",IF(AND(R31="Very High",S31="Very High"),"H25",""))))))))))))))) | AE31: =IF(AND(AC31="Very Low",AD31="Low"),"L1",IF(AND(AC31="Low",AD31="Low"),"L4",IF(OR(AND(AC31="Very Low",AD31="Low"),AND(AC31="Low",AD31="Very Low")),"L2",IF(OR(AND(AC31="Medium",AD31="Very Low"),AND(AC31="Very Low",AD31="Medium")),"L3",IF(OR(AND(AC31="High",AD31="Very Low"),AND(AC31="Very Low",AD31="High")),"L4",IF(OR(AND(AC31="Very High",AD31="Very Low"),AND(AC31="Very Low",AD31="Very High")),"M5",IF(OR(AND(AC31="Low",AD31="Medium"),AND(AC31="Medium",AD31="Low")),"M6",IF(OR(AND(AC31="High",AD31="Low"),AND(AC31="Low",AD31="High")),"M8",IF(AND(AC31="Medium",AD31="Medium"),"M9",IF(OR(AND(AC31="Very High",AD31="Low"),AND(AC31="Low",AD31="Very High")),"M10",IF(OR(AND(AC31="High",AD31="Medium"),AND(AC31="Medium",AD31="High")),"M12",IF(OR(AND(AC31="Very High",AD31="Medium"),AND(AC31="Medium",AD31="Very High")),"H15",IF(AND(AC31="High",AD31="High"),"H16",IF(OR(AND(AC31="Very High",AD31="High"),AND(AC31="High",AD31="Very High")),"H20",IF(AND(AC31="Very High",AD31="Very High"),"H25","")))))))))))))))
B35: NOTES:
B36: Risk Status: 1.Open, 2.Closed, or 3.Realized
B37: T/O/I: 1.Threat, 2.Opportunity, or 3.Issue
B39: Category (select 1):
B40: 1. Political
B41: 2. Legal, Regulatory, Compliance
B42: 3. Funding, Finance, Budget
B43: 4. Management, Governance, Policies, KPI, Performance
B44: 5. Human Resources | X44: `
B45: 6. Stakeholders, Authorities, Approvals, Permits
B46: 7. Requirements, Specifications, Scope, Procurement, Contract
B47: 8. Process, Tools, Technique, Technology
B48: 9. Design, Engineering
B49: 10. Construction, Execution
B50: 11. Testing, Commissioning, Handover
B51: 12. Operation, Maintenance
B53: Risk Description (add all 3):
B54: 1. Source/Cause
B55: 2. Event = Threat, Opportunity, or Issue
B56: 3. Consequence/Effect
B58: Risk Response Strategy for Threats: 1.Terminate, 2.Tolerate, 3.Transfer, or 4.Treat
... B63: Risk Level/Score: Likelihood x Highest Impact (Safety, Cost, Schedule, Environment, Quality, or Reputation. See Risk Scoring Matrix tab)

Sheet Invoice Log
B1: Weekly Progress Report - Invoice Log | AJ1: Y
B2: Project Value | K2: Payment Status | S2: Invoices Summary | AC2: Average Invoices durations | AJ2: N
B3: Original Contract Value | E3: =Progress!B27 -> 52025516 | G3: O&M Value | I3: 0 | J3: EAC | K3: Advance Payment % | M3: 0 | O3: Advance Payment (SAR) | Q3: =E3*M3 -> 0 | S3: No of Submitted Invoices | U3: 0 | W3: Submitted Invoices (SAR) | Y3: =SUM(F9:F58)*1.15 -> 34267317 | AA3: Submiited Invoice Peroid | AB3: =MAX(L9:L46) -> 46291 | AC3: CM / PgM Average Approval duration | AE3: =AVERAGE(P9:P58) -> 1.5714286 | AG3: Average Invoice Value | AH3: =AVERAGE(F9:F58) -> 4256809.6
B4: Revised Contract Value | D4: 21100000 | E4: =E3 -> 52025516 | F4: EAC | G4: Revised O&M Value | I4: 0 | J4: =+#REF!+#REF!+I4 -> #REF! | K4: Retention % | M4: 0 | O4: Retention (SAR) | Q4: =E3*M4 -> 0 | S4: No of Approved Invoices (CM) | U4: =COUNTIF($N$9:$N$59,"Y") -> 7 | W4: Approved Invoices (CM) (SAR) | Y4: =SUMIF($N$9:$N$58,"Y",$J$9:$J$58) -> 34269317 | AC4: MODON PM & Accounts Average Approval duration | AE4: =AVERAGE(W9:W58) -> 9.1428571
B5: Estimate At Completion Value | D5: 20900000 | E5: =E4 -> 52025516 | F5: =+#REF!+#REF!+E5 -> #REF! | G5: Submitted Invoices (Gross Value) | I5: =+F9+F10+F11+F12+F13+F14+F15 -> 29797667 | K5: Penalties and deduction % | M5: =ABS(M6/E3) -> 3.8442675e-05 | O5: AP Recovery (SAR) | Q5: =SUM(G9:G58) -> 0 | S5: No of Approved Invoices (PM) | U5: =COUNTIF($R$9:$R$59,"Y") -> 7 | W5: Approved Invoices (PM) (SAR) | Y5: =SUMIF($R$9:$R$58,"Y",$J$9:$J$58) -> 34269317 | AA5: Invoice Submitted Compared to Contract Value | AB5: =Y3/(E4*1.15) -> 0.57275102 | AC5: Payments Average Duration | AE5: =AVERAGE(AA9:AA58) -> 24
B6: Potential Changes | D6: =D4-D5 -> 200000 | E6: =E4-E5 -> 0 | G6: Total Deduction | I6: =M6+Q6+Q5 -> 2000 | K6: Penalties and deduction (SAR) | M6: =SUM(I9:I58) -> 2000 | O6: Retention Cumulative (SAR) | Q6: =SUM(H9:H58) -> 0 | S6: No of Paid Invoices | U6: =COUNTA(X9:X58) -> 6 | W6: Paid Invoices (SAR) | Y6: =+Y59 -> 31459715 | AC6: Invoices Average total Duration | AE6: =IFERROR(AVERAGE(AC9:AC58),"") -> 35
B7: Invoice Reference | F7: Invoice Value | K7: Period Covered | M7: CM / PgM Approval Timeline | Q7: Modon PM & Accounts Approval | X7: Payment Status | AC7: Total Invoice Duration | AD7: Remarks
B8: # | C8: Invoice No. | D8: Doc Control reference | E8: Submittal Rev. # | F8: Gross Value | G8: AP Recovery | H8: Retention | I8: Deduction / Penalties | J8: Amount (net) + VAT 15% | K8: Start Date | L8: End Date | M8: Date to CM / PgM | N8: CM / PgM Approval (Yes/No) | O8: CM / PgM Reply Date | P8: Days Elapsed | Q8: Date to PM | R8: PM Approval (Yes/No) | S8: PM Reply Date | T8: Date to Accounts | U8: Accounts Approval (Yes/No) | V8: Accounts Approval Date | W8: Days Elapsed | X8: Date Paid | Y8: Amount Paid | Z8: Paid % | AA8: Payment Period (d) | AB8: Amount Pending
B9: 1 | C9: 1 | D9: MKH2-02-003-ENJ-TS9-1-PRW-IPC-0001-00 | E9: 0 | F9: 2233198.6 | G9: =IF(ISBLANK(F9),"",-F9*$M$3*1.15) -> 0 | H9: =IF(ISBLANK(F9),"",-F9*$M$4*1.15) -> 0 | I9: 0 | J9: =IF(ISBLANK(F9),"",SUM(F9:I9)+F9*0.15) -> 2568178.4 | K9: 46068 | L9: 46111 | M9: 46111 | N9: Y | O9: 46112 | P9: =IF(ISBLANK(O9),"",O9-M9) -> 1 | Q9: =O9 -> 46112 | R9: Y | S9: =Q9+2 -> 46114 | T9: =S9+2 -> 46116 | U9: Y | V9: =T9+5 -> 46121 | W9: =IF(ISBLANK(V9),"",V9-Q9) -> 9 | X9: 46158 | Y9: =J9 -> 2568178.4 | Z9: =IF(ISBLANK(Y9),"",Y9/J9) -> 1 | AA9: =IF(ISBLANK(X9),"",X9-V9) -> 37 | AB9: =IF(ISBLANK(Y9),"",(J9-Y9)) -> 0 | AC9: =IF(ISBLANK(X9),"",X9-M9) -> 47
B10: 2 | C10: 2 | D10: MKH2-02-003-ENJ-TS9-1-PRW-IPC-0002-00 | E10: 0 | F10: 5354472.4 | G10: =IF(ISBLANK(F10),"",-F10*$M$3*1.15) -> 0 | H10: =IF(ISBLANK(F10),"",-F10*$M$4*1.15) -> 0 | I10: 0 | J10: =IF(ISBLANK(F10),"",SUM(F10:I10)+F10*0.15) -> 6157643.3 | K10: 46112 | L10: 46141 | M10: 46141 | N10: Y | O10: 46144 | P10: =IF(ISBLANK(O10),"",O10-M10) -> 3 | Q10: =O10 -> 46144 | R10: Y | S10: =Q10+2 -> 46146 | T10: =S10+2 -> 46148 | U10: Y | V10: =T10+5 -> 46153 | W10: =IF(ISBLANK(V10),"",V10-Q10) -> 9 | X10: 46180 | Y10: =J10 -> 6157643.3 | Z10: =IF(ISBLANK(Y10),"",Y10/J10) -> 1 | AA10: =IF(ISBLANK(X10),"",X10-V10) -> 27 | AB10: =IF(ISBLANK(Y10),"",(J10-Y10)) -> 0 | AC10: =IF(ISBLANK(X10),"",X10-M10) -> 39
B11: 3 | C11: 3 | D11: MKH2-02-003-ENJ-TS9-1-PRW-IPC-0003-00 | E11: 0 | F11: 3385248.3 | G11: =IF(ISBLANK(F11),"",-F11*$M$3*1.15) -> 0 | H11: =IF(ISBLANK(F11),"",-F11*$M$4*1.15) -> 0 | I11: 0 | J11: =IF(ISBLANK(F11),"",SUM(F11:I11)+F11*0.15) -> 3893035.5 | K11: 46142 | L11: 46161 | M11: 46161 | N11: Y | O11: 46163 | P11: =IF(ISBLANK(O11),"",O11-M11) -> 2 | Q11: =O11 -> 46163 | R11: Y | S11: =Q11+2 -> 46165 | T11: =S11+2 -> 46167 | U11: Y | V11: =T11+5 -> 46172 | W11: =IF(ISBLANK(V11),"",V11-Q11) -> 9 | X11: 46194 | Y11: =J11 -> 3893035.5 | Z11: =IF(ISBLANK(Y11),"",Y11/J11) -> 1 | AA11: =IF(ISBLANK(X11),"",X11-V11) -> 22 | AB11: =IF(ISBLANK(Y11),"",(J11-Y11)) -> 0 | AC11: =IF(ISBLANK(X11),"",X11-M11) -> 33
B12: 4 | C12: 4 | D12: MKH2-02-003-ENJ-TS9-1-PRW-IPC-0004-00 | E12: 0 | F12: 8068537.9 | G12: =IF(ISBLANK(F12),"",-F12*$M$3*1.15) -> 0 | H12: =IF(ISBLANK(F12),"",-F12*$M$4*1.15) -> 0 | I12: 0 | J12: =IF(ISBLANK(F12),"",SUM(F12:I12)+F12*0.15) -> 9278818.6 | K12: 46162 | L12: 46196 | M12: 46197 | N12: Y | O12: 46198 | P12: =IF(ISBLANK(O12),"",O12-M12) -> 1 | Q12: 46198 | R12: Y | S12: =Q12+2 -> 46200 | T12: =S12+3 -> 46203 | U12: Y | V12: =+T12+4 -> 46207 | W12: =IF(ISBLANK(V12),"",V12-Q12) -> 9 | X12: 46229 | Y12: =J12 -> 9278818.6 | Z12: =IF(ISBLANK(Y12),"",Y12/J12) -> 1 | AA12: =IF(ISBLANK(X12),"",X12-V12) -> 22 | AB12: =IF(ISBLANK(Y12),"",(J12-Y12)) -> 0 | AC12: =IF(ISBLANK(X12),"",X12-M12) -> 32
B13: 5 | C13: 5 | D13: MKH2-02-003-ENJ-TS9-1-PRW-IPC-0005-00 | E13: 0 | F13: 4265230.6 | G13: =IF(ISBLANK(F13),"",-F13*$M$3*1.15) -> 0 | H13: =IF(ISBLANK(F13),"",-F13*$M$4) -> 0 | I13: 0 | J13: =IF(ISBLANK(F13),"",SUM(F13:I13)+F13*0.15) -> 4905015.2 | K13: 46198 | L13: 46227 | M13: 46228 | N13: Y | O13: 46229 | P13: =IF(ISBLANK(O13),"",O13-M13) -> 1 | Q13: 46229 | R13: Y | S13: =Q13+2 -> 46231 | T13: =S13+3 -> 46234 | U13: Y | V13: =+T13+4 -> 46238 | W13: =IF(ISBLANK(V13),"",V13-Q13) -> 9 | X13: 46249 | Y13: =J13 -> 4905015.2 | Z13: =IF(ISBLANK(Y13),"",Y13/J13) -> 1 | AA13: =IF(ISBLANK(X13),"",X13-V13) -> 11 | AB13: =IF(ISBLANK(Y13),"",(J13-Y13)) -> 0 | AC13: =IF(ISBLANK(X13),"",X13-M13) -> 21
B14: 6 | C14: 6 | D14: MKH2-02-003-ENJ-TS9-1-PRW-IPC-0006-00 | E14: 0 | F14: 4047847.2 | G14: =IF(ISBLANK(F14),"",-F14*$M$3*1.15) -> 0 | H14: =IF(ISBLANK(F14),"",-F14*$M$4) -> 0 | I14: 2000 | J14: =IF(ISBLANK(F14),"",SUM(F14:I14)+F14*0.15) -> 4657024.3 | K14: 46228 | L14: 46257 | M14: 46258 | N14: Y | O14: 46259 | P14: =IF(ISBLANK(O14),"",O14-M14) -> 1 | Q14: 46263 | R14: Y | S14: 46264 | T14: 46267 | U14: Y | V14: 46271 | W14: =IF(ISBLANK(V14),"",V14-Q14) -> 8 | X14: 46296 | Y14: =J14 -> 4657024.3 | Z14: =IF(ISBLANK(Y14),"",Y14/J14) -> 1 | AA14: =IF(ISBLANK(X14),"",X14-V14) -> 25 | AB14: =IF(ISBLANK(Y14),"",(J14-Y14)) -> 0 | AC14: =IF(ISBLANK(X14),"",X14-M14) -> 38
B15: 7 | C15: 7 | D15: MKH2-02-003-ENJ-TS9-1-PRW-IPC-0007-00 | E15: 0 | F15: 2443132 | G15: =IF(ISBLANK(F15),"",-F15*$M$3*1.15) -> 0 | H15: =IF(ISBLANK(F15),"",-F15*$M$4) -> 0 | I15: 0 | J15: =IF(ISBLANK(F15),"",SUM(F15:I15)+F15*0.15) -> 2809601.9 | K15: 46258 | L15: 46291 | M15: 46292 | N15: Y | O15: 46294 | P15: =IF(ISBLANK(O15),"",O15-M15) -> 2 | Q15: 46296 | R15: Y | S15: 46301 | T15: 46303 | U15: Y | V15: 46307 | W15: =IF(ISBLANK(V15),"",V15-Q15) -> 11 | Z15: =IF(ISBLANK(Y15),"",Y15/J15) | AA15: =IF(ISBLANK(X15),"",X15-V15) | AB15: =IF(ISBLANK(Y15),"",(J15-Y15)) | AC15: =IF(ISBLANK(X15),"",X15-M15)
B16: 8 | G16: =IF(ISBLANK(F16),"",-F16*$M$3*1.15) | H16: =IF(ISBLANK(F16),"",-F16*$M$4) | J16: =IF(ISBLANK(F16),"",SUM(F16:I16)+F16*0.15) | P16: =IF(ISBLANK(O16),"",O16-M16) | W16: =IF(ISBLANK(V16),"",V16-Q16) | Z16: =IF(ISBLANK(Y16),"",Y16/J16) | AA16: =IF(ISBLANK(X16),"",X16-V16) | AB16: =IF(ISBLANK(Y16),"",(J16-Y16)) | AC16: =IF(ISBLANK(X16),"",X16-M16)
B17: 9 | G17: =IF(ISBLANK(F17),"",-F17*$M$3*1.15) | H17: =IF(ISBLANK(F17),"",-F17*$M$4) | J17: =IF(ISBLANK(F17),"",SUM(F17:I17)+F17*0.15) | P17: =IF(ISBLANK(O17),"",O17-M17) | W17: =IF(ISBLANK(V17),"",V17-Q17) | Z17: =IF(ISBLANK(Y17),"",Y17/J17) | AA17: =IF(ISBLANK(X17),"",X17-V17) | AB17: =IF(ISBLANK(Y17),"",(J17-Y17)) | AC17: =IF(ISBLANK(X17),"",X17-M17)
B18: 10 | G18: =IF(ISBLANK(F18),"",-F18*$M$3*1.15) | H18: =IF(ISBLANK(F18),"",-F18*$M$4) | J18: =IF(ISBLANK(F18),"",SUM(F18:I18)+F18*0.15) | P18: =IF(ISBLANK(O18),"",O18-M18) | W18: =IF(ISBLANK(V18),"",V18-Q18) | Z18: =IF(ISBLANK(Y18),"",Y18/J18) | AA18: =IF(ISBLANK(X18),"",X18-V18) | AB18: =IF(ISBLANK(Y18),"",(J18-Y18)) | AC18: =IF(ISBLANK(X18),"",X18-M18)
B19: 11 | G19: =IF(ISBLANK(F19),"",-F19*$M$3*1.15) | H19: =IF(ISBLANK(F19),"",-F19*$M$4) | J19: =IF(ISBLANK(F19),"",SUM(F19:I19)+F19*0.15) | P19: =IF(ISBLANK(O19),"",O19-M19) | W19: =IF(ISBLANK(V19),"",V19-Q19) | Z19: =IF(ISBLANK(Y19),"",Y19/J19) | AA19: =IF(ISBLANK(X19),"",X19-V19) | AB19: =IF(ISBLANK(Y19),"",(J19-Y19)) | AC19: =IF(ISBLANK(X19),"",X19-M19)
B20: 12 | G20: =IF(ISBLANK(F20),"",-F20*$M$3*1.15) | H20: =IF(ISBLANK(F20),"",-F20*$M$4) | J20: =IF(ISBLANK(F20),"",SUM(F20:I20)+F20*0.15) | P20: =IF(ISBLANK(O20),"",O20-M20) | W20: =IF(ISBLANK(V20),"",V20-Q20) | Z20: =IF(ISBLANK(Y20),"",Y20/J20) | AA20: =IF(ISBLANK(X20),"",X20-V20) | AB20: =IF(ISBLANK(Y20),"",(J20-Y20)) | AC20: =IF(ISBLANK(X20),"",X20-M20)
B21: 13 | G21: =IF(ISBLANK(F21),"",-F21*$M$3*1.15) | H21: =IF(ISBLANK(F21),"",-F21*$M$4) | J21: =IF(ISBLANK(F21),"",SUM(F21:I21)+F21*0.15) | P21: =IF(ISBLANK(O21),"",O21-M21) | W21: =IF(ISBLANK(V21),"",V21-Q21) | Z21: =IF(ISBLANK(Y21),"",Y21/J21) | AA21: =IF(ISBLANK(X21),"",X21-V21) | AB21: =IF(ISBLANK(Y21),"",(J21-Y21)) | AC21: =IF(ISBLANK(X21),"",X21-M21)
B22: 14 | G22: =IF(ISBLANK(F22),"",-F22*$M$3*1.15) | H22: =IF(ISBLANK(F22),"",-F22*$M$4) | J22: =IF(ISBLANK(F22),"",SUM(F22:I22)+F22*0.15) | P22: =IF(ISBLANK(O22),"",O22-M22) | W22: =IF(ISBLANK(V22),"",V22-Q22) | Z22: =IF(ISBLANK(Y22),"",Y22/J22) | AA22: =IF(ISBLANK(X22),"",X22-V22) | AB22: =IF(ISBLANK(Y22),"",(J22-Y22)) | AC22: =IF(ISBLANK(X22),"",X22-M22)
B23: 15 | G23: =IF(ISBLANK(F23),"",-F23*$M$3*1.15) | H23: =IF(ISBLANK(F23),"",-F23*$M$4) | J23: =IF(ISBLANK(F23),"",SUM(F23:I23)+F23*0.15) | P23: =IF(ISBLANK(O23),"",O23-M23) | W23: =IF(ISBLANK(V23),"",V23-Q23) | Z23: =IF(ISBLANK(Y23),"",Y23/J23) | AA23: =IF(ISBLANK(X23),"",X23-V23) | AB23: =IF(ISBLANK(Y23),"",(J23-Y23)) | AC23: =IF(ISBLANK(X23),"",X23-M23)
B24: 16 | G24: =IF(ISBLANK(F24),"",-F24*$M$3*1.15) | H24: =IF(ISBLANK(F24),"",-F24*$M$4) | J24: =IF(ISBLANK(F24),"",SUM(F24:I24)+F24*0.15) | P24: =IF(ISBLANK(O24),"",O24-M24) | W24: =IF(ISBLANK(V24),"",V24-Q24) | Z24: =IF(ISBLANK(Y24),"",Y24/J24) | AA24: =IF(ISBLANK(X24),"",X24-V24) | AB24: =IF(ISBLANK(Y24),"",(J24-Y24)) | AC24: =IF(ISBLANK(X24),"",X24-M24)
B25: 17 | G25: =IF(ISBLANK(F25),"",-F25*$M$3*1.15) | H25: =IF(ISBLANK(F25),"",-F25*$M$4) | J25: =IF(ISBLANK(F25),"",SUM(F25:I25)+F25*0.15) | P25: =IF(ISBLANK(O25),"",O25-M25) | W25: =IF(ISBLANK(V25),"",V25-Q25) | Z25: =IF(ISBLANK(Y25),"",Y25/J25) | AA25: =IF(ISBLANK(X25),"",X25-V25) | AB25: =IF(ISBLANK(Y25),"",(J25-Y25)) | AC25: =IF(ISBLANK(X25),"",X25-M25)
B26: 18 | G26: =IF(ISBLANK(F26),"",-F26*$M$3*1.15) | H26: =IF(ISBLANK(F26),"",-F26*$M$4) | J26: =IF(ISBLANK(F26),"",SUM(F26:I26)+F26*0.15) | P26: =IF(ISBLANK(O26),"",O26-M26) | W26: =IF(ISBLANK(V26),"",V26-Q26) | Z26: =IF(ISBLANK(Y26),"",Y26/J26) | AA26: =IF(ISBLANK(X26),"",X26-V26) | AB26: =IF(ISBLANK(Y26),"",(J26-Y26)) | AC26: =IF(ISBLANK(X26),"",X26-M26)
B27: 19 | G27: =IF(ISBLANK(F27),"",-F27*$M$3*1.15) | H27: =IF(ISBLANK(F27),"",-F27*$M$4) | J27: =IF(ISBLANK(F27),"",SUM(F27:I27)+F27*0.15) | P27: =IF(ISBLANK(O27),"",O27-M27) | W27: =IF(ISBLANK(V27),"",V27-Q27) | Z27: =IF(ISBLANK(Y27),"",Y27/J27) | AA27: =IF(ISBLANK(X27),"",X27-V27) | AB27: =IF(ISBLANK(Y27),"",(J27-Y27)) | AC27: =IF(ISBLANK(X27),"",X27-M27)
... B35: 27 | G35: =IF(ISBLANK(F35),"",-F35*$M$3*1.15) | H35: =IF(ISBLANK(F35),"",-F35*$M$4) | J35: =IF(ISBLANK(F35),"",SUM(F35:I35)+F35*0.15) | P35: =IF(ISBLANK(O35),"",O35-M35) | W35: =IF(ISBLANK(V35),"",V35-Q35) | Z35: =IF(ISBLANK(Y35),"",Y35/J35) | AA35: =IF(ISBLANK(X35),"",X35-V35) | AB35: =IF(ISBLANK(Y35),"",(J35-Y35)) | AC35: =IF(ISBLANK(X35),"",X35-M35)
B36: 28 | G36: =IF(ISBLANK(F36),"",-F36*$M$3*1.15) | H36: =IF(ISBLANK(F36),"",-F36*$M$4) | J36: =IF(ISBLANK(F36),"",SUM(F36:I36)+F36*0.15) | P36: =IF(ISBLANK(O36),"",O36-M36) | W36: =IF(ISBLANK(V36),"",V36-Q36) | Z36: =IF(ISBLANK(Y36),"",Y36/F36) | AA36: =IF(ISBLANK(X36),"",X36-V36) | AB36: =IF(ISBLANK(Y36),"",(J36-Y36)) | AC36: =IF(ISBLANK(X36),"",X36-M36)
B37: 29 | G37: =IF(ISBLANK(F37),"",-F37*$M$3*1.15) | H37: =IF(ISBLANK(F37),"",-F37*$M$4) | J37: =IF(ISBLANK(F37),"",SUM(F37:I37)+F37*0.15) | P37: =IF(ISBLANK(O37),"",O37-M37) | W37: =IF(ISBLANK(V37),"",V37-Q37) | Z37: =IF(ISBLANK(Y37),"",Y37/F37) | AA37: =IF(ISBLANK(X37),"",X37-V37) | AB37: =IF(ISBLANK(Y37),"",(J37-Y37)) | AC37: =IF(ISBLANK(X37),"",X37-M37)
B38: 30 | G38: =IF(ISBLANK(F38),"",-F38*$M$3*1.15) | H38: =IF(ISBLANK(F38),"",-F38*$M$4) | J38: =IF(ISBLANK(F38),"",SUM(F38:I38)+F38*0.15) | P38: =IF(ISBLANK(O38),"",O38-M38) | W38: =IF(ISBLANK(V38),"",V38-Q38) | Z38: =IF(ISBLANK(Y38),"",Y38/F38) | AA38: =IF(ISBLANK(X38),"",X38-V38) | AB38: =IF(ISBLANK(Y38),"",(F38-Y38)) | AC38: =IF(ISBLANK(X38),"",X38-M38)
B39: 31 | G39: =IF(ISBLANK(F39),"",-F39*$M$3*1.15) | H39: =IF(ISBLANK(F39),"",-F39*$M$4) | J39: =IF(ISBLANK(F39),"",SUM(F39:I39)+F39*0.15) | P39: =IF(ISBLANK(O39),"",O39-M39) | W39: =IF(ISBLANK(V39),"",V39-Q39) | Z39: =IF(ISBLANK(Y39),"",Y39/F39) | AA39: =IF(ISBLANK(X39),"",X39-V39) | AB39: =IF(ISBLANK(Y39),"",(F39-Y39)) | AC39: =IF(ISBLANK(X39),"",X39-M39)
B40: 32 | G40: =IF(ISBLANK(F40),"",-F40*$M$3*1.15) | H40: =IF(ISBLANK(F40),"",-F40*$M$4) | J40: =IF(ISBLANK(F40),"",SUM(F40:I40)+F40*0.15) | P40: =IF(ISBLANK(O40),"",O40-M40) | W40: =IF(ISBLANK(V40),"",V40-Q40) | Z40: =IF(ISBLANK(Y40),"",Y40/F40) | AA40: =IF(ISBLANK(X40),"",X40-V40) | AB40: =IF(ISBLANK(Y40),"",(F40-Y40)) | AC40: =IF(ISBLANK(X40),"",X40-M40)
B41: 33 | G41: =IF(ISBLANK(F41),"",-F41*$M$3*1.15) | H41: =IF(ISBLANK(F41),"",-F41*$M$4) | J41: =IF(ISBLANK(F41),"",SUM(F41:I41)+F41*0.15) | P41: =IF(ISBLANK(O41),"",O41-M41) | W41: =IF(ISBLANK(V41),"",V41-Q41) | Z41: =IF(ISBLANK(Y41),"",Y41/F41) | AA41: =IF(ISBLANK(X41),"",X41-V41) | AB41: =IF(ISBLANK(Y41),"",(F41-Y41)) | AC41: =IF(ISBLANK(X41),"",X41-M41)
B42: 34 | G42: =IF(ISBLANK(F42),"",-F42*$M$3*1.15) | H42: =IF(ISBLANK(F42),"",-F42*$M$4) | J42: =IF(ISBLANK(F42),"",SUM(F42:I42)+F42*0.15) | P42: =IF(ISBLANK(O42),"",O42-M42) | W42: =IF(ISBLANK(V42),"",V42-Q42) | Z42: =IF(ISBLANK(Y42),"",Y42/F42) | AA42: =IF(ISBLANK(X42),"",X42-V42) | AB42: =IF(ISBLANK(Y42),"",(F42-Y42)) | AC42: =IF(ISBLANK(X42),"",X42-M42)
B43: 35 | G43: =IF(ISBLANK(F43),"",-F43*$M$3*1.15) | H43: =IF(ISBLANK(F43),"",-F43*$M$4) | J43: =IF(ISBLANK(F43),"",SUM(F43:I43)+F43*0.15) | P43: =IF(ISBLANK(O43),"",O43-M43) | W43: =IF(ISBLANK(V43),"",V43-Q43) | Z43: =IF(ISBLANK(Y43),"",Y43/F43) | AA43: =IF(ISBLANK(X43),"",X43-V43) | AB43: =IF(ISBLANK(Y43),"",(F43-Y43)) | AC43: =IF(ISBLANK(X43),"",X43-M43)
B44: 36 | G44: =IF(ISBLANK(F44),"",-F44*$M$3*1.15) | H44: =IF(ISBLANK(F44),"",-F44*$M$4) | J44: =IF(ISBLANK(F44),"",SUM(F44:I44)+F44*0.15) | P44: =IF(ISBLANK(O44),"",O44-M44) | W44: =IF(ISBLANK(V44),"",V44-Q44) | Z44: =IF(ISBLANK(Y44),"",Y44/F44) | AA44: =IF(ISBLANK(X44),"",X44-V44) | AB44: =IF(ISBLANK(Y44),"",(F44-Y44)) | AC44: =IF(ISBLANK(X44),"",X44-M44)
B45: 37 | G45: =IF(ISBLANK(F45),"",-F45*$M$3*1.15) | H45: =IF(ISBLANK(F45),"",-F45*$M$4) | J45: =IF(ISBLANK(F45),"",SUM(F45:I45)+F45*0.15) | P45: =IF(ISBLANK(O45),"",O45-M45) | W45: =IF(ISBLANK(V45),"",V45-Q45) | Z45: =IF(ISBLANK(Y45),"",Y45/F45) | AA45: =IF(ISBLANK(X45),"",X45-V45) | AB45: =IF(ISBLANK(Y45),"",(F45-Y45)) | AC45: =IF(ISBLANK(X45),"",X45-M45)
B46: 38 | G46: =IF(ISBLANK(F46),"",-F46*$M$3*1.15) | H46: =IF(ISBLANK(F46),"",-F46*$M$4) | J46: =IF(ISBLANK(F46),"",SUM(F46:I46)+F46*0.15) | P46: =IF(ISBLANK(O46),"",O46-M46) | W46: =IF(ISBLANK(V46),"",V46-Q46) | Z46: =IF(ISBLANK(Y46),"",Y46/F46) | AA46: =IF(ISBLANK(X46),"",X46-V46) | AB46: =IF(ISBLANK(Y46),"",(F46-Y46)) | AC46: =IF(ISBLANK(X46),"",X46-M46)
B47: 39 | G47: =IF(ISBLANK(F47),"",-F47*$M$3*1.15) | H47: =IF(ISBLANK(F47),"",-F47*$M$4) | J47: =IF(ISBLANK(F47),"",SUM(F47:I47)+F47*0.15) | Z47: =IF(ISBLANK(Y47),"",Y47/F47) | AB47: =IF(ISBLANK(Y47),"",(F47-Y47))
B48: 40 | G48: =IF(ISBLANK(F48),"",-F48*$M$3*1.15) | H48: =IF(ISBLANK(F48),"",-F48*$M$4) | J48: =IF(ISBLANK(F48),"",SUM(F48:I48)+F48*0.15) | Z48: =IF(ISBLANK(Y48),"",Y48/F48) | AB48: =IF(ISBLANK(Y48),"",(F48-Y48))
B49: 41 | G49: =IF(ISBLANK(F49),"",-F49*$M$3*1.15) | H49: =IF(ISBLANK(F49),"",-F49*$M$4) | J49: =IF(ISBLANK(F49),"",SUM(F49:I49)+F49*0.15) | Z49: =IF(ISBLANK(Y49),"",Y49/F49) | AB49: =IF(ISBLANK(Y49),"",(F49-Y49))
B50: 42 | G50: =IF(ISBLANK(F50),"",-F50*$M$3*1.15) | H50: =IF(ISBLANK(F50),"",-F50*$M$4) | J50: =IF(ISBLANK(F50),"",SUM(F50:I50)+F50*0.15) | Z50: =IF(ISBLANK(Y50),"",Y50/F50) | AB50: =IF(ISBLANK(Y50),"",(F50-Y50))
B51: 43 | G51: =IF(ISBLANK(F51),"",-F51*$M$3*1.15) | H51: =IF(ISBLANK(F51),"",-F51*$M$4) | J51: =IF(ISBLANK(F51),"",SUM(F51:I51)+F51*0.15) | Z51: =IF(ISBLANK(Y51),"",Y51/F51) | AB51: =IF(ISBLANK(Y51),"",(F51-Y51))
B52: 44 | G52: =IF(ISBLANK(F52),"",-F52*$M$3*1.15) | H52: =IF(ISBLANK(F52),"",-F52*$M$4) | J52: =IF(ISBLANK(F52),"",SUM(F52:I52)+F52*0.15) | Z52: =IF(ISBLANK(Y52),"",Y52/F52) | AB52: =IF(ISBLANK(Y52),"",(F52-Y52))
B53: 45 | G53: =IF(ISBLANK(F53),"",-F53*$M$3*1.15) | H53: =IF(ISBLANK(F53),"",-F53*$M$4) | J53: =IF(ISBLANK(F53),"",SUM(F53:I53)+F53*0.15) | Z53: =IF(ISBLANK(Y53),"",Y53/F53) | AB53: =IF(ISBLANK(Y53),"",(F53-Y53))
B54: 46 | G54: =IF(ISBLANK(F54),"",-F54*$M$3*1.15) | H54: =IF(ISBLANK(F54),"",-F54*$M$4) | J54: =IF(ISBLANK(F54),"",SUM(F54:I54)+F54*0.15) | Z54: =IF(ISBLANK(Y54),"",Y54/F54) | AB54: =IF(ISBLANK(Y54),"",(F54-Y54))
B55: 47 | G55: =IF(ISBLANK(F55),"",-F55*$M$3*1.15) | H55: =IF(ISBLANK(F55),"",-F55*$M$4) | J55: =IF(ISBLANK(F55),"",SUM(F55:I55)+F55*0.15) | Z55: =IF(ISBLANK(Y55),"",Y55/F55) | AB55: =IF(ISBLANK(Y55),"",(F55-Y55))
B56: 48 | G56: =IF(ISBLANK(F56),"",-F56*$M$3*1.15) | H56: =IF(ISBLANK(F56),"",-F56*$M$4) | J56: =IF(ISBLANK(F56),"",SUM(F56:I56)+F56*0.15) | Z56: =IF(ISBLANK(Y56),"",Y56/F56) | AB56: =IF(ISBLANK(Y56),"",(F56-Y56))
