Workbook
Name _1B.05.M.010.0010: #REF!
Name _1B.05.M.010.0010: #REF!
Name _1B.05.M.010.0010: #REF!
Name _1B.05.M.010.0010: #REF!
Name _1B.05.M.010.0050: #REF!
Name _1B.05.M.010.0050: #REF!
Name _1B.05.M.010.0050: #REF!
Name _1B.05.M.010.0050: #REF!
Name _1B.05.M.0100.0010: #REF!
Name _1B.05.M.0100.0010: #REF!
Name _1B.05.M.020.0010: #REF!
Name _1B.05.M.020.0010: #REF!
Name _1B.05.M.020.0020: #REF!
Name _1B.05.M.020.0020: #REF!
Name _1B.05.M.020.0030: #REF!
Name _1B.05.M.020.0030: #REF!
Name _1B.05.M.020.0040: #REF!
Name _1B.05.M.020.0040: #REF!
Name _1B.05.M.030.0010: #REF!
Name _1B.05.M.030.0010: #REF!
Name _1B.05.M.030.0020: #REF!
Name _1B.05.M.030.0020: #REF!
Name _1B.05.M.040.0010: #REF!
Name _1B.05.M.040.0010: #REF!
Name _1B.05.M.050.0010: #REF!
Name _1B.05.M.050.0010: #REF!
Name _1B.05.M.050.0020: #REF!
Name _1B.05.M.050.0020: #REF!
Name _1B.05.M.050.0030: #REF!
Name _1B.05.M.050.0030: #REF!
Name _1B.05.M.060.0020: #REF!
Name _1B.05.M.060.0020: #REF!
Name _1B.05.M.060.0100: #REF!
Name _1B.05.M.060.0100: #REF!
Name _1B.05.M.070.0010: #REF!
Name _1B.05.M.070.0010: #REF!
Name _1B.05.M.070.0020: #REF!
Name _1B.05.M.070.0020: #REF!
Name _1B.05.M.070.0030: #REF!
Name _1B.05.M.070.0030: #REF!
Name _1B.05.M.070.0040: #REF!
Name _1B.05.M.070.0040: #REF!
Name _1B.05.M.070.0050: #REF!
Name _1B.05.M.070.0050: #REF!
Name _1B.05.M.080.0010: #REF!
Name _1B.05.M.080.0010: #REF!
Name _1B.05.M.090.0010: #REF!
Name _1B.05.M.090.0010: #REF!
Name _1B.09.P.010.0010: #REF!
Name _1B.09.P.010.0010: #REF!
Name _1B.09.P.010.0020: #REF!
Name _1B.09.P.010.0020: #REF!
Name _1B.09.P.010.0030: #REF!
Name _1B.09.P.010.0030: #REF!
Name _1B.09.P.010.0040: #REF!
Name _1B.09.P.010.0040: #REF!
Name _1B.09.P.010.0050: #REF!
Name _1B.09.P.010.0050: #REF!
Name _1B.09.P.010.0060: #REF!
Name _1B.09.P.010.0060: #REF!

Sheet DB
A1: ='Weekly Progress Report'!$A$1 -> MODON - Weekly Progress Report - Construction Projects
B2: ='Weekly Progress Report'!$A$2 -> Contract General Information | J2: ='Weekly Progress Report'!G2 -> Key Dates | U2: ='Weekly Progress Report'!$M$2 -> Cost Summary (SR) | AD2: ='Weekly Progress Report'!$U$2 -> Performance Summary | AP2: ='Weekly Progress Report'!A59 -> Shop Drawings | AT2: ='Weekly Progress Report'!A68 -> Material Approval | AW2: ='Weekly Progress Report'!A77 -> Procurement Summary | BD2: ='Weekly Progress Report'!L59 -> Quality Reports | BT2: ='Weekly Progress Report'!L67 -> Key Submittals Approval Status | CD2: ='Weekly Progress Report'!L73 -> Invoices Summary | CR2: ='Weekly Progress Report'!L81 -> Resources at Site | CY2: ='Weekly Progress Report'!W59 -> Safety Statistics | FK2: ='Weekly Progress Report'!A86 -> Primavera P6 Schedule Status | FS2: ='Weekly Progress Report'!A95 -> Weekly Prgoress Photos
A3: ='Weekly Progress Report'!AF1 -> Data Date | B3: ='Weekly Progress Report'!A3 -> Project Name | C3: ='Weekly Progress Report'!A4 -> Project ID | D3: ='Weekly Progress Report'!A5 -> Contractor | E3: ='Weekly Progress Report'!A6 -> Consultant | F3: ='Weekly Progress Report'!D4 -> Stage | G3: ='Weekly Progress Report'!D5 -> Status | H3: ='Weekly Progress Report'!D6 -> Modon PM | I3: ='Weekly Progress Report'!AA2 -> Project Scope | J3: ='Weekly Progress Report'!G3 -> Contract Award | K3: ='Weekly Progress Report'!G4 -> Contract Sign | L3: ='Weekly Progress Report'!G5 -> Site Handover | M3: ='Weekly Progress Report'!G6 -> Original Completion | N3: ='Weekly Progress Report'!$I$3 -> Contract Award (Hijri) | O3: ='Weekly Progress Report'!$I$4 -> Contract Sign (Hijri) | P3: ='Weekly Progress Report'!$I$5 -> Site Handover (Hijri) | Q3: ='Weekly Progress Report'!$I$6 -> Original Completion (Hijri) | R3: ='Weekly Progress Report'!$K$3 -> Revised Completion | S3: ='Weekly Progress Report'!$K$4 -> Committed Completion | T3: ='Weekly Progress Report'!$K$5 -> Forecast Completion | U3: ='Weekly Progress Report'!$M$3 -> Original Contract Value | V3: ='Weekly Progress Report'!$M$4 -> Revised Contract Value | W3: ='Weekly Progress Report'!$M$5 -> Estimate At Completion Value | X3: ='Weekly Progress Report'!$M$6 -> Potential Changes | Y3: ='Weekly Progress Report'!$Q$3 -> O&M Value (if any) | Z3: ='Weekly Progress Report'!$Q$4 -> Submitted Invoices (Gross Value) | AA3: ='Weekly Progress Report'!$Q$5 -> Penalities | AB3: ='Weekly Progress Report'!$Q$6 -> FIR Value (Todate) | AC3: Original Plan Value | AD3: ='Weekly Progress Report'!$U$3 -> Plan Value | AE3: ='Weekly Progress Report'!$U$4 -> Earn Value | AF3: ='Weekly Progress Report'!$W$3 -> Phys. Plan Value | AG3: ='Weekly Progress Report'!$W$4 -> Phys. Earn Value | AH3: ='Weekly Progress Report'!$Y$3 -> Quality Score | AI3: ='Weekly Progress Report'!$Y$5 -> Safety Score | AJ3: Weekly PV (SAR) | AK3: Weekly EV (SAR) | AL3: Weekly PV % | AM3: Weekly PV % | AN3: Weekly Phys PV% | AO3: Weekly Phys PV% | AP3: Total SD Planned | AQ3: SD Remaining | AR3: SD Pending | AS3: Total SD Submittals | AT3: Planned Materials Approv | AU3: Material Pending Approval | AV3: Materila Total Submittals | AW3: ='Weekly Progress Report'!C78 -> Total Materials | AX3: ='Weekly Progress Report'!D78 -> Total Number of P.O. | AY3: ='Weekly Progress Report'!E78 -> Actual P.O. To Date | AZ3: ='Weekly Progress Report'!F78 -> Remaining P.O | BA3: ='Weekly Progress Report'!G78 -> Material on Site | BB3: ='Weekly Progress Report'!H78 -> Remaining Materials | BC3: ='Weekly Progress Report'!I78 -> Material Delivery Completion (Date) | BD3: ="NCR "&'Weekly Progress Report'!N60 -> NCR Issued | BE3: ="NCR "&'Weekly Progress Report'!O60 -> NCR Closed | BF3: ="NCR "&'Weekly Progress Report'!P60 -> NCR Pending | BG3: ="NCR "&'Weekly Progress Report'!Q60 -> NCR Avg. Closing (Days) | BH3: ="SIR "&'Weekly Progress Report'!N60 -> SIR Issued | BI3: ="SIR "&'Weekly Progress Report'!O60 -> SIR Closed | BJ3: ="SIR "&'Weekly Progress Report'!P60 -> SIR Pending | BK3: ="SIR "&'Weekly Progress Report'!Q60 -> SIR Avg. Closing (Days) | BL3: ="MIR "&'Weekly Progress Report'!N60 -> MIR Issued | BM3: ="MIR "&'Weekly Progress Report'!O60 -> MIR Closed | BN3: ="MIR "&'Weekly Progress Report'!P60 -> MIR Pending | BO3: ="MIR "&'Weekly Progress Report'!Q60 -> MIR Avg. Closing (Days) | BP3: ="FIR "&'Weekly Progress Report'!N60 -> FIR Issued | BQ3: ="FIR "&'Weekly Progress Report'!O60 -> FIR Closed | BR3: ="FIR "&'Weekly Progress Report'!P60 -> FIR Pending | BS3: ="FIR "&'Weekly Progress Report'!Q60 -> FIR Avg. Closing (Days) | BT3: ='Weekly Progress Report'!L68 -> 1 Quality Plan Approval | BU3: ='Weekly Progress Report'!L69 -> 2 Quality Plan Last Up | BV3: ='Weekly Progress Report'!L70 -> 3 Safety Plan Approval | BW3: ='Weekly Progress Report'!L71 -> 4 Safety Plan Last Up | BX3: ='Weekly Progress Report'!L72 -> 5 Construction Plan Approval | BY3: ='Weekly Progress Report'!Q68 -> 6 Baseline Approval | BZ3: ='Weekly Progress Report'!Q69 -> 7 No of Approved Version of Schedule | CA3: ='Weekly Progress Report'!Q70 -> 8 Last Approved Schedule | CB3: ='Weekly Progress Report'!Q71 -> 9 BOQ Approval Date | CC3: ='Weekly Progress Report'!Q72 -> 10 No of Approved Version of BOQ | CD3: ='Weekly Progress Report'!L74 -> Total Submitted Invoices | CE3: ='Weekly Progress Report'!L75 -> PM Approved Invoices | CF3: ='Weekly Progress Report'!L76 -> No of Paid Invoices | CG3: ='Weekly Progress Report'!L77 -> No of Pending Invoices | CH3: ='Weekly Progress Report'!L78 -> Advance Payment % | CI3: ='Weekly Progress Report'!L79 -> Retention % | CJ3: ='Weekly Progress Report'!L80 -> Deduction / Penalties % | CK3: ='Weekly Progress Report'!O74 -> Submitted Invoices (SAR) | CL3: ='Weekly Progress Report'!O75 -> PM Approved Invoices (SAR) | CM3: ='Weekly Progress Report'!O76 -> Paid Invoices (SAR) | CN3: ='Weekly Progress Report'!O77 -> Last Submitted Period | CO3: ='Weekly Progress Report'!O78 -> Advance Payment (SAR) | CP3: ='Weekly Progress Report'!O79 -> Retention (SAR) | CQ3: ='Weekly Progress Report'!O80 -> Deduction / Penalties (SAR) | CR3: Planned Head Count | CS3: Actual Head Count | CT3: Saudi Staff | CU3: Labor Planned | CV3: Labor Actual | CW3: Equipment Planned | CX3: Equipment Actual | CY3: ="This Week "&'Weekly Progress Report'!X62 -> This Week Total Hours Worked | CZ3: ="This Week "&'Weekly Progress Report'!X63 -> This Week Safe Hours Worked | DA3: ="This Week "&'Weekly Progress Report'!X64 -> This Week LTI | DB3: ="This Week "&'Weekly Progress Report'!X65 -> This Week MTC (Healed w/o Disability) | DC3: ="This Week "&'Weekly Progress Report'!X66 -> This Week MTC (Healed w/ Disability) | DD3: ="This Week "&'Weekly Progress Report'!X67 -> This Week Near Miss | DE3: ="This Week "&'Weekly Progress Report'!X68 -> This Week First Aid Cases | DF3: ="This Week "&'Weekly Progress Report'!X69 -> This Week Fatality | DG3: ="This Week "&'Weekly Progress Report'!X70 -> This Week Fire Incident Cases | DH3: ="This Week "&'Weekly Progress Report'!X71 -> This Week Vehicle Incident | DI3: ="This Week "&'Weekly Progress Report'!X72 -> This Week Property Damages | DJ3: ="This Week "&'Weekly Progress Report'!X73 -> This Week Induction Training | DK3: ="This Week "&'Weekly Progress Report'!X74 -> This Week No.of Internal Training | DL3: ="This Week "&'Weekly Progress Report'!X75 -> This Week No.of Internal Audit | DM3: ="This Week "&'Weekly Progress Report'!X76 -> This Week No. of Toolbox Talks | DN3: ="This Week "&'Weekly Progress Report'!X77 -> This Week Safety Awards/Incentives | DO3: ="This Month "&'Weekly Progress Report'!X62 -> This Month Total Hours Worked | DP3: ="This Month "&'Weekly Progress Report'!X63 -> This Month Safe Hours Worked | DQ3: ="This Month "&'Weekly Progress Report'!X64 -> This Month LTI | DR3: ="This Month "&'Weekly Progress Report'!X65 -> This Month MTC (Healed w/o Disability) | DS3: ="This Month "&'Weekly Progress Report'!X66 -> This Month MTC (Healed w/ Disability) | DT3: ="This Month "&'Weekly Progress Report'!X67 -> This Month Near Miss | DU3: ="This Month "&'Weekly Progress Report'!X68 -> This Month First Aid Cases | DV3: ="This Month "&'Weekly Progress Report'!X69 -> This Month Fatality | DW3: ="This Month "&'Weekly Progress Report'!X70 -> This Month Fire Incident Cases | DX3: ="This Month "&'Weekly Progress Report'!X71 -> This Month Vehicle Incident | DY3: ="This Month "&'Weekly Progress Report'!X72 -> This Month Property Damages | DZ3: ="This Month "&'Weekly Progress Report'!X73 -> This Month Induction Training | EA3: ="This Month "&'Weekly Progress Report'!X74 -> This Month No.of Internal Training | EB3: ="This Month "&'Weekly Progress Report'!X75 -> This Month No.of Internal Audit | EC3: ="This Month "&'Weekly Progress Report'!X76 -> This Month No. of Toolbox Talks | ED3: ="This Month "&'Weekly Progress Report'!X77 -> This Month Safety Awards/Incentives | EE3: ="YTD "&'Weekly Progress Report'!X62 -> YTD Total Hours Worked | EF3: ="YTD "&'Weekly Progress Report'!X63 -> YTD Safe Hours Worked | EG3: ="YTD "&'Weekly Progress Report'!X64 -> YTD LTI | EH3: ="YTD "&'Weekly Progress Report'!X65 -> YTD MTC (Healed w/o Disability) | EI3: ="YTD "&'Weekly Progress Report'!X66 -> YTD MTC (Healed w/ Disability) | EJ3: ="YTD "&'Weekly Progress Report'!X67 -> YTD Near Miss | EK3: ="YTD "&'Weekly Progress Report'!X68 -> YTD First Aid Cases | EL3: ="YTD "&'Weekly Progress Report'!X69 -> YTD Fatality | EM3: ="YTD "&'Weekly Progress Report'!X70 -> YTD Fire Incident Cases | EN3: ="YTD "&'Weekly Progress Report'!X71 -> YTD Vehicle Incident | EO3: ="YTD "&'Weekly Progress Report'!X72 -> YTD Property Damages | EP3: ="YTD "&'Weekly Progress Report'!X73 -> YTD Induction Training | EQ3: ="YTD "&'Weekly Progress Report'!X74 -> YTD No.of Internal Training | ER3: ="YTD "&'Weekly Progress Report'!X75 -> YTD No.of Internal Audit | ES3: ="YTD "&'Weekly Progress Report'!X76 -> YTD No. of Toolbox Talks | ET3: ="YTD "&'Weekly Progress Report'!X77 -> YTD Safety Awards/Incentives | EU3: ="Cum "&'Weekly Progress Report'!X62 -> Cum Total Hours Worked | EV3: ="Cum "&'Weekly Progress Report'!X63 -> Cum Safe Hours Worked | EW3: ="Cum "&'Weekly Progress Report'!X64 -> Cum LTI | EX3: ="Cum "&'Weekly Progress Report'!X65 -> Cum MTC (Healed w/o Disability) | EY3: ="Cum "&'Weekly Progress Report'!X66 -> Cum MTC (Healed w/ Disability) | EZ3: ="Cum "&'Weekly Progress Report'!X67 -> Cum Near Miss | FA3: ="Cum "&'Weekly Progress Report'!X68 -> Cum First Aid Cases | FB3: ="Cum "&'Weekly Progress Report'!X69 -> Cum Fatality | FC3: ="Cum "&'Weekly Progress Report'!X70 -> Cum Fire Incident Cases | FD3: ="Cum "&'Weekly Progress Report'!X71 -> Cum Vehicle Incident | FE3: ="Cum "&'Weekly Progress Report'!X72 -> Cum Property Damages | FF3: ="Cum "&'Weekly Progress Report'!X73 -> Cum Induction Training | FG3: ="Cum "&'Weekly Progress Report'!X74 -> Cum No.of Internal Training | FH3: ="Cum "&'Weekly Progress Report'!X75 -> Cum No.of Internal Audit | FI3: ="Cum "&'Weekly Progress Report'!X76 -> Cum No. of Toolbox Talks | FJ3: ="Cum "&'Weekly Progress Report'!X77 -> Cum Safety Awards/Incentives | FK3: ='Weekly Progress Report'!A89 -> Total Act. | FL3: ='Weekly Progress Report'!B89 -> Not Started | FM3: ='Weekly Progress Report'!C89 -> In Progress | FN3: ='Weekly Progress Report'!D89 -> Completed | FO3: Critical Path Act.Last Week | FP3: Critical Path Act.This Week | FQ3: Failed start Last Week | FR3: Failed start This Week | FS3: ='Weekly Progress Report'!B97 -> 0 | FT3: ='Weekly Progress Report'!D97 -> 0 | FU3: ='Weekly Progress Report'!F97 -> 0 | FV3: ='Weekly Progress Report'!H97 -> 0 | FW3: ='Weekly Progress Report'!J97 -> 0 | FX3: ='Weekly Progress Report'!L97 -> 0 | FY3: ='Weekly Progress Report'!N97 -> 0 | FZ3: ='Weekly Progress Report'!O97 -> 0 | GA3: ='Weekly Progress Report'!P97 -> 0
A4: ='Weekly Progress Report'!AG1 -> 46308 | B4: ='Weekly Progress Report'!B3 -> Development of Infrastructure for phase 1 of the Logistics area at the 2nd Industrial City in Dammam | C4: ='Weekly Progress Report'!B4 -> DAM2-02-009 | D4: ='Weekly Progress Report'!B5 -> Shibh Aljazira Contracting Company | E4: ='Weekly Progress Report'!B6 -> Egis | F4: ='Weekly Progress Report'!E4 -> Construction | G4: ='Weekly Progress Report'!E5 -> Active | H4: ='Weekly Progress Report'!E6 -> Muhammad H Al-Essa | I4: ='Weekly Progress Report'!AA3 -> The project consists of the wet networks mainlines (Sewerage, Storm, Potable, Firefighting & TSE) including the force main line, in addition to the dry networks (Medium Voltage, Low Voltage, Street Lighting & Telecommunication) road crossings & main line connections, scope also included supply, install, testing & commissioning for the potable water pump station and the sewage lift station and implementation of guard rooms and applying all the road earth layers till the asphalt wearing coarse for the project scope area internal roads & finishing the landscape | J4: ='Weekly Progress Report'!H3 -> 45838 | K4: ='Weekly Progress Report'!H4 -> 45852 | L4: ='Weekly Progress Report'!H5 -> 45868 | M4: ='Weekly Progress Report'!H6 -> 46416 | N4: ='Weekly Progress Report'!$J$3 -> 45838 | O4: ='Weekly Progress Report'!$J$4 -> 45852 | P4: ='Weekly Progress Report'!$J$5 -> 45868 | Q4: ='Weekly Progress Report'!$J$6 -> 46416 | R4: ='Weekly Progress Report'!$L$3 -> 46416 | S4: ='Weekly Progress Report'!$L$4 -> 46416 | T4: ='Weekly Progress Report'!$L$5 -> 46425 | U4: ='Weekly Progress Report'!$O$3 -> 1.9890616e+08 | V4: ='Weekly Progress Report'!$O$4 -> 1.9890616e+08 | W4: ='Weekly Progress Report'!$O$5 -> 1.9890616e+08 | X4: ='Weekly Progress Report'!$O$6 -> 0 | Y4: ='Weekly Progress Report'!$S$3 -> 0 | Z4: ='Weekly Progress Report'!$S$4 -> 62889674 | AA4: ='Weekly Progress Report'!$S$5 -> -104500 | AB4: ='Weekly Progress Report'!$S$6 -> 81734062 | AC4: ='Weekly Progress Report'!$J$29 -> 0.66129318 | AD4: ='Weekly Progress Report'!$V$3 -> 0.66129318 | AE4: ='Weekly Progress Report'!$V$4 -> 0.52990858 | AF4: ='Weekly Progress Report'!$X$3 -> 0.65555122 | AG4: ='Weekly Progress Report'!$X$4 -> 0.5299 | AH4: ='Weekly Progress Report'!$Z$3 -> 0.93 | AI4: ='Weekly Progress Report'!$Z$5 -> 0.92857143 | AJ4: ='Weekly Progress Report'!$E$29 -> -12324623 | AK4: ='Weekly Progress Report'!$F$29 -> 2986147.8 | AL4: =AJ4/V4 -> -0.061961997 | AM4: =AK4/V4 -> 0.015012847 | AN4: ='Weekly Progress Report'!S29 -> 0.046783912 | AO4: ='Weekly Progress Report'!T29 -> 0.025579866 | AP4: ='Weekly Progress Report'!C67 -> 1774 | AQ4: ='Weekly Progress Report'!I67 -> 0 | AR4: ='Weekly Progress Report'!J67 -> 0 | AS4: ='Weekly Progress Report'!K67 -> 1774 | AT4: ='Weekly Progress Report'!C76 -> 153 | AU4: ='Weekly Progress Report'!J76 -> 5 | AV4: ='Weekly Progress Report'!K76 -> 149 | AW4: ='Weekly Progress Report'!C85 -> 48 | AX4: ='Weekly Progress Report'!D85 -> 48 | AY4: ='Weekly Progress Report'!E85 -> 42 | AZ4: ='Weekly Progress Report'!F85 -> 0 | BA4: ='Weekly Progress Report'!G85 -> 21 | BB4: ='Weekly Progress Report'!H85 -> 27 | BC4: ='Weekly Progress Report'!I85 -> 46335 | BD4: ='Weekly Progress Report'!N63 -> 4 | BE4: ='Weekly Progress Report'!O63 -> 3 | BF4: ='Weekly Progress Report'!P63 -> 1 | BG4: ='Weekly Progress Report'!Q63 -> 0 | BH4: ='Weekly Progress Report'!N64 -> 50 | BI4: ='Weekly Progress Report'!O64 -> 41 | BJ4: ='Weekly Progress Report'!P64 -> 9 | BK4: ='Weekly Progress Report'!Q64 -> 0 | BL4: ='Weekly Progress Report'!N65 -> 111 | BM4: ='Weekly Progress Report'!O65 -> 110 | BN4: ='Weekly Progress Report'!P65 -> 1 | BO4: ='Weekly Progress Report'!Q65 -> 0 | BP4: ='Weekly Progress Report'!N66 -> 4408 | BQ4: ='Weekly Progress Report'!O66 -> 4286 | BR4: ='Weekly Progress Report'!P66 -> 122 | BS4: ='Weekly Progress Report'!Q66 -> 0 | BT4: ='Weekly Progress Report'!O68 -> 45346 | BU4: ='Weekly Progress Report'!O69 -> 45346 | BV4: ='Weekly Progress Report'!O70 -> 45350 | BW4: ='Weekly Progress Report'!O71 -> 45350 | BX4: ='Weekly Progress Report'!O72 -> 45348 | BY4: ='Weekly Progress Report'!U68 -> 45361 | BZ4: ='Weekly Progress Report'!U69 -> 1 | CA4: ='Weekly Progress Report'!U70 -> 45361 | CB4: ='Weekly Progress Report'!U71 -> 0 | CC4: ='Weekly Progress Report'!U72 -> 1 | CD4: ='Weekly Progress Report'!N74 -> 7 | CE4: ='Weekly Progress Report'!N75 -> 0 | CF4: ='Weekly Progress Report'!N76 -> 0 | CG4: ='Weekly Progress Report'!N77 -> 0 | CH4: ='Weekly Progress Report'!N78 -> 0 | CI4: ='Weekly Progress Report'!N79 -> 0 | CJ4: ='Weekly Progress Report'!N80 -> 0.00052537337 | CK4: ='Weekly Progress Report'!R74 -> 62889674 | CL4: ='Weekly Progress Report'!R75 -> 0 | CM4: ='Weekly Progress Report'!R76 -> 0 | CN4: ='Weekly Progress Report'!R77 -> 46280 | CO4: ='Weekly Progress Report'!R78 -> 0 | CP4: ='Weekly Progress Report'!R79 -> 0 | CQ4: ='Weekly Progress Report'!R80 -> -104500 | CR4: ='Weekly Progress Report'!L84 -> 35 | CS4: ='Weekly Progress Report'!M84 -> 57 | CT4: ='Weekly Progress Report'!O84 -> 4 | CU4: ='Weekly Progress Report'!P84 -> 360 | CV4: ='Weekly Progress Report'!Q84 -> 483 | CW4: ='Weekly Progress Report'!T94 -> 150 | CX4: ='Weekly Progress Report'!U94 -> 326 | CY4: ='Weekly Progress Report'!Z62 -> 34740 | CZ4: ='Weekly Progress Report'!Z63 -> 34740 | DA4: ='Weekly Progress Report'!Z64 -> 0 | DB4: ='Weekly Progress Report'!Z65 -> 0 | DC4: ='Weekly Progress Report'!Z66 -> 0 | DD4: ='Weekly Progress Report'!Z67 -> 0 | DE4: ='Weekly Progress Report'!Z68 -> 0 | DF4: ='Weekly Progress Report'!Z69 -> 0 | DG4: ='Weekly Progress Report'!Z70 -> 0 | DH4: ='Weekly Progress Report'!Z71 -> 0 | DI4: ='Weekly Progress Report'!Z72 -> 0 | DJ4: ='Weekly Progress Report'!Z73 -> 33 | DK4: ='Weekly Progress Report'!Z74 -> 0 | DL4: ='Weekly Progress Report'!Z75 -> 0 | DM4: ='Weekly Progress Report'!Z76 -> 3(323) | DN4: ='Weekly Progress Report'!Z77 -> 0 | DO4: ='Weekly Progress Report'!AB62 -> 69480 | DP4: ='Weekly Progress Report'!AB63 -> 69480 | DQ4: ='Weekly Progress Report'!AB64 -> 0 | DR4: ='Weekly Progress Report'!AB65 -> 0 | DS4: ='Weekly Progress Report'!AB66 -> 0 | DT4: ='Weekly Progress Report'!AB67 -> 0 | DU4: ='Weekly Progress Report'!AB68 -> 0 | DV4: ='Weekly Progress Report'!AB69 -> 0 | DW4: ='Weekly Progress Report'!AB70 -> 0 | DX4: ='Weekly Progress Report'!AB71 -> 0 | DY4: ='Weekly Progress Report'!AB72 -> 0 | DZ4: ='Weekly Progress Report'!AB73 -> 62 | EA4: ='Weekly Progress Report'!AB74 -> 2 (9) | EB4: ='Weekly Progress Report'!AB75 -> 1 | EC4: ='Weekly Progress Report'!AB76 -> 3(648) | ED4: ='Weekly Progress Report'!AB77 -> 0 | EE4: ='Weekly Progress Report'!AC62 -> 774924 | EF4: ='Weekly Progress Report'!AC63 -> 774924 | EG4: ='Weekly Progress Report'!AC64 -> 0 | EH4: ='Weekly Progress Report'!AC65 -> 0 | EI4: ='Weekly Progress Report'!AC66 -> 0 | EJ4: ='Weekly Progress Report'!AC67 -> 0 | EK4: ='Weekly Progress Report'!AC68 -> 0 | EL4: ='Weekly Progress Report'!AC69 -> 0 | EM4: ='Weekly Progress Report'!AC70 -> 0 | EN4: ='Weekly Progress Report'!AC71 -> 0 | EO4: ='Weekly Progress Report'!AC72 -> 0 | EP4: ='Weekly Progress Report'!AC73 -> 114(564) | EQ4: ='Weekly Progress Report'!AC74 -> 5(23) | ER4: ='Weekly Progress Report'!AC75 -> 4 | ES4: ='Weekly Progress Report'!AC76 -> (43(3442) | ET4: ='Weekly Progress Report'!AC77 -> 1 | EU4: ='Weekly Progress Report'!AD62 -> 839982 | EV4: ='Weekly Progress Report'!AD63 -> 839982 | EW4: ='Weekly Progress Report'!AD64 -> 0 | EX4: ='Weekly Progress Report'!AD65 -> 0 | EY4: ='Weekly Progress Report'!AD66 -> 0 | EZ4: ='Weekly Progress Report'!AD67 -> 0 | FA4: ='Weekly Progress Report'!AD68 -> 0 | FB4: ='Weekly Progress Report'!AD69 -> 0 | FC4: ='Weekly Progress Report'!AD70 -> 0 | FD4: ='Weekly Progress Report'!AD71 -> 0 | FE4: ='Weekly Progress Report'!AD72 -> 0 | FF4: ='Weekly Progress Report'!AD73 -> 147(888) | FG4: ='Weekly Progress Report'!AD74 -> 13(98) | FH4: ='Weekly Progress Report'!AD75 -> 4 | FI4: ='Weekly Progress Report'!AD76 -> 56(8671) | FJ4: ='Weekly Progress Report'!AD77 -> 2 | FK4: ='Weekly Progress Report'!A90 -> 4851 | FL4: ='Weekly Progress Report'!B90 -> 2124 | FM4: ='Weekly Progress Report'!C90 -> 388 | FN4: ='Weekly Progress Report'!D90 -> 2339 | FO4: ='Weekly Progress Report'!A94 -> 45 | FP4: ='Weekly Progress Report'!B94 -> 45 | FQ4: ='Weekly Progress Report'!H94 -> 1039 | FR4: ='Weekly Progress Report'!I94 -> 993 | FS4: ='Weekly Progress Report'!B102 -> 0 | FT4: ='Weekly Progress Report'!D102 -> 0 | FU4: ='Weekly Progress Report'!F102 -> 0 | FV4: ='Weekly Progress Report'!H102 -> 0 | FW4: ='Weekly Progress Report'!J102 -> 0 | FX4: ='Weekly Progress Report'!L102 -> 0 | FY4: ='Weekly Progress Report'!N102 -> 0 | FZ4: ='Weekly Progress Report'!O102 -> 0 | GA4: ='Weekly Progress Report'!P102 -> 0

Sheet Weekly Progress Report
A1: MODON - Weekly Progress Report - Construction Projects | AF1: Data Date | AG1: ='General Information'!L1 -> 46308
A2: Contract General Information | G2: Key Dates | M2: Cost Summary (SR) | U2: Performance Summary | AA2: Project Scope
A3: Project Name | B3: ='General Information'!C3 -> Development of Infrastructure for phase 1 of the Logistics area at the 2nd Industrial City in Dammam | G3: Contract Award | H3: ='General Information'!C12 -> 45838 | I3: Contract Award (Hijri) | J3: ='General Information'!C16 -> 45838 | K3: Revised Completion | L3: ='General Information'!C20 -> 46416 | M3: Original Contract Value | O3: ='Invoice Log'!E3 -> 1.9890616e+08 | Q3: O&M Value (if any) | S3: ='Invoice Log'!I3 -> 0 | T3: EAC | U3: Plan Value | V3: =K29 -> 0.66129318 | W3: Phys. Plan Value | X3: =W29 -> 0.65555122 | Y3: Quality Score | Z3: =Quality!AC10 -> 0.93 | AA3: =+Progress!B1 -> The project consists of the wet networks mainlines (Sewerage, Storm, Potable, Firefighting & TSE) including the force main line, in addition to the dry networks (Medium Voltage, Low Voltage, Street Lighting & Telecommunication) road crossings & main line connections, scope also included supply, install, testing & commissioning for the potable water pump station and the sewage lift station and implementation of guard rooms and applying all the road earth layers till the asphalt wearing coarse for the project scope area internal roads & finishing the landscape
A4: Project ID | B4: ='General Information'!C4 -> DAM2-02-009 | D4: Stage | E4: ='General Information'!C7 -> Construction | G4: Contract Sign | H4: ='General Information'!C13 -> 45852 | I4: Contract Sign (Hijri) | J4: ='General Information'!C17 -> 45852 | K4: Committed Completion | L4: ='General Information'!C21 -> 46416 | M4: Revised Contract Value | O4: ='Invoice Log'!E4 -> 1.9890616e+08 | P4: EAC | Q4: Submitted Invoices (Gross Value) | S4: ='Invoice Log'!I5 -> 62889674 | U4: Earn Value | V4: =L29 -> 0.52990858 | W4: Phys. Earn Value | X4: =X29 -> 0.5299 | Z4: =REPT("¢",IF(INT(+Z3*10)>5,5,INT(+Z3*10)))&REPT("£",IF(INT(+Z3*10)>5,0,5-INT(+Z3*10)))&CHAR(10)&REPT("¢",+IF(INT(+Z3*10)>5,-5+INT(+Z3*10),0))&REPT("£",IF(INT(+Z3*10)>5,10-INT(+Z3*10),5)) -> ¢¢¢¢¢ ¢¢¢¢£
A5: Contractor | B5: ='General Information'!C5 -> Shibh Aljazira Contracting Company | D5: Status | E5: ='General Information'!C8 -> Active | G5: Site Handover | H5: ='General Information'!C14 -> 45868 | I5: Site Handover (Hijri) | J5: ='General Information'!C18 -> 45868 | K5: Forecast Completion | L5: ='General Information'!C22 -> 46425 | M5: Estimate At Completion Value | O5: ='Invoice Log'!E5 -> 1.9890616e+08 | P5: =+#REF!+#REF!+O5 -> #REF! | Q5: Penalities | S5: ='Invoice Log'!I6 -> -104500 | U5: Variance | V5: =V4-V3 -> -0.1313846 | W5: Variance | X5: =Y29 -> -0.12565122 | Y5: Safety Score | Z5: ='HSE-Stat'!J23 -> 0.92857143
A6: Consultant | B6: ='General Information'!C6 -> Egis | D6: Modon PM | E6: ='General Information'!C9 -> Muhammad H Al-Essa | G6: Original Completion | H6: ='General Information'!C15 -> 46416 | I6: Original Completion (Hijri) | J6: ='General Information'!C19 -> 46416 | K6: Variance | L6: ='General Information'!C23 -> -9 | M6: Potential Changes | O6: =O4-O5 -> 0 | Q6: FIR Value (Todate) | S6: ='FIR Summary'!I3 -> 81734062 | U6: FIR % | V6: =S6/O4 -> 0.41091769 | W6: Invoiced % | X6: =S4/O4 -> 0.3161776 | Z6: =REPT("¢",IF(INT(+Z5*10)>5,5,INT(+Z5*10)))&REPT("£",IF(INT(+Z5*10)>5,0,5-INT(+Z5*10)))&CHAR(10)&REPT("¢",+IF(INT(+Z5*10)>5,-5+INT(+Z5*10),0))&REPT("£",IF(INT(+Z5*10)>5,10-INT(+Z5*10),5)) -> ¢¢¢¢¢ ¢¢¢¢£
A8: Progress Overview
A9: Earned Value Progress (SAR) | O9: Physical Progress (Effort) | AA9: Earned Value Progress (%)
A10: WBS | C10: BOQ Value (SAR) | D10: % Wt. | E10: Weekly (SAR) | G10: To Date (SAR) | O10: Budgeted | P10: % Wt. | Q10: Weekly Physical Progress | U10: To Date Physical Progress
E11: Planned | F11: Earned | G11: Original Plan | H11: Revised Planned | I11: Earned | J11: Original Plan % | K11: Revised Planned % | L11: Earned % | M11: Variance | N11: SPI | O11: (Manhours) | Q11: Planned | R11: Earned | S11: Plan % | T11: Earned % | U11: Planned | V11: Earned | W11: Plan % | X11: Earned % | Y11: Variance | Z11: SPI
A12: =+Progress!A7 -> Demolishing & Site Clearing | C12: =+Progress!C7 -> 457401.18 | D12: =IF(ISBLANK(C12),"",C12/$C$29) -> 0.0022995827 | E12: =+Progress!E7 -> 0 | F12: =+Progress!F7 -> 0 | G12: =+Progress!G7 -> 457401.18 | H12: =+Progress!H7 -> 457401.18 | I12: =+Progress!I7 -> 457401.18 | J12: =IFERROR(IF(ISBLANK(G12),"",G12/C12),0) -> 1 | K12: =IFERROR(IF(ISBLANK(H12),"",H12/C12),0) -> 1 | L12: =IFERROR(IF(ISBLANK(I12),"",I12/C12),0) -> 1 | M12: =IFERROR(L12-K12,"") -> 0 | N12: =IFERROR(L12/K12,"") -> 1 | O12: =+Progress!K7 -> 3437.41 | P12: =IF(ISBLANK(O12),"",O12/$O$29) -> 0.0037353813 | Q12: =+Progress!M7 -> 0 | R12: =+Progress!N7 -> 0 | S12: =IFERROR(IF(ISBLANK(Q12),"",Q12/O12),0) -> 0 | T12: =IFERROR(IF(ISBLANK(R12),"",R12/O12),0) -> 0 | U12: =+Progress!O7 -> 3437.41 | V12: =+Progress!P7 -> 3262.7443 | W12: =IFERROR(IF(ISBLANK(U12),"",U12/O12),0) -> 1 | X12: =IFERROR(IF(ISBLANK(V12),"",V12/O12),0) -> 0.94918684 | Y12: =IFERROR(X12-W12,"") -> -0.050813164 | Z12: =IFERROR(X12/W12,"") -> 0.94918684
A13: =+Progress!A8 -> Earthworks & Site Grading | C13: =+Progress!C8 -> 31040592 | D13: =IF(ISBLANK(C13),"",C13/$C$29) -> 0.15605646 | E13: =+Progress!E8 -> 0 | F13: =+Progress!F8 -> 0 | G13: =+Progress!G8 -> 31040592 | H13: =+Progress!H8 -> 31040592 | I13: =+Progress!I8 -> 29924053 | J13: =IFERROR(IF(ISBLANK(G13),"",G13/C13),0) -> 1 | K13: =IFERROR(IF(ISBLANK(H13),"",H13/C13),0) -> 1 | L13: =IFERROR(IF(ISBLANK(I13),"",I13/C13),0) -> 0.96402973 | M13: =IFERROR(L13-K13,"") -> -0.035970271 | N13: =IFERROR(L13/K13,"") -> 0.96402973 | O13: =+Progress!K8 -> 22808.8 | P13: =IF(ISBLANK(O13),"",O13/$O$29) -> 0.024785977 | Q13: =+Progress!M8 -> 0 | R13: =+Progress!N8 -> 0 | S13: =IFERROR(IF(ISBLANK(Q13),"",Q13/O13),0) -> 0 | T13: =IFERROR(IF(ISBLANK(R13),"",R13/O13),0) -> 0 | U13: =+Progress!O8 -> 22808.8 | V13: =+Progress!P8 -> 20830.332 | W13: =IFERROR(IF(ISBLANK(U13),"",U13/O13),0) -> 1 | X13: =IFERROR(IF(ISBLANK(V13),"",V13/O13),0) -> 0.91325858 | Y13: =IFERROR(X13-W13,"") -> -0.086741422 | Z13: =IFERROR(X13/W13,"") -> 0.91325858
A14: =+Progress!A9 -> Sewerage Network | C14: =+Progress!C9 -> 5111121.8 | D14: =IF(ISBLANK(C14),"",C14/$C$29) -> 0.025696146 | E14: =+Progress!E9 -> 91525.9 | F14: =+Progress!F9 -> 372237.6 | G14: =+Progress!G9 -> 5069014.3 | H14: =+Progress!H9 -> 5069014.3 | I14: =+Progress!I9 -> 4562022 | J14: =IFERROR(IF(ISBLANK(G14),"",G14/C14),0) -> 0.99176159 | K14: =IFERROR(IF(ISBLANK(H14),"",H14/C14),0) -> 0.99176159 | L14: =IFERROR(IF(ISBLANK(I14),"",I14/C14),0) -> 0.89256766 | M14: =IFERROR(L14-K14,"") -> -0.09919393 | N14: =IFERROR(L14/K14,"") -> 0.89998208 | O14: =+Progress!K9 -> 74260.44 | P14: =IF(ISBLANK(O14),"",O14/$O$29) -> 0.080697694 | Q14: =+Progress!M9 -> 1570.09 | R14: =+Progress!N9 -> 6695.54 | S14: =IFERROR(IF(ISBLANK(Q14),"",Q14/O14),0) -> 0.02114302 | T14: =IFERROR(IF(ISBLANK(R14),"",R14/O14),0) -> 0.090162945 | U14: =+Progress!O9 -> 62840.48 | V14: =+Progress!P9 -> 58190.25 | W14: =IFERROR(IF(ISBLANK(U14),"",U14/O14),0) -> 0.84621745 | X14: =IFERROR(IF(ISBLANK(V14),"",V14/O14),0) -> 0.78359689 | Y14: =IFERROR(X14-W14,"") -> -0.062620553 | Z14: =IFERROR(X14/W14,"") -> 0.92599945
A15: =+Progress!A14 -> Storm Water Network | C15: =+Progress!C14 -> 21808728 | D15: =IF(ISBLANK(C15),"",C15/$C$29) -> 0.1096433 | E15: =+Progress!E14 -> 474784.2 | F15: =+Progress!F14 -> 313708.57 | G15: =+Progress!G14 -> 20519480 | H15: =+Progress!H14 -> 20519480 | I15: =+Progress!I14 -> 18392420 | J15: =IFERROR(IF(ISBLANK(G15),"",G15/C15),0) -> 0.94088382 | K15: =IFERROR(IF(ISBLANK(H15),"",H15/C15),0) -> 0.94088382 | L15: =IFERROR(IF(ISBLANK(I15),"",I15/C15),0) -> 0.84335134 | M15: =IFERROR(L15-K15,"") -> -0.097532475 | N15: =IFERROR(L15/K15,"") -> 0.89633951 | O15: =+Progress!K14 -> 143781.21 | P15: =IF(ISBLANK(O15),"",O15/$O$29) -> 0.15624486 | Q15: =+Progress!M14 -> 2114.92 | R15: =+Progress!N14 -> 596.69 | S15: =IFERROR(IF(ISBLANK(Q15),"",Q15/O15),0) -> 0.014709293 | T15: =IFERROR(IF(ISBLANK(R15),"",R15/O15),0) -> 0.0041499859 | U15: =+Progress!O14 -> 124384.01 | V15: =+Progress!P14 -> 107524.87 | W15: =IFERROR(IF(ISBLANK(U15),"",U15/O15),0) -> 0.86509225 | X15: =IFERROR(IF(ISBLANK(V15),"",V15/O15),0) -> 0.74783674 | Y15: =IFERROR(X15-W15,"") -> -0.1172555 | Z15: =IFERROR(X15/W15,"") -> 0.86445896
A16: =+Progress!A19 -> Potable Water Network | C16: =+Progress!C19 -> 1954044.4 | D16: =IF(ISBLANK(C16),"",C16/$C$29) -> 0.0098239508 | E16: =+Progress!E19 -> -108928.72 | F16: =+Progress!F19 -> 235159.28 | G16: =+Progress!G19 -> 1581432.3 | H16: =+Progress!H19 -> 1581432.3 | I16: =+Progress!I19 -> 1060337.7 | J16: =IFERROR(IF(ISBLANK(G16),"",G16/C16),0) -> 0.80931238 | K16: =IFERROR(IF(ISBLANK(H16),"",H16/C16),0) -> 0.80931238 | L16: =IFERROR(IF(ISBLANK(I16),"",I16/C16),0) -> 0.54263749 | M16: =IFERROR(L16-K16,"") -> -0.2666749 | N16: =IFERROR(L16/K16,"") -> 0.67049201 | O16: =+Progress!K19 -> 57934.51 | P16: =IF(ISBLANK(O16),"",O16/$O$29) -> 0.062956554 | Q16: =+Progress!M19 -> 395.83 | R16: =+Progress!N19 -> 4708.49 | S16: =IFERROR(IF(ISBLANK(Q16),"",Q16/O16),0) -> 0.0068323699 | T16: =IFERROR(IF(ISBLANK(R16),"",R16/O16),0) -> 0.08127263 | U16: =+Progress!O19 -> 42976.16 | V16: =+Progress!P19 -> 32815.297 | W16: =IFERROR(IF(ISBLANK(U16),"",U16/O16),0) -> 0.74180588 | X16: =IFERROR(IF(ISBLANK(V16),"",V16/O16),0) -> 0.56642055 | Y16: =IFERROR(X16-W16,"") -> -0.17538533 | Z16: =IFERROR(X16/W16,"") -> 0.76356977
A17: =+Progress!A24 -> Fire Fighting Network | C17: =+Progress!C24 -> 4678456.7 | D17: =IF(ISBLANK(C17),"",C17/$C$29) -> 0.023520924 | E17: =+Progress!E24 -> 158799.37 | F17: =+Progress!F24 -> 126086.86 | G17: =+Progress!G24 -> 3932068.3 | H17: =+Progress!H24 -> 3932068.3 | I17: =+Progress!I24 -> 3069245.6 | J17: =IFERROR(IF(ISBLANK(G17),"",G17/C17),0) -> 0.84046268 | K17: =IFERROR(IF(ISBLANK(I17),"",I17/C17),0) -> 0.65603805 | L17: =IFERROR(IF(ISBLANK(I17),"",I17/C17),0) -> 0.65603805 | M17: =IFERROR(L17-K17,"") -> 0 | N17: =IFERROR(L17/K17,"") -> 1 | O17: =+Progress!K24 -> 63346.29 | P17: =IF(ISBLANK(O17),"",O17/$O$29) -> 0.068837453 | Q17: =+Progress!M24 -> 1285.84 | R17: =+Progress!N24 -> 2098.87 | S17: =IFERROR(IF(ISBLANK(Q17),"",Q17/O17),0) -> 0.020298584 | T17: =IFERROR(IF(ISBLANK(R17),"",R17/O17),0) -> 0.033133274 | U17: =+Progress!O24 -> 45892.7 | V17: =+Progress!P24 -> 33548.354 | W17: =IFERROR(IF(ISBLANK(U17),"",U17/O17),0) -> 0.72447337 | X17: =IFERROR(IF(ISBLANK(V17),"",V17/O17),0) -> 0.5296025 | Y17: =IFERROR(X17-W17,"") -> -0.19487086 | Z17: =IFERROR(X17/W17,"") -> 0.73101722
A18: =+Progress!A29 -> TSE Network | C18: =+Progress!C29 -> 2995733.6 | D18: =IF(ISBLANK(C18),"",C18/$C$29) -> 0.01506104 | E18: =+Progress!E29 -> 23431.93 | F18: =+Progress!F29 -> 176793.55 | G18: =+Progress!G29 -> 2882625.1 | H18: =+Progress!H29 -> 2882625.1 | I18: =+Progress!I29 -> 686841.65 | J18: =IFERROR(IF(ISBLANK(G18),"",G18/C18),0) -> 0.96224346 | K18: =IFERROR(IF(ISBLANK(I18),"",I18/C18),0) -> 0.22927327 | L18: =IFERROR(IF(ISBLANK(I18),"",I18/C18),0) -> 0.22927327 | M18: =IFERROR(L18-K18,"") -> 0 | N18: =IFERROR(L18/K18,"") -> 1 | O18: =+Progress!K29 -> 48137.98 | P18: =IF(ISBLANK(O18),"",O18/$O$29) -> 0.052310813 | Q18: =+Progress!M29 -> 2888.52 | R18: =+Progress!N29 -> 674.93 | S18: =IFERROR(IF(ISBLANK(Q18),"",Q18/O18),0) -> 0.060005011 | T18: =IFERROR(IF(ISBLANK(R18),"",R18/O18),0) -> 0.014020738 | U18: =+Progress!O29 -> 27650.45 | V18: =+Progress!P29 -> 20399.202 | W18: =IFERROR(IF(ISBLANK(U18),"",U18/O18),0) -> 0.57439988 | X18: =IFERROR(IF(ISBLANK(V18),"",V18/O18),0) -> 0.42376523 | Y18: =IFERROR(X18-W18,"") -> -0.15063465 | Z18: =IFERROR(X18/W18,"") -> 0.73775299
A19: =+Progress!A34 -> Potable Water Pump Station | C19: =+Progress!C34 -> 11076182 | D19: =IF(ISBLANK(C19),"",C19/$C$29) -> 0.055685463 | E19: =+Progress!E34 -> 2488126 | F19: =+Progress!F34 -> 0 | G19: =+Progress!G34 -> 6907518 | H19: =+Progress!H34 -> 6907518 | I19: =+Progress!I34 -> 1734353.2 | J19: =IFERROR(IF(ISBLANK(G19),"",G19/C19),0) -> 0.62363711 | K19: =IFERROR(IF(ISBLANK(H19),"",H19/C19),0) -> 0.62363711 | L19: =IFERROR(IF(ISBLANK(I19),"",I19/C19),0) -> 0.15658403 | M19: =IFERROR(L19-K19,"") -> -0.46705308 | N19: =IFERROR(L19/K19,"") -> 0.25108196 | O19: =+Progress!K34 -> 71778.26 | P19: =IF(ISBLANK(O19),"",O19/$O$29) -> 0.078000347 | Q19: =+Progress!M34 -> 5654.7 | R19: =+Progress!N34 -> 1659.66 | S19: =IFERROR(IF(ISBLANK(Q19),"",Q19/O19),0) -> 0.078780121 | T19: =IFERROR(IF(ISBLANK(R19),"",R19/O19),0) -> 0.023122043 | U19: =+Progress!O34 -> 51296.18 | V19: =+Progress!P34 -> 46334.005 | W19: =IFERROR(IF(ISBLANK(U19),"",U19/O19),0) -> 0.71464786 | X19: =IFERROR(IF(ISBLANK(V19),"",V19/O19),0) -> 0.64551586 | Y19: =IFERROR(X19-W19,"") -> -0.069132006 | Z19: =IFERROR(X19/W19,"") -> 0.90326424
A20: =+Progress!A39 -> Sewerage Lift Station | C20: =+Progress!C39 -> 4985124.7 | D20: =IF(ISBLANK(C20),"",C20/$C$29) -> 0.025062696 | E20: =+Progress!E39 -> 114430.52 | F20: =+Progress!F39 -> 20947.81 | G20: =+Progress!G39 -> 391336.31 | H20: =+Progress!H39 -> 391336.31 | I20: =+Progress!I39 -> 57625.13 | J20: =IFERROR(IF(ISBLANK(G20),"",G20/C20),0) -> 0.078500807 | K20: =IFERROR(IF(ISBLANK(H20),"",H20/C20),0) -> 0.078500807 | L20: =IFERROR(IF(ISBLANK(I20),"",I20/C20),0) -> 0.011559416 | M20: =IFERROR(L20-K20,"") -> -0.066941391 | N20: =IFERROR(L20/K20,"") -> 0.14725219 | O20: =+Progress!K39 -> 70758.97 | P20: =IF(ISBLANK(O20),"",O20/$O$29) -> 0.0768927 | Q20: =+Progress!M39 -> 10661.48 | R20: =+Progress!N39 -> 3197.43 | S20: =IFERROR(IF(ISBLANK(Q20),"",Q20/O20),0) -> 0.15067319 | T20: =IFERROR(IF(ISBLANK(R20),"",R20/O20),0) -> 0.045187628 | U20: =+Progress!O39 -> 54654.05 | V20: =+Progress!P39 -> 46722.801 | W20: =IFERROR(IF(ISBLANK(U20),"",U20/O20),0) -> 0.77239748 | X20: =IFERROR(IF(ISBLANK(V20),"",V20/O20),0) -> 0.66030923 | Y20: =IFERROR(X20-W20,"") -> -0.11208824 | Z20: =IFERROR(X20/W20,"") -> 0.85488269
A21: =+Progress!A44 -> Medium Voltage Network | C21: =+Progress!C44 -> 5452229.2 | D21: =IF(ISBLANK(C21),"",C21/$C$29) -> 0.027411062 | E21: =+Progress!E44 -> -19975.48 | F21: =+Progress!F44 -> 316737.65 | G21: =+Progress!G44 -> 4182436.2 | H21: =+Progress!H44 -> 4182436.2 | I21: =+Progress!I44 -> 1488735.8 | J21: =IFERROR(IF(ISBLANK(G21),"",G21/C21),0) -> 0.76710571 | K21: =IFERROR(IF(ISBLANK(I21),"",I21/C21),0) -> 0.27305084 | L21: =IFERROR(IF(ISBLANK(I21),"",I21/C21),0) -> 0.27305084 | M21: =IFERROR(L21-K21,"") -> 0 | N21: =IFERROR(L21/K21,"") -> 1 | O21: =+Progress!K44 -> 34290.88 | P21: =IF(ISBLANK(O21),"",O21/$O$29) -> 0.037263379 | Q21: =+Progress!M44 -> 2898.34 | R21: =+Progress!N44 -> 1041.47 | S21: =IFERROR(IF(ISBLANK(Q21),"",Q21/O21),0) -> 0.084522182 | T21: =IFERROR(IF(ISBLANK(R21),"",R21/O21),0) -> 0.030371632 | U21: =+Progress!O44 -> 20010.78 | V21: =+Progress!P44 -> 13231.608 | W21: =IFERROR(IF(ISBLANK(U21),"",U21/O21),0) -> 0.58355983 | X21: =IFERROR(IF(ISBLANK(V21),"",V21/O21),0) -> 0.38586375 | Y21: =IFERROR(X21-W21,"") -> -0.19769608 | Z21: =IFERROR(X21/W21,"") -> 0.66122398
A22: =+Progress!A49 -> Low Voltage Network | C22: =+Progress!C49 -> 1876943.1 | D22: =IF(ISBLANK(C22),"",C22/$C$29) -> 0.0094363247 | E22: =+Progress!E49 -> 633182 | F22: =+Progress!F49 -> 0 | G22: =+Progress!G49 -> 1071552.8 | H22: =+Progress!H49 -> 1071552.8 | I22: =+Progress!I49 -> 16626.84 | J22: =IFERROR(IF(ISBLANK(G22),"",G22/C22),0) -> 0.57090318 | K22: =IFERROR(IF(ISBLANK(I22),"",I22/C22),0) -> 0.0088584677 | L22: =IFERROR(IF(ISBLANK(I22),"",I22/C22),0) -> 0.0088584677 | M22: =IFERROR(L22-K22,"") -> 0 | N22: =IFERROR(L22/K22,"") -> 1 | O22: =+Progress!K49 -> 31587.58 | P22: =IF(ISBLANK(O22),"",O22/$O$29) -> 0.034325744 | Q22: =+Progress!M49 -> 3135.04 | R22: =+Progress!N49 -> 0 | S22: =IFERROR(IF(ISBLANK(Q22),"",Q22/O22),0) -> 0.099249135 | T22: =IFERROR(IF(ISBLANK(R22),"",R22/O22),0) -> 0 | U22: =+Progress!O49 -> 15201.3 | V22: =+Progress!P49 -> 6687.5528 | W22: =IFERROR(IF(ISBLANK(U22),"",U22/O22),0) -> 0.48124294 | X22: =IFERROR(IF(ISBLANK(V22),"",V22/O22),0) -> 0.21171463 | Y22: =IFERROR(X22-W22,"") -> -0.26952831 | Z22: =IFERROR(X22/W22,"") -> 0.43993295
A23: =+Progress!A54 -> Street Lighting Network | C23: =+Progress!C54 -> 8486130.6 | D23: =IF(ISBLANK(C23),"",C23/$C$29) -> 0.04266399 | E23: =+Progress!E54 -> -164973.26 | F23: =+Progress!F54 -> 108917.63 | G23: =+Progress!G54 -> 3384258.7 | H23: =+Progress!H54 -> 3384258.7 | I23: =+Progress!I54 -> 1516284.2 | J23: =IFERROR(IF(ISBLANK(G23),"",G23/C23),0) -> 0.3987988 | K23: =IFERROR(IF(ISBLANK(I23),"",I23/C23),0) -> 0.17867792 | L23: =IFERROR(IF(ISBLANK(I23),"",I23/C23),0) -> 0.17867792 | M23: =IFERROR(L23-K23,"") -> 0 | N23: =IFERROR(L23/K23,"") -> 1 | O23: =+Progress!K54 -> 76760.06 | P23: =IF(ISBLANK(O23),"",O23/$O$29) -> 0.083413993 | Q23: =+Progress!M54 -> 255.03 | R23: =+Progress!N54 -> 894.29 | S23: =IFERROR(IF(ISBLANK(Q23),"",Q23/O23),0) -> 0.003322431 | T23: =IFERROR(IF(ISBLANK(R23),"",R23/O23),0) -> 0.01165046 | U23: =+Progress!O54 -> 33151.6 | V23: =+Progress!P54 -> 19627.304 | W23: =IFERROR(IF(ISBLANK(U23),"",U23/O23),0) -> 0.43188606 | X23: =IFERROR(IF(ISBLANK(V23),"",V23/O23),0) -> 0.25569683 | Y23: =IFERROR(X23-W23,"") -> -0.17618923 | Z23: =IFERROR(X23/W23,"") -> 0.59204697
A24: =+Progress!A59 -> Telecommunication Network | C24: =+Progress!C59 -> 4454965.6 | D24: =IF(ISBLANK(C24),"",C24/$C$29) -> 0.022397323 | E24: =+Progress!E59 -> 826182.37 | F24: =+Progress!F59 -> 0 | G24: =+Progress!G59 -> 2503270.3 | H24: =+Progress!H59 -> 2503270.3 | I24: =+Progress!I59 -> 965354.72 | J24: =IFERROR(IF(ISBLANK(G24),"",G24/C24),0) -> 0.56190565 | K24: =IFERROR(IF(ISBLANK(H24),"",H24/C24),0) -> 0.56190565 | L24: =IFERROR(IF(ISBLANK(I24),"",I24/C24),0) -> 0.21669185 | M24: =IFERROR(L24-K24,"") -> -0.3452138 | N24: =IFERROR(L24/K24,"") -> 0.38563742 | O24: =+Progress!K59 -> 62092.94 | P24: =IF(ISBLANK(O24),"",O24/$O$29) -> 0.067475456 | Q24: =+Progress!M59 -> 6377.63 | R24: =+Progress!N59 -> 0 | S24: =IFERROR(IF(ISBLANK(Q24),"",Q24/O24),0) -> 0.10271103 | T24: =IFERROR(IF(ISBLANK(R24),"",R24/O24),0) -> 0 | U24: =+Progress!O59 -> 29835.19 | V24: =+Progress!P59 -> 14676.393 | W24: =IFERROR(IF(ISBLANK(U24),"",U24/O24),0) -> 0.48049247 | X24: =IFERROR(IF(ISBLANK(V24),"",V24/O24),0) -> 0.23636171 | Y24: =IFERROR(X24-W24,"") -> -0.24413076 | Z24: =IFERROR(X24/W24,"") -> 0.49191553
A25: =+Progress!A64 -> Road Works | C25: =+Progress!C64 -> 79068381 | D25: =IF(ISBLANK(C25),"",C25/$C$29) -> 0.39751599 | E25: =+Progress!E64 -> -16425620 | F25: =+Progress!F64 -> 1307961.9 | G25: =+Progress!G64 -> 47364220 | H25: =+Progress!H64 -> 47364220 | I25: =+Progress!I64 -> 41322963 | J25: =IFERROR(IF(ISBLANK(G25),"",G25/C25),0) -> 0.59902857 | K25: =IFERROR(IF(ISBLANK(H25),"",H25/C25),0) -> 0.59902857 | L25: =IFERROR(IF(ISBLANK(I25),"",I25/C25),0) -> 0.5226231 | M25: =IFERROR(L25-K25,"") -> -0.076405469 | N25: =IFERROR(L25/K25,"") -> 0.87245104 | O25: =+Progress!K64 -> 80303.58 | P25: =IF(ISBLANK(O25),"",O25/$O$29) -> 0.087264683 | Q25: =+Progress!M64 -> -2143.45 | R25: =+Progress!N64 -> 313.66 | S25: =IFERROR(IF(ISBLANK(Q25),"",Q25/O25),0) -> -0.026691836 | T25: =IFERROR(IF(ISBLANK(R25),"",R25/O25),0) -> 0.003905928 | U25: =+Progress!O64 -> 36090.33 | V25: =+Progress!P64 -> 25913.579 | W25: =IFERROR(IF(ISBLANK(U25),"",U25/O25),0) -> 0.44942367 | X25: =IFERROR(IF(ISBLANK(V25),"",V25/O25),0) -> 0.32269519 | Y25: =IFERROR(X25-W25,"") -> -0.12672849 | Z25: =IFERROR(X25/W25,"") -> 0.71802001
A26: =+Progress!A68 -> Landscape | C26: =+Progress!C68 -> 14727630 | D26: =IF(ISBLANK(C26),"",C26/$C$29) -> 0.074043103 | E26: =+Progress!E68 -> -428497.66 | F26: =+Progress!F68 -> 0 | G26: =+Progress!G68 -> 142239.46 | H26: =+Progress!H68 -> 142239.46 | I26: =+Progress!I68 -> 98475.6 | J26: =IFERROR(IF(ISBLANK(G26),"",G26/C26),0) -> 0.009658001 | K26: =IFERROR(IF(ISBLANK(H26),"",H26/C26),0) -> 0.009658001 | L26: =IFERROR(IF(ISBLANK(I26),"",I26/C26),0) -> 0.0066864528 | M26: =IFERROR(L26-K26,"") -> -0.0029715481 | N26: =IFERROR(L26/K26,"") -> 0.69232265 | O26: =+Progress!K68 -> 44855.31 | P26: =IF(ISBLANK(O26),"",O26/$O$29) -> 0.048743585 | Q26: =+Progress!M68 -> -522.4 | R26: =+Progress!N68 -> 570.97 | S26: =IFERROR(IF(ISBLANK(Q26),"",Q26/O26),0) -> -0.011646336 | T26: =IFERROR(IF(ISBLANK(R26),"",R26/O26),0) -> 0.012729151 | U26: =+Progress!O68 -> 6582.77 | V26: =+Progress!P68 -> 13439.1 | W26: =IFERROR(IF(ISBLANK(U26),"",U26/O26),0) -> 0.14675565 | X26: =IFERROR(IF(ISBLANK(V26),"",V26/O26),0) -> 0.29961001 | Y26: =IFERROR(X26-W26,"") -> 0.15285436 | Z26: =IFERROR(X26/W26,"") -> 2.0415569
A27: =+Progress!A72 -> Guard Rooms | C27: =+Progress!C72 -> 539598.47 | D27: =IF(ISBLANK(C27),"",C27/$C$29) -> 0.0027128293 | E27: =+Progress!E72 -> 12910.2 | F27: =+Progress!F72 -> 7596.95 | G27: =+Progress!G72 -> 105845.69 | H27: =+Progress!H72 -> 105845.69 | I27: =+Progress!I72 -> 49342.79 | J27: =IFERROR(IF(ISBLANK(G27),"",G27/C27),0) -> 0.19615639 | K27: =IFERROR(IF(ISBLANK(H27),"",H27/C27),0) -> 0.19615639 | L27: =IFERROR(IF(ISBLANK(I27),"",I27/C27),0) -> 0.091443532 | M27: =IFERROR(L27-K27,"") -> -0.10471286 | N27: =IFERROR(L27/K27,"") -> 0.46617666 | O27: =+Progress!K72 -> 34095.79 | P27: =IF(ISBLANK(O27),"",O27/$O$29) -> 0.037051378 | Q27: =+Progress!M72 -> 8480.39 | R27: =+Progress!N72 -> 1087.36 | S27: =IFERROR(IF(ISBLANK(Q27),"",Q27/O27),0) -> 0.2487225 | T27: =IFERROR(IF(ISBLANK(R27),"",R27/O27),0) -> 0.031891327 | U27: =+Progress!O72 -> 26445.7 | V27: =+Progress!P72 -> 24426.488 | W27: =IFERROR(IF(ISBLANK(U27),"",U27/O27),0) -> 0.77562948 | X27: =IFERROR(IF(ISBLANK(V27),"",V27/O27),0) -> 0.71640774 | Y27: =IFERROR(X27-W27,"") -> -0.059221741 | Z27: =IFERROR(X27/W27,"") -> 0.92364687
A28: =Progress!A76 -> Provisional Sum | C28: =Progress!C76 -> 192900.72 | D28: =IF(ISBLANK(C28),"",C28/$C$29) -> 0.00096980766 | E28: =Progress!E76 -> 0 | F28: =Progress!F76 -> 0 | G28: =Progress!G76 -> 0 | H28: =Progress!H76 -> 0 | I28: =Progress!I76 -> 0 | J28: =IFERROR(IF(ISBLANK(G28),"",G28/C28),0) -> 0 | K28: =IFERROR(IF(ISBLANK(I28),"",I28/C28),0) -> 0 | L28: =IFERROR(IF(ISBLANK(I28),"",I28/C28),0) -> 0 | M28: =IFERROR(L28-K28,"") -> 0 | N28: =IFERROR(L28/K28,"") | O28: =Progress!K76 -> 0 | P28: =IF(ISBLANK(O28),"",O28/$O$29) -> 0 | Q28: =Progress!M76 -> 0 | R28: =Progress!N76 -> 0 | S28: =IFERROR(IF(ISBLANK(Q28),"",Q28/O28),0) -> 0 | T28: =IFERROR(IF(ISBLANK(R28),"",R28/O28),0) -> 0 | U28: =Progress!O76 -> 0 | V28: =Progress!P76 -> 0 | W28: =IFERROR(IF(ISBLANK(U28),"",U28/O28),0) -> 0 | X28: =IFERROR(IF(ISBLANK(V28),"",V28/O28),0) -> 0 | Y28: =IFERROR(X28-W28,"") -> 0 | Z28: =IFERROR(X28/W28,"")
B29: Total | C29: =SUM(C12:C28) -> 1.9890616e+08 | D29: =SUM(D12:D28) -> 1 | E29: =SUM(E12:E28) -> -12324623 | F29: =SUM(F12:F28) -> 2986147.8 | G29: =SUM(G12:G28) -> 1.3153529e+08 | H29: =SUM(H12:H28) -> 1.3153529e+08 | I29: =SUM(I12:I28) -> 1.0540208e+08 | J29: =IFERROR(IF(ISBLANK(G29),"",G29/C29),0) -> 0.66129318 | K29: =IFERROR(IF(ISBLANK(H29),"",H29/C29),0) -> 0.66129318 | L29: =IFERROR(IF(ISBLANK(I29),"",I29/C29),0) -> 0.52990858 | M29: =+L29-K29 -> -0.1313846 | N29: =L29/K29 -> 0.80132171 | O29: =SUM(O12:O28) -> 920230.01 | P29: =SUM(P12:P28) -> 1 | Q29: =SUM(Q12:Q28) -> 43051.96 | R29: =SUM(R12:R28) -> 23539.36 | S29: =IFERROR(IF(ISBLANK(Q29),"",Q29/O29),0) -> 0.046783912 | T29: =IFERROR(IF(ISBLANK(R29),"",R29/O29),0) -> 0.025579866 | U29: =SUM(U12:U28) -> 603257.91 | V29: =SUM(V12:V28) -> 487629.88 | W29: =IFERROR(IF(ISBLANK(U29),"",U29/O29),0) -> 0.65555122 | X29: =IFERROR(IF(ISBLANK(V29),"",V29/O29),0) -> 0.5299 | Y29: =+X29-W29 -> -0.12565122 | Z29: =X29/W29 -> 0.80832737
AA30: Construction Milestones
AA31: Item No. | AB31: Milestones | AD31: Original (Baseline) | AE31: Latest Plan | AF31: Forecast | AG31: Status | AH31: Days Change
AA32: =+Milestones!A4 -> 1 | AB32: =+Milestones!B4 -> Award Date | AD32: =+Milestones!C4 -> 45838 | AE32: =+Milestones!D4 -> 45838 | AF32: =+Milestones!E4 -> 45838 | AG32: =+Milestones!F4 -> A | AH32: =+Milestones!G4 -> 0
AA33: =+Milestones!A5 -> 2 | AB33: =+Milestones!B5 -> Contract Sign Date | AD33: =+Milestones!C5 -> 45852 | AE33: =+Milestones!D5 -> 45852 | AF33: =+Milestones!E5 -> 45852 | AG33: =+Milestones!F5 -> A | AH33: =+Milestones!G5 -> 0
AA34: =+Milestones!A6 -> 3 | AB34: =+Milestones!B6 -> Site Handover Date | AD34: =+Milestones!C6 -> 45868 | AE34: =+Milestones!D6 -> 45868 | AF34: =+Milestones!E6 -> 45868 | AG34: =+Milestones!F6 -> A | AH34: =+Milestones!G6 -> 0
AA35: =+Milestones!A7 -> 4 | AB35: =+Milestones!B7 -> Complete Mobilization | AD35: =+Milestones!C7 -> 45899 | AE35: =+Milestones!D7 -> 45899 | AF35: =+Milestones!E7 -> 45899 | AG35: =+Milestones!F7 -> A | AH35: =+Milestones!G7 -> 0
AA36: =+Milestones!A10 -> 7 | AB36: =+Milestones!B10 -> Complete Earthworks | AD36: =+Milestones!C10 -> 46280 | AE36: =+Milestones!D10 -> 46280 | AF36: =+Milestones!E10 -> 46252 | AG36: =+Milestones!F10 -> F | AH36: =+Milestones!G10 -> 28
AA37: =+Milestones!A11 -> 8 | AB37: =+Milestones!B11 -> Complete all Wet Networks | AD37: =+Milestones!C11 -> 46348 | AE37: =+Milestones!D11 -> 46348 | AF37: =+Milestones!E11 -> 46366 | AG37: =+Milestones!F11 -> F | AH37: =+Milestones!G11 -> -18
AA38: =+Milestones!A12 -> 9 | AB38: =+Milestones!B12 -> Complete Electrical Works | AD38: =+Milestones!C12 -> 46350 | AE38: =+Milestones!D12 -> 46350 | AF38: =+Milestones!E12 -> 46373 | AG38: =+Milestones!F12 -> F | AH38: =+Milestones!G12 -> -23
AA39: =+Milestones!A13 -> 10 | AB39: =+Milestones!B13 -> Complete all Works including Testing & Commissioning, Cleanup, Closeout Documentation and Ready for Initial Handover | AD39: =+Milestones!C13 -> 46401 | AE39: =+Milestones!D13 -> 46401 | AF39: =+Milestones!E13 -> 46425 | AG39: =+Milestones!F13 -> F | AH39: =+Milestones!G13 -> -24
AA40: =+Milestones!A14 -> 11 | AB40: =+Milestones!B14 -> Complete Demobilization | AD40: =+Milestones!C14 -> 46412 | AE40: =+Milestones!D14 -> 46412 | AF40: =+Milestones!E14 -> 46435 | AG40: =+Milestones!F14 -> F | AH40: =+Milestones!G14 -> -23
AA41: =+Milestones!A15 -> 12 | AB41: =+Milestones!B15 -> Project Handover | AD41: =+Milestones!C15 -> 46416 | AE41: =+Milestones!D15 -> 46416 | AF41: =+Milestones!E15 -> 46440 | AG41: =+Milestones!F15 -> F | AH41: =+Milestones!G15 -> -24
A57: Performance overview
A58: Submittals Status | L58: Quality | W58: Safety
A59: Shop Drawings | L59: Quality Reports | W59: Safety Statistics | AE59: Proactive Vs Reactive Actions Taken
A60: Item Per WBS | C60: Total | D60: Total Submitted Drawings | I60: Remaining | J60: Pending | K60: Total Submittals | L60: Quality Reports | N60: Issued | O60: Closed | P60: Pending | Q60: Avg. Closing (Days) | R60: Pending | W60: Category | X60: Item | Z60: This Week | AB60: This Month | AC60: Year to Date | AD60: Cumulative
D61: A | E61: B | F61: C | G61: D | H61: Processed | R61: 0-10 Days | S61: 11-20 Days | T61: 21-30 Days | U61: 31-60 Days | V61: > 60 Days
A62: ='Quality-Stat'!A13 -> CVL | C62: =IF('Quality-Stat'!D13="","",'Quality-Stat'!D13) -> 1063 | D62: =IF('Quality-Stat'!E13="","",'Quality-Stat'!E13) -> 8 | E62: =IF('Quality-Stat'!F13="","",'Quality-Stat'!F13) -> 1055 | F62: =IF('Quality-Stat'!G13="","",'Quality-Stat'!G13) -> 0 | G62: =IF('Quality-Stat'!H13="","",'Quality-Stat'!H13) -> 0 | H62: =IF('Quality-Stat'!I13="","",'Quality-Stat'!I13) -> 1063 | I62: =IF('Quality-Stat'!J13="","",'Quality-Stat'!J13) -> 0 | J62: =IF('Quality-Stat'!K13="","",'Quality-Stat'!K13) -> 0 | K62: =IF('Quality-Stat'!L13="","",'Quality-Stat'!L13) -> 1063 | W62: General | X62: ='HSE-Stat'!B4 -> Total Hours Worked | Z62: ='HSE-Stat'!D4 -> 34740 | AB62: ='HSE-Stat'!E4 -> 69480 | AC62: ='HSE-Stat'!F4 -> 774924 | AD62: ='HSE-Stat'!G4 -> 839982 | AG62: Proactive | AH62: =+SUM(AD73:AD77) -> 6
A63: ='Quality-Stat'!A14 -> Mech | C63: =IF('Quality-Stat'!D14="","",'Quality-Stat'!D14) -> 212 | D63: =IF('Quality-Stat'!E14="","",'Quality-Stat'!E14) -> 0 | E63: =IF('Quality-Stat'!F14="","",'Quality-Stat'!F14) -> 212 | F63: =IF('Quality-Stat'!G14="","",'Quality-Stat'!G14) -> 0 | G63: =IF('Quality-Stat'!H14="","",'Quality-Stat'!H14) -> 0 | H63: =IF('Quality-Stat'!I14="","",'Quality-Stat'!I14) -> 212 | I63: =IF('Quality-Stat'!J14="","",'Quality-Stat'!J14) -> 0 | J63: =IF('Quality-Stat'!K14="","",'Quality-Stat'!K14) -> 0 | K63: =IF('Quality-Stat'!L14="","",'Quality-Stat'!L14) -> 212 | L63: Non Conformance (NCR) | N63: 4 | O63: 3 | P63: 1 | Q63: ='Quality-Stat'!F5 -> 0 | R63: 0 | S63: ='Quality-Stat'!H5 -> 0 | T63: ='Quality-Stat'!I5 -> 0 | U63: ='Quality-Stat'!J5 -> 0 | V63: ='Quality-Stat'!K5 -> 0 | X63: ='HSE-Stat'!B5 -> Safe Hours Worked | Z63: ='HSE-Stat'!D5 -> 34740 | AB63: ='HSE-Stat'!E5 -> 69480 | AC63: ='HSE-Stat'!F5 -> 774924 | AD63: ='HSE-Stat'!G5 -> 839982 | AG63: Reactive | AH63: =SUM(AD64:AD72) -> 0
A64: ='Quality-Stat'!A15 -> Elec | C64: =IF('Quality-Stat'!D15="","",'Quality-Stat'!D15) -> 41 | D64: =IF('Quality-Stat'!E15="","",'Quality-Stat'!E15) -> 0 | E64: =IF('Quality-Stat'!F15="","",'Quality-Stat'!F15) -> 41 | F64: =IF('Quality-Stat'!G15="","",'Quality-Stat'!G15) -> 0 | G64: =IF('Quality-Stat'!H15="","",'Quality-Stat'!H15) -> 0 | H64: =IF('Quality-Stat'!I15="","",'Quality-Stat'!I15) -> 41 | I64: =IF('Quality-Stat'!J15="","",'Quality-Stat'!J15) -> 0 | J64: =IF('Quality-Stat'!K15="","",'Quality-Stat'!K15) -> 0 | K64: =IF('Quality-Stat'!L15="","",'Quality-Stat'!L15) -> 41 | L64: Site Instruction (SIR) | N64: ='Quality-Stat'!C6 -> 50 | O64: ='Quality-Stat'!D6 -> 41 | P64: ='Quality-Stat'!E6 -> 9 | Q64: ='Quality-Stat'!F6 -> 0 | R64: ='Quality-Stat'!G6 -> 0 | S64: ='Quality-Stat'!H6 -> 0 | T64: ='Quality-Stat'!I6 -> 0 | U64: ='Quality-Stat'!J6 -> 0 | V64: ='Quality-Stat'!K6 -> 0 | W64: Reactive | X64: ='HSE-Stat'!B6 -> LTI | Z64: ='HSE-Stat'!D6 -> 0 | AB64: ='HSE-Stat'!E6 -> 0 | AC64: ='HSE-Stat'!F6 -> 0 | AD64: ='HSE-Stat'!G6 -> 0
A65: ='Quality-Stat'!A16 -> Landscape & Arch | C65: =IF('Quality-Stat'!D16="","",'Quality-Stat'!D16) -> 458 | D65: =IF('Quality-Stat'!E16="","",'Quality-Stat'!E16) -> 0 | E65: =IF('Quality-Stat'!F16="","",'Quality-Stat'!F16) -> 458 | F65: =IF('Quality-Stat'!G16="","",'Quality-Stat'!G16) -> 0 | G65: =IF('Quality-Stat'!H16="","",'Quality-Stat'!H16) -> 0 | H65: =IF('Quality-Stat'!I16="","",'Quality-Stat'!I16) -> 458 | I65: =IF('Quality-Stat'!J16="","",'Quality-Stat'!J16) -> 0 | J65: =IF('Quality-Stat'!K16="","",'Quality-Stat'!K16) -> 0 | K65: =IF('Quality-Stat'!L16="","",'Quality-Stat'!L16) -> 458 | L65: Material Inspection (MIR) | N65: ='Quality-Stat'!C7 -> 111 | O65: ='Quality-Stat'!D7 -> 110 | P65: ='Quality-Stat'!E7 -> 1 | Q65: ='Quality-Stat'!F7 -> 0 | R65: ='Quality-Stat'!G7 -> 0 | S65: ='Quality-Stat'!H7 -> 0 | T65: ='Quality-Stat'!I7 -> 0 | U65: ='Quality-Stat'!J7 -> 0 | V65: ='Quality-Stat'!K7 -> 0 | X65: ='HSE-Stat'!B7 -> MTC (Healed w/o Disability) | Z65: ='HSE-Stat'!D7 -> 0 | AB65: ='HSE-Stat'!E7 -> 0 | AC65: ='HSE-Stat'!F7 -> 0 | AD65: ='HSE-Stat'!G7 -> 0
L66: Field Inspection (FIR) | N66: ='Quality-Stat'!C8 -> 4408 | O66: ='Quality-Stat'!D8 -> 4286 | P66: ='Quality-Stat'!E8 -> 122 | Q66: ='Quality-Stat'!F8 -> 0 | R66: ='Quality-Stat'!G8 -> 0 | S66: ='Quality-Stat'!H8 -> 0 | T66: ='Quality-Stat'!I8 -> 0 | U66: ='Quality-Stat'!J8 -> 0 | V66: ='Quality-Stat'!K8 -> 0 | X66: ='HSE-Stat'!B8 -> MTC (Healed w/ Disability) | Z66: ='HSE-Stat'!D8 -> 0 | AB66: ='HSE-Stat'!E8 -> 0 | AC66: ='HSE-Stat'!F8 -> 0 | AD66: ='HSE-Stat'!G8 -> 0
A67: TOTAL | C67: =SUM(C62:C66) -> 1774 | D67: =SUM(D62:D66) -> 8 | E67: =SUM(E62:E66) -> 1766 | F67: =SUM(F62:F66) -> 0 | G67: =SUM(G62:G66) -> 0 | H67: =SUM(H62:H66) -> 1774 | I67: =SUM(I62:I66) -> 0 | J67: =SUM(J62:J66) -> 0 | K67: =SUM(K62:K66) -> 1774 | L67: Key Submittals Approval Status | X67: ='HSE-Stat'!B9 -> Near Miss | Z67: ='HSE-Stat'!D9 -> 0 | AB67: ='HSE-Stat'!E9 -> 0 | AC67: ='HSE-Stat'!F9 -> 0 | AD67: ='HSE-Stat'!G9 -> 0
A68: Material Approval | L68: 1 Quality Plan Approval | O68: ='General Information'!C27 -> 45346 | Q68: 6 Baseline Approval | U68: ='General Information'!C39 -> 45361 | X68: ='HSE-Stat'!B10 -> First Aid Cases | Z68: ='HSE-Stat'!D10 -> 0 | AB68: ='HSE-Stat'!E10 -> 0 | AC68: ='HSE-Stat'!F10 -> 0 | AD68: ='HSE-Stat'!G10 -> 0 | AE68: Total Hours Worked Vs Safe Hours Worked
A69: Item Per WBS | C69: Total | D69: Total Submitted Material | I69: Remaining to approve | J69: Pending | K69: Total Submittals | L69: 2 Quality Plan Last Up | O69: ='General Information'!C28 -> 45346 | Q69: 7 No of Approved Version of Schedule | U69: ='General Information'!C40 -> 1 | X69: ='HSE-Stat'!B11 -> Fatality | Z69: ='HSE-Stat'!D11 -> 0 | AB69: ='HSE-Stat'!E11 -> 0 | AC69: ='HSE-Stat'!F11 -> 0 | AD69: ='HSE-Stat'!G11 -> 0
D70: A | E70: B | F70: C | G70: D | H70: Processed | I70: with Designer | L70: 3 Safety Plan Approval | O70: ='General Information'!C31 -> 45350 | Q70: 8 Last Approved Schedule | U70: ='General Information'!C41 -> 45361 | X70: ='HSE-Stat'!B12 -> Fire Incident Cases | Z70: ='HSE-Stat'!D12 -> 0 | AB70: ='HSE-Stat'!E12 -> 0 | AC70: ='HSE-Stat'!F12 -> 0 | AD70: ='HSE-Stat'!G12 -> 0
A71: ='Quality-Stat'!A23 -> Civil & Roads | C71: ='Quality-Stat'!D23 -> 75 | D71: ='Quality-Stat'!E23 -> 2 | E71: ='Quality-Stat'!F23 -> 73 | F71: ='Quality-Stat'!G23 -> 3 | G71: ='Quality-Stat'!H23 -> 1 | H71: ='Quality-Stat'!I23 -> 75 | I71: ='Quality-Stat'!J23 -> 0 | J71: ='Quality-Stat'!K23 -> 4 | K71: ='Quality-Stat'!L23 -> 83 | L71: 4 Safety Plan Last Up | O71: ='General Information'!C32 -> 45350 | Q71: 9 BOQ Approval Date | U71: ='General Information'!C44 -> 0 | X71: ='HSE-Stat'!B13 -> Vehicle Incident | Z71: ='HSE-Stat'!D13 -> 0 | AB71: ='HSE-Stat'!E13 -> 0 | AC71: ='HSE-Stat'!F13 -> 0 | AD71: ='HSE-Stat'!G13 -> 0
A72: ='Quality-Stat'!A24 -> Electrical | C72: ='Quality-Stat'!D24 -> 30 | D72: ='Quality-Stat'!E24 -> 0 | E72: ='Quality-Stat'!F24 -> 22 | F72: ='Quality-Stat'!G24 -> 0 | G72: ='Quality-Stat'!H24 -> 0 | H72: ='Quality-Stat'!I24 -> 22 | I72: ='Quality-Stat'!J24 -> 8 | J72: ='Quality-Stat'!K24 -> 0 | K72: ='Quality-Stat'!L24 -> 22 | L72: 5 Construction Plan Approval | O72: ='General Information'!C48 -> 45348 | Q72: 10 No of Approved Version of BOQ | U72: ='General Information'!C45 -> 1 | X72: ='HSE-Stat'!B14 -> Property Damages | Z72: ='HSE-Stat'!D14 -> 0 | AB72: ='HSE-Stat'!E14 -> 0 | AC72: ='HSE-Stat'!F14 -> 0 | AD72: ='HSE-Stat'!G14 -> 0
A73: ='Quality-Stat'!A25 -> Mechanical | C73: ='Quality-Stat'!D25 -> 48 | D73: ='Quality-Stat'!E25 -> 0 | E73: ='Quality-Stat'!F25 -> 41 | F73: ='Quality-Stat'!G25 -> 0 | G73: ='Quality-Stat'!H25 -> 2 | H73: ='Quality-Stat'!I25 -> 41 | I73: ='Quality-Stat'!J25 -> 7 | J73: ='Quality-Stat'!K25 -> 1 | K73: ='Quality-Stat'!L25 -> 44 | L73: Invoices Summary | W73: Proactive | X73: ='HSE-Stat'!B15 -> Induction Training | Z73: ='HSE-Stat'!D15 -> 33 | AB73: ='HSE-Stat'!E15 -> 62 | AC73: ='HSE-Stat'!F15 -> 114(564) | AD73: ='HSE-Stat'!G15 -> 147(888)
L74: Total Submitted Invoices | N74: ='Invoice Log'!U3 -> 7 | O74: Submitted Invoices (SAR) | R74: ='Invoice Log'!Y3 -> 62889674 | T74: Contract Value (SR) | U74: =O4 -> 1.9890616e+08 | X74: ='HSE-Stat'!B16 -> No.of Internal Training | Z74: ='HSE-Stat'!D16 -> 0 | AB74: ='HSE-Stat'!E16 -> 2 (9) | AC74: ='HSE-Stat'!F16 -> 5(23) | AD74: ='HSE-Stat'!G16 -> 13(98)
L75: PM Approved Invoices | N75: ='Invoice Log'!U5 -> 0 | O75: PM Approved Invoices (SAR) | R75: ='Invoice Log'!Y5 -> 0 | T75: Planned Value (SR) | U75: =H29 -> 1.3153529e+08 | X75: ='HSE-Stat'!B17 -> No.of Internal Audit | Z75: ='HSE-Stat'!D17 -> 0 | AB75: ='HSE-Stat'!E17 -> 1 | AC75: ='HSE-Stat'!F17 -> 4 | AD75: ='HSE-Stat'!G17 -> 4
A76: TOTAL | C76: =SUM(C71:C75) -> 153 | D76: =SUM(D71:D75) -> 2 | E76: =SUM(E71:E75) -> 136 | F76: =SUM(F71:F75) -> 3 | G76: =SUM(G71:G75) -> 3 | H76: =SUM(H71:H75) -> 138 | I76: =SUM(I71:I75) -> 15 | J76: =SUM(J71:J75) -> 5 | K76: =SUM(K71:K75) -> 149 | L76: No of Paid Invoices | N76: ='Invoice Log'!U6 -> 0 | O76: Paid Invoices (SAR) | R76: ='Invoice Log'!Y6 -> 0 | T76: Earned Value (SR) | U76: =I29 -> 1.0540208e+08 | X76: ='HSE-Stat'!B18 -> No. of Toolbox Talks | Z76: ='HSE-Stat'!D18 -> 3(323) | AB76: ='HSE-Stat'!E18 -> 3(648) | AC76: ='HSE-Stat'!F18 -> (43(3442) | AD76: ='HSE-Stat'!G18 -> 56(8671)
A77: Procurement Summary | L77: No of Pending Invoices | N77: =N75-N76 -> 0 | O77: Last Submitted Period | R77: ='Invoice Log'!AB3 -> 46280 | T77: Submitted (SAR) | U77: =R74 -> 62889674 | X77: ='HSE-Stat'!B19 -> Safety Awards/Incentives | Z77: ='HSE-Stat'!D19 -> 0 | AB77: ='HSE-Stat'!E19 -> 0 | AC77: ='HSE-Stat'!F19 -> 1 | AD77: ='HSE-Stat'!G19 -> 2
A78: Item Per WBS | C78: Total Materials | D78: Total Number of P.O. | E78: Actual P.O. To Date | F78: Remaining P.O | G78: Material on Site | H78: Remaining Materials | I78: Material Delivery Completion (Date) | L78: Advance Payment % | N78: ='Invoice Log'!M3 -> 0 | O78: Advance Payment (SAR) | R78: ='Invoice Log'!Q3 -> 0 | T78: PM Approved (SAR) | U78: =R75 -> 0 | W78: Latest Contract Change Order Log
D79: A | E79: B | F79: C | G79: D | H79: Processed | L79: Retention % | N79: ='Invoice Log'!M4 -> 0 | O79: Retention (SAR) | R79: ='Invoice Log'!Q4 -> 0 | T79: Total Paid (SAR) | U79: =R76 -> 0
A80: ='Quality-Stat'!A31 -> Civil & Roads | C80: =IF('Quality-Stat'!D31="","",'Quality-Stat'!D31) -> 75 | D80: =IF('Quality-Stat'!E31="","",'Quality-Stat'!E31) -> 75 | E80: =IF('Quality-Stat'!F31="","",'Quality-Stat'!F31) -> 75 | F80: =IF('Quality-Stat'!G31="","",'Quality-Stat'!G31) -> 0 | G80: =IF('Quality-Stat'!H31="","",'Quality-Stat'!H31) -> 42 | H80: =IF('Quality-Stat'!I31="","",'Quality-Stat'!I31) -> 33 | I80: ='Quality-Stat'!J31 -> 46335 | L80: Deduction / Penalties % | N80: ='Invoice Log'!M5 -> 0.00052537337 | O80: Deduction / Penalties (SAR) | R80: ='Invoice Log'!M6 -> -104500 | W80: CCO No. | X80: Date Added | Y80: Description of Change | AD80: Status | AE80: Cost | AF80: Sch Impact (Months) | AG80: Date Approved | AH80: Duration
A81: ='Quality-Stat'!A32 -> Electrical | C81: =IF('Quality-Stat'!D32="","",'Quality-Stat'!D32) -> 30 | D81: =IF('Quality-Stat'!E32="","",'Quality-Stat'!E32) -> 30 | E81: =IF('Quality-Stat'!F32="","",'Quality-Stat'!F32) -> 22 | F81: =IF('Quality-Stat'!G32="","",'Quality-Stat'!G32) -> 0 | G81: =IF('Quality-Stat'!H32="","",'Quality-Stat'!H32) -> 11 | H81: =IF('Quality-Stat'!I32="","",'Quality-Stat'!I32) -> 19 | I81: ='Quality-Stat'!J32 -> 46292 | L81: Resources at Site
A82: ='Quality-Stat'!A33 -> Mechanical | C82: =IF('Quality-Stat'!D33="","",'Quality-Stat'!D33) -> 48 | D82: =IF('Quality-Stat'!E33="","",'Quality-Stat'!E33) -> 48 | E82: =IF('Quality-Stat'!F33="","",'Quality-Stat'!F33) -> 42 | F82: =IF('Quality-Stat'!G33="","",'Quality-Stat'!G33) -> 0 | G82: =IF('Quality-Stat'!H33="","",'Quality-Stat'!H33) -> 21 | H82: =IF('Quality-Stat'!I33="","",'Quality-Stat'!I33) -> 27 | I82: ='Quality-Stat'!J33 -> 46293 | L82: Head Count - Non Manual | P82: Head Count - Manual | T82: Total Head Count | W82: =CCO!A3 -> 0 | X82: =CCO!B3 -> 0 | Y82: =CCO!C3 -> 0 | AD82: =CCO!D3 -> 0 | AE82: =CCO!E3 -> 0 | AF82: =CCO!F3 -> 0 | AG82: =CCO!G3 -> 0 | AH82: =CCO!H3 -> 0
L83: Planned | M83: Actual | N83: Next Month Forecast | O83: Saudi Staff | P83: Planned | Q83: Actual | R83: Next Month Forecast | S83: Saudi Staff | T83: Total Plan | U83: Total Actual | V83: Variance
L84: =Manpower!A20 -> 35 | M84: =Manpower!B20 -> 57 | N84: =Manpower!F20 -> 122 | O84: 4 | P84: =M94 -> 360 | Q84: =N94 -> 483 | R84: =Manpower!F24 -> 560 | S84: =Manpower!H24 -> 0 | T84: =L84+P84 -> 395 | U84: =M84+Q84 -> 540 | V84: =+U84-T84 -> 145 | W84: =CCO!A4 | X84: =CCO!B4 | Y84: =CCO!C4 | AD84: =IF(CCO!D4="","",CCO!D4) | AE84: =CCO!E4 | AF84: =CCO!F4 | AG84: =CCO!G4 | AH84: =CCO!H4
A85: TOTAL | C85: =IF('Quality-Stat'!D33="","",'Quality-Stat'!D33) -> 48 | D85: =IF('Quality-Stat'!E33="","",'Quality-Stat'!E33) -> 48 | E85: =IF('Quality-Stat'!F33="","",'Quality-Stat'!F33) -> 42 | F85: =IF('Quality-Stat'!G33="","",'Quality-Stat'!G33) -> 0 | G85: =IF('Quality-Stat'!H33="","",'Quality-Stat'!H33) -> 21 | H85: =IF('Quality-Stat'!I33="","",'Quality-Stat'!I33) -> 27 | I85: =MAX(I80:I84) -> 46335 | L85: Manpower Breakdown by Trade | S85: Major Equipment
A86: =Schedule!A1 -> Primavera P6 Schedule Status | L86: Key Trade | M86: Planned | N86: Actual | S86: Type | T86: Planned | U86: Actual | V86: Idle | W86: =CCO!A5 | X86: =CCO!B5 | Y86: =CCO!C5 | AD86: =IF(CCO!D5="","",CCO!D5) | AE86: =CCO!E5 | AF86: =CCO!F5 | AG86: =CCO!G5 | AH86: =CCO!H5
A87: =Schedule!A2 -> Project Activities Overview | L87: =+Manpower!N23 -> General Labor | M87: =Manpower!N24 -> 120 | N87: =Manpower!N25 -> 119 | S87: =+Manpower!$B$49 -> Excavator | T87: =+Manpower!B50 -> 22 | U87: =+Manpower!B51 -> 23 | V87: =+Manpower!B52 -> 0
A88: =Schedule!A3 -> Schedule Statistics | F88: =Schedule!F3 -> Active Schedule Activities | L88: =+Manpower!P23 -> Carpenter | M88: =Manpower!P24 -> 15 | N88: =Manpower!P25 -> 68 | S88: =+Manpower!$D$49 -> Loader | T88: =+Manpower!D50 -> 8 | U88: =+Manpower!D51 -> 13 | V88: =+Manpower!D52 -> 0 | W88: Major Quantity Trackers
A89: =Schedule!A4 -> Total Act. | B89: =Schedule!B4 -> Not Started | C89: =Schedule!C4 -> In Progress | D89: =Schedule!D4 -> Completed | E89: =Schedule!E4 -> % | F89: =Schedule!F4 -> Active | G89: =Schedule!G4 -> Ahead | H89: =Schedule!H4 -> On | ... K89: =Schedule!K4 -> 0 | L89: =+Manpower!R23 -> Plumber | M89: =+Manpower!R24 -> 16 | N89: =Manpower!R25 -> 33 | S89: =+Manpower!$F$49 -> W.Tanker | T89: =+Manpower!F50 -> 14 | U89: =+Manpower!F51 -> 18 | V89: =+Manpower!F52 -> 0 | W89: BOQ N0. | X89: Item Description | AC89: Total Qty | AD89: Measu Unit | AE89: Plan to Date | AF89: Act to Date | AG89: Remaining | AH89: Variance
A90: =Schedule!A5 -> 4851 | B90: =Schedule!B5 -> 2124 | C90: =Schedule!C5 -> 388 | D90: =Schedule!D5 -> 2339 | E90: =Schedule!E5 -> 0.48216863 | F90: =Schedule!F5 -> 388 | G90: =Schedule!G5 -> 7 | H90: =Schedule!H5 -> 1510 | ... J90: =Schedule!J5 -> 1351 | L90: =+Manpower!T23 -> Operator | M90: =Manpower!T24 -> 125 | N90: =Manpower!T25 -> 237 | S90: =+Manpower!$H$49 -> Dumper | T90: =+Manpower!H50 -> 28 | U90: =+Manpower!H51 -> 163 | V90: =+Manpower!H52 -> 0 | W90: ='Major Quantities'!A2 -> B1.1.31 23 19.01 | X90: ='Major Quantities'!B2 -> Surface Dewatering | AC90: =VLOOKUP(X90,'Major Quantities'!$B$2:$G$22,2,FALSE) -> 1 | AD90: =VLOOKUP(X90,'Major Quantities'!$B$2:$G$22,3,FALSE) -> Unit | AE90: =VLOOKUP(X90,'Major Quantities'!$B$2:$G$22,4,FALSE) -> 1 | AF90: =VLOOKUP(X90,'Major Quantities'!$B$2:$G$22,5,FALSE) -> 1 | AG90: =VLOOKUP(X90,'Major Quantities'!$B$2:$G$22,6,FALSE) -> 0 | AH90: =VLOOKUP(X90,'Major Quantities'!$B$2:$H$22,7,FALSE) -> 0
A91: =Schedule!A6 -> Critical Path Activities | D91: =Schedule!D6 -> Free Float Management (Total) | H91: =Schedule!H6 -> Failed Start Activities | L91: =+Manpower!W23 -> Surveyor | M91: =Manpower!W24 -> 14 | N91: =Manpower!W25 -> 9 | S91: =+Manpower!$J$49 -> Dozer | T91: =+Manpower!J50 -> 8 | U91: =+Manpower!J51 -> 10 | V91: =+Manpower!J52 -> 0 | W91: ='Major Quantities'!A3 -> B1.1.31 23 16.01 | X91: ='Major Quantities'!B3 -> All Excavation | AC91: =VLOOKUP(X91,'Major Quantities'!$B$2:$G$22,2,FALSE) -> 853395 | AD91: =VLOOKUP(X91,'Major Quantities'!$B$2:$G$22,3,FALSE) -> m³ | AE91: =VLOOKUP(X91,'Major Quantities'!$B$2:$G$22,4,FALSE) -> 853395 | AF91: =VLOOKUP(X91,'Major Quantities'!$B$2:$G$22,5,FALSE) -> 825820.73 | AG91: =VLOOKUP(X91,'Major Quantities'!$B$2:$G$22,6,FALSE) -> 27574.27 | AH91: =VLOOKUP(X91,'Major Quantities'!$B$2:$H$22,7,FALSE) -> -27574.27
D92: =Schedule!D7 -> Greater Than 14 Days | F92: =Schedule!F7 -> Less Than 14 Days | L92: =+Manpower!X23 -> Others | M92: =Manpower!X24 -> 70 | N92: =Manpower!X25 -> 17 | S92: =+Manpower!$L$49 -> Grader | T92: =+Manpower!L50 -> 8 | U92: =+Manpower!L51 -> 8 | V92: =+Manpower!L52 -> 0 | W92: ='Major Quantities'!A4 -> B1.1.31 23 23.01 | X92: ='Major Quantities'!B4 -> All Backfilling | AC92: =VLOOKUP(X92,'Major Quantities'!$B$2:$G$22,2,FALSE) -> 1481028 | AD92: =VLOOKUP(X92,'Major Quantities'!$B$2:$G$22,3,FALSE) -> m³ | AE92: =VLOOKUP(X92,'Major Quantities'!$B$2:$G$22,4,FALSE) -> 1481028 | AF92: =VLOOKUP(X92,'Major Quantities'!$B$2:$G$22,5,FALSE) -> 1353015.9 | AG92: =VLOOKUP(X92,'Major Quantities'!$B$2:$G$22,6,FALSE) -> 128012.1 | AH92: =VLOOKUP(X92,'Major Quantities'!$B$2:$H$22,7,FALSE) -> -128012.1
A93: =Schedule!A8 -> Last Week | B93: =Schedule!B8 -> This Week | C93: =Schedule!C8 -> Diff | D93: =Schedule!D8 -> Last Week | E93: =Schedule!E8 -> This Week | F93: =Schedule!F8 -> Last Week | G93: =Schedule!G8 -> This Week | H93: =Schedule!H8 -> Last Week | ... K93: =Schedule!K8 -> 0 | S93: =+Manpower!$N$49 -> Other | T93: =+Manpower!N50 -> 62 | U93: =+Manpower!N51 -> 91 | V93: =+Manpower!N52 -> 0 | W93: ='Major Quantities'!A5 -> B1.2.32 11 26.01 | X93: ='Major Quantities'!B5 -> Asphalt (Base+Wearing) | AC93: =VLOOKUP(X93,'Major Quantities'!$B$2:$G$22,2,FALSE) -> 64334 | AD93: =VLOOKUP(X93,'Major Quantities'!$B$2:$G$22,3,FALSE) -> m³ | AE93: =VLOOKUP(X93,'Major Quantities'!$B$2:$G$22,4,FALSE) -> 53869.9 | AF93: =VLOOKUP(X93,'Major Quantities'!$B$2:$G$22,5,FALSE) -> 25214.53 | AG93: =VLOOKUP(X93,'Major Quantities'!$B$2:$G$22,6,FALSE) -> 39119.47 | AH93: =VLOOKUP(X93,'Major Quantities'!$B$2:$H$22,7,FALSE) -> -28655.37
A94: =Schedule!A9 -> 45 | B94: =Schedule!B9 -> 45 | C94: =Schedule!C9 -> 0 | D94: =Schedule!D9 -> 464 | E94: =Schedule!E9 -> 490 | F94: =Schedule!F9 -> 2141 | G94: =Schedule!G9 -> 2019 | H94: =Schedule!H9 -> 1039 | ... J94: =Schedule!J9 -> 46 | L94: Total | M94: =SUM(M87:M93) -> 360 | N94: =SUM(N87:N93) -> 483 | S94: Total | T94: =SUM(T87:T93) -> 150 | U94: =SUM(U87:U93) -> 326 | V94: =SUM(V87:V93) -> 0 | W94: ='Major Quantities'!A6 -> 33 31 00 | X94: ='Major Quantities'!B6 -> Sew. Pipes | AC94: =VLOOKUP(X94,'Major Quantities'!$B$2:$G$22,2,FALSE) -> 7567.08 | AD94: =VLOOKUP(X94,'Major Quantities'!$B$2:$G$22,3,FALSE) -> Lm | AE94: =VLOOKUP(X94,'Major Quantities'!$B$2:$G$22,4,FALSE) -> 2.01 | AF94: =VLOOKUP(X94,'Major Quantities'!$B$2:$G$22,5,FALSE) -> 6748.28 | AG94: =VLOOKUP(X94,'Major Quantities'!$B$2:$G$22,6,FALSE) -> 818.8 | AH94: =VLOOKUP(X94,'Major Quantities'!$B$2:$H$22,7,FALSE) -> 6746.27
A95: Weekly Prgoress Photos | Q95: Top Issues and Risks
A96: ='Weekly Photos'!B4 -> Road & Plots Works | F96: ='Weekly Photos'!B23 -> Wet Utilities | I96: ='Weekly Photos'!I23 -> Pump & Lift Station | L96: ='Weekly Photos'!L4 -> Dry Utilities | Q96: Top 5 Issues
Q97: Issue No | R97: Date Identified | S97: Issue Description | W97: Responsible | X97: Action Taken | AA97: Mitigation | AF97: Current Status | AG97: Expected/Actual Closure | AH97: Duration Elapsed
Q98: =IF(+Issues!B11="","",+Issues!B11) -> 1 | R98: =IF(+Issues!C11="","",+Issues!C11) -> 46113 | S98: =IF(+Issues!D11="","",+Issues!D11) -> قلة عدد العمالة والمعدات و توقف مقاول الباطن | W98: =IF(+Issues!E11="","",+Issues!E11) -> Contractor | X98: =Issues!F11 -> جاري اسناد جزء من المشروع لمقاول آخر و جاري توفير عمالة من الشركة لاستكمال الاعمال المتبقية حيث ان عدد العمالة الحالي 304 والمعدات 184 معدة والمضخات الى 30 مضخة نزح ,و وجوب استمرار زيادة العمالة والمعدات لتحقيق مستهدفات مدن | AF98: =IF(+Issues!H11="","",+Issues!H11) -> Open | AG98: =IF(+Issues!I11="","",+Issues!I11) -> 46143 | AH98: =IF(+Issues!J11="","",+Issues!J11) -> 195
Q99: =IF(+Issues!B12="","",+Issues!B12) -> 2 | R99: =IF(+Issues!C12="","",+Issues!C12) -> 46174 | S99: =IF(+Issues!D12="","",+Issues!D12) -> تأخر أعمال العبارة بالطريق الشرياني | W99: =IF(+Issues!E12="","",+Issues!E12) -> Contractor | X99: =Issues!F12 -> جاري الانتهاء من الحدادة ل 16 فواصل وصب قاعدة لعدد 03 فاصل تم حفر 14 و جاري 03 فواصل أخرى | AF99: =IF(+Issues!H12="","",+Issues!H12) -> Open | AG99: =IF(+Issues!I12="","",+Issues!I12) -> 46204 | AH99: =IF(+Issues!J12="","",+Issues!J12) -> 134
Q100: =IF(+Issues!B13="","",+Issues!B13) -> 3 | R100: =IF(+Issues!C13="","",+Issues!C13) -> 46174 | S100: =IF(+Issues!D13="","",+Issues!D13) -> ضرورة الانتهاء من تنفيذ الشبكات لتحقيق جاهزية الموقع وبدء أعمال الطرق | W100: =IF(+Issues!E13="","",+Issues!E13) -> Other | X100: =Issues!F13 -> تم استبعاد مقاول الباطن يوناسكو و سحب اعتماده لعدم وفاءه بمستهدفات مدن و على المقاول العمل بشكل مباشر على الشبكات او تقديم مقاول باطن للاعتماد | AF100: =IF(+Issues!H13="","",+Issues!H13) -> Open | AG100: =IF(+Issues!I13="","",+Issues!I13) -> 46204 | AH100: =IF(+Issues!J13="","",+Issues!J13) -> 134
Q101: =IF(+Issues!B14="","",+Issues!B14) -> 4 | R101: =IF(+Issues!C14="","",+Issues!C14) | S101: =IF(+Issues!D14="","",+Issues!D14) | W101: =IF(+Issues!E14="","",+Issues!E14) | X101: =Issues!F14 -> 0 | AF101: =IF(+Issues!H14="","",+Issues!H14) | AG101: =IF(+Issues!I14="","",+Issues!I14) | AH101: =IF(+Issues!J14="","",+Issues!J14)
Q102: =IF(+Issues!B15="","",+Issues!B15) -> 5 | R102: =IF(+Issues!C15="","",+Issues!C15) | S102: =IF(+Issues!D15="","",+Issues!D15) | W102: =IF(+Issues!E15="","",+Issues!E15) | X102: =Issues!F15 -> 0 | AF102: =IF(+Issues!H15="","",+Issues!H15) | AG102: =IF(+Issues!I15="","",+Issues!I15) | AH102: =IF(+Issues!J15="","",+Issues!J15)

Sheet General Information
A1: Weekly Progress Report - Construction Projects | K1: Data Date | L1: 46308 | N1: =L1+7 -> 46315
A2: Contract General Information
A3: Project Name | C3: Development of Infrastructure for phase 1 of the Logistics area at the 2nd Industrial City in Dammam
A4: Project ID | C4: DAM2-02-009
A5: Contractor | C5: Shibh Aljazira Contracting Company
A6: Consultant | C6: Egis
A7: Stage | C7: Construction
A8: Status | C8: Active
A9: Modon PM | C9: Muhammad H Al-Essa
A11: Key Dates
A12: Contract Award Date | C12: =Milestones!C4 -> 45838
A13: Contract Sign Date | C13: =Milestones!C5 -> 45852
A14: Site Handover Date | C14: =Milestones!C6 -> 45868
A15: Original Completion | C15: =Milestones!C15 -> 46416
A16: Contract Award Date (Hijri) | C16: =C12 -> 45838
A17: Contract Sign Date (Hijri) | C17: =C13 -> 45852
A18: Site Handover Date (Hijri) | C18: =C14 -> 45868
A19: Original Completion (Hijri) | C19: =C15 -> 46416
A20: Revised Completion Date | C20: =Milestones!D15 -> 46416
A21: Committed Completion Date | C21: =Milestones!D15 -> 46416
A22: Forecast Completion | C22: =Milestones!E13 -> 46425
A23: Variance | C23: =C20-C22 -> -9
A25: Key Project Submittals | C25: Submission Date | D25: Days taken to approve orginal plan from site handover date
A26: Quality Plan submission | C26: 45344 | D26: =C26-C14 -> -524
A27: Quality Plan approval | C27: 45346
A28: Quality Plan Last Update | C28: 45346
A30: Safety Plan submission | C30: 45345 | D30: =C30-C14 -> -523
A31: Safety Plan approval | C31: 45350
A32: Safety Plan Last Update | C32: 45350
A34: Risk Management Plan submission | C34: 45345 | D34: =C34-C14 -> -523
A35: Risk Management Plan approval | C35: 45350
A36: Risk Management Plan Last Update | C36: 45350
A38: Baseline Schedule submission | C38: 45334 | D38: =C38-C14 -> -534
A39: Baseline Schedule approval | C39: 45361
A40: No of Schedule Versions | C40: 1
A41: Last Recovery Schedule Approval Date | C41: 45361
A43: BOQ submission | D43: =C43-C19 -> -46416
A44: BOQ approval
A45: No of Approved Version of BOQ | C45: 1
A47: Construction Plan submission | C47: 45346 | D47: =C47-C14 -> -522
A48: Construction Plan Approval | C48: 45348

Sheet Progress
A1: Project Scope Statement | B1: The project consists of the wet networks mainlines (Sewerage, Storm, Potable, Firefighting & TSE) including the force main line, in addition to the dry networks (Medium Voltage, Low Voltage, Street Lighting & Telecommunication) road crossings & main line connections, scope also included supply, install, testing & commissioning for the potable water pump station and the sewage lift station and implementation of guard rooms and applying all the road earth layers till the asphalt wearing coarse for the project scope area internal roads & finishing the landscape | S1: ='General Information'!$K$1 -> Data Date | T1: ='General Information'!L1 -> 46308
A4: Earned Value Progress (SAR) | K4: Physical Progress (Effort)
A5: WBS | C5: BOQ Value (SAR) | D5: % Wt. | E5: Weekly (SAR) | H5: To Date (SAR) | K5: Budgeted | L5: % Wt. | M5: Weekly Physical Progress | O5: To Date Physical Progress
E6: Planned | F6: Earned | G6: Original Plan | H6: Planned | I6: Earned | K6: (Manhours) | M6: Planned | N6: Earned | O6: Planned | P6: Earned
A7: Demolishing & Site Clearing | C7: 457401.18 | D7: 0.0022995827 | E7: 0 | F7: 0 | G7: 457401.18 | H7: 457401.18 | I7: 457401.18 | K7: 3437.41 | L7: 0.0037353813 | M7: 0 | N7: 0 | O7: 3437.41 | P7: 3262.7443
A8: Earthworks & Site Grading | C8: 31040592 | D8: 0.15605646 | E8: 0 | F8: 0 | G8: 31040592 | H8: 31040592 | I8: 29924053 | K8: 22808.8 | L8: 0.024785977 | M8: 0 | N8: 0 | O8: 22808.8 | P8: 20830.332
A9: Sewerage Network | C9: 5111121.8 | D9: 0.025696146 | E9: 91525.9 | F9: 372237.6 | G9: 5069014.3 | H9: 5069014.3 | I9: 4562022 | K9: 74260.44 | L9: 0.080697694 | M9: 1570.09 | N9: 6695.54 | O9: 62840.48 | P9: 58190.25
A10: Engineering | C10: 0 | D10: 0 | E10: 0 | F10: 0 | G10: 0 | H10: 0 | I10: 0 | K10: 568.6 | L10: 0.000617889 | M10: 0 | N10: 0 | O10: 568.6 | P10: 568.6
A11: Procurement | C11: 0 | D11: 0 | E11: 0 | F11: 0 | G11: 0 | H11: 0 | I11: 0 | K11: 10403.33 | L11: 0.011305141 | M11: 193.39 | N11: 478.41 | O11: 10403.33 | P11: 10403.33
A12: Construction | C12: 5111121.8 | D12: 0.025696146 | E12: 91525.9 | F12: 372237.6 | G12: 5069014.3 | H12: 5069014.3 | I12: 4562022 | K12: 53551.26 | L12: 0.058193342 | M12: 1376.7 | N12: 6217.13 | O12: 51868.55 | P12: 43841.94
A13: Testing & Commissioning | C13: 0 | D13: 0 | E13: 0 | F13: 0 | G13: 0 | H13: 0 | I13: 0 | K13: 9737.25 | L13: 0.010581322 | M13: 0 | N13: 0 | O13: 0 | P13: 6491.5
A14: Storm Water Network | C14: 21808728 | D14: 0.1096433 | E14: 474784.2 | F14: 313708.57 | G14: 20519480 | H14: 20519480 | I14: 18392420 | K14: 143781.21 | L14: 0.15624486 | M14: 2114.92 | N14: 596.69 | O14: 124384.01 | P14: 107524.87
A15: Engineering | C15: 0 | D15: 0 | E15: 0 | F15: 0 | G15: 0 | H15: 0 | I15: 0 | K15: 984.12 | L15: 0.0010694283 | M15: 0 | N15: 0 | O15: 984.12 | P15: 984.12
A16: Procurement | C16: 0 | D16: 0 | E16: 0 | F16: 0 | G16: 0 | H16: 0 | I16: 0 | K16: 14474.2 | L16: 0.015728894 | M16: 34.79 | N16: 52.14 | O16: 14474.2 | P16: 14474.2
A17: Construction | C17: 21808728 | D17: 0.1096433 | E17: 474784.2 | F17: 313708.57 | G17: 20519480 | H17: 20519480 | I17: 18392420 | K17: 118164.9 | L17: 0.12840801 | M17: 2080.12 | N17: 544.54 | O17: 108925.69 | P17: 91331.22
A18: Testing & Commissioning | C18: 0 | D18: 0 | E18: 0 | F18: 0 | G18: 0 | H18: 0 | I18: 0 | K18: 10157.99 | L18: 0.011038534 | M18: 0 | N18: 0 | O18: 0 | P18: 6491.5
... A75: Construction | C75: 539598.47 | D75: 0.0027128293 | E75: 12910.2 | F75: 7596.95 | G75: 105845.69 | H75: 105845.69 | I75: 49342.79 | K75: 6017.94 | L75: 0.0065396042 | M75: 280.66 | N75: 405.4 | O75: 2345.94 | P75: 1270.07
A76: Provisional Sum | C76: 192900.72 | D76: 0.00096980766 | E76: 0 | F76: 0 | G76: 0 | H76: 0 | I76: 0
A77: Closeout | C77: 0 | D77: 0 | E77: 0 | F77: 0 | G77: 0 | H77: 0 | I77: 0 | K77: 0 | L77: 0 | M77: 0 | N77: 0 | O77: 0 | P77: 0
B78: Total | C78: 1.9890616e+08 | D78: 0.99903019 | E78: -12324623 | F78: 2986147.8 | G78: 1.3153529e+08 | H78: 1.3153529e+08 | I78: 1.0540208e+08 | K78: 920230.01 | L78: 1 | M78: 43051.96 | N78: 23539.36 | O78: 603257.91 | P78: =SUM(P7:P77)/2 -> 487990.69
E79: -0.061961997 | F79: 0.015012847 | G79: 0.66129318 | H79: 0.66129318 | I79: 0.52990858 | M79: 0.046783912 | N79: 0.025579866 | O79: 0.65555122 | P79: =P78/K78 -> 0.53029209
H82: =IF(G79=H79,"OK","") -> OK
M83: `

Sheet Weekly Photos
B1: Date | C1: ='Weekly Progress Report'!AG1 -> 46308
B4: Road & Plots Works | L4: Dry Utilities
B23: Wet Utilities | I23: Pump & Lift Station | P23: Box Culvert

Sheet FIR Summary
A2: Project Name | C2: ='General Information'!C3 -> Development of Infrastructure for phase 1 of the Logistics area at the 2nd Industrial City in Dammam | I2: Total FIR Amount
A3: Project ID | C3: ='General Information'!C4 -> DAM2-02-009 | D3: ='Weekly Progress Report'!B4 -> DAM2-02-009 | E3: Project Budget | F3: =Progress!C78 -> 1.9890616e+08 | I3: =G2295 -> 81734062
A4: Date Pariod | C4: Start Date | D4: =G4-6 -> 46302 | E4: To | F4: Data Date | G4: ='General Information'!L1 -> 46308
A6: BOQ Item # | B6: BOQ Description | C6: FIR # | D6: Date | E6: FIR Description | F6: Unit Rate | G6: Current Pariod Quantity | H6: Total (SR) | I6: Comments
K7: =I3/'Invoice Log'!E4 -> 0.41091769
A8: B1.1.02 41 00.01 | B8: Removal of curbstone | C8: DAM2-02-09-SAJ-TS9-1-ROD-FIR-0049-00 | D8: 45998 | E8: FIR for Removal of Existing curb stone as per attached as built Drawing DATA.Zone-1& 2.part 02. as highlighted in attached drawing | F8: 7.902 | G8: 1423.44 | H8: 11248.023
A9: B1.1.02 41 00.01 | B9: Removal of curbstone | C9: DAM2-02-09-SAJ-TS9-1-ROD-FIR-0060-00 | D9: 46005 | E9: FIR for Removal of Existing curb stone (Double) as per attached as built Drawing DATA.Zone-1& 2 | F9: 7.902 | G9: 2838.3 | H9: 22428.247
A10: B1.1.02 41 00.03 | B10: Removal of concrete protection | C10: DAM2-02-09-SAJ-TS9-1-ROD-FIR-0036-00 | D10: 45993 | E10: FIR for Removal of Existing curb stone as per attached as built Drawing DATA.Zone-1& 2.part 01. as highlighted in attached drawing | F10: 28.974 | G10: 3059.48 | H10: 88645.374
A11: B1.1.31 23 16.01 | B11: Excavation (all types of soil) | C11: DAM2-02-09-SAJ-TS9-1-SUR-FIR-0013-01 | D11: 45984 | E11: FIR for the PLOTS NO 4 - Replacement 50 cm | F11: 14.926 | G11: 27560.913 | H11: 411374.19
A12: B1.1.31 23 16.01 | B12: Excavation (all types of soil) | C12: DAM2-02-09-SAJ-TS9-1-SUR-FIR-0015-00 | D12: 45984 | E12: FIR for the PLOT No 5 -Replacement 50 cm | F12: 14.926 | G12: 11444.048 | H12: 170813.86
A13: B1.1.31 23 16.01 | B13: Excavation (all types of soil) | C13: DAM2-02-09-SAJ-TS9-1-SUR-FIR-0017-00 | D13: 45987 | E13: FIR for the cutting of Plot # 04 up to the depth from top of adjoining side Asphalt Road - 0.8 @ Zone-1 | F13: 14.926 | G13: 16997.485 | H13: 253704.46
A14: B1.1.31 23 16.01 | B14: Excavation (all types of soil) | C14: DAM2-02-09-SAJ-TS9-1-SUR-FIR-0018-01 | D14: 45992 | E14: FIR for the cutting of Plot # 05 (PGL-0.8) @ Zone-1 | F14: 14.926 | G14: 9500.5 | H14: 141804.46
A15: B1.1.31 23 16.01 | B15: Excavation (all types of soil) | C15: DAM2-02-09-SAJ-TS9-1-SUR-FIR-0019-01 | D15: 45992 | E15: FIR for replacement cutting for Part-1 of Plot # 01 as per attached Level Sheet (NGL-VAR) @ Zone-1 | F15: 14.926 | G15: 249.457 | H15: 3723.3952
A16: B1.1.31 23 16.01 | B16: Excavation (all types of soil) | C16: DAM2-02-09-SAJ-TS9-1-SUR-FIR-0020-01 | D16: 45992 | E16: FIR for replacement cutting of Part-01 Of Plot # 02 for fill Area as per attached Level Sheet (NGL- VAR) @ Zone-4 | F16: 14.926 | G16: 1548.02 | H16: 23105.747
A17: B1.1.31 23 16.01 | B17: Excavation (all types of soil) | C17: DAM2-02-09-SAJ-TS9-1-SUR-FIR-0021-01 | D17: 45992 | E17: FIR for replacement cutting for Part-01 OF Plot # 03 for fill area as per attached Level Sheet (NGL- VAR) @ Zone-4 | F17: 14.926 | G17: 883.95 | H17: 13193.838
A18: B1.1.31 23 16.01 | B18: Excavation (all types of soil) | C18: DAM2-02-09-SAJ-TS9-1-SUR-FIR-0026-01 | D18: 45992 | E18: cutting (PGL- 0.8) for Part-01 of Plot # 01 as per attached Level Sheet @ Zone-4 | F18: 14.926 | G18: 23527.23 | H18: 351167.43
A19: B1.1.31 23 16.01 | B19: Excavation (all types of soil) | C19: DAM2-02-09-SAJ-TS9-1-SUR-FIR-0027-01 | D19: 45992 | E19: Survey FIR for cutting (PGL - 0.8) for Part-01 Of Plot # 02 as per attached Level Sheet @ Zone-4 | F19: 14.926 | G19: 7677.069 | H19: 114587.93
... A33: B1.1.31 23 16.01 | B33: Excavation (all types of soil) | C33: DAM2-02-09-SAJ-TS9-1-SUR-FIR-0143-00 | D33: 46065 | E33: FIR OF Replacement cut (NGL-Variable) for fill Area Plot 6 (Part-1). | F33: 14.926 | G33: 9353.67 | H33: 139612.88
A34: B1.1.31 23 16.01 | B34: Excavation (all types of soil) | D34: 46196 | E34: As-built Qty for IPC-5 | F34: 14.926 | G34: 27104.166 | H34: 404556.78
A35: B1.1.31 23 16.01 | B35: Excavation (all types of soil) | D35: 46215 | E35: As-built Qty for IPC-6 | F35: 14.926 | G35: 16859.715 | H35: 251648.11
A36: B1.1.31 23 19.01 | B36: Surface Dewatering | C36: DAM2-02-09-SAJ-TS9-1-CVL-FIR-0001 | D36: 46006 | E36: FIR for 35 % DONE External surface Dewatering from Zone-04 to outside. | F36: 2897400 | G36: 0.345 | H36: 999603
A37: B1.1.31 23 19.01 | B37: Surface Dewatering | C37: DAM2-02-09-SAJ-TS9-1-CVL-FIR-0002 | D37: 46047 | E37: FIR for 35 % DONE External surface Dewatering from Zone-04 to outside. | F37: 2897400 | G37: 0.355 | H37: 1028577
A38: B1.1.31 23 19.01 | B38: Surface Dewatering | C38: DAM2-02-09-SAJ-TS9-1-CVL-FIR-0003 | D38: 46183 | E38: FIR for 30 % DONE External surface Dewatering | F38: 2897400 | G38: 0.3 | H38: 869220
A39: B1.1.31 23 23.01 | B39: Engineering backfiling | C39: DAM2-02-09-SAJ-TS9-1-SUR-FIR-0022-00 | D39: 45988 | E39: Survey and compaction testing for (30cm) fill of layer- 01 @ Plot 4 | F39: 28.096 | G39: 18402.62 | H39: 517040.01
A40: B1.1.31 23 23.01 | B40: Engineering backfiling | C40: DAM2-02-09-SAJ-TS9-1-SUR-FIR-0023-00 | D40: 45988 | E40: Survey and compaction testing for (30cm) fill of layer- 01 @ Plot 5 | F40: 28.096 | G40: 7868.85 | H40: 221083.21
A41: B1.1.31 23 23.01 | B41: Engineering backfiling | C41: DAM2-02-09-SAJ-TS9-1-SUR-FIR-0029-01 | D41: 45992 | E41: Survey and compaction testing for (30cm) fill of layer- 03 @ Plot 4 | F41: 28.096 | G41: 105 | H41: 2950.08
A42: B1.1.31 23 23.01 | B42: Engineering backfiling | C42: DAM2-02-09-SAJ-TS9-1-SUR-FIR-0032-00 | D42: 45994 | E42: Survey and compaction testing for (30cm) fill of layer- 04 @ Plot 5 | F42: 28.096 | G42: 1133.61 | H42: 31849.907
A43: B1.1.31 23 23.01 | B43: Engineering backfiling | C43: DAM2-02-09-SAJ-TS9-1-SUR-FIR-0033-00 | D43: 45995 | E43: Survey and compaction testing for (30cm) fill of layer- 05 @ Plot 5 | F43: 28.096 | G43: 694.79 | H43: 19520.82
A44: B1.1.31 23 23.01 | B44: Engineering backfiling | C44: DAM2-02-09-SAJ-TS9-1-SUR-FIR-0034-00 | D44: 45994 | E44: Survey and compaction testing for (30cm) fill of layer- 04 @ Plot 4 | F44: 28.096 | G44: 994.59 | H44: 27944.001
A45: B1.1.31 23 23.01 | B45: Engineering backfiling | C45: DAM2-02-09-SAJ-TS9-1-SUR-FIR-0035-00 | D45: 45994 | E45: Survey and compaction testing for (30cm) fill of layer- 05 @ Plot 4 | F45: 28.096 | G45: 853.98 | H45: 23993.422
A46: B1.1.31 23 23.01 | B46: Engineering backfiling | C46: DAM2-02-09-SAJ-TS9-1-SUR-FIR-0036-00 | D46: 45995 | E46: Survey and compaction testing for (30cm) fill of layer- 06 @ Plot 4 | F46: 28.096 | G46: 791.39 | H46: 22234.893
A47: B1.1.31 23 23.01 | B47: Engineering backfiling | C47: DAM2-02-09-SAJ-TS9-1-SUR-FIR-0037-00 | D47: 45997 | E47: Survey and compaction testing for (30cm) fill of layer- 07 @ Plot 4 | F47: 28.096 | G47: 1480.64 | H47: 41600.061
... A132: B1.1.31 23 23.01 | B132: Engineering backfiling | C132: DAM2-02-09-SAJ-TS9-1-SUR-FIR-0149-00 | D132: 46116 | E132: Inspection for Survey and compaction testing for 9th layer (30cm) fill at Plot 7 (Part 1)-1. | F132: 28.096 | G132: 1462.85 | H132: 41100.234
A133: B1.1.31 23 23.01 | B133: Engineering backfiling | E133: As-built qty for IPC-3 | F133: 28.096 | G133: 78368.706 | H133: 2201847.2
A134: B1.1.31 23 23.01 | B134: Engineering backfiling | D134: 46196 | E134: As-built qty for IPC-5 | F134: 28.096 | G134: 2791.2944 | H134: 78424.209
A135: B1.1.31 23 23.01 | B135: Engineering backfiling | D135: 46215 | E135: As-built qty for IPC-6 | F135: 28.096 | G135: 80724.259 | H135: 2268028.8
A136: B1.1.31 23 23.01 | B136: Engineering backfiling | D136: 46280 | E136: As-built qty for IPC-7 | F136: 28.096 | G136: 100264.76 | H136: 2817038.7
A137: B1.2.31 23 16.01 | B137: Roadway Excavation for cuttings (all types of soil) | C137: DAM2-02-09-SAJ-TS9-1-ROD-FIR-0001-00 | D137: 46011 | E137: FIR for Verification of Level Sheet (RD-1): From Station 00+10.00 to Station 00+830.00 Cutting up to PGL – 0.62 (CUT) | F137: 14.926 | G137: 23909.28 | H137: 356869.91
A138: B1.2.31 23 16.01 | B138: Roadway Excavation for cuttings (all types of soil) | C138: DAM2-02-09-SAJ-TS9-1-ROD-FIR-0002-00 | D138: 46011 | E138: Survey FIR for Verification of LEVEL SHEET (RD-2) - From Station 01+577.52 To Station 02+217.52, Cutting up PGL – 0.62 (CUT) | F138: 14.926 | G138: 16839.92 | H138: 251352.65
A139: B1.2.31 23 16.01 | B139: Roadway Excavation for cuttings (all types of soil) | C139: DAM2-02-09-SAJ-TS9-1-ROD-FIR-0003-00 | D139: 46007 | E139: Survey FIR for Verification of LEVEL SHEET (RD-2) - From Station 01+577.52 To Station 02+217.52, REPLACEMENT CUT ( 50cm) | F139: 14.926 | G139: 13115.5 | H139: 195761.95
A140: B1.2.31 23 16.01 | B140: Roadway Excavation for cuttings (all types of soil) | C140: DAM2-02-09-SAJ-TS9-1-ROD-FIR-0014-00 | D140: 46014 | E140: FIR for the 50cm Replacement cutting@ Asphalt Plot A, zone-1 | F140: 14.926 | G140: 12111.67 | H140: 180778.79
A141: B1.2.31 23 16.01 | B141: Roadway Excavation for cuttings (all types of soil) | C141: DAM2-02-09-SAJ-TS9-1-ROD-FIR-0019-00 | D141: 46015 | E141: FIR for Replacement cut (NGL -50 cm) in filling Area at Asphalt Plot C, Zone-3 | F141: 14.926 | G141: 3350 | H141: 50002.1
A142: B1.2.31 23 16.01 | B142: Roadway Excavation for cuttings (all types of soil) | C142: DAM2-02-09-SAJ-TS9-1-ROD-FIR-0020-00 | D142: 46017 | E142: FIR for the cutting ( NGL to PGL-1M ) in cutting area at Asphalt Plot C, zone-3 | F142: 14.926 | G142: 21847.34 | H142: 326093.4
A143: B1.2.31 23 16.01 | B143: Roadway Excavation for cuttings (all types of soil) | C143: DAM2-02-09-SAJ-TS9-1-ROD-FIR-0026-00 | D143: 45992 | E143: Survey FIR for Fill area REPLACMENT CUT -0.50 m from NGL in Plot D | F143: 14.926 | G143: 10121.35 | H143: 151071.27
A144: B1.2.31 23 16.01 | B144: Roadway Excavation for cuttings (all types of soil) | C144: DAM2-02-09-SAJ-TS9-1-ROD-FIR-0030-01 | D144: 45993 | E144: Survey FIR for Cut Area from NGL to PGL – 1 meter in Plot D | F144: 14.926 | G144: 9393.8 | H144: 140211.86
A145: B1.2.31 23 16.01 | B145: Roadway Excavation for cuttings (all types of soil) | C145: DAM2-02-09-SAJ-TS9-1-ROD-FIR-0037-00 | D145: 45993 | E145: Survey FIR for fill Area replacment cut - 0.50 m from NGL in Plot D | F145: 14.926 | G145: 7790.17 | H145: 116276.08
A146: B1.2.31 23 16.01 | B146: Roadway Excavation for cuttings (all types of soil) | C146: DAM2-02-09-SAJ-TS9-1-ROD-FIR-0055-00 | D146: 46004 | E146: Survey FIR for Fill area REPLACMENT CUT -0.50 m from NGL in Road 2 (Station 00+000 to 00+420) | F146: 14.926 | G146: 6115.11 | H146: 91274.132
A147: B1.2.31 23 16.01 | B147: Roadway Excavation for cuttings (all types of soil) | C147: DAM2-02-09-SAJ-TS9-1-ROD-FIR-0056-00 | D147: 46004 | E147: Survey FIR for Fill Area Replacement Cut -050 m from NGL in Plot D part 3 | F147: 14.926 | G147: 5598.41 | H147: 83561.868
A148: B1.2.31 23 16.01 | B148: Roadway Excavation for cuttings (all types of soil) | C148: DAM2-02-09-SAJ-TS9-1-ROD-FIR-0061-00 | D148: 46005 | E148: Survey FIR for Cut Area from NGL to PGL – 1 meter in Plot D Part 3 | F148: 14.926 | G148: 11386.78 | H148: 169959.08
... A195: B1.2.31 23 16.01 | B195: Roadway Excavation for cuttings (all types of soil) | C195: DAM2-02-09-SAJ-TS9-1-ROD-FIR-0284-00 | D195: 46109 | E195: Survey FIR for Cut Area from NGL to PGL – 1 meter at Roundabout, Station (0+010 to 0+058.255). | F195: 14.926 | G195: 2422.43 | H195: 36157.19
A196: B1.2.31 23 16.01 | B196: Roadway Excavation for cuttings (all types of soil) | D196: 46196 | E196: As-built qty for IPC-5 | F196: 14.926 | G196: 31005.83 | H196: 462793.02
A197: B1.2.31 23 16.01 | B197: Roadway Excavation for cuttings (all types of soil) | D197: 46215 | E197: As-built qty for IPC-6 | F197: 14.926 | G197: 60180.305 | H197: 898251.23
A198: B1.2.31 23 16.01 | B198: Roadway Excavation for cuttings (all types of soil) | D198: 46280 | E198: As-built qty for IPC-7 | F198: 14.926 | G198: 11582.774 | H198: 172884.48
A199: B1.2.31 23 23.01 | B199: Embankment backfiling | C199: DAM2-02-09-SAJ-TS9-1-ROD-FIR-0004-00 | D199: 46007 | E199: FIR for Verification of Level Sheet (RD-1): From Station 00+20.00 to Station 00+830.00 FILL (30cm). LAYER #1 | F199: 27.218 | G199: 9284.22 | H199: 252697.9
A200: B1.2.31 23 23.01 | B200: Embankment backfiling | C200: DAM2-02-09-SAJ-TS9-1-ROD-FIR-0005-00 | D200: 46009 | E200: Survey FIR for fill placement of LAYER- 01 From Station 01+577.52 To Station 02+217.52@ RD-2, ZONE-04(level sheet is attached) | F200: 27.218 | G200: 5684.67 | H200: 154725.35
A201: B1.2.31 23 23.01 | B201: Embankment backfiling | C201: DAM2-02-09-SAJ-TS9-1-ROD-FIR-0007-00 | D201: 46010 | E201: Survey FIR for fill placement(30cm) of layer- 02 From Station 00+20.00 to Station 00+830.00@ RD-1, ZONE-01 (level sheet is attached) | F201: 27.218 | G201: 4280.45 | H201: 116505.29
A202: B1.2.31 23 23.01 | B202: Embankment backfiling | C202: DAM2-02-09-SAJ-TS9-1-ROD-FIR-0009-00 | D202: 46011 | E202: Survey FIR for fill placement of LAYER- 02 From Station 01+577.52 To Station 02+217.52@ RD-2, ZONE-04 (level sheet is attached) | F202: 27.218 | G202: 4280.45 | H202: 116505.29
A203: B1.2.31 23 23.01 | B203: Embankment backfiling | C203: DAM2-02-09-SAJ-TS9-1-ROD-FIR-0012-00 | D203: 46014 | E203: Survey FIR for fill placement(30cm) of layer- 03 From Station 00+20.00 to Station 00+830.00 @ RD-1, ZONE-01 | F203: 27.218 | G203: 7650.73 | H203: 208237.57
A204: B1.2.31 23 23.01 | B204: Embankment backfiling | C204: DAM2-02-09-SAJ-TS9-1-ROD-FIR-0013-00 | D204: 46014 | E204: Survey FIR for fill placement of LAYER- 03 From Station 01+577.52 To Station 02+217.52@ RD-2, ZONE-04 | F204: 27.218 | G204: 3727.118 | H204: 101444.7
A205: B1.2.31 23 23.01 | B205: Embankment backfiling | C205: DAM2-02-09-SAJ-TS9-1-ROD-FIR-0017-00 | D205: 46015 | E205: Survey FIR for fill placement of LAYER- 01 @ Asphalt Plot A, Zone-01 | F205: 27.218 | G205: 7102.5 | H205: 193315.85
A206: B1.2.31 23 23.01 | B206: Embankment backfiling | C206: DAM2-02-09-SAJ-TS9-1-ROD-FIR-0021-00 | D206: 46017 | E206: Survey FIR for fill placement(30cm) of layer- 04 From Station 00+20.00 to Station 00+830.00 @ RD-1, ZONE-01 | F206: 27.218 | G206: 6046.08 | H206: 164562.21
A207: B1.2.31 23 23.01 | B207: Embankment backfiling | C207: DAM2-02-09-SAJ-TS9-1-ROD-FIR-0022-00 | D207: 46017 | E207: Survey FIR for fill placement of LAYER- 04 From Station 01+577.52 To Station 02+217.52@ RD-2, ZONE-04 | F207: 27.218 | G207: 2856.19 | H207: 77739.779
A208: B1.2.31 23 23.01 | B208: Embankment backfiling | C208: DAM2-02-09-SAJ-TS9-1-ROD-FIR-0027-00 | D208: 46018 | E208: Survey and Compaction FIR for fill placement (30 cm) of LAYER-01 @ Asphalt Plot C, Zone-03 | F208: 27.218 | G208: 1933.44 | H208: 52624.37
A209: B1.2.31 23 23.01 | B209: Embankment backfiling | C209: DAM2-02-09-SAJ-TS9-1-ROD-FIR-0028-00 | D209: 46020 | E209: Survey and Compaction FIR for fill placement (30 cm) of LAYER-02 @ Asphalt Plot C, Zone-03 | F209: 27.218 | G209: 1564.77 | H209: 42589.91
A210: B1.2.31 23 23.01 | B210: Embankment backfiling | C210: DAM2-02-09-SAJ-TS9-1-ROD-FIR-0029-00 | D210: 46020 | E210: Survey and Compaction FIR for fill placement (30 cm) of LAYER-03 @ Asphalt Plot A, Zone-01 | F210: 27.218 | G210: 6944.55 | H210: 189016.76
... A398: B1.2.31 23 23.01 | B398: Embankment backfiling | C398: DAM2-02-09-SAJ-TS9-1-ROD-FIR-0296-00 | D398: 46114 | E398: Inspection for survey works and compaction testing for 6th Fill layer (30 cm), at Roundabout, Station (0+000 to 0+006.005 & 0+066.466 TO 0+084.099). | F398: 27.218 | G398: 247.15 | H398: 6726.9287
A399: B1.2.31 23 23.01 | B399: Embankment backfiling | D399: 46196 | E399: As-built qty for IPC-5 | F399: 27.218 | G399: 50358.14 | H399: 1370647.9
A400: B1.2.31 23 23.01 | B400: Embankment backfiling | D400: 46280 | E400: As-built qty for IPC-7 | F400: 27.218 | G400: 101932.33 | H400: 2774394
A401: B1.2.32 11 13.01 | B401: Subgrade | C401: DAM2-02-09-SAJ-TS9-1-ROD-FIR-0315-00 | D401: 46147 | E401: Inspection for survey works and compaction testing of the Subgrade layer (30 cm) at Asphalt Plot A, Zone 1. | F401: 29.852 | G401: 7267.05 | H401: 216935.98
A402: B1.2.32 11 13.01 | B402: Subgrade | C402: DAM2-02-09-SAJ-TS9-1-ROD-FIR-0343-00 | D402: 46163 | E402: Inspection for survey works and compaction testing of the Subgrade layer (30 cm) at Arterial Road from Station 0+220 to 0+550. | F402: 29.852 | G402: 1159.949 | H402: 34626.798
A403: B1.2.32 11 13.01 | B403: Subgrade | C403: DAM2-02-09-SAJ-TS9-1-ROD-FIR-0348-00 | D403: 46174 | E403: Inspection for survey works and compaction testing of the Subgrade layer (30 cm) at Asphalt Plot D (Part 1). | F403: 29.852 | G403: 3418.685 | H403: 102054.58
A404: B1.2.32 11 13.01 | B404: Subgrade | C404: DAM2-02-09-SAJ-TS9-1-ROD-FIR-0356-00 | D404: 46181 | E404: Inspection for survey works and compaction testing of the Subgrade layer (30 cm) at Asphalt Plot D (Part 2). | F404: 29.852 | G404: 2795.595 | H404: 83454.102
A405: B1.2.32 11 13.01 | B405: Subgrade | C405: DAM2-02-09-SAJ-TS9-1-ROD-FIR-0362-00 | D405: 46183 | E405: Inspection for survey works and compaction testing of the Subgrade layer (30 cm) at Arterial Road from Station 0+550 to 0+710. | F405: 29.852 | G405: 474.147 | H405: 14154.236
A406: B1.2.32 11 13.01 | B406: Subgrade | C406: DAM2-02-09-SAJ-TS9-1-ROD-FIR-0371-00 | D406: 46187 | E406: Inspection for survey works and compaction testing of the Subgrade layer (30 cm) at Asphalt Plot D (Part 3). | F406: 29.852 | G406: 2098.494 | H406: 62644.243
A407: B1.2.32 11 13.01 | B407: Subgrade | C407: DAM2-02-09-SAJ-TS9-1-ROD-FIR-0390-00 | D407: 46193 | E407: Inspection for survey works and compaction testing of the Subgrade layer (30 cm) at Asphalt Plot D (Part 4). | F407: 29.852 | G407: 2204.553 | H407: 65810.316
A408: B1.2.32 11 13.01 | B408: Subgrade | C408: DAM2-02-09-SAJ-TS9-1-ROD-FIR-0422-00 | D408: 46197 | E408: Inspection for survey works and compaction testing of the Subgrade layer (30 cm) at Arterial Road from Station 0+026 to 0+200 (R/S). | F408: 29.852 | G408: 732.657 | H408: 21871.277
A409: B1.2.32 11 13.01 | B409: Subgrade | C409: DAM2-02-09-SAJ-TS9-1-ROD-FIR-0458-00 | D409: 46207 | E409: Inspection for survey works and compaction testing of the Subgrade layer (30 cm) at Asphalt Plot D (Part 5). | F409: 29.852 | G409: 1580.091 | H409: 47168.877
A410: B1.2.32 11 13.01 | B410: Subgrade | C410: DAM2-02-09-SAJ-TS9-1-ROD-FIR-0521-00 | D410: 46215 | E410: Inspection for survey works and compaction testing of the Subgrade layer (30 cm) at Asphalt Plot C (Part 1). | F410: 29.852 | G410: 1475.268 | H410: 44039.7
A411: B1.2.32 11 13.01 | B411: Subgrade | C411: DAM2-02-09-SAJ-TS9-1-ROD-FIR-0543-00 | D411: 46218 | E411: Inspection for survey works and compaction testing of the Subgrade layer (30 cm) at Asphalt Plot C (Part 2). | F411: 29.852 | G411: 3232.218 | H411: 96488.172
A412: B1.2.32 11 13.01 | B412: Subgrade | C412: DAM2-02-09-SAJ-TS9-1-ROD-FIR-0544-00 | D412: 46218 | E412: Inspection for survey works and compaction testing of the Subgrade layer (30 cm) at Asphalt Plot C (Part 3). | F412: 29.852 | G412: 1336.413 | H412: 39894.601
... A511: B2.33 71 00 01 01 | B511: Cable, Copper 4x10mm2/ CU/XLPE/SWA/PVC + 1x10mm2 CU/PVC | C511: DAM2-02-09-SAJ-TS9-1-ELE-FIR-0069 | D511: 46284 | E511: FIR for Cable (4x10mm2) Installation for Street Lighting Pole at Road (Arterial RD) Right Side. Sta. 0+052.2 to 0+509.6. @Zone-3 Pole Number :- FP-23-2 to FP-23-2/6/1R = 12m FP-23-2/6/1R to FP-23-2/6/2Y = 34.2m FP-23-2/6/2Y to FP-23-2/6/3B = 34.2m FP-23-2/6/3B to FP-23-2/6/4R = 34.2m FP-23-2/6/4R to FP-23-2/6/5Y = 34.2m FP-23-2/6/5Y to FP-23-2/6/6B = 34.2m FP-23-2/6/6B to FP-23-2/6/7R = 34.2m FP-23-2/6/7R to FP-23-2/6/8Y = 34.2m FP-23-2/6/8Y to FP-23-2/6/9B = 34.2m FP-23-2/6/9B to FP-23-2/6/10R = 34.2m FP-23-2/6/10R to FP-23-2/6/11Y = 34.2m FP-23-2/6/11Y to FP-23-2/6/12B = 34.2m FP-23-2 to FP-23-2/5/1R = 37.5m FP-23-2/5/1R to FP-23-2/5/2Y = 34.2m FP-23-2/5/2Y to FP-23-2/5/3B = 34.2m FP-23-2/5/3B to FP-23-2/5/4R = 34.2m | F511: 62.338 | G511: 316.98 | H511: 19759.899
A512: B2.33 71 00 01 01 | B512: Cable, Copper 4x10mm2/ CU/XLPE/SWA/PVC + 1x10mm2 CU/PVC | C512: DAM2-02-09-SAJ-TS9-1-ELE-FIR-0157 | D512: 46301 | F512: 62.338 | G512: 105.66 | H512: 6586.6331
A513: B2.33 71 16.02 | B513: Lighting poles with 1 arm, height of ( 10) meters, including the power distribution box, cables , and RCC foundation. | C513: DAM2-02-09-SAJ-TS9-1-ELE-FIR-0007 | D513: 46263 | E513: FIR for Survey of Excavation , Compation and Gravel Bedding Placement for Lighting Pole Foundation at Road (RD - 01). Pole Number :- 1) FP-22-2/4/2Y 8) FP-22-2/4/10R 2) FP-22-2/4/3B 9) FP-22-2/4/11Y 3) FP-22-2/4/4R 10) FP-22-2/4/12B 4) FP-22-2/4/5Y 11) FP-22-2/4/13R 5) FP-22-2/4/6B 6) FP-22-2/4/7R 7) FP-22-2/4/8Y | F513: 8923.992 | G513: 0.55 | H513: 4908.1956
A514: B2.33 71 16.02 | B514: Lighting poles with 1 arm, height of ( 10) meters, including the power distribution box, cables , and RCC foundation. | C514: DAM2-02-09-SAJ-TS9-1-ELE-FIR-0008 | D514: 46263 | E514: FIR for Survey of Excavation , Compation and Gravel Bedding Placement for Lighting Pole Foundation at Road (RD - 01). Pole Number :- 1) FP-22-2/4/14Y 8) FP-22-2/4/21B 2) FP-22-2/4/15B 9) FP-22-2/4/22R 3) FP-22-2/4/16R 10) FP-22-2/4/23Y 4) FP-22-2/4/17Y 11) FP-22-2/4/24B 5) FP-22-2/4/18B 12) FP-22-2/4/25R 6) FP-22-2/4/19R 13) FP-22-2/4/26Y 7) FP-22-2/4/20Y 14) FP-22-2/4/27B | F514: 8923.992 | G514: 0.7 | H514: 6246.7944
A515: B2.33 71 16.02 | B515: Lighting poles with 1 arm, height of ( 10) meters, including the power distribution box, cables , and RCC foundation. | C515: DAM2-02-09-SAJ-TS9-1-ELE-FIR-0011 | D515: 46264 | E515: FIR for Survey of Concrete Foundation Installation for Lighting Pole at Road (RD - 01). @Zone-1 Pole Number :- 1) FP-22-2/4/2Y 8) FP-22-2/4/10R 2) FP-22-2/4/3B 9) FP-22-2/4/11Y 3) FP-22-2/4/4R 10) FP-22-2/4/12B 4) FP-22-2/4/5Y 11) FP-22-2/4/13R 5) FP-22-2/4/6B 6) FP-22-2/4/7R 7) FP-22-2/4/8Y | F515: 8923.992 | G515: 1.65 | H515: 14724.587
A516: B2.33 71 16.02 | B516: Lighting poles with 1 arm, height of ( 10) meters, including the power distribution box, cables , and RCC foundation. | C516: DAM2-02-09-SAJ-TS9-1-ELE-FIR-0012 | D516: 46264 | E516: FIR for Survey of Concrete Foundation Installation for Lighting Pole at Road (RD - 01). @Zone-1 Pole Number :- 1) FP-22-2/4/14Y 8) FP-22-2/4/21B 2) FP-22-2/4/15B 9) FP-22-2/4/22R 3) FP-22-2/4/16R 10) FP-22-2/4/23Y 4) FP-22-2/4/17Y 11) FP-22-2/4/24B 5) FP-22-2/4/18B 12) FP-22-2/4/25R 6) FP-22-2/4/19R 13) FP-22-2/4/26Y 7) FP-22-2/4/20Y 14) FP-22-2/4/27B | F516: 8923.992 | G516: 2.1 | H516: 18740.383
A517: B2.33 71 16.02 | B517: Lighting poles with 1 arm, height of ( 10) meters, including the power distribution box, cables , and RCC foundation. | C517: DAM2-02-09-SAJ-TS9-1-ELE-FIR-0027 | D517: 46268 | E517: Survey for Excavation and Gravel Bedding Placement for Lighting Pole Foundation at Road (RD-01). Zone-1 Pole Number: - 1) FP-22-2/3/13R 8) FP-22-2/3/21B 2) FP-22-2/3/15B 9) FP-22-2/3/22R 3) FP-22-2/3/16R 10) FP-22-2/3/23Y 4) FP-22-2/3/17Y 11) FP-22-2/3/24B 5) FP-22-2/3/18B 12) FP-22-2/3/25R 6) FP-22-2/3/19R 13) FP-22-2/3/26Y 7) FP-22-2/3/20Y 14) FP-22-2/3/27B | F517: 8923.992 | G517: 0.7 | H517: 6246.7944
A518: B2.33 71 16.02 | B518: Lighting poles with 1 arm, height of ( 10) meters, including the power distribution box, cables , and RCC foundation. | C518: DAM2-02-09-SAJ-TS9-1-ELE-FIR-0028 | D518: 46268 | E518: Survey for Excavation and Gravel Bedding Placement for Lighting Pole Foundation at Road (RD-01). Zone-1 Pole Number: - 1) FP-22-2/3/28R 8) FP-22-2/3/35Y 2) FP-22-2/3/29Y 9) FP-22-2/3/36B 3) FP-22-2/3/30B 10) FP-22-2/3/37R 4) FP-22-2/3/31R 11) FP-22-2/4/9B 5) FP-22-2/3/32Y 12) FP-22-2/4/28R 6) FP-22-2/3/33B 13) FP-22-2/4/29Y 7) FP-22-2/3/34R 14) FP-22-2/4/30B | F518: 8923.992 | G518: 0.7 | H518: 6246.7944
A519: B2.33 71 16.02 | B519: Lighting poles with 1 arm, height of ( 10) meters, including the power distribution box, cables , and RCC foundation. | C519: DAM2-02-09-SAJ-TS9-1-ELE-FIR-0030 | D519: 46272 | E519: FIR for Survey of Concrete Foundation Installation for Lighting Pole at Road (RD-01) Left Side. Zone-1 Pole Number: - 1) FP-22-2/3/13R 8) FP-22-2/3/21B 2) FP-22-2/3/15B 9) FP-22-2/3/22R 3) FP-22-2/3/16R 10) FP-22-2/3/23Y 4) FP-22-2/3/17Y 11) FP-22-2/3/24B 5) FP-22-2/3/18B 12) FP-22-2/3/25R 6) FP-22-2/3/19R 13) FP-22-2/3/26Y 7) FP-22-2/3/20Y 14) FP-22-2/3/27B | F519: 8923.992 | G519: 2.1 | H519: 18740.383
A520: B2.33 71 16.02 | B520: Lighting poles with 1 arm, height of ( 10) meters, including the power distribution box, cables , and RCC foundation. | C520: DAM2-02-09-SAJ-TS9-1-ELE-FIR-0031 | D520: 46272 | E520: FIR for Survey of Concrete Foundation Installation for Lighting Pole at Road (RD-01) Right & Left Side. Zone-1 Pole Number: - 1) FP-22-2/3/28R 8) FP-22-2/3/35Y 2) FP-22-2/3/29Y 9) FP-22-2/3/36B 3) FP-22-2/3/30B 10) FP-22-2/3/37R 4) FP-22-2/3/31R 11) FP-22-2/4/9B 5) FP-22-2/3/32Y 12) FP-22-2/4/28R 6) FP-22-2/3/33B 13) FP-22-2/4/29Y 7) FP-22-2/3/34R 14) FP-22-2/4/30B | F520: 8923.992 | G520: 2.1 | H520: 18740.383
A521: B2.33 71 16.02 | B521: Lighting poles with 1 arm, height of ( 10) meters, including the power distribution box, cables , and RCC foundation. | C521: DAM2-02-09-SAJ-TS9-1-ELE-FIR-0032 | D521: 46272 | E521: FIR for Assembly & Survey for the Installation of Lighting Pole with arm, including the power Distribution box, at Road (RD - 01) Right Side. @Zone -1 Pole Number :- 1) FP-22-2/4/2Y 8) FP-22-2/4/10R 2) FP-22-2/4/3B 9) FP-22-2/4/11Y 3) FP-22-2/4/4R 10) FP-22-2/4/12B 4) FP-22-2/4/5Y 11) FP-22-2/4/13R 5) FP-22-2/4/6B 6) FP-22-2/4/7R 7) FP-22-2/4/8Y | F521: 8923.992 | G521: 7.15 | H521: 63806.543
A522: B2.33 71 16.02 | B522: Lighting poles with 1 arm, height of ( 10) meters, including the power distribution box, cables , and RCC foundation. | C522: DAM2-02-09-SAJ-TS9-1-ELE-FIR-0033 | D522: 46272 | E522: FIR for Assembly & Survey for the Installation of Lighting Pole with arm, including the power Distribution box, at Road (RD - 01) Right Side. @Zone-1 Pole Number :- 1) FP-22-2/4/14Y 8) FP-22-2/4/21B 2) FP-22-2/4/15B 9) FP-22-2/4/22R 3) FP-22-2/4/16R 10) FP-22-2/4/23Y 4) FP-22-2/4/17Y 11) FP-22-2/4/24B 5) FP-22-2/4/18B 12) FP-22-2/4/25R 6) FP-22-2/4/19R 13) FP-22-2/4/26Y 7) FP-22-2/4/20Y 14) FP-22-2/4/27B | F522: 8923.992 | G522: 9.1 | H522: 81208.327
A523: B2.33 71 16.02 | B523: Lighting poles with 1 arm, height of ( 10) meters, including the power distribution box, cables , and RCC foundation. | C523: DAM2-02-09-SAJ-TS9-1-ELE-FIR-0043 | D523: 46273 | E523: FIR for Assembly & Survey for the Installation of Lighting Pole with arm, including the power Distribution box, at Road (RD-01) Left Side. Zone-1 Pole Number: - 1) FP-22-2/3/13R 8) FP-22-2/3/21B 2) FP-22-2/3/15B 9) FP-22-2/3/22R 3) FP-22-2/3/16R 10) FP-22-2/3/23Y 4) FP-22-2/3/17Y 11) FP-22-2/3/24B 5) FP-22-2/3/18B 12) FP-22-2/3/25R 6) FP-22-2/3/19R 13) FP-22-2/3/26Y 7) FP-22-2/3/20Y 14) FP-22-2/3/27B | F523: 8923.992 | G523: 9.1 | H523: 81208.327
A524: B2.33 71 16.02 | B524: Lighting poles with 1 arm, height of ( 10) meters, including the power distribution box, cables , and RCC foundation. | C524: DAM2-02-09-SAJ-TS9-1-ELE-FIR-0044 | D524: 46273 | E524: FIR for Assembly & Survey for the Installation of Lighting Pole with arm, including the power Distribution box, at Road (RD-01) Right & Left Side. Zone-1 Pole Number: - 1) FP-22-2/3/28R 8) FP-22-2/3/35Y 2) FP-22-2/3/29Y 9) FP-22-2/3/36B 3) FP-22-2/3/30B 10) FP-22-2/3/37R 4) FP-22-2/3/31R 11) FP-22-2/4/9B 5) FP-22-2/3/32Y 12) FP-22-2/4/28R 6) FP-22-2/3/33B 13) FP-22-2/4/29Y 7) FP-22-2/3/34R 14) FP-22-2/4/30B | F524: 8923.992 | G524: 9.1 | H524: 81208.327
... A1161: B5.33 31 00.02.03 | B1161: 200mm Diameter Depth: 2.51m - 3.5m | C1161: DAM2-02-09-SAJ-TS9-1-SEW-FIR-1362 | D1161: 46295 | E1161: Mechanical FIR for Final Air testing of GRP Sewerage Drainage PIPE from MH-A-14-0 to MH-A-14-1 ZONE-04 | F1161: 398.612 | G1161: 6.28 | H1161: 2503.2834
F1162: 398.612 | G1162: 838.42 | H1162: 334204.27
A1163: B5.33 31 00.02.04 | B1163: 200mm Diameter Depth: 3.51m -4.5m | C1163: DAM2-02-09-SAJ-TS9-1-SEW-FIR-0128-00 | D1163: 46037 | E1163: Survey FIR for Excavation and Compaction Testing of Sewerage Pipe Line from MH-B-11 TO MH-B-10, LINE B @ ZONE-03 | F1163: 459.194 | G1163: 8.26 | H1163: 3792.9424
A1164: B5.33 31 00.02.04 | B1164: 200mm Diameter Depth: 3.51m -4.5m | C1164: DAM2-02-09-SAJ-TS9-1-SEW-FIR-0134-00 | D1164: 46041 | E1164: Survey FIR for Gravel Bedding with Geotextile of Sewerage Pipeline from MH-B-11 TO MH-B-10, LINE B @ ZONE-03 | F1164: 459.194 | G1164: 2.76 | H1164: 1267.3754
A1165: B5.33 31 00.02.04 | B1165: 200mm Diameter Depth: 3.51m -4.5m | C1165: DAM2-02-09-SAJ-TS9-1-SEW-FIR-0138-00 | D1165: 46042 | E1165: Mechanical FIR for Installation and Laying of Sewerage Pipeline form MH-B-11 TO MH-B-10, LINE B @ ZONE-03 Pipe DIA 200MM | F1165: 459.194 | G1165: 33.06 | H1165: 15180.954
A1166: B5.33 31 00.02.04 | B1166: 200mm Diameter Depth: 3.51m -4.5m | C1166: DAM2-02-09-SAJ-TS9-1-SEW-FIR-0142-00 | D1166: 46042 | E1166: Mechanical FIR Initial Air Test of Sewerage Pipeline form MH-B-11 TO MH-B-10, Line B @ ZONE-03 Pipe DIA 200MM | F1166: 459.194 | G1166: 2.76 | H1166: 1267.3754
...

Sheet Quality
B2: QC OBSERVATIONS CHECKLIST
BB4: 45986
B6: Project No. | E6: ='General Information'!C4 -> DAM2-02-009 | K6: OBS No. | O6: =((X6-BB4)/7)-1 -> 45 | U6: Inspection Day: | X6: ='General Information'!L1 -> 46308
B8: Project | E8: ='General Information'!C3 -> Development of Infrastructure for phase 1 of the Logistics area at the 2nd Industrial City in Dammam | O8: Contractor: Consultant: | U8: Shibh Aljazira Contracting Company Egis
B10: 4 | D10: Excellent | G10: Quality Management System is being practiced and applies to MODON System | Z10: 90 - 100 | AB10: QC Overall Score | AC10: =Q49 -> 0.93 | AN10: =SUM(Z10:Z13) -> 0 | AO10: 100 | AP10: 0.22883295
B11: 3 | D11: Good | G11: Evidence of compliance with plans and procedures. | Z11: 80 - 89 | AN11: =SUM(Y10:Y14) -> 0 | AO11: 89 | AP11: 0.20366133
B12: 2 | D12: Average | G12: Indication level of compliance with standards but there is room for improvement | Z12: 70 - 79 | AO12: 79 | AP12: 0.18077803
B13: 1 | D13: Improve | G13: Quality and Control is NOT being managed effectively. Needs Improvement | Z13: ≤ 69 | AO13: 69 | AP13: 0.15789474
B14: 0 | D14: N/A | G14: Item was not applicable or this item was not reviewed during the inspection. | Z14: Zero | AO14: 100 | AP14: 0.22883295
B16: No. | C16: Topic | K16: E (4) | L16: G (3) | M16: A (2) | N16: I (1) | O16: N/A (0) | Q16: No. | R16: Topic | Z16: E (4) | AA16: G (3) | AB16: A (2) | AC16: I (1) | AD16: N/A (0) | AO16: =SUM(AO10:AO15) -> 437
K17: 1 | L17: 0.89 | M17: 0.79 | N17: 0.69 | O17: 1 | Z17: 1 | AA17: 0.89 | AB17: 0.79 | AC17: 0.69 | AD17: 1 | AF17: =SUM(AF18:AG46)/COUNT(AF18:AG46) -> 0.91810345
B18: 1 | C18: Control of Access to Site/Office | L18: 1 | Q18: 30 | R18: QC of Excavation | Z18: 0 | AA18: 0 | AB18: 1 | AF18: =SUMPRODUCT($K$17:$O$17,K18:O18) -> 0.89 | AG18: =SUMPRODUCT($Z$17:$AD$17,Z18:AD18) -> 0.79 | AV18: Item Count | AW18: Score | AX18: Distributtion
B19: 2 | C19: Document Control Administration | L19: 1 | M19: 0 | Q19: 31 | R19: QC of Roads/Round about | Z19: 0 | AA19: 0 | AB19: 1 | AC19: 0 | AD19: 0 | AF19: =SUMPRODUCT($K$17:$O$17,K19:O19) -> 0.89 | AG19: =SUMPRODUCT($Z$17:$AD$17,Z19:AD19) -> 0.79 | AX19: Overall | AY19: Relevant
B20: 3 | C20: Project Documents and Progress | L20: 1 | M20: 0 | Q20: 32 | R20: QC of Interlock & Curbstone | Z20: 0 | AB20: 1 | AD20: 0 | AF20: =SUMPRODUCT($K$17:$O$17,K20:O20) -> 0.89 | AG20: =SUMPRODUCT($Z$17:$AD$17,Z20:AD20) -> 0.79 | AM20: 4 | AN20: =58 -> 58 | AO20: counts | AQ20: 4 | AR20: Excellent | AV20: =SUM(Z18:Z46,K18:K46) -> 4 | AW20: =AQ20*AV20 -> 16 | AX20: =AV20/$AV$25 -> 0.068965517 | AY20: =AV20/SUM($AV$20:$AV$23) -> 0.1
B21: 4 | C21: Contractor's Quality Plan/CM (Updated and Reviewed) | L21: 1 | M21: 0 | Q21: 33 | R21: Layers/Backfilling Sampling | Z21: 0 | AA21: 1 | AB21: 0 | AC21: 0 | AD21: 0 | AF21: =SUMPRODUCT($K$17:$O$17,K21:O21) -> 0.89 | AG21: =SUMPRODUCT($Z$17:$AD$17,Z21:AD21) -> 0.89 | AM21: 3 | AN21: =58 -> 58 | AO21: counts | AQ21: 3 | AR21: Good | AV21: =SUM(L18:L46,AA18:AA46) -> 20 | AW21: =AQ21*AV21 -> 60 | AX21: =AV21/$AV$25 -> 0.34482759 | AY21: =AV21/SUM($AV$20:$AV$23) -> 0.5
B22: 5 | C22: MS Log and Paperwork | L22: 1 | M22: 0 | Q22: 34 | R22: Pump Stations Units | Z22: 0 | AD22: 1 | AF22: =SUMPRODUCT($K$17:$O$17,K22:O22) -> 0.89 | AG22: =SUMPRODUCT($Z$17:$AD$17,Z22:AD22) -> 1 | AM22: 2 | AN22: =58 -> 58 | AO22: counts | AQ22: 2 | AR22: Average | AV22: =SUM(M18:M46,AB18:AB46) -> 12 | AW22: =AQ22*AV22 -> 24 | AX22: =AV22/$AV$25 -> 0.20689655 | AY22: =AV22/SUM($AV$20:$AV$23) -> 0.3 | BC22: NB: Insert 1, or 0 in the required cell only.
B23: 6 | C23: RFI, FIR, & MIR Procedure | L23: 0 | M23: 1 | Q23: 35 | R23: Quality of Form Work | Z23: 0 | AA23: 0 | AB23: 0 | AC23: 1 | AD23: 0 | AF23: =SUMPRODUCT($K$17:$O$17,K23:O23) -> 0.79 | AG23: =SUMPRODUCT($Z$17:$AD$17,Z23:AD23) -> 0.69 | AM23: 1 | AN23: =58 -> 58 | AO23: counts | AQ23: 1 | AR23: Improve | AV23: =SUM(N18:N46,AC18:AC46) -> 4 | AW23: =AQ23*AV23 -> 4 | AX23: =AV23/$AV$25 -> 0.068965517 | AY23: =AV23/SUM($AV$20:$AV$23) -> 0.1
B24: 7 | C24: RFI, FIR, & MIR Inventory system | L24: 1 | M24: 0 | Q24: 36 | R24: Design Change List | AC24: 0 | AD24: 1 | AF24: =SUMPRODUCT($K$17:$O$17,K24:O24) -> 0.89 | AG24: =SUMPRODUCT($Z$17:$AD$17,Z24:AD24) -> 1 | AM24: 0 | AN24: =58 -> 58 | AO24: counts | AQ24: 0 | AR24: N/A | AV24: =SUM(O18:O46,AD18:AD46) -> 18 | AW24: =AQ24*AV24 -> 0 | AX24: =AV24/$AV$25 -> 0.31034483 | AY24: -
B25: 8 | C25: NCRs Control & Procedure | L25: 1 | M25: 0 | O25: 0 | Q25: 37 | R25: Quality of Concrete Placing | AA25: 0 | AB25: 0 | AC25: 1 | AD25: 0 | AF25: =SUMPRODUCT($K$17:$O$17,K25:O25) -> 0.89 | AG25: =SUMPRODUCT($Z$17:$AD$17,Z25:AD25) -> 0.69 | AR25: Total | AV25: =SUM(AV20:AV24) -> 58 | AW25: =SUM(AW20:AW24) -> 104 | AX25: =SUM(AX20:AX24) -> 1 | AY25: =SUM(AY20:AY24) -> 1
B26: 9 | C26: NCR Log | K26: 0 | L26: 1 | Q26: 38 | R26: Concrete Surface Finishing | Z26: 0 | AA26: 0 | AB26: 1 | AD26: 0 | AF26: =SUMPRODUCT($K$17:$O$17,K26:O26) -> 0.89 | AG26: =SUMPRODUCT($Z$17:$AD$17,Z26:AD26) -> 0.79
B27: 10 | C27: MODON Standard* | K27: 0 | L27: 1 | Q27: 39 | R27: Pedestals/Columns/Beams Alignment | Z27: 0 | AD27: 1 | AF27: =SUMPRODUCT($K$17:$O$17,K27:O27) -> 0.89 | AG27: =SUMPRODUCT($Z$17:$AD$17,Z27:AD27) -> 1 | AV27: Maz Score Available: | AW27: =SUM(AV20:AV23)*AQ20 -> 160 | AX27: <- Excludes N/A items
B28: 11 | C28: Project Risk Plan/Management* | K28: 0 | L28: 1 | Q28: 40 | R28: Siporex Lifting & Unloading | AB28: 0 | AD28: 1 | AF28: =SUMPRODUCT($K$17:$O$17,K28:O28) -> 0.89 | AG28: =SUMPRODUCT($Z$17:$AD$17,Z28:AD28) -> 1
B29: 12 | C29: Monthly Quality Reports* | K29: 0 | L29: 1 | M29: 0 | Q29: 41 | R29: Siporex Quality Pre-installation | AB29: 0 | AD29: 1 | AF29: =SUMPRODUCT($K$17:$O$17,K29:O29) -> 0.89 | AG29: =SUMPRODUCT($Z$17:$AD$17,Z29:AD29) -> 1
B30: 13 | C30: ITP | K30: 0 | L30: 1 | M30: 0 | O30: 0 | Q30: 42 | R30: Siporex Finishing Quality | Z30: 0 | AD30: 1 | AF30: =SUMPRODUCT($K$17:$O$17,K30:O30) -> 0.89 | AG30: =SUMPRODUCT($Z$17:$AD$17,Z30:AD30) -> 1 | AR30: Total Score | AW30: Percentage (%)
B31: 14 | C31: MODON Weekly Report | K31: 1 | L31: 0 | M31: 0 | Q31: 43 | R31: Roads / Parking Markings | Z31: 0 | AA31: 0 | AC31: 1 | AD31: 0 | AF31: =SUMPRODUCT($K$17:$O$17,K31:O31) -> 1 | AG31: =SUMPRODUCT($Z$17:$AD$17,Z31:AD31) -> 0.69 | AN31: =MAX(AN20:AN24) -> 58 | AR31: =AW25 -> 104 | AW31: =SUM(100/AR33*AR31) -> 65 | AY31: %
B32: 15 | C32: Design Change Official Paperwork* | K32: 0 | M32: 0 | O32: 1 | Q32: 44 | R32: QC of Finishing Outdoors | Z32: 0 | AA32: 0 | AD32: 1 | AF32: =SUMPRODUCT($K$17:$O$17,K32:O32) -> 1 | AG32: =SUMPRODUCT($Z$17:$AD$17,Z32:AD32) -> 1 | AR32: Max Score Available | BP32: 31
B33: 16 | C33: Design Change was Applied* | K33: 0 | M33: 0 | O33: 1 | Q33: 45 | R33: Quality of Finishing Indoors | Z33: 0 | AD33: 1 | AF33: =SUMPRODUCT($K$17:$O$17,K33:O33) -> 1 | AG33: =SUMPRODUCT($Z$17:$AD$17,Z33:AD33) -> 1 | AR33: =AW27 -> 160 | BP33: 32
B34: 17 | C34: Material List | K34: 0 | M34: 1 | Q34: 46 | R34: Stairs Quality | Z34: 0 | AD34: 1 | AF34: =SUMPRODUCT($K$17:$O$17,K34:O34) -> 0.79 | AG34: =SUMPRODUCT($Z$17:$AD$17,Z34:AD34) -> 1 | BP34: 33
B35: 18 | C35: Pending Material Status | K35: 0 | L35: 1 | O35: 0 | Q35: 47 | R35: Tanks Method Statement Work | Z35: 0 | AD35: 1 | AF35: =SUMPRODUCT($K$17:$O$17,K35:O35) -> 0.89 | AG35: =SUMPRODUCT($Z$17:$AD$17,Z35:AD35) -> 1 | BP35: 34
B36: 19 | C36: Lifting Plan* | O36: 1 | Q36: 48 | R36: Electric Rooms | Z36: 0 | AD36: 1 | AF36: =SUMPRODUCT($K$17:$O$17,K36:O36) -> 1 | AG36: =SUMPRODUCT($Z$17:$AD$17,Z36:AD36) -> 1 | BP36: 35
B37: 20 | C37: DWG Log | L37: 1 | M37: 0 | O37: 0 | Q37: 49 | R37: QC of MCC/ATS Plant Units | Z37: 0 | AD37: 1 | AF37: =SUMPRODUCT($K$17:$O$17,K37:O37) -> 0.89 | AG37: =SUMPRODUCT($Z$17:$AD$17,Z37:AD37) -> 1 | BP37: 36
B38: 21 | C38: Invoice Status | K38: 1 | L38: 0 | O38: 0 | Q38: 50 | R38: Qualified Subcontractor | Z38: 0 | AD38: 1 | AF38: =SUMPRODUCT($K$17:$O$17,K38:O38) -> 1 | AG38: =SUMPRODUCT($Z$17:$AD$17,Z38:AD38) -> 1 | BP38: 37
B39: 22 | C39: Site Handover Letter | K39: 1 | L39: 0 | Q39: 51 | R39: Scaffold/Ladders/Slope/Bridge Compliance | Z39: 0 | AD39: 1 | AF39: =SUMPRODUCT($K$17:$O$17,K39:O39) -> 1 | AG39: =SUMPRODUCT($Z$17:$AD$17,Z39:AD39) -> 1 | BP39: 38
B40: 23 | C40: Material Testing Results & Certification | K40: 0 | L40: 0 | M40: 0 | N40: 1 | O40: 0 | Q40: 52 | R40: Protection Applied to Completed Work | AA40: 1 | AC40: 0 | AD40: 0 | AF40: =SUMPRODUCT($K$17:$O$17,K40:O40) -> 0.69 | AG40: =SUMPRODUCT($Z$17:$AD$17,Z40:AD40) -> 0.89
B41: 24 | C41: As Build Drawings Status* | L41: 0 | M41: 1 | O41: 0 | Q41: 53 | R41: Storage Management in/out Control | AA41: 0 | AB41: 1 | AC41: 0 | AF41: =SUMPRODUCT($K$17:$O$17,K41:O41) -> 0.79 | AG41: =SUMPRODUCT($Z$17:$AD$17,Z41:AD41) -> 0.79
B42: 25 | C42: Calibrated Lab Tools & Equipment | K42: 0 | L42: 0 | M42: 1 | N42: 0 | Q42: 54 | R42: Material Control | AA42: 0 | AD42: 1 | AF42: =SUMPRODUCT($K$17:$O$17,K42:O42) -> 0.79 | AG42: =SUMPRODUCT($Z$17:$AD$17,Z42:AD42) -> 1
B43: 26 | C43: Storage Inventory System | L43: 1 | M43: 0 | N43: 0 | Q43: 55 | R43: Manholes Storing and Quality | AA43: 0 | AB43: 1 | AC43: 0 | AD43: 0 | AF43: =SUMPRODUCT($K$17:$O$17,K43:O43) -> 0.89 | AG43: =SUMPRODUCT($Z$17:$AD$17,Z43:AD43) -> 0.79
B44: 27 | C44: Logistics Plan | L44: 1 | M44: 0 | Q44: 56 | R44: Reinforced Steel Quality | AA44: 1 | AD44: 0 | AF44: =SUMPRODUCT($K$17:$O$17,K44:O44) -> 0.89 | AG44: =SUMPRODUCT($Z$17:$AD$17,Z44:AD44) -> 0.89
B45: 28 | C45: Project Progress Planview | K45: 1 | M45: 0 | N45: 0 | Q45: 57 | R45: Safety Overview | Z45: 0 | AB45: 1 | AF45: =SUMPRODUCT($K$17:$O$17,K45:O45) -> 1 | AG45: =SUMPRODUCT($Z$17:$AD$17,Z45:AD45) -> 0.79
B46: 29 | C46: Sufficient Number of QC Inspectors | K46: 0 | L46: 1 | M46: 0 | N46: 0 | Q46: 58 | R46: Waste Management Control | Z46: 0 | AB46: 1 | AF46: =SUMPRODUCT($K$17:$O$17,K46:O46) -> 0.89 | AG46: 2
O47: 0
I48: Score
M49: *QC % | Q49: 0.93
B51: Prepared by: | Q51: Issued to PM:
B53: *QC Observations refer only to the practices and documentation observed at time of inspection. The responsibility of the CM and Contractor is to ensure that aspects of Quality are suitably managed. *Scores are a reflection of the general site conditions based upon the findings at the time of the walk through *If Applicable

Sheet Quality-Stat
A1: Quality Reports
A2: Item | C2: Issued | D2: Closed | E2: Pending | F2: Avg. Closing (Days) | G2: Pending
G3: 0-10 Days | H3: 11-20 Days | I3: 21-30 Days | J3: 31-60 Days | K3: > 60 Days
A5: Non Conforomance Report (NCR) | C5: 49 | D5: 48 | E5: 1 | F5: 0 | G5: 4 | H5: 0 | I5: 0 | J5: 0 | K5: 0
A6: Site Instruction (SI) | C6: 50 | D6: 41 | E6: 9 | F6: 0 | G6: 0 | H6: 0 | I6: 0 | J6: 0 | K6: 0
A7: Material Inspection Report (MIR) | C7: 111 | D7: 110 | E7: 1 | F7: 0 | G7: 0 | H7: 0 | I7: 0 | J7: 0 | K7: 0
A8: Field Inspection Report (FIR) | C8: 4408 | D8: 4286 | E8: 122 | F8: 0 | G8: 0 | H8: 0 | I8: 0 | J8: 0 | K8: 0
A10: Shop Drawings
A11: Item Per WBS | D11: Total Planned | E11: Total Drawings Submitted | J11: Remaining Drawings | K11: Pending | L11: Total Submittals
E12: A | F12: B | G12: C | H12: D | I12: Approved | J12: with Designer | K12: Submittals With Consultant
A13: CVL | D13: 1063 | E13: 8 | F13: 1055 | G13: 0 | H13: 0 | I13: =SUM(E13:F13) -> 1063 | J13: =G13 -> 0 | K13: =J13 -> 0 | L13: =I13+K13+H13 -> 1063
A14: Mech | D14: 212 | E14: 0 | F14: 212 | G14: 0 | H14: 0 | I14: =SUM(E14:F14) -> 212 | J14: =G14 -> 0 | K14: =J14 -> 0 | L14: =I14+K14+H14 -> 212
A15: Elec | D15: 41 | E15: 0 | F15: 41 | G15: 0 | H15: 0 | I15: =SUM(E15:F15) -> 41 | J15: =G15 -> 0 | K15: =J15 -> 0 | L15: =I15+K15+H15 -> 41
A16: Landscape & Arch | D16: 458 | E16: 0 | F16: 458 | G16: 0 | H16: 0 | I16: =SUM(E16:F16) -> 458 | J16: =G16 -> 0 | K16: =J16 -> 0 | L16: =I16+K16+H16 -> 458
A17: TOTAL | D17: =SUM(D13:D16) -> 1774 | E17: =SUM(E13:E16) -> 8 | F17: =SUM(F13:F16) -> 1766 | G17: =SUM(G13:G16) -> 0 | H17: =SUM(H13:H16) -> 0 | I17: =SUM(I13:I16) -> 1774 | J17: =SUM(J13:J16) -> 0 | K17: =SUM(K13:K16) -> 0 | L17: =SUM(L13:L16) -> 1774
A20: Material Approval
A21: Item Per WBS | D21: Total Planned | E21: Total Materials Submitted | J21: Remaining to approve | K21: Pending | L21: Total Submittals
E22: A | F22: B | G22: C | H22: D | I22: Approved | J22: with Designer | K22: Submittals With Consultant
A23: Civil & Roads | D23: 75 | E23: 2 | F23: 73 | G23: 3 | H23: 1 | I23: =SUM(E23:F23) -> 75 | J23: =D23-I23 -> 0 | K23: 4 | L23: =SUM(E23:H23)+K23 -> 83
A24: Electrical | D24: 30 | E24: 0 | F24: 22 | G24: 0 | H24: 0 | I24: =SUM(E24:F24) -> 22 | J24: =D24-I24 -> 8 | K24: 0 | L24: =SUM(E24:H24)+K24 -> 22
A25: Mechanical | D25: 48 | E25: 0 | F25: 41 | G25: 0 | H25: 2 | I25: =SUM(E25:F25) -> 41 | J25: =D25-I25 -> 7 | K25: 1 | L25: =SUM(E25:H25)+K25 -> 44
A26: TOTAL | D26: =SUM(D23:D25) -> 153 | E26: =SUM(E23:E25) -> 2 | F26: =SUM(F23:F25) -> 136 | G26: =SUM(G23:G25) -> 3 | H26: =SUM(H23:H25) -> 3 | I26: =SUM(I23:I25) -> 138 | J26: =SUM(J23:J25) -> 15 | K26: =SUM(K23:K25) -> 5 | L26: =SUM(L23:L25) -> 149
A28: Procurement Summary
A29: Item Per WBS | D29: Total Materials Planned | E29: Total Number of P.O. | F29: Actual P.O. To Date | G29: Remaining P.O | H29: Actual Material on Site | I29: Remaining Materials | J29: Material Delivery Completion (Date)
E30: A | F30: B | G30: C | H30: D | I30: Processed
A31: Civil & Roads | D31: =D23 -> 75 | E31: =D31 -> 75 | F31: =I23 -> 75 | G31: =E31-F31 -> 0 | H31: 42 | I31: =E31-H31 -> 33 | J31: 46335
A32: Electrical | D32: =D24 -> 30 | E32: =D32 -> 30 | F32: 22 | G32: 0 | H32: 11 | I32: =E32-H32 -> 19 | J32: 46292
A33: Mechanical | D33: =D25 -> 48 | E33: =D33 -> 48 | F33: 42 | G33: 0 | H33: 21 | I33: =E33-H33 -> 27 | J33: 46293
A35: TOTAL | D35: =SUM(D31:D34) -> 153 | E35: =SUM(E31:E34) -> 153 | F35: =SUM(F31:F34) -> 139 | G35: =SUM(G31:G34) -> 0 | H35: =SUM(H31:H34) -> 74 | I35: =SUM(I31:I34) -> 79 | J35: =MAX(J31:J34) -> 46335
A37: Consultant Quality Inspections / Observations (Weekly Basis) | I37: Overall Average | J37: =AVERAGE(E36:E109) -> 0.92863749 | L37: Average Closing | M37: =AVERAGE(G35:G109) -> 0
A38: Week Number | B38: Date of Audit | C38: Date Issued | D38: Numbers Of Comments | E38: Quality Score | F38: Date Closed | G38: Closure Duration | I38: This Week Score | J38: =Quality!AC10 -> 0.93 | L38: Average Number of Comments Per Audit | M38: =AVERAGE(D36:D109) -> 0
A39: Week-1 | B39: 45986 | C39: =B39 -> 45986 | D39: 0 | E39: 0.82034483
A40: Week-2 | B40: 45993 | C40: 45993 | D40: 0 | E40: 0.89034483
A41: Week-3 | B41: 46000 | C41: =B41 -> 46000 | D41: 0 | E41: 0.89034483
A42: Week-4 | B42: 46007 | C42: =B42 -> 46007 | D42: 0 | E42: 0.9691
A43: Week-5 | B43: 46014 | C43: =B43 -> 46014 | D43: 0 | E43: 0.93
A44: Week-6 | B44: 46021 | C44: =B44 -> 46021 | D44: 0 | E44: 0.8909
A45: Week-7 | B45: 46028 | C45: =B45 -> 46028 | D45: 0 | E45: 0.91
A46: Week-8 | B46: 46035 | C46: 46035 | D46: 0 | E46: 0.92
A47: Week-9 | B47: 46042 | C47: 46042 | D47: 0 | E47: 0.91
A48: Week-10 | B48: 46049 | C48: 46049 | D48: 0 | E48: 0.91
A49: Week-11 | B49: 46056 | C49: 46056 | D49: 0 | E49: 0.93
A50: Week-12 | B50: 46063 | C50: 46063 | D50: 0 | E50: 0.92
A51: Week-13 | B51: 46070 | C51: 46070 | D51: 0 | E51: 0.91
A52: Week-14 | B52: 46077 | C52: 46077 | D52: 0 | E52: 0.91765278
A53: Week-15 | B53: 46084 | C53: 46070 | D53: 0 | E53: 0.92
A54: Week-16 | B54: 46091 | C54: 46063 | D54: 0 | E54: 0.93
A55: Week-17 | B55: 46098 | C55: 46098 | D55: 0 | E55: 0.96
A56: Week-18 | B56: 46112 | C56: 46112 | D56: 0 | E56: 0.96
A57: Week-19 | B57: 46119 | C57: 46119 | D57: 0 | E57: 0.93
... A83: Week-45 | B83: 46308 | C83: 46308 | D83: 0 | E83: 0.93
A84: Week-46
A85: Week-47
A86: Week-48
A87: Week-49
A88: Week-50
A89: Week-51
A90: Week-52
A91: Week-53
A92: Week-54
A93: Week-55
A94: Week-56
A95: Week-57
... A113: Week-75

Sheet HSE
B1: MODON HSE Site Inspection Report
B2: Date | E2: ='General Information'!L1 -> 46308 | L2: Inspected By: | U2: Muhammad Al Rajjal
B4: Project ID. | E4: ='General Information'!C4 -> DAM2-02-009 | L4: Report No. | P4: =Quality!O6 -> 45 | W4: MODON PM Name | Y4: ='General Information'!C9 -> Muhammad H Al-Essa
B6: Project Name: | E6: ='General Information'!C3 -> Development of Infrastructure for phase 1 of the Logistics area at the 2nd Industrial City in Dammam | L6: Contractor: | R6: ='General Information'!C5 -> Shibh Aljazira Contracting Company | X6: Safety Performance | AA6: 80 | AE6: =(((COUNTIF(L13:Q25,"1")+COUNTIF(AC13:AH25,"1"))*AR13)+(COUNTIF(L13:Q25,"2")+COUNTIF(AC13:AH25,"2"))*AR14+(COUNTIF(L13:Q25,"3")+COUNTIF(AC13:AH25,"3"))*AR15)/((COUNT(L13:Q25)+COUNT(AC13:AH25))*100) -> 0.92857143
B8: Inspections are a snapshot in time and refer only to the practices and documentation observed at the time of the Inspection. It remains the responsibility of the Consultant and Contractor to ensure that all aspects of Health & Safety are suitably managed.
B9: 1 | D9: Good Practice | H9: 2 | I9: Need Improvement | T9: 3 | U9: Fail (Life Threatening Activity) / Comliance with Plan & Procedures | X9: N/A | Y9: Atcitty Not Applicable for this Site Inspection Report
B11: No. | C11: Topic | K11: Wt. | L11: HSE Compliance | S11: No. | T11: Topic | AB11: Wt. | AC11: HSE Compliance
B13: 1 | C13: Access and Egress - (General access to site, segregated from vehicles, / Overhead protection, while entering into the building /Adequate lighting provided when dark or overnight work) | K13: 0.05 | L13: 2 | S13: 14 | T13: Work at Height - (PPE/Fall Protection(Same level, above and blow) / Training / Fall restraint / competency /Safe access & egress to and from work at height / Ladders / Openings (floor/shafts/Provision of emergency rescue) | AB13: 0.05 | AC13: N/A | AP13: 1 | AR13: 100 | AU13: 1
B14: 2 | C14: Traffic Management - (Loading/unloading/sheeting/temp. routes/speed/parking/competence) | K14: 0.03 | L14: 2 | S14: 15 | T14: Scaffolding - (Temp. Scaffolding Work-platform (All types) - qualified scaffolder / Inspection / Tagged / Safe Access/egress / PTW/Falsework & Formwork) | AB14: 0.04 | AC14: N/A | AP14: 2 | AR14: 75 | AU14: 2
B15: 3 | C15: Site Signage - (Project Notice Board & General Signage) | K15: 0.02 | L15: 1 | S15: 16 | T15: Mobile Elevated Work platform (MEWP) - (PTW/competence requirements/conditions/inspections/tagged/training/Full-body harness) | AB15: 0.04 | AC15: N/A | AP15: 3 | AR15: 0 | AU15: 3
B16: 4 | C16: PPE Compliance - (Use, storage, stock, handling & checks - Head, Foot, Eye, Hearing) | K16: 0.05 | L16: 1 | S16: 17 | T16: Excavation & Trenches - (PTW/Edge protection/buffer zone/Slope/Benching/Shoring/Geo-tech report/Atmospheric hazards/Acess&egress/Emergency management / MS&RA/H.E) | AB16: 0.03 | AC16: N/A | AU16: N/A
B17: 5 | C17: Housekeeping - (Material correctly stored/Rubbish cleaned & removed daily/slips & trips hazards) | K17: 0.03 | L17: 1 | S17: 18 | T17: Confined Space - (PTW/Training/competence/Emergency Management/MS & RA/Safe access/egress) | AB17: 0.05 | AC17: N/A
B18: 6 | C18: Storage of Materials - (Transporting, storage, training and use - Combustible / Flammable / Hazardous substances (COSHH) | L18: 1 | S18: 19 | T18: Fire Protection - (Flammable/Oxy. LPG /Combustible separated/FE's/Flashback arrestor/Sparks & slags/Smoking area/PTW/Generators/MS & RA/Emergency Management) | AC18: 1 | AL18: Red | AM18: Serious injury or death (immediately)
B19: 7 | C19: Site Waste Management - (Hazardous waste /Combustible waste / Human waste / Construction waste - asphalt, cable, timber, paving roof sheeting tiles, plastic & bricks) | L19: 2 | S19: 20 | T19: Health & Welfare - (Adequate drinking water/shaded - eating & rest area/washing & sanitary facilities/Certified FA/FA Box & Stock/adequate toilets/Ambulance) | AC19: 1 | AL19: Yellow | AM19: Minor or near miss (3 days to comply)
B20: 8 | C20: Health Surveillance - (Expose to excessive noise/vibration/dust/silica/CO/cement/radiation/extreme weather condition) | K20: 0.03 | L20: 1 | S20: 21 | T20: Environmental Incident Measures - (Spill/ Leakage / Concrete wash / vehicle & eqpts. wash / waste disposal/Sewers and drains/emissions/Emergency Management/Training/site run-off water) | AB20: 0.05 | AC20: 2 | AL20: Green | AM20: No issues
B21: 9 | C21: Electrical Safety - (Electrical qualified /RCD/GFCI/Industrial Cocket/LOTO/Cable-overhung or buried/Cords in good condition/current inspection tag) | K21: 0.05 | L21: 1 | S21: 22 | T21: HSE Communications & Meetings - (Schedule HSE Meetings/Safety Committee meetings/Alerts / Lesson learned/Safety Bulletin contains latest HSE KPI) | AB21: 0.05 | AC21: 1
B22: 10 | C22: Tools & Equipment - (Includes, powered, hydraulic & pneumatic/Guards in place/Properly stored/RCD Protection/Earthed/Good condition & tagged) | K22: 0.03 | L22: 1 | S22: 23 | T22: HSE Plan & Associated Procedures - (Approved updated HSE Plan/ CEMP/HAZComm/Procedures/Standards/Project Safety Risk Register) | AB22: 0.03 | AC22: 1 | AL22: 26 points > 4 minors then is it’s a serious issue
B23: 11 | C23: Manual Handling - (Lifting/loading/pulling/pushing/twisting/awkward posture/repetitive task/frequent and prolong physical effort/Reasonable practicable use of mechanical aid) | K23: 0.03 | L23: 1 | S23: 24 | T23: Health, Safety & Environment Incident reporting - (Review of HSE Statistics, Reporting of Unsafe Act & Conditions/ Reporting of Near Miss incident/Reporting of FA cases/Record MT cases) | AB23: 0.03 | AC23: 1
B24: 12 | C24: Vehicle and mobile equipment / Plant - (dumpers; excavators, cranes, piling rigs, grader, roller, loaders/condition/KSA License/certification) | K24: 0.05 | L24: 1 | S24: 25 | T24: HSE Awareness, Training & Competence - (Policy /Objective & targets/Information, training/Climatic condition awareness/Reponses in emergency situation/ Safety Behavior Observation) | AB24: 0.04 | AC24: 1
B25: 13 | C25: Lifting Operations & Rigging - (Lifting Plan/Lifting devices & gears/PTW/Condition/3rd party certification/bank-man/rigger/slingers/man-basket/inspection record/tagged) | L25: 2 | S25: 26 | T25: Project Leadership Site Tours - (Provide evidence of proactive safety performance/Deficient discovered discussed/Positive feedback/Workers resolving safety issues) | AC25: 2
B27: Prepared by: | G27: =U2 -> Muhammad Al Rajjal | S27: Sent to MODON PM: | X27: =Y4 -> Muhammad H Al-Essa
B28: Safety Results
B29: 1 | D29: =COUNTIF(L13:Q26,"1")+COUNTIF(AB13:AG26,"1") -> 15 | I29: 2 | L29: =COUNTIF(L13:Q26,"2")+COUNTIF(AB13:AG26,"2") -> 6 | U29: 3 | W29: =COUNTIF(L13:Q26,"3")+COUNTIF(AB13:AG26,"3") -> 0

Sheet HSE-Stat
A1: Safety Statistics
A3: Category | B3: Item | D3: This Week | E3: This Month | F3: Year to Date | G3: Cumulative
A4: Category | B4: Total Hours Worked | D4: 34740 | E4: 69480 | F4: 774924 | G4: 839982 | K4: =16*4 -> 64 | L4: =COUNTA(D4:G19) -> 64
B5: Safe Hours Worked | D5: 34740 | E5: 69480 | F5: 774924 | G5: 839982 | L5: =COUNTBLANK(D4:G19) -> 0
A6: Reactive | B6: LTI | D6: 0 | E6: 0 | F6: 0 | G6: 0
B7: MTC (Healed w/o Disability) | D7: 0 | E7: 0 | F7: 0 | G7: 0
B8: MTC (Healed w/ Disability) | D8: 0 | E8: 0 | F8: 0 | G8: 0
B9: Near Miss | D9: 0 | E9: 0 | F9: 0 | G9: 0
B10: First Aid Cases | D10: 0 | E10: 0 | F10: 0 | G10: 0
B11: Fatality | D11: 0 | E11: 0 | F11: 0 | G11: 0
B12: Fire Incident Cases | D12: 0 | E12: 0 | F12: 0 | G12: 0
B13: Vehicle Incident | D13: 0 | E13: 0 | F13: 0 | G13: 0
B14: Property Damages | D14: 0 | E14: 0 | F14: 0 | G14: 0
A15: Proactive | B15: Induction Training | D15: 33 | E15: 62 | F15: 114(564) | G15: 147(888)
B16: No.of Internal Training | D16: 0 | E16: 2 (9) | F16: 5(23) | G16: 13(98)
B17: No.of Internal Audit | D17: 0 | E17: 1 | F17: 4 | G17: 4
B18: No. of Toolbox Talks | D18: 3(323) | E18: 3(648) | F18: (43(3442) | G18: 56(8671)
B19: Safety Awards/Incentives | D19: 0 | E19: 0 | F19: 1 | G19: 2
I20: Category | J20: Item | L20: This Week | M20: This Month | N20: Year to Date | O20: Cumulative
A22: Consultant Safety Inspection (Weekly Basis) | I22: Overall Average | J22: =AVERAGE(E24:E98) -> 0.92240741
A23: Week Number | B23: Date of Audit | C23: Date Issued | D23: Numbers Of Comments | E23: Overall Score | F23: Date Closed | G23: Closure Duration | I23: This Week Score | J23: =VLOOKUP('General Information'!$L$1,'HSE-Stat'!$B$23:$E$95,4,FALSE) -> 0.92857143
A24: Week-1 | B24: 45986 | C24: 45986 | D24: 15 | E24: 0.8125
A25: Week-2 | B25: 45993 | C25: =B25 -> 45993 | D25: 11 | E25: 0.8625
A26: Week-3 | B26: 46000 | C26: 46000 | D26: 9 | E26: 0.89285714
A27: Week-4 | B27: 46007 | C27: 46007 | D27: 8 | E27: 0.9047619
A28: Week-5 | B28: 46014 | C28: 46014 | D28: 7 | E28: 0.91666667
A29: Week-6 | B29: 46021 | C29: 46021 | D29: 7 | E29: 0.91666667
A30: Week-7 | B30: 46028 | C30: 46028 | D30: 7 | E30: 0.91666667
A31: Week-8 | B31: 46035 | C31: 46035 | D31: 6 | E31: 0.92857143
A32: Week-9 | B32: 46042 | C32: 46042 | D32: 6 | E32: 0.92857143
A33: Week-10 | B33: 46049 | C33: 46049 | D33: 5 | E33: 0.94047619
A34: Week-11 | B34: 46056 | C34: 46056 | D34: 5 | E34: 0.94047619
A35: Week-12 | B35: 46063 | C35: 46063 | D35: 5 | E35: 0.94047619
A36: Week-13 | B36: 46070 | C36: 46070 | D36: 6 | E36: 0.92857143
A37: Week-14 | B37: 46077 | C37: 46077 | D37: 7 | E37: 0.91666667
... A67: Week-44 | B67: 46301 | C67: 46301 | D67: 6 | E67: 0.92857143
A68: Week-45 | B68: 46308 | C68: 46308 | D68: =HSE!L29 -> 6 | E68: =HSE!AE6 -> 0.92857143
A69: Week-46
A70: Week-47
A71: Week-48
A72: Week-49
A73: Week-50
A74: Week-51
A75: Week-52
A76: Week-53
A77: Week-54
A78: Week-55
A79: Week-56
A80: Week-57
... A98: Week-75

Sheet Major Quantities
A1: BOQ Number | B1: Description of Item | C1: Total Quantity | D1: Unit of Measurement | E1: Plan To Date | F1: Actual To Date | G1: Remaining Total | H1: Variance | I1: Variance % | J1: Notices | L1: Perf. %
A2: B1.1.31 23 19.01 | B2: Surface Dewatering | C2: 1 | D2: Unit | E2: 1 | F2: 1 | G2: 0 | H2: 0 | I2: 0 | L2: 1 | M2: Actual EW | N2: Plan EW
A3: B1.1.31 23 16.01 | B3: All Excavation | C3: 853395 | D3: m³ | E3: 853395 | F3: 825820.73 | G3: 27574.27 | H3: -27574.27 | I3: -0.032311263 | L3: 0.96768874 | M3: 0.93335125 | N3: 1
A4: B1.1.31 23 23.01 | B4: All Backfilling | C4: 1481028 | D4: m³ | E4: 1481028 | F4: 1353015.9 | G4: 128012.1 | H4: -128012.1 | I4: -0.086434625 | L4: 0.91356538
A5: B1.2.32 11 26.01 | B5: Asphalt (Base+Wearing) | C5: 64334 | D5: m³ | E5: 53869.9 | F5: 25214.53 | G5: 39119.47 | H5: -28655.37 | I5: -0.44541564 | L5: 0.39193164
A6: 33 31 00 | B6: Sew. Pipes | C6: 7567.08 | D6: Lm | E6: 2.01 | F6: 6748.28 | G6: 818.8 | H6: 6746.27 | I6: 0.89152883 | L6: 0.89179446
A7: 33 05 13 | B7: Sew. Manholes Dia. 1200mm | C7: 135.99 | D7: Unit | E7: 135.23 | F7: 128.08 | G7: 7.91 | H7: -7.15 | I7: -0.052577395 | L7: 0.94183396
A8: 33 42 11 | B8: Storm Pipes | C8: 14821.15 | D8: Lm | E8: 14174 | F8: 13652.01 | G8: 1169.14 | H8: -521.99 | I8: -0.035219264 | L8: 0.92111678
A9: 33 05 13 | B9: Storm Manholes | C9: 160.01 | D9: Unit | E9: 150.74 | F9: 133.99 | G9: 26.02 | H9: -16.75 | I9: -0.10468096 | L9: 0.83738516
A10: 33 05 63 | B10: Catch Basins | C10: 337.99 | D10: Unit | E10: 308.25 | F10: 244.1 | G10: 93.89 | H10: -64.15 | I10: -0.18979851 | L10: 0.72221072
A11: 33 14 11 | B11: Potable Pipes | C11: 7213.99 | D11: Lm | E11: 6957.99 | F11: 5509.07 | G11: 1704.92 | H11: -1448.92 | I11: -0.20084863 | L11: 0.76366477
A12: 33 14 13 | B12: Fire Fighting Pipes | C12: 6354.52 | D12: Lm | E12: 5768.5 | F12: 5613.15 | G12: 741.37 | H12: -155.35 | I12: -0.024447165 | L12: 0.88333186
A13: 33 14 13 | B13: TSE Pipes | C13: 57419.14 | D13: Lm | E13: 57419.14 | F13: 7703.4 | G13: 49715.74 | H13: -49715.74 | I13: -0.86583916 | L13: 0.13416084
A14: B2.33 71 49.23 | B14: MV Cables | C14: 12559 | D14: Lm | E14: 11183.2 | F14: 4207.38 | G14: 8351.62 | H14: -6975.82 | I14: -0.5554439 | L14: 0.33500916
A15: B2 33 73 00.01 | B15: Unit Substation 13.8/0.4 K V, 500kVA | C15: 3 | D15: Unit | E15: 0.76 | F15: 0 | G15: 3 | H15: -0.76 | I15: -0.25333333 | L15: 0
... A22: Bill 5.1 | B22: Sewerage Lift Station | C22: 1 | D22: Unit | E22: 0.73496664 | F22: 0.27313595 | G22: 0.72686405 | H22: -0.46183069 | I22: -0.46183069 | L22: 0.27313595

Sheet Risk Register
B2: Department: | K2: Status Date:
B3: Program | K3: ='General Information'!L1 -> 46308
B4: Project: | E4: ='General Information'!C3 -> Development of Infrastructure for phase 1 of the Logistics area at the 2nd Industrial City in Dammam
B5: Project No.: | E5: ='General Information'!C4 -> DAM2-02-009
B6: Project Location: | E6: =RIGHT('General Information'!C3,29) -> 2nd Industrial City in Dammam
R8: Before Treatment | AC8: Post Treatment
B9: Risk Data | H9: Category | K9: Risk Description | N9: Risk Control Dates | P9: Risk Manageability | Q9: Risk Proximity | R9: Most Likely | U9: Risk Owner | V9: Risk Response & Treatment Action | Z9: Treatment Control Dates | AC9: Most Likely | AF9: Treatment Status
B10: Risk ID | C10: Region | D10: Section / Group | E10: City | F10: Project ID | G10: Risk Status | H10: T/O/I | I10: Internal/External | J10: Category | K10: Cause / Source | L10: Risk | M10: Consequence / Effect | N10: Identified | O10: Closed | R10: Liklihood | S10: Impact | T10: Risk Score | V10: Risk Response Strategy | W10: Treatment Action | X10: Treatment Acton Description | Y10: Treatment Action Owner | Z10: Start | AA10: Due | AB10: Closed | AC10: Liklihood | AD10: Impact | AE10: Risk Score
T11: =IF(AND(R11="Very Low",S11="Low"),"L1",IF(AND(R11="Low",S11="Low"),"L4",IF(OR(AND(R11="Very Low",S11="Low"),AND(R11="Low",S11="Very Low")),"L2",IF(OR(AND(R11="Medium",S11="Very Low"),AND(R11="Very Low",S11="Medium")),"L3",IF(OR(AND(R11="High",S11="Very Low"),AND(R11="Very Low",S11="High")),"L4",IF(OR(AND(R11="Very High",S11="Very Low"),AND(R11="Very Low",S11="Very High")),"M5",IF(OR(AND(R11="Low",S11="Medium"),AND(R11="Medium",S11="Low")),"M6",IF(OR(AND(R11="High",S11="Low"),AND(R11="Low",S11="High")),"M8",IF(AND(R11="Medium",S11="Medium"),"M9",IF(OR(AND(R11="Very High",S11="Low"),AND(R11="Low",S11="Very High")),"M10",IF(OR(AND(R11="High",S11="Medium"),AND(R11="Medium",S11="High")),"M12",IF(OR(AND(R11="Very High",S11="Medium"),AND(R11="Medium",S11="Very High")),"H15",IF(AND(R11="High",S11="High"),"H16",IF(OR(AND(R11="Very High",S11="High"),AND(R11="High",S11="Very High")),"H20",IF(AND(R11="Very High",S11="Very High"),"H25",""))))))))))))))) | AE11: =IF(AND(AC11="Very Low",AD11="Low"),"L1",IF(AND(AC11="Low",AD11="Low"),"L4",IF(OR(AND(AC11="Very Low",AD11="Low"),AND(AC11="Low",AD11="Very Low")),"L2",IF(OR(AND(AC11="Medium",AD11="Very Low"),AND(AC11="Very Low",AD11="Medium")),"L3",IF(OR(AND(AC11="High",AD11="Very Low"),AND(AC11="Very Low",AD11="High")),"L4",IF(OR(AND(AC11="Very High",AD11="Very Low"),AND(AC11="Very Low",AD11="Very High")),"M5",IF(OR(AND(AC11="Low",AD11="Medium"),AND(AC11="Medium",AD11="Low")),"M6",IF(OR(AND(AC11="High",AD11="Low"),AND(AC11="Low",AD11="High")),"M8",IF(AND(AC11="Medium",AD11="Medium"),"M9",IF(OR(AND(AC11="Very High",AD11="Low"),AND(AC11="Low",AD11="Very High")),"M10",IF(OR(AND(AC11="High",AD11="Medium"),AND(AC11="Medium",AD11="High")),"M12",IF(OR(AND(AC11="Very High",AD11="Medium"),AND(AC11="Medium",AD11="Very High")),"H15",IF(AND(AC11="High",AD11="High"),"H16",IF(OR(AND(AC11="Very High",AD11="High"),AND(AC11="High",AD11="Very High")),"H20",IF(AND(AC11="Very High",AD11="Very High"),"H25","")))))))))))))))
B12: Rsk-01 | C12: Eastern | D12: Eastern | E12: 2nd Industrial City in Dammam | F12: DAM2-01-029 | G12: Open | H12: Threat | I12: Internal | J12: Design / Planning | K12: قلة عدد العمالة والمعدات و توقف مقاول الباطن | L12: Slow Production | M12: Can't Achieve MODON Goals | N12: 46113 | P12: Moderate | Q12: Overdue | R12: Medium | S12: Medium | U12: Contractor | V12: Terminate | W12: Mitigate | X12: Increase the no. of manpower & equipment - transfer from another projects | Y12: Contractor | Z12: 46063 | AA12: 46129 | AC12: High | AD12: High | AF12: Open
B13: Rsk-02 | C13: Eastern | D13: Eastern | E13: 3rd Industrial City in Dammam | F13: DAM2-01-029 | G13: Escalate | H13: Issue | I13: Internal | J13: Resources / Finance | K13: تأخر أعمال العبارة بالطريق الشرياني | L13: Delay in material installation /construction | M13: Delay in construction | N13: 46174 | P13: Moderate | Q13: Overdue | R13: Medium | S13: Medium | U13: Contractor | V13: Enhance/ Exploit | W13: Mitigate | X13: Delivery Schedule to be provided and committed with | Y13: Contractor | Z13: 46069 | AC13: High | AD13: High | AF13: Open
B14: Rsk-04 | C14: Eastern | D14: Eastern | E14: 6th Industrial City in Dammam | F14: DAM2-01-029 | G14: Open | H14: Issue | I14: Internal | J14: Interface / Communication | K14: ضرورة الانتهاء من تنفيذ الشبكات لتحقيق جاهزية الموقع وبدء أعمال الطرق | L14: Slow work sequence, Delay in Dry Networks | M14: Can't commit with planned dates for fulfilling box culvert | N14: 46174 | P14: Hard | Q14: Med Term | R14: Medium | S14: Medium | U14: Contractor | V14: Treat | W14: Mitigate | X14: Crashing - Increasing manpower & equipment | Y14: Contractor | Z14: 46104 | AC14: High | AD14: High | AF14: Open
B19: NOTES:
B20: Risk Status: 1.Open, 2.Closed, or 3.Realized
B21: T/O/I: 1.Threat, 2.Opportunity, or 3.Issue
B23: Category (select 1):
B24: 1. Political
B25: 2. Legal, Regulatory, Compliance
B26: 3. Funding, Finance, Budget
B27: 4. Management, Governance, Policies, KPI, Performance
B28: 5. Human Resources | X28: `
B29: 6. Stakeholders, Authorities, Approvals, Permits
B30: 7. Requirements, Specifications, Scope, Procurement, Contract
B31: 8. Process, Tools, Technique, Technology
B32: 9. Design, Engineering
B33: 10. Construction, Execution
B34: 11. Testing, Commissioning, Handover
B35: 12. Operation, Maintenance
B37: Risk Description (add all 3):
B38: 1. Source/Cause
B39: 2. Event = Threat, Opportunity, or Issue
B40: 3. Consequence/Effect
B42: Risk Response Strategy for Threats: 1.Terminate, 2.Tolerate, 3.Transfer, or 4.Treat
... B47: Risk Level/Score: Likelihood x Highest Impact (Safety, Cost, Schedule, Environment, Quality, or Reputation. See Risk Scoring Matrix tab)

Sheet CCO
A1: CONTRACT CHANGE ORDER (CCO)
A2: CCO No. | B2: Date Added | C2: Description of Change | D2: Status | E2: SR | F2: Sch Impact (Months) | G2: Date Approved | H2: Duration (days)

Sheet Invoice Log
B1: Weekly Progress Report - Invoice Log | AJ1: Y
B2: Project Value | K2: Payment Status | S2: Invoices Summary | AC2: Average Invoices durations | AJ2: N
B3: Original Contract Value | E3: =Progress!C78 -> 1.9890616e+08 | G3: O&M Value | I3: 0 | J3: EAC | K3: Advance Payment % | M3: 0 | O3: Advance Payment (SAR) | Q3: =E3*M3 -> 0 | S3: No of Submitted Invoices | U3: =MAX($C$9:$C$46) -> 7 | W3: Submitted Invoices (SAR) | Y3: =SUM(F9:F46) -> 62889674 | AA3: Submiited Invoice Peroid | AB3: =MAX(L9:L46) -> 46280 | AC3: CM / PgM Average Approval duration | AE3: =AVERAGE(P9:P59) -> 1 | AG3: Average Invoice Value | AH3: =AVERAGE(F9:F58) -> 8984239.1
B4: Revised Contract Value | D4: 21100000 | E4: =E3 -> 1.9890616e+08 | F4: EAC | G4: Revised O&M Value | I4: 0 | J4: =+#REF!+#REF!+I4 -> #REF! | K4: Retention % | M4: 0 | O4: Retention (SAR) | Q4: =E3*M4 -> 0 | S4: No of Approved Invoices (CM) | U4: =COUNTIF($N$9:$N$59,"Y") -> 7 | W4: Approved Invoices (CM) (SAR) | Y4: =SUMIF($N$9:$N$46,"Y",$F$9:$F$46) -> 62889674 | AC4: MODON PM & Accounts Average Approval duration | AE4: =AVERAGE(W9:W59) -> #DIV/0!
B5: Estimate At Completion Value | D5: 20900000 | E5: =E4 -> 1.9890616e+08 | F5: =+#REF!+#REF!+E5 -> #REF! | G5: Submitted Invoices (Gross Value) | I5: =Y3 -> 62889674 | K5: Penalties and deduction % | M5: =ABS(M6/E3) -> 0.00052537337 | O5: AP Recovery (SAR) | Q5: =SUM(G9:G58) -> 0 | S5: No of Approved Invoices (PM) | U5: =COUNTIF($R$9:$R$59,"Y") -> 0 | W5: Approved Invoices (PM) (SAR) | Y5: =SUMIF($R$9:$R$46,"Y",$F$9:$F$46) -> 0 | AA5: Invoice Submitted Compared to Contract Value | AB5: =Y3/E4 -> 0.3161776 | AC5: Payments Average Duration | AE5: =AVERAGE(AA9:AA59) -> #DIV/0!
B6: Potential Changes | D6: =D4-D5 -> 200000 | E6: =E4-E5 -> 0 | G6: Total Deduction | I6: =M6+Q6+Q5 -> -104500 | K6: Penalties and deduction (SAR) | M6: =SUM(I9:I58) -> -104500 | O6: Retention Cumulative (SAR) | Q6: =SUM(H9:H58) -> 0 | S6: No of Paid Invoices | U6: =COUNTA(X9:X59) -> 0 | W6: Paid Invoices (SAR) | Y6: =SUM(Y9:Y46) -> 0 | AC6: Invoices Average total Duration | AE6: =IFERROR(AVERAGE(AC9:AC59),"")
B7: Invoice Reference | F7: Invoice Value | K7: Period Covered | M7: CM / PgM Approval Timeline | Q7: Modon PM & Accounts Approval | X7: Payment Status | AC7: Total Invoice Duration | AD7: Remarks
B8: # | C8: Invoice No. | D8: Doc Control reference | E8: Submittal Rev. # | F8: Gross Value | G8: AP Recovery | H8: Retention | I8: Deduction / Penalties | J8: Amount (net) + VAT 15% | K8: Start Date | L8: End Date | M8: Date to CM / PgM | N8: CM / PgM Approval (Yes/No) | O8: CM / PgM Reply Date | P8: Days Elapsed | Q8: Date to PM | R8: PM Approval (Yes/No) | S8: PM Reply Date | T8: Date to Accounts | U8: Accounts Approval (Yes/No) | V8: Accounts Approval Date | W8: Days Elapsed | X8: Date Paid | Y8: Amount Paid | Z8: Paid % | AA8: Payment Period (d) | AB8: Amount Pending
B9: 1 | C9: 1 | D9: DAM2-02-09-SAJ-TS9-1-GEN-DSF-041 | E9: 0 | F9: 3437652.2 | G9: =IF(ISBLANK(F9),"",-F9*$M$3) -> 0 | H9: =IF(ISBLANK(F9),"",-F9*$M$4) -> 0 | I9: -104500 | J9: =IF(ISBLANK(F9),"",(SUM(F9:I9)+(F9+G9)*0.15)) -> 3848800 | K9: 45868 | L9: 45991 | M9: 45993 | N9: Y | O9: 45993 | P9: =IF(ISBLANK(O9),"",O9-M9) -> 0 | W9: =IF(ISBLANK(V9),"",V9-Q9) | Z9: =IF(ISBLANK(Y9),"",Y9/J9) | AA9: =IF(ISBLANK(X9),"",X9-V9) | AB9: =IF(ISBLANK(Y9),"",(J9-Y9))
B10: 2 | C10: 2 | D10: DAM2-02-09-SAJ-TS9-1-GEN-DSF-045 | E10: 0 | F10: 5352442.1 | G10: 0 | H10: 0 | I10: 0 | J10: =IF(ISBLANK(F10),"",(SUM(F10:I10)+(F10+G10)*0.15)) -> 6155308.4 | K10: =L9+1 -> 45992 | L10: =K10+14 -> 46006 | M10: =L10+2 -> 46008 | N10: Y | O10: 46009 | P10: =IF(ISBLANK(O10),"",O10-M10) -> 1 | W10: =IF(ISBLANK(V10),"",V10-Q10) | Z10: =IF(ISBLANK(Y10),"",Y10/J10) | AA10: =IF(ISBLANK(X10),"",X10-V10) | AB10: =IF(ISBLANK(Y10),"",(J10-Y10))
B11: 3 | C11: 3 | D11: DAM2-02-09-SAJ-TS9-1-GEN-DSF-049 | E11: 0 | F11: 10988940 | G11: 0 | H11: 0 | I11: 0 | J11: =IF(ISBLANK(F11),"",(SUM(F11:I11)+(F11+G11)*0.15)) -> 12637281 | K11: =L10+1 -> 46007 | L11: =K11+40 -> 46047 | M11: =L11+2 -> 46049 | N11: Y | O11: =M11+1 -> 46050 | P11: =IF(ISBLANK(O11),"",O11-M11) -> 1 | W11: =IF(ISBLANK(V11),"",V11-Q11) | Z11: =IF(ISBLANK(Y11),"",Y11/J11) | AA11: =IF(ISBLANK(X11),"",X11-V11) | AB11: =IF(ISBLANK(Y11),"",(J11-Y11))
B12: 4 | C12: 4 | D12: DAM2-02-09-SAJ-TS9-1-GEN-DSF-056-02 | E12: 2 | F12: 12998014 | G12: 0 | H12: 0 | I12: 0 | J12: =IF(ISBLANK(F12),"",(SUM(F12:I12)+(F12+G12)*0.15)) -> 14947716 | K12: =L11+1 -> 46048 | L12: 46112 | M12: 46139 | N12: Y | O12: =M12 -> 46139 | P12: =IF(ISBLANK(O12),"",O12-M12) -> 0 | W12: =IF(ISBLANK(V12),"",V12-Q12) | Z12: =IF(ISBLANK(Y12),"",Y12/J12) | AA12: =IF(ISBLANK(X12),"",X12-V12) | AB12: =IF(ISBLANK(Y12),"",(J12-Y12)) | AC12: =IF(ISBLANK(X12),"",X12-M12)
B13: 5 | C13: 5 | D13: DAM2-02-09-SAJ-TS9-1-GEN-DSF-067-00 | E13: 0 | F13: 9370944.6 | G13: 0 | H13: 0 | I13: 0 | J13: =IF(ISBLANK(F13),"",(SUM(F13:I13)+(F13+G13)*0.15)) -> 10776586 | K13: =L12+1 -> 46113 | L13: 46196 | M13: 46198 | N13: Y | O13: =M13 -> 46198 | P13: =IF(ISBLANK(O13),"",O13-M13) -> 0 | W13: =IF(ISBLANK(V13),"",V13-Q13) | Z13: =IF(ISBLANK(Y13),"",Y13/J13) | AA13: =IF(ISBLANK(X13),"",X13-V13) | AB13: =IF(ISBLANK(Y13),"",(J13-Y13)) | AC13: =IF(ISBLANK(X13),"",X13-M13)
B14: 6 | C14: 6 | D14: DAM2-02-09-SAJ-TS9-1-GEN-DSF-074-00 | E14: 0 | F14: 8014146.1 | G14: 0 | H14: 0 | I14: 0 | J14: =IF(ISBLANK(F14),"",(SUM(F14:I14)+(F14+G14)*0.15)) -> 9216268 | K14: =L13+1 -> 46197 | L14: =K14+18 -> 46215 | M14: 46242 | N14: Y | O14: =M14 -> 46242 | P14: =IF(ISBLANK(O14),"",O14-M14) -> 0 | W14: =IF(ISBLANK(V14),"",V14-Q14) | Z14: =IF(ISBLANK(Y14),"",Y14/J14) | AA14: =IF(ISBLANK(X14),"",X14-V14) | AB14: =IF(ISBLANK(Y14),"",(J14-Y14)) | AC14: =IF(ISBLANK(X14),"",X14-M14)
B15: 7 | C15: 7 | D15: DAM2-02-09-SAJ-TS9-1-GEN-DSF-084 | E15: 0 | F15: 12727534 | G15: 0 | H15: 0 | I15: 0 | J15: =IF(ISBLANK(F15),"",(SUM(F15:I15)+(F15+G15)*0.15)) -> 14636665 | K15: =L14+1 -> 46216 | L15: =K15+64 -> 46280 | M15: =L15+15 -> 46295 | N15: Y | O15: =M15+5 -> 46300 | P15: =IF(ISBLANK(O15),"",O15-M15) -> 5 | W15: =IF(ISBLANK(V15),"",V15-Q15) | Z15: =IF(ISBLANK(Y15),"",Y15/J15) | AA15: =IF(ISBLANK(X15),"",X15-V15) | AB15: =IF(ISBLANK(Y15),"",(J15-Y15)) | AC15: =IF(ISBLANK(X15),"",X15-M15)
B16: 8 | W16: =IF(ISBLANK(V16),"",V16-Q16) | Z16: =IF(ISBLANK(Y16),"",Y16/J16) | AA16: =IF(ISBLANK(X16),"",X16-V16) | AB16: =IF(ISBLANK(Y16),"",(J16-Y16)) | AC16: =IF(ISBLANK(X16),"",X16-M16)
B17: 9 | W17: =IF(ISBLANK(V17),"",V17-Q17) | Z17: =IF(ISBLANK(Y17),"",Y17/J17) | AA17: =IF(ISBLANK(X17),"",X17-V17) | AB17: =IF(ISBLANK(Y17),"",(J17-Y17)) | AC17: =IF(ISBLANK(X17),"",X17-M17)
B18: 10 | W18: =IF(ISBLANK(V18),"",V18-Q18) | Z18: =IF(ISBLANK(Y18),"",Y18/J18) | AA18: =IF(ISBLANK(X18),"",X18-V18) | AB18: =IF(ISBLANK(Y18),"",(J18-Y18)) | AC18: =IF(ISBLANK(X18),"",X18-M18)
B19: 11 | W19: =IF(ISBLANK(V19),"",V19-Q19) | Z19: =IF(ISBLANK(Y19),"",Y19/J19) | AA19: =IF(ISBLANK(X19),"",X19-V19) | AB19: =IF(ISBLANK(Y19),"",(J19-Y19)) | AC19: =IF(ISBLANK(X19),"",X19-M19)
B20: 12 | W20: =IF(ISBLANK(V20),"",V20-Q20) | Z20: =IF(ISBLANK(Y20),"",Y20/J20) | AA20: =IF(ISBLANK(X20),"",X20-V20) | AB20: =IF(ISBLANK(Y20),"",(J20-Y20)) | AC20: =IF(ISBLANK(X20),"",X20-M20)
B21: 13 | W21: =IF(ISBLANK(V21),"",V21-Q21) | Z21: =IF(ISBLANK(Y21),"",Y21/J21) | AA21: =IF(ISBLANK(X21),"",X21-V21) | AB21: =IF(ISBLANK(Y21),"",(J21-Y21)) | AC21: =IF(ISBLANK(X21),"",X21-M21)
B22: 14 | W22: =IF(ISBLANK(V22),"",V22-Q22) | Z22: =IF(ISBLANK(Y22),"",Y22/J22) | AA22: =IF(ISBLANK(X22),"",X22-V22) | AB22: =IF(ISBLANK(Y22),"",(J22-Y22)) | AC22: =IF(ISBLANK(X22),"",X22-M22)
B23: 15 | W23: =IF(ISBLANK(V23),"",V23-Q23) | Z23: =IF(ISBLANK(Y23),"",Y23/J23) | AA23: =IF(ISBLANK(X23),"",X23-V23) | AB23: =IF(ISBLANK(Y23),"",(J23-Y23)) | AC23: =IF(ISBLANK(X23),"",X23-M23)
B24: 16 | W24: =IF(ISBLANK(V24),"",V24-Q24) | Z24: =IF(ISBLANK(Y24),"",Y24/J24) | AB24: =IF(ISBLANK(Y24),"",(J24-Y24))
B25: 17 | G25: =IF(ISBLANK(F25),"",-F25*$M$3) | H25: =IF(ISBLANK(F25),"",-F25*$M$4) | J25: =IF(ISBLANK(F25),"",(SUM(F25:I25)+(F25+G25)*0.15)) | P25: =IF(ISBLANK(O25),"",O25-M25) | W25: =IF(ISBLANK(V25),"",V25-Q25) | Z25: =IF(ISBLANK(Y25),"",Y25/J25) | AA25: =IF(ISBLANK(X25),"",X25-V25) | AB25: =IF(ISBLANK(Y25),"",(J25-Y25)) | AC25: =IF(ISBLANK(X25),"",X25-M25)
B26: 18 | G26: =IF(ISBLANK(F26),"",-F26*$M$3) | H26: =IF(ISBLANK(F26),"",-F26*$M$4) | J26: =IF(ISBLANK(F26),"",(SUM(F26:I26)+(F26+G26)*0.15)) | P26: =IF(ISBLANK(O26),"",O26-M26) | W26: =IF(ISBLANK(V26),"",V26-Q26) | Z26: =IF(ISBLANK(Y26),"",Y26/J26) | AA26: =IF(ISBLANK(X26),"",X26-V26) | AB26: =IF(ISBLANK(Y26),"",(J26-Y26)) | AC26: =IF(ISBLANK(X26),"",X26-M26)
B27: 19 | G27: =IF(ISBLANK(F27),"",-F27*$M$3) | H27: =IF(ISBLANK(F27),"",-F27*$M$4) | J27: =IF(ISBLANK(F27),"",(SUM(F27:I27)+(F27+G27)*0.15)) | P27: =IF(ISBLANK(O27),"",O27-M27) | W27: =IF(ISBLANK(V27),"",V27-Q27) | Z27: =IF(ISBLANK(Y27),"",Y27/J27) | AA27: =IF(ISBLANK(X27),"",X27-V27) | AB27: =IF(ISBLANK(Y27),"",(J27-Y27)) | AC27: =IF(ISBLANK(X27),"",X27-M27)
B28: 20 | G28: =IF(ISBLANK(F28),"",-F28*$M$3) | H28: =IF(ISBLANK(F28),"",-F28*$M$4) | J28: =IF(ISBLANK(F28),"",(SUM(F28:I28)+(F28+G28)*0.15)) | P28: =IF(ISBLANK(O28),"",O28-M28) | W28: =IF(ISBLANK(V28),"",V28-Q28) | Z28: =IF(ISBLANK(Y28),"",Y28/J28) | AA28: =IF(ISBLANK(X28),"",X28-V28) | AB28: =IF(ISBLANK(Y28),"",(J28-Y28)) | AC28: =IF(ISBLANK(X28),"",X28-M28)
B29: 21 | G29: =IF(ISBLANK(F29),"",-F29*$M$3) | H29: =IF(ISBLANK(F29),"",-F29*$M$4) | J29: =IF(ISBLANK(F29),"",(SUM(F29:I29)+(F29+G29)*0.15)) | P29: =IF(ISBLANK(O29),"",O29-M29) | W29: =IF(ISBLANK(V29),"",V29-Q29) | Z29: =IF(ISBLANK(Y29),"",Y29/J29) | AA29: =IF(ISBLANK(X29),"",X29-V29) | AB29: =IF(ISBLANK(Y29),"",(J29-Y29)) | AC29: =IF(ISBLANK(X29),"",X29-M29)
B30: 22 | G30: =IF(ISBLANK(F30),"",-F30*$M$3) | H30: =IF(ISBLANK(F30),"",-F30*$M$4) | J30: =IF(ISBLANK(F30),"",(SUM(F30:I30)+(F30+G30)*0.15)) | P30: =IF(ISBLANK(O30),"",O30-M30) | W30: =IF(ISBLANK(V30),"",V30-Q30) | Z30: =IF(ISBLANK(Y30),"",Y30/J30) | AA30: =IF(ISBLANK(X30),"",X30-V30) | AB30: =IF(ISBLANK(Y30),"",(J30-Y30)) | AC30: =IF(ISBLANK(X30),"",X30-M30)
B31: 23 | G31: =IF(ISBLANK(F31),"",-F31*$M$3) | H31: =IF(ISBLANK(F31),"",-F31*$M$4) | J31: =IF(ISBLANK(F31),"",(SUM(F31:I31)+(F31+G31)*0.15)) | P31: =IF(ISBLANK(O31),"",O31-M31) | W31: =IF(ISBLANK(V31),"",V31-Q31) | Z31: =IF(ISBLANK(Y31),"",Y31/J31) | AA31: =IF(ISBLANK(X31),"",X31-V31) | AB31: =IF(ISBLANK(Y31),"",(J31-Y31)) | AC31: =IF(ISBLANK(X31),"",X31-M31)
B32: 24 | G32: =IF(ISBLANK(F32),"",-F32*$M$3) | H32: =IF(ISBLANK(F32),"",-F32*$M$4) | J32: =IF(ISBLANK(F32),"",(SUM(F32:I32)+(F32+G32)*0.15)) | P32: =IF(ISBLANK(O32),"",O32-M32) | W32: =IF(ISBLANK(V32),"",V32-Q32) | Z32: =IF(ISBLANK(Y32),"",Y32/J32) | AA32: =IF(ISBLANK(X32),"",X32-V32) | AB32: =IF(ISBLANK(Y32),"",(J32-Y32)) | AC32: =IF(ISBLANK(X32),"",X32-M32)
B33: 25 | G33: =IF(ISBLANK(F33),"",-F33*$M$3) | H33: =IF(ISBLANK(F33),"",-F33*$M$4) | J33: =IF(ISBLANK(F33),"",(SUM(F33:I33)+(F33+G33)*0.15)) | P33: =IF(ISBLANK(O33),"",O33-M33) | W33: =IF(ISBLANK(V33),"",V33-Q33) | Z33: =IF(ISBLANK(Y33),"",Y33/J33) | AA33: =IF(ISBLANK(X33),"",X33-V33) | AB33: =IF(ISBLANK(Y33),"",(J33-Y33)) | AC33: =IF(ISBLANK(X33),"",X33-M33)
B34: 26 | G34: =IF(ISBLANK(F34),"",-F34*$M$3) | H34: =IF(ISBLANK(F34),"",-F34*$M$4) | J34: =IF(ISBLANK(F34),"",(SUM(F34:I34)+(F34+G34)*0.15)) | P34: =IF(ISBLANK(O34),"",O34-M34) | W34: =IF(ISBLANK(V34),"",V34-Q34) | Z34: =IF(ISBLANK(Y34),"",Y34/J34) | AA34: =IF(ISBLANK(X34),"",X34-V34) | AB34: =IF(ISBLANK(Y34),"",(J34-Y34)) | AC34: =IF(ISBLANK(X34),"",X34-M34)
B35: 27 | G35: =IF(ISBLANK(F35),"",-F35*$M$3) | H35: =IF(ISBLANK(F35),"",-F35*$M$4) | J35: =IF(ISBLANK(F35),"",(SUM(F35:I35)+(F35+G35)*0.15)) | P35: =IF(ISBLANK(O35),"",O35-M35) | W35: =IF(ISBLANK(V35),"",V35-Q35) | Z35: =IF(ISBLANK(Y35),"",Y35/J35) | AA35: =IF(ISBLANK(X35),"",X35-V35) | AB35: =IF(ISBLANK(Y35),"",(J35-Y35)) | AC35: =IF(ISBLANK(X35),"",X35-M35)
B36: 28 | G36: =IF(ISBLANK(F36),"",-F36*$M$3) | H36: =IF(ISBLANK(F36),"",-F36*$M$4) | J36: =IF(ISBLANK(F36),"",(SUM(F36:I36)+(F36+G36)*0.15)) | P36: =IF(ISBLANK(O36),"",O36-M36) | W36: =IF(ISBLANK(V36),"",V36-Q36) | Z36: =IF(ISBLANK(Y36),"",Y36/J36) | AA36: =IF(ISBLANK(X36),"",X36-V36) | AB36: =IF(ISBLANK(Y36),"",(J36-Y36)) | AC36: =IF(ISBLANK(X36),"",X36-M36)
... B46: 38 | G46: =IF(ISBLANK(F46),"",-F46*$M$3) | H46: =IF(ISBLANK(F46),"",-F46*$M$4) | J46: =IF(ISBLANK(F46),"",(SUM(F46:I46)+(F46+G46)*0.15)) | P46: =IF(ISBLANK(O46),"",O46-M46) | W46: =IF(ISBLANK(V46),"",V46-Q46) | Z46: =IF(ISBLANK(Y46),"",Y46/J46) | AA46: =IF(ISBLANK(X46),"",X46-V46) | AB46: =IF(ISBLANK(Y46),"",(J46-Y46)) | AC46: =IF(ISBLANK(X46),"",X46-M46)
B47: 39 | G47: =IF(ISBLANK(F47),"",-F47*$M$3) | H47: =IF(ISBLANK(F47),"",-F47*$M$4) | J47: =IF(ISBLANK(F47),"",(SUM(F47:I47)+(F47+G47)*0.15))
B48: 40 | G48: =IF(ISBLANK(F48),"",-F48*$M$3) | H48: =IF(ISBLANK(F48),"",-F48*$M$4) | J48: =IF(ISBLANK(F48),"",(SUM(F48:I48)+(F48+G48)*0.15))
B49: 41 | G49: =IF(ISBLANK(F49),"",-F49*$M$3) | H49: =IF(ISBLANK(F49),"",-F49*$M$4) | J49: =IF(ISBLANK(F49),"",(SUM(F49:I49)+(F49+G49)*0.15))
B50: 42 | G50: =IF(ISBLANK(F50),"",-F50*$M$3) | H50: =IF(ISBLANK(F50),"",-F50*$M$4) | J50: =IF(ISBLANK(F50),"",(SUM(F50:I50)+(F50+G50)*0.15))
B51: 43 | G51: =IF(ISBLANK(F51),"",-F51*$M$3) | H51: =IF(ISBLANK(F51),"",-F51*$M$4) | J51: =IF(ISBLANK(F51),"",(SUM(F51:I51)+(F51+G51)*0.15))
B52: 44 | G52: =IF(ISBLANK(F52),"",-F52*$M$3) | H52: =IF(ISBLANK(F52),"",-F52*$M$4) | J52: =IF(ISBLANK(F52),"",(SUM(F52:I52)+(F52+G52)*0.15))
B53: 45 | G53: =IF(ISBLANK(F53),"",-F53*$M$3) | H53: =IF(ISBLANK(F53),"",-F53*$M$4) | J53: =IF(ISBLANK(F53),"",(SUM(F53:I53)+(F53+G53)*0.15))
B54: 46 | G54: =IF(ISBLANK(F54),"",-F54*$M$3) | H54: =IF(ISBLANK(F54),"",-F54*$M$4) | J54: =IF(ISBLANK(F54),"",(SUM(F54:I54)+(F54+G54)*0.15))
B55: 47 | G55: =IF(ISBLANK(F55),"",-F55*$M$3) | H55: =IF(ISBLANK(F55),"",-F55*$M$4) | J55: =IF(ISBLANK(F55),"",(SUM(F55:I55)+(F55+G55)*0.15))
B56: 48 | G56: =IF(ISBLANK(F56),"",-F56*$M$3) | H56: =IF(ISBLANK(F56),"",-F56*$M$4) | J56: =IF(ISBLANK(F56),"",(SUM(F56:I56)+(F56+G56)*0.15))
B57: 49 | G57: =IF(ISBLANK(F57),"",-F57*$M$3) | H57: =IF(ISBLANK(F57),"",-F57*$M$4) | J57: =IF(ISBLANK(F57),"",(SUM(F57:I57)+(F57+G57)*0.15))
B58: 50 | G58: =IF(ISBLANK(F58),"",-F58*$M$3) | H58: =IF(ISBLANK(F58),"",-F58*$M$4) | J58: =IF(ISBLANK(F58),"",(SUM(F58:I58)+(F58+G58)*0.15))
E59: TOTAL | F59: =SUM(F9:F58) -> 62889674 | G59: =SUM(G9:G58) -> 0 | H59: =SUM(H9:H58) -> 0 | I59: =SUM(I9:I58) -> -104500 | J59: =SUM(J9:J58) -> 72218625 | P59: =IF(ISBLANK(O59),"",O59-M59) | W59: =IF(ISBLANK(V59),"",V59-Q59) | AA59: =IF(ISBLANK(X59),"",X59-V59) | AB59: =SUM(AB9:AB58) -> 0 | AC59: =IF(ISBLANK(X59),"",X59-M59)

Sheet Procurement
D1: ='General Information'!C4 -> DAM2-02-009 | G1: Procurement Log - Long / Short Lead Items | X1: ='General Information'!L1 -> 46308
A2: SR. NO. | B2: Project ID | C2: ACT # in P6 | D2: Item Description | E2: Discipline | F2: (Long \Short) Lead Items | G2: BOQ. No. | H2: Unit | I2: Quantity | J2: Proc. Qty | K2: Planed P.O Date | L2: Date of Pur. Order Issued | M2: Purchase Order No. | N2: Supplier | O2: Supplier Phone | P2: Method of Shipping | Q2: Start Manufacturing Date | R2: Required on Job | S2: Es.D.A. to Site | T2: Acual.D.A. to Site | U2: Lead Time | V2: Approval Status | W2: Completion Rate | X2: Remarks | Y2: Delivery Qty
A3: =ROW()-2 -> 1 | B3: DAM2-01-029 | C3: B2.337126 04 | D3: Office KWH meter | E3: Electrical | F3: LL | G3: B2.337126 04 | H3: EA | I3: 1 | J3: 1 | K3: 46054 | L3: Not Issue | M3: NA | N3: Effective Power | O3: Taha 0555590882 | P3: Trucks | Q3: 46073 | R3: 46177 | T3: 0 | V3: B | W3: =Y3/I3 -> 0 | Y3: 0
A4: =ROW()-2 -> 2 | B4: DAM2-01-029 | C4: B2.337126 04 | D4: Main Guard House KWH meter | E4: Electrical | F4: LL | G4: B2.337126 04 | H4: EA | I4: 1 | J4: 1 | K4: 46060 | L4: 30.11.25 | M4: NA | N4: Effective Power | O4: Taha 0555590882 | P4: Trucks | Q4: 30.11.25 | R4: 46148 | T4: 0 | V4: B | W4: =Y4/I4 -> 0 | Y4: 0
A5: =ROW()-2 -> 3 | B5: DAM2-01-029 | C5: B2.337126 04 | D5: Guard Rooms KWH meter | E5: Electrical | F5: LL | G5: B2.337126 04 | H5: EA | I5: 14 | J5: 14 | K5: 46023 | L5: 45984 | M5: Jc/026Dm/25 | N5: Siemens Limited AGU | O5: Mohmoud 0539124686 | P5: Trucks | Q5: 45984 | R5: 46203 | T5: 0 | V5: B | W5: =Y5/I5 -> 0 | Y5: 0
A6: =ROW()-2 -> 4 | B6: DAM2-01-029 | C6: B2.337126 04 | D6: PW Station KWH meter | E6: Electrical | F6: LL | G6: B2.337126 04 | H6: EA | I6: 1 | J6: 1 | K6: 45954 | L6: 45984 | M6: Jc/027Dm/25 | N6: Siemens Limited AGU | O6: Basil Najjar 0138924503 Mahmoud Hassan 0539124686 | P6: Trucks | Q6: 45984 | R6: 46209 | T6: 0 | V6: B | W6: =Y6/I6 -> 0 | Y6: 0
A7: =ROW()-2 -> 5 | B7: DAM2-01-029 | C7: B2.337126 04 | D7: TSE Station KWH meter | E7: Electrical | F7: LL | G7: B2.337126 04 | H7: EA | I7: 1 | J7: 1 | K7: 46060 | L7: 45991 | M7: DAM-251229 | N7: Saudi Co. fo Lighting Fixtures (SACLF) | O7: Ayman 0510546706 | P7: Trucks | Q7: 45991 | R7: 46151 | T7: 320 | V7: B | W7: =Y7/I7 -> 320 | Y7: 320
A8: =ROW()-2 -> 6 | B8: DAM2-01-029 | C8: B2.337126 04 | D8: Sewage lift Station KWH meter | E8: Electrical | F8: LL | G8: B2.337126 04 | H8: EA | I8: 1 | J8: 1 | K8: 46060 | L8: 45988 | M8: DAM-251228 | N8: Jeddah Cable | O8: Amjad 0561792045 | P8: Trucks | Q8: 45988 | R8: 46161 | T8: 0 | V8: B | W8: =Y8/I8 -> 0 | Y8: 0
A9: =ROW()-2 -> 7 | B9: DAM2-01-029 | C9: B2.337100 02 | D9: 4x300mm2/ AL/XLPE/PVC | E9: Electrical | F9: LL | G9: B2.337100 02 | H9: LM | I9: 50 | J9: 50 | K9: 46060 | L9: 45991 | M9: DAM-251229 | N9: SLC/Philips | O9: Ayman 0510546706 | P9: Trucks | Q9: 45991 | R9: 46145 | T9: 0 | V9: B | W9: =Y9/I9 -> 0 | Y9: 0
A10: =ROW()-2 -> 8 | B10: DAM2-01-029 | C10: B2.337100 02 | D10: 4x185mm2/ AL/XLPE/PVC | E10: Electrical | F10: LL | G10: B2.337100 02 | H10: LM | I10: 1200 | J10: 1200 | K10: 46068 | L10: Not Issue | M10: NA | N10: SLC/Philips | O10: Bassam Imam 0500246975 | P10: Trucks | Q10: 46056 | R10: 46145 | T10: 0 | V10: B | W10: =Y10/I10 -> 0 | Y10: 0
A11: =ROW()-2 -> 9 | B11: DAM2-01-029 | C11: B2.337100 02 | D11: 4x70mm2/ AL/XLPE/PVC | E11: Electrical | F11: LL | G11: B2.337100 02 | H11: LM | I11: 3400 | J11: 3400 | K11: 46032 | L11: 45988 | M11: DAM-251228 | N11: Jeddah Cable | O11: Amjad 0561792045 | P11: Trucks | Q11: 45988 | R11: 46076 | T11: 0 | V11: B | W11: =Y11/I11 -> 0 | Y11: 0
A12: =ROW()-2 -> 10 | B12: DAM2-01-029 | C12: B2.337126 01 | D12: Low Voltage Distribution Pillars | E12: Electrical | F12: LL | G12: B2.337126 01 | H12: EA | I12: 7 | J12: 7 | K12: 46073 | L12: Not Issue | M12: NA | N12: Khreji ABB | O12: Ahmad | P12: Trucks | Q12: 46054 | R12: 46067 | T12: 0 | V12: B | W12: =Y12/I12 -> 0 | Y12: 0
A13: =ROW()-2 -> 11 | B13: DAM2-01-029 | C13: New item | D13: Irrigattion control panel | E13: Electrical | F13: LL | G13: New item | H13: EA | I13: 1 | J13: 1 | K13: 46042 | L13: 20.12.25 | M13: Jc/019Dm/25 | N13: Schneider-MOTS | O13: Muhamad Zubair 0508195967 | P13: Trucks | Q13: 46035 | R13: 46186 | T13: 0 | V13: B | W13: =Y13/I13 -> 0 | Y13: 0
A14: =ROW()-2 -> 12 | B14: DAM2-01-029 | C14: New item | D14: UPS 5KVA for Sewage lift station(Industrial UPS) | E14: Electrical | F14: LL | G14: New item | H14: EA | I14: 1 | J14: 1 | K14: 46021 | L14: 10.01.26 | M14: DAM-251231 | N14: Al-Ojaimi Factory | O14: Hashim 0558092903 | P14: Trucks | Q14: 46043 | R14: 46088 | T14: 0 | V14: B | W14: =Y14/I14 -> 0 | Y14: 0
A15: =ROW()-2 -> 13 | B15: DAM2-01-029 | C15: New item | D15: DB UPS for Sewage lift station | E15: Electrical | F15: LL | G15: New item | H15: EA | I15: 1 | J15: 1 | K15: 46021 | L15: 20.12.25 | M15: Jc/019Dm/25 | N15: Schneider-MOTS | O15: Muhamad Zubair 0508195967 | P15: Trucks | Q15: 46043 | R15: 46088 | T15: 0 | V15: B | W15: =Y15/I15 -> 0 | Y15: 0
A16: =ROW()-2 -> 14 | B16: DAM2-01-029 | C16: New item | D16: UPS 5KVA for Portable water pump station(Industrial UPS) | E16: Electrical | F16: LL | G16: New item | H16: EA | I16: 1 | J16: 1 | K16: 46037 | L16: 20.12.25 | M16: Jc/019Dm/25 | N16: Schneider-MOTS | O16: Muhamad Zubair 0508195967 | P16: Trucks | Q16: 46131 | R16: 46191 | T16: 0 | V16: B | W16: =Y16/I16 -> 0 | Y16: 0
A17: =ROW()-2 -> 15 | B17: DAM2-01-029 | C17: New item | D17: DB UPS for Portable water pump station | E17: Electrical | F17: LL | G17: New item | H17: EA | I17: 1 | J17: 1 | K17: 46021 | L17: 10.01.26 | M17: DAM-251231 | N17: Al-Ojaimi Factory | O17: Hashim 0558092903 | P17: Trucks | Q17: 46023 | R17: 46082 | T17: 0 | V17: B | W17: =Y17/I17 -> 0 | Y17: 0
A18: =ROW()-2 -> 16 | B18: DAM2-01-029 | C18: New item | D18: 630Amp MCCB for fire water pump no.1 | E18: Electrical | F18: LL | G18: New item | H18: EA | I18: 2 | J18: 2 | K18: 46073 | L18: 46006 | M18: DAM-151229 | N18: Jeddah Cable | O18: Amjad 0561792045 | P18: Trucks | Q18: 27.11.25 | R18: 46052 | T18: 12600 | V18: B | W18: =Y18/I18 -> 6300 | Y18: 12600
A19: =ROW()-2 -> 17 | B19: DAM2-01-029 | C19: New item | D19: VFD for fire water Pump no.1 | E19: Electrical | F19: LL | G19: New item | H19: EA | I19: 1 | J19: 1 | K19: 46084 | L19: 45969 | M19: Jc/020Dm/25 | N19: SFFECO | O19: Ahmad Gaballah 050521925 | P19: Trucks | Q19: 45969 | R19: 46174 | T19: 0 | V19: B | W19: =Y19/I19 -> 0 | Y19: 0
A20: =ROW()-2 -> 18 | B20: DAM2-01-029 | C20: New item | D20: 20A, 3P, 60Hz Isolator/disconnect switches IP65 | E20: Electrical | F20: LL | G20: New item | H20: EA | I20: 1 | J20: 1 | K20: 45969 | L20: 45969 | M20: Jc/017Dm/25 | N20: JADF | O20: Azeem alasawey 0542110025 | P20: Trucks | Q20: 46131 | R20: 46146 | T20: 0 | V20: B | W20: =Y20/I20 -> 0 | Y20: 0
A21: =ROW()-2 -> 19 | B21: DAM2-01-029 | C21: New item | D21: Telecom Main Antena at guard room 1 | E21: Electrical | F21: LL | G21: New item | H21: EA | I21: 1 | J21: 1 | K21: 45985 | L21: 46042 | M21: PO UCC-C6-046 | N21: SPS | O21: Rami Hamouri 055 999 4033 | P21: Trucks | Q21: 46000 | R21: 46030 | T21: 61 | V21: B | W21: =Y21/I21 -> 61 | Y21: 61
A22: =ROW()-2 -> 20 | B22: DAM2-01-029 | C22: New item | D22: DC-GR Cabinet | E22: Electrical | F22: LL | G22: New item | H22: EA | I22: 1 | J22: 1 | K22: 45969 | L22: 45969 | M22: PO UCC-C6-004 | N22: SFFECO | O22: Repy 0533723157 | P22: Trucks | Q22: 45969 | R22: 46039 | T22: 0 | V22: B | W22: =Y22/I22 -> 0 | Y22: 0
A23: =ROW()-2 -> 21 | B23: DAM2-01-029 | C23: New item | D23: Telecom Antena guard room2 | E23: Electrical | F23: LL | G23: New item | H23: EA | I23: 3 | J23: 3 | K23: 45969 | L23: 45969 | M23: Jc/018Dm/25 | N23: KSB | O23: Khalid Al Shemy 58 260 9298 | P23: Trucks | Q23: 45969 | R23: 46186 | T23: 0 | V23: B | W23: =Y23/I23 -> 0 | Y23: 0
A24: =ROW()-2 -> 22 | B24: DAM2-01-029 | C24: New item | D24: DC-GR1-Cabinet | E24: Electrical | F24: LL | G24: New item | H24: EA | I24: 3 | J24: 3 | K24: 45969 | L24: 45969 | M24: Jc/020Dm/25 | N24: SFFECO | O24: Ahmed Gaballah 0505219256 | P24: Trucks | Q24: 45969 | R24: 46186 | T24: 0 | V24: B | W24: =Y24/I24 -> 0 | Y24: 0
A25: =ROW()-2 -> 23 | B25: DAM2-01-029 | C25: New item | D25: Clorination -Indutrial socket outlet,1P,with grounding,Suuply & apply including cable,conduit,T&C as per IFC and Project Specs. | E25: Electrical | F25: LL | G25: New item | H25: EA | I25: 6 | J25: 6 | K25: 45969 | L25: 45969 | M25: Jc/018Dm/25 | N25: KSB | O25: Khalid Al Shemy 58 260 9298 | P25: Trucks | Q25: 45969 | R25: 46197 | T25: 0 | V25: B | W25: =Y25/I25 -> 0 | Y25: 0
A26: =ROW()-2 -> 24 | B26: DAM2-01-029 | C26: New item | D26: Clorination-20A dissconnect switch/Isolator ,Suuply & apply including cable,conduit,T&C as per IFC and Project Specs. | E26: Electrical | F26: LL | G26: New item | I26: 2 | J26: 2 | K26: 46107 | L26: Not Issue | M26: NA | N26: Power Technics | O26: Omar 0558665562 | P26: Trucks | Q26: 46137 | R26: 46197 | T26: 0 | V26: B | W26: =Y26/I26 -> 0 | Y26: 0
A27: =ROW()-2 -> 25 | B27: DAM2-01-029 | C27: New item | D27: Clorination-Pendant Lights 35W Normal IP65,4200Lumens ,Suuply & apply including cable,conduit,T&C as per IFC and Project Specs. | E27: Electrical | F27: LL | G27: New item | H27: EA | I27: 3 | J27: 3 | K27: 46116 | L27: Not Issue | M27: NA | N27: AL SAGHEER | O27: Ali Al Fadel 0559339753 | P27: Trucks | Q27: 46146 | R27: 46191 | T27: 0 | V27: B | W27: =Y27/I27 -> 0 | Y27: 0
A28: =ROW()-2 -> 26 | B28: DAM2-01-029 | C28: New item | D28: Clorination-Pendant Lights 35W Emergency IP65 with 3 Hrs kit,4200lumens,Suuply & apply including cable,conduit,T&C as per IFC and Project Specs. | E28: Electrical | F28: LL | G28: New item | H28: EA | I28: 1 | J28: 1 | K28: 46071 | L28: Not Issue | M28: NA | N28: Environmental System | O28: Haytham 0565412827 | P28: Trucks | Q28: 46073 | R28: 46208 | T28: 0 | V28: B | W28: =Y28/I28 -> 0 | Y28: 0
A29: =ROW()-2 -> 27 | B29: DAM2-01-029 | C29: New item | D29: Wall mounted Bulk head lights 15W IP65,Suuply & apply including cable,conduit,T&C as per IFC and Project Specs. | E29: Electrical | F29: LL | G29: New item | H29: EA | I29: 2 | J29: 2 | K29: 46071 | L29: Not Issue | M29: NA | N29: Arabian Scope | O29: Waheed 0555830075 | P29: Trucks | Q29: 46055 | R29: 46208 | T29: 0 | V29: B | W29: =Y29/I29 -> 0 | Y29: 0
A30: =ROW()-2 -> 28 | B30: DAM2-01-029 | C30: New item | D30: Clorination -Grounding system ,Suuply & apply including cable,conduit,T&C as per IFC and Project Specs. | E30: Electrical | F30: LL | G30: New item | H30: EA | I30: 1 | J30: 1 | K30: 46071 | L30: Not Issue | M30: NA | N30: Arabian Scope | O30: Waheed 0555830075 | P30: Trucks | Q30: 46178 | R30: 46208 | T30: 0 | V30: B | W30: =Y30/I30 -> 0 | Y30: 0
A31: =ROW()-2 -> 29 | B31: DAM2-01-029 | C31: New item | D31: Clorination-4x10mm2 CU/XLPE/PVC+1CX100MM2 CU/PVCDB-CL ,Suuply & apply including cable,conduit,T&C as per IFC and Project Specs. | E31: Electrical | F31: LL | G31: New item | H31: LM | I31: 45 | J31: 45 | K31: 46039 | L31: 29.01.26 | M31: Jc/015Dm/26 | N31: Riyadh Crane | O31: Ahmed Qasim 0594602092 | P31: Trucks | Q31: 46069 | R31: 46114 | T31: 0 | V31: B | W31: =Y31/I31 -> 0 | Y31: 0
A32: =ROW()-2 -> 30 | B32: DAM2-01-029 | C32: New item | D32: DI pipe 350 mm, Pn16 | E32: Mechanical | F32: LL | G32: New item | H32: EA | I32: 12 | J32: 12 | K32: 46078 | L32: 28.12.25 | M32: Jc/028Dm/25 | N32: Environmental System | O32: Haytham 0565412827 | P32: Trucks | Q32: 46108 | R32: 46138 | T32: 0 | V32: B | W32: =Y32/I32 -> 0 | Y32: 0
A33: =ROW()-2 -> 31 | B33: DAM2-01-029 | C33: New item | D33: DI Pudle flange 350 mm, Pn16 | E33: Mechanical | F33: LL | G33: New item | H33: EA | I33: 2 | J33: 2 | K33: 45939 | L33: 45969 | M33: Jc/019Dm/25 | N33: MOTS | O33: Muhammad zubair 0508195967 | P33: Trucks | Q33: 45969 | R33: 46183 | T33: 0 | V33: B | W33: =Y33/I33 -> 0 | Y33: 0
A34: =ROW()-2 -> 32 | B34: DAM2-01-029 | C34: New item | D34: DI pipe 200 mm, Pn16 | E34: Mechanical | F34: LL | G34: New item | H34: EA | I34: 24 | J34: 24 | K34: 45991 | L34: 45984 | M34: Jc/025Dm/25 | N34: CUMMINS | O34: Mahmoud 0540488952 | P34: Trucks | Q34: 45984 | R34: 46177 | T34: 0 | V34: B | W34: =Y34/I34 -> 0 | Y34: 0
A35: =ROW()-2 -> 33 | B35: DAM2-01-029 | C35: New item | D35: DI Pudle flange,200mm, Pn16 | E35: Mechanical | F35: LL | G35: New item | H35: EA | I35: 3 | J35: 3 | K35: 45954 | L35: 45984 | M35: Jc/027Dm/25 | N35: Siemens Limited AGU | O35: Basil 0507972833 | P35: Trucks | Q35: 45984 | R35: 46125 | T35: 0 | V35: B | W35: =Y35/I35 -> 0 | Y35: 0
A36: =ROW()-2 -> 34 | B36: DAM2-01-029 | C36: New item | D36: DI gate valve,200mm, Pn16 | E36: Mechanical | F36: SL | G36: New item | H36: EA | I36: 2 | J36: 2 | K36: 46086 | L36: Not Issue | M36: NA | N36: Road Technology | O36: Soheel 597055344 | P36: Trucks | Q36: 46096 | R36: 46127 | T36: 0 | V36: B | W36: =Y36/I36 -> 0 | Y36: 0
A37: =ROW()-2 -> 35 | B37: DAM2-01-029 | C37: New item | D37: DI float valve,200mm, Pn16 | E37: Mechanical | F37: SL | G37: New item | H37: EA | I37: 2 | J37: 2 | K37: 46091 | L37: Not Issue | M37: NA | N37: AL Kamline | O37: Hani 506668043 | P37: Trucks | Q37: 46091 | R37: 46132 | T37: 0 | V37: B | W37: =Y37/I37 -> 0 | Y37: 0
A38: =ROW()-2 -> 36 | B38: DAM2-01-029 | C38: New item | D38: DI Pudle flange,150 mm, Pn16 | E38: Mechanical | F38: SL | G38: New item | H38: EA | I38: 4 | J38: 4 | K38: 45945 | L38: 45931 | M38: PO 001 | N38: SAJCO | O38: Ahmad 0550750285 | P38: Trucks | Q38: 45931 | R38: 45963 | T38: 0 | V38: B | W38: =Y38/I38 -> 0 | Y38: 0
A39: =ROW()-2 -> 37 | B39: DAM2-01-029 | C39: New item | D39: DI gate valve150mm, Pn16 | E39: Mechanical | F39: SL | G39: New item | H39: EA | I39: 2 | J39: 2 | K39: 45945 | L39: 45931 | M39: PO 002 | N39: SAJCO | O39: Ahmad 0550750285 | P39: Trucks | Q39: 45931 | R39: 45977 | T39: 0 | V39: B | W39: =Y39/I39 -> 0 | Y39: 0
A40: =ROW()-2 -> 38 | B40: DAM2-01-029 | C40: New item | D40: DI pipe100 mm, Pn16 | E40: Mechanical | F40: SL | G40: New item | H40: EA | I40: 12 | J40: 12 | K40: 45945 | L40: 45931 | M40: PO 003 | N40: SAJCO | O40: Ahmad 0550750285 | P40: Trucks | Q40: 45931 | R40: 45949 | T40: 0 | V40: B | W40: =Y40/I40 -> 110416.67 | Y40: 1325000
A41: =ROW()-2 -> 39 | B41: DAM2-01-029 | C41: New item | D41: DI Pudle flange,100 mm, Pn16 | E41: Mechanical | F41: SL | G41: New item | H41: EA | I41: 2 | J41: 2 | K41: 45950 | L41: 45979 | M41: PO 004 | N41: SAJCO | O41: Mahmoud 0504467488 | P41: Trucks | Q41: 46091 | R41: 46101 | T41: 0 | V41: B | W41: =Y41/I41 -> 0 | Y41: 0
A42: =ROW()-2 -> 40 | B42: DAM2-01-029 | C42: New item | D42: vent pipe galvanized 100 mm | E42: Mechanical | F42: SL | G42: New item | H42: EA | I42: 12 | J42: 12 | K42: 45950 | L42: 45979 | M42: PO 004 | N42: SAJCO | O42: Mahmoud 0504467488 | P42: Trucks | Q42: 46091 | R42: 46101 | T42: 0 | V42: B | W42: =Y42/I42 -> 0 | Y42: 0
A43: =ROW()-2 -> 41 | B43: DAM2-01-029 | C43: New item | D43: scupper roof drain 110 mm | E43: Mechanical | F43: SL | G43: New item | H43: EA | I43: 8 | J43: 8 | K43: 46037 | L43: 31.01.26 | M43: PO 010 | N43: Riyadh Kingdom | O43: Eyad 0545515566 | P43: Trucks | Q43: 46054 | R43: 46068 | T43: 0 | V43: B | W43: =Y43/I43 -> 0 | Y43: 0
A44: =ROW()-2 -> 42 | B44: DAM2-01-029 | C44: New item | D44: 40Amp Disconnect Switch for Crane(4P IP65) | E44: Electrical | F44: SL | G44: New item | H44: EA | I44: 0 | J44: 0 | K44: 46037 | L44: 31.01.26 | M44: PO 010 | N44: Riyadh Kingdom | O44: Eyad 0545515566 | P44: Trucks | Q44: 46054 | R44: 46068 | T44: 0 | V44: B | W44: =Y44/I44 -> #DIV/0! | Y44: 0
A45: =ROW()-2 -> 43 | B45: DAM2-01-029 | C45: New item | D45: 40Amp Disconnect Switch for penstock(4P IP65) | E45: Electrical | F45: SL | G45: New item | H45: EA | I45: 0 | J45: 0 | K45: 46037 | L45: 05.02.26 | M45: PO 011 | N45: Riyadh Kingdom | O45: Eyad 0545515566 | P45: Trucks | Q45: 46113 | R45: 46133 | T45: 0 | V45: B | W45: =Y45/I45 -> #DIV/0! | Y45: 0
A46: =ROW()-2 -> 44 | B46: DAM2-01-029 | C46: New item | D46: 40Amp Disconnect Switch for Order(4P IP65) Contol Unit | E46: Electrical | F46: SL | G46: New item | H46: EA | I46: 0 | J46: 0 | K46: 46068 | L46: Not Issue | M46: NA | N46: NEXUS | O46: Hasan 564632788 | P46: Trucks | Q46: 46091 | R46: 46121 | T46: 0 | V46: B | W46: =Y46/I46 -> #DIV/0! | Y46: 0
A47: =ROW()-2 -> 45 | B47: DAM2-01-029 | C47: New item | D47: 30Amp Disconnect Switch Bar screen(4P IP65) | E47: Electrical | F47: SL | G47: New item | H47: EA | I47: 0 | J47: 0 | K47: 46042 | L47: 29.01.26 | M47: PO 011 | N47: SAJCO | O47: Ahmad 0550750285 | P47: Trucks | Q47: 46091 | R47: 46121 | T47: 0 | V47: B | W47: =Y47/I47 -> #DIV/0! | Y47: 0
A48: =ROW()-2 -> 46 | B48: DAM2-01-029 | C48: New item | D48: 30Amp Disconnect Switch for Fuel pump control Panel(4P IP65) | E48: Electrical | F48: SL | G48: New item | H48: EA | I48: 0 | J48: 0 | K48: 46021 | L48: 46040 | M48: PO 006 | N48: Saudi Benaa | O48: Muhammad Ghalib 550112470 | P48: Trucks | Q48: 46026 | R48: 46026 | T48: 0 | V48: B | W48: =Y48/I48 -> #DIV/0! | Y48: 0
A49: =ROW()-2 -> 47 | B49: DAM2-01-029 | C49: New item | D49: 3 KW - one Local Control Panel for two pumps(IP-65) | E49: Electrical | F49: SL | G49: New item | H49: EA | I49: 0 | J49: 0 | K49: 46021 | L49: 46037 | M49: PO 007 | N49: AL Faisal Al Rajhi | O49: Mohamed Shaikh 534913166 | P49: Trucks | Q49: 46047 | R49: 46057 | T49: 0 | V49: B | W49: =Y49/I49 -> #DIV/0! | Y49: 0
A50: =ROW()-2 -> 48 | B50: DAM2-01-029 | C50: New item | D50: 630Amp MCCB with IP65 inclosure | E50: Electrical | F50: SL | G50: New item | H50: EA | I50: 0 | J50: 0 | K50: 46018 | L50: Not Issue | M50: PO 012 | N50: Riyadh Kingdom AL Manarateen | O50: AHMED IBRAHIM 500165534 | P50: Trucks | Q50: 46037 | R50: 46026 | T50: 0 | V50: B | W50: =Y50/I50 -> #DIV/0! | Y50: 0
A51: =ROW()-2 -> 49 | B51: DAM2-01-029 | C51: New item | D51: 260kw-Local Control Panel for fire water pump -IP65) | E51: Electrical | F51: SL | G51: New item | H51: EA | I51: 0 | J51: 0 | K51: 46018 | L51: Not Issue | M51: NA | N51: Isam Kabbani | O51: Mamoon 538477569 | P51: Trucks | Q51: 46023 | R51: 46026 | T51: 0 | V51: B | W51: =Y51/I51 -> #DIV/0! | Y51: 0
A52: =ROW()-2 -> 50 | B52: DAM2-01-029 | C52: New item | D52: 260KW VFD for fire water Pump( IP54) | E52: Electrical | F52: SL | G52: New item | H52: EA | I52: 0 | J52: 0 | K52: 46079 | L52: Not Issue | M52: NA | N52: Art International | O52: Ahmad Khaled 54 408 2100 | P52: Trucks | Q52: 46079 | R52: 46109 | T52: 0 | V52: B | W52: =Y52/I52 -> #DIV/0! | Y52: 0
A53: =ROW()-2 -> 51 | B53: DAM2-01-029 | C53: New item | D53: 260 KW-Local Control Panel for fire water pump( IP65) | E53: Electrical | F53: SL | G53: New item | H53: EA | I53: 0 | J53: 0 | K53: 46079 | L53: Not Issue | M53: NA | N53: Art International | O53: Ahmad Khaled 54 408 2100 | P53: Trucks | Q53: 46079 | R53: 46109 | T53: 0 | V53: B | W53: =Y53/I53 -> #DIV/0! | Y53: 0
A54: =ROW()-2 -> 52 | B54: DAM2-01-029 | C54: New item | D54: 40Amp MCCB for Jockey pump | E54: Electrical | F54: SL | G54: New item | H54: EA | I54: 0 | J54: 0 | K54: 46063 | L54: Not Issue | M54: NA | N54: Art International | O54: Ahmad Khaled 54 408 2100 | P54: Trucks | Q54: 46053 | R54: 46083 | T54: 0 | V54: B | W54: =Y54/I54 -> #DIV/0! | Y54: 0
A55: =ROW()-2 -> 53 | B55: DAM2-01-029 | C55: New item | D55: 60 Amp Disconnect Switch for Jocky pump(4P IP65) | E55: Electrical | F55: SL | G55: New item | H55: EA | I55: 0 | J55: 0 | K55: 46063 | L55: Not Issue | M55: NA | N55: MODERN WOOD WORKS FACTORY | O55: Wael Ahour 558338634 | P55: Trucks | Q55: 46159 | R55: 46189 | T55: 0 | V55: B | W55: =Y55/I55 -> #DIV/0! | Y55: 0
A56: =ROW()-2 -> 54 | B56: DAM2-01-029 | C56: New item | D56: 7 KW-Local Control Panel for Jocky pump( IP65) | E56: Electrical | F56: SL | G56: New item | H56: EA | I56: 0 | J56: 0 | K56: 46047 | L56: 29.01.26 | M56: PO 009 | N56: BRC | O56: Modar Al Adwani 502787877 | P56: Trucks | Q56: 46179 | R56: 46224 | T56: 0 | V56: B | W56: =Y56/I56 -> #DIV/0! | Y56: 0
A57: =ROW()-2 -> 55 | B57: DAM2-01-029 | C57: New item | D57: 3KW-one Local Control Panel for two fuel pump(IP65) | E57: Electrical | F57: SL | G57: New item | H57: EA | I57: 0 | J57: 0 | K57: 46047 | L57: 28.01.26 | M57: PO 008 | N57: SAJCO | O57: Ahmad Khaled 54 408 2100 | P57: Trucks | Q57: 46179 | R57: 46224 | T57: 0 | V57: B | W57: =Y57/I57 -> #DIV/0! | Y57: 0
A58: =ROW()-2 -> 56 | B58: DAM2-01-029 | C58: New item | D58: 30Amp disconnect switch for two fuel pumps`s control panel(4P IP65) | E58: Electrical | F58: SL | G58: New item | H58: EA | I58: 0 | J58: 0 | K58: 46078 | L58: Not Issue | M58: NA | N58: Art International | O58: Ahmad Khaled 54 408 2100 | P58: Trucks | Q58: 46144 | R58: 46174 | T58: 0 | V58: B | W58: =Y58/I58 -> #DIV/0! | Y58: 0
A59: =ROW()-2 -> 57 | B59: DAM2-01-029 | C59: New item | D59: 30Amp Disconnect Switch for Crane(4P IP65) | E59: Electrical | F59: SL | G59: New item | H59: EA | I59: 0 | J59: 0 | K59: 46054 | L59: Not Issue | M59: NA | N59: Art International | O59: Ahmad Khaled 54 408 2100 | P59: Trucks | Q59: 46091 | R59: 46118 | T59: 0 | V59: B | W59: =Y59/I59 -> #DIV/0! | Y59: 0
A60: =ROW()-2 -> 58 | B60: DAM2-01-029 | C60: New item | D60: 7KW-One Local Control Panel for two submersible pumps( IP65) | E60: Electrical | F60: SL | G60: New item | H60: EA | I60: 0 | J60: 0 | K60: 45962 | L60: 45940 | M60: PO UCC-C6-031 | N60: Alyaf | O60: Mohamad Osam 559472880 | P60: Trucks | Q60: 45962 | R60: 46356 | T60: 0 | V60: B | W60: =Y60/I60 -> #DIV/0! | Y60: 22200
A61: =ROW()-2 -> 59 | B61: DAM2-01-029 | C61: New item | D61: Low Volatge cable (1x630mm2)CU/MICA/XPLE/LOSH) for fire pump no.2 | E61: Electrical | F61: SL | G61: New item | H61: LM | I61: 0 | J61: 0 | K61: 45962 | L61: 45971 | M61: PO UCC-C6-032 | N61: IKK | O61: Maamoon 506362390 | P61: Trucks | Q61: 46023 | R61: 46026 | T61: 0 | V61: B | W61: =Y61/I61 -> #DIV/0! | Y61: 6000
A62: =ROW()-2 -> 60 | B62: DAM2-01-029 | C62: New item | D62: Low Volatge cable (1x300mm2)CU/MICA/XPLE/LOSH) for fire pump no.2 | E62: Electrical | F62: SL | G62: New item | H62: LM | I62: 0 | J62: 0 | K62: 46037 | L62: Not Issue | M62: NA | N62: SIKA | O62: Saqr Esbitan 555436939 | P62: Trucks | Q62: 46054 | R62: 46068 | T62: 0 | V62: B | W62: =Y62/I62 -> #DIV/0! | Y62: 0
A63: =ROW()-2 -> 61 | B63: DAM2-01-029 | C63: New item | D63: Low Volatge cable 4x10mm2)CU/MICA/XPLE/LOSH) for Jocky Pump | E63: Electrical | F63: SL | G63: New item | H63: LM | I63: 0 | J63: 0 | K63: 46054 | L63: Not Issue | M63: NA | N63: Saudi Paint Co Ltd ( Paintco ) | O63: Mohammad 540806806 | P63: Trucks | Q63: 46082 | R63: 46109 | T63: 0 | V63: B | W63: =Y63/I63 -> #DIV/0! | Y63: 0
A64: =ROW()-2 -> 62 | B64: DAM2-01-029 | C64: New item | D64: Low Volatge cable 1x10mm2)CU/MICA/XPLE/LOSH) for Jocky Pump | E64: Electrical | F64: SL | G64: New item | H64: LM | I64: 0 | J64: 0 | K64: 46054 | L64: Not Issue | M64: NA | N64: Saudi Paint Co Ltd ( Paintco ) | O64: Mohammad 540806806 | P64: Trucks | Q64: 46082 | R64: 46109 | T64: 0 | V64: B | W64: =Y64/I64 -> #DIV/0! | Y64: 0
A65: =ROW()-2 -> 63 | B65: DAM2-01-029 | C65: New item | D65: Draw pit with heavy duty steel cover,size 1400x600x1200mm | E65: Electrical | F65: SL | G65: New item | H65: EA | I65: 0 | J65: 0 | K65: 46054 | L65: Not Issue | M65: NA | N65: Al Fanar | O65: Turki Al Turki 549991949 | P65: Trucks | Q65: 46113 | R65: 46126 | T65: 0 | V65: B | W65: =Y65/I65 -> #DIV/0! | Y65: 0
A66: =ROW()-2 -> 64 | B66: DAM2-01-029 | C66: New item | D66: Draw pit with heavy duty steel cover,size 1400x600x600mm | E66: Electrical | F66: SL | G66: New item | H66: EA | I66: 0 | J66: 0 | K66: 46037 | L66: Not Issue | M66: NA | N66: NA | O66: NA | P66: Trucks | Q66: 46068 | R66: 46083 | T66: 0 | V66: B | W66: =Y66/I66 -> #DIV/0! | Y66: 0
A67: =ROW()-2 -> 65 | B67: DAM2-01-029 | C67: Bill:2-337100.02 | D67: Street lighting duct bank | E67: Electrical | F67: SL | G67: Bill:2-337100.02 | H67: LM | I67: 0 | J67: 0 | K67: 46042 | L67: Not Issue | M67: NA | N67: NA | O67: NA | P67: Trucks | Q67: 46054 | R67: 46083 | T67: 0 | V67: B | W67: =Y67/I67 -> #DIV/0! | Y67: 0
A68: =ROW()-2 -> 66 | B68: DAM2-01-029 | C68: B2.33 7100.01 | D68: LV duct bank | E68: Electrical | F68: SL | G68: B2.33 7100.01 | H68: LM | I68: 0 | J68: 0 | K68: 46042 | L68: Not Issue | M68: NA | N68: NA | O68: NA | P68: Trucks | Q68: 46054 | R68: 46083 | T68: 0 | V68: B | W68: =Y68/I68 -> #DIV/0! | Y68: 0
A69: =ROW()-2 -> 67 | B69: DAM2-01-029 | C69: B2.33 7100 | D69: MV duct back | E69: Electrical | F69: SL | G69: B2.33 7100 | H69: LM | I69: 0 | J69: 0 | K69: 46042 | L69: Not Issue | M69: NA | N69: NA | O69: NA | P69: Trucks | Q69: 46054 | R69: 46083 | T69: 0 | V69: B | W69: =Y69/I69 -> #DIV/0! | Y69: 0
A70: =ROW()-2 -> 68 | B70: DAM2-01-029 | C70: Bill:2.1-338126.03 | D70: Telecom duct bank | E70: Electrical | F70: SL | G70: Bill:2.1-338126.03 | H70: LM | I70: 0 | J70: 0 | K70: 46032 | L70: Not Issue | M70: NA | N70: DCP | O70: Yazan 0532449865 | P70: Trucks | Q70: 46082 | R70: 46109 | T70: 0 | V70: B | W70: =Y70/I70 -> #DIV/0! | Y70: 0
A71: =ROW()-2 -> 69 | B71: DAM2-01-029 | C71: B2.33 7100.02 | D71: MV duct bank(4x150) | E71: Electrical | F71: SL | G71: B2.33 7100.02 | H71: LM | I71: 100 | J71: 100 | K71: 46086 | L71: Not Issue | M71: NA | N71: NA | O71: NA | P71: Trucks | Q71: 46143 | R71: 46212 | T71: 0 | V71: B | W71: =Y71/I71 -> 0 | Y71: 0
A72: =ROW()-2 -> 70 | B72: DAM2-01-029 | C72: Bill-8 | D72: DB-MGR Panel: 32/100 Ampere, 3P, IP66,60Hz incomer MCCB . For guard room 1 | E72: Electrical | F72: SL | G72: Bill-8 | H72: EA | I72: 1 | J72: 1 | K72: 46006 | L72: 46357 | M72: PO 005 | N72: AHMED ALWAN GEN | O72: Mohammad 0549358786 | P72: Trucks | Q72: 46023 | R72: 46026 | T72: 0 | V72: B | W72: =Y72/I72 -> 0 | Y72: 0
A73: =ROW()-2 -> 71 | B73: DAM2-01-029 | C73: Bill-8 | D73: DB-GR Panel: 32/100 Ampere, 3P, IP66,60Hz incomer MCCB .For guard room 2 | E73: Electrical | F73: SL | G73: Bill-8 | H73: EA | I73: 3 | J73: 3 | K73: 46086 | L73: Not Issue | M73: NA | N73: AL Khreji | O73: Mahmoud 0555219643 | P73: Trucks | Q73: 46058 | R73: 46146 | T73: 0 | V73: B | W73: =Y73/I73 -> 0 | Y73: 0
A74: =ROW()-2 -> 72 | B74: DAM2-01-029 | C74: Bill-8 | D74: 4Cx 6mm2 + 1Cx6mm2 Cu/XLPE/PVC FROM KWHM to DB-MGR For guard room 1 & 2 | E74: Electrical | F74: SL | G74: Bill-8 | H74: EA | I74: 40 | J74: 40 | K74: 20.10.25 | L74: 25.01.26 | M74: DAM-260102 | N74: TARIQ NAGADI | O74: Ahmed Al deeb 0539747328 | P74: Trucks | Q74: 46052 | R74: 46096 | T74: 0 | V74: B | W74: =Y74/I74 -> 0 | Y74: 0
A75: =ROW()-2 -> 73 | B75: DAM2-01-029 | C75: Bill-8 | D75: Conduit and accessories FROM KWHM to DB-MGR For guard room 1 & 2 | E75: Electrical | F75: SL | G75: Bill-8 | H75: EA | I75: 40 | J75: 40 | K75: 46037 | L75: 01.01.26 | M75: DAM-251230 | N75: KHAM Factory | O75: Mohammad Faraj 0508042050 | P75: Trucks | Q75: 46054 | R75: 46100 | T75: 0 | V75: B | W75: =Y75/I75 -> 121.35 | Y75: 4854
A76: =ROW()-2 -> 74 | B76: DAM2-01-029 | C76: Bill-8 | D76: ROUND RECESSED LED 11.5 WATTS, IP20, 230V, 60HZ, 1400 LUMENS, For guard room 1&2 | E76: Electrical | F76: SL | G76: Bill-8 | H76: EA | I76: 14 | J76: 14 | K76: 46052 | L76: 22.01.26 | M76: DAM-260101 | N76: Alwasail | O76: BEDIER 506404317 | P76: Trucks | Q76: 46082 | R76: 46100 | T76: 0 | V76: B | W76: =Y76/I76 -> 5357.1429 | Y76: 75000
A77: =ROW()-2 -> 75 | B77: DAM2-01-029 | C77: Bill-8 | D77: ROUND RECESSED LED 11.5 WATTS, IP20, 230V, 60HZ, 1400 LUMENS, with 3 hour emergency battery kit For guard room 1 | E77: Electrical | F77: SL | G77: Bill-8 | H77: EA | I77: 2 | J77: 2 | K77: 46054 | L77: Not Issue | M77: NA | N77: AL Khreji | O77: Mahmoud 0555219643 | P77: Highbed | Q77: 46096 | R77: 46116 | T77: 0 | V77: B | W77: =Y77/I77 -> 0 | Y77: 0
A78: =ROW()-2 -> 76 | B78: DAM2-01-029 | C78: Bill-8 | D78: WALL MOUNTED BULK HEAD OUTDOOR LED 15 WATTS, IP65,230V 60 HZ, For guard room 1&2 | E78: Electrical | F78: SL | G78: Bill-8 | H78: EA | I78: 5 | J78: 5 | K78: 46073 | L78: 10.01.26 | M78: DAM-100126 | N78: Elsewedy | O78: Amjad 0561792045 | P78: Highbed | Q78: 46073 | R78: 46147 | T78: 0 | V78: B | W78: =Y78/I78 -> 0 | Y78: 0
A79: =ROW()-2 -> 77 | B79: DAM2-01-029 | C79: Bill-8 | D79: ROUND RECESSED LED 11.5 WATTS, IP44, 230V, 60HZ, 1400 LUMENS, For guard room 1 | E79: Electrical | F79: SL | G79: Bill-8 | H79: EA | I79: 2 | J79: 2 | K79: 46073 | L79: 10.01.26 | M79: DAM-100126 | N79: Elsewedy | O79: Amjad 0561792045 | P79: Highbed | Q79: 46073 | R79: 46147 | T79: 0 | V79: B | W79: =Y79/I79 -> 0 | Y79: 0
A80: =ROW()-2 -> 78 | B80: DAM2-01-029 | C80: Bill-8 | D80: Conduit and accessories for building lifghting circuits | E80: Electrical | F80: SL | G80: Bill-8 | H80: EA | I80: Tech | J80: Tech | K80: 46016 | L80: 20.01.26 | M80: DAM-260103 | N80: Global Source | O80: Raheeb 555636521 | P80: Trucks | Q80: 45962 | R80: 46021 | T80: 0 | V80: B | W80: =Y80/I80 -> #VALUE! | Y80: 86000
A81: =ROW()-2 -> 79 | B81: DAM2-01-029 | C81: Bill-8 | D81: 3x2.5mm2 Cables & cable Accessories for building ligjhting circuits | E81: Electrical | F81: SL | G81: Bill-8 | H81: EA | I81: Tech | J81: Tech | K81: 46073 | L81: Not Issue | M81: NA | N81: FURSE | O81: NA | P81: Trucks | Q81: 46037 | R81: 46052 | T81: 0 | V81: B | W81: =Y81/I81 -> #VALUE! | Y81: 0
A82: =ROW()-2 -> 80 | B82: DAM2-01-029 | C82: Bill-8 | D82: 13A SINGLE SWITCH SOCKET OUTLET, For guard room 1&2 | E82: Electrical | F82: SL | G82: Bill-8 | H82: EA | I82: 6 | J82: 6 | K82: 46082 | L82: Not Issue | M82: NA | N82: AL Khreji | O82: Mahmoud 0555219643 | P82: Trucks | Q82: 46115 | R82: 46145 | T82: 0 | V82: B | W82: =Y82/I82 -> 0 | Y82: 0
A83: =ROW()-2 -> 81 | B83: DAM2-01-029 | C83: Bill-8 | D83: 13A DOUBLE SWITCH SOCKET OUTLET, For guard room 1&2 | E83: Electrical | F83: SL | G83: Bill-8 | H83: EA | I83: 22 | J83: 22 | K83: 46032 | L83: 25.01.26 | M83: DAM-260102 | N83: TARIQ NAGADI | O83: Ahmed Al deeb 0539747328 | P83: Trucks | Q83: 46042 | R83: 46072 | T83: 88 | V83: B | W83: =Y83/I83 -> 4 | Y83: 88
A84: =ROW()-2 -> 82 | B84: DAM2-01-029 | C84: Bill-8 | D84: 13A SPUR OUTLET, For guard room 1&2 | E84: Electrical | F84: SL | G84: Bill-8 | H84: EA | I84: 6 | J84: 6 | K84: 46054 | L84: Not Issue | M84: NA | N84: NA | O84: NA | P84: Trucks | Q84: 46114 | R84: 46144 | T84: 0 | V84: B | W84: =Y84/I84 -> 0 | Y84: 0
A85: =ROW()-2 -> 83 | B85: DAM2-01-029 | C85: Bill-8 | D85: 20A DOUBLE POLE SWITCH, IP65, For guard room 1 | E85: Electrical | F85: SL | G85: Bill-8 | H85: EA | I85: 3 | J85: 3 | K85: 46091 | L85: Not Issue | M85: NA | N85: NA | O85: NA | P85: Trucks | Q85: 46094 | R85: 46109 | T85: 0 | V85: B | W85: =Y85/I85 -> 0 | Y85: 0
A86: =ROW()-2 -> 84 | B86: DAM2-01-029 | C86: Bill-8 | D86: Conduit and accessories for building wiring devices circuits | E86: Electrical | F86: SL | G86: Bill-8 | H86: EA | I86: Tech | J86: Tech | K86: 46090 | L86: Not Issue | M86: NA | N86: NA | O86: NA | P86: Trucks | Q86: 46129 | R86: 46144 | T86: 0 | V86: B | W86: =Y86/I86 -> #VALUE! | Y86: 0
A87: =ROW()-2 -> 85 | B87: DAM2-01-029 | C87: Bill-8 | D87: 3x4mm2 Cables & cable Accessories for building wiring devices circuits | E87: Electrical | F87: SL | G87: Bill-8 | H87: EA | I87: Tech | J87: Tech | K87: 46090 | L87: Not Issue | M87: NA | N87: NA | O87: NA | P87: Trucks | Q87: 46105 | R87: 46120 | T87: 0 | V87: B | W87: =Y87/I87 -> #VALUE! | Y87: 0
A88: =ROW()-2 -> 86 | B88: DAM2-01-029 | C88: Bill-8 | D88: Supply, install and test the following grounding and lightning system including ground wires, ground rods, inspection pits, terminations, bonding/clamping, civil works and all materials and accessories required to complete the work according to specification, drawing and standards and materials as per approved samples; all materials should be SASO certified. guard room 1&2 | E88: Electrical | F88: SL | G88: Bill-8 | H88: EA | I88: 4 | J88: 4 | K88: 46207 | L88: Not Issue | M88: NA | N88: NA | O88: NA | P88: Trucks | Q88: 46222 | R88: 46237 | T88: 0 | V88: B | W88: =Y88/I88 -> 0 | Y88: 0
A89: =ROW()-2 -> 87 | B89: DAM2-01-029 | C89: Bill-8 | D89: 120 mm2 BCW for grounding & Lightining protection | E89: Electrical | F89: SL | G89: Bill-8 | H89: EA | I89: 4 | J89: 4 | K89: 45942 | L89: 45976 | M89: PO UCC-C6-002 | N89: KHAM Factory | O89: Mohammad Faraj 0508042050 | P89: Highbed | Q89: 45957 | R89: 45972 | T89: 0 | V89: B | W89: =Y89/I89 -> 615 | Y89: 2460
A90: =ROW()-2 -> 88 | B90: DAM2-01-029 | C90: Bill-8 | D90: 70mm2 BCW for grounding & Lightining protection | E90: Electrical | F90: SL | G90: Bill-8 | H90: EA | I90: 4 | J90: 4 | K90: 01.03.26 | L90: Not Issue | M90: NA | N90: Al Muneef | O90: Ahmad Hasson 0550901644 | P90: Highbed | Q90: 46096 | R90: 46111 | T90: 0 | V90: B | W90: =Y90/I90 -> 0 | Y90: 0
A91: =ROW()-2 -> 89 | B91: DAM2-01-029 | C91: Bill-8 | D91: Rod 19mmx2.4mtrfor grounding & Lightining protection | E91: Electrical | F91: SL | G91: Bill-8 | H91: EA | I91: 4 | J91: 4 | K91: 45934 | L91: 45971 | M91: PO UCC-C6-006 | N91: WASAEL,UNION | O91: BEDIER 506404317 | P91: Highbed | Q91: 45949 | R91: 45964 | T91: 13800 | V91: B | W91: =Y91/I91 -> 3450 | Y91: 13800
A92: =ROW()-2 -> 90 | B92: DAM2-01-029 | C92: Bill-8 | D92: Earth pit 300x300mm for grounding & Lightining protection | E92: Electrical | F92: SL | G92: Bill-8 | H92: EA | I92: 4 | J92: 4 | K92: 45964 | L92: 45969 | M92: PO UCC-C6-003 | N92: FUTURE PIPE | O92: Abdul Rasheed 0553177750 | P92: Highbed | Q92: 45979 | R92: 45994 | T92: 10516 | V92: B | W92: =Y92/I92 -> 2629 | Y92: 10516
A93: =ROW()-2 -> 91 | B93: DAM2-01-029 | C93: Bill-8 | D93: Busbar 8way with DS link ffor grounding & Lightining protection | E93: Electrical | F93: SL | G93: Bill-8 | H93: EA | I93: 4 | J93: 4 | K93: 25.11.25 | L93: 45986 | M93: PO UCC-C6-014 | N93: Global Source | O93: Raheeb 555636521 | P93: Trucks | Q93: 45962 | R93: 45972 | T93: 86730 | V93: B | W93: =Y93/I93 -> 21682.5 | Y93: 86730
A94: =ROW()-2 -> 92 | B94: DAM2-01-029 | C94: Bill-8 | D94: 25mm2 x 3mm CU tape & Accessories for grounding & Lightining protection | E94: Electrical | F94: SL | G94: Bill-8 | H94: EA | I94: 4 | J94: 4 | K94: 46069 | L94: Not Issue | M94: NA | N94: SAUDI FANS | O94: Samir 0502007277 | P94: Trucks | Q94: 46084 | R94: 46114 | T94: 0 | V94: B | W94: =Y94/I94 -> 0 | Y94: 0
A95: =ROW()-2 -> 93 | B95: DAM2-01-029 | C95: Bill-8 | D95: 20A, 1P, 60Hz Isolator/disconnect switches IP65 guard room 1&2 | E95: Electrical | F95: SL | G95: Bill-8 | H95: EA | I95: 6 | J95: 6 | K95: 45969 | L95: 45969 | M95: Jc/020Dm/25 | N95: SFFECO | O95: Ahmad Gaballah 050521925 | P95: Trucks | Q95: 45969 | R95: 46120 | T95: 0 | V95: B | W95: =Y95/I95 -> 0 | Y95: 0
A96: =ROW()-2 -> 94 | B96: DAM2-01-029 | C96: Bill-8 | D96: Conduit 25 uPVC for fire Alarm system | E96: Electrical | F96: SL | G96: Bill-8 | H96: LM | I96: Tech | J96: Tech | K96: 45969 | L96: 45969 | M96: Jc/020Dm/25 | N96: SFFECO | O96: Ahmad Gaballah 050521925 | P96: Trucks | Q96: 45969 | R96: 46208 | T96: 0 | V96: B | W96: =Y96/I96 -> #VALUE! | Y96: 0
A97: =ROW()-2 -> 95 | B97: DAM2-01-029 | C97: Bill-8 | D97: Cable 2x1.5mm2 or fire Alarm system | E97: Electrical | F97: SL | G97: Bill-8 | H97: LM | I97: Tech | J97: Tech | K97: 46107 | L97: Not Issue | M97: NA | N97: AL ZAMEL | O97: Mo Rasheed 0594009672 | P97: Trucks | Q97: 46137 | R97: 46167 | T97: 0 | V97: B | W97: =Y97/I97 -> #VALUE! | Y97: 0
A98: =ROW()-2 -> 96 | B98: DAM2-01-029 | C98: Bill-8 | D98: smoke detectorsor fire Alarm system | E98: Electrical | F98: SL | G98: Bill-8 | H98: EA | I98: 3 | J98: 3 | K98: 46066 | L98: Not Issue | M98: NA | N98: NA | O98: NA | P98: Trucks | Q98: 46096 | R98: 46126 | T98: 0 | V98: B | W98: =Y98/I98 -> 0 | Y98: 0
A99: =ROW()-2 -> 97 | B99: DAM2-01-029 | C99: Bill-8 | D99: Sounder indoor or fire Alarm system | E99: Electrical | F99: SL | G99: Bill-8 | H99: EA | I99: 1 | J99: 1 | K99: 46098 | L99: Not Issue | M99: NA | N99: NA | O99: NA | P99: Trucks | Q99: 46128 | R99: 46158 | T99: 0 | V99: B | W99: =Y99/I99 -> 0 | Y99: 0
A100: =ROW()-2 -> 98 | B100: DAM2-01-029 | C100: Bill-8 | D100: FACP Panel with 2 LOOPS ADDRESABLE TYPE COMPLETE WITH BATTERY CHARGER. POWER SUPPLY UNIT. LCD PRINTER KEY BOARD AND AUTOMATIC TELEPHONE DIALER | E100: Electrical | F100: SL | G100: Bill-8 | H100: EA | I100: 1 | J100: 1 | K100: 15.03.26 | L100: Not Issue | M100: NA | N100: NA | O100: NA | P100: Trucks | Q100: 46103 | R100: 46133 | T100: 0 | V100: B | W100: =Y100/I100 -> 0 | Y100: 0
...

Sheet Issues
M3: ='General Information'!L1 -> 46308 | N3: Status | O3: Responsibility
N4: Open | O4: Contractor
N5: Closed | O5: Consultant
O6: Modon
O7: Third Party
O8: Other
B9: Issue Log
B10: Issue No | C10: Date Identified | D10: Issue Description | E10: Responsibility | F10: Action Taken | H10: Current Status | I10: Expected/Actual Closure | J10: Duration Elapsed
B11: 1 | C11: 46113 | D11: قلة عدد العمالة والمعدات و توقف مقاول الباطن | E11: Contractor | F11: جاري اسناد جزء من المشروع لمقاول آخر و جاري توفير عمالة من الشركة لاستكمال الاعمال المتبقية حيث ان عدد العمالة الحالي 304 والمعدات 184 معدة والمضخات الى 30 مضخة نزح ,و وجوب استمرار زيادة العمالة والمعدات لتحقيق مستهدفات مدن | H11: Open | I11: =C11+30 -> 46143 | J11: ='General Information'!$L$1-Issues!C11 -> 195
B12: 2 | C12: 46174 | D12: تأخر أعمال العبارة بالطريق الشرياني | E12: Contractor | F12: جاري الانتهاء من الحدادة ل 16 فواصل وصب قاعدة لعدد 03 فاصل تم حفر 14 و جاري 03 فواصل أخرى | H12: Open | I12: =C12+30 -> 46204 | J12: ='General Information'!$L$1-Issues!C12 -> 134
B13: 3 | C13: 46174 | D13: ضرورة الانتهاء من تنفيذ الشبكات لتحقيق جاهزية الموقع وبدء أعمال الطرق | E13: Other | F13: تم استبعاد مقاول الباطن يوناسكو و سحب اعتماده لعدم وفاءه بمستهدفات مدن و على المقاول العمل بشكل مباشر على الشبكات او تقديم مقاول باطن للاعتماد | H13: Open | I13: =C13+30 -> 46204 | J13: ='General Information'!$L$1-Issues!C13 -> 134
B14: 4
B15: 5
B16: 6
B17: 7
B18: 8
B19: 9
B20: 10
B21: 11
B22: 12
B23: 13
B24: 14
B25: 15
... B60: 50

Sheet Manpower
A1: Head-Count ( Non Manual)
A2: MONTHS | B2: 45868 | C2: =EOMONTH(B2,1) -> 45900 | D2: =EOMONTH(C2,1) -> 45930 | E2: =EOMONTH(D2,1) -> 45961 | F2: =EOMONTH(E2,1) -> 45991 | G2: =EOMONTH(F2,1) -> 46022 | H2: =EOMONTH(G2,1) -> 46053 | I2: =EOMONTH(H2,1) -> 46081 | J2: =EOMONTH(I2,1) -> 46112 | ... X2: =EOMONTH(W2,1) -> 46538
A3: Plan - Monthly | B3: =ROUNDUP(VLOOKUP(B2,'Physical-Chart Data'!$A:$K,2,FALSE)/460,0) -> 1 | C3: =ROUNDUP(VLOOKUP(C2,'Physical-Chart Data'!$A:$K,2,FALSE)/460,0) -> 9 | D3: =ROUNDUP(VLOOKUP(D2,'Physical-Chart Data'!$A:$K,2,FALSE)/460,0) -> 14 | E3: =ROUNDUP(VLOOKUP(E2,'Physical-Chart Data'!$A:$K,2,FALSE)/460,0) -> 27 | F3: =ROUNDUP(VLOOKUP(F2,'Physical-Chart Data'!$A:$K,2,FALSE)/460,0) -> 48 | G3: =ROUNDUP(VLOOKUP(G2,'Physical-Chart Data'!$A:$K,2,FALSE)/1060,0) -> 51 | H3: =ROUNDUP(VLOOKUP(H2,'Physical-Chart Data'!$A:$K,2,FALSE)/2060,0) -> 46 | I3: =ROUNDUP(VLOOKUP(I2,'Physical-Chart Data'!$A:$K,2,FALSE)/2060,0) -> 56 | J3: =ROUNDUP(VLOOKUP(J2,'Physical-Chart Data'!$A:$K,2,FALSE)/2060,0) -> 54 | K3: =ROUNDUP(VLOOKUP(K2,'Physical-Chart Data'!$A:$K,2,FALSE)/2060,0) -> 63 | L3: =ROUNDUP(VLOOKUP(L2,'Physical-Chart Data'!$A:$K,2,FALSE)/2060,0) -> 46 | M3: 53 | N3: 48 | O3: =ROUNDUP(VLOOKUP(O2,'Physical-Chart Data'!$A:$K,2,FALSE)/1060,0) -> 45 | P3: 38 | Q3: 35 | R3: 35 | S3: =ROUNDUP(VLOOKUP(S2,'Physical-Chart Data'!$A:$K,2,FALSE)/1060,0) -> 6 | T3: =ROUNDUP(VLOOKUP(T2,'Physical-Chart Data'!$A:$K,2,FALSE)/1060,0) -> 4
A4: Planned - Cumulative | B4: =B3 -> 1 | C4: =B4+C3 -> 10 | D4: =C4+D3 -> 24 | E4: =D4+E3 -> 51 | F4: =E4+F3 -> 99 | G4: =F4+G3 -> 150 | H4: =G4+H3 -> 196 | I4: =H4+I3 -> 252 | J4: =I4+J3 -> 306 | ... T4: =S4+T3 -> 679
A5: Actual - Monthly | B5: 8 | C5: 14 | D5: 25 | E5: 36 | F5: 46 | G5: 48 | H5: 49 | I5: 52 | J5: 52 | K5: 56 | L5: 56 | M5: 57 | N5: 57 | O5: 57 | P5: 57 | Q5: 57
A6: Actual Cumulative | B6: =B5 -> 8 | C6: =C5+B6 -> 22 | D6: =D5+C6 -> 47 | E6: =E5+D6 -> 83 | F6: =F5+E6 -> 129 | G6: =G5+F6 -> 177 | H6: =H5+G6 -> 226 | I6: =I5+H6 -> 278 | J6: =J5+I6 -> 330 | ... Q6: =Q5+P6 -> 727
A7: Forecast - Monthly | R7: =ROUNDUP(AVERAGE(ROUNDUP(VLOOKUP(R2,'Physical-Chart Data'!$A:$K,11,FALSE)/1000,0),R3),0) -> 122 | S7: =ROUNDUP(AVERAGE(ROUNDUP(VLOOKUP(S2,'Physical-Chart Data'!$A:$K,11,FALSE)/1000,0),S3),0) -> 91 | T7: =ROUNDUP(AVERAGE(ROUNDUP(VLOOKUP(T2,'Physical-Chart Data'!$A:$K,11,FALSE)/1000,0),T3),0) -> 14 | U7: =ROUNDUP(AVERAGE(ROUNDUP(VLOOKUP(U2,'Physical-Chart Data'!$A:$K,11,FALSE)/1000,0),U3),0) -> 0 | V7: =ROUNDUP(AVERAGE(ROUNDUP(VLOOKUP(V2,'Physical-Chart Data'!$A:$K,11,FALSE)/3000,0),V3),0) -> 0 | W7: =ROUNDUP(AVERAGE(ROUNDUP(VLOOKUP(W2,'Physical-Chart Data'!$A:$K,11,FALSE)/3000,0),W3),0) -> 0 | X7: =ROUNDUP(AVERAGE(ROUNDUP(VLOOKUP(X2,'Physical-Chart Data'!$A:$K,11,FALSE)/3000,0),X3),0) -> 0
A8: Saudi Monthly - Actual | B8: 1 | C8: 1 | D8: 3 | E8: 4 | F8: 10 | G8: 10 | H8: 10 | I8: 14 | J8: 15 | K8: 15 | L8: 15 | M8: 16 | N8: 13 | O8: 13 | P8: 13 | Q8: 13
A9: Head-Count (Manual)
A10: MONTHS | B10: 45868 | C10: =EOMONTH(B10,1) -> 45900 | D10: =EOMONTH(C10,1) -> 45930 | E10: =EOMONTH(D10,1) -> 45961 | F10: =EOMONTH(E10,1) -> 45991 | G10: =EOMONTH(F10,1) -> 46022 | H10: =EOMONTH(G10,1) -> 46053 | I10: =EOMONTH(H10,1) -> 46081 | J10: =EOMONTH(I10,1) -> 46112 | ... X10: =EOMONTH(W10,1) -> 46538
A11: Plan - Monthly | B11: =ROUNDUP(VLOOKUP(B10,'Physical-Chart Data'!$A:$K,2,FALSE)/360,0) -> 1 | C11: =ROUNDUP(VLOOKUP(C10,'Physical-Chart Data'!$A:$K,2,FALSE)/360,0) -> 12 | D11: =ROUNDUP(VLOOKUP(D10,'Physical-Chart Data'!$A:$K,2,FALSE)/360,0) -> 18 | E11: =ROUNDUP(VLOOKUP(E10,'Physical-Chart Data'!$A:$K,2,FALSE)/360,0) -> 35 | F11: =ROUNDUP(VLOOKUP(F10,'Physical-Chart Data'!$A:$K,2,FALSE)/260,0) -> 85 | G11: =ROUNDUP(VLOOKUP(G10,'Physical-Chart Data'!$A:$K,2,FALSE)/460,0) -> 116 | H11: =ROUNDUP(VLOOKUP(H10,'Physical-Chart Data'!$A:$K,2,FALSE)/460,0) -> 205 | I11: =ROUNDUP(VLOOKUP(I10,'Physical-Chart Data'!$A:$K,2,FALSE)/560,0) -> 203 | J11: 244 | K11: 248 | L11: =ROUNDUP(VLOOKUP(L10,'Physical-Chart Data'!$A:$K,2,FALSE)/360,0) -> 263 | M11: =ROUNDUP(VLOOKUP(M10,'Physical-Chart Data'!$A:$K,2,FALSE)/260,0) -> 258 | N11: =ROUNDUP(VLOOKUP(N10,'Physical-Chart Data'!$A:$K,2,FALSE)/260,0) -> 243 | O11: =ROUNDUP(VLOOKUP(O10,'Physical-Chart Data'!$A:$K,2,FALSE)/120,0) -> 391 | P11: =ROUNDUP(VLOOKUP(P10,'Physical-Chart Data'!$A:$K,2,FALSE)/200,0) -> 142 | Q11: =ROUNDUP(VLOOKUP(Q10,'Physical-Chart Data'!$A:$K,2,FALSE)/200,0) -> 78 | R11: =ROUNDUP(VLOOKUP(R10,'Physical-Chart Data'!$A:$K,2,FALSE)/200,0) -> 78 | S11: =ROUNDUP(VLOOKUP(S10,'Physical-Chart Data'!$A:$K,2,FALSE)/260,0) -> 24 | T11: =ROUNDUP(VLOOKUP(T10,'Physical-Chart Data'!$A:$K,2,FALSE)/260,0) -> 15
A12: Planned - Cumulative | B12: =B11 -> 1 | C12: =B12+C11 -> 13 | D12: =C12+D11 -> 31 | E12: =D12+E11 -> 66 | F12: =E12+F11 -> 151 | G12: =F12+G11 -> 267 | H12: =G12+H11 -> 472 | I12: =H12+I11 -> 675 | J12: =I12+J11 -> 919 | ... T12: =S12+T11 -> 2659
A13: Actual - Monthly | B13: 5 | C13: 31 | D13: 65 | E13: 80 | F13: 93 | G13: 146 | H13: 151 | I13: 172 | J13: 217 | K13: 305 | L13: 364 | M13: 408 | N13: 420 | O13: 499 | P13: 519 | Q13: 537
A14: Actual Cumulative | B14: =B13 -> 5 | C14: =C13+B14 -> 36 | D14: =D13+C14 -> 101 | E14: =E13+D14 -> 181 | F14: =F13+E14 -> 274 | G14: =G13+F14 -> 420 | H14: =H13+G14 -> 571 | I14: =I13+H14 -> 743 | J14: =J13+I14 -> 960 | ... Q14: =Q13+P14 -> 4012
