Workbook
Name _1B.05.M.010.0010: #REF!
Name _1B.05.M.010.0010: #REF!
Name _1B.05.M.010.0010: #REF!
Name _1B.05.M.010.0010: #REF!
Name _1B.05.M.010.0050: #REF!
Name _1B.05.M.010.0050: #REF!
Name _1B.05.M.010.0050: #REF!
Name _1B.05.M.010.0050: #REF!
Name _1B.05.M.0100.0010: #REF!
Name _1B.05.M.0100.0010: #REF!
Name _1B.05.M.020.0010: #REF!
Name _1B.05.M.020.0010: #REF!
Name _1B.05.M.020.0020: #REF!
Name _1B.05.M.020.0020: #REF!
Name _1B.05.M.020.0030: #REF!
Name _1B.05.M.020.0030: #REF!
Name _1B.05.M.020.0040: #REF!
Name _1B.05.M.020.0040: #REF!
Name _1B.05.M.030.0010: #REF!
Name _1B.05.M.030.0010: #REF!
Name _1B.05.M.030.0020: #REF!
Name _1B.05.M.030.0020: #REF!
Name _1B.05.M.040.0010: #REF!
Name _1B.05.M.040.0010: #REF!
Name _1B.05.M.050.0010: #REF!
Name _1B.05.M.050.0010: #REF!
Name _1B.05.M.050.0020: #REF!
Name _1B.05.M.050.0020: #REF!
Name _1B.05.M.050.0030: #REF!
Name _1B.05.M.050.0030: #REF!
Name _1B.05.M.060.0020: #REF!
Name _1B.05.M.060.0020: #REF!
Name _1B.05.M.060.0100: #REF!
Name _1B.05.M.060.0100: #REF!
Name _1B.05.M.070.0010: #REF!
Name _1B.05.M.070.0010: #REF!
Name _1B.05.M.070.0020: #REF!
Name _1B.05.M.070.0020: #REF!
Name _1B.05.M.070.0030: #REF!
Name _1B.05.M.070.0030: #REF!
Name _1B.05.M.070.0040: #REF!
Name _1B.05.M.070.0040: #REF!
Name _1B.05.M.070.0050: #REF!
Name _1B.05.M.070.0050: #REF!
Name _1B.05.M.080.0010: #REF!
Name _1B.05.M.080.0010: #REF!
Name _1B.05.M.090.0010: #REF!
Name _1B.05.M.090.0010: #REF!
Name _1B.09.P.010.0010: #REF!
Name _1B.09.P.010.0010: #REF!
Name _1B.09.P.010.0020: #REF!
Name _1B.09.P.010.0020: #REF!
Name _1B.09.P.010.0030: #REF!
Name _1B.09.P.010.0030: #REF!
Name _1B.09.P.010.0040: #REF!
Name _1B.09.P.010.0040: #REF!
Name _1B.09.P.010.0050: #REF!
Name _1B.09.P.010.0050: #REF!
Name _1B.09.P.010.0060: #REF!
Name _1B.09.P.010.0060: #REF!

Sheet DB
A1: ='Weekly Progress Report'!$A$1 -> MODON - Weekly Progress Report - Construction Projects
B2: ='Weekly Progress Report'!$A$2 -> Contract General Information | J2: ='Weekly Progress Report'!G2 -> Key Dates | U2: ='Weekly Progress Report'!$M$2 -> Cost Summary (SR) | AD2: ='Weekly Progress Report'!$U$2 -> Performance Summary | AP2: ='Weekly Progress Report'!A59 -> Shop Drawings | AT2: ='Weekly Progress Report'!A68 -> Material Approval | AW2: ='Weekly Progress Report'!A77 -> Procurement Summary | BD2: ='Weekly Progress Report'!L59 -> Quality Reports | BT2: ='Weekly Progress Report'!L67 -> Key Submittals Approval Status | CD2: ='Weekly Progress Report'!L73 -> Invoices Summary | CR2: ='Weekly Progress Report'!L81 -> Resources at Site | CY2: ='Weekly Progress Report'!W59 -> Safety Statistics | FK2: ='Weekly Progress Report'!A86 -> Primavera P6 Schedule Status | FS2: ='Weekly Progress Report'!A95 -> Weekly Prgoress Photos
A3: ='Weekly Progress Report'!AF1 -> Data Date | B3: ='Weekly Progress Report'!A3 -> Project Name | C3: ='Weekly Progress Report'!A4 -> Project ID | D3: ='Weekly Progress Report'!A5 -> Contractor | E3: ='Weekly Progress Report'!A6 -> Consultant | F3: ='Weekly Progress Report'!D4 -> Stage | G3: ='Weekly Progress Report'!D5 -> Status | H3: ='Weekly Progress Report'!D6 -> Modon PM | I3: ='Weekly Progress Report'!AA2 -> Project Scope | J3: ='Weekly Progress Report'!G3 -> Contract Award | K3: ='Weekly Progress Report'!G4 -> Contract Sign | L3: ='Weekly Progress Report'!G5 -> Site Handover | M3: ='Weekly Progress Report'!G6 -> Original Completion | N3: ='Weekly Progress Report'!$I$3 -> Contract Award (Hijri) | O3: ='Weekly Progress Report'!$I$4 -> Contract Sign (Hijri) | P3: ='Weekly Progress Report'!$I$5 -> Site Handover (Hijri) | Q3: ='Weekly Progress Report'!$I$6 -> Original Completion (Hijri) | R3: ='Weekly Progress Report'!$K$3 -> Revised Completion | S3: ='Weekly Progress Report'!$K$4 -> Committed Completion | T3: ='Weekly Progress Report'!$K$5 -> Forecast Completion | U3: ='Weekly Progress Report'!$M$3 -> Original Contract Value | V3: ='Weekly Progress Report'!$M$4 -> Revised Contract Value | W3: ='Weekly Progress Report'!$M$5 -> Estimate At Completion Value | X3: ='Weekly Progress Report'!$M$6 -> Potential Changes | Y3: ='Weekly Progress Report'!$Q$3 -> O&M Value (if any) | Z3: ='Weekly Progress Report'!$Q$4 -> Submitted Invoices (Gross Value) | AA3: ='Weekly Progress Report'!$Q$5 -> Penalities | AB3: ='Weekly Progress Report'!$Q$6 -> FIR Value (Todate) | AC3: Original Plan Value | AD3: ='Weekly Progress Report'!$U$3 -> Plan Value | AE3: ='Weekly Progress Report'!$U$4 -> Earn Value | AF3: ='Weekly Progress Report'!$W$3 -> Phys. Plan Value | AG3: ='Weekly Progress Report'!$W$4 -> Phys. Earn Value | AH3: ='Weekly Progress Report'!$Y$3 -> Quality Score | AI3: ='Weekly Progress Report'!$Y$5 -> Safety Score | AJ3: Weekly PV (SAR) | AK3: Weekly EV (SAR) | AL3: Weekly PV % | AM3: Weekly PV % | AN3: Weekly Phys PV% | AO3: Weekly Phys PV% | AP3: Total SD Planned | AQ3: SD Remaining | AR3: SD Pending | AS3: Total SD Submittals | AT3: Planned Materials Approv | AU3: Material Pending Approval | AV3: Materila Total Submittals | AW3: ='Weekly Progress Report'!C78 -> Total Materials | AX3: ='Weekly Progress Report'!D78 -> Total Number of P.O. | AY3: ='Weekly Progress Report'!E78 -> Actual P.O. To Date | AZ3: ='Weekly Progress Report'!F78 -> Remaining P.O | BA3: ='Weekly Progress Report'!G78 -> Material on Site | BB3: ='Weekly Progress Report'!H78 -> Remaining Materials | BC3: ='Weekly Progress Report'!I78 -> Material Delivery Completion (Date) | BD3: ="NCR "&'Weekly Progress Report'!N60 -> NCR Issued | BE3: ="NCR "&'Weekly Progress Report'!O60 -> NCR Closed | BF3: ="NCR "&'Weekly Progress Report'!P60 -> NCR Pending | BG3: ="NCR "&'Weekly Progress Report'!Q60 -> NCR Avg. Closing (Days) | BH3: ="SIR "&'Weekly Progress Report'!N60 -> SIR Issued | BI3: ="SIR "&'Weekly Progress Report'!O60 -> SIR Closed | BJ3: ="SIR "&'Weekly Progress Report'!P60 -> SIR Pending | BK3: ="SIR "&'Weekly Progress Report'!Q60 -> SIR Avg. Closing (Days) | BL3: ="MIR "&'Weekly Progress Report'!N60 -> MIR Issued | BM3: ="MIR "&'Weekly Progress Report'!O60 -> MIR Closed | BN3: ="MIR "&'Weekly Progress Report'!P60 -> MIR Pending | BO3: ="MIR "&'Weekly Progress Report'!Q60 -> MIR Avg. Closing (Days) | BP3: ="FIR "&'Weekly Progress Report'!N60 -> FIR Issued | BQ3: ="FIR "&'Weekly Progress Report'!O60 -> FIR Closed | BR3: ="FIR "&'Weekly Progress Report'!P60 -> FIR Pending | BS3: ="FIR "&'Weekly Progress Report'!Q60 -> FIR Avg. Closing (Days) | BT3: ='Weekly Progress Report'!L68 -> 1 Quality Plan Approval | BU3: ='Weekly Progress Report'!L69 -> 2 Quality Plan Last Up | BV3: ='Weekly Progress Report'!L70 -> 3 Safety Plan Approval | BW3: ='Weekly Progress Report'!L71 -> 4 Safety Plan Last Up | BX3: ='Weekly Progress Report'!L72 -> 5 Construction Plan Approval | BY3: ='Weekly Progress Report'!Q68 -> 6 Baseline Approval | BZ3: ='Weekly Progress Report'!Q69 -> 7 No of Approved Version of Schedule | CA3: ='Weekly Progress Report'!Q70 -> 8 Last Approved Schedule | CB3: ='Weekly Progress Report'!Q71 -> 9 BOQ Approval Date | CC3: ='Weekly Progress Report'!Q72 -> 10 No of Approved Version of BOQ | CD3: ='Weekly Progress Report'!L74 -> Total Submitted Invoices | CE3: ='Weekly Progress Report'!L75 -> PM Approved Invoices | CF3: ='Weekly Progress Report'!L76 -> No of Paid Invoices | CG3: ='Weekly Progress Report'!L77 -> No of Pending Invoices | CH3: ='Weekly Progress Report'!L78 -> Advance Payment % | CI3: ='Weekly Progress Report'!L79 -> Retention % | CJ3: ='Weekly Progress Report'!L80 -> Deduction / Penalties % | CK3: ='Weekly Progress Report'!O74 -> Submitted Invoices (SAR) | CL3: ='Weekly Progress Report'!O75 -> PM Approved Invoices (SAR) | CM3: ='Weekly Progress Report'!O76 -> Paid Invoices (SAR) | CN3: ='Weekly Progress Report'!O77 -> Last Submitted Period | CO3: ='Weekly Progress Report'!O78 -> Advance Payment (SAR) | CP3: ='Weekly Progress Report'!O79 -> Retention (SAR) | CQ3: ='Weekly Progress Report'!O80 -> Deduction / Penalties (SAR) | CR3: Planned Head Count | CS3: Actual Head Count | CT3: Saudi Staff | CU3: Labor Planned | CV3: Labor Actual | CW3: Equipment Planned | CX3: Equipment Actual | CY3: ="This Week "&'Weekly Progress Report'!X62 -> This Week Total Hours Worked | CZ3: ="This Week "&'Weekly Progress Report'!X63 -> This Week Safe Hours Worked | DA3: ="This Week "&'Weekly Progress Report'!X64 -> This Week LTI | DB3: ="This Week "&'Weekly Progress Report'!X65 -> This Week MTC (Healed w/o Disability) | DC3: ="This Week "&'Weekly Progress Report'!X66 -> This Week MTC (Healed w/ Disability) | DD3: ="This Week "&'Weekly Progress Report'!X67 -> This Week Near Miss | DE3: ="This Week "&'Weekly Progress Report'!X68 -> This Week First Aid Cases | DF3: ="This Week "&'Weekly Progress Report'!X69 -> This Week Fatality | DG3: ="This Week "&'Weekly Progress Report'!X70 -> This Week Fire Incident Cases | DH3: ="This Week "&'Weekly Progress Report'!X71 -> This Week Vehicle Incident | DI3: ="This Week "&'Weekly Progress Report'!X72 -> This Week Property Damages | DJ3: ="This Week "&'Weekly Progress Report'!X73 -> This Week Induction Training | DK3: ="This Week "&'Weekly Progress Report'!X74 -> This Week No.of Internal Training | DL3: ="This Week "&'Weekly Progress Report'!X75 -> This Week No.of Internal Audit | DM3: ="This Week "&'Weekly Progress Report'!X76 -> This Week No. of Toolbox Talks | DN3: ="This Week "&'Weekly Progress Report'!X77 -> This Week Safety Awards/Incentives | DO3: ="This Month "&'Weekly Progress Report'!X62 -> This Month Total Hours Worked | DP3: ="This Month "&'Weekly Progress Report'!X63 -> This Month Safe Hours Worked | DQ3: ="This Month "&'Weekly Progress Report'!X64 -> This Month LTI | DR3: ="This Month "&'Weekly Progress Report'!X65 -> This Month MTC (Healed w/o Disability) | DS3: ="This Month "&'Weekly Progress Report'!X66 -> This Month MTC (Healed w/ Disability) | DT3: ="This Month "&'Weekly Progress Report'!X67 -> This Month Near Miss | DU3: ="This Month "&'Weekly Progress Report'!X68 -> This Month First Aid Cases | DV3: ="This Month "&'Weekly Progress Report'!X69 -> This Month Fatality | DW3: ="This Month "&'Weekly Progress Report'!X70 -> This Month Fire Incident Cases | DX3: ="This Month "&'Weekly Progress Report'!X71 -> This Month Vehicle Incident | DY3: ="This Month "&'Weekly Progress Report'!X72 -> This Month Property Damages | DZ3: ="This Month "&'Weekly Progress Report'!X73 -> This Month Induction Training | EA3: ="This Month "&'Weekly Progress Report'!X74 -> This Month No.of Internal Training | EB3: ="This Month "&'Weekly Progress Report'!X75 -> This Month No.of Internal Audit | EC3: ="This Month "&'Weekly Progress Report'!X76 -> This Month No. of Toolbox Talks | ED3: ="This Month "&'Weekly Progress Report'!X77 -> This Month Safety Awards/Incentives | EE3: ="YTD "&'Weekly Progress Report'!X62 -> YTD Total Hours Worked | EF3: ="YTD "&'Weekly Progress Report'!X63 -> YTD Safe Hours Worked | EG3: ="YTD "&'Weekly Progress Report'!X64 -> YTD LTI | EH3: ="YTD "&'Weekly Progress Report'!X65 -> YTD MTC (Healed w/o Disability) | EI3: ="YTD "&'Weekly Progress Report'!X66 -> YTD MTC (Healed w/ Disability) | EJ3: ="YTD "&'Weekly Progress Report'!X67 -> YTD Near Miss | EK3: ="YTD "&'Weekly Progress Report'!X68 -> YTD First Aid Cases | EL3: ="YTD "&'Weekly Progress Report'!X69 -> YTD Fatality | EM3: ="YTD "&'Weekly Progress Report'!X70 -> YTD Fire Incident Cases | EN3: ="YTD "&'Weekly Progress Report'!X71 -> YTD Vehicle Incident | EO3: ="YTD "&'Weekly Progress Report'!X72 -> YTD Property Damages | EP3: ="YTD "&'Weekly Progress Report'!X73 -> YTD Induction Training | EQ3: ="YTD "&'Weekly Progress Report'!X74 -> YTD No.of Internal Training | ER3: ="YTD "&'Weekly Progress Report'!X75 -> YTD No.of Internal Audit | ES3: ="YTD "&'Weekly Progress Report'!X76 -> YTD No. of Toolbox Talks | ET3: ="YTD "&'Weekly Progress Report'!X77 -> YTD Safety Awards/Incentives | EU3: ="Cum "&'Weekly Progress Report'!X62 -> Cum Total Hours Worked | EV3: ="Cum "&'Weekly Progress Report'!X63 -> Cum Safe Hours Worked | EW3: ="Cum "&'Weekly Progress Report'!X64 -> Cum LTI | EX3: ="Cum "&'Weekly Progress Report'!X65 -> Cum MTC (Healed w/o Disability) | EY3: ="Cum "&'Weekly Progress Report'!X66 -> Cum MTC (Healed w/ Disability) | EZ3: ="Cum "&'Weekly Progress Report'!X67 -> Cum Near Miss | FA3: ="Cum "&'Weekly Progress Report'!X68 -> Cum First Aid Cases | FB3: ="Cum "&'Weekly Progress Report'!X69 -> Cum Fatality | FC3: ="Cum "&'Weekly Progress Report'!X70 -> Cum Fire Incident Cases | FD3: ="Cum "&'Weekly Progress Report'!X71 -> Cum Vehicle Incident | FE3: ="Cum "&'Weekly Progress Report'!X72 -> Cum Property Damages | FF3: ="Cum "&'Weekly Progress Report'!X73 -> Cum Induction Training | FG3: ="Cum "&'Weekly Progress Report'!X74 -> Cum No.of Internal Training | FH3: ="Cum "&'Weekly Progress Report'!X75 -> Cum No.of Internal Audit | FI3: ="Cum "&'Weekly Progress Report'!X76 -> Cum No. of Toolbox Talks | FJ3: ="Cum "&'Weekly Progress Report'!X77 -> Cum Safety Awards/Incentives | FK3: ='Weekly Progress Report'!A89 -> Total Act. | FL3: ='Weekly Progress Report'!B89 -> Not Started | FM3: ='Weekly Progress Report'!C89 -> In Progress | FN3: ='Weekly Progress Report'!D89 -> Completed | FO3: Critical Path Act.Last Week | FP3: Critical Path Act.This Week | FQ3: Failed start Last Week | FR3: Failed start This Week | FS3: ='Weekly Progress Report'!B97 -> 0 | FT3: ='Weekly Progress Report'!D97 -> 0 | FU3: ='Weekly Progress Report'!F97 -> 0 | FV3: ='Weekly Progress Report'!H97 -> 0 | FW3: ='Weekly Progress Report'!J97 -> 0 | FX3: ='Weekly Progress Report'!L97 -> 0 | FY3: ='Weekly Progress Report'!N97 -> 0 | FZ3: ='Weekly Progress Report'!O97 -> 0 | GA3: ='Weekly Progress Report'!P97 -> 0
A4: ='Weekly Progress Report'!AG1 -> 46301 | B4: ='Weekly Progress Report'!B3 -> Development of Infrastructure for phase 1 of the Logistics area at the 2nd Industrial City in Dammam | C4: ='Weekly Progress Report'!B4 -> DAM2-02-009 | D4: ='Weekly Progress Report'!B5 -> Shibh Aljazira Contracting Company | E4: ='Weekly Progress Report'!B6 -> Egis | F4: ='Weekly Progress Report'!E4 -> Construction | G4: ='Weekly Progress Report'!E5 -> Active | H4: ='Weekly Progress Report'!E6 -> Muhammad H Al-Essa | I4: ='Weekly Progress Report'!AA3 -> The project consists of the wet networks mainlines (Sewerage, Storm, Potable, Firefighting & TSE) including the force main line, in addition to the dry networks (Medium Voltage, Low Voltage, Street Lighting & Telecommunication) road crossings & main line connections, scope also included supply, install, testing & commissioning for the potable water pump station and the sewage lift station and implementation of guard rooms and applying all the road earth layers till the asphalt wearing coarse for the project scope area internal roads & finishing the landscape | J4: ='Weekly Progress Report'!H3 -> 45838 | K4: ='Weekly Progress Report'!H4 -> 45852 | L4: ='Weekly Progress Report'!H5 -> 45868 | M4: ='Weekly Progress Report'!H6 -> 46416 | N4: ='Weekly Progress Report'!$J$3 -> 45838 | O4: ='Weekly Progress Report'!$J$4 -> 45852 | P4: ='Weekly Progress Report'!$J$5 -> 45868 | Q4: ='Weekly Progress Report'!$J$6 -> 46416 | R4: ='Weekly Progress Report'!$L$3 -> 46416 | S4: ='Weekly Progress Report'!$L$4 -> 46416 | T4: ='Weekly Progress Report'!$L$5 -> 46418 | U4: ='Weekly Progress Report'!$O$3 -> 1.9890616e+08 | V4: ='Weekly Progress Report'!$O$4 -> 1.9890616e+08 | W4: ='Weekly Progress Report'!$O$5 -> 1.9890616e+08 | X4: ='Weekly Progress Report'!$O$6 -> 0 | Y4: ='Weekly Progress Report'!$S$3 -> 0 | Z4: ='Weekly Progress Report'!$S$4 -> 62889674 | AA4: ='Weekly Progress Report'!$S$5 -> -104500 | AB4: ='Weekly Progress Report'!$S$6 -> 77303418 | AC4: ='Weekly Progress Report'!$J$29 -> 0.72325518 | AD4: ='Weekly Progress Report'!$V$3 -> 0.72325518 | AE4: ='Weekly Progress Report'!$V$4 -> 0.51489574 | AF4: ='Weekly Progress Report'!$X$3 -> 0.60876731 | AG4: ='Weekly Progress Report'!$X$4 -> 0.42474035 | AH4: ='Weekly Progress Report'!$Z$3 -> 0.93 | AI4: ='Weekly Progress Report'!$Z$5 -> 0.92857143 | AJ4: ='Weekly Progress Report'!$E$29 -> -27037643 | AK4: ='Weekly Progress Report'!$F$29 -> -17134541 | AL4: =AJ4/V4 -> -0.13593165 | AM4: =AK4/V4 -> -0.086143842 | AN4: ='Weekly Progress Report'!S29 -> -0.30760358 | AO4: ='Weekly Progress Report'!T29 -> -0.018735675 | AP4: ='Weekly Progress Report'!C67 -> 1774 | AQ4: ='Weekly Progress Report'!I67 -> 0 | AR4: ='Weekly Progress Report'!J67 -> 0 | AS4: ='Weekly Progress Report'!K67 -> 1774 | AT4: ='Weekly Progress Report'!C76 -> 153 | AU4: ='Weekly Progress Report'!J76 -> 3 | AV4: ='Weekly Progress Report'!K76 -> 147 | AW4: ='Weekly Progress Report'!C85 -> 48 | AX4: ='Weekly Progress Report'!D85 -> 48 | AY4: ='Weekly Progress Report'!E85 -> 42 | AZ4: ='Weekly Progress Report'!F85 -> 0 | BA4: ='Weekly Progress Report'!G85 -> 21 | BB4: ='Weekly Progress Report'!H85 -> 27 | BC4: ='Weekly Progress Report'!I85 -> 46335 | BD4: ='Weekly Progress Report'!N63 -> 4 | BE4: ='Weekly Progress Report'!O63 -> 3 | BF4: ='Weekly Progress Report'!P63 -> 1 | BG4: ='Weekly Progress Report'!Q63 -> 0 | BH4: ='Weekly Progress Report'!N64 -> 50 | BI4: ='Weekly Progress Report'!O64 -> 41 | BJ4: ='Weekly Progress Report'!P64 -> 9 | BK4: ='Weekly Progress Report'!Q64 -> 0 | BL4: ='Weekly Progress Report'!N65 -> 109 | BM4: ='Weekly Progress Report'!O65 -> 108 | BN4: ='Weekly Progress Report'!P65 -> 1 | BO4: ='Weekly Progress Report'!Q65 -> 0 | BP4: ='Weekly Progress Report'!N66 -> 4296 | BQ4: ='Weekly Progress Report'!O66 -> 4128 | BR4: ='Weekly Progress Report'!P66 -> 168 | BS4: ='Weekly Progress Report'!Q66 -> 0 | BT4: ='Weekly Progress Report'!O68 -> 45346 | BU4: ='Weekly Progress Report'!O69 -> 45346 | BV4: ='Weekly Progress Report'!O70 -> 45350 | BW4: ='Weekly Progress Report'!O71 -> 45350 | BX4: ='Weekly Progress Report'!O72 -> 45348 | BY4: ='Weekly Progress Report'!U68 -> 45361 | BZ4: ='Weekly Progress Report'!U69 -> 1 | CA4: ='Weekly Progress Report'!U70 -> 45361 | CB4: ='Weekly Progress Report'!U71 -> 0 | CC4: ='Weekly Progress Report'!U72 -> 1 | CD4: ='Weekly Progress Report'!N74 -> 6 | CE4: ='Weekly Progress Report'!N75 -> 0 | CF4: ='Weekly Progress Report'!N76 -> 0 | CG4: ='Weekly Progress Report'!N77 -> 0 | CH4: ='Weekly Progress Report'!N78 -> 0 | CI4: ='Weekly Progress Report'!N79 -> 0 | CJ4: ='Weekly Progress Report'!N80 -> 0.00052537337 | CK4: ='Weekly Progress Report'!R74 -> 62889674 | CL4: ='Weekly Progress Report'!R75 -> 0 | CM4: ='Weekly Progress Report'!R76 -> 0 | CN4: ='Weekly Progress Report'!R77 -> 46280 | CO4: ='Weekly Progress Report'!R78 -> 0 | CP4: ='Weekly Progress Report'!R79 -> 0 | CQ4: ='Weekly Progress Report'!R80 -> -104500 | CR4: ='Weekly Progress Report'!L84 -> 35 | CS4: ='Weekly Progress Report'!M84 -> 57 | CT4: ='Weekly Progress Report'!O84 -> 4 | CU4: ='Weekly Progress Report'!P84 -> 360 | CV4: ='Weekly Progress Report'!Q84 -> 483 | CW4: ='Weekly Progress Report'!T94 -> 150 | CX4: ='Weekly Progress Report'!U94 -> 326 | CY4: ='Weekly Progress Report'!Z62 -> 34740 | CZ4: ='Weekly Progress Report'!Z63 -> 34740 | DA4: ='Weekly Progress Report'!Z64 -> 0 | DB4: ='Weekly Progress Report'!Z65 -> 0 | DC4: ='Weekly Progress Report'!Z66 -> 0 | DD4: ='Weekly Progress Report'!Z67 -> 0 | DE4: ='Weekly Progress Report'!Z68 -> 0 | DF4: ='Weekly Progress Report'!Z69 -> 0 | DG4: ='Weekly Progress Report'!Z70 -> 0 | DH4: ='Weekly Progress Report'!Z71 -> 0 | DI4: ='Weekly Progress Report'!Z72 -> 0 | DJ4: ='Weekly Progress Report'!Z73 -> 29 | DK4: ='Weekly Progress Report'!Z74 -> 0 | DL4: ='Weekly Progress Report'!Z75 -> 0 | DM4: ='Weekly Progress Report'!Z76 -> 3(325) | DN4: ='Weekly Progress Report'!Z77 -> 0 | DO4: ='Weekly Progress Report'!AB62 -> 34740 | DP4: ='Weekly Progress Report'!AB63 -> 34740 | DQ4: ='Weekly Progress Report'!AB64 -> 0 | DR4: ='Weekly Progress Report'!AB65 -> 0 | DS4: ='Weekly Progress Report'!AB66 -> 0 | DT4: ='Weekly Progress Report'!AB67 -> 0 | DU4: ='Weekly Progress Report'!AB68 -> 0 | DV4: ='Weekly Progress Report'!AB69 -> 0 | DW4: ='Weekly Progress Report'!AB70 -> 0 | DX4: ='Weekly Progress Report'!AB71 -> 0 | DY4: ='Weekly Progress Report'!AB72 -> 0 | DZ4: ='Weekly Progress Report'!AB73 -> 29 | EA4: ='Weekly Progress Report'!AB74 -> 2 (9) | EB4: ='Weekly Progress Report'!AB75 -> 1 | EC4: ='Weekly Progress Report'!AB76 -> 3(325) | ED4: ='Weekly Progress Report'!AB77 -> 0 | EE4: ='Weekly Progress Report'!AC62 -> 740184 | EF4: ='Weekly Progress Report'!AC63 -> 740184 | EG4: ='Weekly Progress Report'!AC64 -> 0 | EH4: ='Weekly Progress Report'!AC65 -> 0 | EI4: ='Weekly Progress Report'!AC66 -> 0 | EJ4: ='Weekly Progress Report'!AC67 -> 0 | EK4: ='Weekly Progress Report'!AC68 -> 0 | EL4: ='Weekly Progress Report'!AC69 -> 0 | EM4: ='Weekly Progress Report'!AC70 -> 0 | EN4: ='Weekly Progress Report'!AC71 -> 0 | EO4: ='Weekly Progress Report'!AC72 -> 0 | EP4: ='Weekly Progress Report'!AC73 -> 114(531) | EQ4: ='Weekly Progress Report'!AC74 -> 5(23) | ER4: ='Weekly Progress Report'!AC75 -> 4 | ES4: ='Weekly Progress Report'!AC76 -> (40)3119 | ET4: ='Weekly Progress Report'!AC77 -> 1 | EU4: ='Weekly Progress Report'!AD62 -> 805242 | EV4: ='Weekly Progress Report'!AD63 -> 805242 | EW4: ='Weekly Progress Report'!AD64 -> 0 | EX4: ='Weekly Progress Report'!AD65 -> 0 | EY4: ='Weekly Progress Report'!AD66 -> 0 | EZ4: ='Weekly Progress Report'!AD67 -> 0 | FA4: ='Weekly Progress Report'!AD68 -> 0 | FB4: ='Weekly Progress Report'!AD69 -> 0 | FC4: ='Weekly Progress Report'!AD70 -> 0 | FD4: ='Weekly Progress Report'!AD71 -> 0 | FE4: ='Weekly Progress Report'!AD72 -> 0 | FF4: ='Weekly Progress Report'!AD73 -> 143(855) | FG4: ='Weekly Progress Report'!AD74 -> 13(98) | FH4: ='Weekly Progress Report'!AD75 -> 4 | FI4: ='Weekly Progress Report'!AD76 -> 53(8348 | FJ4: ='Weekly Progress Report'!AD77 -> 2 | FK4: ='Weekly Progress Report'!A90 -> 4851 | FL4: ='Weekly Progress Report'!B90 -> 2454 | FM4: ='Weekly Progress Report'!C90 -> 157 | FN4: ='Weekly Progress Report'!D90 -> 2240 | FO4: ='Weekly Progress Report'!A94 -> 129 | FP4: ='Weekly Progress Report'!B94 -> 45 | FQ4: ='Weekly Progress Report'!H94 -> 1796 | FR4: ='Weekly Progress Report'!I94 -> 1152 | FS4: ='Weekly Progress Report'!B102 -> 0 | FT4: ='Weekly Progress Report'!D102 -> 0 | FU4: ='Weekly Progress Report'!F102 -> 0 | FV4: ='Weekly Progress Report'!H102 -> 0 | FW4: ='Weekly Progress Report'!J102 -> 0 | FX4: ='Weekly Progress Report'!L102 -> 0 | FY4: ='Weekly Progress Report'!N102 -> 0 | FZ4: ='Weekly Progress Report'!O102 -> 0 | GA4: ='Weekly Progress Report'!P102 -> 0

Sheet Weekly Progress Report
A1: MODON - Weekly Progress Report - Construction Projects | AF1: Data Date | AG1: ='General Information'!L1 -> 46301
A2: Contract General Information | G2: Key Dates | M2: Cost Summary (SR) | U2: Performance Summary | AA2: Project Scope
A3: Project Name | B3: ='General Information'!C3 -> Development of Infrastructure for phase 1 of the Logistics area at the 2nd Industrial City in Dammam | G3: Contract Award | H3: ='General Information'!C12 -> 45838 | I3: Contract Award (Hijri) | J3: ='General Information'!C16 -> 45838 | K3: Revised Completion | L3: ='General Information'!C20 -> 46416 | M3: Original Contract Value | O3: ='Invoice Log'!E3 -> 1.9890616e+08 | Q3: O&M Value (if any) | S3: ='Invoice Log'!I3 -> 0 | T3: EAC | U3: Plan Value | V3: =K29 -> 0.72325518 | W3: Phys. Plan Value | X3: =W29 -> 0.60876731 | Y3: Quality Score | Z3: =Quality!AC10 -> 0.93 | AA3: =+Progress!B1 -> The project consists of the wet networks mainlines (Sewerage, Storm, Potable, Firefighting & TSE) including the force main line, in addition to the dry networks (Medium Voltage, Low Voltage, Street Lighting & Telecommunication) road crossings & main line connections, scope also included supply, install, testing & commissioning for the potable water pump station and the sewage lift station and implementation of guard rooms and applying all the road earth layers till the asphalt wearing coarse for the project scope area internal roads & finishing the landscape
A4: Project ID | B4: ='General Information'!C4 -> DAM2-02-009 | D4: Stage | E4: ='General Information'!C7 -> Construction | G4: Contract Sign | H4: ='General Information'!C13 -> 45852 | I4: Contract Sign (Hijri) | J4: ='General Information'!C17 -> 45852 | K4: Committed Completion | L4: ='General Information'!C21 -> 46416 | M4: Revised Contract Value | O4: ='Invoice Log'!E4 -> 1.9890616e+08 | P4: EAC | Q4: Submitted Invoices (Gross Value) | S4: ='Invoice Log'!I5 -> 62889674 | U4: Earn Value | V4: =L29 -> 0.51489574 | W4: Phys. Earn Value | X4: =X29 -> 0.42474035 | Z4: =REPT("¢",IF(INT(+Z3*10)>5,5,INT(+Z3*10)))&REPT("£",IF(INT(+Z3*10)>5,0,5-INT(+Z3*10)))&CHAR(10)&REPT("¢",+IF(INT(+Z3*10)>5,-5+INT(+Z3*10),0))&REPT("£",IF(INT(+Z3*10)>5,10-INT(+Z3*10),5)) -> ¢¢¢¢¢ ¢¢¢¢£
A5: Contractor | B5: ='General Information'!C5 -> Shibh Aljazira Contracting Company | D5: Status | E5: ='General Information'!C8 -> Active | G5: Site Handover | H5: ='General Information'!C14 -> 45868 | I5: Site Handover (Hijri) | J5: ='General Information'!C18 -> 45868 | K5: Forecast Completion | L5: ='General Information'!C22 -> 46418 | M5: Estimate At Completion Value | O5: ='Invoice Log'!E5 -> 1.9890616e+08 | P5: =+#REF!+#REF!+O5 -> #REF! | Q5: Penalities | S5: ='Invoice Log'!I6 -> -104500 | U5: Variance | V5: =V4-V3 -> -0.20835944 | W5: Variance | X5: =Y29 -> -0.18402696 | Y5: Safety Score | Z5: ='HSE-Stat'!J23 -> 0.92857143
A6: Consultant | B6: ='General Information'!C6 -> Egis | D6: Modon PM | E6: ='General Information'!C9 -> Muhammad H Al-Essa | G6: Original Completion | H6: ='General Information'!C15 -> 46416 | I6: Original Completion (Hijri) | J6: ='General Information'!C19 -> 46416 | K6: Variance | L6: ='General Information'!C23 -> -2 | M6: Potential Changes | O6: =O4-O5 -> 0 | Q6: FIR Value (Todate) | S6: ='FIR Summary'!I3 -> 77303418 | U6: FIR % | V6: =S6/O4 -> 0.38864265 | W6: Invoiced % | X6: =S4/O4 -> 0.3161776 | Z6: =REPT("¢",IF(INT(+Z5*10)>5,5,INT(+Z5*10)))&REPT("£",IF(INT(+Z5*10)>5,0,5-INT(+Z5*10)))&CHAR(10)&REPT("¢",+IF(INT(+Z5*10)>5,-5+INT(+Z5*10),0))&REPT("£",IF(INT(+Z5*10)>5,10-INT(+Z5*10),5)) -> ¢¢¢¢¢ ¢¢¢¢£
A8: Progress Overview
A9: Earned Value Progress (SAR) | O9: Physical Progress (Effort) | AA9: Earned Value Progress (%)
A10: WBS | C10: BOQ Value (SAR) | D10: % Wt. | E10: Weekly (SAR) | G10: To Date (SAR) | O10: Budgeted | P10: % Wt. | Q10: Weekly Physical Progress | U10: To Date Physical Progress
E11: Planned | F11: Earned | G11: Original Plan | H11: Revised Planned | I11: Earned | J11: Original Plan % | K11: Revised Planned % | L11: Earned % | M11: Variance | N11: SPI | O11: (Manhours) | Q11: Planned | R11: Earned | S11: Plan % | T11: Earned % | U11: Planned | V11: Earned | W11: Plan % | X11: Earned % | Y11: Variance | Z11: SPI
A12: =+Progress!A7 -> Demolishing & Site Clearing | C12: =+Progress!C7 -> 457401.18 | D12: =IF(ISBLANK(C12),"",C12/$C$29) -> 0.0022995827 | E12: =+Progress!E7 -> 457401.18 | F12: =+Progress!F7 -> 136666.96 | G12: =+Progress!G7 -> 457401.18 | H12: =+Progress!H7 -> 457401.18 | I12: =+Progress!I7 -> 457401.18 | J12: =IFERROR(IF(ISBLANK(G12),"",G12/C12),0) -> 1 | K12: =IFERROR(IF(ISBLANK(H12),"",H12/C12),0) -> 1 | L12: =IFERROR(IF(ISBLANK(I12),"",I12/C12),0) -> 1 | M12: =IFERROR(L12-K12,"") -> 0 | N12: =IFERROR(L12/K12,"") -> 1 | O12: =+Progress!K7 -> 3437.41 | P12: =IF(ISBLANK(O12),"",O12/$O$29) -> 0.0037353813 | Q12: =+Progress!M7 -> 3437.41 | R12: =+Progress!N7 -> -442.59 | S12: =IFERROR(IF(ISBLANK(Q12),"",Q12/O12),0) -> 1 | T12: =IFERROR(IF(ISBLANK(R12),"",R12/O12),0) -> -0.12875683 | U12: =+Progress!O7 -> 3437.41 | V12: =+Progress!P7 -> 3437.41 | W12: =IFERROR(IF(ISBLANK(U12),"",U12/O12),0) -> 1 | X12: =IFERROR(IF(ISBLANK(V12),"",V12/O12),0) -> 1 | Y12: =IFERROR(X12-W12,"") -> 0 | Z12: =IFERROR(X12/W12,"") -> 1
A13: =+Progress!A8 -> Earthworks & Site Grading | C13: =+Progress!C8 -> 31040592 | D13: =IF(ISBLANK(C13),"",C13/$C$29) -> 0.15605646 | E13: =+Progress!E8 -> -21385797 | F13: =+Progress!F8 -> -22502335 | G13: =+Progress!G8 -> 31040592 | H13: =+Progress!H8 -> 31040592 | I13: =+Progress!I8 -> 29924053 | J13: =IFERROR(IF(ISBLANK(G13),"",G13/C13),0) -> 1 | K13: =IFERROR(IF(ISBLANK(H13),"",H13/C13),0) -> 1 | L13: =IFERROR(IF(ISBLANK(I13),"",I13/C13),0) -> 0.96402973 | M13: =IFERROR(L13-K13,"") -> -0.035970271 | N13: =IFERROR(L13/K13,"") -> 0.96402973 | O13: =+Progress!K8 -> 22808.8 | P13: =IF(ISBLANK(O13),"",O13/$O$29) -> 0.024785977 | Q13: =+Progress!M8 -> -45319.2 | R13: =+Progress!N8 -> -24484.41 | S13: =IFERROR(IF(ISBLANK(Q13),"",Q13/O13),0) -> -1.9869173 | T13: =IFERROR(IF(ISBLANK(R13),"",R13/O13),0) -> -1.0734633 | U13: =+Progress!O8 -> 22808.8 | V13: =+Progress!P8 -> 21945.45 | W13: =IFERROR(IF(ISBLANK(U13),"",U13/O13),0) -> 1 | X13: =IFERROR(IF(ISBLANK(V13),"",V13/O13),0) -> 0.96214838 | Y13: =IFERROR(X13-W13,"") -> -0.037851619 | Z13: =IFERROR(X13/W13,"") -> 0.96214838
A14: =+Progress!A9 -> Sewerage Network | C14: =+Progress!C9 -> 5111121.8 | D14: =IF(ISBLANK(C14),"",C14/$C$29) -> 0.025696146 | E14: =+Progress!E9 -> 1624385 | F14: =+Progress!F9 -> -557865.16 | G14: =+Progress!G9 -> 4977488.4 | H14: =+Progress!H9 -> 4977488.4 | I14: =+Progress!I9 -> 4189784.5 | J14: =IFERROR(IF(ISBLANK(G14),"",G14/C14),0) -> 0.97385439 | K14: =IFERROR(IF(ISBLANK(H14),"",H14/C14),0) -> 0.97385439 | L14: =IFERROR(IF(ISBLANK(I14),"",I14/C14),0) -> 0.81973872 | M14: =IFERROR(L14-K14,"") -> -0.15411567 | N14: =IFERROR(L14/K14,"") -> 0.8417467 | O14: =+Progress!K9 -> 74260.44 | P14: =IF(ISBLANK(O14),"",O14/$O$29) -> 0.080697694 | Q14: =+Progress!M9 -> -6577.61 | R14: =+Progress!N9 -> -4703.31 | S14: =IFERROR(IF(ISBLANK(Q14),"",Q14/O14),0) -> -0.088574886 | T14: =IFERROR(IF(ISBLANK(R14),"",R14/O14),0) -> -0.063335337 | U14: =+Progress!O9 -> 61270.39 | V14: =+Progress!P9 -> 53207.64 | W14: =IFERROR(IF(ISBLANK(U14),"",U14/O14),0) -> 0.82507443 | X14: =IFERROR(IF(ISBLANK(V14),"",V14/O14),0) -> 0.71650047 | Y14: =IFERROR(X14-W14,"") -> -0.10857396 | Z14: =IFERROR(X14/W14,"") -> 0.86840707
A15: =+Progress!A14 -> Storm Water Network | C15: =+Progress!C14 -> 21808728 | D15: =IF(ISBLANK(C15),"",C15/$C$29) -> 0.1096433 | E15: =+Progress!E14 -> 2413306.5 | F15: =+Progress!F14 -> -87002.14 | G15: =+Progress!G14 -> 20044696 | H15: =+Progress!H14 -> 20044696 | I15: =+Progress!I14 -> 18078712 | J15: =IFERROR(IF(ISBLANK(G15),"",G15/C15),0) -> 0.91911344 | K15: =IFERROR(IF(ISBLANK(H15),"",H15/C15),0) -> 0.91911344 | L15: =IFERROR(IF(ISBLANK(I15),"",I15/C15),0) -> 0.8289668 | M15: =IFERROR(L15-K15,"") -> -0.090146642 | N15: =IFERROR(L15/K15,"") -> 0.90192 | O15: =+Progress!K14 -> 143781.21 | P15: =IF(ISBLANK(O15),"",O15/$O$29) -> 0.15624486 | Q15: =+Progress!M14 -> -17378.91 | R15: =+Progress!N14 -> -4682.1 | S15: =IFERROR(IF(ISBLANK(Q15),"",Q15/O15),0) -> -0.12087052 | T15: =IFERROR(IF(ISBLANK(R15),"",R15/O15),0) -> -0.03256406 | U15: =+Progress!O14 -> 122269.09 | V15: =+Progress!P14 -> 112215.05 | W15: =IFERROR(IF(ISBLANK(U15),"",U15/O15),0) -> 0.85038295 | X15: =IFERROR(IF(ISBLANK(V15),"",V15/O15),0) -> 0.78045699 | Y15: =IFERROR(X15-W15,"") -> -0.069925966 | Z15: =IFERROR(X15/W15,"") -> 0.9177712
A16: =+Progress!A19 -> Potable Water Network | C16: =+Progress!C19 -> 1954044.4 | D16: =IF(ISBLANK(C16),"",C16/$C$29) -> 0.0098239508 | E16: =+Progress!E19 -> 434690.58 | F16: =+Progress!F19 -> -484026.42 | G16: =+Progress!G19 -> 1690361 | H16: =+Progress!H19 -> 1690361 | I16: =+Progress!I19 -> 825178.44 | J16: =IFERROR(IF(ISBLANK(G16),"",G16/C16),0) -> 0.86505765 | K16: =IFERROR(IF(ISBLANK(H16),"",H16/C16),0) -> 0.86505765 | L16: =IFERROR(IF(ISBLANK(I16),"",I16/C16),0) -> 0.42229258 | M16: =IFERROR(L16-K16,"") -> -0.44276507 | N16: =IFERROR(L16/K16,"") -> 0.48816698 | O16: =+Progress!K19 -> 57934.51 | P16: =IF(ISBLANK(O16),"",O16/$O$29) -> 0.062956554 | Q16: =+Progress!M19 -> -5299.67 | R16: =+Progress!N19 -> -2333.46 | S16: =IFERROR(IF(ISBLANK(Q16),"",Q16/O16),0) -> -0.091476911 | T16: =IFERROR(IF(ISBLANK(R16),"",R16/O16),0) -> -0.040277548 | U16: =+Progress!O19 -> 42580.33 | V16: =+Progress!P19 -> 28245.61 | W16: =IFERROR(IF(ISBLANK(U16),"",U16/O16),0) -> 0.73497351 | X16: =IFERROR(IF(ISBLANK(V16),"",V16/O16),0) -> 0.48754378 | Y16: =IFERROR(X16-W16,"") -> -0.24742973 | Z16: =IFERROR(X16/W16,"") -> 0.66334878
A17: =+Progress!A24 -> Fire Fighting Network | C17: =+Progress!C24 -> 4678456.7 | D17: =IF(ISBLANK(C17),"",C17/$C$29) -> 0.023520924 | E17: =+Progress!E24 -> 728032.03 | F17: =+Progress!F24 -> -843901.22 | G17: =+Progress!G24 -> 3773268.9 | H17: =+Progress!H24 -> 3773268.9 | I17: =+Progress!I24 -> 2943158.8 | J17: =IFERROR(IF(ISBLANK(G17),"",G17/C17),0) -> 0.80651999 | K17: =IFERROR(IF(ISBLANK(I17),"",I17/C17),0) -> 0.62908752 | L17: =IFERROR(IF(ISBLANK(I17),"",I17/C17),0) -> 0.62908752 | M17: =IFERROR(L17-K17,"") -> 0 | N17: =IFERROR(L17/K17,"") -> 1 | O17: =+Progress!K24 -> 63346.29 | P17: =IF(ISBLANK(O17),"",O17/$O$29) -> 0.068837453 | Q17: =+Progress!M24 -> -10585.14 | R17: =+Progress!N24 -> -2914.99 | S17: =IFERROR(IF(ISBLANK(Q17),"",Q17/O17),0) -> -0.1670996 | T17: =IFERROR(IF(ISBLANK(R17),"",R17/O17),0) -> -0.046016744 | U17: =+Progress!O24 -> 44606.86 | V17: =+Progress!P24 -> 32601.72 | W17: =IFERROR(IF(ISBLANK(U17),"",U17/O17),0) -> 0.70417478 | X17: =IFERROR(IF(ISBLANK(V17),"",V17/O17),0) -> 0.51465871 | Y17: =IFERROR(X17-W17,"") -> -0.18951607 | Z17: =IFERROR(X17/W17,"") -> 0.73086785
A18: =+Progress!A29 -> TSE Network | C18: =+Progress!C29 -> 2995733.6 | D18: =IF(ISBLANK(C18),"",C18/$C$29) -> 0.01506104 | E18: =+Progress!E29 -> 1612431.1 | F18: =+Progress!F29 -> -1051657.2 | G18: =+Progress!G29 -> 2859193.2 | H18: =+Progress!H29 -> 2859193.2 | I18: =+Progress!I29 -> 510048.1 | J18: =IFERROR(IF(ISBLANK(G18),"",G18/C18),0) -> 0.95442169 | K18: =IFERROR(IF(ISBLANK(I18),"",I18/C18),0) -> 0.17025816 | L18: =IFERROR(IF(ISBLANK(I18),"",I18/C18),0) -> 0.17025816 | M18: =IFERROR(L18-K18,"") -> 0 | N18: =IFERROR(L18/K18,"") -> 1 | O18: =+Progress!K29 -> 48137.98 | P18: =IF(ISBLANK(O18),"",O18/$O$29) -> 0.052310813 | Q18: =+Progress!M29 -> -11878.07 | R18: =+Progress!N29 -> -6694.06 | S18: =IFERROR(IF(ISBLANK(Q18),"",Q18/O18),0) -> -0.24675049 | T18: =IFERROR(IF(ISBLANK(R18),"",R18/O18),0) -> -0.13905984 | U18: =+Progress!O29 -> 24761.93 | V18: =+Progress!P29 -> 12304.02 | W18: =IFERROR(IF(ISBLANK(U18),"",U18/O18),0) -> 0.51439487 | X18: =IFERROR(IF(ISBLANK(V18),"",V18/O18),0) -> 0.25559901 | Y18: =IFERROR(X18-W18,"") -> -0.25879586 | Z18: =IFERROR(X18/W18,"") -> 0.49689261
A19: =+Progress!A34 -> Potable Water Pump Station | C19: =+Progress!C34 -> 11076182 | D19: =IF(ISBLANK(C19),"",C19/$C$29) -> 0.055685463 | E19: =+Progress!E34 -> -6164181.1 | F19: =+Progress!F34 -> -1545112.6 | G19: =+Progress!G34 -> 4419392 | H19: =+Progress!H34 -> 4419392 | I19: =+Progress!I34 -> 1734353.2 | J19: =IFERROR(IF(ISBLANK(G19),"",G19/C19),0) -> 0.39899959 | K19: =IFERROR(IF(ISBLANK(H19),"",H19/C19),0) -> 0.39899959 | L19: =IFERROR(IF(ISBLANK(I19),"",I19/C19),0) -> 0.15658403 | M19: =IFERROR(L19-K19,"") -> -0.24241556 | N19: =IFERROR(L19/K19,"") -> 0.39244158 | O19: =+Progress!K34 -> 71778.26 | P19: =IF(ISBLANK(O19),"",O19/$O$29) -> 0.078000347 | Q19: =+Progress!M34 -> -10022.52 | R19: =+Progress!N34 -> 6439.69 | S19: =IFERROR(IF(ISBLANK(Q19),"",Q19/O19),0) -> -0.13963169 | T19: =IFERROR(IF(ISBLANK(R19),"",R19/O19),0) -> 0.089716441 | U19: =+Progress!O34 -> 45641.48 | V19: =+Progress!P34 -> 31071.69 | W19: =IFERROR(IF(ISBLANK(U19),"",U19/O19),0) -> 0.63586774 | X19: =IFERROR(IF(ISBLANK(V19),"",V19/O19),0) -> 0.43288441 | Y19: =IFERROR(X19-W19,"") -> -0.20298333 | Z19: =IFERROR(X19/W19,"") -> 0.68077744
A20: =+Progress!A39 -> Sewerage Lift Station | C20: =+Progress!C39 -> 4985124.7 | D20: =IF(ISBLANK(C20),"",C20/$C$29) -> 0.025062696 | E20: =+Progress!E39 -> -3538203.9 | F20: =+Progress!F39 -> -555628.72 | G20: =+Progress!G39 -> 276905.79 | H20: =+Progress!H39 -> 276905.79 | I20: =+Progress!I39 -> 36677.32 | J20: =IFERROR(IF(ISBLANK(G20),"",G20/C20),0) -> 0.055546412 | K20: =IFERROR(IF(ISBLANK(H20),"",H20/C20),0) -> 0.055546412 | L20: =IFERROR(IF(ISBLANK(I20),"",I20/C20),0) -> 0.0073573526 | M20: =IFERROR(L20-K20,"") -> -0.048189059 | N20: =IFERROR(L20/K20,"") -> 0.13245415 | O20: =+Progress!K39 -> 70758.97 | P20: =IF(ISBLANK(O20),"",O20/$O$29) -> 0.0768927 | Q20: =+Progress!M39 -> -8207.43 | R20: =+Progress!N39 -> 8009.38 | S20: =IFERROR(IF(ISBLANK(Q20),"",Q20/O20),0) -> -0.11599137 | T20: =IFERROR(IF(ISBLANK(R20),"",R20/O20),0) -> 0.11319243 | U20: =+Progress!O39 -> 43992.57 | V20: =+Progress!P39 -> 16566.86 | W20: =IFERROR(IF(ISBLANK(U20),"",U20/O20),0) -> 0.62172428 | X20: =IFERROR(IF(ISBLANK(V20),"",V20/O20),0) -> 0.23413088 | Y20: =IFERROR(X20-W20,"") -> -0.3875934 | Z20: =IFERROR(X20/W20,"") -> 0.37658314
A21: =+Progress!A44 -> Medium Voltage Network | C21: =+Progress!C44 -> 5452229.2 | D21: =IF(ISBLANK(C21),"",C21/$C$29) -> 0.027411062 | E21: =+Progress!E44 -> 544090.55 | F21: =+Progress!F44 -> -218032.33 | G21: =+Progress!G44 -> 4202411.7 | H21: =+Progress!H44 -> 4202411.7 | I21: =+Progress!I44 -> 1171998.1 | J21: =IFERROR(IF(ISBLANK(G21),"",G21/C21),0) -> 0.77076944 | K21: =IFERROR(IF(ISBLANK(I21),"",I21/C21),0) -> 0.2149576 | L21: =IFERROR(IF(ISBLANK(I21),"",I21/C21),0) -> 0.2149576 | M21: =IFERROR(L21-K21,"") -> 0 | N21: =IFERROR(L21/K21,"") -> 1 | O21: =+Progress!K44 -> 34290.88 | P21: =IF(ISBLANK(O21),"",O21/$O$29) -> 0.037263379 | Q21: =+Progress!M44 -> -12927.56 | R21: =+Progress!N44 -> 613.08 | S21: =IFERROR(IF(ISBLANK(Q21),"",Q21/O21),0) -> -0.37699703 | T21: =IFERROR(IF(ISBLANK(R21),"",R21/O21),0) -> 0.017878806 | U21: =+Progress!O44 -> 17112.44 | V21: =+Progress!P44 -> 11751.82 | W21: =IFERROR(IF(ISBLANK(U21),"",U21/O21),0) -> 0.49903764 | X21: =IFERROR(IF(ISBLANK(V21),"",V21/O21),0) -> 0.34270978 | Y21: =IFERROR(X21-W21,"") -> -0.15632786 | Z21: =IFERROR(X21/W21,"") -> 0.68674134
A22: =+Progress!A49 -> Low Voltage Network | C22: =+Progress!C49 -> 1876943.1 | D22: =IF(ISBLANK(C22),"",C22/$C$29) -> 0.0094363247 | E22: =+Progress!E49 -> -938830.07 | F22: =+Progress!F49 -> -239073.68 | G22: =+Progress!G49 -> 438370.8 | H22: =+Progress!H49 -> 438370.8 | I22: =+Progress!I49 -> 16626.84 | J22: =IFERROR(IF(ISBLANK(G22),"",G22/C22),0) -> 0.23355572 | K22: =IFERROR(IF(ISBLANK(I22),"",I22/C22),0) -> 0.0088584677 | L22: =IFERROR(IF(ISBLANK(I22),"",I22/C22),0) -> 0.0088584677 | M22: =IFERROR(L22-K22,"") -> 0 | N22: =IFERROR(L22/K22,"") -> 1 | O22: =+Progress!K49 -> 31587.58 | P22: =IF(ISBLANK(O22),"",O22/$O$29) -> 0.034325744 | Q22: =+Progress!M49 -> -13293.74 | R22: =+Progress!N49 -> 360.13 | S22: =IFERROR(IF(ISBLANK(Q22),"",Q22/O22),0) -> -0.42085339 | T22: =IFERROR(IF(ISBLANK(R22),"",R22/O22),0) -> 0.011401 | U22: =+Progress!O49 -> 12066.26 | V22: =+Progress!P49 -> 6547.2 | W22: =IFERROR(IF(ISBLANK(U22),"",U22/O22),0) -> 0.38199381 | X22: =IFERROR(IF(ISBLANK(V22),"",V22/O22),0) -> 0.20727134 | Y22: =IFERROR(X22-W22,"") -> -0.17472247 | Z22: =IFERROR(X22/W22,"") -> 0.54260392
A23: =+Progress!A54 -> Street Lighting Network | C23: =+Progress!C54 -> 8486130.6 | D23: =IF(ISBLANK(C23),"",C23/$C$29) -> 0.04266399 | E23: =+Progress!E54 -> -1475231 | F23: =+Progress!F54 -> -508605.97 | G23: =+Progress!G54 -> 3549231.9 | H23: =+Progress!H54 -> 3549231.9 | I23: =+Progress!I54 -> 1407366.6 | J23: =IFERROR(IF(ISBLANK(G23),"",G23/C23),0) -> 0.41823914 | K23: =IFERROR(IF(ISBLANK(I23),"",I23/C23),0) -> 0.16584314 | L23: =IFERROR(IF(ISBLANK(I23),"",I23/C23),0) -> 0.16584314 | M23: =IFERROR(L23-K23,"") -> 0 | N23: =IFERROR(L23/K23,"") -> 1 | O23: =+Progress!K54 -> 76760.06 | P23: =IF(ISBLANK(O23),"",O23/$O$29) -> 0.083413993 | Q23: =+Progress!M54 -> -38391.43 | R23: =+Progress!N54 -> 2909.95 | S23: =IFERROR(IF(ISBLANK(Q23),"",Q23/O23),0) -> -0.50014851 | T23: =IFERROR(IF(ISBLANK(R23),"",R23/O23),0) -> 0.037909689 | U23: =+Progress!O54 -> 32896.57 | V23: =+Progress!P54 -> 17438.08 | W23: =IFERROR(IF(ISBLANK(U23),"",U23/O23),0) -> 0.42856363 | X23: =IFERROR(IF(ISBLANK(V23),"",V23/O23),0) -> 0.22717648 | Y23: =IFERROR(X23-W23,"") -> -0.20138715 | Z23: =IFERROR(X23/W23,"") -> 0.53008809
A24: =+Progress!A59 -> Telecommunication Network | C24: =+Progress!C59 -> 4454965.6 | D24: =IF(ISBLANK(C24),"",C24/$C$29) -> 0.022397323 | E24: =+Progress!E59 -> -1170100.7 | F24: =+Progress!F59 -> -420209.79 | G24: =+Progress!G59 -> 1677088 | H24: =+Progress!H59 -> 1677088 | I24: =+Progress!I59 -> 965354.72 | J24: =IFERROR(IF(ISBLANK(G24),"",G24/C24),0) -> 0.37645363 | K24: =IFERROR(IF(ISBLANK(H24),"",H24/C24),0) -> 0.37645363 | L24: =IFERROR(IF(ISBLANK(I24),"",I24/C24),0) -> 0.21669185 | M24: =IFERROR(L24-K24,"") -> -0.15976178 | N24: =IFERROR(L24/K24,"") -> 0.57561365 | O24: =+Progress!K59 -> 62092.94 | P24: =IF(ISBLANK(O24),"",O24/$O$29) -> 0.067475456 | Q24: =+Progress!M59 -> -33174.44 | R24: =+Progress!N59 -> 3043.51 | S24: =IFERROR(IF(ISBLANK(Q24),"",Q24/O24),0) -> -0.53427072 | T24: =IFERROR(IF(ISBLANK(R24),"",R24/O24),0) -> 0.049015395 | U24: =+Progress!O59 -> 23457.56 | V24: =+Progress!P59 -> 15462.07 | W24: =IFERROR(IF(ISBLANK(U24),"",U24/O24),0) -> 0.37778144 | X24: =IFERROR(IF(ISBLANK(V24),"",V24/O24),0) -> 0.24901494 | Y24: =IFERROR(X24-W24,"") -> -0.12876649 | Z24: =IFERROR(X24/W24,"") -> 0.65915082
A25: =+Progress!A64 -> Road Works | C25: =+Progress!C64 -> 79068381 | D25: =IF(ISBLANK(C25),"",C25/$C$29) -> 0.39751599 | E25: =+Progress!E64 -> 4629678.6 | F25: =+Progress!F64 -> 11794897 | G25: =+Progress!G64 -> 63789840 | H25: =+Progress!H64 -> 63789840 | I25: =+Progress!I64 -> 40015001 | J25: =IFERROR(IF(ISBLANK(G25),"",G25/C25),0) -> 0.806768 | K25: =IFERROR(IF(ISBLANK(H25),"",H25/C25),0) -> 0.806768 | L25: =IFERROR(IF(ISBLANK(I25),"",I25/C25),0) -> 0.50608094 | M25: =IFERROR(L25-K25,"") -> -0.30068706 | N25: =IFERROR(L25/K25,"") -> 0.62729427 | O25: =+Progress!K64 -> 80303.58 | P25: =IF(ISBLANK(O25),"",O25/$O$29) -> 0.087264683 | Q25: =+Progress!M64 -> -36526.22 | R25: =+Progress!N64 -> 642.95 | S25: =IFERROR(IF(ISBLANK(Q25),"",Q25/O25),0) -> -0.4548517 | T25: =IFERROR(IF(ISBLANK(R25),"",R25/O25),0) -> 0.0080064924 | U25: =+Progress!O64 -> 38233.78 | V25: =+Progress!P64 -> 19355.5 | W25: =IFERROR(IF(ISBLANK(U25),"",U25/O25),0) -> 0.47611551 | X25: =IFERROR(IF(ISBLANK(V25),"",V25/O25),0) -> 0.2410291 | Y25: =IFERROR(X25-W25,"") -> -0.23508641 | Z25: =IFERROR(X25/W25,"") -> 0.50624082
A26: =+Progress!A68 -> Landscape | C26: =+Progress!C68 -> 14727630 | D26: =IF(ISBLANK(C26),"",C26/$C$29) -> 0.074043103 | E26: =+Progress!E68 -> -4388547.8 | F26: =+Progress!F68 -> -49702.42 | G26: =+Progress!G68 -> 570737.12 | H26: =+Progress!H68 -> 570737.12 | I26: =+Progress!I68 -> 98475.6 | J26: =IFERROR(IF(ISBLANK(G26),"",G26/C26),0) -> 0.038752816 | K26: =IFERROR(IF(ISBLANK(H26),"",H26/C26),0) -> 0.038752816 | L26: =IFERROR(IF(ISBLANK(I26),"",I26/C26),0) -> 0.0066864528 | M26: =IFERROR(L26-K26,"") -> -0.032066363 | N26: =IFERROR(L26/K26,"") -> 0.17254108 | O26: =+Progress!K68 -> 44855.31 | P26: =IF(ISBLANK(O26),"",O26/$O$29) -> 0.048743585 | Q26: =+Progress!M68 -> -27678.83 | R26: =+Progress!N68 -> 2488.35 | S26: =IFERROR(IF(ISBLANK(Q26),"",Q26/O26),0) -> -0.61706919 | T26: =IFERROR(IF(ISBLANK(R26),"",R26/O26),0) -> 0.055475037 | U26: =+Progress!O68 -> 7105.17 | V26: =+Progress!P68 -> 3081.95 | W26: =IFERROR(IF(ISBLANK(U26),"",U26/O26),0) -> 0.15840198 | X26: =IFERROR(IF(ISBLANK(V26),"",V26/O26),0) -> 0.068708699 | Y26: =IFERROR(X26-W26,"") -> -0.089693283 | Z26: =IFERROR(X26/W26,"") -> 0.43376161
A27: =+Progress!A72 -> Guard Rooms | C27: =+Progress!C72 -> 539598.47 | D27: =IF(ISBLANK(C27),"",C27/$C$29) -> 0.0027128293 | E27: =+Progress!E72 -> -420766.65 | F27: =+Progress!F72 -> -2951.99 | G27: =+Progress!G72 -> 92935.49 | H27: =+Progress!H72 -> 92935.49 | I27: =+Progress!I72 -> 41745.84 | J27: =IFERROR(IF(ISBLANK(G27),"",G27/C27),0) -> 0.17223083 | K27: =IFERROR(IF(ISBLANK(H27),"",H27/C27),0) -> 0.17223083 | L27: =IFERROR(IF(ISBLANK(I27),"",I27/C27),0) -> 0.077364637 | M27: =IFERROR(L27-K27,"") -> -0.094866188 | N27: =IFERROR(L27/K27,"") -> 0.44919158 | O27: =+Progress!K72 -> 34095.79 | P27: =IF(ISBLANK(O27),"",O27/$O$29) -> 0.037051378 | Q27: =+Progress!M72 -> -9242.69 | R27: =+Progress!N72 -> 4506.75 | S27: =IFERROR(IF(ISBLANK(Q27),"",Q27/O27),0) -> -0.2710801 | T27: =IFERROR(IF(ISBLANK(R27),"",R27/O27),0) -> 0.13217908 | U27: =+Progress!O72 -> 17965.31 | V27: =+Progress!P72 -> 5626.75 | W27: =IFERROR(IF(ISBLANK(U27),"",U27/O27),0) -> 0.52690699 | X27: =IFERROR(IF(ISBLANK(V27),"",V27/O27),0) -> 0.16502771 | Y27: =IFERROR(X27-W27,"") -> -0.36187928 | Z27: =IFERROR(X27/W27,"") -> 0.31320083
A28: =Progress!A76 -> Provisional Sum | C28: =Progress!C76 -> 192900.72 | D28: =IF(ISBLANK(C28),"",C28/$C$29) -> 0.00096980766 | E28: =Progress!E76 -> 0 | F28: =Progress!F76 -> 0 | G28: =Progress!G76 -> 0 | H28: =Progress!H76 -> 0 | I28: =Progress!I76 -> 0 | J28: =IFERROR(IF(ISBLANK(G28),"",G28/C28),0) -> 0 | K28: =IFERROR(IF(ISBLANK(I28),"",I28/C28),0) -> 0 | L28: =IFERROR(IF(ISBLANK(I28),"",I28/C28),0) -> 0 | M28: =IFERROR(L28-K28,"") -> 0 | N28: =IFERROR(L28/K28,"") | O28: =Progress!K76 -> 0 | P28: =IF(ISBLANK(O28),"",O28/$O$29) -> 0 | Q28: =Progress!M76 -> 0 | R28: =Progress!N76 -> 0 | S28: =IFERROR(IF(ISBLANK(Q28),"",Q28/O28),0) -> 0 | T28: =IFERROR(IF(ISBLANK(R28),"",R28/O28),0) -> 0 | U28: =Progress!O76 -> 0 | V28: =Progress!P76 -> 0 | W28: =IFERROR(IF(ISBLANK(U28),"",U28/O28),0) -> 0 | X28: =IFERROR(IF(ISBLANK(V28),"",V28/O28),0) -> 0 | Y28: =IFERROR(X28-W28,"") -> 0 | Z28: =IFERROR(X28/W28,"")
B29: Total | C29: =SUM(C12:C28) -> 1.9890616e+08 | D29: =SUM(D12:D28) -> 1 | E29: =SUM(E12:E28) -> -27037643 | F29: =SUM(F12:F28) -> -17134541 | G29: =SUM(G12:G28) -> 1.4385991e+08 | H29: =SUM(H12:H28) -> 1.4385991e+08 | I29: =SUM(I12:I28) -> 1.0241594e+08 | J29: =IFERROR(IF(ISBLANK(G29),"",G29/C29),0) -> 0.72325518 | K29: =IFERROR(IF(ISBLANK(H29),"",H29/C29),0) -> 0.72325518 | L29: =IFERROR(IF(ISBLANK(I29),"",I29/C29),0) -> 0.51489574 | M29: =+L29-K29 -> -0.20835944 | N29: =L29/K29 -> 0.71191434 | O29: =SUM(O12:O28) -> 920230.01 | P29: =SUM(P12:P28) -> 1 | Q29: =SUM(Q12:Q28) -> -283066.05 | R29: =SUM(R12:R28) -> -17241.13 | S29: =IFERROR(IF(ISBLANK(Q29),"",Q29/O29),0) -> -0.30760358 | T29: =IFERROR(IF(ISBLANK(R29),"",R29/O29),0) -> -0.018735675 | U29: =SUM(U12:U28) -> 560205.95 | V29: =SUM(V12:V28) -> 390858.82 | W29: =IFERROR(IF(ISBLANK(U29),"",U29/O29),0) -> 0.60876731 | X29: =IFERROR(IF(ISBLANK(V29),"",V29/O29),0) -> 0.42474035 | Y29: =+X29-W29 -> -0.18402696 | Z29: =X29/W29 -> 0.69770558
AA30: Construction Milestones
AA31: Item No. | AB31: Milestones | AD31: Original (Baseline) | AE31: Latest Plan | AF31: Forecast | AG31: Status | AH31: Days Change
AA32: =+Milestones!A4 -> 1 | AB32: =+Milestones!B4 -> Award Date | AD32: =+Milestones!C4 -> 45838 | AE32: =+Milestones!D4 -> 45838 | AF32: =+Milestones!E4 -> 45838 | AG32: =+Milestones!F4 -> A | AH32: =+Milestones!G4 -> 0
AA33: =+Milestones!A5 -> 2 | AB33: =+Milestones!B5 -> Contract Sign Date | AD33: =+Milestones!C5 -> 45852 | AE33: =+Milestones!D5 -> 45852 | AF33: =+Milestones!E5 -> 45852 | AG33: =+Milestones!F5 -> A | AH33: =+Milestones!G5 -> 0
AA34: =+Milestones!A6 -> 3 | AB34: =+Milestones!B6 -> Site Handover Date | AD34: =+Milestones!C6 -> 45868 | AE34: =+Milestones!D6 -> 45868 | AF34: =+Milestones!E6 -> 45868 | AG34: =+Milestones!F6 -> A | AH34: =+Milestones!G6 -> 0
AA35: =+Milestones!A7 -> 4 | AB35: =+Milestones!B7 -> Complete Mobilization | AD35: =+Milestones!C7 -> 45899 | AE35: =+Milestones!D7 -> 45899 | AF35: =+Milestones!E7 -> 45899 | AG35: =+Milestones!F7 -> A | AH35: =+Milestones!G7 -> 0
AA36: =+Milestones!A10 -> 7 | AB36: =+Milestones!B10 -> Complete Earthworks | AD36: =+Milestones!C10 -> 46280 | AE36: =+Milestones!D10 -> 46280 | AF36: =+Milestones!E10 -> 46319 | AG36: =+Milestones!F10 -> F | AH36: =+Milestones!G10 -> -39
AA37: =+Milestones!A11 -> 8 | AB37: =+Milestones!B11 -> Complete all Wet Networks | AD37: =+Milestones!C11 -> 46348 | AE37: =+Milestones!D11 -> 46348 | AF37: =+Milestones!E11 -> 46365 | AG37: =+Milestones!F11 -> F | AH37: =+Milestones!G11 -> -17
AA38: =+Milestones!A12 -> 9 | AB38: =+Milestones!B12 -> Complete Electrical Works | AD38: =+Milestones!C12 -> 46350 | AE38: =+Milestones!D12 -> 46350 | AF38: =+Milestones!E12 -> 46366 | AG38: =+Milestones!F12 -> F | AH38: =+Milestones!G12 -> -16
AA39: =+Milestones!A13 -> 10 | AB39: =+Milestones!B13 -> Complete all Works including Testing & Commissioning, Cleanup, Closeout Documentation and Ready for Initial Handover | AD39: =+Milestones!C13 -> 46401 | AE39: =+Milestones!D13 -> 46401 | AF39: =+Milestones!E13 -> 46418 | AG39: =+Milestones!F13 -> F | AH39: =+Milestones!G13 -> -17
AA40: =+Milestones!A14 -> 11 | AB40: =+Milestones!B14 -> Complete Demobilization | AD40: =+Milestones!C14 -> 46412 | AE40: =+Milestones!D14 -> 46412 | AF40: =+Milestones!E14 -> 46428 | AG40: =+Milestones!F14 -> F | AH40: =+Milestones!G14 -> -16
AA41: =+Milestones!A15 -> 12 | AB41: =+Milestones!B15 -> Project Handover | AD41: =+Milestones!C15 -> 46416 | AE41: =+Milestones!D15 -> 46416 | AF41: =+Milestones!E15 -> 46433 | AG41: =+Milestones!F15 -> F | AH41: =+Milestones!G15 -> -17
A57: Performance overview
A58: Submittals Status | L58: Quality | W58: Safety
A59: Shop Drawings | L59: Quality Reports | W59: Safety Statistics | AE59: Proactive Vs Reactive Actions Taken
A60: Item Per WBS | C60: Total | D60: Total Submitted Drawings | I60: Remaining | J60: Pending | K60: Total Submittals | L60: Quality Reports | N60: Issued | O60: Closed | P60: Pending | Q60: Avg. Closing (Days) | R60: Pending | W60: Category | X60: Item | Z60: This Week | AB60: This Month | AC60: Year to Date | AD60: Cumulative
D61: A | E61: B | F61: C | G61: D | H61: Processed | R61: 0-10 Days | S61: 11-20 Days | T61: 21-30 Days | U61: 31-60 Days | V61: > 60 Days
A62: ='Quality-Stat'!A13 -> CVL | C62: =IF('Quality-Stat'!D13="","",'Quality-Stat'!D13) -> 1063 | D62: =IF('Quality-Stat'!E13="","",'Quality-Stat'!E13) -> 8 | E62: =IF('Quality-Stat'!F13="","",'Quality-Stat'!F13) -> 1055 | F62: =IF('Quality-Stat'!G13="","",'Quality-Stat'!G13) -> 0 | G62: =IF('Quality-Stat'!H13="","",'Quality-Stat'!H13) -> 0 | H62: =IF('Quality-Stat'!I13="","",'Quality-Stat'!I13) -> 1063 | I62: =IF('Quality-Stat'!J13="","",'Quality-Stat'!J13) -> 0 | J62: =IF('Quality-Stat'!K13="","",'Quality-Stat'!K13) -> 0 | K62: =IF('Quality-Stat'!L13="","",'Quality-Stat'!L13) -> 1063 | W62: General | X62: ='HSE-Stat'!B4 -> Total Hours Worked | Z62: ='HSE-Stat'!D4 -> 34740 | AB62: ='HSE-Stat'!E4 -> 34740 | AC62: ='HSE-Stat'!F4 -> 740184 | AD62: ='HSE-Stat'!G4 -> 805242 | AG62: Proactive | AH62: =+SUM(AD73:AD77) -> 6
A63: ='Quality-Stat'!A14 -> Mech | C63: =IF('Quality-Stat'!D14="","",'Quality-Stat'!D14) -> 212 | D63: =IF('Quality-Stat'!E14="","",'Quality-Stat'!E14) -> 0 | E63: =IF('Quality-Stat'!F14="","",'Quality-Stat'!F14) -> 212 | F63: =IF('Quality-Stat'!G14="","",'Quality-Stat'!G14) -> 0 | G63: =IF('Quality-Stat'!H14="","",'Quality-Stat'!H14) -> 0 | H63: =IF('Quality-Stat'!I14="","",'Quality-Stat'!I14) -> 212 | I63: =IF('Quality-Stat'!J14="","",'Quality-Stat'!J14) -> 0 | J63: =IF('Quality-Stat'!K14="","",'Quality-Stat'!K14) -> 0 | K63: =IF('Quality-Stat'!L14="","",'Quality-Stat'!L14) -> 212 | L63: Non Conformance (NCR) | N63: 4 | O63: 3 | P63: 1 | Q63: ='Quality-Stat'!F5 -> 0 | R63: 0 | S63: ='Quality-Stat'!H5 -> 0 | T63: ='Quality-Stat'!I5 -> 0 | U63: ='Quality-Stat'!J5 -> 0 | V63: ='Quality-Stat'!K5 -> 0 | X63: ='HSE-Stat'!B5 -> Safe Hours Worked | Z63: ='HSE-Stat'!D5 -> 34740 | AB63: ='HSE-Stat'!E5 -> 34740 | AC63: ='HSE-Stat'!F5 -> 740184 | AD63: ='HSE-Stat'!G5 -> 805242 | AG63: Reactive | AH63: =SUM(AD64:AD72) -> 0
A64: ='Quality-Stat'!A15 -> Elec | C64: =IF('Quality-Stat'!D15="","",'Quality-Stat'!D15) -> 41 | D64: =IF('Quality-Stat'!E15="","",'Quality-Stat'!E15) -> 0 | E64: =IF('Quality-Stat'!F15="","",'Quality-Stat'!F15) -> 41 | F64: =IF('Quality-Stat'!G15="","",'Quality-Stat'!G15) -> 0 | G64: =IF('Quality-Stat'!H15="","",'Quality-Stat'!H15) -> 0 | H64: =IF('Quality-Stat'!I15="","",'Quality-Stat'!I15) -> 41 | I64: =IF('Quality-Stat'!J15="","",'Quality-Stat'!J15) -> 0 | J64: =IF('Quality-Stat'!K15="","",'Quality-Stat'!K15) -> 0 | K64: =IF('Quality-Stat'!L15="","",'Quality-Stat'!L15) -> 41 | L64: Site Instruction (SIR) | N64: ='Quality-Stat'!C6 -> 50 | O64: ='Quality-Stat'!D6 -> 41 | P64: ='Quality-Stat'!E6 -> 9 | Q64: ='Quality-Stat'!F6 -> 0 | R64: ='Quality-Stat'!G6 -> 0 | S64: ='Quality-Stat'!H6 -> 0 | T64: ='Quality-Stat'!I6 -> 0 | U64: ='Quality-Stat'!J6 -> 0 | V64: ='Quality-Stat'!K6 -> 0 | W64: Reactive | X64: ='HSE-Stat'!B6 -> LTI | Z64: ='HSE-Stat'!D6 -> 0 | AB64: ='HSE-Stat'!E6 -> 0 | AC64: ='HSE-Stat'!F6 -> 0 | AD64: ='HSE-Stat'!G6 -> 0
A65: ='Quality-Stat'!A16 -> Landscape & Arch | C65: =IF('Quality-Stat'!D16="","",'Quality-Stat'!D16) -> 458 | D65: =IF('Quality-Stat'!E16="","",'Quality-Stat'!E16) -> 0 | E65: =IF('Quality-Stat'!F16="","",'Quality-Stat'!F16) -> 458 | F65: =IF('Quality-Stat'!G16="","",'Quality-Stat'!G16) -> 0 | G65: =IF('Quality-Stat'!H16="","",'Quality-Stat'!H16) -> 0 | H65: =IF('Quality-Stat'!I16="","",'Quality-Stat'!I16) -> 458 | I65: =IF('Quality-Stat'!J16="","",'Quality-Stat'!J16) -> 0 | J65: =IF('Quality-Stat'!K16="","",'Quality-Stat'!K16) -> 0 | K65: =IF('Quality-Stat'!L16="","",'Quality-Stat'!L16) -> 458 | L65: Material Inspection (MIR) | N65: ='Quality-Stat'!C7 -> 109 | O65: ='Quality-Stat'!D7 -> 108 | P65: ='Quality-Stat'!E7 -> 1 | Q65: ='Quality-Stat'!F7 -> 0 | R65: ='Quality-Stat'!G7 -> 0 | S65: ='Quality-Stat'!H7 -> 0 | T65: ='Quality-Stat'!I7 -> 0 | U65: ='Quality-Stat'!J7 -> 0 | V65: ='Quality-Stat'!K7 -> 0 | X65: ='HSE-Stat'!B7 -> MTC (Healed w/o Disability) | Z65: ='HSE-Stat'!D7 -> 0 | AB65: ='HSE-Stat'!E7 -> 0 | AC65: ='HSE-Stat'!F7 -> 0 | AD65: ='HSE-Stat'!G7 -> 0
L66: Field Inspection (FIR) | N66: ='Quality-Stat'!C8 -> 4296 | O66: ='Quality-Stat'!D8 -> 4128 | P66: ='Quality-Stat'!E8 -> 168 | Q66: ='Quality-Stat'!F8 -> 0 | R66: ='Quality-Stat'!G8 -> 0 | S66: ='Quality-Stat'!H8 -> 0 | T66: ='Quality-Stat'!I8 -> 0 | U66: ='Quality-Stat'!J8 -> 0 | V66: ='Quality-Stat'!K8 -> 0 | X66: ='HSE-Stat'!B8 -> MTC (Healed w/ Disability) | Z66: ='HSE-Stat'!D8 -> 0 | AB66: ='HSE-Stat'!E8 -> 0 | AC66: ='HSE-Stat'!F8 -> 0 | AD66: ='HSE-Stat'!G8 -> 0
A67: TOTAL | C67: =SUM(C62:C66) -> 1774 | D67: =SUM(D62:D66) -> 8 | E67: =SUM(E62:E66) -> 1766 | F67: =SUM(F62:F66) -> 0 | G67: =SUM(G62:G66) -> 0 | H67: =SUM(H62:H66) -> 1774 | I67: =SUM(I62:I66) -> 0 | J67: =SUM(J62:J66) -> 0 | K67: =SUM(K62:K66) -> 1774 | L67: Key Submittals Approval Status | X67: ='HSE-Stat'!B9 -> Near Miss | Z67: ='HSE-Stat'!D9 -> 0 | AB67: ='HSE-Stat'!E9 -> 0 | AC67: ='HSE-Stat'!F9 -> 0 | AD67: ='HSE-Stat'!G9 -> 0
A68: Material Approval | L68: 1 Quality Plan Approval | O68: ='General Information'!C27 -> 45346 | Q68: 6 Baseline Approval | U68: ='General Information'!C39 -> 45361 | X68: ='HSE-Stat'!B10 -> First Aid Cases | Z68: ='HSE-Stat'!D10 -> 0 | AB68: ='HSE-Stat'!E10 -> 0 | AC68: ='HSE-Stat'!F10 -> 0 | AD68: ='HSE-Stat'!G10 -> 0 | AE68: Total Hours Worked Vs Safe Hours Worked
A69: Item Per WBS | C69: Total | D69: Total Submitted Material | I69: Remaining to approve | J69: Pending | K69: Total Submittals | L69: 2 Quality Plan Last Up | O69: ='General Information'!C28 -> 45346 | Q69: 7 No of Approved Version of Schedule | U69: ='General Information'!C40 -> 1 | X69: ='HSE-Stat'!B11 -> Fatality | Z69: ='HSE-Stat'!D11 -> 0 | AB69: ='HSE-Stat'!E11 -> 0 | AC69: ='HSE-Stat'!F11 -> 0 | AD69: ='HSE-Stat'!G11 -> 0
D70: A | E70: B | F70: C | G70: D | H70: Processed | I70: with Designer | L70: 3 Safety Plan Approval | O70: ='General Information'!C31 -> 45350 | Q70: 8 Last Approved Schedule | U70: ='General Information'!C41 -> 45361 | X70: ='HSE-Stat'!B12 -> Fire Incident Cases | Z70: ='HSE-Stat'!D12 -> 0 | AB70: ='HSE-Stat'!E12 -> 0 | AC70: ='HSE-Stat'!F12 -> 0 | AD70: ='HSE-Stat'!G12 -> 0
A71: ='Quality-Stat'!A23 -> Civil & Roads | C71: ='Quality-Stat'!D23 -> 75 | D71: ='Quality-Stat'!E23 -> 2 | E71: ='Quality-Stat'!F23 -> 73 | F71: ='Quality-Stat'!G23 -> 3 | G71: ='Quality-Stat'!H23 -> 1 | H71: ='Quality-Stat'!I23 -> 75 | I71: ='Quality-Stat'!J23 -> 0 | J71: ='Quality-Stat'!K23 -> 3 | K71: ='Quality-Stat'!L23 -> 82 | L71: 4 Safety Plan Last Up | O71: ='General Information'!C32 -> 45350 | Q71: 9 BOQ Approval Date | U71: ='General Information'!C44 -> 0 | X71: ='HSE-Stat'!B13 -> Vehicle Incident | Z71: ='HSE-Stat'!D13 -> 0 | AB71: ='HSE-Stat'!E13 -> 0 | AC71: ='HSE-Stat'!F13 -> 0 | AD71: ='HSE-Stat'!G13 -> 0
A72: ='Quality-Stat'!A24 -> Electrical | C72: ='Quality-Stat'!D24 -> 30 | D72: ='Quality-Stat'!E24 -> 0 | E72: ='Quality-Stat'!F24 -> 22 | F72: ='Quality-Stat'!G24 -> 0 | G72: ='Quality-Stat'!H24 -> 0 | H72: ='Quality-Stat'!I24 -> 22 | I72: ='Quality-Stat'!J24 -> 8 | J72: ='Quality-Stat'!K24 -> 0 | K72: ='Quality-Stat'!L24 -> 22 | L72: 5 Construction Plan Approval | O72: ='General Information'!C48 -> 45348 | Q72: 10 No of Approved Version of BOQ | U72: ='General Information'!C45 -> 1 | X72: ='HSE-Stat'!B14 -> Property Damages | Z72: ='HSE-Stat'!D14 -> 0 | AB72: ='HSE-Stat'!E14 -> 0 | AC72: ='HSE-Stat'!F14 -> 0 | AD72: ='HSE-Stat'!G14 -> 0
A73: ='Quality-Stat'!A25 -> Mechanical | C73: ='Quality-Stat'!D25 -> 48 | D73: ='Quality-Stat'!E25 -> 0 | E73: ='Quality-Stat'!F25 -> 41 | F73: ='Quality-Stat'!G25 -> 0 | G73: ='Quality-Stat'!H25 -> 2 | H73: ='Quality-Stat'!I25 -> 41 | I73: ='Quality-Stat'!J25 -> 7 | J73: ='Quality-Stat'!K25 -> 0 | K73: ='Quality-Stat'!L25 -> 43 | L73: Invoices Summary | W73: Proactive | X73: ='HSE-Stat'!B15 -> Induction Training | Z73: ='HSE-Stat'!D15 -> 29 | AB73: ='HSE-Stat'!E15 -> 29 | AC73: ='HSE-Stat'!F15 -> 114(531) | AD73: ='HSE-Stat'!G15 -> 143(855)
L74: Total Submitted Invoices | N74: ='Invoice Log'!U3 -> 6 | O74: Submitted Invoices (SAR) | R74: ='Invoice Log'!Y3 -> 62889674 | T74: Contract Value (SR) | U74: =O4 -> 1.9890616e+08 | X74: ='HSE-Stat'!B16 -> No.of Internal Training | Z74: ='HSE-Stat'!D16 -> 0 | AB74: ='HSE-Stat'!E16 -> 2 (9) | AC74: ='HSE-Stat'!F16 -> 5(23) | AD74: ='HSE-Stat'!G16 -> 13(98)
L75: PM Approved Invoices | N75: ='Invoice Log'!U5 -> 0 | O75: PM Approved Invoices (SAR) | R75: ='Invoice Log'!Y5 -> 0 | T75: Planned Value (SR) | U75: =H29 -> 1.4385991e+08 | X75: ='HSE-Stat'!B17 -> No.of Internal Audit | Z75: ='HSE-Stat'!D17 -> 0 | AB75: ='HSE-Stat'!E17 -> 1 | AC75: ='HSE-Stat'!F17 -> 4 | AD75: ='HSE-Stat'!G17 -> 4
A76: TOTAL | C76: =SUM(C71:C75) -> 153 | D76: =SUM(D71:D75) -> 2 | E76: =SUM(E71:E75) -> 136 | F76: =SUM(F71:F75) -> 3 | G76: =SUM(G71:G75) -> 3 | H76: =SUM(H71:H75) -> 138 | I76: =SUM(I71:I75) -> 15 | J76: =SUM(J71:J75) -> 3 | K76: =SUM(K71:K75) -> 147 | L76: No of Paid Invoices | N76: ='Invoice Log'!U6 -> 0 | O76: Paid Invoices (SAR) | R76: ='Invoice Log'!Y6 -> 0 | T76: Earned Value (SR) | U76: =I29 -> 1.0241594e+08 | X76: ='HSE-Stat'!B18 -> No. of Toolbox Talks | Z76: ='HSE-Stat'!D18 -> 3(325) | AB76: ='HSE-Stat'!E18 -> 3(325) | AC76: ='HSE-Stat'!F18 -> (40)3119 | AD76: ='HSE-Stat'!G18 -> 53(8348
A77: Procurement Summary | L77: No of Pending Invoices | N77: =N75-N76 -> 0 | O77: Last Submitted Period | R77: ='Invoice Log'!AB3 -> 46280 | T77: Submitted (SAR) | U77: =R74 -> 62889674 | X77: ='HSE-Stat'!B19 -> Safety Awards/Incentives | Z77: ='HSE-Stat'!D19 -> 0 | AB77: ='HSE-Stat'!E19 -> 0 | AC77: ='HSE-Stat'!F19 -> 1 | AD77: ='HSE-Stat'!G19 -> 2
A78: Item Per WBS | C78: Total Materials | D78: Total Number of P.O. | E78: Actual P.O. To Date | F78: Remaining P.O | G78: Material on Site | H78: Remaining Materials | I78: Material Delivery Completion (Date) | L78: Advance Payment % | N78: ='Invoice Log'!M3 -> 0 | O78: Advance Payment (SAR) | R78: ='Invoice Log'!Q3 -> 0 | T78: PM Approved (SAR) | U78: =R75 -> 0 | W78: Latest Contract Change Order Log
D79: A | E79: B | F79: C | G79: D | H79: Processed | L79: Retention % | N79: ='Invoice Log'!M4 -> 0 | O79: Retention (SAR) | R79: ='Invoice Log'!Q4 -> 0 | T79: Total Paid (SAR) | U79: =R76 -> 0
A80: ='Quality-Stat'!A31 -> Civil & Roads | C80: =IF('Quality-Stat'!D31="","",'Quality-Stat'!D31) -> 75 | D80: =IF('Quality-Stat'!E31="","",'Quality-Stat'!E31) -> 75 | E80: =IF('Quality-Stat'!F31="","",'Quality-Stat'!F31) -> 75 | F80: =IF('Quality-Stat'!G31="","",'Quality-Stat'!G31) -> 0 | G80: =IF('Quality-Stat'!H31="","",'Quality-Stat'!H31) -> 42 | H80: =IF('Quality-Stat'!I31="","",'Quality-Stat'!I31) -> 33 | I80: ='Quality-Stat'!J31 -> 46335 | L80: Deduction / Penalties % | N80: ='Invoice Log'!M5 -> 0.00052537337 | O80: Deduction / Penalties (SAR) | R80: ='Invoice Log'!M6 -> -104500 | W80: CCO No. | X80: Date Added | Y80: Description of Change | AD80: Status | AE80: Cost | AF80: Sch Impact (Months) | AG80: Date Approved | AH80: Duration
A81: ='Quality-Stat'!A32 -> Electrical | C81: =IF('Quality-Stat'!D32="","",'Quality-Stat'!D32) -> 30 | D81: =IF('Quality-Stat'!E32="","",'Quality-Stat'!E32) -> 30 | E81: =IF('Quality-Stat'!F32="","",'Quality-Stat'!F32) -> 22 | F81: =IF('Quality-Stat'!G32="","",'Quality-Stat'!G32) -> 0 | G81: =IF('Quality-Stat'!H32="","",'Quality-Stat'!H32) -> 11 | H81: =IF('Quality-Stat'!I32="","",'Quality-Stat'!I32) -> 19 | I81: ='Quality-Stat'!J32 -> 46292 | L81: Resources at Site
A82: ='Quality-Stat'!A33 -> Mechanical | C82: =IF('Quality-Stat'!D33="","",'Quality-Stat'!D33) -> 48 | D82: =IF('Quality-Stat'!E33="","",'Quality-Stat'!E33) -> 48 | E82: =IF('Quality-Stat'!F33="","",'Quality-Stat'!F33) -> 42 | F82: =IF('Quality-Stat'!G33="","",'Quality-Stat'!G33) -> 0 | G82: =IF('Quality-Stat'!H33="","",'Quality-Stat'!H33) -> 21 | H82: =IF('Quality-Stat'!I33="","",'Quality-Stat'!I33) -> 27 | I82: ='Quality-Stat'!J33 -> 46293 | L82: Head Count - Non Manual | P82: Head Count - Manual | T82: Total Head Count | W82: =CCO!A3 -> 0 | X82: =CCO!B3 -> 0 | Y82: =CCO!C3 -> 0 | AD82: =CCO!D3 -> 0 | AE82: =CCO!E3 -> 0 | AF82: =CCO!F3 -> 0 | AG82: =CCO!G3 -> 0 | AH82: =CCO!H3 -> 0
L83: Planned | M83: Actual | N83: Next Month Forecast | O83: Saudi Staff | P83: Planned | Q83: Actual | R83: Next Month Forecast | S83: Saudi Staff | T83: Total Plan | U83: Total Actual | V83: Variance
L84: =Manpower!A20 -> 35 | M84: =Manpower!B20 -> 57 | N84: =Manpower!F20 -> 165 | O84: 4 | P84: =M94 -> 360 | Q84: =N94 -> 483 | R84: =Manpower!F24 -> 560 | S84: =Manpower!H24 -> 0 | T84: =L84+P84 -> 395 | U84: =M84+Q84 -> 540 | V84: =+U84-T84 -> 145 | W84: =CCO!A4 | X84: =CCO!B4 | Y84: =CCO!C4 | AD84: =IF(CCO!D4="","",CCO!D4) | AE84: =CCO!E4 | AF84: =CCO!F4 | AG84: =CCO!G4 | AH84: =CCO!H4
A85: TOTAL | C85: =IF('Quality-Stat'!D33="","",'Quality-Stat'!D33) -> 48 | D85: =IF('Quality-Stat'!E33="","",'Quality-Stat'!E33) -> 48 | E85: =IF('Quality-Stat'!F33="","",'Quality-Stat'!F33) -> 42 | F85: =IF('Quality-Stat'!G33="","",'Quality-Stat'!G33) -> 0 | G85: =IF('Quality-Stat'!H33="","",'Quality-Stat'!H33) -> 21 | H85: =IF('Quality-Stat'!I33="","",'Quality-Stat'!I33) -> 27 | I85: =MAX(I80:I84) -> 46335 | L85: Manpower Breakdown by Trade | S85: Major Equipment
A86: =Schedule!A1 -> Primavera P6 Schedule Status | L86: Key Trade | M86: Planned | N86: Actual | S86: Type | T86: Planned | U86: Actual | V86: Idle | W86: =CCO!A5 | X86: =CCO!B5 | Y86: =CCO!C5 | AD86: =IF(CCO!D5="","",CCO!D5) | AE86: =CCO!E5 | AF86: =CCO!F5 | AG86: =CCO!G5 | AH86: =CCO!H5
A87: =Schedule!A2 -> Project Activities Overview | L87: =+Manpower!N23 -> General Labor | M87: =Manpower!N24 -> 120 | N87: =Manpower!N25 -> 119 | S87: =+Manpower!$B$49 -> Excavator | T87: =+Manpower!B50 -> 22 | U87: =+Manpower!B51 -> 23 | V87: =+Manpower!B52 -> 0
A88: =Schedule!A3 -> Schedule Statistics | F88: =Schedule!F3 -> Active Schedule Activities | L88: =+Manpower!P23 -> Carpenter | M88: =Manpower!P24 -> 15 | N88: =Manpower!P25 -> 68 | S88: =+Manpower!$D$49 -> Loader | T88: =+Manpower!D50 -> 8 | U88: =+Manpower!D51 -> 13 | V88: =+Manpower!D52 -> 0 | W88: Major Quantity Trackers
A89: =Schedule!A4 -> Total Act. | B89: =Schedule!B4 -> Not Started | C89: =Schedule!C4 -> In Progress | D89: =Schedule!D4 -> Completed | E89: =Schedule!E4 -> % | F89: =Schedule!F4 -> Active | G89: =Schedule!G4 -> Ahead | H89: =Schedule!H4 -> On | ... K89: =Schedule!K4 -> 0 | L89: =+Manpower!R23 -> Plumber | M89: =+Manpower!R24 -> 16 | N89: =Manpower!R25 -> 33 | S89: =+Manpower!$F$49 -> W.Tanker | T89: =+Manpower!F50 -> 14 | U89: =+Manpower!F51 -> 18 | V89: =+Manpower!F52 -> 0 | W89: BOQ N0. | X89: Item Description | AC89: Total Qty | AD89: Measu Unit | AE89: Plan to Date | AF89: Act to Date | AG89: Remaining | AH89: Variance
A90: =Schedule!A5 -> 4851 | B90: =Schedule!B5 -> 2454 | C90: =Schedule!C5 -> 157 | D90: =Schedule!D5 -> 2240 | E90: =Schedule!E5 -> 0.46176046 | F90: =Schedule!F5 -> 157 | G90: =Schedule!G5 -> 9 | H90: =Schedule!H5 -> 1419 | ... J90: =Schedule!J5 -> 1309 | L90: =+Manpower!T23 -> Operator | M90: =Manpower!T24 -> 125 | N90: =Manpower!T25 -> 237 | S90: =+Manpower!$H$49 -> Dumper | T90: =+Manpower!H50 -> 28 | U90: =+Manpower!H51 -> 163 | V90: =+Manpower!H52 -> 0 | W90: ='Major Quantities'!A2 -> B1.1.31 23 19.01 | X90: ='Major Quantities'!B2 -> Surface Dewatering | AC90: =VLOOKUP(X90,'Major Quantities'!$B$2:$G$22,2,FALSE) -> 1 | AD90: =VLOOKUP(X90,'Major Quantities'!$B$2:$G$22,3,FALSE) -> Unit | AE90: =VLOOKUP(X90,'Major Quantities'!$B$2:$G$22,4,FALSE) -> 1 | AF90: =VLOOKUP(X90,'Major Quantities'!$B$2:$G$22,5,FALSE) -> 1 | AG90: =VLOOKUP(X90,'Major Quantities'!$B$2:$G$22,6,FALSE) -> 0 | AH90: =VLOOKUP(X90,'Major Quantities'!$B$2:$H$22,7,FALSE) -> 0
A91: =Schedule!A6 -> Critical Path Activities | D91: =Schedule!D6 -> Free Float Management (Total) | H91: =Schedule!H6 -> Failed Start Activities | L91: =+Manpower!W23 -> Surveyor | M91: =Manpower!W24 -> 14 | N91: =Manpower!W25 -> 9 | S91: =+Manpower!$J$49 -> Dozer | T91: =+Manpower!J50 -> 8 | U91: =+Manpower!J51 -> 10 | V91: =+Manpower!J52 -> 0 | W91: ='Major Quantities'!A3 -> B1.1.31 23 16.01 | X91: ='Major Quantities'!B3 -> All Excavation | AC91: =VLOOKUP(X91,'Major Quantities'!$B$2:$G$22,2,FALSE) -> 853395 | AD91: =VLOOKUP(X91,'Major Quantities'!$B$2:$G$22,3,FALSE) -> m³ | AE91: =VLOOKUP(X91,'Major Quantities'!$B$2:$G$22,4,FALSE) -> 853395 | AF91: =VLOOKUP(X91,'Major Quantities'!$B$2:$G$22,5,FALSE) -> 825820.73 | AG91: =VLOOKUP(X91,'Major Quantities'!$B$2:$G$22,6,FALSE) -> 27574.27 | AH91: =VLOOKUP(X91,'Major Quantities'!$B$2:$H$22,7,FALSE) -> -27574.27
D92: =Schedule!D7 -> Greater Than 14 Days | F92: =Schedule!F7 -> Less Than 14 Days | L92: =+Manpower!X23 -> Others | M92: =Manpower!X24 -> 70 | N92: =Manpower!X25 -> 17 | S92: =+Manpower!$L$49 -> Grader | T92: =+Manpower!L50 -> 8 | U92: =+Manpower!L51 -> 8 | V92: =+Manpower!L52 -> 0 | W92: ='Major Quantities'!A4 -> B1.1.31 23 23.01 | X92: ='Major Quantities'!B4 -> All Backfilling | AC92: =VLOOKUP(X92,'Major Quantities'!$B$2:$G$22,2,FALSE) -> 1481028 | AD92: =VLOOKUP(X92,'Major Quantities'!$B$2:$G$22,3,FALSE) -> m³ | AE92: =VLOOKUP(X92,'Major Quantities'!$B$2:$G$22,4,FALSE) -> 1481028 | AF92: =VLOOKUP(X92,'Major Quantities'!$B$2:$G$22,5,FALSE) -> 1341040.3 | AG92: =VLOOKUP(X92,'Major Quantities'!$B$2:$G$22,6,FALSE) -> 139987.75 | AH92: =VLOOKUP(X92,'Major Quantities'!$B$2:$H$22,7,FALSE) -> -139987.75
A93: =Schedule!A8 -> Last Week | B93: =Schedule!B8 -> This Week | C93: =Schedule!C8 -> Diff | D93: =Schedule!D8 -> Last Week | E93: =Schedule!E8 -> This Week | F93: =Schedule!F8 -> Last Week | G93: =Schedule!G8 -> This Week | H93: =Schedule!H8 -> Last Week | ... K93: =Schedule!K8 -> 0 | S93: =+Manpower!$N$49 -> Other | T93: =+Manpower!N50 -> 62 | U93: =+Manpower!N51 -> 91 | V93: =+Manpower!N52 -> 0 | W93: ='Major Quantities'!A5 -> B1.2.32 11 26.01 | X93: ='Major Quantities'!B5 -> Asphalt (Base+Wearing) | AC93: =VLOOKUP(X93,'Major Quantities'!$B$2:$G$22,2,FALSE) -> 64334 | AD93: =VLOOKUP(X93,'Major Quantities'!$B$2:$G$22,3,FALSE) -> m³ | AE93: =VLOOKUP(X93,'Major Quantities'!$B$2:$G$22,4,FALSE) -> 45507.96 | AF93: =VLOOKUP(X93,'Major Quantities'!$B$2:$G$22,5,FALSE) -> 21675.67 | AG93: =VLOOKUP(X93,'Major Quantities'!$B$2:$G$22,6,FALSE) -> 42658.33 | AH93: =VLOOKUP(X93,'Major Quantities'!$B$2:$H$22,7,FALSE) -> -23832.29
A94: =Schedule!A9 -> 129 | B94: =Schedule!B9 -> 45 | C94: =Schedule!C9 -> 84 | D94: =Schedule!D9 -> 928 | E94: =Schedule!E9 -> 327 | F94: =Schedule!F9 -> 1734 | G94: =Schedule!G9 -> 2279 | H94: =Schedule!H9 -> 1796 | ... J94: =Schedule!J9 -> 644 | L94: Total | M94: =SUM(M87:M93) -> 360 | N94: =SUM(N87:N93) -> 483 | S94: Total | T94: =SUM(T87:T93) -> 150 | U94: =SUM(U87:U93) -> 326 | V94: =SUM(V87:V93) -> 0 | W94: ='Major Quantities'!A6 -> 33 31 00 | X94: ='Major Quantities'!B6 -> Sew. Pipes | AC94: =VLOOKUP(X94,'Major Quantities'!$B$2:$G$22,2,FALSE) -> 7567.08 | AD94: =VLOOKUP(X94,'Major Quantities'!$B$2:$G$22,3,FALSE) -> Lm | AE94: =VLOOKUP(X94,'Major Quantities'!$B$2:$G$22,4,FALSE) -> 1.89 | AF94: =VLOOKUP(X94,'Major Quantities'!$B$2:$G$22,5,FALSE) -> 5484.35 | AG94: =VLOOKUP(X94,'Major Quantities'!$B$2:$G$22,6,FALSE) -> 2082.73 | AH94: =VLOOKUP(X94,'Major Quantities'!$B$2:$H$22,7,FALSE) -> 5482.46
A95: Weekly Prgoress Photos | Q95: Top Issues and Risks
A96: ='Weekly Photos'!B4 -> Road & Plots Works | F96: ='Weekly Photos'!B23 -> Electrical Networks (Street Lighting Installations, Telecom Ductbank, MV Cable Excavation) | I96: ='Weekly Photos'!I23 -> Pump & Lift Station | L96: ='Weekly Photos'!L4 -> Wet Networks | Q96: Top 5 Issues
Q97: Issue No | R97: Date Identified | S97: Issue Description | W97: Responsible | X97: Action Taken | AA97: Mitigation | AF97: Current Status | AG97: Expected/Actual Closure | AH97: Duration Elapsed
Q98: =IF(+Issues!B11="","",+Issues!B11) -> 1 | R98: =IF(+Issues!C11="","",+Issues!C11) -> 46113 | S98: =IF(+Issues!D11="","",+Issues!D11) -> قلة عدد العمالة والمعدات و توقف مقاول الباطن | W98: =IF(+Issues!E11="","",+Issues!E11) -> Contractor | X98: =Issues!F11 -> جاري اسناد جزء من المشروع لمقاول آخر و جاري توفير عمالة من الشركة لاستكمال الاعمال المتبقية حيث ان عدد العمالة الحالي 304 والمعدات 184 معدة والمضخات الى 30 مضخة نزح ,و وجوب استمرار زيادة العمالة والمعدات لتحقيق مستهدفات مدن | AF98: =IF(+Issues!H11="","",+Issues!H11) -> Open | AG98: =IF(+Issues!I11="","",+Issues!I11) -> 46143 | AH98: =IF(+Issues!J11="","",+Issues!J11) -> 188
Q99: =IF(+Issues!B12="","",+Issues!B12) -> 2 | R99: =IF(+Issues!C12="","",+Issues!C12) -> 46174 | S99: =IF(+Issues!D12="","",+Issues!D12) -> تأخر أعمال العبارة بالطريق الشرياني | W99: =IF(+Issues!E12="","",+Issues!E12) -> Contractor | X99: =Issues!F12 -> جاري الانتهاء من الحدادة ل 16 فواصل وصب قاعدة لعدد 03 فاصل تم حفر 14 و جاري 03 فواصل أخرى | AF99: =IF(+Issues!H12="","",+Issues!H12) -> Open | AG99: =IF(+Issues!I12="","",+Issues!I12) -> 46204 | AH99: =IF(+Issues!J12="","",+Issues!J12) -> 127
Q100: =IF(+Issues!B13="","",+Issues!B13) -> 3 | R100: =IF(+Issues!C13="","",+Issues!C13) -> 46174 | S100: =IF(+Issues!D13="","",+Issues!D13) -> ضرورة الانتهاء من تنفيذ الشبكات لتحقيق جاهزية الموقع وبدء أعمال الطرق | W100: =IF(+Issues!E13="","",+Issues!E13) -> Other | X100: =Issues!F13 -> تم استبعاد مقاول الباطن يوناسكو و سحب اعتماده لعدم وفاءه بمستهدفات مدن و على المقاول العمل بشكل مباشر على الشبكات او تقديم مقاول باطن للاعتماد | AF100: =IF(+Issues!H13="","",+Issues!H13) -> Open | AG100: =IF(+Issues!I13="","",+Issues!I13) -> 46204 | AH100: =IF(+Issues!J13="","",+Issues!J13) -> 127
Q101: =IF(+Issues!B14="","",+Issues!B14) -> 4 | R101: =IF(+Issues!C14="","",+Issues!C14) | S101: =IF(+Issues!D14="","",+Issues!D14) | W101: =IF(+Issues!E14="","",+Issues!E14) | X101: =Issues!F14 -> 0 | AF101: =IF(+Issues!H14="","",+Issues!H14) | AG101: =IF(+Issues!I14="","",+Issues!I14) | AH101: =IF(+Issues!J14="","",+Issues!J14)
Q102: =IF(+Issues!B15="","",+Issues!B15) -> 5 | R102: =IF(+Issues!C15="","",+Issues!C15) | S102: =IF(+Issues!D15="","",+Issues!D15) | W102: =IF(+Issues!E15="","",+Issues!E15) | X102: =Issues!F15 -> 0 | AF102: =IF(+Issues!H15="","",+Issues!H15) | AG102: =IF(+Issues!I15="","",+Issues!I15) | AH102: =IF(+Issues!J15="","",+Issues!J15)

Sheet General Information
A1: Weekly Progress Report - Construction Projects | K1: Data Date | L1: 46301 | N1: =L1+7 -> 46308
A2: Contract General Information
A3: Project Name | C3: Development of Infrastructure for phase 1 of the Logistics area at the 2nd Industrial City in Dammam
A4: Project ID | C4: DAM2-02-009
A5: Contractor | C5: Shibh Aljazira Contracting Company
A6: Consultant | C6: Egis
A7: Stage | C7: Construction
A8: Status | C8: Active
A9: Modon PM | C9: Muhammad H Al-Essa
A11: Key Dates
A12: Contract Award Date | C12: =Milestones!C4 -> 45838
A13: Contract Sign Date | C13: =Milestones!C5 -> 45852
A14: Site Handover Date | C14: =Milestones!C6 -> 45868
A15: Original Completion | C15: =Milestones!C15 -> 46416
A16: Contract Award Date (Hijri) | C16: =C12 -> 45838
A17: Contract Sign Date (Hijri) | C17: =C13 -> 45852
A18: Site Handover Date (Hijri) | C18: =C14 -> 45868
A19: Original Completion (Hijri) | C19: =C15 -> 46416
A20: Revised Completion Date | C20: =Milestones!D15 -> 46416
A21: Committed Completion Date | C21: =Milestones!D15 -> 46416
A22: Forecast Completion | C22: =Milestones!E13 -> 46418
A23: Variance | C23: =C20-C22 -> -2
A25: Key Project Submittals | C25: Submission Date | D25: Days taken to approve orginal plan from site handover date
A26: Quality Plan submission | C26: 45344 | D26: =C26-C14 -> -524
A27: Quality Plan approval | C27: 45346
A28: Quality Plan Last Update | C28: 45346
A30: Safety Plan submission | C30: 45345 | D30: =C30-C14 -> -523
A31: Safety Plan approval | C31: 45350
A32: Safety Plan Last Update | C32: 45350
A34: Risk Management Plan submission | C34: 45345 | D34: =C34-C14 -> -523
A35: Risk Management Plan approval | C35: 45350
A36: Risk Management Plan Last Update | C36: 45350
A38: Baseline Schedule submission | C38: 45334 | D38: =C38-C14 -> -534
A39: Baseline Schedule approval | C39: 45361
A40: No of Schedule Versions | C40: 1
A41: Last Recovery Schedule Approval Date | C41: 45361
A43: BOQ submission | D43: =C43-C19 -> -46416
A44: BOQ approval
A45: No of Approved Version of BOQ | C45: 1
A47: Construction Plan submission | C47: 45346 | D47: =C47-C14 -> -522
A48: Construction Plan Approval | C48: 45348

Sheet Progress
A1: Project Scope Statement | B1: The project consists of the wet networks mainlines (Sewerage, Storm, Potable, Firefighting & TSE) including the force main line, in addition to the dry networks (Medium Voltage, Low Voltage, Street Lighting & Telecommunication) road crossings & main line connections, scope also included supply, install, testing & commissioning for the potable water pump station and the sewage lift station and implementation of guard rooms and applying all the road earth layers till the asphalt wearing coarse for the project scope area internal roads & finishing the landscape | S1: ='General Information'!$K$1 -> Data Date | T1: ='General Information'!L1 -> 46301
A4: Earned Value Progress (SAR) | K4: Physical Progress (Effort)
A5: WBS | C5: BOQ Value (SAR) | D5: % Wt. | E5: Weekly (SAR) | H5: To Date (SAR) | K5: Budgeted | L5: % Wt. | M5: Weekly Physical Progress | O5: To Date Physical Progress
E6: Planned | F6: Earned | G6: Original Plan | H6: Planned | I6: Earned | K6: (Manhours) | M6: Planned | N6: Earned | O6: Planned | P6: Earned
A7: =K88 -> Demolishing & Site Clearing | C7: =M88 -> 457401.18 | D7: =IF(ISBLANK(C7),"",C7/$C$78) -> 0.0022995827 | E7: =N88-W88 -> 457401.18 | F7: =O88-X88 -> 136666.96 | G7: =HLOOKUP('General Information'!$L$1,Progress!$T$160:$UV$232,ROW()-4,FALSE) -> 457401.18 | H7: =N88 -> 457401.18 | I7: =O88 -> 457401.18 | K7: =P88 -> 3437.41 | L7: =IF(ISBLANK(K7),"",K7/$K$78) -> 0.0037353813 | M7: =Q88-Z88 -> 3437.41 | N7: =R88-AA88 -> -442.59 | O7: =Q88 -> 3437.41 | P7: =R88 -> 3437.41
A8: =K89 -> Earthworks & Site Grading | C8: =M89 -> 31040592 | D8: =IF(ISBLANK(C8),"",C8/$C$78) -> 0.15605646 | E8: =N89-W89 -> -21385797 | F8: =O89-X89 -> -22502335 | G8: =HLOOKUP('General Information'!$L$1,Progress!$T$160:$UV$232,ROW()-4,FALSE) -> 31040592 | H8: =N89 -> 31040592 | I8: =O89 -> 29924053 | K8: =P89 -> 22808.8 | L8: =IF(ISBLANK(K8),"",K8/$K$78) -> 0.024785977 | M8: =Q89-Z89 -> -45319.2 | N8: =R89-AA89 -> -24484.41 | O8: =Q89 -> 22808.8 | P8: =R89 -> 21945.45
A9: =K90 -> Sewerage Network | C9: =M90 -> 5111121.8 | D9: =IF(ISBLANK(C9),"",C9/$C$78) -> 0.025696146 | E9: =N90-W90 -> 1624385 | F9: =O90-X90 -> -557865.16 | G9: =HLOOKUP('General Information'!$L$1,Progress!$T$160:$UV$232,ROW()-4,FALSE) -> 4977488.4 | H9: =N90 -> 4977488.4 | I9: =O90 -> 4189784.5 | K9: =P90 -> 74260.44 | L9: =IF(ISBLANK(K9),"",K9/$K$78) -> 0.080697694 | M9: =Q90-Z90 -> -6577.61 | N9: =R90-AA90 -> -4703.31 | O9: =Q90 -> 61270.39 | P9: =R90 -> 53207.64
A10: =K91 -> Engineering | C10: =M91 -> 0 | D10: =IF(ISBLANK(C10),"",C10/$C$78) -> 0 | E10: =N91-W91 -> -164912.76 | F10: =O91-X91 -> -164912.76 | G10: =HLOOKUP('General Information'!$L$1,Progress!$T$160:$UV$232,ROW()-4,FALSE) -> 0 | H10: =N91 -> 0 | I10: =O91 -> 0 | K10: =P91 -> 568.6 | L10: =IF(ISBLANK(K10),"",K10/$K$78) -> 0.000617889 | M10: =Q91-Z91 -> 568.6 | N10: =R91-AA91 -> 568.6 | O10: =Q91 -> 568.6 | P10: =R91 -> 568.6
A11: =K92 -> Procurement | C11: =M92 -> 0 | D11: =IF(ISBLANK(C11),"",C11/$C$78) -> 0 | E11: =N92-W92 -> -1088658.6 | F11: =O92-X92 -> -1074742.6 | G11: =HLOOKUP('General Information'!$L$1,Progress!$T$160:$UV$232,ROW()-4,FALSE) -> 0 | H11: =N92 -> 0 | I11: =O92 -> 0 | K11: =P92 -> 10403.33 | L11: =IF(ISBLANK(K11),"",K11/$K$78) -> 0.011305141 | M11: =Q92-Z92 -> 641.94 | N11: =R92-AA92 -> 1082.73 | O11: =Q92 -> 10209.94 | P11: =R92 -> 8522.73
A12: =K93 -> Construction | C12: =M93 -> 5111121.8 | D12: =IF(ISBLANK(C12),"",C12/$C$78) -> 0.025696146 | E12: =N93-W93 -> 2877956.3 | F12: =O93-X93 -> 681790.21 | G12: =HLOOKUP('General Information'!$L$1,Progress!$T$160:$UV$232,ROW()-4,FALSE) -> 4977488.4 | H12: =N93 -> 4977488.4 | I12: =O93 -> 4189784.5 | K12: =P93 -> 53551.26 | L12: =IF(ISBLANK(K12),"",K12/$K$78) -> 0.058193342 | M12: =Q93-Z93 -> -7788.15 | N12: =R93-AA93 -> -12846.14 | O12: =Q93 -> 50491.85 | P12: =R93 -> 37624.81
A13: =K94 -> Testing & Commissioning | C13: =M94 -> 0 | D13: =IF(ISBLANK(C13),"",C13/$C$78) -> 0 | E13: =N94-W94 -> 0 | F13: =O94-X94 -> 0 | G13: =HLOOKUP('General Information'!$L$1,Progress!$T$160:$UV$232,ROW()-4,FALSE) -> 0 | H13: =N94 -> 0 | I13: =O94 -> 0 | K13: =P94 -> 9737.25 | L13: =IF(ISBLANK(K13),"",K13/$K$78) -> 0.010581322 | M13: =Q94-Z94 -> 0 | N13: =R94-AA94 -> 6491.5 | O13: =Q94 -> 0 | P13: =R94 -> 6491.5
A14: =K95 -> Storm Water Network | C14: =M95 -> 21808728 | D14: =IF(ISBLANK(C14),"",C14/$C$78) -> 0.1096433 | E14: =N95-W95 -> 2413306.5 | F14: =O95-X95 -> -87002.14 | G14: =HLOOKUP('General Information'!$L$1,Progress!$T$160:$UV$232,ROW()-4,FALSE) -> 20044696 | H14: =N95 -> 20044696 | I14: =O95 -> 18078712 | K14: =P95 -> 143781.21 | L14: =IF(ISBLANK(K14),"",K14/$K$78) -> 0.15624486 | M14: =Q95-Z95 -> -17378.91 | N14: =R95-AA95 -> -4682.1 | O14: =Q95 -> 122269.09 | P14: =R95 -> 112215.05
A15: =K96 -> Engineering | C15: =M96 -> 0 | D15: =IF(ISBLANK(C15),"",C15/$C$78) -> 0 | E15: =N96-W96 -> -468720.89 | F15: =O96-X96 -> -468720.89 | G15: =HLOOKUP('General Information'!$L$1,Progress!$T$160:$UV$232,ROW()-4,FALSE) -> 0 | H15: =N96 -> 0 | I15: =O96 -> 0 | K15: =P96 -> 984.12 | L15: =IF(ISBLANK(K15),"",K15/$K$78) -> 0.0010694283 | M15: =Q96-Z96 -> 984.12 | N15: =R96-AA96 -> 984.12 | O15: =Q96 -> 984.12 | P15: =R96 -> 984.12
A16: =K97 -> Procurement | C16: =M97 -> 0 | D16: =IF(ISBLANK(C16),"",C16/$C$78) -> 0 | E16: =N97-W97 -> -3131749.8 | F16: =O97-X97 -> -3049254.2 | G16: =HLOOKUP('General Information'!$L$1,Progress!$T$160:$UV$232,ROW()-4,FALSE) -> 0 | H16: =N97 -> 0 | I16: =O97 -> 0 | K16: =P97 -> 14474.2 | L16: =IF(ISBLANK(K16),"",K16/$K$78) -> 0.015728894 | M16: =Q97-Z97 -> 903.41 | N16: =R97-AA97 -> 2620.65 | O16: =Q97 -> 14439.41 | P16: =R97 -> 13952.76
A17: =K98 -> Construction | C17: =M98 -> 21808728 | D17: =IF(ISBLANK(C17),"",C17/$C$78) -> 0.1096433 | E17: =N98-W98 -> 6013777.2 | F17: =O98-X98 -> 3430972.9 | G17: =HLOOKUP('General Information'!$L$1,Progress!$T$160:$UV$232,ROW()-4,FALSE) -> 20044696 | H17: =N98 -> 20044696 | I17: =O98 -> 18078712 | K17: =P98 -> 118164.9 | L17: =IF(ISBLANK(K17),"",K17/$K$78) -> 0.12840801 | M17: =Q98-Z98 -> -19266.43 | N17: =R98-AA98 -> -14778.36 | O17: =Q98 -> 106845.57 | P17: =R98 -> 90786.68
A18: =K99 -> Testing & Commissioning | C18: =M99 -> 0 | D18: =IF(ISBLANK(C18),"",C18/$C$78) -> 0 | E18: =N99-W99 -> 0 | F18: =O99-X99 -> 0 | G18: =HLOOKUP('General Information'!$L$1,Progress!$T$160:$UV$232,ROW()-4,FALSE) -> 0 | H18: =N99 -> 0 | I18: =O99 -> 0 | K18: =P99 -> 10157.99 | L18: =IF(ISBLANK(K18),"",K18/$K$78) -> 0.011038534 | M18: =Q99-Z99 -> 0 | N18: =R99-AA99 -> 6491.5 | O18: =Q99 -> 0 | P18: =R99 -> 6491.5
... A75: =K156 -> Construction | C75: =M156 -> 539598.47 | D75: =IF(ISBLANK(C75),"",C75/$C$78) -> 0.0027128293 | E75: =N156-W156 -> -420202.71 | F75: =O156-X156 -> -2388.05 | G75: =HLOOKUP('General Information'!$L$1,Progress!$T$160:$UV$232,ROW()-4,FALSE) -> 92935.49 | H75: =N156 -> 92935.49 | I75: =O156 -> 41745.84 | K75: =P156 -> 6017.94 | L75: =IF(ISBLANK(K75),"",K75/$K$78) -> 0.0065396042 | M75: =Q156-Z156 -> -4342.72 | N75: =R156-AA156 -> -255.33 | O75: =Q156 -> 2065.28 | P75: =R156 -> 864.67
A76: =K157 -> Provisional Sum | C76: =M157 -> 192900.72 | D76: =IF(ISBLANK(C76),"",C76/$C$78) -> 0.00096980766 | E76: =N157-W157 -> 0 | F76: =O157-X157 -> 0 | G76: =HLOOKUP('General Information'!$L$1,Progress!$T$160:$UV$232,ROW()-4,FALSE) -> 0 | H76: =N157 -> 0 | I76: =O157 -> 0
A77: =K158 -> Closeout | C77: =M158 -> 0 | D77: =IF(ISBLANK(C77),"",C77/$C$78) -> 0 | E77: =N158-W158 -> 0 | F77: =O158-X158 -> 0 | G77: =HLOOKUP('General Information'!$L$1,Progress!$T$160:$UV$232,ROW()-4,FALSE) -> 0 | H77: =N158 -> 0 | I77: =O158 -> 0 | K77: =P158 -> 0 | L77: =IF(ISBLANK(K77),"",K77/$K$78) -> 0 | M77: =Q158-Z158 -> 0 | N77: =R158-AA158 -> 0 | O77: =Q158 -> 0 | P77: =R158 -> 0
B78: Total | C78: =C7+C9+C14+C44+C49+C64+C8+C19+C24+C29+C34+C39+C54+C59+C68+C72+C76 -> 1.9890616e+08 | D78: =D7+D9+D14+D44+D49+D64+D8+D19+D24+D29+D34+D39+D54+D59+D68+D72 -> 0.99903019 | E78: =E7+E8+E9+E14+E19+E24+E29+E34+E39+E44+E49+E54+E59+E64+E68+E72+E77+E76 -> -27037643 | F78: =F7+F8+F9+F14+F19+F24+F29+F34+F39+F44+F49+F54+F59+F64+F68+F72+F77+F76 -> -17134541 | G78: =G7+G8+G9+G14+G19+G24+G29+G34+G39+G44+G49+G54+G59+G64+G68+G72+G77+G76 -> 1.4385991e+08 | H78: =H7+H8+H9+H14+H19+H24+H29+H34+H39+H44+H49+H54+H59+H64+H68+H72+H77+H76 -> 1.4385991e+08 | I78: =I7+I8+I9+I14+I19+I24+I29+I34+I39+I44+I49+I54+I59+I64+I68+I72+I77+I76 -> 1.0241594e+08 | K78: =K7+K8+K9+K14+K19+K24+K29+K34+K39+K44+K49+K54+K59+K64+K68+K72+K77+K76 -> 920230.01 | L78: =L7+L9+L14+L44+L49+L64+L8+L19+L24+L29+L34+L39+L54+L59+L68+L72+L77 -> 1 | M78: =M7+M8+M9+M14+M19+M24+M29+M34+M39+M44+M49+M54+M59+M64+M68+M72+M77+M76 -> -283066.05 | N78: =N7+N8+N9+N14+N19+N24+N29+N34+N39+N44+N49+N54+N59+N64+N68+N72+N77+N76 -> -17241.13 | O78: =O7+O8+O9+O14+O19+O24+O29+O34+O39+O44+O49+O54+O59+O64+O68+O72+O77+O76 -> 560205.95 | P78: =P7+P8+P9+P14+P19+P24+P29+P34+P39+P44+P49+P54+P59+P64+P68+P72+P77+P76 -> 390858.82
E79: =E78/$C$78 -> -0.13593165 | F79: =F78/$C$78 -> -0.086143842 | G79: =G78/$C$78 -> 0.72325518 | H79: =H78/$C$78 -> 0.72325518 | I79: =I78/$C$78 -> 0.51489574 | M79: =M78/$K$78 -> -0.30760358 | N79: =N78/$K$78 -> -0.018735675 | O79: =O78/$K$78 -> 0.60876731 | P79: =P78/$K$78 -> 0.42474035
H82: =IF(G79=H79,"OK","") -> OK
M83: `
K87: Activity ID | L87: Activity Name | M87: Budgeted Total Cost | N87: Planned Value Cost | O87: Earned Value Cost | P87: Budgeted Labor Units | Q87: Planned Value Labor Units | R87: Earned Value Labor Units | T87: Activity ID | U87: Activity Name | V87: Budgeted Total Cost | W87: Planned Value Cost | X87: Earned Value Cost | Y87: Budgeted Labor Units | Z87: Planned Value Labor Units | AA87: Earned Value Labor Units
K88: Demolishing & Site Clearing | M88: 457401.18 | N88: 457401.18 | O88: 457401.18 | P88: 3437.41 | Q88: 3437.41 | R88: 3437.41 | T88: Demolishing & Site Clearing | V88: 320734.22 | W88: 0 | X88: 320734.22 | Y88: 3880 | Z88: 0 | AA88: 3880 | AE88: 0.70274435 | AF88: =Q88*AE88*1.1 -> 2657.1825
K89: Earthworks & Site Grading | M89: 31040592 | N89: 31040592 | O89: 29924053 | P89: 22808.8 | Q89: 22808.8 | R89: 21945.45 | T89: Earthworks & Site Grading | V89: 52426388 | W89: 52426388 | X89: 52426388 | Y89: 80728 | Z89: 68128 | AA89: 46429.86 | AE89: 0.71274435 | AF89: =Q89*AE89*1.1 -> 17882.528
K90: Sewerage Network | M90: 5111121.8 | N90: 4977488.4 | O90: 4189784.5 | P90: 74260.44 | Q90: 61270.39 | R90: 53207.64 | T90: Sewerage Network | V90: 5475079.4 | W90: 3353103.5 | X90: 4747649.6 | Y90: 69144 | Z90: 67848 | AA90: 57910.95 | AE90: 0.72274435 | AF90: =Q90*AE90*1.1 -> 48711.111
K91: Engineering | M91: 0 | N91: 0 | O91: 0 | P91: 568.6 | Q91: 568.6 | R91: 568.6 | T91: Engineering | V91: 164912.76 | W91: 164912.76 | X91: 164912.76 | Y91: 0 | Z91: 0 | AA91: 0 | AE91: 0.73274435 | AF91: =Q91*AE91*1.1 -> 458.30228
K92: Procurement | M92: 0 | N92: 0 | O92: 0 | P92: 10403.33 | Q92: 10209.94 | R92: 8522.73 | T92: Procurement | V92: 1088658.6 | W92: 1088658.6 | X92: 1074742.6 | Y92: 9568 | Z92: 9568 | AA92: 7440 | AE92: 0.74274435 | AF92: =Q92*AE92*1.1 -> 8341.7128
K93: Construction | M93: 5111121.8 | N93: 4977488.4 | O93: 4189784.5 | P93: 53551.26 | Q93: 50491.85 | R93: 37624.81 | T93: Construction | V93: 3963051 | W93: 2099532.1 | X93: 3507994.2 | Y93: 59240 | Z93: 58280 | AA93: 50470.95 | AE93: 0.75274435 | AF93: =Q93*AE93*1.1 -> 41808.201
K94: Testing & Commissioning | M94: 0 | N94: 0 | O94: 0 | P94: 9737.25 | Q94: 0 | R94: 6491.5 | T94: Testing & Commissioning | V94: 258457.05 | W94: 0 | X94: 0 | Y94: 336 | Z94: 0 | AA94: 0 | AE94: 0.76274435 | AF94: =Q94*AE94*1.1 -> 0
K95: Storm Water Network | M95: 21808728 | N95: 20044696 | O95: 18078712 | P95: 143781.21 | Q95: 122269.09 | R95: 112215.05 | T95: Storm Water Network | V95: 23737475 | W95: 17631389 | X95: 18165714 | Y95: 141000 | Z95: 139648 | AA95: 116897.15 | AE95: 0.77274435 | AF95: =Q95*AE95*1.1 -> 103931.02
K96: Engineering | M96: 0 | N96: 0 | O96: 0 | P96: 984.12 | Q96: 984.12 | R96: 984.12 | T96: Engineering | V96: 468720.89 | W96: 468720.89 | X96: 468720.89 | Y96: 0 | Z96: 0 | AA96: 0 | AE96: 0.78274435 | AF96: =Q96*AE96*1.1 -> 847.34581
K97: Procurement | M97: 0 | N97: 0 | O97: 0 | P97: 14474.2 | Q97: 14439.41 | R97: 13952.76 | T97: Procurement | V97: 3131749.8 | W97: 3131749.8 | X97: 3049254.2 | Y97: 13536 | Z97: 13536 | AA97: 11332.11 | AE97: 0.79274435 | AF97: =Q97*AE97*1.1 -> 12591.437
K98: Construction | M98: 21808728 | N98: 20044696 | O98: 18078712 | P98: 118164.9 | Q98: 106845.57 | R98: 90786.68 | T98: Construction | V98: 16840556 | W98: 14030918 | X98: 14647739 | Y98: 127072 | Z98: 126112 | AA98: 105565.04 | AE98: 0.80274435 | AF98: =Q98*AE98*1.1 -> 94346.646
K99: Testing & Commissioning | M99: 0 | N99: 0 | O99: 0 | P99: 10157.99 | Q99: 0 | R99: 6491.5 | T99: Testing & Commissioning | V99: 3296447.5 | W99: 0 | X99: 0 | Y99: 392 | Z99: 0 | AA99: 0 | AE99: 0.81274435 | AF99: =Q99*AE99*1.1 -> 0
... K156: Construction | M156: 539598.47 | N156: 92935.49 | O156: 41745.84 | P156: 6017.94 | Q156: 2065.28 | R156: 864.67 | T156: Construction | V156: 513138.2 | W156: 513138.2 | X156: 44133.89 | Y156: 6408 | Z156: 6408 | AA156: 1120 | AE156: 0.88274435 | AF156: =Q156*AE156*1.1 -> 2005.4257
K157: Provisional Sum | M157: 192900.72 | N157: 0 | O157: 0 | P157: 0 | Q157: 0 | R157: 0
K158: Closeout | M158: 0 | N158: 0 | O158: 0 | P158: 0 | Q158: 0 | R158: 0 | T158: Closeout | V158: 0 | W158: 0 | X158: 0 | Y158: 832 | Z158: 0 | AA158: 0 | AE158: 0.85274435 | AF158: =Q158*AE158*1.1 -> 0
Q159: =Q88+Q90+Q95+Q125+Q130+Q145+Q89+Q100+Q105+Q110+Q115+Q120+Q135+Q140+Q149+Q153+Q158 -> 560205.95 | R159: =R88+R90+R95+R125+R130+R145+R89+R100+R105+R110+R115+R120+R135+R140+R149+R153+R158 -> 390858.82 | V159: =V88+V90+V95+V125+V130+V145+V89+V100+V105+V110+V115+V120+V135+V140+V149+V153+V158 -> 1.9890616e+08 | W159: =W88+W90+W95+W125+W130+W145+W89+W100+W105+W110+W115+W120+W135+W140+W149+W153+W158 -> 1.7089756e+08 | X159: =X88+X90+X95+X125+X130+X145+X89+X100+X105+X110+X115+X120+X135+X140+X149+X153+X158 -> 1.1955048e+08 | Y159: =Y88+Y90+Y95+Y125+Y130+Y145+Y89+Y100+Y105+Y110+Y115+Y120+Y135+Y140+Y149+Y153+Y158 -> 884888 | Z159: =Z88+Z90+Z95+Z125+Z130+Z145+Z89+Z100+Z105+Z110+Z115+Z120+Z135+Z140+Z149+Z153+Z158 -> 843272 | AA159: =AA88+AA90+AA95+AA125+AA130+AA145+AA89+AA100+AA105+AA110+AA115+AA120+AA135+AA140+AA149+AA153+AA158 -> 408099.95
K160: Activity ID | L160: Activity Name | M160: Budgeted Total Cost | N160: Planned Value Cost | O160: Earned Value Cost | P160: Budgeted Labor Units | Q160: Planned Value Labor Units | R160: Earned Value Labor Units | S160: Spreadsheet Field | T160: 45868 | U160: 45869 | V160: 45870 | W160: 45871 | X160: 45872 | Y160: 45873 | Z160: 45874 | AA160: 45875 | AB160: 45876 | AC160: 45877 | AD160: 45878 | AE160: 45879 | AF160: 45880 | AG160: 45881 | AH160: 45882 | AI160: 45883 | AJ160: 45884 | AK160: 45885 | AL160: 45886 | AM160: 45887 | AN160: 45888 | AO160: 45889 | AP160: 45890 | AQ160: 45891 | AR160: 45892 | AS160: 45893 | AT160: 45894 | AU160: 45895 | AV160: 45896 | AW160: 45897 | AX160: 45898 | AY160: 45899 | AZ160: 45900 | BA160: 45901 | BB160: 45902 | BC160: 45903 | BD160: 45904 | BE160: 45905 | BF160: 45906 | BG160: 45907 | BH160: 45908 | BI160: 45909 | BJ160: 45910 | BK160: 45911 | BL160: 45912 | BM160: 45913 | BN160: 45914 | BO160: 45915 | BP160: 45916 | BQ160: 45917 | BR160: 45918 | BS160: 45919 | BT160: 45920 | BU160: 45921 | BV160: 45922 | BW160: 45923 | BX160: 45924 | BY160: 45925 | BZ160: 45926 | CA160: 45927 | CB160: 45928 | CC160: 45929 | CD160: 45930 | CE160: 45931 | CF160: 45932 | CG160: 45933 | CH160: 45934 | CI160: 45935 | CJ160: 45936 | CK160: 45937 | CL160: 45938 | CM160: 45939 | CN160: 45940 | CO160: 45941 | CP160: 45942 | CQ160: 45943 | CR160: 45944 | CS160: 45945 | CT160: 45946 | CU160: 45947 | CV160: 45948 | CW160: 45949 | CX160: 45950 | CY160: 45951 | CZ160: 45952 | DA160: 45953 | DB160: 45954 | DC160: 45955 | DD160: 45956 | DE160: 45957 | DF160: 45958 | DG160: 45959 | DH160: 45960 | DI160: 45961 | DJ160: 45962 | DK160: 45963 | DL160: 45964 | DM160: 45965 | DN160: 45966 | DO160: 45967 | DP160: 45968 | DQ160: 45969 | DR160: 45970 | DS160: 45971 | DT160: 45972 | DU160: 45973 | DV160: 45974 | DW160: 45975 | DX160: 45976 | DY160: 45977 | DZ160: 45978 | EA160: 45979 | EB160: 45980 | EC160: 45981 | ED160: 45982 | EE160: 45983 | EF160: 45984 | EG160: 45985 | EH160: 45986 | EI160: 45987 | EJ160: 45988 | EK160: 45989 | EL160: 45990 | EM160: 45991 | EN160: 45992 | EO160: 45993 | EP160: 45994 | EQ160: 45995 | ER160: 45996 | ES160: 45997 | ET160: 45998 | EU160: 45999 | EV160: 46000 | EW160: 46001 | EX160: 46002 | EY160: 46003 | EZ160: 46004 | FA160: 46005 | FB160: 46006 | FC160: 46007 | FD160: 46008 | FE160: 46009 | FF160: 46010 | FG160: 46011 | FH160: 46012 | FI160: 46013 | FJ160: 46014 | FK160: 46015 | FL160: 46016 | FM160: 46017 | FN160: 46018 | FO160: 46019 | FP160: 46020 | FQ160: 46021 | FR160: 46022 | FS160: 46023 | FT160: 46024 | FU160: 46025 | FV160: 46026 | FW160: 46027 | FX160: 46028 | FY160: 46029 | FZ160: 46030 | GA160: 46031 | GB160: 46032 | GC160: 46033 | GD160: 46034 | GE160: 46035 | GF160: 46036 | GG160: 46037 | GH160: 46038 | GI160: 46039 | GJ160: 46040 | GK160: 46041 | GL160: 46042 | GM160: 46043 | GN160: 46044 | GO160: 46045 | GP160: 46046 | GQ160: 46047 | GR160: 46048 | GS160: 46049 | GT160: 46050 | GU160: 46051 | GV160: 46052 | GW160: 46053 | GX160: 46054 | GY160: 46055 | GZ160: 46056 | HA160: 46057 | HB160: 46058 | HC160: 46059 | HD160: 46060 | HE160: 46061 | HF160: 46062 | HG160: 46063 | HH160: 46064 | HI160: 46065 | HJ160: 46066 | HK160: 46067 | HL160: 46068 | HM160: 46069 | HN160: 46070 | HO160: 46071 | HP160: 46072 | HQ160: 46073 | HR160: 46074 | HS160: 46075 | HT160: 46076 | HU160: 46077 | HV160: 46078 | HW160: 46079 | HX160: 46080 | HY160: 46081 | HZ160: 46082 | IA160: 46083 | IB160: 46084 | IC160: 46085 | ID160: 46086 | IE160: 46087 | IF160: 46088 | IG160: 46089 | IH160: 46090 | II160: 46091 | IJ160: 46092 | IK160: 46093 | IL160: 46094 | IM160: 46095 | IN160: 46096 | IO160: 46097 | IP160: 46098 | IQ160: 46099 | IR160: 46100 | IS160: 46101 | IT160: 46102 | IU160: 46103 | IV160: 46104 | IW160: 46105 | IX160: 46106 | IY160: 46107 | IZ160: 46108 | JA160: 46109 | JB160: 46110 | JC160: 46111 | JD160: 46112 | JE160: 46113 | JF160: 46114 | JG160: 46115 | JH160: 46116 | JI160: 46117 | JJ160: 46118 | JK160: 46119 | JL160: 46120 | JM160: 46121 | JN160: 46122 | JO160: 46123 | JP160: 46124 | JQ160: 46125 | JR160: 46126 | JS160: 46127 | JT160: 46128 | JU160: 46129 | JV160: 46130 | JW160: 46131 | JX160: 46132 | JY160: 46133 | JZ160: 46134 | KA160: 46135 | KB160: 46136 | KC160: 46137 | KD160: 46138 | KE160: 46139 | KF160: 46140 | KG160: 46141 | KH160: 46142 | KI160: 46143 | KJ160: 46144 | KK160: 46145 | KL160: 46146 | KM160: 46147 | KN160: 46148 | KO160: 46149 | KP160: 46150 | KQ160: 46151 | KR160: 46152 | KS160: 46153 | KT160: 46154 | KU160: 46155 | KV160: 46156 | KW160: 46157 | KX160: 46158 | KY160: 46159 | KZ160: 46160 | LA160: 46161 | LB160: 46162 | LC160: 46163 | LD160: 46164 | LE160: 46165 | LF160: 46166 | LG160: 46167 | LH160: 46168 | LI160: 46169 | LJ160: 46170 | LK160: 46171 | LL160: 46172 | LM160: 46173 | LN160: 46174 | LO160: 46175 | LP160: 46176 | LQ160: 46177 | LR160: 46178 | LS160: 46179 | LT160: 46180 | LU160: 46181 | LV160: 46182 | LW160: 46183 | LX160: 46184 | LY160: 46185 | LZ160: 46186 | MA160: 46187 | MB160: 46188 | MC160: 46189 | MD160: 46190 | ME160: 46191 | MF160: 46192 | MG160: 46193 | MH160: 46194 | MI160: 46195 | MJ160: 46196 | MK160: 46197 | ML160: 46198 | MM160: 46199 | MN160: 46200 | MO160: 46201 | MP160: 46202 | MQ160: 46203 | MR160: 46204 | MS160: 46205 | MT160: 46206 | MU160: 46207 | MV160: 46208 | MW160: 46209 | MX160: 46210 | MY160: 46211 | MZ160: 46212 | NA160: 46213 | NB160: 46214 | NC160: 46215 | ND160: 46216 | NE160: 46217 | NF160: 46218 | NG160: 46219 | NH160: 46220 | NI160: 46221 | NJ160: 46222 | NK160: 46223 | NL160: 46224 | NM160: 46225 | NN160: 46226 | NO160: 46227 | NP160: 46228 | NQ160: 46229 | NR160: 46230 | NS160: 46231 | NT160: 46232 | NU160: 46233 | NV160: 46234 | NW160: 46235 | NX160: 46236 | NY160: 46237 | NZ160: 46238 | OA160: 46239 | OB160: 46240 | OC160: 46241 | OD160: 46242 | OE160: 46243 | OF160: 46244 | OG160: 46245 | OH160: 46246 | OI160: 46247 | OJ160: 46248 | OK160: 46249 | OL160: 46250 | OM160: 46251 | ON160: 46252 | OO160: 46253 | OP160: 46254 | OQ160: 46255 | OR160: 46256 | OS160: 46257 | OT160: 46258 | OU160: 46259 | OV160: 46260 | OW160: 46261 | OX160: 46262 | OY160: 46263 | OZ160: 46264 | PA160: 46265 | PB160: 46266 | PC160: 46267 | PD160: 46268 | PE160: 46269 | PF160: 46270 | PG160: 46271 | PH160: 46272 | PI160: 46273 | PJ160: 46274 | PK160: 46275 | PL160: 46276 | PM160: 46277 | PN160: 46278 | PO160: 46279 | PP160: 46280 | PQ160: 46281 | PR160: 46282 | PS160: 46283 | PT160: 46284 | PU160: 46285 | PV160: 46286 | PW160: 46287 | PX160: 46288 | PY160: 46289 | PZ160: 46290 | QA160: 46291 | QB160: 46292 | QC160: 46293 | QD160: 46294 | QE160: 46295 | QF160: 46296 | QG160: 46297 | QH160: 46298 | QI160: 46299 | QJ160: 46300 | QK160: 46301 | QL160: 46302 | QM160: 46303 | QN160: 46304 | QO160: 46305 | QP160: 46306 | QQ160: 46307 | QR160: 46308 | QS160: 46309 | QT160: 46310 | QU160: 46311 | QV160: 46312 | QW160: 46313 | QX160: 46314 | QY160: 46315 | QZ160: 46316 | RA160: 46317 | RB160: 46318 | RC160: 46319 | RD160: 46320 | RE160: 46321 | RF160: 46322 | RG160: 46323 | RH160: 46324 | RI160: 46325 | RJ160: 46326 | RK160: 46327 | RL160: 46328 | RM160: 46329 | RN160: 46330 | RO160: 46331 | RP160: 46332 | RQ160: 46333 | RR160: 46334 | RS160: 46335 | RT160: 46336 | RU160: 46337 | RV160: 46338 | RW160: 46339 | RX160: 46340 | RY160: 46341 | RZ160: 46342 | SA160: 46343 | SB160: 46344 | SC160: 46345 | SD160: 46346 | SE160: 46347 | SF160: 46348 | SG160: 46349 | SH160: 46350 | SI160: 46351 | SJ160: 46352 | SK160: 46353 | SL160: 46354 | SM160: 46355 | SN160: 46356 | SO160: 46357 | SP160: 46358 | SQ160: 46359 | SR160: 46360 | SS160: 46361 | ST160: 46362 | SU160: 46363 | SV160: 46364 | SW160: 46365 | SX160: 46366 | SY160: 46367 | SZ160: 46368 | TA160: 46369 | TB160: 46370 | TC160: 46371 | TD160: 46372 | TE160: 46373 | TF160: 46374 | TG160: 46375 | TH160: 46376 | TI160: 46377 | TJ160: 46378 | TK160: 46379 | TL160: 46380 | TM160: 46381 | TN160: 46382 | TO160: 46383 | TP160: 46384 | TQ160: 46385 | TR160: 46386 | TS160: 46387 | TT160: 46388 | TU160: 46389 | TV160: 46390 | TW160: 46391 | TX160: 46392 | TY160: 46393 | TZ160: 46394 | UA160: 46395 | UB160: 46396 | UC160: 46397 | UD160: 46398 | UE160: 46399 | UF160: 46400 | UG160: 46401 | UH160: 46402 | UI160: 46403 | UJ160: 46404 | UK160: 46405 | UL160: 46406 | UM160: 46407 | UN160: 46408 | UO160: 46409 | UP160: 46410 | UQ160: 46411 | UR160: 46412 | US160: 46413 | UT160: 46414 | UU160: 46415 | UV160: 46416 | UW160: 46417 | UX160: 46418 | UY160: 46419 | UZ160: 46420 | VA160: 46421 | VB160: 46422 | VC160: 46423 | VD160: 46424 | VE160: 46425 | VF160: 46426 | VG160: 46427 | VH160: 46428 | VI160: 46429 | VJ160: 46430 | VK160: 46431 | VL160: 46432 | VM160: 46433
K161: Total | M161: 1.9890616e+08 | N161: 1.4385991e+08 | O161: 1.0241594e+08 | P161: 920230 | Q161: 560205.94 | R161: 390858.81 | S161: Cum BL Project Total Cost | BR161: 24583.01 | BS161: 24583.01 | BT161: 61712.17 | BU161: 98841.33 | BV161: 166876.17 | BW161: 166876.17 | BX161: 234911.01 | BY161: 302945.85 | BZ161: 302945.85 | CA161: 370980.69 | CB161: 439015.53 | CC161: 507050.37 | CD161: 579721.05 | CE161: 666299.25 | CF161: 761080.33 | CG161: 761080.33 | CH161: 872332.57 | CI161: 1001462.6 | CJ161: 1134069.4 | CK161: 1276535.6 | CL161: 1366680.4 | CM161: 1463460.2 | CN161: 1463460.2 | CO161: 1562061.6 | CP161: 1619557.1 | CQ161: 1682218.1 | CR161: 1774187.8 | CS161: 1866157.5 | CT161: 1958127.1 | CU161: 1958127.1 | CV161: 2058338.3 | CW161: 2189639.9 | CX161: 2333236.3 | CY161: 2496339 | CZ161: 2662885.1 | DA161: 2829431.1 | DB161: 2829431.1 | DC161: 2911504 | DD161: 2993576.8 | DE161: 3075649.7 | DF161: 3161822.3 | DG161: 3251860.8 | DH161: 3345765.2 | DI161: 3345765.2 | DJ161: 3439669.6 | DK161: 3533574 | DL161: 3630011.6 | DM161: 3728982.5 | DN161: 3827953.3 | DO161: 3926924.1 | DP161: 3926924.1 | DQ161: 4033841.7 | DR161: 4152540.7 | DS161: 4271239.7 | DT161: 4390365.7 | DU161: 4516262.8 | DV161: 4655360.6 | DW161: 4655360.6 | DX161: 4807356.9 | DY161: 4967214.5 | DZ161: 5128998.3 | EA161: 5299977.7 | EB161: 5474125.4 | EC161: 5672709.8 | ED161: 5672709.8 | EE161: 6031884.6 | EF161: 6484227 | EG161: 6938342.1 | EH161: 7392460 | EI161: 7880046.5 | EJ161: 8440959.5 | EK161: 8440959.5 | EL161: 9218787.2 | EM161: 10157702 | EN161: 11647810 | EO161: 12737813 | EP161: 13833044 | EQ161: 14715532 | ER161: 14715532 | ES161: 15218590 | ET161: 15588710 | EU161: 16008598 | EV161: 16455056 | EW161: 16803416 | EX161: 17216345 | EY161: 17216345 | EZ161: 17695942 | FA161: 17968837 | FB161: 18203426 | FC161: 18439748 | FD161: 18676779 | FE161: 18920853 | FF161: 18920853 | FG161: 19166032 | FH161: 19424122 | FI161: 19683782 | FJ161: 19971984 | FK161: 20254969 | FL161: 20547904 | FM161: 20547904 | FN161: 20859019 | FO161: 21178867 | FP161: 21501622 | FQ161: 21831607 | FR161: 22145696 | FS161: 22470744 | FT161: 22470744 | FU161: 22816140 | FV161: 23158616 | FW161: 23504991 | FX161: 23867209 | FY161: 24237050 | FZ161: 24618809 | GA161: 24618809 | GB161: 25012102 | GC161: 25415766 | GD161: 25833174 | GE161: 26258130 | GF161: 26696468 | GG161: 27116437 | GH161: 27116437 | GI161: 27532934 | GJ161: 27973408 | GK161: 28422040 | GL161: 28888785 | GM161: 29356995 | GN161: 29845944 | GO161: 29845944 | GP161: 30340394 | GQ161: 30842006 | GR161: 31360417 | GS161: 31895410 | GT161: 32446528 | GU161: 33013495 | GV161: 33013495 | GW161: 33592014 | GX161: 34143717 | GY161: 34727411 | GZ161: 35310944 | HA161: 35752806 | HB161: 36196425 | HC161: 36196425 | HD161: 36678785 | HE161: 37142534 | HF161: 37537352 | HG161: 37977655 | HH161: 38435718 | HI161: 38915399 | HJ161: 38915399 | HK161: 39415615 | HL161: 39876737 | HM161: 40418235 | HN161: 40921732 | HO161: 41228498 | HP161: 41560740 | HQ161: 41560740 | HR161: 41894138 | HS161: 41894138 | HT161: 42271697 | HU161: 42708201 | HV161: 43259801 | HW161: 43826585 | HX161: 43826585 | HY161: 44202410 | HZ161: 44703920 | IA161: 45157793 | IB161: 45489806 | IC161: 45929857 | ID161: 46998896 | IE161: 46998896 | IF161: 47446074 | IG161: 47846099 | IH161: 48365289 | II161: 48831927 | IJ161: 49217639 | IK161: 49742048 | IL161: 49742048 | IM161: 50334462 | IN161: 50624928 | IO161: 50857793 | IP161: 51063006 | IQ161: 51276560 | IR161: 51276560 | IS161: 51276560 | IT161: 51276560 | IU161: 51276560 | IV161: 51276560 | IW161: 51611086 | IX161: 52039326 | IY161: 52656023 | IZ161: 52656023 | JA161: 52927057 | JB161: 53203650 | JC161: 53584699 | JD161: 54230199 | JE161: 54824180 | JF161: 55417272 | JG161: 55417272 | JH161: 56303409 | JI161: 57519049 | JJ161: 58013998 | JK161: 58221861 | JL161: 58379015 | JM161: 58539778 | JN161: 58539778 | JO161: 58664527 | JP161: 58782921 | JQ161: 58882931 | JR161: 58983412 | JS161: 59077446 | JT161: 59182502 | JU161: 59182502 | JV161: 59290370 | JW161: 59393926 | JX161: 59521762 | JY161: 59664092 | JZ161: 59809339 | KA161: 59962990 | KB161: 59962990 | KC161: 60127230 | KD161: 60320412 | KE161: 60524091 | KF161: 60689615 | KG161: 60855971 | KH161: 61025509 | KI161: 61025509 | KJ161: 61215852 | KK161: 61400918 | KL161: 61587759 | KM161: 61778495 | KN161: 61971916 | KO161: 62167448 | KP161: 62167448 | KQ161: 62366354 | KR161: 62545470 | KS161: 62704263 | KT161: 62829198 | KU161: 62949044 | KV161: 63064725 | KW161: 63064725 | KX161: 63193232 | KY161: 63321351 | KZ161: 63469257 | LA161: 63622297 | LB161: 63773655 | LC161: 63957053 | LD161: 63957053 | LE161: 64159667 | LF161: 64322522 | LG161: 64457350 | LH161: 64457350 | LI161: 64457350 | LJ161: 64457350 | LK161: 64457350 | LL161: 64457350 | LM161: 64577689 | LN161: 64718364 | LO161: 64837815 | LP161: 64958564 | LQ161: 65079032 | LR161: 65079032 | LS161: 65210637 | LT161: 65381375 | LU161: 65544384 | LV161: 65691535 | LW161: 65874731 | LX161: 66057744 | LY161: 66057744 | LZ161: 66257337 | MA161: 66462041 | MB161: 66670544 | MC161: 66875503 | MD161: 67066022 | ME161: 67247383 | MF161: 67247383 | MG161: 67436278 | MH161: 67630336 | MI161: 67831855 | MJ161: 68034250 | MK161: 68254430 | ML161: 68470490 | MM161: 68470490 | MN161: 68688068 | MO161: 68911511 | MP161: 69143080 | MQ161: 69371946 | MR161: 69599337 | MS161: 69818767 | MT161: 69818767 | MU161: 70034942 | MV161: 70252281 | MW161: 70474689 | MX161: 70685150 | MY161: 70891034 | MZ161: 71096163 | NA161: 71096163 | NB161: 71300312 | NC161: 71504396 | ND161: 71718160 | NE161: 71943839 | NF161: 72172617 | NG161: 72402396 | NH161: 72402396 | NI161: 72632826 | NJ161: 72873122 | NK161: 73116199 | NL161: 73362459 | NM161: 73615313 | NN161: 73871928 | NO161: 73871928 | NP161: 74101666 | NQ161: 74313046 | NR161: 74531115 | NS161: 74753108 | NT161: 74981126 | NU161: 75220951 | NV161: 75220951 | NW161: 75487756 | NX161: 75776692 | NY161: 76085148 | NZ161: 76413548 | OA161: 76711533 | OB161: 77041182 | OC161: 77041182 | OD161: 77387157 | OE161: 77742850 | OF161: 78114855 | OG161: 78497074 | OH161: 78906694 | OI161: 79324177 | OJ161: 79324177 | OK161: 79773466 | OL161: 80266916 | OM161: 80733556 | ON161: 81194911 | OO161: 81650051 | OP161: 82112271 | OQ161: 82112271 | OR161: 82581775 | OS161: 83054017 | OT161: 83545779 | OU161: 84042086 | OV161: 84548353 | OW161: 85065455 | OX161: 85065455 | OY161: 85601984 | OZ161: 86146501 | PA161: 86710074 | PB161: 87288101 | PC161: 87889936 | PD161: 88505391 | PE161: 88505391 | PF161: 89161603 | PG161: 89922710 | PH161: 90836438 | PI161: 91653221 | PJ161: 92506961 | PK161: 93407816 | PL161: 93407816 | PM161: 94443398 | PN161: 95628098 | PO161: 97047969 | PP161: 99011172 | PQ161: 1.0304002e+08 | PR161: 1.0924761e+08 | PS161: 1.0924761e+08 | PT161: 1.148617e+08 | PU161: 1.1972619e+08 | PV161: 1.2132828e+08 | PW161: 1.2292349e+08 | PX161: 1.2292349e+08 | PY161: 1.2447229e+08 | PZ161: 1.2447229e+08 | QA161: 1.264299e+08 | QB161: 1.2860199e+08 | QC161: 1.3109781e+08 | QD161: 1.3415166e+08 | QE161: 1.3686531e+08 | QF161: 1.387427e+08 | QG161: 1.387427e+08 | QH161: 1.4015753e+08 | QI161: 1.411776e+08 | QJ161: 1.4235718e+08 | QK161: 1.4385991e+08 | QL161: 1.4695729e+08 | QM161: 1.4817435e+08 | QN161: 1.4817435e+08 | QO161: 1.4943321e+08 | QP161: 151082511 | QQ161: 1.5333552e+08 | QR161: 1.5508427e+08 | QS161: 1.5604438e+08 | QT161: 1.569884e+08 | QU161: 1.569884e+08 | QV161: 1.5818169e+08 | QW161: 1.5969441e+08 | QX161: 1.6074501e+08 | QY161: 1.6209968e+08 | QZ161: 1.6381886e+08 | RA161: 1.646499e+08 | RB161: 1.646499e+08 | RC161: 1.6600606e+08 | RD161: 1.6693149e+08 | RE161: 1.6792074e+08 | RF161: 1.6901382e+08 | RG161: 1.6993758e+08 | RH161: 1.7113636e+08 | RI161: 1.7113636e+08 | RJ161: 1.7229513e+08 | RK161: 1.7303454e+08 | RL161: 1.7361246e+08 | RM161: 1.7430213e+08 | RN161: 1.750695e+08 | RO161: 175887569 | RP161: 175887569 | RQ161: 1.7649816e+08 | RR161: 1.7703426e+08 | RS161: 1.7750624e+08 | RT161: 1.7806858e+08 | RU161: 1.7911731e+08 | RV161: 1.8142357e+08 | RW161: 1.8142357e+08 | RX161: 1.8286934e+08 | RY161: 1.8550677e+08 | RZ161: 1.8645143e+08 | SA161: 1.871967e+08 | SB161: 1.8840971e+08 | SC161: 1.8883315e+08 | SD161: 1.8883315e+08 | SE161: 1.8913898e+08 | SF161: 1.8948285e+08 | SG161: 1.8968556e+08 | SH161: 1.8989621e+08 | SI161: 1.900571e+08 | SJ161: 1.901713e+08 | SK161: 1.9018094e+08 | SL161: 1.9020089e+08 | SM161: 1.9024491e+08 | SN161: 1.9032812e+08 | SO161: 1.9043018e+08 | SP161: 1.9056292e+08 | SQ161: 1.9074501e+08 | SR161: 1.9075465e+08 | SS161: 1.9106193e+08 | ST161: 1.9150546e+08 | SU161: 1.9211838e+08 | SV161: 1.9256303e+08 | SW161: 1.9334021e+08 | SX161: 1.9443825e+08 | SY161: 1.9446802e+08 | SZ161: 1.9513363e+08 | TA161: 1.9562936e+08 | TB161: 1.9617016e+08 | TC161: 1.9710151e+08 | TD161: 1.9851613e+08 | TE161: 1.9890013e+08 | TF161: 1.9890013e+08 | TG161: 1.9890155e+08 | TH161: 1.9890503e+08 | TI161: 1.9890616e+08 | TJ161: 1.9890616e+08 | TK161: 1.9890616e+08 | TL161: 1.9890616e+08 | TM161: 1.9890616e+08 | TN161: 1.9890616e+08 | TO161: 1.9890616e+08 | TP161: 1.9890616e+08 | TQ161: 1.9890616e+08 | TR161: 1.9890616e+08 | TS161: 1.9890616e+08 | TT161: 1.9890616e+08 | TU161: 1.9890616e+08 | TV161: 1.9890616e+08 | TW161: 1.9890616e+08 | TX161: 1.9890616e+08 | TY161: 1.9890616e+08 | TZ161: 1.9890616e+08 | UA161: 1.9890616e+08 | UB161: 1.9890616e+08 | UC161: 1.9890616e+08 | UD161: 1.9890616e+08 | UE161: 1.9890616e+08 | UF161: 1.9890616e+08 | UG161: 1.9890616e+08 | UH161: 1.9890616e+08 | UI161: 1.9890616e+08 | UJ161: 1.9890616e+08 | UK161: 1.9890616e+08 | UL161: 1.9890616e+08 | UM161: 1.9890616e+08 | UN161: 1.9890616e+08 | UO161: 1.9890616e+08 | UP161: 1.9890616e+08 | UQ161: 1.9890616e+08 | UR161: 1.9890616e+08 | US161: 1.9890616e+08 | UT161: 1.9890616e+08 | UU161: 1.9890616e+08 | UV161: 1.9890616e+08 | UW161: 1.9890616e+08 | UX161: 1.9890616e+08 | UY161: 1.9890616e+08 | UZ161: 1.9890616e+08 | VA161: 1.9890616e+08 | VB161: 1.9890616e+08 | VC161: 1.9890616e+08 | VD161: 1.9890616e+08 | VE161: 1.9890616e+08 | VF161: 1.9890616e+08 | VG161: 1.9890616e+08 | VH161: 1.9890616e+08 | VI161: 1.9890616e+08 | VJ161: 1.9890616e+08 | VK161: 1.9890616e+08 | VL161: 1.9890616e+08 | VM161: 1.9890616e+08
K162: Demolishing & Site Clearing | M162: 457401.18 | N162: 457401.18 | O162: 457401.18 | P162: 3437.41 | Q162: 3437.41 | R162: 3437.41 | S162: Cum BL Project Total Cost | GI162: 7736.06 | GJ162: 15472.12 | GK162: 28365.55 | GL162: 51573.72 | GM162: 51573.72 | GN162: 51573.72 | GO162: 51573.72 | GP162: 51573.72 | GQ162: 51573.72 | GR162: 51573.72 | GS162: 51573.72 | GT162: 51573.72 | GU162: 51573.72 | GV162: 51573.72 | GW162: 51573.72 | GX162: 51573.72 | GY162: 51573.72 | GZ162: 51573.72 | HA162: 51573.72 | HB162: 51573.72 | HC162: 51573.72 | HD162: 51573.72 | HE162: 51573.72 | HF162: 51573.72 | HG162: 51573.72 | HH162: 51573.72 | HI162: 51573.72 | HJ162: 51573.72 | HK162: 51573.72 | HL162: 51573.72 | HM162: 51573.72 | HN162: 51573.72 | HO162: 51573.72 | HP162: 51573.72 | HQ162: 51573.72 | HR162: 51573.72 | HS162: 51573.72 | HT162: 51573.72 | HU162: 51573.72 | HV162: 51573.72 | HW162: 51573.72 | HX162: 51573.72 | HY162: 51573.72 | HZ162: 51573.72 | IA162: 51573.72 | IB162: 51573.72 | IC162: 51573.72 | ID162: 51573.72 | IE162: 51573.72 | IF162: 55564.15 | IG162: 59554.57 | IH162: 63545 | II162: 67709.27 | IJ162: 72464.61 | IK162: 77602.4 | IL162: 77602.4 | IM162: 81071.3 | IN162: 84540.19 | IO162: 88009.08 | IP162: 91477.97 | IQ162: 94946.86 | IR162: 94946.86 | IS162: 94946.86 | IT162: 94946.86 | IU162: 94946.86 | IV162: 94946.86 | IW162: 99572.05 | IX162: 104197.24 | IY162: 108822.43 | IZ162: 108822.43 | JA162: 113447.62 | JB162: 118072.81 | JC162: 122698 | JD162: 128393.73 | JE162: 136070.88 | JF162: 145600.28 | JG162: 145600.28 | JH162: 156392.39 | JI162: 167184.49 | JJ162: 183430.89 | JK162: 200295.22 | JL162: 219136.89 | JM162: 243386.66 | JN162: 243386.66 | JO162: 269355.86 | JP162: 277126.41 | JQ162: 284896.97 | JR162: 284896.97 | JS162: 286795.2 | JT162: 288693.44 | JU162: 288693.44 | JV162: 290591.67 | JW162: 293122.65 | JX162: 297804.97 | JY162: 303879.33 | JZ162: 305777.56 | KA162: 307675.8 | KB162: 307675.8 | KC162: 309574.03 | KD162: 312105.01 | KE162: 316787.33 | KF162: 322861.69 | KG162: 322861.69 | KH162: 322861.69 | KI162: 322861.69 | KJ162: 322861.69 | KK162: 322861.69 | KL162: 322861.69 | KM162: 322861.69 | KN162: 322861.69 | KO162: 322861.69 | KP162: 322861.69 | KQ162: 325387.56 | KR162: 327913.43 | KS162: 332123.22 | KT162: 339700.85 | KU162: 339700.85 | KV162: 339700.85 | KW162: 339700.85 | KX162: 342226.72 | KY162: 344752.6 | KZ162: 348962.39 | LA162: 356540.01 | LB162: 360820.26 | LC162: 370257.88 | LD162: 370257.88 | LE162: 382549 | LF162: 400547.13 | LG162: 407423.62 | LH162: 407423.62 | LI162: 407423.62 | LJ162: 407423.62 | LK162: 407423.62 | LL162: 407423.62 | LM162: 421927.83 | LN162: 442591.05 | LO162: 442591.05 | LP162: 442591.05 | LQ162: 442591.05 | LR162: 442591.05 | LS162: 442591.05 | LT162: 442591.05 | LU162: 443234.8 | LV162: 443878.55 | LW162: 444522.3 | LX162: 445166.05 | LY162: 445166.05 | LZ162: 446346.26 | MA162: 448020.01 | MB162: 450101.48 | MC162: 450101.48 | MD162: 451225.88 | ME162: 452458.45 | MF162: 452458.45 | MG162: 454772.72 | MH162: 455830.64 | MI162: 457401.18 | MJ162: 457401.18 | MK162: 457401.18 | ML162: 457401.18 | MM162: 457401.18 | MN162: 457401.18 | MO162: 457401.18 | MP162: 457401.18 | MQ162: 457401.18 | MR162: 457401.18 | MS162: 457401.18 | MT162: 457401.18 | MU162: 457401.18 | MV162: 457401.18 | MW162: 457401.18 | MX162: 457401.18 | MY162: 457401.18 | MZ162: 457401.18 | NA162: 457401.18 | NB162: 457401.18 | NC162: 457401.18 | ND162: 457401.18 | NE162: 457401.18 | NF162: 457401.18 | NG162: 457401.18 | NH162: 457401.18 | NI162: 457401.18 | NJ162: 457401.18 | NK162: 457401.18 | NL162: 457401.18 | NM162: 457401.18 | NN162: 457401.18 | NO162: 457401.18 | NP162: 457401.18 | NQ162: 457401.18 | NR162: 457401.18 | NS162: 457401.18 | NT162: 457401.18 | NU162: 457401.18 | NV162: 457401.18 | NW162: 457401.18 | NX162: 457401.18 | NY162: 457401.18 | NZ162: 457401.18 | OA162: 457401.18 | OB162: 457401.18 | OC162: 457401.18 | OD162: 457401.18 | OE162: 457401.18 | OF162: 457401.18 | OG162: 457401.18 | OH162: 457401.18 | OI162: 457401.18 | OJ162: 457401.18 | OK162: 457401.18 | OL162: 457401.18 | OM162: 457401.18 | ON162: 457401.18 | OO162: 457401.18 | OP162: 457401.18 | OQ162: 457401.18 | OR162: 457401.18 | OS162: 457401.18 | OT162: 457401.18 | OU162: 457401.18 | OV162: 457401.18 | OW162: 457401.18 | OX162: 457401.18 | OY162: 457401.18 | OZ162: 457401.18 | PA162: 457401.18 | PB162: 457401.18 | PC162: 457401.18 | PD162: 457401.18 | PE162: 457401.18 | PF162: 457401.18 | PG162: 457401.18 | PH162: 457401.18 | PI162: 457401.18 | PJ162: 457401.18 | PK162: 457401.18 | PL162: 457401.18 | PM162: 457401.18 | PN162: 457401.18 | PO162: 457401.18 | PP162: 457401.18 | PQ162: 457401.18 | PR162: 457401.18 | PS162: 457401.18 | PT162: 457401.18 | PU162: 457401.18 | PV162: 457401.18 | PW162: 457401.18 | PX162: 457401.18 | PY162: 457401.18 | PZ162: 457401.18 | QA162: 457401.18 | QB162: 457401.18 | QC162: 457401.18 | QD162: 457401.18 | QE162: 457401.18 | QF162: 457401.18 | QG162: 457401.18 | QH162: 457401.18 | QI162: 457401.18 | QJ162: 457401.18 | QK162: 457401.18 | QL162: 457401.18 | QM162: 457401.18 | QN162: 457401.18 | QO162: 457401.18 | QP162: 457401.18 | QQ162: 457401.18 | QR162: 457401.18 | QS162: 457401.18 | QT162: 457401.18 | QU162: 457401.18 | QV162: 457401.18 | QW162: 457401.18 | QX162: 457401.18 | QY162: 457401.18 | QZ162: 457401.18 | RA162: 457401.18 | RB162: 457401.18 | RC162: 457401.18 | RD162: 457401.18 | RE162: 457401.18 | RF162: 457401.18 | RG162: 457401.18 | RH162: 457401.18 | RI162: 457401.18 | RJ162: 457401.18 | RK162: 457401.18 | RL162: 457401.18 | RM162: 457401.18 | RN162: 457401.18 | RO162: 457401.18 | RP162: 457401.18 | RQ162: 457401.18 | RR162: 457401.18 | RS162: 457401.18 | RT162: 457401.18 | RU162: 457401.18 | RV162: 457401.18 | RW162: 457401.18 | RX162: 457401.18 | RY162: 457401.18 | RZ162: 457401.18 | SA162: 457401.18 | SB162: 457401.18 | SC162: 457401.18 | SD162: 457401.18 | SE162: 457401.18 | SF162: 457401.18 | SG162: 457401.18 | SH162: 457401.18 | SI162: 457401.18 | SJ162: 457401.18 | SK162: 457401.18 | SL162: 457401.18 | SM162: 457401.18 | SN162: 457401.18 | SO162: 457401.18 | SP162: 457401.18 | SQ162: 457401.18 | SR162: 457401.18 | SS162: 457401.18 | ST162: 457401.18 | SU162: 457401.18 | SV162: 457401.18 | SW162: 457401.18 | SX162: 457401.18 | SY162: 457401.18 | SZ162: 457401.18 | TA162: 457401.18 | TB162: 457401.18 | TC162: 457401.18 | TD162: 457401.18 | TE162: 457401.18 | TF162: 457401.18 | TG162: 457401.18 | TH162: 457401.18 | TI162: 457401.18 | TJ162: 457401.18 | TK162: 457401.18 | TL162: 457401.18 | TM162: 457401.18 | TN162: 457401.18 | TO162: 457401.18 | TP162: 457401.18 | TQ162: 457401.18 | TR162: 457401.18 | TS162: 457401.18 | TT162: 457401.18 | TU162: 457401.18 | TV162: 457401.18 | TW162: 457401.18 | TX162: 457401.18 | TY162: 457401.18 | TZ162: 457401.18 | UA162: 457401.18 | UB162: 457401.18 | UC162: 457401.18 | UD162: 457401.18 | UE162: 457401.18 | UF162: 457401.18 | UG162: 457401.18 | UH162: 457401.18 | UI162: 457401.18 | UJ162: 457401.18 | UK162: 457401.18 | UL162: 457401.18 | UM162: 457401.18 | UN162: 457401.18 | UO162: 457401.18 | UP162: 457401.18 | UQ162: 457401.18 | UR162: 457401.18 | US162: 457401.18 | UT162: 457401.18 | UU162: 457401.18 | UV162: 457401.18 | UW162: 457401.18 | UX162: 457401.18 | UY162: 457401.18 | UZ162: 457401.18 | VA162: 457401.18 | VB162: 457401.18 | VC162: 457401.18 | VD162: 457401.18 | VE162: 457401.18 | VF162: 457401.18 | VG162: 457401.18 | VH162: 457401.18 | VI162: 457401.18 | VJ162: 457401.18 | VK162: 457401.18 | VL162: 457401.18 | VM162: 457401.18
K163: Earthworks & Site Grading | M163: 31040592 | N163: 31040592 | O163: 29924053 | P163: 22808.8 | Q163: 22808.8 | R163: 21945.45 | S163: Cum BL Project Total Cost | BR163: 24583.01 | BS163: 24583.01 | BT163: 61712.17 | BU163: 98841.33 | BV163: 166876.17 | BW163: 166876.17 | BX163: 234911.01 | BY163: 302945.85 | BZ163: 302945.85 | CA163: 370980.69 | CB163: 439015.53 | CC163: 507050.37 | CD163: 579721.05 | CE163: 666299.25 | CF163: 761080.33 | CG163: 761080.33 | CH163: 872332.57 | CI163: 1001462.6 | CJ163: 1134069.4 | CK163: 1276535.6 | CL163: 1366680.4 | CM163: 1463460.2 | CN163: 1463460.2 | CO163: 1562061.6 | CP163: 1619557.1 | CQ163: 1682218.1 | CR163: 1774187.8 | CS163: 1866157.5 | CT163: 1958127.1 | CU163: 1958127.1 | CV163: 2058338.3 | CW163: 2189639.9 | CX163: 2333236.3 | CY163: 2496339 | CZ163: 2662885.1 | DA163: 2829431.1 | DB163: 2829431.1 | DC163: 2911504 | DD163: 2993576.8 | DE163: 3075649.7 | DF163: 3161822.3 | DG163: 3251860.8 | DH163: 3345765.2 | DI163: 3345765.2 | DJ163: 3439669.6 | DK163: 3533574 | DL163: 3630011.6 | DM163: 3728982.5 | DN163: 3827953.3 | DO163: 3926924.1 | DP163: 3926924.1 | DQ163: 4033841.7 | DR163: 4152540.7 | DS163: 4271239.7 | DT163: 4389938.8 | DU163: 4515362.3 | DV163: 4653986.4 | DW163: 4653986.4 | DX163: 4805509 | DY163: 4964892.9 | DZ163: 5126203 | EA163: 5296708.8 | EB163: 5470382.8 | EC163: 5656082.2 | ED163: 5656082.2 | EE163: 5860376.4 | EF163: 6085968.2 | EG163: 6313332.7 | EH163: 6540699.9 | EI163: 6776207.9 | EJ163: 7022238.3 | EK163: 7022238.3 | EL163: 7273738.2 | EM163: 7529526.3 | EN163: 7796380.6 | EO163: 8051594.5 | EP163: 8270065 | EQ163: 8453118.3 | ER163: 8453118.3 | ES163: 8609769.5 | ET163: 8766420.8 | EU163: 8923072.1 | EV163: 9079723.3 | EW163: 9236374.6 | EX163: 9393025.9 | EY163: 9393025.9 | EZ163: 9549677.2 | FA163: 9706328.4 | FB163: 9862979.7 | FC163: 10019631 | FD163: 10176284 | FE163: 10332938 | FF163: 10332938 | FG163: 10489732 | FH163: 10654826 | FI163: 10821844 | FJ163: 11007294 | FK163: 11195267 | FL163: 11386268 | FM163: 11386268 | FN163: 11591411 | FO163: 11802825 | FP163: 12022117 | FQ163: 12248278 | FR163: 12483624 | FS163: 12733965 | FT163: 12733965 | FU163: 12984309 | FV163: 13236868 | FW163: 13498313 | FX163: 13774224 | FY163: 14053456 | FZ163: 14323677 | GA163: 14323677 | GB163: 14593725 | GC163: 14868871 | GD163: 15151897 | GE163: 15452935 | GF163: 15765878 | GG163: 16083800 | GH163: 16083800 | GI163: 16403959 | GJ163: 16747943 | GK163: 17093222 | GL163: 17445747 | GM163: 17810414 | GN163: 18189274 | GO163: 18189274 | GP163: 18572458 | GQ163: 18962249 | GR163: 19359903 | GS163: 19763559 | GT163: 20180009 | GU163: 20605106 | GV163: 20605106 | GW163: 21038503 | GX163: 21460294 | GY163: 21905364 | GZ163: 22354361 | HA163: 22659394 | HB163: 22947465 | HC163: 22947465 | HD163: 23237563 | HE163: 23527661 | HF163: 23747208 | HG163: 23964097 | HH163: 24183039 | HI163: 24372602 | HJ163: 24372602 | HK163: 24560973 | HL163: 24752815 | HM163: 24930055 | HN163: 25106382 | HO163: 25241502 | HP163: 25388899 | HQ163: 25388899 | HR163: 25503254 | HS163: 25503254 | HT163: 25614713 | HU163: 25703167 | HV163: 25791708 | HW163: 25884580 | HX163: 25884580 | HY163: 25978159 | HZ163: 26059507 | IA163: 26141550 | IB163: 26206997 | IC163: 26278252 | ID163: 26366208 | IE163: 26366208 | IF163: 26454164 | IG163: 26543158 | IH163: 26635217 | II163: 26727276 | IJ163: 26821264 | IK163: 26893072 | IL163: 26893072 | IM163: 26946991 | IN163: 26999155 | IO163: 27054312 | IP163: 27116918 | IQ163: 27180135 | IR163: 27180135 | IS163: 27180135 | IT163: 27180135 | IU163: 27180135 | IV163: 27180135 | IW163: 27264427 | IX163: 27331391 | IY163: 27420930 | IZ163: 27420930 | JA163: 27523247 | JB163: 27627139 | JC163: 27741576 | JD163: 27862518 | JE163: 27944795 | JF163: 28021983 | JG163: 28021983 | JH163: 28038092 | JI163: 28048309 | JJ163: 28058915 | JK163: 28069522 | JL163: 28080129 | JM163: 28090736 | JN163: 28090736 | JO163: 28101343 | JP163: 28111949 | JQ163: 28122556 | JR163: 28133163 | JS163: 28143770 | JT163: 28154377 | JU163: 28154377 | JV163: 28164983 | JW163: 28175590 | JX163: 28186299 | JY163: 28197548 | JZ163: 28208796 | KA163: 28220045 | KB163: 28220045 | KC163: 28231294 | KD163: 28242543 | KE163: 28253792 | KF163: 28265041 | KG163: 28276290 | KH163: 28287538 | KI163: 28287538 | KJ163: 28298787 | KK163: 28310036 | KL163: 28321536 | KM163: 28334038 | KN163: 28343592 | KO163: 28351404 | KP163: 28351404 | KQ163: 28359216 | KR163: 28367216 | KS163: 28375263 | KT163: 28383310 | KU163: 28391357 | KV163: 28399404 | KW163: 28399404 | KX163: 28407451 | KY163: 28415498 | KZ163: 28423545 | LA163: 28431592 | LB163: 28440015 | LC163: 28449315 | LD163: 28449315 | LE163: 28460173 | LF163: 28471203 | LG163: 28482340 | LH163: 28482340 | LI163: 28482340 | LJ163: 28482340 | LK163: 28482340 | LL163: 28482340 | LM163: 28493606 | LN163: 28504871 | LO163: 28516137 | LP163: 28527403 | LQ163: 28538669 | LR163: 28538669 | LS163: 28549935 | LT163: 28561201 | LU163: 28572466 | LV163: 28583732 | LW163: 28594998 | LX163: 28606264 | LY163: 28606264 | LZ163: 28617530 | MA163: 28628796 | MB163: 28640061 | MC163: 28651327 | MD163: 28662593 | ME163: 28673859 | MF163: 28673859 | MG163: 28685125 | MH163: 28696391 | MI163: 28707656 | MJ163: 28718922 | MK163: 28730188 | ML163: 28741454 | MM163: 28741454 | MN163: 28752720 | MO163: 28763986 | MP163: 28775251 | MQ163: 28786517 | MR163: 28797783 | MS163: 28809049 | MT163: 28809049 | MU163: 28820315 | MV163: 28831580 | MW163: 28842846 | MX163: 28854112 | MY163: 28865378 | MZ163: 28876644 | NA163: 28876644 | NB163: 28887910 | NC163: 28899175 | ND163: 28911193 | NE163: 28925097 | NF163: 28939440 | NG163: 28953925 | NH163: 28953925 | NI163: 28968409 | NJ163: 28982894 | NK163: 28997379 | NL163: 29011863 | NM163: 29026348 | NN163: 29040833 | NO163: 29040833 | NP163: 29055317 | NQ163: 29069802 | NR163: 29084287 | NS163: 29098771 | NT163: 29113256 | NU163: 29127740 | NV163: 29127740 | NW163: 29142225 | NX163: 29156710 | NY163: 29171194 | NZ163: 29185679 | OA163: 29200164 | OB163: 29214648 | OC163: 29214648 | OD163: 29229133 | OE163: 29243618 | OF163: 29258102 | OG163: 29272587 | OH163: 29287071 | OI163: 29301556 | OJ163: 29301556 | OK163: 29316888 | OL163: 29332947 | OM163: 29349041 | ON163: 29365135 | OO163: 29381229 | OP163: 29397323 | OQ163: 29397323 | OR163: 29413417 | OS163: 29429511 | OT163: 29445605 | OU163: 29461699 | OV163: 29477793 | OW163: 29493887 | OX163: 29493887 | OY163: 29509981 | OZ163: 29526075 | PA163: 29542169 | PB163: 29558263 | PC163: 29574358 | PD163: 29590452 | PE163: 29590452 | PF163: 29606546 | PG163: 29622640 | PH163: 29638734 | PI163: 29654828 | PJ163: 29670922 | PK163: 29687016 | PL163: 29687016 | PM163: 29703110 | PN163: 29719204 | PO163: 29735298 | PP163: 29751392 | PQ163: 29826349 | PR163: 29901307 | PS163: 29901307 | PT163: 29983956 | PU163: 30082460 | PV163: 30153940 | PW163: 30230330 | PX163: 30230330 | PY163: 30292393 | PZ163: 30292393 | QA163: 30388316 | QB163: 30522608 | QC163: 30672248 | QD163: 30848746 | QE163: 31040592 | QF163: 31040592 | QG163: 31040592 | QH163: 31040592 | QI163: 31040592 | QJ163: 31040592 | QK163: 31040592 | QL163: 31040592 | QM163: 31040592 | QN163: 31040592 | QO163: 31040592 | QP163: 31040592 | QQ163: 31040592 | QR163: 31040592 | QS163: 31040592 | QT163: 31040592 | QU163: 31040592 | QV163: 31040592 | QW163: 31040592 | QX163: 31040592 | QY163: 31040592 | QZ163: 31040592 | RA163: 31040592 | RB163: 31040592 | RC163: 31040592 | RD163: 31040592 | RE163: 31040592 | RF163: 31040592 | RG163: 31040592 | RH163: 31040592 | RI163: 31040592 | RJ163: 31040592 | RK163: 31040592 | RL163: 31040592 | RM163: 31040592 | RN163: 31040592 | RO163: 31040592 | RP163: 31040592 | RQ163: 31040592 | RR163: 31040592 | RS163: 31040592 | RT163: 31040592 | RU163: 31040592 | RV163: 31040592 | RW163: 31040592 | RX163: 31040592 | RY163: 31040592 | RZ163: 31040592 | SA163: 31040592 | SB163: 31040592 | SC163: 31040592 | SD163: 31040592 | SE163: 31040592 | SF163: 31040592 | SG163: 31040592 | SH163: 31040592 | SI163: 31040592 | SJ163: 31040592 | SK163: 31040592 | SL163: 31040592 | SM163: 31040592 | SN163: 31040592 | SO163: 31040592 | SP163: 31040592 | SQ163: 31040592 | SR163: 31040592 | SS163: 31040592 | ST163: 31040592 | SU163: 31040592 | SV163: 31040592 | SW163: 31040592 | SX163: 31040592 | SY163: 31040592 | SZ163: 31040592 | TA163: 31040592 | TB163: 31040592 | TC163: 31040592 | TD163: 31040592 | TE163: 31040592 | TF163: 31040592 | TG163: 31040592 | TH163: 31040592 | TI163: 31040592 | TJ163: 31040592 | TK163: 31040592 | TL163: 31040592 | TM163: 31040592 | TN163: 31040592 | TO163: 31040592 | TP163: 31040592 | TQ163: 31040592 | TR163: 31040592 | TS163: 31040592 | TT163: 31040592 | TU163: 31040592 | TV163: 31040592 | TW163: 31040592 | TX163: 31040592 | TY163: 31040592 | TZ163: 31040592 | UA163: 31040592 | UB163: 31040592 | UC163: 31040592 | UD163: 31040592 | UE163: 31040592 | UF163: 31040592 | UG163: 31040592 | UH163: 31040592 | UI163: 31040592 | UJ163: 31040592 | UK163: 31040592 | UL163: 31040592 | UM163: 31040592 | UN163: 31040592 | UO163: 31040592 | UP163: 31040592 | UQ163: 31040592 | UR163: 31040592 | US163: 31040592 | UT163: 31040592 | UU163: 31040592 | UV163: 31040592 | UW163: 31040592 | UX163: 31040592 | UY163: 31040592 | UZ163: 31040592 | VA163: 31040592 | VB163: 31040592 | VC163: 31040592 | VD163: 31040592 | VE163: 31040592 | VF163: 31040592 | VG163: 31040592 | VH163: 31040592 | VI163: 31040592 | VJ163: 31040592 | VK163: 31040592 | VL163: 31040592 | VM163: 31040592
K164: Sewerage Network | M164: 5111121.8 | N164: 4977488.4 | O164: 4189784.5 | P164: 74260.44 | Q164: 61270.39 | R164: 53207.64 | S164: Cum BL Project Total Cost | DT164: 426.91 | DU164: 900.58 | DV164: 1374.24 | DW164: 1374.24 | DX164: 1847.91 | DY164: 2321.58 | DZ164: 2795.25 | EA164: 3268.92 | EB164: 3742.59 | EC164: 4216.25 | ED164: 4216.25 | EE164: 4689.92 | EF164: 5163.59 | EG164: 5637.26 | EH164: 6110.93 | EI164: 6584.6 | EJ164: 7058.26 | EK164: 7058.26 | EL164: 7531.93 | EM164: 8005.6 | EN164: 8479.27 | EO164: 8952.94 | EP164: 9426.61 | EQ164: 9900.27 | ER164: 9900.27 | ES164: 10511.54 | ET164: 11194.89 | EU164: 11878.26 | EV164: 13721.38 | EW164: 15763.99 | EX164: 18066.8 | EY164: 18066.8 | EZ164: 20369.62 | FA164: 23166.21 | FB164: 26020.75 | FC164: 28904.02 | FD164: 31787.3 | FE164: 38606.68 | FF164: 38606.68 | FG164: 42852.54 | FH164: 47189.39 | FI164: 51234.51 | FJ164: 65370.34 | FK164: 69381.54 | FL164: 75473.05 | FM164: 75473.05 | FN164: 82456.73 | FO164: 86949.91 | FP164: 91640.03 | FQ164: 96666.73 | FR164: 100766.25 | FS164: 105090.46 | FT164: 105090.46 | FU164: 129357.34 | FV164: 148230.55 | FW164: 161951.13 | FX164: 174976.9 | FY164: 189360.54 | FZ164: 214714.49 | GA164: 214714.49 | GB164: 244604.67 | GC164: 279324.55 | GD164: 312559.54 | GE164: 340917.79 | GF164: 370687.4 | GG164: 382852.61 | GH164: 382852.61 | GI164: 386512.68 | GJ164: 389516.96 | GK164: 392313.69 | GL164: 395110.41 | GM164: 397962.75 | GN164: 400923.27 | GO164: 400923.27 | GP164: 403926.59 | GQ164: 407013.14 | GR164: 410235.01 | GS164: 413727.31 | GT164: 417724.98 | GU164: 422354.11 | GV164: 422354.11 | GW164: 427762.18 | GX164: 433403 | GY164: 439114.29 | GZ164: 444874.95 | HA164: 452078.05 | HB164: 462313.57 | HC164: 462313.57 | HD164: 500096.72 | HE164: 526246.5 | HF164: 546543.24 | HG164: 601623.12 | HH164: 636794.78 | HI164: 702020.12 | HJ164: 702020.12 | HK164: 783791.2 | HL164: 831689.04 | HM164: 938982.65 | HN164: 945230.93 | HO164: 951293.53 | HP164: 967402.14 | HQ164: 967402.14 | HR164: 972214.93 | HS164: 972214.93 | HT164: 1008192.8 | HU164: 1013055.4 | HV164: 1019876.2 | HW164: 1030307.9 | HX164: 1030307.9 | HY164: 1043392.8 | HZ164: 1053779.4 | IA164: 1070950.7 | IB164: 1087604.6 | IC164: 1117958.7 | ID164: 1154416.6 | IE164: 1154416.6 | IF164: 1164954 | IG164: 1175186.6 | IH164: 1186542.7 | II164: 1198469.9 | IJ164: 1210156.9 | IK164: 1222007.5 | IL164: 1222007.5 | IM164: 1232440.2 | IN164: 1244242 | IO164: 1256176.1 | IP164: 1270757.1 | IQ164: 1288106 | IR164: 1288106 | IS164: 1288106 | IT164: 1288106 | IU164: 1288106 | IV164: 1288106 | IW164: 1313790.9 | IX164: 1327902.8 | IY164: 1344578.2 | IZ164: 1344578.2 | JA164: 1355903.9 | JB164: 1366144.4 | JC164: 1379652.7 | JD164: 1397441 | JE164: 1422747.6 | JF164: 1458378.3 | JG164: 1458378.3 | JH164: 1477823.5 | JI164: 1502563.7 | JJ164: 1539398.4 | JK164: 1571500.2 | JL164: 1612827.7 | JM164: 1652120.8 | JN164: 1652120.8 | JO164: 1657890.7 | JP164: 1663995.1 | JQ164: 1670905.6 | JR164: 1678520.8 | JS164: 1689076.4 | JT164: 1707207.9 | JU164: 1707207.9 | JV164: 1725821.4 | JW164: 1739429.3 | JX164: 1758955.2 | JY164: 1775751.1 | JZ164: 1798932.7 | KA164: 1822644.7 | KB164: 1822644.7 | KC164: 1847089.1 | KD164: 1888861 | KE164: 1948021.7 | KF164: 1963548.9 | KG164: 1981161.2 | KH164: 2000321.4 | KI164: 2000321.4 | KJ164: 2025183.1 | KK164: 2046231.6 | KL164: 2067387.2 | KM164: 2088811.1 | KN164: 2115398.3 | KO164: 2145821.3 | KP164: 2145821.3 | KQ164: 2182964.3 | KR164: 2228516.3 | KS164: 2267975.1 | KT164: 2292738.4 | KU164: 2319490.6 | KV164: 2346895.2 | KW164: 2346895.2 | KX164: 2375468.4 | KY164: 2406803.8 | KZ164: 2438143.2 | LA164: 2470916.9 | LB164: 2502530.6 | LC164: 2536313.7 | LD164: 2536313.7 | LE164: 2555566.5 | LF164: 2567259.5 | LG164: 2583840.4 | LH164: 2583840.4 | LI164: 2583840.4 | LJ164: 2583840.4 | LK164: 2583840.4 | LL164: 2583840.4 | LM164: 2589400.4 | LN164: 2595029.4 | LO164: 2600716.8 | LP164: 2607579.6 | LQ164: 2615910.2 | LR164: 2615910.2 | LS164: 2620720.4 | LT164: 2625636.8 | LU164: 2631298.1 | LV164: 2634466.5 | LW164: 2637694.3 | LX164: 2648200.6 | LY164: 2648200.6 | LZ164: 2662934.6 | MA164: 2677885.6 | MB164: 2700482 | MC164: 2735037.8 | MD164: 2752055.5 | ME164: 2758002 | MF164: 2758002 | MG164: 2764114.9 | MH164: 2770642.4 | MI164: 2778313.8 | MJ164: 2786649.7 | MK164: 2797809.1 | ML164: 2809225.1 | MM164: 2809225.1 | MN164: 2821618.3 | MO164: 2835648.1 | MP164: 2854163 | MQ164: 2874913.4 | MR164: 2895607 | MS164: 2911595.4 | MT164: 2911595.4 | MU164: 2926358.5 | MV164: 2941544.2 | MW164: 2956740.5 | MX164: 2970976 | MY164: 2982827.3 | MZ164: 2993803.2 | NA164: 2993803.2 | NB164: 3003620.9 | NC164: 3012259.3 | ND164: 3020998.6 | NE164: 3030154.1 | NF164: 3039314.9 | NG164: 3048477.4 | NH164: 3048477.4 | NI164: 3057679.7 | NJ164: 3067026.3 | NK164: 3076375.9 | NL164: 3085745.9 | NM164: 3095245.2 | NN164: 3104798.7 | NO164: 3104798.7 | NP164: 3114375.4 | NQ164: 3124051.5 | NR164: 3133800.8 | NS164: 3143675.6 | NT164: 3153613 | NU164: 3163653.7 | NV164: 3163653.7 | NW164: 3174222.6 | NX164: 3185939.3 | NY164: 3199102.9 | NZ164: 3214897.3 | OA164: 3231312.7 | OB164: 3249594.8 | OC164: 3249594.8 | OD164: 3268890.3 | OE164: 3288664.6 | OF164: 3309005.5 | OG164: 3330215.2 | OH164: 3352413.6 | OI164: 3375022.8 | OJ164: 3375022.8 | OK164: 3398773.3 | OL164: 3427750.4 | OM164: 3458593.6 | ON164: 3494776.7 | OO164: 3521367 | OP164: 3548444.5 | OQ164: 3548444.5 | OR164: 3575753.3 | OS164: 3601198.6 | OT164: 3625729.8 | OU164: 3650222.2 | OV164: 3669947.1 | OW164: 3687281.2 | OX164: 3687281.2 | OY164: 3701837 | OZ164: 3715613.9 | PA164: 3727022.9 | PB164: 3736981.1 | PC164: 3747123.4 | PD164: 3757340 | PE164: 3757340 | PF164: 3767778.6 | PG164: 3778790.6 | PH164: 3790942.6 | PI164: 3803927.2 | PJ164: 3816967.6 | PK164: 3830278 | PL164: 3830278 | PM164: 3844292.1 | PN164: 3858499.1 | PO164: 3872985.3 | PP164: 3887471.4 | PQ164: 4142980.4 | PR164: 4414623.3 | PS164: 4414623.3 | PT164: 4610211 | PU164: 4715297.7 | PV164: 4754549 | PW164: 4780270.7 | PX164: 4780270.7 | PY164: 4805392.8 | PZ164: 4805392.8 | QA164: 4838862.5 | QB164: 4853786.1 | QC164: 4860726.1 | QD164: 4867833.8 | QE164: 4875934.9 | QF164: 4888801.8 | QG164: 4888801.8 | QH164: 4902929.5 | QI164: 4920735.7 | QJ164: 4958200.9 | QK164: 4977488.4 | QL164: 4998541.3 | QM164: 5020967.4 | QN164: 5020967.4 | QO164: 5051253 | QP164: 5061778.8 | QQ164: 5066796.4 | QR164: 5071786 | QS164: 5074421.5 | QT164: 5078574.2 | QU164: 5078574.2 | QV164: 5082127.6 | QW164: 5086714 | QX164: 5092042.9 | QY164: 5092073.8 | QZ164: 5092104.7 | RA164: 5092135.6 | RB164: 5092135.6 | RC164: 5092188.2 | RD164: 5092260.2 | RE164: 5092348.3 | RF164: 5092449 | RG164: 5094640.2 | RH164: 5097437.6 | RI164: 5097437.6 | RJ164: 5101260.8 | RK164: 5109023.7 | RL164: 5111121.8 | RM164: 5111121.8 | RN164: 5111121.8 | RO164: 5111121.8 | RP164: 5111121.8 | RQ164: 5111121.8 | RR164: 5111121.8 | RS164: 5111121.8 | RT164: 5111121.8 | RU164: 5111121.8 | RV164: 5111121.8 | RW164: 5111121.8 | RX164: 5111121.8 | RY164: 5111121.8 | RZ164: 5111121.8 | SA164: 5111121.8 | SB164: 5111121.8 | SC164: 5111121.8 | SD164: 5111121.8 | SE164: 5111121.8 | SF164: 5111121.8 | SG164: 5111121.8 | SH164: 5111121.8 | SI164: 5111121.8 | SJ164: 5111121.8 | SK164: 5111121.8 | SL164: 5111121.8 | SM164: 5111121.8 | SN164: 5111121.8 | SO164: 5111121.8 | SP164: 5111121.8 | SQ164: 5111121.8 | SR164: 5111121.8 | SS164: 5111121.8 | ST164: 5111121.8 | SU164: 5111121.8 | SV164: 5111121.8 | SW164: 5111121.8 | SX164: 5111121.8 | SY164: 5111121.8 | SZ164: 5111121.8 | TA164: 5111121.8 | TB164: 5111121.8 | TC164: 5111121.8 | TD164: 5111121.8 | TE164: 5111121.8 | TF164: 5111121.8 | TG164: 5111121.8 | TH164: 5111121.8 | TI164: 5111121.8 | TJ164: 5111121.8 | TK164: 5111121.8 | TL164: 5111121.8 | TM164: 5111121.8 | TN164: 5111121.8 | TO164: 5111121.8 | TP164: 5111121.8 | TQ164: 5111121.8 | TR164: 5111121.8 | TS164: 5111121.8 | TT164: 5111121.8 | TU164: 5111121.8 | TV164: 5111121.8 | TW164: 5111121.8 | TX164: 5111121.8 | TY164: 5111121.8 | TZ164: 5111121.8 | UA164: 5111121.8 | UB164: 5111121.8 | UC164: 5111121.8 | UD164: 5111121.8 | UE164: 5111121.8 | UF164: 5111121.8 | UG164: 5111121.8 | UH164: 5111121.8 | UI164: 5111121.8 | UJ164: 5111121.8 | UK164: 5111121.8 | UL164: 5111121.8 | UM164: 5111121.8 | UN164: 5111121.8 | UO164: 5111121.8 | UP164: 5111121.8 | UQ164: 5111121.8 | UR164: 5111121.8 | US164: 5111121.8 | UT164: 5111121.8 | UU164: 5111121.8 | UV164: 5111121.8 | UW164: 5111121.8 | UX164: 5111121.8 | UY164: 5111121.8 | UZ164: 5111121.8 | VA164: 5111121.8 | VB164: 5111121.8 | VC164: 5111121.8 | VD164: 5111121.8 | VE164: 5111121.8 | VF164: 5111121.8 | VG164: 5111121.8 | VH164: 5111121.8 | VI164: 5111121.8 | VJ164: 5111121.8 | VK164: 5111121.8 | VL164: 5111121.8 | VM164: 5111121.8
K165: Engineering | M165: 0 | N165: 0 | O165: 0 | P165: 568.6 | Q165: 568.6 | R165: 568.6 | S165: Cum BL Project Total Cost
K166: Procurement | M166: 0 | N166: 0 | O166: 0 | P166: 10403.33 | Q166: 10209.94 | R166: 8522.73 | S166: Cum BL Project Total Cost
K167: Construction | M167: 5111121.8 | N167: 4977488.4 | O167: 4189784.5 | P167: 53551.26 | Q167: 50491.85 | R167: 37624.81 | S167: Cum BL Project Total Cost | DT167: 426.91 | DU167: 900.58 | DV167: 1374.24 | DW167: 1374.24 | DX167: 1847.91 | DY167: 2321.58 | DZ167: 2795.25 | EA167: 3268.92 | EB167: 3742.59 | EC167: 4216.25 | ED167: 4216.25 | EE167: 4689.92 | EF167: 5163.59 | EG167: 5637.26 | EH167: 6110.93 | EI167: 6584.6 | EJ167: 7058.26 | EK167: 7058.26 | EL167: 7531.93 | EM167: 8005.6 | EN167: 8479.27 | EO167: 8952.94 | EP167: 9426.61 | EQ167: 9900.27 | ER167: 9900.27 | ES167: 10511.54 | ET167: 11194.89 | EU167: 11878.26 | EV167: 13721.38 | EW167: 15763.99 | EX167: 18066.8 | EY167: 18066.8 | EZ167: 20369.62 | FA167: 23166.21 | FB167: 26020.75 | FC167: 28904.02 | FD167: 31787.3 | FE167: 38606.68 | FF167: 38606.68 | FG167: 42852.54 | FH167: 47189.39 | FI167: 51234.51 | FJ167: 65370.34 | FK167: 69381.54 | FL167: 75473.05 | FM167: 75473.05 | FN167: 82456.73 | FO167: 86949.91 | FP167: 91640.03 | FQ167: 96666.73 | FR167: 100766.25 | FS167: 105090.46 | FT167: 105090.46 | FU167: 129357.34 | FV167: 148230.55 | FW167: 161951.13 | FX167: 174976.9 | FY167: 189360.54 | FZ167: 214714.49 | GA167: 214714.49 | GB167: 244604.67 | GC167: 279324.55 | GD167: 312559.54 | GE167: 340917.79 | GF167: 370687.4 | GG167: 382852.61 | GH167: 382852.61 | GI167: 386512.68 | GJ167: 389516.96 | GK167: 392313.69 | GL167: 395110.41 | GM167: 397962.75 | GN167: 400923.27 | GO167: 400923.27 | GP167: 403926.59 | GQ167: 407013.14 | GR167: 410235.01 | GS167: 413727.31 | GT167: 417724.98 | GU167: 422354.11 | GV167: 422354.11 | GW167: 427762.18 | GX167: 433403 | GY167: 439114.29 | GZ167: 444874.95 | HA167: 452078.05 | HB167: 462313.57 | HC167: 462313.57 | HD167: 500096.72 | HE167: 526246.5 | HF167: 546543.24 | HG167: 601623.12 | HH167: 636794.78 | HI167: 702020.12 | HJ167: 702020.12 | HK167: 783791.2 | HL167: 831689.04 | HM167: 938982.65 | HN167: 945230.93 | HO167: 951293.53 | HP167: 967402.14 | HQ167: 967402.14 | HR167: 972214.93 | HS167: 972214.93 | HT167: 1008192.8 | HU167: 1013055.4 | HV167: 1019876.2 | HW167: 1030307.9 | HX167: 1030307.9 | HY167: 1043392.8 | HZ167: 1053779.4 | IA167: 1070950.7 | IB167: 1087604.6 | IC167: 1117958.7 | ID167: 1154416.6 | IE167: 1154416.6 | IF167: 1164954 | IG167: 1175186.6 | IH167: 1186542.7 | II167: 1198469.9 | IJ167: 1210156.9 | IK167: 1222007.5 | IL167: 1222007.5 | IM167: 1232440.2 | IN167: 1244242 | IO167: 1256176.1 | IP167: 1270757.1 | IQ167: 1288106 | IR167: 1288106 | IS167: 1288106 | IT167: 1288106 | IU167: 1288106 | IV167: 1288106 | IW167: 1313790.9 | IX167: 1327902.8 | IY167: 1344578.2 | IZ167: 1344578.2 | JA167: 1355903.9 | JB167: 1366144.4 | JC167: 1379652.7 | JD167: 1397441 | JE167: 1422747.6 | JF167: 1458378.3 | JG167: 1458378.3 | JH167: 1477823.5 | JI167: 1502563.7 | JJ167: 1539398.4 | JK167: 1571500.2 | JL167: 1612827.7 | JM167: 1652120.8 | JN167: 1652120.8 | JO167: 1657890.7 | JP167: 1663995.1 | JQ167: 1670905.6 | JR167: 1678520.8 | JS167: 1689076.4 | JT167: 1707207.9 | JU167: 1707207.9 | JV167: 1725821.4 | JW167: 1739429.3 | JX167: 1758955.2 | JY167: 1775751.1 | JZ167: 1798932.7 | KA167: 1822644.7 | KB167: 1822644.7 | KC167: 1847089.1 | KD167: 1888861 | KE167: 1948021.7 | KF167: 1963548.9 | KG167: 1981161.2 | KH167: 2000321.4 | KI167: 2000321.4 | KJ167: 2025183.1 | KK167: 2046231.6 | KL167: 2067387.2 | KM167: 2088811.1 | KN167: 2115398.3 | KO167: 2145821.3 | KP167: 2145821.3 | KQ167: 2182964.3 | KR167: 2228516.3 | KS167: 2267975.1 | KT167: 2292738.4 | KU167: 2319490.6 | KV167: 2346895.2 | KW167: 2346895.2 | KX167: 2375468.4 | KY167: 2406803.8 | KZ167: 2438143.2 | LA167: 2470916.9 | LB167: 2502530.6 | LC167: 2536313.7 | LD167: 2536313.7 | LE167: 2555566.5 | LF167: 2567259.5 | LG167: 2583840.4 | LH167: 2583840.4 | LI167: 2583840.4 | LJ167: 2583840.4 | LK167: 2583840.4 | LL167: 2583840.4 | LM167: 2589400.4 | LN167: 2595029.4 | LO167: 2600716.8 | LP167: 2607579.6 | LQ167: 2615910.2 | LR167: 2615910.2 | LS167: 2620720.4 | LT167: 2625636.8 | LU167: 2631298.1 | LV167: 2634466.5 | LW167: 2637694.3 | LX167: 2648200.6 | LY167: 2648200.6 | LZ167: 2662934.6 | MA167: 2677885.6 | MB167: 2700482 | MC167: 2735037.8 | MD167: 2752055.5 | ME167: 2758002 | MF167: 2758002 | MG167: 2764114.9 | MH167: 2770642.4 | MI167: 2778313.8 | MJ167: 2786649.7 | MK167: 2797809.1 | ML167: 2809225.1 | MM167: 2809225.1 | MN167: 2821618.3 | MO167: 2835648.1 | MP167: 2854163 | MQ167: 2874913.4 | MR167: 2895607 | MS167: 2911595.4 | MT167: 2911595.4 | MU167: 2926358.5 | MV167: 2941544.2 | MW167: 2956740.5 | MX167: 2970976 | MY167: 2982827.3 | MZ167: 2993803.2 | NA167: 2993803.2 | NB167: 3003620.9 | NC167: 3012259.3 | ND167: 3020998.6 | NE167: 3030154.1 | NF167: 3039314.9 | NG167: 3048477.4 | NH167: 3048477.4 | NI167: 3057679.7 | NJ167: 3067026.3 | NK167: 3076375.9 | NL167: 3085745.9 | NM167: 3095245.2 | NN167: 3104798.7 | NO167: 3104798.7 | NP167: 3114375.4 | NQ167: 3124051.5 | NR167: 3133800.8 | NS167: 3143675.6 | NT167: 3153613 | NU167: 3163653.7 | NV167: 3163653.7 | NW167: 3174222.6 | NX167: 3185939.3 | NY167: 3199102.9 | NZ167: 3214897.3 | OA167: 3231312.7 | OB167: 3249594.8 | OC167: 3249594.8 | OD167: 3268890.3 | OE167: 3288664.6 | OF167: 3309005.5 | OG167: 3330215.2 | OH167: 3352413.6 | OI167: 3375022.8 | OJ167: 3375022.8 | OK167: 3398773.3 | OL167: 3427750.4 | OM167: 3458593.6 | ON167: 3494776.7 | OO167: 3521367 | OP167: 3548444.5 | OQ167: 3548444.5 | OR167: 3575753.3 | OS167: 3601198.6 | OT167: 3625729.8 | OU167: 3650222.2 | OV167: 3669947.1 | OW167: 3687281.2 | OX167: 3687281.2 | OY167: 3701837 | OZ167: 3715613.9 | PA167: 3727022.9 | PB167: 3736981.1 | PC167: 3747123.4 | PD167: 3757340 | PE167: 3757340 | PF167: 3767778.6 | PG167: 3778790.6 | PH167: 3790942.6 | PI167: 3803927.2 | PJ167: 3816967.6 | PK167: 3830278 | PL167: 3830278 | PM167: 3844292.1 | PN167: 3858499.1 | PO167: 3872985.3 | PP167: 3887471.4 | PQ167: 4142980.4 | PR167: 4414623.3 | PS167: 4414623.3 | PT167: 4610211 | PU167: 4715297.7 | PV167: 4754549 | PW167: 4780270.7 | PX167: 4780270.7 | PY167: 4805392.8 | PZ167: 4805392.8 | QA167: 4838862.5 | QB167: 4853786.1 | QC167: 4860726.1 | QD167: 4867833.8 | QE167: 4875934.9 | QF167: 4888801.8 | QG167: 4888801.8 | QH167: 4902929.5 | QI167: 4920735.7 | QJ167: 4958200.9 | QK167: 4977488.4 | QL167: 4998541.3 | QM167: 5020967.4 | QN167: 5020967.4 | QO167: 5051253 | QP167: 5061778.8 | QQ167: 5066796.4 | QR167: 5071786 | QS167: 5074421.5 | QT167: 5078574.2 | QU167: 5078574.2 | QV167: 5082127.6 | QW167: 5086714 | QX167: 5092042.9 | QY167: 5092073.8 | QZ167: 5092104.7 | RA167: 5092135.6 | RB167: 5092135.6 | RC167: 5092188.2 | RD167: 5092260.2 | RE167: 5092348.3 | RF167: 5092449 | RG167: 5094640.2 | RH167: 5097437.6 | RI167: 5097437.6 | RJ167: 5101260.8 | RK167: 5109023.7 | RL167: 5111121.8 | RM167: 5111121.8 | RN167: 5111121.8 | RO167: 5111121.8 | RP167: 5111121.8 | RQ167: 5111121.8 | RR167: 5111121.8 | RS167: 5111121.8 | RT167: 5111121.8 | RU167: 5111121.8 | RV167: 5111121.8 | RW167: 5111121.8 | RX167: 5111121.8 | RY167: 5111121.8 | RZ167: 5111121.8 | SA167: 5111121.8 | SB167: 5111121.8 | SC167: 5111121.8 | SD167: 5111121.8 | SE167: 5111121.8 | SF167: 5111121.8 | SG167: 5111121.8 | SH167: 5111121.8 | SI167: 5111121.8 | SJ167: 5111121.8 | SK167: 5111121.8 | SL167: 5111121.8 | SM167: 5111121.8 | SN167: 5111121.8 | SO167: 5111121.8 | SP167: 5111121.8 | SQ167: 5111121.8 | SR167: 5111121.8 | SS167: 5111121.8 | ST167: 5111121.8 | SU167: 5111121.8 | SV167: 5111121.8 | SW167: 5111121.8 | SX167: 5111121.8 | SY167: 5111121.8 | SZ167: 5111121.8 | TA167: 5111121.8 | TB167: 5111121.8 | TC167: 5111121.8 | TD167: 5111121.8 | TE167: 5111121.8 | TF167: 5111121.8 | TG167: 5111121.8 | TH167: 5111121.8 | TI167: 5111121.8 | TJ167: 5111121.8 | TK167: 5111121.8 | TL167: 5111121.8 | TM167: 5111121.8 | TN167: 5111121.8 | TO167: 5111121.8 | TP167: 5111121.8 | TQ167: 5111121.8 | TR167: 5111121.8 | TS167: 5111121.8 | TT167: 5111121.8 | TU167: 5111121.8 | TV167: 5111121.8 | TW167: 5111121.8 | TX167: 5111121.8 | TY167: 5111121.8 | TZ167: 5111121.8 | UA167: 5111121.8 | UB167: 5111121.8 | UC167: 5111121.8 | UD167: 5111121.8 | UE167: 5111121.8 | UF167: 5111121.8 | UG167: 5111121.8 | UH167: 5111121.8 | UI167: 5111121.8 | UJ167: 5111121.8 | UK167: 5111121.8 | UL167: 5111121.8 | UM167: 5111121.8 | UN167: 5111121.8 | UO167: 5111121.8 | UP167: 5111121.8 | UQ167: 5111121.8 | UR167: 5111121.8 | US167: 5111121.8 | UT167: 5111121.8 | UU167: 5111121.8 | UV167: 5111121.8 | UW167: 5111121.8 | UX167: 5111121.8 | UY167: 5111121.8 | UZ167: 5111121.8 | VA167: 5111121.8 | VB167: 5111121.8 | VC167: 5111121.8 | VD167: 5111121.8 | VE167: 5111121.8 | VF167: 5111121.8 | VG167: 5111121.8 | VH167: 5111121.8 | VI167: 5111121.8 | VJ167: 5111121.8 | VK167: 5111121.8 | VL167: 5111121.8 | VM167: 5111121.8
K168: Testing & Commissioning | M168: 0 | N168: 0 | O168: 0 | P168: 9737.25 | Q168: 0 | R168: 6491.5 | S168: Cum BL Project Total Cost
K169: Storm Water Network | M169: 21808728 | N169: 20044696 | O169: 18078712 | P169: 143781.21 | Q169: 122269.09 | R169: 112215.05 | S169: Cum BL Project Total Cost | FB169: 198.41 | FC169: 496.02 | FD169: 1125.09 | FE169: 1710.98 | FF169: 1710.98 | FG169: 2071.38 | FH169: 2501.58 | FI169: 2867.04 | FJ169: 3250.91 | FK169: 3792.58 | FL169: 4639.72 | FM169: 4639.72 | FN169: 8631.11 | FO169: 16084.7 | FP169: 17020.76 | FQ169: 17981.33 | FR169: 18941.9 | FS169: 19902.47 | FT169: 19902.47 | FU169: 21265.92 | FV169: 22889.05 | FW169: 24676.02 | FX169: 27674.14 | FY169: 31488.59 | FZ169: 39083.85 | GA169: 39083.85 | GB169: 52215.11 | GC169: 63772.37 | GD169: 82679.69 | GE169: 95998.57 | GF169: 109383.22 | GG169: 117023.69 | GH169: 117023.69 | GI169: 119724.49 | GJ169: 122240.46 | GK169: 124303.56 | GL169: 125368.34 | GM169: 126585.43 | GN169: 127876.84 | GO169: 127876.84 | GP169: 129673.23 | GQ169: 131674.38 | GR169: 133782.22 | GS169: 135905.68 | GT169: 139617.15 | GU169: 149406.26 | GV169: 149406.26 | GW169: 160863.2 | GX169: 166750.76 | GY169: 176991.32 | GZ169: 179701.77 | HA169: 182412.66 | HB169: 185237.27 | HC169: 185237.27 | HD169: 189565.21 | HE169: 196519.84 | HF169: 204135.83 | HG169: 212155.32 | HH169: 244605.09 | HI169: 296384.67 | HJ169: 296384.67 | HK169: 335967.73 | HL169: 355878.83 | HM169: 411581.36 | HN169: 529795.29 | HO169: 544506.13 | HP169: 560599.14 | HQ169: 560599.14 | HR169: 619580.26 | HS169: 619580.26 | HT169: 689424.08 | HU169: 866982 | HV169: 1156270.3 | HW169: 1452663.8 | HX169: 1452663.8 | HY169: 1553812.7 | HZ169: 1787672.8 | IA169: 1959505.3 | IB169: 2021309.9 | IC169: 2172131 | ID169: 2922046.2 | IE169: 2922046.2 | IF169: 3066353.8 | IG169: 3219151.3 | IH169: 3486910.2 | II169: 3700053.1 | IJ169: 3855753.9 | IK169: 4167343.4 | IL169: 4167343.4 | IM169: 4570322.2 | IN169: 4676470.7 | IO169: 4724668.2 | IP169: 4733061.6 | IQ169: 4744351.7 | IR169: 4744351.7 | IS169: 4744351.7 | IT169: 4744351.7 | IU169: 4744351.7 | IV169: 4744351.7 | IW169: 4764611.4 | IX169: 4784667.5 | IY169: 4794184.2 | IZ169: 4794184.2 | JA169: 4803802.4 | JB169: 4811868.6 | JC169: 4823663.7 | JD169: 4841714.3 | JE169: 4858807.8 | JF169: 4870056.7 | JG169: 4870056.7 | JH169: 4886709.7 | JI169: 4900571 | JJ169: 4923647.7 | JK169: 4940320.4 | JL169: 4967657.6 | JM169: 5003767 | JN169: 5003767 | JO169: 5029296.5 | JP169: 5052265.3 | JQ169: 5081742.5 | JR169: 5118715 | JS169: 5144948.5 | JT169: 5174770.7 | JU169: 5174770.7 | JV169: 5206829.6 | JW169: 5238894.6 | JX169: 5285800.5 | JY169: 5342354.7 | JZ169: 5398761.2 | KA169: 5460833.9 | KB169: 5460833.9 | KC169: 5531898.4 | KD169: 5613478 | KE169: 5683247.8 | KF169: 5756352 | KG169: 5828170.3 | KH169: 5900036 | KI169: 5900036 | KJ169: 5987188.4 | KK169: 6089200.3 | KL169: 6191042.1 | KM169: 6292361.3 | KN169: 6406898.8 | KO169: 6517418.9 | KP169: 6517418.9 | KQ169: 6626494.9 | KR169: 6710830.8 | KS169: 6774652.4 | KT169: 6819776.9 | KU169: 6861695.1 | KV169: 6895565.8 | KW169: 6895565.8 | KX169: 6928497.8 | KY169: 6958719.9 | KZ169: 6988628 | LA169: 7020171.6 | LB169: 7052214.2 | LC169: 7084240.1 | LD169: 7084240.1 | LE169: 7117413.9 | LF169: 7147315.8 | LG169: 7177686.1 | LH169: 7177686.1 | LI169: 7177686.1 | LJ169: 7177686.1 | LK169: 7177686.1 | LL169: 7177686.1 | LM169: 7208644.8 | LN169: 7251584.5 | LO169: 7291688.5 | LP169: 7331523.1 | LQ169: 7369300.1 | LR169: 7369300.1 | LS169: 7421503.5 | LT169: 7510791.7 | LU169: 7569865.1 | LV169: 7611474.9 | LW169: 7681294.8 | LX169: 7740835.1 | LY169: 7740835.1 | LZ169: 7812569.9 | MA169: 7882368.1 | MB169: 7934384.3 | MC169: 7987094.4 | MD169: 8040210.3 | ME169: 8095059 | MF169: 8095059 | MG169: 8155367.4 | MH169: 8221064.3 | MI169: 8291893.1 | MJ169: 8364027.3 | MK169: 8435998.2 | ML169: 8503068.7 | MM169: 8503068.7 | MN169: 8568233.4 | MO169: 8637612.1 | MP169: 8707732.9 | MQ169: 8776852.5 | MR169: 8843584.5 | MS169: 8904279.4 | MT169: 8904279.4 | MU169: 8961329.5 | MV169: 9016946.5 | MW169: 9072106.5 | MX169: 9124972.3 | MY169: 9177657.2 | MZ169: 9230471.5 | NA169: 9230471.5 | NB169: 9282810.4 | NC169: 9335129.2 | ND169: 9387499.5 | NE169: 9440054.1 | NF169: 9492705.4 | NG169: 9545387.7 | NH169: 9545387.7 | NI169: 9598138 | NJ169: 9651481.9 | NK169: 9706212.4 | NL169: 9762585.3 | NM169: 9820787.8 | NN169: 9879708 | NO169: 9879708 | NP169: 9939188.1 | NQ169: 9999992.8 | NR169: 10064025 | NS169: 10129178 | NT169: 10196084 | NU169: 10267213 | NV169: 10267213 | NW169: 10345305 | NX169: 10425642 | NY169: 10508479 | NZ169: 10593529 | OA169: 10684348 | OB169: 10779541 | OC169: 10779541 | OD169: 10880272 | OE169: 10987327 | OF169: 11097764 | OG169: 11211789 | OH169: 11338638 | OI169: 11471663 | OJ169: 11471663 | OK169: 11625260 | OL169: 11812888 | OM169: 11965122 | ON169: 12105272 | OO169: 12247129 | OP169: 12391593 | OQ169: 12391593 | OR169: 12536029 | OS169: 12684961 | OT169: 12834548 | OU169: 12984690 | OV169: 13139122 | OW169: 13299814 | OX169: 13299814 | OY169: 13469913 | OZ169: 13644746 | PA169: 13827960 | PB169: 14016998 | PC169: 14212562 | PD169: 14410778 | PE169: 14410778 | PF169: 14614033 | PG169: 14825134 | PH169: 15052111 | PI169: 15288639 | PJ169: 15525213 | PK169: 15762095 | PL169: 15762095 | PM169: 16031402 | PN169: 16283009 | PO169: 16519630 | PP169: 16768642 | PQ169: 17233702 | PR169: 18047938 | PS169: 18047938 | PT169: 18687516 | PU169: 18829563 | PV169: 18973839 | PW169: 19098035 | PX169: 19098035 | PY169: 19261940 | PZ169: 19261940 | QA169: 19462002 | QB169: 19630656 | QC169: 19668298 | QD169: 19719018 | QE169: 19798443 | QF169: 19846556 | QG169: 19846556 | QH169: 19891337 | QI169: 19936194 | QJ169: 19976497 | QK169: 20044696 | QL169: 20171116 | QM169: 20302811 | QN169: 20302811 | QO169: 20356488 | QP169: 20427809 | QQ169: 20524180 | QR169: 20565812 | QS169: 20650962 | QT169: 20690889 | QU169: 20690889 | QV169: 20732433 | QW169: 20824705 | QX169: 20875722 | QY169: 20927006 | QZ169: 21020115 | RA169: 21066147 | RB169: 21066147 | RC169: 21119747 | RD169: 21203633 | RE169: 21263962 | RF169: 21304036 | RG169: 21364125 | RH169: 21424010 | RI169: 21424010 | RJ169: 21461190 | RK169: 21482887 | RL169: 21519240 | RM169: 21532378 | RN169: 21552930 | RO169: 21580203 | RP169: 21580203 | RQ169: 21602634 | RR169: 21622439 | RS169: 21638856 | RT169: 21655624 | RU169: 21690295 | RV169: 21771291 | RW169: 21771291 | RX169: 21773394 | RY169: 21775848 | RZ169: 21781807 | SA169: 21787191 | SB169: 21793473 | SC169: 21808728 | SD169: 21808728 | SE169: 21808728 | SF169: 21808728 | SG169: 21808728 | SH169: 21808728 | SI169: 21808728 | SJ169: 21808728 | SK169: 21808728 | SL169: 21808728 | SM169: 21808728 | SN169: 21808728 | SO169: 21808728 | SP169: 21808728 | SQ169: 21808728 | SR169: 21808728 | SS169: 21808728 | ST169: 21808728 | SU169: 21808728 | SV169: 21808728 | SW169: 21808728 | SX169: 21808728 | SY169: 21808728 | SZ169: 21808728 | TA169: 21808728 | TB169: 21808728 | TC169: 21808728 | TD169: 21808728 | TE169: 21808728 | TF169: 21808728 | TG169: 21808728 | TH169: 21808728 | TI169: 21808728 | TJ169: 21808728 | TK169: 21808728 | TL169: 21808728 | TM169: 21808728 | TN169: 21808728 | TO169: 21808728 | TP169: 21808728 | TQ169: 21808728 | TR169: 21808728 | TS169: 21808728 | TT169: 21808728 | TU169: 21808728 | TV169: 21808728 | TW169: 21808728 | TX169: 21808728 | TY169: 21808728 | TZ169: 21808728 | UA169: 21808728 | UB169: 21808728 | UC169: 21808728 | UD169: 21808728 | UE169: 21808728 | UF169: 21808728 | UG169: 21808728 | UH169: 21808728 | UI169: 21808728 | UJ169: 21808728 | UK169: 21808728 | UL169: 21808728 | UM169: 21808728 | UN169: 21808728 | UO169: 21808728 | UP169: 21808728 | UQ169: 21808728 | UR169: 21808728 | US169: 21808728 | UT169: 21808728 | UU169: 21808728 | UV169: 21808728 | UW169: 21808728 | UX169: 21808728 | UY169: 21808728 | UZ169: 21808728 | VA169: 21808728 | VB169: 21808728 | VC169: 21808728 | VD169: 21808728 | VE169: 21808728 | VF169: 21808728 | VG169: 21808728 | VH169: 21808728 | VI169: 21808728 | VJ169: 21808728 | VK169: 21808728 | VL169: 21808728 | VM169: 21808728
K170: Engineering | M170: 0 | N170: 0 | O170: 0 | P170: 984.12 | Q170: 984.12 | R170: 984.12 | S170: Cum BL Project Total Cost
K171: Procurement | M171: 0 | N171: 0 | O171: 0 | P171: 14474.2 | Q171: 14439.41 | R171: 13952.76 | S171: Cum BL Project Total Cost
K172: Construction | M172: 21808728 | N172: 20044696 | O172: 18078712 | P172: 118164.9 | Q172: 106845.57 | R172: 90786.68 | S172: Cum BL Project Total Cost | FB172: 198.41 | FC172: 496.02 | FD172: 1125.09 | FE172: 1710.98 | FF172: 1710.98 | FG172: 2071.38 | FH172: 2501.58 | FI172: 2867.04 | FJ172: 3250.91 | FK172: 3792.58 | FL172: 4639.72 | FM172: 4639.72 | FN172: 8631.11 | FO172: 16084.7 | FP172: 17020.76 | FQ172: 17981.33 | FR172: 18941.9 | FS172: 19902.47 | FT172: 19902.47 | FU172: 21265.92 | FV172: 22889.05 | FW172: 24676.02 | FX172: 27674.14 | FY172: 31488.59 | FZ172: 39083.85 | GA172: 39083.85 | GB172: 52215.11 | GC172: 63772.37 | GD172: 82679.69 | GE172: 95998.57 | GF172: 109383.22 | GG172: 117023.69 | GH172: 117023.69 | GI172: 119724.49 | GJ172: 122240.46 | GK172: 124303.56 | GL172: 125368.34 | GM172: 126585.43 | GN172: 127876.84 | GO172: 127876.84 | GP172: 129673.23 | GQ172: 131674.38 | GR172: 133782.22 | GS172: 135905.68 | GT172: 139617.15 | GU172: 149406.26 | GV172: 149406.26 | GW172: 160863.2 | GX172: 166750.76 | GY172: 176991.32 | GZ172: 179701.77 | HA172: 182412.66 | HB172: 185237.27 | HC172: 185237.27 | HD172: 189565.21 | HE172: 196519.84 | HF172: 204135.83 | HG172: 212155.32 | HH172: 244605.09 | HI172: 296384.67 | HJ172: 296384.67 | HK172: 335967.73 | HL172: 355878.83 | HM172: 411581.36 | HN172: 529795.29 | HO172: 544506.13 | HP172: 560599.14 | HQ172: 560599.14 | HR172: 619580.26 | HS172: 619580.26 | HT172: 689424.08 | HU172: 866982 | HV172: 1156270.3 | HW172: 1452663.8 | HX172: 1452663.8 | HY172: 1553812.7 | HZ172: 1787672.8 | IA172: 1959505.3 | IB172: 2021309.9 | IC172: 2172131 | ID172: 2922046.2 | IE172: 2922046.2 | IF172: 3066353.8 | IG172: 3219151.3 | IH172: 3486910.2 | II172: 3700053.1 | IJ172: 3855753.9 | IK172: 4167343.4 | IL172: 4167343.4 | IM172: 4570322.2 | IN172: 4676470.7 | IO172: 4724668.2 | IP172: 4733061.6 | IQ172: 4744351.7 | IR172: 4744351.7 | IS172: 4744351.7 | IT172: 4744351.7 | IU172: 4744351.7 | IV172: 4744351.7 | IW172: 4764611.4 | IX172: 4784667.5 | IY172: 4794184.2 | IZ172: 4794184.2 | JA172: 4803802.4 | JB172: 4811868.6 | JC172: 4823663.7 | JD172: 4841714.3 | JE172: 4858807.8 | JF172: 4870056.7 | JG172: 4870056.7 | JH172: 4886709.7 | JI172: 4900571 | JJ172: 4923647.7 | JK172: 4940320.4 | JL172: 4967657.6 | JM172: 5003767 | JN172: 5003767 | JO172: 5029296.5 | JP172: 5052265.3 | JQ172: 5081742.5 | JR172: 5118715 | JS172: 5144948.5 | JT172: 5174770.7 | JU172: 5174770.7 | JV172: 5206829.6 | JW172: 5238894.6 | JX172: 5285800.5 | JY172: 5342354.7 | JZ172: 5398761.2 | KA172: 5460833.9 | KB172: 5460833.9 | KC172: 5531898.4 | KD172: 5613478 | KE172: 5683247.8 | KF172: 5756352 | KG172: 5828170.3 | KH172: 5900036 | KI172: 5900036 | KJ172: 5987188.4 | KK172: 6089200.3 | KL172: 6191042.1 | KM172: 6292361.3 | KN172: 6406898.8 | KO172: 6517418.9 | KP172: 6517418.9 | KQ172: 6626494.9 | KR172: 6710830.8 | KS172: 6774652.4 | KT172: 6819776.9 | KU172: 6861695.1 | KV172: 6895565.8 | KW172: 6895565.8 | KX172: 6928497.8 | KY172: 6958719.9 | KZ172: 6988628 | LA172: 7020171.6 | LB172: 7052214.2 | LC172: 7084240.1 | LD172: 7084240.1 | LE172: 7117413.9 | LF172: 7147315.8 | LG172: 7177686.1 | LH172: 7177686.1 | LI172: 7177686.1 | LJ172: 7177686.1 | LK172: 7177686.1 | LL172: 7177686.1 | LM172: 7208644.8 | LN172: 7251584.5 | LO172: 7291688.5 | LP172: 7331523.1 | LQ172: 7369300.1 | LR172: 7369300.1 | LS172: 7421503.5 | LT172: 7510791.7 | LU172: 7569865.1 | LV172: 7611474.9 | LW172: 7681294.8 | LX172: 7740835.1 | LY172: 7740835.1 | LZ172: 7812569.9 | MA172: 7882368.1 | MB172: 7934384.3 | MC172: 7987094.4 | MD172: 8040210.3 | ME172: 8095059 | MF172: 8095059 | MG172: 8155367.4 | MH172: 8221064.3 | MI172: 8291893.1 | MJ172: 8364027.3 | MK172: 8435998.2 | ML172: 8503068.7 | MM172: 8503068.7 | MN172: 8568233.4 | MO172: 8637612.1 | MP172: 8707732.9 | MQ172: 8776852.5 | MR172: 8843584.5 | MS172: 8904279.4 | MT172: 8904279.4 | MU172: 8961329.5 | MV172: 9016946.5 | MW172: 9072106.5 | MX172: 9124972.3 | MY172: 9177657.2 | MZ172: 9230471.5 | NA172: 9230471.5 | NB172: 9282810.4 | NC172: 9335129.2 | ND172: 9387499.5 | NE172: 9440054.1 | NF172: 9492705.4 | NG172: 9545387.7 | NH172: 9545387.7 | NI172: 9598138 | NJ172: 9651481.9 | NK172: 9706212.4 | NL172: 9762585.3 | NM172: 9820787.8 | NN172: 9879708 | NO172: 9879708 | NP172: 9939188.1 | NQ172: 9999992.8 | NR172: 10064025 | NS172: 10129178 | NT172: 10196084 | NU172: 10267213 | NV172: 10267213 | NW172: 10345305 | NX172: 10425642 | NY172: 10508479 | NZ172: 10593529 | OA172: 10684348 | OB172: 10779541 | OC172: 10779541 | OD172: 10880272 | OE172: 10987327 | OF172: 11097764 | OG172: 11211789 | OH172: 11338638 | OI172: 11471663 | OJ172: 11471663 | OK172: 11625260 | OL172: 11812888 | OM172: 11965122 | ON172: 12105272 | OO172: 12247129 | OP172: 12391593 | OQ172: 12391593 | OR172: 12536029 | OS172: 12684961 | OT172: 12834548 | OU172: 12984690 | OV172: 13139122 | OW172: 13299814 | OX172: 13299814 | OY172: 13469913 | OZ172: 13644746 | PA172: 13827960 | PB172: 14016998 | PC172: 14212562 | PD172: 14410778 | PE172: 14410778 | PF172: 14614033 | PG172: 14825134 | PH172: 15052111 | PI172: 15288639 | PJ172: 15525213 | PK172: 15762095 | PL172: 15762095 | PM172: 16031402 | PN172: 16283009 | PO172: 16519630 | PP172: 16768642 | PQ172: 17233702 | PR172: 18047938 | PS172: 18047938 | PT172: 18687516 | PU172: 18829563 | PV172: 18973839 | PW172: 19098035 | PX172: 19098035 | PY172: 19261940 | PZ172: 19261940 | QA172: 19462002 | QB172: 19630656 | QC172: 19668298 | QD172: 19719018 | QE172: 19798443 | QF172: 19846556 | QG172: 19846556 | QH172: 19891337 | QI172: 19936194 | QJ172: 19976497 | QK172: 20044696 | QL172: 20171116 | QM172: 20302811 | QN172: 20302811 | QO172: 20356488 | QP172: 20427809 | QQ172: 20524180 | QR172: 20565812 | QS172: 20650962 | QT172: 20690889 | QU172: 20690889 | QV172: 20732433 | QW172: 20824705 | QX172: 20875722 | QY172: 20927006 | QZ172: 21020115 | RA172: 21066147 | RB172: 21066147 | RC172: 21119747 | RD172: 21203633 | RE172: 21263962 | RF172: 21304036 | RG172: 21364125 | RH172: 21424010 | RI172: 21424010 | RJ172: 21461190 | RK172: 21482887 | RL172: 21519240 | RM172: 21532378 | RN172: 21552930 | RO172: 21580203 | RP172: 21580203 | RQ172: 21602634 | RR172: 21622439 | RS172: 21638856 | RT172: 21655624 | RU172: 21690295 | RV172: 21771291 | RW172: 21771291 | RX172: 21773394 | RY172: 21775848 | RZ172: 21781807 | SA172: 21787191 | SB172: 21793473 | SC172: 21808728 | SD172: 21808728 | SE172: 21808728 | SF172: 21808728 | SG172: 21808728 | SH172: 21808728 | SI172: 21808728 | SJ172: 21808728 | SK172: 21808728 | SL172: 21808728 | SM172: 21808728 | SN172: 21808728 | SO172: 21808728 | SP172: 21808728 | SQ172: 21808728 | SR172: 21808728 | SS172: 21808728 | ST172: 21808728 | SU172: 21808728 | SV172: 21808728 | SW172: 21808728 | SX172: 21808728 | SY172: 21808728 | SZ172: 21808728 | TA172: 21808728 | TB172: 21808728 | TC172: 21808728 | TD172: 21808728 | TE172: 21808728 | TF172: 21808728 | TG172: 21808728 | TH172: 21808728 | TI172: 21808728 | TJ172: 21808728 | TK172: 21808728 | TL172: 21808728 | TM172: 21808728 | TN172: 21808728 | TO172: 21808728 | TP172: 21808728 | TQ172: 21808728 | TR172: 21808728 | TS172: 21808728 | TT172: 21808728 | TU172: 21808728 | TV172: 21808728 | TW172: 21808728 | TX172: 21808728 | TY172: 21808728 | TZ172: 21808728 | UA172: 21808728 | UB172: 21808728 | UC172: 21808728 | UD172: 21808728 | UE172: 21808728 | UF172: 21808728 | UG172: 21808728 | UH172: 21808728 | UI172: 21808728 | UJ172: 21808728 | UK172: 21808728 | UL172: 21808728 | UM172: 21808728 | UN172: 21808728 | UO172: 21808728 | UP172: 21808728 | UQ172: 21808728 | UR172: 21808728 | US172: 21808728 | UT172: 21808728 | UU172: 21808728 | UV172: 21808728 | UW172: 21808728 | UX172: 21808728 | UY172: 21808728 | UZ172: 21808728 | VA172: 21808728 | VB172: 21808728 | VC172: 21808728 | VD172: 21808728 | VE172: 21808728 | VF172: 21808728 | VG172: 21808728 | VH172: 21808728 | VI172: 21808728 | VJ172: 21808728 | VK172: 21808728 | VL172: 21808728 | VM172: 21808728
K173: Testing & Commissioning | M173: 0 | N173: 0 | O173: 0 | P173: 10157.99 | Q173: 0 | R173: 6491.5 | S173: Cum BL Project Total Cost
K174: Potable Water Network | M174: 1954044.4 | N174: 1690361 | O174: 825178.44 | P174: 57934.51 | Q174: 42580.33 | R174: 28245.61 | S174: Cum BL Project Total Cost | GX174: 237.02 | GY174: 570.65 | GZ174: 1100.26 | HA174: 1629.88 | HB174: 13362.89 | HC174: 13362.89 | HD174: 27997.81 | HE174: 31391.55 | HF174: 31967.47 | HG174: 32543.39 | HH174: 33119.31 | HI174: 33695.23 | HJ174: 33695.23 | HK174: 34354.02 | HL174: 35040.73 | HM174: 36714.19 | HN174: 38389.71 | HO174: 39646.35 | HP174: 40902.99 | HQ174: 40902.99 | HR174: 42159.63 | HS174: 42159.63 | HT174: 43416.27 | HU174: 44672.91 | HV174: 45977.88 | HW174: 47305.52 | HX174: 47305.52 | HY174: 48926.95 | HZ174: 50619.3 | IA174: 52311.64 | IB174: 54003.99 | IC174: 55696.33 | ID174: 57447.04 | IE174: 57447.04 | IF174: 59306.13 | IG174: 61165.22 | IH174: 63134.6 | II174: 65160.52 | IJ174: 67186.44 | IK174: 69212.41 | IL174: 69212.41 | IM174: 71277.31 | IN174: 73358.67 | IO174: 75561.33 | IP174: 78192.36 | IQ174: 80985.74 | IR174: 80985.74 | IS174: 80985.74 | IT174: 80985.74 | IU174: 80985.74 | IV174: 80985.74 | IW174: 85404.73 | IX174: 89873.5 | IY174: 94423.01 | IZ174: 94423.01 | JA174: 99059.19 | JB174: 104091.49 | JC174: 109505.99 | JD174: 114966.37 | JE174: 120156.63 | JF174: 124725.96 | JG174: 124725.96 | JH174: 129066.15 | JI174: 132020.36 | JJ174: 132879.57 | JK174: 133738.79 | JL174: 134646.72 | JM174: 135649.03 | JN174: 135649.03 | JO174: 136748.6 | JP174: 138265.82 | JQ174: 139812.55 | JR174: 141383.57 | JS174: 143949.78 | JT174: 146730.9 | JU174: 146730.9 | JV174: 149537.9 | JW174: 152296.39 | JX174: 155117.52 | JY174: 158218.64 | JZ174: 161747.18 | KA174: 166041.94 | KB174: 166041.94 | KC174: 170479.9 | KD174: 175219.59 | KE174: 179986.23 | KF174: 184770.39 | KG174: 189606.26 | KH174: 194442.13 | KI174: 194442.13 | KJ174: 199378.78 | KK174: 204818.13 | KL174: 210668.75 | KM174: 217419.6 | KN174: 224639.57 | KO174: 230789.27 | KP174: 230789.27 | KQ174: 237337.8 | KR174: 243817.91 | KS174: 250599.47 | KT174: 257661.96 | KU174: 265336.04 | KV174: 273330.21 | KW174: 273330.21 | KX174: 281544.26 | KY174: 290116.22 | KZ174: 299058.76 | LA174: 308158.15 | LB174: 318480.41 | LC174: 328968.43 | LD174: 328968.43 | LE174: 341780.82 | LF174: 345472.66 | LG174: 349966.21 | LH174: 349966.21 | LI174: 349966.21 | LJ174: 349966.21 | LK174: 349966.21 | LL174: 349966.21 | LM174: 351364.23 | LN174: 352795.35 | LO174: 354284.16 | LP174: 355772.97 | LQ174: 357342.95 | LR174: 357342.95 | LS174: 358979.51 | LT174: 360682.22 | LU174: 362522.68 | LV174: 364445.59 | LW174: 366398.32 | LX174: 369005.62 | LY174: 369005.62 | LZ174: 372773.57 | MA174: 378513.63 | MB174: 391112.63 | MC174: 393208.11 | MD174: 395427.8 | ME174: 397672.27 | MF174: 397672.27 | MG174: 400040.3 | MH174: 402536.31 | MI174: 405346.81 | MJ174: 408192.85 | MK174: 410837.59 | ML174: 413476.25 | MM174: 413476.25 | MN174: 416133.4 | MO174: 418243.14 | MP174: 420445.01 | MQ174: 422651.38 | MR174: 424857.75 | MS174: 427064.11 | MT174: 427064.11 | MU174: 429270.48 | MV174: 431476.84 | MW174: 433743.6 | MX174: 436010.37 | MY174: 438277.13 | MZ174: 440543.89 | NA174: 440543.89 | NB174: 442810.66 | NC174: 445077.42 | ND174: 447344.18 | NE174: 449610.95 | NF174: 451877.71 | NG174: 454186.98 | NH174: 454186.98 | NI174: 456520.96 | NJ174: 458954.49 | NK174: 461422.33 | NL174: 463966.92 | NM174: 466693.47 | NN174: 469435.97 | NO174: 469435.97 | NP174: 472240.25 | NQ174: 475133.96 | NR174: 478103.22 | NS174: 481148.98 | NT174: 484413.92 | NU174: 487683.73 | NV174: 487683.73 | NW174: 491043.46 | NX174: 494478.57 | NY174: 497984.5 | NZ174: 501627.05 | OA174: 505272.75 | OB174: 509078.33 | OC174: 509078.33 | OD174: 512990.66 | OE174: 517052.5 | OF174: 521187.47 | OG174: 525452.05 | OH174: 529924.38 | OI174: 534546.58 | OJ174: 534546.58 | OK174: 539267.41 | OL174: 544136.97 | OM174: 549287.5 | ON174: 554689.67 | OO174: 560387.12 | OP174: 566126.62 | OQ174: 566126.62 | OR174: 571910.85 | OS174: 577737.76 | OT174: 583660.48 | OU174: 589737.56 | OV174: 595912.97 | OW174: 602192.39 | OX174: 602192.39 | OY174: 608548.21 | OZ174: 615131.77 | PA174: 621870.75 | PB174: 628736.01 | PC174: 636248.35 | PD174: 644815.38 | PE174: 644815.38 | PF174: 653748.16 | PG174: 663773.8 | PH174: 674154.55 | PI174: 684417.04 | PJ174: 695984.87 | PK174: 708118.07 | PL174: 708118.07 | PM174: 722649.82 | PN174: 741775.11 | PO174: 757033.38 | PP174: 775139.09 | PQ174: 872034.64 | PR174: 993154.75 | PS174: 993154.75 | PT174: 1225081.5 | PU174: 1365074.3 | PV174: 1424824.8 | PW174: 1456420 | PX174: 1456420 | PY174: 1494891.4 | PZ174: 1494891.4 | QA174: 1521821.6 | QB174: 1552284.8 | QC174: 1587298.3 | QD174: 1607668.1 | QE174: 1619701.9 | QF174: 1630981.4 | QG174: 1630981.4 | QH174: 1640112.4 | QI174: 1655085.4 | QJ174: 1669125.3 | QK174: 1690361 | QL174: 1695996.1 | QM174: 1703995.2 | QN174: 1703995.2 | QO174: 1713055.7 | QP174: 1726975.1 | QQ174: 1743836.3 | QR174: 1777462.5 | QS174: 1789634.9 | QT174: 1800490.2 | QU174: 1800490.2 | QV174: 1821266.7 | QW174: 1841822.3 | QX174: 1846942.9 | QY174: 1854611.6 | QZ174: 1866736.1 | RA174: 1874895.8 | RB174: 1874895.8 | RC174: 1881124.4 | RD174: 1890114.1 | RE174: 1902988.5 | RF174: 1913719.9 | RG174: 1915464.2 | RH174: 1917481.4 | RI174: 1917481.4 | RJ174: 1921533.6 | RK174: 1926238.2 | RL174: 1928634.7 | RM174: 1931031.3 | RN174: 1933427.9 | RO174: 1938620.5 | RP174: 1938620.5 | RQ174: 1946209.6 | RR174: 1947149.8 | RS174: 1948090 | RT174: 1949030.1 | RU174: 1951067.2 | RV174: 1954044.4 | RW174: 1954044.4 | RX174: 1954044.4 | RY174: 1954044.4 | RZ174: 1954044.4 | SA174: 1954044.4 | SB174: 1954044.4 | SC174: 1954044.4 | SD174: 1954044.4 | SE174: 1954044.4 | SF174: 1954044.4 | SG174: 1954044.4 | SH174: 1954044.4 | SI174: 1954044.4 | SJ174: 1954044.4 | SK174: 1954044.4 | SL174: 1954044.4 | SM174: 1954044.4 | SN174: 1954044.4 | SO174: 1954044.4 | SP174: 1954044.4 | SQ174: 1954044.4 | SR174: 1954044.4 | SS174: 1954044.4 | ST174: 1954044.4 | SU174: 1954044.4 | SV174: 1954044.4 | SW174: 1954044.4 | SX174: 1954044.4 | SY174: 1954044.4 | SZ174: 1954044.4 | TA174: 1954044.4 | TB174: 1954044.4 | TC174: 1954044.4 | TD174: 1954044.4 | TE174: 1954044.4 | TF174: 1954044.4 | TG174: 1954044.4 | TH174: 1954044.4 | TI174: 1954044.4 | TJ174: 1954044.4 | TK174: 1954044.4 | TL174: 1954044.4 | TM174: 1954044.4 | TN174: 1954044.4 | TO174: 1954044.4 | TP174: 1954044.4 | TQ174: 1954044.4 | TR174: 1954044.4 | TS174: 1954044.4 | TT174: 1954044.4 | TU174: 1954044.4 | TV174: 1954044.4 | TW174: 1954044.4 | TX174: 1954044.4 | TY174: 1954044.4 | TZ174: 1954044.4 | UA174: 1954044.4 | UB174: 1954044.4 | UC174: 1954044.4 | UD174: 1954044.4 | UE174: 1954044.4 | UF174: 1954044.4 | UG174: 1954044.4 | UH174: 1954044.4 | UI174: 1954044.4 | UJ174: 1954044.4 | UK174: 1954044.4 | UL174: 1954044.4 | UM174: 1954044.4 | UN174: 1954044.4 | UO174: 1954044.4 | UP174: 1954044.4 | UQ174: 1954044.4 | UR174: 1954044.4 | US174: 1954044.4 | UT174: 1954044.4 | UU174: 1954044.4 | UV174: 1954044.4 | UW174: 1954044.4 | UX174: 1954044.4 | UY174: 1954044.4 | UZ174: 1954044.4 | VA174: 1954044.4 | VB174: 1954044.4 | VC174: 1954044.4 | VD174: 1954044.4 | VE174: 1954044.4 | VF174: 1954044.4 | VG174: 1954044.4 | VH174: 1954044.4 | VI174: 1954044.4 | VJ174: 1954044.4 | VK174: 1954044.4 | VL174: 1954044.4 | VM174: 1954044.4
K175: Engineering | M175: 0 | N175: 0 | O175: 0 | P175: 583.28 | Q175: 583.28 | R175: 583.28 | S175: Cum BL Project Total Cost
K176: Procurement | M176: 0 | N176: 0 | O176: 0 | P176: 12873.59 | Q176: 12873.59 | R176: 10590.25 | S176: Cum BL Project Total Cost
K177: Construction | M177: 1954044.4 | N177: 1690361 | O177: 825178.44 | P177: 34379.75 | Q177: 29123.46 | R177: 17072.08 | S177: Cum BL Project Total Cost | GX177: 237.02 | GY177: 570.65 | GZ177: 1100.26 | HA177: 1629.88 | HB177: 13362.89 | HC177: 13362.89 | HD177: 27997.81 | HE177: 31391.55 | HF177: 31967.47 | HG177: 32543.39 | HH177: 33119.31 | HI177: 33695.23 | HJ177: 33695.23 | HK177: 34354.02 | HL177: 35040.73 | HM177: 36714.19 | HN177: 38389.71 | HO177: 39646.35 | HP177: 40902.99 | HQ177: 40902.99 | HR177: 42159.63 | HS177: 42159.63 | HT177: 43416.27 | HU177: 44672.91 | HV177: 45977.88 | HW177: 47305.52 | HX177: 47305.52 | HY177: 48926.95 | HZ177: 50619.3 | IA177: 52311.64 | IB177: 54003.99 | IC177: 55696.33 | ID177: 57447.04 | IE177: 57447.04 | IF177: 59306.13 | IG177: 61165.22 | IH177: 63134.6 | II177: 65160.52 | IJ177: 67186.44 | IK177: 69212.41 | IL177: 69212.41 | IM177: 71277.31 | IN177: 73358.67 | IO177: 75561.33 | IP177: 78192.36 | IQ177: 80985.74 | IR177: 80985.74 | IS177: 80985.74 | IT177: 80985.74 | IU177: 80985.74 | IV177: 80985.74 | IW177: 85404.73 | IX177: 89873.5 | IY177: 94423.01 | IZ177: 94423.01 | JA177: 99059.19 | JB177: 104091.49 | JC177: 109505.99 | JD177: 114966.37 | JE177: 120156.63 | JF177: 124725.96 | JG177: 124725.96 | JH177: 129066.15 | JI177: 132020.36 | JJ177: 132879.57 | JK177: 133738.79 | JL177: 134646.72 | JM177: 135649.03 | JN177: 135649.03 | JO177: 136748.6 | JP177: 138265.82 | JQ177: 139812.55 | JR177: 141383.57 | JS177: 143949.78 | JT177: 146730.9 | JU177: 146730.9 | JV177: 149537.9 | JW177: 152296.39 | JX177: 155117.52 | JY177: 158218.64 | JZ177: 161747.18 | KA177: 166041.94 | KB177: 166041.94 | KC177: 170479.9 | KD177: 175219.59 | KE177: 179986.23 | KF177: 184770.39 | KG177: 189606.26 | KH177: 194442.13 | KI177: 194442.13 | KJ177: 199378.78 | KK177: 204818.13 | KL177: 210668.75 | KM177: 217419.6 | KN177: 224639.57 | KO177: 230789.27 | KP177: 230789.27 | KQ177: 237337.8 | KR177: 243817.91 | KS177: 250599.47 | KT177: 257661.96 | KU177: 265336.04 | KV177: 273330.21 | KW177: 273330.21 | KX177: 281544.26 | KY177: 290116.22 | KZ177: 299058.76 | LA177: 308158.15 | LB177: 318480.41 | LC177: 328968.43 | LD177: 328968.43 | LE177: 341780.82 | LF177: 345472.66 | LG177: 349966.21 | LH177: 349966.21 | LI177: 349966.21 | LJ177: 349966.21 | LK177: 349966.21 | LL177: 349966.21 | LM177: 351364.23 | LN177: 352795.35 | LO177: 354284.16 | LP177: 355772.97 | LQ177: 357342.95 | LR177: 357342.95 | LS177: 358979.51 | LT177: 360682.22 | LU177: 362522.68 | LV177: 364445.59 | LW177: 366398.32 | LX177: 369005.62 | LY177: 369005.62 | LZ177: 372773.57 | MA177: 378513.63 | MB177: 391112.63 | MC177: 393208.11 | MD177: 395427.8 | ME177: 397672.27 | MF177: 397672.27 | MG177: 400040.3 | MH177: 402536.31 | MI177: 405346.81 | MJ177: 408192.85 | MK177: 410837.59 | ML177: 413476.25 | MM177: 413476.25 | MN177: 416133.4 | MO177: 418243.14 | MP177: 420445.01 | MQ177: 422651.38 | MR177: 424857.75 | MS177: 427064.11 | MT177: 427064.11 | MU177: 429270.48 | MV177: 431476.84 | MW177: 433743.6 | MX177: 436010.37 | MY177: 438277.13 | MZ177: 440543.89 | NA177: 440543.89 | NB177: 442810.66 | NC177: 445077.42 | ND177: 447344.18 | NE177: 449610.95 | NF177: 451877.71 | NG177: 454186.98 | NH177: 454186.98 | NI177: 456520.96 | NJ177: 458954.49 | NK177: 461422.33 | NL177: 463966.92 | NM177: 466693.47 | NN177: 469435.97 | NO177: 469435.97 | NP177: 472240.25 | NQ177: 475133.96 | NR177: 478103.22 | NS177: 481148.98 | NT177: 484413.92 | NU177: 487683.73 | NV177: 487683.73 | NW177: 491043.46 | NX177: 494478.57 | NY177: 497984.5 | NZ177: 501627.05 | OA177: 505272.75 | OB177: 509078.33 | OC177: 509078.33 | OD177: 512990.66 | OE177: 517052.5 | OF177: 521187.47 | OG177: 525452.05 | OH177: 529924.38 | OI177: 534546.58 | OJ177: 534546.58 | OK177: 539267.41 | OL177: 544136.97 | OM177: 549287.5 | ON177: 554689.67 | OO177: 560387.12 | OP177: 566126.62 | OQ177: 566126.62 | OR177: 571910.85 | OS177: 577737.76 | OT177: 583660.48 | OU177: 589737.56 | OV177: 595912.97 | OW177: 602192.39 | OX177: 602192.39 | OY177: 608548.21 | OZ177: 615131.77 | PA177: 621870.75 | PB177: 628736.01 | PC177: 636248.35 | PD177: 644815.38 | PE177: 644815.38 | PF177: 653748.16 | PG177: 663773.8 | PH177: 674154.55 | PI177: 684417.04 | PJ177: 695984.87 | PK177: 708118.07 | PL177: 708118.07 | PM177: 722649.82 | PN177: 741775.11 | PO177: 757033.38 | PP177: 775139.09 | PQ177: 872034.64 | PR177: 993154.75 | PS177: 993154.75 | PT177: 1225081.5 | PU177: 1365074.3 | PV177: 1424824.8 | PW177: 1456420 | PX177: 1456420 | PY177: 1494891.4 | PZ177: 1494891.4 | QA177: 1521821.6 | QB177: 1552284.8 | QC177: 1587298.3 | QD177: 1607668.1 | QE177: 1619701.9 | QF177: 1630981.4 | QG177: 1630981.4 | QH177: 1640112.4 | QI177: 1655085.4 | QJ177: 1669125.3 | QK177: 1690361 | QL177: 1695996.1 | QM177: 1703995.2 | QN177: 1703995.2 | QO177: 1713055.7 | QP177: 1726975.1 | QQ177: 1743836.3 | QR177: 1777462.5 | QS177: 1789634.9 | QT177: 1800490.2 | QU177: 1800490.2 | QV177: 1821266.7 | QW177: 1841822.3 | QX177: 1846942.9 | QY177: 1854611.6 | QZ177: 1866736.1 | RA177: 1874895.8 | RB177: 1874895.8 | RC177: 1881124.4 | RD177: 1890114.1 | RE177: 1902988.5 | RF177: 1913719.9 | RG177: 1915464.2 | RH177: 1917481.4 | RI177: 1917481.4 | RJ177: 1921533.6 | RK177: 1926238.2 | RL177: 1928634.7 | RM177: 1931031.3 | RN177: 1933427.9 | RO177: 1938620.5 | RP177: 1938620.5 | RQ177: 1946209.6 | RR177: 1947149.8 | RS177: 1948090 | RT177: 1949030.1 | RU177: 1951067.2 | RV177: 1954044.4 | RW177: 1954044.4 | RX177: 1954044.4 | RY177: 1954044.4 | RZ177: 1954044.4 | SA177: 1954044.4 | SB177: 1954044.4 | SC177: 1954044.4 | SD177: 1954044.4 | SE177: 1954044.4 | SF177: 1954044.4 | SG177: 1954044.4 | SH177: 1954044.4 | SI177: 1954044.4 | SJ177: 1954044.4 | SK177: 1954044.4 | SL177: 1954044.4 | SM177: 1954044.4 | SN177: 1954044.4 | SO177: 1954044.4 | SP177: 1954044.4 | SQ177: 1954044.4 | SR177: 1954044.4 | SS177: 1954044.4 | ST177: 1954044.4 | SU177: 1954044.4 | SV177: 1954044.4 | SW177: 1954044.4 | SX177: 1954044.4 | SY177: 1954044.4 | SZ177: 1954044.4 | TA177: 1954044.4 | TB177: 1954044.4 | TC177: 1954044.4 | TD177: 1954044.4 | TE177: 1954044.4 | TF177: 1954044.4 | TG177: 1954044.4 | TH177: 1954044.4 | TI177: 1954044.4 | TJ177: 1954044.4 | TK177: 1954044.4 | TL177: 1954044.4 | TM177: 1954044.4 | TN177: 1954044.4 | TO177: 1954044.4 | TP177: 1954044.4 | TQ177: 1954044.4 | TR177: 1954044.4 | TS177: 1954044.4 | TT177: 1954044.4 | TU177: 1954044.4 | TV177: 1954044.4 | TW177: 1954044.4 | TX177: 1954044.4 | TY177: 1954044.4 | TZ177: 1954044.4 | UA177: 1954044.4 | UB177: 1954044.4 | UC177: 1954044.4 | UD177: 1954044.4 | UE177: 1954044.4 | UF177: 1954044.4 | UG177: 1954044.4 | UH177: 1954044.4 | UI177: 1954044.4 | UJ177: 1954044.4 | UK177: 1954044.4 | UL177: 1954044.4 | UM177: 1954044.4 | UN177: 1954044.4 | UO177: 1954044.4 | UP177: 1954044.4 | UQ177: 1954044.4 | UR177: 1954044.4 | US177: 1954044.4 | UT177: 1954044.4 | UU177: 1954044.4 | UV177: 1954044.4 | UW177: 1954044.4 | UX177: 1954044.4 | UY177: 1954044.4 | UZ177: 1954044.4 | VA177: 1954044.4 | VB177: 1954044.4 | VC177: 1954044.4 | VD177: 1954044.4 | VE177: 1954044.4 | VF177: 1954044.4 | VG177: 1954044.4 | VH177: 1954044.4 | VI177: 1954044.4 | VJ177: 1954044.4 | VK177: 1954044.4 | VL177: 1954044.4 | VM177: 1954044.4
K178: Testing & Commissioning | M178: 0 | N178: 0 | O178: 0 | P178: 10097.89 | Q178: 0 | R178: 0 | S178: Cum BL Project Total Cost
K179: Fire Fighting Network | M179: 4678456.7 | N179: 3773268.9 | O179: 2943158.8 | P179: 63346.29 | Q179: 44606.86 | R179: 32601.72 | S179: Cum BL Project Total Cost | GY179: 723.14 | GZ179: 1531.71 | HA179: 2494.77 | HB179: 5789.16 | HC179: 5789.16 | HD179: 12166.53 | HE179: 18660.51 | HF179: 25480.26 | HG179: 32437.91 | HH179: 43914.06 | HI179: 56145.1 | HJ179: 56145.1 | HK179: 68383.04 | HL179: 80620.97 | HM179: 92858.9 | HN179: 105096.84 | HO179: 114275.29 | HP179: 123453.74 | HQ179: 123453.74 | HR179: 132632.19 | HS179: 132632.19 | HT179: 141810.64 | HU179: 150989.09 | HV179: 160167.54 | HW179: 169345.99 | HX179: 169345.99 | HY179: 178524.44 | HZ179: 187703 | IA179: 197301.28 | IB179: 207287.47 | IC179: 218814.81 | ID179: 231572.51 | IE179: 231572.51 | IF179: 245714.11 | IG179: 260783.76 | IH179: 276079.36 | II179: 292768.43 | IJ179: 309976.69 | IK179: 328757.34 | IL179: 328757.34 | IM179: 348230.69 | IN179: 369188.02 | IO179: 390508.14 | IP179: 412741.96 | IQ179: 436165.36 | IR179: 436165.36 | IS179: 436165.36 | IT179: 436165.36 | IU179: 436165.36 | IV179: 436165.36 | IW179: 475027.13 | IX179: 512535.61 | IY179: 548880.77 | IZ179: 548880.77 | JA179: 574906.31 | JB179: 602166.15 | JC179: 632837.71 | JD179: 659516.63 | JE179: 677946.81 | JF179: 696772.47 | JG179: 696772.47 | JH179: 714946.57 | JI179: 751109.87 | JJ179: 778568.5 | JK179: 824479.57 | JL179: 844171.05 | JM179: 857991.91 | JN179: 857991.91 | JO179: 876912.41 | JP179: 908419.4 | JQ179: 911635.23 | JR179: 914868.86 | JS179: 916082.64 | JT179: 916916.79 | JU179: 916916.79 | JV179: 917764.55 | JW179: 918715.89 | JX179: 920764.64 | JY179: 924760.27 | JZ179: 928250.44 | KA179: 932006.56 | KB179: 932006.56 | KC179: 935878.65 | KD179: 939750.75 | KE179: 944726.58 | KF179: 950434.11 | KG179: 956661.32 | KH179: 963436.5 | KI179: 963436.5 | KJ179: 971570.67 | KK179: 979603.76 | KL179: 987660.37 | KM179: 996954.57 | KN179: 1007617.6 | KO179: 1019404.6 | KP179: 1019404.6 | KQ179: 1026512.4 | KR179: 1032760.1 | KS179: 1042229.3 | KT179: 1046438.9 | KU179: 1050836.7 | KV179: 1058489 | KW179: 1058489 | KX179: 1072619.8 | KY179: 1083123.4 | KZ179: 1096144.2 | LA179: 1109899.6 | LB179: 1122094.9 | LC179: 1149864.5 | LD179: 1149864.5 | LE179: 1186268.9 | LF179: 1197316 | LG179: 1210432.6 | LH179: 1210432.6 | LI179: 1210432.6 | LJ179: 1210432.6 | LK179: 1210432.6 | LL179: 1210432.6 | LM179: 1214768.4 | LN179: 1218591.4 | LO179: 1221832.7 | LP179: 1225121.9 | LQ179: 1228466.3 | LR179: 1228466.3 | LS179: 1231821.5 | LT179: 1235214.4 | LU179: 1238608.4 | LV179: 1245294.7 | LW179: 1258343 | LX179: 1274993.2 | LY179: 1274993.2 | LZ179: 1290759.5 | MA179: 1309642.5 | MB179: 1328669.3 | MC179: 1333767.1 | MD179: 1340307.7 | ME179: 1346894 | MF179: 1346894 | MG179: 1354130.1 | MH179: 1361389.4 | MI179: 1368659.6 | MJ179: 1376370.5 | MK179: 1383977 | ML179: 1391514.5 | MM179: 1391514.5 | MN179: 1400684.2 | MO179: 1410118.3 | MP179: 1422240.4 | MQ179: 1429892.3 | MR179: 1437548.7 | MS179: 1445258.1 | MT179: 1445258.1 | MU179: 1452994.4 | MV179: 1460754.8 | MW179: 1468552.1 | MX179: 1476351.5 | MY179: 1484163.6 | MZ179: 1492050.9 | NA179: 1492050.9 | NB179: 1499938.2 | NC179: 1507825.6 | ND179: 1515712.9 | NE179: 1523605.2 | NF179: 1531511.8 | NG179: 1539422.7 | NH179: 1539422.7 | NI179: 1547428.4 | NJ179: 1555442 | NK179: 1563529.3 | NL179: 1571747.3 | NM179: 1580516.4 | NN179: 1589676.1 | NO179: 1589676.1 | NP179: 1599265.4 | NQ179: 1609380.9 | NR179: 1620105.6 | NS179: 1631548.2 | NT179: 1644102.2 | NU179: 1657799.8 | NV179: 1657799.8 | NW179: 1672036.4 | NX179: 1686902.1 | NY179: 1703493.4 | NZ179: 1720281.8 | OA179: 1737443.5 | OB179: 1755060.6 | OC179: 1755060.6 | OD179: 1772732.2 | OE179: 1790978 | OF179: 1809895.1 | OG179: 1828989.4 | OH179: 1848221 | OI179: 1868374.3 | OJ179: 1868374.3 | OK179: 1889036.2 | OL179: 1910325.1 | OM179: 1932281.4 | ON179: 1954736.3 | OO179: 1977685.1 | OP179: 2001557.8 | OQ179: 2001557.8 | OR179: 2027358.7 | OS179: 2051745.2 | OT179: 2076194.5 | OU179: 2100654.5 | OV179: 2125078.4 | OW179: 2141866.3 | OX179: 2141866.3 | OY179: 2161999.9 | OZ179: 2180872.1 | PA179: 2196033.6 | PB179: 2212750.5 | PC179: 2229987.5 | PD179: 2248160.7 | PE179: 2248160.7 | PF179: 2266760.2 | PG179: 2286488.2 | PH179: 2309083.6 | PI179: 2339945.6 | PJ179: 2370161.1 | PK179: 2408385 | PL179: 2408385 | PM179: 2462194.8 | PN179: 2521309.4 | PO179: 2584271.5 | PP179: 2658303.1 | PQ179: 2716282.2 | PR179: 2774916.3 | PS179: 2774916.3 | PT179: 2866871.5 | PU179: 3006935 | PV179: 3100654.7 | PW179: 3149621.1 | PX179: 3149621.1 | PY179: 3216449.9 | PZ179: 3216449.9 | QA179: 3268028.2 | QB179: 3329437.3 | QC179: 3375257.9 | QD179: 3420431.4 | QE179: 3488932.5 | QF179: 3577725.8 | QG179: 3577725.8 | QH179: 3647379.4 | QI179: 3726998.5 | QJ179: 3748623.7 | QK179: 3773268.9 | QL179: 3809705.6 | QM179: 3849920.8 | QN179: 3849920.8 | QO179: 3906762.9 | QP179: 3972066.7 | QQ179: 3991093.7 | QR179: 4014085.2 | QS179: 4045828 | QT179: 4067066.8 | QU179: 4067066.8 | QV179: 4105411.5 | QW179: 4137852.3 | QX179: 4181211.8 | QY179: 4254148.8 | QZ179: 4277075.5 | RA179: 4303823.4 | RB179: 4303823.4 | RC179: 4338056.1 | RD179: 4381514.5 | RE179: 4435484.6 | RF179: 4477649.7 | RG179: 4496084.2 | RH179: 4520611.5 | RI179: 4520611.5 | RJ179: 4551476.5 | RK179: 4562294.1 | RL179: 4576268 | RM179: 4578885.3 | RN179: 4582000 | RO179: 4586279 | RP179: 4586279 | RQ179: 4590070.7 | RR179: 4595989 | RS179: 4601259.5 | RT179: 4607726.1 | RU179: 4612058.8 | RV179: 4620795.9 | RW179: 4620795.9 | RX179: 4633308.3 | RY179: 4636485.8 | RZ179: 4640220.8 | SA179: 4643592.4 | SB179: 4649262.1 | SC179: 4657836.2 | SD179: 4657836.2 | SE179: 4664011.3 | SF179: 4665981.1 | SG179: 4667951 | SH179: 4672218.9 | SI179: 4678456.7 | SJ179: 4678456.7 | SK179: 4678456.7 | SL179: 4678456.7 | SM179: 4678456.7 | SN179: 4678456.7 | SO179: 4678456.7 | SP179: 4678456.7 | SQ179: 4678456.7 | SR179: 4678456.7 | SS179: 4678456.7 | ST179: 4678456.7 | SU179: 4678456.7 | SV179: 4678456.7 | SW179: 4678456.7 | SX179: 4678456.7 | SY179: 4678456.7 | SZ179: 4678456.7 | TA179: 4678456.7 | TB179: 4678456.7 | TC179: 4678456.7 | TD179: 4678456.7 | TE179: 4678456.7 | TF179: 4678456.7 | TG179: 4678456.7 | TH179: 4678456.7 | TI179: 4678456.7 | TJ179: 4678456.7 | TK179: 4678456.7 | TL179: 4678456.7 | TM179: 4678456.7 | TN179: 4678456.7 | TO179: 4678456.7 | TP179: 4678456.7 | TQ179: 4678456.7 | TR179: 4678456.7 | TS179: 4678456.7 | TT179: 4678456.7 | TU179: 4678456.7 | TV179: 4678456.7 | TW179: 4678456.7 | TX179: 4678456.7 | TY179: 4678456.7 | TZ179: 4678456.7 | UA179: 4678456.7 | UB179: 4678456.7 | UC179: 4678456.7 | UD179: 4678456.7 | UE179: 4678456.7 | UF179: 4678456.7 | UG179: 4678456.7 | UH179: 4678456.7 | UI179: 4678456.7 | UJ179: 4678456.7 | UK179: 4678456.7 | UL179: 4678456.7 | UM179: 4678456.7 | UN179: 4678456.7 | UO179: 4678456.7 | UP179: 4678456.7 | UQ179: 4678456.7 | UR179: 4678456.7 | US179: 4678456.7 | UT179: 4678456.7 | UU179: 4678456.7 | UV179: 4678456.7 | UW179: 4678456.7 | UX179: 4678456.7 | UY179: 4678456.7 | UZ179: 4678456.7 | VA179: 4678456.7 | VB179: 4678456.7 | VC179: 4678456.7 | VD179: 4678456.7 | VE179: 4678456.7 | VF179: 4678456.7 | VG179: 4678456.7 | VH179: 4678456.7 | VI179: 4678456.7 | VJ179: 4678456.7 | VK179: 4678456.7 | VL179: 4678456.7 | VM179: 4678456.7
K180: Engineering | M180: 0 | N180: 0 | O180: 0 | P180: 481.12 | Q180: 481.12 | R180: 481.12 | S180: Cum BL Project Total Cost
K181: Procurement | M181: 0 | N181: 0 | O181: 0 | P181: 13221.63 | Q181: 13221.63 | R181: 12374.37 | S181: Cum BL Project Total Cost
K182: Construction | M182: 4678456.7 | N182: 3773268.9 | O182: 2943158.8 | P182: 39485.54 | Q182: 30904.11 | R182: 19746.23 | S182: Cum BL Project Total Cost | GY182: 723.14 | GZ182: 1531.71 | HA182: 2494.77 | HB182: 5789.16 | HC182: 5789.16 | HD182: 12166.53 | HE182: 18660.51 | HF182: 25480.26 | HG182: 32437.91 | HH182: 43914.06 | HI182: 56145.1 | HJ182: 56145.1 | HK182: 68383.04 | HL182: 80620.97 | HM182: 92858.9 | HN182: 105096.84 | HO182: 114275.29 | HP182: 123453.74 | HQ182: 123453.74 | HR182: 132632.19 | HS182: 132632.19 | HT182: 141810.64 | HU182: 150989.09 | HV182: 160167.54 | HW182: 169345.99 | HX182: 169345.99 | HY182: 178524.44 | HZ182: 187703 | IA182: 197301.28 | IB182: 207287.47 | IC182: 218814.81 | ID182: 231572.51 | IE182: 231572.51 | IF182: 245714.11 | IG182: 260783.76 | IH182: 276079.36 | II182: 292768.43 | IJ182: 309976.69 | IK182: 328757.34 | IL182: 328757.34 | IM182: 348230.69 | IN182: 369188.02 | IO182: 390508.14 | IP182: 412741.96 | IQ182: 436165.36 | IR182: 436165.36 | IS182: 436165.36 | IT182: 436165.36 | IU182: 436165.36 | IV182: 436165.36 | IW182: 475027.13 | IX182: 512535.61 | IY182: 548880.77 | IZ182: 548880.77 | JA182: 574906.31 | JB182: 602166.15 | JC182: 632837.71 | JD182: 659516.63 | JE182: 677946.81 | JF182: 696772.47 | JG182: 696772.47 | JH182: 714946.57 | JI182: 751109.87 | JJ182: 778568.5 | JK182: 824479.57 | JL182: 844171.05 | JM182: 857991.91 | JN182: 857991.91 | JO182: 876912.41 | JP182: 908419.4 | JQ182: 911635.23 | JR182: 914868.86 | JS182: 916082.64 | JT182: 916916.79 | JU182: 916916.79 | JV182: 917764.55 | JW182: 918715.89 | JX182: 920764.64 | JY182: 924760.27 | JZ182: 928250.44 | KA182: 932006.56 | KB182: 932006.56 | KC182: 935878.65 | KD182: 939750.75 | KE182: 944726.58 | KF182: 950434.11 | KG182: 956661.32 | KH182: 963436.5 | KI182: 963436.5 | KJ182: 971570.67 | KK182: 979603.76 | KL182: 987660.37 | KM182: 996954.57 | KN182: 1007617.6 | KO182: 1019404.6 | KP182: 1019404.6 | KQ182: 1026512.4 | KR182: 1032760.1 | KS182: 1042229.3 | KT182: 1046438.9 | KU182: 1050836.7 | KV182: 1058489 | KW182: 1058489 | KX182: 1072619.8 | KY182: 1083123.4 | KZ182: 1096144.2 | LA182: 1109899.6 | LB182: 1122094.9 | LC182: 1149864.5 | LD182: 1149864.5 | LE182: 1186268.9 | LF182: 1197316 | LG182: 1210432.6 | LH182: 1210432.6 | LI182: 1210432.6 | LJ182: 1210432.6 | LK182: 1210432.6 | LL182: 1210432.6 | LM182: 1214768.4 | LN182: 1218591.4 | LO182: 1221832.7 | LP182: 1225121.9 | LQ182: 1228466.3 | LR182: 1228466.3 | LS182: 1231821.5 | LT182: 1235214.4 | LU182: 1238608.4 | LV182: 1245294.7 | LW182: 1258343 | LX182: 1274993.2 | LY182: 1274993.2 | LZ182: 1290759.5 | MA182: 1309642.5 | MB182: 1328669.3 | MC182: 1333767.1 | MD182: 1340307.7 | ME182: 1346894 | MF182: 1346894 | MG182: 1354130.1 | MH182: 1361389.4 | MI182: 1368659.6 | MJ182: 1376370.5 | MK182: 1383977 | ML182: 1391514.5 | MM182: 1391514.5 | MN182: 1400684.2 | MO182: 1410118.3 | MP182: 1422240.4 | MQ182: 1429892.3 | MR182: 1437548.7 | MS182: 1445258.1 | MT182: 1445258.1 | MU182: 1452994.4 | MV182: 1460754.8 | MW182: 1468552.1 | MX182: 1476351.5 | MY182: 1484163.6 | MZ182: 1492050.9 | NA182: 1492050.9 | NB182: 1499938.2 | NC182: 1507825.6 | ND182: 1515712.9 | NE182: 1523605.2 | NF182: 1531511.8 | NG182: 1539422.7 | NH182: 1539422.7 | NI182: 1547428.4 | NJ182: 1555442 | NK182: 1563529.3 | NL182: 1571747.3 | NM182: 1580516.4 | NN182: 1589676.1 | NO182: 1589676.1 | NP182: 1599265.4 | NQ182: 1609380.9 | NR182: 1620105.6 | NS182: 1631548.2 | NT182: 1644102.2 | NU182: 1657799.8 | NV182: 1657799.8 | NW182: 1672036.4 | NX182: 1686902.1 | NY182: 1703493.4 | NZ182: 1720281.8 | OA182: 1737443.5 | OB182: 1755060.6 | OC182: 1755060.6 | OD182: 1772732.2 | OE182: 1790978 | OF182: 1809895.1 | OG182: 1828989.4 | OH182: 1848221 | OI182: 1868374.3 | OJ182: 1868374.3 | OK182: 1889036.2 | OL182: 1910325.1 | OM182: 1932281.4 | ON182: 1954736.3 | OO182: 1977685.1 | OP182: 2001557.8 | OQ182: 2001557.8 | OR182: 2027358.7 | OS182: 2051745.2 | OT182: 2076194.5 | OU182: 2100654.5 | OV182: 2125078.4 | OW182: 2141866.3 | OX182: 2141866.3 | OY182: 2161999.9 | OZ182: 2180872.1 | PA182: 2196033.6 | PB182: 2212750.5 | PC182: 2229987.5 | PD182: 2248160.7 | PE182: 2248160.7 | PF182: 2266760.2 | PG182: 2286488.2 | PH182: 2309083.6 | PI182: 2339945.6 | PJ182: 2370161.1 | PK182: 2408385 | PL182: 2408385 | PM182: 2462194.8 | PN182: 2521309.4 | PO182: 2584271.5 | PP182: 2658303.1 | PQ182: 2716282.2 | PR182: 2774916.3 | PS182: 2774916.3 | PT182: 2866871.5 | PU182: 3006935 | PV182: 3100654.7 | PW182: 3149621.1 | PX182: 3149621.1 | PY182: 3216449.9 | PZ182: 3216449.9 | QA182: 3268028.2 | QB182: 3329437.3 | QC182: 3375257.9 | QD182: 3420431.4 | QE182: 3488932.5 | QF182: 3577725.8 | QG182: 3577725.8 | QH182: 3647379.4 | QI182: 3726998.5 | QJ182: 3748623.7 | QK182: 3773268.9 | QL182: 3809705.6 | QM182: 3849920.8 | QN182: 3849920.8 | QO182: 3906762.9 | QP182: 3972066.7 | QQ182: 3991093.7 | QR182: 4014085.2 | QS182: 4045828 | QT182: 4067066.8 | QU182: 4067066.8 | QV182: 4105411.5 | QW182: 4137852.3 | QX182: 4181211.8 | QY182: 4254148.8 | QZ182: 4277075.5 | RA182: 4303823.4 | RB182: 4303823.4 | RC182: 4338056.1 | RD182: 4381514.5 | RE182: 4435484.6 | RF182: 4477649.7 | RG182: 4496084.2 | RH182: 4520611.5 | RI182: 4520611.5 | RJ182: 4551476.5 | RK182: 4562294.1 | RL182: 4576268 | RM182: 4578885.3 | RN182: 4582000 | RO182: 4586279 | RP182: 4586279 | RQ182: 4590070.7 | RR182: 4595989 | RS182: 4601259.5 | RT182: 4607726.1 | RU182: 4612058.8 | RV182: 4620795.9 | RW182: 4620795.9 | RX182: 4633308.3 | RY182: 4636485.8 | RZ182: 4640220.8 | SA182: 4643592.4 | SB182: 4649262.1 | SC182: 4657836.2 | SD182: 4657836.2 | SE182: 4664011.3 | SF182: 4665981.1 | SG182: 4667951 | SH182: 4672218.9 | SI182: 4678456.7 | SJ182: 4678456.7 | SK182: 4678456.7 | SL182: 4678456.7 | SM182: 4678456.7 | SN182: 4678456.7 | SO182: 4678456.7 | SP182: 4678456.7 | SQ182: 4678456.7 | SR182: 4678456.7 | SS182: 4678456.7 | ST182: 4678456.7 | SU182: 4678456.7 | SV182: 4678456.7 | SW182: 4678456.7 | SX182: 4678456.7 | SY182: 4678456.7 | SZ182: 4678456.7 | TA182: 4678456.7 | TB182: 4678456.7 | TC182: 4678456.7 | TD182: 4678456.7 | TE182: 4678456.7 | TF182: 4678456.7 | TG182: 4678456.7 | TH182: 4678456.7 | TI182: 4678456.7 | TJ182: 4678456.7 | TK182: 4678456.7 | TL182: 4678456.7 | TM182: 4678456.7 | TN182: 4678456.7 | TO182: 4678456.7 | TP182: 4678456.7 | TQ182: 4678456.7 | TR182: 4678456.7 | TS182: 4678456.7 | TT182: 4678456.7 | TU182: 4678456.7 | TV182: 4678456.7 | TW182: 4678456.7 | TX182: 4678456.7 | TY182: 4678456.7 | TZ182: 4678456.7 | UA182: 4678456.7 | UB182: 4678456.7 | UC182: 4678456.7 | UD182: 4678456.7 | UE182: 4678456.7 | UF182: 4678456.7 | UG182: 4678456.7 | UH182: 4678456.7 | UI182: 4678456.7 | UJ182: 4678456.7 | UK182: 4678456.7 | UL182: 4678456.7 | UM182: 4678456.7 | UN182: 4678456.7 | UO182: 4678456.7 | UP182: 4678456.7 | UQ182: 4678456.7 | UR182: 4678456.7 | US182: 4678456.7 | UT182: 4678456.7 | UU182: 4678456.7 | UV182: 4678456.7 | UW182: 4678456.7 | UX182: 4678456.7 | UY182: 4678456.7 | UZ182: 4678456.7 | VA182: 4678456.7 | VB182: 4678456.7 | VC182: 4678456.7 | VD182: 4678456.7 | VE182: 4678456.7 | VF182: 4678456.7 | VG182: 4678456.7 | VH182: 4678456.7 | VI182: 4678456.7 | VJ182: 4678456.7 | VK182: 4678456.7 | VL182: 4678456.7 | VM182: 4678456.7
K183: Testing & Commissioning | M183: 0 | N183: 0 | O183: 0 | P183: 10157.99 | Q183: 0 | R183: 0 | S183: Cum BL Project Total Cost
K184: TSE Network | M184: 2995733.6 | N184: 2859193.2 | O184: 510048.1 | P184: 48137.98 | Q184: 24761.93 | R184: 12304.02 | S184: Cum BL Project Total Cost | HA184: 610.33 | HB184: 1367.34 | HC184: 1367.34 | HD184: 2124.34 | HE184: 2881.35 | HF184: 4072.73 | HG184: 5330.94 | HH184: 6589.15 | HI184: 7847.36 | HJ184: 7847.36 | HK184: 9105.57 | HL184: 10363.78 | HM184: 11621.99 | HN184: 12880.2 | HO184: 13823.86 | HP184: 15056.86 | HQ184: 15056.86 | HR184: 16732.73 | HS184: 16732.73 | HT184: 19596.97 | HU184: 23321.56 | HV184: 28211.65 | HW184: 33212.83 | HX184: 33212.83 | HY184: 38536.1 | HZ184: 43587.81 | IA184: 48308.98 | IB184: 54563.9 | IC184: 61910.38 | ID184: 70509.07 | IE184: 70509.07 | IF184: 78956.1 | IG184: 84161.34 | IH184: 89843.78 | II184: 96886.03 | IJ184: 105749.45 | IK184: 115879.3 | IL184: 115879.3 | IM184: 127165.9 | IN184: 136591.19 | IO184: 146762.18 | IP184: 158635.57 | IQ184: 171221.63 | IR184: 171221.63 | IS184: 171221.63 | IT184: 171221.63 | IU184: 171221.63 | IV184: 171221.63 | IW184: 190074.78 | IX184: 208828.3 | IY184: 230649.69 | IZ184: 230649.69 | JA184: 252059.58 | JB184: 276498.7 | JC184: 298716.21 | JD184: 315195.52 | JE184: 325117.91 | JF184: 333843.63 | JG184: 333843.63 | JH184: 337279.05 | JI184: 344086.24 | JJ184: 353474.16 | JK184: 358721.05 | JL184: 365206.35 | JM184: 367671.03 | JN184: 367671.03 | JO184: 368376.43 | JP184: 369116.56 | JQ184: 369856.7 | JR184: 370596.85 | JS184: 371814.5 | JT184: 373053.44 | JU184: 373053.44 | JV184: 374346.79 | JW184: 375640.15 | JX184: 376933.5 | JY184: 378226.86 | JZ184: 379621.22 | KA184: 381220.33 | KB184: 381220.33 | KC184: 382855.09 | KD184: 384492.06 | KE184: 386129.03 | KF184: 387769.04 | KG184: 389465.49 | KH184: 391170.81 | KI184: 391170.81 | KJ184: 392692.21 | KK184: 394100.98 | KL184: 395523.02 | KM184: 396979.41 | KN184: 398447.46 | KO184: 400042.85 | KP184: 400042.85 | KQ184: 401900.86 | KR184: 404059.39 | KS184: 406319.9 | KT184: 408852.09 | KU184: 411626.29 | KV184: 414455.27 | KW184: 414455.27 | KX184: 417580.61 | KY184: 420762.46 | KZ184: 424077.9 | LA184: 427549.29 | LB184: 430928.97 | LC184: 434141.82 | LD184: 434141.82 | LE184: 436987.54 | LF184: 438838.27 | LG184: 439662.48 | LH184: 439662.48 | LI184: 439662.48 | LJ184: 439662.48 | LK184: 439662.48 | LL184: 439662.48 | LM184: 440486.7 | LN184: 441310.92 | LO184: 442135.14 | LP184: 442959.36 | LQ184: 443809.32 | LR184: 443809.32 | LS184: 444731.32 | LT184: 445657.16 | LU184: 446583.01 | LV184: 447544.33 | LW184: 448625.86 | LX184: 449867.12 | LY184: 449867.12 | LZ184: 450436.41 | MA184: 451000.21 | MB184: 451381.53 | MC184: 451606.1 | MD184: 451830.67 | ME184: 452055.24 | MF184: 452055.24 | MG184: 452288.62 | MH184: 452522 | MI184: 452755.39 | MJ184: 452988.77 | MK184: 453222.16 | ML184: 453455.54 | MM184: 453455.54 | MN184: 453688.93 | MO184: 453922.31 | MP184: 454155.69 | MQ184: 454389.08 | MR184: 454622.46 | MS184: 454855.85 | MT184: 454855.85 | MU184: 455091.69 | MV184: 455332.3 | MW184: 455574.25 | MX184: 455816.2 | MY184: 456058.14 | MZ184: 456300.09 | NA184: 456300.09 | NB184: 456609.15 | NC184: 456918.2 | ND184: 457230.12 | NE184: 457546.92 | NF184: 457864.54 | NG184: 458189.28 | NH184: 458189.28 | NI184: 458524.69 | NJ184: 458860.11 | NK184: 459195.53 | NL184: 459530.95 | NM184: 459866.37 | NN184: 460203.78 | NO184: 460203.78 | NP184: 460563.49 | NQ184: 460933.01 | NR184: 461309.09 | NS184: 461689.01 | NT184: 462068.93 | NU184: 462452.68 | NV184: 462452.68 | NW184: 462843.25 | NX184: 463243.67 | NY184: 463649.33 | NZ184: 464055.95 | OA184: 464468.6 | OB184: 464887.31 | OC184: 464887.31 | OD184: 465331.06 | OE184: 465811.56 | OF184: 466321.17 | OG184: 466846.55 | OH184: 467395.09 | OI184: 467982.25 | OJ184: 467982.25 | OK184: 468596.61 | OL184: 469218.05 | OM184: 469856.08 | ON184: 470494.11 | OO184: 471142.1 | OP184: 471837.6 | OQ184: 471837.6 | OR184: 472545.15 | OS184: 473268.04 | OT184: 474022.25 | OU184: 474776.45 | OV184: 475539.71 | OW184: 476349.42 | OX184: 476349.42 | OY184: 477204.8 | OZ184: 478065.82 | PA184: 478927.72 | PB184: 479797.63 | PC184: 480697.82 | PD184: 481625.34 | PE184: 481625.34 | PF184: 482553.34 | PG184: 483497.48 | PH184: 484475.56 | PI184: 485454.82 | PJ184: 486720.42 | PK184: 487990.49 | PL184: 487990.49 | PM184: 489361.24 | PN184: 490821.48 | PO184: 494465.09 | PP184: 503540.21 | PQ184: 745316.85 | PR184: 1026268 | PS184: 1026268 | PT184: 1606293.3 | PU184: 1708484.6 | PV184: 1846684.5 | PW184: 1899710.4 | PX184: 1899710.4 | PY184: 1920819.3 | PZ184: 1920819.3 | QA184: 1956731.1 | QB184: 2003354.5 | QC184: 2050827.4 | QD184: 2139669.6 | QE184: 2285194.9 | QF184: 2446072.6 | QG184: 2446072.6 | QH184: 2829987.4 | QI184: 2843518.9 | QJ184: 2850537.9 | QK184: 2859193.2 | QL184: 2865003 | QM184: 2867583.4 | QN184: 2867583.4 | QO184: 2873457.9 | QP184: 2875314.6 | QQ184: 2877663.5 | QR184: 2882625.1 | QS184: 2883265.6 | QT184: 2884034.8 | QU184: 2884034.8 | QV184: 2885810.8 | QW184: 2886362.7 | QX184: 2887896.9 | QY184: 2890249.6 | QZ184: 2893812.4 | RA184: 2896584.2 | RB184: 2896584.2 | RC184: 2900639.8 | RD184: 2906709.5 | RE184: 2910566.9 | RF184: 2915997.9 | RG184: 2925442.6 | RH184: 2928572.9 | RI184: 2928572.9 | RJ184: 2932768.9 | RK184: 2939665.1 | RL184: 2940993 | RM184: 2942651 | RN184: 2943233.7 | RO184: 2944890.1 | RP184: 2944890.1 | RQ184: 2947640.2 | RR184: 2951449.2 | RS184: 2953583 | RT184: 2958133.7 | RU184: 2962615.2 | RV184: 2969423.9 | RW184: 2969423.9 | RX184: 2976090 | RY184: 2988088.5 | RZ184: 2990218.4 | SA184: 2991481.2 | SB184: 2994548.2 | SC184: 2994785.3 | SD184: 2994785.3 | SE184: 2995061.9 | SF184: 2995733.6 | SG184: 2995733.6 | SH184: 2995733.6 | SI184: 2995733.6 | SJ184: 2995733.6 | SK184: 2995733.6 | SL184: 2995733.6 | SM184: 2995733.6 | SN184: 2995733.6 | SO184: 2995733.6 | SP184: 2995733.6 | SQ184: 2995733.6 | SR184: 2995733.6 | SS184: 2995733.6 | ST184: 2995733.6 | SU184: 2995733.6 | SV184: 2995733.6 | SW184: 2995733.6 | SX184: 2995733.6 | SY184: 2995733.6 | SZ184: 2995733.6 | TA184: 2995733.6 | TB184: 2995733.6 | TC184: 2995733.6 | TD184: 2995733.6 | TE184: 2995733.6 | TF184: 2995733.6 | TG184: 2995733.6 | TH184: 2995733.6 | TI184: 2995733.6 | TJ184: 2995733.6 | TK184: 2995733.6 | TL184: 2995733.6 | TM184: 2995733.6 | TN184: 2995733.6 | TO184: 2995733.6 | TP184: 2995733.6 | TQ184: 2995733.6 | TR184: 2995733.6 | TS184: 2995733.6 | TT184: 2995733.6 | TU184: 2995733.6 | TV184: 2995733.6 | TW184: 2995733.6 | TX184: 2995733.6 | TY184: 2995733.6 | TZ184: 2995733.6 | UA184: 2995733.6 | UB184: 2995733.6 | UC184: 2995733.6 | UD184: 2995733.6 | UE184: 2995733.6 | UF184: 2995733.6 | UG184: 2995733.6 | UH184: 2995733.6 | UI184: 2995733.6 | UJ184: 2995733.6 | UK184: 2995733.6 | UL184: 2995733.6 | UM184: 2995733.6 | UN184: 2995733.6 | UO184: 2995733.6 | UP184: 2995733.6 | UQ184: 2995733.6 | UR184: 2995733.6 | US184: 2995733.6 | UT184: 2995733.6 | UU184: 2995733.6 | UV184: 2995733.6 | UW184: 2995733.6 | UX184: 2995733.6 | UY184: 2995733.6 | UZ184: 2995733.6 | VA184: 2995733.6 | VB184: 2995733.6 | VC184: 2995733.6 | VD184: 2995733.6 | VE184: 2995733.6 | VF184: 2995733.6 | VG184: 2995733.6 | VH184: 2995733.6 | VI184: 2995733.6 | VJ184: 2995733.6 | VK184: 2995733.6 | VL184: 2995733.6 | VM184: 2995733.6
K185: Engineering | M185: 0 | N185: 0 | O185: 0 | P185: 1075.88 | Q185: 1075.88 | R185: 1075.88 | S185: Cum BL Project Total Cost
K186: Procurement | M186: 0 | N186: 0 | O186: 0 | P186: 15761.57 | Q186: 6926.74 | R186: 5573.96 | S186: Cum BL Project Total Cost
