Workbook
Name _1B.05.M.010.0010: #REF!
Name _1B.05.M.010.0010: #REF!
Name _1B.05.M.010.0010: #REF!
Name _1B.05.M.010.0050: #REF!
Name _1B.05.M.010.0050: #REF!
Name _1B.05.M.0100.0010: #REF!
Name _1B.05.M.0100.0010: #REF!
Name _1B.05.M.020.0010: #REF!
Name _1B.05.M.020.0010: #REF!
Name _1B.05.M.020.0020: #REF!
Name _1B.05.M.020.0020: #REF!
Name _1B.05.M.020.0030: #REF!
Name _1B.05.M.020.0030: #REF!
Name _1B.05.M.020.0040: #REF!
Name _1B.05.M.020.0040: #REF!
Name _1B.05.M.030.0010: #REF!
Name _1B.05.M.030.0010: #REF!
Name _1B.05.M.030.0020: #REF!
Name _1B.05.M.030.0020: #REF!
Name _1B.05.M.040.0010: #REF!
Name _1B.05.M.040.0010: #REF!
Name _1B.05.M.050.0010: #REF!
Name _1B.05.M.050.0010: #REF!
Name _1B.05.M.050.0020: #REF!
Name _1B.05.M.050.0020: #REF!
Name _1B.05.M.050.0030: #REF!
Name _1B.05.M.050.0030: #REF!
Name _1B.05.M.060.0020: #REF!
Name _1B.05.M.060.0020: #REF!
Name _1B.05.M.060.0100: #REF!
Name _1B.05.M.060.0100: #REF!
Name _1B.05.M.070.0010: #REF!
Name _1B.05.M.070.0010: #REF!
Name _1B.05.M.070.0020: #REF!
Name _1B.05.M.070.0020: #REF!
Name _1B.05.M.070.0030: #REF!
Name _1B.05.M.070.0030: #REF!
Name _1B.05.M.070.0040: #REF!
Name _1B.05.M.070.0040: #REF!
Name _1B.05.M.070.0050: #REF!
Name _1B.05.M.070.0050: #REF!
Name _1B.05.M.080.0010: #REF!
Name _1B.05.M.080.0010: #REF!
Name _1B.05.M.090.0010: #REF!
Name _1B.05.M.090.0010: #REF!
Name _1B.09.P.010.0010: #REF!
Name _1B.09.P.010.0010: #REF!
Name _1B.09.P.010.0020: #REF!
Name _1B.09.P.010.0020: #REF!
Name _1B.09.P.010.0030: #REF!
Name _1B.09.P.010.0030: #REF!
Name _1B.09.P.010.0040: #REF!
Name _1B.09.P.010.0040: #REF!
Name _1B.09.P.010.0050: #REF!
Name _1B.09.P.010.0050: #REF!
Name _1B.09.P.010.0060: #REF!
Name _1B.09.P.010.0060: #REF!
Name _1B.09.P.010.0070: #REF!
Name _1B.09.P.010.0070: #REF!
Name _1B.09.P.020.0010: #REF!

Sheet Weekly Progress Report
A1: MODON - Weekly Progress Report - Construction Projects | AF1: Data Date | AH1: ='General Information'!L1 -> 46293
A2: Contract General Information | G2: Key Dates | M2: Cost Summary (SR) | U2: Performance Summary | AA2: Project Scope
A3: Project Name | B3: ='General Information'!C3 -> Infrastructure Network Development Project in Sudair City for Industry and Business - Phase Two - Part Two | G3: Contract Award | H3: ='General Information'!C12 -> 45998 | I3: Contract Award (Hijri) | J3: ='General Information'!C16 -> 16/6/1447 | K3: Revised Completion | L3: ='General Information'!C20 -> 0 | M3: Original Contract Value | O3: ='Invoice Log'!F3 -> 168629520 | Q3: O&M Value | S3: ='Invoice Log'!J3 -> 0 | T3: EAC | U3: Plan Value | V3: =Progress!H47 -> 0.32072541 | W3: Phys. Plan Value | X3: =W43 -> 0.3565935 | Y3: Quality Score | Z3: =Quality.!AC10 -> 0.81344828 | AA3: =Progress!B1 -> The scope of work of the project includes the implementation of the entire works subject to the contract, including the following: Road and paving works, Potable Water Network Works, Treatment Water Network Works, Sewer network works, Rainwater drainage network works, Irrigation and landscaping network works, Electrical network works including (medium voltage, communications, road lighting), Camera surveillance work
A4: Project ID | B4: ='General Information'!C4 -> SUD1-02-011 | D4: Stage | E4: ='General Information'!C7 -> Construction | G4: Contract Sign | H4: ='General Information'!C13 -> 46020 | I4: Contract Sign (Hijri) | J4: ='General Information'!C17 -> 9/7/1447 | K4: Committed Completion | L4: ='General Information'!C21 -> 46573 | M4: Revised Contract Value | O4: ='Invoice Log'!F4 -> 0 | P4: EAC | Q4: Revised O&M Value | S4: ='Invoice Log'!J4 -> 0 | T4: =+#REF!+#REF!+S4 -> #REF! | U4: Earn Value | V4: =L43 -> 0.43378716 | W4: Phys. Earn Value | X4: =X43 -> 0.39232947 | Z4: =REPT("¢",IF(INT(+Z3*10)>5,5,INT(+Z3*10)))&REPT("£",IF(INT(+Z3*10)>5,0,5-INT(+Z3*10)))&CHAR(10)&REPT("¢",+IF(INT(+Z3*10)>5,-5+INT(+Z3*10),0))&REPT("£",IF(INT(+Z3*10)>5,10-INT(+Z3*10),5)) -> ¢¢¢¢¢ ¢¢¢££
A5: Contractor | B5: ='General Information'!C5 -> Technical Dvelopment Co. "TDC" | D5: Status | E5: ='General Information'!C8 -> Active | G5: Site Handover | H5: ='General Information'!C14 -> 46028 | I5: Site Handover (Hijri) | J5: ='General Information'!C18 -> 17/7/1447 | K5: Forecast Completion | L5: ='General Information'!C22 -> 46573 | M5: Estimate At Completion Value | O5: ='Invoice Log'!F5 -> 168629520 | P5: =+#REF!+#REF!+O5 -> #REF! | Q5: Submitted Invoices (Gross Value) | S5: ='Invoice Log'!J5 -> 16773813 | U5: Variance | V5: =V4-V3 -> 0.11306175 | W5: Variance | X5: =X4-X3 -> 0.035735979 | Y5: Safety Score | Z5: ='HSE. '!AE6 -> 0.81818182
A6: Consultant | B6: ='General Information'!C6 -> Saudi Arabia Consulting Engineering Company "EGIS" | D6: Modon PM | E6: ='General Information'!C9 -> Engr.Zyad Al Shabat | G6: Original Completion | H6: ='General Information'!C15 -> 46573 | I6: Original Completion (Hijri) | J6: ='General Information'!C19 -> 30/1/1449 | K6: Variance | L6: ='General Information'!C23 -> 0 | M6: Potential Changes | O6: ='Invoice Log'!F6 -> 0 | Q6: Total Deduction | S6: ='Invoice Log'!J6 -> -720596.12 | U6: SPI | V6: =V4/V3 -> 1.3525189 | W6: SPI | X6: =X4/X3 -> 1.1002149 | Z6: =REPT("¢",IF(INT(+Z5*10)>5,5,INT(+Z5*10)))&REPT("£",IF(INT(+Z5*10)>5,0,5-INT(+Z5*10)))&CHAR(10)&REPT("¢",+IF(INT(+Z5*10)>5,-5+INT(+Z5*10),0))&REPT("£",IF(INT(+Z5*10)>5,10-INT(+Z5*10),5)) -> ¢¢¢¢¢ ¢¢¢££
A8: Progress Overview
A9: Earned Value Progress (SAR) | O9: =Progress!K4 -> Physical Progress (Effort) | AA9: Earned Value Progress (%)
A10: WBS | C10: BOQ Value (SAR) | D10: % Wt. | E10: Weekly (SAR) | G10: To Date (SAR) | O10: =Progress!K5 -> Budgeted | P10: =Progress!L5 -> % Wt. | Q10: Weekly Physical Progress | U10: To Date Physical Progress
E11: Planned | F11: Earned | G11: Original Plan | H11: =Progress!H6 -> Planned | I11: =Progress!I6 -> Earned | J11: Original Plan % | K11: Cum. Planned % | L11: Cum.Earned % | M11: Variance | N11: SPI | O11: (Manhours) | Q11: Planned | R11: Earned | S11: Plan % | T11: Earned % | U11: Planned | V11: Earned | W11: Plan % | X11: Earned % | Y11: Variance | Z11: SPI
C12: =Progress!C7 -> 0 | D12: =Progress!D7 -> 0 | E12: =Progress!E39 -> 0 | F12: =Progress!F39 -> 0 | G12: =Progress!G39 -> 0 | I12: =I55 -> 0 | J12: =IFERROR(IF(ISBLANK(G12),"",G12/C12),0) -> 0 | K12: =IFERROR(IF(ISBLANK(H12),"",H12/C12),0) | L12: =IFERROR(IF(ISBLANK(I12),"",I12/C12),0) -> 0 | M12: =IFERROR(L12-K12,"") | N12: =IFERROR(L12/K12,"") | P12: =Progress!L7 -> 0 | Q12: =Progress!M7 -> 0 | R12: =Progress!N7 -> 0 | S12: =IFERROR(IF(ISBLANK(Q12),"",Q12/O12),0) -> 0 | T12: =IFERROR(IF(ISBLANK(R12),"",R12/O12),0) -> 0 | U12: =Progress!O7 -> 0 | V12: =Progress!P7 -> 0 | W12: =IFERROR(IF(ISBLANK(U12),"",U12/O12),0) -> 0 | X12: =IFERROR(IF(ISBLANK(V12),"",V12/O12),0) -> 0 | Y12: =IFERROR(X12-W12,"") -> 0 | Z12: =IFERROR(X12/W12,"")
A13: =Progress!A8 -> Mobilization | C13: =Progress!C8 -> 0 | D13: =Progress!D8 -> 0 | E13: =Progress!E40 -> 0 | F13: =Progress!F8 -> 0 | G13: =Progress!G8 -> 0 | H13: =Progress!H8 -> 0 | I13: =Progress!I8 -> 0 | J13: =IFERROR(IF(ISBLANK(G13),"",G13/C13),0) -> 0 | K13: =IFERROR(IF(ISBLANK(H13),"",H13/C13),0) -> 0 | L13: =IFERROR(IF(ISBLANK(I13),"",I13/C13),0) -> 0 | M13: =IFERROR(L13-K13,"") -> 0 | N13: =IFERROR(L13/K13,"") | O13: =Progress!K8 -> 34177 | P13: =Progress!L8 -> 0.029999719 | Q13: =Progress!M8 -> 0 | R13: =Progress!N8 -> 0 | S13: =IFERROR(IF(ISBLANK(Q13),"",Q13/O13),0) -> 0 | T13: =IFERROR(IF(ISBLANK(R13),"",R13/O13),0) -> 0 | U13: =Progress!O8 -> 34177 | V13: =Progress!P8 -> 34177 | W13: =IFERROR(IF(ISBLANK(U13),"",U13/O13),0) -> 1 | X13: =IFERROR(IF(ISBLANK(V13),"",V13/O13),0) -> 1 | Y13: =IFERROR(X13-W13,"") -> 0 | Z13: =IFERROR(X13/W13,"") -> 1
A14: =Progress!A9 -> Engineering | C14: =Progress!C9 -> 0 | D14: =Progress!D9 -> 0 | E14: =Progress!E9 -> 0 | F14: =Progress!F9 -> 0 | G14: =Progress!G9 -> 0 | H14: =Progress!H9 -> 0 | I14: =Progress!I9 -> 0 | J14: =IFERROR(IF(ISBLANK(G14),"",G14/C14),0) -> 0 | K14: =IFERROR(IF(ISBLANK(H14),"",H14/C14),0) -> 0 | L14: =IFERROR(IF(ISBLANK(I14),"",I14/C14),0) -> 0 | M14: =IFERROR(L14-K14,"") -> 0 | N14: =IFERROR(L14/K14,"") | O14: =Progress!K9 -> 56962 | P14: =Progress!L9 -> 0.049999824 | Q14: =Progress!M9 -> 0 | R14: =Progress!N9 -> 0 | S14: =IFERROR(IF(ISBLANK(Q14),"",Q14/O14),0) -> 0 | T14: =IFERROR(IF(ISBLANK(R14),"",R14/O14),0) -> 0 | U14: =Progress!O9 -> 56962 | V14: =Progress!P9 -> 53211 | W14: =IFERROR(IF(ISBLANK(U14),"",U14/O14),0) -> 1 | X14: =IFERROR(IF(ISBLANK(V14),"",V14/O14),0) -> 0.93414908 | Y14: =IFERROR(X14-W14,"") -> -0.065850918 | Z14: =IFERROR(X14/W14,"") -> 0.93414908
A15: =Progress!A10 -> Procurement | C15: =Progress!C10 -> 0 | D15: =Progress!D10 -> 0 | E15: =Progress!E10 -> 0 | F15: =Progress!F10 -> 0 | G15: =Progress!G10 -> 0 | H15: =Progress!H10 -> 0 | I15: =Progress!I10 -> 0 | J15: =IFERROR(IF(ISBLANK(G15),"",G15/C15),0) -> 0 | K15: =IFERROR(IF(ISBLANK(H15),"",H15/C15),0) -> 0 | L15: =IFERROR(IF(ISBLANK(I15),"",I15/C15),0) -> 0 | M15: =IFERROR(L15-K15,"") -> 0 | N15: =IFERROR(L15/K15,"") | O15: =Progress!K10 -> 148102 | P15: =Progress!L10 -> 0.13000025 | Q15: =Progress!M10 -> 1511 | R15: =Progress!N10 -> 0 | S15: =IFERROR(IF(ISBLANK(Q15),"",Q15/O15),0) -> 0.010202428 | T15: =IFERROR(IF(ISBLANK(R15),"",R15/O15),0) -> 0 | U15: =Progress!O10 -> 143233 | V15: =Progress!P10 -> 48418 | W15: =IFERROR(IF(ISBLANK(U15),"",U15/O15),0) -> 0.96712401 | X15: =IFERROR(IF(ISBLANK(V15),"",V15/O15),0) -> 0.32692334 | Y15: =IFERROR(X15-W15,"") -> -0.64020067 | Z15: =IFERROR(X15/W15,"") -> 0.33803663
A16: =Progress!A11 -> Construction | C16: =Progress!C11 -> 1.6862952e+08 | D16: =Progress!D11 -> 1 | E16: =Progress!E11 -> 3995420.2 | F16: =Progress!F11 -> 1709872.9 | G16: =Progress!G11 -> 0 | H16: =Progress!H11 -> 54083772 | I16: =Progress!I11 -> 73149321 | J16: =IFERROR(IF(ISBLANK(G16),"",G16/C16),0) -> 0 | K16: =IFERROR(IF(ISBLANK(H16),"",H16/C16),0) -> 0.32072541 | L16: =IFERROR(IF(ISBLANK(I16),"",I16/C16),0) -> 0.43378716 | M16: =IFERROR(L16-K16,"") -> 0.11306175 | N16: =IFERROR(L16/K16,"") -> 1.3525189 | O16: =Progress!K11 -> 854433 | P16: =Progress!L11 -> 0.75 | Q16: =Progress!M11 -> 13886 | R16: =Progress!N11 -> 3659 | S16: =IFERROR(IF(ISBLANK(Q16),"",Q16/O16),0) -> 0.016251713 | T16: =IFERROR(IF(ISBLANK(R16),"",R16/O16),0) -> 0.0042823721 | U16: =Progress!O11 -> 171875 | V16: =Progress!P11 -> 311153 | W16: =IFERROR(IF(ISBLANK(U16),"",U16/O16),0) -> 0.20115679 | X16: =IFERROR(IF(ISBLANK(V16),"",V16/O16),0) -> 0.36416314 | Y16: =IFERROR(X16-W16,"") -> 0.16300634 | Z16: =IFERROR(X16/W16,"") -> 1.8103447
A17: =Progress!A12 -> ROAD WORKS | C17: =Progress!C12 -> 87969997 | D17: =Progress!D12 -> 0.52167614 | E17: =Progress!E12 -> 3032198.6 | F17: =Progress!F12 -> 1648128 | G17: =Progress!G12 -> 0 | H17: =Progress!H12 -> 45806827 | I17: =Progress!I12 -> 52657041 | J17: =IFERROR(IF(ISBLANK(G17),"",G17/C17),0) -> 0 | K17: =IFERROR(IF(ISBLANK(H17),"",H17/C17),0) -> 0.52070966 | L17: =IFERROR(IF(ISBLANK(I17),"",I17/C17),0) -> 0.59857955 | M17: =IFERROR(L17-K17,"") -> 0.077869883 | N17: =IFERROR(L17/K17,"") -> 1.1495457 | O17: =Progress!K12 -> 186393 | P17: =Progress!L12 -> 0.16361113 | Q17: =Progress!M12 -> 5506 | R17: =Progress!N12 -> 1552 | S17: =IFERROR(IF(ISBLANK(Q17),"",Q17/O17),0) -> 0.029539736 | T17: =IFERROR(IF(ISBLANK(R17),"",R17/O17),0) -> 0.0083264929 | U17: =Progress!O12 -> 115703 | V17: =Progress!P12 -> 139255 | W17: =IFERROR(IF(ISBLANK(U17),"",U17/O17),0) -> 0.62074756 | X17: =IFERROR(IF(ISBLANK(V17),"",V17/O17),0) -> 0.74710424 | Y17: =IFERROR(X17-W17,"") -> 0.12635668 | Z17: =IFERROR(X17/W17,"") -> 1.2035557
A18: =Progress!A13 -> ZONE A | C18: =Progress!C13 -> 54469013 | D18: =Progress!D13 -> 0.32300995 | E18: =Progress!E13 -> 2443662 | F18: =Progress!F13 -> 421282.11 | G18: =Progress!G13 -> 0 | H18: =Progress!H13 -> 24340936 | I18: =Progress!I13 -> 28656488 | J18: =IFERROR(IF(ISBLANK(G18),"",G18/C18),0) -> 0 | K18: =IFERROR(IF(ISBLANK(H18),"",H18/C18),0) -> 0.44687677 | L18: =IFERROR(IF(ISBLANK(I18),"",I18/C18),0) -> 0.52610626 | M18: =IFERROR(L18-K18,"") -> 0.079229487 | N18: =IFERROR(L18/K18,"") -> 1.1772961 | O18: =Progress!K13 -> 121795 | P18: =Progress!L13 -> 0.10690862 | Q18: =Progress!M13 -> 3080 | R18: =Progress!N13 -> 544 | S18: =IFERROR(IF(ISBLANK(Q18),"",Q18/O18),0) -> 0.025288394 | T18: =IFERROR(IF(ISBLANK(R18),"",R18/O18),0) -> 0.0044665216 | U18: =Progress!O13 -> 74862 | V18: =Progress!P13 -> 90010 | W18: =IFERROR(IF(ISBLANK(U18),"",U18/O18),0) -> 0.61465577 | X18: =IFERROR(IF(ISBLANK(V18),"",V18/O18),0) -> 0.7390287 | Y18: =IFERROR(X18-W18,"") -> 0.12437292 | Z18: =IFERROR(X18/W18,"") -> 1.2023456
A19: =Progress!A14 -> ZONE G | C19: =Progress!C14 -> 33500984 | D19: =Progress!D14 -> 0.19866619 | E19: =Progress!E14 -> 588536.68 | F19: =Progress!F14 -> 1226845.9 | G19: =Progress!G14 -> 0 | H19: =Progress!H14 -> 21465891 | I19: =Progress!I14 -> 24000552 | J19: =IFERROR(IF(ISBLANK(G19),"",G19/C19),0) -> 0 | K19: =IFERROR(IF(ISBLANK(H19),"",H19/C19),0) -> 0.64075404 | L19: =IFERROR(IF(ISBLANK(I19),"",I19/C19),0) -> 0.71641335 | M19: =IFERROR(L19-K19,"") -> 0.075659314 | N19: =IFERROR(L19/K19,"") -> 1.1180786 | O19: =Progress!K14 -> 64598 | P19: =Progress!L14 -> 0.056702515 | Q19: =Progress!M14 -> 2425 | R19: =Progress!N14 -> 1009 | S19: =IFERROR(IF(ISBLANK(Q19),"",Q19/O19),0) -> 0.037539862 | T19: =IFERROR(IF(ISBLANK(R19),"",R19/O19),0) -> 0.015619679 | U19: =Progress!O14 -> 40841 | V19: =Progress!P14 -> 49245 | W19: =IFERROR(IF(ISBLANK(U19),"",U19/O19),0) -> 0.6322332 | X19: =IFERROR(IF(ISBLANK(V19),"",V19/O19),0) -> 0.7623301 | Y19: =IFERROR(X19-W19,"") -> 0.13009691 | Z19: =IFERROR(X19/W19,"") -> 1.2057736
A20: =Progress!A15 -> Storm Water Drainage Network | C20: =Progress!C15 -> 25407829 | D20: =Progress!D15 -> 0.15067249 | E20: =Progress!E15 -> 323770.63 | F20: =Progress!F15 -> 0 | G20: =Progress!G15 -> 0 | H20: =Progress!H15 -> 5607920.6 | I20: =Progress!I15 -> 9325845.2 | J20: =IFERROR(IF(ISBLANK(G20),"",G20/C20),0) -> 0 | K20: =IFERROR(IF(ISBLANK(H20),"",H20/C20),0) -> 0.22071624 | L20: =IFERROR(IF(ISBLANK(I20),"",I20/C20),0) -> 0.36704612 | M20: =IFERROR(L20-K20,"") -> 0.14632988 | N20: =IFERROR(L20/K20,"") -> 1.6629774 | O20: =Progress!K15 -> 187421 | P20: =Progress!L15 -> 0.16451348 | Q20: =Progress!M15 -> 3091 | R20: =Progress!N15 -> 0 | S20: =IFERROR(IF(ISBLANK(Q20),"",Q20/O20),0) -> 0.016492282 | T20: =IFERROR(IF(ISBLANK(R20),"",R20/O20),0) -> 0 | U20: =Progress!O15 -> 29500 | V20: =Progress!P15 -> 75282 | W20: =IFERROR(IF(ISBLANK(U20),"",U20/O20),0) -> 0.15739965 | X20: =IFERROR(IF(ISBLANK(V20),"",V20/O20),0) -> 0.40167324 | Y20: =IFERROR(X20-W20,"") -> 0.24427359 | Z20: =IFERROR(X20/W20,"") -> 2.5519322
A21: =Progress!A16 -> ZONE A | C21: =Progress!C16 -> 22856155 | D21: =Progress!D16 -> 0.13554065 | E21: =Progress!E16 -> 292630.25 | F21: =Progress!F16 -> 0 | G21: =Progress!G16 -> 0 | H21: =Progress!H17 -> 282827.44 | I21: =Progress!I16 -> 6792269.6 | J21: =IFERROR(IF(ISBLANK(G21),"",G21/C21),0) -> 0 | K21: =IFERROR(IF(ISBLANK(H21),"",H21/C21),0) -> 0.012374235 | L21: =IFERROR(IF(ISBLANK(I21),"",I21/C21),0) -> 0.29717464 | M21: =IFERROR(L21-K21,"") -> 0.2848004 | N21: =IFERROR(L21/K21,"") -> 24.015596 | O21: =Progress!K16 -> 131130 | P21: =Progress!L16 -> 0.11510265 | Q21: =Progress!M16 -> 2166 | R21: =Progress!N16 -> 0 | S21: =IFERROR(IF(ISBLANK(Q21),"",Q21/O21),0) -> 0.016517959 | T21: =IFERROR(IF(ISBLANK(R21),"",R21/O21),0) -> 0 | U21: =Progress!O16 -> 20841 | V21: =Progress!P16 -> 19664 | W21: =IFERROR(IF(ISBLANK(U21),"",U21/O21),0) -> 0.15893388 | X21: =IFERROR(IF(ISBLANK(V21),"",V21/O21),0) -> 0.14995806 | Y21: =IFERROR(X21-W21,"") -> -0.0089758255 | Z21: =IFERROR(X21/W21,"") -> 0.94352478
A22: =Progress!A17 -> ZONE G | C22: =Progress!C17 -> 2551674.2 | D22: =Progress!D17 -> 0.015131836 | E22: =Progress!E17 -> 0 | F22: =Progress!F17 -> 0 | G22: =Progress!G17 -> 0 | H22: =Progress!H17 -> 282827.44 | I22: =Progress!I17 -> 2533575.5 | J22: =IFERROR(IF(ISBLANK(G22),"",G22/C22),0) -> 0 | K22: =IFERROR(IF(ISBLANK(H22),"",H22/C22),0) -> 0.11083995 | L22: =IFERROR(IF(ISBLANK(I22),"",I22/C22),0) -> 0.99290714 | M22: =IFERROR(L22-K22,"") -> 0.88206719 | N22: =IFERROR(L22/K22,"") -> 8.9580259 | O22: =Progress!K17 -> 56291 | P22: =Progress!L17 -> 0.049410837 | Q22: =Progress!M17 -> 0 | R22: =Progress!N17 -> 0 | S22: =IFERROR(IF(ISBLANK(Q22),"",Q22/O22),0) -> 0 | T22: =IFERROR(IF(ISBLANK(R22),"",R22/O22),0) -> 0 | U22: =Progress!O17 -> 8660 | V22: =Progress!P17 -> 55618 | W22: =IFERROR(IF(ISBLANK(U22),"",U22/O22),0) -> 0.15384342 | X22: =IFERROR(IF(ISBLANK(V22),"",V22/O22),0) -> 0.98804427 | Y22: =IFERROR(X22-W22,"") -> 0.83420085 | Z22: =IFERROR(X22/W22,"") -> 6.4224018
A23: =Progress!A18 -> Sewerage Network | C23: =Progress!C18 -> 7071026.8 | D23: =Progress!D18 -> 0.041932319 | E23: =Progress!E51 -> 0 | F23: =Progress!F18 -> 0 | G23: =Progress!G18 -> 0 | H23: =Progress!H18 -> 16569.23 | I23: =Progress!I18 -> 5356988.8 | O23: =Progress!K18 -> 62221 | P23: =Progress!L18 -> 0.054616044 | Q23: =Progress!M18 -> 221 | R23: =Progress!N18 -> 0 | S23: =IFERROR(IF(ISBLANK(Q23),"",Q23/O23),0) -> 0.0035518555 | T23: =IFERROR(IF(ISBLANK(R23),"",R23/O23),0) -> 0 | U23: =Progress!O18 -> 221 | V23: =Progress!P18 -> 44444 | W23: =IFERROR(IF(ISBLANK(U23),"",U23/O23),0) -> 0.0035518555 | X23: =IFERROR(IF(ISBLANK(V23),"",V23/O23),0) -> 0.7142926 | Y23: =IFERROR(X23-W23,"") -> 0.71074075 | Z23: =IFERROR(X23/W23,"") -> 201.10407
A24: =Progress!A19 -> ZONE A | C24: =Progress!C19 -> 4499744.2 | D24: =Progress!D19 -> 0.026684202 | F24: =Progress!F19 -> 0 | G24: =Progress!G19 -> 0 | H24: =Progress!H19 -> 8297.86 | I24: =Progress!I19 -> 2912490.8 | O24: =Progress!K19 -> 40161 | P24: =Progress!L19 -> 0.035252325 | Q24: =Progress!M19 -> 85 | R24: =Progress!N19 -> 0 | S24: =IFERROR(IF(ISBLANK(Q24),"",Q24/O24),0) -> 0.0021164812 | T24: =IFERROR(IF(ISBLANK(R24),"",R24/O24),0) -> 0 | U24: =Progress!O19 -> 85 | V24: =Progress!P19 -> 23456 | W24: =IFERROR(IF(ISBLANK(U24),"",U24/O24),0) -> 0.0021164812 | X24: =IFERROR(IF(ISBLANK(V24),"",V24/O24),0) -> 0.5840492 | Y24: =IFERROR(X24-W24,"") -> 0.58193272 | Z24: =IFERROR(X24/W24,"") -> 275.95294
A25: =Progress!A20 -> ZONE G | C25: =Progress!C20 -> 2571282.6 | D25: =Progress!D20 -> 0.015248117 | F25: =Progress!F20 -> 0 | G25: =Progress!G20 -> 0 | H25: =Progress!H20 -> 8271.37 | I25: =Progress!I20 -> 2444498.1 | O25: =Progress!K20 -> 22061 | P25: =Progress!L20 -> 0.019364596 | Q25: =Progress!M20 -> 0 | R25: =Progress!N20 -> 0 | S25: =IFERROR(IF(ISBLANK(Q25),"",Q25/O25),0) -> 0 | T25: =IFERROR(IF(ISBLANK(R25),"",R25/O25),0) -> 0 | U25: =Progress!O20 -> 136 | V25: =Progress!P20 -> 20987 | W25: =IFERROR(IF(ISBLANK(U25),"",U25/O25),0) -> 0.0061647251 | X25: =IFERROR(IF(ISBLANK(V25),"",V25/O25),0) -> 0.9513168 | Y25: =IFERROR(X25-W25,"") -> 0.94515208 | Z25: =IFERROR(X25/W25,"") -> 154.31618
A26: =Progress!A21 -> TSE Network | C26: =Progress!C21 -> 4147696.1 | D26: =Progress!D21 -> 0.024596501 | F26: =Progress!F21 -> 13961.66 | G26: =Progress!G21 -> 0 | I26: =Progress!I21 -> 581492.39 | O26: =Progress!K21 -> 87808 | P26: =Progress!L21 -> 0.077075675 | Q26: =Progress!M21 -> 0 | R26: =Progress!N21 -> 455 | S26: =IFERROR(IF(ISBLANK(Q26),"",Q26/O26),0) -> 0 | T26: =IFERROR(IF(ISBLANK(R26),"",R26/O26),0) -> 0.0051817602 | U26: =Progress!O21 -> 0 | V26: =Progress!P21 -> 3248 | W26: =IFERROR(IF(ISBLANK(U26),"",U26/O26),0) -> 0 | X26: =IFERROR(IF(ISBLANK(V26),"",V26/O26),0) -> 0.036989796 | Y26: =IFERROR(X26-W26,"") -> 0.036989796 | Z26: =IFERROR(X26/W26,"")
A27: =Progress!A22 -> ZONE A | C27: =Progress!C22 -> 3158469.4 | D27: =Progress!D22 -> 0.018730228 | E27: =Progress!E43 -> 0 | F27: =Progress!F22 -> 13089.57 | G27: =Progress!G22 -> 0 | H27: =Progress!H35 -> 44969.06 | I27: =Progress!I22 -> 518004.64 | J27: =IFERROR(IF(ISBLANK(G27),"",G27/C27),0) -> 0 | K27: =IFERROR(IF(ISBLANK(H27),"",I27/C27),0) -> 0.16400496 | L27: =IFERROR(IF(ISBLANK(I27),"",I27/C27),0) -> 0.16400496 | M27: =IFERROR(L27-K27,"") -> 0 | N27: =IFERROR(L27/K27,"") -> 1 | O27: =Progress!K22 -> 64717 | P27: =Progress!L22 -> 0.05680697 | Q27: =Progress!M22 -> 0 | R27: =Progress!N43 -> 0 | S27: =IFERROR(IF(ISBLANK(Q27),"",Q27/O27),0) -> 0 | T27: =IFERROR(IF(ISBLANK(R27),"",R27/O27),0) -> 0 | U27: =Progress!O35 -> 1141 | V27: =Progress!P22 -> 1995 | W27: =IFERROR(IF(ISBLANK(U27),"",U27/O27),0) -> 0.017630607 | X27: =IFERROR(IF(ISBLANK(V27),"",V27/O27),0) -> 0.030826522 | Y27: =IFERROR(X27-W27,"") -> 0.013195915 | Z27: =IFERROR(X27/W27,"") -> 1.7484663
A28: =Progress!A23 -> ZONE G | C28: =Progress!C23 -> 989226.71 | D28: =Progress!D23 -> 0.0058662725 | F28: =Progress!F23 -> 872.1 | G28: =Progress!G23 -> 0 | I28: =Progress!I23 -> 63487.76 | O28: =Progress!K23 -> 23091 | P28: =Progress!L23 -> 0.020268705 | Q28: =Progress!M23 -> 0 | R28: =Progress!N44 -> 0 | S28: =IFERROR(IF(ISBLANK(Q28),"",Q28/O28),0) -> 0 | T28: =IFERROR(IF(ISBLANK(R28),"",R28/O28),0) -> 0 | U28: =Progress!O36 -> 0 | V28: =Progress!P23 -> 1252 | W28: =IFERROR(IF(ISBLANK(U28),"",U28/O28),0) -> 0 | X28: =IFERROR(IF(ISBLANK(V28),"",V28/O28),0) -> 0.054220259 | Y28: =IFERROR(X28-W28,"") -> 0.054220259 | Z28: =IFERROR(X28/W28,"")
A29: =Progress!A24 -> Portable Water | C29: =Progress!C24 -> 7780467.6 | D29: =Progress!D24 -> 0.046139416 | F29: =Progress!F24 -> 16207.71 | G29: =Progress!G24 -> 0 | H29: =Progress!H24 -> 0 | I29: =Progress!I24 -> 1517663.9 | J29: =IFERROR(IF(ISBLANK(G29),"",G29/C29),0) -> 0 | K29: =IFERROR(IF(ISBLANK(H29),"",H29/C29),0) -> 0 | L29: =IFERROR(IF(ISBLANK(I29),"",I29/C29),0) -> 0.19506076 | M29: =IFERROR(L29-K29,"") -> 0.19506076 | O29: =Progress!K24 -> 139722 | P29: =Progress!L24 -> 0.12264449 | Q29: =Progress!M24 -> 0 | R29: =Progress!N24 -> 540 | S29: =IFERROR(IF(ISBLANK(Q29),"",Q29/O29),0) -> 0 | T29: =IFERROR(IF(ISBLANK(R29),"",R29/O29),0) -> 0.0038648173 | U29: =Progress!O37 -> 0 | V29: =Progress!P24 -> 14747 | W29: =IFERROR(IF(ISBLANK(U29),"",U29/O29),0) -> 0 | X29: =IFERROR(IF(ISBLANK(V29),"",V29/O29),0) -> 0.1055453 | Y29: =IFERROR(X29-W29,"") -> 0.1055453 | Z29: =IFERROR(X29/W29,"")
A30: =Progress!A25 -> ZONE A | C30: =Progress!C25 -> 4936252.6 | D30: =Progress!D25 -> 0.029272767 | F30: =Progress!F25 -> 16207.71 | G30: =Progress!G25 -> 0 | I30: =Progress!I25 -> 295925.92 | O30: =Progress!K25 -> 99650 | P30: =Progress!L25 -> 0.087470287 | Q30: =Progress!M25 -> 0 | R30: =Progress!N25 -> 540 | S30: =IFERROR(IF(ISBLANK(Q30),"",Q30/O30),0) -> 0 | T30: =IFERROR(IF(ISBLANK(R30),"",R30/O30),0) -> 0.0054189664 | U30: =Progress!O38 -> 0 | V30: =Progress!P25 -> 4061 | W30: =IFERROR(IF(ISBLANK(U30),"",U30/O30),0) -> 0 | X30: =IFERROR(IF(ISBLANK(V30),"",V30/O30),0) -> 0.040752634 | Y30: =IFERROR(X30-W30,"") -> 0.040752634 | Z30: =IFERROR(X30/W30,"")
A31: =Progress!A26 -> ZONE G | C31: =Progress!C26 -> 2844215 | D31: =Progress!D26 -> 0.016866649 | F31: =Progress!F26 -> 0 | G31: =Progress!G26 -> 0 | H31: =Progress!H26 -> 0 | I31: =Progress!I26 -> 1221738 | J31: =IFERROR(IF(ISBLANK(G31),"",G31/C31),0) -> 0 | K31: =IFERROR(IF(ISBLANK(H31),"",H31/C31),0) -> 0 | L31: =IFERROR(IF(ISBLANK(I31),"",I31/C31),0) -> 0.42955192 | M31: =IFERROR(L31-K31,"") -> 0.42955192 | O31: =Progress!K26 -> 40072 | P31: =Progress!L26 -> 0.035174203 | Q31: =Progress!M26 -> 0 | R31: =Progress!N26 -> 0 | S31: =IFERROR(IF(ISBLANK(Q31),"",Q31/O31),0) -> 0 | T31: =IFERROR(IF(ISBLANK(R31),"",R31/O31),0) -> 0 | U31: =Progress!O39 -> 0 | V31: =Progress!P26 -> 10686 | W31: =IFERROR(IF(ISBLANK(U31),"",U31/O31),0) -> 0 | X31: =IFERROR(IF(ISBLANK(V31),"",V31/O31),0) -> 0.26666999 | Y31: =IFERROR(X31-W31,"") -> 0.26666999 | Z31: =IFERROR(X31/W31,"")
A32: =Progress!A27 -> Electrical Works | C32: =Progress!C27 -> 20111193 | D32: =Progress!D27 -> 0.11926259 | F32: =Progress!F27 -> 23290.44 | G32: =Progress!G27 -> 0 | O32: =Progress!K27 -> 99033 | P32: =Progress!L27 -> 0.0869287
A33: =Progress!A28 -> ZONE A | C33: =Progress!C28 -> 13562632 | D33: =Progress!D28 -> 0.080428575 | G33: =Progress!G28 -> 0 | O33: =Progress!K28 -> 63660 | P33: =Progress!L28 -> 0.055879162
A34: =Progress!A29 -> ZONE G | C34: =Progress!C29 -> 6548561.2 | D34: =Progress!D29 -> 0.038834014 | G34: =Progress!G29 -> 0 | O34: =Progress!K29 -> 35373 | P34: =Progress!L29 -> 0.031049538
A35: =Progress!A30 -> Landscape & Irrigation Works | C35: =Progress!C30 -> 6835460.6 | D35: =Progress!D30 -> 0.040535373 | G35: =Progress!G30 -> 0 | O35: =Progress!K30 -> 77656 | P35: =Progress!L30 -> 0.068164502
A36: =Progress!A31 -> ZONE A | C36: =Progress!C31 -> 3801841.7 | D36: =Progress!D31 -> 0.022545529 | G36: =Progress!G31 -> 0 | O36: =Progress!K31 -> 65750 | P36: =Progress!L31 -> 0.057713712
A37: =Progress!A32 -> ZONE G | C37: =Progress!C32 -> 3033618.9 | D37: =Progress!D32 -> 0.017989845 | G37: =Progress!G32 -> 0 | O37: =Progress!K32 -> 11907 | P37: =Progress!L32 -> 0.010451668
A38: =Progress!A33 -> CCTV Works | C38: =Progress!C33 -> 9305849.6 | D38: =Progress!D33 -> 0.055185175 | G38: =Progress!G33 -> 0 | O38: =Progress!K33 -> 14178 | P38: =Progress!L33 -> 0.012445095
A39: =Progress!A34 -> ZONE A | C39: 46056 | D39: =Progress!D34 -> 0.038629034 | G39: =Progress!G34 -> 0 | O39: =Progress!K34 -> 7062 | P39: =Progress!L34 -> 0.0061988477
A40: =Progress!A35 -> ZONE G | C40: 2 | D40: =Progress!D35 -> 0.016556141 | G40: =Progress!G35 -> 0 | O40: =Progress!K35 -> 7116 | P40: =Progress!L35 -> 0.0062462475
A41: =Progress!A36 -> Testing and commissioning | C41: =Progress!C36 -> 0 | D41: =Progress!D36 -> 0 | E41: =Progress!E44 -> 0 | F41: =Progress!F44 -> 0 | G41: =Progress!G36 -> 0 | H41: =Progress!H36 -> 0 | I41: =Progress!I36 -> 0 | J41: =IFERROR(IF(ISBLANK(G41),"",G41/C41),0) -> 0 | K41: =IFERROR(IF(ISBLANK(I41),"",I41/C41),0) -> 0 | L41: =IFERROR(IF(ISBLANK(I41),"",I41/C41),0) -> 0 | M41: =IFERROR(L41-K41,"") -> 0 | N41: =IFERROR(L41/K41,"") | O41: =Progress!K36 -> 22785 | P41: =Progress!L36 -> 0.020000105 | Q41: =Progress!M44 -> 0 | R41: =Progress!N44 -> 0 | S41: =IFERROR(IF(ISBLANK(Q41),"",Q41/O41),0) -> 0 | T41: =IFERROR(IF(ISBLANK(R41),"",R41/O41),0) -> 0 | U41: =Progress!O36 -> 0 | V41: =Progress!P36 -> 0 | W41: =IFERROR(IF(ISBLANK(U41),"",U41/O41),0) -> 0 | X41: =IFERROR(IF(ISBLANK(V41),"",V41/O41),0) -> 0 | Y41: =IFERROR(X41-W41,"") -> 0 | Z41: =IFERROR(X41/W41,"")
A42: =Progress!A37 -> Close out | C42: =Progress!C37 -> 0 | D42: =Progress!D37 -> 0 | E42: =Progress!E45 -> 0 | F42: =Progress!F45 -> 0 | G42: =Progress!G37 -> 0 | H42: =Progress!H37 -> 0 | I42: =Progress!I37 -> 0 | J42: =IFERROR(IF(ISBLANK(G42),"",G42/C42),0) -> 0 | K42: =IFERROR(IF(ISBLANK(I42),"",I42/C42),0) -> 0 | L42: =IFERROR(IF(ISBLANK(I42),"",I42/C42),0) -> 0 | M42: =IFERROR(L42-K42,"") -> 0 | N42: =IFERROR(L42/K42,"") | O42: =Progress!K37 -> 22785 | P42: =Progress!L37 -> 0.020000105 | Q42: =Progress!M45 -> 0 | R42: =Progress!N45 -> 0 | S42: =IFERROR(IF(ISBLANK(Q42),"",Q42/O42),0) -> 0 | T42: =IFERROR(IF(ISBLANK(R42),"",R42/O42),0) -> 0 | U42: =Progress!O37 -> 0 | V42: =Progress!P37 -> 0 | W42: =IFERROR(IF(ISBLANK(U42),"",U42/O42),0) -> 0 | X42: =IFERROR(IF(ISBLANK(V42),"",V42/O42),0) -> 0 | Y42: =IFERROR(X42-W42,"") -> 0 | Z42: =IFERROR(X42/W42,"")
B43: Total | C43: =Progress!C46 -> 1.6862952e+08 | D43: =Progress!D46 -> 1 | E43: =Progress!E46 -> 3995420.2 | F43: =Progress!F46 -> 1709872.9 | G43: =Progress!G46 -> 0 | H43: =Progress!H46 -> 54083772 | I43: =Progress!I46 -> 73149321 | J43: =IFERROR(IF(ISBLANK(G43),"",G43/C43),0) -> 0 | K43: =IFERROR(IF(ISBLANK(H43),"",H43/C43),0) -> 0.32072541 | L43: =IFERROR(IF(ISBLANK(I43),"",I43/C43),0) -> 0.43378716 | M43: =+L43-K43 -> 0.11306175 | N43: =L43/K43 -> 1.3525189 | O43: =Progress!K46 -> 1139244 | P43: =Progress!L46 -> 1 | Q43: =Progress!M46 -> 15397 | R43: =Progress!N46 -> 3659 | S43: =IFERROR(IF(ISBLANK(Q43),"",Q43/O43),0) -> 0.013515103 | T43: =IFERROR(IF(ISBLANK(R43),"",R43/O43),0) -> 0.003211779 | U43: =Progress!O46 -> 406247 | V43: =Progress!P46 -> 446959 | W43: =IFERROR(IF(ISBLANK(U43),"",U43/O43),0) -> 0.3565935 | X43: =IFERROR(IF(ISBLANK(V43),"",V43/O43),0) -> 0.39232947 | Y43: =+X43-W43 -> 0.035735979 | Z43: =X43/W43 -> 1.1002149
AA44: Construction Milestones
AA45: Item No. | AB45: Milestones | AD45: Original (Baseline) | AE45: Latest Plan | AF45: Forecast | AH45: Status | AI45: Days Change
H46: =H9+H10+H11+H36+H37 -> #VALUE! | AA46: =+Milestones!A4 -> 1 | AB46: =+Milestones!B4 -> Project Start Milstone | AD46: =+Milestones!D4 -> 46028 | AE46: =+Milestones!E4 -> 46028 | AF46: =+Milestones!E4 -> 46028 | AH46: =Milestones!F4 -> Finish | AI46: =+Milestones!G4 -> 0
Z47: =+Milestones!#REF! -> #REF! | AA47: =+Milestones!A5 -> 2 | AB47: =+Milestones!B5 -> Mobilization Finish Milestone | AD47: =+Milestones!D5 -> 46058 | AE47: =+Milestones!E5 -> 46058 | AF47: =+Milestones!E5 -> 46058 | AH47: =Milestones!F5 -> Finish | AI47: =+Milestones!G5 -> 0
Z48: =+Milestones!#REF! -> #REF! | AA48: =+Milestones!A6 -> 3 | AB48: =+Milestones!B6 -> Baseline Submission Finish Milestone | AD48: =+Milestones!D6 -> 46058 | AE48: =+Milestones!E6 -> 46118 | AF48: =+Milestones!E6 -> 46118 | AH48: =+Milestones!F6 -> Finish | AI48: =+Milestones!G6 -> -60
Z49: =+Milestones!#REF! -> #REF! | AA49: =+Milestones!A7 -> 4 | AB49: =+Milestones!B7 -> Technical Submittals Finish Milestone | AD49: =+Milestones!D7 -> 46086 | AE49: =+Milestones!E7 -> 46250 | AF49: =+Milestones!E7 -> 46250 | AH49: =+Milestones!F7 -> UP | AI49: =+Milestones!G7 -> -164
Z50: =+Milestones!#REF! -> #REF! | AA50: =+Milestones!A8 -> 5 | AB50: =+Milestones!B8 -> Quality Lap Finish Milestone | AD50: =+Milestones!D8 -> 46058 | AE50: =+Milestones!E8 -> 46069 | AF50: =+Milestones!E8 -> 46069 | AH50: =+Milestones!F8 -> Finish | AI50: =+Milestones!G8 -> -11
Z51: =+Milestones!#REF! -> #REF! | AA51: =+Milestones!A9 -> 6 | AB51: =+Milestones!B9 -> RBF Finish Milestone | AD51: =+Milestones!D9 -> 46058 | AE51: =+Milestones!E9 -> 46069 | AF51: =+Milestones!E9 -> 46069 | AH51: =+Milestones!F9 -> Finish | AI51: =+Milestones!G9 -> -11
G52: 20000000 | H52: 505886 | I52: 463892 | O52: 34555 | P52: 34555 | Z52: =+Milestones!#REF! -> #REF! | AA52: =+Milestones!A10 -> 7 | AB52: =+Milestones!B10 -> All Works Finish Milestone | AD52: =+Milestones!D10 -> 46573 | AE52: =+Milestones!E10 -> 46573 | AF52: =+Milestones!E10 -> 46573 | AH52: =+Milestones!F10 -> UP | AI52: =+Milestones!G10 -> 0
H53: 86640 | I53: 605533 | Z53: =+Milestones!#REF! -> #REF! | AA53: =+Milestones!A11 -> 8 | AB53: =+Milestones!B11 -> Engineering Phase Finish Milestone | AD53: =+Milestones!D11 -> 46086 | AE53: =+Milestones!E11 -> 46293 | AF53: =+Milestones!E11 -> 46293 | AH53: =+Milestones!F11 -> UP | AI53: =+Milestones!G11 -> -207
H54: =H55+H58 -> 926799 | O54: =57592 -> 57592 | P54: 50223 | Z54: =+Milestones!#REF! -> #REF! | AA54: =+Milestones!A12 -> 9 | AB54: =+Milestones!B12 -> Procurment Phase Finish Milestone | AD54: =+Milestones!D12 -> 46410 | AE54: =+Milestones!E12 -> 46404 | AF54: =+Milestones!E12 -> 46404 | AH54: =+Milestones!F12 -> UP | AI54: =+Milestones!G12 -> 6
H55: =H56+H57 -> 921566 | O55: 9755 | P55: 11013
H56: 479000 | I56: 504900 | O56: 4073
H57: 442566 | I57: 1116058 | O57: =O58+O59 -> 3975 | P57: =P58+P59 -> 8164
H58: =H59+H60 -> 5233 | I58: =I59+I60 -> 186144 | O58: 2008 | P58: 2454
H59: 5233 | I59: 186144 | O59: 1967 | P59: 5710
O60: =O61+O62 -> 97 | P60: =P61+P62 -> 635
O61: 97 | P61: 635
A70: Performance overview
A71: Submittals Status | L71: Quality | W71: Safety
A72: Shop Drawings | L72: Quality Reports | W72: Safety Statistics | AE72: Proactive Vs Reactive Actions Taken
A73: Item Per WBS | C73: Total | D73: Total Submitted Drawings | I73: Remaining | J73: Pending | K73: Total Submittals | L73: Quality Reports | N73: Issued | O73: Closed | P73: Pending | Q73: Avg. Closing (Days) | R73: Pending | W73: Category | X73: Item | Z73: This Week | AB73: This Month | AC73: Year to Date | AD73: Cumulative
D74: A | E74: B | F74: C | G74: D | H74: Processed | R74: 0-10 Days | S74: 11-20 Days | T74: 21-30 Days | U74: 31-60 Days | V74: > 60 Days
A75: Road work | C75: =+'Quality-Stat'!D14 -> 130 | D75: =+'Quality-Stat'!E14 -> 28 | E75: =+'Quality-Stat'!F14 -> 102 | F75: =+'Quality-Stat'!G14 -> 0 | G75: =+'Quality-Stat'!H14 -> 0 | H75: =+'Quality-Stat'!I14 -> 130 | I75: =+'Quality-Stat'!J14 -> 0 | J75: =+'Quality-Stat'!K14 -> 0 | K75: =+'Quality-Stat'!L14 -> 130 | W75: General | X75: ='[36]HSE-Stat'!B4 -> Total Hours Worked | Z75: ='HSE-Stat '!D4 -> 36000 | AB75: ='HSE-Stat '!E4 -> 122940 | AC75: ='HSE-Stat '!F4 -> 790456 | AD75: ='HSE-Stat '!G4 -> 490456 | AH75: Proactive | AI75: =+SUM(AD86:AD90) -> 90
A76: wet network(sewer,storm,potable,irrigation) | C76: =+'Quality-Stat'!D15 -> 140 | D76: =+'Quality-Stat'!E15 -> 22 | E76: 112 | F76: =+'Quality-Stat'!G15 -> 0 | G76: =+'Quality-Stat'!H15 -> 0 | H76: 135 | I76: =+'Quality-Stat'!J15 -> 0 | J76: 0 | K76: =+'Quality-Stat'!L15 -> 144 | L76: Non Conformance (NCR) | N76: =+'Quality-Stat'!C6 -> 16 | O76: =+'Quality-Stat'!D6 -> 13 | P76: =+'Quality-Stat'!E6 -> 3 | Q76: =+'Quality-Stat'!F6 -> 0 | R76: =+'Quality-Stat'!G6 -> 3 | S76: =+'Quality-Stat'!H6 -> 0 | T76: =+'Quality-Stat'!I6 -> 0 | U76: =+'Quality-Stat'!J6 -> 0 | V76: =+'Quality-Stat'!K6 -> 0 | X76: ='[36]HSE-Stat'!B5 -> Safe Hours Worked | Z76: ='HSE-Stat '!D5 -> 36000 | AB76: ='HSE-Stat '!E5 -> 122940 | AC76: ='HSE-Stat '!F5 -> 790456 | AD76: ='HSE-Stat '!G5 -> 490456 | AH76: Reactive | AI76: =SUM(AD77:AD85) -> 0
A77: Electrical,Telecom,Street light | C77: =+'Quality-Stat'!D16 -> 107 | D77: =+'Quality-Stat'!E16 -> 4 | E77: =+'Quality-Stat'!F16 -> 103 | F77: =+'Quality-Stat'!G16 -> 0 | G77: =+'Quality-Stat'!H16 -> 0 | H77: =+'Quality-Stat'!I16 -> 107 | I77: =+'Quality-Stat'!J16 -> 0 | J77: =+'Quality-Stat'!K16 -> 0 | K77: =+'Quality-Stat'!L16 -> 107 | L77: Site Instruction (SIR) | N77: =+'Quality-Stat'!C7 -> 5 | O77: =+'Quality-Stat'!D7 -> 5 | P77: =+'Quality-Stat'!E7 -> 0 | Q77: =+'Quality-Stat'!F7 -> 0 | R77: =+'Quality-Stat'!G7 -> 0 | S77: =+'Quality-Stat'!H7 -> 0 | T77: =+'Quality-Stat'!I7 -> 0 | U77: =+'Quality-Stat'!J7 -> 0 | V77: =+'Quality-Stat'!K7 -> 0 | W77: Reactive | X77: 0 | Z77: 0 | AB77: 0 | AC77: ='HSE-Stat '!F6 -> 52 | AD77: 0
A78: Landscape | C78: =+'Quality-Stat'!D17 -> 22 | D78: =+'Quality-Stat'!E17 -> 3 | E78: =+'Quality-Stat'!F17 -> 4 | F78: =+'Quality-Stat'!G17 -> 15 | G78: =+'Quality-Stat'!H17 -> 0 | H78: =+'Quality-Stat'!I17 -> 7 | I78: =+'Quality-Stat'!J17 -> 0 | J78: =+'Quality-Stat'!K17 -> 0 | K78: =+'Quality-Stat'!L17 -> 7 | L78: Material Inspection (MIR) | N78: =+'Quality-Stat'!C8 -> 196 | O78: =+'Quality-Stat'!D8 -> 190 | P78: =+'Quality-Stat'!E8 -> 6 | Q78: =+'Quality-Stat'!F8 -> 0 | R78: =+'Quality-Stat'!G8 -> 6 | S78: =+'Quality-Stat'!H8 -> 0 | T78: =+'Quality-Stat'!I8 -> 0 | U78: =+'Quality-Stat'!J8 -> 0 | V78: =+'Quality-Stat'!K8 -> 0 | X78: 0 | Z78: 0 | AB78: 0 | AC78: ='HSE-Stat '!F7 -> 0 | AD78: 0
A79: CCTV | C79: =+'Quality-Stat'!D18 -> 12 | D79: =+'Quality-Stat'!E18 -> 0 | E79: =+'Quality-Stat'!F18 -> 12 | F79: =+'Quality-Stat'!G18 -> 0 | G79: =+'Quality-Stat'!H18 -> 0 | H79: =+'Quality-Stat'!I18 -> 12 | I79: =+'Quality-Stat'!J18 -> 0 | J79: =+'Quality-Stat'!K18 -> 0 | K79: =+'Quality-Stat'!L18 -> 12 | L79: Field Inspection (FIR) | N79: =+'Quality-Stat'!C9 -> 3182 | O79: =+'Quality-Stat'!D9 -> 3080 | P79: =+'Quality-Stat'!E9 -> 102 | Q79: =+'Quality-Stat'!F9 -> 0 | R79: =+'Quality-Stat'!G9 -> 102 | S79: =+'Quality-Stat'!H9 -> 0 | T79: =+'Quality-Stat'!I9 -> - | U79: =+'Quality-Stat'!J9 -> 0 | V79: =+'Quality-Stat'!K9 -> 0 | X79: 0 | Z79: 0 | AB79: 0 | AC79: ='HSE-Stat '!F8 -> 38 | AD79: 0
A80: TOTAL | C80: =+'Quality-Stat'!D19 -> 411 | D80: =+'Quality-Stat'!E19 -> 57 | E80: =+'Quality-Stat'!F19 -> 339 | F80: =+'Quality-Stat'!G19 -> 15 | G80: =+'Quality-Stat'!H19 -> 0 | H80: =+'Quality-Stat'!I19 -> 396 | I80: =+'Quality-Stat'!J19 -> 0 | J80: =+'Quality-Stat'!K19 -> 4 | K80: =+'Quality-Stat'!L19 -> 400 | L80: Key Submittals Approval Status | X80: 0 | Z80: 0 | AB80: 0 | AC80: ='[36]HSE-Stat'!F9 -> 0 | AD80: 0
A81: Material Approval | L81: 1 Quality Plan Approval | O81: ='General Information'!C27 -> 46112 | Q81: 6 Baseline Approval | U81: ='General Information'!C39 -> 46120 | X81: 0 | Z81: 0 | AB81: 0 | AC81: 0 | AD81: 0 | AE81: Total Hours Worked Vs Safe Hours Worked
A82: Item Per WBS | C82: Total | D82: Total Submitted Material | I82: Remaining to approve | J82: Pending | K82: Total Submittals | L82: 2 Quality Plan Last Up | O82: ='General Information'!C28 -> 46112 | Q82: 7 No of Approved Version of Schedule | U82: ='General Information'!C40 -> 1 | X82: 0 | Z82: 0 | AB82: 0 | AC82: 0 | AD82: 0
D83: A | E83: B | F83: C | G83: D | H83: Processed | I83: with Designer | L83: 3 Safety Plan Approval | O83: ='General Information'!C31 -> 46049 | Q83: 8 Last Approved Schedule | U83: ='General Information'!C41 -> - | X83: 0 | Z83: 0 | AB83: 0 | AC83: ='[36]HSE-Stat'!F12 -> 0 | AD83: 0
A84: Civil /Structural /Architectural | C84: =+'Quality-Stat'!D25 -> 25 | D84: =+'Quality-Stat'!E25 -> 0 | E84: =+'Quality-Stat'!F25 -> 20 | F84: =+'Quality-Stat'!G25 -> 0 | G84: =+'Quality-Stat'!H25 -> 1 | H84: =+'Quality-Stat'!I25 -> 20 | I84: =+'Quality-Stat'!J25 -> 4 | J84: =+'Quality-Stat'!K25 -> 0 | K84: =+'Quality-Stat'!L25 -> 21 | L84: 4 Safety Plan Last Up | O84: ='General Information'!C32 -> 46049 | Q84: 9 BOQ Approval Date | U84: ='General Information'!C44 -> - | X84: 0 | Z84: 0 | AB84: 0 | AC84: 0 | AD84: 0
A85: Mechanical | C85: =+'Quality-Stat'!D26 -> 14 | D85: =+'Quality-Stat'!E26 -> 0 | E85: =+'Quality-Stat'!F26 -> 14 | F85: =+'Quality-Stat'!G26 -> 0 | G85: =+'Quality-Stat'!H26 -> 0 | H85: =+'Quality-Stat'!I26 -> 14 | I85: =+'Quality-Stat'!J26 -> 0 | J85: =+'Quality-Stat'!K26 -> - | K85: =+'Quality-Stat'!L26 -> 14 | L85: 5 Construction Plan Approval | O85: ='General Information'!C48 -> 46063 | Q85: 10 No of Approved Version of BOQ | U85: ='General Information'!C45 -> - | X85: 0 | Z85: 0 | AB85: 0 | AC85: ='[36]HSE-Stat'!F14 -> 46088 | AD85: 0
A86: Electrical | C86: =+'Quality-Stat'!D27 -> 21 | D86: =+'Quality-Stat'!E27 -> 1 | E86: =+'Quality-Stat'!F27 -> 17 | F86: =+'Quality-Stat'!G27 -> 0 | G86: =+'Quality-Stat'!H27 -> 3 | H86: =+'Quality-Stat'!I27 -> 21 | I86: =+'Quality-Stat'!J27 -> 0 | J86: =+'Quality-Stat'!K27 -> 0 | K86: =+'Quality-Stat'!L27 -> 18 | L86: Invoices Summary | W86: Proactive | X86: 0 | Z86: 0 | AB86: 0 | AC86: ='[36]HSE-Stat'!F15 -> 46095 | AD86: 0
L87: Total Submitted Invoices | N87: ='Invoice Log'!V3 -> 3 | O87: Submitted Invoices (SAR) | R87: ='Invoice Log'!Z3 -> 16773813 | T87: Contract Value (SR) | U87: =O4 -> 0 | X87: ='[36]HSE-Stat'!B6 -> No.of Internal Training | Z87: ='HSE-Stat '!D6 -> 1 | AB87: ='HSE-Stat '!E6 -> 4 | AC87: ='HSE-Stat '!F6 -> 52 | AD87: ='HSE-Stat '!G6 -> 52
L88: PM Approved Invoices | N88: ='Invoice Log'!V5 -> 0 | O88: PM Approved Invoices (SAR) | R88: ='Invoice Log'!Z5 -> 0 | T88: Planned Value (SR) | U88: =H43 -> 54083772 | X88: ='[36]HSE-Stat'!B7 -> No.of Internal Audit | Z88: ='[36]HSE-Stat'!D7 -> 0 | AB88: ='[36]HSE-Stat'!E7 -> 0 | AC88: ='[36]HSE-Stat'!F7 -> 0 | AD88: ='[36]HSE-Stat'!G7 -> 0
A89: TOTAL | C89: =+'Quality-Stat'!D28 -> 60 | D89: =SUM(D84:D88) -> 1 | E89: =SUM(E84:E88) -> 51 | F89: =SUM(F84:F88) -> 0 | G89: =SUM(G84:G88) -> 4 | H89: =SUM(H84:H88) -> 55 | I89: =SUM(I84:I88) -> 4 | J89: =SUM(J84:J88) -> 0 | K89: =SUM(K84:K88) -> 53 | L89: No of Paid Invoices | N89: ='Invoice Log'!V6 -> 0 | O89: Paid Invoices (SAR) | R89: ='Invoice Log'!Z6 -> 0 | T89: Earned Value (SR) | U89: =I43 -> 73149321 | X89: ='[36]HSE-Stat'!B8 -> No. of Toolbox Talks | Z89: ='HSE-Stat '!D8 -> 1 | AB89: ='HSE-Stat '!E8 -> 4 | AC89: ='HSE-Stat '!F8 -> 38 | AD89: ='HSE-Stat '!G8 -> 38
A90: Procurement Summary | L90: No of Pending Invoices | N90: =+N87-N89 -> 3 | O90: Last Submitted Period | R90: ='Invoice Log'!AC3 -> 0 | T90: Submitted (SAR) | U90: =R87 -> 16773813 | X90: ='[36]HSE-Stat'!B9 -> Safety Awards/Incentives | Z90: ='[36]HSE-Stat'!D9 -> 0 | AB90: ='[36]HSE-Stat'!E9 -> 0 | AC90: ='[36]HSE-Stat'!F9 -> 0 | AD90: ='[36]HSE-Stat'!G9 -> 0
A91: Item Per WBS | C91: Total Materials | D91: Total Number of P.O. | E91: Actual P.O. To Date | F91: Remaining P.O | G91: Material on Site | H91: Remaining Materials | I91: Material Delivery Completion (Date) | L91: Advance Payment % | N91: ='Invoice Log'!N3 -> 0.1 | O91: Advance Payment (SAR) | R91: ='Invoice Log'!R3 -> 16862952 | T91: PM Approved (SAR) | U91: =R88 -> 0 | W91: Latest Contract Change Order Log
D92: A | E92: B | F92: C | G92: D | H92: Processed | L92: Retention % | N92: ='Invoice Log'!N4 -> 0 | O92: Retention (SAR) | R92: ='Invoice Log'!R4 -> 0 | T92: Total Paid (SAR) | U92: =R89 -> 0
A93: Civil /Structural /Architectural | C93: =+'Quality-Stat'!D33 -> 16 | D93: =+'Quality-Stat'!E33 -> 16 | E93: =+'Quality-Stat'!F33 -> 10 | F93: =+'Quality-Stat'!G33 -> 6 | G93: =+'Quality-Stat'!H33 -> 7 | H93: =IF('Quality-Stat'!I33="","",'Quality-Stat'!I33) -> 9 | I93: {=+'Quality-Stat'!J33:L33} -> - | J93: 0 | K93: 0 | L93: Deduction / Penalties % | N93: ='Invoice Log'!N5 -> -0.0042732501 | O93: Deduction / Penalties (SAR) | R93: ='Invoice Log'!N6 -> -28000 | W93: CCO No. | X93: Date Added | Y93: Description of Change | AD93: Status | AE93: Cost | AF93: Sch Impact (Months) | AH93: Date Approved | AI93: Duration
A94: Mechanical | C94: =IF('Quality-Stat'!D34="","",'Quality-Stat'!D34) -> 75 | D94: =IF('Quality-Stat'!E34="","",'Quality-Stat'!E34) -> 59 | E94: =IF('Quality-Stat'!F34="","",'Quality-Stat'!F34) -> 59 | F94: =IF('Quality-Stat'!G34="","",'Quality-Stat'!G34) -> 17 | G94: =IF('Quality-Stat'!H34="","",'Quality-Stat'!H34) -> 23 | H94: =IF('Quality-Stat'!I34="","",'Quality-Stat'!I34) -> 52 | I94: {=+'Quality-Stat'!J34:L34} -> - | J94: 0 | K94: 0 | L94: Resources at Site
A95: Electrical | C95: =IF('Quality-Stat'!D35="","",'Quality-Stat'!D35) -> 20 | D95: =IF('Quality-Stat'!E35="","",'Quality-Stat'!E35) -> 14 | E95: =IF('Quality-Stat'!F35="","",'Quality-Stat'!F35) -> 14 | F95: =IF('Quality-Stat'!G35="","",'Quality-Stat'!G35) -> 6 | G95: =IF('Quality-Stat'!H35="","",'Quality-Stat'!H35) -> 4 | H95: =IF('Quality-Stat'!I35="","",'Quality-Stat'!I35) -> 16 | I95: {=+'Quality-Stat'!J35:L35} -> - | J95: 0 | K95: 0 | L95: Head Count - Manual | P95: Head Count - Non Manual | T95: Total Head Count | W95: =CCO!A3 -> - | X95: =CCO!B3 -> - | Y95: =CCO!C3 -> - | AD95: =CCO!D3 -> - | AE95: =CCO!E3 -> - | AF95: =CCO!F3 -> - | AH95: =CCO!G3 -> - | AI95: =CCO!H3 -> -
L96: Planned | M96: Actual | N96: Next Month Forecast | O96: Saudi Staff | P96: Planned | Q96: Actual | R96: Next Month Forecast | S96: Saudi Staff | T96: Total Plan | U96: Total Actual | V96: Variance
L97: =Manpower!A24 -> 287 | M97: =Manpower!B24 -> 547 | N97: =Manpower!F24 -> 0 | O97: =Manpower!H24 -> 2 | P97: =Manpower!A20 -> 32 | Q97: =Manpower!B20 -> 53 | R97: =Manpower!F20 -> 0 | S97: =Manpower!H20 -> 4 | T97: =L97+P97 -> 319 | U97: =M97+Q97 -> 600 | V97: =+U97-T97 -> 281
A98: TOTAL | C98: =IF('Quality-Stat'!D36="","",'Quality-Stat'!D36) -> 111 | D98: =IF('Quality-Stat'!E36="","",'Quality-Stat'!E36) -> 89 | E98: =IF('Quality-Stat'!F36="","",'Quality-Stat'!F36) -> 83 | F98: =IF('Quality-Stat'!G36="","",'Quality-Stat'!G36) -> 29 | G98: =IF('Quality-Stat'!H36="","",'Quality-Stat'!H36) -> 34 | H98: =IF('Quality-Stat'!I36="","",'Quality-Stat'!I36) -> 77 | I98: =MAX('Quality-Stat'!J33:L35) -> 0 | L98: Manpower Breakdown by Trade | S98: Major Equipment
A99: =Schedule!A1 -> Primavera P6 Schedule Status | L99: Key Trade | M99: Planned | N99: Actual | S99: Type | T99: Planned | U99: Actual | V99: Idle
A100: =Schedule!A2 -> Project Activities Overview | L100: =+Manpower!N23 -> Engineer | M100: =Manpower!N24 -> 15 | N100: =Manpower!N25 -> 16 | S100: =+Manpower!$B$49 -> PICK UP/Car | T100: =Manpower!B50 -> 7 | U100: =+Manpower!B51 -> 12 | V100: =+Manpower!B52 -> 0
A101: =Schedule!A3 -> Schedule Statistics | F101: =Schedule!F3 -> Active Schedule Activities | L101: =+Manpower!P23 -> Doc. Controller | M101: =Manpower!P24 -> 2 | N101: =Manpower!P25 -> 3 | S101: =+Manpower!$D$49 -> Bus | T101: =+Manpower!D50 -> 4 | U101: =Manpower!D51 -> 6 | V101: =+Manpower!D52 -> 0 | W101: Major Quantity Trackers
A102: =Schedule!A4 -> Total Act. | B102: =Schedule!B4 -> Not Started | C102: =Schedule!C4 -> In Progress | D102: =Schedule!D4 -> Completed | E102: =Schedule!E4 -> % | F102: =Schedule!F4 -> Active | G102: =Schedule!G4 -> Ahead | H102: =Schedule!H4 -> On | ... K102: =Schedule!K4 -> 0 | L102: =+Manpower!R23 -> Proc. Team | M102: =+Manpower!R24 -> 3 | N102: =Manpower!R25 -> 3 | S102: =+Manpower!$F$49 -> Dump Truck | T102: =+Manpower!F50 -> 70 | U102: =Manpower!F51 -> 158 | V102: =+Manpower!F52 -> 0 | W102: BOQ N0. | X102: Item Description | AC102: Total Qty | AD102: Measu Unit | AE102: Plan to Date | AF102: ='Major Quantities'!F2 -> Actual To Date Delivered | AG102: ='Major Quantities'!G2 -> Excecuted on site | AH102: ='Major Quantities'!H2 -> Remaining Total Delivery | AI102: Variance
A103: =Schedule!A5 -> 2115 | B103: =Schedule!B5 -> 1084 | C103: 144 | D103: =Schedule!D5 -> 691 | E103: =Schedule!E5 -> 0.32671395 | F103: =Schedule!F5 -> 9 | G103: =Schedule!G5 -> 8 | H103: =Schedule!H5 -> 0 | I103: =Schedule!I5 -> 11 | J103: =Schedule!J5 -> -3 | L103: =+Manpower!T23 -> Foreman | M103: =Manpower!T24 -> 9 | N103: =Manpower!T25 -> 18 | S103: =+Manpower!$H$49 -> Boom Truck | T103: =+Manpower!H50 -> 2 | U103: =Manpower!H51 -> 5 | V103: =+Manpower!H52 -> 0 | W103: ='Major Quantities'!A3 -> 33 31 00 | X103: ='Major Quantities'!B3 -> GRP Pipes | AC103: ='Major Quantities'!C3 -> 18337 | AD103: ='Major Quantities'!D3 -> m | AE103: ='Major Quantities'!E3 -> 16000 | AF103: ='Major Quantities'!F3 -> 17162 | AG103: ='Major Quantities'!G3 -> 15000 | AH103: ='Major Quantities'!H3 -> 1175 | AI103: ='Major Quantities'!I3 -> 1162
A104: =Schedule!A6 -> Critical Path Activities | D104: =Schedule!D6 -> Free Float Management (Total) | H104: =Schedule!H6 -> Failed Start Activities | L104: =+Manpower!V23 -> Draftman | M104: =+Manpower!V24 -> 2 | N104: =+Manpower!V25 -> 2 | S104: =+Manpower!$J$49 -> Generator + Tower Light | T104: =+Manpower!J50 -> 4 | U104: =Manpower!J51 -> 5 | V104: =+Manpower!J52 -> 0 | W104: ='Major Quantities'!A4 -> 33 05 39 | X104: ='Major Quantities'!B4 -> Manholes | AC104: ='Major Quantities'!C4 -> 251 | AD104: ='Major Quantities'!D4 -> m | AE104: ='Major Quantities'!E4 -> 150 | AF104: ='Major Quantities'!F4 -> 221 | AG104: ='Major Quantities'!G4 -> 175 | AH104: ='Major Quantities'!H4 -> 30 | AI104: ='Major Quantities'!I4 -> 71
D105: =Schedule!D7 -> Greater Than 14 Days | F105: =Schedule!F7 -> Less Than 14 Days | L105: =+Manpower!X23 -> Driver | M105: =+Manpower!X24 -> 135 | N105: =+Manpower!X25 -> 321 | S105: =+Manpower!$L$49 -> JCB | T105: =+Manpower!L50 -> 3 | U105: =Manpower!L51 -> 9 | V105: =+Manpower!L52 -> 0 | W105: ='Major Quantities'!A5 -> 33 42.1 | X105: ='Major Quantities'!B5 -> UPVC Pipes | AC105: ='Major Quantities'!C5 -> 4716 | AD105: ='Major Quantities'!D5 -> m | AE105: ='Major Quantities'!E5 -> 5500 | AF105: ='Major Quantities'!F5 -> 4716 | AG105: ='Major Quantities'!G5 -> 800 | AH105: ='Major Quantities'!H5 -> 0 | AI105: ='Major Quantities'!I5 -> -784
A106: =Schedule!A8 -> Last Week | B106: =Schedule!B8 -> This Week | C106: =Schedule!C8 -> Diff | D106: =Schedule!D8 -> Last Week | E106: =Schedule!E8 -> This Week | F106: =Schedule!F8 -> Last Week | G106: =Schedule!G8 -> This Week | H106: =Schedule!H8 -> Last Week | ... K106: =Schedule!K8 -> 0 | L106: =Manpower!Z23 -> UnSkilled Labor | M106: =Manpower!Z24 -> 41 | N106: =Manpower!Z25 -> 84 | S106: =+Manpower!$N$49 -> Water Tank | T106: =+Manpower!N50 -> 13 | U106: =+Manpower!N51 -> 15 | V106: =+Manpower!N52 -> 0 | W106: ='Major Quantities'!A6 -> 33 42.1 | X106: ='Major Quantities'!B6 -> Fire Hydrants | AC106: ='Major Quantities'!C6 -> 90 | AD106: ='Major Quantities'!D6 -> Unit | AE106: ='Major Quantities'!E6 -> 20 | AF106: ='Major Quantities'!F6 -> 90 | AG106: ='Major Quantities'!G6 -> 0 | AH106: ='Major Quantities'!H6 -> 0 | AI106: ='Major Quantities'!I6 -> 70
A107: =Schedule!A9 -> 20 | B107: =Schedule!B9 -> 19 | C107: =Schedule!C9 -> 1 | D107: =Schedule!D9 -> 200 | E107: =Schedule!E9 -> 191 | F107: =Schedule!F9 -> 1229 | G107: =Schedule!G9 -> 1229 | H107: =Schedule!H9 -> 16 | ... J107: =Schedule!J9 -> 6 | L107: Total | M107: =Manpower!AF24 -> 287 | N107: =Manpower!AF25 -> 600 | S107: Total | T107: =SUM(T100:T106) -> 103 | U107: =SUM(U100:U106) -> 210 | V107: =SUM(V100:V106) -> 0 | W107: ='Major Quantities'!A7 -> 33 05 39 | X107: ='Major Quantities'!B7 -> Catch Basins | AC107: ='Major Quantities'!C7 -> 295 | AD107: ='Major Quantities'!D7 -> Unit | AE107: ='Major Quantities'!E7 -> 150 | AF107: ='Major Quantities'!F7 -> 293 | AG107: ='Major Quantities'!G7 -> 80 | AH107: ='Major Quantities'!H7 -> 2 | AI107: ='Major Quantities'!I7 -> 143
A108: Weekly Prgoress Photos | Q108: Top Issues and Risks
A109: ='Weekly Photos'!L2 -> 0 | F109: ='Weekly Photos'!L21 -> Grading for base course layer works at MC20 Zone A | L109: ='Weekly Photos'!$B$21 -> Compaction for base course layer works at MC20 Zone A | Q109: Top 5 Issues
...

Sheet Sheet1

Sheet Sheet2

Sheet Sheet3

Sheet Sheet4

Sheet Sheet5

Sheet Sheet6

Sheet General Information
A1: Weekly Progress Report - Construction Projects | K1: Data Date | L1: 46293
A2: Contract General Information
A3: Project Name | C3: Infrastructure Network Development Project in Sudair City for Industry and Business - Phase Two - Part Two
A4: Project ID | C4: SUD1-02-011
A5: Contractor | C5: Technical Dvelopment Co. "TDC"
A6: Consultant | C6: Saudi Arabia Consulting Engineering Company "EGIS"
A7: Stage | C7: Construction
A8: Status | C8: Active
A9: Modon PM | C9: Engr.Zyad Al Shabat
H10: =H53 -> 0 | I10: =I53 -> 0
A11: Key Dates | H11: =H54 -> 0 | I11: =I54 -> 0
A12: Contract Award Date | C12: 45998
A13: Contract Sign Date | C13: 46020
A14: Site Handover Date | C14: 46028
A15: Original Completion | C15: 46573
A16: Contract Award Date (Hijri) | C16: 16/6/1447
A17: Contract Sign Date (Hijri) | C17: 9/7/1447
A18: Site Handover Date (Hijri) | C18: 17/7/1447
A19: Original Completion (Hijri) | C19: 30/1/1449
A20: Revised Completion Date | C20: 0
A21: Committed Completion Date | C21: 46573
A22: Forecast Completion | C22: 46573
A23: Variance | C23: =C22-C15 -> 0
A25: Key Project Submittals | C25: Submission Date | D25: Days taken to approve orginal plan from site handover date
A26: Quality Plan submission | C26: 46057 | D26: =C26-C14 -> 29
A27: Quality Plan approval | C27: 46112
A28: Quality Plan Last Update | C28: 46112
A30: Safety Plan submission | C30: 46044 | D30: =C30-C14 -> 16
A31: Safety Plan approval | C31: 46049
A32: Safety Plan Last Update | C32: 46049
A34: Risk Management Plan submission | C34: 46050 | D34: =C34-C14 -> 22
A35: Risk Management Plan approval | C35: 46056
A36: Risk Management Plan Last Update | C36: 46056
A38: Baseline Schedule submission | C38: 46053 | D38: =C38-C14 -> 25
A39: Baseline Schedule approval | C39: 46120
A40: No of Schedule Versions | C40: 1
A41: Last Revised Schedule Approval Date | C41: -
A43: BOQ submission | C43: - | D43: -
A44: BOQ approval | C44: -
A45: No of Approved Version of BOQ | C45: -
A47: Execution Plan submission | C47: 46060 | D47: =C47-C14 -> 32
A48: Execution Plan Approval | C48: 46063

Sheet Progress
A1: Project Scope Statement | B1: The scope of work of the project includes the implementation of the entire works subject to the contract, including the following: Road and paving works, Potable Water Network Works, Treatment Water Network Works, Sewer network works, Rainwater drainage network works, Irrigation and landscaping network works, Electrical network works including (medium voltage, communications, road lighting), Camera surveillance work
A4: Earned Value Progress (SAR) | K4: Physical Progress (Effort)
A5: WBS | C5: BOQ Value (SAR) | D5: % Wt. | E5: Weekly (SAR) | H5: To Date (SAR) | K5: Budgeted | L5: % Wt. | M5: Weekly Physical Progress | O5: To Date Physical Progress
E6: Planned | F6: Earned | G6: Original Plan | H6: Planned | I6: Earned | K6: (Manhours) | M6: Planned | N6: Earned | O6: Planned | P6: Earned
A7: Milestones | C7: 0 | H7: 0 | I7: 0 | K7: 0 | L7: =K7/$K$46 -> 0 | O7: 0 | P7: 0
A8: Mobilization | C8: 0 | H8: 0 | I8: 0 | K8: 34177 | L8: =K8/$K$46 -> 0.029999719 | M8: =O8-O51 -> 0 | N8: =P8-P51 -> 0 | O8: 34177 | P8: 34177
A9: Engineering | C9: 0 | D9: =C9/$C$46 -> 0 | E9: =H9-H52 -> 0 | F9: =I9-I52 -> 0 | G9: 0 | H9: 0 | I9: 0 | K9: 56962 | L9: =K9/$K$46 -> 0.049999824 | M9: =O9-O52 -> 0 | N9: =P9-P52 -> 0 | O9: 56962 | P9: 53211
A10: Procurement | C10: 0 | D10: =C10/$C$46 -> 0 | E10: =H10-H53 -> 0 | F10: =I10-I53 -> 0 | G10: 0 | H10: 0 | I10: 0 | K10: 148102 | L10: =K10/$K$46 -> 0.13000025 | M10: =O10-O53 -> 1511 | N10: =P10-P53 -> 0 | O10: 143233 | P10: 48418
A11: Construction | C11: 1.6862952e+08 | D11: =C11/$C$46 -> 1 | E11: =H11-H54 -> 3995420.2 | F11: =I11-I54 -> 1709872.9 | G11: 0 | H11: 54083772 | I11: 73149321 | K11: 854433 | L11: =K11/$K$46 -> 0.75 | M11: =O11-O54 -> 13886 | N11: =P11-P54 -> 3659 | O11: 171875 | P11: 311153
A12: ROAD WORKS | C12: 87969997 | D12: =C12/$C$11 -> 0.52167614 | E12: =H12-H55 -> 3032198.6 | F12: =I12-I55 -> 1648128 | G12: 0 | H12: 45806827 | I12: 52657041 | K12: 186393 | L12: =K12/$K$46 -> 0.16361113 | M12: =O12-O55 -> 5506 | N12: =P12-P55 -> 1552 | O12: 115703 | P12: 139255
A13: ZONE A | C13: 54469013 | D13: =C13/$C$11 -> 0.32300995 | E13: =H13-H56 -> 2443662 | F13: =I13-I56 -> 421282.11 | G13: 0 | H13: 24340936 | I13: 28656488 | K13: 121795 | L13: =K13/$K$46 -> 0.10690862 | M13: =O13-O56 -> 3080 | N13: =P13-P56 -> 544 | O13: 74862 | P13: 90010
A14: ZONE G | C14: 33500984 | D14: =C14/$C$11 -> 0.19866619 | E14: =H14-H57 -> 588536.68 | F14: =I14-I57 -> 1226845.9 | G14: 0 | H14: 21465891 | I14: 24000552 | K14: 64598 | L14: =K14/$K$46 -> 0.056702515 | M14: =O14-O57 -> 2425 | N14: =P14-P57 -> 1009 | O14: 40841 | P14: 49245
A15: Storm Water Drainage Network | C15: 25407829 | D15: =C15/$C$11 -> 0.15067249 | E15: =H15-H58 -> 323770.63 | F15: =I15-I58 -> 0 | G15: 0 | H15: 5607920.6 | I15: 9325845.2 | K15: 187421 | L15: =K15/$K$46 -> 0.16451348 | M15: =O15-O58 -> 3091 | N15: =P15-P58 -> 0 | O15: 29500 | P15: 75282
A16: ZONE A | C16: 22856155 | D16: =C16/$C$11 -> 0.13554065 | E16: =H16-H59 -> 292630.25 | F16: =I16-I59 -> 0 | G16: 0 | H16: 5325093.1 | I16: 6792269.6 | K16: 131130 | L16: =K16/$K$46 -> 0.11510265 | M16: =O16-O59 -> 2166 | N16: =P16-P59 -> 0 | O16: 20841 | P16: 19664
A17: ZONE G | C17: 2551674.2 | D17: =C17/$C$11 -> 0.015131836 | F17: =I17-I60 -> 0 | G17: 0 | H17: 282827.44 | I17: 2533575.5 | K17: 56291 | L17: =K17/$K$46 -> 0.049410837 | N17: =P17-P60 -> 0 | O17: 8660 | P17: 55618
A18: Sewerage Network | C18: 7071026.8 | D18: =C18/$C$11 -> 0.041932319 | E18: =H18-H61 -> 16569.23 | F18: =I18-I61 -> 0 | G18: 0 | H18: 16569.23 | I18: 5356988.8 | K18: 62221 | L18: =K18/$K$46 -> 0.054616044 | M18: =O18-O61 -> 221 | N18: =P18-P61 -> 0 | O18: 221 | P18: 44444
A19: ZONE A | C19: 4499744.2 | D19: =C19/$C$11 -> 0.026684202 | E19: =H19-H62 -> 8297.86 | F19: =I19-I62 -> 0 | G19: 0 | H19: 8297.86 | I19: 2912490.8 | K19: 40161 | L19: =K19/$K$46 -> 0.035252325 | M19: =O19-O62 -> 85 | N19: =P19-P62 -> 0 | O19: 85 | P19: 23456
A20: ZONE G | C20: 2571282.6 | D20: =C20/$C$11 -> 0.015248117 | E20: =H20-H63 -> 8271.37 | F20: =I20-I63 -> 0 | G20: 0 | H20: 8271.37 | I20: 2444498.1 | K20: 22061 | L20: =K20/$K$46 -> 0.019364596 | N20: =P20-P63 -> 0 | O20: 136 | P20: 20987
A21: TSE Network | C21: 4147696.1 | D21: =C21/$C$11 -> 0.024596501 | E21: =H21-H64 -> 0 | F21: =I21-I64 -> 13961.66 | G21: 0 | H21: 0 | I21: 581492.39 | K21: 87808 | L21: =K21/$K$46 -> 0.077075675 | M21: =O21-O64 -> 0 | N21: =P21-P64 -> 455 | O21: 0 | P21: 3248
A22: ZONE A | C22: 3158469.4 | D22: =C22/$C$11 -> 0.018730228 | E22: =H22-H65 -> 0 | F22: =I22-I65 -> 13089.57 | G22: 0 | H22: 0 | I22: 518004.64 | K22: 64717 | L22: =K22/$K$46 -> 0.05680697 | M22: =O22-O65 -> 0 | N22: =P22-P65 -> 380 | O22: 0 | P22: 1995
A23: ZONE G | C23: 989226.71 | D23: =C23/$C$11 -> 0.0058662725 | E23: =H23-H66 -> 0 | F23: =I23-I66 -> 872.1 | G23: 0 | H23: 0 | I23: 63487.76 | K23: 23091 | L23: =K23/$K$46 -> 0.020268705 | M23: =O23-O66 -> 0 | N23: =P23-P66 -> 74 | O23: 0 | P23: 1252
A24: Portable Water | C24: 7780467.6 | D24: =C24/$C$11 -> 0.046139416 | E24: =H24-H67 -> 0 | F24: =I24-I67 -> 16207.71 | G24: 0 | H24: 0 | I24: 1517663.9 | K24: 139722 | L24: =K24/$K$46 -> 0.12264449 | M24: =O24-O67 -> 0 | N24: =P24-P67 -> 540 | O24: 0 | P24: 14747
A25: ZONE A | C25: 4936252.6 | D25: =C25/$C$11 -> 0.029272767 | E25: =H25-H68 -> 0 | F25: =I25-I68 -> 16207.71 | G25: 0 | H25: 0 | I25: 295925.92 | K25: 99650 | L25: =K25/$K$46 -> 0.087470287 | M25: =O25-O68 -> 0 | N25: =P25-P68 -> 540 | O25: 0 | P25: 4061
A26: ZONE G | C26: 2844215 | D26: =C26/$C$11 -> 0.016866649 | E26: =H26-H69 -> 0 | F26: =I26-I69 -> 0 | G26: 0 | H26: 0 | I26: 1221738 | K26: 40072 | L26: =K26/$K$46 -> 0.035174203 | M26: =O26-O69 -> 0 | N26: =P26-P69 -> 0 | O26: 0 | P26: 10686
A27: Electrical Works | C27: 20111193 | D27: =C27/$C$11 -> 0.11926259 | E27: =H27-H70 -> 587192 | F27: =I27-I70 -> 23290.44 | G27: 0 | H27: 2517547.2 | I27: 3252560.1 | K27: 99033 | L27: =K27/$K$46 -> 0.0869287 | M27: =O27-O70 -> 4096 | N27: =P27-P70 -> 756 | O27: 23528 | P27: 31405
A28: ZONE A | C28: 13562632 | D28: =C28/$C$11 -> 0.080428575 | E28: =H28-H71 -> 380968.12 | F28: =I28-I71 -> 19086.25 | G28: 0 | H28: 1907363.8 | I28: 1970463.2 | K28: 63660 | L28: =K28/$K$46 -> 0.055879162 | M28: =O28-O71 -> 2626 | N28: =P28-P71 -> 637 | O28: 19316 | P28: 17636
A29: ZONE G | C29: 6548561.2 | D29: =C29/$C$11 -> 0.038834014 | E29: =H29-H72 -> 206223.88 | F29: =I29-I72 -> 4204.19 | G29: 0 | H29: 610183.42 | I29: 1282096.9 | K29: 35373 | L29: =K29/$K$46 -> 0.031049538 | M29: =O29-O72 -> 1469 | N29: =P29-P72 -> 120 | O29: 4211 | P29: 13769
A30: Landscape & Irrigation Works | C30: 6835460.6 | D30: =C30/$C$11 -> 0.040535373 | E30: =H30-H73 -> 0 | F30: =I30-I73 -> 8285.05 | G30: 0 | H30: 0 | I30: 20712.61 | K30: 77656 | L30: =K30/$K$46 -> 0.068164502 | M30: =O30-O73 -> 0 | N30: =P30-P73 -> 354 | O30: 0 | P30: 1047
A31: ZONE A | C31: 3801841.7 | D31: =C31/$C$11 -> 0.022545529 | E31: =H31-H74 -> 0 | F31: =I31-I74 -> 8285.05 | G31: 0 | H31: 0 | I31: 20712.61 | K31: 65750 | L31: =K31/$K$46 -> 0.057713712 | M31: =O31-O74 -> 0 | N31: =P31-P74 -> 354 | O31: 0 | P31: 1047
A32: ZONE G | C32: 3033618.9 | D32: =C32/$C$11 -> 0.017989845 | E32: =H32-H75 -> 0 | F32: =I32-I75 -> 0 | G32: 0 | H32: 0 | I32: 0 | K32: 11907 | L32: =K32/$K$46 -> 0.010451668 | M32: =O32-O75 -> 0 | N32: =P32-P75 -> 0 | O32: 0 | P32: 0
... A35: ZONE G | C35: 2791854.1 | D35: =C35/$C$11 -> 0.016556141 | E35: =H35-H78 -> 10706.92 | F35: =I35-I78 -> 0 | G35: 0 | H35: 44969.06 | I35: 95874.69 | K35: 7116 | L35: =K35/$K$46 -> 0.0062462475 | M35: =O35-O78 -> 194 | N35: =P35-P78 -> 0 | O35: 1141 | P35: 730
A36: Testing and commissioning | C36: 0 | D36: =C36/$C$46 -> 0 | E36: =H36-H79 -> 0 | F36: =I36-I79 -> 0 | G36: 0 | H36: 0 | I36: 0 | K36: 22785 | L36: =K36/$K$46 -> 0.020000105 | M36: =O36-O79 -> 0 | N36: =P36-P79 -> 0 | O36: 0 | P36: 0
A37: Close out | C37: 0 | D37: =C37/$C$46 -> 0 | E37: =H37-H80 -> 0 | F37: =I37-I80 -> 0 | H37: 0 | I37: 0 | K37: 22785 | L37: =K37/$K$46 -> 0.020000105 | M37: =O37-O80 -> 0 | N37: =P37-P80 -> 0 | O37: 0 | P37: 0
P38: 0
P39: 0
P40: 0
P41: 0
B46: Total | C46: =SUM(C9+C10+C11+C36+C37) -> 1.6862952e+08 | D46: =D9+D10+D11+D36+D37 -> 1 | E46: =E9+E10+E11+E36 -> 3995420.2 | F46: =F9+F10+F11+F36 -> 1709872.9 | G46: =G9+G10+G11+G37+G38+G36 -> 0 | H46: =H9+H10+H11+H36+H37 -> 54083772 | I46: =+I37+I36+I11+I10+I9 -> 73149321 | K46: =K8+K9+K10+K11+K36+K37 -> 1139244 | L46: =L7+L8+L9+L10+L11+L36+L37 -> 1 | M46: =M8+M9+M10+M11+M36+M37 -> 15397 | N46: =N8+N9+N10+N11+N36+N37 -> 3659 | O46: =O8+O9+O10+O11+O36+O37 -> 406247 | P46: =P8+P9+P10+P11+P36+P37 -> 446959
G47: =G46/C46 -> 0 | H47: =H46/C46 -> 0.32072541 | I47: =I46/C46 -> 0.43378716 | O47: =O46/K46 -> 0.3565935 | P47: =P46/K46 -> 0.39232947
O49: PW Planned | P49: PW Actuals
H51: PW Planned | I51: PW Actuals | M51: Mobilization | O51: 34177 | P51: 34177
G52: Engineering | H52: 0 | I52: 0 | M52: Engineering | O52: 56962 | P52: 53211
G53: Procurement | H53: 0 | I53: 0 | M53: Procurement | O53: 141722 | P53: 48418
G54: Construction | H54: 50088351 | I54: 71439448 | M54: Construction | O54: 157989 | P54: 307494
G55: ROAD WORKS | H55: 42774629 | I55: 51008913 | M55: ROAD WORKS | O55: 110197 | P55: 137703
G56: ZONE A | H56: 21897274 | I56: 28235206 | M56: ZONE A | O56: 71782 | P56: 89466
G57: ZONE G | H57: 20877354 | I57: 22773707 | M57: ZONE G | O57: 38416 | P57: 48236
G58: Storm Water Drainage Network | H58: 5284149.9 | I58: 9325845.2 | M58: Storm Water Drainage Network | O58: 26409 | P58: 75282
G59: ZONE A | H59: 5032462.9 | I59: 6792269.6 | M59: ZONE A | O59: 18675 | P59: 19664
G60: ZONE G | H60: 251687.06 | I60: 2533575.5 | M60: ZONE G | O60: 7734 | P60: 55618
G61: Sewerage Network | H61: 0 | I61: 5356988.8 | M61: Sewerage Network | O61: 0 | P61: 44444
G62: ZONE A | H62: 0 | I62: 2912490.8 | M62: ZONE A | O62: 0 | P62: 23456
G63: ZONE G | H63: 0 | I63: 2444498.1 | M63: ZONE G | O63: 0 | P63: 20987
... G80: Close out | H80: 0 | I80: 0 | M80: Close out | O80: 0 | P80: 0

Sheet Weekly Photos
B1: WEEKLY PROGRESS PHOTOS | V1: ='[37]General Information'!K1 -> Data Date | W1: ='General Information'!L1 -> 46293
B21: Compaction for base course layer works at MC20 Zone A | L21: Grading for base course layer works at MC20 Zone A
B40: Zone G, Asphalt works at road MCE0. 1ST Layer | L40: Zone G, Compaction for asphalt works at road MCE0. 1ST Layer
B59: Fire hydrant 6" delivered to site store- 58 pcs | L59: Asphalt base course cutting core works at Road MCF0, ZONE G.

Sheet Quality.
B2: QC OBSERVATIONS CHECKLIST
BB4: 45377
B6: Project No. | E6: SUD1-02-011 | K6: OBS No. | U6: Inspection Day: | X6: ='General Information'!L1 -> 46293
B8: Project | E8: Infrastructure Networks Development Project in Sudir City for Industry and Business Phase II – Part II | O8: =O52 -> 0 | U8: Technical Development Company Egis Engineering cunsultancy
B10: 4 | D10: Excellent | G10: Quality Management System is being practiced and applies to MODON System | Z10: 90 - 100 | AB10: QC Overall Score | AC10: =Q49 -> 0.81344828 | AN10: =SUM(Z10:Z13) -> 0 | AO10: 100 | AP10: 0.22883295
B11: 3 | D11: Good | G11: Evidence of compliance with plans and procedures. | Z11: 80 - 89 | AN11: =SUM(Y10:Y14) -> 0 | AO11: 89 | AP11: 0.20366133
B12: 2 | D12: Average | G12: Indication level of compliance with standards but there is room for improvement | Z12: 70 - 79 | AO12: 79 | AP12: 0.18077803
B13: 1 | D13: Improve | G13: Quality and Control is NOT being managed effectively. Needs Improvement | Z13: ≤ 69 | AO13: 69 | AP13: 0.15789474
B14: 0 | D14: N/A | G14: Item was not applicable or this item was not reviewed during the inspection. | Z14: Zero | AO14: 100 | AP14: 0.22883295
B16: No. | C16: Topic | K16: E (4) | L16: G (3) | M16: A (2) | N16: I (1) | O16: N/A (0) | P16: =P61 -> 0 | Q16: No. | R16: Topic | Z16: E (4) | AA16: G (3) | AB16: A (2) | AC16: I (1) | AD16: N/A (0) | AO16: =SUM(AO10:AO15) -> 437
K17: 1 | L17: 0.89 | M17: 0.79 | N17: 0.69 | O17: =O62 -> 0 | Z17: 1 | AA17: 0.89 | AB17: 0.79 | AC17: 0.69 | AD17: 1 | AF17: =SUM(AF18:AG46)/COUNT(AF18:AG46) -> 0.81344828
B18: 1 | C18: Control of Access to Site/Office | L18: 1 | Q18: 30 | R18: QC of Excavation | Z18: 0 | AB18: 1 | AC18: 0 | AD18: 0 | AF18: =SUMPRODUCT($K$17:$O$17,K18:O18) -> 0.89 | AG18: =SUMPRODUCT($Z$17:$AD$17,Z18:AD18) -> 0.79 | AV18: Item Count | AW18: Score | AX18: Distributtion
B19: 2 | C19: Document Control Administration | K19: 1 | M19: 0 | Q19: 31 | R19: QC of Roads/Round about | AB19: 1 | AC19: 0 | AF19: =SUMPRODUCT($K$17:$O$17,K19:O19) -> 1 | AG19: =SUMPRODUCT($Z$17:$AD$17,Z19:AD19) -> 0.79 | AX19: Overall | AY19: Relevant
B20: 3 | C20: Project Documents and Progress | K20: 1 | Q20: 32 | R20: QC of Interlock & Curbstone | AB20: 0 | AC20: 0 | AD20: 1 | AF20: =SUMPRODUCT($K$17:$O$17,K20:O20) -> 1 | AG20: =SUMPRODUCT($Z$17:$AD$17,Z20:AD20) -> 1 | AM20: 4 | AN20: =58 -> 58 | AO20: counts | AQ20: 4 | AR20: Excellent | AV20: =SUM(Z18:Z46,K18:K46) -> 3 | AW20: =AQ20*AV20 -> 12 | AX20: =AV20/$AV$25 -> 0.052631579 | AY20: =AV20/SUM($AV$20:$AV$23) -> 0.085714286
B21: 4 | C21: Contractor's Quality Plan/CM (Updated and Reviewed) | K21: 0 | M21: 1 | Q21: 33 | R21: Layers/Backfilling Sampling | Z21: 0 | AA21: 1 | AB21: 0 | AC21: 0 | AD21: 0 | AF21: =SUMPRODUCT($K$17:$O$17,K21:O21) -> 0.79 | AG21: =SUMPRODUCT($Z$17:$AD$17,Z21:AD21) -> 0.89 | AM21: 3 | AN21: =58 -> 58 | AO21: counts | AQ21: 3 | AR21: Good | AV21: =SUM(L18:L46,AA18:AA46) -> 12 | AW21: =AQ21*AV21 -> 36 | AX21: =AV21/$AV$25 -> 0.21052632 | AY21: =AV21/SUM($AV$20:$AV$23) -> 0.34285714
B22: 5 | C22: MS Log and Paperwork | L22: 1 | Q22: 34 | R22: Pump Stations Units | AD22: 1 | AF22: =SUMPRODUCT($K$17:$O$17,K22:O22) -> 0.89 | AG22: =SUMPRODUCT($Z$17:$AD$17,Z22:AD22) -> 1 | AM22: 2 | AN22: =58 -> 58 | AO22: counts | AQ22: 2 | AR22: Average | AV22: =SUM(M18:M46,AB18:AB46) -> 17 | AW22: =AQ22*AV22 -> 34 | AX22: =AV22/$AV$25 -> 0.29824561 | AY22: =AV22/SUM($AV$20:$AV$23) -> 0.48571429
B23: 6 | C23: RFI, FIR, & MIR Procedure | M23: 1 | Q23: 35 | R23: Quality of Form Work | AA23: 0 | AB23: 1 | AC23: 0 | AD23: 0 | AF23: =SUMPRODUCT($K$17:$O$17,K23:O23) -> 0.79 | AG23: =SUMPRODUCT($Z$17:$AD$17,Z23:AD23) -> 0.79 | AM23: 1 | AN23: =58 -> 58 | AO23: counts | AQ23: 1 | AR23: Improve | AV23: =SUM(N18:N46,AC18:AC46) -> 3 | AW23: =AQ23*AV23 -> 3 | AX23: =AV23/$AV$25 -> 0.052631579 | AY23: =AV23/SUM($AV$20:$AV$23) -> 0.085714286
B24: 7 | C24: RFI, FIR, & MIR Inventory system | L24: 1 | Q24: 36 | R24: Design Change List | AD24: 1 | AF24: =SUMPRODUCT($K$17:$O$17,K24:O24) -> 0.89 | AG24: =SUMPRODUCT($Z$17:$AD$17,Z24:AD24) -> 1 | AM24: 0 | AN24: =58 -> 58 | AO24: counts | AQ24: 0 | AR24: N/A | AV24: =SUM(O18:O46,AD18:AD46) -> 22 | AW24: =AQ24*AV24 -> 0 | AX24: =AV24/$AV$25 -> 0.38596491 | AY24: -
B25: 8 | C25: NCRs Control & Procedure | L25: 1 | M25: 0 | N25: 0 | Q25: 37 | R25: Quality of Concrete Placing | AA25: 0 | AB25: 0 | AC25: 0 | AD25: 1 | AF25: =SUMPRODUCT($K$17:$O$17,K25:O25) -> 0.89 | AG25: =SUMPRODUCT($Z$17:$AD$17,Z25:AD25) -> 1 | AR25: Total | AV25: =SUM(AV20:AV24) -> 57 | AW25: =SUM(AW20:AW24) -> 85 | AX25: =SUM(AX20:AX24) -> 1 | AY25: =SUM(AY20:AY24) -> 1
B26: 9 | C26: NCR Log | M26: 1 | Q26: 38 | R26: Concrete Surface Finishing | AA26: 0 | AB26: 0 | AC26: 0 | AD26: 1 | AF26: =SUMPRODUCT($K$17:$O$17,K26:O26) -> 0.79 | AG26: =SUMPRODUCT($Z$17:$AD$17,Z26:AD26) -> 1
B27: 10 | C27: MODON Standard* | K27: 0 | L27: 1 | Q27: 39 | R27: Pedestals/Columns/Beams Alignment | AA27: 0 | AD27: 1 | AF27: =SUMPRODUCT($K$17:$O$17,K27:O27) -> 0.89 | AG27: =SUMPRODUCT($Z$17:$AD$17,Z27:AD27) -> 1 | AV27: Maz Score Available: | AW27: =SUM(AV20:AV23)*AQ20 -> 140 | AX27: <- Excludes N/A items
B28: 11 | C28: Project Risk Plan/Management* | M28: 1 | Q28: 40 | R28: Siporex Lifting & Unloading | AD28: 1 | AF28: =SUMPRODUCT($K$17:$O$17,K28:O28) -> 0.79 | AG28: =SUMPRODUCT($Z$17:$AD$17,Z28:AD28) -> 1
B29: 12 | C29: Monthly Quality Reports* | L29: 0 | M29: 1 | O29: 0 | Q29: 41 | R29: Siporex Quality Pre-installation | AD29: 1 | AF29: =SUMPRODUCT($K$17:$O$17,K29:O29) -> 0.79 | AG29: =SUMPRODUCT($Z$17:$AD$17,Z29:AD29) -> 1
B30: 13 | C30: ITP | L30: 1 | O30: 0 | Q30: 42 | R30: Siporex Finishing Quality | AD30: 1 | AF30: =SUMPRODUCT($K$17:$O$17,K30:O30) -> 0.89 | AG30: =SUMPRODUCT($Z$17:$AD$17,Z30:AD30) -> 1 | AR30: Total Score | AW30: Percentage (%)
B31: 14 | C31: MODON Weekly Report | M31: 1 | N31: 0 | Q31: 43 | R31: Roads / Parking Markings | AC31: 0 | AD31: 1 | AF31: =SUMPRODUCT($K$17:$O$17,K31:O31) -> 0.79 | AG31: =SUMPRODUCT($Z$17:$AD$17,Z31:AD31) -> 1 | AN31: =MAX(AN20:AN24) -> 58 | AR31: =AW25 -> 85 | AW31: =SUM(100/AR33*AR31) -> 60.714286 | AY31: %
B32: 15 | C32: Design Change Official Paperwork* | O32: 1 | Q32: 44 | R32: QC of Finishing Outdoors | AC32: 0 | AD32: 1 | AF32: =SUMPRODUCT($K$17:$O$17,K32:O32) -> 0 | AG32: =SUMPRODUCT($Z$17:$AD$17,Z32:AD32) -> 1 | AR32: Max Score Available | BP32: 31
B33: 16 | C33: Design Change was Applied* | O33: 1 | Q33: 45 | R33: Quality of Finishing Indoors | AD33: 1 | AF33: =SUMPRODUCT($K$17:$O$17,K33:O33) -> 0 | AG33: =SUMPRODUCT($Z$17:$AD$17,Z33:AD33) -> 1 | AR33: =AW27 -> 140 | BP33: 32
B34: 17 | C34: Material List | K34: 0 | L34: 1 | O34: 0 | Q34: 46 | R34: Stairs Quality | AD34: 1 | AF34: =SUMPRODUCT($K$17:$O$17,K34:O34) -> 0.89 | AG34: =SUMPRODUCT($Z$17:$AD$17,Z34:AD34) -> 1 | BP34: 33
B35: 18 | C35: Pending Material Status | L35: 0 | M35: 0 | N35: 1 | O35: 0 | Q35: 47 | R35: Tanks Method Statement Work | AB35: 0 | AC35: 0 | AD35: 1 | AF35: =SUMPRODUCT($K$17:$O$17,K35:O35) -> 0.69 | AG35: =SUMPRODUCT($Z$17:$AD$17,Z35:AD35) -> 1 | BP35: 34
B36: 19 | C36: Lifting Plan* | K36: 0 | L36: 0 | M36: 1 | O36: 0 | Q36: 48 | R36: Electric Rooms | AD36: 1 | AF36: =SUMPRODUCT($K$17:$O$17,K36:O36) -> 0.79 | AG36: =SUMPRODUCT($Z$17:$AD$17,Z36:AD36) -> 1 | BP36: 35
B37: 20 | C37: DWG Log | L37: 1 | Q37: 49 | R37: QC of MCC/ATS Plant Units | AD37: 1 | AF37: =SUMPRODUCT($K$17:$O$17,K37:O37) -> 0.89 | AG37: =SUMPRODUCT($Z$17:$AD$17,Z37:AD37) -> 1 | BP37: 36
B38: 21 | C38: Invoice Status | K38: 0 | L38: 0 | O38: 1 | Q38: 50 | R38: Qualified Subcontractor | AB38: 1 | AD38: 0 | AF38: =SUMPRODUCT($K$17:$O$17,K38:O38) -> 0 | AG38: =SUMPRODUCT($Z$17:$AD$17,Z38:AD38) -> 0.79 | BP38: 37
B39: 22 | C39: Site Handover Letter | K39: 1 | O39: 0 | Q39: 51 | R39: Scaffold/Ladders/Slope/Bridge Compliance | AD39: 1 | AF39: =SUMPRODUCT($K$17:$O$17,K39:O39) -> 1 | AG39: =SUMPRODUCT($Z$17:$AD$17,Z39:AD39) -> 1 | BP39: 38
B40: 23 | C40: Material Testing Results & Certification | L40: 1 | N40: 0 | Q40: 52 | R40: Protection Applied to Completed Work | AA40: 0 | AB40: 1 | AC40: 0 | AD40: 0 | AF40: =SUMPRODUCT($K$17:$O$17,K40:O40) -> 0.89 | AG40: =SUMPRODUCT($Z$17:$AD$17,Z40:AD40) -> 0.79
B41: 24 | C41: As Build Drawings Status* | N41: 0 | O41: 1 | Q41: 53 | R41: Storage Management in/out Control | AA41: 1 | AC41: 0 | AF41: =SUMPRODUCT($K$17:$O$17,K41:O41) -> 0 | AG41: =SUMPRODUCT($Z$17:$AD$17,Z41:AD41) -> 0.89
B42: 25 | C42: Calibrated Lab Tools & Equipment | L42: 1 | M42: 0 | N42: 0 | O42: 0 | Q42: 54 | R42: Material Control | AC42: 0 | AD42: 0 | AF42: =SUMPRODUCT($K$17:$O$17,K42:O42) -> 0.89 | AG42: =SUMPRODUCT($Z$17:$AD$17,Z42:AD42) -> 0
B43: 26 | C43: Storage Inventory System | L43: 0 | N43: 1 | O43: 0 | Q43: 55 | R43: Manholes Storing and Quality | AB43: 1 | AF43: =SUMPRODUCT($K$17:$O$17,K43:O43) -> 0.69 | AG43: =SUMPRODUCT($Z$17:$AD$17,Z43:AD43) -> 0.79
B44: 27 | C44: Logistics Plan | M44: 1 | O44: 0 | Q44: 56 | R44: Reinforced Steel Quality | AB44: 0 | AC44: 0 | AD44: 1 | AF44: =SUMPRODUCT($K$17:$O$17,K44:O44) -> 0.79 | AG44: =SUMPRODUCT($Z$17:$AD$17,Z44:AD44) -> 1
B45: 28 | C45: Project Progress Planview | M45: 1 | N45: 0 | O45: 0 | Q45: 57 | R45: Safety Overview | Z45: 0 | AA45: 0 | AB45: 1 | AC45: 0 | AF45: =SUMPRODUCT($K$17:$O$17,K45:O45) -> 0.79 | AG45: =SUMPRODUCT($Z$17:$AD$17,Z45:AD45) -> 0.79
B46: 29 | C46: Sufficient Number of QC Inspectors | L46: 0 | N46: 1 | O46: 0 | Q46: 58 | R46: Waste Management Control | Z46: 0 | AB46: 1 | AD46: 0 | AF46: =SUMPRODUCT($K$17:$O$17,K46:O46) -> 0.69 | AG46: =SUMPRODUCT($Z$17:$AD$17,Z46:AD46) -> 0.79
O47: 0
I48: Score
M49: *QC % | Q49: =AF17 -> 0.81344828
B51: Prepared by: | G51: Sarvar Ahmad | Q51: Issued to PM: | V51: Engr.Zyad Al Shabat
B53: *QC Observations refer only to the practices and documentation observed at time of inspection. The responsibility of the CM and Contractor is to ensure that aspects of Quality are suitably managed. *Scores are a reflection of the general site conditions based upon the findings at the time of the walk through *If Applicable

Sheet Quality-Stat
A1: Quality -Stat
A2: Quality Reports
A3: Item | C3: Issued | D3: Closed | E3: Pending | F3: Avg. Closing (Days) | G3: Pending
G4: 0-10 Days | H4: 11-20 Days | I4: 21-30 Days | J4: 31-60 Days | K4: > 60 Days
A6: Non Conforomance Report (NCR) | C6: 16 | D6: 13 | E6: 3 | G6: 3 | Q6: 34
A7: Site Instruction (SI) | C7: 5 | D7: 5 | E7: 0 | G7: 0 | H7: 0
A8: Material Inspection Report (MIR) | C8: 196 | D8: 190 | E8: 6 | G8: 6
A9: Field Inspection Request (FIR) | C9: 3182 | D9: 3080 | E9: 102 | G9: 102 | H9: 0 | I9: -
A11: Shop Drawings
A12: Item Per WBS | D12: Total Drawings | E12: Total Drawings Submitted | H12: =H55 -> 0 | I12: =I55 -> 0 | J12: Remaining Drawings | K12: Pending | L12: Total Submittals
E13: A | F13: B | G13: C | H13: D | I13: Processed | J13: with Designer | K13: Submittals With Consultant
A14: Road work/Structural | D14: 130 | E14: 28 | F14: 102 | G14: 0 | H14: 0 | I14: =E14+F14 -> 130 | J14: 0 | K14: 0 | L14: =SUM(E14:F14)+K14 -> 130
A15: wet network(sewer,storm,potable,irrigation) | D15: 140 | E15: 22 | F15: 118 | G15: 0 | H15: 0 | I15: =E15+F15 -> 140 | J15: 0 | K15: 4 | L15: =SUM(E15:F15)+K15 -> 144
A16: Telecom,Street light | D16: 107 | E16: 4 | F16: 103 | G16: 0 | H16: 0 | I16: =E16+F16 -> 107 | J16: =D16-L16 -> 0 | K16: 0 | L16: =SUM(E16:F16)+K16 -> 107
A17: Landscape | C17: Mechanical | D17: 22 | E17: 3 | F17: 4 | G17: 15 | H17: 0 | I17: =E17+F17 -> 7 | K17: 0 | L17: =SUM(E17:F17)+K17 -> 7
A18: CCTV | C18: Electrical | D18: 12 | E18: 0 | F18: 12 | G18: 0 | H18: 0 | I18: =E18+F18 -> 12 | J18: =D18-L18 -> 0 | K18: 0 | L18: =SUM(E18:F18)+K18 -> 12
A19: TOTAL | D19: =SUM(D14:D18) -> 411 | E19: =SUM(E14:E18) -> 57 | F19: =SUM(F14:F18) -> 339 | G19: =SUM(G14:G18) -> 15 | H19: =SUM(H14:H18) -> 0 | I19: =SUM(I14:I18) -> 396 | J19: =SUM(J14:J18) -> 0 | K19: =SUM(K14:K18) -> 4 | L19: =SUM(L14:L18) -> 400
A22: Material Approval
A23: Item Per WBS | D23: Total | E23: Total Materials Submitted | J23: Remaining to approve | K23: Pending | L23: Total Submittals
E24: A | F24: B | G24: C | H24: D | I24: Processed | J24: with Designer | K24: Submittals With Consultant
A25: Civil /Structural /Architectural | D25: 25 | E25: 0 | F25: 20 | G25: 0 | H25: 1 | I25: 20 | J25: 4 | K25: 0 | L25: =SUM(E25:H25)+K25 -> 21 | N25: 34162 | O25: =N25*0.95 -> 32453.9
A26: Mechanical | C26: Mechanical | D26: 14 | E26: 0 | F26: 14 | G26: 0 | H26: 0 | I26: =E26+F26+G26+H26 -> 14 | J26: 0 | K26: - | L26: =E26+F26+G26+J26 -> 14 | N26: 22140 | O26: =N26*0.95 -> 21033
A27: Electrical | C27: Electrical | D27: 21 | E27: 1 | F27: 17 | G27: 0 | H27: 3 | I27: =E27+F27+G27+H27 -> 21 | J27: 0 | K27: 0 | L27: {=E27+F27+G27:H27+J27} -> 18 | M27: 21 | N27: 4500 | O27: =N27*0.95 -> 4275
A28: TOTAL | D28: =SUM(D25:D27) -> 60 | E28: =SUM(E25:E27) -> 1 | F28: =SUM(F25:F27) -> 51 | G28: =SUM(G25:G27) -> 0 | H28: =SUM(H25:H27) -> 4 | I28: =SUM(I25:I27) -> 55 | J28: =SUM(J25:J27) -> 4 | K28: =SUM(K25:K27) -> 0 | L28: =SUM(L25:L27) -> 53 | N28: 51500 | O28: =N28*0.95 -> 48925
A30: Procurement Summary
A31: Item Per WBS | D31: Total Materials | E31: Total Number of P.O. | F31: Actual P.O. To Date | G31: Remaining P.O | H31: Actual Material on Site | I31: Remaining Materials | J31: Material Delivery Completion (Date)
E32: A | F32: B | G32: C | H32: D | I32: Processed
A33: Civil /Structural /Architectural | D33: 16 | E33: 16 | F33: 10 | G33: =E33-F33 -> 6 | H33: 7 | I33: =D33-H33 -> 9 | J33: -
A34: Mechanical | C34: Mechanical | D34: 75 | E34: 59 | F34: 59 | G34: 17 | H34: 23 | I34: =D34-H34 -> 52 | J34: -
A35: Electrical | C35: Electrical | D35: 20 | E35: 14 | F35: 14 | G35: 6 | H35: 4 | I35: 16 | J35: -
A36: TOTAL | D36: =SUM(D33:D35) -> 111 | E36: =SUM(E33:E35) -> 89 | F36: =SUM(F33:F35) -> 83 | G36: =SUM(G33:G35) -> 29 | H36: =SUM(H33:H35) -> 34 | I36: =SUM(I33:I35) -> 77
A38: Consultant Quality Inspections / Observations (Weekly Basis) | I38: Overall Average | J38: - | L38: Average Closing | M38: -
A39: Week Number | B39: Date of Audit | C39: 46056 | D39: Numbers Of Comments | E39: Quality Score | F39: Date Closed | G39: Closure Duration | I39: This Week Score | J39: - | L39: Average Number of Comments Per Audit | M39: -

Sheet HSE-Stat 
A1: Safety Statistics
A3: Category | B3: Item | D3: This Week | E3: This Month | F3: Year to Date | G3: Cumulative
A4: Category | B4: Total Hours Worked | D4: 36000 | E4: 122940 | F4: 790456 | G4: 490456
B5: Safe Hours Worked | D5: 36000 | E5: 122940 | F5: 790456 | G5: 490456
B6: No.of Internal Training | D6: 1 | E6: 4 | F6: 52 | G6: 52
B7: No.of Internal Audit
B8: No. of Toolbox Talks | D8: 1 | E8: 4 | F8: 38 | G8: 38
B9: Safety Awards/Incentives
I10: Category | J10: Item | L10: This Week | M10: This Month | N10: Year to Date | O10: Cumulative
A12: Consultant Safety Inspection (Weekly Basis) | I12: Overall Average | J12: =E24 -> 0.807
A13: Week Number | B13: Date of Audit | C13: Date Issued | D13: Numbers Of Comments | E13: Overall Score | F13: Date Closed | G13: Closure Duration | I13: This Week Score | J13: =E24 -> 0.807
A14: Week-1 | B14: 46084 | C14: 46084 | D14: 6 | E14: 0.78 | F14: 46088 | G14: 4
A15: Week-2 | B15: 46091 | C15: 46091 | D15: 5 | E15: 0.78 | F15: 46095 | G15: 4
A16: Week-3 | B16: 46098 | C16: 46098 | D16: 5 | E16: 0.8 | F16: 46101 | G16: 3
A17: Week-4 | B17: 46105 | C17: 46105 | D17: 7 | E17: 0.8 | F17: 46107 | G17: 2
A18: Week-5 | B18: 46112 | C18: 46112 | D18: 5 | E18: 0.8 | F18: 46114 | G18: 2
A19: Week-6 | B19: 46119 | C19: 46119 | D19: 5 | E19: 0.8 | F19: 46121 | G19: 2
A20: Week-7 | B20: 46126 | C20: 46126 | D20: 6 | E20: 0.8 | F20: 46128 | G20: 0
A21: Week-8 | B21: 46133 | C21: 46133 | D21: 6 | E21: 0.8 | F21: 46136 | G21: 0
A22: Week-9 | B22: 46133 | C22: 46140 | D22: 0 | E22: 0.807 | F22: 46144 | G22: 0
A23: Week-10 | B23: 46174 | C23: 46179 | D23: 0 | E23: 0.807 | F23: 46179 | G23: 0
A24: Week-11 | B24: 46182 | C24: 46182 | D24: 0 | E24: 0.807 | F24: 46182 | G24: 0
A25: Week-12 | B25: 46188 | C25: 46188 | D25: 0 | E25: 0.807 | F25: 46188 | G25: 0
... A40: Week-27 | B40: 46293 | C40: 46293 | D40: 0 | E40: 0.807 | F40: 46293 | G40: 0
A41: Week-28 | D41: 0 | E41: 0 | G41: 0
A42: Week-29 | D42: 0 | E42: 0 | G42: 0

Sheet HSE. 
B1: MODON HSE Site Inspection Report
B2: Date | E2: ='General Information'!L1 -> 46293 | L2: Inspected By: | T2: Engr Ayman Sabry
B4: Project ID. | E4: SUD1-02-011 | L4: Report No. | W4: MODON PM Name | Y4: Engr.Ziyad Al Shabbat
B6: Project Name: | E6: Infrastructure Network Development Project in Sudair City for Industry and Business - Phase Two - Part Two | L6: Contractor: | R6: TECHNICAL DEVELOPMENT CONTRACTING CO. | X6: Safety Performance | AA6: =IF(W29>0,3,IF(L29>6,2,IF(D29>0,2,1)*1)*1) -> 2 | AE6: =(((COUNTIF(L13:Q25,"1")+COUNTIF(AC13:AH25,"1"))*AR13)+(COUNTIF(L13:Q25,"2")+COUNTIF(AC13:AH25,"2"))*AR14+(COUNTIF(L13:Q25,"3")+COUNTIF(AC13:AH25,"3"))*AR15)/((COUNT(L13:Q25)+COUNT(AC13:AH25))*100) -> 0.81818182
B8: Inspections are a snapshot in time and refer only to the practices and documentation observed at the time of the Inspection. It remains the responsibility of the Consultant and Contractor to ensure that all aspects of Health & Safety are suitably managed.
B9: 1 | D9: Good Practice | H9: 2 | I9: Need Improvement | T9: 3 | U9: Fail (Life Threatening Activity) / Comliance with Plan & Procedures | X9: N/A | Y9: Atcitty Not Applicable for this Site Inspection Report
B11: No. | C11: Topic | K11: Wt. | L11: HSE Compliance | S11: No. | T11: Topic | AB11: Wt. | AC11: HSE Compliance
B13: 1 | C13: Access and Egress - (General access to site, segregated from vehicles, / Overhead protection, while entering into the building /Adequate lighting provided when dark or overnight work) | K13: 0.05 | L13: 2 | S13: 14 | T13: Work at Height - (PPE/Fall Protection(Same level, above and blow) / Training / Fall restraint / competency /Safe access & egress to and from work at height / Ladders / Openings (floor/shafts/Provision of emergency rescue) | AB13: 0.05 | AC13: N/A | AP13: 1 | AR13: 100 | AU13: 1
B14: 2 | C14: Traffic Management - (Loading/unloading/sheeting/temp. routes/speed/parking/competence) | K14: 0.03 | L14: 2 | S14: 15 | T14: Scaffolding - (Temp. Scaffolding Work-platform (All types) - qualified scaffolder / Inspection / Tagged / Safe Access/egress / PTW/Falsework & Formwork) | AB14: 0.04 | AC14: N/A | AP14: 2 | AR14: 75 | AU14: 2
B15: 3 | C15: Site Signage - (Project Notice Board & General Signage) | K15: 0.02 | L15: 2 | S15: 16 | T15: Mobile Elevated Work platform (MEWP) - (PTW/competence requirements/conditions/inspections/tagged/training/Full-body harness) | AB15: 0.04 | AC15: N/A | AP15: 3 | AR15: 0 | AU15: 3
B16: 4 | C16: PPE Compliance - (Use, storage, stock, handling & checks - Head, Foot, Eye, Hearing) | K16: 0.05 | L16: 2 | S16: 17 | T16: Excavation & Trenches - (PTW/Edge protection/buffer zone/Slope/Benching/Shoring/Geo-tech report/Atmospheric hazards/Acess&egress/Emergency management / MS&RA/H.E) | AB16: 0.03 | AC16: 2 | AU16: N/A
B17: 5 | C17: Housekeeping - (Material correctly stored/Rubbish cleaned & removed daily/slips & trips hazards) | K17: 0.03 | L17: 2 | S17: 18 | T17: Confined Space - (PTW/Training/competence/Emergency Management/MS & RA/Safe access/egress) | AB17: 0.05 | AC17: 2
B18: 6 | C18: Storage of Materials - (Transporting, storage, training and use - Combustible / Flammable / Hazardous substances (COSHH) | L18: 1 | S18: 19 | T18: Fire Protection - (Flammable/Oxy. LPG /Combustible separated/FE's/Flashback arrestor/Sparks & slags/Smoking area/PTW/Generators/MS & RA/Emergency Management) | AC18: 2 | AL18: Red | AM18: Serious injury or death (immediately)
B19: 7 | C19: Site Waste Management - (Hazardous waste /Combustible waste / Human waste / Construction waste - asphalt, cable, timber, paving roof sheeting tiles, plastic & bricks) | L19: 1 | S19: 20 | T19: Health & Welfare - (Adequate drinking water/shaded - eating & rest area/washing & sanitary facilities/Certified FA/FA Box & Stock/adequate toilets/Ambulance) | AC19: 2 | AL19: Yellow | AM19: Minor or near miss (3 days to comply)
B20: 8 | C20: Health Surveillance - (Expose to excessive noise/vibration/dust/silica/CO/cement/radiation/extreme weather condition) | K20: 0.03 | L20: 1 | S20: 21 | T20: Environmental Incident Measures - (Spill/ Leakage / Concrete wash / vehicle & eqpts. wash / waste disposal/Sewers and drains/emissions/Emergency Management/Training/site run-off water) | AB20: 0.05 | AC20: 2 | AL20: Green | AM20: No issues
B21: 9 | C21: Electrical Safety - (Electrical qualified /RCD/GFCI/Industrial Cocket/LOTO/Cable-overhung or buried/Cords in good condition/current inspection tag) | K21: 0.05 | L21: 1 | S21: 22 | T21: HSE Communications & Meetings - (Schedule HSE Meetings/Safety Committee meetings/Alerts / Lesson learned/Safety Bulletin contains latest HSE KPI) | AB21: 0.05 | AC21: 2
B22: 10 | C22: Tools & Equipment - (Includes, powered, hydraulic & pneumatic/Guards in place/Properly stored/RCD Protection/Earthed/Good condition & tagged) | K22: 0.03 | L22: 1 | S22: 23 | T22: HSE Plan & Associated Procedures - (Approved updated HSE Plan/ CEMP/HAZComm/Procedures/Standards/Project Safety Risk Register) | AB22: 0.03 | AC22: 2 | AL22: 26 points > 4 minors then is it’s a serious issue
B23: 11 | C23: Manual Handling - (Lifting/loading/pulling/pushing/twisting/awkward posture/repetitive task/frequent and prolong physical effort/Reasonable practicable use of mechanical aid) | K23: 0.03 | L23: 1 | S23: 24 | T23: Health, Safety & Environment Incident reporting - (Review of HSE Statistics, Reporting of Unsafe Act & Conditions/ Reporting of Near Miss incident/Reporting of FA cases/Record MT cases) | AB23: 0.03 | AC23: 2
B24: 12 | C24: Vehicle and mobile equipment / Plant - (dumpers; excavators, cranes, piling rigs, grader, roller, loaders/condition/KSA License/certification) | K24: 0.05 | L24: 2 | S24: 25 | T24: HSE Awareness, Training & Competence - (Policy /Objective & targets/Information, training/Climatic condition awareness/Reponses in emergency situation/ Safety Behavior Observation) | AB24: 0.04 | AC24: 2
B25: 13 | C25: Lifting Operations & Rigging - (Lifting Plan/Lifting devices & gears/PTW/Condition/3rd party certification/bank-man/rigger/slingers/man-basket/inspection record/tagged) | L25: N/A | S25: 26 | T25: Project Leadership Site Tours - (Provide evidence of proactive safety performance/Deficient discovered discussed/Positive feedback/Workers resolving safety issues) | AC25: 2
B27: Prepared by: | G27: Abdul kalim | S27: Sent to MODON PM: | X27: Engr.Ziyad Al Shabbat
B28: Safety Results
B29: 1 | D29: =COUNTIF(L13:Q26,"1")+COUNTIF(AB13:AG26,"1") -> 6 | I29: 2 | L29: =COUNTIF(L13:Q26,"2")+COUNTIF(AB13:AG26,"2") -> 16 | U29: 3 | W29: =COUNTIF(L13:Q26,"3")+COUNTIF(AB13:AG26,"3") -> 0

Sheet Major Quantities
A1: MAJOR QUANTITIES Delivered
A2: BOQ Number | B2: Description of Item | C2: Total Quantity | D2: Unit of Measurement | E2: Plan To Date | F2: Actual To Date Delivered | G2: Excecuted on site | H2: Remaining Total Delivery | I2: Variance
A3: 33 31 00 | B3: GRP Pipes | C3: 18337 | D3: m | E3: 16000 | F3: 17162 | G3: 15000 | H3: =C3-F3 -> 1175 | I3: =F3-E3 -> 1162 | J3: =G3/C3 -> 0.81801821 | K3: =C3-G3 -> 3337
A4: 33 05 39 | B4: Manholes | C4: 251 | D4: m | E4: 150 | F4: 221 | G4: 175 | H4: =C4-F4 -> 30 | I4: =F4-E4 -> 71 | J4: =G4/C4 -> 0.69721116 | K4: =C4-G4 -> 76
A5: 33 42.1 | B5: UPVC Pipes | C5: 4716 | D5: m | E5: 5500 | F5: 4716 | G5: 800 | H5: =C5-F5 -> 0 | I5: =F5-E5 -> -784 | J5: =G5/C5 -> 0.16963528
A6: 33 42.1 | B6: Fire Hydrants | C6: 90 | D6: Unit | E6: 20 | F6: 90 | G6: 0 | H6: =C6-F6 -> 0 | I6: =F6-E6 -> 70 | J6: =G6/C6 -> 0
A7: 33 05 39 | B7: Catch Basins | C7: 295 | D7: Unit | E7: 150 | F7: 293 | G7: 80 | H7: =C7-F7 -> 2 | I7: =F7-E7 -> 143 | J7: =G7/C7 -> 0.27118644
A8: 33 42.1 | B8: HDPE Pipes | C8: 28557 | D8: m | E8: 26000 | F8: 28557 | G8: 5000 | H8: =C8-F8 -> 0 | I8: =F8-E8 -> 2557 | J8: =G8/C8 -> 0.17508842
A9: 26 05 13.16 | B9: Medium Voltage Cables | C9: 51500 | D9: m | E9: 0 | F9: 0 | G9: 0 | H9: =C9-F9 -> 51500 | I9: =F9-E9 -> 0 | J9: =G9/C9 -> 0
A10: 26 56 19 | B10: Street Lighting Poles | C10: 592 | D10: Unit | E10: 0 | F10: 1 | G10: 0 | H10: =C10-F10 -> 591 | I10: =F10-E10 -> 1 | J10: =G10/C10 -> 0
A11: 26 05 19 | B11: Low Voltage Cables | C11: 68400 | D11: m | E11: 5000 | F11: 68400 | G11: 0 | H11: =C11-F11 -> 0 | I11: =F11-E11 -> 63400 | J11: =G11/C11 -> 0
A12: 26 11 16 | B12: Unit Substation | C12: 5 | D12: Unit | E12: 0 | F12: 0 | G12: 0 | H12: =C12-F12 -> 5 | I12: =F12-E12 -> 0 | J12: =G12/C12 -> 0
A13: 26 24 16 | B13: Street Lighting Panels | C13: 52 | D13: Unit | E13: 0 | F13: 0 | G13: 0 | H13: =C13-F13 -> 52 | I13: =F13-E13 -> 0 | J13: =G13/C13 -> 0
A14: 33 14 19 | B14: Valves | C14: 218 | D14: Unit | E14: 100 | F14: 198 | G14: 10 | H14: =C14-F14 -> 20 | I14: =F14-E14 -> 98 | J14: =G14/C14 -> 0.04587156
A15: 26 11 16.02 | B15: RMU ( Ring main unit ) | C15: 11 | D15: Unit | E15: 5 | F15: 6 | G15: 0 | H15: =C15-F15 -> 5 | I15: =F15-E15 -> 1 | J15: =G15/C15 -> 0
A16: 26 13 00.01 | B16: NOP | C16: 6 | D16: Unit | E16: 6 | F16: 6 | G16: 0 | H16: =C16-F16 -> 0 | I16: =F16-E16 -> 0 | J16: =G16/C16 -> 0
E21: =27771-4250 -> 23521

Sheet CCO
A1: CONTRACT CHANGE ORDER (CCO)
A2: CCO No. | B2: Date Added | C2: Description of Change | D2: Status | E2: SR | F2: Sch Impact (Months) | G2: Date Approved | H2: Duration (days)
A3: - | B3: - | C3: - | D3: - | E3: - | F3: - | G3: - | H3: -
W18: 0.08

Sheet Invoice Log
B1: Weekly Progress Report - Invoice Log | AK1: Y
B2: Project Value | L2: Payment Status | T2: Invoices Summary | AD2: Average Invoices durations | AK2: N
B3: Original Contract Value | F3: 168629520 | H3: O&M Value | J3: 0 | L3: Advance Payment % | N3: 0.1 | P3: Advance Payment (SAR) | R3: =F3*N3 -> 16862952 | T3: No of Submitted Invoices | V3: =MAX($C$9:$C$39) -> 3 | X3: Submitted Invoices (SAR) | Z3: =SUM(F9:F39) -> 16773813 | AB3: Submiited Invoice Peroid | AD3: CM / PgM Average Approval duration | AF3: 0 | AH3: Average Invoice Value | AI3: 0
B4: Revised Contract Value | F4: 0 | H4: Revised O&M Value | J4: 0 | L4: Retention % | N4: 0 | P4: Retention (SAR) | R4: =F3*N4 -> 0 | T4: No of Approved Invoices (CM) | V4: =COUNTIF($O$9:$O$52,"Y") -> 0 | X4: Approved Invoices (CM) (SAR) | Z4: =SUMIF($O$9:$O$39,"Y",$K$9:$K$39) -> 0 | AD4: MODON PM & Accounts Average Approval duration | AF4: 0
B5: Estimate At Completion Value | F5: 168629520 | H5: Submitted Invoices (Gross Value) | J5: =SUM(F9:F51) -> 16773813 | L5: Penalties and deduction % | N5: =J6/F3 -> -0.0042732501 | P5: AP Recovery (SAR) | R5: =SUM(G9:G51) -> -1677381.3 | T5: No of Approved Invoices (PM) | V5: =COUNTIF($S$9:$S$52,"Y") -> 0 | X5: Approved Invoices (PM) (SAR) | Z5: =SUMIF($S$9:$S$39,"Y",$K$9:$K$39) -> 0 | AB5: Invoice Submitted Compared to Contract Value | AC5: =Z3/F4 -> #DIV/0! | AD5: Payments Average Duration | AF5: 0
B6: Potential Changes | F6: 0 | H6: Total Deduction | J6: =J9+G9 -> -720596.12 | L6: Penalties and deduction (SAR) | N6: =SUM(J9:J51) -> -28000 | P6: Retention Cumulative (SAR) | R6: =SUM(H9:H51) -> 0 | T6: No of Paid Invoices | V6: =COUNTA(Y9:Y52) -> 0 | X6: Paid Invoices (SAR) | Z6: =SUM(Z9:Z39) -> 0 | AD6: Invoices Average total Duration | AF6: =IFERROR(AVERAGE(AD9:AD52),"")
B7: Invoice Reference | F7: Invoice Value | K7: Period Covered | N7: CM / PgM Approval Timeline | R7: Modon PM & Accounts Approval | Y7: Payment Status | AD7: Total Invoice Duration | AE7: Remarks
B8: # | C8: Invoice No. | D8: Doc Control reference | E8: Submittal Rev. # | F8: Gross Value | G8: AP Recovery | H8: Retention | I8: VAT 5%/15% | J8: Deduction / Penalties | K8: Amount (net) | L8: Start Date | M8: End Date | N8: Date to CM / PgM | O8: CM / PgM Approval (Yes/No) | P8: CM / PgM Reply Date | Q8: Days Elapsed | R8: Date to PM | S8: PM Approval (Yes/No) | T8: PM Reply Date | U8: Date to Accounts | V8: Accounts Approval (Yes/No) | W8: Accounts Approval Date | X8: Days Elapsed | Y8: Date Paid | Z8: Amount Paid | AA8: Paid % | AB8: Payment Period (d) | AC8: Amount Pending
B9: 1 | C9: 1 | D9: SUD1-02-011-TDC-TS9-1-IPC-0001-00 | F9: 6935961.2 | G9: =IF(ISBLANK(F9),"",-F9*$N$3) -> -693596.12 | I9: 936354.76 | J9: -27000 | K9: =IF(ISBLANK(F9),"",SUM(F9:J9)) -> 7151719.8 | L9: 46028 | M9: 46201 | Z9: =IF(ISBLANK(Y9),"",K9) | AA9: =IF(ISBLANK(Y9),"",Z9/K9) | AB9: =IF(ISBLANK(W9),"",Y9-W9) | AC9: =IF(ISBLANK(Y9),"",(K9-Z9)) | AD9: =IF(ISBLANK(Y9),"",Y9-N9)
B10: 2 | C10: 2 | D10: SUD1-02-011-TDC-TS9-1-IPC-0002-00 | F10: 5943128.5 | G10: =IF(ISBLANK(F10),"",-F10*$N$3) -> -594312.85 | I10: 802322.34 | J10: 0 | K10: =IF(ISBLANK(F10),"",SUM(F10:J10)) -> 6151138 | L10: 46202 | M10: 46232 | Q10: =IF(ISBLANK(P10),"",P10-N10) | X10: =IF(ISBLANK(W10),"",W10-R10) | Z10: =IF(ISBLANK(Y10),"",K10) | AA10: =IF(ISBLANK(Y10),"",Z10/K10) | AB10: =IF(ISBLANK(W10),"",Y10-W10) | AC10: =IF(ISBLANK(Y10),"",(K10-Z10)) | AD10: =IF(ISBLANK(Y10),"",Y10-N10)
B11: 3 | C11: 3 | D11: SUD1-02-011-TDC-TS9-1-IPC-0003-00 | F11: 3894723.7 | G11: =IF(ISBLANK(F11),"",-F11*$N$3) -> -389472.37 | I11: 525787.71 | J11: -1000 | K11: =IF(ISBLANK(F11),"",SUM(F11:J11)) -> 4030039.1 | L11: 46203 | M11: 46265 | Q11: =IF(ISBLANK(P11),"",P11-N11) | X11: =IF(ISBLANK(W11),"",W11-R11) | Z11: =IF(ISBLANK(Y11),"",K11) | AA11: =IF(ISBLANK(Y11),"",Z11/K11) | AB11: =IF(ISBLANK(W11),"",Y11-W11) | AC11: =IF(ISBLANK(Y11),"",(K11-Z11)) | AD11: =IF(ISBLANK(Y11),"",Y11-N11)
B12: 4 | K12: =IF(ISBLANK(F12),"",SUM(F12:J12)) | Q12: =IF(ISBLANK(P12),"",P12-N12) | X12: =IF(ISBLANK(W12),"",W12-R12) | Z12: =IF(ISBLANK(Y12),"",K12) | AA12: =IF(ISBLANK(Y12),"",Z12/K12) | AB12: =IF(ISBLANK(W12),"",Y12-W12) | AC12: =IF(ISBLANK(Y12),"",(K12-Z12)) | AD12: =IF(ISBLANK(Y12),"",Y12-N12)
B13: 5 | K13: =IF(ISBLANK(F13),"",SUM(F13:J13)) | Q13: =IF(ISBLANK(P13),"",P13-N13) | X13: =IF(ISBLANK(W13),"",W13-R13) | Z13: =IF(ISBLANK(Y13),"",K13) | AA13: =IF(ISBLANK(Y13),"",Z13/K13) | AB13: =IF(ISBLANK(W13),"",Y13-W13) | AC13: =IF(ISBLANK(Y13),"",(K13-Z13)) | AD13: =IF(ISBLANK(Y13),"",Y13-N13)
B14: 6 | K14: =IF(ISBLANK(F14),"",SUM(F14:J14)) | Q14: =IF(ISBLANK(P14),"",P14-N14) | X14: =IF(ISBLANK(W14),"",W14-R14) | Z14: =IF(ISBLANK(Y14),"",K14) | AA14: =IF(ISBLANK(Y14),"",Z14/K14) | AB14: =IF(ISBLANK(W14),"",Y14-W14) | AC14: =IF(ISBLANK(Y14),"",(K14-Z14)) | AD14: =IF(ISBLANK(Y14),"",Y14-N14)
B15: 7 | K15: =IF(ISBLANK(F15),"",SUM(F15:J15)) | Q15: =IF(ISBLANK(P15),"",P15-N15) | X15: =IF(ISBLANK(W15),"",W15-R15) | Z15: =IF(ISBLANK(Y15),"",K15) | AA15: =IF(ISBLANK(Y15),"",Z15/K15) | AB15: =IF(ISBLANK(W15),"",Y15-W15) | AC15: =IF(ISBLANK(Y15),"",(K15-Z15)) | AD15: =IF(ISBLANK(Y15),"",Y15-N15)
B16: 8 | K16: =IF(ISBLANK(F16),"",SUM(F16:J16)) | Q16: =IF(ISBLANK(P16),"",P16-N16) | X16: =IF(ISBLANK(W16),"",W16-R16) | Z16: =IF(ISBLANK(Y16),"",K16) | AA16: =IF(ISBLANK(Y16),"",Z16/K16) | AB16: =IF(ISBLANK(W16),"",Y16-W16) | AC16: =IF(ISBLANK(Y16),"",(K16-Z16)) | AD16: =IF(ISBLANK(Y16),"",Y16-N16)
B17: 9 | K17: =IF(ISBLANK(F17),"",SUM(F17:J17)) | Q17: =IF(ISBLANK(P17),"",P17-N17) | X17: =IF(ISBLANK(W17),"",W17-R17) | Z17: =IF(ISBLANK(Y17),"",K17) | AA17: =IF(ISBLANK(Y17),"",Z17/K17) | AB17: =IF(ISBLANK(W17),"",Y17-W17) | AC17: =IF(ISBLANK(Y17),"",(K17-Z17)) | AD17: =IF(ISBLANK(Y17),"",Y17-N17)
B18: 10 | K18: =IF(ISBLANK(F18),"",SUM(F18:J18)) | Q18: =IF(ISBLANK(P18),"",P18-N18) | W18: 0.08 | X18: =IF(ISBLANK(W18),"",W18-R18) -> 0.08 | Z18: =IF(ISBLANK(Y18),"",K18) | AA18: =IF(ISBLANK(Y18),"",Z18/K18) | AB18: =IF(ISBLANK(W18),"",Y18-W18) -> -0.08 | AC18: =IF(ISBLANK(Y18),"",(K18-Z18)) | AD18: =IF(ISBLANK(Y18),"",Y18-N18)
B19: 11 | K19: =IF(ISBLANK(F19),"",SUM(F19:J19)) | Q19: =IF(ISBLANK(P19),"",P19-N19) | X19: =IF(ISBLANK(W19),"",W19-R19) | Z19: =IF(ISBLANK(Y19),"",K19) | AA19: =IF(ISBLANK(Y19),"",Z19/K19) | AB19: =IF(ISBLANK(W19),"",Y19-W19) | AC19: =IF(ISBLANK(Y19),"",(K19-Z19)) | AD19: =IF(ISBLANK(Y19),"",Y19-N19)
B20: 12 | K20: =IF(ISBLANK(F20),"",SUM(F20:J20)) | Q20: =IF(ISBLANK(P20),"",P20-N20) | X20: =IF(ISBLANK(W20),"",W20-R20) | Z20: =IF(ISBLANK(Y20),"",K20) | AA20: =IF(ISBLANK(Y20),"",Z20/K20) | AB20: =IF(ISBLANK(W20),"",Y20-W20) | AC20: =IF(ISBLANK(Y20),"",(K20-Z20))
B21: 13 | G21: =IF(ISBLANK(F21),"",-F21*$N$3) | H21: =IF(ISBLANK(F21),"",-F21*$N$4) | K21: =IF(ISBLANK(F21),"",SUM(F21:J21)) | Q21: =IF(ISBLANK(P21),"",P21-N21) | X21: =IF(ISBLANK(W21),"",W21-R21) | Z21: =IF(ISBLANK(Y21),"",K21) | AA21: =IF(ISBLANK(Y21),"",Z21/K21) | AB21: =IF(ISBLANK(W21),"",Y21-W21) | AC21: =IF(ISBLANK(Y21),"",(K21-Z21)) | AD21: =IF(ISBLANK(Y21),"",Y21-N21)
B22: 14 | G22: =IF(ISBLANK(F22),"",-F22*$N$3) | H22: =IF(ISBLANK(F22),"",-F22*$N$4) | K22: =IF(ISBLANK(F22),"",SUM(F22:J22)) | Q22: =IF(ISBLANK(P22),"",P22-N22) | X22: =IF(ISBLANK(W22),"",W22-R22) | Z22: =IF(ISBLANK(Y22),"",K22) | AA22: =IF(ISBLANK(Y22),"",Z22/K22) | AB22: =IF(ISBLANK(W22),"",Y22-W22) | AC22: =IF(ISBLANK(Y22),"",(K22-Z22)) | AD22: =IF(ISBLANK(Y22),"",Y22-N22)
B23: 15 | G23: =IF(ISBLANK(F23),"",-F23*$N$3) | H23: =IF(ISBLANK(F23),"",-F23*$N$4) | K23: =IF(ISBLANK(F23),"",SUM(F23:J23)) | Q23: =IF(ISBLANK(P23),"",P23-N23) | X23: =IF(ISBLANK(W23),"",W23-R23) | Z23: =IF(ISBLANK(Y23),"",K23) | AA23: =IF(ISBLANK(Y23),"",Z23/K23) | AB23: =IF(ISBLANK(W23),"",Y23-W23) | AC23: =IF(ISBLANK(Y23),"",(K23-Z23)) | AD23: =IF(ISBLANK(Y23),"",Y23-N23)
B24: 16 | G24: =IF(ISBLANK(F24),"",-F24*$N$3) | H24: =IF(ISBLANK(F24),"",-F24*$N$4) | K24: =IF(ISBLANK(F24),"",SUM(F24:J24)) | Q24: =IF(ISBLANK(P24),"",P24-N24) | X24: =IF(ISBLANK(W24),"",W24-R24) | Z24: =IF(ISBLANK(Y24),"",K24) | AA24: =IF(ISBLANK(Y24),"",Z24/K24) | AB24: =IF(ISBLANK(W24),"",Y24-W24) | AC24: =IF(ISBLANK(Y24),"",(K24-Z24)) | AD24: =IF(ISBLANK(Y24),"",Y24-N24)
B25: 17 | G25: =IF(ISBLANK(F25),"",-F25*$N$3) | H25: =IF(ISBLANK(F25),"",-F25*$N$4) | K25: =IF(ISBLANK(F25),"",SUM(F25:J25)) | Q25: =IF(ISBLANK(P25),"",P25-N25) | X25: =IF(ISBLANK(W25),"",W25-R25) | Z25: =IF(ISBLANK(Y25),"",K25) | AA25: =IF(ISBLANK(Y25),"",Z25/K25) | AB25: =IF(ISBLANK(W25),"",Y25-W25) | AC25: =IF(ISBLANK(Y25),"",(K25-Z25)) | AD25: =IF(ISBLANK(Y25),"",Y25-N25)
B26: 18 | G26: =IF(ISBLANK(F26),"",-F26*$N$3) | H26: =IF(ISBLANK(F26),"",-F26*$N$4) | K26: =IF(ISBLANK(F26),"",SUM(F26:J26)) | Q26: =IF(ISBLANK(P26),"",P26-N26) | X26: =IF(ISBLANK(W26),"",W26-R26) | Z26: =IF(ISBLANK(Y26),"",K26) | AA26: =IF(ISBLANK(Y26),"",Z26/K26) | AB26: =IF(ISBLANK(W26),"",Y26-W26) | AC26: =IF(ISBLANK(Y26),"",(K26-Z26)) | AD26: =IF(ISBLANK(Y26),"",Y26-N26)
B27: 19 | Q27: =IF(ISBLANK(P27),"",P27-N27) | X27: =IF(ISBLANK(W27),"",W27-R27) | Z27: =IF(ISBLANK(Y27),"",K27) | AA27: =IF(ISBLANK(Y27),"",Z27/K27) | AB27: =IF(ISBLANK(W27),"",Y27-W27) | AC27: =IF(ISBLANK(Y27),"",(K27-Z27)) | AD27: =IF(ISBLANK(Y27),"",Y27-N27)
B28: 20 | G28: =IF(ISBLANK(F28),"",-F28*$N$3) | H28: =IF(ISBLANK(F28),"",-F28*$N$4) | K28: =IF(ISBLANK(F28),"",SUM(F28:J28)) | Q28: =IF(ISBLANK(P28),"",P28-N28) | X28: =IF(ISBLANK(W28),"",W28-R28) | Z28: =IF(ISBLANK(Y28),"",K28) | AA28: =IF(ISBLANK(Y28),"",Z28/K28) | AB28: =IF(ISBLANK(W28),"",Y28-W28) | AC28: =IF(ISBLANK(Y28),"",(K28-Z28)) | AD28: =IF(ISBLANK(Y28),"",Y28-N28)
B29: 21 | G29: =IF(ISBLANK(F29),"",-F29*$N$3) | H29: =IF(ISBLANK(F29),"",-F29*$N$4) | K29: =IF(ISBLANK(F29),"",SUM(F29:J29)) | Q29: =IF(ISBLANK(P29),"",P29-N29) | X29: =IF(ISBLANK(W29),"",W29-R29) | Z29: =IF(ISBLANK(Y29),"",K29) | AA29: =IF(ISBLANK(Y29),"",Z29/K29) | AB29: =IF(ISBLANK(W29),"",Y29-W29) | AC29: =IF(ISBLANK(Y29),"",(K29-Z29)) | AD29: =IF(ISBLANK(Y29),"",Y29-N29)
B30: 22 | G30: =IF(ISBLANK(F30),"",-F30*$N$3) | H30: =IF(ISBLANK(F30),"",-F30*$N$4) | K30: =IF(ISBLANK(F30),"",SUM(F30:J30)) | Q30: =IF(ISBLANK(P30),"",P30-N30) | X30: =IF(ISBLANK(W30),"",W30-R30) | Z30: =IF(ISBLANK(Y30),"",K30) | AA30: =IF(ISBLANK(Y30),"",Z30/K30) | AB30: =IF(ISBLANK(W30),"",Y30-W30) | AC30: =IF(ISBLANK(Y30),"",(K30-Z30)) | AD30: =IF(ISBLANK(Y30),"",Y30-N30)
B31: 23 | G31: =IF(ISBLANK(F31),"",-F31*$N$3) | H31: =IF(ISBLANK(F31),"",-F31*$N$4) | K31: =IF(ISBLANK(F31),"",SUM(F31:J31)) | Q31: =IF(ISBLANK(P31),"",P31-N31) | X31: =IF(ISBLANK(W31),"",W31-R31) | Z31: =IF(ISBLANK(Y31),"",K31) | AA31: =IF(ISBLANK(Y31),"",Z31/K31) | AB31: =IF(ISBLANK(W31),"",Y31-W31) | AC31: =IF(ISBLANK(Y31),"",(K31-Z31)) | AD31: =IF(ISBLANK(Y31),"",Y31-N31)
B32: 24 | G32: =IF(ISBLANK(F32),"",-F32*$N$3) | H32: =IF(ISBLANK(F32),"",-F32*$N$4) | K32: =IF(ISBLANK(F32),"",SUM(F32:J32)) | Q32: =IF(ISBLANK(P32),"",P32-N32) | X32: =IF(ISBLANK(W32),"",W32-R32) | Z32: =IF(ISBLANK(Y32),"",K32) | AA32: =IF(ISBLANK(Y32),"",Z32/K32) | AB32: =IF(ISBLANK(W32),"",Y32-W32) | AC32: =IF(ISBLANK(Y32),"",(K32-Z32)) | AD32: =IF(ISBLANK(Y32),"",Y32-N32)
B33: 25 | G33: =IF(ISBLANK(F33),"",-F33*$N$3) | H33: =IF(ISBLANK(F33),"",-F33*$N$4) | K33: =IF(ISBLANK(F33),"",SUM(F33:J33)) | Q33: =IF(ISBLANK(P33),"",P33-N33) | X33: =IF(ISBLANK(W33),"",W33-R33) | Z33: =IF(ISBLANK(Y33),"",K33) | AA33: =IF(ISBLANK(Y33),"",Z33/K33) | AB33: =IF(ISBLANK(W33),"",Y33-W33) | AC33: =IF(ISBLANK(Y33),"",(K33-Z33)) | AD33: =IF(ISBLANK(Y33),"",Y33-N33)
B34: 26 | G34: =IF(ISBLANK(F34),"",-F34*$N$3) | H34: =IF(ISBLANK(F34),"",-F34*$N$4) | K34: =IF(ISBLANK(F34),"",SUM(F34:J34)) | Q34: =IF(ISBLANK(P34),"",P34-N34) | X34: =IF(ISBLANK(W34),"",W34-R34) | Z34: =IF(ISBLANK(Y34),"",K34) | AA34: =IF(ISBLANK(Y34),"",Z34/K34) | AB34: =IF(ISBLANK(W34),"",Y34-W34) | AC34: =IF(ISBLANK(Y34),"",(K34-Z34)) | AD34: =IF(ISBLANK(Y34),"",Y34-N34)
B35: 27 | G35: =IF(ISBLANK(F35),"",-F35*$N$3) | H35: =IF(ISBLANK(F35),"",-F35*$N$4) | K35: =IF(ISBLANK(F35),"",SUM(F35:J35)) | Q35: =IF(ISBLANK(P35),"",P35-N35) | X35: =IF(ISBLANK(W35),"",W35-R35) | Z35: =IF(ISBLANK(Y35),"",K35) | AA35: =IF(ISBLANK(Y35),"",Z35/K35) | AB35: =IF(ISBLANK(W35),"",Y35-W35) | AC35: =IF(ISBLANK(Y35),"",(K35-Z35)) | AD35: =IF(ISBLANK(Y35),"",Y35-N35)
B36: 28 | G36: =IF(ISBLANK(F36),"",-F36*$N$3) | H36: =IF(ISBLANK(F36),"",-F36*$N$4) | K36: =IF(ISBLANK(F36),"",SUM(F36:J36)) | Q36: =IF(ISBLANK(P36),"",P36-N36) | X36: =IF(ISBLANK(W36),"",W36-R36) | Z36: =IF(ISBLANK(Y36),"",K36) | AA36: =IF(ISBLANK(Y36),"",Z36/K36) | AB36: =IF(ISBLANK(W36),"",Y36-W36) | AC36: =IF(ISBLANK(Y36),"",(K36-Z36)) | AD36: =IF(ISBLANK(Y36),"",Y36-N36)
B37: 29 | G37: =IF(ISBLANK(F37),"",-F37*$N$3) | H37: =IF(ISBLANK(F37),"",-F37*$N$4) | K37: =IF(ISBLANK(F37),"",SUM(F37:J37)) | Q37: =IF(ISBLANK(P37),"",P37-N37) | X37: =IF(ISBLANK(W37),"",W37-R37) | Z37: =IF(ISBLANK(Y37),"",K37) | AA37: =IF(ISBLANK(Y37),"",Z37/K37) | AB37: =IF(ISBLANK(W37),"",Y37-W37) | AC37: =IF(ISBLANK(Y37),"",(K37-Z37)) | AD37: =IF(ISBLANK(Y37),"",Y37-N37)
B38: 30 | G38: =IF(ISBLANK(F38),"",-F38*$N$3) | H38: =IF(ISBLANK(F38),"",-F38*$N$4) | K38: =IF(ISBLANK(F38),"",SUM(F38:J38)) | Q38: =IF(ISBLANK(P38),"",P38-N38) | X38: =IF(ISBLANK(W38),"",W38-R38) | Z38: =IF(ISBLANK(Y38),"",K38) | AA38: =IF(ISBLANK(Y38),"",Z38/K38) | AB38: =IF(ISBLANK(W38),"",Y38-W38) | AC38: =IF(ISBLANK(Y38),"",(K38-Z38)) | AD38: =IF(ISBLANK(Y38),"",Y38-N38)
B39: 31 | G39: =IF(ISBLANK(F39),"",-F39*$N$3) | H39: =IF(ISBLANK(F39),"",-F39*$N$4) | K39: =IF(ISBLANK(F39),"",SUM(F39:J39)) | Q39: =IF(ISBLANK(P39),"",P39-N39) | X39: =IF(ISBLANK(W39),"",W39-R39) | Z39: =IF(ISBLANK(Y39),"",K39) | AA39: =IF(ISBLANK(Y39),"",Z39/K39) | AB39: =IF(ISBLANK(W39),"",Y39-W39) | AC39: =IF(ISBLANK(Y39),"",(K39-Z39)) | AD39: =IF(ISBLANK(Y39),"",Y39-N39)
B40: 32 | G40: =IF(ISBLANK(F40),"",-F40*$N$3) | H40: =IF(ISBLANK(F40),"",-F40*$N$4) | Z40: =IF(ISBLANK(Y40),"",K40) | AA40: =IF(ISBLANK(Y40),"",Z40/K40) | AB40: =IF(ISBLANK(W40),"",Y40-W40) | AC40: =IF(ISBLANK(Y40),"",(K40-Z40))
B41: 33 | G41: =IF(ISBLANK(F41),"",-F41*$N$3) | H41: =IF(ISBLANK(F41),"",-F41*$N$4) | Z41: =IF(ISBLANK(Y41),"",K41) | AA41: =IF(ISBLANK(Y41),"",Z41/K41) | AB41: =IF(ISBLANK(W41),"",Y41-W41) | AC41: =IF(ISBLANK(Y41),"",(K41-Z41))
B42: 34 | G42: =IF(ISBLANK(F42),"",-F42*$N$3) | H42: =IF(ISBLANK(F42),"",-F42*$N$4) | Z42: =IF(ISBLANK(Y42),"",K42) | AA42: =IF(ISBLANK(Y42),"",Z42/K42) | AB42: =IF(ISBLANK(W42),"",Y42-W42) | AC42: =IF(ISBLANK(Y42),"",(K42-Z42))
B43: 35 | G43: =IF(ISBLANK(F43),"",-F43*$N$3) | H43: =IF(ISBLANK(F43),"",-F43*$N$4) | Z43: =IF(ISBLANK(Y43),"",K43) | AA43: =IF(ISBLANK(Y43),"",Z43/K43) | AB43: =IF(ISBLANK(W43),"",Y43-W43) | AC43: =IF(ISBLANK(Y43),"",(K43-Z43))
B44: 36 | G44: =IF(ISBLANK(F44),"",-F44*$N$3) | H44: =IF(ISBLANK(F44),"",-F44*$N$4) | Z44: =IF(ISBLANK(Y44),"",K44) | AA44: =IF(ISBLANK(Y44),"",Z44/K44) | AB44: =IF(ISBLANK(W44),"",Y44-W44) | AC44: =IF(ISBLANK(Y44),"",(K44-Z44))
B45: 37 | G45: =IF(ISBLANK(F45),"",-F45*$N$3) | H45: =IF(ISBLANK(F45),"",-F45*$N$4) | Z45: =IF(ISBLANK(Y45),"",K45) | AA45: =IF(ISBLANK(Y45),"",Z45/K45) | AB45: =IF(ISBLANK(W45),"",Y45-W45) | AC45: =IF(ISBLANK(Y45),"",(K45-Z45))
B46: 38 | G46: =IF(ISBLANK(F46),"",-F46*$N$3) | H46: =IF(ISBLANK(F46),"",-F46*$N$4) | Z46: =IF(ISBLANK(Y46),"",K46) | AA46: =IF(ISBLANK(Y46),"",Z46/K46) | AB46: =IF(ISBLANK(W46),"",Y46-W46) | AC46: =IF(ISBLANK(Y46),"",(K46-Z46))
B47: 39 | G47: =IF(ISBLANK(F47),"",-F47*$N$3) | H47: =IF(ISBLANK(F47),"",-F47*$N$4) | Z47: =IF(ISBLANK(Y47),"",K47) | AA47: =IF(ISBLANK(Y47),"",Z47/K47) | AB47: =IF(ISBLANK(W47),"",Y47-W47) | AC47: =IF(ISBLANK(Y47),"",(K47-Z47))
B48: 40 | G48: =IF(ISBLANK(F48),"",-F48*$N$3) | H48: =IF(ISBLANK(F48),"",-F48*$N$4) | Z48: =IF(ISBLANK(Y48),"",K48) | AA48: =IF(ISBLANK(Y48),"",Z48/K48) | AB48: =IF(ISBLANK(W48),"",Y48-W48) | AC48: =IF(ISBLANK(Y48),"",(K48-Z48))
B49: 41 | G49: =IF(ISBLANK(F49),"",-F49*$N$3) | H49: =IF(ISBLANK(F49),"",-F49*$N$4) | Z49: =IF(ISBLANK(Y49),"",K49) | AA49: =IF(ISBLANK(Y49),"",Z49/K49) | AB49: =IF(ISBLANK(W49),"",Y49-W49) | AC49: =IF(ISBLANK(Y49),"",(K49-Z49))
B50: 42 | G50: =IF(ISBLANK(F50),"",-F50*$N$3) | H50: =IF(ISBLANK(F50),"",-F50*$N$4) | Z50: =IF(ISBLANK(Y50),"",K50) | AA50: =IF(ISBLANK(Y50),"",Z50/K50) | AB50: =IF(ISBLANK(W50),"",Y50-W50) | AC50: =IF(ISBLANK(Y50),"",(K50-Z50))
B51: 43 | G51: =IF(ISBLANK(F51),"",-F51*$N$3) | H51: =IF(ISBLANK(F51),"",-F51*$N$4) | Z51: =IF(ISBLANK(Y51),"",K51) | AA51: =IF(ISBLANK(Y51),"",Z51/K51) | AB51: =IF(ISBLANK(W51),"",Y51-W51) | AC51: =IF(ISBLANK(Y51),"",(K51-Z51))
E52: TOTAL | F52: =SUM(F9:F51) -> 16773813 | G52: =SUM(G9:G51) -> -1677381.3 | H52: =SUM(H9:H51) -> 0 | J52: =SUM(J9:J51) -> -28000 | K52: =SUM(K9:K51) -> 17332897 | Q52: =IF(ISBLANK(P52),"",P52-N52) | X52: =IF(ISBLANK(W52),"",W52-R52) | Z52: =SUM(Z9:Z51) -> 0 | AB52: =IF(ISBLANK(Y52),"",Y52-W52) | AC52: =SUM(AC9:AC51) -> 0 | AD52: =IF(ISBLANK(Y52),"",Y52-N52)

Sheet Issues
M3: ='General Information'!L1 -> 46293 | N3: Status | O3: Responsibility
N4: Open | O4: Contractor
N5: Closed | O5: Consultant
O6: Modon
O7: Third Party
O8: Other
A9: Issue Log
A12: Issue ID | B12: Parent Project ID | C12: Contract / Project ID | D12: Project Name | E12: City | F12: Region | G12: Fund Source | H12: Phase | I12: PM / Owner | J12: Contractor / Designer | K12: Current Status | L12: Value (SAR) | M12: Category | N12: Issue Title | O12: Description | P12: Evidence / Data | Q12: Severity (1-5) | R12: Urgency (1-5) | S12: Priority Score | T12: Priority | U12: Action Required | V12: Date Raised | W12: Status | X12: Target Date | Y12: Resolution / Updates | Z12: Source | AA12: Column1
A13: 3120 - 1 | B13: 3120 | C13: SUD1-02-011 | D13: Infrastructure Network Development Project in Sudair City for Industry and Business - Phase Two - Part Two | E13: Sudair | F13: Riyadh Region | G13: Government Funded | H13: Construction / Finishing | I13: Egis / MODON | J13: Technical Development Company for Contracting | K13: Closed | O13: Soil is presently scattered on the road surface. | U13: Install temporary physical hard barricades, warning tape, and clear hazard signage. | V13: 46273 | W13: Closed | X13: 46273
A14: 3120 - 2 | B14: 3120 | C14: SUD1-02-011 | D14: Infrastructure Network Development Project in Sudair City for Industry and Business - Phase Two - Part Two | E14: Sudair | F14: Riyadh Region | G14: Government Funded | H14: Construction / Finishing | I14: Egis / MODON | J14: Technical Development Company for Contracting | K14: Closed | O14: Collected unused barriers on-site and placed them around the existing excavation. | U14: Bobcat sweeper was deployed to remove fine soil from the road surface to eliminate dust and skid hazards. | V14: 46274 | W14: Closed | X14: 46274
A15: 3120 - 3 | B15: 3120 | C15: SUD1-02-011 | D15: Infrastructure Network Development Project in Sudair City for Industry and Business - Phase Two - Part Two | E15: Sudair | F15: Riyadh Region | G15: Government Funded | H15: Construction / Finishing | I15: Egis / MODON | J15: Technical Development Company for Contracting | K15: Closed | O15: Observed workers non complaince with site mandatory PPE | U15: GOOD PRACTICE | V15: 46274 | W15: Closed | X15: 46274
A16: 3120 - 4 | B16: 3120 | C16: SUD1-02-011 | D16: Infrastructure Network Development Project in Sudair City for Industry and Business - Phase Two - Part Two | E16: Sudair | F16: Riyadh Region | G16: Government Funded | H16: Construction / Finishing | I16: Egis / MODON | J16: Technical Development Company for Contracting | K16: Closed | O16: Found conrete pouring activities in night without sufficient lighting. | U16: PPE provided and conduct awareness session | V16: 46282 | W16: Closed | X16: 46282
A17: 3120 - 5 | B17: 3120 | C17: SUD1-02-011 | D17: Infrastructure Network Development Project in Sudair City for Industry and Business - Phase Two - Part Two | E17: Sudair | F17: Riyadh Region | G17: Government Funded | H17: Construction / Finishing | I17: Egis / MODON | J17: Technical Development Company for Contracting | K17: Closed | O17: Discovered an excavation without the required signage. | U17: Tower lights has been provided and engineer has been informed of the requirements | V17: 46283 | W17: Closed | X17: 46283
A18: 3120 - 6 | B18: 3120 | C18: SUD1-02-011 | D18: Infrastructure Network Development Project in Sudair City for Industry and Business - Phase Two - Part Two | E18: Sudair | F18: Riyadh Region | G18: Government Funded | H18: Construction / Finishing | I18: Egis / MODON | J18: Technical Development Company for Contracting | K18: Closed | O18: observe excavation existing utilities without proper supervision | U18: Provide supervison to the excavation team to continous evaluate the working conditions and guide the team of control measures | V18: 46292 | W18: Closed | X18: 46292
A19: 3120 - 7 | B19: 3120 | C19: SUD1-02-011 | D19: Infrastructure Network Development Project in Sudair City for Industry and Business - Phase Two - Part Two | E19: Sudair | F19: Riyadh Region | G19: Government Funded | H19: Construction / Finishing | I19: Egis / MODON | J19: Technical Development Company for Contracting | K19: Closed | O19: Found operators unaware of the risk of underground utilities | U19: An Awareness session was conducted with operators working in utilties contained areas | V19: 46293 | W19: Closed | X19: 46293

Sheet Risk Register
A1: Risk Log
A4: Risk ID | B4: Parent Project ID | C4: Contract / Project ID | D4: Project Name | E4: City | F4: Region | G4: Fund Source | H4: Phase | I4: PM / Owner | J4: Contractor / Designer | K4: Current Status | L4: Value (SAR) | M4: Category | N4: Risk Title | O4: Description | P4: Evidence / Data | Q4: Probability (1-5) | R4: Impact (1-5) | S4: Score | T4: Rating | U4: Response | V4: Mitigation Plan | W4: Date Identified | X4: Status | Y4: Target Date | Z4: Notes / Updates | AA4: Source
A5: 3120 - 1 | B5: 3120 | C5: SUD1-02-011 | D5: Infrastructure Network Development Project in Sudair City for Industry and Business - Phase Two - Part Two | E5: Sudair | F5: Riyadh Region | G5: Government Funded | H5: Construction / Testing & Commissioning | I5: Egis / MODON | J5: Technical Development Company for Contracting | K5: Close | M5: Authorities / Permits | N5: MV System | O5: There is no electricity service delivery agreement between the Modon and the electricity company | P5: TDC Wont be able to suubmit any sort of documents for material approval | T5: H16 | U5: Client/ Contractor | W5: 46111 | X5: Close | Y5: 46112 | Z5: Coordination between all stakholders (Client / Electricity Company and Contractor ) so we can execute our process
A6: 3120 - 2 | B6: 3120 | C6: SUD1-02-011 | D6: Infrastructure Network Development Project in Sudair City for Industry and Business - Phase Two - Part Two | E6: Sudair | F6: Riyadh Region | G6: Government Funded | H6: Construction / Finishing | I6: Egis / MODON | J6: Technical Development Company for Contracting | K6: Close | M6: Interface / Communication | N6: International Issue (War and Conflicts) | O6: Affecting time and cost | P6: The ongoing Conflict during this peiord is affecting the deilvery of the material like GRP which is risking time and cost | T6: M12 | U6: Contractor | W6: 46113 | X6: Close | Y6: 46114 | Z6: Should find alternative solution to this serious issue
A7: 3120 - 3 | B7: 3120 | C7: SUD1-02-011 | D7: Infrastructure Network Development Project in Sudair City for Industry and Business - Phase Two - Part Two | E7: Sudair | F7: Riyadh Region | G7: Government Funded | H7: Construction / Finishing | I7: Egis / MODON | J7: Technical Development Company for Contracting | K7: Close | M7: Safety / Quality | N7: Found an excavation area that requires immediate barricading. | O7: Accidental falls, unauthorized entry, and structural collapse. | P7: Serious injuries or death | T7: H16 | U7: Contractor | W7: 46235 | X7: Close | Y7: 46237 | Z7: Isolating the hazard zone, installing rigid physical barriers, and displaying clear warning signage
A8: 3120 - 4 | B8: 3120 | C8: SUD1-02-011 | D8: Infrastructure Network Development Project in Sudair City for Industry and Business - Phase Two - Part Two | E8: Sudair | F8: Riyadh Region | G8: Government Funded | H8: Construction / Finishing | I8: Egis / MODON | J8: Technical Development Company for Contracting | K8: Close | M8: Safety / Quality | N8: Found soil debris on the road from dump trucks. | O8: Soil and debris spilled from dump trucks onto public roads create severe driving hazards, including sudden loss of traction, cracked windshields from flying rocks, and dangerous swerving maneuvers. | P8: Vehicle damage, and environmental risks | T8: L4 | U8: Contractor | W8: 46235 | X8: Close | Y8: 46235 | Z8: When soil debris from construction dump trucks falls onto public roads, authorities Enforce immediate site cleanup, issue warning letter to drivers, and mandate preventive transport controls
A9: 3120 - 5 | B9: 3120 | C9: SUD1-02-011 | D9: Infrastructure Network Development Project in Sudair City for Industry and Business - Phase Two - Part Two | E9: Sudair | F9: Riyadh Region | G9: Government Funded | H9: Construction / Finishing | I9: Egis / MODON | J9: Technical Development Company for Contracting | K9: Close | M9: Safety / Quality | N9: Observed an excavation in the area without the required barricade. | O9: Accidental falls, equipment rollovers, and site fatalities. | P9: Fatal falls, structural collapses, and heavy legal penalties. | T9: H16 | U9: HSE team/Construction Team | W9: 46273 | X9: Close | Y9: 46273 | Z9: Stop any nearby hazardous work and immediately secure the area with hard barricades and warning signs to prevent falls and unauthorized entry.
A10: 3120 - 6 | B10: 3120 | C10: SUD1-02-011 | D10: Infrastructure Network Development Project in Sudair City for Industry and Business - Phase Two - Part Two | E10: Sudair | F10: Riyadh Region | G10: Government Funded | H10: Construction / Finishing | I10: Egis / MODON | J10: Technical Development Company for Contracting | K10: Close | M10: Safety / Quality | N10: An oil leak was observed from the equipment. | O10: Serious risks to worker safety, environmental health, and machine performance | P10: Severe safety hazards, environmental damage, equipment failure, and costly operational downtime. | T10: H16 | U10: Operator/Maintenance team/HSE team | W10: 46272 | X10: Close | Y10: 46272 | Z10: Initiate a swift and structured Spill Response and Corrective Maintenance Procedure.
A11: 3120 - 7 | B11: 3120 | C11: SUD1-02-011 | D11: Infrastructure Network Development Project in Sudair City for Industry and Business - Phase Two - Part Two | E11: Sudair | F11: Riyadh Region | G11: Government Funded | H11: Construction / Finishing | I11: Egis / MODON | J11: Technical Development Company for Contracting | K11: Close | M11: Safety / Quality | N11: Observed workers non complaince with site mandatory PPE | O11: Non complaince with site mandatory requirements and physical injuries to workers, low visibility and reputational damage | P11: Body injuries, penalties | T11: M12 | U11: HSE team | W11: 46282 | X11: Close | Y11: 46282 | Z11: Stop any workers with non complaince and provide PPE and replace the damage PPE.
A12: 3120 - 8 | B12: 3120 | C12: SUD1-02-011 | D12: Infrastructure Network Development Project in Sudair City for Industry and Business - Phase Two - Part Two | E12: Sudair | F12: Riyadh Region | G12: Government Funded | H12: Construction / Finishing | I12: Egis / MODON | J12: Technical Development Company for Contracting | K12: Close | M12: Safety / Quality | N12: Found conrete pouring activities in night without sufficient lighting. | O12: Serious risks to worker safety and quality of work | P12: Risk to get personal injuries of workers due low visibility and low quality of work due poor illumination. | T12: H16 | U12: Construction team/HSE team | W12: 46283 | X12: Close | Y12: 46272 | Z12: Provide sufficient lighting inform lighting tower during night shift activities.
A13: 3120 - 9 | B13: 3120 | C13: SUD1-02-011 | D13: Infrastructure Network Development Project in Sudair City for Industry and Business - Phase Two - Part Two | E13: Sudair | F13: Riyadh Region | G13: Government Funded | H13: Construction / Testing & Commissioning | I13: Egis / MODON | J13: Technical Development Company for Contracting | K13: Open – Confirmation Pending | L13: 6835460.6 | M13: Interface/Utilities | N13: Pending Substation Location Confirmation Affecting MV Cable Design and Energization | O13: The final substation location is currently pending confirmation between the Client and SEC. The Contractor has already raised an RFI regarding the MV cable size, and the response was received following SEC approval of the MV drawing. Although the cable-size issue has been addressed and the MV cables have been procured, final confirmation of the substation location and associated power-generation interface is still required to complete the MV system coordination and enable energization. Any continued delay may affect testing, energization and ultimately the planned handover milestone. | P13: RFI Ref. SUD1-02-011-TDC-TS9-1-ELE-RFI-0004-00, submitted 04-Feb-2026 and approval/response received 09-Feb-2026 following SEC approval of the MV Drawing. MV cables have been procured. Contractor is proactively progressing road-crossing ducts for MV cables at its own risk. Final substation location and power-generation interface remain pending. | Q13: 5 | R13: 5 | S13: =[38]!Risklog[[#This Row],[Probability (1-5)]]*[38]!Risklog[[#This Row],[Impact (1-5)]] -> 0 | T13: H16 | U13: Mitigate | V13: Expedite formal confirmation of the final substation location between Client and SEC. Continue close interface coordination with Client/SEC and obtain formal confirmation to avoid further design changes. Proceed with preparatory works such as MV cable road-crossing ducts where technically feasible and authorized. Maintain readiness for immediate submission of any revised/final MV cable drawings following location confirmation. Coordinate testing, power-generation interface and energization requirements in advance to minimize downstream impact. Closely monitor the remaining activities against the handover milestone and develop a recovery/acceleration plan if required. | X13: Monitoring | Y13: Required date for substation location confirmation | Z13: Project is currently ahead of schedule. Contractor has already addressed the MV cable-size clarification through RFI Ref. SUD1-02-011-TDC-TS9-1-ELE-RFI-0004-00, submitted on 04-Feb-2026 and responded/approved on 09-Feb-2026 following SEC approval. MV cables have been procured and road-crossing duct works are being progressed at Contractor's own risk. However, final substation location and power-generation/energization requirements remain subject to confirmation between Client and SEC. Continued delay may consume available float and potentially impact energization and handover. | AA13: RFI Ref. SUD1-02-011-TDC-TS9-1-ELE-RFI-0004-00; SEC-approved MV Drawing; Client/SEC correspondence; MV Cable Procurement Records; Site Progress Records; Interface Meeting Minutes; Project Schedule
A14: 3120 - 10 | B14: 3120 | C14: SUD1-02-011 | D14: Infrastructure Network Development Project in Sudair City for Industry and Business - Phase Two - Part Two | E14: Sudair | F14: Riyadh Region | G14: Government Funded | H14: Construction / Finishing | I14: Egis / MODON | J14: Technical Development Company for Contracting | K14: Open – Approval Pending | L14: 10128940 | M14: Design/Technical | N14: Delay in Landscape Proposal / Shop Drawing Approval Affecting Procurement and Installation | O14: The landscape proposal has been submitted by the Contractor and is currently awaiting Client approval. The approval is required to proceed with finalization of the landscape shop drawings and related material procurement. Any delay in approval may affect subsequent procurement, installation and finishing activities and could consume the available schedule float | P14: SUD1-02-011-TDC-TS9-1-ROD-RFI-0036-00 / 23-Aug-2026 | Q14: 3 | R14: 4 | S14: =[38]!Risklog[[#This Row],[Probability (1-5)]]*[38]!Risklog[[#This Row],[Impact (1-5)]] -> 0 | T14: M12 | U14: Mitigate | V14: Expedite Client/Consultant review and approval of the landscape proposal. Maintain regular follow-up until approval is obtained. Prepare shop drawing details in parallel where possible to minimize turnaround time. Identify long-lead materials and prepare procurement actions in advance. Upon approval, prioritize shop drawing submission, material procurement and installation to avoid consuming available float. | X14: Monitoring | Y14: Required approval date | Z14: Project is currently ahead of schedule. However, prolonged approval of the landscape proposal may affect shop drawing finalization, material procurement and installation activities and may consume available float. | AA14: Landscape Proposal Submission / Shop Drawing Register / Procurement Log / Project Schedule
A15: 3120 - 11 | B15: 3120 | C15: SUD1-02-011 | D15: Infrastructure Network Development Project in Sudair City for Industry and Business - Phase Two - Part Two | E15: Sudair | F15: Riyadh Region | G15: Government Funded | H15: Construction / Finishing | I15: Egis / MODON | J15: Technical Development Company for Contracting | K15: Close | M15: Safety / Quality | N15: observe excavation existing utilities without proper supervision | O15: Non complaince with continous supervision by working near utilities could expose the utilities struck by the equipement and utilities could be damage and services could be interupted. | P15: property damages, services interuption and penalties | T15: H16 | U15: Site Team/HSE Team | V15: Provide supervison to the excavation team to continous evaluate the working conditions and guide the team of control measures | W15: 46292 | X15: Close | Y15: 46292 | Z15: Provide supervison to the excavation team to continous evaluate the working conditions and guide the team of control measures
A16: 3120 - 12 | B16: 3120 | C16: SUD1-02-011 | D16: Infrastructure Network Development Project in Sudair City for Industry and Business - Phase Two - Part Two | E16: Sudair | F16: Riyadh Region | G16: Government Funded | H16: Construction / Finishing | I16: Egis / MODON | J16: Technical Development Company for Contracting | K16: Close | M16: Safety / Quality | N16: Found operators unaware of the risk of underground utilities | O16: Serious risks to worker of being electrocuted and could damage the utilities | P16: Risk to get personal injuries of workers due low visibility and low quality of work due poor illumination. | T16: H16 | U16: Site Team/HSE Team | V16: An Awareness session was conducted with operators working in utilties contained areas | W16: 46292 | X16: Close | Y16: 46292 | Z16: An Awareness session was conducted with operators working in utilties contained areas

Sheet Invoice Amount FIR
A1: INVOICE AMOUNT FIR | E1: 168629520
A2: SL. | B2: date of FIR | C2: TOTAL AMOUNT | D2: Total Amount % (as per FIR)
A3: 1 | B3: 46201 | C3: 6935961.2 | D3: =C3/E1 -> 0.041131358
A4: 2 | B4: 46232 | C4: 5943128.5 | D4: =C4/E1 -> 0.035243701
A5: 3 | B5: 46265 | C5: 3894723.7 | D5: =C5/E1 -> 0.023096334
A6: 4
A7: 5
A8: 6
A9: 7
A10: 8
A11: 9
A12: 10
A13: 11
A14: 12
A15: 13
A16: 14
A17: 15
... A21: 19

Sheet Manpower
A1: Head-Count ( Non Manual)
A2: MONTHS | B2: 46028 | C2: =EOMONTH(B2,1) -> 46081 | D2: =EOMONTH(C2,1) -> 46112 | E2: =EOMONTH(D2,1) -> 46142 | F2: =EOMONTH(E2,1) -> 46173 | G2: =EOMONTH(F2,1) -> 46203 | H2: =EOMONTH(G2,1) -> 46234 | I2: =EOMONTH(H2,1) -> 46265 | J2: =EOMONTH(I2,1) -> 46295 | ... T2: =EOMONTH(S2,1) -> 46599
A3: Plan - Monthly | B3: 0 | C3: 25 | D3: 24 | E3: 26 | F3: 29 | G3: 30 | H3: 28 | I3: 32 | J3: 24 | K3: 28 | L3: 26 | M3: 22 | N3: 18 | O3: 21 | P3: 20 | Q3: 19 | R3: 21 | S3: 18 | T3: 15
A4: Planned - Cumulative | B4: =B3 -> 0 | C4: =B4+C3 -> 25 | D4: =C4+D3 -> 49 | E4: =D4+E3 -> 75 | F4: =E4+F3 -> 104 | G4: =F4+G3 -> 134 | H4: =G4+H3 -> 162 | I4: =H4+I3 -> 194 | J4: =I4+J3 -> 218 | ... T4: =S4+T3 -> 426
A5: Actual - Monthly | B5: 11 | C5: 29 | D5: 28 | E5: 42 | F5: 53 | G5: 56 | H5: 57 | I5: 61 | J5: 53
A6: Actual Cumulative | B6: =B5 -> 11 | C6: =B6+C5 -> 40 | D6: =C6+D5 -> 68 | E6: =D6+E5 -> 110 | F6: =E6+F5 -> 163 | G6: =F6+G5 -> 219 | H6: =G6+H5 -> 276 | I6: =H6+I5 -> 337 | J6: =I6+J5 -> 390
A7: Forecast - Monthly
A8: Saudi Monthly - Actual
A9: Head-Count (Manual)
A10: MONTHS | B10: 46028 | C10: =EOMONTH(B10,1) -> 46081 | D10: =EOMONTH(C10,1) -> 46112 | E10: =EOMONTH(D10,1) -> 46142 | F10: =EOMONTH(E10,1) -> 46173 | G10: =EOMONTH(F10,1) -> 46203 | H10: =EOMONTH(G10,1) -> 46234 | I10: =EOMONTH(H10,1) -> 46265 | J10: =EOMONTH(I10,1) -> 46295 | ... T10: =EOMONTH(S10,1) -> 46599
A11: Plan - Monthly | B11: 99.303846 | C11: 169.35 | D11: 75.330769 | E11: 94.219231 | F11: 159.86538 | G11: 267 | H11: 261.63077 | I11: 286.78462 | J11: 340.74615 | K11: 326.71538 | L11: 365.49615 | M11: 279.19231 | N11: 241.23462 | O11: 214.71154 | P11: 216.36923 | Q11: 102.66923 | R11: 122.79615 | S11: 292.72692 | T11: 12.892308
A12: Planned - Cumulative | B12: =B11 -> 99.303846 | C12: =B12+C11 -> 268.65385 | D12: =C12+D11 -> 343.98462 | E12: =D12+E11 -> 438.20385 | F12: =E12+F11 -> 598.06923 | G12: =F12+G11 -> 865.06923 | H12: =G12+H11 -> 1126.7 | I12: =H12+I11 -> 1413.4846 | J12: =I12+J11 -> 1754.2308 | ... T12: =S12+T11 -> 3929.0346
A13: Actual - Monthly | B13: 32 | C13: 148 | D13: 199 | E13: 321 | F13: 405 | G13: 400 | H13: 395 | I13: 377 | J13: 547
A14: Actual Cumulative | B14: =B13 -> 32 | C14: =B14+C13 -> 180 | D14: =C14+D13 -> 379 | E14: =D14+E13 -> 700 | F14: =E14+F13 -> 1105 | G14: =F14+G13 -> 1505 | H14: =G14+H13 -> 1900 | I14: =H14+I13 -> 2277 | J14: =I14+J13 -> 2824
A15: Forecast - Monthly
A16: Saudi - Actual
A18: Head-Count (Non-Manual) | AG18: Month | AI18: =EOMONTH('General Information'!$L$1,0) -> 46295 | AM18: =EOMONTH(AI18,1) -> 46326
A19: Planned | B19: Actual | D19: Variance | F19: Forecast Next Month | H19: Saudi Staff
A20: 32 | B20: 53 | D20: =B20-A20 -> 21 | F20: =HLOOKUP($AM$18,$B$2:$T$8,6,FALSE) -> 0 | H20: 4
A22: Head-Count (Manual) | L22: Man Power by Trade
A23: Planned | B23: Actual | D23: Variance | F23: Forecast Next Month | H23: Saudi Staff | L23: Key Trade | N23: Engineer | P23: Doc. Controller | R23: Proc. Team | T23: Foreman | V23: Draftman | X23: Driver | Z23: UnSkilled Labor | AB23: Skiled labour | AD23: Others | AF23: Total
A24: 287 | B24: 547 | D24: =B24-A24 -> 260 | F24: =HLOOKUP($AM$18,$B$10:$AL$16,6,FALSE) -> 0 | H24: 2 | L24: Plan | N24: 15 | P24: 2 | R24: 3 | T24: 9 | V24: 2 | X24: 135 | Z24: 41 | AB24: 42 | AD24: 38 | AF24: =SUM(N24:AE24) -> 287
L25: Actual | N25: 16 | P25: 3 | R25: 3 | T25: 18 | V25: 2 | X25: 321 | Z25: 84 | AB25: 90 | AD25: 63 | AF25: =SUM(N25:AE25) -> 600
A32: Equipment
A33: MONTHS | B33: 46028 | C33: =EOMONTH(B33,1) -> 46081 | D33: =EOMONTH(C33,1) -> 46112 | E33: =EOMONTH(D33,1) -> 46142 | F33: =EOMONTH(E33,1) -> 46173 | G33: =EOMONTH(F33,1) -> 46203 | H33: =EOMONTH(G33,1) -> 46234 | I33: =EOMONTH(H33,1) -> 46265 | J33: =EOMONTH(I33,1) -> 46295 | ... T33: =EOMONTH(S33,1) -> 46599
A34: Plan - Monthly | B34: 0 | C34: 20 | D34: 44 | E34: 50 | F34: 65.085423 | G34: 228 | H34: 220 | I34: 205 | J34: 190 | K34: 150 | L34: 110 | M34: 80.446154 | N34: 57.873077 | O34: 18.957692 | P34: 10.496154 | Q34: 4.9230769 | R34: 11.123077 | S34: 27.272115 | T34: 0.59711538
A35: Planned - Cumulative | B35: =B34 -> 0 | C35: =B35+C34 -> 20 | D35: =C35+D34 -> 64 | E35: =D35+E34 -> 114 | F35: =E35+F34 -> 179.08542 | G35: =F35+G34 -> 407.08542 | H35: =G35+H34 -> 627.08542 | I35: =H35+I34 -> 832.08542 | J35: =I35+J34 -> 1022.0854 | ... T35: =S35+T34 -> 1493.7739
A36: Actual - Monthly | B36: 0 | C36: 35 | D36: 111 | E36: 241 | F36: 260 | G36: 320 | H36: =B43 -> 326 | I36: 225 | J36: 326
A37: Actual Cumulative | B37: 0 | C37: =B37+C36 -> 35 | D37: =C37+D36 -> 146 | E37: =D37+E36 -> 387 | F37: =E37+F36 -> 647 | G37: =F37+G36 -> 967 | H37: =G37+H36 -> 1293 | I37: =H37+I36 -> 1518 | J37: =I37+J36 -> 1844
A38: Forecast - Monthly
A41: Equipment Count
A42: Planned | B42: Actual | D42: Idle | F42: Variance | H42: Forecast Next Month
A43: 195 | B43: 326 | C43: =HLOOKUP($AI$18,$B$33:$AL$38,2,FALSE) -> 190 | D43: =AJ52 -> 0 | F43: =B43-A43 -> 131 | H43: =HLOOKUP($AM$18,$B$33:$AL$38,6,FALSE) -> 0
A49: Type | B49: PICK UP/Car | C49: Fork lift | D49: Bus | E49: Dumper | F49: Dump Truck | G49: Grader | H49: Boom Truck | J49: Generator + Tower Light | L49: JCB | N49: Water Tank | P49: CRANE | R49: Showel | T49: Tyre ROLLER | V49: Excavator/Poclain | X49: Lowbed Trailer | Z49: Forklift | AB49: BOBCAT | AD49: Bulldozer | AF49: Diesel Tank | AG49: Dyna | AH49: Grader | AI49: Total
A50: Plan | B50: 7 | D50: 4 | F50: 70 | H50: 2 | J50: 4 | L50: 3 | N50: 13 | P50: 2 | R50: 15 | T50: 15 | V50: 19 | X50: 1 | Z50: 1 | AB50: 2 | AD50: 15 | AF50: 4 | AG50: 1 | AH50: 17 | AI50: =SUM(B50:AH50) -> 195
A51: Actual | B51: 12 | D51: 6 | F51: 158 | H51: 5 | J51: 5 | L51: 9 | N51: 15 | P51: 1 | R51: 20 | T51: 20 | V51: 20 | X51: 1 | Z51: 3 | AB51: 6 | AD51: 20 | AF51: 3 | AG51: 2 | AH51: 20 | AI51: 326
A52: Idle

Sheet FIR Summary
A2: Project Name | C2: Infrastructure Network Development Project in Sudair City for Industry and Business - Phase Two - Part Two
A3: Project ID | C3: SUD1-02-011 | E3: Project Budget | F3: ='Invoice Log'!F3 -> 168629520
A4: Date Pariod | C4: Start Date | D4: 46028 | E4: To | F4: Data Date | G4: ='General Information'!L1 -> 46293
A6: BOQ Item # | B6: BOQ Description | C6: Date | D6: FIR # | E6: FIR Description | F6: Unit Rate as per BOQ | G6: Current Pariod Quantity | H6: % Claim | I6: Unit Rate as per claim | J6: Total (SR)
J7: =F7*G7 -> 0
J8: =F8*G8 -> 0
B9: Description | J9: =SUM(J10:J1974) -> 20832056
A10: B1.31 22 00.03 | B10: Embankments to the ROW | C10: 46113 | D10: SUD1-02-011-TDC-TS9-1-ROD-FIR-0008-00 | E10: Check Coordinates level and Compaction F.D.T for Embankment 1st layer at Road # MCE0, STA: 0+500 to STA: 0+610 | F10: 22.31 | G10: 721.03 | H10: 1 | I10: =H10*F10 -> 22.31 | J10: =I10*G10 -> 16086.179
A11: B1.31 22 00.03 | B11: Embankments to the ROW | C11: 46114 | D11: SUD1-02-011-TDC-TS9-1-ROD-FIR-0009-01 | E11: Check Coordinates level and Compaction F.D.T for Embankment 1st layer at Road # MCG0, STA: 0+580 to STA: 0+740 | F11: 22.31 | G11: 1448.15 | H11: 1 | I11: =H11*F11 -> 22.31 | J11: =I11*G11 -> 32308.227
A12: B1.31 22 00.03 | B12: Embankments to the ROW | C12: 46119 | D12: SUD1-02-011-TDC-TS9-1-ROD-FIR-0011-00 | E12: Check Coordinates level and Compaction F.D.T for Embankment 2nd layer at Road # MCE0, STA: 0+710 to STA: 0+860 | F12: 22.31 | G12: 1500.26 | H12: 1 | I12: =H12*F12 -> 22.31 | J12: =I12*G12 -> 33470.801
A13: B1.31 22 00.03 | B13: Embankments to the ROW | C13: 46121 | D13: SUD1-02-011-TDC-TS9-1-ROD-FIR-0013-00 | E13: Check Coordinates level and Compaction F.D.T for Embankment 2nd layer at Road # MCE0, STA: 0+500 to STA: 0+600 | F13: 22.31 | G13: 836.86 | H13: 1 | I13: =H13*F13 -> 22.31 | J13: =I13*G13 -> 18670.347
A14: B1.31 22 00.03 | B14: Embankments to the ROW | C14: 46121 | D14: SUD1-02-011-TDC-TS9-1-ROD-FIR-0014-00 | E14: Check Coordinates level and Compaction F.D.T for Embankment 1st layer at Road # MCG0, STA: 0+380 to STA: 0+480 | F14: 22.31 | G14: 2433.38 | H14: 1 | I14: =H14*F14 -> 22.31 | J14: =I14*G14 -> 54288.708
A15: B1.31 22 00.03 | B15: Embankments to the ROW | C15: 46123 | D15: SUD1-02-011-TDC-TS9-1-ROD-FIR-0015-00 | E15: Check Coordinates level and Compaction F.D.T for Embankment 2nd layer at Road # MCE0, STA: 0+600 to STA: 0+710 | F15: 22.31 | G15: 1362.19 | H15: 1 | I15: =H15*F15 -> 22.31 | J15: =I15*G15 -> 30390.459
A16: B1.31 22 00.03 | B16: Embankments to the ROW | C16: 46125 | D16: SUD1-02-011-TDC-TS9-1-ROD-FIR-0016-00 | E16: Check Coordinates level and Compaction F.D.T for Embankment 1st layer at Road # MCF0, STA: 0+230 to STA: 0+350 | F16: 22.31 | G16: 1995.27 | H16: 1 | I16: =H16*F16 -> 22.31 | J16: =I16*G16 -> 44514.474
A17: B1.31 22 00.03 | B17: Embankments to the ROW | C17: 46128 | D17: SUD1-02-011-TDC-TS9-1-ROD-FIR-0018-00 | E17: Check Coordinates level and Compaction F.D.T for Embankment 3rd layer at Road # MCE0, STA: 0+700 to STA: 0+860 | F17: 22.31 | G17: 1615.11 | H17: 1 | I17: =H17*F17 -> 22.31 | J17: =I17*G17 -> 36033.104
A18: B1.31 22 00.03 | B18: Embankments to the ROW | C18: 46128 | D18: SUD1-02-011-TDC-TS9-1-ROD-FIR-0019-00 | E18: Check Coordinates level and Compaction F.D.T for Embankment 3rd layer at Road # MCE0, STA: 0+620 to STA: 0+700 | F18: 22.31 | G18: 879.49 | H18: 1 | I18: =H18*F18 -> 22.31 | J18: =I18*G18 -> 19621.422
A19: B1.31 22 00.03 | B19: Embankments to the ROW | C19: 46130 | D19: SUD1-02-011-TDC-TS9-1-ROD-FIR-0023-00 | E19: Check Coordinates level and Compaction F.D.T for Embankment 1st layer at Road # MCD0, STA: 0+50 to STA: 0+180 | F19: 22.31 | G19: 932.1 | H19: 1 | I19: =H19*F19 -> 22.31 | J19: =I19*G19 -> 20795.151
A20: B1.31 22 00.03 | B20: Embankments to the ROW | C20: 46130 | D20: SUD1-02-011-TDC-TS9-1-ROD-FIR-0026-00 | E20: Check Coordinates level and Compaction F.D.T for Embankment 1st layer at Road # MCZ0, STA: 0+080.00 to STA: 0+310.00 | F20: 22.31 | G20: 1958.41 | H20: 1 | I20: =H20*F20 -> 22.31 | J20: =I20*G20 -> 43692.127
A21: B1.31 22 00.03 | B21: Embankments to the ROW | C21: 46130 | D21: SUD1-02-011-TDC-TS9-1-ROD-FIR-0027-00 | E21: Check Coordinates level and Compaction F.D.T for Embankment 3rd layer at Road # MCE0, STA: 0+500 to STA: 0+620 | F21: 22.31 | G21: 1257.28 | H21: 1 | I21: =H21*F21 -> 22.31 | J21: =I21*G21 -> 28049.917
... A104: B5 33.31.00.02 | B104: Sewerage Network:GRP Pipes 200 mm (Depth 1.51m to 2.5m) | C104: 46188 | D104: SUD1-02-011-TDC-TS9-1-SEW-FIR-0139-00 | E104: Check Coordinates level and Excavation width Bottom level and compaction for sewerage pipeline trench from existing manhole # MH-39-22 to MH-53-1 at Road MCF0 | F104: 221.14 | G104: 98.8 | H104: 0.05 | I104: =H104*F104 -> 11.057 | J104: =I104*G104 -> 1092.4316
A105: B5 33.05.13.05 | B105: Sewerage Network:GRP Pipes 200 mm (Depth 2.51m to 3.5m) int dia 1200 mm | C105: 46165 | D105: SUD1-02-011-TDC-TS9-1-SEW-FIR-0140-01 | E105: Check Coordinates level and Excavation width Bottom level and compaction for sewerage manhole pit MH- 53-1 at Road MCF0 | F105: 15848.43 | G105: 01 | H105: 0.05 | I105: =H105*F105 -> 792.4215 | J105: =I105*G105 -> 792.4215
A106: B5 33.31.00.02 | B106: Sewerage Network:GRP Pipes 200 mm (Depth 1.51m to 2.5m) | C106: 46188 | D106: SUD1-02-011-TDC-TS9-1-SEW-FIR-0141-00 | E106: Check Coordinates level and Excavation width Bottom level and compaction for sewerage pipeline trench from Existing Manhole # MH 39-23 to MH 52-1 at Road MCF0 | F106: 221.14 | G106: 98.8 | H106: 0.05 | I106: =H106*F106 -> 11.057 | J106: =I106*G106 -> 1092.4316
A107: B5 33.05.13.05 | B107: Sewerage Network:GRP Pipes 200 mm (Depth 2.51m to 3.5m) int dia 1200 mm | C107: 46165 | D107: SUD1-02-011-TDC-TS9-1-SEW-FIR-0142-01 | E107: Check Coordinates level, Excavation width Bottom level and compaction for Sewerage Manhole pit MH- 52-1 at Road MCF0 | F107: 15848.43 | G107: 01 | H107: 0.05 | I107: =H107*F107 -> 792.4215 | J107: =I107*G107 -> 792.4215
A108: B5 33.31.00.02 | B108: Sewerage Network:GRP Pipes 200 mm (Depth 1.51m to 2.5m) | C108: 46187 | D108: SUD1-02-011-TDC-TS9-1-SEW-FIR-0143-02 | E108: Check Sand bedding and GRP pipe installation for sewerage line from Existing Manholes # MH 39-26 to MH 51-1 at Road MCE0 | F108: 221.14 | G108: 98.8 | H108: 0.45 | I108: =H108*F108 -> 99.513 | J108: =I108*G108 -> 9831.8844
A109: B5 33.31.00.02 | B109: Sewerage Network:GRP Pipes 200 mm (Depth 1.51m to 2.5m) | C109: 46166 | D109: SUD1-02-011-TDC-TS9-1-SEW-FIR-0144-01 | E109: Check Sand Bedding and GRP Pipe Installation for Sewerage line from manhole # MH-51-1 to MH-51-2 at Road MCE0 | F109: 221.14 | G109: 98.8 | H109: 0.45 | I109: =H109*F109 -> 99.513 | J109: =I109*G109 -> 9831.8844
A110: B5 33.05.13.05 | B110: Sewerage Network:GRP Pipes 200 mm (Depth 2.51m to 3.5m) | C110: 46162 | D110: SUD1-02-011-TDC-TS9-1-SEW-FIR-0145-00 | E110: Check Formwork, Lean concrete pouring,concrete surface finishing and level at sewerage Manhole Pit No. 51-2 | F110: 15848.43 | G110: 1 | H110: 0.25 | I110: =H110*F110 -> 3962.1075 | J110: =I110*G110 -> 3962.1075
A111: B5 33.05.13.05 | B111: Sewerage Network:GRP Pipes 200 mm (Depth 2.51m to 3.5m) | C111: 46162 | D111: SUD1-02-011-TDC-TS9-1-SEW-FIR-0146-00 | E111: Check Formwork, Lean concrete pouring,concrete surface finishing and level at sewerage Manhole Pit No. 51-1 | F111: 15848.43 | G111: 1 | H111: 0.25 | I111: =H111*F111 -> 3962.1075 | J111: =I111*G111 -> 3962.1075
A112: B5 33.05.13.05 | B112: Sewerage Network:GRP Pipes 200 mm (Depth 2.51m to 3.5m) | C112: 46162 | D112: SUD1-02-011-TDC-TS9-1-SEW-FIR-0147-00 | E112: Check Formwork, Lean concrete pouring,concrete surface finishing and level at sewerage Manhole Pit No. 51-3 | F112: 15848.43 | G112: 1 | H112: 0.25 | I112: =H112*F112 -> 3962.1075 | J112: =I112*G112 -> 3962.1075
A113: B1.31 22 00.03 | B113: Embankments to the ROW | C113: 46162 | D113: SUD1-02-011-TDC-TS9-1-ROD-FIR-0148-00 | E113: Check Coordinates level and Compaction F.D.T for Embankment 6th layer at Road # MCZ0, STA: 0+310 to STA: 0+447.25 | F113: 22.31 | G113: 1824.42 | H113: 1 | I113: =H113*F113 -> 22.31 | J113: =I113*G113 -> 40702.81
A114: B1.31 22 00.03 | B114: Embankments to the ROW | C114: 46162 | D114: SUD1-02-011-TDC-TS9-1-ROD-FIR-0149-00 | E114: Check Coordinates level and Compaction F.D.T for Embankment 9th layer at Road # MCG0, STA: 0+380 to STA: 0+460 | F114: 22.31 | G114: 867.28 | H114: 1 | I114: =H114*F114 -> 22.31 | J114: =I114*G114 -> 19349.017
A115: B5 33.31.00.03 | B115: Sewerage Network:GRP Pipes 200 mm (Depth 2.51m to 3.5m) | C115: 46162 | D115: SUD1-02-011-TDC-TS9-1-SEW-FIR-0150-00 | E115: Check Coordinates level and Excavation width Bottom level and compaction for sewerage pipeline trench from Manhole # MH 49-3 TO MH – 49-2 at Road MCE0 | F115: 329.77 | G115: 98.8 | H115: 0.05 | I115: =H115*F115 -> 16.4885 | J115: =I115*G115 -> 1629.0638
A116: B1.31 22 00.03 | B116: Embankments to the ROW | C116: 46163 | D116: SUD1-02-011-TDC-TS9-1-ROD-FIR-0151-00 | E116: Check Coordinates level and Compaction F.D.T for Embankment 7th layer at Road # MCZ0, STA: 0+170 to STA: 0+310 | F116: 22.31 | G116: 1855.89 | H116: 1 | I116: =H116*F116 -> 22.31 | J116: =I116*G116 -> 41404.906
A117: B1.31 22 00.03 | B117: Embankments to the ROW | C117: 46165 | D117: SUD1-02-011-TDC-TS9-1-ROD-FIR-0152-01 | E117: Check Coordinates level and Compaction F.D.T for Embankment 8th layer at Road # MCG0, STA: 0+224 to STA: 0+380 | F117: 22.31 | G117: 2713.98 | H117: 1 | I117: =H117*F117 -> 22.31 | J117: =I117*G117 -> 60548.894
A118: B5 33.31.00.02 | B118: Sewerage Network:GRP Pipes 200 mm (Depth 1.51m to 2.5m) | C118: 46165 | D118: SUD1-02-011-TDC-TS9-1-SEW-FIR-0153-00 | E118: Check Coordinates level and Excavation width Bottom level and compaction for sewerage pipeline trench from Manhole # MH 51-4 TO MH – 51-5 at Road MCE0 | F118: 221.14 | G118: 58.8 | H118: 0.05 | I118: =H118*F118 -> 11.057 | J118: =I118*G118 -> 650.1516
A119: B5 33.05.13.03 | B119: Sewerage Network: Manhole (Depth 1.51m to 2.5m) Int dia 1200 mm | C119: 46165 | D119: SUD1-02-011-TDC-TS9-1-SEW-FIR-0154-00 | E119: Check Coordinates level, Excavation width Bottom level and compaction for Sewerage Manhole pit MH- 51-5 at Road MCE0 | F119: 12377.1 | G119: 1 | H119: 0.05 | I119: =H119*F119 -> 618.855 | J119: =I119*G119 -> 618.855
... A160: B5 33.31.00.03 | B160: Sewerage Network:GRP Pipes 200 mm (Depth 2.51 m to 3.5m) | C160: 46174 | D160: SUD1-02-011-TDC-TS9-1-SEW-FIR-0198-00 | E160: Check Coordinates level and Excavation width Bottom level and compaction for sewerage pipeline trench from Manhole # MH – 49-3 to MH – 49-4 at Road MCE0 | F160: 329.77 | G160: 101.33 | H160: 0.05 | I160: =H160*F160 -> 16.4885 | J160: =I160*G160 -> 1670.7797
A161: B5.33 05 13.07 | B161: Sewerage Network:GRP Pipes 1000 mm (Depth 3.51m to 4.5m) | C161: 46174 | D161: SUD1-02-011-TDC-TS9-1-SEW-FIR-0199-00 | E161: Check Coordinates level and Excavation width Bottom level and compaction for sewerage manhole pit MH- 49-4 at Road MCE0 | F161: 19319.76 | G161: 01 | H161: 0.05 | I161: =H161*F161 -> 965.988 | J161: =I161*G161 -> 965.988
A162: B1.31 22 00.03 | B162: Embankments to the ROW | C162: 46174 | D162: SUD1-02-011-TDC-TS9-1-ROD-FIR-0203-00 | E162: Check Coordinates level and Compaction F.D.T for Embankment 7th layer at Road connection point MCZ0 to MCE0, STA: 0+000.00 to STA: 0+144.25 | F162: 22.31 | G162: 2430.8 | H162: 1 | I162: =H162*F162 -> 22.31 | J162: =I162*G162 -> 54231.148
A163: B1.31 22 00.03 | B163: Embankments to the ROW | C163: 46174 | D163: SUD1-02-011-TDC-TS9-1-ROD-FIR-0204-00 | E163: Check Coordinates level and Compaction F.D.T for Shoulder (Right & Left side) 3rd layer at Road # MCF0, STA: 0+050 to STA: 0+160 | F163: 22.31 | G163: 520.41 | H163: 1 | I163: =H163*F163 -> 22.31 | J163: =I163*G163 -> 11610.347
A164: B1.31 22 00.03 | B164: Embankments to the ROW | C164: 46174 | D164: SUD1-02-011-TDC-TS9-1-ROD-FIR-0205-00 | E164: Check Coordinates level and Compaction F.D.T for Embankment 3rd layer at Road # MCF0, STA: 0+50 to STA: 0+160 | F164: 22.31 | G164: 178.46 | H164: 1 | I164: =H164*F164 -> 22.31 | J164: =I164*G164 -> 3981.4426
A165: B1.31 22 00.03 | B165: Embankments to the ROW | C165: 46174 | D165: SUD1-02-011-TDC-TS9-1-ROD-FIR-0206-00 | E165: Check Coordinates level and Compaction F.D.T for Shoulder (Right & Left side) 4th layer at Road # MCF0, STA: 0+160 to STA: 0+250 | F165: 22.31 | G165: 382.5 | H165: 1 | I165: =H165*F165 -> 22.31 | J165: =I165*G165 -> 8533.575
A166: B1.31 22 00.03 | B166: Embankments to the ROW | C166: 46174 | D166: SUD1-02-011-TDC-TS9-1-ROD-FIR-0207-00 | E166: Check Coordinates level and Compaction F.D.T for Embankment 4th layer at Road # MCF0, STA: 0+160 to STA: 0+250 | F166: 22.31 | G166: 177.38 | H166: 1 | I166: =H166*F166 -> 22.31 | J166: =I166*G166 -> 3957.3478
A167: B1.31 22 00.03 | B167: Embankments to the ROW | C167: 46182 | D167: SUD1-02-011-TDC-TS9-1-ROD-FIR-0208-01 | E167: Check Coordinates level and Compaction F.D.T for Shoulder (Right & Left side) Embankments 1st layer at Road # MC20, STA: 4+530 to STA: 4+710 | F167: 22.31 | G167: 1043.32 | H167: 1 | I167: =H167*F167 -> 22.31 | J167: =I167*G167 -> 23276.469
A168: B1.31 22 00.03 | B168: Embankments to the ROW | C168: 46182 | D168: SUD1-02-011-TDC-TS9-1-ROD-FIR-0209-01 | E168: Check Coordinates level and Compaction F.D.T for Shoulder (Right & Left side) 2nd layer at Road # MC20, STA: 5+420 to STA: 5+500 | F168: 22.31 | G168: 765.73 | H168: 1 | I168: =H168*F168 -> 22.31 | J168: =I168*G168 -> 17083.436
A169: B1.31 22 00.03 | B169: Embankments to the ROW | C169: 46190 | D169: SUD1-02-011-TDC-TS9-1-ROD-FIR-0210-01 | E169: Check Coordinates level and Compaction F.D.T for Shoulder (Right & Left side) Embankment 1st layer at Road # MCI0, STA: 0+020 to STA: 0+150 | F169: 22.31 | G169: 763.3 | H169: 1 | I169: =H169*F169 -> 22.31 | J169: =I169*G169 -> 17029.223
A170: B1.31 22 00.03 | B170: Embankments to the ROW | C170: 46190 | D170: SUD1-02-011-TDC-TS9-1-ROD-FIR-0211-01 | E170: Check Coordinates level and Compaction F.D.T for Embankment 1st layer at Road # MCI0, STA: 0+020 to STA: 0+150 | F170: 22.31 | G170: 144.78 | H170: 1 | I170: =H170*F170 -> 22.31 | J170: =I170*G170 -> 3230.0418
A171: B1.31 22 00.03 | B171: Embankments to the ROW | C171: 46174 | D171: SUD1-02-011-TDC-TS9-1-ROD-FIR-0212-00 | E171: Check Coordinates level and Compaction F.D.T for Embankment 3rd layer at Road # MCF0, STA: 0+250 to STA: 0+290 | F171: 22.31 | G171: 56.84 | H171: 1 | I171: =H171*F171 -> 22.31 | J171: =I171*G171 -> 1268.1004
A172: B1.31 22 00.03 | B172: Embankments to the ROW | C172: 46174 | D172: SUD1-02-011-TDC-TS9-1-ROD-FIR-0213-00 | E172: Check Coordinates level and Compaction F.D.T for Embankment 2nd layer at Road # MCF0, STA: 0+290 to STA: 0+370 | F172: 22.31 | G172: 101.92 | H172: 1 | I172: =H172*F172 -> 22.31 | J172: =I172*G172 -> 2273.8352
A173: B6.33 42 11.22 | B173: Storm Water Network : Manhole for GRP Pipes 1000mm (Depth: 1.51m -2.51m) | C173: 46175 | D173: SUD1-02-011-TDC-TS9-1-STR-FIR-0215-00 | E173: Check Coordinates level and Excavation width Bottom level and compaction for Storm Water pipeline trench from Existing Manhole # FIMH – G2/6 to MH – G2/6/1 at Road MCG0 | F173: 884.56 | G173: 92.65 | H173: 0.05 | I173: =H173*F173 -> 44.228 | J173: =I173*G173 -> 4097.7242
A174: B6.33 05 39.8 | B174: Storm Water Network : Manhole 2000mm (Depth: 1.51m -2.51m) | C174: 46175 | D174: SUD1-02-011-TDC-TS9-1-STR-FIR-0216-00 | E174: Check Coordinates level and Excavation width Bottom level and compaction for Storm water manhole pit MH- G2/6/1at Road MCG0 | F174: 30133.35 | G174: 01 | H174: 0.05 | I174: =H174*F174 -> 1506.6675 | J174: =I174*G174 -> 1506.6675
A175: B6.33 42 11.22 | B175: Storm Water Network : Manhole for GRP Pipes 1000mm (Depth: 1.51m -2.51m) | C175: 46175 | D175: SUD1-02-011-TDC-TS9-1-STR-FIR-0217-00 | E175: Check Coordinates level and Excavation width Bottom level and compaction for Storm Water pipeline trench from Manhole # MH – G2/6/1 to MH – G2/6/2 at Road MCG0 | F175: 884.56 | G175: 89 | H175: 0.05 | I175: =H175*F175 -> 44.228 | J175: =I175*G175 -> 3936.292
A176: B6.33 05 39.8 | B176: Storm Water Network : Manhole 2000mm (Depth: 1.51m -2.51m) | C176: 46175 | D176: SUD1-02-011-TDC-TS9-1-STR-FIR-0218-00 | E176: Check Coordinates level and Excavation width Bottom level and compaction for Storm Water manhole pit MH- G2/6/2 at Road MCG0 | F176: 30133.35 | G176: 01 | H176: 0.05 | I176: =H176*F176 -> 1506.6675 | J176: =I176*G176 -> 1506.6675
A177: B6.33 42 11.19 | B177: Storm Water Network : Manhole for GRP Pipes 900mm (Depth: 1.51m -2.51m) | C177: 46175 | D177: SUD1-02-011-TDC-TS9-1-STR-FIR-0219-00 | E177: Check Coordinates level and Excavation width Bottom level and compaction for Storm Water pipeline trench from Manhole # MH – G2/6/2 to MH – G2/6/3 at Road MCG0 | F177: 743.93 | G177: 89.25 | H177: 0.05 | I177: =H177*F177 -> 37.1965 | J177: =I177*G177 -> 3319.7876
A178: B6.33 05 39.5 | B178: Storm Water Network : Manhole 1500mm (Depth: 1.51m -2.51m) | C178: 46175 | D178: SUD1-02-011-TDC-TS9-1-STR-FIR-0220-00 | E178: Check Coordinates level and Excavation width Bottom level and compaction for Storm Water manhole pit MH- G2/6/3 at Road MCG0 | F178: 15295.58 | G178: 01 | H178: 0.05 | I178: =H178*F178 -> 764.779 | J178: =I178*G178 -> 764.779
A179: B6.33 42 11.15 | B179: Storm Water Network : Manhole for GRP Pipes 800mm (Depth: 0.00 -1.50 m) | C179: 46175 | D179: SUD1-02-011-TDC-TS9-1-STR-FIR-0221-00 | E179: Check Coordinates level and Excavation width Bottom level and compaction for Storm Water pipeline trench from Manhole # MH – G2/6/3 to MH – G2/6/4 at Road MCG0 | F179: 623.66 | G179: 89.5 | H179: 0.05 | I179: =H179*F179 -> 31.183 | J179: =I179*G179 -> 2790.8785
A180: B6.33 05 39.5 | B180: Storm Water Network : Manhole 1500mm (Depth: 1.51m -2.51m) | C180: 46175 | D180: SUD1-02-011-TDC-TS9-1-STR-FIR-0222-00 | E180: Check Coordinates level and Excavation width Bottom level and compaction for Storm Water manhole pit MH- G2/6/4 at Road MCG0 | F180: 15295.58 | G180: 01 | H180: 0.05 | I180: =H180*F180 -> 764.779 | J180: =I180*G180 -> 764.779
A181: B1.31 22 00.04 | B181: Embankments to the Plot | C181: 46175 | D181: SUD1-02-011-TDC-TS9-1-ROD-FIR-0223-00 | E181: Check Coordinates level and Compaction F.D.T for Embankment 1ST layer at PLOT (5), STA: 0+360 to STA: 0+570 | F181: 22.31 | G181: 4985.91 | H181: 1 | I181: =H181*F181 -> 22.31 | J181: =I181*G181 -> 111235.65
A182: B1.31 22 00.03 | B182: Embankments to the ROW | C182: 46175 | D182: SUD1-02-011-TDC-TS9-1-ROD-FIR-0224-00 | E182: Check Coordinates level and Compaction F.D.T for Embankment 10th layer at Road # MCG0, STA: 0+224 to STA: 0+380 | F182: 22.31 | G182: 2561.16 | H182: 1 | I182: =H182*F182 -> 22.31 | J182: =I182*G182 -> 57139.48
A183: B1.31 22 00.03 | B183: Embankments to the ROW | C183: 46175 | D183: SUD1-02-011-TDC-TS9-1-ROD-FIR-0225-00 | E183: Check Coordinates level and Compaction F.D.T for Embankment 8th layer at Road # MCZ0, STA: 0+310 to STA: 0+447.25 | F183: 22.31 | G183: 1742.06 | H183: 1 | I183: =H183*F183 -> 22.31 | J183: =I183*G183 -> 38865.359
A184: B1.31 22 00.03 | B184: Embankments to the ROW | C184: 46180 | D184: SUD1-02-011-TDC-TS9-1-ROD-FIR-0226-01 | E184: Check Coordinates level and Compaction F.D.T for Embankment 12th layer at Road # MCD0, STA: 0+30 to STA: 0+180 (Bottom Subgrade) | F184: 22.31 | G184: 1221.13 | H184: 1 | I184: =H184*F184 -> 22.31 | J184: =I184*G184 -> 27243.41
A185: B1.31 22 00.03 | B185: Embankments to the ROW | C185: 46175 | D185: SUD1-02-011-TDC-TS9-1-ROD-FIR-0228-00 | E185: Check Coordinates level and Compaction F.D.T for Embankment 3rd layer at Road # MCF0, STA: 0+410 to STA: 0+430 | F185: 22.31 | G185: 220.54 | H185: 1 | I185: =H185*F185 -> 22.31 | J185: =I185*G185 -> 4920.2474
A186: B1.31 22 00.03 | B186: Embankments to the ROW | C186: 46175 | D186: SUD1-02-011-TDC-TS9-1-ROD-FIR-0230-00 | E186: Check Coordinates level and Compaction F.D.T for Embankment 3rd layer at Road # MCH0, STA: 0+70 to STA: 0+310 | F186: 22.31 | G186: 217.56 | H186: 1 | I186: =H186*F186 -> 22.31 | J186: =I186*G186 -> 4853.7636
A187: B5 33.05.13.05 | B187: Sewerage Network:GRP Pipes 200 mm (Depth 2.51m to 3.5m) int dia 1200 mm | C187: 46175 | D187: SUD1-02-011-TDC-TS9-1-SEW-FIR-0231-00 | E187: Check Formwork, Lean concrete pouring,concrete surface finishing and level at sewerage Manhole Pit No. 52-1 | F187: 15848.43 | G187: 1 | H187: 0.25 | I187: =H187*F187 -> 3962.1075 | J187: =I187*G187 -> 3962.1075
A188: B5 33.05.13.05 | B188: Sewerage Network:GRP Pipes 200 mm (Depth 2.51m to 3.5m) int dia 1200 mm | C188: 46175 | D188: SUD1-02-011-TDC-TS9-1-SEW-FIR-0232-00 | E188: Check Formwork, Lean concrete pouring,concrete surface finishing and level at sewerage Manhole Pit No. 53-1 | F188: 15848.43 | G188: 1 | H188: 0.25 | I188: =H188*F188 -> 3962.1075 | J188: =I188*G188 -> 3962.1075
A189: B5.33 05 13.07 | B189: Sewerage Network:GRP Pipes 1000 mm (Depth 3.51m to 4.5m) | C189: 46175 | D189: SUD1-02-011-TDC-TS9-1-SEW-FIR-0233-00 | E189: Check Formwork, Lean concrete pouring,concrete surface finishing and level at sewerage Manhole Pit No. 49-2 | F189: 19319.76 | G189: 1 | H189: 0.25 | I189: =H189*F189 -> 4829.94 | J189: =I189*G189 -> 4829.94
A190: B5.33 05 13.07 | B190: Sewerage Network:GRP Pipes 1000 mm (Depth 3.51m to 4.5m) | C190: 46175 | D190: SUD1-02-011-TDC-TS9-1-SEW-FIR-0234-00 | E190: Check Formwork, Lean concrete pouring,concrete surface finishing and level at sewerage Manhole Pit No. 49-3 | F190: 19319.76 | G190: 1 | H190: 0.25 | I190: =H190*F190 -> 4829.94 | J190: =I190*G190 -> 4829.94
A191: B1.31 22 00.03 | B191: Embankments to the ROW | C191: 46175 | D191: SUD1-02-011-TDC-TS9-1-ROD-FIR-0236-00 | E191: Check Coordinates level and Compaction F.D.T for Embankments of 3rd layer at Road # MCG0, STA: 0+290 to STA: 0+320 | F191: 22.31 | G191: 111.72 | H191: 1 | I191: =H191*F191 -> 22.31 | J191: =I191*G191 -> 2492.4732
A192: B1.31 22 00.03 | B192: Embankments to the ROW | C192: 46175 | D192: SUD1-02-011-TDC-TS9-1-ROD-FIR-0237-00 | E192: Check Coordinates level and Compaction F.D.T for Embankments of 4th layer at Road # MCG0, STA: 0+220 to STA: 0+290 | F192: 22.31 | G192: 249.9 | H192: 1 | I192: =H192*F192 -> 22.31 | J192: =I192*G192 -> 5575.269
A193: B1.31 22 00.03 | B193: Embankments to the ROW | C193: 46175 | D193: SUD1-02-011-TDC-TS9-1-ROD-FIR-0238-00 | E193: Check Coordinates level and Compaction F.D.T for Embankments of 5th layer at Road # MCG0, STA: 0+190 to STA: 0+220 | F193: 22.31 | G193: 103.88 | H193: 1 | I193: =H193*F193 -> 22.31 | J193: =I193*G193 -> 2317.5628
A194: B1.31 22 00.03 | B194: Embankments to the ROW | C194: 46176 | D194: SUD1-02-011-TDC-TS9-1-ROD-FIR-0239-00 | E194: Check Coordinates level and Compaction F.D.T for Embankment 1st layer at Plot (5) STA: 0+350 to STA: 0+467 | F194: 22.31 | G194: 3821.64 | H194: 1 | I194: =H194*F194 -> 22.31 | J194: =I194*G194 -> 85260.788
A195: B1.31 22 00.03 | B195: Embankments to the ROW | C195: 46177 | D195: SUD1-02-011-TDC-TS9-1-ROD-FIR-0240-00 | E195: Check Coordinates level and Compaction F.D.T for Shoulder (Right & Left side) 1st layer at Road # MC20, STA: 5+500 to STA: 5+620 | F195: 22.31 | G195: 849.49 | H195: 1 | I195: =H195*F195 -> 22.31 | J195: =I195*G195 -> 18952.122
A196: B6.33 05 39.8 | B196: Storm Water Network : Manhole 2000mm (Depth: 1.51m -2.51m) | C196: 46177 | D196: SUD1-02-011-TDC-TS9-1-STR-FIR-0241-00 | E196: Check Formwork, Lean concrete pouring,concrete surface finishing and level at Storm water manhole pit MH- G2/6/1at Road MCG0 | F196: 30133.35 | G196: 01 | H196: 0.25 | I196: =H196*F196 -> 7533.3375 | J196: =I196*G196 -> 7533.3375
A197: B6.33 05 39.8 | B197: Storm Water Network : Manhole 2000mm (Depth: 1.51m -2.51m) | C197: 46177 | D197: SUD1-02-011-TDC-TS9-1-STR-FIR-0242-00 | E197: Check Formwork, Lean concrete pouring,concrete surface finishing and level at Storm water manhole pit MH- G2/6/2 at Road MCG0 | F197: 30133.35 | G197: 01 | H197: 0.25 | I197: =H197*F197 -> 7533.3375 | J197: =I197*G197 -> 7533.3375
A198: B6.33 05 39.5 | B198: Storm Water Network : Manhole 1500mm (Depth: 1.51m -2.51m) | C198: 46177 | D198: SUD1-02-011-TDC-TS9-1-STR-FIR-0243-00 | E198: Check Formwork, Lean concrete pouring,concrete surface finishing and level at Storm water manhole pit MH- G2/6/3 at Road MCG0 | F198: 15295.58 | G198: 01 | H198: 0.25 | I198: =H198*F198 -> 3823.895 | J198: =I198*G198 -> 3823.895
A199: B6.33 05 39.5 | B199: Storm Water Network : Manhole 1500mm (Depth: 1.51m -2.51m) | C199: 46177 | D199: SUD1-02-011-TDC-TS9-1-STR-FIR-0244-00 | E199: Check Formwork, Lean concrete pouring,concrete surface finishing and level at Storm water manhole pit MH- G2/6/4 at Road MCG0 | F199: 15295.58 | G199: 01 | H199: 0.25 | I199: =H199*F199 -> 3823.895 | J199: =I199*G199 -> 3823.895
A200: B5.33 05 13.07 | B200: Sewerage Network:GRP Pipes 1000 mm (Depth 3.51m to 4.5m) | C200: 46177 | D200: SUD1-02-011-TDC-TS9-1-SEW-FIR-0245-00 | E200: Check Formwork, Lean concrete pouring,concrete surface finishing and level at sewerage Manhole Pit No. 49-4 | F200: 19319.76 | G200: 1 | H200: 0.25 | I200: =H200*F200 -> 4829.94 | J200: =I200*G200 -> 4829.94
A201: B1.31 22 00.04 | B201: Embankments to the Plot | C201: 46218 | D201: SUD1-02-011-TDC-TS9-1-ROD-FIR-0246-00 | E201: Check Coordinates level, Compaction F.D.T for Embankment 1st Layer STA: 0+360 to 0+467 at Plot. No: - 04 | F201: 22.31 | G201: 6931.74 | H201: 1 | I201: =H201*F201 -> 22.31 | J201: =I201*G201 -> 154647.12
A202: B1.31 22 00.03 | B202: Embankments to the ROW | C202: 46177 | D202: SUD1-02-011-TDC-TS9-1-ROD-FIR-0247-00 | E202: Check Coordinates level and Compaction F.D.T for Embankment 8th layer at Road connection point MCZ0 to MCE0, STA: 0+000.00 to STA: 0+144.25 | F202: 22.31 | G202: 2489.56 | H202: 1 | I202: =H202*F202 -> 22.31 | J202: =I202*G202 -> 55542.084
A203: B1.31 22 00.03 | B203: Embankments to the ROW | C203: 46177 | D203: SUD1-02-011-TDC-TS9-1-ROD-FIR-0248-00 | E203: Check Coordinates level and Compaction F.D.T for Embankment 4th layer at Road # MCF0, STA: 0+410 to STA: 0+430 | F203: 22.31 | G203: 220.93 | H203: 1 | I203: =H203*F203 -> 22.31 | J203: =I203*G203 -> 4928.9483
A204: B1.31 22 00.03 | B204: Embankments to the ROW | C204: 46177 | D204: SUD1-02-011-TDC-TS9-1-ROD-FIR-0249-00 | E204: Check Coordinates level and Compaction F.D.T for Shoulder (Right side) 3rd layer at Road # MCG0, STA: 0+290 to STA: 0+320 | F204: 22.31 | G204: 76.14 | H204: 1 | I204: =H204*F204 -> 22.31 | J204: =I204*G204 -> 1698.6834
A205: B1.31 22 00.03 | B205: Embankments to the ROW | C205: 46177 | D205: SUD1-02-011-TDC-TS9-1-ROD-FIR-0250-00 | E205: Check Coordinates level and Compaction F.D.T for Shoulder (Right side)4th layer at Road # MCG0, STA: 0+220 to STA: 0+290 | F205: 22.31 | G205: 178.5 | H205: 1 | I205: =H205*F205 -> 22.31 | J205: =I205*G205 -> 3982.335
A206: B1.31 22 00.03 | B206: Embankments to the ROW | C206: 46177 | D206: SUD1-02-011-TDC-TS9-1-ROD-FIR-0251-00 | E206: Check Coordinates level and Compaction F.D.T for Shoulder (Right side) 5th layer at Road # MCG0, STA: 0+190 to STA: 0+220 | F206: 22.31 | G206: 85.49 | H206: 1 | I206: =H206*F206 -> 22.31 | J206: =I206*G206 -> 1907.2819
A207: B1.31 22 00.04 | B207: Embankments to the Plot | C207: 46182 | D207: SUD1-02-011-TDC-TS9-1-ROD-FIR-0252-00 | E207: Check Coordinates level and Compaction F.D.T for Embankment 1st layer at PLOT (3), STA: 0+060 to STA: 0+150 | F207: 22.31 | G207: 1,392.73 | H207: 1 | I207: =H207*F207 -> 22.31 | J207: =I207*G207 -> 31071.806
A208: B5.33 05 13.03 | B208: SEWERAGE NETWORK: - Manhole Depth (1.51-2.50m) Internal Diameter :-1200mm | C208: 46196 | D208: SUD1-02-011-TDC-TS9-1-SEW-FIR-0254-00 | E208: Check Formwork, Lean concrete pouring,concrete surface finishing and level at sewerage Manhole Pit No. 12-18 | F208: 12377.1 | G208: 1 | H208: 0.25 | I208: =H208*F208 -> 3094.275 | J208: =I208*G208 -> 3094.275
A209: B1.31 22 00.03 | B209: Embankments to the ROW | C209: 46181 | D209: SUD1-02-011-TDC-TS9-1-ROD-FIR-0255-02 | E209: Check Coordinates level and Compaction F.D.T for Embankment 11th layer at Road # MCG0, STA: 0+240 to STA: 0+360 | F209: 22.31 | G209: 1766.28 | H209: 1 | I209: =H209*F209 -> 22.31 | J209: =I209*G209 -> 39405.707
A210: B1.31 22 00.03 | B210: Embankments to the ROW | C210: 46179 | D210: SUD1-02-011-TDC-TS9-1-ROD-FIR-0256-00 | E210: Check Coordinates level and Compaction F.D.T for Embankment 9th layer at Road # MCZ0, STA: 0+170 to STA: 0+310 | F210: 22.31 | G210: 1766.14 | H210: 1 | I210: =H210*F210 -> 22.31 | J210: =I210*G210 -> 39402.583
A211: B1.31 22 00.03 | B211: Embankments to the ROW | C211: 46179 | D211: SUD1-02-011-TDC-TS9-1-ROD-FIR-0257-00 | E211: Check Coordinates level and Compaction F.D.T for Embankment 5th layer at Road # MCF0, STA: 0+410 to STA: 0+430 | F211: 22.31 | G211: 221.39 | H211: 1 | I211: =H211*F211 -> 22.31 | J211: =I211*G211 -> 4939.2109
A212: B1.31 22 00.03 | B212: Embankments to the ROW | C212: 46181 | D212: SUD1-02-011-TDC-TS9-1-ROD-FIR-0258-00 | E212: Check Coordinates level and Compaction F.D.T for Embankment 3rd layer at Road # MCF0, STA: 0+430 to STA: 0+460 | F212: 22.31 | G212: 258.04 | H212: 1 | I212: =H212*F212 -> 22.31 | J212: =I212*G212 -> 5756.8724
A213: B1.31 22 00.03 | B213: Embankments to the ROW | C213: 46180 | D213: SUD1-02-011-TDC-TS9-1-ROD-FIR-0260-00 | E213: Check Coordinates and bottom level Road Excavation/cutting upto bottom of Sub-Grade at Road # MCD0, STA: 0+30 to STA: 0+40 | F213: 22.31 | G213: 49.190 | H213: 1 | I213: =H213*F213 -> 22.31 | J213: =I213*G213 -> 1097.4289
A214: B1.31 22 00.03 | B214: Embankments to the ROW | C214: 46167 | D214: SUD1-02-011-TDC-TS9-1-ROD-FIR-0261-00 | E214: Check Coordinates level and Compaction F.D.T for Embankment 3rd layer at Road # MCF0, STA: 0+230 to STA: 0+250 | F214: 22.31 | G214: 150.00 | H214: 1 | I214: =H214*F214 -> 22.31 | J214: =I214*G214 -> 3346.5
A215: B1.31 22 00.03 | B215: Embankments to the ROW | C215: 46180 | D215: SUD1-02-011-TDC-TS9-1-ROD-FIR-0262-00 | E215: Check Coordinates and bottom level Road Excavation/cutting and compaction test upto bottom of Sub-Grade at Road # MC20, STA: 4+530 to STA: 4+710 | F215: 22.31 | G215: 799.67 | H215: 1 | I215: =H215*F215 -> 22.31 | J215: =I215*G215 -> 17840.638
A216: B1.31 22 00.04 | B216: Embankments to the Plot | C216: 46184 | D216: SUD1-02-011-TDC-TS9-1-ROD-FIR-0263-00 | E216: Check Coordinates level and Compaction F.D.T for Embankment 1st layer at Plot (5) STA: 0+020 to STA: 0+150 Area (3) | F216: 22.31 | G216: 4339.03 | H216: 1 | I216: =H216*F216 -> 22.31 | J216: =I216*G216 -> 96803.759
A217: B1.31 22 00.03 | B217: Embankments to the ROW | C217: 46180 | D217: SUD1-02-011-TDC-TS9-1-ROD-FIR-0264-00 | E217: Check Coordinates level and Compaction F.D.T for Embankment 10th layer at Road # MCZ0, STA: 0+80 to STA: 0+170 | F217: 22.31 | G217: 911.91 | H217: 1 | I217: =H217*F217 -> 22.31 | J217: =I217*G217 -> 20344.712
A218: B5 33.31.00.02 | B218: Sewerage Network:GRP Pipes 200 mm (Depth 1.51m to 2.5m) | C218: 46180 | D218: SUD1-02-011-TDC-TS9-1-SEW-FIR-0266-00 | E218: Check Coordinates level and Excavation width Bottom level and compaction for sewerage pipeline trench from existing manhole # MH-52-2 to MH-52-3 at Road MCF0 | F218: 221.14 | G218: 98.80 | H218: 0.05 | I218: =H218*F218 -> 11.057 | J218: =I218*G218 -> 1092.4316
... A278: B1.31 22 00.03 | B278: Embankments to the ROW | C278: 46183 | D278: SUD1-02-011-TDC-TS9-1-ROD-FIR-0328-00 | E278: Check Coordinates level and Compaction F.D.T for Shoulder (Right side) Embankments 3rd layer at Road # MCF0, STA: 0+250 to STA: 0+290 | F278: 22.31 | G278: 79.56 | H278: 1 | I278: =H278*F278 -> 22.31 | J278: =I278*G278 -> 1774.9836
A279: B1.31 22 00.04 | B279: Embankments to the Plot | C279: 46186 | D279: SUD1-02-011-TDC-TS9-1-ROD-FIR-0329-00 | E279: Check Coordinates level, Compaction F.D.T for Embankment 1st Layer STA: 0+250 to 0+360 (Left Side) at Plot. No: - 04 | F279: 22.31 | G279: 2208.54 | H279: 1 | I279: =H279*F279 -> 22.31 | J279: =I279*G279 -> 49272.527
A280: B1.31 22 00.01 | B280: Roadway Excavation for cuttings | C280: 46184 | D280: SUD1-02-011-TDC-TS9-1-ROD-FIR-0330-00 | E280: Check Coordinates and bottom level Road cutting and compaction test of bottom Sub-Grade at Road layer 1st STA: 0 +850 to STA: 0+890 at Road # MCA0 | F280: 13.58 | G280: 61.19 | H280: 1 | I280: =H280*F280 -> 13.58 | J280: =I280*G280 -> 830.9602
A281: B1.31 22 00.03 | D281: SUD1-02-011-TDC-TS9-1-ROD-FIR-0331-01 | E281: Check Coordinates and bottom level Road Filling and compaction test of bottom Sub-Grade 1st layer at Road # MCA0, STA: 0+800 to STA: 0+890 | G281: 514.13 | H281: 0.1
A282: B5 33.31.00.01 | B282: Sewerage Network:GRP Pipes 200 mm (Depth 0.00 m to 1.5m) | C282: 46184 | D282: SUD1-02-011-TDC-TS9-1-SEW-FIR-0332-00 | E282: Check Coordinates level and Excavation width Bottom level and compaction for sewerage pipeline trench from Manhole # MH – 49-6 to MH – 49-7 at Road MCE0 | F282: 212.41 | G282: 40.42 | H282: 0.05 | I282: =H282*F282 -> 10.6205 | J282: =I282*G282 -> 429.28061
A283: B5 33.31.00.01 | B283: Sewerage Network:GRP Pipes 200 mm (Depth 0.00 m to 1.5m) | C283: 46184 | D283: SUD1-02-011-TDC-TS9-1-SEW-FIR-0333-00 | E283: Check Coordinates level and Excavation width Bottom level and compaction for sewerage pipeline trench from Manhole # MH – 49-7 to MH – 49-8 at Road MCE0 | F283: 212.41 | G283: 48.80 | H283: 0.05 | I283: =H283*F283 -> 10.6205 | J283: =I283*G283 -> 518.2804
...

Sheet Schedule
A1: Primavera P6 Schedule Status | P1: ='General Information'!$K$1 -> Data Date | Q1: ='General Information'!$L$1 -> 46293
A2: Project Activities Overview
A3: Schedule Statistics | F3: Active Schedule Activities
A4: Total Act. | B4: Not Started | C4: In Progress | D4: Completed | E4: % | F4: Active | G4: Ahead | H4: On | I4: Behind | J4: Flag
A5: 2115 | B5: 1084 | C5: 340 | D5: 691 | E5: =D5/A5 -> 0.32671395 | F5: 9 | G5: 8 | H5: 0 | I5: 11 | J5: =+G5+H5-I5 -> -3
A6: Critical Path Activities | D6: Free Float Management (Total) | H6: Failed Start Activities
D7: Greater Than 14 Days | F7: Less Than 14 Days
A8: Last Week | B8: This Week | C8: Diff | D8: Last Week | E8: This Week | F8: Last Week | G8: This Week | H8: Last Week | I8: This Week | J8: Flag
A9: 20 | B9: 19 | C9: =A9-B9 -> 1 | D9: 200 | E9: 191 | F9: 1229 | G9: 1229 | H9: 16 | I9: 10 | J9: =H9-I9 -> 6

Sheet Milestones
A1: Project Name
A2: Item No. | B2: Milestones | C2: Original (Baseline) | D2: Latest | E2: Forecast | G2: Days Change
B3: ="Contract Duration Current Contract Weeks : "&TEXT(I3, "0")&" of "&TEXT(L3, "0") -> Contract Duration Current Contract Weeks : 38 of 78 | D3: =(D14-D4)/7 -> 77.857143 | E3: =(E14-E4)/7 -> 77.857143 | G3: =(D3-E3)*7 -> 0 | I3: =('General Information'!L1-C4)/7 -> 37.857143 | L3: =D3 -> 77.857143
A4: 1 | B4: Project Start Milstone | C4: 46028 | D4: 46028 | E4: 46028 | F4: Finish | G4: =D4-E4 -> 0
A5: 2 | B5: Mobilization Finish Milestone | C5: 46058 | D5: 46058 | E5: 46058 | F5: Finish | G5: =D5-E5 -> 0
A6: 3 | B6: Baseline Submission Finish Milestone | C6: 46058 | D6: 46058 | E6: 46118 | F6: Finish | G6: =D6-E6 -> -60
A7: 4 | B7: Technical Submittals Finish Milestone | C7: 46086 | D7: 46086 | E7: 46250 | F7: UP | G7: =D7-E7 -> -164
A8: 5 | B8: Quality Lap Finish Milestone | C8: 46058 | D8: 46058 | E8: 46069 | F8: Finish | G8: =D8-E8 -> -11
A9: 6 | B9: RBF Finish Milestone | C9: 46058 | D9: 46058 | E9: 46069 | F9: Finish | G9: =D9-E9 -> -11 | H9: 5058886 | I9: 4463892
A10: 7 | B10: All Works Finish Milestone | C10: 46573 | D10: 46573 | E10: 46573 | F10: UP | G10: =D10-E10 -> 0 | H10: =H53 -> 0 | I10: =I53 -> 0
A11: 8 | B11: Engineering Phase Finish Milestone | C11: 46086 | D11: 46086 | E11: 46293 | F11: UP | G11: =D11-E11 -> -207 | H11: =H54 -> 0 | I11: =I54 -> 0
A12: 9 | B12: Procurment Phase Finish Milestone | C12: 46410 | D12: 46410 | E12: 46404 | F12: UP | G12: =D12-E12 -> 6 | H12: =H55 -> 0 | I12: =I55 -> 0
A13: 10 | B13: Construction Phase Finish Milestone | C13: 46573 | D13: 46573 | E13: 46573 | F13: UP | G13: =D13-E13 -> 0 | H13: =H56 -> 0 | I13: =I56 -> 0
A14: 11 | B14: Project Finish Milstone | C14: 46573 | D14: 46573 | E14: 46573 | F14: - | G14: =D14-E14 -> 0 | H14: =H57 -> 0 | I14: =I57 -> 0
H15: =H58 -> 0 | I15: =I58 -> 0
H16: =H59 -> 0 | I16: =I59 -> 0

Sheet Procurement
A1: PROCUREMENT
A2: Sr. NO. | B2: Project ID | C2: ACT#inP6 | D2: Item Description | E2: Discipline | F2: (Long \Short) Lead Items | G2: BOQ. No. | H2: Unit | I2: Quantity | J2: Proc. Qty | K2: Required P.O Date | L2: Date of Pur. Order Issued | M2: Purchase Order No. | N2: Supplier | O2: Supplier Phone | P2: Method of Shipping | Q2: Required on Job | R2: E.D.A. to Site | S2: A.D.A. to Site | T2: Lead Time | U2: Approval Status | V2: The Impact (BOQ Cost) | W2: Completion Rate | X2: Remarks
A3: 1 | B3: SUD1-02-011 | C3: SIC-ENG-M-SUC-1000 | D3: Earth works material | E3: Civil | F3: Short Lead Items | G3: 31 22 00 | H3: m3 | I3: 2437927 | J3: 2437927 | K3: 46072 | L3: - | M3: - | N3: - | P3: Local trancport | R3: 46088 | T3: =R3-K3 -> 16 | U3: Approved | V3: - | W3: 0.9 | X3: Delivery Ongoing
A4: 2 | B4: SUD1-02-011 | C4: SIC-ENG-M-SUC-1010 | D4: Ready mix concrete | E4: Civil | F4: Short Lead Items | G4: 33 42 16 | H4: m3 | I4: 270 | J4: 270 | K4: 46072 | L4: - | M4: - | N4: - | P4: Local trancport | R4: 46095 | S4: 46184 | T4: =R4-K4 -> 23 | U4: Approved | V4: - | W4: 1 | X4: Delivered
A5: 3 | B5: SUD1-02-011 | C5: SIC-ENG-M-SUC-1020 | D5: Asphalt Mix | E5: Civil | F5: Short Lead Items | G5: 32 11 26 | H5: m3 | I5: 32179 | J5: 32179 | K5: 46072 | L5: - | M5: - | N5: - | P5: Local trancport | R5: 46095 | S5: 46184 | T5: =R5-K5 -> 23 | U5: Approved | V5: - | W5: 0.15 | X5: Delivery Ongoing
A6: 4 | B6: SUD1-02-011 | C6: SIC-ENG-M-SUC-1030 | D6: Road Marking | E6: Civil | F6: Short Lead Items | G6: 32 17 23 | H6: m² | I6: 11860 | J6: 11860 | K6: 46111 | L6: - | M6: - | N6: - | P6: Local trancport | R6: 46124 | T6: =R6-K6 -> 13 | U6: Not submitted | V6: - | W6: -
A7: 5 | B7: SUD1-02-011 | C7: SIC-ENG-M-SUC-1040 | D7: Kerbstone | E7: Civil | F7: Short Lead Items | G7: 32 14 13 | H7: m | I7: 117195 | J7: 117195 | K7: 46125 | L7: - | M7: - | N7: - | P7: Local trancport | R7: 46139 | T7: =R7-K7 -> 14 | U7: Approved | V7: - | W7: 0.2 | X7: Delivery Ongoing
A8: 6 | B8: SUD1-02-011 | C8: SIC-ENG-M-SUC-1050 | D8: Interlock Tiles | E8: Civil | F8: Short Lead Items | G8: 32 14 13.13 | H8: m² | I8: 53000 | J8: 53000 | K8: 46125 | L8: - | M8: - | N8: - | P8: Local trancport | R8: 46152 | T8: =R8-K8 -> 27 | U8: Approved | V8: - | W8: 0.1 | X8: Delivery Ongoing
A9: 7 | B9: SUD1-02-011 | C9: SIC-ENG-M-SUC-1060 | D9: Traffic Signage | E9: Civil | F9: Short Lead Items | G9: 10 14 53 | H9: Unit | I9: 64 | J9: 64 | K9: 46139 | L9: - | M9: - | N9: - | P9: Local trancport | R9: 46098 | T9: 32 | U9: Approved | V9: - | W9: -
A10: 8 | B10: SUD1-02-011 | C10: SIC-ENG-M-SUC-1070 | D10: Construction material | E10: Civil | F10: Short Lead Items | G10: 32 11 23 / 31 22 00.05 | H10: m3 | I10: 102138 | J10: 102138 | K10: 46072 | L10: - | M10: - | N10: - | P10: Local trancport | R10: 46173 | S10: 46232 | T10: =R10-K10 -> 101 | U10: Approved | V10: - | W10: 1 | X10: Delivered
A11: 9 | B11: SUD1-02-011 | C11: SIC-ENG-M-SUC-1080 | D11: Fence for Electrical works | E11: Civil | F11: Short Lead Items | G11: 26.11.00 | H11: Unit | I11: 5 | K11: 46139 | L11: - | M11: - | N11: - | P11: Local trancport | R11: 46219 | T11: =R11-K11 -> 80 | U11: Not submitted | V11: - | W11: -
A12: 10 | B12: SUD1-02-011 | C12: SIC-ENG-M-SUC-1090 | D12: Protection Bollards for CCTV Pole | E12: Civil | F12: Short Lead Items | G12: 33 14 19 | H12: Unit | I12: 86 | K12: 46153 | L12: - | M12: - | N12: - | P12: Local trancport | R12: 46165 | T12: 19 | U12: Approved | V12: - | W12: -
A13: 11 | B13: SUD1-02-011 | C13: SIC-ENG-M-SUC-1100 | D13: Protection (Guard rail) for Fire hydrant | E13: Mechanical | F13: Short Lead Items | G13: 33 14 19 | H13: Unit | I13: 90 | K13: 46167 | L13: - | M13: - | N13: - | P13: Local trancport | R13: 46201 | T13: =R13-K13 -> 34 | U13: Approved | V13: - | W13: -
A14: 12 | B14: SUD1-02-011 | C14: SIC-ENG-M-SUE-1210 | D14: Termination Kits & Joints | E14: Electrical | F14: Short Lead Items | G14: 26 05 13.16 | H14: unit | I14: 144 | K14: 46079 | L14: - | M14: - | N14: - | P14: Local trancport | R14: 46361 | T14: =R14-K14 -> 282 | U14: Approved | V14: - | W14: 1 | X14: Delivered
A15: 13 | B15: SUD1-02-011 | C15: SIC-ENG-M-SUE-1220 | D15: UPVC Ducts & HDPE Ducts for Telecom network | E15: Electrical | F15: Short Lead Items | G15: 33 14 13 | H15: m | I15: 15200 | J15: 15200 | K15: 46156 | P15: Local trancport | R15: 46361 | S15: 46191 | T15: =R15-K15 -> 205 | U15: Approved | V15: - | W15: 1 | X15: Delivered
A16: 14 | B16: SUD1-02-011 | C16: SIC-ENG-M-SUE-1230 | D16: Grounding System | E16: Electrical | F16: Short Lead Items | G16: 26 05 26 | H16: Unit | I16: 50 | J16: 50 | K16: 46189 | L16: - | M16: - | N16: - | P16: Local trancport | R16: 46375 | S16: 46211 | T16: =R16-K16 -> 186 | U16: Approved | V16: - | W16: 1 | X16: Delivered
A17: 15 | B17: SUD1-02-011 | C17: SIC-ENG-M-SUE-1240 | D17: PECD Ducts for CCTV network | E17: Electrical | F17: Short Lead Items | G17: 34 14 19 | H17: Unit | I17: 1 | K17: 46233 | L17: - | M17: - | N17: - | P17: Local trancport | R17: 46398 | T17: =R17-K17 -> 165 | U17: Approved | V17: - | W17: -
A18: 16 | B18: SUD1-02-011 | C18: SIC-ENG-M-SUM-1000 | D18: GRP & UPVC Pipes & Fittings | E18: Mechanical | F18: Long Lead Items | G18: 33 31 00 / 33 42 11 | H18: m | I18: 22100 | J18: 22100 | K18: 46077 | L18: 46090 | M18: 10708 &10697 | N18: AMIANTIT&Nationel marketing | O18: 9668471500 | P18: Local trancport | R18: 46144 | S18: 46192 | T18: =R18-K18 -> 67 | U18: Approved | V18: - | W18: 1 | X18: Delivered
A19: 17 | B19: SUD1-02-011 | C19: SIC-ENG-M-SUM-1010 | D19: HDPE Pipes & Fittings | E19: Mechanical | F19: Long Lead Items | G19: 33 14 13 / 11 | H19: m | I19: 63710 | J19: 63710 | K19: 46096 | L19: 46090 | M19: 10760 | N19: Union pipes | O19: 500632552 | P19: Local trancport | R19: 46152 | S19: 46192 | T19: =R19-K19 -> 56 | U19: Approved | V19: - | W19: 1 | X19: Delivered
A20: 18 | B20: SUD1-02-011 | C20: SIC-ENG-M-SUM-1020 | D20: Gate Valves | E20: Mechanical | F20: Long Lead Items | G20: 33 14 19 | H20: Unit | I20: =105+112+84 -> 301 | J20: =105+112+84 -> 301 | K20: 46112 | L20: - | N20: AVK | O20: 114006355 | P20: Local trancport | R20: 46160 | T20: =R20-K20 -> 48 | U20: Approved | V20: - | W20: 0.4 | X20: Delivery Ongoing
A21: 18.1 | B21: SUD1-02-011 | C21: SIC-ENG-M-SUM-1020 | D21: Butterfly valves | E21: Mechanical | F21: Long Lead Items | G21: 34 14 19 | H21: Unit | I21: =28+4 -> 32 | J21: =28+4 -> 32 | K21: 46112 | N21: AVK | O21: 114006355 | P21: Local trancport | R21: 46160 | T21: =R21-K21 -> 48 | U21: Approved | W21: 0.4 | X21: Delivery Ongoing
A22: 18.2 | B22: SUD1-02-011 | C22: SIC-ENG-M-SUM-1020 | D22: Washout valves | E22: Mechanical | F22: Long Lead Items | G22: 35 14 19 | H22: Unit | I22: =8+6 -> 14 | J22: =8+6 -> 14 | K22: 46112 | N22: AVK | O22: 114006355 | P22: Local trancport | R22: 46160 | T22: =R22-K22 -> 48 | U22: Approved | W22: 0.4 | X22: Delivery Ongoing
A23: 18.3 | B23: SUD1-02-011 | C23: SIC-ENG-M-SUM-1020 | D23: Airrelease valves | E23: Mechanical | F23: Long Lead Items | G23: 36 14 19 | H23: Unit | I23: =10+6+7 -> 23 | J23: =10+6+7 -> 23 | K23: 46112 | N23: AVK | O23: 114006355 | P23: Local trancport | R23: 46160 | T23: =R23-K23 -> 48 | U23: Approved
A24: 19 | B24: SUD1-02-011 | C24: SIC-ENG-M-SUM-1030 | D24: Manhole | E24: Civil | F24: Long Lead Items | G24: 33 05 13 | H24: Unit | I24: 321 | J24: 321 | K24: 46096 | L24: - | N24: Sacep contraction | O24: 53431677 | P24: Local trancport | R24: 46190 | S24: 46208 | T24: =R24-K24 -> 94 | U24: Approved | V24: - | W24: 0.95 | X24: Delivery Ongoing
A25: 20 | B25: SUD1-02-011 | C25: SIC-ENG-M-SUM-1040 | D25: Catch Basin | E25: Civil | F25: Long Lead Items | G25: 33 05 39 | H25: Unit | I25: 250 | J25: 250 | K25: 46126 | L25: - | N25: United Al kharj | O25: 53431677 | P25: Local trancport | R25: 46194 | T25: =R25-K25 -> 68 | U25: Approved | V25: - | W25: 0.8 | X25: Delivery Ongoing
A26: 21 | B26: SUD1-02-011 | C26: SIC-ENG-M-SUM-1050 | D26: Manhole, Catch basin and Valve box Cover | E26: Civil | F26: Long Lead Items | G26: 33 05 13 / 39 | H26: Unit | I26: 571 | J26: 571 | K26: 46140 | L26: - | N26: United Al kharj | O26: 53431677 | P26: Local trancport | R26: 46226 | S26: 46213 | T26: =R26-K26 -> 86 | U26: Approved | V26: - | W26: 0.45 | X26: Delivery Ongoing
A27: 22 | B27: SUD1-02-011 | C27: SIC-ENG-M-SUM-1060 | D27: Fire Hydrant | E27: Mechanical | F27: Long Lead Items | G27: 33 14 19 | H27: Unit | I27: 90 | J27: 90 | K27: 46154 | L27: 46089 | M27: 10699 | N27: AVK | O27: 114006355 | P27: Local trancport | R27: 46289 | T27: =R27-K27 -> 135 | U27: Approved | V27: - | W27: 1 | X27: Delivered
A28: 23 | B28: SUD1-02-011 | C28: SIC-ENG-M-SUM-1070 | D28: Valve of Fire Hydrant | E28: Mechanical | F28: Long Lead Items | G28: 33 14 19 | H28: Unit | I28: 90 | J28: 90 | K28: 46154 | L28: - | N28: AVK | O28: 114006355 | P28: Local trancport | R28: 46289 | T28: =R28-K28 -> 135 | U28: Approved | V28: - | W28: 1 | X28: Delivered
A29: 24 | B29: SUD1-02-011 | C29: SIC-ENG-M-SUE-1000 | D29: MV Cables | E29: Electrical | F29: Long Lead Items | G29: 26 05 13.16 | H29: m | I29: 51500 | J29: 51500 | K29: 46079 | L29: - | P29: Local trancport | R29: 46173 | T29: =R29-K29 -> 94 | U29: Not submitted | V29: - | W29: 0
A30: 25 | B30: SUD1-02-011 | C30: SIC-ENG-M-SUE-1010 | D30: LV Cables | E30: Electrical | F30: Long Lead Items | G30: 26.5.19 | H30: m | I30: 29700 | J30: 29700 | K30: 46098 | L30: - | N30: Hasham Esawady | P30: Local trancport | R30: 46158 | T30: =R30-K30 -> 60 | U30: Approved | V30: - | W30: 0.84 | X30: Delivery Ongoing
A31: 26 | B31: SUD1-02-011 | C31: SIC-ENG-M-SUE-1020 | D31: Street Lighting Poles | E31: Electrical | F31: Long Lead Items | G31: 26 56 19 | H31: Unit | I31: 590 | J31: 590 | K31: 46114 | L31: - | N31: Ababten co | P31: Local trancport | R31: 46183 | T31: =R31-K31 -> 69 | U31: Approved | V31: - | W31: 0.1 | X31: Ongoing
A32: 27 | B32: SUD1-02-011 | C32: SIC-ENG-M-SUE-1030 | D32: Street Lighting Fixtures | E32: Electrical | F32: Long Lead Items | G32: 26 56 19 | H32: Unit | I32: 678 | J32: 678 | K32: 46128 | L32: - | N32: Ababten co | P32: Local trancport | R32: 46197 | T32: =R32-K32 -> 69 | U32: Approved | V32: - | W32: -
A33: 28 | B33: SUD1-02-011 | C33: SIC-ENG-M-SUE-1040 | D33: DrawPits for Lighting | E33: Electrical | F33: Long Lead Items | G33: 33 71 19.13 | H33: Unit | I33: 95 | K33: 46142 | L33: - | N33: - | P33: Local trancport | R33: 46211 | T33: =R33-K33 -> 69 | U33: Approved | V33: - | W33: 1 | X33: Delivered
A34: 29 | B34: SUD1-02-011 | C34: SIC-ENG-M-SUE-1050 | D34: Concrete Manholes & DrawPits for Telecom Network | E34: Electrical | F34: Long Lead Items | G34: 33 71 19.13 | H34: Unit | I34: 122 | K34: 46175 | L34: - | N34: - | P34: Local trancport | R34: 46195 | T34: =R34-K34 -> 20 | U34: Approved | V34: - | W34: -
A35: 30 | B35: SUD1-02-011 | C35: SIC-ENG-M-SUE-1060 | D35: Switchgears - (RMUs) | E35: Electrical | F35: Long Lead Items | G35: 26.11.00 | H35: Unit | I35: 5 | K35: 46203 | L35: - | P35: Local trancport | R35: 46211 | T35: 18 | U35: Approved | V35: - | W35: 1 | X35: Delivered
A36: 31 | B36: SUD1-02-011 | C36: SIC-ENG-M-SUE-1070 | D36: Unit Substation | E36: Electrical | F36: Long Lead Items | G36: 26.11.00 | H36: Unit | I36: 5 | J36: 5 | K36: 46205 | L36: - | P36: Local trancport | R36: 46238 | T36: =R36-K36 -> 33 | U36: Not submitted | V36: - | W36: -
A37: 32 | B37: SUD1-02-011 | C37: SIC-ENG-M-SUE-1080 | D37: Lighting Panels | E37: Electrical | F37: Long Lead Items | G37: 26 24 16 | H37: Unit | I37: 5 | J37: 5 | K37: 46219 | L37: - | N37: MEG manefacture | P37: Local trancport | R37: 46239 | T37: =R37-K37 -> 20 | U37: Approved | V37: - | W37: -
A38: 33 | B38: SUD1-02-011 | C38: SIC-ENG-M-SUE-1090 | D38: KWH Meter with mounting frame | E38: Electrical | F38: Long Lead Items | G38: 26 24 16 | H38: Unit | I38: 5 | K38: 46219 | L38: - | P38: Local trancport | R38: 46266 | T38: =R38-K38 -> 47 | U38: Not submitted | V38: - | W38: -
A39: 34 | B39: SUD1-02-011 | C39: SIC-ENG-M-SUE-1100 | D39: Main Feeder Pillar | E39: Electrical | F39: Long Lead Items | G39: 26 24 16 | H39: Unit | I39: 5 | K39: 46219 | L39: - | P39: Local trancport | R39: 46284 | S39: 46184 | T39: =R39-K39 -> 65 | U39: Approved | V39: - | W39: -
A40: 35 | B40: SUD1-02-011 | C40: SIC-ENG-M-SUE-1110 | D40: CCTV Poles including all hardwares | E40: Electrical | F40: Long Lead Items | G40: 34 14 19 | H40: Unit | I40: 35 | K40: 46233 | L40: - | N40: - | P40: Local trancport | R40: 46282 | T40: =R40-K40 -> 49 | U40: Approved | V40: - | W40: -
A41: 36 | B41: SUD1-02-011 | C41: SIC-ENG-M-SUE-1120 | D41: CCTV Cables "Power" | E41: Electrical | F41: Long Lead Items | G41: 34 14 19 | H41: m | I41: 7500 | K41: 46240 | L41: - | N41: - | P41: Local trancport | R41: 46282 | T41: =R41-K41 -> 42 | U41: Approved | V41: - | W41: -
A42: 37 | B42: SUD1-02-011 | C42: SIC-ENG-M-SUE-1130 | D42: CCTV Cables "CAT6" | E42: Electrical | F42: Long Lead Items | G42: 34 14 19 | H42: Unit | I42: 195 | K42: 46240 | L42: - | N42: - | P42: Local trancport | R42: 46235 | T42: 25 | U42: Approved | V42: - | W42: -
A43: 38 | B43: SUD1-02-011 | C43: SIC-ENG-M-SUE-1140 | D43: Racks and Patch panels | E43: Electrical | F43: Long Lead Items | G43: 35 14 19 | H43: Unit | I43: 3 | K43: 46254 | L43: - | N43: - | P43: Local trancport | R43: 46284 | T43: =R43-K43 -> 30 | U43: Approved | V43: - | W43: -
A44: 39 | B44: SUD1-02-011 | C44: SIC-ENG-M-SUE-1150 | D44: CCTV System,Servers & WorkStations | E44: Electrical | F44: Long Lead Items | G44: 36 14 19 | H44: Unit | I44: 6 | K44: 46268 | L44: - | N44: - | P44: Local trancport | R44: 46296 | T44: =R44-K44 -> 28 | U44: Approved | V44: - | W44: -
A45: 40 | B45: SUD1-02-011 | C45: SIC-ENG-M-SUE-1160 | D45: Professional 55" Video wall at control room | E45: Electrical | F45: Long Lead Items | G45: 37 14 19 | H45: Unit | I45: 6 | K45: 46282 | L45: - | N45: - | P45: Local trancport | R45: 46303 | T45: =R45-K45 -> 21 | U45: Approved | V45: - | W45: -
A46: 41 | B46: SUD1-02-011 | C46: SIC-ENG-M-SUE-1170 | D46: CCTV Switches | E46: Electrical | F46: Long Lead Items | G46: 38 14 19 | H46: Unit | I46: 27 | K46: 46299 | L46: - | N46: - | P46: Local trancport | R46: 46298 | T46: 19 | U46: Approved | V46: - | W46: -
A47: 42 | B47: SUD1-02-011 | C47: SIC-ENG-M-SUE-1180 | D47: CCTV Wireless P2P bridges | E47: Electrical | F47: Long Lead Items | G47: 39 14 19 | H47: Unit | I47: 27 | K47: 46299 | L47: - | N47: - | P47: Local trancport | R47: 46317 | T47: =R47-K47 -> 18 | U47: Approved | V47: - | W47: -
A48: 43 | B48: SUD1-02-011 | C48: SIC-ENG-M-SUE-1190 | D48: CCTV UPS | E48: Electrical | F48: Long Lead Items | G48: 34 14 19 | H48: Unit | I48: 1 | K48: 46313 | L48: - | N48: - | P48: Local trancport | R48: 46331 | T48: =R48-K48 -> 18 | U48: Approved | V48: - | W48: -
A49: 44 | B49: SUD1-02-011 | C49: SIC-ENG-M-SUE-1200 | D49: CCTV Solar System | E49: Electrical | F49: Long Lead Items | G49: 33 14 19 | H49: Unit | I49: 2 | K49: 46327 | N49: - | P49: Local trancport | R49: 46347 | T49: =R49-K49 -> 20 | U49: Approved | V49: - | W49: -
R64362: =+#REF!+25 -> #REF!
A1048537: Y

Sheet EV-Chart Data
B2: Baseline Plan | E2: Revised / Recovery Plan | H2: Earned Value | K2: Gross Paid Value | N2: Forecast | Q2: Actual/Fcst vs Plan
A3: Month | B3: Monthly | C3: Cum | D3: % | E3: Monthly | F3: Cum | G3: % | H3: Monthly | I3: Cum | J3: % | K3: Monthly | L3: Cum | M3: % | N3: Monthly | O3: C um | Q3: Month | R3: Cum
A4: 46028 | C4: =B4 -> 0 | D4: =C4/$C$22 -> 0 | H4: =I4 -> 0 | I4: 0 | J4: =I4/C$22 -> 0 | K4: 0 | L4: =K4 -> 0 | M4: 0 | N4: =O4 -> 0 | O4: 0 | Q4: =H4-B4 -> 0 | R4: =Q4 -> 0 | T4: Actuals thru previous month
A5: 46059 | B5: 5363766 | C5: =C4+B5 -> 5363766 | D5: =C5/$C$22 -> 0.03180799 | H5: =I5-I4 -> 1803473 | I5: 1803473 | J5: =I5/C$22 -> 0.010694883 | K5: 0 | L5: =L4+K5 -> 0 | M5: 0 | N5: =O5-O4 -> 1803473 | O5: 1803473 | Q5: =H5-B5 -> -3560293 | R5: =R4+Q5 -> -3560293
A6: 46087 | B6: 573441 | C6: =C5+B6 -> 5937207 | D6: =C6/$C$22 -> 0.035208586 | H6: =I6-I5 -> 4942335 | I6: 6745808 | J6: =I6/C$22 -> 0.04000372 | K6: 0 | L6: =L5+K6 -> 0 | M6: 0 | N6: =O6-O5 -> 4942335 | O6: 6745808 | Q6: =H6-B6 -> 4368894 | R6: =R5+Q6 -> 808601
A7: 46118 | B7: 657064 | C7: =C6+B7 -> 6594271 | D7: =C7/$C$22 -> 0.039105081 | H7: =I7-I6 -> 1294293 | I7: 8040101 | J7: =I7/C$22 -> 0.047679084 | K7: 0 | L7: =K7+L6 -> 0 | M7: 0 | N7: =O7-O6 -> 1294293 | O7: 8040101 | Q7: =N7-B7 -> 637229 | R7: =R6+Q7 -> 1445830
A8: 46148 | B8: 6765952 | C8: =C7+B8 -> 13360223 | D8: =C8/$C$22 -> 0.079228258 | H8: =I8-I7 -> 5023481 | I8: 13063582 | J8: =I8/C$22 -> 0.077469129 | K8: 0 | L8: =K8+L7 -> 0 | M8: 0 | N8: =O8-O7 -> 5023481 | O8: 13063582 | Q8: =N8-B8 -> -1742471 | R8: =R7+Q8 -> -296641 | T8: Forecast current and future months
A9: 46179 | B9: 15078567 | C9: =C8+B9 -> 28438790 | D9: =C9/$C$22 -> 0.16864657 | H9: =I9-I8 -> 21674992 | I9: 34738574 | J9: =I9/C$22 -> 0.2060053 | K9: 0 | L9: =K9+L8 -> 0 | M9: 0 | N9: =O9-O8 -> 21674992 | O9: 34738574 | Q9: =N9-B9 -> 6596425 | R9: =R8+Q9 -> 6299784
A10: 46209 | B10: 13666374 | C10: =C9+B10 -> 42105164 | D10: =C10/$C$22 -> 0.24969035 | H10: =I10-I9 -> 11876148 | I10: 46614722 | J10: =I10/C$22 -> 0.27643275 | K10: 0 | L10: =K10+L9 -> 0 | M10: 0 | N10: =O10-O9 -> 11876148 | O10: 46614722 | Q10: =N10-B10 -> -1790226 | R10: =R9+Q10 -> 4509558
A11: 46240 | B11: 17215276 | C11: =C10+B11 -> 59320440 | D11: =C11/$C$22 -> 0.35177969 | H11: =I11-I10 -> 15462572 | I11: 62077294 | J11: =I11/C$22 -> 0.36812828 | K11: 0 | L11: =K11+L10 -> 0 | M11: 0 | N11: =O11-O10 -> 15462572 | O11: 62077294 | Q11: =N11-B11 -> -1752703.7 | R11: =R10+Q11 -> 2756854.3
A12: 46271 | B12: 18831769 | C12: =C11+B12 -> 78152209 | D12: =C12/$C$22 -> 0.46345509 | H12: =I12-I11 -> 11072027 | I12: 73149321 | J12: =I12/C$22 -> 0.43378716 | K12: 0 | L12: =K12+L11 -> 0 | M12: 0 | N12: =O12-O11 -> 11072027 | O12: 73149321 | P12: =O12/$C$22 -> 0.43378716 | Q12: =N12-B12 -> -7759742.5 | R12: =R11+Q12 -> -5002888.2
A13: 46301 | B13: 16883223 | C13: =C12+B13 -> 95035432 | D13: =C13/$C$22 -> 0.5635753 | H13: 0 | N13: =O13-O12 -> 16883223 | O13: 90032544 | P13: =O13/$C$22 -> 0.53390738 | Q13: =N13-B13 -> 0 | R13: =R12+Q13 -> -5002888.2
A14: 46332 | B14: 21549951 | C14: =C13+B14 -> 116585383 | D14: =C14/$C$22 -> 0.69136996 | H14: 0 | N14: =O14-O13 -> 21549951 | O14: 1.1158249e+08 | P14: =O14/$C$22 -> 0.66170203 | Q14: =N14-B14 -> 0 | R14: =R13+Q14 -> -5002888.2
A15: 46362 | B15: 14180877 | C15: =C14+B15 -> 130766260 | D15: =C15/$C$22 -> 0.77546482 | H15: 0 | N15: =O15-O14 -> 14180877 | O15: 1.2576337e+08 | P15: =O15/$C$22 -> 0.7457969 | Q15: =N15-B15 -> 0 | R15: =R14+Q15 -> -5002888.2
A16: 46393 | B16: 7380570 | C16: =C15+B16 -> 138146830 | D16: =C16/$C$22 -> 0.81923278 | H16: 0 | N16: =O16-O15 -> 7380570 | O16: 1.3314394e+08 | P16: =O16/$C$22 -> 0.78956486 | Q16: =N16-B16 -> 0 | R16: =R15+Q16 -> -5002888.2
A17: 46424 | B17: 5035339 | C17: =C16+B17 -> 143182169 | D17: =C17/$C$22 -> 0.84909315 | H17: 0 | N17: =O17-O16 -> 5035339 | O17: 1.3817928e+08 | P17: =O17/$C$22 -> 0.81942522 | Q17: =N17-B17 -> 0 | R17: =R16+Q17 -> -5002888.2
A18: 46452 | B18: 2950780 | C18: =C17+B18 -> 146132949 | D18: =C18/$C$22 -> 0.86659174 | H18: 0 | N18: =O18-O17 -> 2950780 | O18: 1.4113006e+08 | P18: =O18/$C$22 -> 0.83692382 | Q18: =N18-B18 -> 0 | R18: =R17+Q18 -> -5002888.2
A19: 46483 | B19: 12729609 | C19: =C18+B19 -> 158862558 | D19: =C19/$C$22 -> 0.94208036 | H19: 0 | N19: =O19-O18 -> 12729609 | O19: 1.5385967e+08 | P19: =O19/$C$22 -> 0.91241243 | Q19: =N19-B19 -> 0 | R19: =R18+Q19 -> -5002888.2
A20: 46513 | B20: 4484392 | C20: =C19+B20 -> 163346950 | D20: =C20/$C$22 -> 0.96867352 | H20: 0 | N20: =O20-O19 -> 4484392 | O20: 1.5834406e+08 | P20: =O20/$C$22 -> 0.9390056 | Q20: =N20-B20 -> 0 | R20: =R19+Q20 -> -5002888.2
A21: 46544 | B21: 4640187 | C21: =C20+B21 -> 167987137 | D21: =C21/$C$22 -> 0.99619057 | H21: 0 | N21: =O21-O20 -> 9643075.2 | O21: 167987137 | P21: =O21/$C$22 -> 0.99619057 | Q21: =N21-B21 -> 5002888.2 | R21: =R20+Q21 -> 0
A22: 46574 | B22: 642382 | C22: =C21+B22 -> 168629519 | D22: =C22/$C$22 -> 1 | H22: 0 | N22: =O22-O21 -> 642382 | O22: 168629519 | P22: =O22/$C$22 -> 1 | Q22: =N22-B22 -> 0 | R22: =R21+Q22 -> 0 | U22: Extended Duration
B23: UPDATE ONLY YELLOW PORTION FROM PRIMAVERA EXPORT, IF NEEDED, EXTEND YELLOW PORTION BASED ON SCHEDULE.
O24: =C22-O22 -> 0 | P24: 79968099
E25: 46614722 | F25: 330920.4 | O25: =N12+O24 -> 11072027
O26: =N10+O24 -> 11876148
D27: 52626416 | E27: 393637.3 | L27: =O22-C22 -> 0
N28: =N21+O24 -> 9643075.2 | O28: 79968099 | P28: =O28+O24 -> 79968099
I29: 0 | L29: =N14-L27 -> 21549951
I30: 1803473 | K30: 21549951 | O30: 0 | Q30: 22625723 | R30: 216225
F31: 52626416 | I31: 6745808 | N31: 16883223 | O31: 1803473
B32: 73149321 | C32: 446959 | F32: 54442306 | I32: 8040101 | K32: =K30+O24 -> 21549951 | L32: 8193506.6 | O32: 6745808
F33: 52626416 | I33: 13063582 | N33: =N31+O24 -> 16883223 | O33: 8040101
B34: 71439448 | C34: 443300 | I34: 34738574 | O34: 13063582
I35: 46614722 | O35: 34738574
I36: 62077294 | O36: 46614722
C37: 64352049 | D37: 464373 | I37: 73149321 | L37: =N21+O24 -> 9643075.2 | O37: 62077294
O38: 73149321
O39: 90032544
C40: 64955814 | D40: 471179 | O40: 1.1158249e+08
O41: 1.2576337e+08
F42: =G39-G40 -> 0 | O42: 1.3314394e+08
O43: 1.3817928e+08
O44: 1.4113006e+08
O45: 1.5385967e+08
O46: 1.5834406e+08
O47: 167987137
O48: 168629519

Sheet Physical-Chart Data
B2: Baseline Plan | E2: Revised / Recovery Plan | H2: Earned Effort % | K2: Forecast | N2: Achieved/Fcst vs Plan
A3: Week | B3: Monthly Effort | C3: Cum Effort | D3: Plan Wt.% | E3: MonthlyEffort | F3: Cum Effort | G3: Plan Wt.% | H3: Monthly Wt. | I3: Cum Wt. | J3: Achieved Wt.% | K3: Monthly Wt. | L3: Cum Wt. | M3: Wt.% | N3: Monthly Wt. | O3: Cum Wt.
A4: 46028 | B4: 29295 | C4: 29295 | D4: =C4/C$22 -> 0.025714421 | H4: 0 | I4: 0 | J4: =I4/C$22 -> 0 | N4: =K4-B4 -> -29295 | O4: =N4 -> -29295 | Q4: Actuals thru previous month
A5: 46059 | B5: 63408 | C5: 92703 | D5: =C5/C$22 -> 0.081372384 | H5: =I5-I4 -> 9176 | I5: 9176 | J5: =I5/C$22 -> 0.0080544642 | K5: =L5-L4 -> 9176 | L5: 9176 | N5: =K5-B5 -> -54232 | O5: =O4+N5 -> -83527
A6: 46087 | B6: 6723 | C6: 99426 | D6: =C6/C$22 -> 0.087273666 | H6: =I6-I5 -> 95495 | I6: 104671 | J6: =I6/C$22 -> 0.091877596 | K6: =L6-L5 -> 95495 | L6: 104671 | N6: =K6-B6 -> 88772 | O6: =O5+N6 -> 5245
A7: 46118 | B7: 22044 | C7: 121470 | D7: =C7/C$22 -> 0.10662334 | H7: =I7-I6 -> 5885 | I7: 110556 | J7: =I7/C$22 -> 0.097043302 | K7: =L7-L6 -> 5885 | L7: 110556 | N7: =K7-B7 -> -16159 | O7: =O6+N7 -> -10914
A8: 46148 | B8: 35051 | C8: 156521 | D8: =C8/C$22 -> 0.13739023 | H8: =I8-I7 -> 46824 | I8: 157380 | J8: =I8/C$22 -> 0.13814424 | K8: =L8-L7 -> 46824 | L8: 157380 | N8: =K8-B8 -> 11773 | O8: =O7+N8 -> 859 | Q8: Forecast current and future months
A9: 46179 | B9: 66568 | C9: 223089 | D9: =C9/C$22 -> 0.19582197 | H9: =I9-I8 -> 115472 | I9: 272852 | J9: =I9/C$22 -> 0.23950269 | K9: =L9-L8 -> 115472 | L9: 272852 | N9: =K9-B9 -> 48904 | O9: =O8+N9 -> 49763
A10: 46209 | B10: 58517 | C10: 281606 | D10: =C10/C$22 -> 0.24718673 | H10: =I10-I9 -> 58068.4 | I10: 330920.4 | J10: =I10/C$22 -> 0.29047368 | K10: =L10-L9 -> 58068.4 | L10: 330920.4 | N10: =K10-B10 -> -448.6 | O10: =O9+N10 -> 49314.4
A11: 46240 | B11: 63858 | C11: 345464 | D11: =C11/C$22 -> 0.30323969 | H11: =I11-I10 -> 59915 | I11: 390835.4 | J11: =I11/C$22 -> 0.34306558 | K11: =L11-L10 -> 59915 | L11: 390835.4 | N11: =K11-B11 -> -3943 | O11: =O10+N11 -> 45371.4
A12: 46271 | B12: 70181 | C12: 415645 | D12: =C12/C$22 -> 0.36484283 | H12: =I12-I11 -> 56123.6 | I12: 446959 | J12: =I12/C$22 -> 0.39232947 | K12: =L12-L11 -> 56123.6 | L12: 446959 | M12: =L12/C22 -> 0.39232947 | N12: =K12-B12 -> -14057.4 | O12: =O11+N12 -> 31314
A13: 46301 | B13: 87930 | C13: 503575 | D13: =C13/C$22 -> 0.44202559 | H13: 0 | K13: =L13-L12 -> 56616 | L13: 503575 | M13: =L13/L$22 -> 0.44202559 | N13: =K13-B13 -> -31314 | O13: =O12+N13 -> 0
A14: 46332 | B14: 94267 | C14: 597842 | D14: =C14/C$22 -> 0.52477081 | K14: =L14-L13 -> 94267 | L14: 597842 | M14: =L14/L$22 -> 0.52477081 | N14: =K14-B14 -> 0 | O14: =O13+N14 -> 0
A15: 46362 | B15: 90588 | C15: 688430 | D15: =C15/C$22 -> 0.6042867 | K15: =L15-L14 -> 90588 | L15: 688430 | M15: =L15/L$22 -> 0.6042867 | N15: =K15-B15 -> 0 | O15: =O14+N15 -> 0
A16: 46393 | B16: 86356 | C16: 774786 | D16: =C16/C$22 -> 0.68008785 | K16: =L16-L15 -> 86356 | L16: 774786 | M16: =L16/L$22 -> 0.68008785 | N16: =K16-B16 -> 0 | O16: =O15+N16 -> 0
A17: 46424 | B17: 86016 | C17: 860802 | D17: =C17/C$22 -> 0.75559055 | K17: =L17-L16 -> 86016 | L17: 860802 | M17: =L17/L$22 -> 0.75559055 | N17: =K17-B17 -> 0 | O17: =O16+N17 -> 0
A18: 46452 | B18: 80671 | C18: 941473 | D18: =C18/C$22 -> 0.82640154 | K18: =L18-L17 -> 80671 | L18: 941473 | M18: =L18/L$22 -> 0.82640154 | N18: =K18-B18 -> 0 | O18: =O17+N18 -> 0
A19: 46483 | B19: 71569 | C19: 1013042 | D19: =C19/C$22 -> 0.88922303 | K19: =L19-L18 -> 71569 | L19: 1013042 | M19: =L19/L$22 -> 0.88922303 | N19: =K19-B19 -> 0 | O19: =O18+N19 -> 0
A20: 46513 | B20: 71175 | C20: 1084216 | D20: =C20/C$22 -> 0.95169779 | K20: =L20-L19 -> 71174 | L20: 1084216 | M20: =L20/L$22 -> 0.95169779 | N20: =K20-B20 -> -1 | O20: =O19+N20 -> -1
A21: 46544 | B21: 38461 | C21: 1122677 | D21: =C21/C$22 -> 0.9854579 | K21: =L21-L20 -> 38461 | L21: 1122677 | M21: =L21/L$22 -> 0.9854579 | N21: =K21-B21 -> 0 | O21: =O20+N21 -> -1
A22: 46574 | B22: 16567 | C22: 1139244 | D22: =C22/C$22 -> 1 | K22: =L22-L21 -> 16567 | L22: 1139244 | M22: =L22/L$22 -> 1 | N22: =K22-B22 -> 0 | O22: =O21+N22 -> -1 | R22: Extended Duration
B23: UPDATE ONLY YELLOW PORTION FROM PRIMAVERA EXPORT, IF NEEDED, EXTEND YELLOW PORTION BASED ON SCHEDULE.
K28: =C22-L22 -> 0 | L28: =C22-L22 -> 0
I29: 330920.4
L30: =K12+L28 -> 56123.6 | M30: 434980.72 | N30: =M30+L28 -> 434980.72
H31: 364039.9
G34: 443300
D35: 9176 | K35: =K13-K36 -> 56616
D36: 104671 | K36: =L22-C22 -> 0
D37: 110556
D38: 157380
D39: 272852 | J39: 9176
D40: 330920.4 | J40: 104671
D41: 455835.4 | J41: 110556
D42: 485514 | J42: 157380
J43: 272852
J44: 330920.4
J45: 455835
J46: 485514
J47: 540160
J48: 608020
J49: 706653
J50: 793681
J51: 866330
J52: 948888
J53: 1023803
J54: 1100929
... J56: 1151844

Sheet Testing
A1: Testing and Commissioning
A2: Item | B2: Planned Start Date | C2: Planned Finish Date | D2: Forecast Start Date | E2: Forecast Finish Date | F2: Actual Start Date | G2: Actual Finish Date | H2: % Completed | I2: Open Comments | J2: Closed Comments
A3: Zone A | B3: 46399 | C3: 46569 | D3: 46380 | E3: 46573
A4: Road works | B4: 46495 | C4: 46499 | D4: 46539 | E4: 46544 | H4: 0 | I4: 0 | J4: 0
A5: Network work | B5: 46512 | C5: 46531 | D5: 46553 | E5: 46567 | H5: 0 | I5: 0 | J5: 0
A6: Sewage Network | B6: 46491 | C6: 46505 | D6: 46506 | E6: 46520 | H6: 0 | I6: 0 | J6: 0
A7: TSE Network | B7: 46520 | C7: 46542 | D7: 46548 | E7: 46573 | H7: 0 | I7: 0 | J7: 0
A8: Potable Network | B8: 46534 | C8: 46549 | D8: 46496 | E8: 46511 | H8: 0 | I8: 0 | J8: 0
A9: Electrical Network | B9: 46415 | C9: 46428 | D9: 46489 | E9: 46499 | H9: 0 | I9: 0 | J9: 0
A10: Landscape & Irrigation Network | B10: 46563 | C10: 46569 | D10: 46566 | E10: 46573 | H10: 0 | I10: 0 | J10: 0
A11: CCTV Medium voltage works | B11: 46399 | C11: 46410 | D11: 46380 | E11: 46392 | H11: 0 | I11: 0 | J11: 0
A12: Zone G | B12: 46399 | C12: 46569 | D12: 46380 | E12: 46573
A13: Road works | B13: 46495 | C13: 46499 | D13: 46539 | E13: 46544 | H13: 0 | I13: 0 | J13: 0
A14: Network work | B14: 46512 | C14: 46531 | D14: 46553 | E14: 46567 | H14: 0 | I14: 0 | J14: 0
A15: Sewage Network | B15: 46491 | C15: 46505 | D15: 46506 | E15: 46520 | H15: 0 | I15: 0 | J15: 0
A16: TSE Network | B16: 46520 | C16: 46542 | D16: 46548 | E16: 46573 | H16: 0 | I16: 0 | J16: 0
A17: Potable Network | B17: 46534 | C17: 46549 | D17: 46496 | E17: 46511 | H17: 0 | I17: 0 | J17: 0
A18: Electrical Network | B18: 46415 | C18: 46428 | D18: 46489 | E18: 46499 | H18: 0 | I18: 0 | J18: 0
A19: Landscape & Irrigation Network | B19: 46563 | C19: 46569 | D19: 46566 | E19: 46573 | H19: 0 | I19: 0 | J19: 0
A20: CCTV Medium voltage works | B20: 46399 | C20: 46410 | D20: 46380 | E20: 46392 | H20: 0 | I20: 0 | J20: 0
A21: Total | H21: =AVERAGE(H16:H20) -> 0 | I21: =SUM(I16:I20) -> 0 | J21: =SUM(J16:J20) -> 0

Sheet Conclusion
A1: تقدم سير مشروع تطوير شبكات البنية التحتية في مدينة سدير للصناعة والأعمال – المرحلة الثانية – الجزء الثاني
A2: معلومات المشروع | F2: نطاق المشروع | L2: موقع المشروع
A3: المقاول | B3: شركة تطوير التقنية للمقاولات | C3: الاستشاري | D3: شركة ايجيس السعودية للاستشارات | F3: البند | G3: الكمية الكلية | H3: الكمية المنفذة | I3: الكمية المتبقية | J3: نسبة المنفذ
A4: تاريخ استلام الموقع | B4: 06-01-2026 م | C4: مدة التنفيذ | D4: 18 شهرًا ميلاديًا | F4: أعمال الطرق والرصف (ROD) | G4: 18,252 م | H4: 0 | I4: 0 | J4: -
A5: بداية العقد | B5: من تاريخ استلام الموقع | C5: قيمة العقد (شامل ضريبة القيمة المضافة) | D5: 193,923,948.00 ريال | F5: أعمال شبكة مياة الشرب (WAT) | G5: 18,021 م | H5: 0 | I5: 0 | J5: -
A6: نسبة الإنجاز المخطط له | B6: 0 | C6: نسبة الإنجاز الفعلي | D6: 0.0003 | F6: أعمال شبكة المياه المعالجة (TSE) | G6: 16,141 م | H6: 0 | I6: 0 | J6: -
C7: =C10+C11+C12+C13+C14+C15+C16+C17 -> 1.6862952e+08 | F7: أعمال شبكة الصرف الصحي (SEW) | G7: 13,040 م | H7: 0 | I7: 0 | J7: -
A8: ملخص جدول الكميات | F8: أعمال شبكة صرف مياه الأمطار (STR) | G8: 13,600 م | H8: 0 | I8: 0 | J8: -
A9: مكونات المشروع | C9: التكلفة (غير شامل ضريبة القيمة المضافة) | D9: النسبة الاجمالية | F9: أعمال شبكة الري والمناظر الطبيعية (IRR) | G9: 29,570 م | H9: 0 | I9: 0 | J9: -
A10: أعمال الطرق | C10: 88002863 | D10: =C10/$C$7 -> 0.52187104 | F10: أعمال الشبكة الكهربائية (ELE) | G10: 51,500 م | H10: 0 | I10: 0 | J10: -
A11: شبكة تصريف مياه الأمطار | C11: 25408257 | D11: =C11/$C$7 -> 0.15067502 | F11: أعمال المراقبة بالكاميرات (CCTV) | G11: 125 كاميرا | H11: 0 | I11: 0 | J11: -
A12: شبكة الصرف الصحي | C12: 7071026.5 | D12: =C12/$C$7 -> 0.041932317 | F12: ملخص التوريدات | L12: تقدم أعمال layout
A13: شبكة المياه المعالجة (TSE) | C13: 4148179.8 | D13: =C13/$C$7 -> 0.024599369 | F13: البند | G13: الكمية الكلية | H13: الكمية المورده | I13: الكمية المتبقية | J13: نسبة التوريد
A14: شبكة مياه الشرب | C14: 7780464.9 | D14: =C14/$C$7 -> 0.0461394
A15: الأعمال الكهربائية | C15: 20085705 | D15: =C15/$C$7 -> 0.11911144
A16: أعمال تنسيق الموقع والري | C16: 6827173.9 | D16: =C16/$C$7 -> 0.040486232
A17: أعمال كاميرات المراقبة (CCTV) | C17: 9305849.7 | D17: =C17/$C$7 -> 0.055185175
A18: معالم البرنامج الزمني
A19: البند | C19: التاريخ حسب الجدول الزمني | D19: ملاحظة
A20: Mobilization Finish Milestone | C20: 46058 | D20: Finish
A21: Baseline Submission Finish Milestone | C21: 46058 | D21: UG | F21: التحديات والعوائق
A22: Technical Submittals Finish Milestone | C22: 46086 | D22: UG | F22: 1-
A23: Quality Lap Finish Milestone | C23: 46058 | D23: Finish | F23: 2-
A24: RBF Finish Milestone | C24: 46058 | D24: Finish | F24: 3-
A25: All Works Finish Milestone | C25: 46573 | D25: UG | F25: 4-
F26: 5-
F27: 6-
F28: 7-

Sheet Codes
C3: Status List
C4: Approved | E4: Y
C5: Pending | E5: N | K5: (Manhours)
C6: Potential | K6: (Mandays)
C10: Phase | D10: Stage | F10: Stage | H10: Status | J10: Score
J11: Low | K11: Contractor | L11: Active
C12: Launch | D12: LOA | F12: LOA | H12: Active | J12: Medium | K12: CM | L12: Expired
C13: Launch | D13: Kick-off Meeting | F13: Kick-off Meeting | H13: On Hold | J13: High | K13: PgM | L13: Occurred
C14: Launch | D14: Site Handover | H14: Terminated | K14: Modon | L14: Pending
C15: Launch | D15: Mobilization | F15: Mobilization | G15: Initial staff and equipment in place, ready to start production | H15: Terminated, Closed | K15: Other
C16: Execution | D16: Construction | F16: Execution | G16: Tender Documents Issued | H16: Substantial Complete | I16: Initial Handover done at site
C17: Execution | D17: T&C | G17: Responses to the OCS completed | H17: Complete | I17: Initial Handover Signed
C18: Execution | D18: Initial Handover | F18: Closeout | G18: Design close-out process complete | H18: Closed | I18: Final Handover done at Site
D19: Warranty Period
D20: Final Handover
B41: Project Status Score
B42: Elements | E42: Max | F42: Score | G42: Planned | H42: Actual | I42: Remarks
B43: SPI (Physical Effort) | E43: 1 | F43: =IFERROR('Weekly Progress Report'!$Z$43,1) -> 1.1002149 | G43: No Entry Required
B44: SPI (Cost) | E44: 1 | F44: =IFERROR('Weekly Progress Report'!$N$43,1) -> 1.3525189 | G44: No Entry Required
B45: On Schedule -Active | E45: 1 | F45: =IFERROR(('Weekly Progress Report'!G103+'Weekly Progress Report'!H103)/'Weekly Progress Report'!F103,1) -> 0.88888889 | G45: No Entry Required | K45: =12/20 -> 0.6
B46: Manpower Availability | E46: 1 | F46: =IFERROR('Weekly Progress Report'!N107/'Weekly Progress Report'!M107,1) -> 2.0905923 | G46: No Entry Required
B47: Major Equipment Availability | E47: 1 | F47: =IFERROR('Weekly Progress Report'!U107/'Weekly Progress Report'!T107,1) -> 2.038835 | G47: No Entry Required
B48: Billing % Compared to Planned | E48: 1 | F48: =IFERROR('Weekly Progress Report'!R89/'Weekly Progress Report'!R87,1) -> 0 | G48: No Entry Required
B49: Safety Score | E49: 1 | F49: =#REF! -> #REF! | G49: No Entry Required
B50: Quality Score | E50: 1 | F50: =[39]Quality.!AC10 -> 0.95068966 | G50: No Entry Required
