Workbook
Name _1B.05.M.010.0010: #REF!
Name _1B.05.M.010.0010: #REF!
Name _1B.05.M.010.0010: #REF!
Name _1B.05.M.010.0050: #REF!
Name _1B.05.M.010.0050: #REF!
Name _1B.05.M.010.0050: #REF!
Name _1B.05.M.0100.0010: #REF!
Name _1B.05.M.0100.0010: #REF!
Name _1B.05.M.020.0010: #REF!
Name _1B.05.M.020.0010: #REF!
Name _1B.05.M.020.0020: #REF!
Name _1B.05.M.020.0020: #REF!
Name _1B.05.M.020.0030: #REF!
Name _1B.05.M.020.0030: #REF!
Name _1B.05.M.020.0040: #REF!
Name _1B.05.M.020.0040: #REF!
Name _1B.05.M.030.0010: #REF!
Name _1B.05.M.030.0010: #REF!
Name _1B.05.M.030.0020: #REF!
Name _1B.05.M.030.0020: #REF!
Name _1B.05.M.040.0010: #REF!
Name _1B.05.M.040.0010: #REF!
Name _1B.05.M.050.0010: #REF!
Name _1B.05.M.050.0010: #REF!
Name _1B.05.M.050.0020: #REF!
Name _1B.05.M.050.0020: #REF!
Name _1B.05.M.050.0030: #REF!
Name _1B.05.M.050.0030: #REF!
Name _1B.05.M.060.0020: #REF!
Name _1B.05.M.060.0020: #REF!
Name _1B.05.M.060.0100: #REF!
Name _1B.05.M.060.0100: #REF!
Name _1B.05.M.070.0010: #REF!
Name _1B.05.M.070.0010: #REF!
Name _1B.05.M.070.0020: #REF!
Name _1B.05.M.070.0020: #REF!
Name _1B.05.M.070.0030: #REF!
Name _1B.05.M.070.0030: #REF!
Name _1B.05.M.070.0040: #REF!
Name _1B.05.M.070.0040: #REF!
Name _1B.05.M.070.0050: #REF!
Name _1B.05.M.070.0050: #REF!
Name _1B.05.M.080.0010: #REF!
Name _1B.05.M.080.0010: #REF!
Name _1B.05.M.090.0010: #REF!
Name _1B.05.M.090.0010: #REF!
Name _1B.09.P.010.0010: #REF!
Name _1B.09.P.010.0010: #REF!
Name _1B.09.P.010.0020: #REF!
Name _1B.09.P.010.0020: #REF!
Name _1B.09.P.010.0030: #REF!
Name _1B.09.P.010.0030: #REF!
Name _1B.09.P.010.0040: #REF!
Name _1B.09.P.010.0040: #REF!
Name _1B.09.P.010.0050: #REF!
Name _1B.09.P.010.0050: #REF!
Name _1B.09.P.010.0060: #REF!
Name _1B.09.P.010.0060: #REF!
Name _1B.09.P.010.0070: #REF!
Name _1B.09.P.010.0070: #REF!

Sheet DB
A1: ='Weekly Progress Report'!$A$1 -> MODON - Weekly Progress Report - Construction Projects
B2: ='Weekly Progress Report'!$A$2 -> Contract General Information | J2: ='Weekly Progress Report'!G2 -> Key Dates | U2: ='Weekly Progress Report'!$M$2 -> Cost Summary (SR) | AD2: ='Weekly Progress Report'!$U$2 -> Performance Summary | AP2: ='Weekly Progress Report'!A52 -> Shop Drawings | AT2: ='Weekly Progress Report'!A62 -> Material Approval | AW2: ='Weekly Progress Report'!A71 -> Procurement Summary | BD2: ='Weekly Progress Report'!L52 -> Quality Reports | BT2: ='Weekly Progress Report'!L61 -> Key Submittals Approval Status | CD2: ='Weekly Progress Report'!L67 -> Invoices Summary | CR2: ='Weekly Progress Report'!L75 -> Resources at Site | CY2: ='Weekly Progress Report'!W52 -> Safety Statistics | FK2: ='Weekly Progress Report'!A80 -> Primavera P6 Schedule Status | FS2: ='Weekly Progress Report'!A93 -> Weekly Prgoress Photos
A3: ='Weekly Progress Report'!AF1 -> Data Date | B3: ='Weekly Progress Report'!A3 -> Project Name | C3: ='Weekly Progress Report'!A4 -> Project ID | D3: ='Weekly Progress Report'!A5 -> Contractor | E3: ='Weekly Progress Report'!A6 -> Consultant | F3: ='Weekly Progress Report'!D4 -> Stage | G3: ='Weekly Progress Report'!D5 -> Status | H3: ='Weekly Progress Report'!D6 -> Modon PM | I3: ='Weekly Progress Report'!AA2 -> Project Scope | J3: ='Weekly Progress Report'!G3 -> Contract Award | K3: ='Weekly Progress Report'!G4 -> Contract Sign | L3: ='Weekly Progress Report'!G5 -> Site Handover | M3: ='Weekly Progress Report'!G6 -> Original Completion | N3: ='Weekly Progress Report'!$I$3 -> Contract Award (Hijri) | O3: ='Weekly Progress Report'!$I$4 -> Contract Sign (Hijri) | P3: ='Weekly Progress Report'!$I$5 -> Site Handover (Hijri) | Q3: ='Weekly Progress Report'!$I$6 -> Original Completion (Hijri) | R3: ='Weekly Progress Report'!$K$3 -> Revised Completion | S3: ='Weekly Progress Report'!$K$4 -> Committed Completion | T3: ='Weekly Progress Report'!$K$5 -> Forecast Completion | U3: ='Weekly Progress Report'!$M$3 -> Original Contract Value | V3: ='Weekly Progress Report'!$M$4 -> Revised Contract Value | W3: ='Weekly Progress Report'!$M$5 -> Estimate At Completion Value | X3: ='Weekly Progress Report'!$M$6 -> Potential Changes | Y3: ='Weekly Progress Report'!$Q$3 -> O&M Value (if any) | Z3: ='Weekly Progress Report'!$Q$4 -> Submitted Invoices (Gross Value) | AA3: ='Weekly Progress Report'!$Q$5 -> Penalities | AB3: ='Weekly Progress Report'!$Q$6 -> FIR Value (THIS WEEK) | AC3: Original Plan Value | AD3: ='Weekly Progress Report'!$U$3 -> Plan Value | AE3: ='Weekly Progress Report'!$U$4 -> Earn Value | AF3: ='Weekly Progress Report'!$W$3 -> Phys. Plan Value | AG3: ='Weekly Progress Report'!$W$4 -> Phys. Earn Value | AH3: ='Weekly Progress Report'!$Y$3 -> Quality Score | AI3: ='Weekly Progress Report'!$Y$5 -> Safety Score | AJ3: Weekly PV (SAR) | AK3: Weekly EV (SAR) | AL3: Weekly PV % | AM3: Weekly PV % | AN3: Weekly Phys PV% | AO3: Weekly Phys PV% | AP3: Total SD Planned | AQ3: SD Remaining | AR3: SD Pending | AS3: Total SD Submittals | AT3: Planned Materials Approv | AU3: Material Pending Approval | AV3: Materila Total Submittals | AW3: ='Weekly Progress Report'!C72 -> Total Materials | AX3: ='Weekly Progress Report'!D72 -> Total Number of P.O. | AY3: ='Weekly Progress Report'!E72 -> Actual P.O. To Date | AZ3: ='Weekly Progress Report'!F72 -> Remaining P.O | BA3: ='Weekly Progress Report'!G72 -> Material on Site | BB3: ='Weekly Progress Report'!H72 -> Remaining Materials | BC3: ='Weekly Progress Report'!I72 -> Material Delivery Completion (Date) | BD3: ="NCR "&'Weekly Progress Report'!N53 -> NCR Issued | BE3: ="NCR "&'Weekly Progress Report'!O53 -> NCR Closed | BF3: ="NCR "&'Weekly Progress Report'!P53 -> NCR Pending | BG3: ="NCR "&'Weekly Progress Report'!Q53 -> NCR Avg. Closing (Days) | BH3: ="SIR "&'Weekly Progress Report'!N53 -> SIR Issued | BI3: ="SIR "&'Weekly Progress Report'!O53 -> SIR Closed | BJ3: ="SIR "&'Weekly Progress Report'!P53 -> SIR Pending | BK3: ="SIR "&'Weekly Progress Report'!Q53 -> SIR Avg. Closing (Days) | BL3: ="MIR "&'Weekly Progress Report'!N53 -> MIR Issued | BM3: ="MIR "&'Weekly Progress Report'!O53 -> MIR Closed | BN3: ="MIR "&'Weekly Progress Report'!P53 -> MIR Pending | BO3: ="MIR "&'Weekly Progress Report'!Q53 -> MIR Avg. Closing (Days) | BP3: ="FIR "&'Weekly Progress Report'!N53 -> FIR Issued | BQ3: ="FIR "&'Weekly Progress Report'!O53 -> FIR Closed | BR3: ="FIR "&'Weekly Progress Report'!P53 -> FIR Pending | BS3: ="FIR "&'Weekly Progress Report'!Q53 -> FIR Avg. Closing (Days) | BT3: ='Weekly Progress Report'!L62 -> 1 Quality Plan Approval | BU3: ='Weekly Progress Report'!L63 -> 2 Quality Plan Last Up | BV3: ='Weekly Progress Report'!L64 -> 3 Safety Plan Approval | BW3: ='Weekly Progress Report'!L65 -> 4 Safety Plan Last Up | BX3: ='Weekly Progress Report'!L66 -> 5 Construction Plan Approval | BY3: ='Weekly Progress Report'!Q62 -> 6 Baseline Approval | BZ3: ='Weekly Progress Report'!Q63 -> 7 No of Approved Version of Schedule | CA3: ='Weekly Progress Report'!Q64 -> 8 Last Approved Schedule | CB3: ='Weekly Progress Report'!Q65 -> 9 BOQ Approval Date | CC3: ='Weekly Progress Report'!Q66 -> 10 No of Approved Version of BOQ | CD3: ='Weekly Progress Report'!L68 -> Total Submitted Invoices | CE3: ='Weekly Progress Report'!L69 -> PM Approved Invoices | CF3: ='Weekly Progress Report'!L70 -> No of Paid Invoices | CG3: ='Weekly Progress Report'!L71 -> No of Pending Invoices | CH3: ='Weekly Progress Report'!L72 -> Advance Payment % | CI3: ='Weekly Progress Report'!L73 -> Retention % | CJ3: ='Weekly Progress Report'!L74 -> Deduction / Penalties % | CK3: ='Weekly Progress Report'!O68 -> Submitted Invoices (SAR) | CL3: ='Weekly Progress Report'!O69 -> PM Approved Invoices (SAR) | CM3: ='Weekly Progress Report'!O70 -> Paid Invoices (SAR) | CN3: ='Weekly Progress Report'!O71 -> Last Submitted Period | CO3: ='Weekly Progress Report'!O72 -> Advance Payment (SAR) | CP3: ='Weekly Progress Report'!O73 -> Retention (SAR) | CQ3: ='Weekly Progress Report'!O74 -> Deduction / Penalties (SAR) | CR3: Planned Head Count | CS3: Actual Head Count | CT3: Saudi Staff | CU3: Labor Planned | CV3: Labor Actual | CW3: Equipment Planned | CX3: Equipment Actual | CY3: ="This Week "&'Weekly Progress Report'!X55 -> This Week Total Hours Worked | CZ3: ="This Week "&'Weekly Progress Report'!X56 -> This Week Safe Hours Worked | DA3: ="This Week "&'Weekly Progress Report'!X57 -> This Week LTI | DB3: ="This Week "&'Weekly Progress Report'!X58 -> This Week MTC (Healed w/o Disability) | DC3: ="This Week "&'Weekly Progress Report'!X60 -> This Week MTC (Healed w/ Disability) | DD3: ="This Week "&'Weekly Progress Report'!X61 -> This Week Near Miss | DE3: ="This Week "&'Weekly Progress Report'!X62 -> This Week First Aid Cases | DF3: ="This Week "&'Weekly Progress Report'!X63 -> This Week Fatality | DG3: ="This Week "&'Weekly Progress Report'!X64 -> This Week Fire Incident Cases | DH3: ="This Week "&'Weekly Progress Report'!X65 -> This Week Vehicle Incident | DI3: ="This Week "&'Weekly Progress Report'!X66 -> This Week Property Damages | DJ3: ="This Week "&'Weekly Progress Report'!X67 -> This Week Induction Training | DK3: ="This Week "&'Weekly Progress Report'!X68 -> This Week No.of Internal Training | DL3: ="This Week "&'Weekly Progress Report'!X69 -> This Week No.of Internal Audit | DM3: ="This Week "&'Weekly Progress Report'!X70 -> This Week No. of Toolbox Talks | DN3: ="This Week "&'Weekly Progress Report'!X71 -> This Week Safety Awards/Incentives | DO3: ="This Month "&'Weekly Progress Report'!X55 -> This Month Total Hours Worked | DP3: ="This Month "&'Weekly Progress Report'!X56 -> This Month Safe Hours Worked | DQ3: ="This Month "&'Weekly Progress Report'!X57 -> This Month LTI | DR3: ="This Month "&'Weekly Progress Report'!X58 -> This Month MTC (Healed w/o Disability) | DS3: ="This Month "&'Weekly Progress Report'!X60 -> This Month MTC (Healed w/ Disability) | DT3: ="This Month "&'Weekly Progress Report'!X61 -> This Month Near Miss | DU3: ="This Month "&'Weekly Progress Report'!X62 -> This Month First Aid Cases | DV3: ="This Month "&'Weekly Progress Report'!X63 -> This Month Fatality | DW3: ="This Month "&'Weekly Progress Report'!X64 -> This Month Fire Incident Cases | DX3: ="This Month "&'Weekly Progress Report'!X65 -> This Month Vehicle Incident | DY3: ="This Month "&'Weekly Progress Report'!X66 -> This Month Property Damages | DZ3: ="This Month "&'Weekly Progress Report'!X67 -> This Month Induction Training | EA3: ="This Month "&'Weekly Progress Report'!X68 -> This Month No.of Internal Training | EB3: ="This Month "&'Weekly Progress Report'!X69 -> This Month No.of Internal Audit | EC3: ="This Month "&'Weekly Progress Report'!X70 -> This Month No. of Toolbox Talks | ED3: ="This Month "&'Weekly Progress Report'!X71 -> This Month Safety Awards/Incentives | EE3: ="YTD "&'Weekly Progress Report'!X55 -> YTD Total Hours Worked | EF3: ="YTD "&'Weekly Progress Report'!X56 -> YTD Safe Hours Worked | EG3: ="YTD "&'Weekly Progress Report'!X57 -> YTD LTI | EH3: ="YTD "&'Weekly Progress Report'!X58 -> YTD MTC (Healed w/o Disability) | EI3: ="YTD "&'Weekly Progress Report'!X60 -> YTD MTC (Healed w/ Disability) | EJ3: ="YTD "&'Weekly Progress Report'!X61 -> YTD Near Miss | EK3: ="YTD "&'Weekly Progress Report'!X62 -> YTD First Aid Cases | EL3: ="YTD "&'Weekly Progress Report'!X63 -> YTD Fatality | EM3: ="YTD "&'Weekly Progress Report'!X64 -> YTD Fire Incident Cases | EN3: ="YTD "&'Weekly Progress Report'!X65 -> YTD Vehicle Incident | EO3: ="YTD "&'Weekly Progress Report'!X66 -> YTD Property Damages | EP3: ="YTD "&'Weekly Progress Report'!X67 -> YTD Induction Training | EQ3: ="YTD "&'Weekly Progress Report'!X68 -> YTD No.of Internal Training | ER3: ="YTD "&'Weekly Progress Report'!X69 -> YTD No.of Internal Audit | ES3: ="YTD "&'Weekly Progress Report'!X70 -> YTD No. of Toolbox Talks | ET3: ="YTD "&'Weekly Progress Report'!X71 -> YTD Safety Awards/Incentives | EU3: ="Cum "&'Weekly Progress Report'!X55 -> Cum Total Hours Worked | EV3: ="Cum "&'Weekly Progress Report'!X56 -> Cum Safe Hours Worked | EW3: ="Cum "&'Weekly Progress Report'!X57 -> Cum LTI | EX3: ="Cum "&'Weekly Progress Report'!X58 -> Cum MTC (Healed w/o Disability) | EY3: ="Cum "&'Weekly Progress Report'!X60 -> Cum MTC (Healed w/ Disability) | EZ3: ="Cum "&'Weekly Progress Report'!X61 -> Cum Near Miss | FA3: ="Cum "&'Weekly Progress Report'!X62 -> Cum First Aid Cases | FB3: ="Cum "&'Weekly Progress Report'!X63 -> Cum Fatality | FC3: ="Cum "&'Weekly Progress Report'!X64 -> Cum Fire Incident Cases | FD3: ="Cum "&'Weekly Progress Report'!X65 -> Cum Vehicle Incident | FE3: ="Cum "&'Weekly Progress Report'!X66 -> Cum Property Damages | FF3: ="Cum "&'Weekly Progress Report'!X67 -> Cum Induction Training | FG3: ="Cum "&'Weekly Progress Report'!X68 -> Cum No.of Internal Training | FH3: ="Cum "&'Weekly Progress Report'!X69 -> Cum No.of Internal Audit | FI3: ="Cum "&'Weekly Progress Report'!X70 -> Cum No. of Toolbox Talks | FJ3: ="Cum "&'Weekly Progress Report'!X71 -> Cum Safety Awards/Incentives | FK3: ='Weekly Progress Report'!A83 -> Total Act. | FL3: ='Weekly Progress Report'!B83 -> Not Started | FM3: ='Weekly Progress Report'!C83 -> In Progress | FN3: ='Weekly Progress Report'!D83 -> Completed | FO3: Critical Path Act.Last Week | FP3: Critical Path Act.This Week | FQ3: Failed start Last Week | FR3: Failed start This Week | FS3: ='Weekly Progress Report'!B95 -> 0 | FT3: ='Weekly Progress Report'!D95 -> 0 | FU3: ='Weekly Progress Report'!F95 -> 0 | FV3: ='Weekly Progress Report'!H95 -> 0 | FW3: ='Weekly Progress Report'!J95 -> 0 | FX3: ='Weekly Progress Report'!L95 -> 0 | FY3: ='Weekly Progress Report'!N95 -> 0 | FZ3: ='Weekly Progress Report'!O95 -> 0 | GA3: ='Weekly Progress Report'!P95 -> 0
A4: ='Weekly Progress Report'!AG1 -> 46307 | B4: ='Weekly Progress Report'!B3 -> ADDITIONAL DEVELOPMENT IN TABOUK INDUSTRIAL CITY | C4: ='Weekly Progress Report'!B4 -> TAB1-02-003 | D4: ='Weekly Progress Report'!B5 -> ASAS for Developing & Operating Industrial Cities | E4: ='Weekly Progress Report'!B6 -> EGIS | F4: ='Weekly Progress Report'!E4 -> INFRASTRUCTURE & UTILITIES | G4: ='Weekly Progress Report'!E5 -> Active | H4: ='Weekly Progress Report'!E6 -> ENG/ YAZEED ALRAGABAH | I4: ='Weekly Progress Report'!AA3 -> The project consists of roads works and the POND A which works as a downstream for the storm water wet utility piping network including manholes and catch basins, continued project wet utilities also sewerage GRP piping network with manholes, potable water and firefighting compound HDPE piping network including the installation of valves and fire hydrants and the irrigation water (TSE) network with all valves and the flow meter, dry utility represented in electrical road lighting network - the installation of poles and the LV cables which is connected to the panel board and the 13.8/0.4 K V unit substation. | J4: ='Weekly Progress Report'!H3 -> 45882 | K4: ='Weekly Progress Report'!H4 -> 45900 | L4: ='Weekly Progress Report'!H5 -> 45904 | M4: ='Weekly Progress Report'!H6 -> 46633 | N4: ='Weekly Progress Report'!$J$3 -> 45882 | O4: ='Weekly Progress Report'!$J$4 -> 45900 | P4: ='Weekly Progress Report'!$J$5 -> 45904 | Q4: ='Weekly Progress Report'!$J$6 -> 46633 | R4: ='Weekly Progress Report'!$L$3 -> 46633 | S4: ='Weekly Progress Report'!$L$4 -> 46633 | T4: ='Weekly Progress Report'!$L$5 -> 46662 | U4: ='Weekly Progress Report'!$O$3 -> 140467862 | V4: ='Weekly Progress Report'!$O$4 -> 140467862 | W4: ='Weekly Progress Report'!$O$5 -> 140467862 | X4: ='Weekly Progress Report'!$O$6 -> 0 | Y4: ='Weekly Progress Report'!$S$3 -> 0 | Z4: ='Weekly Progress Report'!$S$4 -> 43497867 | AA4: ='Weekly Progress Report'!$S$5 -> 58000 | AB4: ='Weekly Progress Report'!$S$6 -> 51776131 | AC4: ='Weekly Progress Report'!$J$22 -> 0.63558139 | AD4: ='Weekly Progress Report'!$V$3 -> 0.37308716 | AE4: ='Weekly Progress Report'!$V$4 -> 0.47569888 | AF4: ='Weekly Progress Report'!$X$3 -> 0.3461685 | AG4: ='Weekly Progress Report'!$X$4 -> 0.4987258 | AH4: ='Weekly Progress Report'!$Z$3 -> 0.92982759 | AI4: ='Weekly Progress Report'!$Z$5 -> 0.94565217 | AJ4: ='Weekly Progress Report'!$E$22 -> 504274.59 | AK4: ='Weekly Progress Report'!$F$22 -> 950868.63 | AL4: =AJ4/V4 -> 0.0035899642 | AM4: =AK4/V4 -> 0.0067692967 | AN4: ='Weekly Progress Report'!S22 -> 0.0059462831 | AO4: ='Weekly Progress Report'!T22 -> 0.013252845 | AP4: ='Weekly Progress Report'!C61 -> 300 | AQ4: ='Weekly Progress Report'!I61 -> 0 | AR4: ='Weekly Progress Report'!J61 -> 0 | AS4: ='Weekly Progress Report'!K61 -> 428 | AT4: ='Weekly Progress Report'!C70 -> 0 | AU4: ='Weekly Progress Report'!J70 -> 1 | AV4: ='Weekly Progress Report'!K70 -> 52 | AW4: ='Weekly Progress Report'!C79 -> 29 | AX4: ='Weekly Progress Report'!D79 -> 29 | AY4: ='Weekly Progress Report'!E79 -> 27 | AZ4: ='Weekly Progress Report'!F79 -> 2 | BA4: ='Weekly Progress Report'!G79 -> 45142 | BB4: ='Weekly Progress Report'!H79 -> 12907 | BC4: ='Weekly Progress Report'!I79 -> 0 | BD4: ='Weekly Progress Report'!N56 -> 11 | BE4: ='Weekly Progress Report'!O56 -> 11 | BF4: ='Weekly Progress Report'!P56 -> 0 | BG4: ='Weekly Progress Report'!Q56 -> 5 | BH4: ='Weekly Progress Report'!N57 -> 20 | BI4: ='Weekly Progress Report'!O57 -> 20 | BJ4: ='Weekly Progress Report'!P57 -> 0 | BK4: ='Weekly Progress Report'!Q57 -> 6 | BL4: ='Weekly Progress Report'!N58 -> 223 | BM4: ='Weekly Progress Report'!O58 -> 221 | BN4: ='Weekly Progress Report'!P58 -> 2 | BO4: ='Weekly Progress Report'!Q58 -> 2 | BP4: ='Weekly Progress Report'!N60 -> 6764 | BQ4: ='Weekly Progress Report'!O60 -> 6526 | BR4: ='Weekly Progress Report'!P60 -> 238 | BS4: ='Weekly Progress Report'!Q60 -> 1 | BT4: ='Weekly Progress Report'!O62 -> 45963 | BU4: ='Weekly Progress Report'!O63 -> 45963 | BV4: ='Weekly Progress Report'!O64 -> 45950 | BW4: ='Weekly Progress Report'!O65 -> 45950 | BX4: ='Weekly Progress Report'!O66 -> #REF! | BY4: ='Weekly Progress Report'!U62 -> 45964 | BZ4: ='Weekly Progress Report'!U63 -> 2 | CA4: ='Weekly Progress Report'!U64 -> 45964 | CB4: ='Weekly Progress Report'!U65 -> 0 | CC4: ='Weekly Progress Report'!U66 -> 0 | CD4: ='Weekly Progress Report'!N68 -> 13 | CE4: ='Weekly Progress Report'!N69 -> 9 | CF4: ='Weekly Progress Report'!N70 -> 9 | CG4: ='Weekly Progress Report'!N71 -> 0 | CH4: ='Weekly Progress Report'!N72 -> 0.1 | CI4: ='Weekly Progress Report'!N73 -> 0 | CJ4: ='Weekly Progress Report'!N74 -> 0.00041290584 | CK4: ='Weekly Progress Report'!R68 -> 43497867 | CL4: ='Weekly Progress Report'!R69 -> 29853856 | CM4: ='Weekly Progress Report'!R70 -> 34389935 | CN4: ='Weekly Progress Report'!R71 -> 46295 | CO4: ='Weekly Progress Report'!R72 -> 14046786 | CP4: ='Weekly Progress Report'!R73 -> 0 | CQ4: ='Weekly Progress Report'!R74 -> 58000 | CR4: ='Weekly Progress Report'!L78 -> 28 | CS4: ='Weekly Progress Report'!M78 -> 32 | CT4: ='Weekly Progress Report'!O78 -> 4 | CU4: ='Weekly Progress Report'!P78 -> 141 | CV4: ='Weekly Progress Report'!Q78 -> 358 | CW4: ='Weekly Progress Report'!T92 -> 38 | CX4: ='Weekly Progress Report'!U92 -> 52 | CY4: ='Weekly Progress Report'!Z55 -> 9660 | CZ4: ='Weekly Progress Report'!Z56 -> 6360 | DA4: ='Weekly Progress Report'!Z57 -> 0 | DB4: ='Weekly Progress Report'!Z58 -> 0 | DC4: ='Weekly Progress Report'!Z60 -> 0 | DD4: ='Weekly Progress Report'!Z61 -> 0 | DE4: ='Weekly Progress Report'!Z62 -> 0 | DF4: ='Weekly Progress Report'!Z63 -> 0 | DG4: ='Weekly Progress Report'!Z64 -> 0 | DH4: ='Weekly Progress Report'!Z65 -> 0 | DI4: ='Weekly Progress Report'!Z66 -> 0 | DJ4: ='Weekly Progress Report'!Z67 -> 0 | DK4: ='Weekly Progress Report'!Z68 -> 0 | DL4: ='Weekly Progress Report'!Z69 -> 0 | DM4: ='Weekly Progress Report'!Z70 -> 1 | DN4: ='Weekly Progress Report'!Z71 -> 0 | DO4: ='Weekly Progress Report'!AB55 -> 20640 | DP4: ='Weekly Progress Report'!AB56 -> 20640 | DQ4: ='Weekly Progress Report'!AB57 -> 0 | DR4: ='Weekly Progress Report'!AB58 -> 0 | DS4: ='Weekly Progress Report'!AB60 -> 0 | DT4: ='Weekly Progress Report'!AB61 -> 0 | DU4: ='Weekly Progress Report'!AB62 -> 0 | DV4: ='Weekly Progress Report'!AB63 -> 0 | DW4: ='Weekly Progress Report'!AB64 -> 0 | DX4: ='Weekly Progress Report'!AB65 -> 0 | DY4: ='Weekly Progress Report'!AB66 -> 0 | DZ4: ='Weekly Progress Report'!AB67 -> 0 | EA4: ='Weekly Progress Report'!AB68 -> 1 | EB4: ='Weekly Progress Report'!AB69 -> 0 | EC4: ='Weekly Progress Report'!AB70 -> 2 | ED4: ='Weekly Progress Report'!AB71 -> 0 | EE4: ='Weekly Progress Report'!AC55 -> 371624 | EF4: ='Weekly Progress Report'!AC56 -> 371624 | EG4: ='Weekly Progress Report'!AC57 -> 0 | EH4: ='Weekly Progress Report'!AC58 -> 0 | EI4: ='Weekly Progress Report'!AC60 -> 0 | EJ4: ='Weekly Progress Report'!AC61 -> 0 | EK4: ='Weekly Progress Report'!AC62 -> 0 | EL4: ='Weekly Progress Report'!AC63 -> 0 | EM4: ='Weekly Progress Report'!AC64 -> 0 | EN4: ='Weekly Progress Report'!AC65 -> 0 | EO4: ='Weekly Progress Report'!AC66 -> 0 | EP4: ='Weekly Progress Report'!AC67 -> 7 | EQ4: ='Weekly Progress Report'!AC68 -> 18 | ER4: ='Weekly Progress Report'!AC69 -> 0 | ES4: ='Weekly Progress Report'!AC70 -> 36 | ET4: ='Weekly Progress Report'!AC71 -> 0 | EU4: ='Weekly Progress Report'!AD55 -> 371624 | EV4: ='Weekly Progress Report'!AD56 -> 371624 | EW4: ='Weekly Progress Report'!AD57 -> 0 | EX4: ='Weekly Progress Report'!AD58 -> 0 | EY4: ='Weekly Progress Report'!AD60 -> 0 | EZ4: ='Weekly Progress Report'!AD61 -> 0 | FA4: ='Weekly Progress Report'!AD62 -> 0 | FB4: ='Weekly Progress Report'!AD63 -> 0 | FC4: ='Weekly Progress Report'!AD64 -> 0 | FD4: ='Weekly Progress Report'!AD65 -> 0 | FE4: ='Weekly Progress Report'!AD66 -> 0 | FF4: ='Weekly Progress Report'!AD67 -> 8 | FG4: ='Weekly Progress Report'!AD68 -> 18 | FH4: ='Weekly Progress Report'!AD69 -> 0 | FI4: ='Weekly Progress Report'!AD70 -> 36 | FJ4: ='Weekly Progress Report'!AD71 -> 0 | FK4: ='Weekly Progress Report'!A84 -> 1492 | FL4: ='Weekly Progress Report'!B84 -> 712 | FM4: ='Weekly Progress Report'!C84 -> 205 | FN4: ='Weekly Progress Report'!D84 -> 575 | FO4: ='Weekly Progress Report'!A89 -> 188 | FP4: ='Weekly Progress Report'!B89 -> 200 | FQ4: ='Weekly Progress Report'!H89 -> 24 | FR4: ='Weekly Progress Report'!I89 -> 24 | FS4: ='Weekly Progress Report'!B100 -> 0 | FT4: ='Weekly Progress Report'!D100 -> 0 | FU4: ='Weekly Progress Report'!F100 -> 0 | FV4: ='Weekly Progress Report'!H100 -> 0 | FW4: ='Weekly Progress Report'!J100 -> 0 | FX4: ='Weekly Progress Report'!L100 -> 0 | FY4: ='Weekly Progress Report'!N100 -> 0 | FZ4: ='Weekly Progress Report'!O100 -> 0 | GA4: ='Weekly Progress Report'!P100 -> 0

Sheet Procurement (2)
C1: =+_xlfn.SINGLE('Weekly Progress Report'!B4) -> TAB1-02-003 | E1: Procurement Log- Long Lead Items | X1: =+'General Information'!L1 -> 46307
A2: Sr. NO. | B2: Project ID | C2: ACT#inP6 | D2: Item Description | E2: Discipline | F2: (Long \Short) Lead Items | G2: BOQ. No. | H2: Unit | I2: Quantity | J2: Proc. Qty | K2: Required P.O Date | L2: Date of Pur. Order Issued | M2: Purchase Order No. | N2: Supplier | O2: Supplier Phone | P2: Method of Shipping | Q2: Required on Job | R2: E.D.A. to Site | S2: A.D.A. to Site | T2: Lead Time | U2: Approval Status | V2: Completion Rate | W2: The Impact (BOQ Cost) | X2: Remarks
C3: SHORT-LEAD
A4: 1 | C4: ROADS | D4: ROADS | F4: Short
A5: 1 | B5: TAB1-01-009 | C5: TAPQDVRD0001 | D5: ABC | E5: ROADS | F5: LONG | H5: m3 | I5: 48485 | J5: 48485 | K5: 45962 | L5: 46105 | M5: SL103026 | N5: شركة خبير المستقبل للاسفلت | P5: Local | Q5: 46121 | R5: 46102 | S5: 46102 | U5: Accepted As Material | V5: 0.32 | X5: po issued
A6: 2 | B6: TAB1-01-009 | C6: TAPQDVRD0002 | D6: BBC Base Course | E6: ROADS | F6: LONG | H6: m3 | I6: 24510 | J6: 24510 | K6: 45962 | L6: 46105 | M6: SL103026 | N6: شركة خبير المستقبل للاسفلت | P6: Local | Q6: 46110 | R6: 46110 | S6: 46110 | U6: Accepted As Material | V6: 0.16 | X6: DELIVERY ONGOING
A7: 3 | B7: TAB1-01-009 | C7: TAPQDVRD0003 | D7: BWC Asphalt Wearing Course | E7: ROADS | F7: LONG | H7: m3 | I7: 14195 | J7: 14195 | K7: 45962 | L7: 46105 | M7: SL103027 | N7: شركة خبير المستقبل للاسفلت | P7: Local | Q7: 46582 | U7: Accepted As Material | X7: po issued
A8: 4 | B8: TAB1-01-009 | C8: TAPQDVRD0004 | D8: Precast Concrete Curbstone | E8: ROADS | F8: LONG | H8: m | I8: 74370 | J8: 74370 | K8: 45962 | L8: 46208 | M8: PO-02156 | N8: جسور المستقبل | P8: Local | Q8: 46119 | R8: 46124 | S8: 46124 | U8: Accepted As Material | V8: 0.05 | X8: DELIVERY ONGOING
A9: 5 | B9: TAB1-01-009 | C9: TAPQDVRD0005 | D9: Precast Concrete Interlocking | E9: ROADS | F9: LONG | H9: m2 | I9: 62075 | J9: 62075 | K9: 45962 | L9: 46208 | M9: PO-02156 | N9: جسور المستقبل | P9: Local | Q9: 46586 | U9: Accepted As Material | X9: po issued
A10: 6 | B10: TAB1-01-009 | C10: TAPQDVRD0008 | D10: Marking for Road | E10: ROADS | F10: LONG | K10: 45962 | L10: 46131 | M10: SL1942026 | N10: شركة أضواء طي الشمال | P10: Local | Q10: 46134 | R10: 46138 | S10: 46138 | U10: Accepted As Material | V10: 0.19 | X10: DELIVERY ONGOING
A11: 7 | B11: TAB1-01-009 | C11: TAPQDVRD0009 | D11: Trafic Sinage | E11: ROADS | F11: LONG | H11: Unit | I11: 246 | J11: 246 | K11: 45962 | P11: Local | Q11: 46140 | U11: Accepted As Material | V11: 0.02 | X11: DELIVERY ONGOING
A12: 2 | C12: ELECTRICAL | D12: ELECTRICAL
A13: 8 | B13: TAB1-01-009 | C13: TAPQDVEL0001 | D13: Pipes ,Fittings | E13: ELECTRICAL | F13: LONG | H13: m | I13: 2145 | J13: 2145 | K13: 46135 | L13: 46134 | M13: SL2242026 | N13: الشركة العربية لصناعة البلاستك | P13: Local | Q13: 46141 | R13: 46141 | S13: 46141 | U13: Accepted As Material | V13: 0.7 | X13: DELIVERY ONGOING | AA13: =13000/48485 -> 0.26812416
A14: 9 | D14: cables (LV ) | K14: 46135 | L14: 46205 | M14: PO-02162 | N14: بحرة | Q14: 46254 | X14: po issued
A15: 10 | B15: TAB1-01-009 | C15: TAPQDVEL0002 | D15: SCOPE MV | E15: ELECTRICAL | F15: LONG | H15: m | I15: 115400 | J15: 115400 | K15: 46135 | L15: 46126 | M15: PO-014255 | N15: شركة ايتيا | P15: Local | Q15: 46254 | R15: 46183 | S15: 46183 | U15: Accepted As Material | V15: 0.12 | X15: DELIVERY ONGOING
A16: 11 | B16: TAB1-01-009 | C16: TAPQDVEL0003 | D16: Poles & Luminares | E16: ELECTRICAL | F16: LONG | H16: Unit | I16: 957 | J16: 957 | K16: 46135 | L16: 46182 | M16: PO-012069 | N16: شركة جلنتي | P16: Local | Q16: 46324 | U16: Accepted As Material | X16: po issued
A17: 13 | B17: TAB1-01-009 | C17: TAPQDVEL0004 | D17: Substations ,ets.. | E17: ELECTRICAL | F17: LONG | H17: Unit | I17: 5 | J17: 5 | K17: 46135 | L17: 46126 | M17: PO-014255 | N17: شركة ايتيا | P17: Local | Q17: 46394 | U17: Accepted As Material | X17: po issued
A18: 14 | B18: TAB1-01-009 | C18: TAPQDVEL0004 | D18: RMU ,ets.. | E18: ELECTRICAL | F18: LONG | H18: Unit | I18: 5 | J18: 5 | K18: 46135 | L18: 46126 | M18: PO-014255 | N18: شركة ايتيا | P18: Local | Q18: 46394 | U18: Accepted As Material | X18: po issued
A19: 16 | D19: Pole Foundation | K19: 46135 | Q19: 46401 | X19: po not issued
A20: 3 | C20: TELECOMMUNICATION | D20: TELECOMMUNICATION
A21: 17 | B21: TAB1-01-009 | C21: TAPQDVTC0001 | D21: Telecommunication Material (Pipes,,ets) | E21: TELECOMMUNICATION | F21: LONG | H21: m | I21: 16522 | J21: 16522 | K21: 46176 | P21: Local | Q21: 46219 | U21: Accepted As Material | V21: 0.01 | X21: po not issued
A22: 4 | C22: CCTV NETWORK | D22: CCTV NETWORK
A23: 18 | B23: TAB1-01-009 | C23: TAPQDVCC0001 | D23: CCTV NETWORK | E23: CCTV NETWORK | F23: LONG | H23: m | I23: 24430 | J23: 24430 | K23: 46202 | L23: 46209 | P23: Local | Q23: 46289 | U23: Accepted As Material | X23: po issued
A24: 5 | C24: POTABLE WATER | D24: POTABLE WATER
A25: 19 | B25: TAB1-01-009 | C25: TAPQDVPT0001 | D25: PE Pipes | E25: POTABLE WATER | F25: LONG | H25: m | I25: 13221 | J25: 13221 | K25: 46025 | L25: 46021 | M25: PO-01613 | N25: UNION PIPES | P25: Local | Q25: 46040 | R25: 46043 | S25: 46043 | U25: Accepted As Material | V25: 0.89 | X25: DELIVERY ONGOING
A26: 20 | B26: TAB1-01-009 | C26: TAPQDVPT0002 | D26: Valves | E26: POTABLE WATER | F26: LONG | H26: Nr | I26: 146 | J26: 146 | K26: 46025 | L26: 46016 | M26: PO-01520 | N26: SPC | P26: Local | Q26: 46063 | R26: 46063 | S26: 46063 | U26: Accepted As Material | V26: 0.78 | X26: DELIVERY ONGOING
A27: 21 | B27: TAB1-01-009 | C27: TAPQDVPT0003 | D27: Fire Hydrent | E27: POTABLE WATER | F27: LONG | H27: Nr | I27: 152 | J27: 152 | K27: 46025 | L27: 46016 | M27: PO-1520 | N27: SPC | P27: Local | Q27: 46073 | R27: 46073 | S27: 46073 | U27: Accepted As Material | V27: 0.68 | X27: DELIVERY ONGOING
A28: 6 | C28: TSE NETWORK | D28: TSE NETWORK
A29: 22 | B29: TAB1-01-009 | C29: TAPQDVTS0001 | D29: PE Pipes | E29: TSE NETWORK | F29: LONG | H29: m | I29: 12223 | J29: 12223 | K29: 46025 | L29: 46021 | M29: PO-01613 | N29: UNION PIPES | P29: Local | Q29: 46044 | R29: 46043 | S29: 46043 | U29: Accepted As Material | V29: 0.89 | X29: DELIVERY ONGOING
A30: 23 | B30: TAB1-01-009 | C30: TAPQDVTS0002 | D30: Valves | E30: TSE NETWORK | F30: LONG | H30: Nr | I30: 141 | J30: 141 | K30: 46025 | L30: 46016 | M30: PO-01520 | N30: SPC | P30: Local | Q30: 46073 | R30: 46063 | S30: 46063 | U30: Accepted As Material | V30: 0.78 | X30: DELIVERY ONGOING
A31: 7 | C31: SEWERAGE NETWORK | D31: SEWERAGE NETWORK
A32: 24 | B32: TAB1-01-009 | C32: TAPQDVSW0001 | D32: GRP Pipes | E32: SEWERAGE NETWORK | F32: LONG | H32: m | I32: 8370 | J32: 8370 | K32: 45980 | L32: 45985 | M32: PO-01437 | N32: TAREQ NAQADI | O32: 533365029 | P32: Local | Q32: 46000 | R32: 46000 | S32: 46000 | U32: Accepted As Material | V32: 0.84 | X32: DELIVERY ONGOING
A33: 25 | B33: TAB1-01-009 | C33: TAPQDVSW0002 | D33: Fiberglass Manholes,ets) | E33: SEWERAGE NETWORK | F33: LONG | H33: Nr | I33: 142 | J33: 142 | K33: 45980 | L33: 46040 | M33: PO-1662 | N33: TAREQ NAQADI | P33: Local | Q33: 46051 | R33: 46055 | S33: 46055 | U33: Accepted As Material | V33: 1 | X33: DONE
A34: 8 | C34: STORM NETWORK | D34: STORM NETWORK
A35: 26 | B35: TAB1-01-009 | C35: TAPQDVST0001 | D35: UPVC Pipes with Fittings | E35: STORM NETWORK | F35: LONG | H35: m | I35: 6621 | J35: 6621 | K35: 46359 | L35: 46019 | M35: PO-01580 | N35: الخام الوطني للصناعات | P35: Local | Q35: 46040 | R35: 46043 | S35: 46043 | U35: Accepted As Material | V35: 1 | X35: DONE
A36: 27 | B36: TAB1-01-009 | C36: TAPQDVST0002 | D36: GRP Pipes with Fittings | E36: STORM NETWORK | F36: LONG | H36: m | I36: 9017 | J36: 9017 | K36: 45982 | L36: 45985 | M36: PO-01437 | N36: TAREQ NAQADI | O36: 533365029 | P36: Local | Q36: 46000 | R36: 46000 | S36: 46000 | U36: Accepted As Material | V36: 0.88 | X36: DELIVERY ONGOING
A37: 28 | B37: TAB1-01-009 | C37: TAPQDVST0005 | D37: Box Culvert | E37: STORM NETWORK | F37: LONG | H37: m3 | I37: 4100 | J37: 4100 | K37: 45982 | L37: 46054 | M37: PO-01183 | N37: TAREQ NAQADI | P37: Local | Q37: 46085 | R37: 46086 | S37: 46086 | U37: Accepted As Material | V37: 0.98 | X37: DELIVERY ONGOING
A38: 29 | B38: TAB1-01-009 | C38: TAPQDVST0006 | D38: Manholes,ets | E38: STORM NETWORK | F38: LONG | H38: Nr | I38: 155 | J38: 155 | K38: 45982 | L38: 46043 | M38: PO -01700 | N38: JOSOR ELMOSTAKBEL | P38: Local | Q38: 46060 | R38: 46086 | S38: 46086 | U38: Accepted As Material | V38: 0.99 | X38: DELIVERY ONGOING
A39: 30 | D39: CATCH BASIN | E39: STORM NETWORK | M39: PO-01886 | N39: TAREQ NAQADI | Q39: 46188 | R39: 46134 | S39: 46134 | U39: Accepted As Material | V39: 0.68 | X39: DELIVERY ONGOING
A40: 31 | B40: TAB1-01-009 | C40: TAPQDVST0007 | D40: RIprab for Ponds | E40: STORM NETWORK | F40: LONG | H40: m2 | I40: 15345 | J40: 15345 | K40: 45982 | L40: 46133 | M40: SL1942027 | N40: SALALEM ELYAMAMAH | P40: Local | Q40: 46134 | R40: 46134 | S40: 46134 | U40: Accepted As Material | V40: 0.3 | X40: DELIVERY ONGOING
A41: 32 | B41: TAB1-01-009 | C41: TAPQDVST0010 | D41: Riprab for Dike | E41: STORM NETWORK | F41: LONG | H41: m2 | I41: 1570 | J41: 1570 | K41: 45982 | L41: 46133 | M41: SL1942027 | N41: SALALEM ELYAMAMAH | P41: Local | Q41: 46134 | R41: 46134 | S41: 46134 | U41: Accepted As Material | V41: 0.9 | X41: DELIVERY ONGOING
D48: CCTV Swiches Lighting panels
D53: Street Lighting panels 1- 63A MCCB Circuit Breaker 2- 6X32 MCB Circuit Breakers 3- 1X63A contactors 4- Photocell & Timer 5- ON/OFF Push Button 6- Indication Lamps 7- Copper Bus Bars 8- Panel Body from Galavanized Steel anti-corrosion (IP65) And includes everything necessary to operate the panels according to the technical specifications or instructions of the supervising engineer.
D54: Feeder pillars 1- 100A MCCB Circuit Breaker 2- 5X63A MCCB Circuit Breakers 3- Indication Lamps 4- Copper Bus Bars 5- Panel Body from Galavanized Steel anti-corrosion (IP65) And includes everything necessary for operation according to the technical specifications or instructions of the supervising engineer.
R64328: =+#REF!+25 -> #REF!

Sheet Weekly Progress Report
A1: MODON - Weekly Progress Report - Construction Projects | AF1: Data Date | AG1: ='General Information'!L1 -> 46307
A2: Contract General Information | G2: Key Dates | M2: Cost Summary (SR) | U2: Performance Summary | AA2: Project Scope
A3: Project Name | B3: ='General Information'!C3 -> ADDITIONAL DEVELOPMENT IN TABOUK INDUSTRIAL CITY | G3: Contract Award | H3: ='General Information'!C12 -> 45882 | I3: Contract Award (Hijri) | J3: ='General Information'!C16 -> 45882 | K3: Revised Completion | L3: ='General Information'!C20 -> 46633 | M3: Original Contract Value | O3: ='Invoice Log'!E3 -> 140467862 | Q3: O&M Value (if any) | S3: ='Invoice Log'!I3 -> 0 | T3: EAC | U3: Plan Value | V3: =K22 -> 0.37308716 | W3: Phys. Plan Value | X3: =W22 -> 0.3461685 | Y3: Quality Score | Z3: =Quality!AC10 -> 0.92982759 | AA3: =+Progress!B1 -> The project consists of roads works and the POND A which works as a downstream for the storm water wet utility piping network including manholes and catch basins, continued project wet utilities also sewerage GRP piping network with manholes, potable water and firefighting compound HDPE piping network including the installation of valves and fire hydrants and the irrigation water (TSE) network with all valves and the flow meter, dry utility represented in electrical road lighting network - the installation of poles and the LV cables which is connected to the panel board and the 13.8/0.4 K V unit substation.
A4: Project ID | B4: ='General Information'!C4 -> TAB1-02-003 | D4: Stage | E4: ='General Information'!C7 -> INFRASTRUCTURE & UTILITIES | G4: Contract Sign | H4: ='General Information'!C13 -> 45900 | I4: Contract Sign (Hijri) | J4: ='General Information'!C17 -> 45900 | K4: Committed Completion | L4: ='General Information'!C21 -> 46633 | M4: Revised Contract Value | O4: ='Invoice Log'!E4 -> 140467862 | P4: EAC | Q4: Submitted Invoices (Gross Value) | S4: ='Invoice Log'!I5 -> 43497867 | U4: Earn Value | V4: =L22 -> 0.47569888 | W4: Phys. Earn Value | X4: =X22 -> 0.4987258 | Z4: =REPT("¢",IF(INT(+Z3*10)>5,5,INT(+Z3*10)))&REPT("£",IF(INT(+Z3*10)>5,0,5-INT(+Z3*10)))&CHAR(10)&REPT("¢",+IF(INT(+Z3*10)>5,-5+INT(+Z3*10),0))&REPT("£",IF(INT(+Z3*10)>5,10-INT(+Z3*10),5)) -> ¢¢¢¢¢ ¢¢¢¢£
A5: Contractor | B5: ='General Information'!C5 -> ASAS for Developing & Operating Industrial Cities | D5: Status | E5: ='General Information'!C8 -> Active | G5: Site Handover | H5: ='General Information'!C14 -> 45904 | I5: Site Handover (Hijri) | J5: ='General Information'!C18 -> 45904 | K5: Forecast Completion | L5: ='General Information'!C22 -> 46662 | M5: Estimate At Completion Value | O5: ='Invoice Log'!E5 -> 140467862 | P5: =+#REF!+#REF!+O5 -> #REF! | Q5: Penalities | S5: ='Invoice Log'!I6 -> 58000 | U5: Variance | V5: =V4-V3 -> 0.10261172 | W5: Variance | X5: =Y22 -> 0.1525573 | Y5: Safety Score | Z5: ='HSE-Stat'!J23 -> 0.94565217
A6: Consultant | B6: ='General Information'!C6 -> EGIS | D6: Modon PM | E6: ='General Information'!C9 -> ENG/ YAZEED ALRAGABAH | G6: Original Completion | H6: ='General Information'!C15 -> 46633 | I6: Original Completion (Hijri) | J6: ='General Information'!C19 -> 46633 | K6: Variance | L6: =H6-L5 -> -29 | M6: Potential Changes | O6: =O4-O5 -> 0 | Q6: FIR Value (THIS WEEK) | S6: ='FIR Summary'!F3 -> 51776131 | U6: FIR % | V6: =S6/O4 -> 0.3685977 | W6: Invoiced % | X6: =S4/O4 -> 0.3096642 | Z6: =REPT("¢",IF(INT(+Z5*10)>5,5,INT(+Z5*10)))&REPT("£",IF(INT(+Z5*10)>5,0,5-INT(+Z5*10)))&CHAR(10)&REPT("¢",+IF(INT(+Z5*10)>5,-5+INT(+Z5*10),0))&REPT("£",IF(INT(+Z5*10)>5,10-INT(+Z5*10),5)) -> ¢¢¢¢¢ ¢¢¢¢£
A8: Progress Overview
A9: Earned Value Progress (SAR) | O9: Physical Progress (Effort) | AA9: Earned Value Progress (%)
A10: WBS | C10: BOQ Value (SAR) | D10: % Wt. | E10: Weekly (SAR) | G10: To Date (SAR) | O10: Budgeted | P10: % Wt. | Q10: Weekly Physical Progress | U10: To Date Physical Progress
E11: Planned | F11: Earned | G11: Original Plan | H11: Revised Planned | I11: Earned | J11: Original Plan % | K11: Revised Planned % | L11: Earned % | M11: Variance | N11: SPI | O11: (Manhours) | Q11: Planned | R11: Earned | S11: Plan % | T11: Earned % | U11: Planned | V11: Earned | W11: Plan % | X11: Earned % | Y11: Variance | Z11: SPI
A12: =Progress!A7 -> MILESTONS | C12: =+Progress!C7 -> 0 | D12: =IF(ISBLANK(C12),"",C12/$C$22) -> 0 | E12: =+Progress!E7 -> 0 | F12: =+Progress!F7 -> 0 | G12: =+Progress!G7 -> 0 | H12: =+Progress!H7 -> 0 | I12: =+Progress!I7 -> 0 | J12: =IFERROR(IF(ISBLANK(G12),"",G12/C12),0) -> 0 | K12: =IFERROR(IF(ISBLANK(H12),"",H12/C12),0) -> 0 | L12: =IFERROR(IF(ISBLANK(I12),"",I12/C12),0) -> 0 | M12: =IFERROR(L12-K12,"") -> 0 | N12: =IFERROR(L12/K12,"") | O12: =+Progress!K7 -> 0 | P12: =IF(ISBLANK(O12),"",O12/$O$22) -> 0 | Q12: =+Progress!M7 -> 0 | R12: =+Progress!N7 -> 0 | S12: =IFERROR(IF(ISBLANK(Q12),"",Q12/O12),0) -> 0 | T12: =IFERROR(IF(ISBLANK(R12),"",R12/O12),0) -> 0 | U12: =+Progress!O7 -> 0 | V12: =+Progress!P7 -> 0 | W12: =IFERROR(IF(ISBLANK(U12),"",U12/O12),0) -> 0 | X12: =IFERROR(IF(ISBLANK(V12),"",V12/O12),0) -> 0 | Y12: =IFERROR(X12-W12,"") -> 0 | Z12: =IFERROR(X12/W12,"")
A13: =Progress!A8 -> MOBILIZATION | C13: =+Progress!C8 -> 0 | D13: =IF(ISBLANK(C13),"",C13/$C$22) -> 0 | E13: =+Progress!E8 -> 0 | F13: =+Progress!F8 -> 0 | G13: =+Progress!G8 -> 0 | H13: =+Progress!H8 -> 0 | I13: =+Progress!I8 -> 0 | J13: =IFERROR(IF(ISBLANK(G13),"",G13/C13),0) -> 0 | K13: =IFERROR(IF(ISBLANK(H13),"",H13/C13),0) -> 0 | L13: =IFERROR(IF(ISBLANK(I13),"",I13/C13),0) -> 0 | M13: =IFERROR(L13-K13,"") -> 0 | N13: =IFERROR(L13/K13,"") | O13: =+Progress!K8 -> 1600 | P13: =IF(ISBLANK(O13),"",O13/$O$22) -> 0.0045154499 | Q13: =+Progress!M8 -> 0 | R13: =+Progress!N8 -> 0 | S13: =IFERROR(IF(ISBLANK(Q13),"",Q13/O13),0) -> 0 | T13: =IFERROR(IF(ISBLANK(R13),"",R13/O13),0) -> 0 | U13: =+Progress!O8 -> 1600 | V13: =+Progress!P8 -> 1600 | W13: =IFERROR(IF(ISBLANK(U13),"",U13/O13),0) -> 1 | X13: =IFERROR(IF(ISBLANK(V13),"",V13/O13),0) -> 1 | Y13: =IFERROR(X13-W13,"") -> 0 | Z13: =IFERROR(X13/W13,"") -> 1
A14: =Progress!A9 -> ENGINEERING | C14: =+Progress!C9 -> 4214035 | D14: =IF(ISBLANK(C14),"",C14/$C$22) -> 0.029999994 | E14: =+Progress!E9 -> 0 | F14: =+Progress!F9 -> 0 | G14: =+Progress!G9 -> 4214035 | H14: =+Progress!H9 -> 4214035 | I14: =+Progress!I9 -> 4214035.9 | J14: =IFERROR(IF(ISBLANK(G14),"",G14/C14),0) -> 1 | K14: =IFERROR(IF(ISBLANK(H14),"",H14/C14),0) -> 1 | L14: =IFERROR(IF(ISBLANK(I14),"",I14/C14),0) -> 1.0000002 | M14: =IFERROR(L14-K14,"") -> 2.0407994e-07 | N14: =IFERROR(L14/K14,"") -> 1.0000002 | O14: =+Progress!K9 -> 0 | P14: =IF(ISBLANK(O14),"",O14/$O$22) -> 0 | Q14: =+Progress!M9 -> 0 | R14: =+Progress!N9 -> 0 | S14: =IFERROR(IF(ISBLANK(Q14),"",Q14/O14),0) -> 0 | T14: =IFERROR(IF(ISBLANK(R14),"",R14/O14),0) -> 0 | U14: =+Progress!O9 -> 0 | V14: =+Progress!P9 -> 0 | W14: =IFERROR(IF(ISBLANK(U14),"",U14/O14),0) -> 0 | X14: =IFERROR(IF(ISBLANK(V14),"",V14/O14),0) -> 0 | Y14: =IFERROR(X14-W14,"") -> 0 | Z14: =IFERROR(X14/W14,"")
A15: =Progress!A10 -> PROCUREMENT | C15: =+Progress!C10 -> 28093572 | D15: =IF(ISBLANK(C15),"",C15/$C$22) -> 0.2 | E15: =+Progress!E10 -> 205448.67 | F15: =+Progress!F10 -> 141539.04 | G15: =+Progress!G10 -> 21377402 | H15: =+Progress!H10 -> 15068661 | I15: =+Progress!I10 -> 17171855 | J15: =IFERROR(IF(ISBLANK(G15),"",G15/C15),0) -> 0.76093569 | K15: =IFERROR(IF(ISBLANK(H15),"",H15/C15),0) -> 0.53637397 | L15: =IFERROR(IF(ISBLANK(I15),"",I15/C15),0) -> 0.61123786 | M15: =IFERROR(L15-K15,"") -> 0.074863882 | N15: =IFERROR(L15/K15,"") -> 1.139574 | O15: =+Progress!K10 -> 0 | P15: =IF(ISBLANK(O15),"",O15/$O$22) -> 0 | Q15: =+Progress!M10 -> 0 | R15: =+Progress!N10 -> 0 | S15: =IFERROR(IF(ISBLANK(Q15),"",Q15/O15),0) -> 0 | T15: =IFERROR(IF(ISBLANK(R15),"",R15/O15),0) -> 0 | U15: =+Progress!O10 -> 0 | V15: =+Progress!P10 -> 0 | W15: =IFERROR(IF(ISBLANK(U15),"",U15/O15),0) -> 0 | X15: =IFERROR(IF(ISBLANK(V15),"",V15/O15),0) -> 0 | Y15: =IFERROR(X15-W15,"") -> 0 | Z15: =IFERROR(X15/W15,"")
A16: =Progress!A11 -> CONSTRUCTION WORKS | C16: =+Progress!C11 -> 94113469 | D16: =IF(ISBLANK(C16),"",C16/$C$22) -> 0.67000001 | E16: =+Progress!E11 -> 298825.92 | F16: =+Progress!F11 -> 809329.59 | G16: =+Progress!G11 -> 58798243 | H16: =+Progress!H11 -> 33124060 | I16: =+Progress!I11 -> 45434514 | J16: =IFERROR(IF(ISBLANK(G16),"",G16/C16),0) -> 0.62475907 | K16: =IFERROR(IF(ISBLANK(H16),"",H16/C16),0) -> 0.35195877 | L16: =IFERROR(IF(ISBLANK(I16),"",I16/C16),0) -> 0.48276314 | M16: =IFERROR(L16-K16,"") -> 0.13080438 | N16: =IFERROR(L16/K16,"") -> 1.3716469 | O16: =+Progress!K11 -> 347187 | P16: =IF(ISBLANK(O16),"",O16/$O$22) -> 0.97981594 | Q16: =+Progress!M11 -> 2107 | R16: =+Progress!N11 -> 4696 | S16: =IFERROR(IF(ISBLANK(Q16),"",Q16/O16),0) -> 0.0060687756 | T16: =IFERROR(IF(ISBLANK(R16),"",R16/O16),0) -> 0.013525852 | U16: =+Progress!O11 -> 121061 | V16: =+Progress!P11 -> 175118 | W16: =IFERROR(IF(ISBLANK(U16),"",U16/O16),0) -> 0.34869105 | X16: =IFERROR(IF(ISBLANK(V16),"",V16/O16),0) -> 0.50439101 | Y16: =IFERROR(X16-W16,"") -> 0.15569995 | Z16: =IFERROR(X16/W16,"") -> 1.446527
A17: =Progress!A12 -> ZONE 01 | C17: =+Progress!C12 -> 18023708 | D17: =IF(ISBLANK(C17),"",C17/$C$22) -> 0.12831197 | E17: =+Progress!E12 -> 47598.42 | F17: =+Progress!F12 -> 56655.1 | G17: =+Progress!G12 -> 16301672 | H17: =+Progress!H12 -> 10109128 | I17: =+Progress!I12 -> 11813165 | J17: =IFERROR(IF(ISBLANK(G17),"",G17/C17),0) -> 0.90445714 | K17: =IFERROR(IF(ISBLANK(H17),"",H17/C17),0) -> 0.56087947 | L17: =IFERROR(IF(ISBLANK(I17),"",I17/C17),0) -> 0.65542368 | M17: =IFERROR(L17-K17,"") -> 0.094544203 | N17: =IFERROR(L17/K17,"") -> 1.1685642 | O17: =Progress!K12 -> 74705 | P17: =Progress!L12 -> 0.21082918 | Q17: =Progress!M12 -> 1105 | R17: =Progress!N12 -> 953 | S17: =IFERROR(IF(ISBLANK(Q17),"",Q17/O17),0) -> 0.014791513 | T17: =IFERROR(IF(ISBLANK(R17),"",R17/O17),0) -> 0.012756844 | U17: =Progress!O12 -> 29328 | V17: =Progress!P12 -> 42378 | W17: =IFERROR(IF(ISBLANK(U17),"",U17/O17),0) -> 0.39258416 | X17: =IFERROR(IF(ISBLANK(V17),"",V17/O17),0) -> 0.56727127 | Y17: =IFERROR(X17-W17,"") -> 0.1746871 | Z17: =IFERROR(X17/W17,"") -> 1.4449673
A18: =Progress!A13 -> ZONE 02 | C18: =+Progress!C13 -> 24418268 | D18: =IF(ISBLANK(C18),"",C18/$C$22) -> 0.17383526 | E18: =+Progress!E13 -> 92411.99 | F18: =+Progress!F13 -> 411400.45 | G18: =+Progress!G13 -> 16533727 | H18: =+Progress!H13 -> 9329697.4 | I18: =+Progress!I13 -> 14890926 | J18: =IFERROR(IF(ISBLANK(G18),"",G18/C18),0) -> 0.67710481 | K18: =IFERROR(IF(ISBLANK(H18),"",H18/C18),0) -> 0.38207859 | L18: =IFERROR(IF(ISBLANK(I18),"",I18/C18),0) -> 0.60982729 | M18: =IFERROR(L18-K18,"") -> 0.2277487 | N18: =IFERROR(L18/K18,"") -> 1.5960781 | O18: =Progress!K13 -> 89699 | P18: =Progress!L13 -> 0.25314459 | Q18: =Progress!M13 -> 743 | R18: =Progress!N13 -> 2189 | S18: =IFERROR(IF(ISBLANK(Q18),"",Q18/O18),0) -> 0.0082832585 | T18: =IFERROR(IF(ISBLANK(R18),"",R18/O18),0) -> 0.02440384 | U18: =Progress!O13 -> 40282 | V18: =Progress!P13 -> 63809 | W18: =IFERROR(IF(ISBLANK(U18),"",U18/O18),0) -> 0.4490797 | X18: =IFERROR(IF(ISBLANK(V18),"",V18/O18),0) -> 0.71136802 | Y18: =IFERROR(X18-W18,"") -> 0.26228832 | Z18: =IFERROR(X18/W18,"") -> 1.5840574
A19: =Progress!A14 -> ZONE 03 | C19: =+Progress!C14 -> 51671493 | D19: =IF(ISBLANK(C19),"",C19/$C$22) -> 0.36785278 | E19: =+Progress!E14 -> 158815.5 | F19: =+Progress!F14 -> 341274.03 | G19: =+Progress!G14 -> 25962845 | H19: =+Progress!H14 -> 13685235 | I19: =+Progress!I14 -> 18730423 | J19: =IFERROR(IF(ISBLANK(G19),"",G19/C19),0) -> 0.50245974 | K19: =IFERROR(IF(ISBLANK(H19),"",H19/C19),0) -> 0.26485077 | L19: =IFERROR(IF(ISBLANK(I19),"",I19/C19),0) -> 0.36249045 | M19: =IFERROR(L19-K19,"") -> 0.097639678 | N19: =IFERROR(L19/K19,"") -> 1.3686592 | O19: =Progress!K14 -> 182783 | P19: =Progress!L14 -> 0.51584217 | Q19: =Progress!M14 -> 258 | R19: =Progress!N14 -> 1554 | S19: =IFERROR(IF(ISBLANK(Q19),"",Q19/O19),0) -> 0.0014115098 | T19: =IFERROR(IF(ISBLANK(R19),"",R19/O19),0) -> 0.0085018847 | U19: =Progress!O14 -> 51451 | V19: =Progress!P14 -> 68931 | W19: =IFERROR(IF(ISBLANK(U19),"",U19/O19),0) -> 0.28148679 | X19: =IFERROR(IF(ISBLANK(V19),"",V19/O19),0) -> 0.37711932 | Y19: =IFERROR(X19-W19,"") -> 0.095632526 | Z19: =IFERROR(X19/W19,"") -> 1.3397407
A20: =Progress!A15 -> CLOSE OUT | C20: =+Progress!C15 -> 14046786 | D20: =IF(ISBLANK(C20),"",C20/$C$22) -> 0.1 | E20: =+Progress!E15 -> 0 | G20: =+Progress!G15 -> 4889079 | H20: =+Progress!H15 -> 0 | I20: =+Progress!I15 -> 0 | J20: =IFERROR(IF(ISBLANK(G20),"",G20/C20),0) -> 0.34805677 | K20: =IFERROR(IF(ISBLANK(I20),"",I20/C20),0) -> 0 | L20: =IFERROR(IF(ISBLANK(I20),"",I20/C20),0) -> 0 | M20: =IFERROR(L20-K20,"") -> 0 | N20: =IFERROR(L20/K20,"") | O20: =Progress!K15 -> 5552 | P20: =IF(ISBLANK(O20),"",O20/$O$22) -> 0.015668611 | Q20: =Progress!M15 -> 0 | R20: =Progress!N15 -> 0 | S20: =IFERROR(IF(ISBLANK(Q20),"",Q20/O20),0) -> 0 | T20: =IFERROR(IF(ISBLANK(R20),"",R20/O20),0) -> 0 | U20: =Progress!O15 -> 0 | V20: =Progress!P15 -> 0 | W20: =IFERROR(IF(ISBLANK(U20),"",U20/O20),0) -> 0 | X20: =IFERROR(IF(ISBLANK(V20),"",V20/O20),0) -> 0 | Y20: =IFERROR(X20-W20,"") -> 0 | Z20: =IFERROR(X20/W20,"")
A21: =Progress!A16 -> 0 | D21: =IF(ISBLANK(C21),"",C21/$C$22) | J21: =IFERROR(IF(ISBLANK(G21),"",G21/C21),0) | K21: =IFERROR(IF(ISBLANK(I21),"",I21/C21),0) | L21: =IFERROR(IF(ISBLANK(I21),"",I21/C21),0) | M21: =IFERROR(L21-K21,"") | N21: =IFERROR(L21/K21,"") | P21: =IF(ISBLANK(O21),"",O21/$O$22) | S21: =IFERROR(IF(ISBLANK(Q21),"",Q21/O21),0) | T21: =IFERROR(IF(ISBLANK(R21),"",R21/O21),0) | W21: =IFERROR(IF(ISBLANK(U21),"",U21/O21),0) | X21: =IFERROR(IF(ISBLANK(V21),"",V21/O21),0) | Y21: =IFERROR(X21-W21,"") | Z21: =IFERROR(X21/W21,"")
B22: Total | C22: =C14+C12+C13+C16+C20+C15 -> 140467862 | D22: =D12+D13+D14+D15+D16+D20 -> 1 | E22: =Progress!E41 -> 504274.59 | F22: =Progress!F41 -> 950868.63 | G22: =Progress!G41 -> 89278759 | H22: =Progress!H41 -> 52406756 | I22: =Progress!I41 -> 66820405 | J22: =IFERROR(IF(ISBLANK(G22),"",G22/C22),0) -> 0.63558139 | K22: =IFERROR(IF(ISBLANK(H22),"",H22/C22),0) -> 0.37308716 | L22: =IFERROR(IF(ISBLANK(I22),"",I22/C22),0) -> 0.47569888 | M22: =+L22-K22 -> 0.10261172 | N22: =L22/K22 -> 1.2750342 | O22: =Progress!K41 -> 354339 | P22: =Progress!L41 -> 1 | Q22: =Progress!M41 -> 2107 | R22: =Progress!N41 -> 4696 | S22: =IFERROR(IF(ISBLANK(Q22),"",Q22/O22),0) -> 0.0059462831 | T22: =IFERROR(IF(ISBLANK(R22),"",R22/O22),0) -> 0.013252845 | U22: =Progress!O41 -> 122661 | V22: =Progress!P41 -> 176718 | W22: =IFERROR(IF(ISBLANK(U22),"",U22/O22),0) -> 0.3461685 | X22: =IFERROR(IF(ISBLANK(V22),"",V22/O22),0) -> 0.4987258 | Y22: =+X22-W22 -> 0.1525573 | Z22: =X22/W22 -> 1.4407024
AA23: Construction Milestones
AA24: Item No. | AB24: Milestones | AD24: Original (Baseline) | AE24: Latest Plan | AF24: Forecast | AG24: Status | AH24: Days Change
AA25: =+Milestones!A4 -> 1 | AB25: =+Milestones!B4 -> Award Date | AD25: =+Milestones!C4 -> 45882 | AE25: =+Milestones!D4 -> 45882 | AF25: =+Milestones!E4 -> 45882 | AG25: =+Milestones!F4 -> A | AH25: =+Milestones!G4 -> 0
AA26: =+Milestones!A5 -> 2 | AB26: =+Milestones!B5 -> Contract Sign Date | AD26: =+Milestones!C5 -> 45900 | AE26: =+Milestones!D5 -> 45900 | AF26: =+Milestones!E5 -> 45900 | AG26: =+Milestones!F5 -> A | AH26: =+Milestones!G5 -> 0
AA27: =+Milestones!A6 -> 3 | AB27: =+Milestones!B6 -> Site Handover Date | AD27: =+Milestones!C6 -> 45904 | AE27: =+Milestones!D6 -> 45904 | AF27: =+Milestones!E6 -> 45904 | AG27: =+Milestones!F6 -> A | AH27: =+Milestones!G6 -> 0
AA28: =+Milestones!A7 -> 4 | AB28: =+Milestones!B7 -> Complete Mobilization | AD28: =+Milestones!C7 -> 46609 | AE28: =+Milestones!D7 -> 46629 | AF28: =+Milestones!E7 -> 46623 | AG28: =+Milestones!F7 -> F | AH28: =+Milestones!G7 -> 6
AA29: =+Milestones!A10 -> 7 | AB29: =+Milestones!B10 -> Complete ZONE 1 | AD29: =+Milestones!C10 -> 46427 | AE29: =+Milestones!D10 -> 46662 | AF29: =+Milestones!E10 -> 46659 | AG29: =+Milestones!F10 -> F | AH29: =+Milestones!G10 -> 3
AA30: =+Milestones!A11 -> 8 | AB30: =+Milestones!B11 -> Complete ZONE 2 | AD30: =+Milestones!C11 -> 46601 | AE30: =+Milestones!D11 -> 46615 | AF30: =+Milestones!E11 -> 46622 | AG30: =+Milestones!F11 -> F | AH30: =+Milestones!G11 -> -7
AA31: =+Milestones!A12 -> 9 | AB31: =+Milestones!B12 -> Complete ZONE 3 | AD31: =+Milestones!C12 -> 46601 | AE31: =+Milestones!D12 -> 46657 | AF31: =+Milestones!E12 -> 46655 | AG31: =+Milestones!F12 -> F | AH31: =+Milestones!G12 -> 2
AA32: =+Milestones!A13 -> 10 | AB32: =+Milestones!B13 -> Complete all Works including Testing & Commissioning, Cleanup, Closeout Documentation and Ready for Initial Handover | AD32: =+Milestones!C13 -> 46609 | AE32: =+Milestones!D13 -> 46643 | AF32: =+Milestones!E13 -> 46643 | AG32: =+Milestones!F13 -> F | AH32: =+Milestones!G13 -> 0
AA33: =+Milestones!A14 -> 11 | AB33: =+Milestones!B14 -> Complete Demobilization | AD33: =+Milestones!C14 -> 46633 | AE33: =+Milestones!D14 -> 46662 | AF33: =+Milestones!E14 -> 46662 | AG33: =+Milestones!F14 -> F | AH33: =+Milestones!G14 -> 0
AA34: =+Milestones!A15 -> 12 | AB34: =+Milestones!B15 -> Project Handover | AD34: =+Milestones!C15 -> 46633 | AE34: =+Milestones!D15 -> 46662 | AF34: =+Milestones!E15 -> 46662 | AG34: =+Milestones!F15 -> F | AH34: =+Milestones!G15 -> 0
A50: Performance overview
A51: Submittals Status | L51: Quality | W51: Safety
A52: Shop Drawings | L52: Quality Reports | W52: Safety Statistics | AE52: Proactive Vs Reactive Actions Taken
A53: Item Per WBS | C53: Total | D53: Total Submitted Drawings | I53: Remaining | J53: Pending | K53: Total Submittals | L53: Quality Reports | N53: Issued | O53: Closed | P53: Pending | Q53: Avg. Closing (Days) | R53: Pending | W53: Category | X53: Item | Z53: This Week | AB53: This Month | AC53: Year to Date | AD53: Cumulative
D54: A | E54: B | F54: C | G54: D | H54: Processed | R54: 0-10 Days | S54: 11-20 Days | T54: 21-30 Days | U54: 31-60 Days | V54: > 60 Days
A55: ='Quality-Stat'!$A$13 -> Electrical Network - Road Lighting | C55: =IF('Quality-Stat'!D13="","",'Quality-Stat'!D13) -> 102 | D55: =IF('Quality-Stat'!E13="","",'Quality-Stat'!E13) -> 33 | E55: =IF('Quality-Stat'!F13="","",'Quality-Stat'!F13) -> 69 | F55: =IF('Quality-Stat'!G13="","",'Quality-Stat'!G13) -> 0 | G55: =IF('Quality-Stat'!H13="","",'Quality-Stat'!H13) -> 0 | H55: =IF('Quality-Stat'!I13="","",'Quality-Stat'!I13) -> 102 | I55: =IF('Quality-Stat'!J13="","",'Quality-Stat'!J13) | J55: =IF('Quality-Stat'!K13="","",'Quality-Stat'!K13) | K55: =IF('Quality-Stat'!L13="","",'Quality-Stat'!L13) -> 102 | W55: General | X55: ='HSE-Stat'!B4 -> Total Hours Worked | Z55: ='HSE-Stat'!D4 -> 9660 | AB55: ='HSE-Stat'!E4 -> 20640 | AC55: ='HSE-Stat'!F4 -> 371624 | AD55: ='HSE-Stat'!G4 -> 371624 | AG55: Proactive | AH55: =+SUM(AD67:AD71) -> 62
A56: ='Quality-Stat'!$A$14 -> Potable Water Network | C56: =IF('Quality-Stat'!D14="","",'Quality-Stat'!D14) -> 53 | D56: =IF('Quality-Stat'!E14="","",'Quality-Stat'!E14) -> 50 | E56: =IF('Quality-Stat'!F14="","",'Quality-Stat'!F14) -> 3 | F56: =IF('Quality-Stat'!G14="","",'Quality-Stat'!G14) -> 0 | G56: =IF('Quality-Stat'!H14="","",'Quality-Stat'!H14) -> 0 | H56: =IF('Quality-Stat'!I14="","",'Quality-Stat'!I14) -> 53 | I56: =IF('Quality-Stat'!J14="","",'Quality-Stat'!J14) | J56: =IF('Quality-Stat'!K14="","",'Quality-Stat'!K14) | K56: =IF('Quality-Stat'!L14="","",'Quality-Stat'!L14) -> 53 | L56: Non Conformance (NCR) | N56: ='Quality-Stat'!C5 -> 11 | O56: ='Quality-Stat'!D5 -> 11 | P56: ='Quality-Stat'!E5 -> 0 | Q56: ='Quality-Stat'!F5 -> 5 | R56: ='Quality-Stat'!G5 -> 0 | S56: ='Quality-Stat'!H5 -> 0 | T56: ='Quality-Stat'!I5 -> 0 | U56: ='Quality-Stat'!J5 -> 0 | V56: ='Quality-Stat'!K5 -> 0 | X56: ='HSE-Stat'!B5 -> Safe Hours Worked | Z56: 6360 | AB56: ='HSE-Stat'!E5 -> 20640 | AC56: ='HSE-Stat'!F5 -> 371624 | AD56: ='HSE-Stat'!G5 -> 371624 | AG56: Reactive | AH56: =SUM(AD57:AD66) -> 0
A57: ='Quality-Stat'!$A$15 -> TSE Network | C57: =IF('Quality-Stat'!D15="","",'Quality-Stat'!D15) -> 50 | D57: =IF('Quality-Stat'!E15="","",'Quality-Stat'!E15) -> 0 | E57: =IF('Quality-Stat'!F15="","",'Quality-Stat'!F15) -> 50 | F57: =IF('Quality-Stat'!G15="","",'Quality-Stat'!G15) -> 0 | G57: =IF('Quality-Stat'!H15="","",'Quality-Stat'!H15) -> 0 | H57: =IF('Quality-Stat'!I15="","",'Quality-Stat'!I15) -> 50 | I57: =IF('Quality-Stat'!J15="","",'Quality-Stat'!J15) -> 0 | J57: =IF('Quality-Stat'!K15="","",'Quality-Stat'!K15) | K57: =IF('Quality-Stat'!L15="","",'Quality-Stat'!L15) -> 50 | L57: Site Instruction (SIR) | N57: ='Quality-Stat'!C6 -> 20 | O57: ='Quality-Stat'!D6 -> 20 | P57: ='Quality-Stat'!E6 -> 0 | Q57: ='Quality-Stat'!F6 -> 6 | R57: ='Quality-Stat'!G6 -> 0 | S57: ='Quality-Stat'!H6 -> 0 | T57: ='Quality-Stat'!I6 -> 0 | U57: ='Quality-Stat'!J6 -> 0 | V57: ='Quality-Stat'!K6 -> 0 | W57: Reactive | X57: ='HSE-Stat'!B6 -> LTI | Z57: ='HSE-Stat'!D6 -> 0 | AB57: ='HSE-Stat'!E6 -> 0 | AC57: ='HSE-Stat'!F6 -> 0 | AD57: ='HSE-Stat'!G6 -> 0
A58: ='Quality-Stat'!$A$16 -> Sewerage Network | C58: =IF('Quality-Stat'!D16="","",'Quality-Stat'!D16) -> 25 | D58: =IF('Quality-Stat'!E16="","",'Quality-Stat'!E16) -> 25 | E58: =IF('Quality-Stat'!F16="","",'Quality-Stat'!F16) -> 0 | F58: =IF('Quality-Stat'!G16="","",'Quality-Stat'!G16) -> 0 | G58: =IF('Quality-Stat'!H16="","",'Quality-Stat'!H16) -> 0 | H58: =IF('Quality-Stat'!I16="","",'Quality-Stat'!I16) -> 25 | I58: 0 | K58: =IF('Quality-Stat'!L16="","",'Quality-Stat'!L16) -> 27 | L58: Material Inspection (MIR) | N58: ='Quality-Stat'!C7 -> 223 | O58: ='Quality-Stat'!D7 -> 221 | P58: ='Quality-Stat'!E7 -> 2 | Q58: ='Quality-Stat'!F7 -> 2 | R58: ='Quality-Stat'!G7 -> 2 | S58: ='Quality-Stat'!H7 -> 0 | T58: ='Quality-Stat'!I7 -> 0 | U58: ='Quality-Stat'!J7 -> 0 | V58: ='Quality-Stat'!K7 -> 0 | X58: ='HSE-Stat'!B7 -> MTC (Healed w/o Disability) | Z58: ='HSE-Stat'!D7 -> 0 | AB58: ='HSE-Stat'!E7 -> 0 | AC58: ='HSE-Stat'!F7 -> 0 | AD58: ='HSE-Stat'!G7 -> 0
A59: ='Quality-Stat'!$A$17 -> Storm Water Network | C59: =IF('Quality-Stat'!D16="","",'Quality-Stat'!D16) -> 25 | D59: =IF('Quality-Stat'!E17="","",'Quality-Stat'!E17) -> 41 | E59: =IF('Quality-Stat'!F17="","",'Quality-Stat'!F17) -> 33 | F59: =IF('Quality-Stat'!G17="","",'Quality-Stat'!G17) -> 2 | G59: =IF('Quality-Stat'!H17="","",'Quality-Stat'!H17) -> 0 | H59: =IF('Quality-Stat'!I16="","",'Quality-Stat'!I16) -> 25 | I59: =IF('Quality-Stat'!J17="","",'Quality-Stat'!J17) -> 0 | J59: =IF('Quality-Stat'!K17="","",'Quality-Stat'!K17) | K59: =IF('Quality-Stat'!L17="","",'Quality-Stat'!L17) -> 35
A60: ROAD | C60: =IF('Quality-Stat'!D17="","",'Quality-Stat'!D17) -> 45 | D60: =IF('Quality-Stat'!E18="","",'Quality-Stat'!E18) -> 37 | E60: =IF('Quality-Stat'!F18="","",'Quality-Stat'!F18) -> 122 | F60: =IF('Quality-Stat'!G18="","",'Quality-Stat'!G18) -> 2 | G60: =IF('Quality-Stat'!H18="","",'Quality-Stat'!H18) -> 0 | H60: =IF('Quality-Stat'!I17="","",'Quality-Stat'!I17) -> 45 | I60: =IF('Quality-Stat'!J18="","",'Quality-Stat'!J18) | J60: =IF('Quality-Stat'!K18="","",'Quality-Stat'!K18) | K60: =IF('Quality-Stat'!L18="","",'Quality-Stat'!L18) -> 161 | L60: Field Inspection (FIR) | N60: ='Quality-Stat'!C8 -> 6764 | O60: ='Quality-Stat'!D8 -> 6526 | P60: ='Quality-Stat'!E8 -> 238 | Q60: ='Quality-Stat'!F8 -> 1 | R60: ='Quality-Stat'!G8 -> 237 | S60: ='Quality-Stat'!H8 -> 0 | T60: ='Quality-Stat'!I8 -> 0 | U60: ='Quality-Stat'!J8 -> 0 | V60: ='Quality-Stat'!K8 -> 0 | X60: ='HSE-Stat'!B8 -> MTC (Healed w/ Disability) | Z60: ='HSE-Stat'!D8 -> 0 | AB60: ='HSE-Stat'!E8 -> 0 | AC60: ='HSE-Stat'!F8 -> 0 | AD60: ='HSE-Stat'!G8 -> 0
A61: TOTAL | C61: =SUM(C55:C60) -> 300 | D61: =SUM(D55:D60) -> 186 | E61: =SUM(E55:E60) -> 277 | F61: =SUM(F55:F60) -> 4 | G61: =SUM(G55:G60) -> 0 | H61: =SUM(H55:H60) -> 300 | I61: =SUM(I55:I60) -> 0 | J61: =SUM(J55:J60) -> 0 | K61: =SUM(K55:K60) -> 428 | L61: Key Submittals Approval Status | X61: ='HSE-Stat'!B9 -> Near Miss | Z61: ='HSE-Stat'!D9 -> 0 | AB61: ='HSE-Stat'!E9 -> 0 | AC61: ='HSE-Stat'!F9 -> 0 | AD61: ='HSE-Stat'!G9 -> 0
A62: Material Approval | L62: 1 Quality Plan Approval | O62: ='General Information'!C27 -> 45963 | Q62: 6 Baseline Approval | U62: ='General Information'!C39 -> 45964 | X62: ='HSE-Stat'!B10 -> First Aid Cases | Z62: ='HSE-Stat'!D10 -> 0 | AB62: ='HSE-Stat'!E10 -> 0 | AC62: ='HSE-Stat'!F10 -> 0 | AD62: ='HSE-Stat'!G10 -> 0 | AE62: Total Hours Worked Vs Safe Hours Worked
A63: Item Per WBS | C63: Total | D63: Total Submitted Material | I63: Remaining to approve | J63: Pending | K63: Total Submittals | L63: 2 Quality Plan Last Up | O63: ='General Information'!C28 -> 45963 | Q63: 7 No of Approved Version of Schedule | U63: ='General Information'!C40 -> 2 | X63: ='HSE-Stat'!B11 -> Fatality | Z63: ='HSE-Stat'!D11 -> 0 | AB63: ='HSE-Stat'!E11 -> 0 | AC63: ='HSE-Stat'!F11 -> 0 | AD63: ='HSE-Stat'!G11 -> 0
D64: A | E64: B | F64: C | G64: D | H64: Processed | I64: with Designer | L64: 3 Safety Plan Approval | O64: ='General Information'!C31 -> 45950 | Q64: 8 Last Approved Schedule | U64: ='General Information'!C41 -> 45964 | X64: ='HSE-Stat'!B12 -> Fire Incident Cases | Z64: ='HSE-Stat'!D12 -> 0 | AB64: ='HSE-Stat'!E12 -> 0 | AC64: ='HSE-Stat'!F12 -> 0 | AD64: ='HSE-Stat'!G12 -> 0
A65: ='Quality-Stat'!$A$25 -> Electrical Network - Road Lighting | C65: =IF('Quality-Stat'!D25="","",'Quality-Stat'!D25) | D65: =IF('Quality-Stat'!E25="","",'Quality-Stat'!E25) -> 0 | E65: =IF('Quality-Stat'!F25="","",'Quality-Stat'!F25) -> 26 | F65: =IF('Quality-Stat'!G25="","",'Quality-Stat'!G25) -> 0 | G65: =IF('Quality-Stat'!H25="","",'Quality-Stat'!H25) -> 0 | H65: =IF('Quality-Stat'!I25="","",'Quality-Stat'!I25) -> 25 | I65: =IF('Quality-Stat'!J25="","",'Quality-Stat'!J25) -> 0 | J65: =IF('Quality-Stat'!K25="","",'Quality-Stat'!K25) -> 0 | K65: =IF('Quality-Stat'!L25="","",'Quality-Stat'!L25) -> 26 | L65: 4 Safety Plan Last Up | O65: ='General Information'!C32 -> 45950 | Q65: 9 BOQ Approval Date | U65: ='General Information'!C44 -> 0 | X65: ='HSE-Stat'!B13 -> Vehicle Incident | Z65: ='HSE-Stat'!D13 -> 0 | AB65: ='HSE-Stat'!E13 -> 0 | AC65: ='HSE-Stat'!F13 -> 0 | AD65: ='HSE-Stat'!G13 -> 0
A66: ='Quality-Stat'!$A$26 -> Potable Water Network | C66: =IF('Quality-Stat'!D26="","",'Quality-Stat'!D26) -> 0 | D66: =IF('Quality-Stat'!E26="","",'Quality-Stat'!E26) -> 0 | E66: =IF('Quality-Stat'!F26="","",'Quality-Stat'!F26) -> 6 | F66: =IF('Quality-Stat'!G26="","",'Quality-Stat'!G26) -> 0 | G66: =IF('Quality-Stat'!H26="","",'Quality-Stat'!H26) -> 0 | H66: =IF('Quality-Stat'!I26="","",'Quality-Stat'!I26) -> 5 | I66: =IF('Quality-Stat'!J26="","",'Quality-Stat'!J26) -> 0 | J66: =IF('Quality-Stat'!K26="","",'Quality-Stat'!K26) -> 1 | K66: =IF('Quality-Stat'!L26="","",'Quality-Stat'!L26) -> 6 | L66: 5 Construction Plan Approval | O66: ='General Information'!#REF! -> #REF! | Q66: 10 No of Approved Version of BOQ | U66: ='General Information'!C45 -> 0 | X66: ='HSE-Stat'!B14 -> Property Damages | Z66: ='HSE-Stat'!D14 -> 0 | AB66: ='HSE-Stat'!E14 -> 0 | AC66: ='HSE-Stat'!F14 -> 0 | AD66: ='HSE-Stat'!G14 -> 0
A67: ='Quality-Stat'!$A$27 -> TSE Network | C67: =IF('Quality-Stat'!D27="","",'Quality-Stat'!D27) -> 0 | D67: =IF('Quality-Stat'!E27="","",'Quality-Stat'!E27) -> 0 | E67: =IF('Quality-Stat'!F27="","",'Quality-Stat'!F27) -> 6 | F67: =IF('Quality-Stat'!G27="","",'Quality-Stat'!G27) -> 0 | G67: =IF('Quality-Stat'!H27="","",'Quality-Stat'!H27) -> 0 | H67: =IF('Quality-Stat'!I27="","",'Quality-Stat'!I27) -> 6 | I67: =IF('Quality-Stat'!J27="","",'Quality-Stat'!J27) -> 0 | J67: =IF('Quality-Stat'!K27="","",'Quality-Stat'!K27) -> 0 | K67: =IF('Quality-Stat'!L27="","",'Quality-Stat'!L27) -> 6 | L67: Invoices Summary | W67: Proactive | X67: ='HSE-Stat'!B15 -> Induction Training | Z67: 0 | AB67: ='HSE-Stat'!E15 -> 0 | AC67: ='HSE-Stat'!F15 -> 7 | AD67: ='HSE-Stat'!G15 -> 8
A68: ='Quality-Stat'!$A$28 -> Sewerage Network | C68: =IF('Quality-Stat'!D28="","",'Quality-Stat'!D28) -> 0 | D68: =IF('Quality-Stat'!E28="","",'Quality-Stat'!E28) -> 0 | E68: =IF('Quality-Stat'!F28="","",'Quality-Stat'!F28) -> 7 | F68: =IF('Quality-Stat'!G28="","",'Quality-Stat'!G28) -> 0 | G68: =IF('Quality-Stat'!H28="","",'Quality-Stat'!H28) -> 0 | H68: =IF('Quality-Stat'!I28="","",'Quality-Stat'!I28) -> 6 | I68: =IF('Quality-Stat'!J28="","",'Quality-Stat'!J28) -> 0 | J68: =IF('Quality-Stat'!K28="","",'Quality-Stat'!K28) -> 0 | K68: =IF('Quality-Stat'!L28="","",'Quality-Stat'!L28) -> 7 | L68: Total Submitted Invoices | N68: ='Invoice Log'!U3 -> 13 | O68: Submitted Invoices (SAR) | R68: ='Invoice Log'!Y3 -> 43497867 | T68: Contract Value (SR) | U68: =O4 -> 140467862 | X68: ='HSE-Stat'!B16 -> No.of Internal Training | Z68: ='HSE-Stat'!D16 -> 0 | AB68: ='HSE-Stat'!E16 -> 1 | AC68: ='HSE-Stat'!F16 -> 18 | AD68: ='HSE-Stat'!G16 -> 18
A69: ='Quality-Stat'!$A$29 -> Storm Water Network | C69: =IF('Quality-Stat'!D29="","",'Quality-Stat'!D29) -> 0 | D69: =IF('Quality-Stat'!E29="","",'Quality-Stat'!E29) -> 0 | E69: =IF('Quality-Stat'!F29="","",'Quality-Stat'!F29) -> 7 | F69: =IF('Quality-Stat'!G29="","",'Quality-Stat'!G29) -> 0 | G69: =IF('Quality-Stat'!H29="","",'Quality-Stat'!H29) -> 0 | H69: =IF('Quality-Stat'!I29="","",'Quality-Stat'!I29) -> 6 | I69: =IF('Quality-Stat'!J29="","",'Quality-Stat'!J29) -> 0 | J69: =IF('Quality-Stat'!K29="","",'Quality-Stat'!K29) -> 0 | K69: =IF('Quality-Stat'!L29="","",'Quality-Stat'!L29) -> 7 | L69: PM Approved Invoices | N69: ='Invoice Log'!U5 -> 9 | O69: PM Approved Invoices (SAR) | R69: ='Invoice Log'!Y5 -> 29853856 | T69: Planned Value (SR) | U69: =H22 -> 52406756 | X69: ='HSE-Stat'!B17 -> No.of Internal Audit | Z69: ='HSE-Stat'!D17 -> 0 | AB69: ='HSE-Stat'!E17 -> 0 | AC69: ='HSE-Stat'!F17 -> 0 | AD69: ='HSE-Stat'!G17 -> 0
A70: TOTAL | C70: =SUM(C65:C69) -> 0 | D70: =SUM(D65:D69) -> 0 | E70: =SUM(E65:E69) -> 52 | F70: =SUM(F65:F69) -> 0 | G70: =SUM(G65:G69) -> 0 | H70: =SUM(H65:H69) -> 48 | I70: =SUM(I65:I69) -> 0 | J70: =SUM(J65:J69) -> 1 | K70: =SUM(K65:K69) -> 52 | L70: No of Paid Invoices | N70: ='Invoice Log'!U6 -> 9 | O70: Paid Invoices (SAR) | R70: ='Invoice Log'!Y6 -> 34389935 | T70: Earned Value (SR) | U70: =I22 -> 66820405 | X70: ='HSE-Stat'!B18 -> No. of Toolbox Talks | Z70: ='HSE-Stat'!D18 -> 1 | AB70: ='HSE-Stat'!E18 -> 2 | AC70: ='HSE-Stat'!F18 -> 36 | AD70: ='HSE-Stat'!G18 -> 36
A71: Procurement Summary | L71: No of Pending Invoices | N71: =N69-N70 -> 0 | O71: Last Submitted Period | R71: ='Invoice Log'!AB3 -> 46295 | T71: Submitted (SAR) | U71: =R68 -> 43497867 | X71: ='HSE-Stat'!B19 -> Safety Awards/Incentives | Z71: ='HSE-Stat'!D19 -> 0 | AB71: ='HSE-Stat'!E19 -> 0 | AC71: ='HSE-Stat'!F19 -> 0 | AD71: ='HSE-Stat'!G19 -> 0
A72: Item Per WBS | C72: Total Materials | D72: Total Number of P.O. | E72: Actual P.O. To Date | F72: Remaining P.O | G72: Material on Site | H72: Remaining Materials | I72: Material Delivery Completion (Date) | L72: Advance Payment % | N72: ='Invoice Log'!M3 -> 0.1 | O72: Advance Payment (SAR) | R72: ='Invoice Log'!Q3 -> 14046786 | T72: PM Approved (SAR) | U72: =R69 -> 29853856 | W72: Latest Contract Change Order Log
D73: A | E73: B | F73: C | G73: D | H73: Processed | L73: Retention % | N73: ='Invoice Log'!M4 -> 0 | O73: Retention (SAR) | R73: ='Invoice Log'!Q4 -> 0 | T73: Total Paid (SAR) | U73: =R70 -> 34389935
A74: ='Quality-Stat'!$A$35 -> Electrical Network - Road Lighting | C74: =IF('Quality-Stat'!D35="","",'Quality-Stat'!D35) -> 9 | D74: =IF('Quality-Stat'!E35="","",'Quality-Stat'!E35) -> 9 | E74: =IF('Quality-Stat'!F35="","",'Quality-Stat'!F35) -> 7 | F74: =IF('Quality-Stat'!G35="","",'Quality-Stat'!G35) -> 2 | G74: =IF('Quality-Stat'!H35="","",'Quality-Stat'!H35) -> 8000 | H74: =IF('Quality-Stat'!I35="","",'Quality-Stat'!I35) -> 0 | L74: Deduction / Penalties % | N74: ='Invoice Log'!M5 -> 0.00041290584 | O74: Deduction / Penalties (SAR) | R74: ='Invoice Log'!M6 -> 58000 | W74: CCO No. | X74: Date Added | Y74: Description of Change | AD74: Status | AE74: Cost | AF74: Sch Impact (Months) | AG74: Date Approved | AH74: Duration
A75: ='Quality-Stat'!$A$36 -> Potable Water Network | C75: =IF('Quality-Stat'!D36="","",'Quality-Stat'!D36) -> 3 | D75: =IF('Quality-Stat'!E36="","",'Quality-Stat'!E36) -> 3 | E75: =IF('Quality-Stat'!F36="","",'Quality-Stat'!F36) -> 3 | F75: =IF('Quality-Stat'!G36="","",'Quality-Stat'!G36) -> 0 | G75: =IF('Quality-Stat'!H36="","",'Quality-Stat'!H36) -> 6474 | H75: =IF('Quality-Stat'!I36="","",'Quality-Stat'!I36) -> 6248 | L75: Resources at Site
A76: ='Quality-Stat'!$A$37 -> TSE Network | C76: =IF('Quality-Stat'!D37="","",'Quality-Stat'!D37) -> 2 | D76: =IF('Quality-Stat'!E37="","",'Quality-Stat'!E37) -> 2 | E76: =IF('Quality-Stat'!F37="","",'Quality-Stat'!F37) -> 2 | F76: =IF('Quality-Stat'!G37="","",'Quality-Stat'!G37) -> 0 | G76: =IF('Quality-Stat'!H37="","",'Quality-Stat'!H37) -> 6474 | H76: =IF('Quality-Stat'!I37="","",'Quality-Stat'!I37) -> 6248 | L76: Head Count - Non Manual | P76: Head Count - Manual | T76: Total Head Count | W76: =CCO!A3 -> 0 | X76: =CCO!B3 -> 0 | Y76: =CCO!C3 -> 0 | AD76: =CCO!D3 -> 0 | AE76: =CCO!E3 -> 0 | AF76: =CCO!F3 -> 0 | AG76: =CCO!G3 -> 0 | AH76: =CCO!H3 -> 0
A77: ='Quality-Stat'!$A$38 -> Sewerage Network | C77: =IF('Quality-Stat'!D38="","",'Quality-Stat'!D38) -> 2 | D77: =IF('Quality-Stat'!E38="","",'Quality-Stat'!E38) -> 2 | E77: =IF('Quality-Stat'!F38="","",'Quality-Stat'!F38) -> 2 | F77: =IF('Quality-Stat'!G38="","",'Quality-Stat'!G38) -> 0 | G77: =IF('Quality-Stat'!H38="","",'Quality-Stat'!H38) -> 7045 | H77: =IF('Quality-Stat'!I38="","",'Quality-Stat'!I38) -> 275 | L77: Planned | M77: Actual | N77: Next Month Forecast | O77: Saudi Staff | P77: Planned | Q77: Actual | R77: Next Month Forecast | S77: Saudi Staff | T77: Total Plan | U77: Total Actual | V77: Variance
A78: ='Quality-Stat'!$A$39 -> Storm Water Network | C78: =IF('Quality-Stat'!D39="","",'Quality-Stat'!D39) -> 6 | D78: =IF('Quality-Stat'!E39="","",'Quality-Stat'!E39) -> 6 | E78: =IF('Quality-Stat'!F39="","",'Quality-Stat'!F39) -> 6 | F78: =IF('Quality-Stat'!G39="","",'Quality-Stat'!G39) -> 0 | G78: =IF('Quality-Stat'!H39="","",'Quality-Stat'!H39) -> 16049 | H78: =IF('Quality-Stat'!I39="","",'Quality-Stat'!I39) -> 136 | L78: =Manpower!A20 -> 28 | M78: =Manpower!B20 -> 32 | N78: =Manpower!F20 -> 28 | O78: 4 | P78: =M92 -> 141 | Q78: =N92 -> 358 | R78: =Manpower!F24 -> 63 | S78: =Manpower!H24 -> 0 | T78: =L78+P78 -> 169 | U78: =M78+Q78 -> 390 | V78: =+U78-T78 -> 221 | W78: =CCO!A4 | X78: =CCO!B4 | Y78: =CCO!C4 | AD78: =IF(CCO!D4="","",CCO!D4) | AE78: =CCO!E4 | AF78: =CCO!F4 | AG78: =CCO!G4 | AH78: =CCO!H4
A79: TOTAL | C79: =IF('Quality-Stat'!D41="","",'Quality-Stat'!D41) -> 29 | D79: =IF('Quality-Stat'!E41="","",'Quality-Stat'!E41) -> 29 | E79: =IF('Quality-Stat'!F41="","",'Quality-Stat'!F41) -> 27 | F79: =IF('Quality-Stat'!G41="","",'Quality-Stat'!G41) -> 2 | G79: =IF('Quality-Stat'!H41="","",'Quality-Stat'!H41) -> 45142 | H79: =IF('Quality-Stat'!I41="","",'Quality-Stat'!I41) -> 12907 | L79: Manpower Breakdown by Trade | S79: Major Equipment
A80: =Schedule!A1 -> Primavera P6 Schedule Status | L80: Key Trade | M80: Planned | N80: Actual | S80: Type | T80: Planned | U80: Actual | V80: Idle | W80: =CCO!A5 | X80: =CCO!B5 | Y80: =CCO!C5 | AD80: =IF(CCO!D5="","",CCO!D5) | AE80: =CCO!E5 | AF80: =CCO!F5 | AG80: =CCO!G5 | AH80: =CCO!H5
A81: =Schedule!A2 -> Project Activities Overview | L81: =+Manpower!N23 -> General Labor | M81: =Manpower!N24 -> 13 | N81: =Manpower!N25 -> 70 | S81: =+Manpower!$B$49 -> Excavator | T81: =+Manpower!B50 -> 15 | U81: =+Manpower!B51 -> 22 | V81: =+Manpower!B52 -> 0
A82: =Schedule!A3 -> Schedule Statistics | F82: =Schedule!F3 -> Active Schedule Activities | L82: =+Manpower!R23 -> Carpenter | M82: =Manpower!R24 -> 0 | N82: =Manpower!R25 -> 15 | S82: =+Manpower!$D$49 -> Loader | T82: =+Manpower!D50 -> 1 | U82: =+Manpower!D51 -> 4 | V82: =+Manpower!D52 -> 0 | W82: Major Quantity Trackers
A83: =Schedule!A4 -> Total Act. | B83: =Schedule!B4 -> Not Started | C83: =Schedule!C4 -> In Progress | D83: =Schedule!D4 -> Completed | E83: =Schedule!E4 -> % | F83: =Schedule!F4 -> Active | G83: =Schedule!G4 -> Ahead | H83: =Schedule!H4 -> On | ... K83: =Schedule!K4 -> 0 | L83: =+Manpower!T23 -> Plumber | M83: =+Manpower!T24 -> 5 | N83: =Manpower!T25 -> 13 | S83: =+Manpower!$F$49 -> Dozer | T83: =+Manpower!F50 -> 1 | U83: =+Manpower!F51 -> 1 | V83: =+Manpower!F52 -> 0 | W83: BOQ N0. | X83: Item Description | AC83: Total Qty | AD83: Measu Unit | AE83: Plan to Date | AF83: Act to Date | AG83: Remaining | AH83: Variance
A84: =Schedule!A5 -> 1492 | B84: =Schedule!B5 -> 712 | C84: =Schedule!C5 -> 205 | D84: =Schedule!D5 -> 575 | E84: =Schedule!E5 -> 0.38538874 | F84: =Schedule!F5 -> 205 | G84: =Schedule!G5 -> 189 | H84: =Schedule!H5 -> 16 | ... J84: =Schedule!J5 -> 205 | L84: =+Manpower!V23 -> OPERATOR | M84: =Manpower!V24 -> 19 | N84: =Manpower!V25 -> 38 | S84: =+Manpower!$H$49 -> Dump truck | T84: =+Manpower!H50 -> 16 | U84: =+Manpower!H51 -> 10 | V84: =+Manpower!H52 -> 0 | W84: ='Major Quantities'!A2 -> 31 22 00 05 | X84: ='Major Quantities'!B2 -> POND Excavation | AC84: =VLOOKUP(X84,'Major Quantities'!$B$2:$G$20,2,FALSE) -> 321070 | AD84: =VLOOKUP(X84,'Major Quantities'!$B$2:$G$20,3,FALSE) -> M3 | AE84: =VLOOKUP(X84,'Major Quantities'!$B$2:$G$20,4,FALSE) -> 296255 | AF84: =VLOOKUP(X84,'Major Quantities'!$B$2:$G$20,5,FALSE) -> 296255 | AG84: =VLOOKUP(X84,'Major Quantities'!$B$2:$G$20,6,FALSE) -> 24815 | AH84: =VLOOKUP(X84,'Major Quantities'!$B$2:$H$20,7,FALSE) -> 0
A85: =Schedule!A6 -> Critical Path Activities | D85: =Schedule!D6 -> Free Float Management (Total) | H85: =Schedule!H6 -> Failed Start Activities | L85: =+Manpower!X23 -> Steel Fixer | M85: =+Manpower!X24 -> 0 | N85: =Manpower!X25 -> 6 | S85: =+Manpower!$J$49 -> Water tanker | T85: =+Manpower!J50 -> 2 | U85: =+Manpower!J51 -> 4 | V85: =+Manpower!J52 -> 0 | W85: ='Major Quantities'!A3 -> 31 22 00 01 | X85: ='Major Quantities'!B3 -> ROAD Excavation | AC85: =VLOOKUP(X85,'Major Quantities'!$B$2:$G$20,2,FALSE) -> 99925 | AD85: =VLOOKUP(X85,'Major Quantities'!$B$2:$G$20,3,FALSE) -> M3 | AE85: =VLOOKUP(X85,'Major Quantities'!$B$2:$G$20,4,FALSE) -> 99925 | AF85: =VLOOKUP(X85,'Major Quantities'!$B$2:$G$20,5,FALSE) -> 93475 | AG85: =VLOOKUP(X85,'Major Quantities'!$B$2:$G$20,6,FALSE) -> 6450 | AH85: =VLOOKUP(X85,'Major Quantities'!$B$2:$H$20,7,FALSE) -> -6450
D86: =Schedule!D7 -> Greater Than 14 Days | F86: =Schedule!F7 -> Less Than 14 Days | L86: =+Manpower!Z23 -> Driver | M86: =+Manpower!Z24 -> 18 | N86: =Manpower!Z25 -> 19 | S86: =+Manpower!$R$49 -> Grader | T86: =+Manpower!R50 -> 1 | U86: =+Manpower!R51 -> 2 | V86: =+Manpower!R52 -> 0 | W86: ='Major Quantities'!A4 -> 31 22 00 02 | X86: ='Major Quantities'!B4 -> ROAD BACKFILL | AC86: =VLOOKUP(X86,'Major Quantities'!$B$2:$G$20,2,FALSE) -> 107100 | AD86: =VLOOKUP(X86,'Major Quantities'!$B$2:$G$20,3,FALSE) -> M3 | AE86: =VLOOKUP(X86,'Major Quantities'!$B$2:$G$20,4,FALSE) -> 107100 | AF86: =VLOOKUP(X86,'Major Quantities'!$B$2:$G$20,5,FALSE) -> 81600 | AG86: =VLOOKUP(X86,'Major Quantities'!$B$2:$G$20,6,FALSE) -> 25500 | AH86: =VLOOKUP(X86,'Major Quantities'!$B$2:$H$20,7,FALSE) -> -25500
L87: =Manpower!P23 -> Milling | M87: =Manpower!P24 -> 1 | N87: =Manpower!P25 -> 0 | S87: =Manpower!P49 -> MILLING MACHINE | T87: =Manpower!P50 -> 1 | U87: =Manpower!P51 -> 1 | V87: =+Manpower!P53 -> 0 | W87: ='Major Quantities'!A5 -> 32 22 00 03 | X87: ='Major Quantities'!B5 -> ROAD SUPGRADE | AC87: ='Major Quantities'!C5 -> 72730 | AD87: =VLOOKUP(X87,'Major Quantities'!$B$2:$G$20,3,FALSE) -> M3 | AE87: =VLOOKUP(X87,'Major Quantities'!$B$2:$G$20,4,FALSE) -> 72730 | AF87: =VLOOKUP(X87,'Major Quantities'!$B$2:$G$20,5,FALSE) -> 53900 | AG87: =VLOOKUP(X87,'Major Quantities'!$B$2:$G$20,6,FALSE) -> 18830 | AH87: =VLOOKUP(X87,'Major Quantities'!$B$2:$H$20,7,FALSE) -> -18830
A88: =Schedule!A8 -> Last Week | B88: =Schedule!B8 -> This Week | C88: =Schedule!C8 -> Diff | D88: =Schedule!D8 -> Last Week | E88: =Schedule!E8 -> This Week | F88: =Schedule!F8 -> Last Week | G88: =Schedule!G8 -> This Week | H88: =Schedule!H8 -> Last Week | ... K88: =Schedule!K8 -> 0 | L88: =+Manpower!AH23 -> Total | M88: =+Manpower!AH24 -> 85 | N88: =Manpower!AH25 -> 197 | S88: =+Manpower!$AD$49 -> Roller | T88: =+Manpower!AD50 -> 1 | U88: =+Manpower!AD51 -> 4 | V88: =+Manpower!V52 -> 0 | W88: ='Major Quantities'!A6 -> 33 31 00 | X88: ='Major Quantities'!B6 -> SEWAGE network | AC88: =VLOOKUP(X88,'Major Quantities'!$B$2:$G$20,2,FALSE) -> 8370 | AD88: =VLOOKUP(X88,'Major Quantities'!$B$2:$G$20,3,FALSE) -> M | AE88: =VLOOKUP(X88,'Major Quantities'!$B$2:$G$20,4,FALSE) -> 0 | AF88: =VLOOKUP(X88,'Major Quantities'!$B$2:$G$20,5,FALSE) -> 6965 | AG88: =VLOOKUP(X88,'Major Quantities'!$B$2:$G$20,6,FALSE) -> 1405 | AH88: =VLOOKUP(X88,'Major Quantities'!$B$2:$H$20,7,FALSE) -> 6965
A89: =Schedule!A9 -> 188 | B89: =Schedule!B9 -> 200 | C89: =Schedule!C9 -> -12 | D89: =Schedule!D9 -> 0 | E89: =Schedule!E9 -> 0 | F89: =Schedule!F9 -> 0 | G89: =Schedule!G9 -> 0 | H89: =Schedule!H9 -> 24 | ... J89: =Schedule!J9 -> 0 | S89: =Manpower!V49 -> Desil tanker | T89: =Manpower!V50 -> 0 | U89: =Manpower!V51 -> 1 | V89: =Manpower!X52 -> 0 | W89: ='Major Quantities'!A7 -> 33 31 00 | X89: ='Major Quantities'!B7 -> STORM network | AC89: =VLOOKUP(X89,'Major Quantities'!$B$2:$G$20,2,FALSE) -> 15638 | AD89: =VLOOKUP(X89,'Major Quantities'!$B$2:$G$20,3,FALSE) -> M | AE89: =VLOOKUP(X89,'Major Quantities'!$B$2:$G$20,4,FALSE) -> 0 | AF89: =VLOOKUP(X89,'Major Quantities'!$B$2:$G$20,5,FALSE) -> 13112 | AG89: =VLOOKUP(X89,'Major Quantities'!$B$2:$G$20,6,FALSE) -> 2526 | AH89: =VLOOKUP(X89,'Major Quantities'!$B$2:$H$20,7,FALSE) -> 13112
S90: =Manpower!T49 -> PAVER BASE COURSE | T90: =Manpower!T50 -> 0 | U90: =Manpower!T51 -> 1 | V90: =Manpower!T52 -> 1 | X90: ='Major Quantities'!B8 -> BACKFILLING DIKE | AC90: =VLOOKUP(X90,'Major Quantities'!$B$2:$G$20,2,FALSE) -> 3865 | AD90: =VLOOKUP(X90,'Major Quantities'!$B$2:$G$20,3,FALSE) -> M3 | AE90: =VLOOKUP(X90,'Major Quantities'!$B$2:$G$20,4,FALSE) -> 0 | AF90: =VLOOKUP(X90,'Major Quantities'!$B$2:$G$20,5,FALSE) -> 3865 | AG90: =VLOOKUP(X90,'Major Quantities'!$B$2:$G$20,6,FALSE) -> 0 | AH90: =VLOOKUP(X90,'Major Quantities'!$B$2:$H$20,7,FALSE) -> 3865
S91: =Manpower!L49 -> SCREEN | T91: =Manpower!L50 -> 0 | U91: =Manpower!L51 -> 2 | V91: =Manpower!L52 -> 0 | X91: ='Major Quantities'!B9 -> TSE network | AC91: =VLOOKUP(X91,'Major Quantities'!$B$2:$G$20,2,FALSE) -> 12223 | AD91: =VLOOKUP(X91,'Major Quantities'!$B$2:$G$20,3,FALSE) -> M | AE91: =VLOOKUP(X91,'Major Quantities'!$B$2:$G$20,4,FALSE) -> 0 | AF91: =VLOOKUP(X91,'Major Quantities'!$B$2:$G$20,5,FALSE) -> 8178 | AG91: =VLOOKUP(X91,'Major Quantities'!$B$2:$G$20,6,FALSE) -> 4045 | AH91: =VLOOKUP(X91,'Major Quantities'!$B$2:$H$20,7,FALSE) -> 8178
L92: Total | M92: =SUM(M81:M88) -> 141 | N92: =SUM(N81:N88) -> 358 | S92: Total | T92: =SUM(T81:T91) -> 38 | U92: =SUM(U81:U91) -> 52 | V92: =SUM(V81:V91) -> 1 | X92: ='Major Quantities'!B10 -> POTABLE WATER network | AC92: =VLOOKUP(X92,'Major Quantities'!$B$2:$G$20,2,FALSE) -> 13221 | AD92: =VLOOKUP(X92,'Major Quantities'!$B$2:$G$20,3,FALSE) -> M | AE92: =VLOOKUP(X92,'Major Quantities'!$B$2:$G$20,4,FALSE) -> 0 | AF92: =VLOOKUP(X92,'Major Quantities'!$B$2:$G$20,5,FALSE) -> 9239 | AG92: =VLOOKUP(X92,'Major Quantities'!$B$2:$G$20,6,FALSE) -> 3982 | AH92: =VLOOKUP(X92,'Major Quantities'!$B$2:$H$20,7,FALSE) -> 9239
A93: Weekly Prgoress Photos | Q93: Top Issues and Risks
A94: ='Weekly Photos'!B23 -> excavation | F94: ='Weekly Photos'!L23 -> bbc | L94: ='Weekly Photos'!B4 -> KERBSTONE | Q94: Top 5 Issues
Q95: Issue No | R95: Date Identified | S95: Issue Description | W95: Responsible | X95: Action Taken | AA95: Mitigation | AF95: Current Status | AG95: Expected/Actual Closure | AH95: Duration Elapsed
Q96: =IF(+Issues!B11="","",+Issues!B11) -> 1 | R96: =IF(+Issues!C11="","",+Issues!C11) -> 45906 | S96: =IF(+Issues!D11="","",+Issues!D11) -> ELECTRICAL CABLE IN POND | W96: E | X96: =IF(+Issues!F11="","",+Issues!F11) -> DIVERT THE CABLE TO BE AWAY FROM THE POND | AF96: =IF(+Issues!H11="","",+Issues!H11) -> Close | AG96: =IF(+Issues!I11="","",+Issues!I11) -> 46132 | AH96: =IF(+Issues!J11="","",+Issues!J11) -> 226
Q97: =IF(+Issues!B12="","",+Issues!B12) -> 2 | R97: =IF(+Issues!C12="","",+Issues!C12) -> 46111 | S97: =IF(+Issues!D12="","",+Issues!D12) -> INDUSTRIAL FACILITIES ENCROACHING ON ROAD LOCAL1- 2-3-4-5-COLLECTOR 3-UPGRADE 39-21 | W97: =IF(+Issues!E12="","",+Issues!E12) -> Consultant | X97: =IF(+Issues!F12="","",+Issues!F12) -> THE RFI HAS BEEN RAISED REGRARDING NETWORK DAMAGE DUE TO INTERFERENCE WITH THE FACTORIES | AF97: =IF(+Issues!H12="","",+Issues!H12) -> Closed | AG97: =IF(+Issues!I12="","",+Issues!I12) -> 46141 | AH97: =IF(+Issues!J12="","",+Issues!J12) -> 30
Q98: =IF(+Issues!B13="","",+Issues!B13) -> 3 | R98: =IF(+Issues!C13="","",+Issues!C13) -> 46064 | S98: =IF(+Issues!D13="","",+Issues!D13) -> TELECOMMUNICATIONS NETWORK INTEGRATION & UNDERSIZED SERVER ROOM IN THE ADMINISTRATION BUILDING | W98: =IF(+Issues!E13="","",+Issues!E13) -> Contractor | X98: =IF(+Issues!F13="","",+Issues!F13) -> THE DRAWING ARE BEING SUBMITTED FOR APPROVAL | AF98: =IF(+Issues!H13="","",+Issues!H13) -> Closed | AG98: =IF(+Issues!I13="","",+Issues!I13) -> 46179 | AH98: =IF(+Issues!J13="","",+Issues!J13) -> 115
Q99: =IF(+Issues!B14="","",+Issues!B14) -> 4 | R99: =IF(+Issues!C14="","",+Issues!C14) -> 46148 | S99: =IF(+Issues!D14="","",+Issues!D14) -> DELAY IN PROCUREMENT FOR MV | W99: =IF(+Issues!E14="","",+Issues!E14) -> Contractor | X99: =IF(+Issues!F14="","",+Issues!F14) -> MATERIAL DELIVERY HAS STARTED | AF99: =IF(+Issues!H14="","",+Issues!H14) -> Closed | AG99: =IF(+Issues!I14="","",+Issues!I14) -> 46188 | AH99: =IF(+Issues!J14="","",+Issues!J14) -> 40
Q100: =IF(+Issues!B15="","",+Issues!B15) -> 5 | R100: =IF(+Issues!C15="","",+Issues!C15) -> 46139 | S100: =IF(+Issues!D15="","",+Issues!D15) -> DELAY IN PROCUREMENT DELIVERY OF MATERIALS INCLUDING CATCHBASIN - SLEEVES PIPES FOR UPVC & GRP | W100: =IF(+Issues!E15="","",+Issues!E15) -> Contractor | X100: =IF(+Issues!F15="","",+Issues!F15) -> PROCUREMENT ACTIVITIES WILL BE INITIATED | AF100: =IF(+Issues!H15="","",+Issues!H15) -> Closed | AG100: =IF(+Issues!I15="","",+Issues!I15) -> 46195 | AH100: =IF(+Issues!J15="","",+Issues!J15) -> 56

Sheet General Information
A1: Weekly Progress Report - Construction Projects | K1: Data Date | L1: 46307
A2: Contract General Information
A3: Project Name | C3: ADDITIONAL DEVELOPMENT IN TABOUK INDUSTRIAL CITY
A4: Project ID | C4: =Quality!E6 -> TAB1-02-003
A5: Contractor | C5: ASAS for Developing & Operating Industrial Cities
A6: Consultant | C6: EGIS
A7: Stage | C7: INFRASTRUCTURE & UTILITIES
A8: Status | C8: Active
A9: Modon PM | C9: ENG/ YAZEED ALRAGABAH
A11: Key Dates
A12: Contract Award Date | C12: =Milestones!C4 -> 45882
A13: Contract Sign Date | C13: =Milestones!C5 -> 45900
A14: Site Handover Date | C14: =Milestones!C6 -> 45904
A15: Original Completion | C15: =Milestones!C15 -> 46633
A16: Contract Award Date (Hijri) | C16: =C12 -> 45882
A17: Contract Sign Date (Hijri) | C17: =C13 -> 45900
A18: Site Handover Date (Hijri) | C18: =C14 -> 45904
A19: Original Completion (Hijri) | C19: =C15 -> 46633
A20: Revised Completion Date | C20: =C15 -> 46633
A21: Committed Completion Date | C21: =C15 -> 46633
A22: Forecast Completion | C22: =Milestones!E15 -> 46662
A23: Variance | C23: =C20-C22 -> -29
A25: Key Project Submittals | C25: Submission Date | D25: Days taken to approve orginal plan from site handover date
A26: Quality Plan submission | C26: 45931 | D26: =C26-C14 -> 27
A27: Quality Plan approval | C27: 45963
A28: Quality Plan Last Update | C28: 45963
A29: NO OF REVESION | C29: 3
A30: Safety Plan submission | C30: 45934 | D30: =C30-C14 -> 30
A31: Safety Plan approval | C31: 45950
A32: Safety Plan Last Update | C32: 45950
A33: NO OF REVESION | C33: 1
A34: Risk Management Plan submission
A35: Risk Management Plan approval
A36: Risk Management Plan Last Update
A38: Baseline Schedule submission | C38: 45944 | D38: =C38-C14 -> 40
A39: Baseline Schedule approval | C39: 45964
A40: No of Schedule Versions | C40: 2
A41: Last Recovery Schedule Approval Date | C41: 45964
A43: BOQ submission
A44: BOQ approval
A45: No of Approved Version of BOQ

Sheet Weekly Photos
B1: Date | C1: ='Weekly Progress Report'!AG1 -> 46307
B4: KERBSTONE | L4: ABC
B23: excavation | L23: bbc

Sheet Progress
A1: Project Scope Statement | B1: The project consists of roads works and the POND A which works as a downstream for the storm water wet utility piping network including manholes and catch basins, continued project wet utilities also sewerage GRP piping network with manholes, potable water and firefighting compound HDPE piping network including the installation of valves and fire hydrants and the irrigation water (TSE) network with all valves and the flow meter, dry utility represented in electrical road lighting network - the installation of poles and the LV cables which is connected to the panel board and the 13.8/0.4 K V unit substation. | S1: ='General Information'!$K$1 -> Data Date | T1: ='General Information'!L1 -> 46307
A4: Earned Value Progress (SAR) | K4: Physical Progress (Effort)
A5: WBS | C5: BOQ Value (SAR) | D5: % Wt. | E5: Weekly (SAR) | H5: To Date (SAR) | K5: Budgeted | L5: % Wt. | M5: Weekly Physical Progress | O5: To Date Physical Progress
E6: Planned | F6: Earned | G6: Original Plan | H6: Planned | I6: Earned | K6: (Manhours) | M6: Planned | N6: Earned | O6: Planned | P6: Earned
A7: MILESTONS | C7: =M51 -> 0 | D7: =IF(ISBLANK(C7),"",C7/$C$41) -> 0 | E7: =N51-W51 -> 0 | F7: =O51-X51 -> 0 | G7: =H7 -> 0 | H7: =I7 -> 0 | I7: =O51 -> 0 | K7: 0 | L7: =IF(ISBLANK(K7),"",K7/$K$41) -> 0 | M7: =D91 -> 0 | N7: =C91 -> 0 | O7: =G91 -> 0 | P7: =F91 -> 0
A8: MOBILIZATION | C8: 0 | D8: =IF(ISBLANK(C8),"",C8/$C$41) -> 0 | E8: 0 | F8: =O52-X52 -> 0 | G8: 0 | H8: 0 | I8: 0 | K8: 1600 | L8: =IF(ISBLANK(K8),"",K8/$K$41) -> 0.0045154499 | M8: =D92 -> 0 | N8: =C92 -> 0 | O8: =G92 -> 1600 | P8: =F92 -> 1600
A9: ENGINEERING | C9: 4214035 | D9: =IF(ISBLANK(C9),"",C9/$C$41) -> 0.029999994 | E9: =D48 -> 0 | F9: =C48 -> 0 | G9: =G48 -> 4214035 | H9: =G48 -> 4214035 | I9: =F48 -> 4214035.9 | K9: 0 | L9: =IF(ISBLANK(K9),"",K9/$K$41) -> 0 | M9: =D93 -> 0 | N9: =C93 -> 0 | O9: =G93 -> 0 | P9: =F93 -> 0
A10: PROCUREMENT | C10: 28093572 | D10: =IF(ISBLANK(C10),"",C10/$C$41) -> 0.2 | E10: =D49 -> 205448.67 | F10: =C49 -> 141539.04 | G10: 21377402 | H10: =G49 -> 15068661 | I10: =F49 -> 17171855 | K10: 0 | L10: =IF(ISBLANK(K10),"",K10/$K$41) -> 0 | M10: =D94 -> 0 | N10: =C94 -> 0 | O10: =G94 -> 0 | P10: =F94 -> 0
A11: CONSTRUCTION WORKS | C11: 94113469 | D11: =D12+D13+D14 -> 0.67000001 | E11: =D86 -> 298825.92 | F11: =C86 -> 809329.59 | G11: 58798243 | H11: =G86 -> 33124060 | I11: =F86 -> 45434514 | K11: 347187 | L11: =IF(ISBLANK(K11),"",K11/$K$41) -> 0.97981594 | M11: =D95 -> 2107 | N11: =C95 -> 4696 | O11: =G95 -> 121061 | P11: =F95 -> 175118
A12: ZONE 01 | C12: 18023708 | D12: 0.12831197 | E12: =D100 -> 47598.42 | F12: =C100 -> 56655.1 | G12: 16301672 | H12: =G100 -> 10109128 | I12: =F100 -> 11813165 | K12: 74705 | L12: =IF(ISBLANK(K12),"",K12/$K$41) -> 0.21082918 | M12: =D104 -> 1105 | N12: =C104 -> 953 | O12: =G104 -> 29328 | P12: =F104 -> 42378
A13: ZONE 02 | C13: 24418268 | D13: 0.17383526 | E13: =D101 -> 92411.99 | F13: =C101 -> 411400.45 | G13: 16533727 | H13: =G101 -> 9329697.4 | I13: =F101 -> 14890926 | K13: 89699 | L13: =IF(ISBLANK(K13),"",K13/$K$41) -> 0.25314459 | M13: =D105 -> 743 | N13: =C105 -> 2189 | O13: =G105 -> 40282 | P13: =F105 -> 63809
A14: ZONE 03 | C14: 51671493 | D14: 0.36785278 | E14: =D102 -> 158815.5 | F14: =C102 -> 341274.03 | G14: 25962845 | H14: =G102 -> 13685235 | I14: =F102 -> 18730423 | K14: 182783 | L14: =IF(ISBLANK(K14),"",K14/$K$41) -> 0.51584217 | M14: =D106 -> 258 | N14: =C106 -> 1554 | O14: =G106 -> 51451 | P14: =F106 -> 68931
A15: CLOSE OUT | C15: 14046786 | D15: =IF(ISBLANK(C15),"",C15/$C$41) -> 0.1 | E15: 0 | F15: =C87 -> 0 | G15: 4889079 | H15: =G87 -> 0 | I15: =F87 -> 0 | K15: 5552 | L15: =IF(ISBLANK(K15),"",K15/$K$41) -> 0.015668611 | N15: =C96 -> 0 | O15: =G96 -> 0 | P15: =F96 -> 0
D16: =IF(ISBLANK(C16),"",C16/$C$41)
D17: =IF(ISBLANK(C17),"",C17/$C$41)
D18: =IF(ISBLANK(C18),"",C18/$C$41)
D19: =IF(ISBLANK(C19),"",C19/$C$41)
D20: =IF(ISBLANK(C20),"",C20/$C$41)
D21: =IF(ISBLANK(C21),"",C21/$C$41)
D22: =IF(ISBLANK(C22),"",C22/$C$41)
D23: =IF(ISBLANK(C23),"",C23/$C$41)
D24: =IF(ISBLANK(C24),"",C24/$C$41)
D25: =IF(ISBLANK(C25),"",C25/$C$41)
D26: =IF(ISBLANK(C26),"",C26/$C$41)
D27: =IF(ISBLANK(C27),"",C27/$C$41)
... D40: =IF(ISBLANK(C40),"",C40/$C$41)
B41: Total | C41: =C7+C8+C9+C10+C11+C15 -> 140467862 | D41: =D7+D8+D9+D10+D11+D15 -> 1 | E41: =E7+E8+E9+E10+E15+E11 -> 504274.59 | F41: =F7+F8+F9+F10+F15+F11 -> 950868.63 | G41: =G9+G10+G7+G8+G11+G15 -> 89278759 | H41: =H9+H10+H7+H8+H11+H15 -> 52406756 | I41: =I9+I10+I7+I8+I11+I15 -> 66820405 | K41: =K7+K8+K9+K10+K11+K15 -> 354339 | L41: =L7+L8+L9+L10+L11+L15 -> 1 | M41: =M7+M8+M9+M10+M11+M15 -> 2107 | N41: =N7+N8+N9+N10+N11+N15 -> 4696 | O41: =O7+O8+O9+O10+O11+O15 -> 122661 | P41: =P7+P8+P9+P10+P11+P15 -> 176718
E42: =E41/$C$41 -> 0.0035899642 | F42: =F41/$C$41 -> 0.0067692967 | G42: =G41/$C$41 -> 0.63558139 | H42: =H41/$C$41 -> 0.37308716 | I42: =I41/$C$41 -> 0.47569888 | M42: =M41/$K$41 -> 0.0059462831 | N42: =N41/$K$41 -> 0.013252845 | O42: =O41/$K$41 -> 0.3461685 | P42: =P41/$K$41 -> 0.4987258
A46: 18023708 | B46: =A46/C41 -> 0.12831197 | D46: THIS WEEK | F46: TO DATE | I46: LAST WEEK | M46: `
A47: 24418268 | B47: =A47/C41 -> 0.17383526 | C47: EARNED | D47: PLANNED | F47: EARNED | G47: PLANNED | H47: EARNED | I47: PLANNED
A48: 51671493 | B48: =A48/C41 -> 0.36785278 | C48: =F48-H48 -> 0 | D48: =G48-I48 -> 0 | F48: 4214035.9 | G48: 4214035 | H48: 4214035.9 | I48: 4214035
C49: =F49-H49 -> 141539.04 | D49: =G49-I49 -> 205448.67 | F49: 17171855 | G49: 15068661 | H49: 17030316 | I49: 14863212 | L49: 3034784.2
D50: =G50-H11 -> -33124060 | H50: 44625185 | I50: 32825234 | K50: Activity ID | L50: Activity Name | M50: Budgeted Total Cost | N50: Planned Value Cost | O50: Earned Value Cost | P50: Budgeted Labor Units | Q50: Planned Value Labor Units | R50: Earned Value Labor Units | T50: Activity ID | U50: Activity Name | V50: Budgeted Total Cost | W50: Planned Value Cost | X50: Earned Value Cost | Y50: Budgeted Labor Units | Z50: Planned Value Labor Units | AA50: Earned Value Labor Units
D51: =G51-H15 -> 0 | H51: 4214035.9 | I51: 4214035 | K51: Mobilization | M51: 0 | N51: 0 | O51: 0 | P51: 73264 | Q51: 24824 | R51: 24818.56 | T51: Mobilization | V51: 0 | W51: 0 | X51: 0 | Y51: 73264 | Z51: 24152 | AA51: 24146.63
D52: =G52-H16 -> 0 | H52: 17030316 | I52: 14863212 | K52: POND A | M52: 8470654 | N52: 3058845 | O52: 3921635.7 | P52: 21368 | Q52: 14428 | R52: 13070.16 | T52: POND A | V52: 8470654 | W52: 3015000 | X52: 3921635.7 | Y52: 21368 | Z52: 14080 | AA52: 12590.16
D53: =G53-H17 -> 0 | H53: 44625185 | I53: 32825234 | K53: Engineering | M53: 0 | N53: 0 | O53: 0 | P53: 720 | Q53: 720 | R53: 720 | T53: Engineering | V53: 0 | W53: 0 | X53: 0 | Y53: 720 | Z53: 720 | AA53: 528
D54: =G54-H18 -> 0 | H54: 4214035.9 | I54: 4214035 | K54: Procurement | M54: 0 | N54: 0 | O54: 0 | P54: 3472 | Q54: 1872 | R54: 1008 | T54: Procurement | V54: 0 | W54: 0 | X54: 0 | Y54: 3472 | Z54: 1824 | AA54: 720
D55: =G55-H19 -> 0 | H55: 17030316 | I55: 14863212 | K55: Construction | M55: 8470654 | N55: 3058845 | O55: 3921635.7 | P55: 17176 | Q55: 11836 | R55: 11342.16 | T55: Construction | V55: 8470654 | W55: 3015000 | X55: 3921635.7 | Y55: 17176 | Z55: 11536 | AA55: 11342.16
D56: =G56-H20 -> 0 | H56: 44625185 | I56: 32825234 | K56: Storm Network | M56: 18712041 | N56: 4045715.8 | O56: 7526225 | P56: 172856 | Q56: 45912 | R56: 66478.76 | T56: Storm Network | V56: 18712041 | W56: 3609053.9 | X56: 7382744.2 | Y56: 172856 | Z56: 41216 | AA56: 64478.11
D57: =G57-H21 -> 0 | H57: 4214035.9 | I57: 4214035 | K57: Engineering | M57: 477625.95 | N57: 477625.95 | O57: 477625.95 | P57: 528 | Q57: 528 | R57: 528 | T57: Engineering | V57: 477625.95 | W57: 477625.95 | X57: 477625.95 | Y57: 528 | Z57: 528 | AA57: 528
D58: =G58-H22 -> 0 | H58: 17030316 | I58: 14863212 | K58: Procurement | M58: 3184173 | N58: 1758490 | O58: 2649528.8 | P58: 11800 | Q58: 6520 | R58: 8391.81 | T58: Procurement | V58: 3184173 | W58: 1644425.8 | X58: 2620191.9 | Y58: 11800 | Z58: 6136 | AA58: 8194.12
D59: =G59-H23 -> 0 | H59: 44625185 | I59: 32825234 | K59: Construction | M59: 12167340 | N59: 1809599.9 | O59: 4399070.3 | P59: 159952 | Q59: 38864 | R59: 57558.95 | T59: Construction | V59: 12167340 | W59: 1487002.1 | X59: 4284926.4 | Y59: 159952 | Z59: 34552 | AA59: 55755.99
D60: =G60-H24 -> 0 | H60: 4214035.9 | I60: 4214035 | K60: Testing & Commissioning | M60: 2882902.5 | N60: 0 | O60: 0 | P60: 576 | Q60: 0 | R60: 0 | T60: Testing & Commissioning | V60: 2882902.5 | W60: 0 | X60: 0 | Y60: 576 | Z60: 0 | AA60: 0
D61: =G61-H25 -> 0 | H61: 17030316 | I61: 14863212 | K61: Sewerage Network | M61: 5198775 | N61: 137774.25 | O61: 2756946.5 | P61: 89168 | Q61: 1280 | R61: 43406.4 | T61: Sewerage Network | V61: 5198775 | W61: 137774.25 | X61: 2484243 | Y61: 89168 | Z61: 1280 | AA61: 39988.27
D62: =G62-H26 -> 0 | H62: 44625185 | I62: 32825234 | K62: Engineering | M62: 137774.25 | N62: 137774.25 | O62: 137774.25 | P62: 440 | Q62: 440 | R62: 440 | T62: Engineering | V62: 137774.25 | W62: 137774.25 | X62: 137774.25 | Y62: 440 | Z62: 440 | AA62: 440
... D81: =G81-H45 -> 0 | H81: 4214035.9 | I81: 4214035 | K81: Close Out | M81: 0 | N81: 0 | O81: 0 | P81: 1200 | Q81: 0 | R81: 0 | T81: Close Out | V81: 0 | W81: 0 | X81: 0 | Y81: 1200 | Z81: 0 | AA81: 0
D82: =G82-H46 -> 0 | H82: 17030316 | I82: 14863212
D83: =G83-H47 -> #VALUE! | H83: 44625185 | I83: 32825234
D84: =G84-H48 -> -4214035.9 | H84: 4214035.9 | I84: 4214035
D85: =G85-H49 -> -17030316 | H85: 17030316 | I85: 14863212
C86: =F86-H86 -> 809329.59 | D86: =G86-I86 -> 298825.92 | F86: 45434514 | G86: 33124060 | H86: 44625185 | I86: 32825234
C87: =F87-H87 -> 0 | D87: =G87-I87 -> 0 | F87: 0 | G87: 0 | I87: 0
C88: =C48+C49+C86+C87 -> 950868.63 | D88: =D48+D49+D86+D87 -> 504274.59 | F88: =SUM(F48:F87) -> 66820405 | G88: =SUM(G48:G87) -> 52406756 | H88: =H48+H49+H86+H87 -> 65869536 | I88: =I48+I49+I86+I87 -> 51902482
C89: THIS WEEK | F89: TO DATE | H89: LAST WEEK
C90: EARNED | D90: PLANNED | F90: EARNED | G90: PLANNED | H90: EARNED | I90: PLANNED
C91: =F91-H91 -> 0 | D91: =G91-I91 -> 0 | G91: 0 | H91: 0 | I91: 0
C92: =F92-H92 -> 0 | D92: =G92-I92 -> 0 | F92: 1600 | G92: 1600 | H92: 1600 | I92: 1600 | K92: 1152 | L92: 1571
C93: =F93-H93 -> 0 | D93: =G93-I93 -> 0 | G93: 0 | H93: 0 | I93: 0 | K93: 14379 | L93: 16255
C94: =F94-H94 -> 0 | D94: =G94-I94 -> 0 | G94: 0 | H94: 0 | I94: 0
C95: =F95-H95 -> 4696 | D95: =G95-I95 -> 2107 | F95: 175118 | G95: 121061 | H95: 170422 | I95: 118954
C96: =F96-H96 -> 0 | D96: =G96-I96 -> 0 | G96: 0 | I96: 0
C97: =SUM(C91:C96) -> 4696 | D97: =SUM(D91:D96) -> 2107 | F97: =SUM(F91:F96) -> 176718 | G97: =SUM(G91:G96) -> 122661 | H97: =SUM(H91:H96) -> 172022 | I97: =SUM(I91:I96) -> 120554
C100: =F100-H100 -> 56655.1 | D100: =G100-I100 -> 47598.42 | F100: 11813165 | G100: 10109128 | H100: 11756510 | I100: 10061529
C101: =F101-H101 -> 411400.45 | D101: =G101-I101 -> 92411.99 | F101: 14890926 | G101: 9329697.4 | H101: 14479526 | I101: 9237285.4
C102: =F102-H102 -> 341274.03 | D102: =G102-I102 -> 158815.5 | F102: 18730423 | G102: 13685235 | H102: 18389149 | I102: 13526419
F103: =SUM(F100:F102) -> 45434514 | G103: =SUM(G100:G102) -> 33124060 | H103: =SUM(H100:H102) -> 44625185 | I103: =SUM(I100:I102) -> 32825234
C104: =F104-H104 -> 953 | D104: =G104-I104 -> 1105 | F104: 42378 | G104: 29328 | H104: 41425 | I104: 28223
C105: =F105-H105 -> 2189 | D105: =G105-I105 -> 743 | F105: 63809 | G105: 40282 | H105: 61620 | I105: 39539
C106: =F106-H106 -> 1554 | D106: =G106-I106 -> 258 | F106: 68931 | G106: 51451 | H106: 67377 | I106: 51193

Sheet FIR Summary
A2: Project Name | C2: ='General Information'!C3 -> ADDITIONAL DEVELOPMENT IN TABOUK INDUSTRIAL CITY
A3: Project ID | C3: Project Budget | D3: 140467862 | E3: Total FIR Amount | F3: =C49 -> 51776131
A4: Date Pariod | C4: Start Date | D4: =F4-6 -> 46301 | E4: To | F4: ='General Information'!L1 -> 46307
A6: SL. | B6: date of FIR | C6: TOTAL AMOUNT | E6: Total Amount % (as per FIR)
A7: 1 | B7: 46009 | C7: 5481497.6 | E7: =C7/D3 -> 0.039023144 | I7: 694495.37
A8: 2 | B8: 46018 | C8: 6294267.3 | E8: =C8/D3 -> 0.044809305 | I8: 29085.997
A9: 3 | B9: 46026 | C9: 6611589.7 | E9: =C9/D3 -> 0.047068344 | I9: 1649842.3
A10: 4 | B10: 46040 | C10: 6870205.8 | E10: =C10/D3 -> 0.04890945 | I10: 53438.985
A11: 5 | B11: 46034 | C11: 7315951.4 | E11: =C11/D3 -> 0.052082742 | I11: 63638.225
A12: 6 | B12: 46048 | C12: 7625043.8 | E12: =C12/D3 -> 0.054283191 | I12: 1228633.9
A13: 7 | B13: 46054 | C13: 9927796.9 | E13: =C13/D3 -> 0.070676643 | I13: 1223854.5
A14: 8 | B14: 46061 | C14: 10171734 | E14: =C14/D3 -> 0.07241325 | I14: 538913.14
A15: 9 | B15: 46068 | C15: 11230039 | E15: =C15/D3 -> 0.079947392 | I15: 78456.886
A16: 10 | B16: 46075 | C16: 12001213 | E16: =C16/D3 -> 0.085437431 | I16: 7020520
A17: 11 | B17: 46082 | C17: 12646730 | E17: =C17/D3 -> 0.090032907 | I17: 439316.2
A18: 12 | B18: 46091 | C18: 13096418 | E18: =C18/D3 -> 0.093234264 | I18: 76222.252
A19: 13 | B19: 46097 | C19: 13670635 | E19: =C19/D3 -> 0.097322155 | I19: =SUM(I7:I18) -> 13096418
A20: 14 | B20: 46105 | C20: 13948404 | E20: =C20/D3 -> 0.09929961 | I20: =SUM(I7:I19) -> 26192836
A21: 15 | B21: 46110 | C21: 14265279 | E21: =C21/D3 -> 0.10155546
A22: 16 | B22: 46118 | C22: 16655783 | E22: =C22/D3 -> 0.11857362
A23: 16 | B23: 46125 | C23: 17041466 | E23: =C23/D3 -> 0.12131933 | I23: 23307507
A24: 17 | B24: 46131 | C24: 18406574 | E24: =C24/D3 -> 0.13103761
A25: 19 | B25: 46138 | C25: 20233593 | E25: =C25/D3 -> 0.14404429
A26: 20 | B26: 46145 | C26: 22462435 | E26: =C26/D3 -> 0.15991156
A27: 21 | B27: 46151 | C27: 23307507 | E27: =C27/D3 -> 0.16592768
A28: 22 | B28: 46159 | C28: 24118465 | E28: =C28/D3 -> 0.17170095 | H28: 24118465
A29: 23 | B29: 46165 | C29: 25053976 | E29: =C29/D3 -> 0.17836091 | I29: =SUM(I22:I28) -> 23307507
A30: 24 | B30: 46173 | C30: 25482985 | E30: =C30/D3 -> 0.18141506 | H30: 29620391
A31: 25 | B31: 46180 | C31: 26822183 | E31: =C31/D3 -> 0.19094889 | I31: 25482985
A32: 26 | B32: 46187 | C32: 27449998 | E32: =C32/D3 -> 0.19541835
A33: 27 | B33: 46195 | C33: 29620391 | E33: =C33/D3 -> 0.21086953 | H33: 34438964
A34: 28 | B34: 46201 | C34: 32264054 | E34: =C34/D3 -> 0.22968993
A35: 29 | B35: 46179 | C35: 33487382 | E35: =C35/D3 -> 0.23839889 | H35: 32264054
A36: 30 | B36: 46216 | C36: 34438964 | E36: =C36/D3 -> 0.24517326
A37: 31 | B37: 46223 | C37: 36225039 | E37: =C37/D3 -> 0.25788845 | H37: 33487382
A38: 32 | B38: 46230 | C38: 38555753 | E38: =C38/D3 -> 0.27448095 | H38: 40536513
A39: 33 | B39: 46237 | C39: 39610513 | E39: =C39/D3 -> 0.28198986 | H39: 41463220
A40: 34 | B40: 46244 | C40: 41463220 | E40: =C40/D3 -> 0.29517941 | H40: 44854869
A41: 35 | B41: 46251 | C41: 44202407 | E41: =C41/D3 -> 0.31467986
A42: 36 | B42: 46257 | C42: 44854869 | E42: =C42/D3 -> 0.31932478
A43: 37 | B43: 46264 | C43: 46432146 | E43: =C43/D3 -> 0.33055352 | H43: 48524583
A44: 38 | B44: 46272 | C44: 46753754 | E44: =C44/D3 -> 0.33284307
A45: 39 | B45: 46279 | C45: 48118249 | E45: =C45/D3 -> 0.342557 | H45: 49536100
A46: 40 | B46: 46285 | C46: 48524583 | E46: =C46/D3 -> 0.34544972
A47: 41 | B47: 46292 | C47: 49536100 | E47: =C47/D3 -> 0.35265077 | H47: 50191338
A48: 42 | B48: 46300 | C48: 50191338 | E48: =C48/D3 -> 0.35731546
A49: 43 | B49: 46306 | C49: 51776131 | E49: =C49/D3 -> 0.3685977 | H49: 51776131

Sheet Quality
B2: QC OBSERVATIONS CHECKLIST
BB4: 45377
B6: Project No. | E6: =Procurement!B13 -> TAB1-02-003 | K6: OBS No. | U6: Inspection Day: | X6: ='General Information'!L1 -> 46307
B8: Project | E8: ='General Information'!C3 -> ADDITIONAL DEVELOPMENT IN TABOUK INDUSTRIAL CITY | O8: Contractor: Consultant: | U8: ASAS for Developing & Operating Industrial CITIES EGIS
B10: 4 | D10: Excellent | G10: Quality Management System is being practiced and applies to MODON System | Z10: 90 - 100 | AB10: QC Overall Score | AC10: =Q49 -> 0.92982759 | AN10: =SUM(Z10:Z13) -> 0 | AO10: 100 | AP10: 0.22883295
B11: 3 | D11: Good | G11: Evidence of compliance with plans and procedures. | Z11: 80 - 89 | AN11: =SUM(Y10:Y14) -> 0 | AO11: 89 | AP11: 0.20366133
B12: 2 | D12: Average | G12: Indication level of compliance with standards but there is room for improvement | Z12: 70 - 79 | AO12: 79 | AP12: 0.18077803
B13: 1 | D13: Improve | G13: Quality and Control is NOT being managed effectively. Needs Improvement | Z13: ≤ 69 | AO13: 69 | AP13: 0.15789474
B14: 0 | D14: N/A | G14: Item was not applicable or this item was not reviewed during the inspection. | Z14: Zero | AO14: 100 | AP14: 0.22883295
B16: No. | C16: Topic | K16: E (4) | L16: G (3) | M16: A (2) | N16: I (1) | O16: N/A (0) | Q16: No. | R16: Topic | Z16: E (4) | AA16: G (3) | AB16: A (2) | AC16: I (1) | AD16: N/A (0) | AO16: =SUM(AO10:AO15) -> 437
K17: 1 | L17: 0.89 | M17: 0.79 | N17: 0.69 | O17: 1 | Z17: 1 | AA17: 0.89 | AB17: 0.79 | AC17: 0.69 | AD17: 1 | AF17: =SUM(AF18:AG46)/COUNT(AF18:AG46) -> 0.92982759
B18: 1 | C18: Control of Access to Site/Office | K18: 0 | L18: 1 | Q18: 30 | R18: QC of Excavation | Z18: 0 | AA18: 1 | AF18: =SUMPRODUCT($K$17:$O$17,K18:O18) -> 0.89 | AG18: =SUMPRODUCT($Z$17:$AD$17,Z18:AD18) -> 0.89 | AV18: Item Count | AW18: Score | AX18: Distributtion
B19: 2 | C19: Document Control Administration | K19: 0 | L19: 0 | M19: 1 | Q19: 31 | R19: QC of Roads/Round about | Z19: 0 | AA19: 1 | AF19: =SUMPRODUCT($K$17:$O$17,K19:O19) -> 0.79 | AG19: =SUMPRODUCT($Z$17:$AD$17,Z19:AD19) -> 0.89 | AX19: Overall | AY19: Relevant
B20: 3 | C20: Project Documents and Progress | L20: 1 | M20: 0 | Q20: 32 | R20: QC of Interlock & Curbstone | Z20: 1 | AD20: 0 | AF20: =SUMPRODUCT($K$17:$O$17,K20:O20) -> 0.89 | AG20: =SUMPRODUCT($Z$17:$AD$17,Z20:AD20) -> 1 | AM20: 4 | AN20: =58 -> 58 | AO20: counts | AQ20: 4 | AR20: Excellent | AV20: =SUM(Z18:Z46,K18:K46) -> 14 | AW20: =AQ20*AV20 -> 56 | AX20: =AV20/$AV$25 -> 0.24137931 | AY20: =AV20/SUM($AV$20:$AV$23) -> 0.34146341
B21: 4 | C21: Contractor's Quality Plan/CM (Updated and Reviewed) | K21: 0 | L21: 1 | Q21: 33 | R21: Layers/Backfilling Sampling | AA21: 0 | AB21: 1 | AC21: 0 | AF21: =SUMPRODUCT($K$17:$O$17,K21:O21) -> 0.89 | AG21: =SUMPRODUCT($Z$17:$AD$17,Z21:AD21) -> 0.79 | AM21: 3 | AN21: =58 -> 58 | AO21: counts | AQ21: 3 | AR21: Good | AV21: =SUM(L18:L46,AA18:AA46) -> 18 | AW21: =AQ21*AV21 -> 54 | AX21: =AV21/$AV$25 -> 0.31034483 | AY21: =AV21/SUM($AV$20:$AV$23) -> 0.43902439
B22: 5 | C22: MS Log and Paperwork | K22: 1 | L22: 0 | M22: 0 | Q22: 34 | R22: Pump Stations Units | AC22: 0 | AD22: 1 | AF22: =SUMPRODUCT($K$17:$O$17,K22:O22) -> 1 | AG22: =SUMPRODUCT($Z$17:$AD$17,Z22:AD22) -> 1 | AM22: 2 | AN22: =58 -> 58 | AO22: counts | AQ22: 2 | AR22: Average | AV22: =SUM(M18:M46,AB18:AB46) -> 7 | AW22: =AQ22*AV22 -> 14 | AX22: =AV22/$AV$25 -> 0.12068966 | AY22: =AV22/SUM($AV$20:$AV$23) -> 0.17073171 | BC22: NB: Insert 1, or 0 in the required cell only.
B23: 6 | C23: RFI, FIR, & MIR Procedure | K23: 1 | L23: 0 | Q23: 35 | R23: Quality of Form Work | AA23: 1 | AB23: 0 | AD23: 0 | AF23: =SUMPRODUCT($K$17:$O$17,K23:O23) -> 1 | AG23: =SUMPRODUCT($Z$17:$AD$17,Z23:AD23) -> 0.89 | AM23: 1 | AN23: =58 -> 58 | AO23: counts | AQ23: 1 | AR23: Improve | AV23: =SUM(N18:N46,AC18:AC46) -> 2 | AW23: =AQ23*AV23 -> 2 | AX23: =AV23/$AV$25 -> 0.034482759 | AY23: =AV23/SUM($AV$20:$AV$23) -> 0.048780488
B24: 7 | C24: RFI, FIR, & MIR Inventory system | K24: 0 | L24: 1 | Q24: 36 | R24: Design Change List | AC24: 0 | AD24: 1 | AF24: =SUMPRODUCT($K$17:$O$17,K24:O24) -> 0.89 | AG24: =SUMPRODUCT($Z$17:$AD$17,Z24:AD24) -> 1 | AM24: 0 | AN24: =58 -> 58 | AO24: counts | AQ24: 0 | AR24: N/A | AV24: =SUM(O18:O46,AD18:AD46) -> 17 | AW24: =AQ24*AV24 -> 0 | AX24: =AV24/$AV$25 -> 0.29310345 | AY24: -
B25: 8 | C25: NCRs Control & Procedure | K25: 0 | L25: 1 | M25: 0 | O25: 0 | Q25: 37 | R25: Quality of Concrete Placing | AA25: 1 | AD25: 0 | AF25: =SUMPRODUCT($K$17:$O$17,K25:O25) -> 0.89 | AG25: =SUMPRODUCT($Z$17:$AD$17,Z25:AD25) -> 0.89 | AR25: Total | AV25: =SUM(AV20:AV24) -> 58 | AW25: =SUM(AW20:AW24) -> 126 | AX25: =SUM(AX20:AX24) -> 1 | AY25: =SUM(AY20:AY24) -> 1
B26: 9 | C26: NCR Log | K26: 1 | L26: 0 | Q26: 38 | R26: Concrete Surface Finishing | Z26: 0 | AA26: 1 | AD26: 0 | AF26: =SUMPRODUCT($K$17:$O$17,K26:O26) -> 1 | AG26: =SUMPRODUCT($Z$17:$AD$17,Z26:AD26) -> 0.89
B27: 10 | C27: MODON Standard* | K27: 0 | L27: 0 | N27: 1 | Q27: 39 | R27: Pedestals/Columns/Beams Alignment | AD27: 1 | AF27: =SUMPRODUCT($K$17:$O$17,K27:O27) -> 0.69 | AG27: =SUMPRODUCT($Z$17:$AD$17,Z27:AD27) -> 1 | AV27: Maz Score Available: | AW27: =SUM(AV20:AV23)*AQ20 -> 164 | AX27: <- Excludes N/A items
B28: 11 | C28: Project Risk Plan/Management* | K28: 0 | M28: 0 | O28: 1 | Q28: 40 | R28: Siporex Lifting & Unloading | AD28: 1 | AF28: =SUMPRODUCT($K$17:$O$17,K28:O28) -> 1 | AG28: =SUMPRODUCT($Z$17:$AD$17,Z28:AD28) -> 1
B29: 12 | C29: Monthly Quality Reports* | K29: 0 | L29: 1 | M29: 0 | Q29: 41 | R29: Siporex Quality Pre-installation | AD29: 1 | AF29: =SUMPRODUCT($K$17:$O$17,K29:O29) -> 0.89 | AG29: =SUMPRODUCT($Z$17:$AD$17,Z29:AD29) -> 1
B30: 13 | C30: ITP | K30: 1 | L30: 0 | M30: 0 | Q30: 42 | R30: Siporex Finishing Quality | AD30: 1 | AF30: =SUMPRODUCT($K$17:$O$17,K30:O30) -> 1 | AG30: =SUMPRODUCT($Z$17:$AD$17,Z30:AD30) -> 1 | AR30: Total Score | AW30: Percentage (%)
B31: 14 | C31: MODON Weekly Report | K31: 1 | L31: 0 | M31: 0 | Q31: 43 | R31: Roads / Parking Markings | AD31: 1 | AF31: =SUMPRODUCT($K$17:$O$17,K31:O31) -> 1 | AG31: =SUMPRODUCT($Z$17:$AD$17,Z31:AD31) -> 1 | AN31: =MAX(AN20:AN24) -> 58 | AR31: =AW25 -> 126 | AW31: =SUM(100/AR33*AR31) -> 76.829268 | AY31: %
B32: 15 | C32: Design Change Official Paperwork* | K32: 0 | O32: 1 | Q32: 44 | R32: QC of Finishing Outdoors | AD32: 1 | AF32: =SUMPRODUCT($K$17:$O$17,K32:O32) -> 1 | AG32: =SUMPRODUCT($Z$17:$AD$17,Z32:AD32) -> 1 | AR32: Max Score Available | BP32: 31
B33: 16 | C33: Design Change was Applied* | K33: 0 | O33: 1 | Q33: 45 | R33: Quality of Finishing Indoors | AD33: 1 | AF33: =SUMPRODUCT($K$17:$O$17,K33:O33) -> 1 | AG33: =SUMPRODUCT($Z$17:$AD$17,Z33:AD33) -> 1 | AR33: =AW27 -> 164 | BP33: 32
B34: 17 | C34: Material List | K34: 1 | L34: 0 | M34: 0 | Q34: 46 | R34: Stairs Quality | AD34: 1 | AF34: =SUMPRODUCT($K$17:$O$17,K34:O34) -> 1 | AG34: =SUMPRODUCT($Z$17:$AD$17,Z34:AD34) -> 1 | BP34: 33
B35: 18 | C35: Pending Material Status | K35: 1 | L35: 0 | O35: 0 | Q35: 47 | R35: Tanks Method Statement Work | AD35: 1 | AF35: =SUMPRODUCT($K$17:$O$17,K35:O35) -> 1 | AG35: =SUMPRODUCT($Z$17:$AD$17,Z35:AD35) -> 1 | BP35: 34
B36: 19 | C36: Lifting Plan* | O36: 1 | Q36: 48 | R36: Electric Rooms | AD36: 1 | AF36: =SUMPRODUCT($K$17:$O$17,K36:O36) -> 1 | AG36: =SUMPRODUCT($Z$17:$AD$17,Z36:AD36) -> 1 | BP36: 35
B37: 20 | C37: DWG Log | K37: 0 | L37: 1 | M37: 0 | O37: 0 | Q37: 49 | R37: QC of MCC/ATS Plant Units | AD37: 1 | AF37: =SUMPRODUCT($K$17:$O$17,K37:O37) -> 0.89 | AG37: =SUMPRODUCT($Z$17:$AD$17,Z37:AD37) -> 1 | BP37: 36
B38: 21 | C38: Invoice Status | K38: 1 | L38: 0 | O38: 0 | Q38: 50 | R38: Qualified Subcontractor | Z38: 0 | AA38: 1 | AB38: 0 | AD38: 0 | AF38: =SUMPRODUCT($K$17:$O$17,K38:O38) -> 1 | AG38: =SUMPRODUCT($Z$17:$AD$17,Z38:AD38) -> 0.89 | BP38: 37
B39: 22 | C39: Site Handover Letter | K39: 1 | L39: 0 | Q39: 51 | R39: Scaffold/Ladders/Slope/Bridge Compliance | AC39: 1 | AD39: 0 | AF39: =SUMPRODUCT($K$17:$O$17,K39:O39) -> 1 | AG39: =SUMPRODUCT($Z$17:$AD$17,Z39:AD39) -> 0.69 | BP39: 38
B40: 23 | C40: Material Testing Results & Certification | K40: 1 | L40: 0 | M40: 0 | N40: 0 | Q40: 52 | R40: Protection Applied to Completed Work | AB40: 1 | AC40: 0 | AD40: 0 | AF40: =SUMPRODUCT($K$17:$O$17,K40:O40) -> 1 | AG40: =SUMPRODUCT($Z$17:$AD$17,Z40:AD40) -> 0.79
B41: 24 | C41: As Build Drawings Status* | L41: 1 | M41: 0 | O41: 0 | Q41: 53 | R41: Storage Management in/out Control | AA41: 1 | AB41: 0 | AD41: 0 | AF41: =SUMPRODUCT($K$17:$O$17,K41:O41) -> 0.89 | AG41: =SUMPRODUCT($Z$17:$AD$17,Z41:AD41) -> 0.89
B42: 25 | C42: Calibrated Lab Tools & Equipment | K42: 1 | L42: 0 | N42: 0 | Q42: 54 | R42: Material Control | AA42: 1 | AB42: 0 | AD42: 0 | AF42: =SUMPRODUCT($K$17:$O$17,K42:O42) -> 1 | AG42: =SUMPRODUCT($Z$17:$AD$17,Z42:AD42) -> 0.89
B43: 26 | C43: Storage Inventory System | L43: 0 | M43: 1 | N43: 0 | Q43: 55 | R43: Manholes Storing and Quality | Z43: 0 | AA43: 1 | AB43: 0 | AD43: 0 | AF43: =SUMPRODUCT($K$17:$O$17,K43:O43) -> 0.79 | AG43: =SUMPRODUCT($Z$17:$AD$17,Z43:AD43) -> 0.89
B44: 27 | C44: Logistics Plan | L44: 0 | M44: 1 | Q44: 56 | R44: Reinforced Steel Quality | Z44: 1 | AA44: 0 | AB44: 0 | AD44: 0 | AF44: =SUMPRODUCT($K$17:$O$17,K44:O44) -> 0.79 | AG44: =SUMPRODUCT($Z$17:$AD$17,Z44:AD44) -> 1
B45: 28 | C45: Project Progress Planview | K45: 1 | M45: 0 | N45: 0 | Q45: 57 | R45: Safety Overview | Z45: 0 | AA45: 0 | AB45: 1 | AC45: 0 | AD45: 0 | AF45: =SUMPRODUCT($K$17:$O$17,K45:O45) -> 1 | AG45: =SUMPRODUCT($Z$17:$AD$17,Z45:AD45) -> 0.79
B46: 29 | C46: Sufficient Number of QC Inspectors | K46: 0 | L46: 1 | M46: 0 | N46: 0 | Q46: 58 | R46: Waste Management Control | AA46: 0 | AB46: 1 | AC46: 0 | AD46: 0 | AF46: =SUMPRODUCT($K$17:$O$17,K46:O46) -> 0.89 | AG46: =SUMPRODUCT($Z$17:$AD$17,Z46:AD46) -> 0.79
O47: 0
I48: Score
M49: *QC % | Q49: =AF17 -> 0.92982759
B51: Prepared by: | G51: ENG / AHMED SAMIR | Q51: Issued to PM: | V51: ENG/ YAZEED ALRAGABAH
B53: *QC Observations refer only to the practices and documentation observed at time of inspection. The responsibility of the CM and Contractor is to ensure that aspects of Quality are suitably managed. *Scores are a reflection of the general site conditions based upon the findings at the time of the walk through *If Applicable

Sheet Quality-Stat
A1: Quality Reports
A2: Item | C2: Issued | D2: Closed | E2: Pending | F2: Avg. Closing (Days) | G2: Pending
G3: 0-10 Days | H3: 11-20 Days | I3: 21-30 Days | J3: 31-60 Days | K3: > 60 Days
N4: 299 | O4: 618 | P4: =N4+O4 -> 917
A5: Non Conforomance Report (NCR) | C5: 11 | D5: 11 | E5: 0 | F5: 5 | G5: 0 | H5: 0 | I5: 0 | J5: 0 | K5: 0 | N5: 1
A6: Site Instruction (SI) | C6: 20 | D6: 20 | E6: 0 | F6: 6 | G6: 0 | H6: 0 | I6: 0 | J6: 0 | K6: 0 | N6: 286 | O6: 583 | P6: =N6+O6 -> 869
A7: Material Inspection Report (MIR) | C7: 223 | D7: 221 | E7: 2 | F7: 2 | G7: 2 | H7: 0 | I7: 0 | J7: 0 | K7: 0
A8: Field Inspection Report (FIR) | C8: 6764 | D8: 6526 | E8: 238 | F8: 1 | G8: 237 | H8: 0 | I8: 0 | J8: 0 | K8: 0
N9: 717 | O9: 25 | P9: =N9+O9 -> 742
A10: Shop Drawings | N10: 5559 | O10: 207 | P10: =N10+O10 -> 5766
A11: Item Per WBS | D11: Total Planned | E11: Total Drawings Submitted | J11: Remaining Drawings | K11: Pending | L11: Total Submittals | N11: 250 | O11: 6 | P11: =N11+O11 -> 256
E12: A | F12: B | G12: C | H12: D | I12: Approved | J12: with Designer | K12: Submittals With Consultant
A13: Electrical Network - Road Lighting | D13: 102 | E13: 33 | F13: =L13-E13 -> 69 | G13: 0 | H13: 0 | I13: 102 | L13: 102
A14: Potable Water Network | D14: 53 | E14: 50 | F14: =D14-E14 -> 3 | G14: 0 | H14: 0 | I14: 53 | L14: 53
A15: TSE Network | D15: 50 | E15: 0 | F15: 50 | G15: 0 | H15: 0 | I15: 50 | J15: =D15-I15 -> 0 | L15: 50
A16: Sewerage Network | D16: 25 | E16: 25 | F16: 0 | G16: 0 | H16: 0 | I16: 25 | J16: =D16-I16 -> 0 | L16: 27
A17: Storm Water Network | D17: 45 | E17: 41 | F17: 33 | G17: 2 | H17: 0 | I17: 45 | J17: =D17-I17 -> 0 | L17: 35 | N17: =161-40 -> 121
A18: ROAD | D18: 153 | E18: 37 | F18: 122 | G18: 2 | H18: 0 | I18: 153 | L18: 161
A19: TOTAL | D19: =SUM(D13:D18) -> 428 | E19: =SUM(E13:E18) -> 186 | F19: =SUM(F13:F18) -> 277 | G19: =SUM(G13:G18) -> 4 | H19: =SUM(H13:H18) -> 0 | I19: =SUM(I13:I18) -> 428 | J19: =SUM(J13:J18) -> 0 | K19: =SUM(K13:K18) -> 0 | L19: =SUM(L13:L18) -> 428
A22: Material Approval
A23: Item Per WBS | D23: Total Planned | E23: Total Materials Submitted | J23: Remaining to approve | K23: Pending | L23: Total Submittals
E24: A | F24: B | G24: C | H24: D | I24: Approved | J24: with Designer | K24: Submittals With Consultant
A25: Electrical Network - Road Lighting | E25: 0 | F25: 26 | G25: 0 | H25: 0 | I25: 25 | J25: 0 | K25: 0 | L25: 26
A26: Potable Water Network | D26: 0 | E26: 0 | F26: 6 | G26: 0 | H26: 0 | I26: 5 | J26: 0 | K26: 1 | L26: 6
A27: TSE Network | D27: 0 | E27: 0 | F27: 6 | G27: 0 | H27: 0 | I27: 6 | J27: 0 | K27: 0 | L27: 6 | O27: 30
A28: Sewerage Network | D28: 0 | E28: 0 | F28: 7 | G28: 0 | H28: 0 | I28: 6 | J28: 0 | K28: 0 | L28: 7
A29: Storm Water Network | D29: 0 | E29: 0 | F29: 7 | G29: 0 | H29: 0 | I29: 6 | J29: 0 | K29: 0 | L29: 7
A30: TOTAL | D30: =SUM(D25:D29) -> 0 | E30: =SUM(E25:E29) -> 0 | F30: =SUM(F25:F29) -> 52 | G30: =SUM(G25:G29) -> 0 | H30: =SUM(H25:H29) -> 0 | I30: =SUM(I25:I29) -> 48 | J30: =SUM(J25:J29) -> 0 | K30: =SUM(K25:K29) -> 1 | L30: =SUM(L25:L29) -> 52
A32: Procurement Summary
A33: Item Per WBS | D33: Total Materials Planned | E33: Total Number of P.O. | F33: Actual P.O. To Date | G33: Remaining P.O | H33: Actual Material on Site | I33: Remaining Materials | J33: Material Delivery Completion (Date)
E34: A | F34: B | G34: C | H34: D | I34: Processed
A35: Electrical Network - Road Lighting | D35: 9 | E35: 9 | F35: 7 | G35: 2 | H35: 8000 | I35: 0
A36: Potable Water Network | D36: 3 | E36: 3 | F36: 3 | G36: =E36-F36 -> 0 | H36: 6474 | I36: 6248
A37: TSE Network | D37: 2 | E37: 2 | F37: 2 | G37: =E37-F37 -> 0 | H37: 6474 | I37: 6248 | N37: 12496 | O37: =N37/2 -> 6248
A38: Sewerage Network | D38: 2 | E38: 2 | F38: 2 | G38: =E38-F38 -> 0 | H38: 7045 | I38: =CONCULUSTION!J15 -> 275
A39: Storm Water Network | D39: 6 | E39: 6 | F39: 6 | G39: =E39-F39 -> 0 | H39: =CONCULUSTION!I16+CONCULUSTION!I17 -> 16049 | I39: =CONCULUSTION!J16 -> 136
A40: Roads | D40: 7 | E40: 7 | F40: 7 | G40: =E40-F40 -> 0 | H40: 1100
A41: TOTAL | D41: =SUM(D35:D40) -> 29 | E41: =SUM(E35:E40) -> 29 | F41: =SUM(F35:F40) -> 27 | G41: =SUM(G35:G40) -> 2 | H41: =SUM(H35:H40) -> 45142 | I41: =SUM(I35:I39) -> 12907
A43: Consultant Quality Inspections / Observations (Weekly Basis) | I43: Overall Average | J43: =AVERAGE(E46:E119) -> 0.92950091 | L43: Average Closing | M43: =AVERAGE(G45:G119) -> 1.5344828
A44: Week Number | B44: Date of Audit | C44: Date Issued | D44: Numbers Of Comments | E44: Quality Score | F44: Date Closed | G44: Closure Duration | I44: This Week Score | J44: =Quality!AC10 -> 0.92982759 | L44: Average Number of Comments Per Audit | M44: =AVERAGE(D46:D119) -> 2.5178571
A45: Week-1 | B45: 45904 | C45: =B45 -> 45904 | D45: 5 | E45: 0.92034483 | F45: =C45+1 -> 45905 | G45: =F45-B45 -> 1
A46: Week-2 | B46: 45911 | C46: =B46 -> 45911 | D46: 5 | E46: 0.91206897 | F46: =C46+1 -> 45912 | G46: =F46-B46 -> 1
A47: Week-3 | B47: 45918 | C47: =B47 -> 45918 | D47: 4 | E47: 0.94827586 | F47: =C47+1 -> 45919 | G47: =F47-B47 -> 1
A48: Week-4 | B48: 45925 | C48: =B48 -> 45925 | D48: 3 | E48: =Quality!AC10 -> 0.92982759 | F48: =C48+1 -> 45926 | G48: =F48-B48 -> 1
A49: Week-5 | B49: 45932 | C49: =B49 -> 45932 | D49: 1 | E49: =92% -> 0.92 | F49: =C49+1 -> 45933 | G49: =F49-B49 -> 1
A50: Week-6 | B50: 45939 | C50: =B50 -> 45939 | D50: 1 | E50: 0.94827586 | F50: =C50+1 -> 45940 | G50: =F50-B50 -> 1
A51: Week-7 | B51: 45946 | C51: =B51 -> 45946 | D51: 1 | E51: =Quality!AC10 -> 0.92982759 | F51: =C51+1 -> 45947 | G51: =F51-B51 -> 1
A52: Week-8 | B52: 45953 | C52: =B52 -> 45953 | D52: 1 | E52: 0.94827586 | F52: =C52+1 -> 45954 | G52: =F52-B52 -> 1
A53: Week-9 | B53: 45960 | C53: =B53 -> 45960 | D53: 1 | E53: 0.93741379 | F53: =C53+1 -> 45961 | G53: =F53-B53 -> 1
A54: Week-10 | B54: 45967 | C54: =B54 -> 45967 | D54: 2 | E54: 0.93741379 | F54: =C54+1 -> 45968 | G54: =F54-B54 -> 1
A55: Week-11 | B55: 45974 | C55: =B55 -> 45974 | D55: 2 | E55: 0.9087931 | F55: =C55+1 -> 45975 | G55: =F55-B55 -> 1
A56: Week-12 | B56: 45981 | C56: =B56 -> 45981 | D56: 4 | E56: 0.9087931 | F56: =C56+1 -> 45982 | G56: =F56-B56 -> 1
A57: Week-13 | B57: 45988 | C57: =B57 -> 45988 | D57: 5 | E57: 0.9087931 | F57: =C57+1 -> 45989 | G57: =F57-B57 -> 1
A58: Week-14 | B58: 45995 | C58: =B58 -> 45995 | D58: 6 | E58: 0.9087931 | F58: 46007 | G58: =F58-B58 -> 12
A59: Week-15 | B59: 46002 | C59: =B59 -> 46002 | D59: 3 | E59: 0.9 | F59: =C59+1 -> 46003 | G59: =F59-B59 -> 1
A60: Week-16 | B60: 46010 | C60: =B60 -> 46010 | D60: 2 | E60: 0.905 | F60: =C60+1 -> 46011 | G60: =F60-B60 -> 1
A61: Week-17 | B61: 46016 | C61: =B61 -> 46016 | D61: 5 | E61: 0.93 | F61: =C61+1 -> 46017 | G61: =F61-B61 -> 1
A62: Week-18 | B62: 46023 | C62: =B62 -> 46023 | D62: 4 | E62: 0.94 | F62: =C62+1 -> 46024 | G62: =F62-B62 -> 1
A63: Week-19 | B63: 46030 | C63: =B63 -> 46030 | D63: 3 | E63: 0.92 | F63: =C63+1 -> 46031 | G63: =F63-B63 -> 1
A64: Week-20 | B64: 46037 | C64: =B64 -> 46037 | D64: 2 | E64: 0.93 | F64: =C64+1 -> 46038 | G64: =F64-B64 -> 1
A65: Week-21 | B65: 46044 | C65: =B65 -> 46044 | D65: 1 | E65: 0.9 | F65: =C65+1 -> 46045 | G65: =F65-B65 -> 1
A66: Week-22 | B66: 46051 | C66: =B66 -> 46051 | D66: 2 | E66: 0.93 | F66: =C66+1 -> 46052 | G66: =F66-B66 -> 1
A67: Week-23 | B67: 46058 | C67: =B67 -> 46058 | D67: 8 | E67: 0.88 | F67: =C67+1 -> 46059 | G67: =F67-B67 -> 1
A68: Week-24 | B68: 46065 | C68: =B68 -> 46065 | D68: 4 | E68: 0.89 | F68: =C68+1 -> 46066 | G68: =F68-B68 -> 1
A69: Week-25 | B69: 46072 | C69: =B69 -> 46072 | D69: 6 | E69: 0.89 | F69: =C69+1 -> 46073 | G69: =F69-B69 -> 1
A70: Week-26 | B70: 46079 | C70: =B70 -> 46079 | D70: 4 | E70: 0.9 | F70: =C70+1 -> 46080 | G70: =F70-B70 -> 1
... A77: Week-33 | B77: 46128 | C77: =B77 -> 46128 | D77: 1 | E77: 0.9 | F77: =C77+1 -> 46129 | G77: =F77-B77 -> 1
A78: Week-34 | B78: 46132 | C78: =B78 -> 46132 | D78: 1 | E78: 0.95 | F78: =C78 -> 46132 | G78: =F78-B78 -> 0
A79: Week-35 | B79: 46137 | C79: 46137 | D79: 1 | E79: 0.95 | F79: 46138 | G79: =F79-B79 -> 1
A80: Week-36 | B80: 46143 | C80: 46144 | D80: 1 | E80: 0.95 | F80: 46144 | G80: =F80-B80 -> 1
A81: Week-37 | B81: 46151 | C81: =B81 -> 46151 | D81: 3 | E81: 0.95 | F81: 46153 | G81: =F81-C81 -> 2
A82: Week-38 | B82: 46157 | C82: 46159 | D82: 1 | E82: 0.93 | F82: 46160 | G82: 3
A83: Week-39 | B83: 46162 | C83: 46163 | D83: 1 | E83: 0.93 | F83: 46166 | G83: =F83-B83 -> 4
A84: Week-40 | B84: 46173 | C84: =B84 -> 46173 | D84: 0 | E84: 0.9 | F84: 46173 | G84: 0
A85: Week-41 | B85: 46184 | C85: =B85 -> 46184 | D85: 1 | E85: 0.95 | F85: 46187 | G85: 2
A86: Week-42 | B86: 46193 | C86: 46193 | D86: 1 | E86: 0.95 | F86: 46194 | G86: 3
A87: Week-43 | B87: 46200 | C87: 46200 | D87: 1 | E87: 0.95 | F87: 46201 | G87: 1
A88: Week-44 | B88: 46204 | C88: 46204 | D88: 5 | E88: 0.95 | F88: 46209 | G88: =F88-C88 -> 5
A89: Week-45 | B89: 46212 | C89: 46212 | D89: 5 | E89: 0.8 | F89: 46217 | G89: 6
A90: Week-46 | B90: 46221 | C90: 46221 | D90: 4 | E90: 0.95 | F90: 46222 | G90: 1
A91: Week-47 | B91: 46228 | C91: 46228 | D91: 1 | E91: 0.97 | F91: 46229 | G91: 1
A92: Week-48 | B92: 46235 | C92: 46235 | D92: 1 | E92: 0.96 | F92: 46236 | G92: 1
A93: Week-49 | B93: 46239 | C93: 46239 | D93: 1 | E93: 0.95 | F93: 46240 | G93: 1
A94: Week-50 | B94: 46249 | C94: 46249 | D94: 3 | E94: 0.96 | F94: 46250 | G94: 2
A95: Week-51 | B95: 46256 | C95: 46256 | D95: 3 | E95: 0.95 | F95: 46257 | G95: 3
A96: Week-52 | B96: 46263 | C96: 46263 | D96: 1 | E96: 0.97 | F96: 46264 | G96: 1
A97: Week-53 | B97: 46270 | C97: 46270 | E97: 0.94 | F97: 46271 | G97: 2
A98: Week-54 | B98: 46277 | C98: 46277 | D98: 1 | E98: 0.98 | F98: 46278 | G98: 1
A99: Week-55 | B99: 46284 | C99: 46284 | D99: 2 | E99: 0.96 | F99: 46285 | G99: 2
A100: Week-56 | B100: 46291 | C100: 46291 | D100: 1 | E100: 0.97 | F100: 46292 | G100: 1
A101: Week-57 | B101: 46298 | C101: 46298 | D101: 3 | E101: 0.96 | F101: 46299 | G101: 1
A102: Week-58 | B102: 46305 | C102: 46305 | D102: 0 | E102: 0.98 | F102: 46306 | G102: 0
A103: Week-59
A104: Week-60
A105: Week-61
A106: Week-62
A107: Week-63
A108: Week-64
A109: Week-65
A110: Week-66
...

Sheet HSE
B1: MODON HSE Site Inspection Report
B2: Date | E2: ='General Information'!L1 -> 46307 | L2: Inspected By:
B4: Project ID. | E4: =Procurement!B8 -> TAB1-02-003 | L4: Report No. | P4: =Quality!O6 -> 0 | W4: MODON PM Name | Y4: ='General Information'!C9 -> ENG/ YAZEED ALRAGABAH
B6: Project Name: | E6: ='General Information'!C3 -> ADDITIONAL DEVELOPMENT IN TABOUK INDUSTRIAL CITY | L6: Contractor: | R6: ='General Information'!C5 -> ASAS for Developing & Operating Industrial Cities | X6: Safety Performance | AA6: =IF(W29>0,3,IF(L29>6,3,IF(D29>0,2,1)*1)*1) -> 2 | AE6: =(((COUNTIF(L13:Q25,"1")+COUNTIF(AC13:AH25,"1"))*AR13)+(COUNTIF(L13:Q25,"2")+COUNTIF(AC13:AH25,"2"))*AR14+(COUNTIF(L13:Q25,"3")+COUNTIF(AC13:AH25,"3"))*AR15)/((COUNT(L13:Q25)+COUNT(AC13:AH25))*100) -> 0.94565217
B8: Inspections are a snapshot in time and refer only to the practices and documentation observed at the time of the Inspection. It remains the responsibility of the Consultant and Contractor to ensure that all aspects of Health & Safety are suitably managed.
B9: 1 | D9: Good Practice | H9: 2 | I9: Need Improvement | T9: 3 | U9: Fail (Life Threatening Activity) / Comliance with Plan & Procedures | X9: N/A | Y9: Atcitty Not Applicable for this Site Inspection Report
B11: No. | C11: Topic | K11: Wt. | L11: HSE Compliance | S11: No. | T11: Topic | AB11: Wt. | AC11: HSE Compliance
B13: 1 | C13: Access and Egress - (General access to site, segregated from vehicles, / Overhead protection, while entering into the building /Adequate lighting provided when dark or overnight work) | K13: 0.05 | L13: 2 | S13: 14 | T13: Work at Height - (PPE/Fall Protection(Same level, above and blow) / Training / Fall restraint / competency /Safe access & egress to and from work at height / Ladders / Openings (floor/shafts/Provision of emergency rescue) | AB13: 0.05 | AC13: N/A | AP13: 1 | AR13: 100 | AU13: 1
B14: 2 | C14: Traffic Management - (Loading/unloading/sheeting/temp. routes/speed/parking/competence) | K14: 0.03 | L14: 1 | S14: 15 | T14: Scaffolding - (Temp. Scaffolding Work-platform (All types) - qualified scaffolder / Inspection / Tagged / Safe Access/egress / PTW/Falsework & Formwork) | AB14: 0.04 | AC14: N/A | AP14: 2 | AR14: 75 | AU14: 2
B15: 3 | C15: Site Signage - (Project Notice Board & General Signage) | K15: 0.02 | L15: 1 | S15: 16 | T15: Mobile Elevated Work platform (MEWP) - (PTW/competence requirements/conditions/inspections/tagged/training/Full-body harness) | AB15: 0.04 | AC15: N/A | AP15: 3 | AR15: 0 | AU15: 3
B16: 4 | C16: PPE Compliance - (Use, storage, stock, handling & checks - Head, Foot, Eye, Hearing) | K16: 0.05 | L16: 2 | S16: 17 | T16: Excavation & Trenches - (PTW/Edge protection/buffer zone/Slope/Benching/Shoring/Geo-tech report/Atmospheric hazards/Acess&egress/Emergency management / MS&RA/H.E) | AB16: 0.03 | AC16: 2 | AU16: N/A
B17: 5 | C17: Housekeeping - (Material correctly stored/Rubbish cleaned & removed daily/slips & trips hazards) | K17: 0.03 | L17: 1 | S17: 18 | T17: Confined Space - (PTW/Training/competence/Emergency Management/MS & RA/Safe access/egress) | AB17: 0.05 | AC17: 1
B18: 6 | C18: Storage of Materials - (Transporting, storage, training and use - Combustible / Flammable / Hazardous substances (COSHH) | L18: 1 | S18: 19 | T18: Fire Protection - (Flammable/Oxy. LPG /Combustible separated/FE's/Flashback arrestor/Sparks & slags/Smoking area/PTW/Generators/MS & RA/Emergency Management) | AC18: 1 | AL18: Red | AM18: Serious injury or death (immediately)
B19: 7 | C19: Site Waste Management - (Hazardous waste /Combustible waste / Human waste / Construction waste - asphalt, cable, timber, paving roof sheeting tiles, plastic & bricks) | L19: 1 | S19: 20 | T19: Health & Welfare - (Adequate drinking water/shaded - eating & rest area/washing & sanitary facilities/Certified FA/FA Box & Stock/adequate toilets/Ambulance) | AC19: 1 | AL19: Yellow | AM19: Minor or near miss (3 days to comply)
B20: 8 | C20: Health Surveillance - (Expose to excessive noise/vibration/dust/silica/CO/cement/radiation/extreme weather condition) | K20: 0.03 | L20: 2 | S20: 21 | T20: Environmental Incident Measures - (Spill/ Leakage / Concrete wash / vehicle & eqpts. wash / waste disposal/Sewers and drains/emissions/Emergency Management/Training/site run-off water) | AB20: 0.05 | AC20: 1 | AL20: Green | AM20: No issues
B21: 9 | C21: Electrical Safety - (Electrical qualified /RCD/GFCI/Industrial Cocket/LOTO/Cable-overhung or buried/Cords in good condition/current inspection tag) | K21: 0.05 | L21: 1 | S21: 22 | T21: HSE Communications & Meetings - (Schedule HSE Meetings/Safety Committee meetings/Alerts / Lesson learned/Safety Bulletin contains latest HSE KPI) | AB21: 0.05 | AC21: 1
B22: 10 | C22: Tools & Equipment - (Includes, powered, hydraulic & pneumatic/Guards in place/Properly stored/RCD Protection/Earthed/Good condition & tagged) | K22: 0.03 | L22: 1 | S22: 23 | T22: HSE Plan & Associated Procedures - (Approved updated HSE Plan/ CEMP/HAZComm/Procedures/Standards/Project Safety Risk Register) | AB22: 0.03 | AC22: 1 | AL22: 26 points > 4 minors then is it’s a serious issue
B23: 11 | C23: Manual Handling - (Lifting/loading/pulling/pushing/twisting/awkward posture/repetitive task/frequent and prolong physical effort/Reasonable practicable use of mechanical aid) | K23: 0.03 | L23: 1 | S23: 24 | T23: Health, Safety & Environment Incident reporting - (Review of HSE Statistics, Reporting of Unsafe Act & Conditions/ Reporting of Near Miss incident/Reporting of FA cases/Record MT cases) | AB23: 0.03 | AC23: 1
B24: 12 | C24: Vehicle and mobile equipment / Plant - (dumpers; excavators, cranes, piling rigs, grader, roller, loaders/condition/KSA License/certification) | K24: 0.05 | L24: 1 | S24: 25 | T24: HSE Awareness, Training & Competence - (Policy /Objective & targets/Information, training/Climatic condition awareness/Reponses in emergency situation/ Safety Behavior Observation) | AB24: 0.04 | AC24: 1
B25: 13 | C25: Lifting Operations & Rigging - (Lifting Plan/Lifting devices & gears/PTW/Condition/3rd party certification/bank-man/rigger/slingers/man-basket/inspection record/tagged) | L25: 2 | S25: 26 | T25: Project Leadership Site Tours - (Provide evidence of proactive safety performance/Deficient discovered discussed/Positive feedback/Workers resolving safety issues) | AC25: 1
B27: Prepared by: | G27: ENG/MOHAMED FAIZAN | S27: Sent to MODON PM: | X27: =Y4 -> ENG/ YAZEED ALRAGABAH
B28: Safety Results
B29: 1 | D29: =COUNTIF(L13:Q26,"1")+COUNTIF(AB13:AG26,"1") -> 18 | I29: 2 | L29: =COUNTIF(L13:Q26,"2")+COUNTIF(AB13:AG26,"2") -> 5 | U29: 3 | W29: =COUNTIF(L13:Q26,"3")+COUNTIF(AB13:AG26,"3") -> 0

Sheet HSE-Stat
A1: Safety Statistics
A3: Category | B3: Item | D3: This Week | E3: This Month | F3: Year to Date | G3: Cumulative
A4: Category | B4: Total Hours Worked | D4: 9660 | E4: =10980+9660 -> 20640 | F4: =32500+4500+4740+4800+5740+5740+6060+6060+6180+6180+6180+6180+6180+6360+3924+3270+6420+6480+5340+5340+5340+5580+6000+6000+7440+2420+7680+10650+12120+12120+12000+12420+12420+12420+12420+12420+12420+12420+13500+13500+11520+10980+9660 -> 371624 | G4: =F4 -> 371624 | K4: =16*4 -> 64 | L4: =COUNTA(D4:G19) -> 64
B5: Safe Hours Worked | D5: =D4 -> 9660 | E5: =E4 -> 20640 | F5: =F4 -> 371624 | G5: =F5 -> 371624 | L5: =COUNTBLANK(D4:G19) -> 0
A6: Reactive | B6: LTI | D6: 0 | E6: 0 | F6: 0 | G6: 0
B7: MTC (Healed w/o Disability) | D7: 0 | E7: 0 | F7: 0 | G7: 0 | M7: =107*10*6 -> 6420
B8: MTC (Healed w/ Disability) | D8: 0 | E8: 0 | F8: 0 | G8: 0
B9: Near Miss | D9: 0 | E9: 0 | F9: 0 | G9: 0 | J9: =750*6 -> 4500
B10: First Aid Cases | D10: 0 | E10: 0 | F10: 0 | G10: 0
B11: Fatality | D11: 0 | E11: 0 | F11: 0 | G11: 0 | L11: =101*10*6 -> 6060
B12: Fire Incident Cases | D12: 0 | E12: 0 | F12: 0 | G12: 0
B13: Vehicle Incident | D13: 0 | E13: 0 | F13: 0 | G13: 0 | O13: =103*10*6 -> 6180
B14: Property Damages | D14: 0 | E14: 0 | F14: 0 | G14: 0
A15: Proactive | B15: Induction Training | D15: 0 | E15: 0 | F15: 7 | G15: 8
B16: No.of Internal Training | D16: 0 | E16: 1 | F16: 18 | G16: 18
B17: No.of Internal Audit | D17: 0 | E17: 0 | F17: 0 | G17: 0
B18: No. of Toolbox Talks | D18: 1 | E18: 2 | F18: 36 | G18: 36
B19: Safety Awards/Incentives | D19: 0 | E19: 0 | F19: 0 | G19: 0
I20: Category | J20: Item | L20: This Week | M20: This Month | N20: Year to Date | O20: Cumulative
A22: Consultant Safety Inspection (Weekly Basis) | I22: Overall Average | J22: =AVERAGE(E24:E98) -> 0.86853448
A23: Week Number | B23: Date of Audit | C23: Date Issued | D23: Numbers Of Comments | E23: Overall Score | F23: Date Closed | G23: Closure Duration | I23: This Week Score | J23: =HSE!AE6 -> 0.94565217
A24: Week-1 | B24: 45904 | C24: =B24 -> 45904 | D24: 7 | E24: 0.75 | F24: =C24+1 -> 45905 | G24: 1
A25: Week-2 | B25: 45911 | C25: =B25 -> 45911 | D25: 1 | E25: 0.81818182 | F25: =C25+1 -> 45912 | G25: 1
A26: Week-3 | B26: 45918 | C26: =B26 -> 45918 | D26: 2 | E26: 0.82 | F26: =C26+1 -> 45919 | G26: 1
A27: Week-4 | B27: 45925 | C27: =B27 -> 45925 | D27: 2 | E27: 0.81818182 | F27: =C27+1 -> 45926 | G27: 1
A28: Week-5 | B28: 45932 | C28: =B28 -> 45932 | D28: 6 | E28: 0.73 | F28: =C28+1 -> 45933 | G28: 1
A29: Week-6 | B29: 45939 | C29: =B29 -> 45939 | D29: 6 | E29: 0.79545455 | F29: =C29+1 -> 45940 | G29: 1
A30: Week-7 | B30: 45946 | C30: =B30 -> 45946 | D30: 5 | E30: 0.79545455 | F30: =C30+1 -> 45947 | G30: 1
A31: Week-8 | B31: 45953 | C31: =B31 -> 45953 | D31: 5 | E31: 0.79545455 | F31: =C31+1 -> 45954 | G31: 1
A32: Week-9 | B32: 45960 | C32: =B32 -> 45960 | D32: 1 | E32: 0.81818182 | F32: =C32+1 -> 45961 | G32: 1
A33: Week-10 | B33: 45967 | C33: =B33 -> 45967 | D33: 5 | E33: 0.89 | F33: =C33+1 -> 45968 | G33: 1
A34: Week-11 | B34: 45974 | C34: =B34 -> 45974 | D34: 2 | E34: 0.875 | F34: =C34+1 -> 45975 | G34: 1
A35: Week-12 | B35: 45981 | C35: =B35 -> 45981 | D35: 2 | E35: 0.875 | F35: =C35+2 -> 45983 | G35: 2
A36: Week-13 | B36: 45988 | C36: =B36 -> 45988 | D36: 2 | E36: 0.89 | F36: =C36+2 -> 45990 | G36: 2
A37: Week-14 | B37: 45995 | C37: =B37 -> 45995 | D37: 1 | E37: 0.89 | F37: =C37+2 -> 45997 | G37: 2
A38: Week-15 | B38: 46002 | C38: =B38 -> 46002 | D38: 2 | E38: 0.45 | F38: =C38+4 -> 46006 | G38: 4
A39: Week-16 | B39: 46010 | C39: =B39 -> 46010 | D39: 2 | E39: 0.9 | F39: =C39+1 -> 46011 | G39: =F39-C39 -> 1
A40: Week-17 | B40: 46016 | C40: =B40 -> 46016 | D40: 6 | E40: 0.79545455 | F40: =(C40+G40) -> 46018 | G40: 2
A41: Week-18 | B41: 46023 | C41: =B41 -> 46023 | D41: 5 | E41: 0.79545455 | F41: =(C41+G41) -> 46025 | G41: 2
A42: Week-19 | B42: 46030 | C42: =B42 -> 46030 | D42: 5 | E42: 0.79545455 | F42: =(C42+G42) -> 46031 | G42: 1
A43: Week-20 | B43: 46037 | C43: =B43 -> 46037 | D43: 1 | E43: 0.81818182 | F43: =(C43+G43) -> 46038 | G43: 1
A44: Week-21 | B44: 46044 | C44: =B44 -> 46044 | D44: 5 | E44: 0.89 | F44: =(C44+G44) -> 46047 | G44: 3
A45: Week-22 | B45: 46051 | C45: =B45 -> 46051 | D45: 2 | E45: 0.875 | F45: =(C45+G45) -> 46053 | G45: 2
A46: Week-23 | B46: 46058 | C46: =B46 -> 46058 | D46: 2 | E46: 0.875 | F46: =(C46+G46) -> 46059 | G46: 1
A47: Week-24 | B47: 46065 | C47: =B47 -> 46065 | D47: 2 | E47: 0.89 | F47: =(C47+G47) -> 46066 | G47: 1
A48: Week-25 | B48: 46072 | C48: =B48 -> 46072 | D48: 1 | E48: 0.89 | F48: =(C48+G48) -> 46073 | G48: 1
A49: Week-26 | B49: 46079 | C49: =B49 -> 46079 | D49: 2 | E49: 0.79545455 | F49: =(C49+G49) -> 46080 | G49: 1
A50: Week-27 | B50: 46086 | C50: =B50 -> 46086 | D50: 2 | E50: 0.79545455 | F50: =(C50+G50) -> 46087 | G50: 1
A51: Week-28 | B51: 46093 | C51: =B51 -> 46093 | D51: 5 | E51: 0.79545455 | F51: =(C51+G51) -> 46095 | G51: 2
... A56: Week-33 | B56: 46128 | C56: =B56 -> 46128 | D56: 1 | E56: 0.87 | F56: =(C56+G56) -> 46128 | G56: 0
A57: Week-34 | B57: 46132 | C57: =B57 -> 46132 | D57: 2 | E57: 0.86 | F57: 46132 | G57: 1
A58: Week-35 | B58: 46135 | C58: =B58 -> 46135 | D58: 2 | E58: 0.88 | F58: 46136 | G58: 1
A59: Week-36 | B59: 46144 | C59: =B59 -> 46144 | D59: 1 | E59: 0.93 | F59: 46144 | G59: 1
A60: Week-37 | B60: 46152 | C60: =B60 -> 46152 | D60: 2 | E60: 0.95 | F60: 46153 | G60: 1
A61: Week-38 | B61: 46159 | C61: 46159 | D61: 1 | E61: 0.93 | F61: 46160 | G61: 1
A62: Week-39 | B62: 46163 | C62: =B62 -> 46163 | D62: 2 | E62: 0.95 | F62: 46164 | G62: 1
A63: Week-40 | B63: 46173 | C63: =B63 -> 46173 | D63: 0 | E63: 0.95 | F63: 46173 | G63: 0
A64: Week-41 | B64: 46186 | C64: =B64 -> 46186 | D64: 1 | E64: 0.95 | F64: 46187 | G64: 2
A65: Week-42 | B65: 46193 | C65: 46193 | D65: 1 | E65: 0.95 | F65: 46194 | G65: 1
A66: Week-43 | B66: 46200 | C66: 46200 | D66: 1 | E66: 0.95 | F66: 46201 | G66: 1
A67: Week-44 | B67: 46208 | C67: 46208 | D67: 2 | E67: 0.95 | F67: 46209 | G67: 1
A68: Week-45 | B68: 46212 | C68: 46212 | D68: 12 | E68: 0.8 | F68: 46217 | G68: 6
A69: Week-46 | B69: 46221 | C69: 46221 | D69: 1 | E69: 0.95 | F69: 46222 | G69: 1
A70: Week-47 | B70: 46228 | C70: 46228 | D70: 1 | E70: 0.95 | F70: 46229 | G70: 1
A71: Week-48 | B71: 46235 | C71: 46235 | D71: 1 | E71: 0.95 | F71: 46236 | G71: 1
A72: Week-49 | B72: 46239 | C72: 46239 | D72: 1 | E72: 0.95 | F72: 46240 | G72: 1
A73: Week-50 | B73: 46249 | C73: 46249 | D73: 1 | E73: 0.95 | F73: 46250 | G73: 1
A74: Week-51 | B74: 46257 | C74: =B74 -> 46257 | D74: 1 | E74: 0.95 | F74: 46258 | G74: 1
A75: Week-52 | B75: 46263 | C75: 46263 | D75: 1 | E75: 0.95 | F75: 46264 | G75: 1
A76: Week-53 | B76: 46271 | C76: 46271 | D76: 1 | E76: 0.95 | F76: 46272 | G76: 1
A77: Week-54 | B77: 46277 | C77: 46277 | D77: 2 | E77: 0.95 | F77: 46278 | G77: 1
A78: Week-55 | B78: 46284 | C78: 46284 | D78: 1 | E78: 0.95 | F78: 46285 | G78: 1
A79: Week-56 | B79: 46292 | C79: 46292 | D79: 1 | E79: 0.95 | F79: 46293 | G79: 1
A80: Week-57 | B80: 46298 | C80: 46298 | D80: 2 | E80: 0.95 | F80: 46299 | G80: 2
A81: Week-58 | B81: 46305 | C81: 46305 | D81: 3 | E81: 0.95 | F81: 46306 | G81: 1
A82: Week-59
A83: Week-60
A84: Week-61
A85: Week-62
A86: Week-63
A87: Week-64
A88: Week-65
A89: Week-66
A90: Week-67
A91: Week-68
A92: Week-69
A93: Week-70
... A98: Week-75

Sheet Major Quantities
A1: BOQ Number | B1: Description of Item | C1: Total Quantity | D1: Unit of Measurement | E1: Plan To Date | F1: Actual To Date | G1: Remaining Total | H1: Variance | I1: Variance % | J1: Notices | L1: Perf. %
A2: 31 22 00 05 | B2: POND Excavation | C2: 321070 | D2: M3 | E2: 296255 | F2: 296255 | G2: =C2-F2 -> 24815 | H2: =F2-E2 -> 0 | I2: =H2/C2 -> 0 | L2: =F2/C2 -> 0.92271156
A3: 31 22 00 01 | B3: ROAD Excavation | C3: 99925 | D3: M3 | E3: 99925 | F3: 93475 | G3: =C3-F3 -> 6450 | H3: =F3-E3 -> -6450 | I3: =H3/C3 -> -0.064548411 | L3: =F3/C3 -> 0.93545159
A4: 31 22 00 02 | B4: ROAD BACKFILL | C4: 107100 | D4: M3 | E4: 107100 | F4: 81600 | G4: =C4-F4 -> 25500 | H4: =F4-E4 -> -25500 | I4: =H4/C4 -> -0.23809524 | L4: =F4/C4 -> 0.76190476
A5: 32 22 00 03 | B5: ROAD SUPGRADE | C5: 72730 | D5: M3 | E5: 72730 | F5: 53900 | G5: =C5-F5 -> 18830 | H5: =F5-E5 -> -18830 | I5: =H5/C5 -> -0.25890279 | L5: =F5/C5 -> 0.74109721
A6: 33 31 00 | B6: SEWAGE network | C6: 8370 | D6: M | F6: 6965 | G6: =C6-F6 -> 1405 | H6: =F6-E6 -> 6965 | I6: =H6/C6 -> 0.83213859 | L6: =F6/C6 -> 0.83213859
A7: 33 31 00 | B7: STORM network | C7: 15638 | D7: M | F7: 13112 | G7: =C7-F7 -> 2526 | H7: =F7-E7 -> 13112 | I7: =H7/C7 -> 0.83847039 | L7: =F7/C7 -> 0.83847039
A8: 31 22 00 07 | B8: BACKFILLING DIKE | C8: 3865 | D8: M3 | F8: 3865 | G8: =C8-F8 -> 0 | H8: =F8-E8 -> 3865 | I8: =H8/C8 -> 1 | L8: =F8/C8 -> 1
B9: TSE network | C9: 12223 | D9: M | F9: 8178 | G9: =C9-F9 -> 4045 | H9: =F9-E9 -> 8178 | I9: =H9/C9 -> 0.66906651 | L9: =F9/C9 -> 0.66906651
B10: POTABLE WATER network | C10: 13221 | D10: M | F10: 9239 | G10: =C10-F10 -> 3982 | H10: =F10-E10 -> 9239 | I10: =H10/C10 -> 0.6988125 | K10: =80800+800 -> 81600 | L10: =F10/C10 -> 0.6988125
B11: ELECTRICAL MV | C11: 23700 | D11: M | F11: 4998 | G11: =C11-F11 -> 18702 | H11: =F11-E11 -> 4998 | I11: =H11/C11 -> 0.21088608 | L11: =F11/C11 -> 0.21088608
B12: BBC | C12: 27310 | D12: M3 | F12: 7972 | G12: =C12-F12 -> 19338 | H12: =F12-E12 -> 7972 | I12: =H12/C12 -> 0.29190773 | L12: =F12/C12 -> 0.29190773
B13: ABC | C13: 48485 | D13: M3 | F13: 18078 | G13: =C13-F13 -> 30407 | H13: =F13-E13 -> 18078 | I13: =H13/C13 -> 0.37285758 | L13: =F13/C13 -> 0.37285758
G14: =C14-F14 -> 0 | H14: =F14-E14 -> 0 | L14: =F14/C14 -> #DIV/0!
G15: =C15-F15 -> 0 | H15: =F15-E15 -> 0 | L15: =F15/C15 -> #DIV/0!
G16: =C16-F16 -> 0 | H16: =F16-E16 -> 0 | L16: =F16/C16 -> #DIV/0!
G17: =C17-F17 -> 0 | H17: =F17-E17 -> 0 | L17: =F17/C17 -> #DIV/0!
G18: =C18-F18 -> 0 | H18: =F18-E18 -> 0 | L18: =F18/C18 -> #DIV/0!
G19: =C19-F19 -> 0 | H19: =F19-E19 -> 0 | L19: =F19/C19 -> #DIV/0!
G20: =C20-F20 -> 0 | H20: =F20-E20 -> 0 | L20: =F20/C20 -> #DIV/0!
A32: Activity ID | B32: Activity Name | C32: Resource Name | D32: Price / Unit | E32: Budgeted Units | F32: Actual Units | G32: Budgeted Cost | I32: Actual | J32: 45319 | K32: 45320 | L32: 45321 | M32: 45322 | N32: 45323 | O32: 45324 | P32: 45325 | Q32: 45326 | R32: 45327 | S32: 45328 | T32: 45329 | U32: 45330 | V32: 45331 | W32: 45332 | X32: 45333 | Y32: 45334 | Z32: 45335 | AA32: 45336 | AB32: 45337 | AC32: 45338 | AD32: 45339 | AE32: 45340 | AF32: 45341 | AG32: 45342 | AH32: 45343 | AI32: 45344 | AJ32: 45345 | AK32: 45346 | AL32: 45347 | AM32: 45348 | AN32: 45349 | AO32: 45350 | AP32: 45351 | AQ32: 45352 | AR32: 45353 | AS32: 45354 | AT32: 45355 | AU32: 45356 | AV32: 45357 | AW32: 45358 | AX32: 45359 | AY32: 45360 | AZ32: 45361 | BA32: 45362 | BB32: 45363 | BC32: 45364 | BD32: 45365 | BE32: 45366 | BF32: 45367 | BG32: 45368 | BH32: 45369 | BI32: 45370 | BJ32: 45371 | BK32: 45372 | BL32: 45373 | BM32: 45374 | BN32: 45375 | BO32: 45376 | BP32: 45377 | BQ32: 45378 | BR32: 45379 | BS32: 45380 | BT32: 45381 | BU32: 45382 | BV32: 45383 | BW32: 45384 | BX32: 45385 | BY32: 45386 | BZ32: 45387 | CA32: 45388 | CB32: 45389 | CC32: 45390 | CD32: 45391 | CE32: 45392 | CF32: 45393 | CG32: 45394 | CH32: 45395 | CI32: 45396 | CJ32: 45397 | CK32: 45398 | CL32: 45399 | CM32: 45400 | CN32: 45401 | CO32: 45402 | CP32: 45403 | CQ32: 45404 | CR32: 45405 | CS32: 45406 | CT32: 45407 | CU32: 45408 | CV32: 45409 | CW32: 45410 | CX32: 45411 | CY32: 45412 | CZ32: 45413 | DA32: 45414 | DB32: 45415 | DC32: 45416 | DD32: 45417 | DE32: 45418 | DF32: 45419 | DG32: 45420 | DH32: 45421 | DI32: 45422 | DJ32: 45423 | DK32: 45424 | DL32: 45425 | DM32: 45426 | DN32: 45427 | DO32: 45428 | DP32: 45429 | DQ32: 45430 | DR32: 45431 | DS32: 45432 | DT32: 45433 | DU32: 45434 | DV32: 45435 | DW32: 45436 | DX32: 45437 | DY32: 45438 | DZ32: 45439 | EA32: 45440 | EB32: 45441 | EC32: 45442 | ED32: 45443 | EE32: 45444 | EF32: 45445 | EG32: 45446 | EH32: 45447 | EI32: 45448 | EJ32: 45449 | EK32: 45450 | EL32: 45451 | EM32: 45452 | EN32: 45453 | EO32: 45454 | EP32: 45455 | EQ32: 45456 | ER32: 45457 | ES32: 45458 | ET32: 45459 | EU32: 45460 | EV32: 45461 | EW32: 45462 | EX32: 45463 | EY32: 45464 | EZ32: 45465 | FA32: 45466 | FB32: 45467 | FC32: 45468 | FD32: 45469 | FE32: 45470 | FF32: 45471 | FG32: 45472 | FH32: 45473 | FI32: 45474 | FJ32: 45475 | FK32: 45476 | FL32: 45477 | FM32: 45478 | FN32: 45479 | FO32: 45480 | FP32: 45481 | FQ32: 45482 | FR32: 45483 | FS32: 45484 | FT32: 45485 | FU32: 45486 | FV32: 45487 | FW32: 45488 | FX32: 45489 | FY32: 45490 | FZ32: 45491 | GA32: 45492 | GB32: 45493 | GC32: 45494 | GD32: 45495 | GE32: 45496 | GF32: 45497 | GG32: 45498 | GH32: 45499 | GI32: 45500 | GJ32: 45501 | GK32: 45502 | GL32: 45503 | GM32: 45504 | GN32: 45505 | GO32: 45506 | GP32: 45507 | GQ32: 45508 | GR32: 45509 | GS32: 45510 | GT32: 45511 | GU32: 45512 | GV32: 45513 | GW32: 45514 | GX32: 45515 | GY32: 45516 | GZ32: 45517 | HA32: 45518 | HB32: 45519 | HC32: 45520 | HD32: 45521 | HE32: 45522 | HF32: 45523 | HG32: 45524 | HH32: 45525 | HI32: 45526 | HJ32: 45527 | HK32: 45528 | HL32: 45529 | HM32: 45530 | HN32: 45531 | HO32: 45532 | HP32: 45533 | HQ32: 45534 | HR32: 45535 | HS32: 45536 | HT32: 45537 | HU32: 45538 | HV32: 45539 | HW32: 45540 | HX32: 45541 | HY32: 45542 | HZ32: 45543 | IA32: 45544 | IB32: 45545 | IC32: 45546 | ID32: 45547 | IE32: 45548 | IF32: 45549 | IG32: 45550 | IH32: 45551 | II32: 45552 | IJ32: 45553 | IK32: 45554 | IL32: 45555 | IM32: 45556 | IN32: 45557 | IO32: 45558 | IP32: 45559 | IQ32: 45560 | IR32: 45561 | IS32: 45562 | IT32: 45563 | IU32: 45564 | IV32: 45565 | IW32: 45566 | IX32: 45567 | IY32: 45568 | IZ32: 45569 | JA32: 45570 | JB32: 45571 | JC32: 45572 | JD32: 45573 | JE32: 45574 | JF32: 45575 | JG32: 45576 | JH32: 45577 | JI32: 45578 | JJ32: 45579 | JK32: 45580 | JL32: 45581 | JM32: 45582 | JN32: 45583 | JO32: 45584 | JP32: 45585 | JQ32: 45586 | JR32: 45587 | JS32: 45588 | JT32: 45589 | JU32: 45590 | JV32: 45591 | JW32: 45592 | JX32: 45593 | JY32: 45594 | JZ32: 45595 | KA32: 45596 | KB32: 45597 | KC32: 45598 | KD32: 45599 | KE32: 45600 | KF32: 45601 | KG32: 45602 | KH32: 45603 | KI32: 45604 | KJ32: 45605 | KK32: 45606 | KL32: 45607 | KM32: 45608 | KN32: 45609 | KO32: 45610 | KP32: 45611 | KQ32: 45612 | KR32: 45613 | KS32: 45614 | KT32: 45615 | KU32: 45616 | KV32: 45617 | KW32: 45618 | KX32: 45619 | KY32: 45620 | KZ32: 45621 | LA32: 45622 | LB32: 45623 | LC32: 45624 | LD32: 45625 | LE32: 45626 | LF32: 45627 | LG32: 45628 | LH32: 45629 | LI32: 45630 | LJ32: 45631 | LK32: 45632 | LL32: 45633 | LM32: 45634 | LN32: 45635 | LO32: 45636 | LP32: 45637 | LQ32: 45638 | LR32: 45639 | LS32: 45640 | LT32: 45641 | LU32: 45642 | LV32: 45643 | LW32: 45644 | LX32: 45645 | LY32: 45646 | LZ32: 45647 | MA32: 45648 | MB32: 45649 | MC32: 45650 | MD32: 45651 | ME32: 45652 | MF32: 45653 | MG32: 45654 | MH32: 45655 | MI32: 45656 | MJ32: 45657 | MK32: 45658 | ML32: 45659 | MM32: 45660 | MN32: 45661 | MO32: 45662 | MP32: 45663 | MQ32: 45664 | MR32: 45665 | MS32: 45666 | MT32: 45667 | MU32: 45668 | MV32: 45669 | MW32: 45670 | MX32: 45671 | MY32: 45672 | MZ32: 45673 | NA32: 45674 | NB32: 45675 | NC32: 45676 | ND32: 45677 | NE32: 45678 | NF32: 45679 | NG32: 45680 | NH32: 45681 | NI32: 45682 | NJ32: 45683 | NK32: 45684 | NL32: 45685 | NM32: 45686 | NN32: 45687 | NO32: 45688 | NP32: 45689 | NQ32: 45690 | NR32: 45691 | NS32: 45692 | NT32: 45693 | NU32: 45694 | NV32: 45695 | NW32: 45696 | NX32: 45697 | NY32: 45698 | NZ32: 45699 | OA32: 45700 | OB32: 45701 | OC32: 45702 | OD32: 45703 | OE32: 45704 | OF32: 45705 | OG32: 45706 | OH32: 45707 | OI32: 45708 | OJ32: 45709 | OK32: 45710 | OL32: 45711 | OM32: 45712 | ON32: 45713 | OO32: 45714 | OP32: 45715 | OQ32: 45716 | OR32: 45717 | OS32: 45718 | OT32: 45719 | OU32: 45720 | OV32: 45721 | OW32: 45722 | OX32: 45723 | OY32: 45724 | OZ32: 45725 | PA32: 45726 | PB32: 45727 | PC32: 45728 | PD32: 45729 | PE32: 45730 | PF32: 45731 | PG32: 45732 | PH32: 45733 | PI32: 45734 | PJ32: 45735 | PK32: 45736 | PL32: 45737 | PM32: 45738 | PN32: 45739 | PO32: 45740 | PP32: 45741 | PQ32: 45742 | PR32: 45743 | PS32: 45744 | PT32: 45745 | PU32: 45746 | PV32: 45747 | PW32: 45748 | PX32: 45749 | PY32: 45750 | PZ32: 45751 | QA32: 45752 | QB32: 45753 | QC32: 45754 | QD32: 45755 | QE32: 45756 | QF32: 45757 | QG32: 45758 | QH32: 45759 | QI32: 45760 | QJ32: 45761 | QK32: 45762 | QL32: 45763 | QM32: 45764 | QN32: 45765 | QO32: 45766 | QP32: 45767 | QQ32: 45768 | QR32: 45769 | QS32: 45770 | QT32: 45771 | QU32: 45772 | QV32: 45773 | QW32: 45774 | QX32: 45775 | QY32: 45776 | QZ32: 45777 | RA32: 45778 | RB32: 45779 | RC32: 45780 | RD32: 45781 | RE32: 45782 | RF32: 45783 | RG32: 45784 | RH32: 45785 | RI32: 45786 | RJ32: 45787 | RK32: 45788 | RL32: 45789 | RM32: 45790 | RN32: 45791 | RO32: 45792 | RP32: 45793 | RQ32: 45794 | RR32: 45795 | RS32: 45796 | RT32: 45797 | RU32: 45798 | RV32: 45799 | RW32: 45800 | RX32: 45801 | RY32: 45802 | RZ32: 45803 | SA32: 45804 | SB32: 45805 | SC32: 45806 | SD32: 45807 | SE32: 45808 | SF32: 45809 | SG32: 45810 | SH32: 45811 | SI32: 45812 | SJ32: 45813 | SK32: 45814 | SL32: 45815 | SM32: 45816 | SN32: 45817 | SO32: 45818 | SP32: 45819 | SQ32: 45820 | SR32: 45821 | SS32: 45822 | ST32: 45823 | SU32: 45824 | SV32: 45825 | SW32: 45826 | SX32: 45827 | SY32: 45828 | SZ32: 45829 | TA32: 45830 | TB32: 45831 | TC32: 45832 | TD32: 45833 | TE32: 45834 | TF32: 45835 | TG32: 45836 | TH32: 45837 | TI32: 45838 | TJ32: 45839 | TK32: 45840 | TL32: 45841 | TM32: 45842 | TN32: 45843 | TO32: 45844 | TP32: 45845 | TQ32: 45846 | TR32: 45847 | TS32: 45848 | TT32: 45849 | TU32: 45850 | TV32: 45851 | TW32: 45852 | TX32: 45853 | TY32: 45854 | TZ32: 45855 | UA32: 45856 | UB32: 45857 | UC32: 45858 | UD32: 45859 | UE32: 45860 | UF32: 45861 | UG32: 45862 | UH32: 45863 | UI32: 45864 | UJ32: 45865 | UK32: 45866 | UL32: 45867 | UM32: 45868 | UN32: 45869 | UO32: 45870 | UP32: 45871 | UQ32: 45872 | UR32: 45873 | US32: 45874 | UT32: 45875 | UU32: 45876 | UV32: 45877 | UW32: 45878 | UX32: 45879 | UY32: 45880 | UZ32: 45881 | VA32: 45882 | VB32: 45883 | VC32: 45884 | VD32: 45885 | VE32: 45886 | VF32: 45887 | VG32: 45888 | VH32: 45889 | VI32: 45890 | VJ32: 45891 | VK32: 45892 | VL32: 45893 | VM32: 45894 | VN32: 45895 | VO32: 45896 | VP32: 45897 | VQ32: 45898 | VR32: 45899 | VS32: 45900 | VT32: 45901 | VU32: 45902 | VV32: 45903 | VW32: 45904 | VX32: 45905 | VY32: 45906 | VZ32: 45907 | WA32: 45908 | WB32: 45909 | WC32: 45910 | WD32: 45911 | WE32: 45912 | WF32: 45913 | WG32: 45914 | WH32: 45915 | WI32: 45916 | WJ32: 45917 | WK32: 45918 | WL32: 45919 | WM32: 45920 | WN32: 45921 | WO32: 45922 | WP32: 45923 | WQ32: 45924 | WR32: 45925 | WS32: 45926 | WT32: 45927 | WU32: 45928 | WV32: 45929 | WW32: 45930 | WX32: 45931 | WY32: 45932 | WZ32: 45933 | XA32: 45934 | XB32: 45935 | XC32: 45936 | XD32: 45937 | XE32: 45938 | XF32: 45939 | XG32: 45940 | XH32: 45941 | XI32: 45942 | XJ32: 45943 | XK32: 45944 | XL32: 45945 | XM32: 45946 | XN32: 45947 | XO32: 45948 | XP32: 45949 | XQ32: 45950 | XR32: 45951 | XS32: 45952 | XT32: 45953 | XU32: 45954 | XV32: 45955 | XW32: 45956 | XX32: 45957 | XY32: 45958 | XZ32: 45959 | YA32: 45960 | YB32: 45961 | YC32: 45962 | YD32: 45963 | YE32: 45964 | YF32: 45965 | YG32: 45966 | YH32: 45967 | YI32: 45968 | YJ32: 45969 | YK32: 45970 | YL32: 45971 | YM32: 45972 | YN32: 45973 | YO32: 45974 | YP32: 45975 | YQ32: 45976 | YR32: 45977 | YS32: 45978 | YT32: 45979 | YU32: 45980 | YV32: 45981 | YW32: 45982 | YX32: 45983 | YY32: 45984 | YZ32: 45985 | ZA32: 45986 | ZB32: 45987 | ZC32: 45988 | ZD32: 45989 | ZE32: 45990 | ZF32: 45991 | ZG32: 45992 | ZH32: 45993 | ZI32: 45994 | ZJ32: 45995 | ZK32: 45996 | ZL32: 45997 | ZM32: 45998 | ZN32: 45999 | ZO32: 46000 | ZP32: 46001 | ZQ32: 46002 | ZR32: 46003 | ZS32: 46004 | ZT32: 46005 | ZU32: 46006 | ZV32: 46007 | ZW32: 46008 | ZX32: 46009
A33: Total | E33: 102031 | F33: 44934.91 | G33: 45093675 | I33: =F33 -> 44934.91 | J33: 21.55 | K33: 21.55 | L33: 21.55 | M33: 21.55 | N33: 21.55 | P33: 21.83 | Q33: 21.83 | R33: 21.83 | S33: 0.27 | T33: 0.27 | U33: 1.46 | W33: 1.46 | X33: 1.46 | Y33: 70.33 | Z33: 70.33 | AA33: 70.33 | AB33: 112.19 | AD33: 112.19 | AE33: 112.19 | AF33: 59.21 | AG33: 59.21 | AH33: 59.21 | AK33: 35.32 | AL33: 35.32 | AM33: 16.44 | AN33: 16.85 | AO33: 16.85 | AP33: 0.87 | AR33: 0.27 | AS33: 0.27 | AT33: 0 | AU33: 0 | AV33: 0 | AW33: 189.2 | AY33: 189.2 | AZ33: 189.2 | BA33: 141.9 | BB33: 141.9 | BC33: 141.9 | BD33: 141.9 | BF33: 141.9 | BG33: 141.9 | BH33: 141.9 | BI33: 141.9 | BJ33: 141.9 | BK33: 141.9 | BM33: 141.9 | BN33: 141.9 | BO33: 141.9 | BP33: 141.9 | BQ33: 141.9 | BR33: 141.9 | BT33: 141.9 | BU33: 141.9 | BV33: 141.9 | BW33: 141.9 | BX33: 127.2 | BY33: 126.6 | CA33: 126.6 | CB33: 126.6 | CC33: 126.6 | CD33: 126.6 | CJ33: 168.8 | CK33: 168.8 | CL33: 168.8 | CM33: 168.8 | CO33: 168.8 | CP33: 168.8 | CQ33: 168.8 | CR33: 168.8 | CS33: 168.8 | CT33: 168.8 | CV33: 168.8 | CW33: 168.8 | CX33: 168.8 | CY33: 176.59 | CZ33: 184.37 | DA33: 184.37 | DC33: 184.37 | DD33: 184.37 | DE33: 184.37 | DF33: 184.37 | DG33: 184.48 | DH33: 184.59 | DJ33: 184.59 | DK33: 184.59 | DL33: 184.59 | DM33: 188.22 | DN33: 191.86 | DO33: 191.87 | DQ33: 192.51 | DR33: 193.15 | DS33: 189.52 | DT33: 173.9 | DU33: 161.91 | DV33: 162.5 | DX33: 164.88 | DY33: 167.11 | DZ33: 167.57 | EA33: 167.58 | EB33: 166.99 | EC33: 168.41 | EE33: 169.07 | EF33: 168.89 | EG33: 170.07 | EH33: 170.1 | EI33: 168.12 | EJ33: 166.1 | EL33: 173.18 | EM33: 181.19 | EN33: 182.12 | EO33: 182.19 | EP33: 182.26 | EQ33: 715.97 | ES33: 1253.81 | ET33: 1257.95 | EZ33: 1259.46 | FA33: 1260.97 | FB33: 1261.4 | FC33: 1257.71 | FD33: 1256.27 | FE33: 1258.96 | FG33: 1258.8 | FH33: 1259.08 | FI33: 1257.81 | FJ33: 1253.41 | FK33: 1250.72 | FL33: 1250.72 | FN33: 1256.66 | FO33: 1261.05 | FP33: 1261.24 | FQ33: 1262.99 | FR33: 1262.99 | FS33: 1396.73 | FU33: 1526.57 | FV33: 1521.77 | FW33: 1520.73 | FX33: 1520.58 | FY33: 1520.58 | FZ33: 1518.2 | GB33: 1516.6 | GC33: 1522.61 | GD33: 1531.64 | GE33: 1535.45 | GF33: 785.51 | GG33: 35.59 | GI33: 28.78 | GJ33: 21.94 | GK33: 21.94 | GL33: 23.84 | GM33: 25.12 | GN33: 24.42 | GP33: 24.2 | GQ33: 36.24 | GR33: 48.4 | GS33: 52.11 | GT33: 55.84 | GU33: 55.69 | GW33: 42.55 | GX33: 28.38 | GY33: 33.58 | GZ33: 40.48 | HA33: 41.01 | HB33: 41.81 | HD33: 72.51 | HE33: 274.38 | HF33: 459.01 | HG33: 471.56 | HH33: 471.46 | HI33: 467.45 | HK33: 464.26 | HL33: 452.44 | HM33: 444.04 | HN33: 448.3 | HO33: 448.19 | HP33: 445.73 | HR33: 444.97 | HS33: 442.3 | HT33: 438.04 | HU33: 260.54 | HV33: 83.03 | HW33: 78.29 | HY33: 43.88 | HZ33: 13.3 | IA33: 197.77 | IB33: 383.29 | IC33: 383.45 | ID33: 381.68 | IF33: 380 | IG33: 194.34 | IH33: 8.59 | II33: 8.59 | IJ33: 8.77 | IK33: 8.69 | IM33: 8.43 | IN33: 8.44 | IP33: 8.28 | IQ33: 8.96 | IR33: 9.8 | IT33: 9.74 | IU33: 11.69 | IV33: 13.68 | IW33: 14.81 | IX33: 15.72 | IY33: 15.51 | JA33: 14.14 | JB33: 15.53 | JC33: 19.42 | JD33: 22.57 | JE33: 24.53 | JF33: 27.69 | JH33: 35.94 | JI33: 41.52 | JJ33: 42.66 | JK33: 42.76 | JL33: 53.47 | JM33: 69.64 | JO33: 62.96 | JP33: 58.15 | JQ33: 72.8 | JR33: 112.27 | JS33: 142.58 | JT33: 129.26 | JV33: 127.31 | JW33: 144.73 | JX33: 105.34 | JY33: 57.11 | JZ33: 64.4 | KA33: 64.56 | KC33: 46.25 | KD33: 41.41 | KE33: 50.63 | KF33: 54.8 | KG33: 49.72 | KH33: 44.52 | KJ33: 47.52 | KK33: 50.57 | KL33: 39.97 | KM33: 29.71 | KN33: 37.26 | KO33: 44.53 | KQ33: 39.58 | KR33: 33.69 | KS33: 51.95 | KT33: 91.66 | KU33: 108.72 | KV33: 106.4 | KX33: 107.85 | KY33: 99.66 | KZ33: 92.65 | LA33: 83.03 | LB33: 72.46 | LC33: 60.56 | LE33: 48.38 | LF33: 45.24 | LG33: 44.94 | LH33: 57.38 | LI33: 66.43 | LJ33: 97.63 | LL33: 122.69 | LM33: 88.44 | LN33: 64.32 | LO33: 139.59 | LP33: 214.39 | LQ33: 219.2 | LS33: 217.1 | LT33: 215.73 | LU33: 224.41 | LV33: 153.08 | LW33: 75.72 | LX33: 77.28 | LZ33: 77.93 | MA33: 79.36 | MB33: 76.9 | MC33: 73.16 | MD33: 71.12 | ME33: 78.67 | MG33: 87.82 | MH33: 87.1 | MI33: 77.2 | MJ33: 62.8 | MK33: 63.13 | ML33: 66.81 | MN33: 64.95 | MO33: 63.67 | MP33: 51.03 | MQ33: 37.85 | MR33: 33.5 | MS33: 29.9 | MU33: 29.85 | MV33: 28.91 | MW33: 27.97 | MX33: 23.83 | MY33: 38.57 | MZ33: 58.66 | NB33: 38.82 | NC33: 17.75 | ND33: 17.73 | NE33: 16.56 | NF33: 15.49 | NG33: 15.6 | NI33: 15.6 | NJ33: 15.6 | NK33: 15.59 | NL33: 15.58 | NM33: 15.59 | NN33: 14.44 | NP33: 18.24 | NQ33: 23.21 | NR33: 23.26 | NS33: 23.31 | NT33: 23.31 | NU33: 23.31 | NW33: 32.13 | NX33: 40.95 | NY33: 40.95 | NZ33: 44.56 | OA33: 44.66 | OB33: 41.15 | OD33: 41.15 | OE33: 37.19 | OF33: 33.23 | OG33: 40.64 | OH33: 48.13 | OI33: 48.21 | OL33: 49.78 | OM33: 51.42 | ON33: 51.48 | OO33: 55.47 | OP33: 49.97 | OR33: 30.38 | OS33: 30.4 | OT33: 42.94 | OU33: 42.94 | OV33: 42.62 | OW33: 41.99 | OY33: 39.52 | OZ33: 39.62 | PA33: 38.85 | PB33: 37.2 | PC33: 41.88 | PD33: 39.29 | PF33: 38 | PG33: 38 | PH33: 36.57 | PI33: 34.12 | PJ33: 32.89 | PK33: 32.89 | PM33: 38.78 | PN33: 34.91 | PO33: 33.02 | PP33: 33.11 | PQ33: 33.11 | PR33: 33.11 | PT33: 33.11 | PY33: 44.87 | QA33: 41.58 | QB33: 25.17 | QC33: 25.17 | QD33: 24.87 | QE33: 23.97 | QF33: 21.96 | QH33: 26.95 | QI33: 59.98 | QJ33: 59.98 | QK33: 57.9 | QL33: 51.64 | QM33: 51.68 | QO33: 67.07 | QP33: 112.2 | QQ33: 110.21 | QR33: 105.83 | QS33: 105.85 | QT33: 93.69 | QV33: 57.03 | QW33: 57.06 | QX33: 60.03 | QY33: 73 | QZ33: 85.47 | RA33: 84.59 | RC33: 84.59 | RD33: 83.47 | RE33: 74.96 | RF33: 65.16 | RG33: 87.05 | RH33: 96.26 | RJ33: 81.82 | RK33: 88.54 | RL33: 92.61 | RM33: 92.47 | RN33: 92.47 | RO33: 88.12 | RQ33: 93.15 | RR33: 80.89 | RS33: 77.48 | RT33: 77.44 | RU33: 71.49 | RV33: 77.95 | RX33: 109.23 | RY33: 94.06 | RZ33: 48.46 | SA33: 57.19 | SB33: 82.65 | SC33: 70.88 | SE33: 33.17 | SF33: 23.85 | SG33: 26.07 | SH33: 23.38 | SI33: 15.24 | SJ33: 15.09 | SP33: 15.39 | SQ33: 15.14 | SS33: 14.41 | ST33: 15.11 | SU33: 18.47 | SV33: 23.22 | SW33: 23.21 | SX33: 23.18 | SZ33: 31.08 | TA33: 54.77 | TB33: 54.77 | TC33: 54.77 | TD33: 58.18 | TE33: 75.04 | TG33: 95.06 | TH33: 128.25 | TI33: 226.95 | TJ33: 228.05 | TK33: 188.29 | TL33: 69 | TN33: 67.01 | TO33: 57.64 | TP33: 47.52 | TQ33: 46.01 | TR33: 42.06 | TS33: 43.71 | TU33: 43.57 | TV33: 43.5 | TW33: 43.11 | TX33: 43.31 | TY33: 43.29 | TZ33: 41.84 | UB33: 32.36 | UC33: 16.67 | UD33: 15.57 | UE33: 18.25 | UF33: 27.31 | UG33: 29.33 | UI33: 29.03 | UJ33: 31.79 | UK33: 29.01 | UL33: 73.54 | UM33: 71.55 | UN33: 35.98 | UP33: 36.5 | UQ33: 38.47 | UR33: 41.74 | US33: 49.19 | UT33: 69.2 | UU33: 126.69 | UW33: 100.17 | UX33: 39.12 | UY33: 41.31 | UZ33: 52.36 | VA33: 55.87 | VB33: 32.83 | VD33: 32.65 | VE33: 32.1 | VF33: 32.1 | VG33: 33.15 | VH33: 36.26 | VI33: 36.38 | VK33: 36.5 | VL33: 33.19 | VM33: 23.46 | VN33: 24.23 | VO33: 23.62 | VP33: 20.59 | VR33: 20.57 | VS33: 31.85 | VT33: 67.01 | VU33: 82.05 | VV33: 118.49 | VW33: 121.05 | VY33: 117.22 | VZ33: 148.48 | WA33: 243.82 | WB33: 243.97 | WC33: 242.68 | WD33: 242.22 | WF33: 230.75 | WG33: 238.39 | WH33: 352.51 | WI33: 355.95 | WJ33: 362.35 | WK33: 359.99 | WM33: 359.75 | WN33: 365.12 | WO33: 378.86 | WQ33: 321.98 | WR33: 172.61 | WT33: 172.81 | WU33: 173.28 | WV33: 176.82 | WW33: 182.75 | WX33: 182.4 | WY33: 190.28 | XA33: 207.41 | XB33: 208.55 | XC33: 188.07 | XD33: 150.81 | XE33: 207.66 | XF33: 171.87 | XH33: 72.23 | XI33: 98.64 | XJ33: 176.75 | XK33: 173.92 | XL33: 164.68 | XM33: 135.94 | XO33: 135.06 | XP33: 135.74 | XQ33: 134.42 | XR33: 170 | XS33: 300.86 | XT33: 333.41 | XV33: 335.99 | XW33: 379.73 | XX33: 335.5 | XY33: 202 | XZ33: 200.23 | YA33: 241.61 | YC33: 366.26 | YD33: 364.93 | YE33: 373.75 | YF33: 440.86 | YG33: 526.67 | YH33: 526.62 | YJ33: 527.57 | YK33: 500.4 | YL33: 404.75 | YM33: 388.18 | YN33: 388.38 | YO33: 351.31 | YQ33: 231.37 | YR33: 217.45 | YS33: 244.64 | YT33: 247.28 | YU33: 254.64 | YV33: 235.11 | YX33: 181.35 | YY33: 181.02 | YZ33: 166.1 | ZA33: 123.29 | ZB33: 123.29 | ZC33: 121.71 | ZE33: 108.76 | ZF33: 84.11 | ZG33: 83.53 | ZH33: 82.26 | ZI33: 82.26 | ZJ33: 82.26 | ZL33: 82.26 | ZM33: 96.75 | ZN33: 140.23 | ZO33: 140.23 | ZP33: 140.23 | ZQ33: 140.23 | ZS33: 140.23 | ZT33: 140.23 | ZU33: 140.23 | ZV33: 140.23 | ZW33: 140.23 | ZX33: 105.17
A34: 2 Way PVC | E34: 90 | F34: 0 | G34: 42300 | I34: =F34 -> 0 | VV34: 1.23 | VW34: 3.68 | VZ34: 0.73 | WA34: 2.94 | WB34: 2.94 | WC34: 2.94 | WD34: 2.94 | WF34: 2.51 | WG34: 1.23 | WH34: 1.23 | WI34: 1.23 | WJ34: 0.92 | XF34: 0.21 | XH34: 0.85 | XI34: 0.85 | XJ34: 0.85 | XK34: 0.85 | XL34: 2.5 | XM34: 7.45 | XO34: 7.59 | XP34: 8.02 | XQ34: 6.87 | XR34: 3.41 | XS34: 4.07 | XT34: 5.34 | XV34: 3.21 | XW34: 3.21 | XX34: 3.21 | XY34: 2.64 | XZ34: 0.92 | YA34: 0.92 | YC34: 0.92 | YD34: 0.92 | YE34: 0.69
A35: 3-outlet Fire Hydrant (2 x 2.5 inch and 1 x 4 inch) | E35: 60 | F35: 1.8 | G35: 1043400 | I35: =F35 -> 1.8 | AN35: 0.6 | AO35: 0.6 | AP35: 0.6 | OM35: 0.07 | ON35: 0.13 | OO35: 0.13 | OP35: 0.13 | OR35: 0.1 | OS35: 0.1 | OT35: 0.1 | OU35: 0.1 | OV35: 0.1 | OW35: 0.1 | OY35: 0.1 | OZ35: 0.1 | PA35: 0.1 | PB35: 0.1 | PC35: 0.1 | PD35: 0.1 | PF35: 0.1 | PG35: 0.1 | PH35: 0.1 | PI35: 0.1 | PJ35: 0.1 | PK35: 0.1 | PM35: 0.1 | PN35: 0.1 | PO35: 0.1 | PP35: 0.1 | PQ35: 0.1 | PR35: 0.1 | PT35: 0.1 | PY35: 0.13 | QA35: 0.13 | QB35: 0.13 | QC35: 0.13 | QD35: 0.13 | QE35: 0.13 | QF35: 0.13 | QH35: 0.13 | QI35: 0.13 | QJ35: 0.13 | QK35: 0.13 | QL35: 0.13 | QM35: 0.13 | QO35: 0.13 | QP35: 0.13 | QQ35: 0.13 | QR35: 0.13 | QS35: 0.13 | QT35: 0.13 | QV35: 0.13 | QW35: 0.13 | QX35: 0.13 | QY35: 0.13 | QZ35: 0.13 | RA35: 0.13 | RC35: 0.13 | RD35: 0.13 | RE35: 0.13 | RF35: 0.13 | RG35: 0.13 | RH35: 0.13 | RJ35: 0.13 | RK35: 0.13 | RL35: 0.13 | RM35: 0.13 | RN35: 0.13 | RO35: 0.13 | RQ35: 0.13 | RR35: 0.13 | RS35: 0.13 | RT35: 0.23 | RU35: 0.5 | RV35: 0.5 | RX35: 0.5 | RY35: 0.56 | RZ35: 0.75 | SA35: 1.09 | SB35: 2.1 | SC35: 2.19 | SE35: 2.44 | SF35: 2.44 | SG35: 2.44 | SH35: 2.1 | SI35: 1.09 | SJ35: 1.09 | SP35: 1.09 | SQ35: 1.03 | SS35: 0.84 | ST35: 0.74 | SU35: 0.38 | SV35: 0.13 | SW35: 0.2 | SX35: 0.39 | SZ35: 0.39 | TA35: 0.39 | TB35: 0.39 | TC35: 0.39 | TD35: 0.36 | TE35: 0.26 | TG35: 0.26 | TH35: 0.42 | TI35: 0.9 | TJ35: 0.9 | TK35: 0.9 | TL35: 0.9 | TN35: 0.9 | TO35: 0.9 | TP35: 0.9 | TQ35: 0.9 | TR35: 0.9 | TS35: 0.9 | TU35: 0.9 | TV35: 0.75 | TW35: 0.29 | TX35: 0.29 | TY35: 0.29 | TZ35: 0.29 | UB35: 0.29 | UC35: 0.29 | UD35: 0.29 | UE35: 0.22 | UT35: 0.05 | UU35: 0.2 | UW35: 0.25 | UX35: 0.4 | UY35: 0.43 | UZ35: 0.51 | VA35: 0.44 | VB35: 0.23 | VD35: 0.23 | VE35: 0.23 | VF35: 0.18 | VG35: 0.03 | VH35: 0.03 | VI35: 0.03 | VK35: 0.03 | VL35: 0.03 | VM35: 0.03 | VN35: 0.02 | YT35: 0.19 | YU35: 0.75 | YV35: 0.75 | YX35: 0.75 | YY35: 0.75 | YZ35: 0.75 | ZA35: 0.75 | ZB35: 0.75 | ZC35: 0.56
A36: 300 mm diameter pipe | E36: 925 | F36: 0 | G36: 342250 | I36: =F36 -> 0 | HD36: 12.68 | HE36: 25.37 | HF36: 25.37 | HG36: 25.37 | HH36: 25.37 | HI36: 25.37 | HK36: 25.37 | HL36: 25.37 | HM36: 25.37 | HN36: 25.37 | HO36: 25.37 | HP36: 25.37 | HR36: 25.37 | HS36: 25.37 | HT36: 25.37 | HU36: 25.37 | HV36: 25.37 | HW36: 25.37 | HY36: 12.68 | IU36: 0.57 | IV36: 1.14 | IW36: 1.14 | IX36: 1.14 | IY36: 1.14 | JA36: 0.57 | JR36: 9.58 | JS36: 19.16 | JT36: 19.16 | JV36: 19.16 | JW36: 20.97 | JX36: 13.21 | JY36: 3.63 | JZ36: 3.63 | KA36: 1.81 | KT36: 6.5 | KU36: 13 | KV36: 13 | KX36: 13 | KY36: 6.5 | LJ36: 7.54 | LL36: 15.09 | LM36: 7.54 | LO36: 18.02 | LP36: 36.04 | LQ36: 36.04 | LS36: 36.04 | LT36: 36.04 | LU36: 36.04 | LV36: 18.02 | MY36: 10.13 | MZ36: 20.25 | NB36: 10.13 | NW36: 1.69 | NX36: 3.38 | NY36: 3.38 | NZ36: 3.38 | OA36: 1.69
A37: 4 Way PVC | E37: 102 | F37: 0 | G37: 95880 | I37: =F37 -> 0 | XR37: 0.85 | XS37: 3.4 | XT37: 3.4 | XV37: 6.12 | XW37: 14.28 | XX37: 14.28 | XY37: 14.28 | XZ37: 14.28 | YA37: 12.41 | YC37: 6.8 | YD37: 6.8 | YE37: 5.1
A38: 400 mm diameter pipe | E38: 1231 | F38: 0 | G38: 689360 | I38: =F38 -> 0 | HD38: 14.86 | HE38: 29.73 | HF38: 29.73 | HG38: 29.73 | HH38: 29.73 | HI38: 29.73 | HK38: 29.73 | HL38: 29.73 | HM38: 29.73 | HN38: 29.73 | HO38: 29.73 | HP38: 29.73 | HR38: 29.73 | HS38: 29.73 | HT38: 29.73 | HU38: 29.73 | HV38: 29.73 | HW38: 29.73 | HY38: 14.86 | IU38: 0.67 | IV38: 1.34 | IW38: 1.34 | IX38: 1.34 | IY38: 1.34 | JA38: 0.67 | JR38: 12.29 | JS38: 24.58 | JT38: 24.58 | JV38: 24.58 | JW38: 26.9 | JX38: 16.94 | JY38: 4.65 | JZ38: 4.65 | KA38: 2.33 | KT38: 11.8 | KU38: 23.6 | KV38: 23.6 | KX38: 23.6 | KY38: 11.8 | LJ38: 12.63 | LL38: 25.26 | LM38: 12.63 | LO38: 30.17 | LP38: 60.33 | LQ38: 60.33 | LS38: 60.33 | LT38: 60.33 | LU38: 60.33 | LV38: 30.17 | MY38: 7.65 | MZ38: 15.3 | NB38: 7.65 | NW38: 1.27 | NX38: 2.55 | NY38: 2.55 | NZ38: 2.55 | OA38: 1.27
A39: 500 mm diameter pipe | E39: 625 | F39: 0 | G39: 468750 | I39: =F39 -> 0 | HD39: 2.98 | HE39: 5.96 | HF39: 5.96 | HG39: 5.96 | HH39: 5.96 | HI39: 5.96 | HK39: 5.96 | HL39: 5.96 | HM39: 5.96 | HN39: 5.96 | HO39: 5.96 | HP39: 5.96 | HR39: 5.96 | HS39: 5.96 | HT39: 5.96 | HU39: 5.96 | HV39: 5.96 | HW39: 5.96 | HY39: 2.98 | IU39: 0.13 | IV39: 0.27 | IW39: 0.27 | IX39: 0.27 | IY39: 0.27 | JA39: 0.13 | JR39: 15.53 | JS39: 31.05 | JT39: 31.05 | JV39: 31.05 | JW39: 34 | JX39: 21.41 | JY39: 5.88 | JZ39: 5.88 | KA39: 2.94 | KT39: 3.05 | KU39: 6.1 | KV39: 6.1 | KX39: 6.1 | KY39: 3.05 | LJ39: 9.04 | LL39: 18.09 | LM39: 9.04 | LO39: 21.6 | LP39: 43.2 | LQ39: 43.2 | LS39: 43.2 | LT39: 43.2 | LU39: 43.2 | LV39: 21.6 | MY39: 3.34 | MZ39: 6.68 | NB39: 3.34 | NW39: 0.56 | NX39: 1.11 | NY39: 1.11 | NZ39: 1.11 | OA39: 0.56
A40: Acess Entrace Ramp | E40: 2 | F40: 0 | G40: 70500 | I40: =F40 -> 0 | HU40: 0.2 | HV40: 0.4 | HW40: 0.4 | HY40: 0.4 | HZ40: 0.4 | IA40: 0.2
A41: Air V CH On pipes Dia. 160 mm | E41: 3 | F41: 0 | G41: 28680 | I41: =F41 -> 0 | QT41: 0.02 | QV41: 0.08 | QW41: 0.08 | QX41: 0.08 | QY41: 0.09 | QZ41: 0.15 | RA41: 0.15 | RC41: 0.15 | RD41: 0.15 | RE41: 0.15 | RF41: 0.15 | RG41: 0.15 | RH41: 0.14 | RJ41: 0.1 | RK41: 0.1 | RL41: 0.18 | RM41: 0.4 | RN41: 0.4 | RO41: 0.3
A42: Air V CH On pipes Dia. 250 mm | E42: 3 | F42: 0 | G42: 28680 | I42: =F42 -> 0 | RS42: 0.01 | RT42: 0.03 | RU42: 0.03 | RV42: 0.05 | RX42: 0.1 | RY42: 0.1 | RZ42: 0.1 | SA42: 0.09 | SB42: 0.05 | SC42: 0.1 | SE42: 0.25 | SF42: 0.23 | SG42: 0.15 | SH42: 0.16 | SI42: 0.2 | SJ42: 0.18 | SP42: 0.13 | SQ42: 0.12 | SS42: 0.11 | ST42: 0.23 | SU42: 0.23 | SV42: 0.2 | SW42: 0.15
A43: Air V CH On pipes Dia. 315 mm | E43: 1 | F43: 0 | G43: 9560 | I43: =F43 -> 0 | TZ43: 0.01 | UB43: 0.02 | UC43: 0.02 | UD43: 0.02 | UE43: 0.02 | UF43: 0.03 | UG43: 0.07 | UI43: 0.07 | UJ43: 0.07 | UK43: 0.07 | UL43: 0.07 | UM43: 0.06 | UN43: 0.03 | UP43: 0.03 | UQ43: 0.06 | UR43: 0.13 | US43: 0.13 | UT43: 0.1
A44: Air valve chamber; on 160 mm dia pipeline Depth 1.5- 3 m | E44: 7 | F44: 0 | G44: 66990 | I44: =F44 -> 0 | UC44: 0.03 | UD44: 0.1 | UE44: 0.1 | UF44: 0.11 | UG44: 0.15 | UI44: 0.15 | UJ44: 0.15 | UK44: 0.15 | UL44: 0.15 | UM44: 0.15 | UN44: 0.15 | UP44: 0.13 | UQ44: 0.08 | UR44: 0.08 | US44: 0.08 | UT44: 0.13 | UU44: 0.3 | UW44: 0.3 | UX44: 0.3 | UY44: 0.22 | VI44: 0.01 | VK44: 0.05 | VL44: 0.05 | VM44: 0.05 | VN44: 0.06 | VO44: 0.08 | VP44: 0.08 | VR44: 0.08 | VS44: 0.08 | VT44: 0.08 | VU44: 0.07 | VV44: 0.07 | VW44: 0.07 | VY44: 0.07 | VZ44: 0.07 | WA44: 0.07 | WB44: 0.07 | WC44: 0.07 | WD44: 0.07 | WF44: 0.07 | WG44: 0.09 | WH44: 0.16 | WI44: 0.16 | WJ44: 0.17 | WK44: 0.2 | WM44: 0.2 | WN44: 0.17 | WO44: 0.07 | WQ44: 0.07 | WR44: 0.07 | WT44: 0.07 | WU44: 0.07 | WV44: 0.07 | WW44: 0.07 | WX44: 0.07 | WY44: 0.06 | XA44: 0.02 | XB44: 0.02 | XC44: 0.02 | XD44: 0.02 | XE44: 0.02 | XF44: 0.02 | XH44: 0.02 | XI44: 0.02 | XJ44: 0.02 | XK44: 0.06 | XL44: 0.16 | XM44: 0.16 | XO44: 0.16 | XP44: 0.16 | XQ44: 0.12
A45: Chain link fence | E45: 650 | F45: 0 | G45: 113750 | I45: =F45 -> 0 | YD45: 4.88 | YE45: 19.5 | YF45: 19.5 | YG45: 19.5 | YH45: 19.5 | YJ45: 20.43 | YK45: 23.21 | YL45: 23.21 | YM45: 23.21 | YN45: 23.21 | YO45: 23.21 | YQ45: 23.21 | YR45: 31.34 | YS45: 55.71 | YT45: 55.71 | YU45: 55.71 | YV45: 55.71 | YX45: 55.71 | YY45: 55.71 | YZ45: 41.79
A46: Conc. lining, incl PC & Expansion Joints | E46: 3000 | F46: 1043.41 | G46: 4935000 | I46: =F46 -> 1043.41 | XD46: 27.69 | XE46: 110.77 | XF46: 83.07 | XI46: 27.69 | XJ46: 110.77 | XK46: 110.77 | XL46: 99.69 | XM46: 66.46 | XO46: 66.46 | XP46: 66.46 | XQ46: 66.46 | XR46: 105.23 | XS46: 221.53 | XT46: 221.53 | XV46: 221.53 | XW46: 221.53 | XX46: 177.22 | XY46: 44.31 | XZ46: 44.31 | YA46: 68.83 | YC46: 142.39 | YD46: 131.32 | YE46: 98.09 | YF46: 98.09 | YG46: 98.09 | YH46: 98.09 | YJ46: 98.09 | YK46: 73.56
A47: Double Catch basin | E47: 20 | F47: 2.43 | G47: 483000 | I47: =F47 -> 2.43 | U47: 0.1 | W47: 0.1 | X47: 0.1 | Y47: 0.1 | Z47: 0.1 | AA47: 0.1 | BX47: 0.02 | BY47: 0.02 | CA47: 0.02 | CB47: 0.02 | CC47: 0.02 | CD47: 0.02 | CJ47: 0.02 | CK47: 0.02 | CL47: 0.02 | CM47: 0.02 | CO47: 0.02 | CP47: 0.02 | CQ47: 0.02 | CR47: 0.02 | CS47: 0.02 | CT47: 0.02 | CV47: 0.02 | CW47: 0.02 | CX47: 0.02 | CY47: 0.02 | CZ47: 0.02 | DA47: 0.02 | DC47: 0.02 | DD47: 0.02 | DE47: 0.02 | DF47: 0.02 | DG47: 0.02 | DH47: 0.02 | DJ47: 0.02 | DK47: 0.02 | DL47: 0.02 | DM47: 0.02 | DN47: 0.02 | DO47: 0.02 | DQ47: 0.02 | DR47: 0.02 | DS47: 0.02 | DT47: 0.02 | DU47: 0.02 | DV47: 0.02 | DX47: 0.02 | DY47: 0.02 | DZ47: 0.02 | EA47: 0.02 | EB47: 0.02 | EC47: 0.02 | EE47: 0.02 | EF47: 0.02 | EG47: 0.02 | EH47: 0.02 | EI47: 0.02 | EJ47: 0.02 | EL47: 0.02 | EM47: 0.02 | EN47: 0.02 | EO47: 0.02 | EP47: 0.02 | EQ47: 0.02 | ES47: 0.02 | ET47: 0.02 | EZ47: 0.02 | FA47: 0.02 | FB47: 0.02 | FC47: 0.02 | FD47: 0.02 | FE47: 0.02 | FG47: 0.02 | FH47: 0.02 | FI47: 0.02 | FJ47: 0.02 | FK47: 0.02 | FL47: 0.02 | FN47: 0.02 | FO47: 0.02 | FP47: 0.02 | FQ47: 0.02 | FR47: 0.02 | FS47: 0.02 | FU47: 0.02 | FV47: 0.02 | FW47: 0.02 | FX47: 0.02 | FY47: 0.02 | FZ47: 0.02 | GB47: 0.02 | GC47: 0.02 | GD47: 0.02 | GE47: 0.02 | GF47: 0.02 | GG47: 0.02 | GI47: 0.02 | GJ47: 0.02 | GK47: 0.02 | GL47: 0.02 | GM47: 0.02 | GN47: 0.02 | GP47: 0.02 | GQ47: 0.02 | GR47: 0.02 | GS47: 0.02 | GT47: 0.02 | GU47: 0.02 | GW47: 0.02 | GX47: 0.02 | GY47: 0.02 | GZ47: 0.02 | HA47: 0.02 | HB47: 0.02 | HD47: 0.02 | HE47: 0.02 | HF47: 0.02 | HG47: 0.02 | HH47: 0.02 | HI47: 0.02 | HK47: 0.02 | HL47: 0.02 | HM47: 0.02 | HN47: 0.02 | HO47: 0.02 | HP47: 0.02 | HR47: 0.02 | HS47: 0.02 | HT47: 0.02 | HU47: 0.02 | HV47: 0.02 | HW47: 0.02 | HY47: 0.02 | HZ47: 0.02 | IA47: 0.02 | IB47: 0.03 | IC47: 0.04 | ID47: 0.04 | IF47: 0.04 | IG47: 0.04 | IH47: 0.04 | II47: 0.04 | IJ47: 0.05 | IK47: 0.05 | IM47: 0.05 | IN47: 0.05 | IP47: 0.08 | IQ47: 0.1 | IR47: 0.1 | IT47: 0.1 | IU47: 0.06 | IV47: 0.02 | IW47: 0.02 | IX47: 0.02 | IY47: 0.02 | JA47: 0.03 | JB47: 0.03 | JC47: 0.03 | JD47: 0.03 | JE47: 0.03 | JF47: 0.08 | JH47: 0.13 | JI47: 0.13 | JJ47: 0.13 | JK47: 0.13 | JL47: 0.13 | JM47: 0.16 | JO47: 0.19 | JP47: 0.19 | JQ47: 0.19 | JR47: 0.31 | JS47: 0.44 | JT47: 0.44 | JV47: 0.44 | JW47: 0.23 | JX47: 0.02 | JY47: 0.02 | JZ47: 0.02 | KA47: 0.04 | KC47: 0.06 | KD47: 0.06 | KE47: 0.06 | KF47: 0.06 | KG47: 0.06 | KH47: 0.06 | KJ47: 0.06 | KK47: 0.06 | KL47: 0.04 | KM47: 0.02 | KN47: 0.02 | KO47: 0.02 | KQ47: 0.02 | KR47: 0.02 | KS47: 0.02 | KT47: 0.02 | KU47: 0.02 | KV47: 0.02 | KX47: 0.01 | LB47: 0.27 | LC47: 0.54 | LE47: 0.54 | LF47: 0.67 | LG47: 0.8 | LH47: 1.41 | LI47: 2.01 | LJ47: 1 | LM47: 0.1 | LN47: 0.2 | LO47: 0.2 | LP47: 0.2 | LQ47: 0.1 | NF47: 0.02 | NG47: 0.04 | NI47: 0.04 | NJ47: 0.04 | NK47: 0.04 | NL47: 0.04 | NM47: 0.06 | NN47: 0.07 | NP47: 0.07 | NQ47: 0.07 | NR47: 0.12 | NS47: 0.17 | NT47: 0.17 | NU47: 0.17 | NW47: 0.08 | OA47: 0.01 | OB47: 0.02 | OD47: 0.02 | OE47: 0.02 | OF47: 0.02 | OG47: 0.02 | OH47: 0.02 | OI47: 0.01 | YA47: 0.06 | YC47: 0.25 | YD47: 0.25 | YE47: 0.25 | YF47: 0.25 | YG47: 0.25 | YH47: 0.25 | YJ47: 0.25 | YK47: 0.19
A48: Double swing main entrance gate | E48: 2 | F48: 0 | G48: 117500 | I48: =F48 -> 0 | YZ48: 0.17 | ZA48: 0.67 | ZB48: 0.67 | ZC48: 0.5
A49: Drawpit incl. cover | E49: 23 | F49: 0 | G49: 135700 | I49: =F49 -> 0 | VS49: 0.05 | VT49: 0.2 | VU49: 0.2 | VV49: 0.24 | VW49: 0.38 | VY49: 0.38 | VZ49: 0.38 | WA49: 0.38 | WB49: 0.38 | WC49: 0.38 | WD49: 0.38 | WF49: 0.39 | WG49: 0.45 | WH49: 0.45 | WI49: 0.45 | WJ49: 0.42 | WK49: 0.27 | WM49: 0.12 | WN49: 0.2 | WO49: 0.45 | WQ49: 0.42 | WR49: 0.3 | WT49: 0.2 | WU49: 0.2 | WV49: 0.17 | WW49: 0.07 | WX49: 0.07 | WY49: 0.05 | XB49: 0.28 | XC49: 0.83 | XF49: 0.46 | XH49: 1.93 | XI49: 2.13 | XJ49: 1.65 | XK49: 1.1 | XL49: 1.1 | XM49: 0.92 | XO49: 0.45 | XP49: 0.7 | XQ49: 0.61 | XR49: 0.33 | XS49: 0.33 | XT49: 0.33 | XV49: 0.32 | XW49: 0.3 | XX49: 0.3 | XY49: 0.3 | XZ49: 0.25 | YA49: 0.08 | YC49: 0.08 | YD49: 0.08 | YE49: 0.08 | YF49: 0.06
A50: Earthing | E50: 13 | F50: 0 | G50: 152750 | I50: =F50 -> 0 | YN50: 0.33 | YO50: 0.98 | YR50: 0.76 | YS50: 3.03 | YT50: 3.03 | YU50: 2.49 | YV50: 0.87 | YX50: 0.87 | YY50: 0.65
A51: Excavation | E51: 37125 | F51: 36754.04 | G51: 2227500 | I51: =F51 -> 36754.04 | AW51: 189.2 | AY51: 189.2 | AZ51: 189.2 | BA51: 141.9 | BB51: 141.9 | BC51: 141.9 | BD51: 141.9 | BF51: 141.9 | BG51: 141.9 | BH51: 141.9 | BI51: 141.9 | BJ51: 141.9 | BK51: 141.9 | BM51: 141.9 | BN51: 141.9 | BO51: 141.9 | BP51: 141.9 | BQ51: 141.9 | BR51: 141.9 | BT51: 141.9 | BU51: 141.9 | BV51: 141.9 | BW51: 141.9 | BX51: 120.97 | BY51: 120.97 | CA51: 120.97 | CB51: 120.97 | CC51: 120.97 | CD51: 120.97 | CJ51: 161.29 | CK51: 161.29 | CL51: 161.29 | CM51: 161.29 | CO51: 161.29 | CP51: 161.29 | CQ51: 161.29 | CR51: 161.29 | CS51: 161.29 | CT51: 161.29 | CV51: 161.29 | CW51: 161.29 | CX51: 161.29 | CY51: 168.11 | CZ51: 174.92 | DA51: 174.92 | DC51: 174.92 | DD51: 174.92 | DE51: 174.92 | DF51: 174.92 | DG51: 174.92 | DH51: 174.92 | DJ51: 174.92 | DK51: 174.92 | DL51: 174.92 | DM51: 174.92 | DN51: 174.92 | DO51: 174.92 | DQ51: 174.92 | DR51: 174.92 | DS51: 174.92 | DT51: 162.89 | DU51: 150.86 | DV51: 150.86 | DX51: 150.86 | DY51: 150.86 | DZ51: 150.86 | EA51: 150.86 | EB51: 150.86 | EC51: 150.86 | EE51: 150.86 | EF51: 150.86 | EG51: 150.86 | EH51: 150.86 | EI51: 150.86 | EJ51: 150.86 | EL51: 150.86 | EM51: 150.86 | EN51: 150.86 | EO51: 150.86 | EP51: 150.86 | EQ51: 691.69 | ES51: 1232.52 | ET51: 1232.52 | EZ51: 1232.52 | FA51: 1232.52 | FB51: 1232.52 | FC51: 1232.52 | FD51: 1232.52 | FE51: 1232.52 | FG51: 1232.52 | FH51: 1232.52 | FI51: 1232.52 | FJ51: 1232.52 | FK51: 1232.52 | FL51: 1232.52 | FN51: 1232.52 | FO51: 1232.52 | FP51: 1232.52 | FQ51: 1232.52 | FR51: 1232.52 | FS51: 616.26
A52: Filling | E52: 16500 | F52: 0 | G52: 825000 | I52: =F52 -> 0 | FS52: 750 | FU52: 1500 | FV52: 1500 | FW52: 1500 | FX52: 1500 | FY52: 1500 | FZ52: 1500 | GB52: 1500 | GC52: 1500 | GD52: 1500 | GE52: 1500 | GF52: 750
A53: Filling with imported Material | E53: 1856 | F53: 0 | G53: 129920 | I53: =F53 -> 0 | IA53: 185.6 | IB53: 371.2 | IC53: 371.2 | ID53: 371.2 | IF53: 371.2 | IG53: 185.6
A54: Flow meter chamber on 630 mm dia pipeline Depth 0- 1.5 m | E54: 1 | F54: 0.03 | G54: 9570 | I54: =F54 -> 0.03 | AK54: 0.01 | AL54: 0.01 | AM54: 0.01 | XB54: 0.01 | XC54: 0.02 | XD54: 0.02 | XE54: 0.02 | XF54: 0.02 | XH54: 0.02 | XI54: 0.02 | XJ54: 0.02 | XK54: 0.02 | XL54: 0.02 | XM54: 0.02 | XO54: 0.03 | XP54: 0.03 | XQ54: 0.03 | XR54: 0.03 | XS54: 0.02 | XT54: 0.02 | XV54: 0.02 | XW54: 0.04 | XX54: 0.12 | XY54: 0.12 | XZ54: 0.12 | YA54: 0.09 | ZC54: 0 | ZE54: 0.01 | ZF54: 0.01 | ZG54: 0.01 | ZH54: 0.01 | ZI54: 0.01 | ZJ54: 0.01 | ZL54: 0.01 | ZM54: 0.01
A55: LED Lumin 110 W | E55: 193 | F55: 5.79 | G55: 675500 | I55: =F55 -> 5.79 | AB55: 0.97 | AD55: 0.97 | AE55: 0.97 | AF55: 0.97 | AG55: 0.97 | AH55: 0.97 | TG55: 0.14 | TH55: 0.55 | TI55: 0.55 | TJ55: 0.55 | TK55: 0.55 | TL55: 0.55 | TN55: 0.55 | TO55: 0.55 | TP55: 0.55 | TQ55: 0.55 | TR55: 0.55 | TS55: 0.55 | TU55: 0.55 | TV55: 0.55 | TW55: 0.55 | TX55: 0.55 | TY55: 0.55 | TZ55: 0.55 | UB55: 0.55 | UC55: 0.55 | UD55: 0.55 | UE55: 0.55 | UF55: 0.55 | UG55: 0.55 | UI55: 0.55 | UJ55: 0.55 | UK55: 0.55 | UL55: 0.55 | UM55: 0.55 | UN55: 0.55 | UP55: 0.55 | UQ55: 0.55 | UR55: 0.55 | US55: 0.55 | UT55: 0.55 | UU55: 0.55 | UW55: 0.55 | UX55: 0.55 | UY55: 0.55 | UZ55: 0.55 | VA55: 0.55 | VB55: 0.55 | VD55: 0.55 | VE55: 0.55 | VF55: 0.55 | VG55: 0.55 | VH55: 0.55 | VI55: 0.55 | VK55: 0.55 | VL55: 0.55 | VM55: 0.55 | VN55: 0.55 | VO55: 0.55 | VP55: 0.55 | VR55: 0.55 | VS55: 0.55 | VT55: 0.55 | VU55: 0.55 | VV55: 0.55 | VW55: 0.55 | VY55: 0.55 | VZ55: 0.55 | WA55: 0.55 | WB55: 0.55 | WC55: 0.55 | WD55: 0.55 | WF55: 0.55 | WG55: 0.55 | WH55: 0.55 | WI55: 0.55 | WJ55: 0.41 | WX55: 1.27 | WY55: 5.06 | XA55: 6.07 | XB55: 9.08 | XC55: 9.08 | XD55: 9.08 | XE55: 8.08 | XF55: 5.9 | XH55: 8.41 | XI55: 7.15 | XJ55: 2.51 | YD55: 1.82 | YE55: 7.27 | YF55: 7.27 | YG55: 7.27 | YH55: 7.27 | YJ55: 7.27 | YK55: 7.27 | YL55: 5.45 | YV55: 0.56 | YX55: 2.23 | YY55: 2.23 | YZ55: 1.68 | ZM55: 0.48 | ZN55: 1.93 | ZO55: 1.93 | ZP55: 1.93 | ZQ55: 1.93 | ZS55: 1.93 | ZT55: 1.93 | ZU55: 1.93 | ZV55: 1.93 | ZW55: 1.93 | ZX55: 1.45
A56: Outfall 1000 | E56: 1 | F56: 0 | G56: 18800 | I56: =F56 -> 0 | GM56: 0.03 | GN56: 0.06 | GP56: 0.06 | GQ56: 0.06 | GR56: 0.06 | GS56: 0.18 | GT56: 0.3 | GU56: 0.16 | GW56: 0.02 | GX56: 0.02 | GY56: 0.02 | GZ56: 0.02 | HA56: 0.01
A57: Outfall 1400 | E57: 1 | F57: 0 | G57: 23500 | I57: =F57 -> 0 | GG57: 0.03 | GI57: 0.06 | GJ57: 0.06 | GK57: 0.06 | GL57: 0.06 | GM57: 0.18 | GN57: 0.3 | GP57: 0.16 | GQ57: 0.02 | GR57: 0.02 | GS57: 0.02 | GT57: 0.02 | GU57: 0.01
A58: Pipe encasement dia 200mm | E58: 215 | F58: 0 | G58: 202100 | I58: =F58 -> 0 | LN58: 1.89 | LO58: 3.77 | LP58: 3.77 | LQ58: 3.77 | LS58: 3.77 | LT58: 3.77 | LU58: 8.17 | LV58: 12.57 | LW58: 12.57 | LX58: 7.79 | LZ58: 3.02 | MA58: 3.02 | MB58: 3.02 | MC58: 3.02 | MD58: 5 | ME58: 6.98 | MG58: 6.98 | MH58: 6.98 | MI58: 6.98 | MJ58: 6.98 | MK58: 9.31 | ML58: 11.63 | MN58: 11.63 | MO58: 11.63 | MP58: 11.63 | MQ58: 11.63 | MR58: 8.14 | MS58: 4.65 | MU58: 4.65 | MV58: 4.65 | MW58: 4.65 | MX58: 4.65 | MY58: 2.33
A59: Pipe encasement dia 250mm | E59: 215 | F59: 0 | G59: 202100 | I59: =F59 -> 0 | KL59: 0.64 | KM59: 1.29 | KN59: 1.29 | KO59: 1.29 | KQ59: 1.29 | KR59: 1.29 | KS59: 1.29 | KT59: 1.29 | KU59: 1.29 | KV59: 2.02 | KX59: 2.76 | KY59: 2.76 | KZ59: 2.76 | LA59: 2.76 | LB59: 2.76 | LC59: 2.76 | LE59: 1.86 | LF59: 0.97 | LG59: 0.97 | LH59: 0.97 | LI59: 0.97 | LJ59: 0.97 | LL59: 0.97 | LM59: 0.97 | LN59: 0.48 | LU59: 3.61 | LV59: 7.21 | LW59: 7.21 | LX59: 7.21 | LZ59: 7.21 | MA59: 7.21 | MB59: 9.62 | MC59: 12.02 | MD59: 12.02 | ME59: 12.02 | MG59: 12.02 | MH59: 12.02 | MI59: 8.42 | MJ59: 4.81 | MK59: 4.81 | ML59: 4.81 | MN59: 4.81 | MO59: 4.81 | MP59: 2.4 | OP59: 0.97 | OR59: 1.45 | OS59: 1.45 | OT59: 1.45 | OU59: 1.45 | OV59: 1.45 | OW59: 1.45 | OY59: 6.03 | OZ59: 6.03 | PA59: 4.42 | PB59: 1.21 | PC59: 1.21 | PD59: 1.21 | PF59: 1.21 | PG59: 1.21
A60: Pipe encasement dia 315mm | E60: 215 | F60: 0 | G60: 202100 | I60: =F60 -> 0 | LV60: 1.08 | LW60: 2.17 | LX60: 2.17 | LZ60: 2.17 | MA60: 2.17 | MB60: 2.17 | MC60: 4.7 | MD60: 7.22 | ME60: 7.22 | MG60: 4.48 | MH60: 1.73 | MI60: 1.73 | MJ60: 1.73 | MK60: 1.73 | ML60: 0.87 | OE60: 3.22 | OF60: 6.44 | OG60: 6.44 | OH60: 6.44 | OI60: 6.44 | OL60: 6.44 | OM60: 6.44 | ON60: 6.44 | OO60: 10.37 | OP60: 14.31 | OR60: 10.73 | OS60: 10.73 | OT60: 10.73 | OU60: 10.73 | OV60: 10.73 | OW60: 10.73 | OY60: 3.68 | OZ60: 3.68 | PA60: 3.68 | PB60: 3.68 | PC60: 3.68 | PD60: 3.68 | PF60: 3.68 | PG60: 3.68 | PH60: 3.68 | PI60: 1.23
A61: Pot Air V on pipes with dia(160) mm. | E61: 4 | F61: 0.12 | G61: 11280 | I61: =F61 -> 0.12 | AF61: 0.02 | AG61: 0.02 | AH61: 0.02 | AK61: 0.02 | AL61: 0.02 | AM61: 0.02 | AN61: 0.02 | AO61: 0.02 | NN61: 0 | NP61: 0.01 | NQ61: 0.01 | NR61: 0.01 | NS61: 0.01 | NT61: 0.01 | NU61: 0.01 | NW61: 0.01 | NX61: 0.01 | NY61: 0.01 | NZ61: 0.01 | OA61: 0.01 | OB61: 0.01 | OD61: 0.01 | OE61: 0.01 | OF61: 0.01 | OG61: 0.01 | OH61: 0.01 | OI61: 0.01 | OL61: 0.01 | OM61: 0.01 | ON61: 0.01 | OO61: 0.01 | OP61: 0.01 | OR61: 0.01 | OS61: 0.01 | OT61: 0.01 | OU61: 0.01 | OV61: 0.01 | OW61: 0.01 | OY61: 0.01 | OZ61: 0.01 | PA61: 0.01 | PB61: 0.01 | PC61: 0.01 | PD61: 0.01 | PF61: 0.01 | PG61: 0.01 | PH61: 0.01 | PI61: 0.01 | PJ61: 0.01 | PK61: 0.01 | PM61: 0.01 | PN61: 0.01 | PO61: 0.01 | PP61: 0.01 | PQ61: 0.01 | PR61: 0.01 | PT61: 0.01 | PY61: 0.01 | QA61: 0.01 | QB61: 0.01 | QC61: 0.01 | QD61: 0.01 | QE61: 0.01 | QF61: 0.01 | QH61: 0.01 | QI61: 0.01 | QJ61: 0.01 | QK61: 0.01 | QL61: 0.01 | QM61: 0.01 | QO61: 0.01 | QP61: 0.01 | QQ61: 0.01 | QR61: 0.01 | QS61: 0.01 | QT61: 0.02 | QV61: 0.07 | QW61: 0.07 | QX61: 0.07 | QY61: 0.09 | QZ61: 0.14 | RA61: 0.14 | RC61: 0.14 | RD61: 0.14 | RE61: 0.14 | RF61: 0.14 | RG61: 0.14 | RH61: 0.13 | RJ61: 0.09 | RK61: 0.09 | RL61: 0.16 | RM61: 0.37 | RN61: 0.37 | RO61: 0.28 | RQ61: 0.01 | RR61: 0.01 | RS61: 0.01 | RT61: 0.01 | RU61: 0.01 | RV61: 0.01 | RX61: 0.01 | RY61: 0.01 | RZ61: 0.01 | SA61: 0.01 | SB61: 0.01 | SC61: 0.01 | SE61: 0.01 | SF61: 0.01 | SG61: 0.01 | SH61: 0.01 | SI61: 0.01 | SJ61: 0.01 | SP61: 0.01 | SQ61: 0.01 | SS61: 0.01 | YT61: 0.01 | YU61: 0.05 | YV61: 0.05 | YX61: 0.05 | YY61: 0.05 | YZ61: 0.05 | ZA61: 0.05 | ZB61: 0.05 | ZC61: 0.04
A62: Pot Air V on pipes with dia(250) mm. | E62: 2 | F62: 0.06 | G62: 5640 | I62: =F62 -> 0.06 | AF62: 0.01 | AG62: 0.01 | AH62: 0.01 | AK62: 0.01 | AL62: 0.01 | AM62: 0.01 | AN62: 0.01 | AO62: 0.01 | NN62: 0 | NP62: 0 | NQ62: 0 | NR62: 0 | NS62: 0 | NT62: 0 | NU62: 0 | NW62: 0 | NX62: 0 | NY62: 0 | NZ62: 0 | OA62: 0 | OB62: 0 | OD62: 0 | OE62: 0 | OF62: 0 | OG62: 0 | OH62: 0 | OI62: 0 | OL62: 0 | OM62: 0 | ON62: 0 | OO62: 0 | OP62: 0 | OR62: 0 | OS62: 0 | OT62: 0 | OU62: 0 | OV62: 0 | OW62: 0 | OY62: 0 | OZ62: 0 | PA62: 0 | PB62: 0 | PC62: 0 | PD62: 0 | PF62: 0 | PG62: 0 | PH62: 0 | PI62: 0 | PJ62: 0 | PK62: 0 | PM62: 0 | PN62: 0 | PO62: 0 | PP62: 0 | PQ62: 0 | PR62: 0 | PT62: 0 | PY62: 0 | QA62: 0 | QB62: 0 | QC62: 0 | QD62: 0 | QE62: 0 | QF62: 0 | QH62: 0 | QI62: 0 | QJ62: 0 | QK62: 0 | QL62: 0 | QM62: 0 | QO62: 0 | QP62: 0 | QQ62: 0 | QR62: 0 | QS62: 0 | QT62: 0 | QV62: 0 | QW62: 0 | QX62: 0 | QY62: 0 | QZ62: 0 | RA62: 0 | RC62: 0 | RD62: 0 | RE62: 0 | RF62: 0 | RG62: 0 | RH62: 0 | RJ62: 0 | RK62: 0 | RL62: 0 | RM62: 0 | RN62: 0 | RO62: 0 | RQ62: 0 | RR62: 0 | RS62: 0.01 | RT62: 0.02 | RU62: 0.02 | RV62: 0.03 | RX62: 0.05 | RY62: 0.05 | RZ62: 0.05 | SA62: 0.04 | SB62: 0.03 | SC62: 0.05 | SE62: 0.12 | SF62: 0.1 | SG62: 0.07 | SH62: 0.08 | SI62: 0.09 | SJ62: 0.09 | SP62: 0.06 | SQ62: 0.06 | SS62: 0.05 | ST62: 0.1 | SU62: 0.1 | SV62: 0.09 | SW62: 0.07 | YT62: 0.01 | YU62: 0.03 | YV62: 0.03 | YX62: 0.03 | YY62: 0.03 | YZ62: 0.03 | ZA62: 0.03 | ZB62: 0.03 | ZC62: 0.02
A63: Pot Air V on pipes with dia(315) mm. | E63: 1 | F63: 0.03 | G63: 2820 | I63: =F63 -> 0.03 | AF63: 0 | AG63: 0 | AH63: 0 | AK63: 0 | AL63: 0 | AM63: 0 | AN63: 0 | AO63: 0 | NN63: 0 | NP63: 0 | NQ63: 0 | NR63: 0 | NS63: 0 | NT63: 0 | NU63: 0 | NW63: 0 | NX63: 0 | NY63: 0 | NZ63: 0 | OA63: 0 | OB63: 0 | OD63: 0 | OE63: 0 | OF63: 0 | OG63: 0 | OH63: 0 | OI63: 0 | OL63: 0 | OM63: 0 | ON63: 0 | OO63: 0 | OP63: 0 | OR63: 0 | OS63: 0 | OT63: 0 | OU63: 0 | OV63: 0 | OW63: 0 | OY63: 0 | OZ63: 0 | PA63: 0 | PB63: 0 | PC63: 0 | PD63: 0 | PF63: 0 | PG63: 0 | PH63: 0 | PI63: 0 | PJ63: 0 | PK63: 0 | PM63: 0 | PN63: 0 | PO63: 0 | PP63: 0 | PQ63: 0 | PR63: 0 | PT63: 0 | PY63: 0 | QA63: 0 | QB63: 0 | QC63: 0 | QD63: 0 | QE63: 0 | QF63: 0 | QH63: 0 | QI63: 0 | QJ63: 0 | QK63: 0 | QL63: 0 | QM63: 0 | QO63: 0 | QP63: 0 | QQ63: 0 | QR63: 0 | QS63: 0 | QT63: 0 | QV63: 0 | QW63: 0 | QX63: 0 | QY63: 0 | QZ63: 0 | RA63: 0 | RC63: 0 | RD63: 0 | RE63: 0 | RF63: 0 | RG63: 0 | RH63: 0 | RJ63: 0 | RK63: 0 | RL63: 0 | RM63: 0 | RN63: 0 | RO63: 0 | RQ63: 0 | RR63: 0 | RS63: 0 | RT63: 0 | RU63: 0 | RV63: 0 | RX63: 0 | RY63: 0 | RZ63: 0 | SA63: 0 | SB63: 0 | SC63: 0 | SE63: 0 | SF63: 0 | SG63: 0 | SH63: 0 | SI63: 0 | SJ63: 0 | SP63: 0 | SQ63: 0 | SS63: 0 | TZ63: 0.01 | UB63: 0.03 | UC63: 0.03 | UD63: 0.03 | UE63: 0.03 | UF63: 0.03 | UG63: 0.02 | UI63: 0.02 | UJ63: 0.02 | UK63: 0.02 | UL63: 0.02 | UM63: 0.03 | UN63: 0.04 | UP63: 0.04 | UQ63: 0.06 | UR63: 0.09 | US63: 0.09 | UT63: 0.07 | YT63: 0 | YU63: 0.01 | YV63: 0.01 | YX63: 0.01 | YY63: 0.01 | YZ63: 0.01 | ZA63: 0.01 | ZB63: 0.01 | ZC63: 0.01
A64: Pot Butterfly Valves Dia. 315 mm | E64: 1 | F64: 0.03 | G64: 13630 | I64: =F64 -> 0.03 | AF64: 0 | AG64: 0 | AH64: 0 | AK64: 0 | AL64: 0 | AM64: 0 | AN64: 0 | AO64: 0 | NN64: 0 | NP64: 0 | NQ64: 0 | NR64: 0 | NS64: 0 | NT64: 0 | NU64: 0 | NW64: 0 | NX64: 0 | NY64: 0 | NZ64: 0 | OA64: 0 | OB64: 0 | OD64: 0 | OE64: 0 | OF64: 0 | OG64: 0 | OH64: 0 | OI64: 0 | OL64: 0 | OM64: 0 | ON64: 0 | OO64: 0 | OP64: 0 | OR64: 0 | OS64: 0 | OT64: 0 | OU64: 0 | OV64: 0 | OW64: 0 | OY64: 0 | OZ64: 0 | PA64: 0 | PB64: 0 | PC64: 0 | PD64: 0 | PF64: 0 | PG64: 0 | PH64: 0 | PI64: 0 | PJ64: 0 | PK64: 0 | PM64: 0 | PN64: 0 | PO64: 0 | PP64: 0 | PQ64: 0 | PR64: 0 | PT64: 0 | PY64: 0 | QA64: 0 | QB64: 0 | QC64: 0 | QD64: 0 | QE64: 0 | QF64: 0 | QH64: 0 | QI64: 0 | QJ64: 0 | QK64: 0.02 | QL64: 0.05 | QM64: 0.01 | QO64: 0.05 | QP64: 0.05 | QQ64: 0.05 | QR64: 0.05 | QS64: 0.05 | QT64: 0.04 | QV64: 0.04 | QW64: 0.06 | QX64: 0.14 | QY64: 0.1 | QZ64: 0 | RA64: 0 | RC64: 0 | RD64: 0 | RE64: 0 | RF64: 0 | RG64: 0 | RH64: 0 | RJ64: 0 | RK64: 0 | RL64: 0 | RM64: 0 | RN64: 0 | RO64: 0 | RQ64: 0 | RR64: 0 | RS64: 0 | RT64: 0 | RU64: 0 | RV64: 0 | RX64: 0 | RY64: 0 | RZ64: 0 | SA64: 0 | SB64: 0 | SC64: 0 | SE64: 0 | SF64: 0 | SG64: 0 | SH64: 0 | SI64: 0 | SJ64: 0 | SP64: 0 | SQ64: 0 | SS64: 0 | YT64: 0 | YU64: 0.01 | YV64: 0.01 | YX64: 0.01 | YY64: 0.01 | YZ64: 0.01 | ZA64: 0.01 | ZB64: 0.01 | ZC64: 0.01
A65: Pot Gate Valves Dia. 160 mm | E65: 12 | F65: 0.36 | G65: 36720 | I65: =F65 -> 0.36 | AF65: 0.05 | AG65: 0.05 | AH65: 0.05 | AK65: 0.05 | AL65: 0.05 | AM65: 0.05 | AN65: 0.05 | AO65: 0.05 | NN65: 0.01 | NP65: 0.02 | NQ65: 0.02 | NR65: 0.02 | NS65: 0.02 | NT65: 0.02 | NU65: 0.02 | NW65: 0.02 | NX65: 0.02 | NY65: 0.02 | NZ65: 0.02 | OA65: 0.02 | OB65: 0.02 | OD65: 0.02 | OE65: 0.02 | OF65: 0.02 | OG65: 0.02 | OH65: 0.02 | OI65: 0.02 | OL65: 0.02 | OM65: 0.02 | ON65: 0.02 | OO65: 0.02 | OP65: 0.02 | OR65: 0.02 | OS65: 0.02 | OT65: 0.02 | OU65: 0.02 | OV65: 0.02 | OW65: 0.02 | OY65: 0.02 | OZ65: 0.02 | PA65: 0.02 | PB65: 0.02 | PC65: 0.02 | PD65: 0.02 | PF65: 0.02 | PG65: 0.02 | PH65: 0.02 | PI65: 0.02 | PJ65: 0.02 | PK65: 0.02 | PM65: 0.02 | PN65: 0.02 | PO65: 0.02 | PP65: 0.02 | PQ65: 0.02 | PR65: 0.02 | PT65: 0.02 | PY65: 0.02 | QA65: 0.02 | QB65: 0.02 | QC65: 0.02 | QD65: 0.02 | QE65: 0.02 | QF65: 0.02 | QH65: 0.02 | QI65: 0.02 | QJ65: 0.02 | QK65: 0.26 | QL65: 0.96 | QM65: 0.96 | QO65: 0.96 | QP65: 0.79 | QQ65: 0.26 | QR65: 0.26 | QS65: 0.26 | QT65: 0.2 | QV65: 0.02 | QW65: 0.02 | QX65: 0.02 | QY65: 0.02 | QZ65: 0.02 | RA65: 0.02 | RC65: 0.02 | RD65: 0.02 | RE65: 0.02 | RF65: 0.02 | RG65: 0.02 | RH65: 0.16 | RJ65: 0.56 | RK65: 0.46 | RL65: 0.16 | RM65: 0.12 | RN65: 0.02 | RO65: 0.02 | RQ65: 0.06 | RR65: 0.16 | RS65: 0.16 | RT65: 0.16 | RU65: 0.13 | RV65: 0.06 | RX65: 0.06 | RY65: 0.06 | RZ65: 0.05 | SA65: 0.02 | SB65: 0.02 | SC65: 0.02 | SE65: 0.02 | SF65: 0.02 | SG65: 0.02 | SH65: 0.02 | SI65: 0.02 | SJ65: 0.02 | SP65: 0.02 | SQ65: 0.02 | SS65: 0.02 | UM65: 0.09 | UN65: 0.36 | UP65: 0.36 | UQ65: 0.29 | UR65: 0.09 | US65: 0.09 | UT65: 0.07 | YT65: 0.04 | YU65: 0.15 | YV65: 0.15 | YX65: 0.15 | YY65: 0.15 | YZ65: 0.15 | ZA65: 0.15 | ZB65: 0.15 | ZC65: 0.11
A66: Pot Gate Valves Dia. 200 mm | E66: 2 | F66: 0.06 | G66: 8460 | I66: =F66 -> 0.06 | AF66: 0.01 | AG66: 0.01 | AH66: 0.01 | AK66: 0.01 | AL66: 0.01 | AM66: 0.01 | AN66: 0.01 | AO66: 0.01 | NN66: 0 | NP66: 0 | NQ66: 0 | NR66: 0 | NS66: 0 | NT66: 0 | NU66: 0 | NW66: 0 | NX66: 0 | NY66: 0 | NZ66: 0 | OA66: 0 | OB66: 0 | OD66: 0 | OE66: 0 | OF66: 0 | OG66: 0 | OH66: 0 | OI66: 0 | OL66: 0 | OM66: 0 | ON66: 0 | OO66: 0 | OP66: 0 | OR66: 0 | OS66: 0 | OT66: 0 | OU66: 0 | OV66: 0 | OW66: 0 | OY66: 0 | OZ66: 0 | PA66: 0 | PB66: 0 | PC66: 0 | PD66: 0 | PF66: 0 | PG66: 0 | PH66: 0 | PI66: 0 | PJ66: 0 | PK66: 0 | PM66: 0 | PN66: 0 | PO66: 0 | PP66: 0 | PQ66: 0 | PR66: 0 | PT66: 0 | PY66: 0 | QA66: 0 | QB66: 0 | QC66: 0 | QD66: 0 | QE66: 0 | QF66: 0 | QH66: 0 | QI66: 0 | QJ66: 0 | QK66: 0 | QL66: 0 | QM66: 0 | QO66: 0 | QP66: 0 | QQ66: 0 | QR66: 0 | QS66: 0 | QT66: 0 | QV66: 0 | QW66: 0 | QX66: 0 | QY66: 0 | QZ66: 0 | RA66: 0 | RC66: 0 | RD66: 0 | RE66: 0 | RF66: 0 | RG66: 0 | RH66: 0 | RJ66: 0 | RK66: 0 | RL66: 0 | RM66: 0 | RN66: 0 | RO66: 0 | RQ66: 0 | RR66: 0 | RS66: 0 | RT66: 0 | RU66: 0.07 | RV66: 0.27 | RX66: 0.27 | RY66: 0.27 | RZ66: 0.22 | SA66: 0.07 | SB66: 0.07 | SC66: 0.07 | SE66: 0.05 | SF66: 0 | SG66: 0 | SH66: 0 | SI66: 0 | SJ66: 0 | SP66: 0 | SQ66: 0 | SS66: 0 | YT66: 0.01 | YU66: 0.03 | YV66: 0.03 | YX66: 0.03 | YY66: 0.03 | YZ66: 0.03 | ZA66: 0.03 | ZB66: 0.03 | ZC66: 0.02
A67: Pot Gate Valves Dia. 225 mm | E67: 3 | F67: 0.09 | G67: 18330 | I67: =F67 -> 0.09 | AF67: 0.01 | AG67: 0.01 | AH67: 0.01 | AK67: 0.01 | AL67: 0.01 | AM67: 0.01 | AN67: 0.01 | AO67: 0.01 | NN67: 0 | NP67: 0.01 | NQ67: 0.01 | NR67: 0.01 | NS67: 0.01 | NT67: 0.01 | NU67: 0.01 | NW67: 0.01 | NX67: 0.01 | NY67: 0.01 | NZ67: 0.01 | OA67: 0.01 | OB67: 0.01 | OD67: 0.01 | OE67: 0.01 | OF67: 0.01 | OG67: 0.01 | OH67: 0.01 | OI67: 0.01 | OL67: 0.01 | OM67: 0.01 | ON67: 0.01 | OO67: 0.01 | OP67: 0.01 | OR67: 0 | OS67: 0 | OT67: 0 | OU67: 0 | OV67: 0 | OW67: 0 | OY67: 0 | OZ67: 0 | PA67: 0 | PB67: 0 | PC67: 0 | PD67: 0 | PF67: 0 | PG67: 0 | PH67: 0 | PI67: 0 | PJ67: 0 | PK67: 0 | PM67: 0 | PN67: 0 | PO67: 0 | PP67: 0 | PQ67: 0 | PR67: 0 | PT67: 0 | PY67: 0.01 | QA67: 0.01 | QB67: 0.01 | QC67: 0.01 | QD67: 0.01 | QE67: 0.01 | QF67: 0.01 | QH67: 0.01 | QI67: 0.01 | QJ67: 0.01 | QK67: 0.01 | QL67: 0.01 | QM67: 0.01 | QO67: 0.01 | QP67: 0.01 | QQ67: 0.01 | QR67: 0.01 | QS67: 0.01 | QT67: 0.01 | QV67: 0.01 | QW67: 0.01 | QX67: 0.01 | QY67: 0.01 | QZ67: 0.01 | RA67: 0.01 | RC67: 0.01 | RD67: 0.01 | RE67: 0.01 | RF67: 0.01 | RG67: 0.01 | RH67: 0.01 | RJ67: 0.01 | RK67: 0.14 | RL67: 0.54 | RM67: 0.44 | RN67: 0.14 | RO67: 0.11 | RQ67: 0.01 | RR67: 0.01 | RS67: 0.01 | RT67: 0.01 | RU67: 0.01 | RV67: 0.01 | RX67: 0.01 | RY67: 0.01 | RZ67: 0.01 | SA67: 0.01 | SB67: 0.01 | SC67: 0.01 | SE67: 0.01 | SF67: 0.01 | SG67: 0.01 | SH67: 0.01 | SI67: 0.01 | SJ67: 0.01 | SP67: 0.01 | SQ67: 0.01 | SS67: 0 | TO67: 0.03 | TP67: 0.13 | TQ67: 0.13 | TR67: 0.13 | TS67: 0.11 | TU67: 0.03 | TV67: 0.03 | TW67: 0.03 | TX67: 0.03 | YT67: 0.01 | YU67: 0.04 | YV67: 0.04 | YX67: 0.04 | YY67: 0.04 | YZ67: 0.04 | ZA67: 0.04 | ZB67: 0.04 | ZC67: 0.03
A68: Pot Gate Valves Dia. 250 mm | E68: 3 | F68: 0.09 | G68: 21150 | I68: =F68 -> 0.09 | AF68: 0.01 | AG68: 0.01 | AH68: 0.01 | AK68: 0.01 | AL68: 0.01 | AM68: 0.01 | AN68: 0.01 | AO68: 0.01 | NN68: 0 | NP68: 0.01 | NQ68: 0.01 | NR68: 0.01 | NS68: 0.01 | NT68: 0.01 | NU68: 0.01 | NW68: 0.01 | NX68: 0.01 | NY68: 0.01 | NZ68: 0.01 | OA68: 0.01 | OB68: 0.01 | OD68: 0.01 | OE68: 0.01 | OF68: 0.01 | OG68: 0.01 | OH68: 0.01 | OI68: 0.01 | OL68: 0.01 | OM68: 0.01 | ON68: 0.01 | OO68: 0.01 | OP68: 0.01 | OR68: 0 | OS68: 0 | OT68: 0 | OU68: 0 | OV68: 0 | OW68: 0 | OY68: 0 | OZ68: 0 | PA68: 0 | PB68: 0 | PC68: 0 | PD68: 0 | PF68: 0 | PG68: 0 | PH68: 0 | PI68: 0 | PJ68: 0 | PK68: 0 | PM68: 0 | PN68: 0 | PO68: 0 | PP68: 0 | PQ68: 0 | PR68: 0 | PT68: 0 | PY68: 0.01 | QA68: 0.01 | QB68: 0.01 | QC68: 0.01 | QD68: 0.01 | QE68: 0.01 | QF68: 0.01 | QH68: 0.01 | QI68: 0.01 | QJ68: 0.01 | QK68: 0.01 | QL68: 0.01 | QM68: 0.01 | QO68: 0.01 | QP68: 0.01 | QQ68: 0.01 | QR68: 0.01 | QS68: 0.01 | QT68: 0.01 | QV68: 0.01 | QW68: 0.01 | QX68: 0.01 | QY68: 0.01 | QZ68: 0.01 | RA68: 0.01 | RC68: 0.01 | RD68: 0.01 | RE68: 0.01 | RF68: 0.01 | RG68: 0.01 | RH68: 0.01 | RJ68: 0.01 | RK68: 0.01 | RL68: 0.01 | RM68: 0.07 | RN68: 0.27 | RO68: 0.22 | RQ68: 0.07 | RR68: 0.06 | RS68: 0.01 | RT68: 0.01 | RU68: 0.01 | RV68: 0.01 | RX68: 0.01 | RY68: 0.01 | RZ68: 0.07 | SA68: 0.27 | SB68: 0.27 | SC68: 0.27 | SE68: 0.22 | SF68: 0.07 | SG68: 0.07 | SH68: 0.07 | SI68: 0.06 | SJ68: 0.01 | SP68: 0.01 | SQ68: 0.01 | SS68: 0 | YT68: 0.01 | YU68: 0.04 | YV68: 0.04 | YX68: 0.04 | YY68: 0.04 | YZ68: 0.04 | ZA68: 0.04 | ZB68: 0.04 | ZC68: 0.03
A69: Pot Gate Valves Dia. 280 mm | E69: 1 | F69: 0.03 | G69: 8225 | I69: =F69 -> 0.03 | AF69: 0 | AG69: 0 | AH69: 0 | AK69: 0 | AL69: 0 | AM69: 0 | AN69: 0 | AO69: 0 | NN69: 0 | NP69: 0 | NQ69: 0 | NR69: 0 | NS69: 0 | NT69: 0 | NU69: 0 | NW69: 0 | NX69: 0 | NY69: 0 | NZ69: 0 | OA69: 0 | OB69: 0 | OD69: 0 | OE69: 0 | OF69: 0 | OG69: 0 | OH69: 0 | OI69: 0 | OL69: 0 | OM69: 0 | ON69: 0 | OO69: 0 | OP69: 0 | OR69: 0 | OS69: 0 | OT69: 0 | OU69: 0 | OV69: 0 | OW69: 0 | OY69: 0 | OZ69: 0 | PA69: 0 | PB69: 0 | PC69: 0 | PD69: 0 | PF69: 0 | PG69: 0 | PH69: 0 | PI69: 0 | PJ69: 0 | PK69: 0 | PM69: 0 | PN69: 0 | PO69: 0 | PP69: 0 | PQ69: 0 | PR69: 0 | PT69: 0 | PY69: 0 | QA69: 0 | QB69: 0 | QC69: 0 | QD69: 0 | QE69: 0 | QF69: 0 | QH69: 0 | QI69: 0 | QJ69: 0 | QK69: 0 | QL69: 0 | QM69: 0 | QO69: 0 | QP69: 0 | QQ69: 0 | QR69: 0 | QS69: 0 | QT69: 0 | QV69: 0 | QW69: 0 | QX69: 0 | QY69: 0 | QZ69: 0 | RA69: 0 | RC69: 0 | RD69: 0 | RE69: 0 | RF69: 0 | RG69: 0 | RH69: 0 | RJ69: 0 | RK69: 0 | RL69: 0 | RM69: 0 | RN69: 0 | RO69: 0 | RQ69: 0 | RR69: 0 | RS69: 0 | RT69: 0 | RU69: 0 | RV69: 0 | RX69: 0 | RY69: 0 | RZ69: 0 | SA69: 0 | SB69: 0 | SC69: 0 | SE69: 0.04 | SF69: 0.14 | SG69: 0.14 | SH69: 0.14 | SI69: 0.11 | SJ69: 0.04 | SP69: 0.04 | SQ69: 0.04 | SS69: 0.03 | YT69: 0 | YU69: 0.01 | YV69: 0.01 | YX69: 0.01 | YY69: 0.01 | YZ69: 0.01 | ZA69: 0.01 | ZB69: 0.01 | ZC69: 0.01
A70: Pot HDPE 160mm 0.0 to 1.5m | E70: 300 | F70: 9 | G70: 96000 | I70: =F70 -> 9 | AB70: 1.13 | AD70: 1.13 | AE70: 1.13 | AF70: 1.13 | AG70: 1.13 | AH70: 1.13 | AK70: 1.13 | AL70: 1.13 | NP70: 0.33 | NQ70: 0.67 | NR70: 0.67 | NS70: 0.67 | NT70: 0.67 | NU70: 0.67 | NW70: 0.67 | NX70: 0.67 | NY70: 0.67 | NZ70: 0.67 | OA70: 0.67 | OB70: 0.67 | OD70: 0.67 | OE70: 0.67 | OF70: 0.67 | OG70: 0.67 | OH70: 0.67 | OI70: 0.67 | OL70: 0.67 | OM70: 0.67 | ON70: 0.67 | OO70: 0.67 | OP70: 0.67 | OR70: 0.5 | OS70: 0.5 | OT70: 0.5 | OU70: 0.5 | OV70: 0.5 | OW70: 0.5 | OY70: 0.5 | OZ70: 0.5 | PA70: 0.5 | PB70: 0.5 | PC70: 0.5 | PD70: 0.5 | PF70: 0.5 | PG70: 0.5 | PH70: 0.5 | PI70: 0.5 | PJ70: 0.5 | PK70: 0.5 | PM70: 0.5 | PN70: 0.5 | PO70: 0.5 | PP70: 0.5 | PQ70: 0.5 | PR70: 0.5 | PT70: 0.5 | PY70: 0.67 | QA70: 0.67 | QB70: 0.67 | QC70: 0.67 | QD70: 1.76 | QE70: 5.04 | QF70: 5.04 | QH70: 4.68 | QI70: 3.59 | QJ70: 3.59 | QK70: 5.04 | QL70: 9.42 | QM70: 9.42 | QO70: 9.42 | QP70: 9.42 | QQ70: 7.96 | QR70: 3.59 | QS70: 3.59 | QT70: 3.51 | QV70: 3.29 | QW70: 3.29 | QX70: 3.29 | QY70: 7.55 | QZ70: 15.4 | RA70: 0.67 | RC70: 0.67 | RD70: 2.08 | RE70: 6.34 | RF70: 12.01 | RG70: 29.03 | RH70: 23.36 | RJ70: 6.34 | RK70: 7.05 | RL70: 9.17 | RM70: 7.05 | RN70: 0.67 | RO70: 0.67 | RQ70: 0.67 | RR70: 0.67 | RS70: 0.67 | RT70: 0.67 | RU70: 0.67 | RV70: 0.67 | RX70: 0.67 | RY70: 0.67 | RZ70: 0.67 | SA70: 0.67 | SB70: 0.67 | SC70: 0.5 | YT70: 0.94 | YU70: 3.75 | YV70: 3.75 | YX70: 3.75 | YY70: 3.75 | YZ70: 3.75 | ZA70: 3.75 | ZB70: 3.75 | ZC70: 2.81
A71: Pot HDPE 160mm 1.5 to 3.0m | E71: 2300 | F71: 99.73 | G71: 1081000 | I71: =F71 -> 99.73 | AB71: 8.63 | AD71: 8.63 | AE71: 8.63 | AF71: 8.63 | AG71: 8.63 | AH71: 8.63 | AK71: 8.63 | AL71: 8.63 | NP71: 2.56 | NQ71: 5.11 | NR71: 5.11 | NS71: 5.11 | NT71: 5.11 | NU71: 5.11 | NW71: 5.11 | NX71: 5.11 | NY71: 5.11 | NZ71: 5.11 | OA71: 5.11 | OB71: 5.11 | OD71: 5.11 | OE71: 5.11 | OF71: 5.11 | OG71: 5.11 | OH71: 5.11 | OI71: 5.11 | OL71: 5.11 | OM71: 5.11 | ON71: 5.11 | OO71: 5.11 | OP71: 5.11 | OR71: 3.83 | OS71: 3.83 | OT71: 3.83 | OU71: 3.83 | OV71: 3.83 | OW71: 3.83 | OY71: 3.83 | OZ71: 3.83 | PA71: 3.83 | PB71: 3.83 | PC71: 3.83 | PD71: 3.83 | PF71: 3.83 | PG71: 3.83 | PH71: 3.83 | PI71: 3.83 | PJ71: 3.83 | PK71: 3.83 | PM71: 3.83 | PN71: 3.83 | PO71: 3.83 | PP71: 3.83 | PQ71: 3.83 | PR71: 3.83 | PT71: 3.83 | PY71: 5.11 | QA71: 5.11 | QB71: 5.11 | QC71: 5.11 | QD71: 5.11 | QE71: 5.11 | QF71: 5.11 | QH71: 16.49 | QI71: 50.61 | QJ71: 50.61 | QK71: 46.82 | QL71: 35.45 | QM71: 35.45 | QO71: 50.62 | QP71: 96.12 | QQ71: 96.12 | QR71: 96.12 | QS71: 96.12 | QT71: 84.03 | QV71: 47.76 | QW71: 47.76 | QX71: 47 | QY71: 44.73 | QZ71: 49.34 | RA71: 63.19 | RC71: 63.19 | RD71: 56.36 | RE71: 31.27 | RF71: 17.43 | RG71: 16.19 | RH71: 12.5 | RJ71: 12.5 | RK71: 12.5 | RL71: 12.5 | RM71: 10.65 | RN71: 5.11 | RO71: 5.11 | RQ71: 5.11 | RR71: 5.11 | RS71: 5.11 | RT71: 5.11 | RU71: 5.11 | RV71: 5.11 | RX71: 5.11 | RY71: 5.11 | RZ71: 5.11 | SA71: 5.11 | SB71: 5.11 | SC71: 3.83 | SU71: 1.54 | SV71: 6.16 | SW71: 6.16 | SX71: 6.16 | SZ71: 5.65 | TA71: 4.11 | TB71: 4.11 | TC71: 4.11 | TD71: 6.51 | TE71: 13.69 | TG71: 13.69 | TH71: 13.69 | TI71: 13.69 | TJ71: 13.69 | TK71: 11.3 | TL71: 4.11 | TN71: 4.11 | TO71: 4.11 | TP71: 4.11 | TQ71: 4.11 | TR71: 4.11 | TS71: 4.11 | TU71: 4.11 | TV71: 4.11 | TW71: 3.08 | UE71: 2.75 | UF71: 11.02 | UG71: 11.02 | UI71: 13.77 | UJ71: 16.53 | UK71: 13.77 | UL71: 55.09 | UM71: 43.15 | UN71: 7.35 | UP71: 7.35 | UQ71: 7.58 | UR71: 8.26 | US71: 8.26 | UT71: 8.26 | UU71: 6.2 | YT71: 7.19 | YU71: 28.75 | YV71: 28.75 | YX71: 28.75 | YY71: 28.75 | YZ71: 28.75 | ZA71: 28.75 | ZB71: 28.75 | ZC71: 21.56
A72: Pot HDPE 200mm 1.5 to 3.0m | E72: 750 | F72: 22.5 | G72: 412500 | I72: =F72 -> 22.5 | AB72: 2.81 | AD72: 2.81 | AE72: 2.81 | AF72: 2.81 | AG72: 2.81 | AH72: 2.81 | AK72: 2.81 | AL72: 2.81 | NP72: 0.83 | NQ72: 1.67 | NR72: 1.67 | NS72: 1.67 | NT72: 1.67 | NU72: 1.67 | NW72: 1.67 | NX72: 1.67 | NY72: 1.67 | NZ72: 1.67 | OA72: 1.67 | OB72: 1.67 | OD72: 1.67 | OE72: 1.67 | OF72: 1.67 | OG72: 1.67 | OH72: 1.67 | OI72: 1.67 | OL72: 1.67 | OM72: 1.67 | ON72: 1.67 | OO72: 1.67 | OP72: 1.67 | OR72: 1.25 | OS72: 1.25 | OT72: 1.25 | OU72: 1.25 | OV72: 1.25 | OW72: 1.25 | OY72: 1.25 | OZ72: 1.25 | PA72: 1.25 | PB72: 1.25 | PC72: 1.25 | PD72: 1.25 | PF72: 1.25 | PG72: 1.25 | PH72: 1.25 | PI72: 1.25 | PJ72: 1.25 | PK72: 1.25 | PM72: 1.25 | PN72: 1.25 | PO72: 1.25 | PP72: 1.25 | PQ72: 1.25 | PR72: 1.25 | PT72: 1.25 | PY72: 1.67 | QA72: 1.67 | QB72: 1.67 | QC72: 1.67 | QD72: 1.67 | QE72: 1.67 | QF72: 1.67 | QH72: 1.67 | QI72: 1.67 | QJ72: 1.67 | QK72: 1.67 | QL72: 1.67 | QM72: 1.67 | QO72: 1.67 | QP72: 1.67 | QQ72: 1.67 | QR72: 1.67 | QS72: 1.67 | QT72: 1.67 | QV72: 1.67 | QW72: 1.67 | QX72: 5.33 | QY72: 16.31 | QZ72: 16.31 | RA72: 16.31 | RC72: 16.31 | RD72: 17.26 | RE72: 19.56 | RF72: 17.94 | RG72: 24.04 | RH72: 42.52 | RJ72: 43.06 | RK72: 43.78 | RL72: 45.94 | RM72: 45.22 | RN72: 36.96 | RO72: 18.75 | RQ72: 19.02 | RR72: 17.73 | RS72: 13.87 | RT72: 13.87 | RU72: 13.87 | RV72: 13.87 | RX72: 13.87 | RY72: 10.82 | RZ72: 1.67 | SA72: 1.67 | SB72: 1.67 | SC72: 1.25 | YT72: 2.34 | YU72: 9.38 | YV72: 9.38 | YX72: 9.38 | YY72: 9.38 | YZ72: 9.38 | ZA72: 9.38 | ZB72: 9.38 | ZC72: 7.03
A73: Pot HDPE 225mm 1.5 to 3.0m | E73: 550 | F73: 16.5 | G73: 324501.3 | I73: =F73 -> 16.5 | AB73: 2.06 | AD73: 2.06 | AE73: 2.06 | AF73: 2.06 | AG73: 2.06 | AH73: 2.06 | AK73: 2.06 | AL73: 2.06 | NP73: 0.61 | NQ73: 1.22 | NR73: 1.22 | NS73: 1.22 | NT73: 1.22 | NU73: 1.22 | NW73: 1.22 | NX73: 1.22 | NY73: 1.22 | NZ73: 1.22 | OA73: 1.22 | OB73: 1.22 | OD73: 1.22 | OE73: 1.22 | OF73: 1.22 | OG73: 1.22 | OH73: 1.22 | OI73: 1.22 | OL73: 1.22 | OM73: 1.22 | ON73: 1.22 | OO73: 1.22 | OP73: 1.22 | OR73: 0.92 | OS73: 0.92 | OT73: 0.92 | OU73: 0.92 | OV73: 0.92 | OW73: 0.92 | OY73: 0.92 | OZ73: 0.92 | PA73: 0.92 | PB73: 0.92 | PC73: 0.92 | PD73: 0.92 | PF73: 0.92 | PG73: 0.92 | PH73: 0.92 | PI73: 0.92 | PJ73: 0.92 | PK73: 0.92 | PM73: 0.92 | PN73: 0.92 | PO73: 0.92 | PP73: 0.92 | PQ73: 0.92 | PR73: 0.92 | PT73: 0.92 | PY73: 1.22 | QA73: 1.22 | QB73: 1.22 | QC73: 1.22 | QD73: 1.22 | QE73: 1.22 | QF73: 1.22 | QH73: 1.22 | QI73: 1.22 | QJ73: 1.22 | QK73: 1.22 | QL73: 1.22 | QM73: 1.22 | QO73: 1.22 | QP73: 1.22 | QQ73: 1.22 | QR73: 1.22 | QS73: 1.22 | QT73: 1.22 | QV73: 1.22 | QW73: 1.22 | QX73: 1.22 | QY73: 1.22 | QZ73: 1.22 | RA73: 1.22 | RC73: 1.22 | RD73: 1.22 | RE73: 1.22 | RF73: 1.22 | RG73: 1.22 | RH73: 1.22 | RJ73: 1.22 | RK73: 1.22 | RL73: 1.22 | RM73: 1.22 | RN73: 1.22 | RO73: 4.22 | RQ73: 13.2 | RR73: 13.2 | RS73: 13.2 | RT73: 14.19 | RU73: 17.19 | RV73: 33.15 | RX73: 81.05 | RY73: 65.08 | RZ73: 17.19 | SA73: 19.18 | SB73: 25.17 | SC73: 18.88 | SZ73: 0.46 | TA73: 1.84 | TB73: 1.84 | TC73: 1.84 | TD73: 1.79 | TE73: 1.64 | TG73: 1.64 | TH73: 2.46 | TI73: 4.92 | TJ73: 4.92 | TK73: 4.92 | TL73: 4.92 | TN73: 4.1 | TO73: 1.64 | TP73: 1.64 | TQ73: 1.6 | TR73: 1.48 | TS73: 1.48 | TU73: 1.48 | TV73: 1.48 | TW73: 1.11 | YT73: 1.72 | YU73: 6.88 | YV73: 6.88 | YX73: 6.88 | YY73: 6.88 | YZ73: 6.88 | ZA73: 6.88 | ZB73: 6.88 | ZC73: 5.16
A74: Pot HDPE 250mm 1.5 to 3.0m | E74: 850 | F74: 25.5 | G74: 552498.7 | I74: =F74 -> 25.5 | AB74: 3.19 | AD74: 3.19 | AE74: 3.19 | AF74: 3.19 | AG74: 3.19 | AH74: 3.19 | AK74: 3.19 | AL74: 3.19 | NP74: 0.94 | NQ74: 1.89 | NR74: 1.89 | NS74: 1.89 | NT74: 1.89 | NU74: 1.89 | NW74: 1.89 | NX74: 1.89 | NY74: 1.89 | NZ74: 1.89 | OA74: 1.89 | OB74: 1.89 | OD74: 1.89 | OE74: 1.89 | OF74: 1.89 | OG74: 1.89 | OH74: 1.89 | OI74: 1.89 | OL74: 1.89 | OM74: 1.89 | ON74: 1.89 | OO74: 1.89 | OP74: 1.89 | OR74: 1.42 | OS74: 1.42 | OT74: 1.42 | OU74: 1.42 | OV74: 1.42 | OW74: 1.42 | OY74: 1.42 | OZ74: 1.42 | PA74: 1.42 | PB74: 1.42 | PC74: 1.42 | PD74: 1.42 | PF74: 1.42 | PG74: 1.42 | PH74: 1.42 | PI74: 1.42 | PJ74: 1.42 | PK74: 1.42 | PM74: 1.42 | PN74: 1.42 | PO74: 1.42 | PP74: 1.42 | PQ74: 1.42 | PR74: 1.42 | PT74: 1.42 | PY74: 1.89 | QA74: 1.89 | QB74: 1.89 | QC74: 1.89 | QD74: 1.89 | QE74: 1.89 | QF74: 1.89 | QH74: 1.89 | QI74: 1.89 | QJ74: 1.89 | QK74: 1.89 | QL74: 1.89 | QM74: 1.89 | QO74: 1.89 | QP74: 1.89 | QQ74: 1.89 | QR74: 1.89 | QS74: 1.89 | QT74: 1.89 | QV74: 1.89 | QW74: 1.89 | QX74: 1.89 | QY74: 1.89 | QZ74: 1.89 | RA74: 1.89 | RC74: 1.89 | RD74: 5.23 | RE74: 15.25 | RF74: 15.25 | RG74: 15.25 | RH74: 15.25 | RJ74: 15.62 | RK74: 16.74 | RL74: 16.74 | RM74: 22.3 | RN74: 39.01 | RO74: 39.01 | RQ74: 39.01 | RR74: 39.01 | RS74: 39.01 | RT74: 36.46 | RU74: 28.81 | RV74: 23.25 | RX74: 6.54 | RY74: 10.27 | RZ74: 21.46 | SA74: 27.66 | SB74: 46.27 | SC74: 39.6 | SE74: 16.23 | SF74: 6.98 | SG74: 9.31 | SH74: 6.98 | YT74: 2.66 | YU74: 10.63 | YV74: 10.63 | YX74: 10.63 | YY74: 10.63 | YZ74: 10.63 | ZA74: 10.63 | ZB74: 10.63 | ZC74: 7.97
A75: Pot HDPE 280mm 1.5 to 3.0m | E75: 110 | F75: 8.62 | G75: 79200 | I75: =F75 -> 8.62 | AB75: 0.41 | AD75: 0.41 | AE75: 0.41 | AF75: 0.41 | AG75: 0.41 | AH75: 0.41 | AK75: 0.41 | AL75: 0.41 | NP75: 0.12 | NQ75: 0.24 | NR75: 0.24 | NS75: 0.24 | NT75: 0.24 | NU75: 0.24 | NW75: 0.24 | NX75: 0.24 | NY75: 0.24 | NZ75: 0.24 | OA75: 0.24 | OB75: 0.24 | OD75: 0.24 | OE75: 0.24 | OF75: 0.24 | OG75: 0.24 | OH75: 0.24 | OI75: 0.24 | OL75: 0.24 | OM75: 0.24 | ON75: 0.24 | OO75: 0.24 | OP75: 0.24 | OR75: 0.18 | OS75: 0.18 | OT75: 0.18 | OU75: 0.18 | OV75: 0.18 | OW75: 0.18 | OY75: 0.18 | OZ75: 0.18 | PA75: 0.18 | PB75: 0.18 | PC75: 0.18 | PD75: 0.18 | PF75: 0.18 | PG75: 0.18 | PH75: 0.18 | PI75: 0.18 | PJ75: 0.18 | PK75: 0.18 | PM75: 0.18 | PN75: 0.18 | PO75: 0.18 | PP75: 0.18 | PQ75: 0.18 | PR75: 0.18 | PT75: 0.18 | PY75: 0.24 | QA75: 0.24 | QB75: 0.24 | QC75: 0.24 | QD75: 0.24 | QE75: 0.24 | QF75: 0.24 | QH75: 0.24 | QI75: 0.24 | QJ75: 0.24 | QK75: 0.24 | QL75: 0.24 | QM75: 0.24 | QO75: 0.24 | QP75: 0.24 | QQ75: 0.24 | QR75: 0.24 | QS75: 0.24 | QT75: 0.24 | QV75: 0.24 | QW75: 0.24 | QX75: 0.24 | QY75: 0.24 | QZ75: 0.24 | RA75: 0.24 | RC75: 0.24 | RD75: 0.24 | RE75: 0.24 | RF75: 0.24 | RG75: 0.24 | RH75: 0.24 | RJ75: 1.63 | RK75: 5.77 | RL75: 5.31 | RM75: 3.93 | RN75: 7.61 | RO75: 18.67 | RQ75: 14.98 | RR75: 3.93 | RS75: 4.39 | RT75: 5.77 | RU75: 4.39 | RV75: 0.24 | RX75: 0.24 | RY75: 0.24 | RZ75: 0.24 | SA75: 0.24 | SB75: 0.24 | SC75: 0.18 | YT75: 0.34 | YU75: 1.38 | YV75: 1.38 | YX75: 1.38 | YY75: 1.38 | YZ75: 1.38 | ZA75: 1.38 | ZB75: 1.38 | ZC75: 1.03
A76: Pot HDPE 315mm 0.0 to 1.5m | E76: 175 | F76: 5.25 | G76: 112000 | I76: =F76 -> 5.25 | AB76: 0.66 | AD76: 0.66 | AE76: 0.66 | AF76: 0.66 | AG76: 0.66 | AH76: 0.66 | AK76: 0.66 | AL76: 0.66 | NP76: 0.19 | NQ76: 0.39 | NR76: 0.39 | NS76: 0.39 | NT76: 0.39 | NU76: 0.39 | NW76: 0.39 | NX76: 0.39 | NY76: 0.39 | NZ76: 0.39 | OA76: 0.39 | OB76: 0.39 | OD76: 0.39 | OE76: 0.39 | OF76: 0.39 | OG76: 0.39 | OH76: 0.39 | OI76: 0.39 | OL76: 0.39 | OM76: 0.39 | ON76: 0.39 | OO76: 0.39 | OP76: 0.39 | OR76: 0.29 | OS76: 0.29 | OT76: 0.29 | OU76: 0.29 | OV76: 0.29 | OW76: 0.29 | OY76: 0.29 | OZ76: 0.29 | PA76: 0.29 | PB76: 0.29 | PC76: 0.29 | PD76: 0.29 | PF76: 0.29 | PG76: 0.29 | PH76: 0.29 | PI76: 0.29 | PJ76: 0.29 | PK76: 0.29 | PM76: 0.29 | PN76: 0.29 | PO76: 0.29 | PP76: 0.29 | PQ76: 0.29 | PR76: 0.29 | PT76: 0.29 | PY76: 0.39 | QA76: 0.39 | QB76: 0.39 | QC76: 0.39 | QD76: 0.39 | QE76: 0.39 | QF76: 0.39 | QH76: 0.39 | QI76: 0.39 | QJ76: 0.39 | QK76: 0.39 | QL76: 0.39 | QM76: 0.39 | QO76: 0.39 | QP76: 0.39 | QQ76: 0.39 | QR76: 0.39 | QS76: 0.39 | QT76: 0.39 | QV76: 0.39 | QW76: 0.39 | QX76: 0.39 | QY76: 0.39 | QZ76: 0.39 | RA76: 0.39 | RC76: 0.39 | RD76: 0.39 | RE76: 0.39 | RF76: 0.39 | RG76: 0.39 | RH76: 0.39 | RJ76: 0.39 | RK76: 0.39 | RL76: 0.39 | RM76: 0.39 | RN76: 0.39 | RO76: 0.39 | RQ76: 0.39 | RR76: 0.39 | RS76: 0.39 | RT76: 0.39 | RU76: 0.39 | RV76: 0.39 | RX76: 0.39 | RY76: 0.39 | RZ76: 0.39 | SA76: 0.39 | SB76: 0.39 | SC76: 0.29 | TD76: 1.1 | TE76: 4.4 | TG76: 4.4 | TH76: 4.4 | TI76: 4.76 | TJ76: 5.86 | TK76: 9.28 | TL76: 19.54 | TN76: 19.54 | TO76: 16.12 | TP76: 5.86 | TQ76: 4.4 | TW76: 1.47 | TX76: 5.86 | TY76: 5.86 | TZ76: 4.4 | YT76: 0.55 | YU76: 2.19 | YV76: 2.19 | YX76: 2.19 | YY76: 2.19 | YZ76: 2.19 | ZA76: 2.19 | ZB76: 2.19 | ZC76: 1.64
A77: Pot Wash out valve with dia (160) mm | E77: 2 | F77: 0.06 | G77: 6200 | I77: =F77 -> 0.06 | AF77: 0.01 | AG77: 0.01 | AH77: 0.01 | AK77: 0.01 | AL77: 0.01 | AM77: 0.01 | AN77: 0.01 | AO77: 0.01 | NN77: 0 | NP77: 0 | NQ77: 0 | NR77: 0 | NS77: 0 | NT77: 0 | NU77: 0 | NW77: 0 | NX77: 0 | NY77: 0 | NZ77: 0 | OA77: 0 | OB77: 0 | OD77: 0 | OE77: 0 | OF77: 0 | OG77: 0 | OH77: 0 | OI77: 0 | OL77: 0 | OM77: 0 | ON77: 0 | OO77: 0 | OP77: 0 | OR77: 0 | OS77: 0 | OT77: 0 | OU77: 0 | OV77: 0 | OW77: 0 | OY77: 0 | OZ77: 0 | PA77: 0 | PB77: 0 | PC77: 0 | PD77: 0 | PF77: 0 | PG77: 0 | PH77: 0 | PI77: 0 | PJ77: 0 | PK77: 0 | PM77: 0 | PN77: 0 | PO77: 0 | PP77: 0 | PQ77: 0 | PR77: 0 | PT77: 0 | PY77: 0 | QA77: 0 | QB77: 0 | QC77: 0 | QD77: 0 | QE77: 0 | QF77: 0 | QH77: 0 | QI77: 0 | QJ77: 0 | QK77: 0 | QL77: 0 | QM77: 0.04 | QO77: 0.1 | QP77: 0 | QQ77: 0 | QR77: 0 | QS77: 0 | QT77: 0.02 | QV77: 0.05 | QW77: 0.05 | QX77: 0.05 | QY77: 0.05 | QZ77: 0.05 | RA77: 0.05 | RC77: 0.05 | RD77: 0.05 | RE77: 0.05 | RF77: 0.05 | RG77: 0.05 | RH77: 0.04 | RJ77: 0.03 | RK77: 0.03 | RL77: 0.03 | RM77: 0.03 | RN77: 0.03 | RO77: 0.05 | RQ77: 0.14 | RR77: 0.14 | RS77: 0.14 | RT77: 0.1 | RU77: 0 | RV77: 0 | RX77: 0 | RY77: 0 | RZ77: 0 | SA77: 0 | SB77: 0 | SC77: 0 | SE77: 0 | SF77: 0 | SG77: 0 | SH77: 0 | SI77: 0 | SJ77: 0 | SP77: 0 | SQ77: 0 | SS77: 0 | YT77: 0.01 | YU77: 0.03 | YV77: 0.03 | YX77: 0.03 | YY77: 0.03 | YZ77: 0.03 | ZA77: 0.03 | ZB77: 0.03 | ZC77: 0.02
A78: Pot Wash out valve with dia (200) mm | E78: 1 | F78: 0.03 | G78: 4580 | I78: =F78 -> 0.03 | AF78: 0 | AG78: 0 | AH78: 0 | AK78: 0 | AL78: 0 | AM78: 0 | AN78: 0 | AO78: 0 | NN78: 0 | NP78: 0 | NQ78: 0 | NR78: 0 | NS78: 0 | NT78: 0 | NU78: 0 | NW78: 0 | NX78: 0 | NY78: 0 | NZ78: 0 | OA78: 0 | OB78: 0 | OD78: 0 | OE78: 0 | OF78: 0 | OG78: 0 | OH78: 0 | OI78: 0 | OL78: 0 | OM78: 0 | ON78: 0 | OO78: 0 | OP78: 0 | OR78: 0 | OS78: 0 | OT78: 0 | OU78: 0 | OV78: 0 | OW78: 0 | OY78: 0 | OZ78: 0 | PA78: 0 | PB78: 0 | PC78: 0 | PD78: 0 | PF78: 0 | PG78: 0 | PH78: 0 | PI78: 0 | PJ78: 0 | PK78: 0 | PM78: 0 | PN78: 0 | PO78: 0 | PP78: 0 | PQ78: 0 | PR78: 0 | PT78: 0 | PY78: 0 | QA78: 0 | QB78: 0 | QC78: 0 | QD78: 0 | QE78: 0 | QF78: 0 | QH78: 0 | QI78: 0 | QJ78: 0 | QK78: 0 | QL78: 0 | QM78: 0 | QO78: 0 | QP78: 0 | QQ78: 0 | QR78: 0 | QS78: 0 | QT78: 0 | QV78: 0 | QW78: 0 | QX78: 0 | QY78: 0 | QZ78: 0 | RA78: 0 | RC78: 0 | RD78: 0 | RE78: 0 | RF78: 0 | RG78: 0 | RH78: 0 | RJ78: 0 | RK78: 0 | RL78: 0 | RM78: 0 | RN78: 0 | RO78: 0 | RQ78: 0 | RR78: 0 | RS78: 0 | RT78: 0 | RU78: 0.01 | RV78: 0.04 | RX78: 0.04 | RY78: 0.07 | RZ78: 0.07 | SA78: 0.07 | SB78: 0.06 | SC78: 0.04 | SE78: 0.04 | SF78: 0.07 | SG78: 0.07 | SH78: 0.07 | SI78: 0.05 | SJ78: 0 | SP78: 0 | SQ78: 0 | SS78: 0 | YT78: 0 | YU78: 0.01 | YV78: 0.01 | YX78: 0.01 | YY78: 0.01 | YZ78: 0.01 | ZA78: 0.01 | ZB78: 0.01 | ZC78: 0.01
