Workbook
Name _1B.05.M.010.0010: #REF!
Name _1B.05.M.010.0010: #REF!
Name _1B.05.M.010.0010: #REF!
Name _1B.05.M.010.0010: #REF!
Name _1B.05.M.010.0050: #REF!
Name _1B.05.M.010.0050: #REF!
Name _1B.05.M.010.0050: #REF!
Name _1B.05.M.010.0050: #REF!
Name _1B.05.M.0100.0010: #REF!
Name _1B.05.M.0100.0010: #REF!
Name _1B.05.M.0100.0010: #REF!
Name _1B.05.M.020.0010: #REF!
Name _1B.05.M.020.0010: #REF!
Name _1B.05.M.020.0010: #REF!
Name _1B.05.M.020.0020: #REF!
Name _1B.05.M.020.0020: #REF!
Name _1B.05.M.020.0020: #REF!
Name _1B.05.M.020.0030: #REF!
Name _1B.05.M.020.0030: #REF!
Name _1B.05.M.020.0030: #REF!
Name _1B.05.M.020.0040: #REF!
Name _1B.05.M.020.0040: #REF!
Name _1B.05.M.020.0040: #REF!
Name _1B.05.M.030.0010: #REF!
Name _1B.05.M.030.0010: #REF!
Name _1B.05.M.030.0010: #REF!
Name _1B.05.M.030.0020: #REF!
Name _1B.05.M.030.0020: #REF!
Name _1B.05.M.030.0020: #REF!
Name _1B.05.M.040.0010: #REF!
Name _1B.05.M.040.0010: #REF!
Name _1B.05.M.040.0010: #REF!
Name _1B.05.M.050.0010: #REF!
Name _1B.05.M.050.0010: #REF!
Name _1B.05.M.050.0010: #REF!
Name _1B.05.M.050.0020: #REF!
Name _1B.05.M.050.0020: #REF!
Name _1B.05.M.050.0020: #REF!
Name _1B.05.M.050.0030: #REF!
Name _1B.05.M.050.0030: #REF!
Name _1B.05.M.050.0030: #REF!
Name _1B.05.M.060.0020: #REF!
Name _1B.05.M.060.0020: #REF!
Name _1B.05.M.060.0020: #REF!
Name _1B.05.M.060.0100: #REF!
Name _1B.05.M.060.0100: #REF!
Name _1B.05.M.060.0100: #REF!
Name _1B.05.M.070.0010: #REF!
Name _1B.05.M.070.0010: #REF!
Name _1B.05.M.070.0010: #REF!
Name _1B.05.M.070.0020: #REF!
Name _1B.05.M.070.0020: #REF!
Name _1B.05.M.070.0020: #REF!
Name _1B.05.M.070.0030: #REF!
Name _1B.05.M.070.0030: #REF!
Name _1B.05.M.070.0030: #REF!
Name _1B.05.M.070.0040: #REF!
Name _1B.05.M.070.0040: #REF!
Name _1B.05.M.070.0040: #REF!
Name _1B.05.M.070.0050: #REF!

Sheet DB
A1: ='[47]Weekly Progress Report'!$A$1 -> MODON - Weekly Progress Report - Construction Projects
B2: ='[47]Weekly Progress Report'!$A$2 -> Contract General Information | J2: ='[47]Weekly Progress Report'!G2 -> Key Dates | U2: ='[47]Weekly Progress Report'!$M$2 -> Cost Summary (SR) | AD2: ='[47]Weekly Progress Report'!$U$2 -> Performance Summary | AP2: ='[47]Weekly Progress Report'!A52 -> Shop Drawings | AT2: ='[47]Weekly Progress Report'!A61 -> Material Approval | AW2: ='[47]Weekly Progress Report'!A70 -> Procurement Summary | BD2: ='[47]Weekly Progress Report'!L52 -> Quality Reports | BT2: ='[47]Weekly Progress Report'!L60 -> Key Submittals Approval Status | CD2: ='[47]Weekly Progress Report'!L66 -> Invoices Summary | CR2: ='[47]Weekly Progress Report'!L74 -> Resources at Site | CY2: ='[47]Weekly Progress Report'!W52 -> Safety Statistics | FK2: ='[47]Weekly Progress Report'!A79 -> Primavera P6 Schedule Status | FS2: ='[47]Weekly Progress Report'!A88 -> Weekly Prgoress Photos
A3: ='[47]Weekly Progress Report'!AF1 -> Data Date | B3: ='[47]Weekly Progress Report'!A3 -> Project Name | C3: ='[47]Weekly Progress Report'!A4 -> Project ID | D3: ='[47]Weekly Progress Report'!A5 -> Contractor | E3: ='[47]Weekly Progress Report'!A6 -> Consultant | F3: ='[47]Weekly Progress Report'!D4 -> Stage | G3: ='[47]Weekly Progress Report'!D5 -> Status | H3: ='[47]Weekly Progress Report'!D6 -> Modon PM | I3: ='[47]Weekly Progress Report'!AA2 -> Project Scope | J3: ='[47]Weekly Progress Report'!G3 -> Contract Award | K3: ='[47]Weekly Progress Report'!G4 -> Contract Sign | L3: ='[47]Weekly Progress Report'!G5 -> Site Handover | M3: ='[47]Weekly Progress Report'!G6 -> Original Completion | N3: ='[47]Weekly Progress Report'!$I$3 -> Contract Award (Hijri) | O3: ='[47]Weekly Progress Report'!$I$4 -> Contract Sign (Hijri) | P3: ='[47]Weekly Progress Report'!$I$5 -> Site Handover (Hijri) | Q3: ='[47]Weekly Progress Report'!$I$6 -> Original Completion (Hijri) | R3: ='[47]Weekly Progress Report'!$K$3 -> Revised Completion | S3: ='[47]Weekly Progress Report'!$K$4 -> Committed Completion | T3: ='[47]Weekly Progress Report'!$K$5 -> Forecast Completion | U3: ='[47]Weekly Progress Report'!$M$3 -> Original Contract Value | V3: ='[47]Weekly Progress Report'!$M$4 -> Revised Contract Value | W3: ='[47]Weekly Progress Report'!$M$5 -> Estimate At Completion Value | X3: ='[47]Weekly Progress Report'!$M$6 -> Potential Changes | Y3: ='[47]Weekly Progress Report'!$Q$3 -> O&M Value (if any) | Z3: ='[47]Weekly Progress Report'!$Q$4 -> Submitted Invoices (Gross Value) | AA3: ='[47]Weekly Progress Report'!$Q$5 -> Penalities | AB3: ='[47]Weekly Progress Report'!$Q$6 -> FIR Value (Todate) | AC3: Original Plan Value | AD3: ='[47]Weekly Progress Report'!$U$3 -> Plan Value | AE3: ='[47]Weekly Progress Report'!$U$4 -> Earn Value | AF3: ='[47]Weekly Progress Report'!$W$3 -> Phys. Plan Value | AG3: ='[47]Weekly Progress Report'!$W$4 -> Phys. Earn Value | AH3: ='[47]Weekly Progress Report'!$Y$3 -> Quality Score | AI3: ='[47]Weekly Progress Report'!$Y$5 -> Safety Score | AJ3: Weekly PV (SAR) | AK3: Weekly EV (SAR) | AL3: Weekly PV % | AM3: Weekly PV % | AN3: Weekly Phys PV% | AO3: Weekly Phys PV% | AP3: Total SD Planned | AQ3: SD Remaining | AR3: SD Pending | AS3: Total SD Submittals | AT3: Planned Materials Approv | AU3: Material Pending Approval | AV3: Materila Total Submittals | AW3: ='[47]Weekly Progress Report'!C71 -> Total Materials | AX3: ='[47]Weekly Progress Report'!D71 -> Total Number of P.O. | AY3: ='[47]Weekly Progress Report'!E71 -> Actual P.O. To Date | AZ3: ='[47]Weekly Progress Report'!F71 -> Remaining P.O | BA3: ='[47]Weekly Progress Report'!G71 -> Material on Site | BB3: ='[47]Weekly Progress Report'!H71 -> Remaining Materials | BC3: ='[47]Weekly Progress Report'!I71 -> Material Delivery Completion (Date) | BD3: ="NCR "&'[47]Weekly Progress Report'!N53 -> NCR Issued | BE3: ="NCR "&'[47]Weekly Progress Report'!O53 -> NCR Closed | BF3: ="NCR "&'[47]Weekly Progress Report'!P53 -> NCR Pending | BG3: ="NCR "&'[47]Weekly Progress Report'!Q53 -> NCR Avg. Closing (Days) | BH3: ="SIR "&'[47]Weekly Progress Report'!N53 -> SIR Issued | BI3: ="SIR "&'[47]Weekly Progress Report'!O53 -> SIR Closed | BJ3: ="SIR "&'[47]Weekly Progress Report'!P53 -> SIR Pending | BK3: ="SIR "&'[47]Weekly Progress Report'!Q53 -> SIR Avg. Closing (Days) | BL3: ="MIR "&'[47]Weekly Progress Report'!N53 -> MIR Issued | BM3: ="MIR "&'[47]Weekly Progress Report'!O53 -> MIR Closed | BN3: ="MIR "&'[47]Weekly Progress Report'!P53 -> MIR Pending | BO3: ="MIR "&'[47]Weekly Progress Report'!Q53 -> MIR Avg. Closing (Days) | BP3: ="FIR "&'[47]Weekly Progress Report'!N53 -> FIR Issued | BQ3: ="FIR "&'[47]Weekly Progress Report'!O53 -> FIR Closed | BR3: ="FIR "&'[47]Weekly Progress Report'!P53 -> FIR Pending | BS3: ="FIR "&'[47]Weekly Progress Report'!Q53 -> FIR Avg. Closing (Days) | BT3: ='[47]Weekly Progress Report'!L61 -> 1 Quality Plan Approval | BU3: ='[47]Weekly Progress Report'!L62 -> 2 Quality Plan Last Up | BV3: ='[47]Weekly Progress Report'!L63 -> 3 Safety Plan Approval | BW3: ='[47]Weekly Progress Report'!L64 -> 4 Safety Plan Last Up | BX3: ='[47]Weekly Progress Report'!L65 -> 5 Construction Plan Approval | BY3: ='[47]Weekly Progress Report'!Q61 -> 6 Baseline Approval | BZ3: ='[47]Weekly Progress Report'!Q62 -> 7 No of Approved Version of Schedule | CA3: ='[47]Weekly Progress Report'!Q63 -> 8 Last Approved Schedule | CB3: ='[47]Weekly Progress Report'!Q64 -> 9 BOQ Approval Date | CC3: ='[47]Weekly Progress Report'!Q65 -> 10 No of Approved Version of BOQ | CD3: ='[47]Weekly Progress Report'!L67 -> Total Submitted Invoices | CE3: ='[47]Weekly Progress Report'!L68 -> PM Approved Invoices | CF3: ='[47]Weekly Progress Report'!L69 -> No of Paid Invoices | CG3: ='[47]Weekly Progress Report'!L70 -> No of Pending Invoices | CH3: ='[47]Weekly Progress Report'!L71 -> Advance Payment % | CI3: ='[47]Weekly Progress Report'!L72 -> Retention % | CJ3: ='[47]Weekly Progress Report'!L73 -> Deduction / Penalties % | CK3: ='[47]Weekly Progress Report'!O67 -> Submitted Invoices (SAR) | CL3: ='[47]Weekly Progress Report'!O68 -> PM Approved Invoices (SAR) | CM3: ='[47]Weekly Progress Report'!O69 -> Paid Invoices (SAR) | CN3: ='[47]Weekly Progress Report'!O70 -> Last Submitted Period | CO3: ='[47]Weekly Progress Report'!O71 -> Advance Payment (SAR) | CP3: ='[47]Weekly Progress Report'!O72 -> Retention (SAR) | CQ3: ='[47]Weekly Progress Report'!O73 -> Deduction / Penalties (SAR) | CR3: Planned Head Count | CS3: Actual Head Count | CT3: Saudi Staff | CU3: Labor Planned | CV3: Labor Actual | CW3: Equipment Planned | CX3: Equipment Actual | CY3: ="This Week "&'[47]Weekly Progress Report'!X55 -> This Week Total Hours Worked | CZ3: ="This Week "&'[47]Weekly Progress Report'!X56 -> This Week Safe Hours Worked | DA3: ="This Week "&'[47]Weekly Progress Report'!X57 -> This Week LTI | DB3: ="This Week "&'[47]Weekly Progress Report'!X58 -> This Week MTC (Healed w/o Disability) | DC3: ="This Week "&'[47]Weekly Progress Report'!X59 -> This Week MTC (Healed w/ Disability) | DD3: ="This Week "&'[47]Weekly Progress Report'!X60 -> This Week Near Miss | DE3: ="This Week "&'[47]Weekly Progress Report'!X61 -> This Week First Aid Cases | DF3: ="This Week "&'[47]Weekly Progress Report'!X62 -> This Week Fatality | DG3: ="This Week "&'[47]Weekly Progress Report'!X63 -> This Week Fire Incident Cases | DH3: ="This Week "&'[47]Weekly Progress Report'!X64 -> This Week Vehicle Incident | DI3: ="This Week "&'[47]Weekly Progress Report'!X65 -> This Week Property Damages | DJ3: ="This Week "&'[47]Weekly Progress Report'!X66 -> This Week Induction Training | DK3: ="This Week "&'[47]Weekly Progress Report'!X67 -> This Week No.of Internal Training | DL3: ="This Week "&'[47]Weekly Progress Report'!X68 -> This Week No.of Internal Audit | DM3: ="This Week "&'[47]Weekly Progress Report'!X69 -> This Week No. of Toolbox Talks | DN3: ="This Week "&'[47]Weekly Progress Report'!X70 -> This Week Safety Awards/Incentives | DO3: ="This Month "&'[47]Weekly Progress Report'!X55 -> This Month Total Hours Worked | DP3: ="This Month "&'[47]Weekly Progress Report'!X56 -> This Month Safe Hours Worked | DQ3: ="This Month "&'[47]Weekly Progress Report'!X57 -> This Month LTI | DR3: ="This Month "&'[47]Weekly Progress Report'!X58 -> This Month MTC (Healed w/o Disability) | DS3: ="This Month "&'[47]Weekly Progress Report'!X59 -> This Month MTC (Healed w/ Disability) | DT3: ="This Month "&'[47]Weekly Progress Report'!X60 -> This Month Near Miss | DU3: ="This Month "&'[47]Weekly Progress Report'!X61 -> This Month First Aid Cases | DV3: ="This Month "&'[47]Weekly Progress Report'!X62 -> This Month Fatality | DW3: ="This Month "&'[47]Weekly Progress Report'!X63 -> This Month Fire Incident Cases | DX3: ="This Month "&'[47]Weekly Progress Report'!X64 -> This Month Vehicle Incident | DY3: ="This Month "&'[47]Weekly Progress Report'!X65 -> This Month Property Damages | DZ3: ="This Month "&'[47]Weekly Progress Report'!X66 -> This Month Induction Training | EA3: ="This Month "&'[47]Weekly Progress Report'!X67 -> This Month No.of Internal Training | EB3: ="This Month "&'[47]Weekly Progress Report'!X68 -> This Month No.of Internal Audit | EC3: ="This Month "&'[47]Weekly Progress Report'!X69 -> This Month No. of Toolbox Talks | ED3: ="This Month "&'[47]Weekly Progress Report'!X70 -> This Month Safety Awards/Incentives | EE3: ="YTD "&'[47]Weekly Progress Report'!X55 -> YTD Total Hours Worked | EF3: ="YTD "&'[47]Weekly Progress Report'!X56 -> YTD Safe Hours Worked | EG3: ="YTD "&'[47]Weekly Progress Report'!X57 -> YTD LTI | EH3: ="YTD "&'[47]Weekly Progress Report'!X58 -> YTD MTC (Healed w/o Disability) | EI3: ="YTD "&'[47]Weekly Progress Report'!X59 -> YTD MTC (Healed w/ Disability) | EJ3: ="YTD "&'[47]Weekly Progress Report'!X60 -> YTD Near Miss | EK3: ="YTD "&'[47]Weekly Progress Report'!X61 -> YTD First Aid Cases | EL3: ="YTD "&'[47]Weekly Progress Report'!X62 -> YTD Fatality | EM3: ="YTD "&'[47]Weekly Progress Report'!X63 -> YTD Fire Incident Cases | EN3: ="YTD "&'[47]Weekly Progress Report'!X64 -> YTD Vehicle Incident | EO3: ="YTD "&'[47]Weekly Progress Report'!X65 -> YTD Property Damages | EP3: ="YTD "&'[47]Weekly Progress Report'!X66 -> YTD Induction Training | EQ3: ="YTD "&'[47]Weekly Progress Report'!X67 -> YTD No.of Internal Training | ER3: ="YTD "&'[47]Weekly Progress Report'!X68 -> YTD No.of Internal Audit | ES3: ="YTD "&'[47]Weekly Progress Report'!X69 -> YTD No. of Toolbox Talks | ET3: ="YTD "&'[47]Weekly Progress Report'!X70 -> YTD Safety Awards/Incentives | EU3: ="Cum "&'[47]Weekly Progress Report'!X55 -> Cum Total Hours Worked | EV3: ="Cum "&'[47]Weekly Progress Report'!X56 -> Cum Safe Hours Worked | EW3: ="Cum "&'[47]Weekly Progress Report'!X57 -> Cum LTI | EX3: ="Cum "&'[47]Weekly Progress Report'!X58 -> Cum MTC (Healed w/o Disability) | EY3: ="Cum "&'[47]Weekly Progress Report'!X59 -> Cum MTC (Healed w/ Disability) | EZ3: ="Cum "&'[47]Weekly Progress Report'!X60 -> Cum Near Miss | FA3: ="Cum "&'[47]Weekly Progress Report'!X61 -> Cum First Aid Cases | FB3: ="Cum "&'[47]Weekly Progress Report'!X62 -> Cum Fatality | FC3: ="Cum "&'[47]Weekly Progress Report'!X63 -> Cum Fire Incident Cases | FD3: ="Cum "&'[47]Weekly Progress Report'!X64 -> Cum Vehicle Incident | FE3: ="Cum "&'[47]Weekly Progress Report'!X65 -> Cum Property Damages | FF3: ="Cum "&'[47]Weekly Progress Report'!X66 -> Cum Induction Training | FG3: ="Cum "&'[47]Weekly Progress Report'!X67 -> Cum No.of Internal Training | FH3: ="Cum "&'[47]Weekly Progress Report'!X68 -> Cum No.of Internal Audit | FI3: ="Cum "&'[47]Weekly Progress Report'!X69 -> Cum No. of Toolbox Talks | FJ3: ="Cum "&'[47]Weekly Progress Report'!X70 -> Cum Safety Awards/Incentives | FK3: ='[47]Weekly Progress Report'!A82 -> Total Act. | FL3: ='[47]Weekly Progress Report'!B82 -> Not Started | FM3: ='[47]Weekly Progress Report'!C82 -> In Progress | FN3: ='[47]Weekly Progress Report'!D82 -> Completed | FO3: Critical Path Act.Last Week | FP3: Critical Path Act.This Week | FQ3: Failed start Last Week | FR3: Failed start This Week | FS3: ='[47]Weekly Progress Report'!B90 -> 0 | FT3: ='[47]Weekly Progress Report'!D90 -> 0 | FU3: ='[47]Weekly Progress Report'!F90 -> 0 | FV3: ='[47]Weekly Progress Report'!H90 -> 0 | FW3: ='[47]Weekly Progress Report'!J90 -> 0 | FX3: ='[47]Weekly Progress Report'!L90 -> 0 | FY3: ='[47]Weekly Progress Report'!N90 -> 0 | FZ3: ='[47]Weekly Progress Report'!O90 -> 0 | GA3: ='[47]Weekly Progress Report'!P90 -> 0
A4: ='[47]Weekly Progress Report'!AG1 -> 45503 | B4: ='[47]Weekly Progress Report'!B3 -> Hail - Developing of Infrastructure Hail industrial city PHASE II - Eastern side Project | C4: ='[47]Weekly Progress Report'!B4 -> HAL1-02-005 | D4: ='[47]Weekly Progress Report'!B5 -> Shibh Aljazira Contracting Company | E4: ='[47]Weekly Progress Report'!B6 -> JASARA Program Managemant Company | F4: ='[47]Weekly Progress Report'!E4 -> Construction | G4: ='[47]Weekly Progress Report'!E5 -> Active | H4: ='[47]Weekly Progress Report'!E6 -> Abdulaziz M. Al-Musallam | I4: ='[47]Weekly Progress Report'!AA3 -> The project consists of the POND A which works as a downstream for the storm water wet utility piping network including manholes and catch basins, continued project wet utilities also sewerage GRP piping network with manholes, potable water and firefighting compound HDPE piping network including the installation of valves and fire hydrants and the irrigation water (TSE) network with all valves and the flow meter, dry utility represented in electrical road lighting network - the installation of poles and the LV cables which is connected to the panel board and the 13.8/0.4 K V unit substation. | J4: ='[47]Weekly Progress Report'!H3 -> 45186 | K4: ='[47]Weekly Progress Report'!H4 -> 45280 | L4: ='[47]Weekly Progress Report'!H5 -> 45298 | M4: ='[47]Weekly Progress Report'!H6 -> 46028 | N4: ='[47]Weekly Progress Report'!$J$3 -> 45186 | O4: ='[47]Weekly Progress Report'!$J$4 -> 45280 | P4: ='[47]Weekly Progress Report'!$J$5 -> 45298 | Q4: ='[47]Weekly Progress Report'!$J$6 -> 46028 | R4: ='[47]Weekly Progress Report'!$L$3 -> 46028 | S4: ='[47]Weekly Progress Report'!$L$4 -> 46028 | T4: ='[47]Weekly Progress Report'!$L$5 -> 46051 | U4: ='[47]Weekly Progress Report'!$O$3 -> 45093675 | V4: ='[47]Weekly Progress Report'!$O$4 -> 45093675 | W4: ='[47]Weekly Progress Report'!$O$5 -> 45093675 | X4: ='[47]Weekly Progress Report'!$O$6 -> 0 | Y4: ='[47]Weekly Progress Report'!$S$3 -> 0 | Z4: ='[47]Weekly Progress Report'!$S$4 -> 5707774.5 | AA4: ='[47]Weekly Progress Report'!$S$5 -> -579777.45 | AB4: ='[47]Weekly Progress Report'!$S$6 -> 450291.6 | AC4: ='[47]Weekly Progress Report'!$J$22 -> 0.16837174 | AD4: ='[47]Weekly Progress Report'!$V$3 -> 0.16837174 | AE4: ='[47]Weekly Progress Report'!$V$4 -> 0.32293379 | AF4: ='[47]Weekly Progress Report'!$X$3 -> 0.18753642 | AG4: ='[47]Weekly Progress Report'!$X$4 -> 0.29839637 | AH4: ='[47]Weekly Progress Report'!$Z$3 -> 0.9087931 | AI4: ='[47]Weekly Progress Report'!$Z$5 -> 0.875 | AJ4: ='[47]Weekly Progress Report'!$E$22 -> 480506.96 | AK4: ='[47]Weekly Progress Report'!$F$22 -> 439683.4 | AL4: =AJ4/V4 -> 0.010655751 | AM4: =AK4/V4 -> 0.009750445 | AN4: ='[47]Weekly Progress Report'!S22 -> 0.010957581 | AO4: ='[47]Weekly Progress Report'!T22 -> 0.014106639 | AP4: ='[47]Weekly Progress Report'!C60 -> 85 | AQ4: ='[47]Weekly Progress Report'!I60 -> 6 | AR4: ='[47]Weekly Progress Report'!J60 -> 0 | AS4: ='[47]Weekly Progress Report'!K60 -> 79 | AT4: ='[47]Weekly Progress Report'!C69 -> 102 | AU4: ='[47]Weekly Progress Report'!J69 -> 1 | AV4: ='[47]Weekly Progress Report'!K69 -> 39 | AW4: ='[47]Weekly Progress Report'!C78 -> 31 | AX4: ='[47]Weekly Progress Report'!D78 -> 28 | AY4: ='[47]Weekly Progress Report'!E78 -> 5 | AZ4: ='[47]Weekly Progress Report'!F78 -> 23 | BA4: ='[47]Weekly Progress Report'!G78 -> 4 | BB4: ='[47]Weekly Progress Report'!H78 -> 27 | BC4: ='[47]Weekly Progress Report'!I78 -> 45533 | BD4: ='[47]Weekly Progress Report'!N56 -> 3 | BE4: ='[47]Weekly Progress Report'!O56 -> 3 | BF4: ='[47]Weekly Progress Report'!P56 -> 0 | BG4: ='[47]Weekly Progress Report'!Q56 -> 0 | BH4: ='[47]Weekly Progress Report'!N57 -> 3 | BI4: ='[47]Weekly Progress Report'!O57 -> 3 | BJ4: ='[47]Weekly Progress Report'!P57 -> 0 | BK4: ='[47]Weekly Progress Report'!Q57 -> 0 | BL4: ='[47]Weekly Progress Report'!N58 -> 30 | BM4: ='[47]Weekly Progress Report'!O58 -> 29 | BN4: ='[47]Weekly Progress Report'!P58 -> 1 | BO4: ='[47]Weekly Progress Report'!Q58 -> 0 | BP4: ='[47]Weekly Progress Report'!N59 -> 489 | BQ4: ='[47]Weekly Progress Report'!O59 -> 460 | BR4: ='[47]Weekly Progress Report'!P59 -> 29 | BS4: ='[47]Weekly Progress Report'!Q59 -> 0 | BT4: ='[47]Weekly Progress Report'!O61 -> 45346 | BU4: ='[47]Weekly Progress Report'!O62 -> 45346 | BV4: ='[47]Weekly Progress Report'!O63 -> 45350 | BW4: ='[47]Weekly Progress Report'!O64 -> 45350 | BX4: ='[47]Weekly Progress Report'!O65 -> 45348 | BY4: ='[47]Weekly Progress Report'!U61 -> 45361 | BZ4: ='[47]Weekly Progress Report'!U62 -> 1 | CA4: ='[47]Weekly Progress Report'!U63 -> 45361 | CB4: ='[47]Weekly Progress Report'!U64 -> 0 | CC4: ='[47]Weekly Progress Report'!U65 -> 1 | CD4: ='[47]Weekly Progress Report'!N67 -> 4 | CE4: ='[47]Weekly Progress Report'!N68 -> 0 | CF4: ='[47]Weekly Progress Report'!N69 -> 0 | CG4: ='[47]Weekly Progress Report'!N70 -> 0 | CH4: ='[47]Weekly Progress Report'!N71 -> 0.1 | CI4: ='[47]Weekly Progress Report'!N72 -> 0 | CJ4: ='[47]Weekly Progress Report'!N73 -> 0.00019958453 | CK4: ='[47]Weekly Progress Report'!R67 -> 5707774.5 | CL4: ='[47]Weekly Progress Report'!R68 -> 0 | CM4: ='[47]Weekly Progress Report'!R69 -> 0 | CN4: ='[47]Weekly Progress Report'!R70 -> 45473 | CO4: ='[47]Weekly Progress Report'!R71 -> 4509367.5 | CP4: ='[47]Weekly Progress Report'!R72 -> 0 | CQ4: ='[47]Weekly Progress Report'!R73 -> -9000 | CR4: ='[47]Weekly Progress Report'!L77 -> 30 | CS4: ='[47]Weekly Progress Report'!M77 -> 26 | CT4: ='[47]Weekly Progress Report'!O77 -> 4 | CU4: ='[47]Weekly Progress Report'!P77 -> 86 | CV4: ='[47]Weekly Progress Report'!Q77 -> 90 | CW4: ='[47]Weekly Progress Report'!T87 -> 37 | CX4: ='[47]Weekly Progress Report'!U87 -> 45 | CY4: ='[47]Weekly Progress Report'!Z55 -> 5568 | CZ4: ='[47]Weekly Progress Report'!Z56 -> 5568 | DA4: ='[47]Weekly Progress Report'!Z57 -> 0 | DB4: ='[47]Weekly Progress Report'!Z58 -> 0 | DC4: ='[47]Weekly Progress Report'!Z59 -> 0 | DD4: ='[47]Weekly Progress Report'!Z60 -> 0 | DE4: ='[47]Weekly Progress Report'!Z61 -> 0 | DF4: ='[47]Weekly Progress Report'!Z62 -> 0 | DG4: ='[47]Weekly Progress Report'!Z63 -> 0 | DH4: ='[47]Weekly Progress Report'!Z64 -> 0 | DI4: ='[47]Weekly Progress Report'!Z65 -> 0 | DJ4: ='[47]Weekly Progress Report'!Z66 -> 0 | DK4: ='[47]Weekly Progress Report'!Z67 -> 0 | DL4: ='[47]Weekly Progress Report'!Z68 -> 0 | DM4: ='[47]Weekly Progress Report'!Z69 -> 1(50) | DN4: ='[47]Weekly Progress Report'!Z70 -> 0 | DO4: ='[47]Weekly Progress Report'!AB55 -> 26288 | DP4: ='[47]Weekly Progress Report'!AB56 -> 26288 | DQ4: ='[47]Weekly Progress Report'!AB57 -> 0 | DR4: ='[47]Weekly Progress Report'!AB58 -> 0 | DS4: ='[47]Weekly Progress Report'!AB59 -> 0 | DT4: ='[47]Weekly Progress Report'!AB60 -> 0 | DU4: ='[47]Weekly Progress Report'!AB61 -> 2 | DV4: ='[47]Weekly Progress Report'!AB62 -> 0 | DW4: ='[47]Weekly Progress Report'!AB63 -> 0 | DX4: ='[47]Weekly Progress Report'!AB64 -> 0 | DY4: ='[47]Weekly Progress Report'!AB65 -> 0 | DZ4: ='[47]Weekly Progress Report'!AB66 -> 22(28) | EA4: ='[47]Weekly Progress Report'!AB67 -> 1 (4) | EB4: ='[47]Weekly Progress Report'!AB68 -> 0 | EC4: ='[47]Weekly Progress Report'!AB69 -> 3(122) | ED4: ='[47]Weekly Progress Report'!AB70 -> 0 | EE4: ='[47]Weekly Progress Report'!AC55 -> 86904 | EF4: ='[47]Weekly Progress Report'!AC56 -> 86904 | EG4: ='[47]Weekly Progress Report'!AC57 -> 0 | EH4: ='[47]Weekly Progress Report'!AC58 -> 0 | EI4: ='[47]Weekly Progress Report'!AC59 -> 0 | EJ4: ='[47]Weekly Progress Report'!AC60 -> 2 | EK4: ='[47]Weekly Progress Report'!AC61 -> 2 | EL4: ='[47]Weekly Progress Report'!AC62 -> 0 | EM4: ='[47]Weekly Progress Report'!AC63 -> 0 | EN4: ='[47]Weekly Progress Report'!AC64 -> 0 | EO4: ='[47]Weekly Progress Report'!AC65 -> 1 | EP4: ='[47]Weekly Progress Report'!AC66 -> 43(106) | EQ4: ='[47]Weekly Progress Report'!AC67 -> 8(56) | ER4: ='[47]Weekly Progress Report'!AC68 -> 3 | ES4: ='[47]Weekly Progress Report'!AC69 -> 17(592) | ET4: ='[47]Weekly Progress Report'!AC70 -> 4 | EU4: ='[47]Weekly Progress Report'!AD55 -> 86904 | EV4: ='[47]Weekly Progress Report'!AD56 -> 86904 | EW4: ='[47]Weekly Progress Report'!AD57 -> 0 | EX4: ='[47]Weekly Progress Report'!AD58 -> 0 | EY4: ='[47]Weekly Progress Report'!AD59 -> 0 | EZ4: ='[47]Weekly Progress Report'!AD60 -> 2 | FA4: ='[47]Weekly Progress Report'!AD61 -> 2 | FB4: ='[47]Weekly Progress Report'!AD62 -> 0 | FC4: ='[47]Weekly Progress Report'!AD63 -> 0 | FD4: ='[47]Weekly Progress Report'!AD64 -> 0 | FE4: ='[47]Weekly Progress Report'!AD65 -> 1 | FF4: ='[47]Weekly Progress Report'!AD66 -> 43(106) | FG4: ='[47]Weekly Progress Report'!AD67 -> 8(56) | FH4: ='[47]Weekly Progress Report'!AD68 -> 3 | FI4: ='[47]Weekly Progress Report'!AD69 -> 17(592) | FJ4: ='[47]Weekly Progress Report'!AD70 -> 4 | FK4: ='[47]Weekly Progress Report'!A83 -> 1116 | FL4: ='[47]Weekly Progress Report'!B83 -> 750 | FM4: ='[47]Weekly Progress Report'!C83 -> 167 | FN4: ='[47]Weekly Progress Report'!D83 -> 199 | FO4: ='[47]Weekly Progress Report'!A87 -> 170 | FP4: ='[47]Weekly Progress Report'!B87 -> 149 | FQ4: ='[47]Weekly Progress Report'!H87 -> 27 | FR4: ='[47]Weekly Progress Report'!I87 -> 20 | FS4: ='[47]Weekly Progress Report'!B95 -> 0 | FT4: ='[47]Weekly Progress Report'!D95 -> 0 | FU4: ='[47]Weekly Progress Report'!F95 -> 0 | FV4: ='[47]Weekly Progress Report'!H95 -> 0 | FW4: ='[47]Weekly Progress Report'!J95 -> 0 | FX4: ='[47]Weekly Progress Report'!L95 -> 0 | FY4: ='[47]Weekly Progress Report'!N95 -> 0 | FZ4: ='[47]Weekly Progress Report'!O95 -> 0 | GA4: ='[47]Weekly Progress Report'!P95 -> 0

Sheet Sheet3
A1: ='Weekly Progress Report'!$A$1 -> MODON - Weekly Progress Report - Construction Projects
B2: ='Weekly Progress Report'!$A$2 -> Contract General Information
A3: ='Weekly Progress Report'!AF1 -> Data Date | B3: ='Weekly Progress Report'!A3 -> Project Name | C3: ='Weekly Progress Report'!A4 -> Project ID | D3: ='Weekly Progress Report'!A5 -> Contractor | E3: ='Weekly Progress Report'!A6 -> Consultant | F3: ='Weekly Progress Report'!D4 -> Stage | G3: ='Weekly Progress Report'!D5 -> Status | H3: ='Weekly Progress Report'!D6 -> Modon PM | I3: ='Weekly Progress Report'!AA2 -> Project Scope | J3: ='Weekly Progress Report'!G3 -> Contract Award | K3: ='Weekly Progress Report'!G4 -> Contract Sign | L3: ='Weekly Progress Report'!G5 -> Site Handover | M3: ='Weekly Progress Report'!G6 -> Original Completion | N3: ='Weekly Progress Report'!I3 -> Contract Award (Hijri) | O3: ='Weekly Progress Report'!I4 -> Contract Sign (Hijri) | P3: ='Weekly Progress Report'!I5 -> Site Handover (Hijri) | Q3: ='Weekly Progress Report'!I6 -> Original Completion (Hijri) | R3: ='Weekly Progress Report'!K3 -> Revised Completion | S3: ='Weekly Progress Report'!K4 -> Committed Completion | T3: ='Weekly Progress Report'!K5 -> Forecast Completion | U3: ='Weekly Progress Report'!M3 -> Original Contract Value | V3: ='Weekly Progress Report'!M4 -> Revised Contract Value | W3: ='Weekly Progress Report'!M5 -> Estimate At Completion Value | X3: ='Weekly Progress Report'!M6 -> Potential Changes | Y3: ='Weekly Progress Report'!Q3 -> O&M Value (if any) | Z3: ='Weekly Progress Report'!Q4 -> Submitted Invoices (Gross Value) | AA3: ='Weekly Progress Report'!Q5 -> Penalities | AB3: ='Weekly Progress Report'!Q6 -> FIR Value (Todate) | AC3: Original Plan Value | AD3: ='Weekly Progress Report'!U3 -> Plan Value | AE3: ='Weekly Progress Report'!U4 -> Earn Value | AF3: ='Weekly Progress Report'!W3 -> Phys. Plan Value | AG3: ='Weekly Progress Report'!W4 -> Phys. Earn Value | AH3: ='Weekly Progress Report'!Y3 -> Quality Score | AI3: ='Weekly Progress Report'!Y5 -> Safety Score | AJ3: Weekly PV (SAR) | AK3: Weekly EV (SAR) | AL3: Weekly PV % | AM3: Weekly PV % | AN3: Weekly Phys PV% | AO3: Weekly Phys PV% | AP3: Total SD Planned | AQ3: SD Remaining | AR3: SD Pending | AS3: Total SD Submittals | AT3: Planned Materials Approv | AU3: Material Pending Approval | AV3: Materila Total Submittals | AW3: ='[47]Weekly Progress Report'!C71 -> Total Materials | AX3: ='[47]Weekly Progress Report'!D71 -> Total Number of P.O. | AY3: ='[47]Weekly Progress Report'!E71 -> Actual P.O. To Date | AZ3: ='[47]Weekly Progress Report'!F71 -> Remaining P.O | BA3: ='[47]Weekly Progress Report'!G71 -> Material on Site | BB3: ='[47]Weekly Progress Report'!H71 -> Remaining Materials | BC3: ='[47]Weekly Progress Report'!I71 -> Material Delivery Completion (Date) | BD3: ="NCR "&'[47]Weekly Progress Report'!N53 -> NCR Issued | BE3: ="NCR "&'[47]Weekly Progress Report'!O53 -> NCR Closed | BF3: ="NCR "&'[47]Weekly Progress Report'!P53 -> NCR Pending | BG3: ="NCR "&'[47]Weekly Progress Report'!Q53 -> NCR Avg. Closing (Days) | BH3: ="SIR "&'[47]Weekly Progress Report'!N53 -> SIR Issued | BI3: ="SIR "&'[47]Weekly Progress Report'!O53 -> SIR Closed | BJ3: ="SIR "&'[47]Weekly Progress Report'!P53 -> SIR Pending | BK3: ="SIR "&'[47]Weekly Progress Report'!Q53 -> SIR Avg. Closing (Days) | BL3: ="MIR "&'[47]Weekly Progress Report'!N53 -> MIR Issued | BM3: ="MIR "&'[47]Weekly Progress Report'!O53 -> MIR Closed | BN3: ="MIR "&'[47]Weekly Progress Report'!P53 -> MIR Pending | BO3: ="MIR "&'[47]Weekly Progress Report'!Q53 -> MIR Avg. Closing (Days) | BP3: ="FIR "&'[47]Weekly Progress Report'!N53 -> FIR Issued | BQ3: ="FIR "&'[47]Weekly Progress Report'!O53 -> FIR Closed | BR3: ="FIR "&'[47]Weekly Progress Report'!P53 -> FIR Pending | BS3: ="FIR "&'[47]Weekly Progress Report'!Q53 -> FIR Avg. Closing (Days) | BT3: ='[47]Weekly Progress Report'!L61 -> 1 Quality Plan Approval | BU3: ='[47]Weekly Progress Report'!L62 -> 2 Quality Plan Last Up | BV3: ='[47]Weekly Progress Report'!L63 -> 3 Safety Plan Approval | BW3: ='[47]Weekly Progress Report'!L64 -> 4 Safety Plan Last Up | BX3: ='[47]Weekly Progress Report'!L65 -> 5 Construction Plan Approval | BY3: ='[47]Weekly Progress Report'!Q61 -> 6 Baseline Approval | BZ3: ='[47]Weekly Progress Report'!Q62 -> 7 No of Approved Version of Schedule | CA3: ='[47]Weekly Progress Report'!Q63 -> 8 Last Approved Schedule | CB3: ='[47]Weekly Progress Report'!Q64 -> 9 BOQ Approval Date | CC3: ='[47]Weekly Progress Report'!Q65 -> 10 No of Approved Version of BOQ | CD3: ='[47]Weekly Progress Report'!L67 -> Total Submitted Invoices | CE3: ='[47]Weekly Progress Report'!L68 -> PM Approved Invoices | CF3: ='[47]Weekly Progress Report'!L69 -> No of Paid Invoices | CG3: ='[47]Weekly Progress Report'!L70 -> No of Pending Invoices | CH3: ='[47]Weekly Progress Report'!L71 -> Advance Payment % | CI3: ='[47]Weekly Progress Report'!L72 -> Retention % | CJ3: ='[47]Weekly Progress Report'!L73 -> Deduction / Penalties % | CK3: ='[47]Weekly Progress Report'!O67 -> Submitted Invoices (SAR) | CL3: ='[47]Weekly Progress Report'!O68 -> PM Approved Invoices (SAR) | CM3: ='[47]Weekly Progress Report'!O69 -> Paid Invoices (SAR) | CN3: ='[47]Weekly Progress Report'!O70 -> Last Submitted Period | CO3: ='[47]Weekly Progress Report'!O71 -> Advance Payment (SAR) | CP3: ='[47]Weekly Progress Report'!O72 -> Retention (SAR) | CQ3: ='[47]Weekly Progress Report'!O73 -> Deduction / Penalties (SAR) | CR3: Planned Head Count | CS3: Actual Head Count | CT3: Saudi Staff | CU3: Labor Planned | CV3: Labor Actual | CW3: Equipment Planned | CX3: Equipment Actual | CY3: ="This Week "&'[47]Weekly Progress Report'!X55 -> This Week Total Hours Worked | CZ3: ="This Week "&'[47]Weekly Progress Report'!X56 -> This Week Safe Hours Worked | DA3: ="This Week "&'[47]Weekly Progress Report'!X57 -> This Week LTI | DB3: ="This Week "&'[47]Weekly Progress Report'!X58 -> This Week MTC (Healed w/o Disability) | DC3: ="This Week "&'[47]Weekly Progress Report'!X59 -> This Week MTC (Healed w/ Disability) | DD3: ="This Week "&'[47]Weekly Progress Report'!X60 -> This Week Near Miss | DE3: ="This Week "&'[47]Weekly Progress Report'!X61 -> This Week First Aid Cases | DF3: ="This Week "&'[47]Weekly Progress Report'!X62 -> This Week Fatality | DG3: ="This Week "&'[47]Weekly Progress Report'!X63 -> This Week Fire Incident Cases | DH3: ="This Week "&'[47]Weekly Progress Report'!X64 -> This Week Vehicle Incident | DI3: ="This Week "&'[47]Weekly Progress Report'!X65 -> This Week Property Damages | DJ3: ="This Week "&'[47]Weekly Progress Report'!X66 -> This Week Induction Training | DK3: ="This Week "&'[47]Weekly Progress Report'!X67 -> This Week No.of Internal Training | DL3: ="This Week "&'[47]Weekly Progress Report'!X68 -> This Week No.of Internal Audit | DM3: ="This Week "&'[47]Weekly Progress Report'!X69 -> This Week No. of Toolbox Talks | DN3: ="This Week "&'[47]Weekly Progress Report'!X70 -> This Week Safety Awards/Incentives | DO3: ="This Month "&'[47]Weekly Progress Report'!X55 -> This Month Total Hours Worked | DP3: ="This Month "&'[47]Weekly Progress Report'!X56 -> This Month Safe Hours Worked | DQ3: ="This Month "&'[47]Weekly Progress Report'!X57 -> This Month LTI | DR3: ="This Month "&'[47]Weekly Progress Report'!X58 -> This Month MTC (Healed w/o Disability) | DS3: ="This Month "&'[47]Weekly Progress Report'!X59 -> This Month MTC (Healed w/ Disability) | DT3: ="This Month "&'[47]Weekly Progress Report'!X60 -> This Month Near Miss | DU3: ="This Month "&'[47]Weekly Progress Report'!X61 -> This Month First Aid Cases | DV3: ="This Month "&'[47]Weekly Progress Report'!X62 -> This Month Fatality | DW3: ="This Month "&'[47]Weekly Progress Report'!X63 -> This Month Fire Incident Cases | DX3: ="This Month "&'[47]Weekly Progress Report'!X64 -> This Month Vehicle Incident | DY3: ="This Month "&'[47]Weekly Progress Report'!X65 -> This Month Property Damages | DZ3: ="This Month "&'[47]Weekly Progress Report'!X66 -> This Month Induction Training | EA3: ="This Month "&'[47]Weekly Progress Report'!X67 -> This Month No.of Internal Training | EB3: ="This Month "&'[47]Weekly Progress Report'!X68 -> This Month No.of Internal Audit | EC3: ="This Month "&'[47]Weekly Progress Report'!X69 -> This Month No. of Toolbox Talks | ED3: ="This Month "&'[47]Weekly Progress Report'!X70 -> This Month Safety Awards/Incentives | EE3: ="YTD "&'[47]Weekly Progress Report'!X55 -> YTD Total Hours Worked | EF3: ="YTD "&'[47]Weekly Progress Report'!X56 -> YTD Safe Hours Worked | EG3: ="YTD "&'[47]Weekly Progress Report'!X57 -> YTD LTI | EH3: ="YTD "&'[47]Weekly Progress Report'!X58 -> YTD MTC (Healed w/o Disability) | EI3: ="YTD "&'[47]Weekly Progress Report'!X59 -> YTD MTC (Healed w/ Disability) | EJ3: ="YTD "&'[47]Weekly Progress Report'!X60 -> YTD Near Miss | EK3: ="YTD "&'[47]Weekly Progress Report'!X61 -> YTD First Aid Cases | EL3: ="YTD "&'[47]Weekly Progress Report'!X62 -> YTD Fatality | EM3: ="YTD "&'[47]Weekly Progress Report'!X63 -> YTD Fire Incident Cases | EN3: ="YTD "&'[47]Weekly Progress Report'!X64 -> YTD Vehicle Incident | EO3: ="YTD "&'[47]Weekly Progress Report'!X65 -> YTD Property Damages | EP3: ="YTD "&'[47]Weekly Progress Report'!X66 -> YTD Induction Training | EQ3: ="YTD "&'[47]Weekly Progress Report'!X67 -> YTD No.of Internal Training | ER3: ="YTD "&'[47]Weekly Progress Report'!X68 -> YTD No.of Internal Audit | ES3: ="YTD "&'[47]Weekly Progress Report'!X69 -> YTD No. of Toolbox Talks | ET3: ="YTD "&'[47]Weekly Progress Report'!X70 -> YTD Safety Awards/Incentives | EU3: ="Cum "&'[47]Weekly Progress Report'!X55 -> Cum Total Hours Worked | EV3: ="Cum "&'[47]Weekly Progress Report'!X56 -> Cum Safe Hours Worked | EW3: ="Cum "&'[47]Weekly Progress Report'!X57 -> Cum LTI | EX3: ="Cum "&'[47]Weekly Progress Report'!X58 -> Cum MTC (Healed w/o Disability) | EY3: ="Cum "&'[47]Weekly Progress Report'!X59 -> Cum MTC (Healed w/ Disability) | EZ3: ="Cum "&'[47]Weekly Progress Report'!X60 -> Cum Near Miss | FA3: ="Cum "&'[47]Weekly Progress Report'!X61 -> Cum First Aid Cases | FB3: ="Cum "&'[47]Weekly Progress Report'!X62 -> Cum Fatality | FC3: ="Cum "&'[47]Weekly Progress Report'!X63 -> Cum Fire Incident Cases | FD3: ="Cum "&'[47]Weekly Progress Report'!X64 -> Cum Vehicle Incident | FE3: ="Cum "&'[47]Weekly Progress Report'!X65 -> Cum Property Damages | FF3: ="Cum "&'[47]Weekly Progress Report'!X66 -> Cum Induction Training | FG3: ="Cum "&'[47]Weekly Progress Report'!X67 -> Cum No.of Internal Training | FH3: ="Cum "&'[47]Weekly Progress Report'!X68 -> Cum No.of Internal Audit | FI3: ="Cum "&'[47]Weekly Progress Report'!X69 -> Cum No. of Toolbox Talks | FJ3: ="Cum "&'[47]Weekly Progress Report'!X70 -> Cum Safety Awards/Incentives | FK3: ='[47]Weekly Progress Report'!A82 -> Total Act. | FL3: ='[47]Weekly Progress Report'!B82 -> Not Started | FM3: ='[47]Weekly Progress Report'!C82 -> In Progress | FN3: ='[47]Weekly Progress Report'!D82 -> Completed | FO3: Critical Path Act.Last Week | FP3: Critical Path Act.This Week | FQ3: Failed start Last Week | FR3: Failed start This Week | FS3: ='[47]Weekly Progress Report'!B90 -> 0 | FT3: ='[47]Weekly Progress Report'!D90 -> 0 | FU3: ='[47]Weekly Progress Report'!F90 -> 0 | FV3: ='[47]Weekly Progress Report'!H90 -> 0 | FW3: ='[47]Weekly Progress Report'!J90 -> 0 | FX3: ='[47]Weekly Progress Report'!L90 -> 0 | FY3: ='[47]Weekly Progress Report'!N90 -> 0 | FZ3: ='[47]Weekly Progress Report'!O90 -> 0 | GA3: ='[47]Weekly Progress Report'!P90 -> 0
A4: ='Weekly Progress Report'!AG1 -> 46313 | B4: ='Weekly Progress Report'!B3 -> Playgrounds Initiative - Qassim, Hail & Tabuk | C4: ='Weekly Progress Report'!B4 -> MLTX-02-003 | D4: ='Weekly Progress Report'!B5 -> Advanced Construction & Contracting Company | E4: ='Weekly Progress Report'!B6 -> Egis | F4: ='Weekly Progress Report'!E4 -> Construction | G4: ='Weekly Progress Report'!E5 -> Active | H4: ='Weekly Progress Report'!E6 -> Bader Alrowaidan | I4: ='Weekly Progress Report'!AA3 -> Construction of Playgrounds Initiatives at 03 Location(Qassim, Hail, Tabuk). The project includes civil, architectural, electrical, mechanical and landscape works, as well as general site works, according to the plans and technical specifications. | J4: ='Weekly Progress Report'!H3 -> 46028 | K4: ='Weekly Progress Report'!H4 -> 46070 | L4: ='Weekly Progress Report'!H5 -> 46070 | M4: ='Weekly Progress Report'!H6 -> 46372 | N4: ='Weekly Progress Report'!J3 -> 46028 | O4: ='Weekly Progress Report'!J4 -> 46070 | P4: ='Weekly Progress Report'!J5 -> 46070 | Q4: ='Weekly Progress Report'!J6 -> 46372 | R4: ='Weekly Progress Report'!L3 -> 46372 | S4: ='Weekly Progress Report'!L4 -> 46372 | T4: ='Weekly Progress Report'!L5 -> 46425 | U4: ='Weekly Progress Report'!O3 -> 35709993 | V4: ='Weekly Progress Report'!O4 -> 35709993 | W4: ='Weekly Progress Report'!O5 -> 35709993 | X4: ='Weekly Progress Report'!O6 -> 0 | Y4: ='Weekly Progress Report'!S3 -> 0 | Z4: ='Weekly Progress Report'!S4 -> 2317493.3 | AA4: ='Weekly Progress Report'!S5 -> -250749.33 | AB4: ='Weekly Progress Report'!S6 -> 3298582.9 | AC4: ='Weekly Progress Report'!J18 -> 0.80317475 | AD4: ='Weekly Progress Report'!V3 -> 0.80317475 | AE4: ='Weekly Progress Report'!V4 -> 0.69001808 | AF4: ='Weekly Progress Report'!X3 -> 0.8024895 | AG4: ='Weekly Progress Report'!X4 -> 0.74790042 | AH4: ='Weekly Progress Report'!Z3 -> 0.91310345 | AI4: ='Weekly Progress Report'!Z5 -> 0.91304348 | AJ4: ='Weekly Progress Report'!E18 -> 28512896 | AK4: ='Weekly Progress Report'!F18 -> 24528613 | AL4: =AJ4/V4 -> 0.79845707 | AM4: =AK4/V4 -> 0.68688372 | AN4: ='Weekly Progress Report'!S18 -> 0.7194961 | AO4: ='Weekly Progress Report'!T18 -> 0.66946611 | AP4: ='Weekly Progress Report'!C57 -> 393 | AQ4: ='Weekly Progress Report'!I57 -> 0 | AR4: ='Weekly Progress Report'!J57 -> 44 | AS4: ='Weekly Progress Report'!K57 -> 393 | AT4: ='Weekly Progress Report'!C67 -> 141 | AU4: ='Weekly Progress Report'!J67 -> 12 | AV4: ='Weekly Progress Report'!K67 -> 141 | AW4: ='Weekly Progress Report'!C76 -> 57 | AX4: ='Weekly Progress Report'!D76 -> 57 | AY4: ='Weekly Progress Report'!E76 -> 33 | AZ4: ='Weekly Progress Report'!F76 -> 25 | BA4: ='Weekly Progress Report'!G76 -> 8 | BB4: ='Weekly Progress Report'!H76 -> 0 | BC4: ='Weekly Progress Report'!I76 | BD4: ='[47]Weekly Progress Report'!N56 -> 3 | BE4: ='[47]Weekly Progress Report'!O56 -> 3 | BF4: ='[47]Weekly Progress Report'!P56 -> 0 | BG4: ='[47]Weekly Progress Report'!Q56 -> 0 | BH4: ='[47]Weekly Progress Report'!N57 -> 3 | BI4: ='[47]Weekly Progress Report'!O57 -> 3 | BJ4: ='[47]Weekly Progress Report'!P57 -> 0 | BK4: ='[47]Weekly Progress Report'!Q57 -> 0 | BL4: ='[47]Weekly Progress Report'!N58 -> 30 | BM4: ='[47]Weekly Progress Report'!O58 -> 29 | BN4: ='[47]Weekly Progress Report'!P58 -> 1 | BO4: ='[47]Weekly Progress Report'!Q58 -> 0 | BP4: ='[47]Weekly Progress Report'!N59 -> 489 | BQ4: ='[47]Weekly Progress Report'!O59 -> 460 | BR4: ='[47]Weekly Progress Report'!P59 -> 29 | BS4: ='[47]Weekly Progress Report'!Q59 -> 0 | BT4: ='[47]Weekly Progress Report'!O61 -> 45346 | BU4: ='[47]Weekly Progress Report'!O62 -> 45346 | BV4: ='[47]Weekly Progress Report'!O63 -> 45350 | BW4: ='[47]Weekly Progress Report'!O64 -> 45350 | BX4: ='[47]Weekly Progress Report'!O65 -> 45348 | BY4: ='[47]Weekly Progress Report'!U61 -> 45361 | BZ4: ='[47]Weekly Progress Report'!U62 -> 1 | CA4: ='[47]Weekly Progress Report'!U63 -> 45361 | CB4: ='[47]Weekly Progress Report'!U64 -> 0 | CC4: ='[47]Weekly Progress Report'!U65 -> 1 | CD4: ='[47]Weekly Progress Report'!N67 -> 4 | CE4: ='[47]Weekly Progress Report'!N68 -> 0 | CF4: ='[47]Weekly Progress Report'!N69 -> 0 | CG4: ='[47]Weekly Progress Report'!N70 -> 0 | CH4: ='[47]Weekly Progress Report'!N71 -> 0.1 | CI4: ='[47]Weekly Progress Report'!N72 -> 0 | CJ4: ='[47]Weekly Progress Report'!N73 -> 0.00019958453 | CK4: ='[47]Weekly Progress Report'!R67 -> 5707774.5 | CL4: ='[47]Weekly Progress Report'!R68 -> 0 | CM4: ='[47]Weekly Progress Report'!R69 -> 0 | CN4: ='[47]Weekly Progress Report'!R70 -> 45473 | CO4: ='[47]Weekly Progress Report'!R71 -> 4509367.5 | CP4: ='[47]Weekly Progress Report'!R72 -> 0 | CQ4: ='[47]Weekly Progress Report'!R73 -> -9000 | CR4: ='[47]Weekly Progress Report'!L77 -> 30 | CS4: ='[47]Weekly Progress Report'!M77 -> 26 | CT4: ='[47]Weekly Progress Report'!O77 -> 4 | CU4: ='[47]Weekly Progress Report'!P77 -> 86 | CV4: ='[47]Weekly Progress Report'!Q77 -> 90 | CW4: ='[47]Weekly Progress Report'!T87 -> 37 | CX4: ='[47]Weekly Progress Report'!U87 -> 45 | CY4: ='[47]Weekly Progress Report'!Z55 -> 5568 | CZ4: ='[47]Weekly Progress Report'!Z56 -> 5568 | DA4: ='[47]Weekly Progress Report'!Z57 -> 0 | DB4: ='[47]Weekly Progress Report'!Z58 -> 0 | DC4: ='[47]Weekly Progress Report'!Z59 -> 0 | DD4: ='[47]Weekly Progress Report'!Z60 -> 0 | DE4: ='[47]Weekly Progress Report'!Z61 -> 0 | DF4: ='[47]Weekly Progress Report'!Z62 -> 0 | DG4: ='[47]Weekly Progress Report'!Z63 -> 0 | DH4: ='[47]Weekly Progress Report'!Z64 -> 0 | DI4: ='[47]Weekly Progress Report'!Z65 -> 0 | DJ4: ='[47]Weekly Progress Report'!Z66 -> 0 | DK4: ='[47]Weekly Progress Report'!Z67 -> 0 | DL4: ='[47]Weekly Progress Report'!Z68 -> 0 | DM4: ='[47]Weekly Progress Report'!Z69 -> 1(50) | DN4: ='[47]Weekly Progress Report'!Z70 -> 0 | DO4: ='[47]Weekly Progress Report'!AB55 -> 26288 | DP4: ='[47]Weekly Progress Report'!AB56 -> 26288 | DQ4: ='[47]Weekly Progress Report'!AB57 -> 0 | DR4: ='[47]Weekly Progress Report'!AB58 -> 0 | DS4: ='[47]Weekly Progress Report'!AB59 -> 0 | DT4: ='[47]Weekly Progress Report'!AB60 -> 0 | DU4: ='[47]Weekly Progress Report'!AB61 -> 2 | DV4: ='[47]Weekly Progress Report'!AB62 -> 0 | DW4: ='[47]Weekly Progress Report'!AB63 -> 0 | DX4: ='[47]Weekly Progress Report'!AB64 -> 0 | DY4: ='[47]Weekly Progress Report'!AB65 -> 0 | DZ4: ='[47]Weekly Progress Report'!AB66 -> 22(28) | EA4: ='[47]Weekly Progress Report'!AB67 -> 1 (4) | EB4: ='[47]Weekly Progress Report'!AB68 -> 0 | EC4: ='[47]Weekly Progress Report'!AB69 -> 3(122) | ED4: ='[47]Weekly Progress Report'!AB70 -> 0 | EE4: ='[47]Weekly Progress Report'!AC55 -> 86904 | EF4: ='[47]Weekly Progress Report'!AC56 -> 86904 | EG4: ='[47]Weekly Progress Report'!AC57 -> 0 | EH4: ='[47]Weekly Progress Report'!AC58 -> 0 | EI4: ='[47]Weekly Progress Report'!AC59 -> 0 | EJ4: ='[47]Weekly Progress Report'!AC60 -> 2 | EK4: ='[47]Weekly Progress Report'!AC61 -> 2 | EL4: ='[47]Weekly Progress Report'!AC62 -> 0 | EM4: ='[47]Weekly Progress Report'!AC63 -> 0 | EN4: ='[47]Weekly Progress Report'!AC64 -> 0 | EO4: ='[47]Weekly Progress Report'!AC65 -> 1 | EP4: ='[47]Weekly Progress Report'!AC66 -> 43(106) | EQ4: ='[47]Weekly Progress Report'!AC67 -> 8(56) | ER4: ='[47]Weekly Progress Report'!AC68 -> 3 | ES4: ='[47]Weekly Progress Report'!AC69 -> 17(592) | ET4: ='[47]Weekly Progress Report'!AC70 -> 4 | EU4: ='[47]Weekly Progress Report'!AD55 -> 86904 | EV4: ='[47]Weekly Progress Report'!AD56 -> 86904 | EW4: ='[47]Weekly Progress Report'!AD57 -> 0 | EX4: ='[47]Weekly Progress Report'!AD58 -> 0 | EY4: ='[47]Weekly Progress Report'!AD59 -> 0 | EZ4: ='[47]Weekly Progress Report'!AD60 -> 2 | FA4: ='[47]Weekly Progress Report'!AD61 -> 2 | FB4: ='[47]Weekly Progress Report'!AD62 -> 0 | FC4: ='[47]Weekly Progress Report'!AD63 -> 0 | FD4: ='[47]Weekly Progress Report'!AD64 -> 0 | FE4: ='[47]Weekly Progress Report'!AD65 -> 1 | FF4: ='[47]Weekly Progress Report'!AD66 -> 43(106) | FG4: ='[47]Weekly Progress Report'!AD67 -> 8(56) | FH4: ='[47]Weekly Progress Report'!AD68 -> 3 | FI4: ='[47]Weekly Progress Report'!AD69 -> 17(592) | FJ4: ='[47]Weekly Progress Report'!AD70 -> 4 | FK4: ='[47]Weekly Progress Report'!A83 -> 1116 | FL4: ='[47]Weekly Progress Report'!B83 -> 750 | FM4: ='[47]Weekly Progress Report'!C83 -> 167 | FN4: ='[47]Weekly Progress Report'!D83 -> 199 | FO4: ='[47]Weekly Progress Report'!A87 -> 170 | FP4: ='[47]Weekly Progress Report'!B87 -> 149 | FQ4: ='[47]Weekly Progress Report'!H87 -> 27 | FR4: ='[47]Weekly Progress Report'!I87 -> 20 | FS4: ='[47]Weekly Progress Report'!B95 -> 0 | FT4: ='[47]Weekly Progress Report'!D95 -> 0 | FU4: ='[47]Weekly Progress Report'!F95 -> 0 | FV4: ='[47]Weekly Progress Report'!H95 -> 0 | FW4: ='[47]Weekly Progress Report'!J95 -> 0 | FX4: ='[47]Weekly Progress Report'!L95 -> 0 | FY4: ='[47]Weekly Progress Report'!N95 -> 0 | FZ4: ='[47]Weekly Progress Report'!O95 -> 0 | GA4: ='[47]Weekly Progress Report'!P95 -> 0

Sheet Weekly Progress Report
A1: MODON - Weekly Progress Report - Construction Projects | AF1: Data Date | AG1: ='General Information'!M1 -> 46313
A2: Contract General Information | G2: Key Dates | M2: Cost Summary (SR) | U2: Performance Summary | AA2: Project Scope
A3: Project Name | B3: ='General Information'!D3 -> Playgrounds Initiative - Qassim, Hail & Tabuk | G3: Contract Award | H3: ='General Information'!D12 -> 46028 | I3: Contract Award (Hijri) | J3: ='General Information'!D16 -> 46028 | K3: Revised Completion | L3: ='General Information'!D20 -> 46372 | M3: Original Contract Value | O3: ='Invoice Log'!E3 -> 35709993 | Q3: O&M Value (if any) | S3: ='Invoice Log'!I3 -> 0 | T3: EAC | U3: Plan Value | V3: =K18 -> 0.80317475 | W3: Phys. Plan Value | X3: =W18 -> 0.8024895 | Y3: Quality Score | Z3: =Quality!AC10 -> 0.91310345 | AA3: =Progress!B1 -> Construction of Playgrounds Initiatives at 03 Location(Qassim, Hail, Tabuk). The project includes civil, architectural, electrical, mechanical and landscape works, as well as general site works, according to the plans and technical specifications.
A4: Project ID | B4: ='General Information'!D4 -> MLTX-02-003 | D4: Stage | E4: ='General Information'!D7 -> Construction | G4: Contract Sign | H4: ='General Information'!D13 -> 46070 | I4: Contract Sign (Hijri) | J4: ='General Information'!D17 -> 46070 | K4: Committed Completion | L4: ='General Information'!D21 -> 46372 | M4: Revised Contract Value | O4: ='Invoice Log'!E4 -> 35709993 | Q4: Submitted Invoices (Gross Value) | S4: ='Invoice Log'!I5 -> 2317493.3 | T4: EAC | U4: Earn Value | V4: =L18 -> 0.69001808 | W4: Phys. Earn Value | X4: =X18 -> 0.74790042 | Z4: =REPT("¢",IF(INT(+Z3*10)>5,5,INT(+Z3*10)))&REPT("£",IF(INT(+Z3*10)>5,0,5-INT(+Z3*10)))&CHAR(10)&REPT("¢",+IF(INT(+Z3*10)>5,-5+INT(+Z3*10),0))&REPT("£",IF(INT(+Z3*10)>5,10-INT(+Z3*10),5)) -> ¢¢¢¢¢ ¢¢¢¢£
A5: Contractor | B5: ='General Information'!D5 -> Advanced Construction & Contracting Company | D5: Status | E5: ='General Information'!D8 -> Active | G5: Site Handover | H5: ='General Information'!D14 -> 46070 | I5: Site Handover (Hijri) | J5: ='General Information'!D18 -> 46070 | K5: Forecast Completion | L5: ='General Information'!D22 -> 46425 | M5: Estimate At Completion Value | O5: ='Invoice Log'!E5 -> 35709993 | Q5: Penalities | S5: ='Invoice Log'!I6 -> -250749.33 | T5: EAC | U5: Variance | V5: =V4-V3 -> -0.11315666 | W5: Variance | X5: =Y18 -> -0.054589082 | Y5: Safety Score | Z5: ='HSE-Stat'!J23 -> 0.91304348
A6: Consultant | B6: ='General Information'!D6 -> Egis | D6: Modon PM | E6: ='General Information'!D9 -> Bader Alrowaidan | G6: Original Completion | H6: ='General Information'!D15 -> 46372 | I6: Original Completion (Hijri) | J6: ='General Information'!D19 -> 46372 | K6: Variance | L6: ='General Information'!D23 -> -53 | M6: Potential Changes | O6: =O4-O5 -> 0 | Q6: FIR Value (Todate) | S6: ='FIR Summary'!I3 -> 3298582.9 | U6: FIR % | V6: =S6/O4 -> 0.092371423 | W6: Invoiced % | X6: =S4/O4 -> 0.064897613 | Z6: =REPT("¢",IF(INT(+Z5*10)>5,5,INT(+Z5*10)))&REPT("£",IF(INT(+Z5*10)>5,0,5-INT(+Z5*10)))&CHAR(10)&REPT("¢",+IF(INT(+Z5*10)>5,-5+INT(+Z5*10),0))&REPT("£",IF(INT(+Z5*10)>5,10-INT(+Z5*10),5)) -> ¢¢¢¢¢ ¢¢¢¢£
A8: Progress Overview
A9: Earned Value Progress (SAR) | O9: Physical Progress (Effort) | AA9: Earned Value Progress (%)
A10: WBS | C10: BOQ Value (SAR) | D10: % Wt. | E10: Weekly (SAR) | G10: To Date (SAR) | O10: Budgeted | P10: % Wt. | Q10: Weekly Physical Progress | U10: To Date Physical Progress
E11: Planned | F11: Earned | G11: Original Plan | H11: Revised Planned | I11: Earned | J11: Original Plan % | K11: Revised Planned % | L11: Earned % | M11: Variance | N11: SPI | O11: (Manhours) | Q11: Planned | R11: Earned | S11: Plan % | T11: Earned % | U11: Planned | V11: Earned | W11: Plan % | X11: Earned % | Y11: Variance | Z11: SPI
A12: =Progress!A7 -> PROJECT MILESTONE | C12: =Progress!B7 -> 0 | D12: =IF(ISBLANK(C12),"",C12/$C$18) -> 0 | E12: =Progress!D7 -> 0 | F12: =Progress!E7 -> 0 | G12: =Progress!F7 -> 0 | H12: =Progress!G7 -> 0 | I12: =Progress!H7 -> 0 | J12: =IFERROR(IF(ISBLANK(G12),"",G12/C12),0) -> 0 | K12: =IFERROR(IF(ISBLANK(H12),"",H12/C12),0) -> 0 | L12: =IFERROR(IF(ISBLANK(I12),"",I12/C12),0) -> 0 | M12: =IFERROR(L12-K12,"") -> 0 | N12: =IFERROR(L12/K12,"") | O12: =Progress!J7 -> 10000 | P12: =IF(ISBLANK(O12),"",O12/$O$18) -> 0.29994001 | Q12: =Progress!L7 -> 227 | R12: =Progress!M7 -> 885 | S12: =IFERROR(IF(ISBLANK(Q12),"",Q12/O12),0) -> 0.0227 | T12: =IFERROR(IF(ISBLANK(R12),"",R12/O12),0) -> 0.0885 | U12: =Progress!N7 -> 7927 | V12: =Progress!O7 -> 7935 | W12: =IFERROR(IF(ISBLANK(U12),"",U12/O12),0) -> 0.7927 | X12: =IFERROR(IF(ISBLANK(V12),"",V12/O12),0) -> 0.7935 | Y12: =IFERROR(X12-W12,"") -> 0.0008 | Z12: =IFERROR(X12/W12,"") -> 1.0010092
A13: =Progress!A8 -> MOBILIZATION | C13: =Progress!B8 -> 0 | D13: =IF(ISBLANK(C13),"",C13/$C$18) -> 0 | E13: =Progress!D8 -> 0 | F13: =Progress!E8 -> 0 | G13: =Progress!F8 -> 0 | H13: =Progress!G8 -> 0 | I13: =Progress!H8 -> 0 | J13: =IFERROR(IF(ISBLANK(G13),"",G13/C13),0) -> 0 | K13: =IFERROR(IF(ISBLANK(H13),"",H13/C13),0) -> 0 | L13: =IFERROR(IF(ISBLANK(I13),"",I13/C13),0) -> 0 | M13: =IFERROR(L13-K13,"") -> 0 | N13: =IFERROR(L13/K13,"") | O13: =Progress!J8 -> 0 | P13: =IF(ISBLANK(O13),"",O13/$O$18) -> 0 | Q13: =Progress!L8 -> 0 | R13: =Progress!M8 -> 0 | S13: =IFERROR(IF(ISBLANK(Q13),"",Q13/O13),0) -> 0 | T13: =IFERROR(IF(ISBLANK(R13),"",R13/O13),0) -> 0 | U13: =Progress!N8 -> 0 | V13: =Progress!O8 -> 0 | W13: =IFERROR(IF(ISBLANK(U13),"",U13/O13),0) -> 0 | X13: =IFERROR(IF(ISBLANK(V13),"",V13/O13),0) -> 0 | Y13: =IFERROR(X13-W13,"") -> 0 | Z13: =IFERROR(X13/W13,"")
A14: =Progress!A9 -> ENGINEERING | C14: =Progress!B9 -> 1071299.8 | D14: =IF(ISBLANK(C14),"",C14/$C$18) -> 0.03 | E14: =Progress!D9 -> 1090347.2 | F14: =Progress!E9 -> 1090347.2 | G14: =Progress!F9 -> 1071299.8 | H14: =Progress!G9 -> 1071299.8 | I14: =Progress!H9 -> 1071299.8 | J14: =IFERROR(IF(ISBLANK(G14),"",G14/C14),0) -> 1 | K14: =IFERROR(IF(ISBLANK(H14),"",H14/C14),0) -> 1 | L14: =IFERROR(IF(ISBLANK(I14),"",I14/C14),0) -> 1 | M14: =IFERROR(L14-K14,"") -> 0 | N14: =IFERROR(L14/K14,"") -> 1 | O14: =Progress!J9 -> 0 | P14: =IF(ISBLANK(O14),"",O14/$O$18) -> 0 | Q14: =Progress!L9 -> 0 | R14: =Progress!M9 -> 0 | S14: =IFERROR(IF(ISBLANK(Q14),"",Q14/O14),0) -> 0 | T14: =IFERROR(IF(ISBLANK(R14),"",R14/O14),0) -> 0 | U14: =Progress!N9 -> 0 | V14: =Progress!O9 -> 0 | W14: =IFERROR(IF(ISBLANK(U14),"",U14/O14),0) -> 0 | X14: =IFERROR(IF(ISBLANK(V14),"",V14/O14),0) -> 0 | Y14: =IFERROR(X14-W14,"") -> 0 | Z14: =IFERROR(X14/W14,"")
A15: =Progress!A19 -> PROCUREMENT | C15: =Progress!B19 -> 9641698.1 | D15: =IF(ISBLANK(C15),"",C15/$C$18) -> 0.27 | E15: =Progress!D19 -> 9813124.6 | F15: =Progress!E19 -> 8945474.8 | G15: =Progress!F19 -> 9641698.1 | H15: =Progress!G19 -> 9641698.1 | I15: =Progress!H19 -> 8769229.7 | J15: =IFERROR(IF(ISBLANK(G15),"",G15/C15),0) -> 1 | K15: =IFERROR(IF(ISBLANK(H15),"",H15/C15),0) -> 1 | L15: =IFERROR(IF(ISBLANK(I15),"",I15/C15),0) -> 0.90951092 | M15: =IFERROR(L15-K15,"") -> -0.090489082 | N15: =IFERROR(L15/K15,"") -> 0.90951092 | O15: =Progress!J19 -> 0 | P15: =IF(ISBLANK(O15),"",O15/$O$18) -> 0 | Q15: =Progress!L19 -> 0 | R15: =Progress!M19 -> 0 | S15: =IFERROR(IF(ISBLANK(Q15),"",Q15/O15),0) -> 0 | T15: =IFERROR(IF(ISBLANK(R15),"",R15/O15),0) -> 0 | U15: =Progress!N19 -> 0 | V15: =Progress!O19 -> 0 | W15: =IFERROR(IF(ISBLANK(U15),"",U15/O15),0) -> 0 | X15: =IFERROR(IF(ISBLANK(V15),"",V15/O15),0) -> 0 | Y15: =IFERROR(X15-W15,"") -> 0 | Z15: =IFERROR(X15/W15,"")
A16: =Progress!A29 -> CONSTRUCTION | C16: =Progress!B29 -> 21425996 | D16: =IF(ISBLANK(C16),"",C16/$C$18) -> 0.6 | E16: =Progress!D29 -> 17500390 | F16: =Progress!E29 -> 13921267 | G16: =Progress!F29 -> 17861237 | H16: =Progress!G29 -> 17861237 | I16: =Progress!H29 -> 14189805 | J16: =IFERROR(IF(ISBLANK(G16),"",G16/C16),0) -> 0.83362458 | K16: =IFERROR(IF(ISBLANK(H16),"",H16/C16),0) -> 0.83362458 | L16: =IFERROR(IF(ISBLANK(I16),"",I16/C16),0) -> 0.6622705 | M16: =IFERROR(L16-K16,"") -> -0.17135408 | N16: =IFERROR(L16/K16,"") -> 0.79444695 | O16: =Progress!J29 -> 22188 | P16: =IF(ISBLANK(O16),"",O16/$O$18) -> 0.6655069 | Q16: =Progress!L29 -> 23717 | R16: =Progress!M29 -> 21229 | S16: =IFERROR(IF(ISBLANK(Q16),"",Q16/O16),0) -> 1.0689111 | T16: =IFERROR(IF(ISBLANK(R16),"",R16/O16),0) -> 0.95677844 | U16: =Progress!N29 -> 18795 | V16: =Progress!O29 -> 16835 | W16: =IFERROR(IF(ISBLANK(U16),"",U16/O16),0) -> 0.8470795 | X16: =IFERROR(IF(ISBLANK(V16),"",V16/O16),0) -> 0.75874346 | Y16: =IFERROR(X16-W16,"") -> -0.088336037 | Z16: =IFERROR(X16/W16,"") -> 0.89571695
A17: =Progress!A41 -> CLOSEOUT | C17: =Progress!B41 -> 3570999.3 | D17: =IF(ISBLANK(C17),"",C17/$C$18) -> 0.1 | E17: =Progress!D41 -> 109034.72 | F17: =Progress!E41 -> 571523.92 | G17: =Progress!F41 -> 107129.98 | H17: =Progress!G41 -> 107129.98 | I17: =Progress!H41 -> 610206.45 | J17: =IFERROR(IF(ISBLANK(G17),"",G17/C17),0) -> 0.03 | K17: =IFERROR(IF(ISBLANK(H17),"",H17/C17),0) -> 0.03 | L17: =IFERROR(IF(ISBLANK(I17),"",I17/C17),0) -> 0.17087834 | M17: =IFERROR(L17-K17,"") -> 0.14087834 | N17: =IFERROR(L17/K17,"") -> 5.6959448 | O17: =Progress!J41 -> 1152 | P17: =IF(ISBLANK(O17),"",O17/$O$18) -> 0.034553089 | Q17: =Progress!L41 -> 44 | R17: =Progress!M41 -> 206 | S17: =IFERROR(IF(ISBLANK(Q17),"",Q17/O17),0) -> 0.038194444 | T17: =IFERROR(IF(ISBLANK(R17),"",R17/O17),0) -> 0.17881944 | U17: =Progress!N41 -> 33 | V17: =Progress!O41 -> 165 | W17: =IFERROR(IF(ISBLANK(U17),"",U17/O17),0) -> 0.028645833 | X17: =IFERROR(IF(ISBLANK(V17),"",V17/O17),0) -> 0.14322917 | Y17: =IFERROR(X17-W17,"") -> 0.11458333 | Z17: =IFERROR(X17/W17,"") -> 5
B18: Total | C18: =SUM(C13:C17) -> 35709993 | D18: =SUM(D13:D17) -> 1 | E18: =SUM(E12:E17) -> 28512896 | F18: =SUM(F12:F17) -> 24528613 | G18: =SUM(G12:G17) -> 28681365 | H18: =SUM(H12:H17) -> 28681365 | I18: =SUM(I12:I17) -> 24640541 | J18: =IFERROR(IF(ISBLANK(G18),"",G18/C18),0) -> 0.80317475 | K18: =IFERROR(IF(ISBLANK(H18),"",H18/C18),0) -> 0.80317475 | L18: =IFERROR(IF(ISBLANK(I18),"",I18/C18),0) -> 0.69001808 | M18: =+L18-K18 -> -0.11315666 | N18: =L18/K18 -> 0.85911327 | O18: =SUM(O12:O17) -> 33340 | P18: =SUM(P12:P17) -> 1 | Q18: =SUM(Q12:Q17) -> 23988 | R18: =SUM(R12:R17) -> 22320 | S18: =IFERROR(IF(ISBLANK(Q18),"",Q18/O18),0) -> 0.7194961 | T18: =IFERROR(IF(ISBLANK(R18),"",R18/O18),0) -> 0.66946611 | U18: =SUM(U12:U17) -> 26755 | V18: =SUM(V12:V17) -> 24935 | W18: =IFERROR(IF(ISBLANK(U18),"",U18/O18),0) -> 0.8024895 | X18: =IFERROR(IF(ISBLANK(V18),"",V18/O18),0) -> 0.74790042 | Y18: =+X18-W18 -> -0.054589082 | Z18: =X18/W18 -> 0.93197533
AA19: Construction Milestones
AA20: Item No. | AB20: Milestones | AD20: Original (Baseline) | AE20: Latest Plan | AF20: Forecast | AG20: Status | AH20: Days Change
AA21: =+Milestones!B5 -> 1 | AB21: =+Milestones!C5 -> Award Date | AD21: =+Milestones!D5 -> 46028 | AE21: =+Milestones!E5 -> 46028 | AF21: =+Milestones!F5 -> 46028 | AG21: =+Milestones!G5 -> A | AH21: =+Milestones!H5 -> 0
AA22: =+Milestones!B6 -> 2 | AB22: =+Milestones!C6 -> Contract Sign Date | AD22: =+Milestones!D6 -> 46070 | AE22: =+Milestones!E6 -> 46070 | AF22: =+Milestones!F6 -> 46070 | AG22: =+Milestones!G6 -> A | AH22: =+Milestones!H6 -> 0
AA23: =+Milestones!B7 -> 3 | AB23: =+Milestones!C7 -> Site Handover Date | AD23: =+Milestones!D7 -> 46070 | AE23: =+Milestones!E7 -> 46070 | AF23: =+Milestones!F7 -> 46070 | AG23: =+Milestones!G7 -> A | AH23: =+Milestones!H7 -> 0
AA24: =+Milestones!B8 -> 4 | AB24: =+Milestones!C8 -> Complete Mobilization | AD24: =+Milestones!D8 -> 46099 | AE24: =+Milestones!E8 -> 46099 | AF24: =+Milestones!F8 -> 46126 | AG24: =+Milestones!G8 -> A | AH24: =+Milestones!H8 -> 0
AA25: =+Milestones!B11 -> 7 | AB25: =+Milestones!C11 -> Complete Construction | AD25: =+Milestones!D11 -> 46370 | AE25: =+Milestones!E11 -> 46370 | AF25: =+Milestones!F11 -> 46410 | AG25: =+Milestones!G11 -> F | AH25: =+Milestones!H11 -> -40
AA26: =+Milestones!B12 -> 8 | AB26: =+Milestones!C12 -> Complete all Works including Testing & Commissioning, Cleanup, Closeout Documentation and Ready for Initial Handover | AD26: =+Milestones!D12 -> 46372 | AE26: =+Milestones!E12 -> 46372 | AF26: =+Milestones!F12 -> 46420 | AG26: =+Milestones!G12 -> F | AH26: =+Milestones!H12 -> -48
AA27: =+Milestones!B13 -> 9 | AB27: =+Milestones!C13 -> Complete Demobilization | AD27: =+Milestones!D13 -> 46372 | AE27: =+Milestones!E13 -> 46372 | AF27: =+Milestones!F13 -> 46424 | AG27: =+Milestones!G13 -> F | AH27: =+Milestones!H13 -> -52
AA28: =+Milestones!B14 -> 10 | AB28: =+Milestones!C14 -> Project Handover | AD28: =+Milestones!D14 -> 46372 | AE28: =+Milestones!E14 -> 46372 | AF28: =+Milestones!F14 -> 46425 | AG28: =+Milestones!G14 -> F | AH28: =+Milestones!H14 -> -53
A46: Performance overview
A47: Submittals Status | L47: Quality | W47: Safety
A48: Shop Drawings | L48: Quality Reports | W48: Safety Statistics | AE48: Proactive Vs Reactive Actions Taken
A49: Item Per WBS | C49: Total | D49: Total Submitted Drawings | I49: Remaining | J49: Pending | K49: Total Submittals | L49: Quality Reports | N49: Issued | O49: Closed | P49: Pending | Q49: Avg. Closing (Days) | R49: Pending | W49: Category | X49: Item | Z49: This Week | AB49: This Month | AC49: Year to Date | AD49: Cumulative
D50: A | E50: B | F50: C | G50: D | H50: Processed | R50: 0-10 Days | S50: 11-20 Days | T50: 21-30 Days | U50: 31-60 Days | V50: > 60 Days
A51: ='Quality-Stat'!A13 -> Architectural | C51: =IF('Quality-Stat'!D13=0,"",'Quality-Stat'!D13) -> 58 | D51: =IF('Quality-Stat'!E13=0,"",'Quality-Stat'!E13) -> 6 | E51: =IF('Quality-Stat'!F13=0,"",'Quality-Stat'!F13) -> 33 | F51: =IF('Quality-Stat'!G13=0,"",'Quality-Stat'!G13) -> 2 | G51: =IF('Quality-Stat'!H13=0,"",'Quality-Stat'!H13) | H51: =IF('Quality-Stat'!I13=0,"",'Quality-Stat'!I13) -> 39 | I51: =IF('Quality-Stat'!J13=0,"",'Quality-Stat'!J13) | J51: =IF('Quality-Stat'!K13=0,"",'Quality-Stat'!K13) -> 17 | K51: =IF('Quality-Stat'!L13=0,"",'Quality-Stat'!L13) -> 58 | W51: General | X51: ='HSE-Stat'!B4 -> Total Hours Worked | Z51: ='HSE-Stat'!D4 -> 8160 | AB51: ='HSE-Stat'!E4 -> 15240 | AC51: ='HSE-Stat'!F4 -> 97870 | AD51: ='HSE-Stat'!G4 -> 97870 | AG51: Proactive | AH51: =+SUM(AD63:AD68) -> 531
A52: ='Quality-Stat'!A14 -> Civil / Structural | C52: =IF('Quality-Stat'!D14=0,"",'Quality-Stat'!D14) -> 84 | D52: =IF('Quality-Stat'!E14=0,"",'Quality-Stat'!E14) | E52: =IF('Quality-Stat'!F14=0,"",'Quality-Stat'!F14) -> 66 | F52: =IF('Quality-Stat'!G14=0,"",'Quality-Stat'!G14) | G52: =IF('Quality-Stat'!H14=0,"",'Quality-Stat'!H14) -> 12 | H52: =IF('Quality-Stat'!I14=0,"",'Quality-Stat'!I14) -> 66 | I52: =IF('Quality-Stat'!J14=0,"",'Quality-Stat'!J14) | J52: =IF('Quality-Stat'!K14=0,"",'Quality-Stat'!K14) -> 6 | K52: =IF('Quality-Stat'!L14=0,"",'Quality-Stat'!L14) -> 84 | L52: Non Conformance (NCR) | N52: =IF('Quality-Stat'!C5=0,"",'Quality-Stat'!C5) -> 17 | O52: =IF('Quality-Stat'!D5=0,"",'Quality-Stat'!D5) -> 7 | P52: =IF('Quality-Stat'!E5=0,"",'Quality-Stat'!E5) -> 10 | Q52: =IF('Quality-Stat'!F5=0,"",'Quality-Stat'!F5) | R52: =IF('Quality-Stat'!G5=0,"",'Quality-Stat'!G5) -> 8 | S52: =IF('Quality-Stat'!H5=0,"",'Quality-Stat'!H5) -> 2 | T52: =IF('Quality-Stat'!I5=0,"",'Quality-Stat'!I5) | U52: =IF('Quality-Stat'!J5=0,"",'Quality-Stat'!J5) | V52: =IF('Quality-Stat'!K5=0,"",'Quality-Stat'!K5) | X52: ='HSE-Stat'!B5 -> Safe Hours Worked | Z52: ='HSE-Stat'!D5 -> 8160 | AB52: ='HSE-Stat'!E5 -> 15240 | AC52: ='HSE-Stat'!F5 -> 97870 | AD52: ='HSE-Stat'!G5 -> 97870 | AG52: Reactive | AH52: =SUM(AD53:AD62) -> 212
A53: ='Quality-Stat'!A15 -> Mechanical | C53: =IF('Quality-Stat'!D15=0,"",'Quality-Stat'!D15) -> 42 | D53: =IF('Quality-Stat'!E15=0,"",'Quality-Stat'!E15) -> 16 | E53: =IF('Quality-Stat'!F15=0,"",'Quality-Stat'!F15) -> 22 | F53: =IF('Quality-Stat'!G15=0,"",'Quality-Stat'!G15) -> 2 | G53: =IF('Quality-Stat'!H15=0,"",'Quality-Stat'!H15) | H53: =IF('Quality-Stat'!I15=0,"",'Quality-Stat'!I15) -> 38 | I53: =IF('Quality-Stat'!J15=0,"",'Quality-Stat'!J15) | J53: =IF('Quality-Stat'!K15=0,"",'Quality-Stat'!K15) -> 2 | K53: =IF('Quality-Stat'!L15=0,"",'Quality-Stat'!L15) -> 42 | L53: Site Instruction (SIR) | N53: =IF('Quality-Stat'!C6=0,"",'Quality-Stat'!C6) -> 7 | O53: =IF('Quality-Stat'!D6=0,"",'Quality-Stat'!D6) -> 6 | P53: =IF('Quality-Stat'!E6=0,"",'Quality-Stat'!E6) -> 1 | Q53: =IF('Quality-Stat'!F6=0,"",'Quality-Stat'!F6) | R53: =IF('Quality-Stat'!G6=0,"",'Quality-Stat'!G6) | S53: =IF('Quality-Stat'!H6=0,"",'Quality-Stat'!H6) | T53: =IF('Quality-Stat'!I6=0,"",'Quality-Stat'!I6) -> 1 | U53: =IF('Quality-Stat'!J6=0,"",'Quality-Stat'!J6) | V53: =IF('Quality-Stat'!K6=0,"",'Quality-Stat'!K6) | W53: Reactive | X53: ='HSE-Stat'!B6 -> LTI | Z53: ='HSE-Stat'!D6 -> 0 | AB53: ='HSE-Stat'!E6 -> 0 | AC53: ='HSE-Stat'!F6 -> 0 | AD53: ='HSE-Stat'!G6 -> 0
A54: ='Quality-Stat'!A16 -> Electrical | C54: =IF('Quality-Stat'!D16=0,"",'Quality-Stat'!D16) -> 98 | D54: =IF('Quality-Stat'!E16=0,"",'Quality-Stat'!E16) -> 4 | E54: =IF('Quality-Stat'!F16=0,"",'Quality-Stat'!F16) -> 43 | F54: =IF('Quality-Stat'!G16=0,"",'Quality-Stat'!G16) -> 12 | G54: =IF('Quality-Stat'!H16=0,"",'Quality-Stat'!H16) -> 22 | H54: =IF('Quality-Stat'!I16=0,"",'Quality-Stat'!I16) -> 47 | I54: =IF('Quality-Stat'!J16=0,"",'Quality-Stat'!J16) | J54: =IF('Quality-Stat'!K16=0,"",'Quality-Stat'!K16) -> 17 | K54: =IF('Quality-Stat'!L16=0,"",'Quality-Stat'!L16) -> 98 | L54: Material Inspection (MIR) | N54: =IF('Quality-Stat'!C7=0,"",'Quality-Stat'!C7) -> 76 | O54: =IF('Quality-Stat'!D7=0,"",'Quality-Stat'!D7) -> 53 | P54: =IF('Quality-Stat'!E7=0,"",'Quality-Stat'!E7) -> 23 | Q54: =IF('Quality-Stat'!F7=0,"",'Quality-Stat'!F7) | R54: =IF('Quality-Stat'!G7=0,"",'Quality-Stat'!G7) -> 20 | S54: =IF('Quality-Stat'!H7=0,"",'Quality-Stat'!H7) -> 3 | T54: =IF('Quality-Stat'!I7=0,"",'Quality-Stat'!I7) | U54: =IF('Quality-Stat'!J7=0,"",'Quality-Stat'!J7) | V54: =IF('Quality-Stat'!K7=0,"",'Quality-Stat'!K7) | X54: ='HSE-Stat'!B7 -> MTC (Healed w/o Disability) | Z54: ='HSE-Stat'!D7 -> 0 | AB54: ='HSE-Stat'!E7 -> 0 | AC54: ='HSE-Stat'!F7 -> 0 | AD54: ='HSE-Stat'!G7 -> 0
A55: ='Quality-Stat'!A17 -> Landscape | C55: =IF('Quality-Stat'!D17=0,"",'Quality-Stat'!D17) -> 69 | D55: =IF('Quality-Stat'!E17=0,"",'Quality-Stat'!E17) -> 4 | E55: =IF('Quality-Stat'!F17=0,"",'Quality-Stat'!F17) -> 59 | F55: =IF('Quality-Stat'!G17=0,"",'Quality-Stat'!G17) -> 1 | G55: =IF('Quality-Stat'!H17=0,"",'Quality-Stat'!H17) -> 3 | H55: =IF('Quality-Stat'!I17=0,"",'Quality-Stat'!I17) -> 63 | I55: =IF('Quality-Stat'!J17=0,"",'Quality-Stat'!J17) | J55: =IF('Quality-Stat'!K17=0,"",'Quality-Stat'!K17) -> 2 | K55: =IF('Quality-Stat'!L17=0,"",'Quality-Stat'!L17) -> 69 | L55: Field Inspection (FIR) | N55: =IF('Quality-Stat'!C8=0,"",'Quality-Stat'!C8) -> 658 | O55: =IF('Quality-Stat'!D8=0,"",'Quality-Stat'!D8) -> 488 | P55: =IF('Quality-Stat'!E8=0,"",'Quality-Stat'!E8) -> 170 | Q55: =IF('Quality-Stat'!F8=0,"",'Quality-Stat'!F8) | R55: =IF('Quality-Stat'!G8=0,"",'Quality-Stat'!G8) -> 140 | S55: =IF('Quality-Stat'!H8=0,"",'Quality-Stat'!H8) -> 15 | T55: =IF('Quality-Stat'!I8=0,"",'Quality-Stat'!I8) -> 15 | U55: =IF('Quality-Stat'!J8=0,"",'Quality-Stat'!J8) | V55: =IF('Quality-Stat'!K8=0,"",'Quality-Stat'!K8) | X55: ='HSE-Stat'!B8 -> MTC (Healed w/ Disability) | Z55: ='HSE-Stat'!D8 -> 0 | AB55: ='HSE-Stat'!E8 -> 0 | AC55: ='HSE-Stat'!F8 -> 0 | AD55: ='HSE-Stat'!G8 -> 0
A56: ='Quality-Stat'!A18 -> General | C56: =IF('Quality-Stat'!D18=0,"",'Quality-Stat'!D18) -> 42 | D56: =IF('Quality-Stat'!E18=0,"",'Quality-Stat'!E18) -> 6 | E56: =IF('Quality-Stat'!F18=0,"",'Quality-Stat'!F18) -> 36 | F56: =IF('Quality-Stat'!G18=0,"",'Quality-Stat'!G18) | G56: =IF('Quality-Stat'!H18=0,"",'Quality-Stat'!H18) | H56: =IF('Quality-Stat'!I18=0,"",'Quality-Stat'!I18) -> 42 | I56: =IF('Quality-Stat'!J18=0,"",'Quality-Stat'!J18) | J56: =IF('Quality-Stat'!K18=0,"",'Quality-Stat'!K18) | K56: =IF('Quality-Stat'!L18=0,"",'Quality-Stat'!L18) -> 42 | L56: TOTAL | N56: =SUM(N52:N55) -> 758 | O56: =SUM(O52:O55) -> 554 | P56: =SUM(P52:P55) -> 204 | R56: =SUM(R52:R55) -> 168 | S56: =SUM(S52:S55) -> 20 | T56: =SUM(T52:T55) -> 16 | U56: =SUM(U52:U55) -> 0 | X56: ='HSE-Stat'!B9 -> Near Miss | Z56: ='HSE-Stat'!D9 -> 0 | AB56: ='HSE-Stat'!E9 -> 0 | AC56: ='HSE-Stat'!F9 -> 0 | AD56: ='HSE-Stat'!G9 -> 0
A57: TOTAL | C57: =SUM(C51:C56) -> 393 | D57: =SUM(D51:D56) -> 36 | E57: =SUM(E51:E56) -> 259 | F57: =SUM(F51:F56) -> 17 | G57: =SUM(G51:G56) -> 37 | H57: =SUM(H51:H56) -> 295 | I57: =SUM(I51:I56) -> 0 | J57: =SUM(J51:J56) -> 44 | K57: =SUM(K51:K56) -> 393 | L57: Key Submittals Approval Status | X57: ='HSE-Stat'!B10 -> First Aid Cases | Z57: ='HSE-Stat'!D10 -> 0 | AB57: ='HSE-Stat'!E10 -> 0 | AC57: ='HSE-Stat'!F10 -> 0 | AD57: ='HSE-Stat'!G10 -> 0
A58: Material Approval | L58: 1 Quality Plan Approval | O58: ='General Information'!D27 -> 0 | Q58: 6 Baseline Approval | U58: ='General Information'!D39 -> 46086 | X58: ='HSE-Stat'!B11 -> Fatality | Z58: ='HSE-Stat'!D11 -> 0 | AB58: ='HSE-Stat'!E11 -> 0 | AC58: ='HSE-Stat'!F11 -> 0 | AD58: ='HSE-Stat'!G11 -> 0 | AE58: Total Hours Worked Vs Safe Hours Worked
A59: Item Per WBS | C59: Total | D59: Total Submitted Material | I59: Remaining to approve | J59: Pending | K59: Total Submittals | L59: 2 Quality Plan Last Up | O59: ='General Information'!D28 -> 46093 | Q59: 7 No of Approved Version of Schedule | U59: ='General Information'!D40 -> 2 | X59: ='HSE-Stat'!B12 -> Fire Incident Cases | Z59: ='HSE-Stat'!D12 -> 0 | AB59: ='HSE-Stat'!E12 -> 0 | AC59: ='HSE-Stat'!F12 -> 0 | AD59: ='HSE-Stat'!G12 -> 0
D60: A | E60: B | F60: C | G60: D | H60: Processed | I60: with Designer | L60: 3 Safety Plan Approval | O60: ='General Information'!D31 -> 0 | Q60: 8 Last Approved Schedule | U60: ='General Information'!D41 -> 46211 | X60: ='HSE-Stat'!B13 -> Vehicle Incident | Z60: ='HSE-Stat'!D13 -> 0 | AB60: ='HSE-Stat'!E13 -> 0 | AC60: ='HSE-Stat'!F13 -> 0 | AD60: ='HSE-Stat'!G13 -> 0
A61: ='Quality-Stat'!A25 -> Architectural | C61: =IF('Quality-Stat'!D25=0,"",'Quality-Stat'!D25) -> 41 | D61: =IF('Quality-Stat'!E25=0,"",'Quality-Stat'!E25) -> 4 | E61: =IF('Quality-Stat'!F25=0,"",'Quality-Stat'!F25) -> 35 | F61: =IF('Quality-Stat'!G25=0,"",'Quality-Stat'!G25) -> 1 | G61: =IF('Quality-Stat'!H25=0,"",'Quality-Stat'!H25) | H61: =IF('Quality-Stat'!I25=0,"",'Quality-Stat'!I25) -> 39 | I61: =IF('Quality-Stat'!J25=0,"",'Quality-Stat'!J25) | J61: =IF('Quality-Stat'!K25=0,"",'Quality-Stat'!K25) -> 1 | K61: =IF('Quality-Stat'!L25=0,"",'Quality-Stat'!L25) -> 41 | L61: 4 Safety Plan Last Up | O61: ='General Information'!D32 -> 0 | Q61: 9 BOQ Approval Date | U61: =IF(ISBLANK('General Information'!D44),"",'General Information'!D44) | X61: ='HSE-Stat'!B14 -> Property Damages | Z61: ='HSE-Stat'!D14 -> 0 | AB61: ='HSE-Stat'!E14 -> 0 | AC61: ='HSE-Stat'!F14 -> 0 | AD61: ='HSE-Stat'!G14 -> 0
A62: ='Quality-Stat'!A26 -> Civil / Structural | C62: =IF('Quality-Stat'!D26=0,"",'Quality-Stat'!D26) -> 51 | D62: =IF('Quality-Stat'!E26=0,"",'Quality-Stat'!E26) -> 1 | E62: =IF('Quality-Stat'!F26=0,"",'Quality-Stat'!F26) -> 41 | F62: =IF('Quality-Stat'!G26=0,"",'Quality-Stat'!G26) -> 4 | G62: =IF('Quality-Stat'!H26=0,"",'Quality-Stat'!H26) | H62: =IF('Quality-Stat'!I26=0,"",'Quality-Stat'!I26) -> 42 | I62: =IF('Quality-Stat'!J26=0,"",'Quality-Stat'!J26) | J62: =IF('Quality-Stat'!K26=0,"",'Quality-Stat'!K26) -> 5 | K62: =IF('Quality-Stat'!L26=0,"",'Quality-Stat'!L26) -> 51 | L62: 5 Construction Plan Approval | O62: =IF(ISBLANK('General Information'!D48),"",'General Information'!D48) | Q62: 10 No of Approved Version of BOQ | U62: =IF(ISBLANK('General Information'!D45),"",'General Information'!D45) | W62: Proactive | X62: ='HSE-Stat'!B15 -> Induction Training | Z62: ='HSE-Stat'!D15 -> 40 | AB62: ='HSE-Stat'!E15 -> 63 | AC62: ='HSE-Stat'!F15 -> 212 | AD62: ='HSE-Stat'!G15 -> 212
A63: ='Quality-Stat'!A27 -> Mechanical | C63: =IF('Quality-Stat'!D27=0,"",'Quality-Stat'!D27) -> 19 | D63: =IF('Quality-Stat'!E27=0,"",'Quality-Stat'!E27) | E63: =IF('Quality-Stat'!F27=0,"",'Quality-Stat'!F27) -> 14 | F63: =IF('Quality-Stat'!G27=0,"",'Quality-Stat'!G27) -> 1 | G63: =IF('Quality-Stat'!H27=0,"",'Quality-Stat'!H27) | H63: =IF('Quality-Stat'!I27=0,"",'Quality-Stat'!I27) -> 14 | I63: =IF('Quality-Stat'!J27=0,"",'Quality-Stat'!J27) | J63: =IF('Quality-Stat'!K27=0,"",'Quality-Stat'!K27) -> 4 | K63: =IF('Quality-Stat'!L27=0,"",'Quality-Stat'!L27) -> 19 | L63: Invoices Summary | X63: ='HSE-Stat'!B16 -> No.of Internal Training | Z63: ='HSE-Stat'!D16 -> 0 | AB63: ='HSE-Stat'!E16 -> 1 | AC63: ='HSE-Stat'!F16 -> 1 | AD63: ='HSE-Stat'!G16 -> 1
A64: ='Quality-Stat'!A28 -> Electrical | C64: =IF('Quality-Stat'!D28=0,"",'Quality-Stat'!D28) -> 28 | D64: =IF('Quality-Stat'!E28=0,"",'Quality-Stat'!E28) | E64: =IF('Quality-Stat'!F28=0,"",'Quality-Stat'!F28) -> 26 | F64: =IF('Quality-Stat'!G28=0,"",'Quality-Stat'!G28) -> 2 | G64: =IF('Quality-Stat'!H28=0,"",'Quality-Stat'!H28) | H64: =IF('Quality-Stat'!I28=0,"",'Quality-Stat'!I28) -> 26 | I64: =IF('Quality-Stat'!J28=0,"",'Quality-Stat'!J28) | J64: =IF('Quality-Stat'!K28=0,"",'Quality-Stat'!K28) | K64: =IF('Quality-Stat'!L28=0,"",'Quality-Stat'!L28) -> 28 | L64: Total Submitted Invoices | N64: =IF(ISBLANK('Invoice Log'!U3),"",'Invoice Log'!U3) -> 0 | O64: Submitted Invoices (SAR) | R64: ='Invoice Log'!Y3 -> 2317493.3 | T64: Contract Value (SR) | U64: =O4 -> 35709993 | X64: ='HSE-Stat'!B17 -> No.of Internal Audit | Z64: ='HSE-Stat'!D17 -> 0 | AB64: ='HSE-Stat'!E17 -> 0 | AC64: ='HSE-Stat'!F17 -> 0 | AD64: ='HSE-Stat'!G17 -> 0
A65: ='Quality-Stat'!A29 -> Landscape | C65: =IF('Quality-Stat'!D29=0,"",'Quality-Stat'!D29) -> 2 | D65: =IF('Quality-Stat'!E29=0,"",'Quality-Stat'!E29) | E65: =IF('Quality-Stat'!F29=0,"",'Quality-Stat'!F29) | F65: =IF('Quality-Stat'!G29=0,"",'Quality-Stat'!G29) | G65: =IF('Quality-Stat'!H29=0,"",'Quality-Stat'!H29) | H65: =IF('Quality-Stat'!I29=0,"",'Quality-Stat'!I29) | I65: =IF('Quality-Stat'!J29=0,"",'Quality-Stat'!J29) | J65: =IF('Quality-Stat'!K29=0,"",'Quality-Stat'!K29) -> 2 | K65: =IF('Quality-Stat'!L29=0,"",'Quality-Stat'!L29) -> 2 | L65: PM Approved Invoices | N65: ='Invoice Log'!U5 -> 0 | O65: PM Approved Invoices (SAR) | R65: ='Invoice Log'!Y5 -> 0 | T65: Planned Value (SR) | U65: =H18 -> 28681365 | X65: ='HSE-Stat'!B18 -> No. of Toolbox Talks | Z65: ='HSE-Stat'!D18 -> 46 | AB65: ='HSE-Stat'!E18 -> 87 | AC65: ='HSE-Stat'!F18 -> 530 | AD65: ='HSE-Stat'!G18 -> 530
A66: ='Quality-Stat'!A30 -> General | C66: =IF('Quality-Stat'!D30=0,"",'Quality-Stat'!D30) | D66: =IF('Quality-Stat'!E30=0,"",'Quality-Stat'!E30) | E66: =IF('Quality-Stat'!F30=0,"",'Quality-Stat'!F30) | F66: =IF('Quality-Stat'!G30=0,"",'Quality-Stat'!G30) | G66: =IF('Quality-Stat'!H30=0,"",'Quality-Stat'!H30) | H66: =IF('Quality-Stat'!I30=0,"",'Quality-Stat'!I30) | I66: =IF('Quality-Stat'!J30=0,"",'Quality-Stat'!J30) | J66: =IF('Quality-Stat'!K30=0,"",'Quality-Stat'!K30) | K66: =IF('Quality-Stat'!L30=0,"",'Quality-Stat'!L30) | X66: ='HSE-Stat'!B19 -> Safety Awards/Incentives | Z66: ='HSE-Stat'!D19 -> 0 | AB66: ='HSE-Stat'!E19 -> 0 | AC66: ='HSE-Stat'!F19 -> 0 | AD66: ='HSE-Stat'!G19 -> 0
A67: TOTAL | C67: =SUM(C61:C66) -> 141 | D67: =SUM(D61:D66) -> 5 | E67: =SUM(E61:E66) -> 116 | F67: =SUM(F61:F66) -> 8 | G67: =SUM(G61:G66) -> 0 | H67: =SUM(H61:H66) -> 121 | I67: =SUM(I61:I66) -> 0 | J67: =SUM(J61:J66) -> 12 | K67: =SUM(K61:K66) -> 141 | L67: No of Paid Invoices | N67: ='Invoice Log'!U6 -> 0 | O67: Paid Invoices (SAR) | R67: ='Invoice Log'!Y6 -> 2379605.6 | T67: Earned Value (SR) | U67: =I18 -> 24640541
A68: Procurement Summary | L68: No of Pending Invoices | N68: =N65-N67 -> 0 | O68: Last Submitted Period | R68: ='Invoice Log'!AB3 -> 29/09/2026 | T68: Submitted (SAR) | U68: =R64 -> 2317493.3
A69: Item Per WBS | C69: Total Materials | D69: Total Number of P.O. | E69: Actual P.O. To Date | F69: Remaining P.O | G69: Material on Site | H69: Remaining Materials | I69: Material Delivery Completion (Date) | L69: Advance Payment % | N69: ='Invoice Log'!M3 -> 0 | O69: Advance Payment (SAR) | R69: ='Invoice Log'!Q3 -> 0 | T69: PM Approved (SAR) | U69: =R65 -> 0 | W69: Latest Contract Change Order Log
D70: A | E70: B | F70: C | G70: D | H70: Processed | L70: Retention % | N70: ='Invoice Log'!M4 -> 0 | O70: Retention (SAR) | R70: ='Invoice Log'!Q4 -> 0 | T70: Total Paid (SAR) | U70: =R67 -> 2379605.6
A71: ='Quality-Stat'!A36 -> Architectural | C71: =IF('Quality-Stat'!D36=0,"",'Quality-Stat'!D36) -> 11 | D71: =IF('Quality-Stat'!E36=0,"",'Quality-Stat'!E36) -> 11 | E71: =IF('Quality-Stat'!F36=0,"",'Quality-Stat'!F36) -> 7 | F71: =IF('Quality-Stat'!G36=0,"",'Quality-Stat'!G36) -> 4 | G71: =IF('Quality-Stat'!H36=0,"",'Quality-Stat'!H36) -> 3 | H71: =IF('Quality-Stat'!I36=0,"",'Quality-Stat'!I36) | I71: =IF('Quality-Stat'!J36=0,"",'Quality-Stat'!J36) | L71: Deduction / Penalties % | N71: ='Invoice Log'!M5 -> 0.00053206395 | O71: Deduction / Penalties (SAR) | R71: ='Invoice Log'!M6 -> -19000 | W71: CCO No. | X71: Date Added | Y71: Description of Change | AD71: Status | AE71: Cost | AF71: Sch Impact (Months) | AG71: Date Approved | AH71: Duration
A72: ='Quality-Stat'!A37 -> Civil / Structural | C72: =IF('Quality-Stat'!D37=0,"",'Quality-Stat'!D37) -> 19 | D72: =IF('Quality-Stat'!E37=0,"",'Quality-Stat'!E37) -> 19 | E72: =IF('Quality-Stat'!F37=0,"",'Quality-Stat'!F37) -> 15 | F72: =IF('Quality-Stat'!G37=0,"",'Quality-Stat'!G37) -> 4 | G72: =IF('Quality-Stat'!H37=0,"",'Quality-Stat'!H37) -> 3 | H72: =IF('Quality-Stat'!I37=0,"",'Quality-Stat'!I37) | I72: =IF('Quality-Stat'!J37=0,"",'Quality-Stat'!J37) | L72: Resources at Site
A73: ='Quality-Stat'!A38 -> Mechanical | C73: =IF('Quality-Stat'!D38=0,"",'Quality-Stat'!D38) -> 20 | D73: =IF('Quality-Stat'!E38=0,"",'Quality-Stat'!E38) -> 20 | E73: =IF('Quality-Stat'!F38=0,"",'Quality-Stat'!F38) -> 8 | F73: =IF('Quality-Stat'!G38=0,"",'Quality-Stat'!G38) -> 13 | G73: =IF('Quality-Stat'!H38=0,"",'Quality-Stat'!H38) -> 1 | H73: =IF('Quality-Stat'!I38=0,"",'Quality-Stat'!I38) | I73: =IF('Quality-Stat'!J38=0,"",'Quality-Stat'!J38) | L73: Head Count - Non Manual | P73: Head Count - Manual | T73: Total Head Count | W73: =IF(ISBLANK(CCO!A3),"",CCO!A3) | X73: =IF(ISBLANK(CCO!B3),"",CCO!B3) | Y73: =IF(ISBLANK(CCO!C3),"",CCO!C3) | AD73: =IF(ISBLANK(CCO!D3),"",CCO!D3) | AE73: =IF(ISBLANK(CCO!E3),"",CCO!E3) | AF73: =IF(ISBLANK(CCO!F3),"",CCO!F3) | AG73: =IF(ISBLANK(CCO!G3),"",CCO!G3) | AH73: =IF(ISBLANK(CCO!H3),"",CCO!H3)
A74: ='Quality-Stat'!A39 -> Electrical | C74: =IF('Quality-Stat'!D39=0,"",'Quality-Stat'!D39) -> 7 | D74: =IF('Quality-Stat'!E39=0,"",'Quality-Stat'!E39) -> 7 | E74: =IF('Quality-Stat'!F39=0,"",'Quality-Stat'!F39) -> 3 | F74: =IF('Quality-Stat'!G39=0,"",'Quality-Stat'!G39) -> 4 | G74: =IF('Quality-Stat'!H39=0,"",'Quality-Stat'!H39) -> 1 | H74: =IF('Quality-Stat'!I39=0,"",'Quality-Stat'!I39) | I74: =IF('Quality-Stat'!J39=0,"",'Quality-Stat'!J39) | L74: Planned | M74: Actual | N74: Next Month Forecast | O74: Saudi Staff | P74: Planned | Q74: Actual | R74: Next Month Forecast | S74: Saudi Staff | T74: Total Plan | U74: Total Actual | V74: Variance
A75: ='Quality-Stat'!A40 -> General | C75: =IF('Quality-Stat'!D40=0,"",'Quality-Stat'!D40) | D75: =IF('Quality-Stat'!E40=0,"",'Quality-Stat'!E40) | E75: =IF('Quality-Stat'!F40=0,"",'Quality-Stat'!F40) | F75: =IF('Quality-Stat'!G40=0,"",'Quality-Stat'!G40) | G75: =IF('Quality-Stat'!H40=0,"",'Quality-Stat'!H40) | H75: =IF('Quality-Stat'!I40=0,"",'Quality-Stat'!I40) | I75: =IF('Quality-Stat'!J40=0,"",'Quality-Stat'!J40) | L75: =Manpower!B20 -> 8 | M75: =Manpower!C20 -> 16 | N75: =Manpower!G20 -> 8 | O75: =Manpower!I20 -> 2 | P75: =M112 -> 32 | Q75: =N112 -> 77 | R75: =Manpower!G24 -> 20 | S75: =Manpower!I24 -> 0 | T75: =L75+P75 -> 40 | U75: =M75+Q75 -> 93 | V75: =+U75-T75 -> 53 | W75: =IF(ISBLANK(CCO!A5),"",CCO!A5) | X75: =IF(ISBLANK(CCO!B5),"",CCO!B5) | Y75: =IF(ISBLANK(CCO!C5),"",CCO!C5) | AD75: =IF(ISBLANK(CCO!D5),"",CCO!D5) | AE75: =IF(ISBLANK(CCO!E5),"",CCO!E5) | AF75: =IF(ISBLANK(CCO!F5),"",CCO!F5) | AG75: =IF(ISBLANK(CCO!G5),"",CCO!G5) | AH75: =IF(ISBLANK(CCO!H5),"",CCO!H5)
A76: TOTAL | C76: =SUM(C71:C75) -> 57 | D76: =SUM(D71:D75) -> 57 | E76: =SUM(E71:E75) -> 33 | F76: =SUM(F71:F75) -> 25 | G76: =SUM(G71:G75) -> 8 | H76: =SUM(H71:H75) -> 0 | I76: =IF(SUM(I71:K75)=0,"",SUM(I71:K75)) | L76: Manpower Breakdown by Trade | S76: Major Equipment
A77: =Schedule!A1 -> Primavera P6 Schedule Status | L77: Key Trade | M77: Planned | N77: Actual | S77: Type | T77: Planned | U77: Actual | V77: Idle | W77: =IF(ISBLANK(CCO!A7),"",CCO!A7) | X77: =IF(ISBLANK(CCO!B7),"",CCO!B7) | Y77: =IF(ISBLANK(CCO!C7),"",CCO!C7) | AD77: =IF(ISBLANK(CCO!D7),"",CCO!D7) | AE77: =IF(ISBLANK(CCO!E7),"",CCO!E7) | AF77: =IF(ISBLANK(CCO!F7),"",CCO!F7) | AG77: =IF(ISBLANK(CCO!G7),"",CCO!G7) | AH77: =IF(ISBLANK(CCO!H7),"",CCO!H7)
A78: =Schedule!A2 -> Project Activities Overview | L78: =Manpower!AT4 -> Site Engineer | M78: =Manpower!AT5 -> 1 | N78: =Manpower!AT6 -> 3 | S78: =Manpower!AT35 -> Spray Machine | T78: =Manpower!AT36 -> 1 | U78: =Manpower!AT37 -> - | V78: =IF(ISBLANK(Manpower!AT38),"",Manpower!AT38)
A79: =Schedule!A3 -> Schedule Statistics | F79: =Schedule!F3 -> Active Schedule Activities | L79: =Manpower!AU4 -> Mason | M79: =Manpower!AU5 -> 1 | N79: =Manpower!AU6 -> 4 | S79: =Manpower!AU35 -> Excavator | T79: =Manpower!AU36 -> 1 | U79: =Manpower!AU37 -> 2 | V79: =IF(ISBLANK(Manpower!AU38),"",Manpower!AU38) | W79: Major Quantity Trackers
A80: =Schedule!A4 -> Total Act. | B80: =Schedule!B4 -> Not Started | C80: =Schedule!C4 -> In Progress | D80: =Schedule!D4 -> Completed | E80: =Schedule!E4 -> % | F80: =Schedule!F4 -> Active | G80: =Schedule!G4 -> Ahead | H80: =Schedule!H4 -> On | ... K80: =Schedule!K4 -> 0 | L80: =Manpower!AV4 -> Labor / Helper | M80: =Manpower!AV5 -> 8 | N80: =Manpower!AV6 -> 16 | S80: =Manpower!AV35 -> Paving Machine | T80: =Manpower!AV36 -> 1 | U80: =Manpower!AV37 -> - | V80: =IF(ISBLANK(Manpower!AV38),"",Manpower!AV38) | W80: BOQ N0. | X80: Item Description | AC80: Total Qty | AD80: Measu Unit | AE80: Plan to Date | AF80: Act to Date | AG80: Remaining | AH80: Variance
A81: =Schedule!A5 -> 1929 | B81: =Schedule!B5 -> 86 | C81: =Schedule!C5 -> 223 | D81: =Schedule!D5 -> 1620 | E81: =Schedule!E5 -> 0.83981337 | F81: =Schedule!F5 -> 223 | G81: =Schedule!G5 -> 43 | H81: =Schedule!H5 -> 51 | ... J81: =Schedule!J5 -> -121 | L81: =Manpower!AW4 -> Plumber | M81: =Manpower!AW5 -> 1 | N81: =Manpower!AW6 -> 4 | S81: =Manpower!AW35 -> Crane | T81: =Manpower!AW36 -> 1 | U81: =Manpower!AW37 -> - | V81: =IF(ISBLANK(Manpower!AW38),"",Manpower!AW38) | W81: ='Major Quantities'!A2 -> 2.1.1 | X81: ='Major Quantities'!B2 -> Excavation | AC81: =VLOOKUP(X81,'Major Quantities'!$B$2:$G$19,2,FALSE) -> 29400 | AD81: =VLOOKUP(X81,'Major Quantities'!$B$2:$G$19,3,FALSE) -> m3 | AE81: =VLOOKUP(X81,'Major Quantities'!$B$2:$G$19,4,FALSE) -> 29400 | AF81: =VLOOKUP(X81,'Major Quantities'!$B$2:$G$19,5,FALSE) -> 29400 | AG81: =VLOOKUP(X81,'Major Quantities'!$B$2:$G$19,6,FALSE) -> 0 | AH81: =VLOOKUP(X81,'Major Quantities'!$B$2:$H$19,7,FALSE) -> 0
A82: =Schedule!A6 -> Critical Path Activities | D82: =Schedule!D6 -> Free Float Management (Total) | H82: =Schedule!H6 -> Failed Start Activities | L82: =Manpower!AX4 -> Electrician | M82: =Manpower!AX5 -> 2 | N82: =Manpower!AX6 -> 4 | S82: =Manpower!AX35 -> Dump Truck | T82: =Manpower!AX36 -> 1 | U82: =Manpower!AX37 -> 2 | V82: =IF(ISBLANK(Manpower!AX38),"",Manpower!AX38) | W82: ='Major Quantities'!A3 -> 2.1.2 | X82: ='Major Quantities'!B3 -> Backfilling with selected fill material | AC82: =VLOOKUP(X82,'Major Quantities'!$B$2:$G$19,2,FALSE) -> 29400 | AD82: =VLOOKUP(X82,'Major Quantities'!$B$2:$G$19,3,FALSE) -> m3 | AE82: =VLOOKUP(X82,'Major Quantities'!$B$2:$G$19,4,FALSE) -> 29400 | AF82: =VLOOKUP(X82,'Major Quantities'!$B$2:$G$19,5,FALSE) -> 29400 | AG82: =VLOOKUP(X82,'Major Quantities'!$B$2:$G$19,6,FALSE) -> 0 | AH82: =VLOOKUP(X82,'Major Quantities'!$B$2:$H$19,7,FALSE) -> 0
D83: =Schedule!D7 -> Greater Than 14 Days | F83: =Schedule!F7 -> Less Than 14 Days | L83: =Manpower!AY4 -> HVAC Technician | M83: =Manpower!AY5 -> 1 | N83: =Manpower!AY6 -> - | S83: =Manpower!AY35 -> Compactor | T83: =Manpower!AY36 -> - | U83: =Manpower!AY37 -> 2 | V83: =IF(ISBLANK(Manpower!AY38),"",Manpower!AY38) | W83: ='Major Quantities'!A4 -> 2.2.1 | X83: ='Major Quantities'!B4 -> Interlock Tiles for parking | AC83: =VLOOKUP(X83,'Major Quantities'!$B$2:$G$19,2,FALSE) -> 7140 | AD83: =VLOOKUP(X83,'Major Quantities'!$B$2:$G$19,3,FALSE) -> m² | AE83: =VLOOKUP(X83,'Major Quantities'!$B$2:$G$19,4,FALSE) -> 5901.21 | AF83: =VLOOKUP(X83,'Major Quantities'!$B$2:$G$19,5,FALSE) -> 6640.2 | AG83: =VLOOKUP(X83,'Major Quantities'!$B$2:$G$19,6,FALSE) -> 499.8 | AH83: =VLOOKUP(X83,'Major Quantities'!$B$2:$H$19,7,FALSE) -> 738.99
A84: =Schedule!A8 -> Last Week | B84: =Schedule!B8 -> This Week | C84: =Schedule!C8 -> Diff | D84: =Schedule!D8 -> Last Week | E84: =Schedule!E8 -> This Week | F84: =Schedule!F8 -> Last Week | G84: =Schedule!G8 -> This Week | H84: =Schedule!H8 -> Last Week | ... K84: =Schedule!K8 -> 0 | L84: =Manpower!AZ4 -> Tile Fixer | M84: =Manpower!AZ5 -> 1 | N84: =Manpower!AZ6 -> 2 | S84: =Manpower!AZ35 -> Roller Compactor | T84: =Manpower!AZ36 -> - | U84: =Manpower!AZ37 -> 2 | V84: =IF(ISBLANK(Manpower!AZ38),"",Manpower!AZ38) | W84: ='Major Quantities'!A5 -> 2.3.1.2 | X84: ='Major Quantities'!B5 -> Stamped Concrete Floor | AC84: =VLOOKUP(X84,'Major Quantities'!$B$2:$G$19,2,FALSE) -> 7800 | AD84: =VLOOKUP(X84,'Major Quantities'!$B$2:$G$19,3,FALSE) -> m² | AE84: =VLOOKUP(X84,'Major Quantities'!$B$2:$G$19,4,FALSE) -> 7033.26 | AF84: =VLOOKUP(X84,'Major Quantities'!$B$2:$G$19,5,FALSE) -> 6630 | AG84: =VLOOKUP(X84,'Major Quantities'!$B$2:$G$19,6,FALSE) -> 1170 | AH84: =VLOOKUP(X84,'Major Quantities'!$B$2:$H$19,7,FALSE) -> -403.26
A85: =Schedule!A9 -> 205 | B85: =Schedule!B9 -> 174 | C85: =Schedule!C9 -> 31 | D85: =Schedule!D9 -> 54 | E85: =Schedule!E9 -> 39 | F85: =Schedule!F9 -> 284 | G85: =Schedule!G9 -> 270 | H85: =Schedule!H9 -> 77 | ... J85: =Schedule!J9 -> 35 | L85: =Manpower!BA4 -> Applicator | M85: =Manpower!BA5 -> 2 | N85: =Manpower!BA6 -> - | S85: =Manpower!BA35 -> Grader | T85: =Manpower!BA36 -> - | U85: =Manpower!BA37 -> 1 | V85: =IF(ISBLANK(Manpower!BA38),"",Manpower!BA38) | W85: ='Major Quantities'!A6 -> 2.3.1.3 | X85: ='Major Quantities'!B6 -> Tartan Floor | AC85: =VLOOKUP(X85,'Major Quantities'!$B$2:$G$19,2,FALSE) -> 10950 | AD85: =VLOOKUP(X85,'Major Quantities'!$B$2:$G$19,3,FALSE) -> m² | AE85: =VLOOKUP(X85,'Major Quantities'!$B$2:$G$19,4,FALSE) -> 9920.7 | AF85: =VLOOKUP(X85,'Major Quantities'!$B$2:$G$19,5,FALSE) -> 8000 | AG85: =VLOOKUP(X85,'Major Quantities'!$B$2:$G$19,6,FALSE) -> 2950 | AH85: =VLOOKUP(X85,'Major Quantities'!$B$2:$H$19,7,FALSE) -> -1920.7
L86: =Manpower!BB4 -> ELV Technician | M86: =Manpower!BB5 -> 2 | N86: =Manpower!BB6 -> - | S86: =Manpower!BB35 -> Boom Truck | T86: =Manpower!BB36 -> - | U86: =Manpower!BB37 -> 1 | V86: =IF(ISBLANK(Manpower!BB38),"",Manpower!BB38) | W86: ='Major Quantities'!A7 -> 2.3.1.4 | X86: ='Major Quantities'!B7 -> Compacted Natural Ground Soil | AC86: =VLOOKUP(X86,'Major Quantities'!$B$2:$G$19,2,FALSE) -> 33300 | AD86: =VLOOKUP(X86,'Major Quantities'!$B$2:$G$19,3,FALSE) -> m² | AE86: =VLOOKUP(X86,'Major Quantities'!$B$2:$G$19,4,FALSE) -> 33300 | AF86: =VLOOKUP(X86,'Major Quantities'!$B$2:$G$19,5,FALSE) -> 33300 | AG86: =VLOOKUP(X86,'Major Quantities'!$B$2:$G$19,6,FALSE) -> 0 | AH86: =VLOOKUP(X86,'Major Quantities'!$B$2:$H$19,7,FALSE) -> 0
L87: =Manpower!BC4 -> Facade Technician | M87: =Manpower!BC5 -> 1 | N87: =Manpower!BC6 -> - | S87: =Manpower!BC35 -> Pickup Car | T87: =Manpower!BC36 -> - | U87: =Manpower!BC37 -> 3 | V87: =IF(ISBLANK(Manpower!BB39),"",Manpower!BB39) | W87: ='Major Quantities'!A8 -> 2.3.2.3 | X87: ='Major Quantities'!B8 -> Kerb type K4 | AC87: =VLOOKUP(X87,'Major Quantities'!$B$2:$G$19,2,FALSE) -> 27100 | AD87: =VLOOKUP(X87,'Major Quantities'!$B$2:$G$19,3,FALSE) -> L.m | AE87: =VLOOKUP(X87,'Major Quantities'!$B$2:$G$19,4,FALSE) -> 27100 | AF87: =VLOOKUP(X87,'Major Quantities'!$B$2:$G$19,5,FALSE) -> 27100 | AG87: =VLOOKUP(X87,'Major Quantities'!$B$2:$G$19,6,FALSE) -> 0 | AH87: =VLOOKUP(X87,'Major Quantities'!$B$2:$H$19,7,FALSE) -> 0
L88: =Manpower!BD4 -> Crane Operator | M88: =Manpower!BD5 -> 1 | N88: =Manpower!BD6 -> - | S88: =Manpower!BD35 -> Wheel Loader | T88: =Manpower!BD36 -> - | U88: =Manpower!BD37 -> 2 | V88: =IF(ISBLANK(Manpower!BB40),"",Manpower!BB40) | W88: ='Major Quantities'!A9 -> 2.3.4.2.1 | X88: ='Major Quantities'!B9 -> Lawn | AC88: =VLOOKUP(X88,'Major Quantities'!$B$2:$G$19,2,FALSE) -> 19100 | AD88: =VLOOKUP(X88,'Major Quantities'!$B$2:$G$19,3,FALSE) -> m² | AE88: =VLOOKUP(X88,'Major Quantities'!$B$2:$G$19,4,FALSE) -> 12539.15 | AF88: =VLOOKUP(X88,'Major Quantities'!$B$2:$G$19,5,FALSE) -> 0 | AG88: =VLOOKUP(X88,'Major Quantities'!$B$2:$G$19,6,FALSE) -> 19100 | AH88: =VLOOKUP(X88,'Major Quantities'!$B$2:$H$19,7,FALSE) -> -12539.15
L89: =Manpower!BE4 -> Mechanical Technician | M89: =Manpower!BE5 -> 1 | N89: =Manpower!BE6 -> - | S89: =Manpower!BE35 -> Water Tanker | T89: =Manpower!BE36 -> - | U89: =Manpower!BE37 -> 1 | V89: =IF(ISBLANK(Manpower!BB41),"",Manpower!BB41) | W89: ='Major Quantities'!A10 -> 2.3.5.1 | X89: ='Major Quantities'!B10 -> Football Playground | AC89: =VLOOKUP(X89,'Major Quantities'!$B$2:$G$19,2,FALSE) -> 7350 | AD89: =VLOOKUP(X89,'Major Quantities'!$B$2:$G$19,3,FALSE) -> m² | AE89: =VLOOKUP(X89,'Major Quantities'!$B$2:$G$19,4,FALSE) -> 7350 | AF89: =VLOOKUP(X89,'Major Quantities'!$B$2:$G$19,5,FALSE) -> 4400 | AG89: =VLOOKUP(X89,'Major Quantities'!$B$2:$G$19,6,FALSE) -> 2950 | AH89: =VLOOKUP(X89,'Major Quantities'!$B$2:$H$19,7,FALSE) -> -2950
L90: =Manpower!BF4 -> Painter | M90: =Manpower!BF5 -> 1 | N90: =Manpower!BF6 -> - | S90: =Manpower!BF35 -> Forklift | T90: =Manpower!BF36 -> - | U90: =Manpower!BF37 -> 2 | V90: =IF(ISBLANK(Manpower!BB42),"",Manpower!BB42) | W90: ='Major Quantities'!A11 -> 15.5.1.5 | X90: ='Major Quantities'!B11 -> Pipe line O.D 25mm PN 10, in depth 0 to 1.5m | AC90: =VLOOKUP(X90,'Major Quantities'!$B$2:$G$19,2,FALSE) -> 11100 | AD90: =VLOOKUP(X90,'Major Quantities'!$B$2:$G$19,3,FALSE) -> m | AE90: =VLOOKUP(X90,'Major Quantities'!$B$2:$G$19,4,FALSE) -> 10545 | AF90: =VLOOKUP(X90,'Major Quantities'!$B$2:$G$19,5,FALSE) -> 1811.52 | AG90: =VLOOKUP(X90,'Major Quantities'!$B$2:$G$19,6,FALSE) -> 9288.48 | AH90: =VLOOKUP(X90,'Major Quantities'!$B$2:$H$19,7,FALSE) -> -8733.48
L91: =Manpower!BG4 -> Surveyor | M91: =Manpower!BG5 -> 1 | N91: =Manpower!BG6 -> 1 | S91: =Manpower!BG35 -> Backhoe | T91: =Manpower!BG36 -> - | U91: =Manpower!BG37 -> 2 | V91: =IF(ISBLANK(Manpower!BB44),"",Manpower!BB44)
L92: =Manpower!BH4 -> Glass Installer | M92: =Manpower!BH5 -> 1 | N92: =Manpower!BH6 -> - | S92: Total | T92: =SUM(T78:T91) -> 5 | U92: =SUM(U78:U91) -> 20 | V92: =IF(SUM(V78:V86)=0,"",SUM(V78:V86))
L93: =Manpower!BI4 -> Excavator Operator | M93: =Manpower!BI5 -> 1 | N93: =Manpower!BI6 -> 2
L94: =Manpower!BJ4 -> Dump Truck Driver | M94: =Manpower!BJ5 -> 1 | N94: =Manpower!BJ6 -> 2
L95: =Manpower!BK4 -> Safety Officer | M95: =Manpower!BK5 -> 1 | N95: =Manpower!BK6 -> 3
L96: =Manpower!BL4 -> Paving Machine Operator | M96: =Manpower!BL5 -> 1 | N96: =Manpower!BL6 -> -
L97: =Manpower!BM4 -> Concrete Mason | M97: =Manpower!BM5 -> 1 | N97: =Manpower!BM6 -> -
L98: =Manpower!BN4 -> Carpenter | M98: =Manpower!BN5 -> 1 | N98: =Manpower!BN6 -> 2
L99: =Manpower!BO4 -> Gardener | M99: =Manpower!BO5 -> 1 | N99: =Manpower!BO6 -> -
L100: =Manpower!BP4 -> Backhoe Operator | M100: =Manpower!BP5 -> - | N100: =Manpower!BP6 -> 2
L101: =Manpower!BQ4 -> Wheel loader Operator | M101: =Manpower!BQ5 -> - | N101: =Manpower!BQ6 -> 2
L102: =Manpower!BR4 -> Store keeper | M102: =Manpower!BR5 -> - | N102: =Manpower!BR6 -> 2
L103: =Manpower!BS4 -> Security Guard | M103: =Manpower!BS5 -> - | N103: =Manpower!BS6 -> 3
L104: =Manpower!BT4 -> Boom Truck Operator | M104: =Manpower!BT5 -> - | N104: =Manpower!BT6 -> 1
L105: =Manpower!BU4 -> Foreman | M105: =Manpower!BU5 -> - | N105: =Manpower!BU6 -> 4
L106: =Manpower!BV4 -> Pickup Driver | M106: =Manpower!BV5 -> - | N106: =Manpower!BV6 -> 3
L107: =Manpower!BW4 -> Steel Fixer | M107: =Manpower!BW5 -> - | N107: =Manpower!BW6 -> 3
L108: =Manpower!BX4 -> Curbstone Installer | M108: =Manpower!BX5 -> - | N108: =Manpower!BX6 -> 8
L109: =Manpower!BY4 -> Compactor Operator | M109: =Manpower!BY5 -> - | N109: =Manpower!BY6 -> 2
L110: =Manpower!BZ4 -> Roller Compactor Operator | M110: =Manpower!BZ5 -> - | N110: =Manpower!BZ6 -> 2
L111: =Manpower!CA4 -> Forklift Operator | M111: =Manpower!CA5 -> - | N111: =Manpower!CA6 -> 2
L112: Total | M112: =SUM(M78:M111) -> 32 | N112: =SUM(N78:N111) -> 77
A115: Weekly Prgoress Photos | Q115: Top Issues and Risks
A116: ='Weekly Photos'!B4 -> Excavation, Bitumen Coat, Concrete Pouring, Base Course Installation, Asphalt Work, Curbstone Installation, Compaction & Levelling | Q116: Top 5 Issues
Q117: Issue No | R117: Date Identified | S117: Issue Description | W117: Responsible | X117: Action Taken | AA117: Mitigation | AF117: Current Status | AG117: Expected/Actual Closure | AH117: Duration Elapsed
Q118: =IF(Issues!B11="","",Issues!B11) -> 1 | R118: =IF(Issues!C11="","",Issues!C11) -> 46123 | S118: =IF(Issues!D11="","",Issues!D11) -> Delay in starting work at Hail site project due to not getting the aoorved work permit | W118: =IF(Issues!E11="","",Issues!E11) -> Other | X118: =IF(Issues!F11="","",Issues!F11) -> Submit request to BALADI Platform for approval the work permit request | AF118: =IF(Issues!H11="","",Issues!H11) -> Closed | AG118: =IF(Issues!I11="","",Issues!I11) -> 46131 | AH118: =IF(Issues!J11="","",Issues!J11)
Q119: =IF(Issues!B12="","",Issues!B12) -> 2 | R119: =IF(Issues!C12="","",Issues!C12) | S119: =IF(Issues!D12="","",Issues!D12) | W119: =IF(Issues!E12="","",Issues!E12) | X119: =IF(Issues!F12="","",Issues!F12) | AF119: =IF(Issues!H12="","",Issues!H12) | AG119: =IF(Issues!I12="","",Issues!I12) | AH119: =IF(Issues!J12="","",Issues!J12)
Q120: =IF(Issues!B13="","",Issues!B13) -> 3 | R120: =IF(Issues!C13="","",Issues!C13) | S120: =IF(Issues!D13="","",Issues!D13) | W120: =IF(Issues!E13="","",Issues!E13) | X120: =IF(Issues!F13="","",Issues!F13) | AF120: =IF(Issues!H13="","",Issues!H13) | AG120: =IF(Issues!I13="","",Issues!I13) | AH120: =IF(Issues!J13="","",Issues!J13)
...

Sheet Codes
C3: Status List
C4: Approved | E4: Y
C5: Pending | E5: N | K5: (Manhours)
C6: Potential | K6: (Mandays)
C10: Phase | D10: Stage | F10: Stage | H10: Status | J10: Score
J11: Low | K11: Contractor | L11: Active
C12: Launch | D12: LOA | F12: LOA | H12: Active | J12: Medium | K12: CM | L12: Expired
C13: Launch | D13: Kick-off Meeting | F13: Kick-off Meeting | H13: On Hold | J13: High | K13: PgM | L13: Occurred
C14: Launch | D14: Site Handover | H14: Terminated | K14: Modon | L14: Pending
C15: Launch | D15: Mobilization | F15: Mobilization | G15: Initial staff and equipment in place, ready to start production | H15: Terminated, Closed | K15: Other
C16: Execution | D16: Construction | F16: Execution | G16: Tender Documents Issued | H16: Substantial Complete | I16: Initial Handover done at site
C17: Execution | D17: T&C | G17: Responses to the OCS completed | H17: Complete | I17: Initial Handover Signed
C18: Execution | D18: Initial Handover | F18: Closeout | G18: Design close-out process complete | H18: Closed | I18: Final Handover done at Site
D19: Warranty Period
D20: Final Handover
F36: #DIV/0!
B41: Project Status Score
B42: Elements | E42: Max | F42: Score | G42: Planned | H42: Actual | I42: Remarks
B43: SPI (Physical Effort) | E43: 1 | F43: =IFERROR('Weekly Progress Report'!$Z$18,1) -> 0.93197533 | G43: No Entry Required
B44: SPI (Cost) | E44: 1 | F44: =IFERROR('Weekly Progress Report'!$N$18,1) -> 0.85911327 | G44: No Entry Required
B45: On Schedule -Active | E45: 1 | F45: =IFERROR(('Weekly Progress Report'!G81+'Weekly Progress Report'!H81)/'Weekly Progress Report'!F81,1) -> 0.42152466 | G45: No Entry Required | K45: =12/20 -> 0.6
B46: Manpower Availability | E46: 1 | F46: =IFERROR('Weekly Progress Report'!#REF!/'Weekly Progress Report'!M112,1) -> 1 | G46: No Entry Required
B47: Major Equipment Availability | E47: 1 | F47: =IFERROR('Weekly Progress Report'!U92/'Weekly Progress Report'!T92,1) -> 4 | G47: No Entry Required
B48: Billing % Compared to Planned | E48: 1 | F48: =IFERROR('Weekly Progress Report'!R67/'Weekly Progress Report'!R64,1) -> 1.0268015 | G48: No Entry Required
B49: Safety Score | E49: 1 | F49: ='Weekly Progress Report'!Z5 -> 0.91304348 | G49: No Entry Required
B50: Quality Score | E50: 1 | F50: ='Weekly Progress Report'!Z3 -> 0.91310345 | G50: No Entry Required

Sheet General Information
B1: Weekly Progress Report - Construction Projects | L1: Data Date | M1: 46313
B2: Contract General Information
B3: Project Name | D3: Playgrounds Initiative - Qassim, Hail & Tabuk
B4: Project ID | D4: MLTX-02-003
B5: Contractor | D5: Advanced Construction & Contracting Company
B6: Consultant | D6: Egis
B7: Stage | D7: Construction
B8: Status | D8: Active
B9: Modon PM | D9: Bader Alrowaidan
B11: Key Dates
B12: Contract Award Date | D12: =Milestones!D5 -> 46028
B13: Contract Sign Date | D13: =Milestones!D6 -> 46070
B14: Site Handover Date | D14: =Milestones!D7 -> 46070
B15: Original Completion | D15: =Milestones!D14 -> 46372
B16: Contract Award Date (Hijri) | D16: =D12 -> 46028
B17: Contract Sign Date (Hijri) | D17: =D13 -> 46070
B18: Site Handover Date (Hijri) | D18: =D14 -> 46070
B19: Original Completion (Hijri) | D19: =D15 -> 46372
B20: Revised Completion Date | D20: =D15 -> 46372
B21: Committed Completion Date | D21: =Milestones!D14 -> 46372
B22: Forecast Completion | D22: =Milestones!F14 -> 46425
B23: Variance | D23: =IF(ISBLANK(D20),"",D20-D22) -> -53
B25: Key Project Submittals | D25: Submission Date | E25: Days taken to approve orginal plan from site handover date
B26: Quality Plan submission | D26: 46070 | E26: =D26-D14 -> 0
B27: Quality Plan approval
B28: Quality Plan Last Update | D28: 46093
B30: Safety Plan submission | D30: 46070 | E30: =D30-D14 -> 0
B31: Safety Plan approval
B32: Safety Plan Last Update
B34: Risk Management Plan submission | D34: 46070 | E34: =IF(ISBLANK(D34),"",D34-D14) -> 0
B35: Risk Management Plan approval
B36: Risk Management Plan Last Update
B38: Baseline Schedule submission | D38: 46081 | E38: =D38-D14 -> 11
B39: Baseline Schedule approval | D39: 46086
B40: No of Schedule Versions | D40: 2
B41: Last Recovery Schedule Approval Date | D41: 46211
B43: BOQ submission | D43: 46070 | E43: =IF(ISBLANK(D43),"",D43-D14) -> 0
B44: BOQ approval
B45: No of Approved Version of BOQ
B47: Construction Plan submission | D47: 46070 | E47: =IF(ISBLANK(D47),"",D47-D14) -> 0
B48: Construction Plan Approval

Sheet Progress
A1: Project Scope | B1: Construction of Playgrounds Initiatives at 03 Location(Qassim, Hail, Tabuk). The project includes civil, architectural, electrical, mechanical and landscape works, as well as general site works, according to the plans and technical specifications.
A4: Work Progress (SAR) | J4: Manpower Status
A5: WBS | B5: BOQ Value (SAR) | C5: % Wt. | D5: Weekly Progress | G5: To Date Progress | J5: Budgeted Manhours | K5: % Wt. | L5: Weekly Manhours | N5: To Date Manhours
D6: Planned | E6: Earned | F6: Original Plan | G6: Planned | H6: Earned | J6: Budgeted Manhours | K6: % Wt. | L6: Planned | M6: Earned | N6: Planned | O6: Earned
A7: PROJECT MILESTONE | B7: ='Current Week'!J3 -> 0 | C7: =IF(ISBLANK(B7)," ",B7/$B$45) -> 0 | D7: ='Current Week'!H3-'Previous Week'!H3 -> 0 | E7: ='Current Week'!I3-'Previous Week'!I3 -> 0 | F7: =G7 -> 0 | G7: ='Current Week'!H3 -> 0 | H7: ='Current Week'!I3 -> 0 | J7: ='Current Week'!M3 -> 10000 | K7: =IF(ISBLANK(J7),"",J7/$J$45) -> 0.29994001 | L7: ='Current Week'!N3-'Previous Week'!N3 -> 227 | M7: ='Current Week'!O3-'Previous Week'!O3 -> 885 | N7: ='Current Week'!N3 -> 7927 | O7: ='Current Week'!O3 -> 7935
A8: MOBILIZATION | B8: ='Current Week'!J17+'Current Week'!J865+'Current Week'!J1610 -> 0 | C8: =IF(ISBLANK(B8),"",B8/$B$45) -> 0 | D8: =('Current Week'!H17+'Current Week'!H865+'Current Week'!H1610)-('Previous Week'!H17-'Previous Week'!H865-'Previous Week'!H1610) -> 0 | E8: =('Current Week'!I17+'Current Week'!I865+'Current Week'!I1610)-('Previous Week'!I17-'Previous Week'!I865-'Previous Week'!I1610) -> 0 | F8: =G8 -> 0 | G8: ='Current Week'!H17+'Current Week'!H865+'Current Week'!H1610 -> 0 | H8: ='Current Week'!I17+'Current Week'!I865+'Current Week'!I1610 -> 0 | J8: ='Current Week'!M17+'Current Week'!M865+'Current Week'!M1610 -> 0 | K8: =IF(ISBLANK(J8),"",J8/$J$45) -> 0 | L8: =('Current Week'!N17+'Current Week'!N865+'Current Week'!N1610)-('Previous Week'!N17-'Previous Week'!N865-'Previous Week'!N1610) -> 0 | M8: =('Current Week'!O17+'Current Week'!O865+'Current Week'!O1610)-('Previous Week'!O17-'Previous Week'!O865-'Previous Week'!O1610) -> 0 | N8: ='Current Week'!N17+'Current Week'!N865+'Current Week'!N1610 -> 0 | O8: ='Current Week'!O17+'Current Week'!O865+'Current Week'!O1610 -> 0
A9: ENGINEERING | B9: ='Current Week'!J34+'Current Week'!J882+'Current Week'!J1627 -> 1071299.8 | C9: =IF(ISBLANK(B9),"",B9/$B$45) -> 0.03 | D9: =('Current Week'!H34+'Current Week'!H882+'Current Week'!H1627)-('Previous Week'!H34-'Previous Week'!H882-'Previous Week'!H1627) -> 1090347.2 | E9: =('Current Week'!I34+'Current Week'!I882+'Current Week'!I1627)-('Previous Week'!I34-'Previous Week'!I882-'Previous Week'!I1627) -> 1090347.2 | F9: =G9 -> 1071299.8 | G9: ='Current Week'!H34+'Current Week'!H882+'Current Week'!H1627 -> 1071299.8 | H9: ='Current Week'!I34+'Current Week'!I882+'Current Week'!I1627 -> 1071299.8 | J9: ='Current Week'!M34+'Current Week'!M882+'Current Week'!M1627 -> 0 | K9: =IF(ISBLANK(J9),"",J9/$J$45) -> 0 | L9: =('Current Week'!N34+'Current Week'!N882+'Current Week'!N1627)-('Previous Week'!N34-'Previous Week'!N882-'Previous Week'!N1627) -> 0 | M9: =('Current Week'!O34+'Current Week'!O882+'Current Week'!O1627)-('Previous Week'!O34-'Previous Week'!O882-'Previous Week'!O1627) -> 0 | N9: ='Current Week'!N34+'Current Week'!N882+'Current Week'!N1627 -> 0 | O9: ='Current Week'!O34+'Current Week'!O882+'Current Week'!O1627 -> 0
A10: QASSIM | B10: ='Current Week'!J34 -> 526126.2 | C10: =IF(ISBLANK(B10),"",B10/$B$45) -> 0.014733304 | D10: =('Current Week'!H34-'Previous Week'!H34) -> 0 | E10: =('Current Week'!I34-'Previous Week'!I34) -> 0 | F10: =G10 -> 526126.2 | G10: ='Current Week'!H34 -> 526126.2 | H10: ='Current Week'!I34 -> 526126.2 | J10: ='Current Week'!M34 -> 0 | K10: =IF(ISBLANK(J10),"",J10/$J$45) -> 0 | L10: ='Current Week'!N34-'Previous Week'!N34 -> 0 | M10: ='Current Week'!O34-'Previous Week'!O34 -> 0 | N10: ='Current Week'!N34 -> 0 | O10: ='Current Week'!O34 -> 0
A11: SHOP DRAWINGS SUBMITTAL | B11: ='Current Week'!J119 -> 0 | C11: =IF(ISBLANK(B11),"",B11/$B$45) -> 0 | D11: ='Current Week'!H119-'Previous Week'!H119 -> 0 | E11: ='Current Week'!I119-'Previous Week'!I119 -> 0 | F11: =G11 -> 0 | G11: ='Current Week'!H119 -> 0 | H11: ='Current Week'!I119 -> 0 | J11: ='Current Week'!M119 -> 0 | K11: =IF(ISBLANK(J11),"",J11/$J$45) -> 0 | L11: ='Current Week'!N119-'Previous Week'!N119 -> 0 | M11: ='Current Week'!O119-'Previous Week'!O119 -> 0 | N11: ='Current Week'!N119 -> 0 | O11: ='Current Week'!O119 -> 0
A12: MATERIAL SUBMITTAL | B12: ='Current Week'!J285 -> 526126.2 | C12: =IF(ISBLANK(B12),"",B12/$B$45) -> 0.014733304 | D12: ='Current Week'!H285-'Previous Week'!H285 -> 0 | E12: ='Current Week'!I285-'Previous Week'!I285 -> 0 | F12: =G12 -> 526126.2 | G12: ='Current Week'!H285 -> 526126.2 | H12: ='Current Week'!I285 -> 526126.2 | J12: ='Current Week'!M285 -> 0 | K12: =IF(ISBLANK(J12),"",J12/$J$45) -> 0 | L12: ='Current Week'!N285-'Previous Week'!N285 -> 0 | M12: ='Current Week'!O285-'Previous Week'!O285 -> 0 | N12: ='Current Week'!N285 -> 0 | O12: ='Current Week'!O285 -> 0
A13: HAIL | B13: ='Current Week'!J882 -> 204439.56 | C13: =IF(ISBLANK(B13),"",B13/$B$45) -> 0.0057249958 | D13: ='Current Week'!H882-'Previous Week'!H882 -> 0 | E13: ='Current Week'!I882-'Previous Week'!I882 -> 0 | F13: =G13 -> 204439.56 | G13: ='Current Week'!H882 -> 204439.56 | H13: ='Current Week'!I882 -> 204439.56 | J13: ='Current Week'!M882 -> 0 | L13: ='Current Week'!N882-'Previous Week'!N882 -> 0 | M13: ='Current Week'!O882-'Previous Week'!O882 -> 0 | N13: ='Current Week'!N882 -> 0 | O13: ='Current Week'!O882 -> 0
A14: SHOP DRAWINGS SUBMITTAL | B14: ='Current Week'!J948 -> 0 | C14: =IF(ISBLANK(B14),"",B14/$B$45) -> 0 | D14: ='Current Week'!H948-'Previous Week'!H948 -> 0 | E14: ='Current Week'!I948-'Previous Week'!I948 -> 0 | F14: =G14 -> 0 | G14: ='Current Week'!H948 -> 0 | H14: ='Current Week'!I948 -> 0 | J14: ='Current Week'!M948 -> 0 | K14: =IF(ISBLANK(J14),"",J14/$J$45) -> 0 | L14: ='Current Week'!N948-'Previous Week'!N948 -> 0 | M14: ='Current Week'!O948-'Previous Week'!O948 -> 0 | N14: ='Current Week'!N948 -> 0 | O14: ='Current Week'!O948 -> 0
A15: MATERIAL SUBMITTAL | B15: ='Current Week'!J1099 -> 204439.56 | C15: =IF(ISBLANK(B15),"",B15/$B$45) -> 0.0057249958 | D15: ='Current Week'!H1099-'Previous Week'!H1099 -> 0 | E15: ='Current Week'!I1099-'Previous Week'!I1099 -> 0 | F15: =G15 -> 204439.56 | G15: ='Current Week'!H1099 -> 204439.56 | H15: ='Current Week'!I1099 -> 204439.56 | J15: ='Current Week'!M1099 -> 0 | K15: =IF(ISBLANK(J15),"",J15/$J$45) -> 0 | L15: ='Current Week'!N1099-'Previous Week'!N1099 -> 0 | M15: ='Current Week'!O1099-'Previous Week'!O1099 -> 0 | N15: ='Current Week'!N1099 -> 0 | O15: ='Current Week'!O1099 -> 0
A16: TABUK | B16: ='Current Week'!J1627 -> 340734.03 | C16: =IF(ISBLANK(B16),"",B16/$B$45) -> 0.0095416997 | D16: ='Current Week'!H1627-'Previous Week'!H1627 -> 0 | E16: ='Current Week'!I1627-'Previous Week'!I1627 -> 0 | F16: =G16 -> 340734.03 | G16: ='Current Week'!H1627 -> 340734.03 | H16: ='Current Week'!I1627 -> 340734.03 | J16: ='Current Week'!M1627 -> 0 | L16: ='Current Week'!N1627-'Previous Week'!N1627 -> 0 | M16: ='Current Week'!O1627-'Previous Week'!O1627 -> 0 | N16: ='Current Week'!N1627 -> 0 | O16: ='Current Week'!O1627 -> 0
A17: SHOP DRAWINGS SUBMITTAL | B17: ='Current Week'!J1712 -> 0 | C17: =IF(ISBLANK(B17),"",B17/$B$45) -> 0 | D17: ='Current Week'!H1712-'Previous Week'!H1712 -> 0 | E17: ='Current Week'!I1712-'Previous Week'!I1712 -> 0 | F17: =G17 -> 0 | G17: ='Current Week'!H1712 -> 0 | H17: ='Current Week'!I1712 -> 0 | J17: ='Current Week'!M1712 -> 0 | K17: =IF(ISBLANK(J17),"",J17/$J$45) -> 0 | L17: ='Current Week'!N1712-'Previous Week'!N1712 -> 0 | M17: ='Current Week'!O1712-'Previous Week'!O1712 -> 0 | N17: ='Current Week'!N1712 -> 0 | O17: ='Current Week'!O1712 -> 0
A18: MATERIAL SUBMITTAL | B18: ='Current Week'!J1885 -> 340734.03 | C18: =IF(ISBLANK(B18),"",B18/$B$45) -> 0.0095416997 | D18: ='Current Week'!H1885-'Previous Week'!H1885 -> 0 | E18: ='Current Week'!I1885-'Previous Week'!I1885 -> 0 | F18: =G18 -> 340734.03 | G18: ='Current Week'!H1885 -> 340734.03 | H18: ='Current Week'!I1885 -> 340734.03 | J18: ='Current Week'!M1885 -> 0 | K18: =IF(ISBLANK(J18),"",J18/$J$45) -> 0 | L18: ='Current Week'!N1885-'Previous Week'!N1885 -> 0 | M18: ='Current Week'!O1885-'Previous Week'!O1885 -> 0 | N18: ='Current Week'!N1885 -> 0 | O18: ='Current Week'!O1885 -> 0
A19: PROCUREMENT | B19: ='Current Week'!J379+'Current Week'!J1185+'Current Week'!J1974 -> 9641698.1 | C19: =IF(ISBLANK(B19),"",B19/$B$45) -> 0.27 | D19: =('Current Week'!H379+'Current Week'!H1185+'Current Week'!H1974)-('Previous Week'!H379-'Previous Week'!H1185-'Previous Week'!H1974) -> 9813124.6 | E19: =('Current Week'!I379+'Current Week'!I1185+'Current Week'!I1974)-('Previous Week'!I379-'Previous Week'!I1185-'Previous Week'!I1974) -> 8945474.8 | F19: =G19 -> 9641698.1 | G19: ='Current Week'!H379+'Current Week'!H1185+'Current Week'!H1974 -> 9641698.1 | H19: ='Current Week'!I379+'Current Week'!I1185+'Current Week'!I1974 -> 8769229.7 | J19: ='Current Week'!M379+'Current Week'!M1185+'Current Week'!M1974 -> 0 | K19: =IF(ISBLANK(J19),"",J19/$J$45) -> 0 | L19: =('Current Week'!N379+'Current Week'!N1185+'Current Week'!N1974)-('Previous Week'!N379-'Previous Week'!N1185-'Previous Week'!N1974) -> 0 | M19: =('Current Week'!O379+'Current Week'!O1185+'Current Week'!O1974)-('Previous Week'!O379-'Previous Week'!O1185-'Previous Week'!O1974) -> 0 | N19: ='Current Week'!N379+'Current Week'!N1185+'Current Week'!N1974 -> 0 | O19: ='Current Week'!O379+'Current Week'!O1185+'Current Week'!O1974 -> 0
A20: QASSIM | B20: ='Current Week'!J379 -> 4735135.8 | C20: =IF(ISBLANK(B20),"",B20/$B$45) -> 0.13259974 | D20: ='Current Week'!H379-'Previous Week'!H379 -> 0 | E20: ='Current Week'!I379-'Previous Week'!I379 -> 393630.22 | F20: =G20 -> 4735135.8 | G20: ='Current Week'!H379 -> 4735135.8 | H20: ='Current Week'!I379 -> 4290343.4 | J20: ='Current Week'!M379 -> 0 | L20: ='Current Week'!N379-'Previous Week'!N379 -> 0 | M20: ='Current Week'!O379-'Previous Week'!O379 -> 0 | N20: ='Current Week'!N379 -> 0 | O20: ='Current Week'!O379 -> 0
A21: LONG LEAD ITEMS | B21: ='Current Week'!J380 -> 3229967.3 | C21: =IF(ISBLANK(B21),"",B21/$B$45) -> 0.090449957 | D21: ='Current Week'!H380-'Previous Week'!H380 -> 0 | E21: ='Current Week'!I380-'Previous Week'!I380 -> 377836.78 | F21: =G21 -> 3229967.3 | G21: ='Current Week'!H380 -> 3229967.3 | H21: ='Current Week'!I380 -> 2815918.8 | J21: ='Current Week'!M380 -> 0 | K21: =IF(ISBLANK(J21),"",J21/$J$45) -> 0 | L21: ='Current Week'!N380-'Previous Week'!N380 -> 0 | M21: ='Current Week'!O380-'Previous Week'!O380 -> 0 | N21: ='Current Week'!N380 -> 0 | O21: ='Current Week'!O380 -> 0
A22: SHORT LEAD ITEMS | B22: ='Current Week'!J526 -> 1505168.5 | C22: =IF(ISBLANK(B22),"",B22/$B$45) -> 0.042149783 | D22: ='Current Week'!H526-'Previous Week'!H526 -> 0 | E22: ='Current Week'!I526-'Previous Week'!I526 -> 15793.44 | F22: =G22 -> 1505168.5 | G22: ='Current Week'!H526 -> 1505168.5 | H22: ='Current Week'!I526 -> 1474424.7 | J22: ='Current Week'!M526 -> 0 | K22: =IF(ISBLANK(J22),"",J22/$J$45) -> 0 | L22: ='Current Week'!N526-'Previous Week'!N526 -> 0 | M22: ='Current Week'!O526-'Previous Week'!O526 -> 0 | N22: ='Current Week'!N526 -> 0 | O22: ='Current Week'!O526 -> 0
A23: HAIL | B23: ='Current Week'!J1185 -> 1839956 | C23: =IF(ISBLANK(B23),"",B23/$B$45) -> 0.051524962 | D23: ='Current Week'!H1185-'Previous Week'!H1185 -> 0 | E23: ='Current Week'!I1185-'Previous Week'!I1185 -> 28384.23 | F23: =G23 -> 1839956 | G23: ='Current Week'!H1185 -> 1839956 | H23: ='Current Week'!I1185 -> 1816202.8 | J23: ='Current Week'!M1185 -> 0 | L23: ='Current Week'!N1185-'Previous Week'!N1185 -> 0 | M23: ='Current Week'!O1185-'Previous Week'!O1185 -> 0 | N23: ='Current Week'!N1185 -> 0 | O23: ='Current Week'!O1185 -> 0
A24: LONG LEAD ITEMS | B24: ='Current Week'!J1186 -> 999589.41 | C24: =IF(ISBLANK(B24),"",B24/$B$45) -> 0.027991868 | D24: ='Current Week'!H1186-'Previous Week'!H1186 -> 0 | E24: ='Current Week'!I1186-'Previous Week'!I1186 -> 19306.16 | F24: =G24 -> 999589.41 | G24: ='Current Week'!H1186 -> 999589.41 | H24: ='Current Week'!I1186 -> 981462.29 | J24: ='Current Week'!M1186 -> 0 | K24: =IF(ISBLANK(J24),"",J24/$J$45) -> 0 | L24: ='Current Week'!N1186-'Previous Week'!N1186 -> 0 | M24: ='Current Week'!O1186-'Previous Week'!O1186 -> 0 | N24: ='Current Week'!N1186 -> 0 | O24: ='Current Week'!O1186 -> 0
A25: SHORT LEAD ITEMS | B25: ='Current Week'!J1319 -> 840366.63 | C25: =IF(ISBLANK(B25),"",B25/$B$45) -> 0.023533094 | D25: ='Current Week'!H1319-'Previous Week'!H1319 -> 0 | E25: ='Current Week'!I1319-'Previous Week'!I1319 -> 9078.05 | F25: =G25 -> 840366.63 | G25: ='Current Week'!H1319 -> 840366.63 | H25: ='Current Week'!I1319 -> 834740.53 | J25: ='Current Week'!M1319 -> 0 | K25: =IF(ISBLANK(J25),"",J25/$J$45) -> 0 | L25: ='Current Week'!N1319-'Previous Week'!N1319 -> 0 | M25: ='Current Week'!O1319-'Previous Week'!O1319 -> 0 | N25: ='Current Week'!N1319 -> 0 | O25: ='Current Week'!O1319 -> 0
A26: TABUK | B26: ='Current Week'!J1974 -> 3066606.3 | C26: =IF(ISBLANK(B26),"",B26/$B$45) -> 0.085875297 | D26: ='Current Week'!H1974-'Previous Week'!H1974 -> 0 | E26: ='Current Week'!I1974-'Previous Week'!I1974 -> 377543.73 | F26: =G26 -> 3066606.3 | G26: ='Current Week'!H1974 -> 3066606.3 | H26: ='Current Week'!I1974 -> 2662683.5 | J26: ='Current Week'!M1974 -> 0 | L26: ='Current Week'!N1974-'Previous Week'!N1974 -> 0 | M26: ='Current Week'!O1974-'Previous Week'!O1974 -> 0 | N26: ='Current Week'!N1974 -> 0 | O26: ='Current Week'!O1974 -> 0
A27: LONG LEAD ITEMS | B27: ='Current Week'!J1975 -> 2561939.8 | C27: =IF(ISBLANK(B27),"",B27/$B$45) -> 0.071742938 | D27: ='Current Week'!H1975-'Previous Week'!H1975 -> 0 | E27: ='Current Week'!I1975-'Previous Week'!I1975 -> 376757.42 | F27: =G27 -> 2561939.8 | G27: ='Current Week'!H1975 -> 2561939.8 | H27: ='Current Week'!I1975 -> 2161684.9 | J27: ='Current Week'!M1975 -> 0 | K27: =IF(ISBLANK(J27),"",J27/$J$45) -> 0 | L27: ='Current Week'!N1975-'Previous Week'!N1975 -> 0 | M27: ='Current Week'!O1975-'Previous Week'!O1975 -> 0 | N27: ='Current Week'!N1975 -> 0 | O27: ='Current Week'!O1975 -> 0
A28: SHORT LEAD ITEMS | B28: ='Current Week'!J2121 -> 504666.45 | C28: =IF(ISBLANK(B28),"",B28/$B$45) -> 0.014132359 | D28: ='Current Week'!H2121-'Previous Week'!H2121 -> 0 | E28: ='Current Week'!I2121-'Previous Week'!I2121 -> 786.32 | F28: =G28 -> 504666.45 | G28: ='Current Week'!H2121 -> 504666.45 | H28: ='Current Week'!I2121 -> 500998.54 | J28: ='Current Week'!M2121 -> 0 | K28: =IF(ISBLANK(J28),"",J28/$J$45) -> 0 | L28: ='Current Week'!N2121-'Previous Week'!N2121 -> 0 | M28: ='Current Week'!O2121-'Previous Week'!O2121 -> 0 | N28: ='Current Week'!N2121 -> 0 | O28: ='Current Week'!O2121 -> 0
A29: CONSTRUCTION | B29: ='Current Week'!J641+'Current Week'!J1435+'Current Week'!J2235 -> 21425996 | C29: =IF(ISBLANK(B29),"",B29/$B$45) -> 0.6 | D29: =('Current Week'!H641+'Current Week'!H1435+'Current Week'!H2235)-('Previous Week'!H641-'Previous Week'!H1435-'Previous Week'!H2235) -> 17500390 | E29: =('Current Week'!I641+'Current Week'!I1435+'Current Week'!I2235)-('Previous Week'!I641-'Previous Week'!I1435-'Previous Week'!I2235) -> 13921267 | F29: =G29 -> 17861237 | G29: ='Current Week'!H641+'Current Week'!H1435+'Current Week'!H2235 -> 17861237 | H29: ='Current Week'!I641+'Current Week'!I1435+'Current Week'!I2235 -> 14189805 | J29: ='Current Week'!M641+'Current Week'!M1435+'Current Week'!M2235 -> 22188 | K29: =IF(ISBLANK(J29),"",J29/$J$45) -> 0.6655069 | L29: =('Current Week'!N641+'Current Week'!N1435+'Current Week'!N2235)-('Previous Week'!N641-'Previous Week'!N1435-'Previous Week'!N2235) -> 23717 | M29: =('Current Week'!O641+'Current Week'!O1435+'Current Week'!O2235)-('Previous Week'!O641-'Previous Week'!O1435-'Previous Week'!O2235) -> 21229 | N29: ='Current Week'!N641+'Current Week'!N1435+'Current Week'!N2235 -> 18795 | O29: ='Current Week'!O641+'Current Week'!O1435+'Current Week'!O2235 -> 16835
A30: QASSIM | B30: ='Current Week'!J641 -> 10522524 | C30: =IF(ISBLANK(B30),"",B30/$B$45) -> 0.29466609 | D30: ='Current Week'!H641-'Previous Week'!H641 -> 516953.07 | E30: ='Current Week'!I641-'Previous Week'!I641 -> 275629.64 | F30: =G30 -> 8948881.5 | G30: ='Current Week'!H641 -> 8948881.5 | H30: ='Current Week'!I641 -> 7197982.4 | J30: ='Current Week'!M641 -> 8112 | K30: =IF(ISBLANK(J30),"",J30/$J$45) -> 0.24331134 | L30: ='Current Week'!N641-'Previous Week'!N641 -> 409 | M30: ='Current Week'!O641-'Previous Week'!O641 -> 467 | N30: ='Current Week'!N641 -> 6809 | O30: ='Current Week'!O641 -> 6065
A31: PLAYGROUND AND LANDSCAPING WORK | B31: ='Current Week'!J642 -> 6019638.4 | C31: =IF(ISBLANK(B31),"",B31/$B$45) -> 0.16857014 | D31: ='Current Week'!H642-'Previous Week'!H642 -> 269950.21 | E31: ='Current Week'!I642-'Previous Week'!I642 -> 269791.79 | F31: =G31 -> 5378139.1 | G31: ='Current Week'!H642 -> 5378139.1 | H31: ='Current Week'!I642 -> 5433056.1 | J31: ='Current Week'!M642 -> 5288 | K31: =IF(ISBLANK(J31),"",J31/$J$45) -> 0.15860828 | L31: ='Current Week'!N642-'Previous Week'!N642 -> 243 | M31: ='Current Week'!O642-'Previous Week'!O642 -> 422 | N31: ='Current Week'!N642 -> 4345 | O31: ='Current Week'!O642 -> 4048
A32: AIR DOME CONSTRUCTION | B32: ='Current Week'!J778 -> 4178041.2 | C32: =IF(ISBLANK(B32),"",B32/$B$45) -> 0.11699922 | D32: ='Current Week'!H778-'Previous Week'!H778 -> 184703.48 | E32: ='Current Week'!I778-'Previous Week'!I778 -> 0 | F32: =G32 -> 3260143 | G32: ='Current Week'!H778 -> 3260143 | H32: ='Current Week'!I778 -> 1461181.7 | J32: ='Current Week'!M778 -> 1116 | K32: =IF(ISBLANK(J32),"",J32/$J$45) -> 0.033473305 | L32: ='Current Week'!N778-'Previous Week'!N778 -> 41 | M32: ='Current Week'!O778-'Previous Week'!O778 -> 0 | N32: ='Current Week'!N778 -> 865 | O32: ='Current Week'!O778 -> 446
A33: TOILET BUILDING WORKS | B33: ='Current Week'!J804 -> 324844.38 | C33: =IF(ISBLANK(B33),"",B33/$B$45) -> 0.009096736 | D33: ='Current Week'!H804-'Previous Week'!H804 -> 62299.36 | E33: ='Current Week'!I804-'Previous Week'!I804 -> 5837.86 | F33: =G33 -> 310599.36 | G33: ='Current Week'!H804 -> 310599.36 | H33: ='Current Week'!I804 -> 303744.63 | J33: ='Current Week'!M804 -> 1708 | K33: =IF(ISBLANK(J33),"",J33/$J$45) -> 0.051229754 | L33: ='Current Week'!N804-'Previous Week'!N804 -> 124 | M33: ='Current Week'!O804-'Previous Week'!O804 -> 45 | N33: ='Current Week'!N804 -> 1599 | O33: ='Current Week'!O804 -> 1571
A34: HAIL | B34: ='Current Week'!J1435 -> 4088791.2 | C34: =IF(ISBLANK(B34),"",B34/$B$45) -> 0.11449992 | D34: ='Current Week'!H1435-'Previous Week'!H1435 -> 335606.94 | E34: ='Current Week'!I1435-'Previous Week'!I1435 -> 234285.44 | F34: =G34 -> 3836982.5 | G34: ='Current Week'!H1435 -> 3836982.5 | H34: ='Current Week'!I1435 -> 3434319.4 | J34: ='Current Week'!M1435 -> 5964 | K34: =IF(ISBLANK(J34),"",J34/$J$45) -> 0.17888422 | L34: ='Current Week'!N1435-'Previous Week'!N1435 -> 211 | M34: ='Current Week'!O1435-'Previous Week'!O1435 -> 407 | N34: ='Current Week'!N1435 -> 5398 | O34: ='Current Week'!O1435 -> 4553
A35: PLAYGROUND AND LANDSCAPING WORK | B35: ='Current Week'!J1436 -> 3760297.6 | C35: =IF(ISBLANK(B35),"",B35/$B$45) -> 0.10530099 | D35: ='Current Week'!H1436-'Previous Week'!H1436 -> 325613.23 | E35: ='Current Week'!I1436-'Previous Week'!I1436 -> 221795.36 | F35: =G35 -> 3508489 | G35: ='Current Week'!H1436 -> 3508489 | H35: ='Current Week'!I1436 -> 3160875.2 | J35: ='Current Week'!M1436 -> 4256 | K35: =IF(ISBLANK(J35),"",J35/$J$45) -> 0.12765447 | L35: ='Current Week'!N1436-'Previous Week'!N1436 -> 198 | M35: ='Current Week'!O1436-'Previous Week'!O1436 -> 390 | N35: ='Current Week'!N1436 -> 3690 | O35: ='Current Week'!O1436 -> 3096
A36: TOILET BUILDING WORKS | B36: ='Current Week'!J1549 -> 328493.58 | C36: =IF(ISBLANK(B36),"",B36/$B$45) -> 0.0091989259 | D36: ='Current Week'!H1549-'Previous Week'!H1549 -> 9993.71 | E36: ='Current Week'!I1549-'Previous Week'!I1549 -> 12490.08 | F36: =G36 -> 328493.58 | G36: ='Current Week'!H1549 -> 328493.58 | H36: ='Current Week'!I1549 -> 273444.26 | J36: ='Current Week'!M1549 -> 1708 | K36: =IF(ISBLANK(J36),"",J36/$J$45) -> 0.051229754 | L36: ='Current Week'!N1549-'Previous Week'!N1549 -> 13 | M36: ='Current Week'!O1549-'Previous Week'!O1549 -> 18 | N36: ='Current Week'!N1549 -> 1708 | O36: ='Current Week'!O1549 -> 1458
A37: TABUK | B37: ='Current Week'!J2235 -> 6814680.6 | C37: =IF(ISBLANK(B37),"",B37/$B$45) -> 0.19083399 | D37: ='Current Week'!H2235-'Previous Week'!H2235 -> 505666.59 | E37: ='Current Week'!I2235-'Previous Week'!I2235 -> 103722.2 | F37: =G37 -> 5075372.6 | G37: ='Current Week'!H2235 -> 5075372.6 | H37: ='Current Week'!I2235 -> 3557503.1 | J37: ='Current Week'!M2235 -> 8112 | K37: =IF(ISBLANK(J37),"",J37/$J$45) -> 0.24331134 | L37: ='Current Week'!N2235-'Previous Week'!N2235 -> 453 | M37: ='Current Week'!O2235-'Previous Week'!O2235 -> 371 | N37: ='Current Week'!N2235 -> 6588 | O37: ='Current Week'!O2235 -> 6217
A38: PLAYGROUND AND LANDSCAPING WORK | B38: ='Current Week'!J2236 -> 2311795 | C38: =IF(ISBLANK(B38),"",B38/$B$45) -> 0.064738042 | D38: ='Current Week'!H2236-'Previous Week'!H2236 -> 91455.92 | E38: ='Current Week'!I2236-'Previous Week'!I2236 -> 96732.13 | F38: =G38 -> 1913311.4 | G38: ='Current Week'!H2236 -> 1913311.4 | H38: ='Current Week'!I2236 -> 2041669.6 | J38: ='Current Week'!M2236 -> 5288 | K38: =IF(ISBLANK(J38),"",J38/$J$45) -> 0.15860828 | L38: ='Current Week'!N2236-'Previous Week'!N2236 -> 186 | M38: ='Current Week'!O2236-'Previous Week'!O2236 -> 346 | N38: ='Current Week'!N2236 -> 4288 | O38: ='Current Week'!O2236 -> 4204
A39: AIR DOME CONSTRUCTION | B39: ='Current Week'!J2373 -> 4178041.2 | C39: =IF(ISBLANK(B39),"",B39/$B$45) -> 0.11699922 | D39: ='Current Week'!H2373-'Previous Week'!H2373 -> 307146.35 | E39: ='Current Week'!I2373-'Previous Week'!I2373 -> 0 | F39: =G39 -> 2880615.3 | G39: ='Current Week'!H2373 -> 2880615.3 | H39: ='Current Week'!I2373 -> 1210693.4 | J39: ='Current Week'!M2373 -> 1116 | K39: =IF(ISBLANK(J39),"",J39/$J$45) -> 0.033473305 | L39: ='Current Week'!N2373-'Previous Week'!N2373 -> 58 | M39: ='Current Week'!O2373-'Previous Week'!O2373 -> 0 | N39: ='Current Week'!N2373 -> 784 | O39: ='Current Week'!O2373 -> 392
A40: TOILET BUILDING WORKS | B40: ='Current Week'!J2399 -> 324844.38 | C40: =IF(ISBLANK(B40),"",B40/$B$45) -> 0.009096736 | D40: ='Current Week'!H2399-'Previous Week'!H2399 -> 107064.32 | E40: ='Current Week'!I2399-'Previous Week'!I2399 -> 6990.07 | F40: =G40 -> 281445.86 | G40: ='Current Week'!H2399 -> 281445.86 | H40: ='Current Week'!I2399 -> 305140.07 | J40: ='Current Week'!M2399 -> 1708 | K40: =IF(ISBLANK(J40),"",J40/$J$45) -> 0.051229754 | L40: ='Current Week'!N2396-'Previous Week'!N2396 -> 16 | M40: ='Current Week'!O2396-'Previous Week'!O2396 -> 0 | N40: ='Current Week'!N2396 -> 16 | O40: ='Current Week'!O2396 -> 0
A41: CLOSEOUT | B41: ='Current Week'!J856+'Current Week'!J1601+'Current Week'!J2453 -> 3570999.3 | C41: =IF(ISBLANK(B41),"",B41/$B$45) -> 0.1 | D41: =('Current Week'!H856+'Current Week'!H1601+'Current Week'!H2453)-('Previous Week'!H856-'Previous Week'!H1601-'Previous Week'!H2453) -> 109034.72 | E41: =('Current Week'!I856+'Current Week'!I1601+'Current Week'!I2453)-('Previous Week'!I856-'Previous Week'!I1601-'Previous Week'!I2453) -> 571523.92 | F41: =G41 -> 107129.98 | G41: ='Current Week'!H856+'Current Week'!H1601+'Current Week'!H2453 -> 107129.98 | H41: ='Current Week'!I856+'Current Week'!I1601+'Current Week'!I2453 -> 610206.45 | J41: ='Current Week'!M856+'Current Week'!M1601+'Current Week'!M2453 -> 1152 | K41: =IF(ISBLANK(J41),"",J41/$J$45) -> 0.034553089 | L41: =('Current Week'!N856+'Current Week'!N1601+'Current Week'!N2453)-('Previous Week'!N856-'Previous Week'!N1601-'Previous Week'!N2453) -> 44 | M41: =('Current Week'!O856+'Current Week'!O1601+'Current Week'!O2453)-('Previous Week'!O856-'Previous Week'!O1601-'Previous Week'!O2453) -> 206 | N41: ='Current Week'!N856+'Current Week'!N1601+'Current Week'!N2453 -> 33 | O41: ='Current Week'!O856+'Current Week'!O1601+'Current Week'!O2453 -> 165
A42: QASSIM | B42: ='Current Week'!J856 -> 1753754 | C42: =IF(ISBLANK(B42),"",B42/$B$45) -> 0.049111015 | D42: ='Current Week'!H856-'Previous Week'!H856 -> 0 | E42: ='Current Week'!I856-'Previous Week'!I856 -> 0 | F42: =G42 -> 52612.62 | G42: ='Current Week'!H856 -> 52612.62 | H42: ='Current Week'!I856 -> 324444.49 | J42: ='Current Week'!M856 -> 384 | K42: =IF(ISBLANK(J42),"",J42/$J$45) -> 0.011517696 | L42: ='Current Week'!N856-'Previous Week'!N856 -> 0 | M42: ='Current Week'!O856-'Previous Week'!O856 -> 0 | N42: ='Current Week'!N856 -> 11 | O42: ='Current Week'!O856 -> 62
A43: HAIL | B43: ='Current Week'!J1601 -> 681465.2 | C43: =IF(ISBLANK(B43),"",B43/$B$45) -> 0.019083319 | D43: ='Current Week'!H1601-'Previous Week'!H1601 -> 0 | E43: ='Current Week'!I1601-'Previous Week'!I1601 -> 0 | F43: =G43 -> 20443.96 | G43: ='Current Week'!H1601 -> 20443.96 | H43: ='Current Week'!I1601 -> 75642.64 | J43: ='Current Week'!M1601 -> 384 | K43: =IF(ISBLANK(J43),"",J43/$J$45) -> 0.011517696 | L43: ='Current Week'!N1601-'Previous Week'!N1601 -> 0 | M43: ='Current Week'!O1601-'Previous Week'!O1601 -> 0 | N43: ='Current Week'!N1601 -> 11 | O43: ='Current Week'!O1601 -> 41
A44: TABUK | B44: ='Current Week'!J2453 -> 1135780.1 | C44: =IF(ISBLANK(B44),"",B44/$B$45) -> 0.031805666 | D44: ='Current Week'!H2453-'Previous Week'!H2453 -> 0 | E44: ='Current Week'!I2453-'Previous Week'!I2453 -> 0 | F44: =G44 -> 34073.4 | G44: ='Current Week'!H2453 -> 34073.4 | H44: ='Current Week'!I2453 -> 210119.32 | J44: ='Current Week'!M245 -> 0 | K44: =IF(ISBLANK(J44),"",J44/$J$45) -> 0 | L44: ='Current Week'!N2453-'Previous Week'!N2453 -> 0 | M44: ='Current Week'!O2453-'Previous Week'!O2453 -> 0 | N44: ='Current Week'!N2453 -> 11 | O44: ='Current Week'!O2453 -> 62
A45: TOTAL | B45: =B8+B9+B19+B29+B41 -> 35709993 | C45: =C7+C8+C9+C19+C29+C41 -> 1 | D45: =D7+D8+D9+D19+D29+D41 -> 28512896 | E45: =E8+E9+E19+E29+E41 -> 24528613 | F45: =F8+F9+F19+F29+F41 -> 28681365 | G45: =G8+G9+G19+G29+G41 -> 28681365 | H45: =H8+H9+H19+H29+H41 -> 24640541 | J45: =J7+J8+J9+J19+J29+J41 -> 33340 | K45: =K7+K8+K9+K19+K29+K41 -> 1 | L45: =L7+L8+L9+L19+L29+L41 -> 23988 | M45: =M7+M8+M9+M19+M29+M41 -> 22320 | N45: =N7+N8+N9+N19+N29+N41 -> 26755 | O45: =O7+O8+O9+O19+O29+O41 -> 24935

Sheet Current Week
A1: Activity ID | B1: Activity Name | C1: BL Project Duration | D1: BL Project Start | E1: BL Project Finish | F1: Actual Start | G1: Actual Finish | H1: Planned Value Cost | I1: Earned Value Cost | J1: Budgeted Total Cost | K1: Schedule % Complete | L1: Performance % Complete | M1: Budgeted Labor Units | N1: Planned Value Labor Units | O1: Earned Value Labor Units | P1: Critical | Q1: Activity Count | R1: Actual Completed Activities | S1: Actual In-Progress Activities | T1: Actual Not-Started Activities
A2: PLAYGROUNDS INITIATIVE - QASSIM, HAIL & TABUK - 18-Oct-2026 | C2: 250 | D2: 46070 | E2: 46372 | F2: 46070 | H2: 28681365 | I2: 24640541 | J2: 35709993 | K2: 0.8032 | L2: 0.69 | M2: 33340 | N2: 26756 | O2: 24935 | Q2: 1929 | R2: 1620 | S2: 223 | T2: 86
A3: MILESTONES | C3: 250 | D3: 46070 | E3: 46372 | F3: 46070 | H3: 0 | I3: 0 | J3: 0 | K3: 0 | L3: 0 | M3: 10000 | N3: 7927 | O3: 7935 | Q3: 10 | R3: 4 | S3: 1 | T3: 5
A4: GENERAL MILESTONES | C4: 250 | D4: 46070 | E4: 46372 | F4: 46070 | H4: 0 | I4: 0 | J4: 0 | K4: 0 | L4: 0 | M4: 10000 | N4: 7927 | O4: 7935 | Q4: 4 | R4: 2 | S4: 1 | T4: 1
A5: PG-GN-MS-10 | B5: Project Commencement Date | C5: 0 | D5: 46070 | F5: 46070 | H5: 0 | I5: 0 | J5: 0 | K5: 1 | L5: 1 | M5: 0 | N5: 0 | O5: 0 | P5: No | Q5: 1 | R5: 1 | S5: 0 | T5: 0
A6: PG-GN-MS-30 | B6: Project Durations(Completed) | C6: 101 | D6: 46070 | E6: 46197 | F6: 46070 | G6: 46197 | H6: 0 | I6: 0 | J6: 0 | K6: 1 | L6: 1 | M6: 4100 | N6: 4100 | O6: 4100 | P6: No | Q6: 1 | R6: 1 | S6: 0 | T6: 0
A7: PG-GN-MS-30_R | B7: Project Durations(Remaining) | C7: 148 | D7: 46198 | E7: 46371 | F7: 46204 | H7: 0 | I7: 0 | J7: 0 | K7: 0.6486 | L7: 0.65 | M7: 5900 | N7: 3827 | O7: 3835 | P7: No | Q7: 1 | R7: 0 | S7: 1 | T7: 0
A8: PG-GN-MS-20 | B8: Project Completion Date | C8: 0 | E8: 46372 | H8: 0 | I8: 0 | J8: 0 | K8: 0 | L8: 0 | M8: 0 | N8: 0 | O8: 0 | P8: Yes | Q8: 1 | R8: 0 | S8: 0 | T8: 1
A9: CONTRACUAL MILESTONES | C9: 188 | D9: 46147 | E9: 46372 | F9: 46147 | H9: 0 | I9: 0 | J9: 0 | K9: 0 | L9: 0 | M9: 0 | N9: 0 | O9: 0 | Q9: 6 | R9: 2 | S9: 0 | T9: 4
A10: PG-IN-MS-20 | B10: Completion of Earthworks (Cut and fill) For Site Layout | C10: 0 | E10: 46147 | G10: 46147 | H10: 0 | I10: 0 | J10: 0 | K10: 1 | L10: 1 | M10: 0 | N10: 0 | O10: 0 | P10: No | Q10: 1 | R10: 1 | S10: 0 | T10: 0
A11: PG-IN-MS-10 | B11: Site Preparation, Work Plans, Schedule ,Drawings Submittals | C11: 0 | E11: 46238 | G11: 46281 | H11: 0 | I11: 0 | J11: 0 | K11: 1 | L11: 1 | M11: 0 | N11: 0 | O11: 0 | P11: No | Q11: 1 | R11: 1 | S11: 0 | T11: 0
A12: PG-IN-MS-30 | B12: Completion of Toilet Building | C12: 0 | E12: 46323 | H12: 0 | I12: 0 | J12: 0 | K12: 0 | L12: 0 | M12: 0 | N12: 0 | O12: 0 | P12: No | Q12: 1 | R12: 0 | S12: 0 | T12: 1
A13: PG-IN-MS-50 | B13: Completion of Playground Works | C13: 0 | E13: 46363 | H13: 0 | I13: 0 | J13: 0 | K13: 0 | L13: 0 | M13: 0 | N13: 0 | O13: 0 | P13: No | Q13: 1 | R13: 0 | S13: 0 | T13: 1
A14: PG-IN-MS-40 | B14: Completion of Landscape Works | C14: 0 | E14: 46372 | H14: 0 | I14: 0 | J14: 0 | K14: 0 | L14: 0 | M14: 0 | N14: 0 | O14: 0 | P14: Yes | Q14: 1 | R14: 0 | S14: 0 | T14: 1
A15: PG-IN-MS-60 | B15: Substantial Completion - All Works | C15: 0 | E15: 46372 | H15: 0 | I15: 0 | J15: 0 | K15: 0 | L15: 0 | M15: 0 | N15: 0 | O15: 0 | P15: Yes | Q15: 1 | R15: 0 | S15: 0 | T15: 1
A16: QASSIM | C16: 250 | D16: 46070 | E16: 46372 | F16: 46070 | H16: 14262756 | I16: 12338896 | J16: 17537540 | K16: 0.8133 | L16: 0.7036 | M16: 8496 | N16: 6820 | O16: 6127 | Q16: 667 | R16: 554 | S16: 86 | T16: 27
A17: MOBILIZATION | C17: 29 | D17: 46070 | E17: 46110 | F17: 46070 | G17: 46109 | H17: 0 | I17: 0 | J17: 0 | K17: 0 | L17: 0 | M17: 0 | N17: 0 | O17: 0 | Q17: 9 | R17: 9 | S17: 0 | T17: 0
A18: TEMPORARY CAMP | C18: 28 | D18: 46070 | E18: 46109 | F18: 46070 | G18: 46108 | H18: 0 | I18: 0 | J18: 0 | K18: 0 | L18: 0 | M18: 0 | N18: 0 | O18: 0 | Q18: 4 | R18: 4 | S18: 0 | T18: 0
A19: PG-Q-MOB-CAM-10 | B19: Temporary Underground Utilities works | C19: 28 | D19: 46070 | E19: 46109 | F19: 46070 | G19: 46108 | H19: 0 | I19: 0 | J19: 0 | K19: 1 | L19: 1 | M19: 0 | N19: 0 | O19: 0 | P19: No | Q19: 1 | R19: 1 | S19: 0 | T19: 0
A20: PG-Q-MOB-CAM-20 | B20: Temporary Porta-Cabins | C20: 21 | D20: 46079 | E20: 46109 | F20: 46079 | G20: 46108 | H20: 0 | I20: 0 | J20: 0 | K20: 1 | L20: 1 | M20: 0 | N20: 0 | O20: 0 | P20: No | Q20: 1 | R20: 1 | S20: 0 | T20: 0
A21: PG-Q-MOB-CAM-30 | B21: Temporary Toilets | C21: 21 | D21: 46079 | E21: 46109 | F21: 46079 | G21: 46108 | H21: 0 | I21: 0 | J21: 0 | K21: 1 | L21: 1 | M21: 0 | N21: 0 | O21: 0 | P21: No | Q21: 1 | R21: 1 | S21: 0 | T21: 0
A22: PG-Q-MOB-CAM-40 | B22: Temporary Mosque | C22: 13 | D22: 46089 | E22: 46109 | F22: 46089 | G22: 46108 | H22: 0 | I22: 0 | J22: 0 | K22: 1 | L22: 1 | M22: 0 | N22: 0 | O22: 0 | P22: No | Q22: 1 | R22: 1 | S22: 0 | T22: 0
A23: SITE OFFICES | C23: 29 | D23: 46070 | E23: 46110 | F23: 46070 | G23: 46109 | H23: 0 | I23: 0 | J23: 0 | K23: 0 | L23: 0 | M23: 0 | N23: 0 | O23: 0 | Q23: 5 | R23: 5 | S23: 0 | T23: 0
A24: PG-Q-MOB-SO-10 | B24: Temporary Underground Utilities works | C24: 29 | D24: 46070 | E24: 46110 | F24: 46070 | G24: 46109 | H24: 0 | I24: 0 | J24: 0 | K24: 1 | L24: 1 | M24: 0 | N24: 0 | O24: 0 | P24: No | Q24: 1 | R24: 1 | S24: 0 | T24: 0
A25: PG-Q-MOB-SO-20 | B25: Temporary Porta-Cabins | C25: 22 | D25: 46079 | E25: 46110 | F25: 46079 | G25: 46109 | H25: 0 | I25: 0 | J25: 0 | K25: 1 | L25: 1 | M25: 0 | N25: 0 | O25: 0 | P25: No | Q25: 1 | R25: 1 | S25: 0 | T25: 0
A26: PG-Q-MOB-SO-30 | B26: Temporary Toilets | C26: 22 | D26: 46079 | E26: 46110 | F26: 46079 | G26: 46109 | H26: 0 | I26: 0 | J26: 0 | K26: 1 | L26: 1 | M26: 0 | N26: 0 | O26: 0 | P26: No | Q26: 1 | R26: 1 | S26: 0 | T26: 0
A27: PG-Q-MOB-SO-40 | B27: Temporary Mosque | C27: 16 | D27: 46086 | E27: 46110 | F27: 46086 | G27: 46109 | H27: 0 | I27: 0 | J27: 0 | K27: 1 | L27: 1 | M27: 0 | N27: 0 | O27: 0 | P27: No | Q27: 1 | R27: 1 | S27: 0 | T27: 0
A28: PG-Q-MOB-SO-50 | B28: Car Parking Area | C28: 10 | D28: 46093 | E28: 46110 | F28: 46093 | G28: 46109 | H28: 0 | I28: 0 | J28: 0 | K28: 1 | L28: 1 | M28: 0 | N28: 0 | O28: 0 | P28: No | Q28: 1 | R28: 1 | S28: 0 | T28: 0
A29: GENERAL REQUIEREMENTS | C29: 57 | D29: 46070 | E29: 46142 | F29: 46070 | G29: 46141 | H29: 0 | I29: 0 | J29: 0 | K29: 0 | L29: 0 | M29: 0 | N29: 0 | O29: 0 | Q29: 4 | R29: 4 | S29: 0 | T29: 0
A30: PG-Q-GEN-20 | B30: HSSE Submission Plan | C30: 57 | D30: 46070 | E30: 46142 | F30: 46070 | G30: 46141 | H30: 0 | I30: 0 | J30: 0 | K30: 1 | L30: 1 | M30: 0 | N30: 0 | O30: 0 | P30: No | Q30: 1 | R30: 1 | S30: 0 | T30: 0
A31: PG-Q-GEN-30 | B31: Surveying report Submission Plan | C31: 57 | D31: 46070 | E31: 46142 | F31: 46070 | G31: 46141 | H31: 0 | I31: 0 | J31: 0 | K31: 1 | L31: 1 | M31: 0 | N31: 0 | O31: 0 | P31: No | Q31: 1 | R31: 1 | S31: 0 | T31: 0
A32: PG-Q-GEN-40 | B32: Baseline Submission | C32: 6 | D32: 46081 | E32: 46088 | F32: 46081 | G32: 46086 | H32: 0 | I32: 0 | J32: 0 | K32: 1 | L32: 1 | M32: 0 | N32: 0 | O32: 0 | P32: No | Q32: 1 | R32: 1 | S32: 0 | T32: 0
A33: PG-Q-GEN-10 | B33: QA/QC Submission Plan | C33: 16 | D33: 46093 | E33: 46116 | F33: 46093 | G33: 46116 | H33: 0 | I33: 0 | J33: 0 | K33: 1 | L33: 1 | M33: 0 | N33: 0 | O33: 0 | P33: No | Q33: 1 | R33: 1 | S33: 0 | T33: 0
A34: ENGINEERING | C34: 146 | D34: 46070 | E34: 46250 | F34: 46070 | H34: 526126.2 | I34: 526126.2 | J34: 526126.2 | K34: 1 | L34: 1 | M34: 0 | N34: 0 | O34: 0 | Q34: 262 | R34: 258 | S34: 4 | T34: 0
A35: SHOP DRAWINGS SUBMITTALS | C35: 136 | D35: 46070 | E35: 46238 | F35: 46070 | H35: 0 | I35: 0 | J35: 0 | K35: 0 | L35: 0 | M35: 0 | N35: 0 | O35: 0 | Q35: 62 | R35: 58 | S35: 4 | T35: 0
A36: STRUCTURAL DRAWINGS | C36: 111 | D36: 46070 | E36: 46209 | F36: 46070 | G36: 46214 | H36: 0 | I36: 0 | J36: 0 | K36: 0 | L36: 0 | M36: 0 | N36: 0 | O36: 0 | Q36: 12 | R36: 12 | S36: 0 | T36: 0
A37: PROJECT FENCE | C37: 19 | D37: 46141 | E37: 46163 | F37: 46141 | G37: 46162 | H37: 0 | I37: 0 | J37: 0 | K37: 0 | L37: 0 | M37: 0 | N37: 0 | O37: 0 | Q37: 2 | R37: 2 | S37: 0 | T37: 0
A38: PG-Q-EN-ST-SD-SB-10 | B38: Excavation Drawings | C38: 19 | D38: 46141 | E38: 46163 | F38: 46141 | G38: 46162 | H38: 0 | I38: 0 | J38: 0 | K38: 1 | L38: 1 | M38: 0 | N38: 0 | O38: 0 | P38: No | Q38: 1 | R38: 1 | S38: 0 | T38: 0
A39: PG-Q-EN-ST-SD-SB-20 | B39: Foundation Drawings | C39: 19 | D39: 46141 | E39: 46163 | F39: 46141 | G39: 46162 | H39: 0 | I39: 0 | J39: 0 | K39: 1 | L39: 1 | M39: 0 | N39: 0 | O39: 0 | P39: No | Q39: 1 | R39: 1 | S39: 0 | T39: 0
A40: PADEL PLAYGROUND FENCE | C40: 19 | D40: 46141 | E40: 46163 | F40: 46141 | G40: 46162 | H40: 0 | I40: 0 | J40: 0 | K40: 0 | L40: 0 | M40: 0 | N40: 0 | O40: 0 | Q40: 2 | R40: 2 | S40: 0 | T40: 0
A41: PG-Q-EN-ST-SD-SB-30 | B41: Excavation Drawings | C41: 19 | D41: 46141 | E41: 46163 | F41: 46141 | G41: 46162 | H41: 0 | I41: 0 | J41: 0 | K41: 1 | L41: 1 | M41: 0 | N41: 0 | O41: 0 | P41: No | Q41: 1 | R41: 1 | S41: 0 | T41: 0
A42: PG-Q-EN-ST-SD-SB-40 | B42: Foundation Drawings | C42: 19 | D42: 46141 | E42: 46163 | F42: 46141 | G42: 46162 | H42: 0 | I42: 0 | J42: 0 | K42: 1 | L42: 1 | M42: 0 | N42: 0 | O42: 0 | P42: No | Q42: 1 | R42: 1 | S42: 0 | T42: 0
A43: AIR DOME | C43: 10 | D43: 46198 | E43: 46209 | F43: 46204 | G43: 46214 | H43: 0 | I43: 0 | J43: 0 | K43: 0 | L43: 0 | M43: 0 | N43: 0 | O43: 0 | Q43: 2 | R43: 2 | S43: 0 | T43: 0
A44: PG-Q-EN-ST-SD-SB-50 | B44: Excavation Drawings | C44: 8 | D44: 46198 | E44: 46207 | F44: 46204 | G44: 46205 | H44: 0 | I44: 0 | J44: 0 | K44: 1 | L44: 1 | M44: 0 | N44: 0 | O44: 0 | P44: No | Q44: 1 | R44: 1 | S44: 0 | T44: 0
A45: PG-Q-EN-ST-SD-SB-60 | B45: Foundation Drawings | C45: 10 | D45: 46198 | E45: 46209 | F45: 46210 | G45: 46214 | H45: 0 | I45: 0 | J45: 0 | K45: 1 | L45: 1 | M45: 0 | N45: 0 | O45: 0 | P45: No | Q45: 1 | R45: 1 | S45: 0 | T45: 0
A46: TOILET BUILDING | C46: 43 | D46: 46070 | E46: 46126 | F46: 46070 | G46: 46125 | H46: 0 | I46: 0 | J46: 0 | K46: 0 | L46: 0 | M46: 0 | N46: 0 | O46: 0 | Q46: 2 | R46: 2 | S46: 0 | T46: 0
A47: PG-Q-EN-ST-SD-SB-70 | B47: Excavation Drawings | C47: 43 | D47: 46070 | E47: 46126 | F47: 46070 | G47: 46125 | H47: 0 | I47: 0 | J47: 0 | K47: 1 | L47: 1 | M47: 0 | N47: 0 | O47: 0 | P47: No | Q47: 1 | R47: 1 | S47: 0 | T47: 0
A48: PG-Q-EN-ST-SD-SB-80 | B48: Foundation Drawings | C48: 41 | D48: 46072 | E48: 46126 | F48: 46072 | G48: 46125 | H48: 0 | I48: 0 | J48: 0 | K48: 1 | L48: 1 | M48: 0 | N48: 0 | O48: 0 | P48: No | Q48: 1 | R48: 1 | S48: 0 | T48: 0
A49: WATER STORAGE TANK | C49: 41 | D49: 46072 | E49: 46126 | F49: 46072 | G49: 46125 | H49: 0 | I49: 0 | J49: 0 | K49: 0 | L49: 0 | M49: 0 | N49: 0 | O49: 0 | Q49: 2 | R49: 2 | S49: 0 | T49: 0
A50: PG-Q-EN-ST-SD-SB-90 | B50: Excavation Drawings | C50: 41 | D50: 46072 | E50: 46126 | F50: 46072 | G50: 46125 | H50: 0 | I50: 0 | J50: 0 | K50: 1 | L50: 1 | M50: 0 | N50: 0 | O50: 0 | P50: No | Q50: 1 | R50: 1 | S50: 0 | T50: 0
A51: PG-Q-EN-ST-SD-SB-100 | B51: Foundation Drawings | C51: 39 | D51: 46076 | E51: 46126 | F51: 46076 | G51: 46125 | H51: 0 | I51: 0 | J51: 0 | K51: 1 | L51: 1 | M51: 0 | N51: 0 | O51: 0 | P51: No | Q51: 1 | R51: 1 | S51: 0 | T51: 0
A52: SEPTIC TANK | C52: 13 | D52: 46140 | E52: 46155 | F52: 46140 | G52: 46154 | H52: 0 | I52: 0 | J52: 0 | K52: 0 | L52: 0 | M52: 0 | N52: 0 | O52: 0 | Q52: 2 | R52: 2 | S52: 0 | T52: 0
A53: PG-Q-EN-ST-SD-SB-110 | B53: Reinforcement Detail Drawings | C53: 13 | D53: 46140 | E53: 46155 | F53: 46140 | G53: 46154 | H53: 0 | I53: 0 | J53: 0 | K53: 1 | L53: 1 | M53: 0 | N53: 0 | O53: 0 | P53: No | Q53: 1 | R53: 1 | S53: 0 | T53: 0
A54: PG-Q-EN-ST-SD-SB-120 | B54: Concrete Detail Drawings | C54: 13 | D54: 46140 | E54: 46155 | F54: 46140 | G54: 46154 | H54: 0 | I54: 0 | J54: 0 | K54: 1 | L54: 1 | M54: 0 | N54: 0 | O54: 0 | P54: No | Q54: 1 | R54: 1 | S54: 0 | T54: 0
A55: ARCHITECTURAL DRAWINGS | C55: 124 | D55: 46072 | E55: 46226 | F55: 46072 | G55: 46275 | H55: 0 | I55: 0 | J55: 0 | K55: 0 | L55: 0 | M55: 0 | N55: 0 | O55: 0 | Q55: 13 | R55: 13 | S55: 0 | T55: 0
A56: TOILET BUILDING | C56: 42 | D56: 46072 | E56: 46127 | F56: 46072 | G56: 46127 | H56: 0 | I56: 0 | J56: 0 | K56: 0 | L56: 0 | M56: 0 | N56: 0 | O56: 0 | Q56: 10 | R56: 10 | S56: 0 | T56: 0
A57: PG-Q-EN-AR-SD-SB-10 | B57: Ground Floor Plan | C57: 40 | D57: 46072 | E57: 46125 | F57: 46072 | G57: 46125 | H57: 0 | I57: 0 | J57: 0 | K57: 1 | L57: 1 | M57: 0 | N57: 0 | O57: 0 | P57: No | Q57: 1 | R57: 1 | S57: 0 | T57: 0
A58: PG-Q-EN-AR-SD-SB-20 | B58: Roof Floor Plan | C58: 37 | D58: 46078 | E58: 46126 | F58: 46078 | G58: 46125 | H58: 0 | I58: 0 | J58: 0 | K58: 1 | L58: 1 | M58: 0 | N58: 0 | O58: 0 | P58: No | Q58: 1 | R58: 1 | S58: 0 | T58: 0
A59: PG-Q-EN-AR-SD-SB-50 | B59: Floor Finish Layout | C59: 36 | D59: 46078 | E59: 46125 | F59: 46078 | G59: 46125 | H59: 0 | I59: 0 | J59: 0 | K59: 1 | L59: 1 | M59: 0 | N59: 0 | O59: 0 | P59: No | Q59: 1 | R59: 1 | S59: 0 | T59: 0
A60: PG-Q-EN-AR-SD-SB-60 | B60: Reflected Ceiling Layout | C60: 37 | D60: 46078 | E60: 46125 | F60: 46078 | G60: 46125 | H60: 0 | I60: 0 | J60: 0 | K60: 1 | L60: 1 | M60: 0 | N60: 0 | O60: 0 | P60: No | Q60: 1 | R60: 1 | S60: 0 | T60: 0
A61: PG-Q-EN-AR-SD-SB-70 | B61: Enlarged Toilets Layout | C61: 38 | D61: 46078 | E61: 46127 | F61: 46078 | G61: 46127 | H61: 0 | I61: 0 | J61: 0 | K61: 1 | L61: 1 | M61: 0 | N61: 0 | O61: 0 | P61: No | Q61: 1 | R61: 1 | S61: 0 | T61: 0
A62: PG-Q-EN-AR-SD-SB-30 | B62: Elevations | C62: 34 | D62: 46082 | E62: 46126 | F62: 46082 | G62: 46125 | H62: 0 | I62: 0 | J62: 0 | K62: 1 | L62: 1 | M62: 0 | N62: 0 | O62: 0 | P62: No | Q62: 1 | R62: 1 | S62: 0 | T62: 0
A63: PG-Q-EN-AR-SD-SB-80 | B63: Doors & Windows Schedule | C63: 35 | D63: 46082 | E63: 46127 | F63: 46082 | G63: 46127 | H63: 0 | I63: 0 | J63: 0 | K63: 1 | L63: 1 | M63: 0 | N63: 0 | O63: 0 | P63: No | Q63: 1 | R63: 1 | S63: 0 | T63: 0
A64: PG-Q-EN-AR-SD-SB-90 | B64: Aluminum Work | C64: 35 | D64: 46082 | E64: 46127 | F64: 46082 | G64: 46127 | H64: 0 | I64: 0 | J64: 0 | K64: 1 | L64: 1 | M64: 0 | N64: 0 | O64: 0 | P64: No | Q64: 1 | R64: 1 | S64: 0 | T64: 0
A65: PG-Q-EN-AR-SD-SB-100 | B65: Cladding Details | C65: 34 | D65: 46082 | E65: 46126 | F65: 46082 | G65: 46125 | H65: 0 | I65: 0 | J65: 0 | K65: 1 | L65: 1 | M65: 0 | N65: 0 | O65: 0 | P65: No | Q65: 1 | R65: 1 | S65: 0 | T65: 0
A66: PG-Q-EN-AR-SD-SB-40 | B66: Sections | C66: 32 | D66: 46084 | E66: 46125 | F66: 46084 | G66: 46125 | H66: 0 | I66: 0 | J66: 0 | K66: 1 | L66: 1 | M66: 0 | N66: 0 | O66: 0 | P66: No | Q66: 1 | R66: 1 | S66: 0 | T66: 0
A67: AIR DOME | C67: 15 | D67: 46210 | E67: 46226 | F67: 46248 | G67: 46275 | H67: 0 | I67: 0 | J67: 0 | K67: 0 | L67: 0 | M67: 0 | N67: 0 | O67: 0 | Q67: 3 | R67: 3 | S67: 0 | T67: 0
A68: PG-Q-EN-AR-SD-SB-110 | B68: Membrane & Insulation Details | C68: 15 | D68: 46210 | E68: 46226 | F68: 46248 | G68: 46275 | H68: 0 | I68: 0 | J68: 0 | K68: 1 | L68: 1 | M68: 0 | N68: 0 | O68: 0 | P68: No | Q68: 1 | R68: 1 | S68: 0 | T68: 0
A69: PG-Q-EN-AR-SD-SB-120 | B69: Steel Cable System | C69: 15 | D69: 46210 | E69: 46226 | F69: 46248 | G69: 46275 | H69: 0 | I69: 0 | J69: 0 | K69: 1 | L69: 1 | M69: 0 | N69: 0 | O69: 0 | P69: No | Q69: 1 | R69: 1 | S69: 0 | T69: 0
A70: PG-Q-EN-AR-SD-SB-130 | B70: Doors & Access Sytem Drawings | C70: 15 | D70: 46210 | E70: 46226 | F70: 46248 | G70: 46275 | H70: 0 | I70: 0 | J70: 0 | K70: 1 | L70: 1 | M70: 0 | N70: 0 | O70: 0 | P70: No | Q70: 1 | R70: 1 | S70: 0 | T70: 0
A71: LANDSCAPE DRAWINGS | C71: 39 | D71: 46076 | E71: 46126 | F71: 46076 | G71: 46125 | H71: 0 | I71: 0 | J71: 0 | K71: 0 | L71: 0 | M71: 0 | N71: 0 | O71: 0 | Q71: 13 | R71: 13 | S71: 0 | T71: 0
A72: PG-Q-EN-LS-SD-SB-10 | B72: Hardscape Layout Plan | C72: 36 | D72: 46076 | E72: 46123 | F72: 46076 | G72: 46121 | H72: 0 | I72: 0 | J72: 0 | K72: 1 | L72: 1 | M72: 0 | N72: 0 | O72: 0 | P72: No | Q72: 1 | R72: 1 | S72: 0 | T72: 0
A73: PG-Q-EN-LS-SD-SB-20 | B73: Interlock Tile Details | C73: 36 | D73: 46076 | E73: 46123 | F73: 46076 | G73: 46121 | H73: 0 | I73: 0 | J73: 0 | K73: 1 | L73: 1 | M73: 0 | N73: 0 | O73: 0 | P73: No | Q73: 1 | R73: 1 | S73: 0 | T73: 0
A74: PG-Q-EN-LS-SD-SB-30 | B74: Stamped Concrete Pattern & Section | C74: 36 | D74: 46076 | E74: 46123 | F74: 46076 | G74: 46121 | H74: 0 | I74: 0 | J74: 0 | K74: 1 | L74: 1 | M74: 0 | N74: 0 | O74: 0 | P74: No | Q74: 1 | R74: 1 | S74: 0 | T74: 0
A75: PG-Q-EN-LS-SD-SB-40 | B75: Tartan Flooring Layout & Details | C75: 36 | D75: 46076 | E75: 46123 | F75: 46076 | G75: 46121 | H75: 0 | I75: 0 | J75: 0 | K75: 1 | L75: 1 | M75: 0 | N75: 0 | O75: 0 | P75: No | Q75: 1 | R75: 1 | S75: 0 | T75: 0
A76: PG-Q-EN-LS-SD-SB-50 | B76: Bike Path Layout & Details | C76: 36 | D76: 46076 | E76: 46123 | F76: 46076 | G76: 46121 | H76: 0 | I76: 0 | J76: 0 | K76: 1 | L76: 1 | M76: 0 | N76: 0 | O76: 0 | P76: No | Q76: 1 | R76: 1 | S76: 0 | T76: 0
A77: PG-Q-EN-LS-SD-SB-60 | B77: Walking Path layout & Details | C77: 36 | D77: 46076 | E77: 46123 | F77: 46076 | G77: 46121 | H77: 0 | I77: 0 | J77: 0 | K77: 1 | L77: 1 | M77: 0 | N77: 0 | O77: 0 | P77: No | Q77: 1 | R77: 1 | S77: 0 | T77: 0
A78: PG-Q-EN-LS-SD-SB-70 | B78: Tree Planting Plan & Details | C78: 39 | D78: 46076 | E78: 46126 | F78: 46076 | G78: 46125 | H78: 0 | I78: 0 | J78: 0 | K78: 1 | L78: 1 | M78: 0 | N78: 0 | O78: 0 | P78: No | Q78: 1 | R78: 1 | S78: 0 | T78: 0
A79: PG-Q-EN-LS-SD-SB-80 | B79: Traffic Sign Location & Details | C79: 39 | D79: 46076 | E79: 46126 | F79: 46076 | G79: 46125 | H79: 0 | I79: 0 | J79: 0 | K79: 1 | L79: 1 | M79: 0 | N79: 0 | O79: 0 | P79: No | Q79: 1 | R79: 1 | S79: 0 | T79: 0
A80: PG-Q-EN-LS-SD-SB-90 | B80: Football Playground Layout | C80: 39 | D80: 46076 | E80: 46126 | F80: 46076 | G80: 46125 | H80: 0 | I80: 0 | J80: 0 | K80: 1 | L80: 1 | M80: 0 | N80: 0 | O80: 0 | P80: No | Q80: 1 | R80: 1 | S80: 0 | T80: 0
A81: PG-Q-EN-LS-SD-SB-100 | B81: Padel Playground Layout | C81: 39 | D81: 46076 | E81: 46126 | F81: 46076 | G81: 46125 | H81: 0 | I81: 0 | J81: 0 | K81: 1 | L81: 1 | M81: 0 | N81: 0 | O81: 0 | P81: No | Q81: 1 | R81: 1 | S81: 0 | T81: 0
A82: PG-Q-EN-LS-SD-SB-110 | B82: Basketball Playground Layout | C82: 39 | D82: 46076 | E82: 46126 | F82: 46076 | G82: 46125 | H82: 0 | I82: 0 | J82: 0 | K82: 1 | L82: 1 | M82: 0 | N82: 0 | O82: 0 | P82: No | Q82: 1 | R82: 1 | S82: 0 | T82: 0
A83: PG-Q-EN-LS-SD-SB-120 | B83: Playground Details | C83: 39 | D83: 46076 | E83: 46126 | F83: 46076 | G83: 46125 | H83: 0 | I83: 0 | J83: 0 | K83: 1 | L83: 1 | M83: 0 | N83: 0 | O83: 0 | P83: No | Q83: 1 | R83: 1 | S83: 0 | T83: 0
A84: PG-Q-EN-LS-SD-SB-130 | B84: Padel Fence Elevation & Details | C84: 39 | D84: 46076 | E84: 46126 | F84: 46076 | G84: 46125 | H84: 0 | I84: 0 | J84: 0 | K84: 1 | L84: 1 | M84: 0 | N84: 0 | O84: 0 | P84: No | Q84: 1 | R84: 1 | S84: 0 | T84: 0
A85: MECHANICAL DRAWINGS | C85: 111 | D85: 46081 | E85: 46218 | F85: 46081 | H85: 0 | I85: 0 | J85: 0 | K85: 0 | L85: 0 | M85: 0 | N85: 0 | O85: 0 | Q85: 10 | R85: 9 | S85: 1 | T85: 0
A86: WATER SUPPLY SYSTEM | C86: 32 | D86: 46081 | E86: 46123 | F86: 46081 | G86: 46121 | H86: 0 | I86: 0 | J86: 0 | K86: 0 | L86: 0 | M86: 0 | N86: 0 | O86: 0 | Q86: 4 | R86: 4 | S86: 0 | T86: 0
A87: PG-Q-EN-ME-SD-SB-20 | B87: Pump Room Layout | C87: 32 | D87: 46081 | E87: 46123 | F87: 46081 | G87: 46121 | H87: 0 | I87: 0 | J87: 0 | K87: 1 | L87: 1 | M87: 0 | N87: 0 | O87: 0 | P87: No | Q87: 1 | R87: 1 | S87: 0 | T87: 0
A88: PG-Q-EN-ME-SD-SB-10 | B88: Cold & Hot Water Piping Layout | C88: 28 | D88: 46085 | E88: 46123 | F88: 46085 | G88: 46121 | H88: 0 | I88: 0 | J88: 0 | K88: 1 | L88: 1 | M88: 0 | N88: 0 | O88: 0 | P88: No | Q88: 1 | R88: 1 | S88: 0 | T88: 0
A89: PG-Q-EN-ME-SD-SB-30 | B89: Booster Pump Details | C89: 28 | D89: 46085 | E89: 46123 | F89: 46085 | G89: 46121 | H89: 0 | I89: 0 | J89: 0 | K89: 1 | L89: 1 | M89: 0 | N89: 0 | O89: 0 | P89: No | Q89: 1 | R89: 1 | S89: 0 | T89: 0
A90: PG-Q-EN-ME-SD-SB-40 | B90: GRP Water Tank Details | C90: 24 | D90: 46090 | E90: 46123 | F90: 46090 | G90: 46121 | H90: 0 | I90: 0 | J90: 0 | K90: 1 | L90: 1 | M90: 0 | N90: 0 | O90: 0 | P90: No | Q90: 1 | R90: 1 | S90: 0 | T90: 0
A91: SEWER AND DRAINAGE SYSTEM | C91: 28 | D91: 46085 | E91: 46123 | F91: 46085 | G91: 46121 | H91: 0 | I91: 0 | J91: 0 | K91: 0 | L91: 0 | M91: 0 | N91: 0 | O91: 0 | Q91: 3 | R91: 3 | S91: 0 | T91: 0
A92: PG-Q-EN-ME-SD-SB-50 | B92: Drainage Layout | C92: 28 | D92: 46085 | E92: 46123 | F92: 46085 | G92: 46121 | H92: 0 | I92: 0 | J92: 0 | K92: 1 | L92: 1 | M92: 0 | N92: 0 | O92: 0 | P92: No | Q92: 1 | R92: 1 | S92: 0 | T92: 0
A93: PG-Q-EN-ME-SD-SB-60 | B93: Floor Drains & Cleanouts Details | C93: 24 | D93: 46090 | E93: 46123 | F93: 46090 | G93: 46121 | H93: 0 | I93: 0 | J93: 0 | K93: 1 | L93: 1 | M93: 0 | N93: 0 | O93: 0 | P93: No | Q93: 1 | R93: 1 | S93: 0 | T93: 0
A94: PG-Q-EN-ME-SD-SB-70 | B94: Inspection Chamber Details | C94: 21 | D94: 46093 | E94: 46123 | F94: 46093 | G94: 46121 | H94: 0 | I94: 0 | J94: 0 | K94: 1 | L94: 1 | M94: 0 | N94: 0 | O94: 0 | P94: No | Q94: 1 | R94: 1 | S94: 0 | T94: 0
A95: IRRIGATION SYSTEM | C95: 24 | D95: 46090 | E95: 46123 | F95: 46090 | G95: 46121 | H95: 0 | I95: 0 | J95: 0 | K95: 0 | L95: 0 | M95: 0 | N95: 0 | O95: 0 | Q95: 2 | R95: 2 | S95: 0 | T95: 0
A96: PG-Q-EN-ME-SD-SB-80 | B96: HDPE Pipe Routing | C96: 24 | D96: 46090 | E96: 46123 | F96: 46090 | G96: 46121 | H96: 0 | I96: 0 | J96: 0 | K96: 1 | L96: 1 | M96: 0 | N96: 0 | O96: 0 | P96: No | Q96: 1 | R96: 1 | S96: 0 | T96: 0
A97: PG-Q-EN-ME-SD-SB-90 | B97: Irrigation Network Layout | C97: 21 | D97: 46093 | E97: 46123 | F97: 46093 | G97: 46121 | H97: 0 | I97: 0 | J97: 0 | K97: 1 | L97: 1 | M97: 0 | N97: 0 | O97: 0 | P97: No | Q97: 1 | R97: 1 | S97: 0 | T97: 0
A98: AIR DOME | C98: 18 | D98: 46198 | E98: 46218 | F98: 46233 | H98: 0 | I98: 0 | J98: 0 | K98: 0 | L98: 0 | M98: 0 | N98: 0 | O98: 0 | Q98: 1 | R98: 0 | S98: 1 | T98: 0
A99: PG-Q-EN-ME-SD-SB-100 | B99: Air Package and HVAC System Drawings | C99: 18 | D99: 46198 | E99: 46218 | F99: 46233 | H99: 0 | I99: 0 | J99: 0 | K99: 1 | L99: 0.9 | M99: 0 | N99: 0 | O99: 0 | P99: Yes | Q99: 1 | R99: 0 | S99: 1 | T99: 0
A100: ELECTRICAL DRAWINGS | C100: 70 | D100: 46153 | E100: 46238 | F100: 46153 | H100: 0 | I100: 0 | J100: 0 | K100: 0 | L100: 0 | M100: 0 | N100: 0 | O100: 0 | Q100: 14 | R100: 11 | S100: 3 | T100: 0
...

Sheet Previous Week
A1: Activity ID | B1: Activity Name | C1: BL Project Duration | D1: BL Project Start | E1: BL Project Finish | F1: Actual Start | G1: Actual Finish | H1: Planned Value Cost | I1: Earned Value Cost | J1: Budgeted Total Cost | K1: Schedule % Complete | L1: Performance % Complete | M1: Budgeted Labor Units | N1: Planned Value Labor Units | O1: Earned Value Labor Units | P1: Critical | Q1: Activity Count | R1: Actual Completed Activities | S1: Actual In-Progress Activities | T1: Actual Not-Started Activities
A2: PLAYGROUNDS INITIATIVE - QASSIM, HAIL & TABUK - 11-Oct-2026 | C2: 250 | D2: 46070 | E2: 46372 | F2: 46070 | H2: 27323138 | I2: 23227345 | J2: 35709993 | K2: 0.7688 | L2: 0.6536 | M2: 33340 | N2: 25456 | O2: 22804 | Q2: 1929 | R2: 1591 | S2: 205 | T2: 133
A3: MILESTONES | C3: 250 | D3: 46070 | E3: 46372 | F3: 46070 | H3: 0 | I3: 0 | J3: 0 | K3: 0 | L3: 0 | M3: 10000 | N3: 7700 | O3: 7050 | Q3: 10 | R3: 4 | S3: 1 | T3: 5
A4: GENERAL MILESTONES | C4: 250 | D4: 46070 | E4: 46372 | F4: 46070 | H4: 0 | I4: 0 | J4: 0 | K4: 0 | L4: 0 | M4: 10000 | N4: 7700 | O4: 7050 | Q4: 4 | R4: 2 | S4: 1 | T4: 1
A5: PG-GN-MS-10 | B5: Project Commencement Date | C5: 0 | D5: 46070 | F5: 46070 | H5: 0 | I5: 0 | J5: 0 | K5: 1 | L5: 1 | M5: 0 | N5: 0 | O5: 0 | P5: No | Q5: 1 | R5: 1 | S5: 0 | T5: 0
A6: PG-GN-MS-30 | B6: Project Durations(Completed) | C6: 101 | D6: 46070 | E6: 46197 | F6: 46070 | G6: 46197 | H6: 0 | I6: 0 | J6: 0 | K6: 1 | L6: 1 | M6: 4100 | N6: 4100 | O6: 4100 | P6: No | Q6: 1 | R6: 1 | S6: 0 | T6: 0
A7: PG-GN-MS-30_R | B7: Project Durations(Remaining) | C7: 148 | D7: 46198 | E7: 46371 | F7: 46204 | H7: 0 | I7: 0 | J7: 0 | K7: 0.6102 | L7: 0.5 | M7: 5900 | N7: 3600 | O7: 2950 | P7: Yes | Q7: 1 | R7: 0 | S7: 1 | T7: 0
A8: PG-GN-MS-20 | B8: Project Completion Date | C8: 0 | E8: 46372 | H8: 0 | I8: 0 | J8: 0 | K8: 0 | L8: 0 | M8: 0 | N8: 0 | O8: 0 | P8: Yes | Q8: 1 | R8: 0 | S8: 0 | T8: 1
A9: CONTRACUAL MILESTONES | C9: 188 | D9: 46147 | E9: 46372 | F9: 46147 | H9: 0 | I9: 0 | J9: 0 | K9: 0 | L9: 0 | M9: 0 | N9: 0 | O9: 0 | Q9: 6 | R9: 2 | S9: 0 | T9: 4
A10: PG-IN-MS-20 | B10: Completion of Earthworks (Cut and fill) For Site Layout | C10: 0 | E10: 46147 | G10: 46147 | H10: 0 | I10: 0 | J10: 0 | K10: 1 | L10: 1 | M10: 0 | N10: 0 | O10: 0 | P10: No | Q10: 1 | R10: 1 | S10: 0 | T10: 0
A11: PG-IN-MS-10 | B11: Site Preparation, Work Plans, Schedule ,Drawings Submittals | C11: 0 | E11: 46238 | G11: 46281 | H11: 0 | I11: 0 | J11: 0 | K11: 1 | L11: 1 | M11: 0 | N11: 0 | O11: 0 | P11: No | Q11: 1 | R11: 1 | S11: 0 | T11: 0
A12: PG-IN-MS-30 | B12: Completion of Toilet Building | C12: 0 | E12: 46323 | H12: 0 | I12: 0 | J12: 0 | K12: 0 | L12: 0 | M12: 0 | N12: 0 | O12: 0 | P12: Yes | Q12: 1 | R12: 0 | S12: 0 | T12: 1
A13: PG-IN-MS-50 | B13: Completion of Playground Works | C13: 0 | E13: 46363 | H13: 0 | I13: 0 | J13: 0 | K13: 0 | L13: 0 | M13: 0 | N13: 0 | O13: 0 | P13: No | Q13: 1 | R13: 0 | S13: 0 | T13: 1
A14: PG-IN-MS-40 | B14: Completion of Landscape Works | C14: 0 | E14: 46372 | H14: 0 | I14: 0 | J14: 0 | K14: 0 | L14: 0 | M14: 0 | N14: 0 | O14: 0 | P14: Yes | Q14: 1 | R14: 0 | S14: 0 | T14: 1
A15: PG-IN-MS-60 | B15: Substantial Completion - All Works | C15: 0 | E15: 46372 | H15: 0 | I15: 0 | J15: 0 | K15: 0 | L15: 0 | M15: 0 | N15: 0 | O15: 0 | P15: Yes | Q15: 1 | R15: 0 | S15: 0 | T15: 1
A16: QASSIM | C16: 250 | D16: 46070 | E16: 46372 | F16: 46070 | H16: 13745803 | I16: 11669637 | J16: 17537540 | K16: 0.7915 | L16: 0.672 | M16: 8496 | N16: 6412 | O16: 5660 | Q16: 667 | R16: 552 | S16: 66 | T16: 49
A17: MOBILIZATION | C17: 29 | D17: 46070 | E17: 46110 | F17: 46070 | G17: 46109 | H17: 0 | I17: 0 | J17: 0 | K17: 0 | L17: 0 | M17: 0 | N17: 0 | O17: 0 | Q17: 9 | R17: 9 | S17: 0 | T17: 0
A18: TEMPORARY CAMP | C18: 28 | D18: 46070 | E18: 46109 | F18: 46070 | G18: 46108 | H18: 0 | I18: 0 | J18: 0 | K18: 0 | L18: 0 | M18: 0 | N18: 0 | O18: 0 | Q18: 4 | R18: 4 | S18: 0 | T18: 0
A19: PG-Q-MOB-CAM-10 | B19: Temporary Underground Utilities works | C19: 28 | D19: 46070 | E19: 46109 | F19: 46070 | G19: 46108 | H19: 0 | I19: 0 | J19: 0 | K19: 1 | L19: 1 | M19: 0 | N19: 0 | O19: 0 | P19: No | Q19: 1 | R19: 1 | S19: 0 | T19: 0
A20: PG-Q-MOB-CAM-20 | B20: Temporary Porta-Cabins | C20: 21 | D20: 46079 | E20: 46109 | F20: 46079 | G20: 46108 | H20: 0 | I20: 0 | J20: 0 | K20: 1 | L20: 1 | M20: 0 | N20: 0 | O20: 0 | P20: No | Q20: 1 | R20: 1 | S20: 0 | T20: 0
A21: PG-Q-MOB-CAM-30 | B21: Temporary Toilets | C21: 21 | D21: 46079 | E21: 46109 | F21: 46079 | G21: 46108 | H21: 0 | I21: 0 | J21: 0 | K21: 1 | L21: 1 | M21: 0 | N21: 0 | O21: 0 | P21: No | Q21: 1 | R21: 1 | S21: 0 | T21: 0
A22: PG-Q-MOB-CAM-40 | B22: Temporary Mosque | C22: 13 | D22: 46089 | E22: 46109 | F22: 46089 | G22: 46108 | H22: 0 | I22: 0 | J22: 0 | K22: 1 | L22: 1 | M22: 0 | N22: 0 | O22: 0 | P22: No | Q22: 1 | R22: 1 | S22: 0 | T22: 0
A23: SITE OFFICES | C23: 29 | D23: 46070 | E23: 46110 | F23: 46070 | G23: 46109 | H23: 0 | I23: 0 | J23: 0 | K23: 0 | L23: 0 | M23: 0 | N23: 0 | O23: 0 | Q23: 5 | R23: 5 | S23: 0 | T23: 0
A24: PG-Q-MOB-SO-10 | B24: Temporary Underground Utilities works | C24: 29 | D24: 46070 | E24: 46110 | F24: 46070 | G24: 46109 | H24: 0 | I24: 0 | J24: 0 | K24: 1 | L24: 1 | M24: 0 | N24: 0 | O24: 0 | P24: No | Q24: 1 | R24: 1 | S24: 0 | T24: 0
A25: PG-Q-MOB-SO-20 | B25: Temporary Porta-Cabins | C25: 22 | D25: 46079 | E25: 46110 | F25: 46079 | G25: 46109 | H25: 0 | I25: 0 | J25: 0 | K25: 1 | L25: 1 | M25: 0 | N25: 0 | O25: 0 | P25: No | Q25: 1 | R25: 1 | S25: 0 | T25: 0
A26: PG-Q-MOB-SO-30 | B26: Temporary Toilets | C26: 22 | D26: 46079 | E26: 46110 | F26: 46079 | G26: 46109 | H26: 0 | I26: 0 | J26: 0 | K26: 1 | L26: 1 | M26: 0 | N26: 0 | O26: 0 | P26: No | Q26: 1 | R26: 1 | S26: 0 | T26: 0
A27: PG-Q-MOB-SO-40 | B27: Temporary Mosque | C27: 16 | D27: 46086 | E27: 46110 | F27: 46086 | G27: 46109 | H27: 0 | I27: 0 | J27: 0 | K27: 1 | L27: 1 | M27: 0 | N27: 0 | O27: 0 | P27: No | Q27: 1 | R27: 1 | S27: 0 | T27: 0
A28: PG-Q-MOB-SO-50 | B28: Car Parking Area | C28: 10 | D28: 46093 | E28: 46110 | F28: 46093 | G28: 46109 | H28: 0 | I28: 0 | J28: 0 | K28: 1 | L28: 1 | M28: 0 | N28: 0 | O28: 0 | P28: No | Q28: 1 | R28: 1 | S28: 0 | T28: 0
A29: GENERAL REQUIEREMENTS | C29: 57 | D29: 46070 | E29: 46142 | F29: 46070 | G29: 46141 | H29: 0 | I29: 0 | J29: 0 | K29: 0 | L29: 0 | M29: 0 | N29: 0 | O29: 0 | Q29: 4 | R29: 4 | S29: 0 | T29: 0
A30: PG-Q-GEN-20 | B30: HSSE Submission Plan | C30: 57 | D30: 46070 | E30: 46142 | F30: 46070 | G30: 46141 | H30: 0 | I30: 0 | J30: 0 | K30: 1 | L30: 1 | M30: 0 | N30: 0 | O30: 0 | P30: No | Q30: 1 | R30: 1 | S30: 0 | T30: 0
A31: PG-Q-GEN-30 | B31: Surveying report Submission Plan | C31: 57 | D31: 46070 | E31: 46142 | F31: 46070 | G31: 46141 | H31: 0 | I31: 0 | J31: 0 | K31: 1 | L31: 1 | M31: 0 | N31: 0 | O31: 0 | P31: No | Q31: 1 | R31: 1 | S31: 0 | T31: 0
A32: PG-Q-GEN-40 | B32: Baseline Submission | C32: 6 | D32: 46081 | E32: 46088 | F32: 46081 | G32: 46086 | H32: 0 | I32: 0 | J32: 0 | K32: 1 | L32: 1 | M32: 0 | N32: 0 | O32: 0 | P32: No | Q32: 1 | R32: 1 | S32: 0 | T32: 0
A33: PG-Q-GEN-10 | B33: QA/QC Submission Plan | C33: 16 | D33: 46093 | E33: 46116 | F33: 46093 | G33: 46116 | H33: 0 | I33: 0 | J33: 0 | K33: 1 | L33: 1 | M33: 0 | N33: 0 | O33: 0 | P33: No | Q33: 1 | R33: 1 | S33: 0 | T33: 0
A34: ENGINEERING | C34: 146 | D34: 46070 | E34: 46250 | F34: 46070 | H34: 526126.2 | I34: 526126.2 | J34: 526126.2 | K34: 1 | L34: 1 | M34: 0 | N34: 0 | O34: 0 | Q34: 262 | R34: 258 | S34: 4 | T34: 0
A35: SHOP DRAWINGS SUBMITTALS | C35: 136 | D35: 46070 | E35: 46238 | F35: 46070 | H35: 0 | I35: 0 | J35: 0 | K35: 0 | L35: 0 | M35: 0 | N35: 0 | O35: 0 | Q35: 62 | R35: 58 | S35: 4 | T35: 0
A36: STRUCTURAL DRAWINGS | C36: 111 | D36: 46070 | E36: 46209 | F36: 46070 | G36: 46214 | H36: 0 | I36: 0 | J36: 0 | K36: 0 | L36: 0 | M36: 0 | N36: 0 | O36: 0 | Q36: 12 | R36: 12 | S36: 0 | T36: 0
A37: PROJECT FENCE | C37: 19 | D37: 46141 | E37: 46163 | F37: 46141 | G37: 46162 | H37: 0 | I37: 0 | J37: 0 | K37: 0 | L37: 0 | M37: 0 | N37: 0 | O37: 0 | Q37: 2 | R37: 2 | S37: 0 | T37: 0
A38: PG-Q-EN-ST-SD-SB-10 | B38: Excavation Drawings | C38: 19 | D38: 46141 | E38: 46163 | F38: 46141 | G38: 46162 | H38: 0 | I38: 0 | J38: 0 | K38: 1 | L38: 1 | M38: 0 | N38: 0 | O38: 0 | P38: No | Q38: 1 | R38: 1 | S38: 0 | T38: 0
A39: PG-Q-EN-ST-SD-SB-20 | B39: Foundation Drawings | C39: 19 | D39: 46141 | E39: 46163 | F39: 46141 | G39: 46162 | H39: 0 | I39: 0 | J39: 0 | K39: 1 | L39: 1 | M39: 0 | N39: 0 | O39: 0 | P39: No | Q39: 1 | R39: 1 | S39: 0 | T39: 0
A40: PADEL PLAYGROUND FENCE | C40: 19 | D40: 46141 | E40: 46163 | F40: 46141 | G40: 46162 | H40: 0 | I40: 0 | J40: 0 | K40: 0 | L40: 0 | M40: 0 | N40: 0 | O40: 0 | Q40: 2 | R40: 2 | S40: 0 | T40: 0
A41: PG-Q-EN-ST-SD-SB-30 | B41: Excavation Drawings | C41: 19 | D41: 46141 | E41: 46163 | F41: 46141 | G41: 46162 | H41: 0 | I41: 0 | J41: 0 | K41: 1 | L41: 1 | M41: 0 | N41: 0 | O41: 0 | P41: No | Q41: 1 | R41: 1 | S41: 0 | T41: 0
A42: PG-Q-EN-ST-SD-SB-40 | B42: Foundation Drawings | C42: 19 | D42: 46141 | E42: 46163 | F42: 46141 | G42: 46162 | H42: 0 | I42: 0 | J42: 0 | K42: 1 | L42: 1 | M42: 0 | N42: 0 | O42: 0 | P42: No | Q42: 1 | R42: 1 | S42: 0 | T42: 0
A43: AIR DOME | C43: 10 | D43: 46198 | E43: 46209 | F43: 46204 | G43: 46214 | H43: 0 | I43: 0 | J43: 0 | K43: 0 | L43: 0 | M43: 0 | N43: 0 | O43: 0 | Q43: 2 | R43: 2 | S43: 0 | T43: 0
A44: PG-Q-EN-ST-SD-SB-50 | B44: Excavation Drawings | C44: 8 | D44: 46198 | E44: 46207 | F44: 46204 | G44: 46205 | H44: 0 | I44: 0 | J44: 0 | K44: 1 | L44: 1 | M44: 0 | N44: 0 | O44: 0 | P44: No | Q44: 1 | R44: 1 | S44: 0 | T44: 0
A45: PG-Q-EN-ST-SD-SB-60 | B45: Foundation Drawings | C45: 10 | D45: 46198 | E45: 46209 | F45: 46210 | G45: 46214 | H45: 0 | I45: 0 | J45: 0 | K45: 1 | L45: 1 | M45: 0 | N45: 0 | O45: 0 | P45: No | Q45: 1 | R45: 1 | S45: 0 | T45: 0
A46: TOILET BUILDING | C46: 43 | D46: 46070 | E46: 46126 | F46: 46070 | G46: 46125 | H46: 0 | I46: 0 | J46: 0 | K46: 0 | L46: 0 | M46: 0 | N46: 0 | O46: 0 | Q46: 2 | R46: 2 | S46: 0 | T46: 0
A47: PG-Q-EN-ST-SD-SB-70 | B47: Excavation Drawings | C47: 43 | D47: 46070 | E47: 46126 | F47: 46070 | G47: 46125 | H47: 0 | I47: 0 | J47: 0 | K47: 1 | L47: 1 | M47: 0 | N47: 0 | O47: 0 | P47: No | Q47: 1 | R47: 1 | S47: 0 | T47: 0
A48: PG-Q-EN-ST-SD-SB-80 | B48: Foundation Drawings | C48: 41 | D48: 46072 | E48: 46126 | F48: 46072 | G48: 46125 | H48: 0 | I48: 0 | J48: 0 | K48: 1 | L48: 1 | M48: 0 | N48: 0 | O48: 0 | P48: No | Q48: 1 | R48: 1 | S48: 0 | T48: 0
A49: WATER STORAGE TANK | C49: 41 | D49: 46072 | E49: 46126 | F49: 46072 | G49: 46125 | H49: 0 | I49: 0 | J49: 0 | K49: 0 | L49: 0 | M49: 0 | N49: 0 | O49: 0 | Q49: 2 | R49: 2 | S49: 0 | T49: 0
A50: PG-Q-EN-ST-SD-SB-90 | B50: Excavation Drawings | C50: 41 | D50: 46072 | E50: 46126 | F50: 46072 | G50: 46125 | H50: 0 | I50: 0 | J50: 0 | K50: 1 | L50: 1 | M50: 0 | N50: 0 | O50: 0 | P50: No | Q50: 1 | R50: 1 | S50: 0 | T50: 0
A51: PG-Q-EN-ST-SD-SB-100 | B51: Foundation Drawings | C51: 39 | D51: 46076 | E51: 46126 | F51: 46076 | G51: 46125 | H51: 0 | I51: 0 | J51: 0 | K51: 1 | L51: 1 | M51: 0 | N51: 0 | O51: 0 | P51: No | Q51: 1 | R51: 1 | S51: 0 | T51: 0
A52: SEPTIC TANK | C52: 13 | D52: 46140 | E52: 46155 | F52: 46140 | G52: 46154 | H52: 0 | I52: 0 | J52: 0 | K52: 0 | L52: 0 | M52: 0 | N52: 0 | O52: 0 | Q52: 2 | R52: 2 | S52: 0 | T52: 0
A53: PG-Q-EN-ST-SD-SB-110 | B53: Reinforcement Detail Drawings | C53: 13 | D53: 46140 | E53: 46155 | F53: 46140 | G53: 46154 | H53: 0 | I53: 0 | J53: 0 | K53: 1 | L53: 1 | M53: 0 | N53: 0 | O53: 0 | P53: No | Q53: 1 | R53: 1 | S53: 0 | T53: 0
A54: PG-Q-EN-ST-SD-SB-120 | B54: Concrete Detail Drawings | C54: 13 | D54: 46140 | E54: 46155 | F54: 46140 | G54: 46154 | H54: 0 | I54: 0 | J54: 0 | K54: 1 | L54: 1 | M54: 0 | N54: 0 | O54: 0 | P54: No | Q54: 1 | R54: 1 | S54: 0 | T54: 0
A55: ARCHITECTURAL DRAWINGS | C55: 124 | D55: 46072 | E55: 46226 | F55: 46072 | G55: 46275 | H55: 0 | I55: 0 | J55: 0 | K55: 0 | L55: 0 | M55: 0 | N55: 0 | O55: 0 | Q55: 13 | R55: 13 | S55: 0 | T55: 0
A56: TOILET BUILDING | C56: 42 | D56: 46072 | E56: 46127 | F56: 46072 | G56: 46127 | H56: 0 | I56: 0 | J56: 0 | K56: 0 | L56: 0 | M56: 0 | N56: 0 | O56: 0 | Q56: 10 | R56: 10 | S56: 0 | T56: 0
A57: PG-Q-EN-AR-SD-SB-10 | B57: Ground Floor Plan | C57: 40 | D57: 46072 | E57: 46125 | F57: 46072 | G57: 46125 | H57: 0 | I57: 0 | J57: 0 | K57: 1 | L57: 1 | M57: 0 | N57: 0 | O57: 0 | P57: No | Q57: 1 | R57: 1 | S57: 0 | T57: 0
A58: PG-Q-EN-AR-SD-SB-20 | B58: Roof Floor Plan | C58: 37 | D58: 46078 | E58: 46126 | F58: 46078 | G58: 46125 | H58: 0 | I58: 0 | J58: 0 | K58: 1 | L58: 1 | M58: 0 | N58: 0 | O58: 0 | P58: No | Q58: 1 | R58: 1 | S58: 0 | T58: 0
A59: PG-Q-EN-AR-SD-SB-50 | B59: Floor Finish Layout | C59: 36 | D59: 46078 | E59: 46125 | F59: 46078 | G59: 46125 | H59: 0 | I59: 0 | J59: 0 | K59: 1 | L59: 1 | M59: 0 | N59: 0 | O59: 0 | P59: No | Q59: 1 | R59: 1 | S59: 0 | T59: 0
A60: PG-Q-EN-AR-SD-SB-60 | B60: Reflected Ceiling Layout | C60: 37 | D60: 46078 | E60: 46125 | F60: 46078 | G60: 46125 | H60: 0 | I60: 0 | J60: 0 | K60: 1 | L60: 1 | M60: 0 | N60: 0 | O60: 0 | P60: No | Q60: 1 | R60: 1 | S60: 0 | T60: 0
A61: PG-Q-EN-AR-SD-SB-70 | B61: Enlarged Toilets Layout | C61: 38 | D61: 46078 | E61: 46127 | F61: 46078 | G61: 46127 | H61: 0 | I61: 0 | J61: 0 | K61: 1 | L61: 1 | M61: 0 | N61: 0 | O61: 0 | P61: No | Q61: 1 | R61: 1 | S61: 0 | T61: 0
A62: PG-Q-EN-AR-SD-SB-30 | B62: Elevations | C62: 34 | D62: 46082 | E62: 46126 | F62: 46082 | G62: 46125 | H62: 0 | I62: 0 | J62: 0 | K62: 1 | L62: 1 | M62: 0 | N62: 0 | O62: 0 | P62: No | Q62: 1 | R62: 1 | S62: 0 | T62: 0
A63: PG-Q-EN-AR-SD-SB-80 | B63: Doors & Windows Schedule | C63: 35 | D63: 46082 | E63: 46127 | F63: 46082 | G63: 46127 | H63: 0 | I63: 0 | J63: 0 | K63: 1 | L63: 1 | M63: 0 | N63: 0 | O63: 0 | P63: No | Q63: 1 | R63: 1 | S63: 0 | T63: 0
A64: PG-Q-EN-AR-SD-SB-90 | B64: Aluminum Work | C64: 35 | D64: 46082 | E64: 46127 | F64: 46082 | G64: 46127 | H64: 0 | I64: 0 | J64: 0 | K64: 1 | L64: 1 | M64: 0 | N64: 0 | O64: 0 | P64: No | Q64: 1 | R64: 1 | S64: 0 | T64: 0
A65: PG-Q-EN-AR-SD-SB-100 | B65: Cladding Details | C65: 34 | D65: 46082 | E65: 46126 | F65: 46082 | G65: 46125 | H65: 0 | I65: 0 | J65: 0 | K65: 1 | L65: 1 | M65: 0 | N65: 0 | O65: 0 | P65: No | Q65: 1 | R65: 1 | S65: 0 | T65: 0
A66: PG-Q-EN-AR-SD-SB-40 | B66: Sections | C66: 32 | D66: 46084 | E66: 46125 | F66: 46084 | G66: 46125 | H66: 0 | I66: 0 | J66: 0 | K66: 1 | L66: 1 | M66: 0 | N66: 0 | O66: 0 | P66: No | Q66: 1 | R66: 1 | S66: 0 | T66: 0
A67: AIR DOME | C67: 15 | D67: 46210 | E67: 46226 | F67: 46248 | G67: 46275 | H67: 0 | I67: 0 | J67: 0 | K67: 0 | L67: 0 | M67: 0 | N67: 0 | O67: 0 | Q67: 3 | R67: 3 | S67: 0 | T67: 0
A68: PG-Q-EN-AR-SD-SB-110 | B68: Membrane & Insulation Details | C68: 15 | D68: 46210 | E68: 46226 | F68: 46248 | G68: 46275 | H68: 0 | I68: 0 | J68: 0 | K68: 1 | L68: 1 | M68: 0 | N68: 0 | O68: 0 | P68: No | Q68: 1 | R68: 1 | S68: 0 | T68: 0
A69: PG-Q-EN-AR-SD-SB-120 | B69: Steel Cable System | C69: 15 | D69: 46210 | E69: 46226 | F69: 46248 | G69: 46275 | H69: 0 | I69: 0 | J69: 0 | K69: 1 | L69: 1 | M69: 0 | N69: 0 | O69: 0 | P69: No | Q69: 1 | R69: 1 | S69: 0 | T69: 0
A70: PG-Q-EN-AR-SD-SB-130 | B70: Doors & Access Sytem Drawings | C70: 15 | D70: 46210 | E70: 46226 | F70: 46248 | G70: 46275 | H70: 0 | I70: 0 | J70: 0 | K70: 1 | L70: 1 | M70: 0 | N70: 0 | O70: 0 | P70: No | Q70: 1 | R70: 1 | S70: 0 | T70: 0
A71: LANDSCAPE DRAWINGS | C71: 39 | D71: 46076 | E71: 46126 | F71: 46076 | G71: 46125 | H71: 0 | I71: 0 | J71: 0 | K71: 0 | L71: 0 | M71: 0 | N71: 0 | O71: 0 | Q71: 13 | R71: 13 | S71: 0 | T71: 0
A72: PG-Q-EN-LS-SD-SB-10 | B72: Hardscape Layout Plan | C72: 36 | D72: 46076 | E72: 46123 | F72: 46076 | G72: 46121 | H72: 0 | I72: 0 | J72: 0 | K72: 1 | L72: 1 | M72: 0 | N72: 0 | O72: 0 | P72: No | Q72: 1 | R72: 1 | S72: 0 | T72: 0
A73: PG-Q-EN-LS-SD-SB-20 | B73: Interlock Tile Details | C73: 36 | D73: 46076 | E73: 46123 | F73: 46076 | G73: 46121 | H73: 0 | I73: 0 | J73: 0 | K73: 1 | L73: 1 | M73: 0 | N73: 0 | O73: 0 | P73: No | Q73: 1 | R73: 1 | S73: 0 | T73: 0
A74: PG-Q-EN-LS-SD-SB-30 | B74: Stamped Concrete Pattern & Section | C74: 36 | D74: 46076 | E74: 46123 | F74: 46076 | G74: 46121 | H74: 0 | I74: 0 | J74: 0 | K74: 1 | L74: 1 | M74: 0 | N74: 0 | O74: 0 | P74: No | Q74: 1 | R74: 1 | S74: 0 | T74: 0
A75: PG-Q-EN-LS-SD-SB-40 | B75: Tartan Flooring Layout & Details | C75: 36 | D75: 46076 | E75: 46123 | F75: 46076 | G75: 46121 | H75: 0 | I75: 0 | J75: 0 | K75: 1 | L75: 1 | M75: 0 | N75: 0 | O75: 0 | P75: No | Q75: 1 | R75: 1 | S75: 0 | T75: 0
A76: PG-Q-EN-LS-SD-SB-50 | B76: Bike Path Layout & Details | C76: 36 | D76: 46076 | E76: 46123 | F76: 46076 | G76: 46121 | H76: 0 | I76: 0 | J76: 0 | K76: 1 | L76: 1 | M76: 0 | N76: 0 | O76: 0 | P76: No | Q76: 1 | R76: 1 | S76: 0 | T76: 0
A77: PG-Q-EN-LS-SD-SB-60 | B77: Walking Path layout & Details | C77: 36 | D77: 46076 | E77: 46123 | F77: 46076 | G77: 46121 | H77: 0 | I77: 0 | J77: 0 | K77: 1 | L77: 1 | M77: 0 | N77: 0 | O77: 0 | P77: No | Q77: 1 | R77: 1 | S77: 0 | T77: 0
A78: PG-Q-EN-LS-SD-SB-70 | B78: Tree Planting Plan & Details | C78: 39 | D78: 46076 | E78: 46126 | F78: 46076 | G78: 46125 | H78: 0 | I78: 0 | J78: 0 | K78: 1 | L78: 1 | M78: 0 | N78: 0 | O78: 0 | P78: No | Q78: 1 | R78: 1 | S78: 0 | T78: 0
A79: PG-Q-EN-LS-SD-SB-80 | B79: Traffic Sign Location & Details | C79: 39 | D79: 46076 | E79: 46126 | F79: 46076 | G79: 46125 | H79: 0 | I79: 0 | J79: 0 | K79: 1 | L79: 1 | M79: 0 | N79: 0 | O79: 0 | P79: No | Q79: 1 | R79: 1 | S79: 0 | T79: 0
A80: PG-Q-EN-LS-SD-SB-90 | B80: Football Playground Layout | C80: 39 | D80: 46076 | E80: 46126 | F80: 46076 | G80: 46125 | H80: 0 | I80: 0 | J80: 0 | K80: 1 | L80: 1 | M80: 0 | N80: 0 | O80: 0 | P80: No | Q80: 1 | R80: 1 | S80: 0 | T80: 0
A81: PG-Q-EN-LS-SD-SB-100 | B81: Padel Playground Layout | C81: 39 | D81: 46076 | E81: 46126 | F81: 46076 | G81: 46125 | H81: 0 | I81: 0 | J81: 0 | K81: 1 | L81: 1 | M81: 0 | N81: 0 | O81: 0 | P81: No | Q81: 1 | R81: 1 | S81: 0 | T81: 0
A82: PG-Q-EN-LS-SD-SB-110 | B82: Basketball Playground Layout | C82: 39 | D82: 46076 | E82: 46126 | F82: 46076 | G82: 46125 | H82: 0 | I82: 0 | J82: 0 | K82: 1 | L82: 1 | M82: 0 | N82: 0 | O82: 0 | P82: No | Q82: 1 | R82: 1 | S82: 0 | T82: 0
A83: PG-Q-EN-LS-SD-SB-120 | B83: Playground Details | C83: 39 | D83: 46076 | E83: 46126 | F83: 46076 | G83: 46125 | H83: 0 | I83: 0 | J83: 0 | K83: 1 | L83: 1 | M83: 0 | N83: 0 | O83: 0 | P83: No | Q83: 1 | R83: 1 | S83: 0 | T83: 0
A84: PG-Q-EN-LS-SD-SB-130 | B84: Padel Fence Elevation & Details | C84: 39 | D84: 46076 | E84: 46126 | F84: 46076 | G84: 46125 | H84: 0 | I84: 0 | J84: 0 | K84: 1 | L84: 1 | M84: 0 | N84: 0 | O84: 0 | P84: No | Q84: 1 | R84: 1 | S84: 0 | T84: 0
A85: MECHANICAL DRAWINGS | C85: 111 | D85: 46081 | E85: 46218 | F85: 46081 | H85: 0 | I85: 0 | J85: 0 | K85: 0 | L85: 0 | M85: 0 | N85: 0 | O85: 0 | Q85: 10 | R85: 9 | S85: 1 | T85: 0
A86: WATER SUPPLY SYSTEM | C86: 32 | D86: 46081 | E86: 46123 | F86: 46081 | G86: 46121 | H86: 0 | I86: 0 | J86: 0 | K86: 0 | L86: 0 | M86: 0 | N86: 0 | O86: 0 | Q86: 4 | R86: 4 | S86: 0 | T86: 0
A87: PG-Q-EN-ME-SD-SB-20 | B87: Pump Room Layout | C87: 32 | D87: 46081 | E87: 46123 | F87: 46081 | G87: 46121 | H87: 0 | I87: 0 | J87: 0 | K87: 1 | L87: 1 | M87: 0 | N87: 0 | O87: 0 | P87: No | Q87: 1 | R87: 1 | S87: 0 | T87: 0
A88: PG-Q-EN-ME-SD-SB-10 | B88: Cold & Hot Water Piping Layout | C88: 28 | D88: 46085 | E88: 46123 | F88: 46085 | G88: 46121 | H88: 0 | I88: 0 | J88: 0 | K88: 1 | L88: 1 | M88: 0 | N88: 0 | O88: 0 | P88: No | Q88: 1 | R88: 1 | S88: 0 | T88: 0
A89: PG-Q-EN-ME-SD-SB-30 | B89: Booster Pump Details | C89: 28 | D89: 46085 | E89: 46123 | F89: 46085 | G89: 46121 | H89: 0 | I89: 0 | J89: 0 | K89: 1 | L89: 1 | M89: 0 | N89: 0 | O89: 0 | P89: No | Q89: 1 | R89: 1 | S89: 0 | T89: 0
A90: PG-Q-EN-ME-SD-SB-40 | B90: GRP Water Tank Details | C90: 24 | D90: 46090 | E90: 46123 | F90: 46090 | G90: 46121 | H90: 0 | I90: 0 | J90: 0 | K90: 1 | L90: 1 | M90: 0 | N90: 0 | O90: 0 | P90: No | Q90: 1 | R90: 1 | S90: 0 | T90: 0
A91: SEWER AND DRAINAGE SYSTEM | C91: 28 | D91: 46085 | E91: 46123 | F91: 46085 | G91: 46121 | H91: 0 | I91: 0 | J91: 0 | K91: 0 | L91: 0 | M91: 0 | N91: 0 | O91: 0 | Q91: 3 | R91: 3 | S91: 0 | T91: 0
A92: PG-Q-EN-ME-SD-SB-50 | B92: Drainage Layout | C92: 28 | D92: 46085 | E92: 46123 | F92: 46085 | G92: 46121 | H92: 0 | I92: 0 | J92: 0 | K92: 1 | L92: 1 | M92: 0 | N92: 0 | O92: 0 | P92: No | Q92: 1 | R92: 1 | S92: 0 | T92: 0
A93: PG-Q-EN-ME-SD-SB-60 | B93: Floor Drains & Cleanouts Details | C93: 24 | D93: 46090 | E93: 46123 | F93: 46090 | G93: 46121 | H93: 0 | I93: 0 | J93: 0 | K93: 1 | L93: 1 | M93: 0 | N93: 0 | O93: 0 | P93: No | Q93: 1 | R93: 1 | S93: 0 | T93: 0
A94: PG-Q-EN-ME-SD-SB-70 | B94: Inspection Chamber Details | C94: 21 | D94: 46093 | E94: 46123 | F94: 46093 | G94: 46121 | H94: 0 | I94: 0 | J94: 0 | K94: 1 | L94: 1 | M94: 0 | N94: 0 | O94: 0 | P94: No | Q94: 1 | R94: 1 | S94: 0 | T94: 0
A95: IRRIGATION SYSTEM | C95: 24 | D95: 46090 | E95: 46123 | F95: 46090 | G95: 46121 | H95: 0 | I95: 0 | J95: 0 | K95: 0 | L95: 0 | M95: 0 | N95: 0 | O95: 0 | Q95: 2 | R95: 2 | S95: 0 | T95: 0
A96: PG-Q-EN-ME-SD-SB-80 | B96: HDPE Pipe Routing | C96: 24 | D96: 46090 | E96: 46123 | F96: 46090 | G96: 46121 | H96: 0 | I96: 0 | J96: 0 | K96: 1 | L96: 1 | M96: 0 | N96: 0 | O96: 0 | P96: No | Q96: 1 | R96: 1 | S96: 0 | T96: 0
A97: PG-Q-EN-ME-SD-SB-90 | B97: Irrigation Network Layout | C97: 21 | D97: 46093 | E97: 46123 | F97: 46093 | G97: 46121 | H97: 0 | I97: 0 | J97: 0 | K97: 1 | L97: 1 | M97: 0 | N97: 0 | O97: 0 | P97: No | Q97: 1 | R97: 1 | S97: 0 | T97: 0
A98: AIR DOME | C98: 18 | D98: 46198 | E98: 46218 | F98: 46233 | H98: 0 | I98: 0 | J98: 0 | K98: 0 | L98: 0 | M98: 0 | N98: 0 | O98: 0 | Q98: 1 | R98: 0 | S98: 1 | T98: 0
A99: PG-Q-EN-ME-SD-SB-100 | B99: Air Package and HVAC System Drawings | C99: 18 | D99: 46198 | E99: 46218 | F99: 46233 | H99: 0 | I99: 0 | J99: 0 | K99: 1 | L99: 0.9 | M99: 0 | N99: 0 | O99: 0 | P99: Yes | Q99: 1 | R99: 0 | S99: 1 | T99: 0
A100: ELECTRICAL DRAWINGS | C100: 70 | D100: 46153 | E100: 46238 | F100: 46153 | H100: 0 | I100: 0 | J100: 0 | K100: 0 | L100: 0 | M100: 0 | N100: 0 | O100: 0 | Q100: 14 | R100: 11 | S100: 3 | T100: 0
...

Sheet Weekly Photos
B1: Date | C1: ='General Information'!M1 -> 46313
B4: Excavation, Bitumen Coat, Concrete Pouring, Base Course Installation, Asphalt Work, Curbstone Installation, Compaction & Levelling

Sheet FIR Summary
A2: Project Name | C2: Playground Initiative ( QASSIM , HAIL & TABUK) | I2: Total FIR Amount
A3: Project ID | C3: MLTX-02-003 | E3: Project Budget | F3: ='[48]Invoice Log'!E3 -> 35709993 | I3: =Total -> 3298582.9
A4: Date Pariod | C4: Start Date | D4: ='[48]Invoice Log'!AG17 -> 45669 | E4: To | F4: Data Date | G4: ='[48]Invoice Log'!AH17 -> 22/12/2025
A6: BOQ Item # | B6: BOQ Description | C6: FIR # | D6: Date | E6: FIR Description | F6: Unit Rate | G6: Current Pariod Quantity | H6: Total (SR) | I6: Comments
H7: =F7*G7 -> 0
H8: =F8*G8 -> 0
B9: Description | H9: =SUBTOTAL(9,H10:H76) -> 3294127.7 | K9: =H9/45093675 -> 0.073050771
A10: IPA-01
A11: 2.1.1 | B11: Excavation | C11: MLTX-02-003-ADV-TS9-1-CVL-FIR-0310-00 | D11: 46268 | E11: Verification of Excavation Quantities for = 1. Court 1- Football court 2. Court 1- Basketball court 3. Court 1- Padel court 4. Court 1- Interlock 5. Court 1- Stamped concrete 6. Court 2- Football court 7. Court 2- Interlock 8. Court 2- Stamped concrete 9. Parking 10. Tartan 1, 2, 3, 4 11. Tartan 1-4- Stamped 12. Tartan 11, 12 As shown in the approved drawings. | F11: 24 | G11: 2549.66 | H11: =F11*G11 -> 61191.84
A12: 2.1.2 | B12: Backfilling with selected fill material free of debris and boulders, in layers. Price also includes testing each layer by a specialized laboratory. The works shall satisfy the project specification and soil report requirements and shall be accepted and approved by the Engineer. | C12: MLTX-02-003-ADV-TS9-1-CVL-FIR-0053-00 | D12: 46135 | E12: under Shower and locker building | F12: 51 | G12: 1310.95 | H12: =F12*G12 -> 66858.45
A13: 2.2.1 | B13: interlock tiles for parking 8cm | C13: MLTX-02-003-ADV-TS9-1-CVL-FIR-0426-00 | D13: 46291 | E13: Subgrade Layer (300 mm) | F13: 67 | G13: 437.07 | H13: =F13*G13 -> 29283.69
C14: MLTX-02-003-ADV-TS9-1-CVL-FIR-0427-00 | D14: 46291 | E14: Base Course Layer(200 mm) | F14: 67 | G14: 437.07 | H14: =F14*G14 -> 29283.69
C15: MLTX-02-003-ADV-TS9-1-CVL-FIR-0435-00 | D15: 46292 | E15: Base Course Layer(200 mm) | F15: 67 | G15: 144.1 | H15: =F15*G15 -> 9654.7
C16: MLTX-02-003-ADV-TS9-1-CVL-FIR-0434-00 | D16: 46292 | E16: Subgrade Layer (300 mm) | F16: 67 | G16: 144.1 | H16: =F16*G16 -> 9654.7
A17: 2.3.1.1 | B17: Interlock tiles grey scale with black marble chips 600*300*60mm zero joint | C17: MLTX-02-003-ADV-TS9-1-CVL-FIR-0444-00 | D17: 46292 | E17: Sub grade backfilling Quantities under interlock tiles as highlighted in the drawings (location 1 &location 2) | F17: 77 | G17: 474.57 | H17: =F17*G17 -> 36541.89
A18: 2.3.1.3 | B18: Tartan floor | C18: MLTX-02-003-ADV-TS9-1-CVL-FIR-0415-00 | D18: 46291 | E18: (Tartan: 1 +3+11+12) Subbase | F18: 234 | G18: 276.63 | H18: =F18*G18 -> 64731.42
C19: MLTX-02-003-ADV-TS9-1-CVL-FIR-0416-00 | D19: 46291 | E19: (Tartan: 2+4) Subbase | F19: 234 | G19: 29.8 | H19: =F19*G19 -> 6973.2
C20: MLTX-02-003-ADV-TS9-1-CVL-FIR-0418-00 | D20: 46291 | E20: (Tartan: 2+4+11+12) Concrete Layer | F20: 234 | G20: 296.55 | H20: =F20*G20 -> 69392.7
C21: MLTX-02-003-ADV-TS9-1-CVL-FIR-0438-00 | D21: 46292 | E21: (Tartan: 1+2+3+4+9) Subbase | F21: 234 | G21: 162.06 | H21: =F21*G21 -> 37922.04
A22: 2.3.2.1 | B22: Kerb type K1A | C22: MLTX-02-003-ADV-TS9-1-CVL-FIR-0190-00 | D22: 46292 | E22: Qassim Parking Area | F22: 78 | G22: 177.38 | H22: =F22*G22 -> 13835.64
C23: MLTX-02-003-ADV-TS9-1-CVL-FIR-0375-00 | D23: 46277 | E23: Cycle Track | F23: 78 | G23: 86.01 | H23: =F23*G23 -> 6708.78
C24: MLTX-02-003-ADV-TS9-1-CVL-FIR-0306-02 | D24: 46264 | E24: for walkway as shown in the attached shop drawing. | F24: 78 | G24: 386.16 | H24: =F24*G24 -> 30120.48
C25: MLTX-02-003-ADV-TS9-1-CVL-FIR-0441-00 | D25: 46289 | E25: for Walking path (Cycle Track) as shown in the attached drawings | F25: 78 | G25: 184.01 | H25: =F25*G25 -> 14352.78
A26: 2.3.2.3 | B26: Kerb type K4 | C26: MLTX-02-003-ADV-TS9-1-CVL-FIR-0178-00 | D26: 46226 | E26: Curb stones for TARTAN AREA 1,2,3,4 as shown in the attached drawings. | F26: 79 | G26: 211.01 | H26: =F26*G26 -> 16669.79
C27: MLTX-02-003-ADV-TS9-1-CVL-FIR-0150-00 | D27: 46226 | E27: Parking Area | F27: 79 | G27: 297 | H27: =F27*G27 -> 23463
C28: MLTX-02-003-ADV-TS9-1-CVL-FIR-0177-01 | D28: 46228 | E28: Football Court 2 as per highlight DWG | F28: 79 | G28: 146.09 | H28: =F28*G28 -> 11541.11
C29: MLTX-02-003-ADV-TS9-1-CVL-FIR-0217-01 | D29: 46233 | E29: Curb Stones for TARTAN AREA 11, 12 | F29: 79 | G29: 319.64 | H29: =F29*G29 -> 25251.56
C30: MLTX-02-003-ADV-TS9-1-CVL-FIR-0288-00 | D30: 46251 | E30: (K4) for Walking path (Cycle Track) as shown in the attached drawings. | F30: 79 | G30: 96.04 | H30: =F30*G30 -> 7587.16
C31: MLTX-02-003-ADV-TS9-1-CVL-FIR-0374-00 | D31: 46293 | E31: Cycle Track | F31: 79 | G31: 70.89 | H31: =F31*G31 -> 5600.31
C32: MLTX-02-003-ADV-TS9-1-CVL-FIR-0307-01 | D32: 46263 | E32: (K4) for walkway as shown in the attached shop drawing. | F32: 79 | G32: 380.21 | H32: =F32*G32 -> 30036.59
A33: 2.3.5.1 | B33: Football playground | C33: MLTX-02-003-ADV-TS9-1-CVL-FIR-0417-00 | D33: 46287 | E33: Court 1 Backfilling works | F33: 161 | G33: 84.76 | H33: =F33*G33 -> 13646.36
C34: MLTX-02-003-ADV-TS9-1-CVL-FIR-0420-00 | D34: 46291 | E34: Court 2 Backfilling works | F34: 161 | G34: 84.76 | H34: =F34*G34 -> 13646.36
C35: MLTX-02-003-ADV-TS9-1-CVL-FIR-0436-00 | D35: 46292 | E35: Court 1 Backfilling works | F35: 161 | G35: 84.76 | H35: =F35*G35 -> 13646.36
C36: MLTX-02-003-ADV-TS9-1-CVL-FIR-0437-00 | D36: 46292 | E36: Court 2 Backfilling works | F36: 161 | G36: 84.76 | H36: =F36*G36 -> 13646.36
A37: 2.3.5.2 | B37: Padel playgound | C37: MLTX-02-003-ADV-TS9-1-CVL-FIR-0425-00 | D37: 46291 | E37: Padel playgound Backfilling works | F37: 376 | G37: 29.35 | H37: =F37*G37 -> 11035.6
C38: MLTX-02-003-ADV-TS9-1-CVL-FIR-0440-00 | D38: 46292 | E38: Padel playgound Backfilling works | F38: 376 | G38: 29.35 | H38: =F38*G38 -> 11035.6
A39: 2.3.5.3 | B39: Basketball playground | C39: MLTX-02-003-ADV-TS9-1-CVL-FIR-0422-00 | D39: 46291 | E39: Basketball playground Backfilling works | F39: 348 | G39: 91.88 | H39: =F39*G39 -> 31974.24
C40: MLTX-02-003-ADV-TS9-1-CVL-FIR-0423-00 | D40: 46291 | E40: Basketball playground Concrete Layer (140 mm) | F40: 348 | G40: 214.38 | H40: =F40*G40 -> 74604.24
C41: MLTX-02-003-ADV-TS9-1-CVL-FIR-0439-00 | D41: 46292 | E41: Basketball playground Backfilling works | F41: 348 | G41: 91.88 | H41: =F41*G41 -> 31974.24
A42: 2.3.9 | B42: air dome | C42: MLTX-02-003-ADV-TS9-1-CVL-FIR-0421-00 | D42: 46291 | E42: Strip footing and Raft foundation | F42: 6958008 | G42: 0.08 | H42: =F42*G42 -> 556640.64
C43: MLTX-02-003-ADV-TS9-1-CVL-FIR-0457-00 | D43: 46292 | E43: Upstand | F43: 6958008 | G43: 0.02 | H43: =F43*G43 -> 139160.16
C44: MLTX-02-003-ADV-TS9-1-CVL-FIR-0428-00 | D44: 46292 | E44: Strip footing and Raft foundation | F44: 6958008 | G44: 0.1 | H44: =F44*G44 -> 695800.8
A45: 3.1.1 | B45: lean concrete under foundation | C45: MLTX-02-003-ADV-TS9-1-CVL-FIR-0068-02 | D45: 46189 | E45: under Shower and locker building | F45: 467 | G45: 3.59 | H45: =F45*G45 -> 1676.53
C46: MLTX-02-003-ADV-TS9-1-CVL-FIR-0303-00 | D46: 46257 | E46: under GRP Tank | F46: 467 | G46: 0.87 | H46: =F46*G46 -> 406.29
C47: MLTX-02-003-ADV-TS9-1-CVL-FIR-0091-00 | D47: 46196 | E47: under Shower and locker building | F47: 467 | G47: 3.64 | H47: =F47*G47 -> 1699.88
H48: 100244.13
A50: IPA-02
A51: 2.2.1 | B51: interlock tiles for parking 8cm | C51: MLTX-02-003-ADV-TS9-1-CVL-FIR-0185-01 | D51: 46299 | E51: FIR for installation of Interlock Pavers in the Parking Area, as shown in the attached drawing. | F51: 67 | G51: =1942.52*0.5*0.9 -> 874.134 | H51: =F51*G51 -> 58566.978
A52: 2.3.1.2 | B52: Stamped concrete floor | C52: MLTX-02-003-ADV-TS9-1-CVL-FIR-0517-00 | D52: 46302 | E52: FIR for Concrete Pouring for Stamped Concrete (Court 2) as shown in highlighted drawing. | F52: 126 | G52: =360.82*0.9 -> 324.738 | H52: =F52*G52 -> 40916.988
C53: MLTX-02-003-ADV-TS9-1-CVL-FIR-0486-00 | D53: 46299 | E53: stamped concrete in (Tartan 1 & 3) Area | F53: 126 | G53: =242.66*0.9 -> 218.394 | H53: =F53*G53 -> 27517.644
C54: MLTX-02-003-ADV-TS9-1-CVL-FIR-0470-00 | D54: 46298 | E54: FIR For Concrete Pouring for Stamped Concrete at the Location Tartan (5&7) as Shown In the as shown in highlighted drawing. | F54: 126 | G54: =269.42*0.9 -> 242.478 | H54: =F54*G54 -> 30552.228
C55: MLTX-02-003-ADV-TS9-1-CVL-FIR-0572-00 | D55: 46307 | E55: FIR for Concrete Pouring For Stamped Concrete (Tartan 2 & 4) as shown in highlighted drawing. | F55: 126 | G55: =135.34*0.9 -> 121.806 | H55: =F55*G55 -> 15347.556
C56: MLTX-02-003-ADV-TS9-1-CVL-FIR-0573-00 | D56: 46307 | E56: FIR for Concrete Pouring For Stamped Concrete (COURT-2 AREA) as shown in highlighted drawing. | F56: 126 | G56: =360.82*0.9 -> 324.738 | H56: =F56*G56 -> 40916.988
A57: 2.3.1.3 | B57: Tartan floor | C57: MLTX-02-003-ADV-TS9-1-CVL-FIR-0489-00 | D57: 46306 | E57: FIR for concrete pouring (35 Mpa) for Grade Slab (Tartan 9) as shown in highlighted drawing. | F57: 234 | G57: =160.29*0.9 -> 144.261 | H57: =F57*G57 -> 33757.074
C58: MLTX-02-003-ADV-TS9-1-CVL-FIR-0490-00 | D58: 46306 | E58: Field inspection request for Concrete pouring (c35) Grade Slab at Tartan 1–3, as highlighted in the attached drawing. | F58: 234 | G58: =25.98*0.9 -> 23.382 | H58: =F58*G58 -> 5471.388
C59: MLTX-02-003-ADV-TS9-1-CVL-FIR-0539-00 | D59: 46305 | E59: FIR for Concrete Pouring for Tartan 1 & 3 as shown in highlighted drawing. | F59: 234 | G59: =181.23*0.9 -> 163.107 | H59: =F59*G59 -> 38167.038
F60: 234 | H60: =F60*G60 -> 0
A61: 2.3.2.3 | B61: Kerb type K4 | C61: MLTX-02-003-ADV-TS9-1-CVL-FIR-0474-00 | D61: 46299 | E61: Curb stones (K4) for Court 2 | F61: 79 | G61: =250.43*0.9 -> 225.387 | H61: =F61*G61 -> 17805.573
C62: MLTX-02-003-ADV-TS9-1-CVL-FIR-0308-01 | D62: 46308 | E62: Curb stones (K4) for Court 2 | F62: 79 | G62: =153.725*0.9 -> 138.3525 | H62: =F62*G62 -> 10929.847
C63: MLTX-02-003-ADV-TS9-1-CVL-FIR-0546-00 | D63: 46309 | E63: Field inspection request for the installation of curbstone at TARTAN-9 area, as highlighted in the attached shop drawing. | F63: 79 | G63: =88.18*0.9 -> 79.362 | H63: =F63*G63 -> 6269.598
A65: 2.3.5.1 | B65: Football playground | C65: MLTX-02-003-ADV-TS9-1-CVL-FIR-0528-00 | D65: 46302 | E65: Court 2 Asphalt Base Course (50 mm) | F65: 161 | G65: =188.36*0.9 -> 169.524 | H65: =F65*G65 -> 27293.364
C66: MLTX-02-003-ADV-TS9-1-CVL-FIR-0563-00 | D66: 46309 | E66: Court 1 Asphalt Base Course (50 mm) | F66: 161 | G66: =188.36*0.9 -> 169.524 | H66: =F66*G66 -> 27293.364
C67: MLTX-02-003-ADV-TS9-1-CVL-FIR-0564-00 | D67: 46309 | E67: Asphalt Wearing Course on Football Court 1, | F67: 161 | G67: =188.36*0.9 -> 169.524 | H67: =F67*G67 -> 27293.364
A68: 2.3.9 | B68: air dome | C68: MLTX-02-003-ADV-TS9-1-CVL-FIR-0523-00 | D68: 46307 | E68: FIR for RCC concrete pouring (35 Mpa) for Air Dome Raft Footing as shown in highlighted drawing. | F68: 6958008 | G68: =0.041*0.9 -> 0.0369 | H68: =F68*G68 -> 256750.5
C69: MLTX-02-003-ADV-TS9-1-CVL-FIR-0591-00 | D69: 46307 | E69: FIR for pouring of concrete (RCC) for curtain wall area Raft foundation as attached highlighted shop drawings | F69: 6958008 | G69: =0.04*0.9 -> 0.036 | H69: =F69*G69 -> 250488.29
A71: 3.4 | B71: The autoclaved aerated panel for slabs | C71: MLTX-02-003-ADV-TS9-1-CVL-FIR-0508-00 | D71: 46299 | E71: FIR for Installation of Autoclaved Aerated Panels for Parapet wall, Shower and locker building as shown in the attached shop drawing. | F71: 189 | G71: =30.96*0.9 -> 27.864 | H71: =F71*G71 -> 5266.296
C72: MLTX-02-003-ADV-TS9-1-CVL-FIR-0242-01 | D72: 46307 | E72: FIR for installation of Autoclave Aerated Panels for walls, Lintels, Slab And Parapet Wall for Shower and locker building (Toilet) as shown in the attached shop drawing. | F72: 189 | G72: =224.116*0.9 -> 201.7044 | H72: =F72*G72 -> 38122.132
C73: MLTX-02-003-ADV-TS9-1-CVL-FIR-0554-00 | D73: 46305 | E73: FIR for installation of Autoclaved Aerated Panels for Slab, Shower and locker building as shown in the attached shop drawing. | F73: 189 | G73: =72.304*0.9 -> 65.0736 | H73: =F73*G73 -> 12298.91
A74: 7.3 | B74: Supply and install liquid applied waterproofing membrane for toilets according to drawings and specifications. | C74: MLTX-02-003-ADV-TS9-1-CVL-FIR-0583-00 | D74: 46308 | E74: FIR for installation of 2 layers of Waterproofing Membrane in Toilets floor area as highlighted in the drawings | F74: 34 | G74: =37.5*0.9 -> 33.75 | H74: =F74*G74 -> 1147.5
A75: 7.5 | B75: 2 layers of waterproofing membrane 4mm including layer protection board for RC footings and RC walls in contact with soil according to the drawings and specification | C75: MLTX-02-003-ADV-TS9-1-CVL-FIR-0562-00 | D75: 46306 | E75: FIR for application of Waterproofing Membrane below the septic tank foundation and RCC Walls as highlighted in the drawings | F75: 73 | G75: =49.4*0.9 -> 44.46 | H75: =F75*G75 -> 3245.58
A76: 9.1.1.1 | B76: Anti-slip glazed grey ceramic tiles, 600*600 mm | C76: MLTX-02-003-ADV-TS9-1-CVL-FIR-0445-00 | D76: 46291 | E76: Ceramic Tiles on Floor – in location The (Shower and locker building) as | F76: 105 | G76: =12.87*0.9 -> 11.583 | H76: =F76*G76 -> 1216.215
A77: 9.1.1.2 | B77: Light grey Ceramic tiles, 300*300 mm | C77: MLTX-02-003-ADV-TS9-1-CVL-FIR-0443-00 | D77: 46291 | E77: Ceramic Tiles on Floor – in location The (Shower and locker building) | F77: 103 | G77: =48.06*0.9 -> 43.254 | H77: =F77*G77 -> 4455.162
A82: Total Period Amount | H82: =SUBTOTAL(9,H10:H81) -> 3298582.9

Sheet Quality
B2: QC OBSERVATIONS CHECKLIST
BB4: 45377
B6: Project No. | E6: MLTX-02-003 | K6: OBS No. | O6: =((X6-BB4)/7)-1 -> 105.71429 | U6: Inspection Day: | X6: 46124
B8: Project | E8: Playgrounds Initiative (Qassim Oasis, Hail and Tabuk Industrial City) | O8: Contractor: Consultant: | U8: Advanced Construction & Contracting Company Egis
B10: 4 | D10: Excellent | G10: Quality Management System is being practiced and applies to MODON System | Z10: 90 - 100 | AB10: QC Overall Score | AC10: =Q49 -> 0.91310345 | AN10: =SUM(Z10:Z13) -> 0 | AO10: 100 | AP10: 0.22883295
B11: 3 | D11: Good | G11: Evidence of compliance with plans and procedures. | Z11: 80 - 89 | AN11: =SUM(Y10:Y14) -> 0 | AO11: 89 | AP11: 0.20366133
B12: 2 | D12: Average | G12: Indication level of compliance with standards but there is room for improvement | Z12: 70 - 79 | AO12: 79 | AP12: 0.18077803
B13: 1 | D13: Improve | G13: Quality and Control is NOT being managed effectively. Needs Improvement | Z13: ≤ 69 | AO13: 69 | AP13: 0.15789474
B14: 0 | D14: N/A | G14: Item was not applicable or this item was not reviewed during the inspection. | Z14: Zero | AO14: 100 | AP14: 0.22883295
B16: No. | C16: Topic | K16: E (4) | L16: G (3) | M16: A (2) | N16: I (1) | O16: N/A (0) | Q16: No. | R16: Topic | Z16: E (4) | AA16: G (3) | AB16: A (2) | AC16: I (1) | AD16: N/A (0) | AO16: =SUM(AO10:AO15) -> 437
K17: 1 | L17: 0.89 | M17: 0.79 | N17: 0.69 | O17: 1 | Z17: 1 | AA17: 0.89 | AB17: 0.79 | AC17: 0.69 | AD17: 1 | AF17: =SUM(AF18:AG46)/COUNT(AF18:AG46) -> 0.91310345
B18: 1 | C18: Control of Access to Site/Office | L18: 1 | Q18: 30 | R18: QC of Excavation | Z18: 0 | AA18: 1 | AF18: =SUMPRODUCT($K$17:$O$17,K18:O18) -> 0.89 | AG18: =SUMPRODUCT($Z$17:$AD$17,Z18:AD18) -> 0.89 | AV18: Item Count | AW18: Score | AX18: Distributtion
B19: 2 | C19: Document Control Administration | L19: 1 | Q19: 31 | R19: QC of Roads/Round about | Z19: 0 | AA19: 1 | AF19: =SUMPRODUCT($K$17:$O$17,K19:O19) -> 0.89 | AG19: =SUMPRODUCT($Z$17:$AD$17,Z19:AD19) -> 0.89 | AX19: Overall | AY19: Relevant
B20: 3 | C20: Project Documents and Progress | L20: 1 | M20: 0 | Q20: 32 | R20: QC of Interlock & Curbstone | Z20: 0 | AA20: 1 | AD20: 0 | AF20: =SUMPRODUCT($K$17:$O$17,K20:O20) -> 0.89 | AG20: =SUMPRODUCT($Z$17:$AD$17,Z20:AD20) -> 0.89 | AM20: 4 | AN20: =58 -> 58 | AO20: counts | AQ20: 4 | AR20: Excellent | AV20: =SUM(Z18:Z46,K18:K46) -> 5 | AW20: =AQ20*AV20 -> 20 | AX20: =AV20/$AV$25 -> 0.086206897 | AY20: =AV20/SUM($AV$20:$AV$23) -> 0.12820513
B21: 4 | C21: Contractor's Quality Plan/CM (Updated and Reviewed) | L21: 1 | Q21: 33 | R21: Layers/Backfilling Sampling | Z21: 0 | AA21: 1 | AB21: 0 | AC21: 0 | AD21: 0 | AF21: =SUMPRODUCT($K$17:$O$17,K21:O21) -> 0.89 | AG21: =SUMPRODUCT($Z$17:$AD$17,Z21:AD21) -> 0.89 | AM21: 3 | AN21: =58 -> 58 | AO21: counts | AQ21: 3 | AR21: Good | AV21: =SUM(L18:L46,AA18:AA46) -> 24 | AW21: =AQ21*AV21 -> 72 | AX21: =AV21/$AV$25 -> 0.4137931 | AY21: =AV21/SUM($AV$20:$AV$23) -> 0.61538462
B22: 5 | C22: MS Log and Paperwork | L22: 1 | M22: 0 | Q22: 34 | R22: Pump Stations Units | Z22: 0 | AA22: 1 | AB22: 0 | AD22: 0 | AF22: =SUMPRODUCT($K$17:$O$17,K22:O22) -> 0.89 | AG22: =SUMPRODUCT($Z$17:$AD$17,Z22:AD22) -> 0.89 | AM22: 2 | AN22: =58 -> 58 | AO22: counts | AQ22: 2 | AR22: Average | AV22: =SUM(M18:M46,AB18:AB46) -> 7 | AW22: =AQ22*AV22 -> 14 | AX22: =AV22/$AV$25 -> 0.12068966 | AY22: =AV22/SUM($AV$20:$AV$23) -> 0.17948718 | BC22: NB: Insert 1, or 0 in the required cell only.
B23: 6 | C23: RFI, FIR, & MIR Procedure | L23: 1 | Q23: 35 | R23: Quality of Form Work | Z23: 0 | AA23: 1 | AD23: 0 | AF23: =SUMPRODUCT($K$17:$O$17,K23:O23) -> 0.89 | AG23: =SUMPRODUCT($Z$17:$AD$17,Z23:AD23) -> 0.89 | AM23: 1 | AN23: =58 -> 58 | AO23: counts | AQ23: 1 | AR23: Improve | AV23: =SUM(N18:N46,AC18:AC46) -> 3 | AW23: =AQ23*AV23 -> 3 | AX23: =AV23/$AV$25 -> 0.051724138 | AY23: =AV23/SUM($AV$20:$AV$23) -> 0.076923077
B24: 7 | C24: RFI, FIR, & MIR Inventory system | L24: 1 | Q24: 36 | R24: Design Change List | AC24: 0 | AD24: 1 | AF24: =SUMPRODUCT($K$17:$O$17,K24:O24) -> 0.89 | AG24: =SUMPRODUCT($Z$17:$AD$17,Z24:AD24) -> 1 | AM24: 0 | AN24: =58 -> 58 | AO24: counts | AQ24: 0 | AR24: N/A | AV24: =SUM(O18:O46,AD18:AD46) -> 19 | AW24: =AQ24*AV24 -> 0 | AX24: =AV24/$AV$25 -> 0.32758621 | AY24: -
B25: 8 | C25: NCRs Control & Procedure | L25: 1 | Q25: 37 | R25: Quality of Concrete Placing | AA25: 1 | AC25: 0 | AD25: 0 | AF25: =SUMPRODUCT($K$17:$O$17,K25:O25) -> 0.89 | AG25: =SUMPRODUCT($Z$17:$AD$17,Z25:AD25) -> 0.89 | AR25: Total | AV25: =SUM(AV20:AV24) -> 58 | AW25: =SUM(AW20:AW24) -> 109 | AX25: =SUM(AX20:AX24) -> 1 | AY25: =SUM(AY20:AY24) -> 1
B26: 9 | C26: NCR Log | K26: 0 | L26: 1 | Q26: 38 | R26: Concrete Surface Finishing | Z26: 0 | AA26: 1 | AD26: 0 | AF26: =SUMPRODUCT($K$17:$O$17,K26:O26) -> 0.89 | AG26: =SUMPRODUCT($Z$17:$AD$17,Z26:AD26) -> 0.89
B27: 10 | C27: MODON Standard* | K27: 0 | L27: 1 | Q27: 39 | R27: Pedestals/Columns/Beams Alignment | Z27: 0 | AD27: 1 | AF27: =SUMPRODUCT($K$17:$O$17,K27:O27) -> 0.89 | AG27: =SUMPRODUCT($Z$17:$AD$17,Z27:AD27) -> 1 | AV27: Maz Score Available: | AW27: =SUM(AV20:AV23)*AQ20 -> 156 | AX27: <- Excludes N/A items
B28: 11 | C28: Project Risk Plan/Management* | K28: 1 | Q28: 40 | R28: Siporex Lifting & Unloading | AB28: 0 | AD28: 1 | AF28: =SUMPRODUCT($K$17:$O$17,K28:O28) -> 1 | AG28: =SUMPRODUCT($Z$17:$AD$17,Z28:AD28) -> 1
B29: 12 | C29: Monthly Quality Reports* | K29: 0 | L29: 1 | M29: 0 | Q29: 41 | R29: Siporex Quality Pre-installation | AB29: 0 | AD29: 1 | AF29: =SUMPRODUCT($K$17:$O$17,K29:O29) -> 0.89 | AG29: =SUMPRODUCT($Z$17:$AD$17,Z29:AD29) -> 1
B30: 13 | C30: ITP | K30: 0 | L30: 1 | M30: 0 | Q30: 42 | R30: Siporex Finishing Quality | Z30: 0 | AD30: 1 | AF30: =SUMPRODUCT($K$17:$O$17,K30:O30) -> 0.89 | AG30: =SUMPRODUCT($Z$17:$AD$17,Z30:AD30) -> 1 | AR30: Total Score | AW30: Percentage (%)
B31: 14 | C31: MODON Weekly Report | K31: 0 | L31: 1 | M31: 0 | Q31: 43 | R31: Roads / Parking Markings | Z31: 0 | AA31: 0 | AD31: 1 | AF31: =SUMPRODUCT($K$17:$O$17,K31:O31) -> 0.89 | AG31: =SUMPRODUCT($Z$17:$AD$17,Z31:AD31) -> 1 | AN31: =MAX(AN20:AN24) -> 58 | AR31: =AW25 -> 109 | AW31: =SUM(100/AR33*AR31) -> 69.871795 | AY31: %
B32: 15 | C32: Design Change Official Paperwork* | K32: 0 | M32: 1 | O32: 0 | Q32: 44 | R32: QC of Finishing Outdoors | Z32: 0 | AA32: 0 | AD32: 1 | AF32: =SUMPRODUCT($K$17:$O$17,K32:O32) -> 0.79 | AG32: =SUMPRODUCT($Z$17:$AD$17,Z32:AD32) -> 1 | AR32: Max Score Available | BP32: 31
B33: 16 | C33: Design Change was Applied* | K33: 0 | M33: 1 | O33: 0 | Q33: 45 | R33: Quality of Finishing Indoors | Z33: 0 | AD33: 1 | AF33: =SUMPRODUCT($K$17:$O$17,K33:O33) -> 0.79 | AG33: =SUMPRODUCT($Z$17:$AD$17,Z33:AD33) -> 1 | AR33: =AW27 -> 156 | BP33: 32
B34: 17 | C34: Material List | K34: 0 | L34: 1 | M34: 0 | Q34: 46 | R34: Stairs Quality | Z34: 0 | AD34: 1 | AF34: =SUMPRODUCT($K$17:$O$17,K34:O34) -> 0.89 | AG34: =SUMPRODUCT($Z$17:$AD$17,Z34:AD34) -> 1 | BP34: 33
B35: 18 | C35: Pending Material Status | K35: 0 | L35: 1 | O35: 0 | Q35: 47 | R35: Tanks Method Statement Work | Z35: 0 | AD35: 1 | AF35: =SUMPRODUCT($K$17:$O$17,K35:O35) -> 0.89 | AG35: =SUMPRODUCT($Z$17:$AD$17,Z35:AD35) -> 1 | BP35: 34
B36: 19 | C36: Lifting Plan* | O36: 1 | Q36: 48 | R36: Electric Rooms | Z36: 0 | AD36: 1 | AF36: =SUMPRODUCT($K$17:$O$17,K36:O36) -> 1 | AG36: =SUMPRODUCT($Z$17:$AD$17,Z36:AD36) -> 1 | BP36: 35
B37: 20 | C37: DWG Log | M37: 1 | O37: 0 | Q37: 49 | R37: QC of MCC/ATS Plant Units | Z37: 0 | AD37: 1 | AF37: =SUMPRODUCT($K$17:$O$17,K37:O37) -> 0.79 | AG37: =SUMPRODUCT($Z$17:$AD$17,Z37:AD37) -> 1 | BP37: 36
B38: 21 | C38: Invoice Status | K38: 1 | L38: 0 | O38: 0 | Q38: 50 | R38: Qualified Subcontractor | Z38: 0 | AD38: 1 | AF38: =SUMPRODUCT($K$17:$O$17,K38:O38) -> 1 | AG38: =SUMPRODUCT($Z$17:$AD$17,Z38:AD38) -> 1 | BP38: 37
B39: 22 | C39: Site Handover Letter | K39: 1 | L39: 0 | Q39: 51 | R39: Scaffold/Ladders/Slope/Bridge Compliance | Z39: 0 | AD39: 1 | AF39: =SUMPRODUCT($K$17:$O$17,K39:O39) -> 1 | AG39: =SUMPRODUCT($Z$17:$AD$17,Z39:AD39) -> 1 | BP39: 38
B40: 23 | C40: Material Testing Results & Certification | K40: 0 | L40: 1 | M40: 0 | N40: 0 | Q40: 52 | R40: Protection Applied to Completed Work | AC40: 0 | AD40: 1 | AF40: =SUMPRODUCT($K$17:$O$17,K40:O40) -> 0.89 | AG40: =SUMPRODUCT($Z$17:$AD$17,Z40:AD40) -> 1
B41: 24 | C41: As Build Drawings Status* | L41: 0 | O41: 1 | Q41: 53 | R41: Storage Management in/out Control | AA41: 0 | AC41: 1 | AF41: =SUMPRODUCT($K$17:$O$17,K41:O41) -> 1 | AG41: =SUMPRODUCT($Z$17:$AD$17,Z41:AD41) -> 0.69
B42: 25 | C42: Calibrated Lab Tools & Equipment | K42: 1 | L42: 0 | N42: 0 | Q42: 54 | R42: Material Control | AA42: 0 | AC42: 0 | AD42: 1 | AF42: =SUMPRODUCT($K$17:$O$17,K42:O42) -> 1 | AG42: =SUMPRODUCT($Z$17:$AD$17,Z42:AD42) -> 1
B43: 26 | C43: Storage Inventory System | L43: 0 | N43: 1 | Q43: 55 | R43: Manholes Storing and Quality | AA43: 0 | AC43: 1 | AD43: 0 | AF43: =SUMPRODUCT($K$17:$O$17,K43:O43) -> 0.69 | AG43: =SUMPRODUCT($Z$17:$AD$17,Z43:AD43) -> 0.69
B44: 27 | C44: Logistics Plan | M44: 1 | Q44: 56 | R44: Reinforced Steel Quality | AA44: 0 | AD44: 1 | AF44: =SUMPRODUCT($K$17:$O$17,K44:O44) -> 0.79 | AG44: =SUMPRODUCT($Z$17:$AD$17,Z44:AD44) -> 1
B45: 28 | C45: Project Progress Planview | K45: 1 | M45: 0 | N45: 0 | Q45: 57 | R45: Safety Overview | Z45: 0 | AB45: 1 | AF45: =SUMPRODUCT($K$17:$O$17,K45:O45) -> 1 | AG45: =SUMPRODUCT($Z$17:$AD$17,Z45:AD45) -> 0.79
B46: 29 | C46: Sufficient Number of QC Inspectors | K46: 0 | M46: 1 | N46: 0 | Q46: 58 | R46: Waste Management Control | Z46: 0 | AB46: 1 | AF46: =SUMPRODUCT($K$17:$O$17,K46:O46) -> 0.79 | AG46: =SUMPRODUCT($Z$17:$AD$17,Z46:AD46) -> 0.79
O47: 0
I48: Score
M49: *QC % | Q49: =AF17 -> 0.91310345
B51: Prepared by: | G51: Abdelmutalb Eldukhri | Q51: Issued to PM: | V51: Abdulaziz M. Al-Musallam
B53: *QC Observations refer only to the practices and documentation observed at time of inspection. The responsibility of the CM and Contractor is to ensure that aspects of Quality are suitably managed. *Scores are a reflection of the general site conditions based upon the findings at the time of the walk through *If Applicable

Sheet Quality-Stat
A1: Quality Reports
A2: Item | C2: Issued | D2: Closed | E2: Pending | F2: Avg. Closing (Days) | G2: Pending
G3: 0-10 Days | H3: 11-20 Days | I3: 21-30 Days | J3: 31-60 Days | K3: > 60 Days
A5: Non Conforomance Report (NCR) | C5: 17 | D5: 7 | E5: 10 | F5: 0 | G5: 8 | H5: 2 | I5: 0 | J5: 0 | K5: 0
A6: Site Instruction (SI) | C6: 7 | D6: 6 | E6: 1 | F6: 0 | G6: 0 | H6: 0 | I6: 1 | J6: 0 | K6: 0
A7: Material Inspection Report (MIR) | C7: 76 | D7: 53 | E7: 23 | F7: 0 | G7: 20 | H7: 3 | I7: 0 | J7: 0 | K7: 0
A8: Field Inspection Report (FIR) | C8: 658 | D8: 488 | E8: 170 | F8: 0 | G8: 140 | H8: 15 | I8: 15 | J8: 0 | K8: 0
A10: Shop Drawings
A11: Item | D11: Total Planned | E11: Total Drawings Submitted | J11: Remaining Drawings | K11: Pending | L11: Total Submittals
E12: A | F12: B | G12: C | H12: D | I12: Approved | J12: with Designer | K12: Submittals With Consultant
A13: Architectural | D13: 58 | E13: 6 | F13: 33 | G13: 2 | H13: 0 | I13: =E13+F13 -> 39 | J13: 0 | K13: 17 | L13: =G13+H13+I13+K13 -> 58
A14: Civil / Structural | D14: 84 | E14: 0 | F14: 66 | G14: 0 | H14: 12 | I14: 66 | J14: 0 | K14: 6 | L14: 84
A15: Mechanical | D15: 42 | E15: 16 | F15: 22 | G15: 2 | H15: 0 | I15: =E15+F15 -> 38 | J15: 0 | K15: 2 | L15: =G15+H15+I15+K15 -> 42
A16: Electrical | D16: 98 | E16: 4 | F16: 43 | G16: 12 | H16: 22 | I16: 47 | J16: 0 | K16: 17 | L16: =G16+H16+I16+K16 -> 98
A17: Landscape | D17: 69 | E17: 4 | F17: 59 | G17: 1 | H17: 3 | I17: 63 | J17: 0 | K17: 2 | L17: =G17+H17+I17+K17 -> 69
A18: General | D18: 42 | E18: 6 | F18: 36 | G18: 0 | H18: 0 | I18: 42 | J18: 0 | K18: 0 | L18: 42
A19: TOTAL | D19: 259 | E19: =SUM(E13:E18) -> 36 | F19: =SUM(F13:F18) -> 259 | G19: =SUM(G13:G18) -> 17 | H19: =SUM(H13:H18) -> 37 | I19: =SUM(I13:I18) -> 295 | J19: =SUM(J13:J18) -> 0 | K19: =SUM(K13:K18) -> 44 | L19: =SUM(L13:L18) -> 393
A22: Material Approval
A23: Item | D23: Total Planned | E23: Total Materials Submitted | J23: Remaining to approve | K23: Pending | L23: Total Submittals
E24: A | F24: B | G24: C | H24: D | I24: Approved | J24: with Designer | K24: Submittals With Consultant
A25: Architectural | D25: 41 | E25: 4 | F25: 35 | G25: 1 | H25: 0 | I25: 39 | K25: 1 | L25: =G25+H25+K25+I25 -> 41
A26: Civil / Structural | D26: 51 | E26: 1 | F26: 41 | G26: 4 | H26: 0 | I26: =E26+F26 -> 42 | K26: 5 | L26: =G26+H26+K26+I26 -> 51
A27: Mechanical | D27: 19 | E27: 0 | F27: 14 | G27: 1 | H27: 0 | I27: =E27+F27 -> 14 | K27: 4 | L27: =G27+H27+K27+I27 -> 19
A28: Electrical | D28: 28 | E28: 0 | F28: 26 | G28: 2 | H28: 0 | I28: 26 | K28: 0 | L28: =G28+H28+K28+I28 -> 28
A29: Landscape | D29: 2 | F29: 0 | G29: 0 | I29: =E29+F29 -> 0 | K29: 2 | L29: =G29+H29+K29+I29 -> 2
A30: General
A31: TOTAL | D31: =SUM(D25:D30) -> 141 | E31: =SUM(E25:E30) -> 5 | F31: =SUM(F25:F30) -> 116 | G31: =SUM(G25:G30) -> 8 | H31: =SUM(H25:H30) -> 0 | I31: =SUM(I25:I30) -> 121 | J31: =SUM(J25:J30) -> 0 | K31: =SUM(K25:K30) -> 12 | L31: =SUM(L25:L30) -> 141
A33: Procurement Summary
A34: Item | D34: Total Materials Planned | E34: Total Number of P.O. | F34: Actual P.O. To Date | G34: Remaining P.O | H34: Actual Material on Site | I34: Remaining Materials | J34: Material Delivery Completion (Date)
E35: A | F35: B | G35: C | H35: D | I35: Processed
A36: Architectural | D36: 11 | E36: 11 | F36: 7 | G36: 4 | H36: 3
A37: Civil / Structural | D37: 19 | E37: 19 | F37: 15 | G37: 4 | H37: 3
A38: Mechanical | D38: 20 | E38: 20 | F38: 8 | G38: 13 | H38: 1
A39: Electrical | D39: 7 | E39: 7 | F39: 3 | G39: 4 | H39: 1
A40: General
A41: TOTAL | D41: =SUM(D36:D40) -> 57 | E41: =SUM(E36:E40) -> 57 | F41: =SUM(F36:F40) -> 33 | G41: =SUM(G36:G40) -> 25 | H41: =SUM(H36:H40) -> 8 | I41: =SUM(I36:I40) -> 0 | J41: =MAX(J36:J40) -> 0
A43: Consultant Quality Inspections / Observations (Weekly Basis) | I43: Overall Average | J43: =AVERAGE(E46:E119) -> #DIV/0! | L43: Average Closing | M43: =AVERAGE(G45:G119) -> #DIV/0!
A44: Week Number | B44: Date of Audit | C44: Date Issued | D44: Numbers Of Comments | E44: Quality Score | F44: Date Closed | G44: Closure Duration | I44: This Week Score | J44: =[49]Quality!AC10 -> 0.9087931 | L44: Average Number of Comments Per Audit | M44: =AVERAGE(D46:D119) -> #DIV/0!
A45: Week-1
A46: Week-2
A47: Week-3
A48: Week-4
A49: Week-5
A50: Week-6
A51: Week-7
A52: Week-8
A53: Week-9
A54: Week-10
A55: Week-11
A56: Week-12
... A119: Week-75

Sheet HSE
B1: MODON HSE Site Inspection Report
B2: Date | E2: 46310 | L2: Inspected By: | U2: Saud Al Shammari
B4: Project ID. | E4: MLTX-02-003 | L4: Report No. | P4: 28 | W4: MODON PM Name | Y4: Bader K. Alrowaidan
B6: Project Name: | E6: Central Region Playground Initiative Project (Hail, Qassim & Tabuk) | L6: Contractor: | R6: Advanced Construction & Contracting Company | X6: Safety Performance | AA6: =IF(W29>0,3,IF(L29>6,3,IF(D29>0,2,1)*1)*1) -> 3 | AE6: =(((COUNTIF(L13:Q25,"1")+COUNTIF(AC13:AH25,"1"))*AR13)+(COUNTIF(L13:Q25,"2")+COUNTIF(AC13:AH25,"2"))*AR14+(COUNTIF(L13:Q25,"3")+COUNTIF(AC13:AH25,"3"))*AR15)/((COUNT(L13:Q25)+COUNT(AC13:AH25))*100) -> 0.91304348 | AK6: Date: | AX6: 10 to 15
B8: Inspections are a snapshot in time and refer only to the practices and documentation observed at the time of the Inspection. It remains the responsibility of the Consultant and Contractor to ensure that all aspects of Health & Safety are suitably managed.
B9: 1 | D9: Good Practice | H9: 2 | I9: Need Improvement | T9: 3 | U9: Fail (Life Threatening Activity) / Comliance with Plan & Procedures | X9: N/A | Y9: Activity Not Applicable for this Site Inspection Report
B11: No. | C11: Topic | K11: Wt. | L11: HSE Compliance | S11: No. | T11: Topic | AB11: Wt. | AC11: HSE Compliance
B13: 1 | C13: Access and Egress - (General access to site, segregated from vehicles, / Overhead protection, while entering into the building /Adequate lighting provided when dark or overnight work) | K13: 0.05 | L13: 1 | S13: 14 | T13: Work at Height - (PPE/Fall Protection(Same level, above and below) / Training / Fall restraint / competency /Safe access & egress to and from work at height / Ladders / Openings (floor/shafts/Provision of emergency rescue) | AB13: 0.05 | AC13: 2 | AP13: 1 | AR13: 100 | AU13: 1
B14: 2 | C14: Traffic Management - (Loading/unloading/sheeting/temp. routes/speed/parking/competence) | K14: 0.03 | L14: 1 | S14: 15 | T14: Scaffolding - (Temp. Scaffolding Work-platform (All types) - qualified scaffolder / Inspection / Tagged / Safe Access/egress / PTW/Falsework & Formwork) | AB14: 0.04 | AC14: 2 | AP14: 2 | AR14: 75 | AU14: 2
B15: 3 | C15: Site Signage - (Project Notice Board & General Signage) | K15: 0.02 | L15: 1 | S15: 16 | T15: Mobile Elevated Work platform (MEWP) - (PTW/competence requirements/conditions/inspections/tagged/training/Full-body harness) | AB15: 0.04 | AC15: N/A | AP15: 3 | AR15: 0 | AU15: 3
B16: 4 | C16: PPE Compliance - (Use, storage, stock, handling & checks - Head, Foot, Eye, Hearing) | K16: 0.05 | L16: 1 | S16: 17 | T16: Excavation & Trenches - (PTW/Edge protection/buffer zone/Slope/Benching/Shoring/Geo-tech report/Atmospheric hazards/Acess&egress/Emergency management / MS&RA/H.E) | AB16: 0.03 | AC16: 2 | AU16: N/A
B17: 5 | C17: Housekeeping - (Material correctly stored / Rubbish cleaned & removed daily/slips & trips hazards) | K17: 0.03 | L17: 2 | S17: 18 | T17: Confined Space - (PTW/Training/competence/Emergency Management/MS & RA/Safe access/egress) | AB17: 0.05 | AC17: N/A
B18: 6 | C18: Storage of Materials - (Transporting, storage, training and use - Combustible / Flammable / Hazardous substances (COSHH) | L18: 2 | S18: 19 | T18: Fire Protection - (Flammable/Oxy. LPG /Combustible separated/FE's/Flashback arrestor/Sparks & slags/Smoking area/PTW/Generators/MS & RA/Emergency Management) | AC18: 1 | AL18: Red | AM18: Serious injury or death (immediately)
B19: 7 | C19: Site Waste Management - (Hazardous waste /Combustible waste / Human waste / Construction waste - asphalt, cable, timber, paving roof sheeting tiles, plastic & bricks) | L19: 2 | S19: 20 | T19: Health & Welfare - (Adequate drinking water/shaded - eating & rest area/washing & sanitary facilities/Certified FA/FA Box & Stock/adequate toilets/Ambulance) | AC19: 1 | AL19: Yellow | AM19: Minor or near miss (3 days to comply)
B20: 8 | C20: Health Surveillance - (Expose to excessive noise/vibration/dust/silica/CO/cement/radiation/extreme weather condition) | K20: 0.03 | L20: 1 | S20: 21 | T20: Environmental Incident Measures - (Spill/ Leakage / Concrete wash / vehicle & eqpts. wash / waste disposal/Sewers and drains/emissions/Emergency Management/Training/site run-off water) | AB20: 0.05 | AC20: 2 | AL20: Green | AM20: No issues
B21: 9 | C21: Electrical Safety - (Electrical qualified /RCD/GFCI/Industrial Socket/LOTO/Cable-overhung or buried/Cords in good condition/current inspection tag) | K21: 0.05 | L21: 1 | S21: 22 | T21: HSE Communications & Meetings - (Schedule HSE Meetings/Safety Committee meetings/Alerts / Lesson learned/Safety Bulletin contains latest HSE KPI) | AB21: 0.05 | AC21: 1
B22: 10 | C22: Tools & Equipment - (Includes, powered, hydraulic & pneumatic/Guards in place/Properly stored/RCD Protection/Earthed/Good condition & tagged) | K22: 0.03 | L22: 1 | S22: 23 | T22: HSE Plan & Associated Procedures - (Approved updated HSE Plan/ CEMP/HAZComm/Procedures/Standards/Project Safety Risk Register) | AB22: 0.03 | AC22: 1 | AL22: 26 points > 4 minors then is it’s a serious issue
B23: 11 | C23: Manual Handling - (Lifting/loading/pulling/pushing/twisting/awkward posture/repetitive task/frequent and prolong physical effort/Reasonable practicable use of mechanical aid) | K23: 0.03 | L23: 1 | S23: 24 | T23: Health, Safety & Environment Incident reporting - (Review of HSE Statistics, Reporting of Unsafe Act & Conditions/ Reporting of Near Miss incident/Reporting of FA cases/Record MT cases) | AB23: 0.03 | AC23: 1
