Workbook
Name _1B.05.M.010.0010: #REF!
Name _1B.05.M.010.0010: #REF!
Name _1B.05.M.010.0050: #REF!
Name _1B.05.M.010.0050: #REF!
Name _1B.05.M.0100.0010: #REF!
Name _1B.05.M.020.0010: #REF!
Name _1B.05.M.020.0020: #REF!
Name _1B.05.M.020.0030: #REF!
Name _1B.05.M.020.0040: #REF!
Name _1B.05.M.030.0010: #REF!
Name _1B.05.M.030.0020: #REF!
Name _1B.05.M.040.0010: #REF!
Name _1B.05.M.050.0010: #REF!
Name _1B.05.M.050.0020: #REF!
Name _1B.05.M.050.0030: #REF!
Name _1B.05.M.060.0020: #REF!
Name _1B.05.M.060.0100: #REF!
Name _1B.05.M.070.0010: #REF!
Name _1B.05.M.070.0020: #REF!
Name _1B.05.M.070.0030: #REF!
Name _1B.05.M.070.0040: #REF!
Name _1B.05.M.070.0050: #REF!
Name _1B.05.M.080.0010: #REF!
Name _1B.05.M.090.0010: #REF!
Name _1B.09.P.010.0010: #REF!
Name _1B.09.P.010.0020: #REF!
Name _1B.09.P.010.0030: #REF!
Name _1B.09.P.010.0040: #REF!
Name _1B.09.P.010.0050: #REF!
Name _1B.09.P.010.0060: #REF!
Name _1B.09.P.010.0070: #REF!
Name _1B.09.P.020.0010: #REF!
Name _1B.09.P.020.0020: #REF!
Name _1B.09.P.020.0030: #REF!
Name _1B.09.P.020.0040: #REF!
Name _1B.09.P.020.0050: #REF!
Name _1B.09.P.020.0060: #REF!
Name _1B.09.P.020.0070: #REF!
Name _1B.09.P.020.0080: #REF!
Name _1B.09.P.020.0090: #REF!
Name _1B.09.P.020.0100: #REF!
Name _1B.09.P.020.0110: #REF!
Name _1B.09.P.020.0120: #REF!
Name _1B.09.P.020.0130: #REF!
Name _1B.09.P.020.0140: #REF!
Name _1B.09.P.020.0150: #REF!
Name _1B.09.P.030.0010: #REF!
Name _1B.09.P.030.0020: #REF!
Name _1B.09.P.030.0030: #REF!
Name _1B.09.P.030.0040: #REF!
Name _1B.09.P.030.0050: #REF!
Name _1B.09.P.030.0060: #REF!
Name _1B.09.P.040.0010: #REF!
Name _1B.09.P.040.0020: #REF!
Name _1B.09.P.040.0030: #REF!
Name _1B.09.P.050.0010: #REF!
Name _1B.09.P.050.0020: #REF!
Name _1B.09.P.060.0010: #REF!
Name _1B.09.P.060.0020: #REF!
Name _1B.09.P.060.0030: #REF!

Sheet DB
A1: ='Weekly Progress Report'!$A$1 -> MODON - Weekly Progress Report - Construction Projects
B2: ='Weekly Progress Report'!$A$2 -> Contract General Information | J2: ='Weekly Progress Report'!G2 -> Key Dates | U2: ='Weekly Progress Report'!$M$2 -> Cost Summary (SR) | AD2: ='Weekly Progress Report'!$U$2 -> Performance Summary | AP2: ='Weekly Progress Report'!A58 -> Shop Drawings | AT2: ='Weekly Progress Report'!A67 -> Material Approval | AW2: ='Weekly Progress Report'!A76 -> Procurement Summary | BD2: ='Weekly Progress Report'!L58 -> Quality Reports | BT2: ='Weekly Progress Report'!L66 -> Key Submittals Approval Status | CD2: ='Weekly Progress Report'!L72 -> Invoices Summary | CR2: ='Weekly Progress Report'!L80 -> Resources at Site | CY2: ='Weekly Progress Report'!W58 -> Safety Statistics | FK2: ='Weekly Progress Report'!A85 -> Primavera P6 Schedule Status | FS2: ='Weekly Progress Report'!A94 -> Weekly Prgoress Photos
A3: ='Weekly Progress Report'!AF1 -> Data Date | B3: ='Weekly Progress Report'!A3 -> Project Name | C3: ='Weekly Progress Report'!A4 -> Project ID | D3: ='Weekly Progress Report'!A5 -> Contractor | E3: ='Weekly Progress Report'!A6 -> Consultant | F3: ='Weekly Progress Report'!D4 -> Stage | G3: ='Weekly Progress Report'!D5 -> Status | H3: ='Weekly Progress Report'!D6 -> Modon PM | I3: ='Weekly Progress Report'!AA2 -> Project Scope | J3: ='Weekly Progress Report'!G3 -> Contract Award | K3: ='Weekly Progress Report'!G4 -> Contract Sign | L3: ='Weekly Progress Report'!G5 -> Site Handover | M3: ='Weekly Progress Report'!G6 -> Original Completion | N3: ='Weekly Progress Report'!$I$3 -> Contract Award (Hijri) | O3: ='Weekly Progress Report'!$I$4 -> Contract Sign (Hijri) | P3: ='Weekly Progress Report'!$I$5 -> Site Handover (Hijri) | Q3: ='Weekly Progress Report'!$I$6 -> Original Completion (Hijri) | R3: ='Weekly Progress Report'!$K$3 -> Revised Completion | S3: ='Weekly Progress Report'!$K$4 -> Committed Completion | T3: ='Weekly Progress Report'!$K$5 -> Forecast Completion | U3: ='Weekly Progress Report'!$M$3 -> Original Contract Value | V3: ='Weekly Progress Report'!$M$4 -> Revised Contract Value | W3: ='Weekly Progress Report'!$M$5 -> Estimate At Completion Value | X3: ='Weekly Progress Report'!$M$6 -> Potential Changes | Y3: ='Weekly Progress Report'!$Q$3 -> O&M Value (if any) | Z3: ='Weekly Progress Report'!$Q$4 -> Submitted Invoices (Gross Value) | AA3: ='Weekly Progress Report'!$Q$5 -> Penalities | AB3: ='Weekly Progress Report'!$Q$6 -> FIR Value (Todate) | AC3: Original Plan Value | AD3: ='Weekly Progress Report'!$U$3 -> Plan Value | AE3: ='Weekly Progress Report'!$U$4 -> Earn Value | AF3: ='Weekly Progress Report'!$W$3 -> Phys. Plan Value | AG3: ='Weekly Progress Report'!$W$4 -> Phys. Earn Value | AH3: ='Weekly Progress Report'!$Y$3 -> Quality Score | AI3: ='Weekly Progress Report'!$Y$5 -> Safety Score | AJ3: Weekly PV (SAR) | AK3: Weekly EV (SAR) | AL3: Weekly PV % | AM3: Weekly PV % | AN3: Weekly Phys PV% | AO3: Weekly Phys PV% | AP3: Total SD Planned | AQ3: SD Remaining | AR3: SD Pending | AS3: Total SD Submittals | AT3: Planned Materials Approv | AU3: Material Pending Approval | AV3: Materila Total Submittals | AW3: ='Weekly Progress Report'!C77 -> Total Materials | AX3: ='Weekly Progress Report'!D77 -> Total Number of P.O. | AY3: ='Weekly Progress Report'!E77 -> Actual P.O. To Date | AZ3: ='Weekly Progress Report'!F77 -> Remaining P.O | BA3: ='Weekly Progress Report'!G77 -> Material on Site | BB3: ='Weekly Progress Report'!H77 -> Remaining Materials | BC3: ='Weekly Progress Report'!I77 -> Material Delivery Completion (Date) | BD3: ="NCR "&'Weekly Progress Report'!N59 -> NCR Issued | BE3: ="NCR "&'Weekly Progress Report'!O59 -> NCR Closed | BF3: ="NCR "&'Weekly Progress Report'!P59 -> NCR Pending | BG3: ="NCR "&'Weekly Progress Report'!Q59 -> NCR Avg. Closing (Days) | BH3: ="SIR "&'Weekly Progress Report'!N59 -> SIR Issued | BI3: ="SIR "&'Weekly Progress Report'!O59 -> SIR Closed | BJ3: ="SIR "&'Weekly Progress Report'!P59 -> SIR Pending | BK3: ="SIR "&'Weekly Progress Report'!Q59 -> SIR Avg. Closing (Days) | BL3: ="MIR "&'Weekly Progress Report'!N59 -> MIR Issued | BM3: ="MIR "&'Weekly Progress Report'!O59 -> MIR Closed | BN3: ="MIR "&'Weekly Progress Report'!P59 -> MIR Pending | BO3: ="MIR "&'Weekly Progress Report'!Q59 -> MIR Avg. Closing (Days) | BP3: ="FIR "&'Weekly Progress Report'!N59 -> FIR Issued | BQ3: ="FIR "&'Weekly Progress Report'!O59 -> FIR Closed | BR3: ="FIR "&'Weekly Progress Report'!P59 -> FIR Pending | BS3: ="FIR "&'Weekly Progress Report'!Q59 -> FIR Avg. Closing (Days) | BT3: ='Weekly Progress Report'!L67 -> 1 Quality Plan Approval | BU3: ='Weekly Progress Report'!L68 -> 2 Quality Plan Last Up | BV3: ='Weekly Progress Report'!L69 -> 3 Safety Plan Approval | BW3: ='Weekly Progress Report'!L70 -> 4 Safety Plan Last Up | BX3: ='Weekly Progress Report'!L71 -> 5 Execution Plan Approval | BY3: ='Weekly Progress Report'!Q67 -> 6 Baseline Approval | BZ3: ='Weekly Progress Report'!Q68 -> 7 No of Approved Version of Schedule | CA3: ='Weekly Progress Report'!Q69 -> 8 Last Approved Schedule | CB3: ='Weekly Progress Report'!Q70 -> 9 BOQ Approval Date | CC3: ='Weekly Progress Report'!Q71 -> 10 No of Approved Version of BOQ | CD3: ='Weekly Progress Report'!L73 -> Total Submitted Invoices | CE3: ='Weekly Progress Report'!L74 -> PM Approved Invoices | CF3: ='Weekly Progress Report'!L75 -> No of Paid Invoices | CG3: ='Weekly Progress Report'!L76 -> No of Pending Invoices | CH3: ='Weekly Progress Report'!L77 -> Advance Payment % | CI3: ='Weekly Progress Report'!L78 -> Retention % | CJ3: ='Weekly Progress Report'!L79 -> Deduction / Penalties % | CK3: ='Weekly Progress Report'!O73 -> Submitted Invoices (SAR) | CL3: ='Weekly Progress Report'!O74 -> PM Approved Invoices (SAR) | CM3: ='Weekly Progress Report'!O75 -> Paid Invoices (SAR) | CN3: ='Weekly Progress Report'!O76 -> Last Submitted Period | CO3: ='Weekly Progress Report'!O77 -> Advance Payment (SAR) | CP3: ='Weekly Progress Report'!O78 -> Retention (SAR) | CQ3: ='Weekly Progress Report'!O79 -> Deduction / Penalties (SAR) | CR3: Planned Head Count | CS3: Actual Head Count | CT3: Saudi Staff | CU3: Labor Planned | CV3: Labor Actual | CW3: Equipment Planned | CX3: Equipment Actual | CY3: ="This Week "&'Weekly Progress Report'!X61 -> This Week Total Hours Worked | CZ3: ="This Week "&'Weekly Progress Report'!X62 -> This Week Safe Hours Worked | DA3: ="This Week "&'Weekly Progress Report'!X63 -> This Week LTI | DB3: ="This Week "&'Weekly Progress Report'!X64 -> This Week MTC (Healed w/o Disability) | DC3: ="This Week "&'Weekly Progress Report'!X65 -> This Week MTC (Healed w/ Disability) | DD3: ="This Week "&'Weekly Progress Report'!X66 -> This Week Near Miss | DE3: ="This Week "&'Weekly Progress Report'!X67 -> This Week First Aid Cases | DF3: ="This Week "&'Weekly Progress Report'!X68 -> This Week Fatality | DG3: ="This Week "&'Weekly Progress Report'!X69 -> This Week Fire Incident Cases | DH3: ="This Week "&'Weekly Progress Report'!X70 -> This Week Vehicle Incident | DI3: ="This Week "&'Weekly Progress Report'!X71 -> This Week Property Damages | DJ3: ="This Week "&'Weekly Progress Report'!X72 -> This Week Induction Training | DK3: ="This Week "&'Weekly Progress Report'!X73 -> This Week No.of Internal Training | DL3: ="This Week "&'Weekly Progress Report'!X74 -> This Week No.of Internal Audit | DM3: ="This Week "&'Weekly Progress Report'!X75 -> This Week No. of Toolbox Talks | DN3: ="This Week "&'Weekly Progress Report'!X76 -> This Week Safety Awards/Incentives | DO3: ="This Month "&'Weekly Progress Report'!X61 -> This Month Total Hours Worked | DP3: ="This Month "&'Weekly Progress Report'!X62 -> This Month Safe Hours Worked | DQ3: ="This Month "&'Weekly Progress Report'!X63 -> This Month LTI | DR3: ="This Month "&'Weekly Progress Report'!X64 -> This Month MTC (Healed w/o Disability) | DS3: ="This Month "&'Weekly Progress Report'!X65 -> This Month MTC (Healed w/ Disability) | DT3: ="This Month "&'Weekly Progress Report'!X66 -> This Month Near Miss | DU3: ="This Month "&'Weekly Progress Report'!X67 -> This Month First Aid Cases | DV3: ="This Month "&'Weekly Progress Report'!X68 -> This Month Fatality | DW3: ="This Month "&'Weekly Progress Report'!X69 -> This Month Fire Incident Cases | DX3: ="This Month "&'Weekly Progress Report'!X70 -> This Month Vehicle Incident | DY3: ="This Month "&'Weekly Progress Report'!X71 -> This Month Property Damages | DZ3: ="This Month "&'Weekly Progress Report'!X72 -> This Month Induction Training | EA3: ="This Month "&'Weekly Progress Report'!X73 -> This Month No.of Internal Training | EB3: ="This Month "&'Weekly Progress Report'!X74 -> This Month No.of Internal Audit | EC3: ="This Month "&'Weekly Progress Report'!X75 -> This Month No. of Toolbox Talks | ED3: ="This Month "&'Weekly Progress Report'!X76 -> This Month Safety Awards/Incentives | EE3: ="YTD "&'Weekly Progress Report'!X61 -> YTD Total Hours Worked | EF3: ="YTD "&'Weekly Progress Report'!X62 -> YTD Safe Hours Worked | EG3: ="YTD "&'Weekly Progress Report'!X63 -> YTD LTI | EH3: ="YTD "&'Weekly Progress Report'!X64 -> YTD MTC (Healed w/o Disability) | EI3: ="YTD "&'Weekly Progress Report'!X65 -> YTD MTC (Healed w/ Disability) | EJ3: ="YTD "&'Weekly Progress Report'!X66 -> YTD Near Miss | EK3: ="YTD "&'Weekly Progress Report'!X67 -> YTD First Aid Cases | EL3: ="YTD "&'Weekly Progress Report'!X68 -> YTD Fatality | EM3: ="YTD "&'Weekly Progress Report'!X69 -> YTD Fire Incident Cases | EN3: ="YTD "&'Weekly Progress Report'!X70 -> YTD Vehicle Incident | EO3: ="YTD "&'Weekly Progress Report'!X71 -> YTD Property Damages | EP3: ="YTD "&'Weekly Progress Report'!X72 -> YTD Induction Training | EQ3: ="YTD "&'Weekly Progress Report'!X73 -> YTD No.of Internal Training | ER3: ="YTD "&'Weekly Progress Report'!X74 -> YTD No.of Internal Audit | ES3: ="YTD "&'Weekly Progress Report'!X75 -> YTD No. of Toolbox Talks | ET3: ="YTD "&'Weekly Progress Report'!X76 -> YTD Safety Awards/Incentives | EU3: ="Cum "&'Weekly Progress Report'!X61 -> Cum Total Hours Worked | EV3: ="Cum "&'Weekly Progress Report'!X62 -> Cum Safe Hours Worked | EW3: ="Cum "&'Weekly Progress Report'!X63 -> Cum LTI | EX3: ="Cum "&'Weekly Progress Report'!X64 -> Cum MTC (Healed w/o Disability) | EY3: ="Cum "&'Weekly Progress Report'!X65 -> Cum MTC (Healed w/ Disability) | EZ3: ="Cum "&'Weekly Progress Report'!X66 -> Cum Near Miss | FA3: ="Cum "&'Weekly Progress Report'!X67 -> Cum First Aid Cases | FB3: ="Cum "&'Weekly Progress Report'!X68 -> Cum Fatality | FC3: ="Cum "&'Weekly Progress Report'!X69 -> Cum Fire Incident Cases | FD3: ="Cum "&'Weekly Progress Report'!X70 -> Cum Vehicle Incident | FE3: ="Cum "&'Weekly Progress Report'!X71 -> Cum Property Damages | FF3: ="Cum "&'Weekly Progress Report'!X72 -> Cum Induction Training | FG3: ="Cum "&'Weekly Progress Report'!X73 -> Cum No.of Internal Training | FH3: ="Cum "&'Weekly Progress Report'!X74 -> Cum No.of Internal Audit | FI3: ="Cum "&'Weekly Progress Report'!X75 -> Cum No. of Toolbox Talks | FJ3: ="Cum "&'Weekly Progress Report'!X76 -> Cum Safety Awards/Incentives | FK3: ='Weekly Progress Report'!A88 -> Total Act. | FL3: ='Weekly Progress Report'!B88 -> Not Started | FM3: ='Weekly Progress Report'!C88 -> In Progress | FN3: ='Weekly Progress Report'!D88 -> Completed | FO3: Critical Path Act.Last Week | FP3: Critical Path Act.This Week | FQ3: Failed start Last Week | FR3: Failed start This Week | FS3: ='Weekly Progress Report'!B96 -> 0 | FT3: ='Weekly Progress Report'!D96 -> 0 | FU3: ='Weekly Progress Report'!F96 -> 0 | FV3: ='Weekly Progress Report'!H96 -> 0 | FW3: ='Weekly Progress Report'!J96 -> 0 | FX3: ='Weekly Progress Report'!L96 -> 0 | FY3: ='Weekly Progress Report'!N96 -> 0 | FZ3: ='Weekly Progress Report'!O96 -> 0 | GA3: ='Weekly Progress Report'!P96 -> 0
A4: ='Weekly Progress Report'!AG1 -> 46308 | B4: ='Weekly Progress Report'!B3 -> LAND DEVELOPMENT OF JEDDAH OASIS | C4: ='Weekly Progress Report'!B4 -> JHD4-02-007 | D4: ='Weekly Progress Report'!B5 -> AL-ENJAZ TRADING AND CONTRACTING COMPANY | E4: ='Weekly Progress Report'!B6 -> SAUDI ARABIA CONSULTING ENGINEERING COMPANY "EGIS" | F4: ='Weekly Progress Report'!E4 -> Construction | G4: ='Weekly Progress Report'!E5 -> Active | H4: ='Weekly Progress Report'!E6 -> Mohammed Alshunaifi | I4: ='Weekly Progress Report'!AA3 -> Land development of jeddah oasis (The project includes construction of Roads works ; Storm water piping network with catch basins and manholes, Box Culvert ;Sewerage piping network with manhole ; Potable water piping network with fitting , valves and fire hydrant ;TSE Network ; Sewerage pump stations ;Channels ;36 KV medium voltage cable with Ring Main Unit ; Street Lighting with Unit Sub-stations , Ring Main Units and Low Voltage Cables ,concrete ducts at road crossing) | J4: ='Weekly Progress Report'!H3 -> 45970 | K4: ='Weekly Progress Report'!H4 -> 45977 | L4: ='Weekly Progress Report'!H5 -> 45985 | M4: ='Weekly Progress Report'!H6 -> 46530 | N4: ='Weekly Progress Report'!$J$3 -> 45970 | O4: ='Weekly Progress Report'!$J$4 -> 45977 | P4: ='Weekly Progress Report'!$J$5 -> 45985 | Q4: ='Weekly Progress Report'!$J$6 -> 46530 | R4: ='Weekly Progress Report'!$L$3 -> 46530 | S4: ='Weekly Progress Report'!$L$4 -> 46530 | T4: ='Weekly Progress Report'!$L$5 -> 46406 | U4: ='Weekly Progress Report'!$O$3 -> 57304348 | V4: ='Weekly Progress Report'!$O$4 -> 57304348 | W4: ='Weekly Progress Report'!$O$5 -> 57304348 | X4: ='Weekly Progress Report'!$O$6 -> 0 | Y4: ='Weekly Progress Report'!$S$3 -> 0 | Z4: ='Weekly Progress Report'!$S$4 -> 35217377 | AA4: ='Weekly Progress Report'!$S$5 -> 0 | AB4: ='Weekly Progress Report'!$S$6 -> 53231723 | AC4: ='Weekly Progress Report'!$J$28 -> 0.74182849 | AD4: ='Weekly Progress Report'!$V$3 -> 0.5984533 | AE4: ='Weekly Progress Report'!$V$4 -> 0.93306282 | AF4: ='Weekly Progress Report'!$X$3 -> 0.76402226 | AG4: ='Weekly Progress Report'!$X$4 -> 0.96133708 | AH4: ='Weekly Progress Report'!$Z$3 -> 0.85303793 | AI4: ='Weekly Progress Report'!$Z$5 -> 0.88 | AJ4: ='Weekly Progress Report'!$E$28 -> 706912.69 | AK4: ='Weekly Progress Report'!$F$28 -> 1259332.5 | AL4: =AJ4/V4 -> 0.012336109 | AM4: =AK4/V4 -> 0.021976213 | AN4: ='Weekly Progress Report'!S28 -> 0.012335407 | AO4: ='Weekly Progress Report'!T28 -> 0.010316841 | AP4: ='Weekly Progress Report'!C66 -> 393 | AQ4: ='Weekly Progress Report'!I66 -> 0 | AR4: ='Weekly Progress Report'!J66 -> 4 | AS4: ='Weekly Progress Report'!K66 -> 393 | AT4: ='Weekly Progress Report'!C75 -> 146 | AU4: ='Weekly Progress Report'!J75 -> 0 | AV4: ='Weekly Progress Report'!K75 -> 146 | AW4: ='Weekly Progress Report'!C84 -> 34 | AX4: ='Weekly Progress Report'!D84 -> 34 | AY4: ='Weekly Progress Report'!E84 -> 34 | AZ4: ='Weekly Progress Report'!F84 -> 0 | BA4: ='Weekly Progress Report'!G84 -> 27 | BB4: ='Weekly Progress Report'!H84 -> 7 | BC4: ='Weekly Progress Report'!I84 -> 46280 | BD4: ='Weekly Progress Report'!N62 -> 43 | BE4: ='Weekly Progress Report'!O62 -> 43 | BF4: ='Weekly Progress Report'!P62 -> 0 | BG4: ='Weekly Progress Report'!Q62 -> 0 | BH4: ='Weekly Progress Report'!N63 -> 10 | BI4: ='Weekly Progress Report'!O63 -> 10 | BJ4: ='Weekly Progress Report'!P63 -> 0 | BK4: ='Weekly Progress Report'!Q63 -> 0 | BL4: ='Weekly Progress Report'!N64 -> 116 | BM4: ='Weekly Progress Report'!O64 -> 116 | BN4: ='Weekly Progress Report'!P64 -> 0 | BO4: ='Weekly Progress Report'!Q64 -> 0 | BP4: ='Weekly Progress Report'!N65 -> 1571 | BQ4: ='Weekly Progress Report'!O65 -> 1551 | BR4: ='Weekly Progress Report'!P65 -> 20 | BS4: ='Weekly Progress Report'!Q65 -> 0 | BT4: ='Weekly Progress Report'!O67 -> 46039 | BU4: ='Weekly Progress Report'!O68 -> 1 | BV4: ='Weekly Progress Report'!O69 -> 46019 | BW4: ='Weekly Progress Report'!O70 -> 1 | BX4: ='Weekly Progress Report'!O71 -> 46034 | BY4: ='Weekly Progress Report'!U67 -> 46012 | BZ4: ='Weekly Progress Report'!U68 -> 1 | CA4: ='Weekly Progress Report'!U69 -> 46012 | CB4: ='Weekly Progress Report'!U70 -> 45985 | CC4: ='Weekly Progress Report'!U71 -> 1 | CD4: ='Weekly Progress Report'!N73 -> 8 | CE4: ='Weekly Progress Report'!N74 -> 7 | CF4: ='Weekly Progress Report'!N75 -> 3 | CG4: ='Weekly Progress Report'!N76 -> 4 | CH4: ='Weekly Progress Report'!N77 -> 0 | CI4: ='Weekly Progress Report'!N78 -> 0 | CJ4: ='Weekly Progress Report'!N79 -> 0 | CK4: ='Weekly Progress Report'!R73 -> 40499983 | CL4: ='Weekly Progress Report'!R74 -> 33617268 | CM4: ='Weekly Progress Report'!R75 -> 27469389 | CN4: ='Weekly Progress Report'!R76 -> 0 | CO4: ='Weekly Progress Report'!R77 -> 0 | CP4: ='Weekly Progress Report'!R78 -> 0 | CQ4: ='Weekly Progress Report'!R79 -> 0 | CR4: ='Weekly Progress Report'!L83 -> 12 | CS4: ='Weekly Progress Report'!M83 -> 49 | CT4: ='Weekly Progress Report'!O83 -> 0 | CU4: ='Weekly Progress Report'!P83 -> 61 | CV4: ='Weekly Progress Report'!Q83 -> 181 | CW4: ='Weekly Progress Report'!T93 -> 30 | CX4: ='Weekly Progress Report'!U93 -> 113 | CY4: ='Weekly Progress Report'!Z61 -> 11376 | CZ4: ='Weekly Progress Report'!Z62 -> 11376 | DA4: ='Weekly Progress Report'!Z63 -> 0 | DB4: ='Weekly Progress Report'!Z64 -> 0 | DC4: ='Weekly Progress Report'!Z65 -> 0 | DD4: ='Weekly Progress Report'!Z66 -> 0 | DE4: ='Weekly Progress Report'!Z67 -> 0 | DF4: ='Weekly Progress Report'!Z68 -> 0 | DG4: ='Weekly Progress Report'!Z69 -> 0 | DH4: ='Weekly Progress Report'!Z70 -> 0 | DI4: ='Weekly Progress Report'!Z71 -> 0 | DJ4: ='Weekly Progress Report'!Z72 -> 0 | DK4: ='Weekly Progress Report'!Z73 -> 5 | DL4: ='Weekly Progress Report'!Z74 -> 0 | DM4: ='Weekly Progress Report'!Z75 -> 1 | DN4: ='Weekly Progress Report'!Z76 -> 0 | DO4: ='Weekly Progress Report'!AB61 -> 22752 | DP4: ='Weekly Progress Report'!AB62 -> 22752 | DQ4: ='Weekly Progress Report'!AB63 -> 0 | DR4: ='Weekly Progress Report'!AB64 -> 0 | DS4: ='Weekly Progress Report'!AB65 -> 0 | DT4: ='Weekly Progress Report'!AB66 -> 0 | DU4: ='Weekly Progress Report'!AB67 -> 0 | DV4: ='Weekly Progress Report'!AB68 -> 0 | DW4: ='Weekly Progress Report'!AB69 -> 0 | DX4: ='Weekly Progress Report'!AB70 -> 0 | DY4: ='Weekly Progress Report'!AB71 -> 0 | DZ4: ='Weekly Progress Report'!AB72 -> 0 | EA4: ='Weekly Progress Report'!AB73 -> 12 | EB4: ='Weekly Progress Report'!AB74 -> 0 | EC4: ='Weekly Progress Report'!AB75 -> 2 | ED4: ='Weekly Progress Report'!AB76 -> 0 | EE4: ='Weekly Progress Report'!AC61 -> 491606 | EF4: ='Weekly Progress Report'!AC62 -> 491606 | EG4: ='Weekly Progress Report'!AC63 -> 0 | EH4: ='Weekly Progress Report'!AC64 -> 0 | EI4: ='Weekly Progress Report'!AC65 -> 0 | EJ4: ='Weekly Progress Report'!AC66 -> 0 | EK4: ='Weekly Progress Report'!AC67 -> 0 | EL4: ='Weekly Progress Report'!AC68 -> 0 | EM4: ='Weekly Progress Report'!AC69 -> 0 | EN4: ='Weekly Progress Report'!AC70 -> 0 | EO4: ='Weekly Progress Report'!AC71 -> 0 | EP4: ='Weekly Progress Report'!AC72 -> 69 | EQ4: ='Weekly Progress Report'!AC73 -> 264 | ER4: ='Weekly Progress Report'!AC74 -> 0 | ES4: ='Weekly Progress Report'!AC75 -> 42 | ET4: ='Weekly Progress Report'!AC76 -> 0 | EU4: ='Weekly Progress Report'!AD61 -> 504766 | EV4: ='Weekly Progress Report'!AD62 -> 504766 | EW4: ='Weekly Progress Report'!AD63 -> 0 | EX4: ='Weekly Progress Report'!AD64 -> 0 | EY4: ='Weekly Progress Report'!AD65 -> 0 | EZ4: ='Weekly Progress Report'!AD66 -> 0 | FA4: ='Weekly Progress Report'!AD67 -> 0 | FB4: ='Weekly Progress Report'!AD68 -> 0 | FC4: ='Weekly Progress Report'!AD69 -> 0 | FD4: ='Weekly Progress Report'!AD70 -> 0 | FE4: ='Weekly Progress Report'!AD71 -> 0 | FF4: ='Weekly Progress Report'!AD72 -> 80 | FG4: ='Weekly Progress Report'!AD73 -> 269 | FH4: ='Weekly Progress Report'!AD74 -> 0 | FI4: ='Weekly Progress Report'!AD75 -> 43 | FJ4: ='Weekly Progress Report'!AD76 -> 0 | FK4: ='Weekly Progress Report'!A89 -> 1218 | FL4: ='Weekly Progress Report'!B89 -> 24 | FM4: ='Weekly Progress Report'!C89 -> 21 | FN4: ='Weekly Progress Report'!D89 -> 1164 | FO4: ='Weekly Progress Report'!A93 -> 0 | FP4: ='Weekly Progress Report'!B93 -> 0 | FQ4: ='Weekly Progress Report'!H93 -> 4 | FR4: ='Weekly Progress Report'!I93 -> 2 | FS4: ='Weekly Progress Report'!B101 -> 0 | FT4: ='Weekly Progress Report'!D101 -> 0 | FU4: ='Weekly Progress Report'!F101 -> 0 | FV4: ='Weekly Progress Report'!H101 -> 0 | FW4: ='Weekly Progress Report'!J101 -> 0 | FX4: ='Weekly Progress Report'!L101 -> 0 | FY4: ='Weekly Progress Report'!N101 -> 0 | FZ4: ='Weekly Progress Report'!O101 -> 0 | GA4: ='Weekly Progress Report'!P101 -> 0

Sheet Weekly Progress Report
A1: MODON - Weekly Progress Report - Construction Projects | AD1: =+HSE!L4 -> Report No. | AE1: =+HSE!P4 -> 47 | AF1: Data Date | AG1: ='General Information'!L1 -> 46308
A2: Contract General Information | G2: Key Dates | M2: Cost Summary (SR) | U2: Performance Summary | AA2: Project Scope
A3: Project Name | B3: ='General Information'!C3 -> LAND DEVELOPMENT OF JEDDAH OASIS | G3: Contract Award | H3: ='General Information'!C12 -> 45970 | I3: Contract Award (Hijri) | J3: ='General Information'!C16 -> 45970 | K3: Revised Completion | L3: ='General Information'!C20 -> 46530 | M3: Original Contract Value | O3: ='Invoice Log'!E3 -> 57304348 | Q3: O&M Value (if any) | S3: ='Invoice Log'!I3 -> 0 | T3: EAC | U3: Plan Value | V3: =K28 -> 0.5984533 | W3: Phys. Plan Value | X3: =W28 -> 0.76402226 | Y3: Quality Score | Z3: =Quality!AC10 -> 0.85303793 | AA3: =+Progress!B1 -> Land development of jeddah oasis (The project includes construction of Roads works ; Storm water piping network with catch basins and manholes, Box Culvert ;Sewerage piping network with manhole ; Potable water piping network with fitting , valves and fire hydrant ;TSE Network ; Sewerage pump stations ;Channels ;36 KV medium voltage cable with Ring Main Unit ; Street Lighting with Unit Sub-stations , Ring Main Units and Low Voltage Cables ,concrete ducts at road crossing)
A4: Project ID | B4: ='General Information'!C4 -> JHD4-02-007 | D4: Stage | E4: ='General Information'!C7 -> Construction | G4: Contract Sign | H4: ='General Information'!C13 -> 45977 | I4: Contract Sign (Hijri) | J4: ='General Information'!C17 -> 45977 | K4: Committed Completion | L4: ='General Information'!C21 -> 46530 | M4: Revised Contract Value | O4: ='Invoice Log'!E4 -> 57304348 | P4: EAC | Q4: Submitted Invoices (Gross Value) | S4: =+'Invoice Log'!F59 -> 35217377 | U4: Earn Value | V4: =L28 -> 0.93306282 | W4: Phys. Earn Value | X4: =X28 -> 0.96133708 | Z4: =REPT("¢",IF(INT(+Z3*10)>5,5,INT(+Z3*10)))&REPT("£",IF(INT(+Z3*10)>5,0,5-INT(+Z3*10)))&CHAR(10)&REPT("¢",+IF(INT(+Z3*10)>5,-5+INT(+Z3*10),0))&REPT("£",IF(INT(+Z3*10)>5,10-INT(+Z3*10),5)) -> ¢¢¢¢¢ ¢¢¢££
A5: Contractor | B5: ='General Information'!C5 -> AL-ENJAZ TRADING AND CONTRACTING COMPANY | D5: Status | E5: ='General Information'!C8 -> Active | G5: Site Handover | H5: ='General Information'!C14 -> 45985 | I5: Site Handover (Hijri) | J5: ='General Information'!C18 -> 45985 | K5: Forecast Completion | L5: ='General Information'!C22 -> 46406 | M5: Estimate At Completion Value | O5: ='Invoice Log'!E5 -> 57304348 | P5: =+#REF!+#REF!+O5 -> #REF! | Q5: Penalities | S5: ='Invoice Log'!M6 -> 0 | U5: Variance | V5: =V4-V3 -> 0.33460951 | W5: Variance | X5: =X4-X3 -> 0.19731482 | Y5: Safety Score | Z5: ='HSE-Stat'!J23 -> 0.88
A6: Consultant | B6: ='General Information'!C6 -> SAUDI ARABIA CONSULTING ENGINEERING COMPANY "EGIS" | D6: Modon PM | E6: ='General Information'!C9 -> Mohammed Alshunaifi | G6: Original Completion | H6: ='General Information'!C15 -> 46530 | I6: Original Completion (Hijri) | J6: ='General Information'!C19 -> 46530 | K6: Variance | L6: ='General Information'!C23 -> 124 | M6: Potential Changes | O6: =O4-O5 -> 0 | Q6: FIR Value (Todate) | S6: =+'FIR summary '!K2 -> 53231723 | U6: FIR % | V6: =S6/O4 -> 0.92892992 | W6: Invoiced % | X6: =S4/O4 -> 0.61456728 | Z6: =REPT("¢",IF(INT(+Z5*10)>5,5,INT(+Z5*10)))&REPT("£",IF(INT(+Z5*10)>5,0,5-INT(+Z5*10)))&CHAR(10)&REPT("¢",+IF(INT(+Z5*10)>5,-5+INT(+Z5*10),0))&REPT("£",IF(INT(+Z5*10)>5,10-INT(+Z5*10),5)) -> ¢¢¢¢¢ ¢¢¢££
A8: Progress Overview
A9: Earned Value Progress (SAR) | O9: Physical Progress (Effort) | AA9: Earned Value Progress (%)
A10: WBS | C10: BOQ Value (SAR) | D10: % Wt. | E10: Weekly (SAR) | G10: To Date (SAR) | O10: Budgeted | P10: % Wt. | Q10: Weekly Physical Progress | U10: To Date Physical Progress
E11: Planned | F11: Earned | G11: Original Plan | H11: Revised Planned | I11: Earned | J11: Original Plan % | K11: Revised Planned % | L11: Earned % | M11: Variance | N11: SPI | O11: (Manhours) | Q11: Planned | R11: Earned | S11: Plan % | T11: Earned % | U11: Planned | V11: Earned | W11: Plan % | X11: Earned % | Y11: Variance | Z11: SPI
A12: =+Progress!A7 -> Preliminaries | C12: =+Progress!C7 -> 0 | D12: =IF(ISBLANK(C12),"",C12/$C$28) -> 0 | E12: =+Progress!E7 -> 0 | F12: =+Progress!F7 -> 0 | G12: =+Progress!G7 -> 0 | H12: =+Progress!H7 -> 0 | I12: =+Progress!I7 -> 0 | J12: =IFERROR(IF(ISBLANK(G12),"",G12/C12),0) -> 0 | K12: =IFERROR(IF(ISBLANK(H12),"",H12/C12),0) -> 0 | L12: =IFERROR(IF(ISBLANK(I12),"",I12/C12),0) -> 0 | M12: =IFERROR(L12-K12,"") -> 0 | N12: =IFERROR(L12/K12,"") | O12: =+Progress!K7 -> 8492 | P12: =IF(ISBLANK(O12),"",O12/$O$28) -> 0.020904465 | Q12: =+Progress!M7 -> 0 | R12: =+Progress!N7 -> 0 | S12: =IFERROR(IF(ISBLANK(Q12),"",Q12/O12),0) -> 0 | T12: =IFERROR(IF(ISBLANK(R12),"",R12/O12),0) -> 0 | U12: =+Progress!O7 -> 8492 | V12: =+Progress!P7 -> 8492 | W12: =IFERROR(IF(ISBLANK(U12),"",U12/O12),0) -> 1 | X12: =IFERROR(IF(ISBLANK(V12),"",V12/O12),0) -> 1 | Y12: =IFERROR(X12-W12,"") -> 0 | Z12: =IFERROR(X12/W12,"") -> 1
A13: =+Progress!A9 -> Engineering | C13: =+Progress!C9 -> 1719130.4 | D13: =IF(ISBLANK(C13),"",C13/$C$28) -> 0.03 | E13: =+Progress!E9 -> 0 | F13: =+Progress!F9 -> 0 | G13: =+Progress!G9 -> 1719130.4 | H13: =+Progress!H9 -> 1690948 | I13: =+Progress!I9 -> 1719130.4 | J13: =IFERROR(IF(ISBLANK(G13),"",G13/C13),0) -> 1 | K13: =IFERROR(IF(ISBLANK(H13),"",H13/C13),0) -> 0.98360656 | L13: =IFERROR(IF(ISBLANK(I13),"",I13/C13),0) -> 1 | M13: =IFERROR(L13-K13,"") -> 0.016393445 | N13: =IFERROR(L13/K13,"") -> 1.0166667 | O13: =+Progress!K9 -> 18263 | P13: =IF(ISBLANK(O13),"",O13/$O$28) -> 0.044957401 | Q13: =+Progress!M9 -> 108 | R13: =+Progress!N9 -> 0 | S13: =IFERROR(IF(ISBLANK(Q13),"",Q13/O13),0) -> 0.0059135958 | T13: =IFERROR(IF(ISBLANK(R13),"",R13/O13),0) -> 0 | U13: =+Progress!O9 -> 18189 | V13: =+Progress!P9 -> 18270 | W13: =IFERROR(IF(ISBLANK(U13),"",U13/O13),0) -> 0.99594809 | X13: =IFERROR(IF(ISBLANK(V13),"",V13/O13),0) -> 1.0003833 | Y13: =IFERROR(X13-W13,"") -> 0.0044351968 | Z13: =IFERROR(X13/W13,"") -> 1.0044532
A14: =+Progress!A11 -> Procuments | C14: =+Progress!C11 -> 11460870 | D14: =IF(ISBLANK(C14),"",C14/$C$28) -> 0.2 | E14: =+Progress!E11 -> 393541.03 | F14: =+Progress!F11 -> 0 | G14: =+Progress!G11 -> 10712587 | H14: =+Progress!H11 -> 9731079.8 | I14: =+Progress!I11 -> 11460870 | J14: =IFERROR(IF(ISBLANK(G14),"",G14/C14),0) -> 0.93470982 | K14: =IFERROR(IF(ISBLANK(H14),"",H14/C14),0) -> 0.84906994 | L14: =IFERROR(IF(ISBLANK(I14),"",I14/C14),0) -> 1 | M14: =IFERROR(L14-K14,"") -> 0.15093006 | N14: =IFERROR(L14/K14,"") -> 1.1777593 | O14: =+Progress!K11 -> 82180 | P14: =IF(ISBLANK(O14),"",O14/$O$28) -> 0.20229969 | Q14: =+Progress!M11 -> 1086 | R14: =+Progress!N11 -> 0 | S14: =IFERROR(IF(ISBLANK(Q14),"",Q14/O14),0) -> 0.013214894 | T14: =IFERROR(IF(ISBLANK(R14),"",R14/O14),0) -> 0 | U14: =+Progress!O11 -> 79551 | V14: =+Progress!P11 -> 83973 | W14: =IFERROR(IF(ISBLANK(U14),"",U14/O14),0) -> 0.96800925 | X14: =IFERROR(IF(ISBLANK(V14),"",V14/O14),0) -> 1.021818 | Y14: =IFERROR(X14-W14,"") -> 0.053808713 | Z14: =IFERROR(X14/W14,"") -> 1.055587
A15: =+Progress!A13 -> ROAD WORKS | C15: =+Progress!C13 -> 13221675 | D15: =IF(ISBLANK(C15),"",C15/$C$28) -> 0.23072726 | E15: =+Progress!E13 -> 116746.48 | F15: =+Progress!F13 -> 201466.73 | G15: =+Progress!G13 -> 8086622.7 | H15: =+Progress!H13 -> 7989416.3 | I15: =+Progress!I13 -> 14417397 | J15: =IFERROR(IF(ISBLANK(G15),"",G15/C15),0) -> 0.61161862 | K15: =IFERROR(IF(ISBLANK(H15),"",H15/C15),0) -> 0.60426657 | L15: =IFERROR(IF(ISBLANK(I15),"",I15/C15),0) -> 1.0904365 | M15: =IFERROR(L15-K15,"") -> 0.48616991 | N15: =IFERROR(L15/K15,"") -> 1.804562 | O15: =+Progress!K13 -> 53186 | P15: =IF(ISBLANK(O15),"",O15/$O$28) -> 0.13092615 | Q15: =+Progress!M13 -> 540 | R15: =+Progress!N13 -> 1563 | S15: =IFERROR(IF(ISBLANK(Q15),"",Q15/O15),0) -> 0.010153048 | T15: =IFERROR(IF(ISBLANK(R15),"",R15/O15),0) -> 0.029387433 | U15: =+Progress!O13 -> 39667 | V15: =+Progress!P13 -> 56207 | W15: =IFERROR(IF(ISBLANK(U15),"",U15/O15),0) -> 0.74581657 | X15: =IFERROR(IF(ISBLANK(V15),"",V15/O15),0) -> 1.0568007 | Y15: =IFERROR(X15-W15,"") -> 0.31098409 | Z15: =IFERROR(X15/W15,"") -> 1.4169713
A16: =+Progress!A15 -> Electrical Works | C16: =+Progress!C15 -> 3953631.6 | D16: =IF(ISBLANK(C16),"",C16/$C$28) -> 0.068993572 | E16: =+Progress!E15 -> 90863.03 | F16: =+Progress!F15 -> 113449.56 | G16: =+Progress!G15 -> 2790664.9 | H16: =+Progress!H15 -> 1529434.3 | I16: =+Progress!I15 -> 4232139.5 | J16: =IFERROR(IF(ISBLANK(G16),"",G16/C16),0) -> 0.70584847 | K16: =IFERROR(IF(ISBLANK(H16),"",H16/C16),0) -> 0.3868429 | L16: =IFERROR(IF(ISBLANK(I16),"",I16/C16),0) -> 1.0704436 | M16: =IFERROR(L16-K16,"") -> 0.68360065 | N16: =IFERROR(L16/K16,"") -> 2.7671273 | O16: =+Progress!K15 -> 58660 | P16: =IF(ISBLANK(O16),"",O16/$O$28) -> 0.14440131 | Q16: =+Progress!M15 -> 1272 | R16: =+Progress!N15 -> 1009 | S16: =IFERROR(IF(ISBLANK(Q16),"",Q16/O16),0) -> 0.021684282 | T16: =IFERROR(IF(ISBLANK(R16),"",R16/O16),0) -> 0.017200818 | U16: =+Progress!O15 -> 22808 | V16: =+Progress!P15 -> 49140 | W16: =IFERROR(IF(ISBLANK(U16),"",U16/O16),0) -> 0.38881691 | X16: =IFERROR(IF(ISBLANK(V16),"",V16/O16),0) -> 0.83770883 | Y16: =IFERROR(X16-W16,"") -> 0.44889192 | Z16: =IFERROR(X16/W16,"") -> 2.1545072
A17: =+Progress!A17 -> Demolition Works | C17: =+Progress!C17 -> 506619.53 | D17: =IF(ISBLANK(C17),"",C17/$C$28) -> 0.0088408567 | E17: =+Progress!E17 -> 0 | F17: =+Progress!F17 -> 0 | G17: =+Progress!G17 -> 506619.53 | H17: =+Progress!H17 -> 505616.54 | I17: =+Progress!I17 -> 505616.54 | J17: =IFERROR(IF(ISBLANK(G17),"",G17/C17),0) -> 1 | K17: =IFERROR(IF(ISBLANK(H17),"",H17/C17),0) -> 0.99802023 | L17: =IFERROR(IF(ISBLANK(I17),"",I17/C17),0) -> 0.99802023 | M17: =IFERROR(L17-K17,"") -> 0 | N17: =IFERROR(L17/K17,"") -> 1 | O17: =+Progress!K17 -> 14710 | P17: =IF(ISBLANK(O17),"",O17/$O$28) -> 0.036211103 | Q17: =+Progress!M17 -> 0 | R17: =+Progress!N17 -> 0 | S17: =IFERROR(IF(ISBLANK(Q17),"",Q17/O17),0) -> 0 | T17: =IFERROR(IF(ISBLANK(R17),"",R17/O17),0) -> 0 | U17: =+Progress!O17 -> 16105 | V17: =+Progress!P17 -> 16105 | W17: =IFERROR(IF(ISBLANK(U17),"",U17/O17),0) -> 1.0948334 | X17: =IFERROR(IF(ISBLANK(V17),"",V17/O17),0) -> 1.0948334 | Y17: =IFERROR(X17-W17,"") -> 0 | Z17: =IFERROR(X17/W17,"") -> 1
A18: =+Progress!A19 -> Storm Water Network | C18: =+Progress!C19 -> 3336320.6 | D18: =IF(ISBLANK(C18),"",C18/$C$28) -> 0.058221073 | E18: =+Progress!E19 -> 59901.47 | F18: =+Progress!F19 -> 0 | G18: =+Progress!G19 -> 3336320.6 | H18: =+Progress!H19 -> 2238976.9 | I18: =+Progress!I19 -> 2558110.5 | J18: =IFERROR(IF(ISBLANK(G18),"",G18/C18),0) -> 1 | K18: =IFERROR(IF(ISBLANK(H18),"",H18/C18),0) -> 0.67109163 | L18: =IFERROR(IF(ISBLANK(I18),"",I18/C18),0) -> 0.76674599 | M18: =IFERROR(L18-K18,"") -> 0.095654356 | N18: =IFERROR(L18/K18,"") -> 1.1425355 | O18: =+Progress!K19 -> 29100 | P18: =IF(ISBLANK(O18),"",O18/$O$28) -> 0.071634472 | Q18: =+Progress!M19 -> 270 | R18: =+Progress!N19 -> 0 | S18: =IFERROR(IF(ISBLANK(Q18),"",Q18/O18),0) -> 0.0092783505 | T18: =IFERROR(IF(ISBLANK(R18),"",R18/O18),0) -> 0 | U18: =+Progress!O19 -> 26800 | V18: =+Progress!P19 -> 29900 | W18: =IFERROR(IF(ISBLANK(U18),"",U18/O18),0) -> 0.9209622 | X18: =IFERROR(IF(ISBLANK(V18),"",V18/O18),0) -> 1.0274914 | Y18: =IFERROR(X18-W18,"") -> 0.10652921 | Z18: =IFERROR(X18/W18,"") -> 1.1156716
A19: =+Progress!A21 -> Plots | C19: =+Progress!C21 -> 7378530.4 | D19: =IF(ISBLANK(C19),"",C19/$C$28) -> 0.12876039 | E19: =+Progress!E21 -> 0 | F19: =+Progress!F21 -> 152056.15 | G19: =+Progress!G21 -> 7378530.4 | H19: =+Progress!H21 -> 4337407.5 | I19: =+Progress!I21 -> 6820991.2 | J19: =IFERROR(IF(ISBLANK(G19),"",G19/C19),0) -> 1 | K19: =IFERROR(IF(ISBLANK(H19),"",H19/C19),0) -> 0.58784166 | L19: =IFERROR(IF(ISBLANK(I19),"",I19/C19),0) -> 0.92443764 | M19: =IFERROR(L19-K19,"") -> 0.33659598 | N19: =IFERROR(L19/K19,"") -> 1.5725963 | O19: =+Progress!K21 -> 12640 | P19: =IF(ISBLANK(O19),"",O19/$O$28) -> 0.031115455 | Q19: =+Progress!M21 -> 0 | R19: =+Progress!N21 -> 215 | S19: =IFERROR(IF(ISBLANK(Q19),"",Q19/O19),0) -> 0 | T19: =IFERROR(IF(ISBLANK(R19),"",R19/O19),0) -> 0.017009494 | U19: =+Progress!O21 -> 10430 | V19: =+Progress!P21 -> 13856 | W19: =IFERROR(IF(ISBLANK(U19),"",U19/O19),0) -> 0.82515823 | X19: =IFERROR(IF(ISBLANK(V19),"",V19/O19),0) -> 1.0962025 | Y19: =IFERROR(X19-W19,"") -> 0.2710443 | Z19: =IFERROR(X19/W19,"") -> 1.3284756
A20: =+Progress!A23 -> Sewer Water Network | C20: =+Progress!C23 -> 2156250.5 | D20: =IF(ISBLANK(C20),"",C20/$C$28) -> 0.037628043 | E20: =+Progress!E23 -> 0 | F20: =+Progress!F23 -> 0 | G20: =+Progress!G23 -> 2156250.5 | H20: =+Progress!H23 -> 1505981 | I20: =+Progress!I23 -> 1505981 | J20: =IFERROR(IF(ISBLANK(G20),"",G20/C20),0) -> 1 | K20: =IFERROR(IF(ISBLANK(H20),"",H20/C20),0) -> 0.69842581 | L20: =IFERROR(IF(ISBLANK(I20),"",I20/C20),0) -> 0.69842581 | M20: =IFERROR(L20-K20,"") -> 0 | N20: =IFERROR(L20/K20,"") -> 1 | O20: =+Progress!K23 -> 24496 | P20: =IF(ISBLANK(O20),"",O20/$O$28) -> 0.060300963 | Q20: =+Progress!M23 -> 0 | R20: =+Progress!N23 -> 0 | S20: =IFERROR(IF(ISBLANK(Q20),"",Q20/O20),0) -> 0 | T20: =IFERROR(IF(ISBLANK(R20),"",R20/O20),0) -> 0 | U20: =+Progress!O23 -> 20616 | V20: =+Progress!P23 -> 20616 | W20: =IFERROR(IF(ISBLANK(U20),"",U20/O20),0) -> 0.84160679 | X20: =IFERROR(IF(ISBLANK(V20),"",V20/O20),0) -> 0.84160679 | Y20: =IFERROR(X20-W20,"") -> 0 | Z20: =IFERROR(X20/W20,"") -> 1
A21: =+Progress!A25 -> TSE Network | C21: =+Progress!C25 -> 1589264.4 | D21: =IF(ISBLANK(C21),"",C21/$C$28) -> 0.027733749 | E21: =+Progress!E25 -> 34853.63 | F21: =+Progress!F25 -> 0 | G21: =+Progress!G25 -> 1433580.4 | H21: =+Progress!H25 -> 1162894.8 | I21: =+Progress!I25 -> 1342832 | J21: =IFERROR(IF(ISBLANK(G21),"",G21/C21),0) -> 0.90204023 | K21: =IFERROR(IF(ISBLANK(H21),"",H21/C21),0) -> 0.73171889 | L21: =IFERROR(IF(ISBLANK(I21),"",I21/C21),0) -> 0.84493933 | M21: =IFERROR(L21-K21,"") -> 0.11322044 | N21: =IFERROR(L21/K21,"") -> 1.1547321 | O21: =+Progress!K25 -> 39495 | P21: =IF(ISBLANK(O21),"",O21/$O$28) -> 0.097223487 | Q21: =+Progress!M25 -> 480 | R21: =+Progress!N25 -> 0 | S21: =IFERROR(IF(ISBLANK(Q21),"",Q21/O21),0) -> 0.012153437 | T21: =IFERROR(IF(ISBLANK(R21),"",R21/O21),0) -> 0 | U21: =+Progress!O25 -> 32200 | V21: =+Progress!P25 -> 37150 | W21: =IFERROR(IF(ISBLANK(U21),"",U21/O21),0) -> 0.81529308 | X21: =IFERROR(IF(ISBLANK(V21),"",V21/O21),0) -> 0.9406254 | Y21: =IFERROR(X21-W21,"") -> 0.12533232 | Z21: =IFERROR(X21/W21,"") -> 1.1537267
A22: =+Progress!A27 -> Potable Water Network | C22: =+Progress!C27 -> 2200624.9 | D22: =IF(ISBLANK(C22),"",C22/$C$28) -> 0.038402407 | E22: =+Progress!E27 -> 9817.23 | F22: =+Progress!F27 -> 0 | G22: =+Progress!G27 -> 2140576.5 | H22: =+Progress!H27 -> 1775528.8 | I22: =+Progress!I27 -> 2005333.6 | J22: =IFERROR(IF(ISBLANK(G22),"",G22/C22),0) -> 0.97271301 | K22: =IFERROR(IF(ISBLANK(H22),"",H22/C22),0) -> 0.80682935 | L22: =IFERROR(IF(ISBLANK(I22),"",I22/C22),0) -> 0.91125642 | M22: =IFERROR(L22-K22,"") -> 0.10442707 | N22: =IFERROR(L22/K22,"") -> 1.1294289 | O22: =+Progress!K27 -> 31247 | P22: =IF(ISBLANK(O22),"",O22/$O$28) -> 0.076919668 | Q22: =+Progress!M27 -> 958 | R22: =+Progress!N27 -> 0 | S22: =IFERROR(IF(ISBLANK(Q22),"",Q22/O22),0) -> 0.030658943 | T22: =IFERROR(IF(ISBLANK(R22),"",R22/O22),0) -> 0 | U22: =+Progress!O27 -> 22760 | V22: =+Progress!P27 -> 27107 | W22: =IFERROR(IF(ISBLANK(U22),"",U22/O22),0) -> 0.72838993 | X22: =IFERROR(IF(ISBLANK(V22),"",V22/O22),0) -> 0.86750728 | Y22: =IFERROR(X22-W22,"") -> 0.13911736 | Z22: =IFERROR(X22/W22,"") -> 1.190993
A23: =+Progress!A29 -> Sewage Lift Station | C23: =+Progress!C29 -> 3049343.4 | D23: =IF(ISBLANK(C23),"",C23/$C$28) -> 0.053213125 | E23: =+Progress!E29 -> 1189.82 | F23: =+Progress!F29 -> 628633.39 | G23: =+Progress!G29 -> 0 | H23: =+Progress!H29 -> 5992.14 | I23: =+Progress!I29 -> 1845852.3 | J23: =IFERROR(IF(ISBLANK(G23),"",G23/C23),0) -> 0 | K23: =IFERROR(IF(ISBLANK(H23),"",H23/C23),0) -> 0.0019650591 | L23: =IFERROR(IF(ISBLANK(I23),"",I23/C23),0) -> 0.6053278 | M23: =IFERROR(L23-K23,"") -> 0.60336274 | N23: =IFERROR(L23/K23,"") -> 308.0456 | O23: =+Progress!K29 -> 15410 | P23: =IF(ISBLANK(O23),"",O23/$O$28) -> 0.037934269 | Q23: =+Progress!M29 -> 297 | R23: =+Progress!N29 -> 1164 | S23: =IFERROR(IF(ISBLANK(Q23),"",Q23/O23),0) -> 0.019273199 | T23: =IFERROR(IF(ISBLANK(R23),"",R23/O23),0) -> 0.075535367 | U23: =+Progress!O29 -> 1107 | V23: =+Progress!P29 -> 13114 | W23: =IFERROR(IF(ISBLANK(U23),"",U23/O23),0) -> 0.07183647 | X23: =IFERROR(IF(ISBLANK(V23),"",V23/O23),0) -> 0.85100584 | Y23: =IFERROR(X23-W23,"") -> 0.77916937 | Z23: =IFERROR(X23/W23,"") -> 11.846432
A24: =+Progress!A31 -> Box Culvert | C24: =+Progress!C31 -> 499321.73 | D24: =IF(ISBLANK(C24),"",C24/$C$28) -> 0.0087135051 | E24: =+Progress!E31 -> 0 | F24: =+Progress!F31 -> 0 | G24: =+Progress!G31 -> 499321.73 | H24: =+Progress!H31 -> 499735.96 | I24: =+Progress!I31 -> 499735.96 | J24: =IFERROR(IF(ISBLANK(G24),"",G24/C24),0) -> 1 | K24: =IFERROR(IF(ISBLANK(H24),"",H24/C24),0) -> 1.0008296 | L24: =IFERROR(IF(ISBLANK(I24),"",I24/C24),0) -> 1.0008296 | M24: =IFERROR(L24-K24,"") -> 0 | N24: =IFERROR(L24/K24,"") -> 1 | O24: =+Progress!K31 -> 2200 | P24: =IF(ISBLANK(O24),"",O24/$O$28) -> 0.0054156646 | Q24: =+Progress!M31 -> 0 | R24: =+Progress!N31 -> 0 | S24: =IFERROR(IF(ISBLANK(Q24),"",Q24/O24),0) -> 0 | T24: =IFERROR(IF(ISBLANK(R24),"",R24/O24),0) -> 0 | U24: =+Progress!O31 -> 2515 | V24: =+Progress!P31 -> 2515 | W24: =IFERROR(IF(ISBLANK(U24),"",U24/O24),0) -> 1.1431818 | X24: =IFERROR(IF(ISBLANK(V24),"",V24/O24),0) -> 1.1431818 | Y24: =IFERROR(X24-W24,"") -> 0 | Z24: =IFERROR(X24/W24,"") -> 1
A25: =+Progress!A33 -> Open Drain Channel | C25: =+Progress!C33 -> 389804.75 | D25: =IF(ISBLANK(C25),"",C25/$C$28) -> 0.0068023591 | E25: =+Progress!E33 -> 0 | F25: =+Progress!F33 -> 0 | G25: =+Progress!G33 -> 0 | H25: =+Progress!H33 -> 389804.76 | I25: =+Progress!I33 -> 389804.76 | J25: =IFERROR(IF(ISBLANK(G25),"",G25/C25),0) -> 0 | K25: =IFERROR(IF(ISBLANK(H25),"",H25/C25),0) -> 1 | L25: =IFERROR(IF(ISBLANK(I25),"",I25/C25),0) -> 1 | M25: =IFERROR(L25-K25,"") -> 0 | N25: =IFERROR(L25/K25,"") -> 1 | O25: =+Progress!K33 -> 5040 | P25: =IF(ISBLANK(O25),"",O25/$O$28) -> 0.012406795 | Q25: =+Progress!M33 -> 0 | R25: =+Progress!N33 -> 0 | S25: =IFERROR(IF(ISBLANK(Q25),"",Q25/O25),0) -> 0 | T25: =IFERROR(IF(ISBLANK(R25),"",R25/O25),0) -> 0 | U25: =+Progress!O33 -> 6458 | V25: =+Progress!P33 -> 6458 | W25: =IFERROR(IF(ISBLANK(U25),"",U25/O25),0) -> 1.2813492 | X25: =IFERROR(IF(ISBLANK(V25),"",V25/O25),0) -> 1.2813492 | Y25: =IFERROR(X25-W25,"") -> 0 | Z25: =IFERROR(X25/W25,"") -> 1
A26: =+Progress!A35 -> Under Pass | C26: =+Progress!C35 -> 112526.05 | D26: =IF(ISBLANK(C26),"",C26/$C$28) -> 0.0019636564 | E26: =+Progress!E35 -> 0 | F26: =+Progress!F35 -> 0 | G26: =+Progress!G35 -> 112526.05 | H26: =+Progress!H35 -> 112526.05 | I26: =+Progress!I35 -> 112526.05 | J26: =IFERROR(IF(ISBLANK(G26),"",G26/C26),0) -> 1 | K26: =IFERROR(IF(ISBLANK(H26),"",H26/C26),0) -> 1 | L26: =IFERROR(IF(ISBLANK(I26),"",I26/C26),0) -> 1 | M26: =IFERROR(L26-K26,"") -> 0 | N26: =IFERROR(L26/K26,"") -> 1 | O26: =+Progress!K35 -> 1400 | P26: =IF(ISBLANK(O26),"",O26/$O$28) -> 0.003446332 | Q26: =+Progress!M35 -> 0 | R26: =+Progress!N35 -> 0 | S26: =IFERROR(IF(ISBLANK(Q26),"",Q26/O26),0) -> 0 | T26: =IFERROR(IF(ISBLANK(R26),"",R26/O26),0) -> 0 | U26: =+Progress!O35 -> 1400 | V26: =+Progress!P35 -> 1400 | W26: =IFERROR(IF(ISBLANK(U26),"",U26/O26),0) -> 1 | X26: =IFERROR(IF(ISBLANK(V26),"",V26/O26),0) -> 1 | Y26: =IFERROR(X26-W26,"") -> 0 | Z26: =IFERROR(X26/W26,"") -> 1
A27: =+Progress!A37 -> Testing and Commissioning | C27: =+Progress!C37 -> 5730434.8 | D27: =IF(ISBLANK(C27),"",C27/$C$28) -> 0.1 | E27: =+Progress!E37 -> 0 | F27: =+Progress!F37 -> 163726.7 | G27: =+Progress!G37 -> 1637267.1 | H27: =+Progress!H37 -> 818633.54 | I27: =+Progress!I37 -> 4052236 | J27: =IFERROR(IF(ISBLANK(G27),"",G27/C27),0) -> 0.28571429 | K27: =IFERROR(IF(ISBLANK(H27),"",H27/C27),0) -> 0.14285714 | L27: =IFERROR(IF(ISBLANK(I27),"",I27/C27),0) -> 0.70714286 | M27: =IFERROR(L27-K27,"") -> 0.56428571 | N27: =IFERROR(L27/K27,"") -> 4.95 | O27: =+Progress!K37 -> 9710 | P27: =IF(ISBLANK(O27),"",O27/$O$28) -> 0.023902774 | Q27: =+Progress!M37 -> 0 | R27: =+Progress!N37 -> 240 | S27: =IFERROR(IF(ISBLANK(Q27),"",Q27/O27),0) -> 0 | T27: =IFERROR(IF(ISBLANK(R27),"",R27/O27),0) -> 0.024716787 | U27: =+Progress!O37 -> 1270 | V27: =+Progress!P37 -> 6220 | W27: =IFERROR(IF(ISBLANK(U27),"",U27/O27),0) -> 0.130793 | X27: =IFERROR(IF(ISBLANK(V27),"",V27/O27),0) -> 0.64057673 | Y27: =IFERROR(X27-W27,"") -> 0.50978373 | Z27: =IFERROR(X27/W27,"") -> 4.8976378
B28: Total | C28: =SUM(C12:C27) -> 57304348 | D28: =SUM(D12:D27) -> 1 | E28: =SUM(E12:E27) -> 706912.69 | F28: =SUM(F12:F27) -> 1259332.5 | G28: =SUM(G12:G27) -> 42509998 | H28: =SUM(H12:H27) -> 34293976 | I28: =SUM(I12:I27) -> 53468556 | J28: =IFERROR(IF(ISBLANK(G28),"",G28/C28),0) -> 0.74182849 | K28: =IFERROR(IF(ISBLANK(H28),"",H28/C28),0) -> 0.5984533 | L28: =IFERROR(IF(ISBLANK(I28),"",I28/C28),0) -> 0.93306282 | M28: =+L28-K28 -> 0.33460951 | N28: =L28/K28 -> 1.5591238 | O28: =SUM(O12:O27) -> 406229 | P28: =SUM(P12:P27) -> 1 | Q28: =SUM(Q12:Q27) -> 5011 | R28: =SUM(R12:R27) -> 4191 | S28: =IFERROR(IF(ISBLANK(Q28),"",Q28/O28),0) -> 0.012335407 | T28: =IFERROR(IF(ISBLANK(R28),"",R28/O28),0) -> 0.010316841 | U28: =SUM(U12:U27) -> 310368 | V28: =SUM(V12:V27) -> 390523 | W28: =IFERROR(IF(ISBLANK(U28),"",U28/O28),0) -> 0.76402226 | X28: =IFERROR(IF(ISBLANK(V28),"",V28/O28),0) -> 0.96133708 | Y28: =+X28-W28 -> 0.19731482 | Z28: =X28/W28 -> 1.2582579
AA29: Construction Milestones
AA30: Item No. | AB30: Milestones | AD30: Original (Baseline) | AE30: Latest Plan | AF30: Forecast | AG30: Status | AH30: Days Change
AA31: =+Milestones!A4 -> 1 | AB31: =+Milestones!B4 -> Award Date | AD31: =+Milestones!C4 -> 45970 | AE31: =+Milestones!D4 -> 45970 | AF31: =+Milestones!E4 -> 45970 | AG31: =+Milestones!F4 -> A | AH31: =+Milestones!G4 -> 0
AA32: =+Milestones!A5 -> 2 | AB32: =+Milestones!B5 -> Contract Sign Date | AD32: =+Milestones!C5 -> 45977 | AE32: =+Milestones!D5 -> 45977 | AF32: =+Milestones!E5 -> 45977 | AG32: =+Milestones!F5 -> A | AH32: =+Milestones!G5 -> 0
AA33: =+Milestones!A6 -> 3 | AB33: =+Milestones!B6 -> Site Handover Date | AD33: =+Milestones!C6 -> 45985 | AE33: =+Milestones!D6 -> 45985 | AF33: =+Milestones!E6 -> 45985 | AG33: =+Milestones!F6 -> A | AH33: =+Milestones!G6 -> 0
AA34: =+Milestones!A7 -> 4 | AB34: =+Milestones!B7 -> Complete Mobilization | AD34: =+Milestones!C7 -> 46014 | AE34: =+Milestones!D7 -> 46014 | AF34: =+Milestones!E7 -> 46014 | AG34: =+Milestones!F7 -> A | AH34: =+Milestones!G7 -> 0
AA35: =+Milestones!A10 -> 7 | AB35: =+Milestones!B10 -> Complete delivery of all equipment and materials | AD35: =+Milestones!C10 -> 46387 | AE35: =+Milestones!D10 -> 46393 | AF35: =+Milestones!E10 -> 46301 | AG35: =+Milestones!F10 -> A | AH35: =+Milestones!G10 -> 92
AA36: =+Milestones!A11 -> 8 | AB36: =+Milestones!B11 -> Complete Road Works | AD36: =+Milestones!C11 -> 46287 | AE36: =+Milestones!D11 -> 46373 | AF36: =+Milestones!E11 -> 46308 | AG36: =+Milestones!F11 | AH36: =+Milestones!G11 -> 65
AA37: =+Milestones!A12 -> 9 | AB37: =+Milestones!B12 -> Complete Electrical – Mv Distribution Network | AD37: =+Milestones!C12 -> 46513 | AE37: =+Milestones!D12 -> 46433 | AF37: =+Milestones!E12 -> 46308 | AG37: =+Milestones!F12 | AH37: =+Milestones!G12 -> 125
AA38: =+Milestones!A13 -> 10 | AB38: =+Milestones!B13 -> Completion of Potable Water Network | AD38: =+Milestones!C13 -> 46349 | AE38: =+Milestones!D13 -> 46406 | AF38: =+Milestones!E13 -> 46270 | AG38: =+Milestones!F13 -> A | AH38: =+Milestones!G13 -> 136
AA39: =+Milestones!A14 -> 11 | AB39: =+Milestones!B14 -> Complete all Works including Testing & Commissioning, Cleanup, Closeout Documentation and Ready for Initial Handover | AD39: =+Milestones!C14 -> 46530 | AE39: =+Milestones!D14 -> 46539 | AF39: =+Milestones!E14 -> 46393 | AG39: =+Milestones!F14 | AH39: =+Milestones!G14 -> 146
AA40: =+Milestones!A15 -> 12 | AB40: =+Milestones!B15 -> Complete Demobilization | AD40: =+Milestones!C15 -> 46530 | AE40: =+Milestones!D15 -> 46552 | AF40: =+Milestones!E15 -> 46406 | AG40: =+Milestones!F15 | AH40: =+Milestones!G15 -> 146
A56: Performance overview
A57: Submittals Status | L57: Quality | W57: Safety
A58: Shop Drawings | L58: Quality Reports | W58: Safety Statistics | AE58: Proactive Vs Reactive Actions Taken
A59: Item Per WBS | C59: Total | D59: Total Submitted Drawings | I59: Remaining | J59: Pending | K59: Total Submittals | L59: Quality Reports | N59: Issued | O59: Closed | P59: Pending | Q59: Avg. Closing (Days) | R59: Pending | W59: Category | X59: Item | Z59: This Week | AB59: This Month | AC59: Year to Date | AD59: Cumulative
D60: A | E60: B | F60: C | G60: D | H60: Processed | R60: 0-10 Days | S60: 11-20 Days | T60: 21-30 Days | U60: 31-60 Days | V60: > 60 Days
A61: ='Quality-Stat'!$A$13 -> General | C61: =IF('Quality-Stat'!D13="","",'Quality-Stat'!D13) -> 1 | D61: =IF('Quality-Stat'!E13="","",'Quality-Stat'!E13) -> 0 | E61: =IF('Quality-Stat'!F13="","",'Quality-Stat'!F13) -> 1 | F61: =IF('Quality-Stat'!G13="","",'Quality-Stat'!G13) -> 0 | G61: =IF('Quality-Stat'!H13="","",'Quality-Stat'!H13) -> 0 | H61: =IF('Quality-Stat'!I13="","",'Quality-Stat'!I13) -> 1 | I61: =IF('Quality-Stat'!J13="","",'Quality-Stat'!J13) -> 0 | J61: =IF('Quality-Stat'!K13="","",'Quality-Stat'!K13) -> 0 | K61: =IF('Quality-Stat'!L13="","",'Quality-Stat'!L13) -> 1 | W61: General | X61: ='HSE-Stat'!B4 -> Total Hours Worked | Z61: ='HSE-Stat'!D4 -> 11376 | AB61: ='HSE-Stat'!E4 -> 22752 | AC61: ='HSE-Stat'!F4 -> 491606 | AD61: ='HSE-Stat'!G4 -> 504766 | AG61: Proactive | AH61: =+SUM(AD72:AD76) -> 392
A62: ='Quality-Stat'!$A$14 -> Road Works | C62: =IF('Quality-Stat'!D14="","",'Quality-Stat'!D14) -> 264 | D62: =IF('Quality-Stat'!E14="","",'Quality-Stat'!E14) -> 50 | E62: =IF('Quality-Stat'!F14="","",'Quality-Stat'!F14) -> 210 | F62: =IF('Quality-Stat'!G14="","",'Quality-Stat'!G14) -> 0 | G62: =IF('Quality-Stat'!H14="","",'Quality-Stat'!H14) -> 0 | H62: =IF('Quality-Stat'!I14="","",'Quality-Stat'!I14) -> 264 | I62: =IF('Quality-Stat'!J14="","",'Quality-Stat'!J14) -> 0 | J62: =IF('Quality-Stat'!K14="","",'Quality-Stat'!K14) -> 4 | K62: =IF('Quality-Stat'!L14="","",'Quality-Stat'!L14) -> 264 | L62: Non Conformance (NCR) | N62: ='Quality-Stat'!D5 -> 43 | O62: ='Quality-Stat'!E5 -> 43 | P62: ='Quality-Stat'!F5 -> 0 | Q62: ='Quality-Stat'!G5 -> 0 | R62: ='Quality-Stat'!H5 -> 0 | S62: ='Quality-Stat'!I5 -> 0 | T62: ='Quality-Stat'!J5 -> 0 | U62: ='Quality-Stat'!K5 -> 0 | V62: ='Quality-Stat'!L5 -> 0 | X62: ='HSE-Stat'!B5 -> Safe Hours Worked | Z62: ='HSE-Stat'!D5 -> 11376 | AB62: ='HSE-Stat'!E5 -> 22752 | AC62: ='HSE-Stat'!F5 -> 491606 | AD62: ='HSE-Stat'!G5 -> 504766 | AG62: Reactive | AH62: =SUM(AD63:AD71) -> 0
A63: ='Quality-Stat'!$A$15 -> Civil | C63: =IF('Quality-Stat'!D15="","",'Quality-Stat'!D15) -> 46 | D63: =IF('Quality-Stat'!E15="","",'Quality-Stat'!E15) -> 7 | E63: =IF('Quality-Stat'!F15="","",'Quality-Stat'!F15) -> 39 | F63: =IF('Quality-Stat'!G15="","",'Quality-Stat'!G15) -> 0 | G63: =IF('Quality-Stat'!H15="","",'Quality-Stat'!H15) -> 0 | H63: =IF('Quality-Stat'!I15="","",'Quality-Stat'!I15) -> 46 | I63: =IF('Quality-Stat'!J15="","",'Quality-Stat'!J15) -> 0 | J63: =IF('Quality-Stat'!K15="","",'Quality-Stat'!K15) -> 0 | K63: =IF('Quality-Stat'!L15="","",'Quality-Stat'!L15) -> 46 | L63: Site Instruction (SIR/SOR) | N63: ='Quality-Stat'!D6 -> 10 | O63: ='Quality-Stat'!E6 -> 10 | P63: ='Quality-Stat'!F6 -> 0 | Q63: ='Quality-Stat'!G6 -> 0 | R63: ='Quality-Stat'!H6 -> 0 | S63: ='Quality-Stat'!I6 -> 0 | T63: ='Quality-Stat'!J6 -> 0 | U63: ='Quality-Stat'!K6 -> 0 | V63: ='Quality-Stat'!L6 -> 0 | W63: Reactive | X63: ='HSE-Stat'!B6 -> LTI | Z63: ='HSE-Stat'!D6 -> 0 | AB63: ='HSE-Stat'!E6 -> 0 | AC63: ='HSE-Stat'!F6 -> 0 | AD63: ='HSE-Stat'!G6 -> 0
A64: ='Quality-Stat'!$A$16 -> Mechanical | C64: =IF('Quality-Stat'!D16="","",'Quality-Stat'!D16) -> 9 | D64: =IF('Quality-Stat'!E16="","",'Quality-Stat'!E16) -> 0 | E64: =IF('Quality-Stat'!F16="","",'Quality-Stat'!F16) -> 9 | F64: =IF('Quality-Stat'!G16="","",'Quality-Stat'!G16) -> 0 | G64: =IF('Quality-Stat'!H16="","",'Quality-Stat'!H16) -> 0 | H64: =IF('Quality-Stat'!I16="","",'Quality-Stat'!I16) -> 9 | I64: =IF('Quality-Stat'!J16="","",'Quality-Stat'!J16) -> 0 | J64: =IF('Quality-Stat'!K16="","",'Quality-Stat'!K16) -> 0 | K64: =IF('Quality-Stat'!L16="","",'Quality-Stat'!L16) -> 9 | L64: Material Inspection (MRIR) | N64: ='Quality-Stat'!D7 -> 116 | O64: ='Quality-Stat'!E7 -> 116 | P64: ='Quality-Stat'!F7 -> 0 | Q64: ='Quality-Stat'!G7 -> 0 | R64: ='Quality-Stat'!H7 -> 0 | S64: ='Quality-Stat'!I7 -> 0 | T64: ='Quality-Stat'!J7 -> 0 | U64: ='Quality-Stat'!K7 -> 0 | V64: ='Quality-Stat'!L7 -> 0 | X64: ='HSE-Stat'!B7 -> MTC (Healed w/o Disability) | Z64: ='HSE-Stat'!D7 -> 0 | AB64: ='HSE-Stat'!E7 -> 0 | AC64: ='HSE-Stat'!F7 -> 0 | AD64: ='HSE-Stat'!G7 -> 0
A65: ='Quality-Stat'!$A$17 -> Electrical | C65: =IF('Quality-Stat'!D17="","",'Quality-Stat'!D17) -> 73 | D65: =IF('Quality-Stat'!E17="","",'Quality-Stat'!E17) -> 6 | E65: =IF('Quality-Stat'!F17="","",'Quality-Stat'!F17) -> 67 | F65: =IF('Quality-Stat'!G17="","",'Quality-Stat'!G17) -> 0 | G65: =IF('Quality-Stat'!H17="","",'Quality-Stat'!H17) -> 0 | H65: =IF('Quality-Stat'!I17="","",'Quality-Stat'!I17) -> 73 | I65: =IF('Quality-Stat'!J17="","",'Quality-Stat'!J17) -> 0 | J65: =IF('Quality-Stat'!K17="","",'Quality-Stat'!K17) -> 0 | K65: =IF('Quality-Stat'!L17="","",'Quality-Stat'!L17) -> 73 | L65: Field Inspection (FIR) | N65: ='Quality-Stat'!D8 -> 1571 | O65: ='Quality-Stat'!E8 -> 1551 | P65: ='Quality-Stat'!F8 -> 20 | Q65: ='Quality-Stat'!G8 -> 0 | R65: ='Quality-Stat'!H8 -> 0 | S65: ='Quality-Stat'!I8 -> 0 | T65: ='Quality-Stat'!J8 -> 0 | U65: ='Quality-Stat'!K8 -> 0 | V65: ='Quality-Stat'!L8 -> 0 | X65: ='HSE-Stat'!B8 -> MTC (Healed w/ Disability) | Z65: ='HSE-Stat'!D8 -> 0 | AB65: ='HSE-Stat'!E8 -> 0 | AC65: ='HSE-Stat'!F8 -> 0 | AD65: ='HSE-Stat'!G8 -> 0
A66: TOTAL | C66: =SUM(C61:C65) -> 393 | D66: =SUM(D61:D65) -> 63 | E66: =SUM(E61:E65) -> 326 | F66: =SUM(F61:F65) -> 0 | G66: =SUM(G61:G65) -> 0 | H66: =SUM(H61:H65) -> 393 | I66: =SUM(I61:I65) -> 0 | J66: =SUM(J61:J65) -> 4 | K66: =SUM(K61:K65) -> 393 | L66: Key Submittals Approval Status | X66: ='HSE-Stat'!B9 -> Near Miss | Z66: ='HSE-Stat'!D9 -> 0 | AB66: ='HSE-Stat'!E9 -> 0 | AC66: ='HSE-Stat'!F9 -> 0 | AD66: ='HSE-Stat'!G9 -> 0
A67: Material Approval | L67: 1 Quality Plan Approval | O67: =+'General Information'!C27 -> 46039 | Q67: 6 Baseline Approval | U67: ='General Information'!C39 -> 46012 | X67: ='HSE-Stat'!B10 -> First Aid Cases | Z67: ='HSE-Stat'!D10 -> 0 | AB67: ='HSE-Stat'!E10 -> 0 | AC67: ='HSE-Stat'!F10 -> 0 | AD67: ='HSE-Stat'!G10 -> 0 | AE67: Total Hours Worked Vs Safe Hours Worked
A68: Item Per WBS | C68: Total | D68: Total Submitted Material | I68: Remaining to approve | J68: Pending | K68: Total Submittals | L68: 2 Quality Plan Last Up | O68: =+'General Information'!C28 -> 1 | Q68: 7 No of Approved Version of Schedule | U68: ='General Information'!C40 -> 1 | X68: ='HSE-Stat'!B11 -> Fatality | Z68: ='HSE-Stat'!D11 -> 0 | AB68: ='HSE-Stat'!E11 -> 0 | AC68: ='HSE-Stat'!F11 -> 0 | AD68: ='HSE-Stat'!G11 -> 0
D69: A | E69: B | F69: C | G69: D | H69: Processed | I69: with Designer | L69: 3 Safety Plan Approval | O69: =+'General Information'!C31 -> 46019 | Q69: 8 Last Approved Schedule | U69: ='General Information'!C41 -> 46012 | X69: ='HSE-Stat'!B12 -> Fire Incident Cases | Z69: ='HSE-Stat'!D12 -> 0 | AB69: ='HSE-Stat'!E12 -> 0 | AC69: ='HSE-Stat'!F12 -> 0 | AD69: ='HSE-Stat'!G12 -> 0
A70: ='Quality-Stat'!$A$31 -> General | C70: =IF('Quality-Stat'!D31="","",'Quality-Stat'!D31) -> 0 | D70: =IF('Quality-Stat'!E31="","",'Quality-Stat'!E31) -> 0 | E70: =IF('Quality-Stat'!F31="","",'Quality-Stat'!F31) -> 0 | F70: =IF('Quality-Stat'!G31="","",'Quality-Stat'!G31) -> 0 | G70: =IF('Quality-Stat'!H31="","",'Quality-Stat'!H31) -> 0 | H70: =IF('Quality-Stat'!I31="","",'Quality-Stat'!I31) -> 0 | I70: =IF('Quality-Stat'!J31="","",'Quality-Stat'!J31) -> 0 | J70: =IF('Quality-Stat'!K31="","",'Quality-Stat'!K31) -> 0 | K70: =IF('Quality-Stat'!L31="","",'Quality-Stat'!L31) -> 0 | L70: 4 Safety Plan Last Up | O70: =+'General Information'!C32 -> 1 | Q70: 9 BOQ Approval Date | U70: =+'General Information'!C44 -> 45985 | X70: ='HSE-Stat'!B13 -> Vehicle Incident | Z70: ='HSE-Stat'!D13 -> 0 | AB70: ='HSE-Stat'!E13 -> 0 | AC70: ='HSE-Stat'!F13 -> 0 | AD70: ='HSE-Stat'!G13 -> 0
A71: ='Quality-Stat'!$A$32 -> Road Works | C71: =IF('Quality-Stat'!D32="","",'Quality-Stat'!D32) -> 0 | D71: =IF('Quality-Stat'!E32="","",'Quality-Stat'!E32) -> 0 | E71: =IF('Quality-Stat'!F32="","",'Quality-Stat'!F32) -> 0 | F71: =IF('Quality-Stat'!G32="","",'Quality-Stat'!G32) -> 0 | G71: =IF('Quality-Stat'!H32="","",'Quality-Stat'!H32) -> 0 | H71: =IF('Quality-Stat'!I32="","",'Quality-Stat'!I32) -> 0 | I71: =IF('Quality-Stat'!J32="","",'Quality-Stat'!J32) -> 0 | J71: =IF('Quality-Stat'!K32="","",'Quality-Stat'!K32) -> 0 | K71: =IF('Quality-Stat'!L32="","",'Quality-Stat'!L32) -> 0 | L71: 5 Execution Plan Approval | O71: =+'General Information'!C48 -> 46034 | Q71: 10 No of Approved Version of BOQ | U71: ='General Information'!C45 -> 1 | X71: ='HSE-Stat'!B14 -> Property Damages | Z71: ='HSE-Stat'!D14 -> 0 | AB71: ='HSE-Stat'!E14 -> 0 | AC71: ='HSE-Stat'!F14 -> 0 | AD71: ='HSE-Stat'!G14 -> 0
A72: ='Quality-Stat'!$A$33 -> Civil | C72: =IF('Quality-Stat'!D33="","",'Quality-Stat'!D33) -> 54 | D72: =IF('Quality-Stat'!E33="","",'Quality-Stat'!E33) -> 54 | E72: =IF('Quality-Stat'!F33="","",'Quality-Stat'!F33) -> 0 | F72: =IF('Quality-Stat'!G33="","",'Quality-Stat'!G33) -> 0 | G72: =IF('Quality-Stat'!H33="","",'Quality-Stat'!H33) | H72: =IF('Quality-Stat'!I33="","",'Quality-Stat'!I33) -> 54 | I72: =IF('Quality-Stat'!J33="","",'Quality-Stat'!J33) -> 0 | J72: =IF('Quality-Stat'!K33="","",'Quality-Stat'!K33) -> 0 | K72: =IF('Quality-Stat'!L33="","",'Quality-Stat'!L33) -> 54 | L72: Invoices Summary | W72: Proactive | X72: ='HSE-Stat'!B15 -> Induction Training | Z72: ='HSE-Stat'!D15 -> 0 | AB72: ='HSE-Stat'!E15 -> 0 | AC72: ='HSE-Stat'!F15 -> 69 | AD72: ='HSE-Stat'!G15 -> 80
A73: ='Quality-Stat'!$A$34 -> Mechanical | C73: =IF('Quality-Stat'!D34="","",'Quality-Stat'!D34) -> 59 | D73: =IF('Quality-Stat'!E34="","",'Quality-Stat'!E34) -> 55 | E73: =IF('Quality-Stat'!F34="","",'Quality-Stat'!F34) -> 4 | F73: =IF('Quality-Stat'!G34="","",'Quality-Stat'!G34) -> 0 | G73: =IF('Quality-Stat'!H34="","",'Quality-Stat'!H34) -> 0 | H73: =IF('Quality-Stat'!I34="","",'Quality-Stat'!I34) -> 59 | I73: =IF('Quality-Stat'!J34="","",'Quality-Stat'!J34) -> 0 | J73: =IF('Quality-Stat'!K34="","",'Quality-Stat'!K34) -> 0 | K73: =IF('Quality-Stat'!L34="","",'Quality-Stat'!L34) -> 59 | L73: Total Submitted Invoices | N73: ='Invoice Log'!U3 -> 8 | O73: Submitted Invoices (SAR) | R73: ='Invoice Log'!Y3 -> 40499983 | T73: Contract Value (SR) | U73: =O4 -> 57304348 | X73: ='HSE-Stat'!B16 -> No.of Internal Training | Z73: ='HSE-Stat'!D16 -> 5 | AB73: ='HSE-Stat'!E16 -> 12 | AC73: ='HSE-Stat'!F16 -> 264 | AD73: ='HSE-Stat'!G16 -> 269
A74: ='Quality-Stat'!$A$35 -> Electrical | C74: =IF('Quality-Stat'!D35="","",'Quality-Stat'!D35) -> 33 | D74: =IF('Quality-Stat'!E35="","",'Quality-Stat'!E35) -> 0 | E74: =IF('Quality-Stat'!F35="","",'Quality-Stat'!F35) -> 33 | F74: =IF('Quality-Stat'!G35="","",'Quality-Stat'!G35) -> 0 | G74: =IF('Quality-Stat'!H35="","",'Quality-Stat'!H35) -> 0 | H74: =IF('Quality-Stat'!I35="","",'Quality-Stat'!I35) -> 33 | I74: =IF('Quality-Stat'!J35="","",'Quality-Stat'!J35) -> 0 | J74: =IF('Quality-Stat'!K35="","",'Quality-Stat'!K35) -> 0 | K74: =IF('Quality-Stat'!L35="","",'Quality-Stat'!L35) -> 33 | L74: PM Approved Invoices | N74: ='Invoice Log'!U5 -> 7 | O74: PM Approved Invoices (SAR) | R74: ='Invoice Log'!Y5 -> 33617268 | T74: Planned Value (SR) | U74: =H28 -> 34293976 | X74: ='HSE-Stat'!B17 -> No.of Internal Audit | Z74: ='HSE-Stat'!D17 -> 0 | AB74: ='HSE-Stat'!E17 -> 0 | AC74: ='HSE-Stat'!F17 -> 0 | AD74: ='HSE-Stat'!G17 -> 0
A75: TOTAL | C75: =SUM(C70:C74) -> 146 | D75: =SUM(D70:D74) -> 109 | E75: =SUM(E70:E74) -> 37 | F75: =SUM(F70:F74) -> 0 | G75: =SUM(G70:G74) -> 0 | H75: =SUM(H70:H74) -> 146 | I75: =SUM(I70:I74) -> 0 | J75: =SUM(J70:J74) -> 0 | K75: =SUM(K70:K74) -> 146 | L75: No of Paid Invoices | N75: ='Invoice Log'!U6 -> 3 | O75: Paid Invoices (SAR) | R75: ='Invoice Log'!Y6 -> 27469389 | T75: Earned Value (SR) | U75: =I28 -> 53468556 | X75: ='HSE-Stat'!B18 -> No. of Toolbox Talks | Z75: ='HSE-Stat'!D18 -> 1 | AB75: ='HSE-Stat'!E18 -> 2 | AC75: ='HSE-Stat'!F18 -> 42 | AD75: ='HSE-Stat'!G18 -> 43
A76: Procurement Summary | L76: No of Pending Invoices | N76: =N74-N75 -> 4 | O76: Last Submitted Period | T76: Submitted (SAR) | U76: =R73 -> 40499983 | X76: ='HSE-Stat'!B19 -> Safety Awards/Incentives | Z76: ='HSE-Stat'!D19 -> 0 | AB76: ='HSE-Stat'!E19 -> 0 | AC76: ='HSE-Stat'!F19 -> 0 | AD76: ='HSE-Stat'!G19 -> 0
A77: Item Per WBS | C77: Total Materials | D77: Total Number of P.O. | E77: Actual P.O. To Date | F77: Remaining P.O | G77: Material on Site | H77: Remaining Materials | I77: Material Delivery Completion (Date) | L77: Advance Payment % | N77: ='Invoice Log'!M3 -> 0 | O77: Advance Payment (SAR) | R77: ='Invoice Log'!Q3 -> 0 | T77: PM Approved (SAR) | U77: =R74 -> 33617268 | W77: Latest Contract Change Order Log
D78: A | E78: B | F78: C | G78: D | H78: Processed | L78: Retention % | N78: ='Invoice Log'!M4 -> 0 | O78: Retention (SAR) | R78: ='Invoice Log'!Q4 -> 0 | T78: Total Paid (SAR) | U78: =R75 -> 27469389
A79: ='Quality-Stat'!$A$41 -> General | C79: =IF('Quality-Stat'!D41="","",'Quality-Stat'!D41) -> 0 | D79: =IF('Quality-Stat'!E41="","",'Quality-Stat'!E41) -> 0 | E79: =IF('Quality-Stat'!F41="","",'Quality-Stat'!F41) | F79: =IF('Quality-Stat'!G41="","",'Quality-Stat'!G41) -> 0 | G79: =IF('Quality-Stat'!H41="","",'Quality-Stat'!H41) -> 0 | H79: =IF('Quality-Stat'!I41="","",'Quality-Stat'!I41) -> 0 | I79: ='Quality-Stat'!J41 -> 46081 | L79: Deduction / Penalties % | N79: ='Invoice Log'!M5 -> 0 | O79: Deduction / Penalties (SAR) | R79: ='Invoice Log'!M6 -> 0 | W79: CCO No. | X79: Date Added | Y79: Description of Change | AD79: Status | AE79: Cost | AF79: Sch Impact (Months) | AG79: Date Approved | AH79: Duration
A80: ='Quality-Stat'!$A$42 -> Road Works | C80: =IF('Quality-Stat'!D42="","",'Quality-Stat'!D42) -> 0 | D80: =IF('Quality-Stat'!E42="","",'Quality-Stat'!E42) -> 0 | E80: =IF('Quality-Stat'!F42="","",'Quality-Stat'!F42) | F80: =IF('Quality-Stat'!G42="","",'Quality-Stat'!G42) -> 0 | G80: =IF('Quality-Stat'!H42="","",'Quality-Stat'!H42) -> 0 | H80: =IF('Quality-Stat'!I42="","",'Quality-Stat'!I42) -> 0 | I80: ='Quality-Stat'!J42 -> 46081 | L80: Resources at Site
A81: ='Quality-Stat'!$A$43 -> Civil | C81: =IF('Quality-Stat'!D43="","",'Quality-Stat'!D43) -> 0 | D81: =IF('Quality-Stat'!E43="","",'Quality-Stat'!E43) -> 0 | E81: =IF('Quality-Stat'!F43="","",'Quality-Stat'!F43) -> 0 | F81: =IF('Quality-Stat'!G43="","",'Quality-Stat'!G43) -> 0 | G81: =IF('Quality-Stat'!H43="","",'Quality-Stat'!H43) -> 0 | H81: =IF('Quality-Stat'!I43="","",'Quality-Stat'!I43) -> 0 | I81: ='Quality-Stat'!J43 -> 46081 | L81: Head Count - Non Manual | P81: Head Count - Manual | T81: Total Head Count | W81: =CCO!A3 -> 0 | X81: =CCO!B3 -> 0 | Y81: =CCO!C3 -> 0 | AD81: =CCO!D3 -> 0 | AE81: =CCO!E3 -> 0 | AF81: =CCO!F3 -> 0 | AG81: =CCO!G3 -> 0 | AH81: =CCO!H3 -> 0
A82: ='Quality-Stat'!$A$44 -> Mechanical | C82: =IF('Quality-Stat'!D44="","",'Quality-Stat'!D44) -> 18 | D82: =IF('Quality-Stat'!E44="","",'Quality-Stat'!E44) -> 18 | E82: =IF('Quality-Stat'!F44="","",'Quality-Stat'!F44) -> 18 | F82: =IF('Quality-Stat'!G44="","",'Quality-Stat'!G44) -> 0 | G82: =IF('Quality-Stat'!H44="","",'Quality-Stat'!H44) -> 15 | H82: =IF('Quality-Stat'!I44="","",'Quality-Stat'!I44) -> 3 | I82: ='Quality-Stat'!J44 -> 46280 | L82: Planned | M82: Actual | N82: Next Month Forecast | O82: Saudi Staff | P82: Planned | Q82: Actual | R82: Next Month Forecast | S82: Saudi Staff | T82: Total Plan | U82: Total Actual | V82: Variance
A83: ='Quality-Stat'!$A$45 -> Electrical | C83: =IF('Quality-Stat'!D45="","",'Quality-Stat'!D45) -> 16 | D83: =IF('Quality-Stat'!E45="","",'Quality-Stat'!E45) -> 16 | E83: =IF('Quality-Stat'!F45="","",'Quality-Stat'!F45) -> 16 | F83: =IF('Quality-Stat'!G45="","",'Quality-Stat'!G45) -> 0 | G83: =IF('Quality-Stat'!H45="","",'Quality-Stat'!H45) -> 12 | H83: =IF('Quality-Stat'!I45="","",'Quality-Stat'!I45) -> 4 | I83: ='Quality-Stat'!J45 -> 46280 | L83: =Manpower!A20 -> 12 | M83: =Manpower!B20 -> 49 | N83: =Manpower!F20 -> 12 | O83: =Manpower!H20 -> 0 | P83: =M93 -> 61 | Q83: =N93 -> 181 | R83: =Manpower!F24 -> 47 | S83: =Manpower!H24 -> 0 | T83: =L83+P83 -> 73 | U83: =M83+Q83 -> 230 | V83: =+U83-T83 -> 157 | W83: =CCO!A4 | X83: =CCO!B4 | Y83: =CCO!C4 | AD83: =IF(CCO!D4="","",CCO!D4) | AE83: =CCO!E4 | AF83: =CCO!F4 | AG83: =CCO!G4 | AH83: =CCO!H4
A84: TOTAL | C84: =IF('Quality-Stat'!D46="","",'Quality-Stat'!D46) -> 34 | D84: =IF('Quality-Stat'!E46="","",'Quality-Stat'!E46) -> 34 | E84: =IF('Quality-Stat'!F46="","",'Quality-Stat'!F46) -> 34 | F84: =IF('Quality-Stat'!G46="","",'Quality-Stat'!G46) -> 0 | G84: =IF('Quality-Stat'!H46="","",'Quality-Stat'!H46) -> 27 | H84: =IF('Quality-Stat'!I46="","",'Quality-Stat'!I46) -> 7 | I84: =MAX(I79:I83) -> 46280 | L84: Manpower Breakdown by Trade | S84: Major Equipment
A85: =Schedule!A1 -> Primavera P6 Schedule Status | L85: Key Trade | M85: Planned | N85: Actual | S85: Type | T85: Planned | U85: Actual | V85: Idle | W85: =CCO!A5 | X85: =CCO!B5 | Y85: =CCO!C5 | AD85: =IF(CCO!D5="","",CCO!D5) | AE85: =CCO!E5 | AF85: =CCO!F5 | AG85: =CCO!G5 | AH85: =CCO!H5
A86: =Schedule!A2 -> Project Activities Overview | L86: =+Manpower!N23 -> General Labor | M86: =Manpower!N24 -> 14 | N86: =Manpower!N25 -> 16 | S86: =+Manpower!$B$49 -> Excavator | T86: =+Manpower!B50 -> 2 | U86: =+Manpower!B51 -> 15 | V86: =+Manpower!B52 -> 0
A87: =Schedule!A3 -> Schedule Statistics | F87: =Schedule!F3 -> Active Schedule Activities | L87: =+Manpower!P23 -> Carpenter | M87: =Manpower!P24 -> 0 | N87: =Manpower!P25 -> 0 | S87: =+Manpower!$D$49 -> Loader | T87: =+Manpower!D50 -> 3 | U87: =+Manpower!D51 -> 8 | V87: =+Manpower!D52 -> 0 | W87: Major Quantity Trackers
A88: =Schedule!A4 -> Total Act. | B88: =Schedule!B4 -> Not Started | C88: =Schedule!C4 -> In Progress | D88: =Schedule!D4 -> Completed | E88: =Schedule!E4 -> % | F88: =Schedule!F4 -> Active | G88: =Schedule!G4 -> Ahead | H88: =Schedule!H4 -> On | ... K88: =Schedule!K4 -> 0 | L88: =+Manpower!R23 -> Plumber | M88: =+Manpower!R24 -> 0 | N88: =Manpower!R25 -> 0 | S88: =+Manpower!$F$49 -> Dozer | T88: =+Manpower!F50 -> 2 | U88: =+Manpower!F51 -> 7 | V88: =+Manpower!F52 -> 0 | W88: BOQ N0. | X88: Item Description | AC88: Total Qty | AD88: Measu Unit | AE88: Plan to Date | AF88: Act to Date | AG88: Remaining | AH88: Variance
A89: =Schedule!A5 -> 1218 | B89: =Schedule!B5 -> 24 | C89: =Schedule!C5 -> 21 | D89: =Schedule!D5 -> 1164 | E89: =Schedule!E5 -> 0.95566502 | F89: =Schedule!F5 -> 21 | G89: =Schedule!G5 -> 21 | H89: =Schedule!H5 -> 0 | ... J89: =Schedule!J5 -> 21 | L89: =+Manpower!T23 -> Operator | M89: =Manpower!T24 -> 42 | N89: =Manpower!T25 -> 99 | S89: =+Manpower!$H$49 -> Dump Truck | T89: =+Manpower!H50 -> 20 | U89: =+Manpower!H51 -> 40 | V89: =+Manpower!H52 -> 0 | W89: ='Major Quantities'!A2 -> B1.31 22 00.03 | X89: ='Major Quantities'!B2 -> Road backfilling | AC89: ='Major Quantities'!C2 -> 329706.66 | AD89: ='Major Quantities'!D2 -> m³ | AE89: ='Major Quantities'!E2 -> 329706.66 | AF89: ='Major Quantities'!F2 -> 329706.66 | AG89: ='Major Quantities'!G2 -> 0 | AH89: ='Major Quantities'!H2 -> 0
A90: =Schedule!A6 -> Critical Path Activities | D90: =Schedule!D6 -> Free Float Management (Total) | H90: =Schedule!H6 -> Failed Start Activities | L90: =+Manpower!V23 -> Steel Fixer | M90: =+Manpower!V24 -> 0 | N90: =+Manpower!V25 -> 0 | S90: =+Manpower!$J$49 -> Crane | T90: =+Manpower!J50 -> 1 | U90: =+Manpower!J51 -> 1 | V90: =+Manpower!J52 -> 0 | W90: ='Major Quantities'!A3 -> B1.31 22 00.04 | X90: ='Major Quantities'!B3 -> Plots backfilling | AC90: ='Major Quantities'!C3 -> 718628.27 | AD90: ='Major Quantities'!D3 -> m³ | AE90: ='Major Quantities'!E3 -> 485631 | AF90: ='Major Quantities'!F3 -> 654314 | AG90: ='Major Quantities'!G3 -> 64314.27 | AH90: ='Major Quantities'!H3 -> 168683
D91: =Schedule!D7 -> Greater Than 14 Days | F91: =Schedule!F7 -> Less Than 14 Days | L91: =+Manpower!X23 -> Mason | M91: =+Manpower!X24 -> 0 | N91: =+Manpower!X25 -> 0 | S91: =+Manpower!$L$49 -> Grader | T91: =+Manpower!L50 -> 2 | U91: =+Manpower!L51 -> 8 | V91: =+Manpower!L52 -> 0 | W91: ='Major Quantities'!A4 -> B1.31 22 00.05 | X91: ='Major Quantities'!B4 -> Subgrade | AC91: ='Major Quantities'!C4 -> 30811.51 | AD91: ='Major Quantities'!D4 -> m³ | AE91: ='Major Quantities'!E4 -> 30811.51 | AF91: ='Major Quantities'!F4 -> 30811.51 | AG91: ='Major Quantities'!G4 -> 0 | AH91: ='Major Quantities'!H4 -> 0
A92: =Schedule!A8 -> Last Week | B92: =Schedule!B8 -> This Week | C92: =Schedule!C8 -> Diff | D92: =Schedule!D8 -> Last Week | E92: =Schedule!E8 -> This Week | F92: =Schedule!F8 -> Last Week | G92: =Schedule!G8 -> This Week | H92: =Schedule!H8 -> Last Week | ... K92: =Schedule!K8 -> 0 | L92: =+Manpower!Z23 -> Others | M92: =+Manpower!Z24 -> 5 | N92: =+Manpower!Z25 -> 66 | S92: =+Manpower!$N$49 -> Other | T92: =+Manpower!N50 -> 0 | U92: =+Manpower!N51 -> 34 | V92: =+Manpower!N52 -> 0 | W92: ='Major Quantities'!A5 -> B1.32 11 23.01 | X92: ='Major Quantities'!B5 -> Aggregate base course | AC92: ='Major Quantities'!C5 -> 19162 | AD92: ='Major Quantities'!D5 -> m³ | AE92: ='Major Quantities'!E5 -> 19162 | AF92: ='Major Quantities'!F5 -> 19162 | AG92: ='Major Quantities'!G5 -> 0 | AH92: ='Major Quantities'!H5 -> 0
A93: =Schedule!A9 -> 0 | B93: =Schedule!B9 -> 0 | C93: =Schedule!C9 -> 0 | D93: =Schedule!D9 -> 4 | E93: =Schedule!E9 -> 4 | F93: =Schedule!F9 -> 8 | G93: =Schedule!G9 -> 8 | H93: =Schedule!H9 -> 4 | ... J93: =Schedule!J9 -> 2 | L93: Total | M93: =SUM(M86:M92) -> 61 | N93: =SUM(N86:N92) -> 181 | S93: Total | T93: =SUM(T86:T92) -> 30 | U93: =SUM(U86:U92) -> 113 | V93: =SUM(V86:V92) -> 0 | W93: ='Major Quantities'!A6 -> B1.32 11 26.01 | X93: ='Major Quantities'!B6 -> Bituminous base course (Grading I - Class A), including Prime Coat (MC1) and tack coat (RC2) (if any) | AC93: ='Major Quantities'!C6 -> 7129 | AD93: ='Major Quantities'!D6 -> m³ | AE93: ='Major Quantities'!E6 -> 5865 | AF93: ='Major Quantities'!F6 -> 7129 | AG93: ='Major Quantities'!G6 -> 0 | AH93: ='Major Quantities'!H6 -> 1264
A94: Weekly Prgoress Photos | Q94: Top Issues and Risks
A95: ='Weekly Photos'!B23 -> MV Cable Work at Existing Zone | F95: ='Weekly Photos'!L23 -> Installation of AC in Lift Station | L95: ='Weekly Photos'!B4 -> Land Backfilling | Q95: Top 5 Issues
Q96: Issue No | R96: Date Identified | S96: Issue Description | W96: Responsible | X96: Action Taken | AA96: Mitigation | AF96: Current Status | AG96: Expected/Actual Closure | AH96: Duration Elapsed
Q97: ='Issue '!A5 -> 1 | R97: ='Issue '!V5 -> 45992 | S97: ='Issue '!O5 -> Reducing the scope of works along Road No. 6, including all utility networks located within this road | W97: =IF(+#REF!="","",+#REF!) -> #REF! | X97: ='Issue '!Y5 -> Issuing a new scope of work to include all ongoing activities covered under the contract | AF97: ='Issue '!W5 -> Closed | AG97: ='Issue '!X5 -> 46047 | AH97: =AG97-R97 -> 55
Q98: ='Issue '!A6 -> 2 | R98: ='Issue '!V6 -> 46019 | S98: ='Issue '!O6 -> Scope of Work for the Proposed Wadi Channel and Box Culvert The proposed scope of work does not include the installation of rock protection at either the upstream or downstream ends to safeguard the soil against erosion resulting from water flow. Furthermore, the revised alignment of the wadi channel does not incorporate any rock protection measures along the direction of the water flow | W98: =IF(+#REF!="","",+#REF!) -> #REF! | X98: ='Issue '!Y6 -> There is a need to issue a decision regarding the implementation of grouted riprap works along the wadi, as well as at the inlet and outlet of the culvert | AF98: ='Issue '!W6 -> Closed | AG98: ='Issue '!X6 -> 46047 | AH98: =AG98-R98 -> 28
Q99: ='Issue '!A7 -> 3 | R99: ='Issue '!V7 -> 46019 | S99: ='Issue '!O7 -> Cross‑Section of the Wadi Channel The wadi channel has a bottom width of 15 meters and a depth of 2 meters, while the top width reaches 24 meters. According to the flow direction, the proposed box culvert CU‑02, with dimensions (3 × 2 × 1.5), provides a total bottom width of only 6.7 meters. This indicates a significant discrepancy between the width of the wadi channel and the width of the proposed culvert | W99: =IF(+#REF!="","",+#REF!) -> #REF! | X99: ='Issue '!Y7 -> The IFC is followed as shown in the drawings | AF99: ='Issue '!W7 -> Closed | AG99: ='Issue '!X7 -> 46021 | AH99: =AG99-R99 -> 2
Q100: ='Issue '!A8 -> 4 | R100: ='Issue '!V8 -> 46019 | S100: ='Issue '!O8 -> In accordance with the scope of work for the existing underpasses—which includes the removal of portions of the side walls (upstream and downstream), the installation of retaining walls at the inlet and outlet, and the construction of a concrete slab at the opening of the existing road’s top slab—we would like to inform you of the following: It is anticipated that, in the future, water leakage may occur, along with the emission of unpleasant odors, in addition to the potential emergence of health-related issues as a result of these works | W100: =IF(+#REF!="","",+#REF!) -> #REF! | X100: ='Issue '!Y8 -> The complete removal of the existing underpass concrete elements, followed by backfilling with selected and properly compacted fill materials in accordance with the approved technical specifications, in preparation for re‑establishing the road level and connecting it to the surrounding network | AF100: ='Issue '!W8 -> Closed | AG100: ='Issue '!X8 -> 46047 | AH100: =AG100-R100 -> 28
Q101: ='Issue '!A9 -> 5 | R101: ='Issue '!V9 -> 46021 | S101: ='Issue '!O9 -> Install and maintain hard barriers around all deep openings, enforce strict no-leaning/no-entry rules, conduct regular toolbox talks, ensure continuous supervision, and implement confined space controls if entry is required. | W101: =IF(+#REF!="","",+#REF!) -> #REF! | X101: ='Issue '!Y9 -> Provided hard barrications around the excavations, permit is obtained and excavation safety training has been delivered. | AF101: ='Issue '!W9 -> Closed | AG101: ='Issue '!X9 -> 46113 | AH101: =AG101-R101 -> 92

Sheet FIR summary 
A1: Project Name | C1: =+'General Information'!C3:I3 -> LAND DEVELOPMENT OF JEDDAH OASIS | F1: Total FIR Amount | I1: =+Total -> 1103431.6 | J1: Cum Previous FIR | K1: Cum up To Date FRI
A2: Project ID | C2: =+'General Information'!C4:I4 -> JHD4-02-007 | E2: Project Budget | F2: 57304348 | J2: 42652526 | K2: ='FIR sum'!C49 -> 53231723
A3: Date Period | C3: =+F3-6 -> 46302 | E3: To | F3: =+'General Information'!L1 -> 46308
A5: BOQ Item # | B5: BOQ Description | C5: FIR # | D5: FIR DATE | E5: FIR Description | F5: Unit | G5: Unit Rate | H5: Current Pariod Quantity | I5: Total (SR)
A7: B4.33 14 13.02 | B7: Chamber at pipe 400 mm Dia, Depth 1.5 - 4.0 m | C7: JDH4-02-007-ENJ-TS9-1-CVL-FIR-1052 | D7: 46257 | E7: INSPECTION REQUEST FOR EXCAVATION & LEAN CONCRETE & REINFORCED CONCRETE BASE OF BUTTERFLY VALVE ROOM DIA 400 MM FOR IRRIGATION LINE -02 DIA 400 MM , ROAD (1) AT STATION (00+060) NUMBER (101) | G7: 56485.2 | H7: 0.2 | I7: 11297.04
A8: B4.33 14 13.02 | B8: Chamber at pipe 400 mm Dia, Depth 1.5 - 4.0 m | C8: JDH4-02-007-ENJ-TS9-1-CVL-FIR-1053 | D8: 46257 | E8: INSPECTION REQUEST FOR REINFORCED CONCRETE WALL OF BUTTERFLY VALVE ROOM DIA 400 MM FOR IRRIGATION LINE -02 DIA 400 MM , ROAD (1) AT STATION (00+060) NUMBER (101) | G8: 56485.2 | H8: 0.2 | I8: 11297.04
A9: B4.33 14 13.02 | B9: Chamber at pipe 400 mm Dia, Depth 1.5 - 4.0 m | C9: JDH4-02-007-ENJ-TS9-1-CVL-FIR-1054 | D9: 46166 | E9: INSPECTION REQUEST FOR REINFORCED CONCRETE SLAB OF BUTTERFLY VALVE ROOM DIA 400 MM FOR IRRIGATION LINE -02 DIA 400 MM , ROAD (1) AT STATION (00+060) NUMBER (101) | G9: 56485.2 | H9: 0.2 | I9: 11297.04
A10: B4.33 14 13.02 | B10: Chamber at pipe 400 mm Dia, Depth 1.5 - 4.0 m | C10: JDH4-02-007-ENJ-TS9-1-CVL-FIR-1055 | D10: 46166 | E10: INSPECTION REQUEST FOR Bitumin Insulation , BACKFILLING , Installation and finishing Cover Frames FOR BUTTERFLY VALVE ROOM DIA 400 MM FOR IRRIGATION LINE -02 DIA 400 MM , ROAD (1) AT STATION (00+060) NUMBER (101) | G10: 56485.2 | H10: 0.4 | I10: 22594.08
A11: B7.7.2 | B11: 2 Coats of Bituminous Paint | C11: JDH4-02-007-ENJ-TS9-1-CVL-FIR-1056 | D11: 46166 | E11: Inspection Request for Application of 2 Coats of Bituminous Paint for Remaining of pumping station control foundation , Under Ground fuel tank and oddor Inside Lift Station | G11: 28.2426 | H11: 97.78 | I11: 2761.5614
A12: B1.32 14 13.03 | B12: Precast Concrete curb, Type (K4) | C12: JDH4-02-007-ENJ-TS9-1-CVL-FIR-1057 | D12: 45893 | E12: INSPECTION REQUEST FOR CASTING ( Curbstone K4 ) AT (ROAD 5 LEFT) RIGHT & LEFT SIDE FROM STATION 0+00 TO 0+400 | G12: 56.49 | H12: 783.36 | I12: 44252.006
A13: B1.31 22 00.04 | B13: Plots backfilling | C13: JDH4-02-007-ENJ-TS9-1-CVL-FIR-1058 | D13: 59408 | E13: INSPECTION REQUEST FOR BACKFILING SELECTED MATERIAL FOR 30 CM OVER ROCK FILL AT PLOT 1 AS PER SHOP DRAWING | G13: 23.54 | H13: 8199.19 | I13: 193008.93
A14: B1.32 14 13.02 | B14: Precast Concrete curb, Type (K2) | C14: JDH4-02-007-ENJ-TS9-1-CVL-FIR-1059 | D14: 46261 | E14: INSPECTION REQUEST FOR CASTING ( Curbstone K2 ) AT ROAD 5 LEFT FROM STATION 0+00 TO 0+400 | G14: 56.4852 | H14: 12 | I14: 677.8224
A15: B1.32 14 13.02 | B15: Precast Concrete curb, Type (K2) | C15: JDH4-02-007-ENJ-TS9-1-CVL-FIR-1060 | D15: 46261 | E15: INSPECTION REQUEST FOR CASTINIG ( Curbstone K2 ) AT NTERSECTION BETWEEN ROAD 04R & 07N | G15: 56.4852 | H15: 12 | I15: 677.8224
A16: B1.32 14 13.13.01 | B16: Interlocking block pavers for sidewalk/footpath | C16: JDH4-02-007-ENJ-TS9-1-CVL-FIR-1061 | D16: 46261 | E16: INSPECTION REQUEST FOR PRECAST INTERLCOKING BLOCK PAVERS AT (ROAD 5 LEFT) RIGHT & LEFT SIDE FROM STATION 0+000 TO 0+400 | G16: 70.61 | H16: 885.13 | I16: 62499.029
A17: B1.31 22 00.03 | B17: Road backfilling | C17: JDH4-02-007-ENJ-TS9-1-CVL-FIR-1062 | D17: 46261 | E17: INSPECTION REQUEST FOR N.G.L FOR TENT ROAD FROM STATION 0+00 TO 0+241 | G17: 23.54 | H17: 0 | I17: 0
A18: B1.31 22 00.01 | B18: Road excavation | C18: JDH4-02-007-ENJ-TS9-1-CVL-FIR-1063 | D18: 46261 | E18: INSPECTION REQUEST FOR EXCAVATION AT ROAD 1 FROM STATION 0+030 TO 0+604 | G18: 26.36 | H18: 3699.99 | I18: 97531.736
... A27: B2.31 23 00.01 | B27: Excavation for Trench size 40cm wide and 80cm deep (for 1 cable) | C27: JDH4-02-007-ENJ-TS9-1-ELE-FIR-0063 | D27: 46260 | E27: Inspection Request for Medium Voltage Cable Trench Excavation Size 40cm wide and 80cm deep for ( 1 Cable ) At Road 03 & 01 & 04L & 05L & 07S & EXISTING ROAD | G27: 37.66 | H27: 803.2 | I27: 30248.512
A43: Total Pariod Amount | I43: 1103431.6
A104: MEC | B104: 140
A105: CIVIL | B105: 539
A106: TEL | B106: 8
A107: ELEC | B107: 6

Sheet FIR sum
A1: S.NO | B1: FIR Date | C1: FIR Amount | D1: FIR % | E1: FIR Cum % | H1: 57304348
A2: 1
A3: 2
A4: 3
A5: 4
A6: 5 | B6: 46014 | C6: 0 | D6: =C6/$H$1 -> 0 | E6: =D6 -> 0
A7: 6 | B7: 46021 | C7: 0 | D7: =C7/$H$1 -> 0 | E7: =D7+E6 -> 0
A8: 7 | B8: 46028 | C8: 1077571.9 | D8: =C8/$H$1 -> 0.018804365 | E8: =D8+E7 -> 0.018804365
A9: 8 | B9: 46035 | C9: 542607.01 | D9: =C9/$H$1 -> 0.0094688628 | E9: =D9+E8 -> 0.028273228
A10: 9 | B10: 46042 | C10: 582575.96 | D10: =C10/$H$1 -> 0.010166348 | E10: =D10+E9 -> 0.038439576
A11: 10 | B11: 46049 | C11: 637735.66 | D11: =C11/$H$1 -> 0.011128923 | E11: =D11+E10 -> 0.049568499
A12: 11 | B12: 46055 | C12: 645396.07 | D12: =C12/$H$1 -> 0.011262602 | E12: =D12+E11 -> 0.060831101
A13: 12 | B13: 46063 | C13: 1281198.6 | D13: =C13/$H$1 -> 0.022357791 | E13: =D13+E12 -> 0.083188892
A14: 13 | B14: 46070 | C14: 2381311.4 | D14: =C14/$H$1 -> 0.041555511 | E14: =D14+E13 -> 0.1247444
A15: 14 | B15: 46077 | C15: 1191399.1 | D15: =C15/$H$1 -> 0.020790728 | E15: =D15+E14 -> 0.14553513
A16: 15 | B16: 46084 | C16: 867347.91 | D16: =C16/$H$1 -> 0.015135813 | E16: =D16+E15 -> 0.16067094
A17: 16 | B17: 46091 | C17: 999995.21 | D17: =C17/$H$1 -> 0.017450599 | E17: =D17+E16 -> 0.17812154
A18: 17 | B18: 46098 | C18: 1218608.1 | D18: =C18/$H$1 -> 0.021265543 | E18: =D18+E17 -> 0.19938709
... A25: 24 | B25: 46147 | C25: 1322147.5 | D25: =C25/$H$1 -> 0.023072377 | E25: =D25+E24 -> 0.37000294
A26: 25 | B26: =B25+7 -> 46154 | C26: 980131.33 | D26: =C26/$H$1 -> 0.017103961 | E26: =D26+E25 -> 0.3871069
A27: 26 | B27: =B26+7 -> 46161 | C27: 1205942.3 | D27: =C27/$H$1 -> 0.021044517 | E27: =D27+E26 -> 0.40815142
A28: 27 | B28: =B27+7 -> 46168 | C28: 1449798.2 | D28: =C28/$H$1 -> 0.025299968 | E28: =D28+E27 -> 0.43345139
A29: 28 | B29: =B28+7 -> 46175 | C29: 738582.78 | D29: =C29/$H$1 -> 0.012888774 | E29: =D29+E28 -> 0.44634016
A30: 29 | B30: =B29+7 -> 46182 | C30: 1189112 | D30: =C30/$H$1 -> 0.020750816 | E30: =D30+E29 -> 0.46709098
A31: 30 | B31: =B30+7 -> 46189 | C31: 1772610.9 | D31: =C31/$H$1 -> 0.03093327 | E31: =D31+E30 -> 0.49802425
A32: 31 | B32: =B31+7 -> 46196 | C32: 1439350.6 | D32: =C32/$H$1 -> 0.025117651 | E32: =D32+E31 -> 0.5231419
A33: 32 | B33: =B32+7 -> 46203 | C33: 1082355.1 | D33: =C33/$H$1 -> 0.018887835 | E33: =D33+E32 -> 0.54202973
A34: 33 | B34: =B33+7 -> 46210 | C34: 1805213.4 | D34: =C34/$H$1 -> 0.031502207 | E34: =D34+E33 -> 0.57353194
A35: 34 | B35: =B34+7 -> 46217 | C35: 1180368.6 | D35: =C35/$H$1 -> 0.020598239 | E35: =D35+E34 -> 0.59413018
A36: 35 | B36: =B35+7 -> 46224 | C36: 2095216.2 | D36: =C36/$H$1 -> 0.036562954 | E36: =D36+E35 -> 0.63069313
A37: 36 | B37: =B36+7 -> 46231 | C37: 1687000.7 | D37: =C37/$H$1 -> 0.029439315 | E37: =D37+E36 -> 0.66013245
... A48: 47 | B48: =B47+7 -> 46308 | C48: 1103431.6 | D48: =C48/$H$1 -> 0.019255636 | E48: =D48+E47 -> 0.92892992
B49: Total | C49: =SUM(C6:C48) -> 53231723

Sheet Progress
A1: Project Scope Statement | B1: Land development of jeddah oasis (The project includes construction of Roads works ; Storm water piping network with catch basins and manholes, Box Culvert ;Sewerage piping network with manhole ; Potable water piping network with fitting , valves and fire hydrant ;TSE Network ; Sewerage pump stations ;Channels ;36 KV medium voltage cable with Ring Main Unit ; Street Lighting with Unit Sub-stations , Ring Main Units and Low Voltage Cables ,concrete ducts at road crossing) | S1: ='General Information'!$K$1 -> Data Date | T1: ='General Information'!L1 -> 46308
A4: Earned Value Progress (SAR) | K4: Physical Progress (Effort)
A5: WBS | C5: BOQ Value (SAR) | D5: % Wt. | E5: Weekly (SAR) | H5: To Date (SAR) | K5: Budgeted | L5: % Wt. | M5: Weekly Physical Progress | O5: To Date Physical Progress
E6: Planned | F6: Earned | G6: Original Plan | H6: Planned | I6: Earned | K6: (Manhours) | M6: Planned | N6: Earned | O6: Planned | P6: Earned
A7: Preliminaries | C7: =SUBTOTAL(9,C8:C8) -> 0 | D7: =IF(ISBLANK(C7),"",C7/$C$41) -> 0 | E7: =SUBTOTAL(9,E8:E8) -> 0 | F7: =SUBTOTAL(9,F8:F8) -> 0 | G7: =SUBTOTAL(9,G8:G8) -> 0 | H7: =SUBTOTAL(9,H8:H8) -> 0 | I7: =SUBTOTAL(9,I8:I8) -> 0 | K7: =SUBTOTAL(9,K8:K8) -> 8492 | L7: =IF(ISBLANK(K7),"",K7/$K$41) -> 0.020904465 | M7: =SUBTOTAL(9,M8:M8) -> 0 | N7: =SUBTOTAL(9,N8:N8) -> 0 | O7: =SUBTOTAL(9,O8:O8) -> 8492 | P7: =SUBTOTAL(9,P8:P8) -> 8492
A8: Mobilization | C8: 0 | D8: =IF(ISBLANK(C8),"",C8/$C$41) -> 0 | E8: =+'Progress (2)'!I4 -> 0 | F8: =+'Progress (2)'!J4 -> 0 | G8: =+'Progress (2)'!K4 -> 0 | H8: =+'Progress (2)'!L4 -> 0 | I8: =+'Progress (2)'!M4 -> 0 | K8: 8492 | L8: =IF(ISBLANK(K8),"",K8/$K$41) -> 0.020904465 | M8: =+'Progress (2)'!O4 -> 0 | N8: =+'Progress (2)'!P4 -> 0 | O8: =+'Progress (2)'!Q4 -> 8492 | P8: =+'Progress (2)'!R4 -> 8492
A9: Engineering | C9: =SUBTOTAL(9,C10:C10) -> 1719130.4 | D9: =IF(ISBLANK(C9),"",C9/$C$41) -> 0.03 | E9: =SUBTOTAL(9,E10:E10) -> 0 | F9: =SUBTOTAL(9,F10:F10) -> 0 | G9: =SUBTOTAL(9,G10:G10) -> 1719130.4 | H9: =SUBTOTAL(9,H10:H10) -> 1690948 | I9: =SUBTOTAL(9,I10:I10) -> 1719130.4 | K9: =SUBTOTAL(9,K10:K10) -> 18263 | L9: =IF(ISBLANK(K9),"",K9/$K$41) -> 0.044957401 | M9: =SUBTOTAL(9,M10:M10) -> 108 | N9: =SUBTOTAL(9,N10:N10) -> 0 | O9: =SUBTOTAL(9,O10:O10) -> 18189 | P9: =SUBTOTAL(9,P10:P10) -> 18270
A10: Engineering | C10: 1719130.4 | D10: =IF(ISBLANK(C10),"",C10/$C$41) -> 0.03 | E10: =+'Progress (2)'!I5 -> 0 | F10: =+'Progress (2)'!J5 -> 0 | G10: =+'Progress (2)'!K5 -> 1719130.4 | H10: =+'Progress (2)'!L5 -> 1690948 | I10: =+'Progress (2)'!M5 -> 1719130.4 | K10: 18263 | L10: =IF(ISBLANK(K10),"",K10/$K$41) -> 0.044957401 | M10: =+'Progress (2)'!O5 -> 108 | N10: =+'Progress (2)'!P5 -> 0 | O10: =+'Progress (2)'!Q5 -> 18189 | P10: =+'Progress (2)'!R5 -> 18270
A11: Procuments | C11: =SUBTOTAL(9,C12:C12) -> 11460870 | D11: =IF(ISBLANK(C11),"",C11/$C$41) -> 0.2 | E11: =SUBTOTAL(9,E12:E12) -> 393541.03 | F11: =SUBTOTAL(9,F12:F12) -> 0 | G11: =SUBTOTAL(9,G12:G12) -> 10712587 | H11: =SUBTOTAL(9,H12:H12) -> 9731079.8 | I11: =SUBTOTAL(9,I12:I12) -> 11460870 | K11: =SUBTOTAL(9,K12:K12) -> 82180 | L11: =IF(ISBLANK(K11),"",K11/$K$41) -> 0.20229969 | M11: =SUBTOTAL(9,M12:M12) -> 1086 | N11: =SUBTOTAL(9,N12:N12) -> 0 | O11: =SUBTOTAL(9,O12:O12) -> 79551 | P11: =SUBTOTAL(9,P12:P12) -> 83973
A12: Procuments | C12: 11460870 | D12: =IF(ISBLANK(C12),"",C12/$C$41) -> 0.2 | E12: =+'Progress (2)'!I6 -> 393541.03 | F12: =+'Progress (2)'!J6 -> 0 | G12: =+'Progress (2)'!K6 -> 10712587 | H12: =+'Progress (2)'!L6 -> 9731079.8 | I12: =+'Progress (2)'!M6 -> 11460870 | K12: 82180 | L12: =IF(ISBLANK(K12),"",K12/$K$41) -> 0.20229969 | M12: =+'Progress (2)'!O6 -> 1086 | N12: =+'Progress (2)'!P6 -> 0 | O12: =+'Progress (2)'!Q6 -> 79551 | P12: =+'Progress (2)'!R6 -> 83973
A13: ROAD WORKS | C13: =SUBTOTAL(9,C14:C14) -> 13221675 | D13: =IF(ISBLANK(C13),"",C13/$C$41) -> 0.23072726 | E13: =SUBTOTAL(9,E14:E14) -> 116746.48 | F13: =SUBTOTAL(9,F14:F14) -> 201466.73 | G13: =SUBTOTAL(9,G14:G14) -> 8086622.7 | H13: =SUBTOTAL(9,H14:H14) -> 7989416.3 | I13: =SUBTOTAL(9,I14:I14) -> 14417397 | K13: =SUBTOTAL(9,K14:K14) -> 53186 | L13: =IF(ISBLANK(K13),"",K13/$K$41) -> 0.13092615 | M13: =SUBTOTAL(9,M14:M14) -> 540 | N13: =SUBTOTAL(9,N14:N14) -> 1563 | O13: =SUBTOTAL(9,O14:O14) -> 39667 | P13: =SUBTOTAL(9,P14:P14) -> 56207
A14: ROAD WORKS | C14: 13221675 | D14: =IF(ISBLANK(C14),"",C14/$C$41) -> 0.23072726 | E14: =+'Progress (2)'!I7 -> 116746.48 | F14: =+'Progress (2)'!J7 -> 201466.73 | G14: =+'Progress (2)'!K7 -> 8086622.7 | H14: =+'Progress (2)'!L7 -> 7989416.3 | I14: =+'Progress (2)'!M7 -> 14417397 | K14: 53186 | L14: =IF(ISBLANK(K14),"",K14/$K$41) -> 0.13092615 | M14: =+'Progress (2)'!O7 -> 540 | N14: =+'Progress (2)'!P7 -> 1563 | O14: =+'Progress (2)'!Q7 -> 39667 | P14: =+'Progress (2)'!R7 -> 56207
A15: Electrical Works | C15: =SUBTOTAL(9,C16:C16) -> 3953631.6 | D15: =IF(ISBLANK(C15),"",C15/$C$41) -> 0.068993572 | E15: =SUBTOTAL(9,E16:E16) -> 90863.03 | F15: =SUBTOTAL(9,F16:F16) -> 113449.56 | G15: =SUBTOTAL(9,G16:G16) -> 2790664.9 | H15: =SUBTOTAL(9,H16:H16) -> 1529434.3 | I15: =SUBTOTAL(9,I16:I16) -> 4232139.5 | K15: =SUBTOTAL(9,K16:K16) -> 58660 | L15: =IF(ISBLANK(K15),"",K15/$K$41) -> 0.14440131 | M15: =SUBTOTAL(9,M16:M16) -> 1272 | N15: =SUBTOTAL(9,N16:N16) -> 1009 | O15: =SUBTOTAL(9,O16:O16) -> 22808 | P15: =SUBTOTAL(9,P16:P16) -> 49140
A16: Electrical Works | C16: 3953631.6 | D16: =IF(ISBLANK(C16),"",C16/$C$41) -> 0.068993572 | E16: =+'Progress (2)'!I8 -> 90863.03 | F16: =+'Progress (2)'!J8 -> 113449.56 | G16: =+'Progress (2)'!K8 -> 2790664.9 | H16: =+'Progress (2)'!L8 -> 1529434.3 | I16: =+'Progress (2)'!M8 -> 4232139.5 | K16: 58660 | L16: =IF(ISBLANK(K16),"",K16/$K$41) -> 0.14440131 | M16: =+'Progress (2)'!O8 -> 1272 | N16: =+'Progress (2)'!P8 -> 1009 | O16: =+'Progress (2)'!Q8 -> 22808 | P16: =+'Progress (2)'!R8 -> 49140
A17: Demolition Works | C17: =SUBTOTAL(9,C18:C18) -> 506619.53 | D17: =IF(ISBLANK(C17),"",C17/$C$41) -> 0.0088408567 | E17: =SUBTOTAL(9,E18:E18) -> 0 | F17: =SUBTOTAL(9,F18:F18) -> 0 | G17: =SUBTOTAL(9,G18:G18) -> 506619.53 | H17: =SUBTOTAL(9,H18:H18) -> 505616.54 | I17: =SUBTOTAL(9,I18:I18) -> 505616.54 | K17: =SUBTOTAL(9,K18:K18) -> 14710 | L17: =IF(ISBLANK(K17),"",K17/$K$41) -> 0.036211103 | M17: =SUBTOTAL(9,M18:M18) -> 0 | N17: =SUBTOTAL(9,N18:N18) -> 0 | O17: =SUBTOTAL(9,O18:O18) -> 16105 | P17: =SUBTOTAL(9,P18:P18) -> 16105
A18: Demolition Works | C18: 506619.53 | D18: =IF(ISBLANK(C18),"",C18/$C$41) -> 0.0088408567 | E18: =+'Progress (2)'!I9 -> 0 | F18: =+'Progress (2)'!J9 -> 0 | G18: =+'Progress (2)'!K9 -> 506619.53 | H18: =+'Progress (2)'!L9 -> 505616.54 | I18: =+'Progress (2)'!M9 -> 505616.54 | K18: 14710 | L18: =IF(ISBLANK(K18),"",K18/$K$41) -> 0.036211103 | M18: =+'Progress (2)'!O9 -> 0 | N18: =+'Progress (2)'!P9 -> 0 | O18: =+'Progress (2)'!Q9 -> 16105 | P18: =+'Progress (2)'!R9 -> 16105
A19: Storm Water Network | C19: =SUBTOTAL(9,C20:C20) -> 3336320.6 | D19: =IF(ISBLANK(C19),"",C19/$C$41) -> 0.058221073 | E19: =SUBTOTAL(9,E20:E20) -> 59901.47 | F19: =SUBTOTAL(9,F20:F20) -> 0 | G19: =SUBTOTAL(9,G20:G20) -> 3336320.6 | H19: =SUBTOTAL(9,H20:H20) -> 2238976.9 | I19: =SUBTOTAL(9,I20:I20) -> 2558110.5 | K19: =SUBTOTAL(9,K20:K20) -> 29100 | L19: =IF(ISBLANK(K19),"",K19/$K$41) -> 0.071634472 | M19: =SUBTOTAL(9,M20:M20) -> 270 | N19: =SUBTOTAL(9,N20:N20) -> 0 | O19: =SUBTOTAL(9,O20:O20) -> 26800 | P19: =SUBTOTAL(9,P20:P20) -> 29900
A20: Storm Water Network | C20: 3336320.6 | D20: =IF(ISBLANK(C20),"",C20/$C$41) -> 0.058221073 | E20: =+'Progress (2)'!I10 -> 59901.47 | F20: =+'Progress (2)'!J10 -> 0 | G20: =+'Progress (2)'!K10 -> 3336320.6 | H20: =+'Progress (2)'!L10 -> 2238976.9 | I20: =+'Progress (2)'!M10 -> 2558110.5 | K20: 29100 | L20: =IF(ISBLANK(K20),"",K20/$K$41) -> 0.071634472 | M20: =+'Progress (2)'!O10 -> 270 | N20: =+'Progress (2)'!P10 -> 0 | O20: =+'Progress (2)'!Q10 -> 26800 | P20: =+'Progress (2)'!R10 -> 29900
A21: Plots | C21: =SUBTOTAL(9,C22:C22) -> 7378530.4 | D21: =IF(ISBLANK(C21),"",C21/$C$41) -> 0.12876039 | E21: =SUBTOTAL(9,E22:E22) -> 0 | F21: =SUBTOTAL(9,F22:F22) -> 152056.15 | G21: =SUBTOTAL(9,G22:G22) -> 7378530.4 | H21: =SUBTOTAL(9,H22:H22) -> 4337407.5 | I21: =SUBTOTAL(9,I22:I22) -> 6820991.2 | K21: =SUBTOTAL(9,K22:K22) -> 12640 | L21: =IF(ISBLANK(K21),"",K21/$K$41) -> 0.031115455 | M21: =SUBTOTAL(9,M22:M22) -> 0 | N21: =SUBTOTAL(9,N22:N22) -> 215 | O21: =SUBTOTAL(9,O22:O22) -> 10430 | P21: =SUBTOTAL(9,P22:P22) -> 13856
A22: Plots | C22: 7378530.4 | D22: =IF(ISBLANK(C22),"",C22/$C$41) -> 0.12876039 | E22: =+'Progress (2)'!I11 -> 0 | F22: =+'Progress (2)'!J11 -> 152056.15 | G22: =+'Progress (2)'!K11 -> 7378530.4 | H22: =+'Progress (2)'!L11 -> 4337407.5 | I22: =+'Progress (2)'!M11 -> 6820991.2 | K22: 12640 | L22: =IF(ISBLANK(K22),"",K22/$K$41) -> 0.031115455 | M22: =+'Progress (2)'!O11 -> 0 | N22: =+'Progress (2)'!P11 -> 215 | O22: =+'Progress (2)'!Q11 -> 10430 | P22: =+'Progress (2)'!R11 -> 13856
A23: Sewer Water Network | C23: =SUBTOTAL(9,C24:C24) -> 2156250.5 | D23: =IF(ISBLANK(C23),"",C23/$C$41) -> 0.037628043 | E23: =SUBTOTAL(9,E24:E24) -> 0 | F23: =SUBTOTAL(9,F24:F24) -> 0 | G23: =SUBTOTAL(9,G24:G24) -> 2156250.5 | H23: =SUBTOTAL(9,H24:H24) -> 1505981 | I23: =SUBTOTAL(9,I24:I24) -> 1505981 | K23: =SUBTOTAL(9,K24:K24) -> 24496 | L23: =IF(ISBLANK(K23),"",K23/$K$41) -> 0.060300963 | M23: =SUBTOTAL(9,M24:M24) -> 0 | N23: =SUBTOTAL(9,N24:N24) -> 0 | O23: =SUBTOTAL(9,O24:O24) -> 20616 | P23: =SUBTOTAL(9,P24:P24) -> 20616
A24: Sewer Water Network | C24: 2156250.5 | D24: =IF(ISBLANK(C24),"",C24/$C$41) -> 0.037628043 | E24: =+'Progress (2)'!I12 -> 0 | F24: =+'Progress (2)'!J12 -> 0 | G24: =+'Progress (2)'!K12 -> 2156250.5 | H24: =+'Progress (2)'!L12 -> 1505981 | I24: =+'Progress (2)'!M12 -> 1505981 | K24: 24496 | L24: =IF(ISBLANK(K24),"",K24/$K$41) -> 0.060300963 | M24: =+'Progress (2)'!O12 -> 0 | N24: =+'Progress (2)'!P12 -> 0 | O24: =+'Progress (2)'!Q12 -> 20616 | P24: =+'Progress (2)'!R12 -> 20616
A25: TSE Network | C25: =SUBTOTAL(9,C26:C26) -> 1589264.4 | D25: =IF(ISBLANK(C25),"",C25/$C$41) -> 0.027733749 | E25: =SUBTOTAL(9,E26:E26) -> 34853.63 | F25: =SUBTOTAL(9,F26:F26) -> 0 | G25: =SUBTOTAL(9,G26:G26) -> 1433580.4 | H25: =SUBTOTAL(9,H26:H26) -> 1162894.8 | I25: =SUBTOTAL(9,I26:I26) -> 1342832 | K25: =SUBTOTAL(9,K26:K26) -> 39495 | L25: =IF(ISBLANK(K25),"",K25/$K$41) -> 0.097223487 | M25: =SUBTOTAL(9,M26:M26) -> 480 | N25: =SUBTOTAL(9,N26:N26) -> 0 | O25: =SUBTOTAL(9,O26:O26) -> 32200 | P25: =SUBTOTAL(9,P26:P26) -> 37150
A26: TSE Network | C26: 1589264.4 | D26: =IF(ISBLANK(C26),"",C26/$C$41) -> 0.027733749 | E26: =+'Progress (2)'!I13 -> 34853.63 | F26: =+'Progress (2)'!J13 -> 0 | G26: =+'Progress (2)'!K13 -> 1433580.4 | H26: =+'Progress (2)'!L13 -> 1162894.8 | I26: =+'Progress (2)'!M13 -> 1342832 | K26: 39495 | L26: =IF(ISBLANK(K26),"",K26/$K$41) -> 0.097223487 | M26: =+'Progress (2)'!O13 -> 480 | N26: =+'Progress (2)'!P13 -> 0 | O26: =+'Progress (2)'!Q13 -> 32200 | P26: =+'Progress (2)'!R13 -> 37150
A27: Potable Water Network | C27: =SUBTOTAL(9,C28:C28) -> 2200624.9 | D27: =IF(ISBLANK(C27),"",C27/$C$41) -> 0.038402407 | E27: =SUBTOTAL(9,E28:E28) -> 9817.23 | F27: =SUBTOTAL(9,F28:F28) -> 0 | G27: =SUBTOTAL(9,G28:G28) -> 2140576.5 | H27: =SUBTOTAL(9,H28:H28) -> 1775528.8 | I27: =SUBTOTAL(9,I28:I28) -> 2005333.6 | K27: =SUBTOTAL(9,K28:K28) -> 31247 | L27: =IF(ISBLANK(K27),"",K27/$K$41) -> 0.076919668 | M27: =SUBTOTAL(9,M28:M28) -> 958 | N27: =SUBTOTAL(9,N28:N28) -> 0 | O27: =SUBTOTAL(9,O28:O28) -> 22760 | P27: =SUBTOTAL(9,P28:P28) -> 27107
A28: Potable Water Network | C28: 2200624.9 | D28: =IF(ISBLANK(C28),"",C28/$C$41) -> 0.038402407 | E28: =+'Progress (2)'!I14 -> 9817.23 | F28: =+'Progress (2)'!J14 -> 0 | G28: =+'Progress (2)'!K14 -> 2140576.5 | H28: =+'Progress (2)'!L14 -> 1775528.8 | I28: =+'Progress (2)'!M14 -> 2005333.6 | K28: 31247 | L28: =IF(ISBLANK(K28),"",K28/$K$41) -> 0.076919668 | M28: =+'Progress (2)'!O14 -> 958 | N28: =+'Progress (2)'!P14 -> 0 | O28: =+'Progress (2)'!Q14 -> 22760 | P28: =+'Progress (2)'!R14 -> 27107
A29: Sewage Lift Station | C29: =SUBTOTAL(9,C30:C30) -> 3049343.4 | D29: =IF(ISBLANK(C29),"",C29/$C$41) -> 0.053213125 | E29: =SUBTOTAL(9,E30:E30) -> 1189.82 | F29: =SUBTOTAL(9,F30:F30) -> 628633.39 | G29: =SUBTOTAL(9,G30:G30) -> 0 | H29: =SUBTOTAL(9,H30:H30) -> 5992.14 | I29: =SUBTOTAL(9,I30:I30) -> 1845852.3 | K29: =SUBTOTAL(9,K30:K30) -> 15410 | L29: =IF(ISBLANK(K29),"",K29/$K$41) -> 0.037934269 | M29: =SUBTOTAL(9,M30:M30) -> 297 | N29: =SUBTOTAL(9,N30:N30) -> 1164 | O29: =SUBTOTAL(9,O30:O30) -> 1107 | P29: =SUBTOTAL(9,P30:P30) -> 13114
A30: Sewage Lift Station | C30: 3049343.4 | D30: =IF(ISBLANK(C30),"",C30/$C$41) -> 0.053213125 | E30: =+'Progress (2)'!I15 -> 1189.82 | F30: =+'Progress (2)'!J15 -> 628633.39 | G30: =+'Progress (2)'!K15 -> 0 | H30: =+'Progress (2)'!L15 -> 5992.14 | I30: =+'Progress (2)'!M15 -> 1845852.3 | K30: 15410 | L30: =IF(ISBLANK(K30),"",K30/$K$41) -> 0.037934269 | M30: =+'Progress (2)'!O15 -> 297 | N30: =+'Progress (2)'!P15 -> 1164 | O30: =+'Progress (2)'!Q15 -> 1107 | P30: =+'Progress (2)'!R15 -> 13114
A31: Box Culvert | C31: =SUBTOTAL(9,C32:C32) -> 499321.73 | D31: =IF(ISBLANK(C31),"",C31/$C$41) -> 0.0087135051 | E31: =SUBTOTAL(9,E32:E32) -> 0 | F31: =SUBTOTAL(9,F32:F32) -> 0 | G31: =SUBTOTAL(9,G32:G32) -> 499321.73 | H31: =SUBTOTAL(9,H32:H32) -> 499735.96 | I31: =SUBTOTAL(9,I32:I32) -> 499735.96 | K31: =SUBTOTAL(9,K32:K32) -> 2200 | L31: =IF(ISBLANK(K31),"",K31/$K$41) -> 0.0054156646 | M31: =SUBTOTAL(9,M32:M32) -> 0 | N31: =SUBTOTAL(9,N32:N32) -> 0 | O31: =SUBTOTAL(9,O32:O32) -> 2515 | P31: =SUBTOTAL(9,P32:P32) -> 2515
A32: Box Culvert | C32: 499321.73 | D32: =IF(ISBLANK(C32),"",C32/$C$41) -> 0.0087135051 | E32: =+'Progress (2)'!I16 -> 0 | F32: =+'Progress (2)'!J16 -> 0 | G32: =+'Progress (2)'!K16 -> 499321.73 | H32: =+'Progress (2)'!L16 -> 499735.96 | I32: =+'Progress (2)'!M16 -> 499735.96 | K32: 2200 | L32: =IF(ISBLANK(K32),"",K32/$K$41) -> 0.0054156646 | M32: =+'Progress (2)'!O16 -> 0 | N32: =+'Progress (2)'!P16 -> 0 | O32: =+'Progress (2)'!Q16 -> 2515 | P32: =+'Progress (2)'!R16 -> 2515
A33: Open Drain Channel | C33: =SUBTOTAL(9,C34:C34) -> 389804.75 | D33: =IF(ISBLANK(C33),"",C33/$C$41) -> 0.0068023591 | E33: =SUBTOTAL(9,E34:E34) -> 0 | F33: =SUBTOTAL(9,F34:F34) -> 0 | G33: =SUBTOTAL(9,G34:G34) -> 0 | H33: =SUBTOTAL(9,H34:H34) -> 389804.76 | I33: =SUBTOTAL(9,I34:I34) -> 389804.76 | K33: =SUBTOTAL(9,K34:K34) -> 5040 | L33: =IF(ISBLANK(K33),"",K33/$K$41) -> 0.012406795 | M33: =SUBTOTAL(9,M34:M34) -> 0 | N33: =SUBTOTAL(9,N34:N34) -> 0 | O33: =SUBTOTAL(9,O34:O34) -> 6458 | P33: =SUBTOTAL(9,P34:P34) -> 6458
A34: Open Drain Channel | C34: 389804.75 | D34: =IF(ISBLANK(C34),"",C34/$C$41) -> 0.0068023591 | E34: =+'Progress (2)'!I17 -> 0 | F34: =+'Progress (2)'!J17 -> 0 | G34: =+'Progress (2)'!K17 -> 0 | H34: =+'Progress (2)'!L17 -> 389804.76 | I34: =+'Progress (2)'!M17 -> 389804.76 | K34: 5040 | L34: =IF(ISBLANK(K34),"",K34/$K$41) -> 0.012406795 | M34: =+'Progress (2)'!O17 -> 0 | N34: =+'Progress (2)'!P17 -> 0 | O34: =+'Progress (2)'!Q17 -> 6458 | P34: =+'Progress (2)'!R17 -> 6458
A35: Under Pass | C35: =SUBTOTAL(9,C36:C36) -> 112526.05 | D35: =IF(ISBLANK(C35),"",C35/$C$41) -> 0.0019636564 | E35: =SUBTOTAL(9,E36:E36) -> 0 | F35: =SUBTOTAL(9,F36:F36) -> 0 | G35: =SUBTOTAL(9,G36:G36) -> 112526.05 | H35: =SUBTOTAL(9,H36:H36) -> 112526.05 | I35: =SUBTOTAL(9,I36:I36) -> 112526.05 | K35: =SUBTOTAL(9,K36:K36) -> 1400 | L35: =IF(ISBLANK(K35),"",K35/$K$41) -> 0.003446332 | M35: =SUBTOTAL(9,M36:M36) -> 0 | N35: =SUBTOTAL(9,N36:N36) -> 0 | O35: =SUBTOTAL(9,O36:O36) -> 1400 | P35: =SUBTOTAL(9,P36:P36) -> 1400
A36: Under Pass | C36: 112526.05 | D36: =IF(ISBLANK(C36),"",C36/$C$41) -> 0.0019636564 | E36: =+'Progress (2)'!I18 -> 0 | F36: =+'Progress (2)'!J18 -> 0 | G36: =+'Progress (2)'!K18 -> 112526.05 | H36: =+'Progress (2)'!L18 -> 112526.05 | I36: =+'Progress (2)'!M18 -> 112526.05 | K36: 1400 | L36: =IF(ISBLANK(K36),"",K36/$K$41) -> 0.003446332 | M36: =+'Progress (2)'!O18 -> 0 | N36: =+'Progress (2)'!P18 -> 0 | O36: =+'Progress (2)'!Q18 -> 1400 | P36: =+'Progress (2)'!R18 -> 1400
A37: Testing and Commissioning | C37: =SUBTOTAL(9,C38:C38) -> 5730434.8 | D37: =IF(ISBLANK(C37),"",C37/$C$41) -> 0.1 | E37: =SUBTOTAL(9,E38:E38) -> 0 | F37: =SUBTOTAL(9,F38:F38) -> 163726.7 | G37: =SUBTOTAL(9,G38:G38) -> 1637267.1 | H37: =SUBTOTAL(9,H38:H38) -> 818633.54 | I37: =SUBTOTAL(9,I38:I38) -> 4052236 | K37: =SUBTOTAL(9,K38:K38) -> 9710 | L37: =IF(ISBLANK(K37),"",K37/$K$41) -> 0.023902774 | M37: =SUBTOTAL(9,M38:M38) -> 0 | N37: =SUBTOTAL(9,N38:N38) -> 240 | O37: =SUBTOTAL(9,O38:O38) -> 1270 | P37: =SUBTOTAL(9,P38:P38) -> 6220
A38: Testing and Commissioning | C38: 5730434.8 | D38: =IF(ISBLANK(C38),"",C38/$C$41) -> 0.1 | E38: =+'Progress (2)'!I19 -> 0 | F38: =+'Progress (2)'!J19 -> 163726.7 | G38: =+'Progress (2)'!K19 -> 1637267.1 | H38: =+'Progress (2)'!L19 -> 818633.54 | I38: =+'Progress (2)'!M19 -> 4052236 | K38: 9710 | L38: =IF(ISBLANK(K38),"",K38/$K$41) -> 0.023902774 | M38: =+'Progress (2)'!O19 -> 0 | N38: =+'Progress (2)'!P19 -> 240 | O38: =+'Progress (2)'!Q19 -> 1270 | P38: =+'Progress (2)'!R19 -> 6220
D39: =IF(ISBLANK(C39),"",C39/$C$41) | E39: 0 | F39: 0 | G39: 0 | H39: 0 | I39: 0 | K39: 0 | L39: =IF(ISBLANK(K39),"",K39/$K$41) -> 0 | M39: 0 | N39: 0 | O39: 0 | P39: 0
D40: =IF(ISBLANK(C40),"",C40/$C$41) | E40: 0 | F40: 0 | G40: 0 | H40: 0 | I40: 0 | K40: 0 | L40: =IF(ISBLANK(K40),"",K40/$K$41) -> 0 | M40: 0 | N40: 0 | O40: 0 | P40: 0
B41: Total | C41: =+SUM(C9,C11,C13,C15,C17,C19,C21,C23,C25,C27,C29,C31,C33,C35,C37) -> 57304348 | D41: =+SUM(D9,D11,D13,D15,D17,D19,D21,D23,D25,D27,D29,D31,D33,D35,D37) -> 1 | E41: =+SUM(E7,E9,E11,E13,E15,E17,E19,E21,E23,E25,E27,E29,E31,E33,E35,E37) -> 706912.69 | F41: =+SUM(F7,F9,F11,F13,F15,F17,F19,F21,F23,F25,F27,F29,F31,F33,F35,F37) -> 1259332.5 | G41: =+SUM(G7,G9,G11,G13,G15,G17,G19,G21,G23,G25,G27,G29,G31,G33,G35,G37) -> 42509998 | H41: =+SUM(H7,H9,H11,H13,H15,H17,H19,H21,H23,H25,H27,H29,H31,H33,H35,H37) -> 34293976 | I41: =+SUM(I7,I9,I11,I13,I15,I17,I19,I21,I23,I25,I27,I29,I31,I33,I35,I37) -> 53468556 | J41: =+SUM(J9,J11,J13,J15,J17,J19,J21,J23,J25,J27,J29,J31,J33,J35,J37) -> 0 | K41: =+SUM(K9,K11,K13,K15,K17,K19,K21,K23,K25,K27,K29,K31,K33,K35,K37,K7) -> 406229 | L41: =+SUM(L7,L9,L11,L13,L15,L17,L19,L21,L23,L25,L27,L29,L31,L33,L35,L37) -> 1 | M41: =+SUM(M7,M9,M11,M13,M15,M17,M19,M21,M23,M25,M27,M29,M31,M33,M35,M37) -> 5011 | N41: =+SUM(N7,N9,N11,N13,N15,N17,N19,N21,N23,N25,N27,N29,N31,N33,N35,N37) -> 4191 | O41: =+SUM(O7,O9,O11,O13,O15,O17,O19,O21,O23,O25,O27,O29,O31,O33,O35,O37) -> 310368 | P41: =+SUM(P7,P9,P11,P13,P15,P17,P19,P21,P23,P25,P27,P29,P31,P33,P35,P37) -> 390523
E42: =E41/$C$41 -> 0.012336109 | F42: =F41/$C$41 -> 0.021976213 | G42: =G41/$C$41 -> 0.74182849 | H42: =H41/$C$41 -> 0.5984533 | I42: =I41/$C$41 -> 0.93306282 | M42: =M41/$K$41 -> 0.012335407 | N42: =N41/$K$41 -> 0.010316841 | O42: =O41/$K$41 -> 0.76402226 | P42: =P41/$K$41 -> 0.96133708
F47: 47712387

Sheet Progress (2)
A1: CM This Week | I1: This Week | K1: CM | O1: This Week | Q1: CM
A2: Activity ID | B2: Planned Value Cost | C2: Earned Value Cost | D2: Planned Value Labor Units | E2: Earned Value Labor Units | F2: Schedule % Complete | G2: Performance % Complete | H2: Activity ID | I2: Planned Value Cost | J2: Earned Value Cost | K2: CM Original Plan | L2: CM Planned | M2: CM Earned | O2: Planned Value Labor Units | P2: Earned Value Labor Units | Q2: CM Planned Value Labor Units | R2: CM Earned Value Labor Units
A3: Total | B3: 34293976 | C3: 53468556 | D3: 310367 | E3: 390522 | F3: 0.5985 | G3: 0.9331 | H3: Total | I3: =+B3-B23 -> 706912.69 | J3: =+C3-C23 -> 1259332.5 | K3: =B49 -> 42509998 | L3: =+B3 -> 34293976 | M3: =+C3 -> 53468556 | O3: =+D3-D23 -> 5010 | P3: =+E3-E23 -> 4191 | Q3: =+D3 -> 310367 | R3: =+E3 -> 390522
A4: Mobilization | B4: 0 | C4: 0 | D4: 8492 | E4: 8492 | F4: 0 | G4: 0 | H4: Mobilization | I4: =+B4-B24 -> 0 | J4: =+C4-C24 -> 0 | K4: =B50 -> 0 | L4: =+B4 -> 0 | M4: =+C4 -> 0 | O4: =+D4-D24 -> 0 | P4: =+E4-E24 -> 0 | Q4: =+D4 -> 8492 | R4: =+E4 -> 8492
A5: Engineering | B5: 1690948 | C5: 1719130.4 | D5: 18189 | E5: 18270 | F5: 0.9836 | G5: 1 | H5: Engineering | I5: =+B5-B25 -> 0 | J5: =+C5-C25 -> 0 | K5: =B51 -> 1719130.4 | L5: =+B5 -> 1690948 | M5: =+C5 -> 1719130.4 | O5: =+D5-D25 -> 108 | P5: =+E5-E25 -> 0 | Q5: =+D5 -> 18189 | R5: =+E5 -> 18270
A6: Procuments | B6: 9731079.8 | C6: 11460870 | D6: 79551 | E6: 83973 | F6: 0.8491 | G6: 1 | H6: Procuments | I6: =+B6-B26 -> 393541.03 | J6: =+C6-C26 -> 0 | K6: =B52 -> 10712587 | L6: =+B6 -> 9731079.8 | M6: =+C6 -> 11460870 | O6: =+D6-D26 -> 1086 | P6: =+E6-E26 -> 0 | Q6: =+D6 -> 79551 | R6: =+E6 -> 83973
A7: Road Works | B7: 7989416.3 | C7: 14417397 | D7: 39667 | E7: 56207 | F7: 0.5456 | G7: 0.9846 | H7: Road Works | I7: =+B7-B27 -> 116746.48 | J7: =+C7-C27 -> 201466.73 | K7: =B53 -> 8086622.7 | L7: =+B7 -> 7989416.3 | M7: =+C7 -> 14417397 | O7: =+D7-D27 -> 540 | P7: =+E7-E27 -> 1563 | Q7: =+D7 -> 39667 | R7: =+E7 -> 56207
A8: Electrical Works | B8: 1529434.3 | C8: 4232139.5 | D8: 22808 | E8: 49140 | F8: 0.3473 | G8: 0.961 | H8: Electrical Works | I8: =+B8-B28 -> 90863.03 | J8: =+C8-C28 -> 113449.56 | K8: =B54 -> 2790664.9 | L8: =+B8 -> 1529434.3 | M8: =+C8 -> 4232139.5 | O8: =+D8-D28 -> 1272 | P8: =+E8-E28 -> 1009 | Q8: =+D8 -> 22808 | R8: =+E8 -> 49140
A9: Demolition Works | B9: 505616.54 | C9: 505616.54 | D9: 16105 | E9: 16105 | F9: 1 | G9: 1 | H9: Demolition Works | I9: =+B9-B29 -> 0 | J9: =+C9-C29 -> 0 | K9: =B55 -> 506619.53 | L9: =+B9 -> 505616.54 | M9: =+C9 -> 505616.54 | O9: =+D9-D29 -> 0 | P9: =+E9-E29 -> 0 | Q9: =+D9 -> 16105 | R9: =+E9 -> 16105
A10: Storm Water Network | B10: 2238976.9 | C10: 2558110.5 | D10: 26800 | E10: 29900 | F10: 0.8752 | G10: 1 | H10: Storm Water Network | I10: =+B10-B30 -> 59901.47 | J10: =+C10-C30 -> 0 | K10: =B56 -> 3336320.6 | L10: =+B10 -> 2238976.9 | M10: =+C10 -> 2558110.5 | O10: =+D10-D30 -> 270 | P10: =+E10-E30 -> 0 | Q10: =+D10 -> 26800 | R10: =+E10 -> 29900
A11: Plots | B11: 4337407.5 | C11: 6820991.2 | D11: 10430 | E11: 13856 | F11: 0.5878 | G11: 0.9244 | H11: Plots | I11: =+B11-B31 -> 0 | J11: =+C11-C31 -> 152056.15 | K11: =B57 -> 7378530.4 | L11: =+B11 -> 4337407.5 | M11: =+C11 -> 6820991.2 | O11: =+D11-D31 -> 0 | P11: =+E11-E31 -> 215 | Q11: =+D11 -> 10430 | R11: =+E11 -> 13856
A12: Sewer Water Network | B12: 1505981 | C12: 1505981 | D12: 20616 | E12: 20616 | F12: 1 | G12: 1 | H12: Sewer Water Network | I12: =+B12-B32 -> 0 | J12: =+C12-C32 -> 0 | K12: =B58 -> 2156250.5 | L12: =+B12 -> 1505981 | M12: =+C12 -> 1505981 | O12: =+D12-D32 -> 0 | P12: =+E12-E32 -> 0 | Q12: =+D12 -> 20616 | R12: =+E12 -> 20616
A13: TSE Network | B13: 1162894.8 | C13: 1342832 | D13: 32200 | E13: 37150 | F13: 0.866 | G13: 1 | H13: TSE Network | I13: =+B13-B33 -> 34853.63 | J13: =+C13-C33 -> 0 | K13: =B59 -> 1433580.4 | L13: =+B13 -> 1162894.8 | M13: =+C13 -> 1342832 | O13: =+D13-D33 -> 480 | P13: =+E13-E33 -> 0 | Q13: =+D13 -> 32200 | R13: =+E13 -> 37150
A14: Potable Water Network | B14: 1775528.8 | C14: 2005333.6 | D14: 22760 | E14: 27107 | F14: 0.8854 | G14: 1 | H14: Potable Water Network | I14: =+B14-B34 -> 9817.23 | J14: =+C14-C34 -> 0 | K14: =B60 -> 2140576.5 | L14: =+B14 -> 1775528.8 | M14: =+C14 -> 2005333.6 | O14: =+D14-D34 -> 958 | P14: =+E14-E34 -> 0 | Q14: =+D14 -> 22760 | R14: =+E14 -> 27107
... A20: No Construction | B20: 0 | C20: 0 | D20: 0 | E20: 0 | F20: 0 | G20: 0 | H20: No Construction | I20: =+B20-B40 -> 0 | J20: =+C20-C40 -> 0 | K20: =B66 -> 0 | L20: =+B20 -> 0 | M20: =+C20 -> 0 | O20: =+D20-D40 -> 0 | P20: =+E20-E40 -> 0 | Q20: =+D20 -> 0 | R20: =+E20 -> 0
A21: CM Last Week
A22: Activity ID | B22: Planned Value Cost | C22: Earned Value Cost | D22: Planned Value Labor Units | E22: Earned Value Labor Units | F22: Schedule % Complete | G22: Performance % Complete
A23: Total | B23: 33587064 | C23: 52209224 | D23: 305357 | E23: 386331 | F23: 0.5861 | G23: 0.9111 | H23: 10 | I23: =+D3*$H$23 -> 3103670 | J23: =+E3*$H$23 -> 3905220
A24: Mobilization | B24: 0 | C24: 0 | D24: 8492 | E24: 8492 | F24: 0 | G24: 0 | I24: =+D4*$H$23 -> 84920 | J24: =+E4*$H$23 -> 84920
A25: Engineering | B25: 1690948 | C25: 1719130.4 | D25: 18081 | E25: 18270 | F25: 0.9836 | G25: 1 | I25: =+D5*$H$23 -> 181890 | J25: =+E5*$H$23 -> 182700
A26: Procuments | B26: 9337538.8 | C26: 11460870 | D26: 78465 | E26: 83973 | F26: 0.8147 | G26: 1 | I26: =+D6*$H$23 -> 795510 | J26: =+E6*$H$23 -> 839730
A27: Road Works | B27: 7872669.8 | C27: 14215930 | D27: 39127 | E27: 54644 | F27: 0.5377 | G27: 0.9709 | I27: =+D7*$H$23 -> 396670 | J27: =+E7*$H$23 -> 562070
A28: Electrical Works | B28: 1438571.3 | C28: 4118690 | D28: 21536 | E28: 48131 | F28: 0.3267 | G28: 0.9353 | I28: =+D8*$H$23 -> 228080 | J28: =+E8*$H$23 -> 491400
A29: Demolition Works | B29: 505616.54 | C29: 505616.54 | D29: 16105 | E29: 16105 | F29: 1 | G29: 1 | I29: =+D9*$H$23 -> 161050 | J29: =+E9*$H$23 -> 161050
A30: Storm Water Network | B30: 2179075.4 | C30: 2558110.5 | D30: 26530 | E30: 29900 | F30: 0.8518 | G30: 1 | I30: =+D10*$H$23 -> 268000 | J30: =+E10*$H$23 -> 299000
A31: Plots | B31: 4337407.5 | C31: 6668935 | D31: 10430 | E31: 13641 | F31: 0.5878 | G31: 0.9038 | I31: =+D11*$H$23 -> 104300 | J31: =+E11*$H$23 -> 138560
A32: Sewer Water Network | B32: 1505981 | C32: 1505981 | D32: 20616 | E32: 20616 | F32: 1 | G32: 1 | I32: =+D12*$H$23 -> 206160 | J32: =+E12*$H$23 -> 206160
A33: TSE Network | B33: 1128041.2 | C33: 1342832 | D33: 31720 | E33: 37150 | F33: 0.84 | G33: 1 | I33: =+D13*$H$23 -> 322000 | J33: =+E13*$H$23 -> 371500
A34: Potable Water Network | B34: 1765711.5 | C34: 2005333.6 | D34: 21802 | E34: 27107 | F34: 0.8805 | G34: 1 | I34: =+D14*$H$23 -> 227600 | J34: =+E14*$H$23 -> 271070
A35: Sewage Lift Station | B35: 4802.32 | C35: 1217218.9 | D35: 810 | E35: 11950 | F35: 0.0016 | G35: 0.3992 | I35: =+D15*$H$23 -> 11070 | J35: =+E15*$H$23 -> 131140
... A40: No Construction | B40: 0 | C40: 0 | D40: 0 | E40: 0 | F40: 0 | G40: 0 | I40: =+D20*$H$23 -> 0 | J40: =+E20*$H$23 -> 0
A48: Activity ID | B48: Planned Value Cost | C48: Earned Value Cost | D48: Planned Value Labor Units | E48: Earned Value Labor Units | F48: Schedule % Complete | G48: Performance % Complete
A49: Total | B49: 42509998 | C49: 8768117.7 | D49: 331189 | E49: 59696 | F49: 0.7418 | G49: 0.153
A50: Mobilization | B50: 0 | C50: 0 | D50: 8492 | E50: 8012 | F50: 0 | G50: 0
A51: Engineering | B51: 1719130.4 | C51: 1338667.1 | D51: 18263 | E51: 17627 | F51: 1 | G51: 0.7787
A52: Procuments | B52: 10712587 | C52: 1719130.4 | D52: 81194 | E52: 6008 | F52: 0.9347 | G52: 0.15
A53: Road Works | B53: 8086622.7 | C53: 1934930.4 | D53: 30729 | E53: 6392 | F53: 0.6116 | G53: 0.1463
A54: Electrical Works | B54: 2790664.9 | C54: 0 | D54: 41560 | E54: 0 | F54: 0.7058 | G54: 0
A55: Demolition Works | B55: 506619.53 | C55: 310742.83 | D55: 14710 | E55: 6324 | F55: 1 | G55: 0.6134
A56: Storm Water Network | B56: 3336320.6 | C56: 798295.39 | D56: 29100 | E56: 7333 | F56: 1 | G56: 0.2393
A57: Plots | B57: 7378530.4 | C57: 2171172.5 | D57: 12640 | E57: 3203 | F57: 1 | G57: 0.2943
A58: Sewer Water Network | B58: 2156250.5 | C58: 759.92 | D58: 24496 | E58: 54 | F58: 1 | G58: 0.0004
A59: TSE Network | B59: 1433580.4 | C59: 66472.69 | D59: 35575 | E59: 1766 | F59: 0.902 | G59: 0.0418
A60: Potable Water Network | B60: 2140576.5 | C60: 0 | D60: 28291 | E60: 0 | F60: 0.9727 | G60: 0
... A65: Testing and Commissioning | B65: 1637267.1 | C65: 0 | D65: 2540 | E65: 0 | F65: 0.2857 | G65: 0
A66: No Construction | C66: 0 | D66: 0 | E66: 0 | F66: 0 | G66: 0
B69: =SUM(B50:B66) -> 42509998
B70: =B49-B69 -> -0.0099999905

Sheet General Information
A1: Weekly Progress Report - Construction Projects | K1: Data Date | L1: 46308
A2: Contract General Information
A3: Project Name | C3: LAND DEVELOPMENT OF JEDDAH OASIS
A4: Project ID | C4: JHD4-02-007
A5: Contractor | C5: AL-ENJAZ TRADING AND CONTRACTING COMPANY
A6: Consultant | C6: SAUDI ARABIA CONSULTING ENGINEERING COMPANY "EGIS"
A7: Stage | C7: Construction
A8: Status | C8: Active
A9: Modon PM | C9: Mohammed Alshunaifi
A11: Key Dates
A12: Contract Award Date | C12: 45970 | N12: =+M13/N13 -> 0.59266055
A13: Contract Sign Date | C13: 45977 | M13: =+L1-C14 -> 323 | N13: =+O13-C14 -> 545 | O13: 46530
A14: Site Handover Date | C14: 45985 | M14: =+L1-C14 -> 323 | N14: =+O14-C14 -> 364 | O14: 46349 | P14: =+M14/N14 -> 0.88736264
A15: Original Completion | C15: 46530 | K15: =C15-C14 -> 545 | L15: =C15-L1 -> 222 | M15: =L1-C14 -> 323 | N15: =O14-C14 -> 364 | O15: =L1-C14 -> 323
A16: Contract Award Date (Hijri) | C16: =+C12 -> 45970 | L16: =L15/K15 -> 0.40733945 | M16: =M15/K15 -> 0.59266055 | O16: =O15/N15 -> 0.88736264
A17: Contract Sign Date (Hijri) | C17: =+C13 -> 45977
A18: Site Handover Date (Hijri) | C18: =+C14 -> 45985
A19: Original Completion (Hijri) | C19: =+C15 -> 46530
A20: Revised Completion Date | C20: =+C15 -> 46530
A21: Committed Completion Date | C21: =+C20 -> 46530
A22: Forecast Completion | C22: =Milestones!E15 -> 46406
A23: Variance | C23: =C20-C22 -> 124
A25: Key Project Submittals | C25: Submission Date | D25: Days taken to approve orginal plan from site handover date
A26: Quality Plan submission | C26: 45999 | D26: =C26-C14 -> 14
A27: Quality Plan approval | C27: 46039
A28: Quality Plan Last Update | C28: 1
A30: Safety Plan submission | C30: 46007 | D30: =C30-C14 -> 22
A31: Safety Plan approval | C31: 46019
A32: Safety Plan Last Update | C32: 1
A34: Risk Management Plan submission | C34: 46026 | D34: =C34-C14 -> 41
A35: Risk Management Plan approval | C35: 46027
A36: Risk Management Plan Last Update | C36: 1
A38: Baseline Schedule submission | C38: 46012 | D38: =C38-C14 -> 27
A39: Baseline Schedule approval | C39: 46012
A40: No of Schedule Versions | C40: 1
A41: Last Recovery Schedule Approval Date | C41: =C39 -> 46012
A43: BOQ submission | C43: 45985 | D43: =C43-C14 -> 0
A44: BOQ approval | C44: 45985
A45: No of Approved Version of BOQ | C45: 1
A47: Project Execution Plan submission | C47: 46026 | D47: =C47-C14 -> 41
A48: Execution Plan Approval | C48: 46034

Sheet Weekly Photos
B1: Date | C1: ='Weekly Progress Report'!AG1 -> 46308
B4: Land Backfilling | L4: Earth Work at Khaima Road
B23: MV Cable Work at Existing Zone | L23: Installation of AC in Lift Station

Sheet Quality
B2: QC OBSERVATIONS CHECKLIST
BB4: ='General Information'!C14 -> 45985
B6: Project No. | E6: ='General Information'!C4 -> JHD4-02-007 | K6: OBS No. | O6: =ROUNDDOWN(((X6-BB4)/7)+1,0) -> 47 | U6: Inspection Day: | X6: ='General Information'!L1 -> 46308
B8: Project | E8: ='General Information'!C3 -> LAND DEVELOPMENT OF JEDDAH OASIS | O8: Contractor: Consultant: | U8: ='General Information'!C5&" "&'General Information'!C6 -> AL-ENJAZ TRADING AND CONTRACTING COMPANY SAUDI ARABIA CONSULTING ENGINEERING COMPANY "EGIS"
B10: 4 | D10: Excellent | G10: Quality Management System is being practiced and applies to MODON System | Z10: 90 - 100 | AB10: QC Overall Score | AC10: =Q49 -> 0.85303793 | AN10: =SUM(Z10:Z13) -> 0 | AO10: 100 | AP10: 0.22883295
B11: 3 | D11: Good | G11: Evidence of compliance with plans and procedures. | Z11: 80 - 89 | AN11: =SUM(Y10:Y14) -> 0 | AO11: 89 | AP11: 0.20366133
B12: 2 | D12: Average | G12: Indication level of compliance with standards but there is room for improvement | Z12: 70 - 79 | AO12: 79 | AP12: 0.18077803
B13: 1 | D13: Improve | G13: Quality and Control is NOT being managed effectively. Needs Improvement | Z13: ≤ 69 | AO13: 69 | AP13: 0.15789474
B14: 0 | D14: N/A | G14: Item was not applicable or this item was not reviewed during the inspection. | Z14: Zero | AO14: 100 | AP14: 0.22883295
B16: No. | C16: Topic | K16: E (4) | L16: G (3) | M16: A (2) | N16: I (1) | O16: N/A (0) | Q16: No. | R16: Topic | Z16: E (4) | AA16: G (3) | AB16: A (2) | AC16: I (1) | AD16: N/A (0) | AO16: =SUM(AO10:AO15) -> 437
K17: 1 | L17: 0.89 | M17: 0.79 | N17: 0.69 | O17: 1 | Z17: 1 | AA17: 0.89 | AB17: 0.79 | AC17: 0.69 | AD17: 1 | AF17: =SUM(AF18:AG46)/COUNT(AF18:AG46) -> 0.85303793
B18: 1 | C18: Control of Access to Site/Office | L18: 1 | Q18: 30 | R18: QC of Excavation | AA18: 1 | AF18: =SUMPRODUCT($K$17:$O$17,K18:O18) -> 0.89 | AG18: =SUMPRODUCT($Z$17:$AD$17,Z18:AD18) -> 0.89 | AV18: Item Count | AW18: Score | AX18: Distributtion
B19: 2 | C19: Document Control Administration | L19: 1 | Q19: 31 | R19: QC of Roads/Round about | AC19: 1 | AF19: =SUMPRODUCT($K$17:$O$17,K19:O19) -> 0.89 | AG19: =SUMPRODUCT($Z$17:$AD$17,Z19:AD19) -> 0.69 | AX19: Overall | AY19: Relevant
B20: 3 | C20: Project Documents and Progress | L20: 1 | Q20: 32 | R20: QC of Interlock & Curbstone | AD20: 1 | AF20: 0 | AG20: =SUMPRODUCT($Z$17:$AD$17,Z20:AD20) -> 1 | AM20: 4 | AN20: =58 -> 58 | AO20: counts | AQ20: 4 | AR20: Excellent | AV20: =SUM(Z18:Z46,K18:K46) -> 4 | AW20: =AQ20*AV20 -> 16 | AX20: =AV20/$AV$25 -> 0.07020007 | AY20: =AV20/SUM($AV$20:$AV$23) -> 0.086994345
B21: 4 | C21: Contractor's Quality Plan/CM (Updated and Reviewed) | L21: 1 | Q21: 33 | R21: Layers/Backfilling Sampling | AA21: 0.5 | AF21: =SUMPRODUCT($K$17:$O$17,K21:O21) -> 0.89 | AG21: =SUMPRODUCT($Z$17:$AD$17,Z21:AD21) -> 0.445 | AM21: 3 | AN21: =58 -> 58 | AO21: counts | AQ21: 3 | AR21: Good | AV21: =SUM(L18:L46,AA18:AA46) -> 27.5 | AW21: =AQ21*AV21 -> 82.5 | AX21: =AV21/$AV$25 -> 0.48262548 | AY21: =AV21/SUM($AV$20:$AV$23) -> 0.59808612
B22: 5 | C22: MS Log and Paperwork | L22: 1 | Q22: 34 | R22: Pump Stations Units | AA22: 1 | AF22: =SUMPRODUCT($K$17:$O$17,K22:O22) -> 0.89 | AG22: =SUMPRODUCT($Z$17:$AD$17,Z22:AD22) -> 0.89 | AM22: 2 | AN22: =58 -> 58 | AO22: counts | AQ22: 2 | AR22: Average | AV22: =SUM(M18:M46,AB18:AB46) -> 9 | AW22: =AQ22*AV22 -> 18 | AX22: =AV22/$AV$25 -> 0.15795016 | AY22: =AV22/SUM($AV$20:$AV$23) -> 0.19573728 | BC22: NB: Insert 1, or 0 in the required cell only.
B23: 6 | C23: RFI, FIR, & MIR Procedure | L23: 1 | Q23: 35 | R23: Quality of Form Work | AB23: 1 | AF23: =SUMPRODUCT($K$17:$O$17,K23:O23) -> 0.89 | AG23: =SUMPRODUCT($Z$17:$AD$17,Z23:AD23) -> 0.79 | AM23: 1 | AN23: =58 -> 58 | AO23: counts | AQ23: 1 | AR23: Improve | AV23: =SUM(N18:N46,AC18:AC46) -> 5.48 | AW23: =AQ23*AV23 -> 5.48 | AX23: =AV23/$AV$25 -> 0.096174096 | AY23: =AV23/SUM($AV$20:$AV$23) -> 0.11918225
B24: 7 | C24: RFI, FIR, & MIR Inventory system | L24: 1 | Q24: 36 | R24: Design Change List | AD24: 0 | AF24: =SUMPRODUCT($K$17:$O$17,K24:O24) -> 0.89 | AG24: =SUMPRODUCT($Z$17:$AD$17,Z24:AD24) -> 0 | AM24: 0 | AN24: =58 -> 58 | AO24: counts | AQ24: 0 | AR24: N/A | AV24: =SUM(O18:O46,AD18:AD46) -> 11 | AW24: =AQ24*AV24 -> 0 | AX24: =AV24/$AV$25 -> 0.19305019 | AY24: -
B25: 8 | C25: NCRs Control & Procedure | L25: 1 | Q25: 37 | R25: Quality of Concrete Placing | AB25: 0 | AF25: =SUMPRODUCT($K$17:$O$17,K25:O25) -> 0.89 | AG25: =SUMPRODUCT($Z$17:$AD$17,Z25:AD25) -> 0 | AR25: Total | AV25: =SUM(AV20:AV24) -> 56.98 | AW25: =SUM(AW20:AW24) -> 121.98 | AX25: =SUM(AX20:AX24) -> 1 | AY25: =SUM(AY20:AY24) -> 1
B26: 9 | C26: NCR Log | L26: 1 | Q26: 38 | R26: Concrete Surface Finishing | AB26: 1 | AF26: =SUMPRODUCT($K$17:$O$17,K26:O26) -> 0.89 | AG26: =SUMPRODUCT($Z$17:$AD$17,Z26:AD26) -> 0.79
B27: 10 | C27: MODON Standard* | L27: 1 | Q27: 39 | R27: Pedestals/Columns/Beams Alignment | AD27: 1 | AF27: =SUMPRODUCT($K$17:$O$17,K27:O27) -> 0.89 | AG27: =SUMPRODUCT($Z$17:$AD$17,Z27:AD27) -> 1 | AV27: Maz Score Available: | AW27: =SUM(AV20:AV23)*AQ20 -> 183.92 | AX27: <- Excludes N/A items
B28: 11 | C28: Project Risk Plan/Management* | M28: 1 | Q28: 40 | R28: Siporex Lifting & Unloading | AD28: 1 | AF28: =SUMPRODUCT($K$17:$O$17,K28:O28) -> 0.79 | AG28: =SUMPRODUCT($Z$17:$AD$17,Z28:AD28) -> 1
B29: 12 | C29: Monthly Quality Reports* | L29: 1 | Q29: 41 | R29: Siporex Quality Pre-installation | AD29: 1 | AF29: =SUMPRODUCT($K$17:$O$17,K29:O29) -> 0.89 | AG29: =SUMPRODUCT($Z$17:$AD$17,Z29:AD29) -> 1
B30: 13 | C30: ITP | L30: 1 | Q30: 42 | R30: Siporex Finishing Quality | AD30: 1 | AF30: =SUMPRODUCT($K$17:$O$17,K30:O30) -> 0.89 | AG30: =SUMPRODUCT($Z$17:$AD$17,Z30:AD30) -> 1 | AR30: Total Score | AW30: Percentage (%)
B31: 14 | C31: MODON Weekly Report | L31: 1 | Q31: 43 | R31: Roads / Parking Markings | AB31: 1 | AC31: 1 | AF31: =SUMPRODUCT($K$17:$O$17,K31:O31) -> 0.89 | AG31: =SUMPRODUCT($Z$17:$AD$17,Z31:AD31) -> 1.48 | AN31: =MAX(AN20:AN24) -> 58 | AR31: =AW25 -> 121.98 | AW31: =SUM(100/AR33*AR31) -> 66.322314 | AY31: %
B32: 15 | C32: Design Change Official Paperwork* | N32: 1 | Q32: 44 | R32: QC of Finishing Outdoors | AB32: 1 | AC32: 0.48 | AF32: =SUMPRODUCT($K$17:$O$17,K32:O32) -> 0.69 | AG32: =SUMPRODUCT($Z$17:$AD$17,Z32:AD32) -> 1.1212 | AR32: Max Score Available | BP32: 31
B33: 16 | C33: Design Change was Applied* | O33: 1 | Q33: 45 | R33: Quality of Finishing Indoors | AB33: 1 | AF33: =SUMPRODUCT($K$17:$O$17,K33:O33) -> 1 | AG33: =SUMPRODUCT($Z$17:$AD$17,Z33:AD33) -> 0.79 | AR33: =AW27 -> 183.92 | BP33: 32
B34: 17 | C34: Material List | K34: 1 | Q34: 46 | R34: Stairs Quality | AD34: 1 | AF34: =SUMPRODUCT($K$17:$O$17,K34:O34) -> 1 | AG34: =SUMPRODUCT($Z$17:$AD$17,Z34:AD34) -> 1 | BP34: 33
B35: 18 | C35: Pending Material Status | L35: 1 | Q35: 47 | R35: Tanks Method Statement Work | AD35: 1 | AF35: =SUMPRODUCT($K$17:$O$17,K35:O35) -> 0.89 | AG35: =SUMPRODUCT($Z$17:$AD$17,Z35:AD35) -> 1 | BP35: 34
B36: 19 | C36: Lifting Plan* | N36: 1 | Q36: 48 | R36: Electric Rooms | AB36: 1 | AF36: =SUMPRODUCT($K$17:$O$17,K36:O36) -> 0.69 | AG36: =SUMPRODUCT($Z$17:$AD$17,Z36:AD36) -> 0.79 | BP36: 35
B37: 20 | C37: DWG Log | K37: 1 | Q37: 49 | R37: QC of MCC/ATS Plant Units | AD37: 1 | AF37: =SUMPRODUCT($K$17:$O$17,K37:O37) -> 1 | AG37: =SUMPRODUCT($Z$17:$AD$17,Z37:AD37) -> 1 | BP37: 36
B38: 21 | C38: Invoice Status | L38: 1 | Q38: 50 | R38: Qualified Subcontractor | Z38: 1 | AF38: =SUMPRODUCT($K$17:$O$17,K38:O38) -> 0.89 | AG38: =SUMPRODUCT($Z$17:$AD$17,Z38:AD38) -> 1 | BP38: 37
B39: 22 | C39: Site Handover Letter | O39: 1 | Q39: 51 | R39: Scaffold/Ladders/Slope/Bridge Compliance | AD39: 1 | AF39: =SUMPRODUCT($K$17:$O$17,K39:O39) -> 1 | AG39: =SUMPRODUCT($Z$17:$AD$17,Z39:AD39) -> 1 | BP39: 38
B40: 23 | C40: Material Testing Results & Certification | L40: 1 | Q40: 52 | R40: Protection Applied to Completed Work | AC40: 1 | AF40: =SUMPRODUCT($K$17:$O$17,K40:O40) -> 0.89 | AG40: =SUMPRODUCT($Z$17:$AD$17,Z40:AD40) -> 0.69
B41: 24 | C41: As Build Drawings Status* | L41: 1 | Q41: 53 | R41: Storage Management in/out Control | AA41: 1 | AF41: =SUMPRODUCT($K$17:$O$17,K41:O41) -> 0.89 | AG41: =SUMPRODUCT($Z$17:$AD$17,Z41:AD41) -> 0.89
B42: 25 | C42: Calibrated Lab Tools & Equipment | L42: 1 | Q42: 54 | R42: Material Control | AA42: 1 | AF42: =SUMPRODUCT($K$17:$O$17,K42:O42) -> 0.89 | AG42: =SUMPRODUCT($Z$17:$AD$17,Z42:AD42) -> 0.89
B43: 26 | C43: Storage Inventory System | M43: 1 | Q43: 55 | R43: Manholes Storing and Quality | AA43: 1 | AF43: =SUMPRODUCT($K$17:$O$17,K43:O43) -> 0.79 | AG43: =SUMPRODUCT($Z$17:$AD$17,Z43:AD43) -> 0.89
B44: 27 | C44: Logistics Plan | L44: 1 | Q44: 56 | R44: Reinforced Steel Quality | AA44: 1 | AF44: =SUMPRODUCT($K$17:$O$17,K44:O44) -> 0.89 | AG44: =SUMPRODUCT($Z$17:$AD$17,Z44:AD44) -> 0.89
B45: 28 | C45: Project Progress Planview | L45: 1 | Q45: 57 | R45: Safety Overview | AA45: 1 | AF45: =SUMPRODUCT($K$17:$O$17,K45:O45) -> 0.89 | AG45: =SUMPRODUCT($Z$17:$AD$17,Z45:AD45) -> 0.89
B46: 29 | C46: Sufficient Number of QC Inspectors | M46: 1 | Q46: 58 | R46: Waste Management Control | Z46: 1 | AF46: =SUMPRODUCT($K$17:$O$17,K46:O46) -> 0.79 | AG46: =SUMPRODUCT($Z$17:$AD$17,Z46:AD46) -> 1
I48: Score
M49: *QC % | Q49: =AF17 -> 0.85303793
B51: Prepared by: | Q51: Issued to PM: | V51: Mohammed Alshunaifi
B53: *QC Observations refer only to the practices and documentation observed at time of inspection. The responsibility of the CM and Contractor is to ensure that aspects of Quality are suitably managed. *Scores are a reflection of the general site conditions based upon the findings at the time of the walk through *If Applicable

Sheet Quality-Stat
A1: Quality Reports
A2: Item | D2: Issued | E2: Closed | F2: Pending | G2: Avg. Closing (Days) | H2: Pending
H3: 0-10 Days | I3: 11-20 Days | J3: 21-30 Days | K3: 31-60 Days | L3: > 60 Days
A5: Non Conforomance Report (NCR) | D5: 43 | E5: 43 | F5: =D5-E5 -> 0 | G5: 0 | H5: 0 | I5: 0 | J5: 0 | K5: 0 | L5: 0
A6: Site Instruction (SIR/SOR) | D6: 10 | E6: 10 | F6: =+D6-E6 -> 0 | G6: 0 | H6: 0 | I6: 0 | J6: 0 | K6: 0 | L6: 0
A7: Material Inspection Report (MRIR) | D7: 116 | E7: 116 | F7: =+D7-E7 -> 0 | G7: 0 | H7: 0 | I7: 0 | J7: 0 | K7: 0 | L7: 0
A8: Field Inspection Report (FIR) | D8: 1571 | E8: 1551 | F8: =D8-E8 -> 20 | G8: 0 | H8: 0 | I8: 0 | J8: 0 | K8: 0 | L8: 0
A10: Shop Drawings
A11: Item Per WBS | D11: Total Planned | E11: Total Drawings Submitted | J11: Remaining Drawings | K11: Pending | L11: Total Submittals
E12: A | F12: B | G12: C | H12: D | I12: Processed | J12: with Designer | K12: Submittals With Consultant
A13: General | D13: 1 | E13: 0 | F13: 1 | G13: 0 | H13: 0 | I13: =E13+F13+G13+H13+K13 -> 1 | J13: =D13-I13 -> 0 | K13: 0 | L13: =E13+F13+G13+H13+K13+J13 -> 1 | M13: =+I13/D13 -> 1 | N13: =+L13/D13 -> 1 | R13: =+D13 -> 1 | S13: =+E13 -> 0 | T13: =+F13 -> 1 | U13: =+G13 -> 0 | V13: =+H13 -> 0 | W13: =+I13 -> 1 | X13: =+J1+3 -> 3 | Y13: =+K13 -> 0
A14: Road Works | D14: =I14 -> 264 | E14: 50 | F14: 210 | G14: 0 | H14: 0 | I14: =E14+F14+G14+H14+K14 -> 264 | J14: =D14-I14 -> 0 | K14: 4 | L14: =E14+F14+G14+H14+K14+J14 -> 264 | M14: =+I14/D14 -> 1 | N14: =+L14/D14 -> 1 | R14: =+D14+D15 -> 310 | S14: =+E14+E15 -> 57 | T14: =+F14+F15 -> 249 | U14: =+G14+G15 -> 0 | V14: =+H14+H15 -> 0 | W14: =+I14+I15 -> 310 | X14: =+J14+J15 -> 0 | Y14: =+K14+K15 -> 4
A15: Civil | D15: =I15 -> 46 | E15: 7 | F15: 39 | G15: 0 | H15: 0 | I15: =E15+F15+G15+H15+K15 -> 46 | J15: =D15-I15 -> 0 | K15: 0 | L15: =E15+F15+G15+H15+K15+J15 -> 46 | R15: =+D16 -> 9 | S15: =+E16 -> 0 | T15: =+F16 -> 9 | U15: =+G16 -> 0 | V15: =+H16 -> 0 | W15: =+I16 -> 9 | X15: =+J16 -> 0 | Y15: =+K16 -> 0
A16: Mechanical | D16: =I16 -> 9 | E16: 0 | F16: 9 | G16: 0 | H16: 0 | I16: =E16+F16+G16+H16+K16 -> 9 | J16: =D16-I16 -> 0 | K16: 0 | L16: =E16+F16+G16+H16+K16+J16 -> 9 | M16: =+I16/D16 -> 1 | N16: =+L16/D16 -> 1 | R16: =+D17 -> 73 | S16: =+E17 -> 6 | T16: =+F17 -> 67 | U16: =+G17 -> 0 | V16: =+H17 -> 0 | W16: =+I17 -> 73 | X16: =+J17 -> 0 | Y16: =+K17 -> 0
A17: Electrical | D17: =I17 -> 73 | E17: 6 | F17: 67 | G17: 0 | H17: 0 | I17: =E17+F17+G17+H17+K17 -> 73 | J17: =D17-I17 -> 0 | K17: 0 | L17: =E17+F17+G17+H17+K17+J17 -> 73 | M17: =+I17/D17 -> 1 | N17: =+L17/D17 -> 1 | R17: =+D36 -> 146 | S17: =+E36 -> 109 | T17: =+F36 -> 37 | U17: =+G36 -> 0 | V17: =+H36 -> 0 | W17: =+I36 -> 146 | X17: =+J36 -> 0 | Y17: =+K36 -> 0
A18: Telecom | D18: =I18 -> 25 | E18: 0 | F18: 25 | G18: 0 | I18: =E18+F18+G18+H18+K18 -> 25 | J18: =D18-I18 -> 0 | K18: 0 | L18: =E18+F18+G18+H18+K18+J18 -> 25 | M18: =+I18/D18 -> 1
A19: Potable | D19: =I19 -> 89 | E19: 3 | F19: 86 | G19: 0 | H19: 0 | I19: =E19+F19+G19+H19+K19 -> 89 | J19: =D19-I19 -> 0 | K19: 0 | L19: =E19+F19+G19+H19+K19+J19 -> 89
A20: Sewer | D20: =I20 -> 29 | E20: 1 | F20: 28 | G20: 0 | H20: 0 | I20: =E20+F20+G20+H20+K20 -> 29 | J20: =D20-I20 -> 0 | K20: 0 | L20: =E20+F20+G20+H20+K20+J20 -> 29
A21: Irrigation | D21: =I21 -> 64 | E21: 14 | F21: 50 | G21: 0 | H21: 0 | I21: =E21+F21+G21+H21+K21 -> 64 | J21: =D21-I21 -> 0 | K21: 0 | L21: =E21+F21+G21+H21+K21+J21 -> 64
A22: Strom | D22: =I22 -> 66 | E22: 21 | F22: 45 | G22: 0 | H22: 0 | I22: =E22+F22+G22+H22+K22 -> 66 | J22: 0 | K22: 0 | L22: =E22+F22+G22+H22+K22+J22 -> 66
B23: Architectural | D23: =I23 -> 9 | E23: 1 | F23: 8 | G23: 0 | H23: 0 | I23: =E23+F23+G23+H23+K23 -> 9 | J23: 0 | K23: 0 | L23: =E23+F23+G23+H23+K23+J23 -> 9
A24: Enviromental | D24: =I24 -> 27 | E24: 0 | F24: 27 | G24: 0 | H24: 0 | I24: =E24+F24+G24+H24+K24 -> 27 | J24: =D24-I24 -> 0 | K24: 0 | L24: =E24+F24+G24+H24+K24+J24 -> 27
A25: TOTAL | D25: =SUM(D13:D24) -> 702 | E25: =SUM(E13:E24) -> 103 | F25: =SUM(F13:F24) -> 595 | G25: =SUM(G13:G24) -> 0 | H25: =SUM(H13:H24) -> 0 | I25: =SUM(I13:I24) -> 702 | J25: =SUM(J13:J24) -> 0 | K25: =SUM(K13:K24) -> 4 | L25: =SUM(L13:L24) -> 702 | M25: =+I25/D25 -> 1 | N25: =+L25/D25 -> 1
I26: =+I25/D25 -> 1
A28: Material Approval
A29: Item Per WBS | D29: Total Planned | E29: Total Materials Submitted | J29: Remaining to approve | K29: Pending | L29: Total Submittals
E30: A | F30: B | G30: C | H30: D | I30: Processed | J30: with Designer | K30: Submittals With Consultant
A31: General | D31: =I31 -> 0 | E31: 0 | F31: 0 | G31: 0 | H31: 0 | I31: 0 | J31: 0 | K31: 0 | L31: 0
A32: Road Works | D32: =I32 -> 0 | E32: 0 | F32: 0 | G32: 0 | H32: 0 | I32: 0 | J32: 0 | K32: 0 | L32: 0 | P32: 75
A33: Civil | D33: =I33 -> 54 | E33: 54 | F33: 0 | G33: 0 | I33: =L33 -> 54 | J33: 0 | K33: 0 | L33: =E33+F33+G33+H33+K33 -> 54 | P33: 16
A34: Mechanical | D34: =I34 -> 59 | E34: 55 | F34: 4 | G34: 0 | H34: 0 | I34: =L34 -> 59 | J34: 0 | K34: 0 | L34: =E34+F34+G34+H34+K34 -> 59 | P34: =P32-P33 -> 59
A35: Electrical | D35: 33 | E35: 0 | F35: 33 | G35: 0 | H35: 0 | I35: =L35 -> 33 | J35: 0 | K35: 0 | L35: =E35+F35+G35+H35+J35+K35 -> 33
A36: TOTAL | D36: =SUM(D31:D35) -> 146 | E36: =SUM(E31:E35) -> 109 | F36: =SUM(F31:F35) -> 37 | G36: =SUM(G31:G35) -> 0 | H36: =SUM(H31:H35) -> 0 | I36: =SUM(I31:I35) -> 146 | J36: =SUM(J31:J35) -> 0 | K36: =SUM(K31:K35) -> 0 | L36: =SUM(L31:L35) -> 146 | N36: =+L36/D36 -> 1
A38: Procurement Summary
A39: Item Per WBS | D39: Total Materials Planned | E39: Total Number of P.O. | F39: Actual P.O. To Date | G39: Remaining P.O | H39: Actual Material on Site | I39: Remaining Materials | J39: Material Delivery Completion (Date)
E40: A | F40: B | G40: C | H40: D | I40: Processed
A41: General | D41: 0 | E41: 0 | G41: 0 | H41: 0 | I41: 0 | J41: 46081
A42: Road Works | D42: 0 | E42: 0 | G42: 0 | H42: 0 | I42: 0 | J42: 46081
A43: Civil | D43: 0 | E43: 0 | F43: 0 | G43: 0 | H43: 0 | I43: 0 | J43: 46081
A44: Mechanical | D44: 18 | E44: 18 | F44: 18 | G44: 0 | H44: 15 | I44: =D44-H44 -> 3 | J44: 46280
A45: Electrical | D45: 16 | E45: 16 | F45: 16 | G45: 0 | H45: 12 | I45: =D45-H45 -> 4 | J45: 46280
A46: TOTAL | D46: =SUM(D41:D45) -> 34 | E46: =SUM(E41:E45) -> 34 | F46: =SUM(F41:F45) -> 34 | G46: =SUM(G41:G45) -> 0 | H46: =SUM(H41:H45) -> 27 | I46: =SUM(I41:I45) -> 7 | J46: =MAX(J41:J45) -> 46280
A48: Consultant Quality Inspections / Observations (Weekly Basis) | I48: Overall Average | J48: =AVERAGE(E50:E124) -> 0.86880529 | L48: Average Closing | M48: =AVERAGE(G50:G124) -> 2
A49: Week Number | B49: Date of Audit | C49: Date Issued | D49: Numbers Of Comments | E49: Quality Score | F49: Date Closed | G49: Closure Duration | I49: This Week Score | J49: =Quality!AC10 -> 0.85303793 | L49: Average Number of Comments Per Audit | M49: =AVERAGE(D50:D124) -> 1.9534884
A50: Week-1
A51: Week-2
A52: Week-3
A53: Week-4
A54: Week-5 | B54: 46014 | C54: =+B54-3 -> 46011 | D54: 1 | E54: 0.875 | F54: =+C54+2 -> 46013 | G54: =F54-C54 -> 2
A55: Week-6 | B55: 46021 | C55: =+B55-3 -> 46018 | D55: 1 | E55: 0.87689655 | F55: =+C55+2 -> 46020 | G55: =F55-C55 -> 2
A56: Week-7 | B56: 46028 | C56: =+B56-3 -> 46025 | D56: 2 | E56: 0.87672414 | F56: =+C56+2 -> 46027 | G56: =F56-C56 -> 2
A57: Week-8 | B57: 46035 | C57: =+B57-3 -> 46032 | D57: 2 | E57: 0.88913793 | F57: =+C57+2 -> 46034 | G57: =F57-C57 -> 2
A58: Week-9 | B58: 46042 | C58: =+B58-3 -> 46039 | D58: 2 | E58: 0.88913793 | F58: =+C58+2 -> 46041 | G58: =F58-C58 -> 2
A59: Week-10 | B59: 46049 | C59: =+B59-3 -> 46046 | D59: 2 | E59: 0.88913793 | F59: =+C59+2 -> 46048 | G59: 2
A60: Week-11 | B60: 46055 | C60: =+B60-3 -> 46052 | D60: 2 | E60: 0.88913793 | F60: =+C60+2 -> 46054 | G60: 2
A61: Week-12 | B61: 46063 | C61: =+B61-3 -> 46060 | D61: 2 | E61: 0.88913793 | F61: =+C61+2 -> 46062 | G61: 2
A62: Week-13 | B62: 46070 | C62: =+B62-3 -> 46067 | D62: 2 | E62: 0.88913793 | F62: =+C62+2 -> 46069 | G62: 2
A63: Week-14 | B63: 46077 | C63: =+B63-3 -> 46074 | D63: 2 | E63: 0.88913793 | F63: =+C63+2 -> 46076 | G63: 2
A64: Week-15 | B64: 46084 | C64: =+B64-3 -> 46081 | D64: 2 | E64: 0.88913793 | F64: =+C64+2 -> 46083 | G64: 2
A65: Week-16 | B65: 46091 | C65: =+B65-3 -> 46088 | D65: 2 | E65: 0.88913793 | F65: =+C65+2 -> 46090 | G65: 2
A66: Week-17 | B66: 46098 | C66: =+B66-3 -> 46095 | D66: 2 | E66: 0.88913793 | F66: =+C66+2 -> 46097 | G66: 2
A67: Week-18 | B67: 46105 | C67: =+B67-3 -> 46102 | D67: 2 | E67: 0.88913793 | F67: =+C67+2 -> 46104 | G67: 2
A68: Week-19 | B68: 46112 | C68: =+B68-3 -> 46109 | D68: 2 | E68: 0.88913793 | F68: =+C68+2 -> 46111 | G68: 2
A69: Week-20 | B69: 46119 | C69: =+B69-3 -> 46116 | D69: 2 | E69: 0.88913793 | F69: =+C69+2 -> 46118 | G69: 2
A70: Week-21 | B70: 46126 | C70: =+B70-3 -> 46123 | D70: 2 | E70: 0.88913793 | F70: =+C70+2 -> 46125 | G70: 2
A71: Week-22 | B71: 46133 | C71: =+B71-3 -> 46130 | D71: 2 | E71: 0.88913793 | F71: =+C71+2 -> 46132 | G71: 2
A72: Week-23 | B72: 46140 | C72: =+B72-3 -> 46137 | D72: 2 | E72: =+Quality!AC10 -> 0.85303793 | F72: =+C72+2 -> 46139 | G72: 2
A73: Week-24 | B73: 46147 | C73: =+B73-3 -> 46144 | D73: 2 | E73: 0.8891 | F73: =+C73+2 -> 46146 | G73: 2
A74: Week-25 | B74: 46154 | C74: =+B74-3 -> 46151 | D74: 2 | E74: 0.8891 | F74: =+C74+2 -> 46153 | G74: 2
A75: Week-26 | B75: 46161 | C75: =+B75-3 -> 46158 | D75: 2 | E75: 0.8891 | F75: =+C75+2 -> 46160 | G75: 2
A76: Week-27 | B76: 46168 | C76: =+B76-3 -> 46165 | D76: 2 | E76: 0.8891 | F76: =+C76+2 -> 46167 | G76: 2
A77: Week-28 | B77: 46175 | C77: =+B77-3 -> 46172 | D77: 2 | E77: 0.8891 | F77: =+C77+2 -> 46174 | G77: 2
A78: Week-29 | B78: 46182 | C78: =+B78-3 -> 46179 | D78: 2 | E78: 0.8891 | F78: =+C78+2 -> 46181 | G78: 2
A79: Week-30 | B79: 46189 | C79: =+B79-3 -> 46186 | D79: 2 | E79: 0.8891 | F79: =+C79+2 -> 46188 | G79: 2
A80: Week-31 | B80: 46196 | C80: =+B80-3 -> 46193 | D80: 2 | E80: 0.834 | F80: =+C80+2 -> 46195 | G80: 2
A81: Week-32 | B81: 46203 | C81: =+B81-3 -> 46200 | D81: 2 | E81: 0.834 | F81: =+C81+2 -> 46202 | G81: 2
A82: Week-33 | B82: 46210 | C82: =+B82-3 -> 46207 | D82: 2 | E82: 0.834 | F82: =+C82+2 -> 46209 | G82: 2
A83: Week-34 | B83: 46217 | C83: =+B83-3 -> 46214 | D83: 2 | E83: 0.834 | F83: =+C83+2 -> 46216 | G83: 2
A84: Week-35 | B84: 46224 | C84: =+B84-3 -> 46221 | D84: 2 | E84: 0.834 | F84: =+C84+2 -> 46223 | G84: 2
... A96: Week-47 | B96: 46308 | C96: =+B96-3 -> 46305 | D96: 2 | E96: 0.853 | F96: =+C96+2 -> 46307 | G96: 2
A97: Week-48
A98: Week-49
A99: Week-50
A100: Week-51
A101: Week-52
A102: Week-53
A103: Week-54
A104: Week-55
A105: Week-56
A106: Week-57
A107: Week-58
A108: Week-59
... A124: Week-75

Sheet HSE
B1: MODON HSE Site Inspection Report
B2: Date: | E2: ='General Information'!L1 -> 46308 | L2: Inspected By: | U2: Mubashar Suhail
B4: Project ID. | E4: ='General Information'!C4 -> JHD4-02-007 | L4: Report No. | P4: =Quality!O6 -> 47 | W4: MODON PM Name | Y4: ='General Information'!C9 -> Mohammed Alshunaifi
B6: Project Name: | E6: ='General Information'!C3 -> LAND DEVELOPMENT OF JEDDAH OASIS | L6: Contractor: | R6: ='General Information'!C5 -> AL-ENJAZ TRADING AND CONTRACTING COMPANY | X6: Safety Performance | AA6: =IF(W29>0,3,IF(L29>6,2,IF(D29>9,1,1)*1)*1) -> 2 | AE6: =(((COUNTIF(L13:Q25,"1")+COUNTIF(AC13:AH25,"1"))*AR13)+(COUNTIF(L13:Q25,"2")+COUNTIF(AC13:AH25,"2"))*AR14+(COUNTIF(L13:Q25,"3")+COUNTIF(AC13:AH25,"3"))*AR15)/((COUNT(L13:Q25)+COUNT(AC13:AH25))*100) -> 0.88
B8: Inspections are a snapshot in time and refer only to the practices and documentation observed at the time of the Inspection. It remains the responsibility of the Consultant and Contractor to ensure that all aspects of Health & Safety are suitably managed.
B9: 1 | D9: Good Practice | H9: 2 | I9: Need Improvement | T9: 3 | U9: Fail (Life Threatening Activity) / Comliance with Plan & Procedures | X9: N/A | Y9: Atcitty Not Applicable for this Site Inspection Report
B11: No. | C11: Topic | K11: Wt. | L11: HSE Compliance | S11: No. | T11: Topic | AB11: Wt. | AC11: HSE Compliance
B13: 1 | C13: Access and Egress - (General access to site, segregated from vehicles, / Overhead protection, while entering into the building /Adequate lighting provided when dark or overnight work) | K13: 0.05 | L13: 2 | S13: 14 | T13: Work at Height - (PPE/Fall Protection(Same level, above and blow) / Training / Fall restraint / competency /Safe access & egress to and from work at height / Ladders / Openings (floor/shafts/Provision of emergency rescue) | AB13: 0.05 | AC13: 2 | AP13: 1 | AR13: 100 | AU13: 1
B14: 2 | C14: Traffic Management - (Loading/unloading/sheeting/temp. routes/speed/parking/competence) | K14: 0.03 | L14: 1 | S14: 15 | T14: Scaffolding - (Temp. Scaffolding Work-platform (All types) - qualified scaffolder / Inspection / Tagged / Safe Access/egress / PTW/Falsework & Formwork) | AB14: 0.04 | AC14: 2 | AP14: 2 | AR14: 75 | AU14: 2
B15: 3 | C15: Site Signage - (Project Notice Board & General Signage) | K15: 0.02 | L15: 1 | S15: 16 | T15: Mobile Elevated Work platform (MEWP) - (PTW/competence requirements/conditions/inspections/tagged/training/Full-body harness) | AB15: 0.04 | AC15: 2 | AP15: 3 | AR15: 0 | AU15: 3
B16: 4 | C16: PPE Compliance - (Use, storage, stock, handling & checks - Head, Foot, Eye, Hearing) | K16: 0.05 | L16: 1 | S16: 17 | T16: Excavation & Trenches - (PTW/Edge protection/buffer zone/Slope/Benching/Shoring/Geo-tech report/Atmospheric hazards/Acess&egress/Emergency management / MS&RA/H.E) | AB16: 0.03 | AC16: 2 | AU16: N/A
B17: 5 | C17: Housekeeping - (Material correctly stored/Rubbish cleaned & removed daily/slips & trips hazards) | K17: 0.03 | L17: 1 | S17: 18 | T17: Confined Space - (PTW/Training/competence/Emergency Management/MS & RA/Safe access/egress) | AB17: 0.05 | AC17: N/A
B18: 6 | C18: Storage of Materials - (Transporting, storage, training and use - Combustible / Flammable / Hazardous substances (COSHH) | L18: 1 | S18: 19 | T18: Fire Protection - (Flammable/Oxy. LPG /Combustible separated/FE's/Flashback arrestor/Sparks & slags/Smoking area/PTW/Generators/MS & RA/Emergency Management) | AC18: 2 | AL18: Red | AM18: Serious injury or death (immediately)
B19: 7 | C19: Site Waste Management - (Hazardous waste /Combustible waste / Human waste / Construction waste - asphalt, cable, timber, paving roof sheeting tiles, plastic & bricks) | L19: 1 | S19: 20 | T19: Health & Welfare - (Adequate drinking water/shaded - eating & rest area/washing & sanitary facilities/Certified FA/FA Box & Stock/adequate toilets/Ambulance) | AC19: 2 | AL19: Yellow | AM19: Minor or near miss (3 days to comply)
B20: 8 | C20: Health Surveillance - (Expose to excessive noise/vibration/dust/silica/CO/cement/radiation/extreme weather condition) | K20: 0.03 | L20: 1 | S20: 21 | T20: Environmental Incident Measures - (Spill/ Leakage / Concrete wash / vehicle & eqpts. wash / waste disposal/Sewers and drains/emissions/Emergency Management/Training/site run-off water) | AB20: 0.05 | AC20: 2 | AL20: Green | AM20: No issues
B21: 9 | C21: Electrical Safety - (Electrical qualified /RCD/GFCI/Industrial Cocket/LOTO/Cable-overhung or buried/Cords in good condition/current inspection tag) | K21: 0.05 | L21: 1 | S21: 22 | T21: HSE Communications & Meetings - (Schedule HSE Meetings/Safety Committee meetings/Alerts / Lesson learned/Safety Bulletin contains latest HSE KPI) | AB21: 0.05 | AC21: 2
B22: 10 | C22: Tools & Equipment - (Includes, powered, hydraulic & pneumatic/Guards in place/Properly stored/RCD Protection/Earthed/Good condition & tagged) | K22: 0.03 | L22: 2 | S22: 23 | T22: HSE Plan & Associated Procedures - (Approved updated HSE Plan/ CEMP/HAZComm/Procedures/Standards/Project Safety Risk Register) | AB22: 0.03 | AC22: 1 | AL22: 26 points > 4 minors then is it’s a serious issue
B23: 11 | C23: Manual Handling - (Lifting/loading/pulling/pushing/twisting/awkward posture/repetitive task/frequent and prolong physical effort/Reasonable practicable use of mechanical aid) | K23: 0.03 | L23: 1 | S23: 24 | T23: Health, Safety & Environment Incident reporting - (Review of HSE Statistics, Reporting of Unsafe Act & Conditions/ Reporting of Near Miss incident/Reporting of FA cases/Record MT cases) | AB23: 0.03 | AC23: 2
B24: 12 | C24: Vehicle and mobile equipment / Plant - (dumpers; excavators, cranes, piling rigs, grader, roller, loaders/condition/KSA License/certification) | K24: 0.05 | L24: 1 | S24: 25 | T24: HSE Awareness, Training & Competence - (Policy /Objective & targets/Information, training/Climatic condition awareness/Reponses in emergency situation/ Safety Behavior Observation) | AB24: 0.04 | AC24: 1
B25: 13 | C25: Lifting Operations & Rigging - (Lifting Plan/Lifting devices & gears/PTW/Condition/3rd party certification/bank-man/rigger/slingers/man-basket/inspection record/tagged) | L25: 2 | S25: 26 | T25: Project Leadership Site Tours - (Provide evidence of proactive safety performance/Deficient discovered discussed/Positive feedback/Workers resolving safety issues) | AC25: 1
B27: Prepared by: | G27: Mubashar Sohail | S27: Sent to MODON PM: | X27: Mohammed Alshunaifi
B28: Safety Results
B29: 1 | D29: =COUNTIF(L13:Q26,"1")+COUNTIF(AB13:AG26,"1") -> 13 | I29: 2 | L29: =COUNTIF(L13:Q26,"2")+COUNTIF(AB13:AG26,"2") -> 12 | U29: 3 | W29: =COUNTIF(L13:Q26,"3")+COUNTIF(AB13:AG26,"3") -> 0

Sheet HSE-Stat
A1: Safety Statistics | K1: 18400
A3: Category | B3: Item | D3: This Week | E3: This Month | F3: Year to Date | G3: Cumulative
A4: Category | B4: Total Hours Worked | D4: 11376 | E4: 22752 | F4: 491606 | G4: 504766
B5: Safe Hours Worked | D5: 11376 | E5: 22752 | F5: 491606 | G5: 504766
A6: Reactive | B6: LTI | D6: 0 | E6: 0 | F6: 0 | G6: 0
B7: MTC (Healed w/o Disability) | D7: 0 | E7: 0 | F7: 0 | G7: 0
B8: MTC (Healed w/ Disability) | D8: 0 | E8: 0 | F8: 0 | G8: 0
B9: Near Miss | D9: 0 | E9: 0 | F9: 0 | G9: 0
B10: First Aid Cases | D10: 0 | E10: 0 | F10: 0 | G10: 0
B11: Fatality | D11: 0 | E11: 0 | F11: 0 | G11: 0
B12: Fire Incident Cases | D12: 0 | E12: 0 | F12: 0 | G12: 0
B13: Vehicle Incident | D13: 0 | E13: 0 | F13: 0 | G13: 0
B14: Property Damages | D14: 0 | E14: 0 | F14: 0 | G14: 0
A15: Proactive | B15: Induction Training | D15: 0 | E15: 0 | F15: 69 | G15: 80
B16: No.of Internal Training | D16: 5 | E16: 12 | F16: 264 | G16: 269
B17: No.of Internal Audit | D17: 0 | E17: 0 | F17: 0 | G17: 0
B18: No. of Toolbox Talks | D18: 1 | E18: 2 | F18: 42 | G18: 43
B19: Safety Awards/Incentives | D19: 0 | E19: 0 | F19: 0 | G19: 0
I20: Category | J20: Item | L20: This Week | M20: This Month | N20: Year to Date | O20: Cumulative
A22: Consultant Safety Inspection (Weekly Basis) | I22: Overall Average | J22: =AVERAGE(E24:E98) -> 0.88182002
A23: Week Number | B23: Date of Audit | C23: Date Issued | D23: Numbers Of Comments | E23: Overall Score | F23: Date Closed | G23: Closure Duration | I23: This Week Score | J23: =HSE!AE6 -> 0.88
A24: Week-1
A25: Week-2
A26: Week-3
A27: Week-4
A28: Week-5 | B28: 46014 | C28: =+B28-3 -> 46011 | D28: 5 | E28: 0.91304348 | F28: =+C28+2 -> 46013 | G28: =F28-C28 -> 2
A29: Week-6 | B29: 46021 | C29: =+B29-3 -> 46018 | D29: 3 | E29: 0.90217391 | F29: =+C29+2 -> 46020 | G29: =F29-C29 -> 2
A30: Week-7 | B30: 46028 | C30: =+B30-3 -> 46025 | D30: 3 | E30: 0.91304348 | F30: =+C30+2 -> 46027 | G30: =F30-C30 -> 2
A31: Week-8 | B31: 46035 | C31: =+B31-3 -> 46032 | D31: 3 | E31: 0.91 | F31: =+C31+2 -> 46034 | G31: =F31-C31 -> 2
A32: Week-9 | B32: 46042 | C32: =+B32-3 -> 46039 | D32: 3 | E32: 0.81 | F32: =+C32+2 -> 46041 | G32: =F32-C32 -> 2
A33: Week-10 | B33: 46049 | C33: =+B33-3 -> 46046 | D33: 3 | E33: 0.81 | F33: =+C33+2 -> 46048 | G33: =F33-C33 -> 2
A34: Week-11 | B34: 46055 | C34: =+B34-3 -> 46052 | D34: 3 | E34: 0.81 | F34: =+C34+2 -> 46054 | G34: 2
A35: Week-12 | B35: 46063 | C35: =+B35-3 -> 46060 | D35: 3 | E35: 0.81 | F35: =+C35+2 -> 46062 | G35: 2
A36: Week-13 | B36: 46070 | C36: =+B36-3 -> 46067 | D36: 9 | E36: =+HSE!AE6 -> 0.88 | F36: =+C36+2 -> 46069 | G36: 6
A37: Week-14 | B37: 46077 | C37: =+B37-3 -> 46074 | D37: 5 | E37: 0.88 | F37: =+C37+2 -> 46076 | G37: 5
A38: Week-15 | B38: 46084 | C38: =+B38-3 -> 46081 | D38: 5 | E38: 0.88 | F38: =+C38+2 -> 46083 | G38: 5
A39: Week-16 | B39: 46089 | C39: 46090 | D39: 6 | E39: 0.88 | F39: 46096 | G39: 6
A40: Week-17 | B40: 46098 | C40: =+B40-3 -> 46095 | D40: 6 | E40: 0.88 | F40: =+C40+2 -> 46097 | G40: 6
A41: Week-18 | B41: 46105 | C41: =+B41-3 -> 46102 | D41: 6 | E41: 0.9 | F41: =+C41+2 -> 46104 | G41: 0
A42: Week-19 | B42: 46112 | C42: =+B42-3 -> 46109 | D42: 6 | E42: 0.88 | F42: =+C42+2 -> 46111 | G42: 6
A43: Week-20 | B43: 46119 | C43: =+B43-3 -> 46116 | D43: 4 | E43: 0.88 | F43: =+C43+2 -> 46118 | G43: 1
A44: Week-21 | B44: 46126 | C44: =+B44-3 -> 46123 | D44: 5 | E44: 0.88 | F44: =+C44+2 -> 46125 | G44: 5
A45: Week-22 | B45: 46133 | C45: =+B45-3 -> 46130 | D45: 5 | E45: 0.88 | F45: =+C45+2 -> 46132 | G45: 6
A46: Week-23 | B46: 46140 | C46: =+B46-3 -> 46137 | D46: 6 | E46: 0.88 | F46: =+C46+2 -> 46139 | G46: 4
A47: Week-24 | B47: 46147 | C47: =+B47-3 -> 46144 | D47: 5 | E47: 0.9 | F47: =+C47+2 -> 46146 | G47: 3
A48: Week-25 | B48: 46154 | C48: =+B48-3 -> 46151 | D48: 5 | E48: 0.88 | F48: =+C48+2 -> 46153 | G48: 4
A49: Week-26 | B49: 46161 | C49: =+B49-3 -> 46158 | D49: 3 | E49: 0.88 | F49: =+C49+2 -> 46160 | G49: 4
A50: Week-27 | B50: 46168 | C50: =+B50-3 -> 46165 | D50: 5 | E50: 0.9 | F50: =+C50+2 -> 46167 | G50: 5
A51: Week-28 | B51: 46175 | C51: =+B51-3 -> 46172 | D51: 0 | E51: 0.9 | F51: =+C51+2 -> 46174 | G51: 0
A52: Week-29 | B52: 46182 | C52: =+B52-3 -> 46179 | D52: 6 | E52: 0.88 | F52: 46180 | G52: 4
A53: Week-30 | B53: 46189 | C53: =+B53-3 -> 46186 | D53: 3 | E53: 0.9 | F53: =+C53+2 -> 46188 | G53: 5
A54: Week-31 | B54: 46196 | C54: =+B54-3 -> 46193 | D54: 5 | E54: 0.88 | F54: =+C54+2 -> 46195 | G54: 5
A55: Week-32 | B55: 46203 | C55: =+B55-3 -> 46200 | D55: 7 | E55: 0.88 | F55: =+C55+2 -> 46202 | G55: 4
A56: Week-33 | B56: 46210 | C56: =+B56-3 -> 46207 | D56: 4 | E56: 0.9 | F56: =+C56+2 -> 46209 | G56: 3
A57: Week-34 | B57: 46217 | C57: =+B57-3 -> 46214 | D57: 5 | E57: 0.9 | F57: =+C57+2 -> 46216 | G57: 6
A58: Week-35 | B58: 46224 | C58: =+B58-3 -> 46221 | D58: 4 | E58: 0.9 | F58: =+C58+2 -> 46223 | G58: 4
A59: Week-36 | B59: 46231 | C59: =+B59-3 -> 46228 | D59: 5 | E59: 0.88 | F59: =+C59+2 -> 46230 | G59: 5
A60: Week-37 | B60: 46238 | C60: =+B60-3 -> 46235 | D60: 5 | E60: 0.88 | F60: =+C60+2 -> 46237 | G60: 5
A61: Week-38 | B61: 46245 | C61: =+B61-3 -> 46242 | D61: 6 | E61: 0.88 | F61: =+C61+2 -> 46244 | G61: 5
A62: Week-39 | B62: 46252 | C62: =+B62-3 -> 46249 | D62: 6 | E62: 0.88 | F62: =+C62+2 -> 46251 | G62: 5
A63: Week-40 | B63: 46259 | C63: =+B63-3 -> 46256 | D63: 6 | E63: 0.88 | F63: =+C63+2 -> 46258 | G63: 5
A64: Week-41 | B64: 46259 | C64: 46260 | D64: 3 | E64: 0.9 | F64: 46264 | G64: 4
A65: Week-42 | B65: 46273 | C65: =+B65-3 -> 46270 | D65: 4 | E65: 0.9 | F65: =+C65+2 -> 46272 | G65: 5
A66: Week-43 | B66: 46280 | C66: =+B66-3 -> 46277 | D66: 6 | E66: 0.88 | F66: =+C66+2 -> 46279 | G66: 5
A67: Week-44 | B67: 46287 | C67: =+B67-3 -> 46284 | D67: 5 | E67: 0.88 | F67: =+C67+2 -> 46286 | G67: 5
A68: Week-45 | B68: 46294 | C68: =+B68-3 -> 46291 | D68: 5 | E68: 0.9 | F68: =+C68+2 -> 46293 | G68: 5
A69: Week-46 | B69: 46301 | C69: =+B69-3 -> 46298 | D69: 5 | E69: 0.9 | F69: =+C69+2 -> 46300 | G69: 4
A70: Week-47 | B70: 46308 | C70: =+B70-3 -> 46305 | D70: 5 | E70: 0.88 | F70: =+C70+2 -> 46307 | G70: 3
A71: Week-48
A72: Week-49
A73: Week-50
A74: Week-51
A75: Week-52
A76: Week-53
A77: Week-54
A78: Week-55
A79: Week-56
A80: Week-57
A81: Week-58
A82: Week-59
... A98: Week-75

Sheet Risk Register  
A1: Risk Log
A4: Risk ID | B4: Parent Project ID | C4: Contract / Project ID | D4: Project Name | E4: City | F4: Region | G4: Fund Source | H4: Phase | I4: PM / Owner | J4: Contractor / Designer | K4: Current Status | L4: Value (SAR) | M4: Category | N4: Risk Title | O4: Description | P4: Evidence / Data | Q4: Probability (1-5) | R4: Impact (1-5) | S4: Score | T4: Rating | U4: Response | V4: Mitigation Plan | W4: Date Identified | X4: Status | Y4: Target Date | Z4: Notes / Updates | AA4: Source
A5: 1 | C5: JDH4-02-007 | D5: Land Development of Jeddah Oasis | E5: Jeddah | F5: Western | I5: Mohamed Al Shunaifi | J5: AL-ENJAZ Trading & Contracting Company | K5: Work in progress | L5: 65900000 | M5: Quality / Resources | N5: Delay in Inspection & Testing Due to Shortage of Required Equipment | O5: Potential delays in conducting inspections and testing of the completed works due to a shortage of the required equipment may result in delays to the project handover | P5: Insufficient availability of the required inspection and testing equipment may delay the inspection, testing, and handover of completed works. | Q5: 4 | R5: 4 | S5: 16 | T5: High | U5: Ensure timely availability of all required inspection and testing equipment, coordinate with the concerned departments, and monitor equipment readiness prior to planned inspections and testing activities. | V5: 46283 | W5: Closed | X5: 46285 | Y5: Ensure availability of required inspection and testing equipment to avoid delays. | Z5: Quality Department / Site Inspection Activities
A6: 2 | C6: JDH4-02-007 | D6: Land Development of Jeddah Oasis | E6: Jeddah | F6: Western | I6: Mohamed Al Shunaifi | J6: AL-ENJAZ Trading & Contracting Company | K6: Work in progress | L6: 65900000 | M6: Procurement / Quality | N6: Delay in Material & Supplier Approvals | O6: Delay in the approval of project materials and suppliers, which may affect the timely delivery of materials, completion of works, and overall project handover | P6: Pending material and supplier approval requests affecting procurement lead times | Q6: 4 | R6: 4 | S6: 16 | T6: High | U6: Expedite pending approvals and closely follow up with the Consultant and relevant departments | V6: 46044 | W6: Closed | X6: 46051 | Y6: Monitor approval status and expedite pending submissions to avoid material delivery delays | Z6: Material & Supplier Approval Log / Procurement Department
A7: 3 | C7: JDH4-02-007 | D7: Land Development of Jeddah Oasis | E7: Jeddah | F7: Western | I7: Mohamed Al Shunaifi | J7: AL-ENJAZ Trading & Contracting Company | K7: Work in progress | L7: 65900000 | M7: Quality/HSE | N7: Delay in Material Approval & MIR Submission | O7: Failure to submit delivered materials for Consultant approval the required MIR, which may delay material utilization on site, impact work progress, and consequently delay project handover | P7: Materials delivered to site pending Consultant approval and MIR submission | Q7: 4 | R7: 4 | S7: 16 | T7: High | U7: Ensure timely MIR submission and obtain Consultant approval before material use | V7: 46002 | W7: Closed | X7: 46009 | Y7: Monitor delivered materials and expedite pending MIR submissions and approvals | Z7: Material Receiving Records / MIR Log / Quality Department
A8: 4 | C8: JDH4-02-007 | D8: Land Development of Jeddah Oasis | E8: Jeddah | F8: Western | I8: Mohamed Al Shunaifi | J8: AL-ENJAZ Trading & Contracting Company | K8: Work in progress | L8: 65900000 | M8: Quality/HSE | N8: Heat Stress and Heat-Related Illnesses due to High Ambient Temperature | O8: Extreme high temperatures in Jeddah during outdoor construction activities increase the risk of heat exhaustion, heat stroke, and reduced worker concentration, potentially leading to incidents which might also be fire related. | P8: Jeddah summer conditions with temperatures frequently exceeding 40°C; outdoor heavy activities ongoing | Q8: 4 | R8: 4 | S8: 16 | T8: High | U8: Enforce mandatory rest breaks during peak heat hours (12:00–15:00), provide shaded rest areas and drinking water, conduct heat stress toolbox talks, monitor workers, and adjust work schedules where necessary. | V8: 18/04/2026 | W8: Closed | X8: 46058 | Y8: Strictly implemented the 3 hour summer break, provided cold drinking water, ORS and suun shades etc and provided fire extinguishers for equipment. | Z8: Heat Stress Document
A9: 5 | C9: JDH4-02-007 | D9: Land Development of Jeddah Oasis | E9: Jeddah | F9: Western | I9: Mohamed Al Shunaifi | J9: AL-ENJAZ Trading & Contracting Company | K9: Work in progress | L9: 65900000 | M9: Quality/HSE | N9: Vehicle and Mobile Equipment Related Incidents during Road Works | O9: Ongoing road works and asphalt paving activities involving multiple mobile equipment and temporary traffic arrangements increase the risk of vehicle-plant collision, run-over, or struck-by incidents involving workers and equipment. | P9: Active wearing course, road marking, and traffic management activities within the project site | Q9: 5 | R9: 4 | S9: 20 | T9: High | U9: Strict implementation of approved Traffic Management Plan, use of banksmen, speed limit enforcement (20 km/h), proper barricading, high-visibility clothing, and daily inspection of traffic control measures. | V9: 46242 | W9: Closed | X9: 15/8/2026 | Y9: Provided flagman and ensured signboards at site and monitoring compliance | Z9: Regularly approved updated site traffic layouts from consultant.
A10: 6 | C10: JDH4-02-007 | D10: Land Development of Jeddah Oasis | E10: Jeddah | F10: Western | I10: Mohamed Al Shunaifi | J10: AL-ENJAZ Trading & Contracting Company | K10: Work in progress | L10: 65900000 | M10: Quality/HSE | N10: Theft Incident during night | O10: Risk of Fall into Deep Open Excavations | P10: Presence of open excavations increases the risk of workers falling into the openings, which may result in fatal or serious injuries or vehicles falling into excavations. | Q10: 5 | R10: 5 | S10: 25 | T10: High | U10: Install and maintain hard barriers around all deep openings, enforce strict no-leaning/no-entry rules, conduct regular toolbox talks, ensure continuous supervision, and implement confined space controls if entry is required. | V10: 30/12/2025 | W10: Closed | X10: 46113 | Y10: Provided hard barrications around the excavations, permit is obtained and excavation safety training has been delivered. | Z10: Permit to work, excavation safety trainings etc.
A11: 7 | C11: JDH4-02-007 | D11: Land Development of Jeddah Oasis | E11: Jeddah | F11: Western | I11: Mohamed Al Shunaifi | J11: AL-ENJAZ Trading & Contracting Company | K11: Work in progress | L11: 65900000 | M11: Quality/HSE | N11: Falling of equipment during tent road activity | O11: Risk of equipment falling during tent road construction activities which may cause injury to workers or damage to property. | P11: Ongoing tent road related activities involving Dump truck and mobile equipment | Q11: 4 | R11: 4 | S11: 16 | T11: High | U11: Install and maintain Hard barriers at the edge,Conduct regular Toolbox talk ,and ensure continous Supervision. | V11: 45667 | W11: Closed | X11: 46122 | Z11: Permit to work,Toolbox talk, trainings etc.

Sheet Procurement
A1: Sr. NO. | B1: Project ID | C1: ACT # in P6 | D1: Item Description | E1: Discipline | F1: (Long \Short) Lead Items | G1: BOQ. No. | H1: Unit | I1: Quantity | J1: Proc. Qty | K1: Required P.O Date | L1: Date of Pur. Order Issued | M1: Purchase Order No. | N1: Supplier | O1: Supplier Phone | P1: Method of Shipping | Q1: Required on Job | R1: E.D.A. to Site | S1: A.D.A. to Site | T1: Lead Time | U1: Approval Status | V1: The Impact (BOQ Cost) | W1: Completion Rate | X1: Remarks
A2: 1 | B2: JHD4-02-007 | C2: JDH4-02-007-PR-1740 | D2: Catch Basins | E2: Mech. | F2: Long Lead Items | G2: B6.33 05 39.01 | H2: nr | I2: 32 | J2: 32 | K2: 46021 | L2: 46043 | M2: P119134 | N2: T. Nagadi Factory | O2: 0500195198 | P2: Land | Q2: 46103 | R2: 46103 | S2: 46047 | T2: =+IF(ISBLANK(S2),"",(S2-L2)) -> 4 | U2: Approved | V2: 367153.8 | W2: =+J2/I2 -> 1 | X2: Completed
A3: 2 | B3: JHD4-02-007 | C3: JDH4-02-007-PR-1680 | D3: GRP Pipes | E3: Mech. | F3: Long Lead Items | G3: B5.33 31&B6.33 42 | H3: m | I3: 5420 | J3: 5420 | K3: 46020 | L3: 46019 | M3: Po117310,P117449 | N3: T. Nagadi Factory | O3: 0500195198 | P3: Land | Q3: 46060 | R3: 46060 | S3: 46019 | T3: =+IF(ISBLANK(S3),"",(S3-L3)) -> 0 | U3: Approved | V3: 5596610.1 | W3: =+J3/I3 -> 1 | X3: Completed
A4: 3 | B4: JHD4-02-007 | C4: JDH4-02-007-PR-1710 | D4: Manholes | E4: Mech. | F4: Long Lead Items | G4: B5.33 05 | H4: nr | I4: 87 | J4: 87 | K4: 343 | L4: 46023 | M4: P117657 | N4: T. Nagadi Factory | O4: 0500195198 | P4: Land | Q4: 46067 | R4: 46067 | S4: 46032 | T4: =+IF(ISBLANK(S4),"",(S4-L4)) -> 9 | U4: Approved | V4: 2882628.1 | W4: =+J4/I4 -> 1 | X4: Completed
A5: 4 | B5: JHD4-02-007 | C5: JDH4-02-007-PR-1590 | D5: HDPE For Network | E5: Mech. | F5: Long Lead Items | G5: B3.33 14 &B4.33 31 | H5: m | I5: 8969 | J5: 8969 | K5: 46020 | L5: 46021 | M5: P117525 | N5: NEPROPLAST | O5: 0557128534 | P5: Land | Q5: 46055 | R5: 46055 | S5: 46022 | T5: =+IF(ISBLANK(S5),"",(S5-L5)) -> 1 | U5: Approved | V5: 2950231.4 | W5: =+J5/I5 -> 1 | X5: Completed
A6: 5 | B6: JHD4-02-007 | C6: JDH4-02-007-PR-1230 | D6: UPVC | E6: Mech. | F6: Long Lead Items | G6: B2.33 &B7.16 | H6: 3 | I6: 361 | J6: 361 | K6: 46026 | N6: Al-Munif | O6: 0507775269 | P6: Land | Q6: 46068 | R6: 46068 | T6: =+IF(ISBLANK(S6),"",(S6-L6)) | U6: Approved | V6: 301442.69 | W6: =+J6/I6 -> 1 | X6: Completed
A7: 6 | B7: JHD4-02-007 | C7: JDH4-02-007-PR-2280 | D7: HDPE For Telcom | E7: Elec. | F7: Long Lead Items | G7: B2.33 71 | H7: m | I7: 45580 | J7: 45580 | K7: 46044 | P7: Land | Q7: 46089 | R7: 46089 | T7: =+IF(ISBLANK(S7),"",(S7-L7)) | U7: Approved | V7: 2151144.7 | W7: =+J7/I7 -> 1 | X7: Completed
A8: 7 | B8: JHD4-02-007 | C8: JDH4-02-007-PR-2320 | D8: Fire Fighting System | E8: Mech. | F8: Long Lead Items | G8: B7.15.17.1.1 | H8: Lot | I8: 1 | J8: 1 | K8: 46040 | P8: Land | Q8: 46086 | R8: 46086 | T8: =+IF(ISBLANK(S8),"",(S8-L8)) | U8: Approved | V8: 70606.5 | W8: =+J8/I8 -> 1 | X8: Completed
A9: 8 | B9: JHD4-02-007 | C9: JDH4-02-007-PR-2410 | D9: CCTV System | E9: Elec. | F9: Long Lead Items | G9: B7.16.15.1 | H9: nr | I9: 7 | J9: 7 | K9: 46044 | P9: Land | Q9: 46085 | R9: 46085 | T9: =+IF(ISBLANK(S9),"",(S9-L9)) | U9: Approved | V9: 296547.3 | W9: =+J9/I9 -> 1 | X9: Completed
A10: 9 | B10: JHD4-02-007 | C10: JDH4-02-007-PR-1290 | D10: Valves | E10: Mech. | F10: Long Lead Items | G10: B3&B4&B7 | H10: nr | I10: 68 | J10: 68 | K10: 46023 | L10: 46063 | M10: P120734 | N10: T-Nagadi | O10: 0500195198 | P10: Land | Q10: 46148 | R10: 46148 | T10: =+IF(ISBLANK(S10),"",(S10-L10)) | U10: Approved | V10: 626985.72 | W10: =+J10/I10 -> 1 | X10: Completed
A11: 10 | B11: JHD4-02-007 | C11: JDH4-02-007-PR-2460 | D11: Fire Hydrant | E11: Mech. | F11: Long Lead Items | G11: B3.33 14 19.11 | H11: nr | I11: 30 | J11: 30 | K11: 46020 | P11: Land | Q11: 46141 | R11: 46141 | T11: =+IF(ISBLANK(S11),"",(S11-L11)) | U11: Approved | V11: 423639 | W11: =+J11/I11 -> 1 | X11: Completed
A12: 11 | B12: JHD4-02-007 | C12: JDH4-02-007-PR-1120 | D12: Medium Voltage Cable | E12: Mech. | F12: Long Lead Items | G12: B2.26.05.13.16.01 | H12: m | I12: 13117 | J12: 13117 | K12: 46044 | P12: Land | Q12: 46127 | R12: 46127 | T12: =+IF(ISBLANK(S12),"",(S12-L12)) | U12: Approved | V12: 1166457 | W12: =+J12/I12 -> 1 | X12: Completed
A13: 12 | B13: JHD4-02-007 | C13: JDH4-02-007-PR-1130 | D13: Unit Sub-station | E13: Elec. | F13: Long Lead Items | G13: B2.26 11 16.01 | H13: Unit | I13: 1 | J13: 1 | K13: 46044 | P13: Sea | Q13: 46186 | R13: 46186 | T13: =+IF(ISBLANK(S13),"",(S13-L13)) | U13: Approved | V13: 112970.4 | W13: =+J13/I13 -> 1 | X13: Completed
A14: 13 | B14: JHD4-02-007 | C14: JDH4-02-007-PR-1140 | D14: Low Voltage Cables | E14: Elec. | F14: Long Lead Items | G14: B2.26 05 &B7.16 | H14: m | I14: 13117 | J14: 13117 | K14: 46030 | P14: Land | Q14: 46114 | R14: 46114 | T14: =+IF(ISBLANK(S14),"",(S14-L14)) | U14: Approved | V14: 690832.83 | W14: =+J14/I14 -> 1 | X14: Completed
A15: 14 | B15: JHD4-02-007 | C15: JDH4-02-007-PR-1960 | D15: Ring Main Unit (RMU) | E15: Elec. | F15: Long Lead Items | G15: B2.26 11 16.02 | H15: Unit | I15: 3 | J15: 3 | K15: 46044 | P15: Sea | Q15: 46141 | R15: 46141 | T15: =+IF(ISBLANK(S15),"",(S15-L15)) | U15: Approved | V15: 94142.001 | W15: =+J15/I15 -> 1 | X15: Completed
A16: 15 | B16: JHD4-02-007 | C16: JDH4-02-007-PR-1150 | D16: Lighting poles | E16: Elec. | F16: Long Lead Items | G16: B2.26 56 | H16: Unit | I16: 258 | J16: 258 | K16: 46044 | P16: Land | Q16: 46125 | R16: 46125 | T16: =+IF(ISBLANK(S16),"",(S16-L16)) | U16: Approved | V16: 527101.06 | W16: =+J16/I16 -> 1 | X16: Completed
A17: 16 | B17: JHD4-02-007 | C17: JDH4-02-007-PR-1160 | D17: Street Lighting Luminaire | E17: Elec. | F17: Long Lead Items | G17: B2.26.56.19 | H17: Unit | I17: 258 | J17: 258 | K17: 46044 | P17: Land | Q17: 46145 | R17: 46145 | T17: =+IF(ISBLANK(S17),"",(S17-L17)) | U17: Approved | V17: 124173.3 | W17: =+J17/I17 -> 1 | X17: Completed
A18: 17 | B18: JHD4-02-007 | C18: JDH4-02-007-PR-1170 | D18: Feeder Pillers | E18: Elec. | F18: Long Lead Items | G18: B2.33 71 16.01 | H18: Unit | I18: 1 | J18: 1 | K18: 46040 | P18: Sea | Q18: 46137 | R18: 46137 | T18: =+IF(ISBLANK(S18),"",(S18-L18)) | U18: Approved | V18: 32949.7 | W18: 1 | X18: Completed
A19: 18 | B19: JHD4-02-007 | C19: JDH4-02-007-PR-2500 | D19: Distribution Panels | E19: Elec. | F19: Long Lead Items | G19: B7.16.2.1 | H19: Item/set | I19: 1 | J19: 1 | K19: 46044 | P19: Sea | Q19: 46128 | R19: 46128 | T19: =+IF(ISBLANK(S19),"",(S19-L19)) | U19: Approved | V19: 42363.9 | W19: 1 | X19: Completed
A20: 19 | B20: JHD4-02-007 | C20: JDH4-02-007-PR-2090 | D20: Odours Control system | E20: Mech. | F20: Long Lead Items | G20: B7.15.8.1 | H20: Set | I20: 1 | J20: 1 | K20: 46030 | P20: Sea | Q20: 46166 | R20: 46166 | T20: =+IF(ISBLANK(S20),"",(S20-L20)) | U20: Approved | V20: 235355 | W20: =+J20/I20 -> 1 | X20: Completed
A21: 20 | B21: JHD4-02-007 | C21: JDH4-02-007-PR-2200 | D21: Crane | E21: Mech. | F21: Long Lead Items | G21: B7.15.9.1 | H21: nr | I21: 1 | J21: 1 | K21: 46046 | P21: Sea | Q21: 46177 | R21: 46177 | T21: =+IF(ISBLANK(S21),"",(S21-L21)) | U21: Approved | V21: 141213 | W21: =+J21/I21 -> 1 | X21: Completed
A22: 21 | B22: JHD4-02-007 | C22: JDH4-02-007-PR-2100 | D22: Air Vents | E22: Mech. | F22: Long Lead Items | G22: B7.15.10.3 | H22: Lot | I22: 1 | J22: 1 | K22: 46040 | P22: Land | Q22: 46236 | R22: 46236 | T22: =+IF(ISBLANK(S22),"",(S22-L22)) | U22: Approved | V22: 2353.55 | W22: =+J22/I22 -> 1 | X22: Completed
A23: 22 | B23: JHD4-02-007 | C23: JDH4-02-007-PR-2240 | D23: Screening Container | E23: Mech. | F23: Long Lead Items | G23: B7.15.12.1 | H23: nr | I23: 1 | J23: 1 | K23: 46040 | P23: Land | Q23: 46236 | R23: 46236 | T23: =+IF(ISBLANK(S23),"",(S23-L23)) | U23: Approved | V23: 14121.3 | W23: =+J23/I23 -> 1 | X23: Completed
A24: 23 | B24: JHD4-02-007 | C24: JDH4-02-007-PR-2110 | D24: Baffle Plates | E24: Mech. | F24: Long Lead Items | G24: B7.15.13.1 | H24: nr | I24: 1 | J24: 1 | K24: 46040 | L24: 46055 | M24: P120012 | N24: International Center of Fiberglass | P24: Land | Q24: 46196 | R24: 46196 | T24: =+IF(ISBLANK(S24),"",(S24-#REF!)) | U24: Approved | V24: 14121.3 | W24: =+J24/I24 -> 1 | X24: Completed
A25: 24 | B25: JHD4-02-007 | C25: JDH4-02-007-PR-2120 | D25: Anti-Water Hammer Equipment | E25: Mech. | F25: Long Lead Items | G25: B7.15.14.2.1 | H25: Lot | I25: 1 | J25: 1 | K25: 46040 | P25: Sea | Q25: 46237 | R25: 46237 | T25: =+IF(ISBLANK(S25),"",(S25-L25)) | U25: Approved | V25: 1317988 | W25: =+J25/I25 -> 1 | X25: Completed
A26: 25 | B26: JHD4-02-007 | C26: JDH4-02-007-PR-2080 | D26: Pumps | E26: Mech. | F26: Long Lead Items | G26: B7.15.1.1 | H26: nr | I26: 2 | J26: 2 | K26: 46040 | L26: 46049 | M26: P119594 | N26: ZAMIL Trading | O26: 0507972833 | P26: Sea | Q26: 46242 | R26: 46280 | T26: =+IF(ISBLANK(S26),"",(S26-L26)) | U26: Approved | V26: 348325.4 | W26: =+J26/I26 -> 1 | X26: under‑manufacturing
A27: 26 | B27: JHD4-02-007 | C27: JDH4-02-007-PR-2610 | D27: MCCB (VFD) | E27: Mech. | F27: Long Lead Items | G27: B7.16.1.1 | H27: Item/set | I27: 1 | J27: 1 | K27: 46040 | P27: Sea | Q27: 46166 | R27: 46280 | T27: =+IF(ISBLANK(S27),"",(S27-L27)) | U27: Approved | V27: 112970.4 | W27: =+J27/I27 -> 1 | X27: under‑manufacturing
A28: 27 | B28: JHD4-02-007 | C28: JDH4-02-007-PR-2620 | D28: Local Control Panel/ Monitoring Control Panel | E28: Elec. | F28: Long Lead Items | G28: B7.16.1.1&B7.16.14.1.1&B7.16.17.1 | H28: item | I28: 3 | J28: 3 | K28: 46040 | P28: Sea | Q28: 46231 | R28: 46280 | T28: =+IF(ISBLANK(S28),"",(S28-L28)) | U28: Approved | V28: 522488.1 | W28: =+J28/I28 -> 1 | X28: under‑manufacturing
A29: 28 | B29: JHD4-02-007 | C29: JDH4-02-007-PR-2630 | D29: Generator | E29: Elec. | F29: Long Lead Items | G29: B7.16.4.1 | H29: Item/set | I29: 1 | J29: 1 | K29: 46040 | P29: Sea | Q29: 46196 | R29: 46196 | T29: =+IF(ISBLANK(S29),"",(S29-L29)) | U29: Approved | V29: 112970.4 | W29: =+J29/I29 -> 1 | X29: under‑manufacturing
A30: 29 | B30: JHD4-02-007 | C30: JDH4-02-007-PR-2840 | D30: Power Factor Correction Capacitor Bank | E30: Elec. | F30: Long Lead Items | G30: B7.16.5.1 | H30: Item/set | I30: 1 | J30: 1 | K30: 46044 | P30: Land | Q30: 46251 | R30: 46251 | T30: =+IF(ISBLANK(S30),"",(S30-L30)) | U30: Approved | V30: 32949.7 | W30: =+J30/I30 -> 1 | X30: under‑manufacturing
A31: 30 | B31: JHD4-02-007 | C31: JDH4-02-007-PR-2980 | D31: Enclosed Switches and Circuit Breakers | E31: Elec. | F31: Long Lead Items | G31: 16.9 | H31: nr | I31: 7 | J31: 4 | K31: 46044 | P31: Land | Q31: 46240 | R31: 46240 | T31: =+IF(ISBLANK(S31),"",(S31-L31)) | U31: Approved | V31: 7531.3601 | W31: =+J31/I31 -> 0.57142857 | X31: On Progress
A32: 31 | B32: JHD4-02-007 | C32: JDH4-02-007-PR-3080 | D32: ICT (Data& telephone System) | E32: Elec. | F32: Long Lead Items | G32: B7.16.15.1 | H32: nr | I32: 7 | J32: 7 | K32: 46044 | P32: Land | Q32: 46240 | R32: 46240 | T32: =+IF(ISBLANK(S32),"",(S32-L32)) | U32: Approved | V32: 296547.3 | W32: =+J32/I32 -> 1 | X32: Completed
A33: 32 | B33: JHD4-02-007 | C33: JDH4-02-007-PR-3140 | D33: PLC | E33: Elec. | F33: Long Lead Items | G33: B7.16.17.1 | H33: item | I33: 1 | J33: 1 | K33: 46044 | P33: Sea | Q33: 46240 | R33: 46280 | T33: =+IF(ISBLANK(S33),"",(S33-L33)) | U33: Approved | V33: 376568 | W33: =+J33/I33 -> 1 | X33: under‑manufacturing
A34: 33 | B34: JHD4-02-007 | C34: JDH4-02-007-PR-3020 | D34: Instrumentation for Process Systems | E34: Elec. | F34: Long Lead Items | G34: 16.19 | H34: item | I34: 18 | J34: 18 | K34: 46044 | P34: Land | Q34: 46251 | R34: 46280 | T34: =+IF(ISBLANK(S34),"",(S34-L34)) | U34: Approved | V34: 273011.8 | W34: =+J34/I34 -> 1 | X34: under‑manufacturing
A35: 34 | B35: JHD4-02-007 | C35: JDH4-02-007-PR-3021 | D35: flow meter | E35: Mech. | F35: Long Lead Items | G35: B7.15.1.2 | H35: item | I35: 1 | J35: 1 | K35: 46044 | P35: Sea | Q35: 46251 | R35: 46280 | U35: Approved | V35: 14121.3 | W35: =+J35/I35 -> 1 | X35: under‑manufacturing
A36: 35 | B36: JHD4-02-007 | C36: JDH4-02-007-PR-3022 | D36: ATS | E36: Elec. | F36: Long Lead Items | G36: B7.16.1.1 | H36: nr | I36: 1 | J36: 1 | K36: 46044 | P36: Sea | Q36: 46251 | R36: 46280 | U36: Approved | V36: 112970.4 | W36: =+J36/I36 -> 1 | X36: under‑manufacturing
A37: 36 | B37: JHD4-02-007 | C37: JDH4-02-007-PR-3023 | D37: IDF Cabinet 9U (for data &Telephone) | E37: Elec. | F37: Long Lead Items | G37: B7.16.14.1.1 | H37: Item/set | I37: 1 | J37: 1 | K37: 46044 | P37: Sea | Q37: 46251 | R37: 46251 | U37: Approved | V37: 32949.7 | W37: =+J37/I37 -> 1 | X37: Completed

Sheet Milestones
A1: ="Milestones "&'General Information'!C3 -> Milestones LAND DEVELOPMENT OF JEDDAH OASIS
A2: Item No. | B2: Milestones | C2: Original (Baseline) | D2: Latest | E2: Forecast | G2: Days Change | I2: Week # | J2: Report #
B3: ="Contract Duration Current Contract Weeks : "&TEXT(I3, "0")&" of "&TEXT(L3, "0") -> Contract Duration Current Contract Weeks : 47 of 79 | C3: =(C14-C6)/7 -> 77.857143 | D3: =(D14-D6)/7 -> 79.142857 | E3: =(E15-E6)/7 -> 60.142857 | G3: =(D3-E3)*7 -> 133 | I3: =+Quality!O6 -> 47 | J3: =ROUNDUP(I3,0) -> 47 | L3: =D3 -> 79.142857
A4: 1 | B4: Award Date | C4: =+'General Information'!C12:I12 -> 45970 | D4: 45970 | E4: =C4 -> 45970 | F4: A | G4: =D4-E4 -> 0
A5: 2 | B5: Contract Sign Date | C5: =+'General Information'!C13:I13 -> 45977 | D5: 45977 | E5: =C5 -> 45977 | F5: A | G5: =D5-E5 -> 0
A6: 3 | B6: Site Handover Date | C6: =+'General Information'!C14:I14 -> 45985 | D6: 45985 | E6: =C6 -> 45985 | F6: A | G6: =D6-E6 -> 0
A7: 4 | B7: Complete Mobilization | C7: 46014 | D7: 46014 | E7: =C7 -> 46014 | F7: A | G7: =D7-E7 -> 0
A8: 5 | B8: Completion of Earthworks & Site Grading For Plots | C8: 46104 | D8: 46238 | E8: 46308 | G8: =D8-E8 -> -70
A9: 6 | B9: Complete Submittals and place order for all long-lead items. | C9: 46347 | D9: 46217 | E9: 46217 | F9: A | G9: =D9-E9 -> 0
A10: 7 | B10: Complete delivery of all equipment and materials | C10: 46387 | D10: 46393 | E10: 46301 | F10: A | G10: =D10-E10 -> 92
A11: 8 | B11: Complete Road Works | C11: 46287 | D11: 46373 | E11: 46308 | G11: =D11-E11 -> 65
A12: 9 | B12: Complete Electrical – Mv Distribution Network | C12: 46513 | D12: 46433 | E12: 46308 | G12: =D12-E12 -> 125
A13: 10 | B13: Completion of Potable Water Network | C13: 46349 | D13: 46406 | E13: 46270 | F13: A | G13: =D13-E13 -> 136
A14: 11 | B14: Complete all Works including Testing & Commissioning, Cleanup, Closeout Documentation and Ready for Initial Handover | C14: 46530 | D14: 46539 | E14: 46393 | G14: =D14-E14 -> 146
A15: 12 | B15: Complete Demobilization | C15: 46530 | D15: 46552 | E15: 46406 | G15: =D15-E15 -> 146
B20: Activity ID | C20: Activity Name | D20: Original Duration | E20: BL Project Start | F20: BL Project Finish | G20: Start | H20: Finish
B21: JDH4-02-007-MS-1050 | C21: Completion of Earthworks & Site Grading For Plots | D21: 0 | F21: 46104 | H21: 46132
B22: JDH4-02-007-MS-1060 | C22: Completion of Sewerage networks | D22: 0 | F22: 46225 | H22: 46239
B23: JDH4-02-007-MS-1070 | C23: Completion of Road Works | D23: 0 | F23: 46287 | H23: 46338
B24: JDH4-02-007-MS-1080 | C24: Completion of Potable Water Network | D24: 0 | F24: 46349 | H24: 46387
B25: JDH4-02-007-MS-1090 | C25: Completion of TSE Network | D25: 0 | F25: 46349 | H25: 46369
B26: JDH4-02-007-MS-1100 | C26: Completion of Electrical Networks | D26: 0 | F26: 46391 | H26: 46413
B27: JDH4-02-007-MS-1110 | C27: Completion of Entire Project | D27: 0 | F27: =D15 -> 46552 | H27: 46559

Sheet Major Quantities
A1: BOQ Number | B1: Description of Item | C1: Total Quantity | D1: Unit of Measurement | E1: Plan To Date | F1: Actual To Date | G1: Remaining Total | H1: Variance | I1: Variance % | J1: Notices | L1: Actual To Date %
A2: B1.31 22 00.03 | B2: Road backfilling | C2: 329706.66 | D2: m³ | E2: =C2 -> 329706.66 | F2: =C2 -> 329706.66 | G2: =C2-F2 -> 0 | H2: =F2-E2 -> 0 | I2: =H2/E2 -> 0 | L2: =F2/C2 -> 1
A3: B1.31 22 00.04 | B3: Plots backfilling | C3: 718628.27 | D3: m³ | E3: 485631 | F3: 654314 | G3: =C3-F3 -> 64314.27 | H3: =F3-E3 -> 168683 | I3: =H3/E3 -> 0.34734809 | L3: =F3/C3 -> 0.91050412
A4: B1.31 22 00.05 | B4: Subgrade | C4: 30811.51 | D4: m³ | E4: =C4*1 -> 30811.51 | F4: =C4 -> 30811.51 | G4: =C4-F4 -> 0 | H4: =F4-E4 -> 0 | I4: =H4/E4 -> 0 | L4: =F4/C4 -> 1
A5: B1.32 11 23.01 | B5: Aggregate base course | C5: 19162 | D5: m³ | E5: =C5*1 -> 19162 | F5: =C5*1 -> 19162 | G5: =C5-F5 -> 0 | H5: =F5-E5 -> 0 | I5: =H5/E5 -> 0 | L5: =F5/C5 -> 1
A6: B1.32 11 26.01 | B6: Bituminous base course (Grading I - Class A), including Prime Coat (MC1) and tack coat (RC2) (if any) | C6: 7129 | D6: m³ | E6: 5865 | F6: =C6*1 -> 7129 | G6: =C6-F6 -> 0 | H6: =F6-E6 -> 1264 | I6: =H6/E6 -> 0.21551577 | L6: =F6/C6 -> 1
A7: B1.32 12 16.01 | B7: Bituminous concrete wearing course, (Grading I - Class A), including tack coat (RC2). | C7: 4052 | D7: m³ | E7: 0 | F7: 4052 | G7: =C7-F7 -> 0 | H7: =F7-E7 -> 4052 | I7: =H7/E7 -> #DIV/0! | L7: =F7/C7 -> 1 | O7: =0.7*C7 -> 2836.4
A8: B1.32 14 13.01 | B8: Precast Concrete curb, Type (K1) | C8: 22496 | D8: m³ | E8: 20364 | F8: 22496 | G8: =C8-F8 -> 0 | H8: =F8-E8 -> 2132 | I8: =H8/E8 -> 0.10469456 | L8: =F8/C8 -> 1
A9: B1.32 14 13.13.01 | B9: Interlocking block pavers for sidewalk/footpath | C9: 12677.13 | D9: m² | E9: 11245 | F9: 12677.13 | G9: =C9-F9 -> 0 | H9: =F9-E9 -> 1432.13 | I9: =H9/E9 -> 0.12735705 | L9: =F9/C9 -> 1
A10: B2.26.05.13.16.01 | B10: Cable: 15KV 3Cx500mm² AL/XLPE/LLDPE unarmored | C10: 5632 | D10: m² | E10: 4260 | F10: 5632 | G10: =C10-F10 -> 0 | H10: =F10-E10 -> 1372 | I10: =H10/E10 -> 0.32206573 | L10: =F10/C10 -> 1
A11: B2.26 27 33.01 | B11: Main: 100A, MCCB, 5-50A, MCCB | C11: 1 | D11: Unit | E11: 0 | F11: 0 | G11: =C11-F11 -> 1 | H11: =F11-E11 -> 0 | I11: =H11/E11 -> #DIV/0! | L11: =F11/C11 -> 0
A12: B2.26 11 16.01 | B12: Unit Substation , 13.8/0.4 kV, 500kVA with RMU | C12: 1 | D12: Unit | E12: 0 | F12: 0 | G12: =C12-F12 -> 1 | H12: =F12-E12 -> 0 | I12: =H12/E12 -> #DIV/0! | L12: =F12/C12 -> 0
A13: B2.26 11 16.02 | B13: Ring Main Unit (RMU) 3-way, 13.8kV | C13: 3 | D13: Unit | E13: 0 | F13: 3 | G13: =C13-F13 -> 0 | H13: =F13-E13 -> 3 | I13: =H13/E13 -> #DIV/0! | L13: =F13/C13 -> 1
A14: B2.26 05 19.01 | B14: Cables, Copper, (4Cx16mm²,Cu/XLPE/SWA/PVC +1x10mm² PVC/PVC) | C14: 6457 | D14: m | E14: 4453 | F14: 6457 | G14: =C14-F14 -> 0 | H14: =F14-E14 -> 2004 | I14: =H14/E14 -> 0.45003369 | L14: =F14/C14 -> 1
A15: B2.26 56 19.01 | B15: Lighting poles with one arm, height of ( 7 ) meters, including the power distribution box, cables , and RCC foundation. | C15: 256 | D15: Unit | E15: 185 | F15: 256 | G15: =C15-F15 -> 0 | H15: =F15-E15 -> 71 | I15: =H15/E15 -> 0.38378378 | L15: =F15/C15 -> 1
A16: B2.26 56 19.02 | B16: Lighting poles with two arm, height of ( 7 ) meters, including the power distribution box, cables , and RCC foundation. | C16: 2 | D16: Unit | E16: 2 | F16: 2 | G16: =C16-F16 -> 0 | H16: =F16-E16 -> 0 | I16: =H16/E16 -> 0 | L16: =F16/C16 -> 1
A17: B2.33 71 16.01 | B17: Street Lighting Feeder pillars | C17: 1 | D17: Unit | E17: 1 | F17: 1 | G17: =C17-F17 -> 0 | H17: =F17-E17 -> 0 | I17: =H17/E17 -> 0 | L17: =F17/C17 -> 1
A18: B2.33 71 19.01 | B18: 6 way 50mm HDPE Pipe | C18: 6424 | D18: m | E18: 5562 | F18: 6424 | G18: =C18-F18 -> 0 | H18: =F18-E18 -> 862 | I18: =H18/E18 -> 0.15498022 | L18: =F18/C18 -> 1 | V18: 6424
A19: B2.33 71 19.01.01 | B19: 2 x 32 mm diameter HDPE ducts | C19: 4604 | D19: m | E19: 3835 | F19: 4604 | G19: =C19-F19 -> 0 | H19: =F19-E19 -> 769 | I19: =H19/E19 -> 0.20052151 | L19: =F19/C19 -> 1 | V19: 4604
A20: B3.33 14 13.01 | B20: HDPE for Potable water | C20: 4025 | D20: m | E20: 3864 | F20: 4025 | G20: =C20-F20 -> 0 | H20: =F20-E20 -> 161 | I20: =H20/E20 -> 0.041666667 | L20: =F20/C20 -> 1
A21: B4.33 31 00.01 | B21: HDPE for TSE Network | C21: 4209 | D21: m | E21: 4209 | F21: 4209 | G21: =C21-F21 -> 0 | H21: =F21-E21 -> 0 | I21: =H21/E21 -> 0 | L21: =F21/C21 -> 1
A22: B4.31 05 05.13 | B22: valves | C22: 77 | D22: nr | E22: 77 | F22: 77 | G22: =C22-F22 -> 0 | H22: =F22-E22 -> 0 | I22: =H22/E22 -> 0 | L22: =F22/C22 -> 1
A23: B5.33 31 00.01 | B23: GRP for Sewerage Network | C23: 2735 | D23: m | E23: 2735 | F23: 2735 | G23: =C23-F23 -> 0 | H23: =F23-E23 -> 0 | I23: =H23/E23 -> 0 | L23: =F23/C23 -> 1
A24: B5.33 05 13.01 | B24: Manholes Sewerage Network | C24: 45 | D24: nr | E24: 45 | F24: 45 | G24: =C24-F24 -> 0 | H24: =F24-E24 -> 0 | I24: =H24/E24 -> 0 | L24: =F24/C24 -> 1
A25: B6.33 42 11.01 | B25: GRP for Storm Water Drainage | C25: 3971 | D25: m | E25: 3971 | F25: 3971 | G25: =C25-F25 -> 0 | H25: =F25-E25 -> 0 | I25: =H25/E25 -> 0 | L25: =F25/C25 -> 1
A26: B6.33 05 39.01 | B26: Manholes Storm Water Drainage | C26: 42 | D26: nr | E26: 42 | F26: 42 | G26: =C26-F26 -> 0 | H26: =F26-E26 -> 0 | I26: =H26/E26 -> 0 | L26: =F26/C26 -> 1
A27: B6.33 05 39.01 | B27: Catch basin | C27: 77 | D27: nr | E27: 77 | F27: 77 | G27: =C27-F27 -> 0 | H27: =F27-E27 -> 0 | I27: =H27/E27 -> 0 | L27: =F27/C27 -> 1
A28: B7.15.1.1 | B28: Submersible pump IP68, with the following requirements, as minimum: Capacity : 70 l/s Head : 18 m Free passage: ≥80 mm Pump efficiency at duty point: ≥ 70% Pump speed: 1800 rpm Factory test: according to ISO 9906, Grade 2B Motor efficiency & power factor at full load: ≥ 90% & ≥ 0.8 | C28: 2 | D28: nr | E28: 0 | F28: 0 | G28: =C28-F28 -> 2 | H28: =F28-E28 -> 0 | I28: =H28/E28 -> #DIV/0! | L28: =F28/C28 -> 0
A29: B7.15.8.1 | B29: Odors scrubbing system (fan capacity not less than 2300 cubic meter/hour) | C29: 1 | D29: set | E29: 1 | F29: 1 | G29: =C29-F29 -> 0 | H29: =F29-E29 -> 0 | I29: =H29/E29 -> 0 | L29: =F29/C29 -> 1
A30: B7.15.9.1 | B30: Manually operated davit crane (portable), 1 ton capacity. | C30: 1 | D30: nr | E30: 0 | F30: 1 | G30: =C30-F30 -> 0 | H30: =F30-E30 -> 1 | I30: =H30/E30 -> #DIV/0! | L30: =F30/C30 -> 1
A31: B7.15.14.2.1 | B31: As per requirements of water hammer study which is approved by Engineer, supply, install, test and commissioning for all necessary items to protect pumps, force main and all piping system against this phenomenon and according to standard specifications and Engineer instructions, the contractor shall review the present study for water hammer protection system (included in project documents) and submit a new study for water hammer protection system (based on actual pump and equipment characteristics), including the calculations and all proposed equipment, while maintaining the equipment in the present study as much as possible. The study shall be submitted to the Engineer for approval.. Price includes all civil, mechanical, electrical, and control works to complete this item. | C31: 1 | D31: lot | E31: 0 | F31: 1 | G31: =C31-F31 -> 0 | H31: =F31-E31 -> 1 | I31: =H31/E31 -> #DIV/0! | L31: =F31/C31 -> 1
... A44: B7.16.17.1 | B44: Supply, installation, testing and commissioning of PLC system, serving the pumping station and all related utilities. The PLC shall consists but limited to the following: NEMA 4X type Cabinet (800mm x 1200mm x 600mm) including RTU , PLC I/O interface modules , Digital I/P modules , Digital O/P Modules , Analogue I/P Modules , Analogue O/P modules, RTD I/P , Analogue Hart I/P Modules, communication modules, power supply modules, Terminal Blocks with cover , Dual redundant hot standby CPU 64-bit microprocessor with 64-bit internal & external bus equipped with at least 32MB RAM and at least 32MB Flash memory , programming software,HMI 9" screen, panel (2000*1200*800 mm), trunking, terminal strips, relays, circuit breakers, electronic thermo- hygrometer, fans, LED Lamp, media converters, patch panel, industrial ethernet managed switch for connection to SCADA control room ( connection is not in scope) , GSM/4G MODEM ready for connection with GSM/4G antenna, over residual current device (2P 25A/300mA) , surge protection 24VDC and all modules as shown on drawings and all necessary items including interfaces with the electrical systems factory panels and instrumentation sensors/transmitters, to deliver a complete and integrated system, and to cater for this phase and all future phases, all as per specifications and design drawings ; all materials should be SASO certified. | C44: 1 | D44: item | E44: 0 | F44: 0 | G44: =C44-F44 -> 1 | H44: =F44-E44 -> 0 | I44: =H44/E44 -> #DIV/0! | L44: =F44/C44 -> 0
G45: =C45-F45 -> 0 | H45: =F45-E45 -> 0 | I45: =H45/E45 -> #DIV/0! | L45: =F45/C45 -> #DIV/0!
G46: =C46-F46 -> 0 | H46: =F46-E46 -> 0 | I46: =H46/E46 -> #DIV/0! | L46: =F46/C46 -> #DIV/0!
G47: =C47-F47 -> 0 | H47: =F47-E47 -> 0 | I47: =H47/E47 -> #DIV/0! | L47: =F47/C47 -> #DIV/0!
G48: =C48-F48 -> 0 | H48: =F48-E48 -> 0 | I48: =H48/E48 -> #DIV/0! | L48: =F48/C48 -> #DIV/0!
G49: =C49-F49 -> 0 | H49: =F49-E49 -> 0 | I49: =H49/E49 -> #DIV/0! | L49: =F49/C49 -> #DIV/0!
G50: =C50-F50 -> 0 | H50: =F50-E50 -> 0 | I50: =H50/E50 -> #DIV/0! | L50: =F50/C50 -> #DIV/0!
G51: =C51-F51 -> 0 | H51: =F51-E51 -> 0 | I51: =H51/E51 -> #DIV/0! | L51: =F51/C51 -> #DIV/0!
G52: =C52-F52 -> 0 | H52: =F52-E52 -> 0 | I52: =H52/E52 -> #DIV/0! | L52: =F52/C52 -> #DIV/0!
J57: 46349
J58: 45985 | K58: =J57-J58+1 -> 365
J59: 46196 | K59: =J57-J59+1 -> 154
K60: =K59/K58 -> 0.42191781

Sheet CCO
A1: CONTRACT CHANGE ORDER (CCO)
A2: CCO No. | B2: Date Added | C2: Description of Change | D2: Status | E2: SR | F2: Sch Impact (Months) | G2: Date Approved | H2: Duration (days)

Sheet Issue 
A1: Issue Log
A4: Issue ID | B4: Parent Project ID | C4: Contract / Project ID | D4: Project Name | E4: City | F4: Region | G4: Fund Source | H4: Phase | I4: PM / Owner | J4: Contractor / Designer | K4: Current Status | L4: Value (SAR) | M4: Category | N4: Issue Title | O4: Description | P4: Evidence / Data | Q4: Severity (1-5) | R4: Urgency (1-5) | S4: Priority Score | T4: Priority | U4: Action Required | V4: Date Raised | W4: Status | X4: Target Date | Y4: Resolution / Updates | Z4: Source
A5: 1 | C5: JDH4-02-007 | D5: Land Development of Jeddah Oasis | E5: Jeddah | F5: Western | I5: Mohamed Al Shunaifi | J5: AL-ENJAZ Trading & Contracting Company | K5: Work in progress | L5: 65900000 | M5: Scope | N5: Reduction in Scope of Works – Road No. 6 | O5: Reducing the scope of works along Road No. 6, including all utility networks located within this road | Q5: 4 | R5: 4 | S5: =Issuelog[[#This Row],[Severity (1-5)]]*Issuelog[[#This Row],[Urgency (1-5)]] -> 16 | T5: High | U5: Confirm and formally document the reduction in scope along Road No. 6, including the associated utility networks. Obtain approval from the relevant stakeholders and update the scope, BOQ, drawings, programme, and contract documents accordingly. | V5: 45992 | W5: Closed | X5: 46047 | Y5: Issuing a new scope of work to include all ongoing activities covered under the contract
A6: 2 | C6: JDH4-02-007 | D6: Land Development of Jeddah Oasis | E6: Jeddah | F6: Western | I6: Mohamed Al Shunaifi | J6: AL-ENJAZ Trading & Contracting Company | K6: Work in progress | L6: 65900000 | M6: Design/Technical | N6: Missing Rock Protection – Wadi Channel and Box Culvert | O6: Scope of Work for the Proposed Wadi Channel and Box Culvert The proposed scope of work does not include the installation of rock protection at either the upstream or downstream ends to safeguard the soil against erosion resulting from water flow. Furthermore, the revised alignment of the wadi channel does not incorporate any rock protection measures along the direction of the water flow | Q6: 4 | R6: 5 | S6: =Issuelog[[#This Row],[Severity (1-5)]]*Issuelog[[#This Row],[Urgency (1-5)]] -> 20 | T6: High | U6: Review the proposed wadi channel and box culvert design and provide suitable rock protection at the upstream and downstream ends and along the water-flow direction to prevent soil erosion. Obtain the necessary design approval before proceeding with the works. | V6: 46019 | W6: Closed | X6: 46047 | Y6: There is a need to issue a decision regarding the implementation of grouted riprap works along the wadi, as well as at the inlet and outlet of the culvert
A7: 3 | C7: JDH4-02-007 | D7: Land Development of Jeddah Oasis | E7: Jeddah | F7: Western | I7: Mohamed Al Shunaifi | J7: AL-ENJAZ Trading & Contracting Company | K7: Work in progress | L7: 65900000 | M7: Scope | N7: Discrepancy Between Wadi Channel and Box Culvert Width | O7: Cross‑Section of the Wadi Channel The wadi channel has a bottom width of 15 meters and a depth of 2 meters, while the top width reaches 24 meters. According to the flow direction, the proposed box culvert CU‑02, with dimensions (3 × 2 × 1.5), provides a total bottom width of only 6.7 meters. This indicates a significant discrepancy between the width of the wadi channel and the width of the proposed culvert | Q7: 5 | R7: 4 | S7: =Issuelog[[#This Row],[Severity (1-5)]]*Issuelog[[#This Row],[Urgency (1-5)]] -> 20 | T7: High | U7: Conduct a technical/hydraulic review of the proposed CU-02 box culvert against the wadi channel cross-section and design flow requirements. Confirm the adequacy of the culvert dimensions and revise the design if required before construction. | V7: 46019 | W7: Closed | X7: 46021 | Y7: The IFC is followed as shown in the drawings
A8: 4 | C8: JDH4-02-007 | D8: Land Development of Jeddah Oasis | E8: Jeddah | F8: Western | I8: Mohamed Al Shunaifi | J8: AL-ENJAZ Trading & Contracting Company | K8: Work in progress | L8: 65900000 | M8: Scope | N8: Potential Water Leakage and Odour – Existing Underpasses | O8: In accordance with the scope of work for the existing underpasses—which includes the removal of portions of the side walls (upstream and downstream), the installation of retaining walls at the inlet and outlet, and the construction of a concrete slab at the opening of the existing road’s top slab—we would like to inform you of the following: It is anticipated that, in the future, water leakage may occur, along with the emission of unpleasant odors, in addition to the potential emergence of health-related issues as a result of these works | Q8: 3 | R8: 3 | S8: =Issuelog[[#This Row],[Severity (1-5)]]*Issuelog[[#This Row],[Urgency (1-5)]] -> 9 | T8: High | U8: Review the proposed modification works and provide appropriate waterproofing, drainage, and ventilation measures to prevent water leakage, stagnant water, unpleasant odours, and potential health/environmental issues. Obtain consultant/client approval before implementation. | V8: 46019 | W8: Closed | X8: 46047 | Y8: The complete removal of the existing underpass concrete elements, followed by backfilling with selected and properly compacted fill materials in accordance with the approved technical specifications, in preparation for re‑establishing the road level and connecting it to the surrounding network
A9: 5 | C9: JDH4-02-007 | D9: Land Development of Jeddah Oasis | E9: Jeddah | F9: Western | I9: Mohamed Al Shunaifi | J9: AL-ENJAZ Trading & Contracting Company | K9: Work in progress | L9: 65900000 | M9: Quality/HSE | N9: Safety Risk at Deep Openings | O9: Install and maintain hard barriers around all deep openings, enforce strict no-leaning/no-entry rules, conduct regular toolbox talks, ensure continuous supervision, and implement confined space controls if entry is required. | Q9: 4 | R9: 3 | S9: =Issuelog[[#This Row],[Severity (1-5)]]*Issuelog[[#This Row],[Urgency (1-5)]] -> 12 | T9: High | U9: Install and maintain rigid barriers around all deep openings. Enforce no-entry/no-leaning requirements, conduct regular toolbox talks, provide continuous supervision, and implement confined-space controls where applicable. | V9: 46021 | W9: Closed | X9: 46113 | Y9: Provided hard barrications around the excavations, permit is obtained and excavation safety training has been delivered.
A10: 6 | C10: JDH4-02-007 | D10: Land Development of Jeddah Oasis | E10: Jeddah | F10: Western | I10: Mohamed Al Shunaifi | J10: AL-ENJAZ Trading & Contracting Company | K10: Work in progress | L10: 65900000 | M10: Design/Technical | N10: Approval of MV Network Materials and Quantities | O10: Approval of MV network materials and Quantity by SEC & Modon | Q10: 5 | R10: 4 | S10: =Issuelog[[#This Row],[Severity (1-5)]]*Issuelog[[#This Row],[Urgency (1-5)]] -> 20 | T10: High | U10: Obtain formal approval from SEC and MODON for the proposed MV network materials and quantities. Ensure procurement and installation are carried out only in accordance with the approved materials, quantities, specifications, and drawings. | V10: 46077 | W10: Closed | X10: 46142 | Y10: The Modon and SEC to be finalized the issues related to MV network to excuting the work
A11: 7 | C11: JDH4-02-007 | D11: Land Development of Jeddah Oasis | E11: Jeddah | F11: Western | I11: Mohamed Al Shunaifi | J11: AL-ENJAZ Trading & Contracting Company | K11: Work in progress | L11: 65900000 | M11: Quality/HSE | N11: Heat Stress During Peak Working Hours | O11: Enforce mandatory rest breaks during peak heat hours (12:00–15:00), provide shaded rest areas and drinking water, conduct heat stress toolbox talks, monitor workers, and adjust work schedules where necessary. | Q11: 3 | R11: 3 | S11: =Issuelog[[#This Row],[Severity (1-5)]]*Issuelog[[#This Row],[Urgency (1-5)]] -> 9 | T11: Medium | U11: Implement mandatory rest breaks during peak heat hours (12:00–15:00), provide shaded rest areas and sufficient drinking water, conduct heat-stress awareness/toolbox talks, monitor workers, and adjust working hours where required. | V11: 46136 | W11: Closed | X11: 46144 | Y11: Strictly implemented the 3 hour summer break, provided cold drinking water, ORS and suun shades etc and provided fire extinguishers for equipment.
A12: 8 | C12: JDH4-02-007 | D12: Land Development of Jeddah Oasis | E12: Jeddah | F12: Western | I12: Mohamed Al Shunaifi | J12: AL-ENJAZ Trading & Contracting Company | K12: Work in progress | L12: 65900000 | M12: Quality/HSE | N12: Traffic Management and Site Safety Compliance | O12: Strict implementation of approved Traffic Management Plan, use of banksmen, speed limit enforcement (20 km/h), proper barricading, high-visibility clothing, and daily inspection of traffic control measures. | Q12: 3 | R12: 4 | S12: =Issuelog[[#This Row],[Severity (1-5)]]*Issuelog[[#This Row],[Urgency (1-5)]] -> 12 | T12: High | U12: Strictly implement the approved Traffic Management Plan. Provide trained banksmen, enforce the 20 km/h speed limit, maintain proper barricading, ensure high-visibility PPE is worn, and conduct daily inspections of traffic-control arrangements. | V12: 46242 | W12: Closed | X12: 46249 | Y12: Provided flagman and ensured signboards at site and monitoring compliance

Sheet Invoice Log
B1: Weekly Progress Report - Invoice Log | AJ1: Y
B2: Project Value | K2: Payment Status | S2: Invoices Summary | AC2: Average Invoices durations | AJ2: N
B3: Original Contract Value | E3: =Progress!C41 -> 57304348 | G3: O&M Value | I3: 0 | J3: EAC | K3: Advance Payment % | M3: 0 | O3: Advance Payment (SAR) | Q3: =E3*M3 -> 0 | S3: No of Submitted Invoices | U3: =MAX($C$9:$C$46) -> 8 | W3: Submitted Invoices (SAR) | Y3: =SUM(F9:F58)*1.15 -> 40499983 | AA3: Submiited Invoice Peroid | AB3: =MAX(L9:L46) -> 46264 | AC3: CM / PgM Average Approval duration | AE3: =AVERAGE(P9:P58) -> 0.71428571 | AG3: Average Invoice Value | AH3: =AVERAGE(F9:F58) -> 4402172.1
B4: Revised Contract Value | D4: 21100000 | E4: =E3 -> 57304348 | F4: EAC | G4: Revised O&M Value | I4: 0 | J4: =+#REF!+#REF!+I4 -> #REF! | K4: Retention % | M4: 0 | O4: Retention (SAR) | Q4: =E3*M4 -> 0 | S4: No of Approved Invoices (CM) | U4: =COUNTIF($N$9:$N$59,"Y") -> 8 | W4: Approved Invoices (CM) (SAR) | Y4: =SUMIF($N$9:$N$58,"Y",$J$9:$J$58) -> 40499983 | AC4: MODON PM & Accounts Average Approval duration | AE4: =AVERAGE(W9:W58) -> 9.8571429
B5: Estimate At Completion Value | D5: 20900000 | E5: =E4 -> 57304348 | F5: =+#REF!+#REF!+E5 -> #REF! | G5: Submitted Invoices (Gross Value) | I5: 5420855.2 | K5: Penalties and deduction % | M5: =ABS(M6/E3) -> 0 | O5: AP Recovery (SAR) | Q5: =SUM(G9:G58) -> 0 | S5: No of Approved Invoices (PM) | U5: =COUNTIF($R$9:$R$59,"Y") -> 7 | W5: Approved Invoices (PM) (SAR) | Y5: =SUMIF($R$9:$R$58,"Y",$J$9:$J$58) -> 33617268 | AA5: Invoice Submitted Compared to Contract Value | AB5: =Y3/(E4*1.15) -> 0.61456728 | AC5: Payments Average Duration | AE5: =AVERAGE(AA9:AA58) -> 37
B6: Potential Changes | D6: =D4-D5 -> 200000 | E6: =E4-E5 -> 0 | G6: Total Deduction | I6: =M6+Q6+Q5 -> 0 | K6: Penalties and deduction (SAR) | M6: =SUM(I9:I58) -> 0 | O6: Retention Cumulative (SAR) | Q6: =SUM(H9:H58) -> 0 | S6: No of Paid Invoices | U6: =COUNTA(X9:X58) -> 3 | W6: Paid Invoices (SAR) | Y6: =+Y59 -> 27469389 | AC6: Invoices Average total Duration | AE6: =IFERROR(AVERAGE(AC9:AC58),"") -> 65.333333
B7: Invoice Reference | F7: Invoice Value | K7: Period Covered | M7: CM / PgM Approval Timeline | Q7: Modon PM & Accounts Approval | X7: Payment Status | AC7: Total Invoice Duration | AD7: Remarks
B8: # | C8: Invoice No. | D8: Doc Control reference | E8: Submittal Rev. # | F8: Gross Value | G8: AP Recovery | H8: Retention | I8: Deduction / Penalties | J8: Amount (net) + VAT 15% | K8: Start Date | L8: End Date | M8: Date to CM / PgM | N8: CM / PgM Approval (Yes/No) | O8: CM / PgM Reply Date | P8: Days Elapsed | Q8: Date to PM | R8: PM Approval (Yes/No) | S8: PM Reply Date | T8: Date to Accounts | U8: Accounts Approval (Yes/No) | V8: Accounts Approval Date | W8: Days Elapsed | X8: Date Paid | Y8: Amount Paid | Z8: Paid % | AA8: Payment Period (d) | AB8: Amount Pending
B9: 1 | C9: 1 | D9: JDH4-02-007-ENJ-TS9-1-GEN-IPC-0001-00 | E9: 0 | F9: 1746674.4 | G9: =IF(ISBLANK(F9),"",-F9*$M$3*1.15) -> 0 | H9: =IF(ISBLANK(F9),"",-F9*$M$4*1.15) -> 0 | I9: 0 | J9: =IF(ISBLANK(F9),"",SUM(F9:I9)+F9*0.15) -> 2008675.6 | K9: 45985 | L9: 46049 | M9: 46062 | N9: Y | O9: 46063 | P9: =IF(ISBLANK(O9),"",O9-M9) -> 1 | Q9: 46069 | R9: Y | S9: 46069 | T9: =S9+3 -> 46072 | V9: 46092 | W9: =IF(ISBLANK(V9),"",V9-Q9) -> 23 | X9: 46149 | Y9: 2008675.6 | Z9: =IF(ISBLANK(Y9),"",Y9/J9) -> 1 | AA9: =IF(ISBLANK(X9),"",X9-V9) -> 57 | AB9: =IF(ISBLANK(Y9),"",(J9-Y9)) -> 0 | AC9: =IF(ISBLANK(X9),"",X9-M9) -> 87
B10: 2 | C10: 2 | D10: JDH4-02-007-ENJ-TS9-1-GEN-IPC-0002-01 | E10: 1 | F10: 3674180.7 | G10: =IF(ISBLANK(F10),"",-F10*$M$3*1.15) -> 0 | H10: =IF(ISBLANK(F10),"",-F10*$M$4*1.15) -> 0 | J10: =IF(ISBLANK(F10),"",SUM(F10:I10)+F10*0.15) -> 4225307.8 | K10: =L9+1 -> 46050 | L10: 46079 | M10: 46085 | N10: Y | O10: 46086 | P10: =IF(ISBLANK(O10),"",O10-M10) -> 1 | Q10: 46102 | R10: Y | S10: 46102 | T10: =S10+3 -> 46105 | V10: 46114 | W10: =IF(ISBLANK(V10),"",V10-Q10) -> 12 | X10: 46149 | Y10: 4225307.8 | Z10: =IF(ISBLANK(Y10),"",Y10/J10) -> 1 | AA10: =IF(ISBLANK(X10),"",X10-V10) -> 35 | AB10: =IF(ISBLANK(Y10),"",(J10-Y10)) -> 0 | AC10: =IF(ISBLANK(X10),"",X10-M10) -> 64
B11: 3 | C11: 3 | D11: JDH4-02-007-ENJ-TS9-1-GEN-IPC-0003-01 | E11: 1 | F11: 6206943.3 | G11: =IF(ISBLANK(F11),"",-F11*$M$3*1.15) -> 0 | H11: =IF(ISBLANK(F11),"",-F11*$M$4*1.15) -> 0 | J11: =IF(ISBLANK(F11),"",SUM(F11:I11)+F11*0.15) -> 7137984.7 | K11: =L10+1 -> 46080 | L11: 46131 | M11: 46131 | N11: Y | O11: 46132 | P11: =IF(ISBLANK(O11),"",O11-M11) -> 1 | Q11: 46147 | R11: Y | S11: 46147 | T11: =S11+3 -> 46150 | V11: 46157 | W11: =IF(ISBLANK(V11),"",V11-Q11) -> 10 | X11: 46176 | Y11: 7137984.7 | Z11: =IF(ISBLANK(Y11),"",Y11/J11) -> 1 | AA11: =IF(ISBLANK(X11),"",X11-V11) -> 19 | AB11: =IF(ISBLANK(Y11),"",(J11-Y11)) -> 0.0089999996 | AC11: =IF(ISBLANK(X11),"",X11-M11) -> 45
B12: 4 | C12: 4 | D12: JDH4-02-007-ENJ-TS9-1-GEN-IPC-0004-01 | E12: 1 | F12: 4258632.4 | G12: =IF(ISBLANK(F12),"",-F12*$M$3*1.15) -> 0 | H12: =IF(ISBLANK(F12),"",-F12*$M$4*1.15) -> 0 | J12: =IF(ISBLANK(F12),"",SUM(F12:I12)+F12*0.15) -> 4897427.3 | K12: =L11+1 -> 46132 | L12: 46155 | M12: 46155 | N12: Y | O12: 46156 | P12: =IF(ISBLANK(O12),"",O12-M12) -> 1 | Q12: 46156 | R12: Y | S12: 46156 | T12: =S12+3 -> 46159 | V12: =T12+3 -> 46162 | W12: =IF(ISBLANK(V12),"",V12-Q12) -> 6 | Y12: =J12 -> 4897427.3 | Z12: =IF(ISBLANK(Y12),"",Y12/J12) -> 1 | AA12: =IF(ISBLANK(X12),"",X12-V12) | AB12: =IF(ISBLANK(Y12),"",(J12-Y12)) -> 0 | AC12: =IF(ISBLANK(X12),"",X12-M12)
B13: 5 | C13: 5 | D13: JDH4-02-007-ENJ-TS9-1-GEN-IPC-0005-00 | E13: 0 | F13: 2976928.8 | G13: =IF(ISBLANK(F13),"",-F13*$M$3*1.15) -> 0 | H13: =IF(ISBLANK(F13),"",-F13*$M$4*1.15) -> 0 | J13: =IF(ISBLANK(F13),"",SUM(F13:I13)+F13*0.15) -> 3423468.1 | K13: =L12+1 -> 46156 | L13: 46184 | M13: 46184 | N13: Y | O13: 46184 | P13: =IF(ISBLANK(O13),"",O13-M13) -> 0 | Q13: 46184 | R13: Y | S13: 46184 | T13: =S13+3 -> 46187 | V13: =T13+3 -> 46190 | W13: =IF(ISBLANK(V13),"",V13-Q13) -> 6 | Y13: =J13 -> 3423468.1 | Z13: =IF(ISBLANK(Y13),"",Y13/J13) -> 1 | AA13: =IF(ISBLANK(X13),"",X13-V13) | AB13: =IF(ISBLANK(Y13),"",(J13-Y13)) -> 0 | AC13: =IF(ISBLANK(X13),"",X13-M13)
B14: 6 | C14: 6 | D14: JDH4-02-007-ENJ-TS9-1-GEN-IPC-0006-00 | E14: 0 | F14: 5023065.2 | G14: =IF(ISBLANK(F14),"",-F14*$M$3*1.15) -> 0 | H14: =IF(ISBLANK(F14),"",-F14*$M$4*1.15) -> 0 | J14: =IF(ISBLANK(F14),"",SUM(F14:I14)+F14*0.15) -> 5776525 | K14: =L13+1 -> 46185 | L14: 46207 | M14: 46207 | N14: Y | O14: 46208 | P14: =IF(ISBLANK(O14),"",O14-M14) -> 1 | Q14: 46208 | R14: Y | S14: 46208 | T14: =S14+3 -> 46211 | V14: =T14+3 -> 46214 | W14: =IF(ISBLANK(V14),"",V14-Q14) -> 6 | Y14: =J14 -> 5776525 | Z14: =IF(ISBLANK(Y14),"",Y14/J14) -> 1 | AA14: =IF(ISBLANK(X14),"",X14-V14) | AB14: =IF(ISBLANK(Y14),"",(J14-Y14)) -> 0 | AC14: =IF(ISBLANK(X14),"",X14-M14)
B15: 7 | C15: 7 | D15: JDH4-02-007-ENJ-TS9-1-GEN-IPC-0007-00 | E15: 0 | F15: 5345982.5 | G15: =IF(ISBLANK(F15),"",-F15*$M$3*1.15) -> 0 | H15: =IF(ISBLANK(F15),"",-F15*$M$4) -> 0 | J15: =IF(ISBLANK(F15),"",SUM(F15:I15)+F15*0.15) -> 6147879.8 | K15: =L14+1 -> 46208 | L15: 46226 | M15: 46226 | N15: Y | O15: 46226 | P15: =IF(ISBLANK(O15),"",O15-M15) -> 0 | Q15: 46226 | R15: Y | S15: 46226 | T15: =S15+3 -> 46229 | V15: =T15+3 -> 46232 | W15: =IF(ISBLANK(V15),"",V15-Q15) -> 6 | Z15: =IF(ISBLANK(Y15),"",Y15/J15) | AA15: =IF(ISBLANK(X15),"",X15-V15) | AB15: =IF(ISBLANK(Y15),"",(J15-Y15)) | AC15: =IF(ISBLANK(X15),"",X15-M15)
B16: 8 | C16: 8 | D16: JDH4-02-007-ENJ-TS9-1-GEN-IPC-0008-00 | E16: 0 | F16: 5984969.5 | G16: =IF(ISBLANK(F16),"",-F16*$M$3*1.15) -> 0 | H16: =IF(ISBLANK(F16),"",-F16*$M$4) -> 0 | J16: =IF(ISBLANK(F16),"",SUM(F16:I16)+F16*0.15) -> 6882715 | K16: 46227 | L16: 46264 | M16: 46264 | N16: Y | P16: =IF(ISBLANK(O16),"",O16-M16) | W16: =IF(ISBLANK(V16),"",V16-Q16) | Z16: =IF(ISBLANK(Y16),"",Y16/J16) | AA16: =IF(ISBLANK(X16),"",X16-V16) | AB16: =IF(ISBLANK(Y16),"",(J16-Y16)) | AC16: =IF(ISBLANK(X16),"",X16-M16)
B17: 9 | G17: =IF(ISBLANK(F17),"",-F17*$M$3*1.15) | H17: =IF(ISBLANK(F17),"",-F17*$M$4) | J17: =IF(ISBLANK(F17),"",SUM(F17:I17)+F17*0.15) | P17: =IF(ISBLANK(O17),"",O17-M17) | W17: =IF(ISBLANK(V17),"",V17-Q17) | Z17: =IF(ISBLANK(Y17),"",Y17/J17) | AA17: =IF(ISBLANK(X17),"",X17-V17) | AB17: =IF(ISBLANK(Y17),"",(J17-Y17)) | AC17: =IF(ISBLANK(X17),"",X17-M17)
B18: 10 | G18: =IF(ISBLANK(F18),"",-F18*$M$3*1.15) | H18: =IF(ISBLANK(F18),"",-F18*$M$4) | J18: =IF(ISBLANK(F18),"",SUM(F18:I18)+F18*0.15) | P18: =IF(ISBLANK(O18),"",O18-M18) | W18: =IF(ISBLANK(V18),"",V18-Q18) | Z18: =IF(ISBLANK(Y18),"",Y18/J18) | AA18: =IF(ISBLANK(X18),"",X18-V18) | AB18: =IF(ISBLANK(Y18),"",(J18-Y18)) | AC18: =IF(ISBLANK(X18),"",X18-M18)
B19: 11 | G19: =IF(ISBLANK(F19),"",-F19*$M$3*1.15) | H19: =IF(ISBLANK(F19),"",-F19*$M$4) | J19: =IF(ISBLANK(F19),"",SUM(F19:I19)+F19*0.15) | P19: =IF(ISBLANK(O19),"",O19-M19) | W19: =IF(ISBLANK(V19),"",V19-Q19) | Z19: =IF(ISBLANK(Y19),"",Y19/J19) | AA19: =IF(ISBLANK(X19),"",X19-V19) | AB19: =IF(ISBLANK(Y19),"",(J19-Y19)) | AC19: =IF(ISBLANK(X19),"",X19-M19)
B20: 12 | G20: =IF(ISBLANK(F20),"",-F20*$M$3*1.15) | H20: =IF(ISBLANK(F20),"",-F20*$M$4) | J20: =IF(ISBLANK(F20),"",SUM(F20:I20)+F20*0.15) | P20: =IF(ISBLANK(O20),"",O20-M20) | W20: =IF(ISBLANK(V20),"",V20-Q20) | Z20: =IF(ISBLANK(Y20),"",Y20/J20) | AA20: =IF(ISBLANK(X20),"",X20-V20) | AB20: =IF(ISBLANK(Y20),"",(J20-Y20)) | AC20: =IF(ISBLANK(X20),"",X20-M20)
B21: 13 | G21: =IF(ISBLANK(F21),"",-F21*$M$3*1.15) | H21: =IF(ISBLANK(F21),"",-F21*$M$4) | J21: =IF(ISBLANK(F21),"",SUM(F21:I21)+F21*0.15) | P21: =IF(ISBLANK(O21),"",O21-M21) | W21: =IF(ISBLANK(V21),"",V21-Q21) | Z21: =IF(ISBLANK(Y21),"",Y21/J21) | AA21: =IF(ISBLANK(X21),"",X21-V21) | AB21: =IF(ISBLANK(Y21),"",(J21-Y21)) | AC21: =IF(ISBLANK(X21),"",X21-M21)
B22: 14 | G22: =IF(ISBLANK(F22),"",-F22*$M$3*1.15) | H22: =IF(ISBLANK(F22),"",-F22*$M$4) | J22: =IF(ISBLANK(F22),"",SUM(F22:I22)+F22*0.15) | P22: =IF(ISBLANK(O22),"",O22-M22) | W22: =IF(ISBLANK(V22),"",V22-Q22) | Z22: =IF(ISBLANK(Y22),"",Y22/J22) | AA22: =IF(ISBLANK(X22),"",X22-V22) | AB22: =IF(ISBLANK(Y22),"",(J22-Y22)) | AC22: =IF(ISBLANK(X22),"",X22-M22)
B23: 15 | G23: =IF(ISBLANK(F23),"",-F23*$M$3*1.15) | H23: =IF(ISBLANK(F23),"",-F23*$M$4) | J23: =IF(ISBLANK(F23),"",SUM(F23:I23)+F23*0.15) | P23: =IF(ISBLANK(O23),"",O23-M23) | W23: =IF(ISBLANK(V23),"",V23-Q23) | Z23: =IF(ISBLANK(Y23),"",Y23/J23) | AA23: =IF(ISBLANK(X23),"",X23-V23) | AB23: =IF(ISBLANK(Y23),"",(J23-Y23)) | AC23: =IF(ISBLANK(X23),"",X23-M23)
B24: 16 | G24: =IF(ISBLANK(F24),"",-F24*$M$3*1.15) | H24: =IF(ISBLANK(F24),"",-F24*$M$4) | J24: =IF(ISBLANK(F24),"",SUM(F24:I24)+F24*0.15) | P24: =IF(ISBLANK(O24),"",O24-M24) | W24: =IF(ISBLANK(V24),"",V24-Q24) | Z24: =IF(ISBLANK(Y24),"",Y24/J24) | AA24: =IF(ISBLANK(X24),"",X24-V24) | AB24: =IF(ISBLANK(Y24),"",(J24-Y24)) | AC24: =IF(ISBLANK(X24),"",X24-M24)
B25: 17 | G25: =IF(ISBLANK(F25),"",-F25*$M$3*1.15) | H25: =IF(ISBLANK(F25),"",-F25*$M$4) | J25: =IF(ISBLANK(F25),"",SUM(F25:I25)+F25*0.15) | P25: =IF(ISBLANK(O25),"",O25-M25) | W25: =IF(ISBLANK(V25),"",V25-Q25) | Z25: =IF(ISBLANK(Y25),"",Y25/J25) | AA25: =IF(ISBLANK(X25),"",X25-V25) | AB25: =IF(ISBLANK(Y25),"",(J25-Y25)) | AC25: =IF(ISBLANK(X25),"",X25-M25)
B26: 18 | G26: =IF(ISBLANK(F26),"",-F26*$M$3*1.15) | H26: =IF(ISBLANK(F26),"",-F26*$M$4) | J26: =IF(ISBLANK(F26),"",SUM(F26:I26)+F26*0.15) | P26: =IF(ISBLANK(O26),"",O26-M26) | W26: =IF(ISBLANK(V26),"",V26-Q26) | Z26: =IF(ISBLANK(Y26),"",Y26/J26) | AA26: =IF(ISBLANK(X26),"",X26-V26) | AB26: =IF(ISBLANK(Y26),"",(J26-Y26)) | AC26: =IF(ISBLANK(X26),"",X26-M26)
B27: 19 | G27: =IF(ISBLANK(F27),"",-F27*$M$3*1.15) | H27: =IF(ISBLANK(F27),"",-F27*$M$4) | J27: =IF(ISBLANK(F27),"",SUM(F27:I27)+F27*0.15) | P27: =IF(ISBLANK(O27),"",O27-M27) | W27: =IF(ISBLANK(V27),"",V27-Q27) | Z27: =IF(ISBLANK(Y27),"",Y27/J27) | AA27: =IF(ISBLANK(X27),"",X27-V27) | AB27: =IF(ISBLANK(Y27),"",(J27-Y27)) | AC27: =IF(ISBLANK(X27),"",X27-M27)
B28: 20 | G28: =IF(ISBLANK(F28),"",-F28*$M$3*1.15) | H28: =IF(ISBLANK(F28),"",-F28*$M$4) | J28: =IF(ISBLANK(F28),"",SUM(F28:I28)+F28*0.15) | P28: =IF(ISBLANK(O28),"",O28-M28) | W28: =IF(ISBLANK(V28),"",V28-Q28) | Z28: =IF(ISBLANK(Y28),"",Y28/J28) | AA28: =IF(ISBLANK(X28),"",X28-V28) | AB28: =IF(ISBLANK(Y28),"",(J28-Y28)) | AC28: =IF(ISBLANK(X28),"",X28-M28)
... B35: 27 | G35: =IF(ISBLANK(F35),"",-F35*$M$3*1.15) | H35: =IF(ISBLANK(F35),"",-F35*$M$4) | J35: =IF(ISBLANK(F35),"",SUM(F35:I35)+F35*0.15) | P35: =IF(ISBLANK(O35),"",O35-M35) | W35: =IF(ISBLANK(V35),"",V35-Q35) | Z35: =IF(ISBLANK(Y35),"",Y35/J35) | AA35: =IF(ISBLANK(X35),"",X35-V35) | AB35: =IF(ISBLANK(Y35),"",(J35-Y35)) | AC35: =IF(ISBLANK(X35),"",X35-M35)
B36: 28 | G36: =IF(ISBLANK(F36),"",-F36*$M$3*1.15) | H36: =IF(ISBLANK(F36),"",-F36*$M$4) | J36: =IF(ISBLANK(F36),"",SUM(F36:I36)+F36*0.15) | P36: =IF(ISBLANK(O36),"",O36-M36) | W36: =IF(ISBLANK(V36),"",V36-Q36) | Z36: =IF(ISBLANK(Y36),"",Y36/F36) | AA36: =IF(ISBLANK(X36),"",X36-V36) | AB36: =IF(ISBLANK(Y36),"",(J36-Y36)) | AC36: =IF(ISBLANK(X36),"",X36-M36)
B37: 29 | G37: =IF(ISBLANK(F37),"",-F37*$M$3*1.15) | H37: =IF(ISBLANK(F37),"",-F37*$M$4) | J37: =IF(ISBLANK(F37),"",SUM(F37:I37)+F37*0.15) | P37: =IF(ISBLANK(O37),"",O37-M37) | W37: =IF(ISBLANK(V37),"",V37-Q37) | Z37: =IF(ISBLANK(Y37),"",Y37/F37) | AA37: =IF(ISBLANK(X37),"",X37-V37) | AB37: =IF(ISBLANK(Y37),"",(J37-Y37)) | AC37: =IF(ISBLANK(X37),"",X37-M37)
B38: 30 | G38: =IF(ISBLANK(F38),"",-F38*$M$3*1.15) | H38: =IF(ISBLANK(F38),"",-F38*$M$4) | J38: =IF(ISBLANK(F38),"",SUM(F38:I38)+F38*0.15) | P38: =IF(ISBLANK(O38),"",O38-M38) | W38: =IF(ISBLANK(V38),"",V38-Q38) | Z38: =IF(ISBLANK(Y38),"",Y38/F38) | AA38: =IF(ISBLANK(X38),"",X38-V38) | AB38: =IF(ISBLANK(Y38),"",(F38-Y38)) | AC38: =IF(ISBLANK(X38),"",X38-M38)
