Workbook
Name _1B.05.M.010.0010: #REF!
Name _1B.05.M.010.0010: #REF!
Name _1B.05.M.010.0050: #REF!
Name _1B.05.M.010.0050: #REF!
Name _1B.05.M.0100.0010: #REF!
Name _1B.05.M.020.0010: #REF!
Name _1B.05.M.020.0020: #REF!
Name _1B.05.M.020.0030: #REF!
Name _1B.05.M.020.0040: #REF!
Name _1B.05.M.030.0010: #REF!
Name _1B.05.M.030.0020: #REF!
Name _1B.05.M.040.0010: #REF!
Name _1B.05.M.050.0010: #REF!
Name _1B.05.M.050.0020: #REF!
Name _1B.05.M.050.0030: #REF!
Name _1B.05.M.060.0020: #REF!
Name _1B.05.M.060.0100: #REF!
Name _1B.05.M.070.0010: #REF!
Name _1B.05.M.070.0020: #REF!
Name _1B.05.M.070.0030: #REF!
Name _1B.05.M.070.0040: #REF!
Name _1B.05.M.070.0050: #REF!
Name _1B.05.M.080.0010: #REF!
Name _1B.05.M.090.0010: #REF!
Name _1B.09.P.010.0010: #REF!
Name _1B.09.P.010.0020: #REF!
Name _1B.09.P.010.0030: #REF!
Name _1B.09.P.010.0040: #REF!
Name _1B.09.P.010.0050: #REF!
Name _1B.09.P.010.0060: #REF!
Name _1B.09.P.010.0070: #REF!
Name _1B.09.P.020.0010: #REF!
Name _1B.09.P.020.0020: #REF!
Name _1B.09.P.020.0030: #REF!
Name _1B.09.P.020.0040: #REF!
Name _1B.09.P.020.0050: #REF!
Name _1B.09.P.020.0060: #REF!
Name _1B.09.P.020.0070: #REF!
Name _1B.09.P.020.0080: #REF!
Name _1B.09.P.020.0090: #REF!
Name _1B.09.P.020.0100: #REF!
Name _1B.09.P.020.0110: #REF!
Name _1B.09.P.020.0120: #REF!
Name _1B.09.P.020.0130: #REF!
Name _1B.09.P.020.0140: #REF!
Name _1B.09.P.020.0150: #REF!
Name _1B.09.P.030.0010: #REF!
Name _1B.09.P.030.0020: #REF!
Name _1B.09.P.030.0030: #REF!
Name _1B.09.P.030.0040: #REF!
Name _1B.09.P.030.0050: #REF!
Name _1B.09.P.030.0060: #REF!
Name _1B.09.P.040.0010: #REF!
Name _1B.09.P.040.0020: #REF!
Name _1B.09.P.040.0030: #REF!
Name _1B.09.P.050.0010: #REF!
Name _1B.09.P.050.0020: #REF!
Name _1B.09.P.060.0010: #REF!
Name _1B.09.P.060.0020: #REF!
Name _1B.09.P.060.0030: #REF!

Sheet DB
A1: ='Weekly Progress Report'!#REF! -> #REF!
B2: ='Weekly Progress Report'!#REF! -> #REF! | J2: ='Weekly Progress Report'!F2 -> Key Dates | U2: ='Weekly Progress Report'!$L$2 -> Cost Summary (SR) | AD2: ='Weekly Progress Report'!$T$2 -> Performance Summary | AP2: ='Weekly Progress Report'!#REF! -> #REF! | AT2: ='Weekly Progress Report'!#REF! -> #REF! | AW2: ='Weekly Progress Report'!#REF! -> #REF! | BD2: ='Weekly Progress Report'!K51 -> Quality Reports | BT2: ='Weekly Progress Report'!K59 -> Key Submittals Approval Status | CD2: ='Weekly Progress Report'!K65 -> Invoices Summary | CR2: ='Weekly Progress Report'!K73 -> Resources at Site | CY2: ='Weekly Progress Report'!V51 -> Safety Statistics | FK2: ='Weekly Progress Report'!#REF! -> #REF! | FS2: ='Weekly Progress Report'!#REF! -> #REF!
A3: ='Weekly Progress Report'!AE1 -> Data Date | B3: ='Weekly Progress Report'!#REF! -> #REF! | C3: ='Weekly Progress Report'!#REF! -> #REF! | D3: ='Weekly Progress Report'!#REF! -> #REF! | E3: ='Weekly Progress Report'!#REF! -> #REF! | F3: ='Weekly Progress Report'!C4 -> Stage | G3: ='Weekly Progress Report'!C5 -> Status | H3: ='Weekly Progress Report'!C6 -> Modon PM | I3: ='Weekly Progress Report'!Z2 -> Project Scope | J3: ='Weekly Progress Report'!F3 -> Contract Award | K3: ='Weekly Progress Report'!F4 -> Contract Sign | L3: ='Weekly Progress Report'!F5 -> Site Handover | M3: ='Weekly Progress Report'!F6 -> Original Completion | N3: ='Weekly Progress Report'!$H$3 -> Contract Award (Hijri) | O3: ='Weekly Progress Report'!$H$4 -> Contract Sign (Hijri) | P3: ='Weekly Progress Report'!$H$5 -> Site Handover (Hijri) | Q3: ='Weekly Progress Report'!$H$6 -> Original Completion (Hijri) | R3: ='Weekly Progress Report'!$J$3 -> Revised Completion | S3: ='Weekly Progress Report'!$J$4 -> Committed Completion | T3: ='Weekly Progress Report'!$J$5 -> Forecast Completion | U3: ='Weekly Progress Report'!$L$3 -> Original Contract Value | V3: ='Weekly Progress Report'!$L$4 -> Revised Contract Value | W3: ='Weekly Progress Report'!$L$5 -> Estimate At Completion Value | X3: ='Weekly Progress Report'!$L$6 -> Potential Changes | Y3: ='Weekly Progress Report'!$P$3 -> O&M Value (if any) | Z3: ='Weekly Progress Report'!$P$4 -> Submitted Invoices (Gross Value) | AA3: ='Weekly Progress Report'!$P$5 -> Penalities | AB3: ='Weekly Progress Report'!$P$6 -> FIR Value (Todate) | AC3: Original Plan Value | AD3: ='Weekly Progress Report'!$T$3 -> Plan Value | AE3: ='Weekly Progress Report'!$T$4 -> Earn Value | AF3: ='Weekly Progress Report'!$V$3 -> Phys. Plan Value | AG3: ='Weekly Progress Report'!$V$4 -> Phys. Earn Value | AH3: ='Weekly Progress Report'!$X$3 -> Quality Score | AI3: ='Weekly Progress Report'!$X$5 -> Safety Score | AJ3: Weekly PV (SAR) | AK3: Weekly EV (SAR) | AL3: Weekly PV % | AM3: Weekly PV % | AN3: Weekly Phys PV% | AO3: Weekly Phys PV% | AP3: Total SD Planned | AQ3: SD Remaining | AR3: SD Pending | AS3: Total SD Submittals | AT3: Planned Materials Approv | AU3: Material Pending Approval | AV3: Materila Total Submittals | AW3: ='Weekly Progress Report'!B70 -> Total Materials | AX3: ='Weekly Progress Report'!C70 -> Total Number of P.O. | AY3: ='Weekly Progress Report'!D70 -> Actual P.O. To Date | AZ3: ='Weekly Progress Report'!E70 -> Remaining P.O | BA3: ='Weekly Progress Report'!F70 -> Material on Site | BB3: ='Weekly Progress Report'!G70 -> Remaining Materials | BC3: ='Weekly Progress Report'!H70 -> Material Delivery Completion (Date) | BD3: ="NCR "&'Weekly Progress Report'!M52 -> NCR Issued | BE3: ="NCR "&'Weekly Progress Report'!N52 -> NCR Closed | BF3: ="NCR "&'Weekly Progress Report'!O52 -> NCR Pending | BG3: ="NCR "&'Weekly Progress Report'!P52 -> NCR Avg. Closing (Days) | BH3: ="SIR "&'Weekly Progress Report'!M52 -> SIR Issued | BI3: ="SIR "&'Weekly Progress Report'!N52 -> SIR Closed | BJ3: ="SIR "&'Weekly Progress Report'!O52 -> SIR Pending | BK3: ="SIR "&'Weekly Progress Report'!P52 -> SIR Avg. Closing (Days) | BL3: ="MIR "&'Weekly Progress Report'!M52 -> MIR Issued | BM3: ="MIR "&'Weekly Progress Report'!N52 -> MIR Closed | BN3: ="MIR "&'Weekly Progress Report'!O52 -> MIR Pending | BO3: ="MIR "&'Weekly Progress Report'!P52 -> MIR Avg. Closing (Days) | BP3: ="FIR "&'Weekly Progress Report'!M52 -> FIR Issued | BQ3: ="FIR "&'Weekly Progress Report'!N52 -> FIR Closed | BR3: ="FIR "&'Weekly Progress Report'!O52 -> FIR Pending | BS3: ="FIR "&'Weekly Progress Report'!P52 -> FIR Avg. Closing (Days) | BT3: ='Weekly Progress Report'!K60 -> 1 Quality Plan Approval | BU3: ='Weekly Progress Report'!K61 -> 2 Quality Plan Last Up | BV3: ='Weekly Progress Report'!K62 -> 3 Safety Plan Approval | BW3: ='Weekly Progress Report'!K63 -> 4 Safety Plan Last Up | BX3: ='Weekly Progress Report'!K64 -> 5 Execution Plan Approval | BY3: ='Weekly Progress Report'!P60 -> 6 Baseline Approval | BZ3: ='Weekly Progress Report'!P61 -> 7 No of Approved Version of Schedule | CA3: ='Weekly Progress Report'!P62 -> 8 Last Approved Schedule | CB3: ='Weekly Progress Report'!P63 -> 9 BOQ Approval Date | CC3: ='Weekly Progress Report'!P64 -> 10 No of Approved Version of BOQ | CD3: ='Weekly Progress Report'!K66 -> Total Submitted Invoices | CE3: ='Weekly Progress Report'!K67 -> PM Approved Invoices | CF3: ='Weekly Progress Report'!K68 -> No of Paid Invoices | CG3: ='Weekly Progress Report'!K69 -> No of Pending Invoices | CH3: ='Weekly Progress Report'!K70 -> Advance Payment % | CI3: ='Weekly Progress Report'!K71 -> Retention % | CJ3: ='Weekly Progress Report'!K72 -> Deduction / Penalties % | CK3: ='Weekly Progress Report'!N66 -> Submitted Invoices (SAR) | CL3: ='Weekly Progress Report'!N67 -> PM Approved Invoices (SAR) | CM3: ='Weekly Progress Report'!N68 -> Paid Invoices (SAR) | CN3: ='Weekly Progress Report'!N69 -> Last Submitted Period | CO3: ='Weekly Progress Report'!N70 -> Advance Payment (SAR) | CP3: ='Weekly Progress Report'!N71 -> Retention (SAR) | CQ3: ='Weekly Progress Report'!N72 -> Deduction / Penalties (SAR) | CR3: Planned Head Count | CS3: Actual Head Count | CT3: Saudi Staff | CU3: Labor Planned | CV3: Labor Actual | CW3: Equipment Planned | CX3: Equipment Actual | CY3: ="This Week "&'Weekly Progress Report'!W54 -> This Week Total Hours Worked | CZ3: ="This Week "&'Weekly Progress Report'!W55 -> This Week Safe Hours Worked | DA3: ="This Week "&'Weekly Progress Report'!W56 -> This Week LTI | DB3: ="This Week "&'Weekly Progress Report'!W57 -> This Week MTC (Healed w/o Disability) | DC3: ="This Week "&'Weekly Progress Report'!W58 -> This Week MTC (Healed w/ Disability) | DD3: ="This Week "&'Weekly Progress Report'!W59 -> This Week Near Miss | DE3: ="This Week "&'Weekly Progress Report'!W60 -> This Week First Aid Cases | DF3: ="This Week "&'Weekly Progress Report'!W61 -> This Week Fatality | DG3: ="This Week "&'Weekly Progress Report'!W62 -> This Week Fire Incident Cases | DH3: ="This Week "&'Weekly Progress Report'!W63 -> This Week Vehicle Incident | DI3: ="This Week "&'Weekly Progress Report'!W64 -> This Week Property Damages | DJ3: ="This Week "&'Weekly Progress Report'!W65 -> This Week Induction Training | DK3: ="This Week "&'Weekly Progress Report'!W66 -> This Week No.of Internal Training | DL3: ="This Week "&'Weekly Progress Report'!W67 -> This Week No.of Internal Audit | DM3: ="This Week "&'Weekly Progress Report'!W68 -> This Week No. of Toolbox Talks | DN3: ="This Week "&'Weekly Progress Report'!W69 -> This Week Safety Awards/Incentives | DO3: ="This Month "&'Weekly Progress Report'!W54 -> This Month Total Hours Worked | DP3: ="This Month "&'Weekly Progress Report'!W55 -> This Month Safe Hours Worked | DQ3: ="This Month "&'Weekly Progress Report'!W56 -> This Month LTI | DR3: ="This Month "&'Weekly Progress Report'!W57 -> This Month MTC (Healed w/o Disability) | DS3: ="This Month "&'Weekly Progress Report'!W58 -> This Month MTC (Healed w/ Disability) | DT3: ="This Month "&'Weekly Progress Report'!W59 -> This Month Near Miss | DU3: ="This Month "&'Weekly Progress Report'!W60 -> This Month First Aid Cases | DV3: ="This Month "&'Weekly Progress Report'!W61 -> This Month Fatality | DW3: ="This Month "&'Weekly Progress Report'!W62 -> This Month Fire Incident Cases | DX3: ="This Month "&'Weekly Progress Report'!W63 -> This Month Vehicle Incident | DY3: ="This Month "&'Weekly Progress Report'!W64 -> This Month Property Damages | DZ3: ="This Month "&'Weekly Progress Report'!W65 -> This Month Induction Training | EA3: ="This Month "&'Weekly Progress Report'!W66 -> This Month No.of Internal Training | EB3: ="This Month "&'Weekly Progress Report'!W67 -> This Month No.of Internal Audit | EC3: ="This Month "&'Weekly Progress Report'!W68 -> This Month No. of Toolbox Talks | ED3: ="This Month "&'Weekly Progress Report'!W69 -> This Month Safety Awards/Incentives | EE3: ="YTD "&'Weekly Progress Report'!W54 -> YTD Total Hours Worked | EF3: ="YTD "&'Weekly Progress Report'!W55 -> YTD Safe Hours Worked | EG3: ="YTD "&'Weekly Progress Report'!W56 -> YTD LTI | EH3: ="YTD "&'Weekly Progress Report'!W57 -> YTD MTC (Healed w/o Disability) | EI3: ="YTD "&'Weekly Progress Report'!W58 -> YTD MTC (Healed w/ Disability) | EJ3: ="YTD "&'Weekly Progress Report'!W59 -> YTD Near Miss | EK3: ="YTD "&'Weekly Progress Report'!W60 -> YTD First Aid Cases | EL3: ="YTD "&'Weekly Progress Report'!W61 -> YTD Fatality | EM3: ="YTD "&'Weekly Progress Report'!W62 -> YTD Fire Incident Cases | EN3: ="YTD "&'Weekly Progress Report'!W63 -> YTD Vehicle Incident | EO3: ="YTD "&'Weekly Progress Report'!W64 -> YTD Property Damages | EP3: ="YTD "&'Weekly Progress Report'!W65 -> YTD Induction Training | EQ3: ="YTD "&'Weekly Progress Report'!W66 -> YTD No.of Internal Training | ER3: ="YTD "&'Weekly Progress Report'!W67 -> YTD No.of Internal Audit | ES3: ="YTD "&'Weekly Progress Report'!W68 -> YTD No. of Toolbox Talks | ET3: ="YTD "&'Weekly Progress Report'!W69 -> YTD Safety Awards/Incentives | EU3: ="Cum "&'Weekly Progress Report'!W54 -> Cum Total Hours Worked | EV3: ="Cum "&'Weekly Progress Report'!W55 -> Cum Safe Hours Worked | EW3: ="Cum "&'Weekly Progress Report'!W56 -> Cum LTI | EX3: ="Cum "&'Weekly Progress Report'!W57 -> Cum MTC (Healed w/o Disability) | EY3: ="Cum "&'Weekly Progress Report'!W58 -> Cum MTC (Healed w/ Disability) | EZ3: ="Cum "&'Weekly Progress Report'!W59 -> Cum Near Miss | FA3: ="Cum "&'Weekly Progress Report'!W60 -> Cum First Aid Cases | FB3: ="Cum "&'Weekly Progress Report'!W61 -> Cum Fatality | FC3: ="Cum "&'Weekly Progress Report'!W62 -> Cum Fire Incident Cases | FD3: ="Cum "&'Weekly Progress Report'!W63 -> Cum Vehicle Incident | FE3: ="Cum "&'Weekly Progress Report'!W64 -> Cum Property Damages | FF3: ="Cum "&'Weekly Progress Report'!W65 -> Cum Induction Training | FG3: ="Cum "&'Weekly Progress Report'!W66 -> Cum No.of Internal Training | FH3: ="Cum "&'Weekly Progress Report'!W67 -> Cum No.of Internal Audit | FI3: ="Cum "&'Weekly Progress Report'!W68 -> Cum No. of Toolbox Talks | FJ3: ="Cum "&'Weekly Progress Report'!W69 -> Cum Safety Awards/Incentives | FK3: ='Weekly Progress Report'!#REF! -> #REF! | FL3: ='Weekly Progress Report'!A81 -> Not Started | FM3: ='Weekly Progress Report'!B81 -> In Progress | FN3: ='Weekly Progress Report'!C81 -> Completed | FO3: Critical Path Act.Last Week | FP3: Critical Path Act.This Week | FQ3: Failed start Last Week | FR3: Failed start This Week | FS3: ='Weekly Progress Report'!A89 -> 0 | FT3: ='Weekly Progress Report'!C89 -> 0 | FU3: ='Weekly Progress Report'!E89 -> 0 | FV3: ='Weekly Progress Report'!G89 -> 0 | FW3: ='Weekly Progress Report'!I89 -> 0 | FX3: ='Weekly Progress Report'!K89 -> 0 | FY3: ='Weekly Progress Report'!M89 -> 0 | FZ3: ='Weekly Progress Report'!N89 -> 0 | GA3: ='Weekly Progress Report'!O89 -> 0
A4: ='Weekly Progress Report'!AF1 -> 46315 | B4: ='Weekly Progress Report'!A3 -> Road Development for the Support Services Area at the Second Industrial City in Makkah (Al-Akayshiyah) | C4: ='Weekly Progress Report'!A4 -> MKH2-02-004 | D4: ='Weekly Progress Report'!A5 -> Al Enjaz Trading & Contracting Co. | E4: ='Weekly Progress Report'!A6 -> Saudi Arabia Consulting Engineering Company "EGIS" | F4: ='Weekly Progress Report'!D4 -> Construction | G4: ='Weekly Progress Report'!D5 -> Active | H4: ='Weekly Progress Report'!D6 -> Engr. Abdallah Aljulaifi | I4: ='Weekly Progress Report'!Z3 -> Road Development for the Services Area at the Second Industrial City in Makkah, Al-Akayshiah (The project includes construction of Roads works & Storm Water Drainage Network) | J4: ='Weekly Progress Report'!G3 -> 46153 | K4: ='Weekly Progress Report'!G4 -> 46198 | L4: ='Weekly Progress Report'!G5 -> 46198 | M4: ='Weekly Progress Report'!G6 -> 46623 | N4: ='Weekly Progress Report'!$I$3 -> 11/05/1447 | O4: ='Weekly Progress Report'!$I$4 -> 25/06/1447 | P4: ='Weekly Progress Report'!$I$5 -> 25/06/1447 | Q4: ='Weekly Progress Report'!$I$6 -> 24/08/1448 | R4: ='Weekly Progress Report'!$K$3 -> 46623 | S4: ='Weekly Progress Report'!$K$4 -> 46623 | T4: ='Weekly Progress Report'!$K$5 -> 46674 | U4: ='Weekly Progress Report'!$N$3 -> 33040004 | V4: ='Weekly Progress Report'!$N$4 -> 33040004 | W4: ='Weekly Progress Report'!$N$5 -> 33040004 | X4: ='Weekly Progress Report'!$N$6 -> 0 | Y4: ='Weekly Progress Report'!$R$3 -> 0 | Z4: ='Weekly Progress Report'!$R$4 -> 6754935.1 | AA4: ='Weekly Progress Report'!$R$5 -> 2000 | AB4: ='Weekly Progress Report'!$R$6 -> 9511214.6 | AC4: ='Weekly Progress Report'!$I$21 -> 0.19120944 | AD4: ='Weekly Progress Report'!$U$3 -> 0.19120944 | AE4: ='Weekly Progress Report'!$U$4 -> 0.33353984 | AF4: ='Weekly Progress Report'!$W$3 -> 0.32617229 | AG4: ='Weekly Progress Report'!$W$4 -> 0.45226223 | AH4: ='Weekly Progress Report'!$Y$3 -> 0.89086207 | AI4: ='Weekly Progress Report'!$Y$5 -> 0.875 | AJ4: ='Weekly Progress Report'!$D$21 -> 842582 | AK4: ='Weekly Progress Report'!$E$21 -> 1602838.6 | AL4: =AJ4/V4 -> 0.025501873 | AM4: =AK4/V4 -> 0.048512058 | AN4: ='Weekly Progress Report'!R21 -> 0.081998262 | AO4: ='Weekly Progress Report'!S21 -> 0.08528295 | AP4: ='Weekly Progress Report'!B59 -> 12 | AQ4: ='Weekly Progress Report'!H59 -> 0 | AR4: ='Weekly Progress Report'!I59 -> 0 | AS4: ='Weekly Progress Report'!J59 -> 12 | AT4: ='Weekly Progress Report'!B68 -> 42 | AU4: ='Weekly Progress Report'!I68 -> 0 | AV4: ='Weekly Progress Report'!J68 -> 42 | AW4: ='Weekly Progress Report'!B77 -> 9 | AX4: ='Weekly Progress Report'!C77 -> 9 | AY4: ='Weekly Progress Report'!D77 -> 4 | AZ4: ='Weekly Progress Report'!E77 -> 5 | BA4: ='Weekly Progress Report'!F77 -> 4 | BB4: ='Weekly Progress Report'!G77 -> 5 | BC4: ='Weekly Progress Report'!H77 -> 46356 | BD4: ='Weekly Progress Report'!M55 -> 0 | BE4: ='Weekly Progress Report'!N55 -> 0 | BF4: ='Weekly Progress Report'!O55 -> 0 | BG4: ='Weekly Progress Report'!P55 -> 0 | BH4: ='Weekly Progress Report'!M56 -> 1 | BI4: ='Weekly Progress Report'!N56 -> 1 | BJ4: ='Weekly Progress Report'!O56 -> 0 | BK4: ='Weekly Progress Report'!P56 -> 2 | BL4: ='Weekly Progress Report'!M57 -> 42 | BM4: ='Weekly Progress Report'!N57 -> 42 | BN4: ='Weekly Progress Report'!O57 -> 0 | BO4: ='Weekly Progress Report'!P57 -> 4 | BP4: ='Weekly Progress Report'!M58 -> 204 | BQ4: ='Weekly Progress Report'!N58 -> 175 | BR4: ='Weekly Progress Report'!O58 -> 29 | BS4: ='Weekly Progress Report'!P58 -> 4 | BT4: ='Weekly Progress Report'!N60 -> 46222 | BU4: ='Weekly Progress Report'!N61 -> 46222 | BV4: ='Weekly Progress Report'!N62 -> 46217 | BW4: ='Weekly Progress Report'!N63 -> 46217 | BX4: ='Weekly Progress Report'!N64 -> 46218 | BY4: ='Weekly Progress Report'!T60 -> 45851 | BZ4: ='Weekly Progress Report'!T61 -> 1 | CA4: ='Weekly Progress Report'!T62 -> 45851 | CB4: ='Weekly Progress Report'!T63 -> 0 | CC4: ='Weekly Progress Report'!T64 -> 0 | CD4: ='Weekly Progress Report'!M66 -> 0 | CE4: ='Weekly Progress Report'!M67 -> 3 | CF4: ='Weekly Progress Report'!M68 -> 2 | CG4: ='Weekly Progress Report'!M69 -> 1 | CH4: ='Weekly Progress Report'!M70 -> 0 | CI4: ='Weekly Progress Report'!M71 -> 0 | CJ4: ='Weekly Progress Report'!M72 -> 6.053268e-05 | CK4: ='Weekly Progress Report'!Q66 -> 7768175.4 | CL4: ='Weekly Progress Report'!Q67 -> 7770175.4 | CM4: ='Weekly Progress Report'!Q68 -> 3778784.9 | CN4: ='Weekly Progress Report'!Q69 -> 0 | CO4: ='Weekly Progress Report'!Q70 -> 0 | CP4: ='Weekly Progress Report'!Q71 -> 0 | CQ4: ='Weekly Progress Report'!Q72 -> 2000 | CR4: ='Weekly Progress Report'!K76 -> 13 | CS4: ='Weekly Progress Report'!L76 -> 27 | CT4: ='Weekly Progress Report'!N76 -> 0 | CU4: ='Weekly Progress Report'!O76 -> 15 | CV4: ='Weekly Progress Report'!P76 -> 67 | CW4: ='Weekly Progress Report'!S86 -> 9 | CX4: ='Weekly Progress Report'!T86 -> 61 | CY4: ='Weekly Progress Report'!Y54 -> 2976 | CZ4: ='Weekly Progress Report'!Y55 -> 2976 | DA4: ='Weekly Progress Report'!Y56 -> 0 | DB4: ='Weekly Progress Report'!Y57 -> 0 | DC4: ='Weekly Progress Report'!Y58 -> 0 | DD4: ='Weekly Progress Report'!Y59 -> 0 | DE4: ='Weekly Progress Report'!Y60 -> 0 | DF4: ='Weekly Progress Report'!Y61 -> 0 | DG4: ='Weekly Progress Report'!Y62 -> 0 | DH4: ='Weekly Progress Report'!Y63 -> 0 | DI4: ='Weekly Progress Report'!Y64 -> 0 | DJ4: ='Weekly Progress Report'!Y65 -> 0 | DK4: ='Weekly Progress Report'!Y66 -> 2 | DL4: ='Weekly Progress Report'!Y67 -> 0 | DM4: ='Weekly Progress Report'!Y68 -> 1 | DN4: ='Weekly Progress Report'!Y69 -> 0 | DO4: ='Weekly Progress Report'!AA54 -> 11136 | DP4: ='Weekly Progress Report'!AA55 -> 11136 | DQ4: ='Weekly Progress Report'!AA56 -> 0 | DR4: ='Weekly Progress Report'!AA57 -> 0 | DS4: ='Weekly Progress Report'!AA58 -> 0 | DT4: ='Weekly Progress Report'!AA59 -> 1 | DU4: ='Weekly Progress Report'!AA60 -> 0 | DV4: ='Weekly Progress Report'!AA61 -> 0 | DW4: ='Weekly Progress Report'!AA62 -> 0 | DX4: ='Weekly Progress Report'!AA63 -> 0 | DY4: ='Weekly Progress Report'!AA64 -> 0 | DZ4: ='Weekly Progress Report'!AA65 -> 1 | EA4: ='Weekly Progress Report'!AA66 -> 5 | EB4: ='Weekly Progress Report'!AA67 -> 0 | EC4: ='Weekly Progress Report'!AA68 -> 4 | ED4: ='Weekly Progress Report'!AA69 -> 0 | EE4: ='Weekly Progress Report'!AB54 -> 36989 | EF4: ='Weekly Progress Report'!AB55 -> 36989 | EG4: ='Weekly Progress Report'!AB56 -> 0 | EH4: ='Weekly Progress Report'!AB57 -> 0 | EI4: ='Weekly Progress Report'!AB58 -> 0 | EJ4: ='Weekly Progress Report'!AB59 -> 1 | EK4: ='Weekly Progress Report'!AB60 -> 0 | EL4: ='Weekly Progress Report'!AB61 -> 0 | EM4: ='Weekly Progress Report'!AB62 -> 0 | EN4: ='Weekly Progress Report'!AB63 -> 0 | EO4: ='Weekly Progress Report'!AB64 -> 0 | EP4: ='Weekly Progress Report'!AB65 -> 4 | EQ4: ='Weekly Progress Report'!AB66 -> 19 | ER4: ='Weekly Progress Report'!AB67 -> 1 | ES4: ='Weekly Progress Report'!AB68 -> 18 | ET4: ='Weekly Progress Report'!AB69 -> 0 | EU4: ='Weekly Progress Report'!AC54 -> 36989 | EV4: ='Weekly Progress Report'!AC55 -> 36989 | EW4: ='Weekly Progress Report'!AC56 -> 0 | EX4: ='Weekly Progress Report'!AC57 -> 0 | EY4: ='Weekly Progress Report'!AC58 -> 0 | EZ4: ='Weekly Progress Report'!AC59 -> 1 | FA4: ='Weekly Progress Report'!AC60 -> 0 | FB4: ='Weekly Progress Report'!AC61 -> 0 | FC4: ='Weekly Progress Report'!AC62 -> 0 | FD4: ='Weekly Progress Report'!AC63 -> 0 | FE4: ='Weekly Progress Report'!AC64 -> 0 | FF4: ='Weekly Progress Report'!AC65 -> 4 | FG4: ='Weekly Progress Report'!AC66 -> 19 | FH4: ='Weekly Progress Report'!AC67 -> 1 | FI4: ='Weekly Progress Report'!AC68 -> 18 | FJ4: ='Weekly Progress Report'!AC69 -> 0 | FK4: ='Weekly Progress Report'!#REF! -> #REF! | FL4: ='Weekly Progress Report'!A82 -> 199 | FM4: ='Weekly Progress Report'!B82 -> 34 | FN4: ='Weekly Progress Report'!C82 -> 148 | FO4: ='Weekly Progress Report'!#REF! -> #REF! | FP4: ='Weekly Progress Report'!A86 -> 168 | FQ4: ='Weekly Progress Report'!G86 -> 25 | FR4: ='Weekly Progress Report'!H86 -> 29 | FS4: ='Weekly Progress Report'!A94 -> 0 | FT4: ='Weekly Progress Report'!C94 -> 0 | FU4: ='Weekly Progress Report'!E94 -> 0 | FV4: ='Weekly Progress Report'!G94 -> 0 | FW4: ='Weekly Progress Report'!I94 -> 0 | FX4: ='Weekly Progress Report'!K94 -> 0 | FY4: ='Weekly Progress Report'!M94 -> 0 | FZ4: ='Weekly Progress Report'!N94 -> 0 | GA4: ='Weekly Progress Report'!O94 -> 0

Sheet Weekly Progress Report
AC1: =+HSE!L4 -> Report No. | AD1: =+HSE!P4 -> 17 | AE1: Data Date | AF1: ='General Information'!L1 -> 46315
F2: Key Dates | L2: Cost Summary (SR) | T2: Performance Summary | Z2: Project Scope
A3: ='General Information'!C3 -> Road Development for the Support Services Area at the Second Industrial City in Makkah (Al-Akayshiyah) | F3: Contract Award | G3: ='General Information'!C12 -> 46153 | H3: Contract Award (Hijri) | I3: ='General Information'!C16 -> 11/05/1447 | J3: Revised Completion | K3: ='General Information'!C20 -> 46623 | L3: Original Contract Value | N3: ='Invoice Log'!E3 -> 33040004 | P3: O&M Value (if any) | R3: ='Invoice Log'!I3 -> 0 | S3: EAC | T3: Plan Value | U3: =J21 -> 0.19120944 | V3: Phys. Plan Value | W3: =V21 -> 0.32617229 | X3: Quality Score | Y3: =Quality!AC10 -> 0.89086207 | Z3: =+Progress!A1 -> Road Development for the Services Area at the Second Industrial City in Makkah, Al-Akayshiah (The project includes construction of Roads works & Storm Water Drainage Network)
A4: ='General Information'!C4 -> MKH2-02-004 | C4: Stage | D4: ='General Information'!C7 -> Construction | F4: Contract Sign | G4: ='General Information'!C13 -> 46198 | H4: Contract Sign (Hijri) | I4: ='General Information'!C17 -> 25/06/1447 | J4: Committed Completion | K4: ='General Information'!C21 -> 46623 | L4: Revised Contract Value | N4: ='Invoice Log'!E4 -> 33040004 | O4: EAC | P4: Submitted Invoices (Gross Value) | R4: =+'Invoice Log'!F59 -> 6754935.1 | T4: Earn Value | U4: =K21 -> 0.33353984 | V4: Phys. Earn Value | W4: =W21 -> 0.45226223 | Y4: =REPT("¢",IF(INT(+Y3*10)>5,5,INT(+Y3*10)))&REPT("£",IF(INT(+Y3*10)>5,0,5-INT(+Y3*10)))&CHAR(10)&REPT("¢",+IF(INT(+Y3*10)>5,-5+INT(+Y3*10),0))&REPT("£",IF(INT(+Y3*10)>5,10-INT(+Y3*10),5)) -> ¢¢¢¢¢ ¢¢¢££
A5: ='General Information'!C5 -> Al Enjaz Trading & Contracting Co. | C5: Status | D5: ='General Information'!C8 -> Active | F5: Site Handover | G5: ='General Information'!C14 -> 46198 | H5: Site Handover (Hijri) | I5: ='General Information'!C18 -> 25/06/1447 | J5: Forecast Completion | K5: ='General Information'!C22 -> 46674 | L5: Estimate At Completion Value | N5: ='Invoice Log'!E5 -> 33040004 | O5: =+#REF!+#REF!+N5 -> #REF! | P5: Penalities | R5: ='Invoice Log'!M6 -> 2000 | T5: Variance | U5: =U4-U3 -> 0.1423304 | V5: Variance | W5: =W4-W3 -> 0.12608994 | X5: Safety Score | Y5: ='HSE-Stat'!J23 -> 0.875
A6: ='General Information'!C6 -> Saudi Arabia Consulting Engineering Company "EGIS" | C6: Modon PM | D6: ='General Information'!C9 -> Engr. Abdallah Aljulaifi | F6: Original Completion | G6: ='General Information'!C15 -> 46623 | H6: Original Completion (Hijri) | I6: ='General Information'!C19 -> 24/08/1448 | J6: Variance | K6: ='General Information'!C23 -> -51 | L6: Potential Changes | N6: =N4-N5 -> 0 | P6: FIR Value (Todate) | R6: =+'FIR summary '!K2 -> 9511214.6 | T6: FIR % | U6: =R6/N4 -> 0.28786966 | V6: Invoiced % | W6: =R4/N4 -> 0.20444716 | Y6: =REPT("¢",IF(INT(+Y5*10)>5,5,INT(+Y5*10)))&REPT("£",IF(INT(+Y5*10)>5,0,5-INT(+Y5*10)))&CHAR(10)&REPT("¢",+IF(INT(+Y5*10)>5,-5+INT(+Y5*10),0))&REPT("£",IF(INT(+Y5*10)>5,10-INT(+Y5*10),5)) -> ¢¢¢¢¢ ¢¢¢££
N9: Physical Progress (Effort) | Z9: Earned Value Progress (%)
B10: BOQ Value (SAR) | C10: % Wt. | D10: Weekly (SAR) | F10: To Date (SAR) | N10: Budgeted | O10: % Wt. | P10: Weekly Physical Progress | T10: To Date Physical Progress
D11: Planned | E11: Earned | F11: Original Plan | G11: Revised Planned | H11: Earned | I11: Original Plan % | J11: Revised Planned % | K11: Earned % | L11: Variance | M11: SPI | N11: (Manhours) | P11: Planned | Q11: Earned | R11: Plan % | S11: Earned % | T11: Planned | U11: Earned | V11: Plan % | W11: Earned % | X11: Variance | Y11: SPI
B12: =+Progress!B7 -> 0 | C12: =IF(ISBLANK(B12),"",B12/$B$21) -> 0 | D12: =+Progress!D7 -> 0 | E12: =+Progress!E7 -> - | F12: =+Progress!F7 -> 0 | G12: =+Progress!G7 -> 0 | H12: =+Progress!H7 -> - | I12: =IFERROR(IF(ISBLANK(F12),"",F12/B12),0) -> 0 | J12: =IFERROR(IF(ISBLANK(G12),"",G12/B12),0) -> 0 | K12: =IFERROR(IF(ISBLANK(H12),"",H12/B12),0) -> 0 | L12: =IFERROR(K12-J12,"") -> 0 | M12: =IFERROR(K12/J12,"") | N12: =+Progress!J7 -> 7892 | O12: =IF(ISBLANK(N12),"",N12/$N$21) -> 0.036104122 | P12: =+Progress!L7 -> 0 | Q12: =+Progress!M7 -> 0 | R12: =IFERROR(IF(ISBLANK(P12),"",P12/N12),0) -> 0 | S12: =IFERROR(IF(ISBLANK(Q12),"",Q12/N12),0) -> 0 | T12: =+Progress!N7 -> 7892 | U12: =+Progress!O7 -> 7892 | V12: =IFERROR(IF(ISBLANK(T12),"",T12/N12),0) -> 1 | W12: =IFERROR(IF(ISBLANK(U12),"",U12/N12),0) -> 1 | X12: =IFERROR(W12-V12,"") -> 0 | Y12: =IFERROR(W12/V12,"") -> 1
B13: =+Progress!B9 -> 0 | C13: =IF(ISBLANK(B13),"",B13/$B$21) -> 0 | D13: =+Progress!D9 -> 0 | E13: =+Progress!E9 -> 0 | F13: =+Progress!F9 -> 0 | G13: =+Progress!G9 -> 0 | H13: =+Progress!H9 -> 0 | I13: =IFERROR(IF(ISBLANK(F13),"",F13/B13),0) -> 0 | J13: =IFERROR(IF(ISBLANK(G13),"",G13/B13),0) -> 0 | K13: =IFERROR(IF(ISBLANK(H13),"",H13/B13),0) -> 0 | L13: =IFERROR(K13-J13,"") -> 0 | M13: =IFERROR(K13/J13,"") | N13: =+Progress!J9 -> 5832 | O13: =IF(ISBLANK(N13),"",N13/$N$21) -> 0.026680086 | P13: =+Progress!L9 -> 0 | Q13: =+Progress!M9 -> 0 | R13: =IFERROR(IF(ISBLANK(P13),"",P13/N13),0) -> 0 | S13: =IFERROR(IF(ISBLANK(Q13),"",Q13/N13),0) -> 0 | T13: =+Progress!N9 -> 5832 | U13: =+Progress!O9 -> 5832 | V13: =IFERROR(IF(ISBLANK(T13),"",T13/N13),0) -> 1 | W13: =IFERROR(IF(ISBLANK(U13),"",U13/N13),0) -> 1 | X13: =IFERROR(W13-V13,"") -> 0 | Y13: =IFERROR(W13/V13,"") -> 1
B14: =+Progress!B11 -> 0 | C14: =IF(ISBLANK(B14),"",B14/$B$21) -> 0 | D14: =+Progress!D11 -> 0 | E14: =+Progress!E11 -> 0 | F14: =+Progress!F11 -> 0 | G14: =+Progress!G11 -> 0 | H14: =+Progress!H11 -> 0 | I14: =IFERROR(IF(ISBLANK(F14),"",F14/B14),0) -> 0 | J14: =IFERROR(IF(ISBLANK(G14),"",G14/B14),0) -> 0 | K14: =IFERROR(IF(ISBLANK(H14),"",H14/B14),0) -> 0 | L14: =IFERROR(K14-J14,"") -> 0 | M14: =IFERROR(K14/J14,"") | N14: =+Progress!J11 -> 4916 | O14: =IF(ISBLANK(N14),"",N14/$N$21) -> 0.022489592 | P14: =+Progress!L11 -> 362 | Q14: =+Progress!M11 -> 0 | R14: =IFERROR(IF(ISBLANK(P14),"",P14/N14),0) -> 0.073637103 | S14: =IFERROR(IF(ISBLANK(Q14),"",Q14/N14),0) -> 0 | T14: =+Progress!N11 -> 3784 | U14: =+Progress!O11 -> 2918 | V14: =IFERROR(IF(ISBLANK(T14),"",T14/N14),0) -> 0.76973149 | W14: =IFERROR(IF(ISBLANK(U14),"",U14/N14),0) -> 0.59357201 | X14: =IFERROR(W14-V14,"") -> -0.17615948 | Y14: =IFERROR(W14/V14,"") -> 0.77114165
B15: =+Progress!B13 -> 19411954 | C15: =IF(ISBLANK(B15),"",B15/$B$21) -> 0.5875288 | D15: =+Progress!D13 -> 391828.36 | E15: =+Progress!E13 -> 481104.9 | F15: =+Progress!F13 -> 4517610.4 | G15: =+Progress!G13 -> 4517610.4 | H15: =+Progress!H13 -> 6884338.4 | I15: =IFERROR(IF(ISBLANK(F15),"",F15/B15),0) -> 0.23272311 | J15: =IFERROR(IF(ISBLANK(G15),"",G15/B15),0) -> 0.23272311 | K15: =IFERROR(IF(ISBLANK(H15),"",H15/B15),0) -> 0.35464428 | L15: =IFERROR(K15-J15,"") -> 0.12192117 | M15: =IFERROR(K15/J15,"") -> 1.5238894 | N15: 118680 | O15: =IF(ISBLANK(N15),"",N15/$N$21) -> 0.54293426 | P15: =+Progress!L13 -> 3780 | Q15: =+Progress!M13 -> 3333 | R15: =IFERROR(IF(ISBLANK(P15),"",P15/N15),0) -> 0.031850354 | S15: =IFERROR(IF(ISBLANK(Q15),"",Q15/N15),0) -> 0.028083923 | T15: =+Progress!N13 -> 37820 | U15: =+Progress!O13 -> 59417 | V15: =IFERROR(IF(ISBLANK(T15),"",T15/N15),0) -> 0.31867206 | W15: =IFERROR(IF(ISBLANK(U15),"",U15/N15),0) -> 0.5006488 | X15: =IFERROR(W15-V15,"") -> 0.18197674 | Y15: =IFERROR(W15/V15,"") -> 1.5710471
B16: =+Progress!B15 -> 13628050 | C16: =IF(ISBLANK(B16),"",B16/$B$21) -> 0.4124712 | D16: =+Progress!D15 -> 450753.64 | E16: =+Progress!E15 -> 1121733.7 | F16: =+Progress!F15 -> 1799950.3 | G16: =+Progress!G15 -> 1799950.3 | H16: =+Progress!H15 -> 4135819.2 | I16: =IFERROR(IF(ISBLANK(F16),"",F16/B16),0) -> 0.13207688 | J16: =IFERROR(IF(ISBLANK(G16),"",G16/B16),0) -> 0.13207688 | K16: =IFERROR(IF(ISBLANK(H16),"",H16/B16),0) -> 0.30347843 | L16: =IFERROR(K16-J16,"") -> 0.17140155 | M16: =IFERROR(K16/J16,"") -> 2.2977408 | N16: 77910 | O16: =IF(ISBLANK(N16),"",N16/$N$21) -> 0.3564207 | P16: =+Progress!L15 -> 4820 | Q16: =+Progress!M15 -> 5988 | R16: =IFERROR(IF(ISBLANK(P16),"",P16/N16),0) -> 0.061866256 | S16: =IFERROR(IF(ISBLANK(Q16),"",Q16/N16),0) -> 0.076857913 | T16: =+Progress!N15 -> 15970 | U16: =+Progress!O15 -> 22801 | V16: =IFERROR(IF(ISBLANK(T16),"",T16/N16),0) -> 0.20498011 | W16: =IFERROR(IF(ISBLANK(U16),"",U16/N16),0) -> 0.2926582 | X16: =IFERROR(W16-V16,"") -> 0.08767809 | Y16: =IFERROR(W16/V16,"") -> 1.4277395
B17: =+Progress!B17 -> 0 | C17: =IF(ISBLANK(B17),"",B17/$B$21) -> 0 | D17: =+Progress!D17 -> 0 | E17: =+Progress!E17 -> 0 | F17: =+Progress!F17 -> 0 | G17: =+Progress!G17 -> 0 | H17: =+Progress!H17 -> 0 | I17: =IFERROR(IF(ISBLANK(F17),"",F17/B17),0) -> 0 | J17: =IFERROR(IF(ISBLANK(G17),"",G17/B17),0) -> 0 | K17: =IFERROR(IF(ISBLANK(H17),"",H17/B17),0) -> 0 | L17: =IFERROR(K17-J17,"") -> 0 | M17: =IFERROR(K17/J17,"") | N17: =+Progress!J17 -> 2400 | O17: =IF(ISBLANK(N17),"",N17/$N$21) -> 0.010979459 | P17: =+Progress!L17 -> 0 | Q17: =+Progress!M17 -> 0 | R17: =IFERROR(IF(ISBLANK(P17),"",P17/N17),0) -> 0 | S17: =IFERROR(IF(ISBLANK(Q17),"",Q17/N17),0) -> 0 | T17: =+Progress!N17 -> 0 | U17: =+Progress!O17 -> 0 | V17: =IFERROR(IF(ISBLANK(T17),"",T17/N17),0) -> 0 | W17: =IFERROR(IF(ISBLANK(U17),"",U17/N17),0) -> 0 | X17: =IFERROR(W17-V17,"") -> 0 | Y17: =IFERROR(W17/V17,"")
C18: =IF(ISBLANK(B18),"",B18/$B$21) | I18: =IFERROR(IF(ISBLANK(F18),"",F18/B18),0) | J18: =IFERROR(IF(ISBLANK(G18),"",G18/B18),0) | K18: =IFERROR(IF(ISBLANK(H18),"",H18/B18),0) | L18: =IFERROR(K18-J18,"") | M18: =IFERROR(K18/J18,"") | N18: =+Progress!J19 -> 960 | O18: =IF(ISBLANK(N18),"",N18/$N$21) -> 0.0043917837 | P18: =+Progress!L19 -> 0 | Q18: =+Progress!M19 -> 0 | R18: =IFERROR(IF(ISBLANK(P18),"",P18/N18),0) -> 0 | S18: =IFERROR(IF(ISBLANK(Q18),"",Q18/N18),0) -> 0 | T18: =+Progress!N19 -> 0 | U18: =+Progress!O19 -> 0 | V18: =IFERROR(IF(ISBLANK(T18),"",T18/N18),0) -> 0 | W18: =IFERROR(IF(ISBLANK(U18),"",U18/N18),0) -> 0 | X18: =IFERROR(W18-V18,"") -> 0 | Y18: =IFERROR(W18/V18,"")
C19: =IF(ISBLANK(B19),"",B19/$B$21) | I19: =IFERROR(IF(ISBLANK(F19),"",F19/B19),0) | J19: =IFERROR(IF(ISBLANK(G19),"",G19/B19),0) | K19: =IFERROR(IF(ISBLANK(H19),"",H19/B19),0) | L19: =IFERROR(K19-J19,"") | M19: =IFERROR(K19/J19,"") | O19: =IF(ISBLANK(N19),"",N19/$N$21) | P19: =+Progress!L21 -> 8962 | Q19: =+Progress!M21 -> 9321 | R19: =IFERROR(IF(ISBLANK(P19),"",P19/N19),0) -> 0 | S19: =IFERROR(IF(ISBLANK(Q19),"",Q19/N19),0) -> 0 | V19: =IFERROR(IF(ISBLANK(T19),"",T19/N19),0) | W19: =IFERROR(IF(ISBLANK(U19),"",U19/N19),0) | X19: =IFERROR(W19-V19,"") | Y19: =IFERROR(W19/V19,"")
B20: =+Progress!B17 -> 0 | C20: =IF(ISBLANK(B20),"",B20/$B$21) -> 0 | D20: =+Progress!D17 -> 0 | E20: =+Progress!E17 -> 0 | F20: =+Progress!F17 -> 0 | G20: =+Progress!G17 -> 0 | H20: =+Progress!H17 -> 0 | I20: =IFERROR(IF(ISBLANK(F20),"",F20/B20),0) -> 0 | J20: =IFERROR(IF(ISBLANK(G20),"",G20/B20),0) -> 0 | K20: =IFERROR(IF(ISBLANK(H20),"",H20/B20),0) -> 0 | L20: =IFERROR(K20-J20,"") -> 0 | M20: =IFERROR(K20/J20,"") | O20: =IF(ISBLANK(N20),"",N20/$N$21) | P20: =+Progress!L17 -> 0 | Q20: =+Progress!M17 -> 0 | R20: =IFERROR(IF(ISBLANK(P20),"",P20/N20),0) -> 0 | S20: =IFERROR(IF(ISBLANK(Q20),"",Q20/N20),0) -> 0 | T20: =+Progress!N17 -> 0 | U20: =+Progress!O17 -> 0 | V20: =IFERROR(IF(ISBLANK(T20),"",T20/N20),0) -> 0 | W20: =IFERROR(IF(ISBLANK(U20),"",U20/N20),0) -> 0 | X20: =IFERROR(W20-V20,"") -> 0 | Y20: =IFERROR(W20/V20,"")
A21: Total | B21: =SUM(B12:B20) -> 33040004 | C21: =SUM(C12:C20) -> 1 | D21: =SUM(D12:D20) -> 842582 | E21: =SUM(E12:E20) -> 1602838.6 | F21: =SUM(F12:F20) -> 6317560.7 | G21: =SUM(G12:G20) -> 6317560.7 | H21: =SUM(H12:H20) -> 11020158 | I21: =IFERROR(IF(ISBLANK(F21),"",F21/B21),0) -> 0.19120944 | J21: =IFERROR(IF(ISBLANK(G21),"",G21/B21),0) -> 0.19120944 | K21: =IFERROR(IF(ISBLANK(H21),"",H21/B21),0) -> 0.33353984 | L21: =+K21-J21 -> 0.1423304 | M21: =K21/J21 -> 1.7443691 | N21: =SUM(N12:N20) -> 218590 | O21: =SUM(O12:O20) -> 1 | P21: =SUM(P12:P20) -> 17924 | Q21: =SUM(Q12:Q20) -> 18642 | R21: =IFERROR(IF(ISBLANK(P21),"",P21/N21),0) -> 0.081998262 | S21: =IFERROR(IF(ISBLANK(Q21),"",Q21/N21),0) -> 0.08528295 | T21: =SUM(T12:T20) -> 71298 | U21: =SUM(U12:U20) -> 98860 | V21: =IFERROR(IF(ISBLANK(T21),"",T21/N21),0) -> 0.32617229 | W21: =IFERROR(IF(ISBLANK(U21),"",U21/N21),0) -> 0.45226223 | X21: =+W21-V21 -> 0.12608994 | Y21: =W21/V21 -> 1.3865747
Z22: Construction Milestones
Z23: Item No. | AA23: Milestones | AC23: Original (Baseline) | AD23: Latest Plan | AE23: Forecast | AF23: Status | AG23: Days Change
Z24: =+Milestones!A4 -> 1 | AA24: =+Milestones!B4 -> Project Commencement Date | AC24: =+Milestones!C4 -> 46198 | AD24: =+Milestones!D4 -> 46198 | AE24: =+Milestones!E4 -> 46198 | AF24: =+Milestones!F4 -> A | AG24: =+Milestones!G4 -> 0
Z25: =+Milestones!A5 -> 2 | AA25: =+Milestones!B5 -> Project Completion | AC25: =+Milestones!C5 -> 46623 | AD25: =+Milestones!D5 -> 46623 | AE25: =+Milestones!E5 -> 46674 | AF25: =+Milestones!F5 -> F | AG25: =+Milestones!G5 -> -51
Z26: =+Milestones!A6 -> 3 | AA26: =+Milestones!B6 -> Completion of Mobilization | AC26: =+Milestones!C6 -> 46226 | AD26: =+Milestones!D6 -> 46226 | AE26: =+Milestones!E6 -> 46249 | AF26: =+Milestones!F6 -> A | AG26: =+Milestones!G6 -> -23
Z27: =+Milestones!A7 -> 4 | AA27: =+Milestones!B7 -> Baseline Programme Submission | AC27: =+Milestones!C7 -> 46215 | AD27: =+Milestones!D7 -> 46215 | AE27: =+Milestones!E7 -> 46215 | AF27: =+Milestones!F7 -> A | AG27: =+Milestones!G7 -> 0
Z28: =+Milestones!A8 -> 5 | AA28: =+Milestones!B8 -> Submission and Approval of drawings and Materials | AC28: =+Milestones!C8 -> 46257 | AD28: =+Milestones!D8 -> 46257 | AE28: =+Milestones!E8 -> 46284 | AF28: =+Milestones!F8 -> A | AG28: =+Milestones!G8 -> -27
Z29: =+Milestones!A9 -> 6 | AA29: =+Milestones!B9 -> Completion of Road Works | AC29: =+Milestones!C9 -> 46501 | AD29: =+Milestones!D9 -> 46501 | AE29: =+Milestones!E9 -> 46553 | AF29: =+Milestones!F9 -> F | AG29: =+Milestones!G9 -> -52
Z30: =+Milestones!A10 -> 7 | AA30: =+Milestones!B10 -> Completion of Storm Water Dranage | AC30: =+Milestones!C10 -> 46442 | AD30: =+Milestones!D10 -> 46442 | AE30: =+Milestones!E10 -> 46487 | AF30: =+Milestones!F10 -> F | AG30: =+Milestones!G10 -> -45
Z31: =+Milestones!A11 -> 8 | AA31: =+Milestones!B11 -> Completion of Entire Project | AC31: =+Milestones!C11 -> 46623 | AD31: =+Milestones!D11 -> 46623 | AE31: =+Milestones!E11 -> 46674 | AF31: =+Milestones!F11 -> F | AG31: =+Milestones!G11 -> -51
K50: Quality | V50: Safety
K51: Quality Reports | V51: Safety Statistics | AD51: Proactive Vs Reactive Actions Taken
B52: Total | C52: Total Submitted Drawings | H52: Remaining | I52: Pending | J52: Total Submittals | K52: Quality Reports | M52: Issued | N52: Closed | O52: Pending | P52: Avg. Closing (Days) | Q52: Pending | V52: Category | W52: Item | Y52: This Week | AA52: This Month | AB52: Year to Date | AC52: Cumulative
C53: A | D53: B | E53: C | F53: D | G53: Processed | Q53: 0-10 Days | R53: 11-20 Days | S53: 21-30 Days | T53: 31-60 Days | U53: > 60 Days
B54: =IF('Quality-Stat'!D13="","",'Quality-Stat'!D13) -> 1 | C54: =IF('Quality-Stat'!E13="","",'Quality-Stat'!E13) -> 0 | D54: =IF('Quality-Stat'!F13="","",'Quality-Stat'!F13) -> 1 | E54: =IF('Quality-Stat'!G13="","",'Quality-Stat'!G13) -> 0 | F54: =IF('Quality-Stat'!H13="","",'Quality-Stat'!H13) -> 0 | G54: =IF('Quality-Stat'!I13="","",'Quality-Stat'!I13) -> 1 | H54: =IF('Quality-Stat'!J13="","",'Quality-Stat'!J13) -> 0 | I54: =IF('Quality-Stat'!K13="","",'Quality-Stat'!K13) -> 0 | J54: =IF('Quality-Stat'!L13="","",'Quality-Stat'!L13) -> 1 | V54: General | W54: ='HSE-Stat'!B4 -> Total Hours Worked | Y54: ='HSE-Stat'!D4 -> 2976 | AA54: ='HSE-Stat'!E4 -> 11136 | AB54: ='HSE-Stat'!F4 -> 36989 | AC54: ='HSE-Stat'!G4 -> 36989 | AF54: Proactive | AG54: =+SUM(AC65:AC69) -> 42
B55: =IF('Quality-Stat'!D14="","",'Quality-Stat'!D14) -> 11 | C55: =IF('Quality-Stat'!E14="","",'Quality-Stat'!E14) -> 0 | D55: =IF('Quality-Stat'!F14="","",'Quality-Stat'!F14) -> 11 | E55: =IF('Quality-Stat'!G14="","",'Quality-Stat'!G14) -> 0 | F55: =IF('Quality-Stat'!H14="","",'Quality-Stat'!H14) -> 0 | G55: =IF('Quality-Stat'!I14="","",'Quality-Stat'!I14) -> 11 | H55: =IF('Quality-Stat'!J14="","",'Quality-Stat'!J14) -> 0 | I55: =IF('Quality-Stat'!K14="","",'Quality-Stat'!K14) -> 0 | J55: =IF('Quality-Stat'!L14="","",'Quality-Stat'!L14) -> 11 | K55: Non Conformance (NCR) | M55: ='Quality-Stat'!D5 -> 0 | N55: ='Quality-Stat'!E5 -> 0 | O55: ='Quality-Stat'!F5 -> 0 | P55: ='Quality-Stat'!G5 -> 0 | Q55: ='Quality-Stat'!H5 -> 0 | R55: ='Quality-Stat'!I5 -> 0 | S55: ='Quality-Stat'!J5 -> 0 | T55: ='Quality-Stat'!K5 -> 0 | U55: ='Quality-Stat'!L5 -> 0 | W55: ='HSE-Stat'!B5 -> Safe Hours Worked | Y55: ='HSE-Stat'!D5 -> 2976 | AA55: ='HSE-Stat'!E5 -> 11136 | AB55: ='HSE-Stat'!F5 -> 36989 | AC55: ='HSE-Stat'!G5 -> 36989 | AF55: Reactive | AG55: =SUM(AC56:AC64) -> 1
B56: =IF('Quality-Stat'!D15="","",'Quality-Stat'!D15) -> 0 | C56: =IF('Quality-Stat'!E15="","",'Quality-Stat'!E15) -> 0 | D56: =IF('Quality-Stat'!F15="","",'Quality-Stat'!F15) -> 0 | E56: =IF('Quality-Stat'!G15="","",'Quality-Stat'!G15) -> 0 | F56: =IF('Quality-Stat'!H15="","",'Quality-Stat'!H15) -> 0 | G56: =IF('Quality-Stat'!I15="","",'Quality-Stat'!I15) -> 0 | H56: =IF('Quality-Stat'!J15="","",'Quality-Stat'!J15) -> 0 | I56: =IF('Quality-Stat'!K15="","",'Quality-Stat'!K15) -> 0 | J56: =IF('Quality-Stat'!L15="","",'Quality-Stat'!L15) -> 0 | K56: Site Instruction (SIR/SOR) | M56: ='Quality-Stat'!D6 -> 1 | N56: ='Quality-Stat'!E6 -> 1 | O56: ='Quality-Stat'!F6 -> 0 | P56: ='Quality-Stat'!G6 -> 2 | Q56: ='Quality-Stat'!H6 -> 0 | R56: ='Quality-Stat'!I6 -> 0 | S56: ='Quality-Stat'!J6 -> 0 | T56: ='Quality-Stat'!K6 -> 0 | U56: ='Quality-Stat'!L6 -> 0 | V56: Reactive | W56: ='HSE-Stat'!B6 -> LTI | Y56: ='HSE-Stat'!D6 -> 0 | AA56: ='HSE-Stat'!E6 -> 0 | AB56: ='HSE-Stat'!F6 -> 0 | AC56: ='HSE-Stat'!G6 -> 0
B57: =IF('Quality-Stat'!D16="","",'Quality-Stat'!D16) -> 0 | C57: =IF('Quality-Stat'!E16="","",'Quality-Stat'!E16) -> 0 | D57: =IF('Quality-Stat'!F16="","",'Quality-Stat'!F16) -> 0 | E57: =IF('Quality-Stat'!G16="","",'Quality-Stat'!G16) -> 0 | F57: =IF('Quality-Stat'!H16="","",'Quality-Stat'!H16) -> 0 | G57: =IF('Quality-Stat'!I16="","",'Quality-Stat'!I16) -> 0 | H57: =IF('Quality-Stat'!J16="","",'Quality-Stat'!J16) -> 0 | I57: =IF('Quality-Stat'!K16="","",'Quality-Stat'!K16) -> 0 | J57: =IF('Quality-Stat'!L16="","",'Quality-Stat'!L16) -> 0 | K57: Material Inspection (MRIR) | M57: ='Quality-Stat'!D7 -> 42 | N57: ='Quality-Stat'!E7 -> 42 | O57: ='Quality-Stat'!F7 -> 0 | P57: ='Quality-Stat'!G7 -> 4 | Q57: ='Quality-Stat'!H7 -> 0 | R57: ='Quality-Stat'!I7 -> 0 | S57: ='Quality-Stat'!J7 -> 0 | T57: ='Quality-Stat'!K7 -> 0 | U57: ='Quality-Stat'!L7 -> 0 | W57: ='HSE-Stat'!B7 -> MTC (Healed w/o Disability) | Y57: ='HSE-Stat'!D7 -> 0 | AA57: ='HSE-Stat'!E7 -> 0 | AB57: ='HSE-Stat'!F7 -> 0 | AC57: ='HSE-Stat'!G7 -> 0
B58: =IF('Quality-Stat'!D17="","",'Quality-Stat'!D17) -> 0 | C58: =IF('Quality-Stat'!E17="","",'Quality-Stat'!E17) -> 0 | D58: =IF('Quality-Stat'!F17="","",'Quality-Stat'!F17) -> 0 | E58: =IF('Quality-Stat'!G17="","",'Quality-Stat'!G17) -> 0 | F58: =IF('Quality-Stat'!H17="","",'Quality-Stat'!H17) -> 0 | G58: =IF('Quality-Stat'!I17="","",'Quality-Stat'!I17) -> 0 | H58: =IF('Quality-Stat'!J17="","",'Quality-Stat'!J17) -> 0 | I58: =IF('Quality-Stat'!K17="","",'Quality-Stat'!K17) -> 0 | J58: =IF('Quality-Stat'!L17="","",'Quality-Stat'!L17) -> 0 | K58: Field Inspection (FIR) | M58: ='Quality-Stat'!D8 -> 204 | N58: ='Quality-Stat'!E8 -> 175 | O58: ='Quality-Stat'!F8 -> 29 | P58: ='Quality-Stat'!G8 -> 4 | Q58: ='Quality-Stat'!H8 -> 17 | R58: ='Quality-Stat'!I8 -> 0 | S58: ='Quality-Stat'!J8 -> 0 | T58: ='Quality-Stat'!K8 -> 0 | U58: ='Quality-Stat'!L8 -> 0 | W58: ='HSE-Stat'!B8 -> MTC (Healed w/ Disability) | Y58: ='HSE-Stat'!D8 -> 0 | AA58: ='HSE-Stat'!E8 -> 0 | AB58: ='HSE-Stat'!F8 -> 0 | AC58: ='HSE-Stat'!G8 -> 0
B59: =SUM(B54:B58) -> 12 | C59: =SUM(C54:C58) -> 0 | D59: =SUM(D54:D58) -> 12 | E59: =SUM(E54:E58) -> 0 | F59: =SUM(F54:F58) -> 0 | G59: =SUM(G54:G58) -> 12 | H59: =SUM(H54:H58) -> 0 | I59: =SUM(I54:I58) -> 0 | J59: =SUM(J54:J58) -> 12 | K59: Key Submittals Approval Status | W59: ='HSE-Stat'!B9 -> Near Miss | Y59: ='HSE-Stat'!D9 -> 0 | AA59: ='HSE-Stat'!E9 -> 1 | AB59: ='HSE-Stat'!F9 -> 1 | AC59: ='HSE-Stat'!G9 -> 1
K60: 1 Quality Plan Approval | N60: =+'General Information'!C27 -> 46222 | P60: 6 Baseline Approval | T60: ='General Information'!C39 -> 45851 | W60: ='HSE-Stat'!B10 -> First Aid Cases | Y60: ='HSE-Stat'!D10 -> 0 | AA60: ='HSE-Stat'!E10 -> 0 | AB60: ='HSE-Stat'!F10 -> 0 | AC60: ='HSE-Stat'!G10 -> 0 | AD60: Total Hours Worked Vs Safe Hours Worked
B61: Total | C61: Total Submitted Material | H61: Remaining to approve | I61: Pending | J61: Total Submittals | K61: 2 Quality Plan Last Up | N61: =+'General Information'!C28 -> 46222 | P61: 7 No of Approved Version of Schedule | T61: ='General Information'!C40 -> 1 | W61: ='HSE-Stat'!B11 -> Fatality | Y61: ='HSE-Stat'!D11 -> 0 | AA61: ='HSE-Stat'!E11 -> 0 | AB61: ='HSE-Stat'!F11 -> 0 | AC61: ='HSE-Stat'!G11 -> 0
C62: A | D62: B | E62: C | F62: D | G62: Processed | H62: with Designer | K62: 3 Safety Plan Approval | N62: =+'General Information'!C31 -> 46217 | P62: 8 Last Approved Schedule | T62: ='General Information'!C41 -> 45851 | W62: ='HSE-Stat'!B12 -> Fire Incident Cases | Y62: ='HSE-Stat'!D12 -> 0 | AA62: ='HSE-Stat'!E12 -> 0 | AB62: ='HSE-Stat'!F12 -> 0 | AC62: ='HSE-Stat'!G12 -> 0
B63: =IF('Quality-Stat'!D30="","",'Quality-Stat'!D30) -> 0 | C63: =IF('Quality-Stat'!E30="","",'Quality-Stat'!E30) -> 0 | D63: =IF('Quality-Stat'!F30="","",'Quality-Stat'!F30) -> 0 | E63: =IF('Quality-Stat'!G30="","",'Quality-Stat'!G30) -> 0 | F63: =IF('Quality-Stat'!H30="","",'Quality-Stat'!H30) -> 0 | G63: =IF('Quality-Stat'!I30="","",'Quality-Stat'!I30) -> 0 | H63: =IF('Quality-Stat'!J30="","",'Quality-Stat'!J30) -> 0 | I63: =IF('Quality-Stat'!K30="","",'Quality-Stat'!K30) -> 0 | J63: =IF('Quality-Stat'!L30="","",'Quality-Stat'!L30) -> 0 | K63: 4 Safety Plan Last Up | N63: =+'General Information'!C32 -> 46217 | P63: 9 BOQ Approval Date | T63: =+'General Information'!C44 -> 0 | W63: ='HSE-Stat'!B13 -> Vehicle Incident | Y63: ='HSE-Stat'!D13 -> 0 | AA63: ='HSE-Stat'!E13 -> 0 | AB63: ='HSE-Stat'!F13 -> 0 | AC63: ='HSE-Stat'!G13 -> 0
B64: =IF('Quality-Stat'!D31="","",'Quality-Stat'!D31) -> 23 | C64: =IF('Quality-Stat'!E31="","",'Quality-Stat'!E31) -> 0 | D64: =IF('Quality-Stat'!F31="","",'Quality-Stat'!F31) -> 22 | E64: =IF('Quality-Stat'!G31="","",'Quality-Stat'!G31) -> 0 | F64: =IF('Quality-Stat'!H31="","",'Quality-Stat'!H31) -> 1 | G64: =IF('Quality-Stat'!I31="","",'Quality-Stat'!I31) -> 22 | H64: =IF('Quality-Stat'!J31="","",'Quality-Stat'!J31) -> 0 | I64: =IF('Quality-Stat'!K31="","",'Quality-Stat'!K31) -> 0 | J64: =IF('Quality-Stat'!L31="","",'Quality-Stat'!L31) -> 23 | K64: 5 Execution Plan Approval | N64: =+'General Information'!C48 -> 46218 | P64: 10 No of Approved Version of BOQ | T64: ='General Information'!C45 -> 0 | W64: ='HSE-Stat'!B14 -> Property Damages | Y64: ='HSE-Stat'!D14 -> 0 | AA64: ='HSE-Stat'!E14 -> 0 | AB64: ='HSE-Stat'!F14 -> 0 | AC64: ='HSE-Stat'!G14 -> 0
B65: =IF('Quality-Stat'!D32="","",'Quality-Stat'!D32) -> 19 | C65: =IF('Quality-Stat'!E32="","",'Quality-Stat'!E32) -> 0 | D65: =IF('Quality-Stat'!F32="","",'Quality-Stat'!F32) -> 18 | E65: =IF('Quality-Stat'!G32="","",'Quality-Stat'!G32) -> 0 | F65: =IF('Quality-Stat'!H32="","",'Quality-Stat'!H32) -> 1 | G65: =IF('Quality-Stat'!I32="","",'Quality-Stat'!I32) -> 18 | H65: =IF('Quality-Stat'!J32="","",'Quality-Stat'!J32) -> 0 | I65: =IF('Quality-Stat'!K32="","",'Quality-Stat'!K32) -> 0 | J65: =IF('Quality-Stat'!L32="","",'Quality-Stat'!L32) -> 19 | K65: Invoices Summary | V65: Proactive | W65: ='HSE-Stat'!B15 -> Induction Training | Y65: ='HSE-Stat'!D15 -> 0 | AA65: ='HSE-Stat'!E15 -> 1 | AB65: ='HSE-Stat'!F15 -> 4 | AC65: ='HSE-Stat'!G15 -> 4
B66: =IF('Quality-Stat'!D33="","",'Quality-Stat'!D33) -> 0 | C66: =IF('Quality-Stat'!E33="","",'Quality-Stat'!E33) -> 0 | D66: =IF('Quality-Stat'!F33="","",'Quality-Stat'!F33) -> 0 | E66: =IF('Quality-Stat'!G33="","",'Quality-Stat'!G33) -> 0 | F66: =IF('Quality-Stat'!H33="","",'Quality-Stat'!H33) -> 0 | G66: =IF('Quality-Stat'!I33="","",'Quality-Stat'!I33) -> 0 | H66: =IF('Quality-Stat'!J33="","",'Quality-Stat'!J33) -> 0 | I66: =IF('Quality-Stat'!K33="","",'Quality-Stat'!K33) -> 0 | J66: =IF('Quality-Stat'!L33="","",'Quality-Stat'!L33) -> 0 | K66: Total Submitted Invoices | M66: ='Invoice Log'!U3 -> 0 | N66: Submitted Invoices (SAR) | Q66: ='Invoice Log'!Y3 -> 7768175.4 | S66: Contract Value (SR) | T66: =N4 -> 33040004 | W66: ='HSE-Stat'!B16 -> No.of Internal Training | Y66: ='HSE-Stat'!D16 -> 2 | AA66: ='HSE-Stat'!E16 -> 5 | AB66: ='HSE-Stat'!F16 -> 19 | AC66: ='HSE-Stat'!G16 -> 19
B67: =IF('Quality-Stat'!D34="","",'Quality-Stat'!D34) -> 0 | C67: =IF('Quality-Stat'!E34="","",'Quality-Stat'!E34) -> 0 | D67: =IF('Quality-Stat'!F34="","",'Quality-Stat'!F34) -> 0 | E67: =IF('Quality-Stat'!G34="","",'Quality-Stat'!G34) -> 0 | F67: =IF('Quality-Stat'!H34="","",'Quality-Stat'!H34) -> 0 | G67: =IF('Quality-Stat'!I34="","",'Quality-Stat'!I34) -> 0 | H67: =IF('Quality-Stat'!J34="","",'Quality-Stat'!J34) -> 0 | I67: =IF('Quality-Stat'!K34="","",'Quality-Stat'!K34) -> 0 | J67: =IF('Quality-Stat'!L34="","",'Quality-Stat'!L34) -> 0 | K67: PM Approved Invoices | M67: ='Invoice Log'!U5 -> 3 | N67: PM Approved Invoices (SAR) | Q67: ='Invoice Log'!Y5 -> 7770175.4 | S67: Planned Value (SR) | T67: =G21 -> 6317560.7 | W67: ='HSE-Stat'!B17 -> No.of Internal Audit | Y67: ='HSE-Stat'!D17 -> 0 | AA67: ='HSE-Stat'!E17 -> 0 | AB67: ='HSE-Stat'!F17 -> 1 | AC67: ='HSE-Stat'!G17 -> 1
B68: =SUM(B63:B67) -> 42 | C68: =SUM(C63:C67) -> 0 | D68: =SUM(D63:D67) -> 40 | E68: =SUM(E63:E67) -> 0 | F68: =SUM(F63:F67) -> 2 | G68: =SUM(G63:G67) -> 40 | H68: =SUM(H63:H67) -> 0 | I68: =SUM(I63:I67) -> 0 | J68: =SUM(J63:J67) -> 42 | K68: No of Paid Invoices | M68: ='Invoice Log'!U6 -> 2 | N68: Paid Invoices (SAR) | Q68: ='Invoice Log'!Y6 -> 3778784.9 | S68: Earned Value (SR) | T68: =H21 -> 11020158 | W68: ='HSE-Stat'!B18 -> No. of Toolbox Talks | Y68: ='HSE-Stat'!D18 -> 1 | AA68: ='HSE-Stat'!E18 -> 4 | AB68: ='HSE-Stat'!F18 -> 18 | AC68: ='HSE-Stat'!G18 -> 18
K69: No of Pending Invoices | M69: =M67-M68 -> 1 | N69: Last Submitted Period | S69: Submitted (SAR) | T69: =Q66 -> 7768175.4 | W69: ='HSE-Stat'!B19 -> Safety Awards/Incentives | Y69: ='HSE-Stat'!D19 -> 0 | AA69: ='HSE-Stat'!E19 -> 0 | AB69: ='HSE-Stat'!F19 -> 0 | AC69: ='HSE-Stat'!G19 -> 0
B70: Total Materials | C70: Total Number of P.O. | D70: Actual P.O. To Date | E70: Remaining P.O | F70: Material on Site | G70: Remaining Materials | H70: Material Delivery Completion (Date) | K70: Advance Payment % | M70: ='Invoice Log'!M3 -> 0 | N70: Advance Payment (SAR) | Q70: ='Invoice Log'!Q3 -> 0 | S70: PM Approved (SAR) | T70: =Q67 -> 7770175.4 | V70: Latest Contract Change Order Log
C71: A | D71: B | E71: C | F71: D | G71: Processed | K71: Retention % | M71: ='Invoice Log'!M4 -> 0 | N71: Retention (SAR) | Q71: ='Invoice Log'!Q4 -> 0 | S71: Total Paid (SAR) | T71: =Q68 -> 3778784.9
B72: =IF('Quality-Stat'!D40="","",'Quality-Stat'!D40) -> 0 | C72: =IF('Quality-Stat'!E40="","",'Quality-Stat'!E40) -> 0 | D72: =IF('Quality-Stat'!F40="","",'Quality-Stat'!F40) | E72: =IF('Quality-Stat'!G40="","",'Quality-Stat'!G40) -> 0 | F72: =IF('Quality-Stat'!H40="","",'Quality-Stat'!H40) -> 0 | G72: =IF('Quality-Stat'!I40="","",'Quality-Stat'!I40) -> 0 | H72: ='Quality-Stat'!J40 -> 0 | K72: Deduction / Penalties % | M72: ='Invoice Log'!M5 -> 6.053268e-05 | N72: Deduction / Penalties (SAR) | Q72: ='Invoice Log'!M6 -> 2000 | V72: CCO No. | W72: Date Added | X72: Description of Change | AC72: Status | AD72: Cost | AE72: Sch Impact (Months) | AF72: Date Approved | AG72: Duration
B73: =IF('Quality-Stat'!D41="","",'Quality-Stat'!D41) -> 6 | C73: =IF('Quality-Stat'!E41="","",'Quality-Stat'!E41) -> 6 | D73: =IF('Quality-Stat'!F41="","",'Quality-Stat'!F41) -> 1 | E73: =IF('Quality-Stat'!G41="","",'Quality-Stat'!G41) -> 5 | F73: =IF('Quality-Stat'!H41="","",'Quality-Stat'!H41) -> 1 | G73: =IF('Quality-Stat'!I41="","",'Quality-Stat'!I41) -> 5 | H73: ='Quality-Stat'!J41 -> 46356 | K73: Resources at Site
B74: =IF('Quality-Stat'!D42="","",'Quality-Stat'!D42) -> 3 | C74: =IF('Quality-Stat'!E42="","",'Quality-Stat'!E42) -> 3 | D74: =IF('Quality-Stat'!F42="","",'Quality-Stat'!F42) -> 3 | E74: =IF('Quality-Stat'!G42="","",'Quality-Stat'!G42) -> 0 | F74: =IF('Quality-Stat'!H42="","",'Quality-Stat'!H42) -> 3 | G74: =IF('Quality-Stat'!I42="","",'Quality-Stat'!I42) -> 0 | H74: ='Quality-Stat'!J42 -> 46277 | K74: Head Count - Non Manual | O74: Head Count - Manual | S74: Total Head Count | V74: =CCO!A3 -> 0 | W74: =CCO!B3 -> 0 | X74: =CCO!C3 -> 0 | AC74: =CCO!D3 -> 0 | AD74: =CCO!E3 -> 0 | AE74: =CCO!F3 -> 0 | AF74: =CCO!G3 -> 0 | AG74: =CCO!H3 -> 0
B75: =IF('Quality-Stat'!D43="","",'Quality-Stat'!D43) -> 0 | C75: =IF('Quality-Stat'!E43="","",'Quality-Stat'!E43) -> 0 | D75: =IF('Quality-Stat'!F43="","",'Quality-Stat'!F43) -> 0 | E75: =IF('Quality-Stat'!G43="","",'Quality-Stat'!G43) -> 0 | F75: =IF('Quality-Stat'!H43="","",'Quality-Stat'!H43) -> 0 | G75: =IF('Quality-Stat'!I43="","",'Quality-Stat'!I43) -> 0 | H75: ='Quality-Stat'!J43 -> 0 | K75: Planned | L75: Actual | M75: Next Month Forecast | N75: Saudi Staff | O75: Planned | P75: Actual | Q75: Next Month Forecast | R75: Saudi Staff | S75: Total Plan | T75: Total Actual | U75: Variance
B76: =IF('Quality-Stat'!D44="","",'Quality-Stat'!D44) -> 0 | C76: =IF('Quality-Stat'!E44="","",'Quality-Stat'!E44) -> 0 | D76: =IF('Quality-Stat'!F44="","",'Quality-Stat'!F44) -> 0 | E76: =IF('Quality-Stat'!G44="","",'Quality-Stat'!G44) -> 0 | F76: =IF('Quality-Stat'!H44="","",'Quality-Stat'!H44) -> 0 | G76: =IF('Quality-Stat'!I44="","",'Quality-Stat'!I44) -> 0 | H76: ='Quality-Stat'!J44 -> 0 | K76: =Manpower!A20 -> 13 | L76: =Manpower!B20 -> 27 | M76: =Manpower!F20 -> 13 | N76: =Manpower!H20 -> 0 | O76: =L86 -> 15 | P76: =M86 -> 67 | Q76: =Manpower!F24 -> 169 | R76: =Manpower!H24 -> 0 | S76: =K76+O76 -> 28 | T76: =L76+P76 -> 94 | U76: =+T76-S76 -> 66 | V76: =CCO!A4 | W76: =CCO!B4 | X76: =CCO!C4 | AC76: =IF(CCO!D4="","",CCO!D4) | AD76: =CCO!E4 | AE76: =CCO!F4 | AF76: =CCO!G4 | AG76: =CCO!H4
B77: =IF('Quality-Stat'!D45="","",'Quality-Stat'!D45) -> 9 | C77: =IF('Quality-Stat'!E45="","",'Quality-Stat'!E45) -> 9 | D77: =IF('Quality-Stat'!F45="","",'Quality-Stat'!F45) -> 4 | E77: =IF('Quality-Stat'!G45="","",'Quality-Stat'!G45) -> 5 | F77: =IF('Quality-Stat'!H45="","",'Quality-Stat'!H45) -> 4 | G77: =IF('Quality-Stat'!I45="","",'Quality-Stat'!I45) -> 5 | H77: =MAX(H72:H76) -> 46356 | K77: Manpower Breakdown by Trade | R77: Major Equipment
K78: Key Trade | L78: Planned | M78: Actual | R78: Type | S78: Planned | T78: Actual | U78: Idle | V78: =CCO!A5 | W78: =CCO!B5 | X78: =CCO!C5 | AC78: =IF(CCO!D5="","",CCO!D5) | AD78: =CCO!E5 | AE78: =CCO!F5 | AF78: =CCO!G5 | AG78: =CCO!H5
K79: =+Manpower!N23 -> General Labor | L79: =Manpower!N24 -> 6 | M79: =Manpower!N25 -> 6 | R79: =+Manpower!$B$49 -> Excavator | S79: =+Manpower!B50 -> 0 | T79: =+Manpower!B51 -> 7 | U79: =+Manpower!B52 -> 0
E80: =Schedule!F3 -> Active Schedule Activities | K80: =+Manpower!P23 -> Carpenter | L80: =Manpower!P24 -> 0 | M80: =Manpower!P25 -> 0 | R80: =+Manpower!$D$49 -> Loader | S80: =+Manpower!D50 -> 0 | T80: =+Manpower!D51 -> 6 | U80: =+Manpower!D52 -> 0 | V80: Major Quantity Trackers
A81: =Schedule!B4 -> Not Started | B81: =Schedule!C4 -> In Progress | C81: =Schedule!D4 -> Completed | D81: =Schedule!E4 -> % | E81: =Schedule!F4 -> Active | F81: =Schedule!G4 -> Ahead | G81: =Schedule!H4 -> On | H81: =Schedule!I4 -> Behind | ... J81: =Schedule!K4 -> 0 | K81: =+Manpower!R23 -> Plumber | L81: =+Manpower!R24 -> 0 | M81: =Manpower!R25 -> 0 | R81: =+Manpower!$F$49 -> Dozer | S81: =+Manpower!F50 -> 2 | T81: =+Manpower!F51 -> 10 | U81: =+Manpower!F52 -> 0 | V81: BOQ N0. | W81: Item Description | AB81: Total Qty | AC81: Measu Unit | AD81: Plan to Date | AE81: Act to Date | AF81: Remaining | AG81: Variance
A82: =Schedule!B5 -> 199 | B82: =Schedule!C5 -> 34 | C82: =Schedule!D5 -> 148 | D82: =Schedule!E5 -> 0.38845144 | E82: =Schedule!F5 -> 34 | F82: =Schedule!G5 -> 30 | G82: =Schedule!H5 -> 0 | H82: =Schedule!I5 -> 4 | I82: =Schedule!J5 -> 26 | K82: =+Manpower!T23 -> Operator | L82: =Manpower!T24 -> 4 | M82: =Manpower!T25 -> 34 | R82: =+Manpower!$H$49 -> Dump Truck | S82: =+Manpower!H50 -> 4 | T82: =+Manpower!H51 -> 20 | U82: =+Manpower!H52 -> 0 | V82: ='Major Quantities'!A2 -> B1.31 22 00.01 | W82: ='Major Quantities'!B2 -> Roadway Excavation for cuttings (all types of soil) | AB82: ='Major Quantities'!C2 -> 252114.84 | AC82: ='Major Quantities'!D2 -> m³ | AD82: ='Major Quantities'!E2 -> 148344.47 | AE82: ='Major Quantities'!F2 -> 222090.04 | AF82: ='Major Quantities'!G2 -> 30024.804 | AG82: ='Major Quantities'!H2 -> 73745.57
C83: =Schedule!D6 -> Free Float Management (Total) | G83: =Schedule!H6 -> Failed Start Activities | K83: =+Manpower!V23 -> Steel Fixer | L83: =+Manpower!V24 -> 0 | M83: =+Manpower!V25 -> 0 | R83: =+Manpower!$J$49 -> Crane | S83: =+Manpower!J50 -> 0 | T83: =+Manpower!J51 -> 3 | U83: =+Manpower!J52 -> 0 | V83: ='Major Quantities'!A3 -> B1.31 22 00.02 | W83: ='Major Quantities'!B3 -> Embankments to the ROW with common / suitable excavated material or with suitable imported material | AB83: ='Major Quantities'!C3 -> 221841.34 | AC83: ='Major Quantities'!D3 -> m³ | AD83: ='Major Quantities'!E3 -> 130531.24 | AE83: ='Major Quantities'!F3 -> 183569.4 | AF83: ='Major Quantities'!G3 -> 38271.936 | AG83: ='Major Quantities'!H3 -> 53038.16
C84: =Schedule!D7 -> Greater Than 14 Days | E84: =Schedule!F7 -> Less Than 14 Days | K84: =+Manpower!X23 -> Mason | L84: =+Manpower!X24 -> 0 | M84: =+Manpower!X25 -> 0 | R84: =+Manpower!$L$49 -> Grader | S84: =+Manpower!L50 -> 0 | T84: =+Manpower!L51 -> 4 | U84: =+Manpower!L52 -> 0 | V84: ='Major Quantities'!A4 -> B1.31 22 00.05 | W84: ='Major Quantities'!B4 -> Subgrade | AB84: ='Major Quantities'!C4 -> 21604 | AC84: ='Major Quantities'!D4 -> m³ | AD84: ='Major Quantities'!E4 -> 0 | AE84: ='Major Quantities'!F4 -> 0 | AF84: ='Major Quantities'!G4 -> 21604 | AG84: ='Major Quantities'!H4 -> 0
A85: =Schedule!B8 -> This Week | B85: =Schedule!C8 -> Diff | C85: =Schedule!D8 -> Last Week | D85: =Schedule!E8 -> This Week | E85: =Schedule!F8 -> Last Week | F85: =Schedule!G8 -> This Week | G85: =Schedule!H8 -> Last Week | H85: =Schedule!I8 -> This Week | ... J85: =Schedule!K8 -> 0 | K85: =+Manpower!Z23 -> Others | L85: =+Manpower!Z24 -> 5 | M85: =+Manpower!Z25 -> 27 | R85: =+Manpower!$N$49 -> Other | S85: =+Manpower!N50 -> 3 | T85: =+Manpower!N51 -> 11 | U85: =+Manpower!N52 -> 0 | V85: ='Major Quantities'!A5 -> B1.32 11 23.01 | W85: ='Major Quantities'!B5 -> Aggregate base course | AB85: ='Major Quantities'!C5 -> 14403 | AC85: ='Major Quantities'!D5 -> m³ | AD85: ='Major Quantities'!E5 -> 0 | AE85: ='Major Quantities'!F5 -> 0 | AF85: ='Major Quantities'!G5 -> 14403 | AG85: ='Major Quantities'!H5 -> 0
A86: =Schedule!B9 -> 168 | B86: =Schedule!C9 -> 15 | C86: =Schedule!D9 -> 24 | D86: =Schedule!E9 -> 22 | E86: =Schedule!F9 -> 215 | F86: =Schedule!G9 -> 211 | G86: =Schedule!H9 -> 25 | H86: =Schedule!I9 -> 29 | I86: =Schedule!J9 -> -4 | K86: Total | L86: =SUM(L79:L85) -> 15 | M86: =SUM(M79:M85) -> 67 | R86: Total | S86: =SUM(S79:S85) -> 9 | T86: =SUM(T79:T85) -> 61 | U86: =SUM(U79:U85) -> 0 | V86: ='Major Quantities'!A6 -> B1.32 11 26.01 | W86: ='Major Quantities'!B6 -> Bituminous base course (Grading I - Class A), including Prime Coat (MC1) and tack coat (RC2) (if any) | AB86: ='Major Quantities'!C6 -> 7129 | AC86: ='Major Quantities'!D6 -> m³ | AD86: ='Major Quantities'!E6 -> 0 | AE86: ='Major Quantities'!F6 -> 0 | AF86: ='Major Quantities'!G6 -> 7129 | AG86: ='Major Quantities'!H6 -> 0
P87: Top Issues and Risks
E88: ='Weekly Photos'!L23 -> Installation of Manhole Works at Local 29 for Storm Drainage | K88: ='Weekly Photos'!B4 -> Cutting Works for Local 17 | P88: Top 5 Issues
P89: Issue No | Q89: Date Identified | R89: Issue Description | V89: Responsible | W89: Action Taken | Z89: Mitigation | AE89: Current Status | AF89: Expected/Actual Closure | AG89: Duration Elapsed
P90: =IF(+Issues!B11="","",+Issues!B11) -> 1 | Q90: =IF(+Issues!C11="","",+Issues!C11) | R90: =IF(+Issues!D11="","",+Issues!D11) | V90: =IF(+Issues!E11="","",+Issues!E11) | W90: =IF(+Issues!F11="","",+Issues!F11) | AE90: =IF(+Issues!H11="","",+Issues!H11) | AF90: =IF(+Issues!I11="","",+Issues!I11) | AG90: =IF(+Issues!J11="","",+Issues!J11) -> 0
P91: =IF(+Issues!B12="","",+Issues!B12) -> 2 | Q91: =IF(+Issues!C12="","",+Issues!C12) | R91: =IF(+Issues!D12="","",+Issues!D12) | V91: =IF(+Issues!E12="","",+Issues!E12) | W91: =IF(+Issues!F12="","",+Issues!F12) | AE91: =IF(+Issues!H12="","",+Issues!H12) | AF91: =IF(+Issues!I12="","",+Issues!I12) | AG91: =IF(+Issues!J12="","",+Issues!J12) -> 0
P92: =IF(+Issues!B13="","",+Issues!B13) -> 3 | Q92: =IF(+Issues!C13="","",+Issues!C13) | R92: =IF(+Issues!D13="","",+Issues!D13) | V92: =IF(+Issues!E13="","",+Issues!E13) | W92: =IF(+Issues!F13="","",+Issues!F13) | AE92: =IF(+Issues!H13="","",+Issues!H13) | AF92: =IF(+Issues!I13="","",+Issues!I13) | AG92: =IF(+Issues!J13="","",+Issues!J13) -> 0
P93: =IF(+Issues!B14="","",+Issues!B14) -> 4 | Q93: =IF(+Issues!C14="","",+Issues!C14) | R93: =IF(+Issues!D14="","",+Issues!D14) | V93: =IF(+Issues!E14="","",+Issues!E14) | W93: =IF(+Issues!F14="","",+Issues!F14) | AE93: =IF(+Issues!H14="","",+Issues!H14) | AF93: =IF(+Issues!I14="","",+Issues!I14) | AG93: =IF(+Issues!J14="","",+Issues!J14) -> 0
P94: =IF(+Issues!B15="","",+Issues!B15) -> 5 | Q94: =IF(+Issues!C15="","",+Issues!C15) | R94: =IF(+Issues!D15="","",+Issues!D15) | V94: =IF(+Issues!E15="","",+Issues!E15) | W94: =IF(+Issues!F15="","",+Issues!F15) | AE94: =IF(+Issues!H15="","",+Issues!H15) | AF94: =IF(+Issues!I15="","",+Issues!I15) | AG94: =IF(+Issues!J15="","",+Issues!J15)

Sheet FIR summary 
A1: Project Name | C1: =+'General Information'!C3:I3 -> Road Development for the Support Services Area at the Second Industrial City in Makkah (Al-Akayshiyah) | F1: Total FIR Amount | I1: =+Total -> 178710 | J1: Cum Previous FIR up to 29-09-2026 | K1: Cum up To Date FRI
A2: Project ID | C2: =+'General Information'!C4:I4 -> MKH2-02-004 | E2: Project Budget | F2: 33040004 | J2: 7582918.3 | K2: =J2+778382.62+971203.72+178710 -> 9511214.6
A3: Date Period | C3: =+F3-6 -> 46309 | E3: To | F3: =+'General Information'!L1 -> 46315
A5: BOQ Item # | B5: BOQ Description | C5: FIR # | D5: FIR DATE | E5: FIR Description | F5: Unit | G5: Unit Rate | H5: Current Pariod Quantity | I5: Total (SR)
A6: ROAD WORKS | K6: =+K2/33040004 -> 0.28786966
A7: B1.31 22 00.01 | B7: Roadway Excavation for cuttings (all types of soil) | F7: m3 | G7: 22 | I7: =+H7*G7 -> 0
F8: m3 | G8: 22 | I8: =+H8*G8 -> 0
A9: B1.31 22 00.02 | B9: Embankments to the ROW with common / suitable excavated material or with suitable imported material | F9: m3 | G9: 16 | I9: =+H9*G9 -> 0
F10: m3 | G10: 16 | I10: =+H10*G10 -> 0
F11: m3 | G11: 16 | I11: =+H11*G11 -> 0
F12: m3 | G12: 16 | I12: =+H12*G12 -> 0
A13: B1.31 22 00.03 | B13: Subgrade | C13: MKH2-02-004-ENJ-TS9-1-CVL-FIR-0058-00 | D13: 15/10/2026 | E13: Inspection of Survey and Compaction test for subgrade 1st layer for local road 28 from st: 0+300 to 0+650 | F13: m3 | G13: 22 | H13: 1021.75 | I13: =+H13*G13 -> 22478.5
A14: B1.32 11 23.01 | B14: Aggregate base course | F14: m3 | G14: 52 | I14: =+H14*G14 -> 0
A15: B1.32 11 26.01 | B15: Bituminous base course (Grading I - Class A), including Prime Coat (MC1) and tack coat (RC2) (if any) | F15: m3 | G15: 560 | I15: =+H15*G15 -> 0
A16: B1.32 14 13.01 | B16: Precast Concrete Kerb, Type K1-A | F16: m | G16: 65 | I16: =+H16*G16 -> 0
A17: B1.32 14 13.02 | B17: Precast Concrete Kerb, Type K4 | F17: m | G17: 55 | I17: =+H17*G17 -> 0
A18: B1.32 14 13.03 | B18: Precast Concrete Kerb, Type K1-B | F18: m | G18: 55 | I18: =+H18*G18 -> 0
A19: B1.32 14 13.04 | B19: Depressed curbs Type K2 | F19: m | G19: 55 | I19: =+H19*G19 -> 0
A20: B1.32 14 13.13.01 | B20: 60mm thick - Interlocking block pavers for sidewalk/footpath | F20: m2 | G20: 70 | I20: =+H20*G20 -> 0
A21: B1.32 17 23.01 | B21: Retroreflective Thermoplastic White paiting and traffic lines | F21: m² | G21: 45 | I21: =+H21*G21 -> 0
A22: B1.32 17 23.02 | B22: Retroreflective Thermoplastic Yellow paiting and traffic lines | F22: m² | G22: 45 | I22: =+H22*G22 -> 0
A23: B1.32 17 23.06 | B23: (Speed Hump) with retroreflectiveThermoplastic yellow | F23: Unit | G23: 12000 | I23: =+H23*G23 -> 0
A24: B1.10 14 53.01 | B24: Traffic signs, ground mounted, Sheet Alumenium, (breakaway)Single post, with all accessories | F24: Unit | G24: 1800 | I24: =+H24*G24 -> 0
A25: STORM WATER DRAINAGE | I25: =+H25*G25 -> 0
A26: B6.33 42 11.07 | B26: Depth: 0.0m - 1.5m | F26: m | G26: 450 | I26: =+H26*G26 -> 0
A27: B6.33 42 11.08 | B27: Depth: 1.51m - 2.5m | F27: m | G27: 600 | I27: =+H27*G27 -> 0
A28: B6.33 42 11.09 | B28: Depth: > 2.5m | F28: m | G28: 1500 | I28: =+H28*G28 -> 0
A29: B6.33 42 11.10 | B29: Depth: 0.0m - 1.5m | C29: MKH2-02-004-ENJ-TS9-1-STR-FIR-0095-00 | D29: 13/10/2026 | E29: Relative Density Test (RDT) above Storm pipeline,local road ( 11 ) Line-M-8 ,GRP Pipe Dia(500),Depth (0.00:1.50), MH-M-8-5 TO MH-M-8-6 , MH-M-8-6 TO MH-M-8-7 . | F29: m | G29: 550 | H29: 39.53 | I29: =+H29*G29 -> 21741.5
F30: m | G30: 550 | I30: =+H30*G30 -> 0
F31: m | G31: 550 | I31: =+H31*G31 -> 0
A32: B6.33 42 11.11 | B32: Depth: 1.51m - 2.5m | F32: m | G32: 700 | I32: =+H32*G32 -> 0
A33: B6.33 42 11.12 | B33: Depth: more than 2.5m | F33: m | G33: 2000 | I33: =+H33*G33 -> 0
A34: B6.33 42 11.13 | B34: Depth: 0.0m - 1.5m | C34: MKH2-02-004-ENJ-TS9-1-STR-FIR-0094-00 | D34: 13/10/2026 | E34: Relative Density Test (RDT) above Storm pipeline,local road ( 11 ) Line-M-8 ,GRP Pipe Dia(600),Depth (0.00:1.50), MH-M-8-2 TO MH-M-8-3 , MH-M-8-3 TO MH-M-8-4 , MH-M-8-4 TO MH-M-8-5 | F34: m | G34: 650 | H34: 59.26 | I34: =+H34*G34 -> 38519
C35: MKH2-02-004-ENJ-TS9-1-STR-FIR-0099-00 | D35: 14/10/2026 | E35: Excavation & Relative Density Test (RDT) for bedding under for storm pipeline of local road ( 29 ) Line-M-13 ,GRP Pipe Dia(600),Depth (0.00:1.50), MH-M-13-2 TO MH-M-13-3 , MH-M-13-3 TO MH-M-13-4 , MH-M-13-4 TO MH-M-13-5 | F35: m | G35: 650 | H35: 59.02 | I35: =+H35*G35 -> 38363
A36: B6.33 42 11.16 | B36: Depth: 0.0m - 1.5m | C36: MKH2-02-004-ENJ-TS9-1-STR-FIR-0097-00 | D36: 13/10/2026 | E36: Survey for top of pipe and installation of Storm pipeline,local road ( 29 ) Line-M-13 ,GRP Pipe Dia(700),Depth (1.51:2.50), MH-M-13 TO MH-M-13-1 | F36: m | G36: 750 | H36: 8.54 | I36: =+H36*G36 -> 6405
F37: m | G37: 750 | I37: =+H37*G37 -> 0
F38: m | G38: 750 | I38: =+H38*G38 -> 0
F39: m | G39: 750 | I39: =+H39*G39 -> 0
F40: m | G40: 750 | I40: =+H40*G40 -> 0
F41: m | G41: 750 | I41: =+H41*G41 -> 0
A42: B6.33 42 11.17 | B42: Depth: 1.51m - 2.5m | C42: MKH2-02-004-ENJ-TS9-1-STR-FIR-0098-00 | D42: 13/10/2026 | E42: Survey for top of pipe and installation of Storm pipeline,local road ( 29 ) Line-M-13 ,GRP Pipe Dia(700),Depth (0.00:1.50), MH-M-13-1 TO MH-M-13-2 | F42: m | G42: 900 | H42: 14.67 | I42: =+H42*G42 -> 13203
F43: m | G43: 900 | I43: =+H43*G43 -> 0
F44: m | G44: 900 | I44: =+H44*G44 -> 0
A45: B6.33 42 11.19 | B45: Depth: 0.0m - 1.5m | F45: m | G45: 1000 | I45: =+H45*G45 -> 0
F46: m | G46: 900 | I46: =+H46*G46 -> 0
A47: B6.33 42 11.20 | B47: Depth: 1.51m - 2.5m | F47: m | G47: 1100 | I47: =+H47*G47 -> 0
A48: B6.33 42 11.23 | B48: Depth: 1.51m - 2.5m | F48: m | G48: 1800 | I48: =+H48*G48 -> 0
F49: m | G49: 1800 | I49: =+H49*G49 -> 0
A50: B6.33 42 11.24 | B50: Depth: 2.51m - 3.5m | F50: m | G50: 2000 | I50: =+H50*G50 -> 0
F51: m | G51: 2000 | I51: =+H51*G51 -> 0
F52: m | G52: 2000 | I52: =+H52*G52 -> 0
A53: B6.33 42 11.28 | B53: Depth: > 3.5m | F53: m | G53: 4500 | I53: =+H53*G53 -> 0
F54: m | G54: 4500 | I54: =+H54*G54 -> 0
F55: m | G55: 2000 | I55: =+H55*G55 -> 0
A56: B6.33 05 39.02 | B56: MH depth 1.51 - 2.5m | C56: MKH2-02-004-ENJ-TS9-1-STR-FIR-0096-00 | D56: 13/10/2026 | E56: Installation for base precast manhole storm network at line M dia ( 1200 mm ) (MH-M-8-3 , MH-M-8-4 , MH-M-8-5 , MH-M-8-6 , MH-M-8-7, MH-M-8-8 ) depth (1.51 : 2.50 ) | F56: nr | G56: 18000 | H56: 1.5 | I56: =+H56*G56 -> 27000
F57: nr | G57: 18000 | I57: =+H57*G57 -> 0
F58: nr | G58: 18000 | I58: =+H58*G58 -> 0
A59: B6.33 05 39.05 | B59: MH depth 1.51 - 2.5m | C59: MKH2-02-004-ENJ-TS9-1-STR-FIR-0105-00 | D59: 14/10/2026 | E59: Installation for base precast manhole storm network at line M-13 dia ( 1500 mm ) (MH-M-13-1 , MH-M-13-2 ) depth (1.51 : 2.50 ) | F59: nr | G59: 22000 | H59: 0.5 | I59: =+H59*G59 -> 11000
F60: nr | G60: 22000 | I60: =+H60*G60 -> 0
F61: nr | G61: 22000 | I61: =+H61*G61 -> 0
A62: B6.33 05 39.06 | B62: MH depth more than 2.5 m | F62: nr | G62: 35000 | I62: =+H62*G62 -> 0
