Workbook
Name At_risk: #REF!
Name atrisk_total_net_rent_for_cashflow: #REF!
Name Audit_Category: #REF!
Name BC: #REF!
Name BCTemp: #REF!
Name BQ: #REF!
Name car_park_cash_flow: #REF!
Name CEMP_Category: #REF!
Name CESMM3rdDiv: #REF!
Name Channel_Template: #REF!
Name ChannelSched: #REF!
Name complete: #REF!
Name completion_date: #REF!
Name Conc_01: #REF!
Name CONC_06: #REF!
Name CONC_09: #REF!
Name CONC_11: #REF!
Name CONC_16: #REF!
Name CONC_23: #REF!
Name CulType: #REF!
Name CulvertSched: #REF!
Name CUlvertType: #REF!
Name CulvSched: #REF!
Name Date: #REF!
Name EMP_Category: #REF!
Name Exclusions: #REF!
Name GG: #REF!
Name Incident_Tier: #REF!
Name Incident_Type: #REF!
Name Inside_Dia__ID: #REF!
Name IssEscStatus1: #REF!
Name IssEscStatus1: #REF!
Name IssEscStatus1: #REF!
Name IssEscStatus1: #REF!
Name K9B_1: #REF!
Name K9B_2: #REF!
Name KK: #REF!
Name kpi: #REF!
Name LAB_PART: #REF!
Name LAB_UPLIFT: #REF!
Name Manhole: #REF!
Name MATL_PART: #REF!
Name MS_DW_1: #REF!
Name MS_DW_10: #REF!
Name MS_DW_13: #REF!
Name MS_DW_14: #REF!
Name MS_DW_15: #REF!
Name MS_DW_16: #REF!
Name MS_DW_2: #REF!
Name MS_DW_3: #REF!
Name MS_DW_4: #REF!
Name MS_DW_5: #REF!
Name MS_DW_6: #REF!
Name MS_DW_7: #REF!
Name MS_DW_8: #REF!
Name MS_DW_9: #REF!
Name Pavement_Type: #REF!
Name PhaseCode: #REF!
Name PILE_1_MOOR: #REF!
Name PILE_10_Moor: #REF!

Sheet DB
A1: ='Weekly Progress Report'!$A$1 -> MODON - Weekly Progress Report - Construction Projects
B2: ='Weekly Progress Report'!$A$2 -> Contract General Information | J2: ='Weekly Progress Report'!G2 -> Key Dates | U2: ='Weekly Progress Report'!$M$2 -> Cost Summary (SR) | AD2: ='Weekly Progress Report'!$U$2 -> Performance Summary | AP2: ='Weekly Progress Report'!A67 -> Shop Drawings | AT2: ='Weekly Progress Report'!A76 -> Material Approval | AW2: ='Weekly Progress Report'!A85 -> Procurement Summary | BD2: ='Weekly Progress Report'!L67 -> Quality Reports | BT2: ='Weekly Progress Report'!L75 -> Key Submittals Approval Status | CD2: ='Weekly Progress Report'!L81 -> Invoices Summary | CR2: ='Weekly Progress Report'!L89 -> Resources at Site | CY2: ='Weekly Progress Report'!W67 -> Safety Statistics | FK2: ='Weekly Progress Report'!A94 -> Primavera P6 Schedule Status | FS2: ='Weekly Progress Report'!A103 -> Testing And Commissioning
A3: ='Weekly Progress Report'!AF1 -> Data Date | B3: ='Weekly Progress Report'!A3 -> Project Name | C3: ='Weekly Progress Report'!A4 -> Project ID | D3: ='Weekly Progress Report'!A5 -> Contractor | E3: ='Weekly Progress Report'!A6 -> Consultant | F3: ='Weekly Progress Report'!D4 -> Stage | G3: ='Weekly Progress Report'!D5 -> Status | H3: ='Weekly Progress Report'!D6 -> Modon PM | I3: ='Weekly Progress Report'!AA2 -> Project Scope | J3: ='Weekly Progress Report'!G3 -> Contract Award | K3: ='Weekly Progress Report'!G4 -> Contract Sign | L3: ='Weekly Progress Report'!G5 -> Site Handover | M3: ='Weekly Progress Report'!G6 -> Original Completion | N3: ='Weekly Progress Report'!$I$3 -> Contract Award (Hijri) | O3: ='Weekly Progress Report'!$I$4 -> Contract Sign (Hijri) | P3: ='Weekly Progress Report'!$I$5 -> Site Handover (Hijri) | Q3: ='Weekly Progress Report'!$I$6 -> Original Completion (Hijri) | R3: ='Weekly Progress Report'!$K$3 -> Revised Completion | S3: ='Weekly Progress Report'!$K$4 -> Committed Completion | T3: ='Weekly Progress Report'!$K$5 -> Forecast Completion | U3: ='Weekly Progress Report'!$M$3 -> Original Contract Value | V3: ='Weekly Progress Report'!$M$4 -> Revised Contract Value | W3: ='Weekly Progress Report'!$M$5 -> Estimate At Completion Value | X3: ='Weekly Progress Report'!$M$6 -> Potential Changes | Y3: ='Weekly Progress Report'!$Q$3 -> O&M Value | Z3: ='Weekly Progress Report'!$Q$4 -> Revised O&M Value | AA3: ='Weekly Progress Report'!$Q$5 -> Submitted Invoices (Gross Value) | AB3: ='Weekly Progress Report'!$Q$6 -> Total Deduction | AC3: Original Plan Value | AD3: ='Weekly Progress Report'!$U$3 -> Plan Value | AE3: ='Weekly Progress Report'!$U$4 -> Earn Value | AF3: ='Weekly Progress Report'!$W$3 -> Phys. Plan Value | AG3: ='Weekly Progress Report'!$W$4 -> Phys. Earn Value | AH3: ='Weekly Progress Report'!$Y$3 -> Quality Score | AI3: ='Weekly Progress Report'!$Y$5 -> Safety Score | AJ3: Weekly PV (SAR) | AK3: Weekly EV (SAR) | AL3: Weekly PV % | AM3: Weekly PV % | AN3: Weekly Phys PV% | AO3: Weekly Phys PV% | AP3: Total SD Planned | AQ3: SD Remaining | AR3: SD Pending | AS3: Total SD Submittals | AT3: Planned Materials Approv | AU3: Material Pending Approval | AV3: Materila Total Submittals | AW3: ='Weekly Progress Report'!C86 -> Total Materials | AX3: ='Weekly Progress Report'!D86 -> Total Number of P.O. | AY3: ='Weekly Progress Report'!E86 -> Actual P.O. To Date | AZ3: ='Weekly Progress Report'!F86 -> Remaining P.O | BA3: ='Weekly Progress Report'!G86 -> Material on Site | BB3: ='Weekly Progress Report'!H86 -> Remaining Materials | BC3: ='Weekly Progress Report'!I86 -> Material Delivery Completion (Date) | BD3: ="NCR "&'Weekly Progress Report'!N68 -> NCR Issued | BE3: ="NCR "&'Weekly Progress Report'!O68 -> NCR Closed | BF3: ="NCR "&'Weekly Progress Report'!P68 -> NCR Pending | BG3: ="NCR "&'Weekly Progress Report'!Q68 -> NCR Avg. Closing (Days) | BH3: ="SIR "&'Weekly Progress Report'!N68 -> SIR Issued | BI3: ="SIR "&'Weekly Progress Report'!O68 -> SIR Closed | BJ3: ="SIR "&'Weekly Progress Report'!P68 -> SIR Pending | BK3: ="SIR "&'Weekly Progress Report'!Q68 -> SIR Avg. Closing (Days) | BL3: ="MIR "&'Weekly Progress Report'!N68 -> MIR Issued | BM3: ="MIR "&'Weekly Progress Report'!O68 -> MIR Closed | BN3: ="MIR "&'Weekly Progress Report'!P68 -> MIR Pending | BO3: ="MIR "&'Weekly Progress Report'!Q68 -> MIR Avg. Closing (Days) | BP3: ="FIR "&'Weekly Progress Report'!N68 -> FIR Issued | BQ3: ="FIR "&'Weekly Progress Report'!O68 -> FIR Closed | BR3: ="FIR "&'Weekly Progress Report'!P68 -> FIR Pending | BS3: ="FIR "&'Weekly Progress Report'!Q68 -> FIR Avg. Closing (Days) | BT3: ='Weekly Progress Report'!L76 -> 1 Quality Plan Approval | BU3: ='Weekly Progress Report'!L77 -> 2 Quality Plan Last Up | BV3: ='Weekly Progress Report'!L78 -> 3 Safety Plan Approval | BW3: ='Weekly Progress Report'!L79 -> 4 Safety Plan Last Up | BX3: ='Weekly Progress Report'!L80 -> 5 Construction Plan Approval | BY3: ='Weekly Progress Report'!Q76 -> 6 Baseline Approval | BZ3: ='Weekly Progress Report'!Q77 -> 7 No of Approved Version of Schedule | CA3: ='Weekly Progress Report'!Q78 -> 8 Last Approved Schedule | CB3: ='Weekly Progress Report'!Q79 -> 9 BOQ Approval Date | CC3: ='Weekly Progress Report'!Q80 -> 10 No of Approved Version of BOQ | CD3: ='Weekly Progress Report'!L82 -> Total Submitted Invoices | CE3: ='Weekly Progress Report'!L83 -> PM Approved Invoices | CF3: ='Weekly Progress Report'!L84 -> No of Paid Invoices | CG3: ='Weekly Progress Report'!L85 -> No of Pending Invoices | CH3: ='Weekly Progress Report'!L86 -> Advance Payment % | CI3: ='Weekly Progress Report'!L87 -> Retention % | CJ3: ='Weekly Progress Report'!L88 -> Deduction / Penalties % | CK3: ='Weekly Progress Report'!O82 -> Submitted Invoices (SAR) | CL3: ='Weekly Progress Report'!O83 -> PM Approved Invoices (SAR) | CM3: ='Weekly Progress Report'!O84 -> Paid Invoices (SAR) | CN3: ='Weekly Progress Report'!O85 -> Last Submitted Period | CO3: ='Weekly Progress Report'!O86 -> Advance Payment (SAR) | CP3: ='Weekly Progress Report'!O87 -> Retention (SAR) | CQ3: ='Weekly Progress Report'!O88 -> Deduction / Penalties (SAR) | CR3: Planned Head Count | CS3: Actual Head Count | CT3: Saudi Staff | CU3: Labor Planned | CV3: Labor Actual | CW3: Equipment Planned | CX3: Equipment Actual | CY3: ="This Week "&'Weekly Progress Report'!X70 -> This Week Total Hours Worked | CZ3: ="This Week "&'Weekly Progress Report'!X71 -> This Week Safe Hours Worked | DA3: ="This Week "&'Weekly Progress Report'!X72 -> This Week LTI | DB3: ="This Week "&'Weekly Progress Report'!X73 -> This Week MTC (Healed w/o Disability) | DC3: ="This Week "&'Weekly Progress Report'!X74 -> This Week MTC (Healed w/ Disability) | DD3: ="This Week "&'Weekly Progress Report'!X75 -> This Week Near Miss | DE3: ="This Week "&'Weekly Progress Report'!X76 -> This Week First Aid Cases | DF3: ="This Week "&'Weekly Progress Report'!X77 -> This Week Fatality | DG3: ="This Week "&'Weekly Progress Report'!X78 -> This Week Fire Incident Cases | DH3: ="This Week "&'Weekly Progress Report'!X79 -> This Week Vehicle Incident | DI3: ="This Week "&'Weekly Progress Report'!X80 -> This Week Property Damages | DJ3: ="This Week "&'Weekly Progress Report'!X81 -> This Week Induction Training | DK3: ="This Week "&'Weekly Progress Report'!X82 -> This Week No.of Internal Training | DL3: ="This Week "&'Weekly Progress Report'!X83 -> This Week No.of Internal Audit | DM3: ="This Week "&'Weekly Progress Report'!X84 -> This Week No. of Toolbox Talks | DN3: ="This Week "&'Weekly Progress Report'!X85 -> This Week Safety Awards/Incentives | DO3: ="This Month "&'Weekly Progress Report'!X70 -> This Month Total Hours Worked | DP3: ="This Month "&'Weekly Progress Report'!X71 -> This Month Safe Hours Worked | DQ3: ="This Month "&'Weekly Progress Report'!X72 -> This Month LTI | DR3: ="This Month "&'Weekly Progress Report'!X73 -> This Month MTC (Healed w/o Disability) | DS3: ="This Month "&'Weekly Progress Report'!X74 -> This Month MTC (Healed w/ Disability) | DT3: ="This Month "&'Weekly Progress Report'!X75 -> This Month Near Miss | DU3: ="This Month "&'Weekly Progress Report'!X76 -> This Month First Aid Cases | DV3: ="This Month "&'Weekly Progress Report'!X77 -> This Month Fatality | DW3: ="This Month "&'Weekly Progress Report'!X78 -> This Month Fire Incident Cases | DX3: ="This Month "&'Weekly Progress Report'!X79 -> This Month Vehicle Incident | DY3: ="This Month "&'Weekly Progress Report'!X80 -> This Month Property Damages | DZ3: ="This Month "&'Weekly Progress Report'!X81 -> This Month Induction Training | EA3: ="This Month "&'Weekly Progress Report'!X82 -> This Month No.of Internal Training | EB3: ="This Month "&'Weekly Progress Report'!X83 -> This Month No.of Internal Audit | EC3: ="This Month "&'Weekly Progress Report'!X84 -> This Month No. of Toolbox Talks | ED3: ="This Month "&'Weekly Progress Report'!X85 -> This Month Safety Awards/Incentives | EE3: ="YTD "&'Weekly Progress Report'!X70 -> YTD Total Hours Worked | EF3: ="YTD "&'Weekly Progress Report'!X71 -> YTD Safe Hours Worked | EG3: ="YTD "&'Weekly Progress Report'!X72 -> YTD LTI | EH3: ="YTD "&'Weekly Progress Report'!X73 -> YTD MTC (Healed w/o Disability) | EI3: ="YTD "&'Weekly Progress Report'!X74 -> YTD MTC (Healed w/ Disability) | EJ3: ="YTD "&'Weekly Progress Report'!X75 -> YTD Near Miss | EK3: ="YTD "&'Weekly Progress Report'!X76 -> YTD First Aid Cases | EL3: ="YTD "&'Weekly Progress Report'!X77 -> YTD Fatality | EM3: ="YTD "&'Weekly Progress Report'!X78 -> YTD Fire Incident Cases | EN3: ="YTD "&'Weekly Progress Report'!X79 -> YTD Vehicle Incident | EO3: ="YTD "&'Weekly Progress Report'!X80 -> YTD Property Damages | EP3: ="YTD "&'Weekly Progress Report'!X81 -> YTD Induction Training | EQ3: ="YTD "&'Weekly Progress Report'!X82 -> YTD No.of Internal Training | ER3: ="YTD "&'Weekly Progress Report'!X83 -> YTD No.of Internal Audit | ES3: ="YTD "&'Weekly Progress Report'!X84 -> YTD No. of Toolbox Talks | ET3: ="YTD "&'Weekly Progress Report'!X85 -> YTD Safety Awards/Incentives | EU3: ="Cum "&'Weekly Progress Report'!X70 -> Cum Total Hours Worked | EV3: ="Cum "&'Weekly Progress Report'!X71 -> Cum Safe Hours Worked | EW3: ="Cum "&'Weekly Progress Report'!X72 -> Cum LTI | EX3: ="Cum "&'Weekly Progress Report'!X73 -> Cum MTC (Healed w/o Disability) | EY3: ="Cum "&'Weekly Progress Report'!X74 -> Cum MTC (Healed w/ Disability) | EZ3: ="Cum "&'Weekly Progress Report'!X75 -> Cum Near Miss | FA3: ="Cum "&'Weekly Progress Report'!X76 -> Cum First Aid Cases | FB3: ="Cum "&'Weekly Progress Report'!X77 -> Cum Fatality | FC3: ="Cum "&'Weekly Progress Report'!X78 -> Cum Fire Incident Cases | FD3: ="Cum "&'Weekly Progress Report'!X79 -> Cum Vehicle Incident | FE3: ="Cum "&'Weekly Progress Report'!X80 -> Cum Property Damages | FF3: ="Cum "&'Weekly Progress Report'!X81 -> Cum Induction Training | FG3: ="Cum "&'Weekly Progress Report'!X82 -> Cum No.of Internal Training | FH3: ="Cum "&'Weekly Progress Report'!X83 -> Cum No.of Internal Audit | FI3: ="Cum "&'Weekly Progress Report'!X84 -> Cum No. of Toolbox Talks | FJ3: ="Cum "&'Weekly Progress Report'!X85 -> Cum Safety Awards/Incentives | FK3: ='Weekly Progress Report'!A97 -> Total Act. | FL3: ='Weekly Progress Report'!B97 -> Not Started | FM3: ='Weekly Progress Report'!C97 -> In Progress | FN3: ='Weekly Progress Report'!D97 -> Completed | FO3: Critical Path Act.Last Week | FP3: Critical Path Act.This Week | FQ3: Failed start Last Week | FR3: Failed start This Week | FS3: ='Weekly Progress Report'!B105 -> Planned Start Date | FT3: ='Weekly Progress Report'!D105 -> Planned Finish Date | FU3: ='Weekly Progress Report'!F105 -> Forecast Start Date | FV3: ='Weekly Progress Report'!H105 -> Forecast Finish Date | FW3: ='Weekly Progress Report'!J105 -> Actual Start Date | FX3: ='Weekly Progress Report'!L105 -> Actual Finish Date | FY3: ='Weekly Progress Report'!N105 -> % Completed | FZ3: ='Weekly Progress Report'!O105 -> Open Comments | GA3: ='Weekly Progress Report'!P105 -> Closed Comments
A4: ='Weekly Progress Report'!AG1 -> 11-10-2026 | B4: ='Weekly Progress Report'!B3 -> Completion Of The Infrastructure Development Of The First Phase In The Third Industrial City In Jeddah | C4: ='Weekly Progress Report'!B4 -> JDH3 - 02 - 008 | D4: ='Weekly Progress Report'!B5 -> ALRAWAF CONTRACTING | E4: ='Weekly Progress Report'!B6 -> egis | F4: ='Weekly Progress Report'!E4 -> Construction | G4: ='Weekly Progress Report'!E5 -> Active | H4: ='Weekly Progress Report'!E6 -> Shuaib A.Alshuaibi | I4: ='Weekly Progress Report'!AA3 -> The project includes Completion of works construction of Sewage piping network with manhole Construction.Construction of a Stormwater piping network with catch basins and manholes which will be connected to pond. Construction of Irrigation Network, inculding pipes, valve chambers. Potable water piping network including pipes and valve chambers. 13.8 KV medium voltage cable. Installation of street lighting poles along main roads.Execution of the communication network, including the installation of underground ducts and the extension of communication cables to provide telecom and data services to the site. Completion and preparation of internal and external roads, including asphalt layers and sidewalks. | J4: ='Weekly Progress Report'!H3 -> 45469 | K4: ='Weekly Progress Report'!H4 -> 45495 | L4: ='Weekly Progress Report'!H5 -> 45502 | M4: ='Weekly Progress Report'!H6 -> 46231 | N4: ='Weekly Progress Report'!$J$3 -> 20-12-1445 | O4: ='Weekly Progress Report'!$J$4 -> 16-1-1446 | P4: ='Weekly Progress Report'!$J$5 -> 23-1-1446 | Q4: ='Weekly Progress Report'!$J$6 -> 14-2-1448 | R4: ='Weekly Progress Report'!$L$3 -> 46291 | S4: ='Weekly Progress Report'!$L$4 -> 46291 | T4: ='Weekly Progress Report'!$L$5 -> 46341 | U4: ='Weekly Progress Report'!$O$3 -> 3.1974488e+08 | V4: ='Weekly Progress Report'!$O$4 -> 3.1974488e+08 | W4: ='Weekly Progress Report'!$O$5 -> 3.1974488e+08 | X4: ='Weekly Progress Report'!$O$6 -> 0 | Y4: ='Weekly Progress Report'!$S$3 -> 0 | Z4: ='Weekly Progress Report'!$S$4 -> 0 | AA4: ='Weekly Progress Report'!$S$5 -> 2.5021413e+08 | AB4: ='Weekly Progress Report'!$S$6 -> -25281413 | AC4: ='Weekly Progress Report'!$J$38 -> 1 | AD4: ='Weekly Progress Report'!$V$3 -> 1 | AE4: ='Weekly Progress Report'!$V$4 -> 0.98755924 | AF4: ='Weekly Progress Report'!$X$3 -> 0.99931314 | AG4: ='Weekly Progress Report'!$X$4 -> 0.98911437 | AH4: ='Weekly Progress Report'!$Z$3 -> 0.90551724 | AI4: ='Weekly Progress Report'!$Z$5 -> 0.81818182 | AJ4: ='Weekly Progress Report'!$E$38 -> 0 | AK4: ='Weekly Progress Report'!$F$38 -> 467114.68 | AL4: =AJ4/V4 -> 0 | AM4: =AK4/V4 -> 0.0014608981 | AN4: ='Weekly Progress Report'!S38 -> 0 | AO4: ='Weekly Progress Report'!T38 -> 0.00081173899 | AP4: ='Weekly Progress Report'!C75 -> 2539 | AQ4: ='Weekly Progress Report'!I75 -> 24 | AR4: ='Weekly Progress Report'!J75 -> 14 | AS4: ='Weekly Progress Report'!K75 -> 2518 | AT4: ='Weekly Progress Report'!C84 -> 78 | AU4: ='Weekly Progress Report'!J84 -> 36 | AV4: ='Weekly Progress Report'!K84 -> 78 | AW4: ='Weekly Progress Report'!C93 -> 20 | AX4: ='Weekly Progress Report'!D93 -> 20 | AY4: ='Weekly Progress Report'!E93 -> 12 | AZ4: ='Weekly Progress Report'!F93 -> 8 | BA4: ='Weekly Progress Report'!G93 -> 10 | BB4: ='Weekly Progress Report'!H93 -> 0 | BC4: ='Weekly Progress Report'!I93 -> 0 | BD4: ='Weekly Progress Report'!N71 -> 102 | BE4: ='Weekly Progress Report'!O71 -> 99 | BF4: ='Weekly Progress Report'!P71 -> 3 | BG4: ='Weekly Progress Report'!Q71 -> 7 | BH4: ='Weekly Progress Report'!N72 -> 187 | BI4: ='Weekly Progress Report'!O72 -> 177 | BJ4: ='Weekly Progress Report'!P72 -> 10 | BK4: ='Weekly Progress Report'!Q72 -> 5 | BL4: ='Weekly Progress Report'!N73 -> 357 | BM4: ='Weekly Progress Report'!O73 -> 355 | BN4: ='Weekly Progress Report'!P73 -> 2 | BO4: ='Weekly Progress Report'!Q73 -> 0 | BP4: ='Weekly Progress Report'!N74 -> 30963 | BQ4: ='Weekly Progress Report'!O74 -> 30863 | BR4: ='Weekly Progress Report'!P74 -> 100 | BS4: ='Weekly Progress Report'!Q74 -> 0 | BT4: ='Weekly Progress Report'!O76 -> 45654 | BU4: ='Weekly Progress Report'!O77 -> 45654 | BV4: ='Weekly Progress Report'!O78 -> 45523 | BW4: ='Weekly Progress Report'!O79 -> 45582 | BX4: ='Weekly Progress Report'!O80 -> 45743 | BY4: ='Weekly Progress Report'!U76 -> 45533 | BZ4: ='Weekly Progress Report'!U77 -> 3 | CA4: ='Weekly Progress Report'!U78 -> 45586 | CB4: ='Weekly Progress Report'!U79 -> 45538 | CC4: ='Weekly Progress Report'!U80 -> 1 | CD4: ='Weekly Progress Report'!N82 -> 0 | CE4: ='Weekly Progress Report'!N83 -> 23 | CF4: ='Weekly Progress Report'!N84 -> 0 | CG4: ='Weekly Progress Report'!N85 -> 0 | CH4: ='Weekly Progress Report'!N86 -> 0.1 | CI4: ='Weekly Progress Report'!N87 -> 0 | CJ4: ='Weekly Progress Report'!N88 -> 0.00081314829 | CK4: ='Weekly Progress Report'!R82 -> 2.5021413e+08 | CL4: ='Weekly Progress Report'!R83 -> 2.465379e+08 | CM4: ='Weekly Progress Report'!R84 -> 0 | CN4: ='Weekly Progress Report'!R85 -> 46265 | CO4: ='Weekly Progress Report'!R86 -> 31974488 | CP4: ='Weekly Progress Report'!R87 -> 0 | CQ4: ='Weekly Progress Report'!R88 -> -260000 | CR4: ='Weekly Progress Report'!L92 -> 0 | CS4: ='Weekly Progress Report'!M92 -> 1092 | CT4: ='Weekly Progress Report'!O92 -> 0 | CU4: ='Weekly Progress Report'!P92 -> 0 | CV4: ='Weekly Progress Report'!Q92 -> 92 | CW4: ='Weekly Progress Report'!T102 -> 167 | CX4: ='Weekly Progress Report'!U102 -> 135 | CY4: ='Weekly Progress Report'!Z70 -> 22920 | CZ4: ='Weekly Progress Report'!Z71 -> 22920 | DA4: ='Weekly Progress Report'!Z72 -> 0 | DB4: ='Weekly Progress Report'!Z73 -> 0 | DC4: ='Weekly Progress Report'!Z74 -> 0 | DD4: ='Weekly Progress Report'!Z75 -> 0 | DE4: ='Weekly Progress Report'!Z76 -> 0 | DF4: ='Weekly Progress Report'!Z77 -> 0 | DG4: ='Weekly Progress Report'!Z78 -> 0 | DH4: ='Weekly Progress Report'!Z79 -> 0 | DI4: ='Weekly Progress Report'!Z80 -> 0 | DJ4: ='Weekly Progress Report'!Z81 -> 0 | DK4: ='Weekly Progress Report'!Z82 -> 2 | DL4: ='Weekly Progress Report'!Z83 -> 0 | DM4: ='Weekly Progress Report'!Z84 -> 8 | DN4: ='Weekly Progress Report'!Z85 -> 0 | DO4: ='Weekly Progress Report'!AB70 -> 97050 | DP4: ='Weekly Progress Report'!AB71 -> 97050 | DQ4: ='Weekly Progress Report'!AB72 -> 0 | DR4: ='Weekly Progress Report'!AB73 -> 0 | DS4: ='Weekly Progress Report'!AB74 -> 0 | DT4: ='Weekly Progress Report'!AB75 -> 0 | DU4: ='Weekly Progress Report'!AB76 -> 0 | DV4: ='Weekly Progress Report'!AB77 -> 0 | DW4: ='Weekly Progress Report'!AB78 -> 0 | DX4: ='Weekly Progress Report'!AB79 -> 0 | DY4: ='Weekly Progress Report'!AB80 -> 0 | DZ4: ='Weekly Progress Report'!AB81 -> 0 | EA4: ='Weekly Progress Report'!AB82 -> 7 | EB4: ='Weekly Progress Report'!AB83 -> 0 | EC4: ='Weekly Progress Report'!AB84 -> 34 | ED4: ='Weekly Progress Report'!AB85 -> 0 | EE4: ='Weekly Progress Report'!AC70 -> 1866079 | EF4: ='Weekly Progress Report'!AC71 -> 1866079 | EG4: ='Weekly Progress Report'!AC72 -> 0 | EH4: ='Weekly Progress Report'!AC73 -> 0 | EI4: ='Weekly Progress Report'!AC74 -> 0 | EJ4: ='Weekly Progress Report'!AC75 -> 9 | EK4: ='Weekly Progress Report'!AC76 -> 0 | EL4: ='Weekly Progress Report'!AC77 -> 0 | EM4: ='Weekly Progress Report'!AC78 -> 0 | EN4: ='Weekly Progress Report'!AC79 -> 1 | EO4: ='Weekly Progress Report'!AC80 -> 0 | EP4: ='Weekly Progress Report'!AC81 -> 96 | EQ4: ='Weekly Progress Report'!AC82 -> 145 | ER4: ='Weekly Progress Report'!AC83 -> 0 | ES4: ='Weekly Progress Report'!AC84 -> 3181 | ET4: ='Weekly Progress Report'!AC85 -> 0 | EU4: ='Weekly Progress Report'!AD70 -> 2210362 | EV4: ='Weekly Progress Report'!AD71 -> 2210362 | EW4: ='Weekly Progress Report'!AD72 -> 0 | EX4: ='Weekly Progress Report'!AD73 -> 0 | EY4: ='Weekly Progress Report'!AD74 -> 0 | EZ4: ='Weekly Progress Report'!AD75 -> 11 | FA4: ='Weekly Progress Report'!AD76 -> 0 | FB4: ='Weekly Progress Report'!AD77 -> 0 | FC4: ='Weekly Progress Report'!AD78 -> 0 | FD4: ='Weekly Progress Report'!AD79 -> 1 | FE4: ='Weekly Progress Report'!AD80 -> 0 | FF4: ='Weekly Progress Report'!AD81 -> 223 | FG4: ='Weekly Progress Report'!AD82 -> 178 | FH4: ='Weekly Progress Report'!AD83 -> 0 | FI4: ='Weekly Progress Report'!AD84 -> 3335 | FJ4: ='Weekly Progress Report'!AD85 -> 0 | FK4: ='Weekly Progress Report'!A98 -> 9236 | FL4: ='Weekly Progress Report'!B98 -> 141 | FM4: ='Weekly Progress Report'!C98 -> 75 | FN4: ='Weekly Progress Report'!D98 -> 9020 | FO4: ='Weekly Progress Report'!A102 -> 215 | FP4: ='Weekly Progress Report'!B102 -> 216 | FQ4: ='Weekly Progress Report'!H102 -> 366 | FR4: ='Weekly Progress Report'!I102 -> 324 | FS4: ='Weekly Progress Report'!B110 | FT4: ='Weekly Progress Report'!D110 | FU4: ='Weekly Progress Report'!F110 | FV4: ='Weekly Progress Report'!H110 | FW4: ='Weekly Progress Report'!J110 | FX4: ='Weekly Progress Report'!L110 | FY4: ='Weekly Progress Report'!N110 -> 0 | FZ4: ='Weekly Progress Report'!O110 -> 0 | GA4: ='Weekly Progress Report'!P110 -> 0

Sheet Weekly Progress Report
A1: MODON - Weekly Progress Report - Construction Projects | AF1: Data Date | AG1: ='General Information'!L1 -> 11-10-2026
A2: Contract General Information | G2: Key Dates | M2: Cost Summary (SR) | U2: Performance Summary | AA2: Project Scope
A3: Project Name | B3: ='General Information'!C3 -> Completion Of The Infrastructure Development Of The First Phase In The Third Industrial City In Jeddah | G3: Contract Award | H3: ='General Information'!C12 -> 45469 | I3: Contract Award (Hijri) | J3: ='General Information'!C16 -> 20-12-1445 | K3: Revised Completion | L3: ='General Information'!C20 -> 46291 | M3: Original Contract Value | O3: ='Invoice Log'!F3 -> 3.1974488e+08 | Q3: O&M Value | S3: ='Invoice Log'!J3 -> 0 | T3: EAC | U3: Plan Value | V3: =J38 -> 1 | W3: Phys. Plan Value | X3: =W38 -> 0.99931314 | Y3: Quality Score | Z3: =Quality!AC10 -> 0.90551724 | AA3: =Progress!B1 -> The project includes Completion of works construction of Sewage piping network with manhole Construction.Construction of a Stormwater piping network with catch basins and manholes which will be connected to pond. Construction of Irrigation Network, inculding pipes, valve chambers. Potable water piping network including pipes and valve chambers. 13.8 KV medium voltage cable. Installation of street lighting poles along main roads.Execution of the communication network, including the installation of underground ducts and the extension of communication cables to provide telecom and data services to the site. Completion and preparation of internal and external roads, including asphalt layers and sidewalks.
A4: Project ID | B4: ='General Information'!C4 -> JDH3 - 02 - 008 | D4: Stage | E4: ='General Information'!C7 -> Construction | G4: Contract Sign | H4: ='General Information'!C13 -> 45495 | I4: Contract Sign (Hijri) | J4: ='General Information'!C17 -> 16-1-1446 | K4: Committed Completion | L4: ='General Information'!C21 -> 46291 | M4: Revised Contract Value | O4: ='Invoice Log'!F4 -> 3.1974488e+08 | P4: EAC | Q4: Revised O&M Value | S4: ='Invoice Log'!J4 -> 0 | T4: =+#REF!+#REF!+S4 -> #REF! | U4: Earn Value | V4: =L38 -> 0.98755924 | W4: Phys. Earn Value | X4: =X38 -> 0.98911437 | Z4: =REPT("¢",IF(INT(+Z3*10)>5,5,INT(+Z3*10)))&REPT("£",IF(INT(+Z3*10)>5,0,5-INT(+Z3*10)))&CHAR(10)&REPT("¢",+IF(INT(+Z3*10)>5,-5+INT(+Z3*10),0))&REPT("£",IF(INT(+Z3*10)>5,10-INT(+Z3*10),5)) -> ¢¢¢¢¢ ¢¢¢¢£
A5: Contractor | B5: ='General Information'!C5 -> ALRAWAF CONTRACTING | D5: Status | E5: ='General Information'!C8 -> Active | G5: Site Handover | H5: ='General Information'!C14 -> 45502 | I5: Site Handover (Hijri) | J5: ='General Information'!C18 -> 23-1-1446 | K5: Forecast Completion | L5: ='General Information'!C22 -> 46341 | M5: Estimate At Completion Value | O5: ='Invoice Log'!F5 -> 3.1974488e+08 | P5: =+#REF!+#REF!+O5 -> #REF! | Q5: Submitted Invoices (Gross Value) | S5: ='Invoice Log'!J5 -> 2.5021413e+08 | U5: Variance | V5: =V4-V3 -> -0.012440759 | W5: Variance | X5: =X4-X3 -> -0.010198772 | Y5: Safety Score | Z5: ='HSE-Stat'!J23 -> 0.81818182
A6: Consultant | B6: ='General Information'!C6 -> egis | D6: Modon PM | E6: ='General Information'!C9 -> Shuaib A.Alshuaibi | G6: Original Completion | H6: ='General Information'!C15 -> 46231 | I6: Original Completion (Hijri) | J6: ='General Information'!C19 -> 14-2-1448 | K6: Variance | L6: ='General Information'!C23 -> -50 | M6: Potential Changes | O6: =O4-O5 -> 0 | Q6: Total Deduction | S6: ='Invoice Log'!J6 -> -25281413 | U6: SPI | V6: =V4/V3 -> 0.98755924 | W6: SPI | X6: =X4/X3 -> 0.98979422 | Z6: =REPT("¢",IF(INT(+Z5*10)>5,5,INT(+Z5*10)))&REPT("£",IF(INT(+Z5*10)>5,0,5-INT(+Z5*10)))&CHAR(10)&REPT("¢",+IF(INT(+Z5*10)>5,-5+INT(+Z5*10),0))&REPT("£",IF(INT(+Z5*10)>5,10-INT(+Z5*10),5)) -> ¢¢¢¢¢ ¢¢¢££
A8: Progress Overview
A9: Earned Value Progress (SAR) | O9: Physical Progress (Effort) | AA9: Earned Value Progress (%)
A10: WBS | C10: BOQ Value (SAR) | D10: % Wt. | E10: Weekly (SAR) | G10: To Date (SAR) | O10: Budgeted | P10: % Wt. | Q10: Weekly Physical Progress | U10: To Date Physical Progress
E11: Planned | F11: Earned | G11: Revised Plan | H11: Revised Plan | I11: Earned | J11: =Progress!G6 -> Revised Plan | K11: =Progress!H6 -> Revised Plan | L11: Earned % | M11: Variance | N11: SPI | O11: (Manhours) | Q11: Planned | R11: Earned | S11: Plan % | T11: Earned % | U11: Planned | V11: Earned | W11: Plan % | X11: Earned % | Y11: Variance | Z11: SPI
A12: =Progress!A7 -> JDH3-02-008-Authorities Permits & Approval - AT | C12: =Progress!C7 -> 0 | D12: =Progress!D7 -> 0 | E12: =Progress!E7 -> 0 | F12: =Progress!F7 -> 0 | G12: =Progress!G7 -> 0 | H12: =Progress!H7 -> 0 | I12: =Progress!I7 -> 0 | J12: =IFERROR(IF(ISBLANK(G12),"",G12/C12),0) -> 0 | K12: =IFERROR(IF(ISBLANK(H12),"",H12/C12),0) -> 0 | L12: =IFERROR(IF(ISBLANK(I12),"",I12/C12),0) -> 0 | M12: =IFERROR(L12-K12,"") -> 0 | N12: =IFERROR(L12/J12,"") | O12: =+Progress!K7 -> 0 | P12: =IF(ISBLANK(O12),"",O12/$O$38) -> 0 | Q12: =Progress!M7 -> 0 | R12: =Progress!N7 -> 0 | S12: =IFERROR(IF(ISBLANK(Q12),"",Q12/O12),0) -> 0 | T12: =IFERROR(IF(ISBLANK(R12),"",R12/O12),0) -> 0 | U12: =Progress!O7 -> 0 | V12: =Progress!P7 -> 0 | W12: =IFERROR(IF(ISBLANK(U12),"",U12/O12),0) -> 0 | X12: =IFERROR(IF(ISBLANK(V12),"",V12/O12),0) -> 0 | Y12: =IFERROR(X12-W12,"") -> 0 | Z12: =IFERROR(X12/W12,"")
A13: =Progress!A8 -> JDH3-02-008-Engineering | C13: =Progress!C8 -> 9592346.3 | D13: =Progress!D8 -> 0.03 | E13: =Progress!E8 -> 0 | F13: =Progress!F8 -> 0 | G13: =Progress!G8 -> 9592346.3 | H13: =Progress!H8 -> 9592346.3 | I13: =Progress!I8 -> 9592346.3 | J13: =IFERROR(IF(ISBLANK(G13),"",G13/C13),0) -> 1 | K13: =IFERROR(IF(ISBLANK(H13),"",H13/C13),0) -> 1 | L13: =IFERROR(IF(ISBLANK(I13),"",I13/C13),0) -> 1 | M13: =IFERROR(L13-K13,"") -> 0 | N13: =IFERROR(L13/J13,"") -> 1 | O13: =+Progress!K8 -> 0 | P13: =IF(ISBLANK(O13),"",O13/$O$38) -> 0 | Q13: =Progress!M8 -> 0 | R13: =Progress!N8 -> 0 | S13: =IFERROR(IF(ISBLANK(Q13),"",Q13/O13),0) -> 0 | T13: =IFERROR(IF(ISBLANK(R13),"",R13/O13),0) -> 0 | U13: =Progress!O8 -> 0 | V13: =Progress!P8 -> 0 | W13: =IFERROR(IF(ISBLANK(U13),"",U13/O13),0) -> 0 | X13: =IFERROR(IF(ISBLANK(V13),"",V13/O13),0) -> 0 | Y13: =IFERROR(X13-W13,"") -> 0 | Z13: =IFERROR(X13/W13,"")
A14: =Progress!A9 -> JDH3-02-008-Procurement | C14: =Progress!C9 -> 63948975 | D14: =Progress!D9 -> 0.2 | E14: =Progress!E9 -> 0 | F14: =Progress!F9 -> 0 | G14: =Progress!G9 -> 63948975 | H14: =Progress!H9 -> 63948975 | I14: =Progress!I9 -> 63948975 | J14: =IFERROR(IF(ISBLANK(G14),"",G14/C14),0) -> 1 | K14: =IFERROR(IF(ISBLANK(H14),"",H14/C14),0) -> 1 | L14: =IFERROR(IF(ISBLANK(I14),"",I14/C14),0) -> 1 | M14: =IFERROR(L14-K14,"") -> 0 | N14: =IFERROR(L14/J14,"") -> 1 | O14: =+Progress!K9 -> 0 | P14: =IF(ISBLANK(O14),"",O14/$O$38) -> 0 | Q14: =Progress!M9 -> 0 | R14: =Progress!N9 -> 0 | S14: =IFERROR(IF(ISBLANK(Q14),"",Q14/O14),0) -> 0 | T14: =IFERROR(IF(ISBLANK(R14),"",R14/O14),0) -> 0 | U14: =Progress!O9 -> 0 | V14: =Progress!P9 -> 0 | W14: =IFERROR(IF(ISBLANK(U14),"",U14/O14),0) -> 0 | X14: =IFERROR(IF(ISBLANK(V14),"",V14/O14),0) -> 0 | Y14: =IFERROR(X14-W14,"") -> 0 | Z14: =IFERROR(X14/W14,"")
A15: =Progress!A10 -> JDH3-02-008-Construction | C15: =Progress!C10 -> 2.1422907e+08 | D15: =Progress!D10 -> 0.67 | E15: =Progress!E10 -> 0 | F15: =Progress!F10 -> 245364.71 | G15: =Progress!G10 -> 2.1422907e+08 | H15: =Progress!H10 -> 2.1422907e+08 | I15: =Progress!I10 -> 2.1186851e+08 | J15: =IFERROR(IF(ISBLANK(G15),"",G15/C15),0) -> 1 | K15: =IFERROR(IF(ISBLANK(H15),"",H15/C15),0) -> 1 | L15: =IFERROR(IF(ISBLANK(I15),"",I15/C15),0) -> 0.98898117 | M15: =IFERROR(L15-K15,"") -> -0.011018835 | N15: =IFERROR(L15/J15,"") -> 0.98898117 | O15: =+Progress!K10 -> 48045 | P15: =IF(ISBLANK(O15),"",O15/$O$38) -> 1 | Q15: =Progress!M10 -> 0 | R15: =Progress!N10 -> 39 | S15: =IFERROR(IF(ISBLANK(Q15),"",Q15/O15),0) -> 0 | T15: =IFERROR(IF(ISBLANK(R15),"",R15/O15),0) -> 0.00081173899 | U15: =Progress!O10 -> 48012 | V15: =Progress!P10 -> 47522 | W15: =IFERROR(IF(ISBLANK(U15),"",U15/O15),0) -> 0.99931314 | X15: =IFERROR(IF(ISBLANK(V15),"",V15/O15),0) -> 0.98911437 | Y15: =IFERROR(X15-W15,"") -> -0.010198772 | Z15: =IFERROR(X15/W15,"") -> 0.98979422
A16: =Progress!A11 -> Pond and Swales - PS | C16: =Progress!C11 -> 27026698 | D16: =Progress!D11 -> 0.084525819 | E16: =Progress!E11 -> 0 | F16: =Progress!F11 -> 0 | G16: =Progress!G11 -> 27026698 | H16: =Progress!H11 -> 27026698 | I16: =Progress!I11 -> 27026698 | J16: =IFERROR(IF(ISBLANK(G16),"",G16/C16),0) -> 1 | K16: =IFERROR(IF(ISBLANK(H16),"",H16/C16),0) -> 1 | L16: =IFERROR(IF(ISBLANK(I16),"",I16/C16),0) -> 1 | M16: =IFERROR(L16-K16,"") -> 0 | N16: =IFERROR(L16/J16,"") -> 1 | O16: =+Progress!K11 -> 3720 | P16: =IF(ISBLANK(O16),"",O16/$O$38) -> 0.077427412 | Q16: =Progress!M11 -> 0 | R16: =Progress!N11 -> 0 | S16: =IFERROR(IF(ISBLANK(Q16),"",Q16/O16),0) -> 0 | T16: =IFERROR(IF(ISBLANK(R16),"",R16/O16),0) -> 0 | U16: =Progress!O11 -> 3720 | V16: =Progress!P11 -> 3720 | W16: =IFERROR(IF(ISBLANK(U16),"",U16/O16),0) -> 1 | X16: =IFERROR(IF(ISBLANK(V16),"",V16/O16),0) -> 1 | Y16: =IFERROR(X16-W16,"") -> 0 | Z16: =IFERROR(X16/W16,"") -> 1
A17: =Progress!A12 -> High Mast | C17: =Progress!C12 -> 2003227.7 | D17: =Progress!D12 -> 0.0062650814 | E17: =Progress!E12 -> 0 | F17: =Progress!F12 -> 0 | G17: =Progress!G12 -> 2003227.7 | H17: =Progress!H12 -> 2003227.7 | I17: =Progress!I12 -> 2003227.7 | J17: =IFERROR(IF(ISBLANK(G17),"",G17/C17),0) -> 1 | K17: =IFERROR(IF(ISBLANK(H17),"",H17/C17),0) -> 1 | L17: =IFERROR(IF(ISBLANK(I17),"",I17/C17),0) -> 1 | M17: =IFERROR(L17-K17,"") -> 0 | N17: =IFERROR(L17/J17,"") -> 1 | O17: =+Progress!K12 -> 1222 | P17: =IF(ISBLANK(O17),"",O17/$O$38) -> 0.025434489 | Q17: =Progress!M12 -> 0 | R17: =Progress!N12 -> 0 | S17: =IFERROR(IF(ISBLANK(Q17),"",Q17/O17),0) -> 0 | T17: =IFERROR(IF(ISBLANK(R17),"",R17/O17),0) -> 0 | U17: =Progress!O12 -> 1222 | V17: =Progress!P12 -> 1222 | W17: =IFERROR(IF(ISBLANK(U17),"",U17/O17),0) -> 1 | X17: =IFERROR(IF(ISBLANK(V17),"",V17/O17),0) -> 1 | Y17: =IFERROR(X17-W17,"") -> 0 | Z17: =IFERROR(X17/W17,"") -> 1
A18: =Progress!A13 -> ELDREES | C18: =Progress!C13 -> 353857.85 | D18: =Progress!D13 -> 0.0011066881 | E18: =Progress!E13 -> 0 | F18: =Progress!F13 -> 0 | G18: =Progress!G13 -> 353857.85 | H18: =Progress!H13 -> 353857.85 | I18: =Progress!I13 -> 353857.85 | J18: =IFERROR(IF(ISBLANK(G18),"",G18/C18),0) -> 1 | K18: =IFERROR(IF(ISBLANK(H18),"",H18/C18),0) -> 1 | L18: =IFERROR(IF(ISBLANK(I18),"",I18/C18),0) -> 1 | M18: =IFERROR(L18-K18,"") -> 0 | N18: =IFERROR(L18/J18,"") -> 1 | O18: =+Progress!K13 -> 125 | P18: =IF(ISBLANK(O18),"",O18/$O$38) -> 0.0026017275 | Q18: =Progress!M13 -> 0 | R18: =Progress!N13 -> 0 | S18: =IFERROR(IF(ISBLANK(Q18),"",Q18/O18),0) -> 0 | T18: =IFERROR(IF(ISBLANK(R18),"",R18/O18),0) -> 0 | U18: =Progress!O13 -> 125 | V18: =Progress!P13 -> 125 | W18: =IFERROR(IF(ISBLANK(U18),"",U18/O18),0) -> 1 | X18: =IFERROR(IF(ISBLANK(V18),"",V18/O18),0) -> 1 | Y18: =IFERROR(X18-W18,"") -> 0 | Z18: =IFERROR(X18/W18,"") -> 1
A19: =Progress!A14 -> MR | C19: =Progress!C14 -> 73833427 | D19: =Progress!D14 -> 0.23091356 | E19: =Progress!E14 -> 0 | F19: =Progress!F14 -> 0 | G19: =Progress!G14 -> 73833427 | H19: =Progress!H14 -> 73833427 | I19: =Progress!I14 -> 73419907 | J19: =IFERROR(IF(ISBLANK(G19),"",G19/C19),0) -> 1 | K19: =IFERROR(IF(ISBLANK(H19),"",H19/C19),0) -> 1 | L19: =IFERROR(IF(ISBLANK(I19),"",I19/C19),0) -> 0.99439928 | M19: =IFERROR(L19-K19,"") -> -0.0056007251 | N19: =IFERROR(L19/J19,"") -> 0.99439927 | O19: =+Progress!K14 -> 17520 | P19: =IF(ISBLANK(O19),"",O19/$O$38) -> 0.36465813 | Q19: =Progress!M14 -> 0 | R19: =Progress!N14 -> 0 | S19: =IFERROR(IF(ISBLANK(Q19),"",Q19/O19),0) -> 0 | T19: =IFERROR(IF(ISBLANK(R19),"",R19/O19),0) -> 0 | U19: =Progress!O14 -> 17507 | V19: =Progress!P14 -> 17409 | W19: =IFERROR(IF(ISBLANK(U19),"",U19/O19),0) -> 0.99925799 | X19: =IFERROR(IF(ISBLANK(V19),"",V19/O19),0) -> 0.99366438 | Y19: =IFERROR(X19-W19,"") -> -0.0055936073 | Z19: =IFERROR(X19/W19,"") -> 0.99440224
A20: =Progress!A15 -> Z01 | C20: =Progress!C15 -> 12724319 | D20: =Progress!D15 -> 0.039795223 | E20: =Progress!E15 -> 0 | F20: =Progress!F15 -> 0 | G20: =Progress!G15 -> 12724319 | H20: =Progress!H15 -> 12724319 | I20: =Progress!I15 -> 12724319 | J20: =IFERROR(IF(ISBLANK(G20),"",G20/C20),0) -> 1 | K20: =IFERROR(IF(ISBLANK(H20),"",H20/C20),0) -> 1 | L20: =IFERROR(IF(ISBLANK(I20),"",I20/C20),0) -> 1 | M20: =IFERROR(L20-K20,"") -> 0 | N20: =IFERROR(L20/J20,"") -> 1 | O20: =+Progress!K15 -> 2771 | P20: =IF(ISBLANK(O20),"",O20/$O$38) -> 0.057675096 | Q20: =Progress!M15 -> 0 | R20: =Progress!N15 -> 0 | S20: =IFERROR(IF(ISBLANK(Q20),"",Q20/O20),0) -> 0 | T20: =IFERROR(IF(ISBLANK(R20),"",R20/O20),0) -> 0 | U20: =Progress!O15 -> 2770 | V20: =Progress!P15 -> 2771 | W20: =IFERROR(IF(ISBLANK(U20),"",U20/O20),0) -> 0.99963912 | X20: =IFERROR(IF(ISBLANK(V20),"",V20/O20),0) -> 1 | Y20: =IFERROR(X20-W20,"") -> 0.00036088055 | Z20: =IFERROR(X20/W20,"") -> 1.000361
A21: =Progress!A16 -> Z02 | C21: =Progress!C16 -> 1453405.8 | D21: =Progress!D16 -> 0.0045455172 | E21: =Progress!E16 -> 0 | F21: =Progress!F16 -> 74152.78 | G21: =Progress!G16 -> 1453405.8 | H21: =Progress!H16 -> 1453405.8 | I21: =Progress!I16 -> 1268023.9 | J21: =IFERROR(IF(ISBLANK(G21),"",G21/C21),0) -> 1 | K21: =IFERROR(IF(ISBLANK(H21),"",H21/C21),0) -> 1 | L21: =IFERROR(IF(ISBLANK(I21),"",I21/C21),0) -> 0.87244997 | M21: =IFERROR(L21-K21,"") -> -0.12755003 | N21: =IFERROR(L21/J21,"") -> 0.87244997 | O21: =+Progress!K16 -> 484 | P21: =IF(ISBLANK(O21),"",O21/$O$38) -> 0.010073889 | Q21: =Progress!M16 -> 0 | R21: =Progress!N16 -> 11 | S21: =IFERROR(IF(ISBLANK(Q21),"",Q21/O21),0) -> 0 | T21: =IFERROR(IF(ISBLANK(R21),"",R21/O21),0) -> 0.022727273 | U21: =Progress!O16 -> 484 | V21: =Progress!P16 -> 457 | W21: =IFERROR(IF(ISBLANK(U21),"",U21/O21),0) -> 1 | X21: =IFERROR(IF(ISBLANK(V21),"",V21/O21),0) -> 0.94421488 | Y21: =IFERROR(X21-W21,"") -> -0.055785124 | Z21: =IFERROR(X21/W21,"") -> 0.94421488
A22: =Progress!A17 -> Z02-1 | C22: =Progress!C17 -> 10584846 | D22: =Progress!D17 -> 0.033104036 | E22: 319 | F22: =Progress!F17 -> 0 | G22: =Progress!G17 -> 10584846 | H22: =Progress!H17 -> 10584846 | I22: =Progress!I17 -> 10584846 | J22: =IFERROR(IF(ISBLANK(G22),"",G22/C22),0) -> 1 | K22: =IFERROR(IF(ISBLANK(H22),"",H22/C22),0) -> 1 | L22: =IFERROR(IF(ISBLANK(I22),"",I22/C22),0) -> 1 | M22: =IFERROR(L22-K22,"") -> 0 | N22: =IFERROR(L22/J22,"") -> 1 | O22: =+Progress!K17 -> 2709 | P22: =IF(ISBLANK(O22),"",O22/$O$38) -> 0.056384639 | Q22: =Progress!M17 -> 0 | R22: =Progress!N17 -> 0 | S22: =IFERROR(IF(ISBLANK(Q22),"",Q22/O22),0) -> 0 | T22: =IFERROR(IF(ISBLANK(R22),"",R22/O22),0) -> 0 | U22: =Progress!O17 -> 2693 | V22: =Progress!P17 -> 2709 | W22: =IFERROR(IF(ISBLANK(U22),"",U22/O22),0) -> 0.99409376 | X22: =IFERROR(IF(ISBLANK(V22),"",V22/O22),0) -> 1 | Y22: =IFERROR(X22-W22,"") -> 0.0059062385 | Z22: =IFERROR(X22/W22,"") -> 1.0059413
A23: =Progress!A18 -> Z02-2 | C23: =Progress!C18 -> 11951477 | D23: =Progress!D18 -> 0.037378164 | E23: =Progress!E18 -> 0 | F23: =Progress!F18 -> 0 | G23: =Progress!G18 -> 11951477 | H23: =Progress!H18 -> 11951477 | I23: =Progress!I18 -> 11951477 | J23: =IFERROR(IF(ISBLANK(G23),"",G23/C23),0) -> 1 | K23: =IFERROR(IF(ISBLANK(H23),"",H23/C23),0) -> 1 | L23: =IFERROR(IF(ISBLANK(I23),"",I23/C23),0) -> 1 | M23: =IFERROR(L23-K23,"") -> 0 | N23: =IFERROR(L23/J23,"") -> 1 | O23: =+Progress!K18 -> 3089 | P23: =IF(ISBLANK(O23),"",O23/$O$38) -> 0.064293891 | Q23: =Progress!M18 -> 0 | R23: =Progress!N18 -> 0 | S23: =IFERROR(IF(ISBLANK(Q23),"",Q23/O23),0) -> 0 | T23: =IFERROR(IF(ISBLANK(R23),"",R23/O23),0) -> 0 | U23: =Progress!O18 -> 3089 | V23: =Progress!P18 -> 3089 | W23: =IFERROR(IF(ISBLANK(U23),"",U23/O23),0) -> 1 | X23: =IFERROR(IF(ISBLANK(V23),"",V23/O23),0) -> 1 | Y23: =IFERROR(X23-W23,"") -> 0 | Z23: =IFERROR(X23/W23,"") -> 1
A24: =Progress!A19 -> Z03 | C24: =Progress!C19 -> 709820.88 | D24: =Progress!D19 -> 0.0022199601 | E24: =Progress!E19 -> 0 | F24: =Progress!F19 -> 0 | G24: =Progress!G19 -> 709820.88 | H24: =Progress!H19 -> 709820.88 | I24: =Progress!I19 -> 709820.88 | J24: =IFERROR(IF(ISBLANK(G24),"",G24/C24),0) -> 1 | K24: =IFERROR(IF(ISBLANK(H24),"",H24/C24),0) -> 1 | L24: =IFERROR(IF(ISBLANK(I24),"",I24/C24),0) -> 1 | M24: =IFERROR(L24-K24,"") -> 0 | N24: =IFERROR(L24/J24,"") -> 1 | O24: =+Progress!K19 -> 378 | P24: =IF(ISBLANK(O24),"",O24/$O$38) -> 0.0078676241 | Q24: =Progress!M19 -> 0 | R24: =Progress!N19 -> 0 | S24: =IFERROR(IF(ISBLANK(Q24),"",Q24/O24),0) -> 0 | T24: =IFERROR(IF(ISBLANK(R24),"",R24/O24),0) -> 0 | U24: =Progress!O19 -> 378 | V24: =Progress!P19 -> 378 | W24: =IFERROR(IF(ISBLANK(U24),"",U24/O24),0) -> 1 | X24: =IFERROR(IF(ISBLANK(V24),"",V24/O24),0) -> 1 | Y24: =IFERROR(X24-W24,"") -> 0 | Z24: =IFERROR(X24/W24,"") -> 1
A25: =Progress!A20 -> Z04 | C25: =Progress!C20 -> 791520.69 | D25: =Progress!D20 -> 0.0024754758 | E25: =Progress!E20 -> 0 | F25: =Progress!F20 -> 0 | G25: =Progress!G20 -> 791520.69 | H25: =Progress!H20 -> 791520.69 | I25: =Progress!I20 -> 582653.1 | J25: =IFERROR(IF(ISBLANK(G25),"",G25/C25),0) -> 1 | K25: =IFERROR(IF(ISBLANK(H25),"",H25/C25),0) -> 1 | L25: =IFERROR(IF(ISBLANK(I25),"",I25/C25),0) -> 0.7361186 | M25: =IFERROR(L25-K25,"") -> -0.2638814 | N25: =IFERROR(L25/J25,"") -> 0.7361186 | O25: =+Progress!K20 -> 337 | P25: =IF(ISBLANK(O25),"",O25/$O$38) -> 0.0070142575 | Q25: =Progress!M20 -> 0 | R25: =Progress!N20 -> 0 | S25: =IFERROR(IF(ISBLANK(Q25),"",Q25/O25),0) -> 0 | T25: =IFERROR(IF(ISBLANK(R25),"",R25/O25),0) -> 0 | U25: =Progress!O20 -> 337 | V25: =Progress!P20 -> 310 | W25: =IFERROR(IF(ISBLANK(U25),"",U25/O25),0) -> 1 | X25: =IFERROR(IF(ISBLANK(V25),"",V25/O25),0) -> 0.91988131 | Y25: =IFERROR(X25-W25,"") -> -0.080118694 | Z25: =IFERROR(X25/W25,"") -> 0.91988131
A26: =Progress!A21 -> Z05 | C26: =Progress!C21 -> 6381167 | D26: =Progress!D21 -> 0.019957058 | E26: =Progress!E21 -> 0 | F26: =Progress!F21 -> 102028.39 | G26: =Progress!G21 -> 6381167 | H26: =Progress!H21 -> 6381167 | I26: =Progress!I21 -> 5519896.3 | J26: =IFERROR(IF(ISBLANK(G26),"",G26/C26),0) -> 1 | K26: =IFERROR(IF(ISBLANK(H26),"",H26/C26),0) -> 1 | L26: =IFERROR(IF(ISBLANK(I26),"",I26/C26),0) -> 0.86502927 | M26: =IFERROR(L26-K26,"") -> -0.13497073 | N26: =IFERROR(L26/J26,"") -> 0.86502927 | O26: =+Progress!K21 -> 3703 | P26: =IF(ISBLANK(O26),"",O26/$O$38) -> 0.077073577 | Q26: =Progress!M21 -> 0 | R26: =Progress!N21 -> 13 | S26: =IFERROR(IF(ISBLANK(Q26),"",Q26/O26),0) -> 0 | T26: =IFERROR(IF(ISBLANK(R26),"",R26/O26),0) -> 0.003510667 | U26: =Progress!O21 -> 3703 | V26: =Progress!P21 -> 3458 | W26: =IFERROR(IF(ISBLANK(U26),"",U26/O26),0) -> 1 | X26: =IFERROR(IF(ISBLANK(V26),"",V26/O26),0) -> 0.93383743 | Y26: =IFERROR(X26-W26,"") -> -0.066162571 | Z26: =IFERROR(X26/W26,"") -> 0.93383743
A27: =Progress!A22 -> Z06 | B27: =B32/2 -> 1988934.4 | C27: =Progress!C22 -> 15215702 | D27: =Progress!D22 -> 0.047587008 | E27: =Progress!E22 -> 0 | F27: =Progress!F22 -> 43378.29 | G27: =Progress!G22 -> 15215702 | H27: =Progress!H22 -> 15215702 | I27: =Progress!I22 -> 15151456 | J27: =IFERROR(IF(ISBLANK(G27),"",G27/C27),0) -> 1 | K27: =IFERROR(IF(ISBLANK(H27),"",H27/C27),0) -> 1 | L27: =IFERROR(IF(ISBLANK(I27),"",I27/C27),0) -> 0.99577766 | M27: =IFERROR(L27-K27,"") -> -0.0042223402 | N27: =IFERROR(L27/J27,"") -> 0.99577766 | O27: =+Progress!K22 -> 3016 | P27: =IF(ISBLANK(O27),"",O27/$O$38) -> 0.062774482 | Q27: =Progress!M22 -> 0 | R27: =Progress!N22 -> 8 | S27: =IFERROR(IF(ISBLANK(Q27),"",Q27/O27),0) -> 0 | T27: =IFERROR(IF(ISBLANK(R27),"",R27/O27),0) -> 0.0026525199 | U27: =Progress!O22 -> 3016 | V27: =Progress!P22 -> 3004 | W27: =IFERROR(IF(ISBLANK(U27),"",U27/O27),0) -> 1 | X27: =IFERROR(IF(ISBLANK(V27),"",V27/O27),0) -> 0.99602122 | Y27: =IFERROR(X27-W27,"") -> -0.0039787798 | Z27: =IFERROR(X27/W27,"") -> 0.99602122
A28: =Progress!A23 -> Z07 | C28: =Progress!C23 -> 14082635 | D28: =Progress!D23 -> 0.044043347 | E28: =Progress!E23 -> 0 | F28: =Progress!F23 -> 0 | G28: =Progress!G23 -> 14082635 | H28: =Progress!H23 -> 14082635 | I28: =Progress!I23 -> 14082635 | J28: =IFERROR(IF(ISBLANK(G28),"",G28/C28),0) -> 1 | K28: =IFERROR(IF(ISBLANK(H28),"",H28/C28),0) -> 1 | L28: =IFERROR(IF(ISBLANK(I28),"",I28/C28),0) -> 1 | M28: =IFERROR(L28-K28,"") -> 0 | N28: =IFERROR(L28/J28,"") -> 1 | O28: =+Progress!K23 -> 2682 | P28: =IF(ISBLANK(O28),"",O28/$O$38) -> 0.055822666 | Q28: =Progress!M23 -> 0 | R28: =Progress!N23 -> 0 | S28: =IFERROR(IF(ISBLANK(Q28),"",Q28/O28),0) -> 0 | T28: =IFERROR(IF(ISBLANK(R28),"",R28/O28),0) -> 0 | U28: =Progress!O23 -> 2682 | V28: =Progress!P23 -> 2682 | W28: =IFERROR(IF(ISBLANK(U28),"",U28/O28),0) -> 1 | X28: =IFERROR(IF(ISBLANK(V28),"",V28/O28),0) -> 1 | Y28: =IFERROR(X28-W28,"") -> 0 | Z28: =IFERROR(X28/W28,"") -> 1
A29: =Progress!A24 -> Z07-1 | C29: =Progress!C24 -> 9569376.8 | D29: =Progress!D24 -> 0.029928163 | E29: =Progress!E24 -> 0 | F29: =Progress!F24 -> 0 | G29: =Progress!G24 -> 9569376.8 | H29: =Progress!H24 -> 9569376.8 | I29: =Progress!I24 -> 9569376.8 | J29: =IFERROR(IF(ISBLANK(G29),"",G29/C29),0) -> 1 | K29: =IFERROR(IF(ISBLANK(H29),"",H29/C29),0) -> 1 | L29: =IFERROR(IF(ISBLANK(I29),"",I29/C29),0) -> 1 | M29: =IFERROR(L29-K29,"") -> 0 | N29: =IFERROR(L29/J29,"") -> 1 | O29: =+Progress!K24 -> 2065 | P29: =IF(ISBLANK(O29),"",O29/$O$38) -> 0.042980539 | Q29: =Progress!M24 -> 0 | R29: =Progress!N24 -> 0 | S29: =IFERROR(IF(ISBLANK(Q29),"",Q29/O29),0) -> 0 | T29: =IFERROR(IF(ISBLANK(R29),"",R29/O29),0) -> 0 | U29: =Progress!O24 -> 2065 | V29: =Progress!P24 -> 2065 | W29: =IFERROR(IF(ISBLANK(U29),"",U29/O29),0) -> 1 | X29: =IFERROR(IF(ISBLANK(V29),"",V29/O29),0) -> 1 | Y29: =IFERROR(X29-W29,"") -> 0 | Z29: =IFERROR(X29/W29,"") -> 1
A30: =Progress!A25 -> Z08 | C30: =Progress!C25 -> 1069834.5 | D30: =Progress!D25 -> 0.0033459005 | E30: =Progress!E25 -> 0 | F30: =Progress!F25 -> 0 | G30: =Progress!G25 -> 1069834.5 | H30: =Progress!H25 -> 1069834.5 | I30: =Progress!I25 -> 744135.82 | J30: =IFERROR(IF(ISBLANK(G30),"",G30/C30),0) -> 1 | K30: =IFERROR(IF(ISBLANK(H30),"",H30/C30),0) -> 1 | L30: =IFERROR(IF(ISBLANK(I30),"",I30/C30),0) -> 0.6955616 | M30: =IFERROR(L30-K30,"") -> -0.3044384 | N30: =IFERROR(L30/J30,"") -> 0.6955616 | O30: =+Progress!K25 -> 339 | P30: =IF(ISBLANK(O30),"",O30/$O$38) -> 0.0070558851 | Q30: =Progress!M25 -> 0 | R30: =Progress!N25 -> 0 | S30: =IFERROR(IF(ISBLANK(Q30),"",Q30/O30),0) -> 0 | T30: =IFERROR(IF(ISBLANK(R30),"",R30/O30),0) -> 0 | U30: =Progress!O25 -> 339 | V30: =Progress!P25 -> 296 | W30: =IFERROR(IF(ISBLANK(U30),"",U30/O30),0) -> 1 | X30: =IFERROR(IF(ISBLANK(V30),"",V30/O30),0) -> 0.87315634 | Y30: =IFERROR(X30-W30,"") -> -0.12684366 | Z30: =IFERROR(X30/W30,"") -> 0.87315634
A31: =Progress!A26 -> Z09 | C31: =Progress!C26 -> 5049850.4 | D31: =Progress!D26 -> 0.015793374 | E31: =Progress!E26 -> 0 | F31: =Progress!F26 -> 16732.15 | G31: =Progress!G26 -> 5049850.4 | H31: =Progress!H26 -> 5049850.4 | I31: =Progress!I26 -> 4963978.2 | J31: =IFERROR(IF(ISBLANK(G31),"",G31/C31),0) -> 1 | K31: =IFERROR(IF(ISBLANK(H31),"",H31/C31),0) -> 1 | L31: =IFERROR(IF(ISBLANK(I31),"",I31/C31),0) -> 0.98299509 | M31: =IFERROR(L31-K31,"") -> -0.017004912 | N31: =IFERROR(L31/J31,"") -> 0.98299509 | O31: =+Progress!K26 -> 886 | P31: =IF(ISBLANK(O31),"",O31/$O$38) -> 0.018441045 | Q31: =Progress!M26 -> 0 | R31: =Progress!N26 -> 3 | S31: =IFERROR(IF(ISBLANK(Q31),"",Q31/O31),0) -> 0 | T31: =IFERROR(IF(ISBLANK(R31),"",R31/O31),0) -> 0.0033860045 | U31: =Progress!O26 -> 884 | V31: =Progress!P26 -> 872 | W31: =IFERROR(IF(ISBLANK(U31),"",U31/O31),0) -> 0.99774266 | X31: =IFERROR(IF(ISBLANK(V31),"",V31/O31),0) -> 0.98419865 | Y31: =IFERROR(X31-W31,"") -> -0.013544018 | Z31: =IFERROR(X31/W31,"") -> 0.98642534
A32: =Progress!A27 -> Z10 | B32: =C38-I38 -> 3977868.9 | C32: =Progress!C27 -> 8833596.8 | D32: =Progress!D27 -> 0.027627016 | E32: =Progress!E27 -> 0 | F32: =Progress!F27 -> 0 | G32: =Progress!G27 -> 8833596.8 | H32: =Progress!H27 -> 8833596.8 | I32: =Progress!I27 -> 8666952.3 | J32: =IFERROR(IF(ISBLANK(G32),"",G32/C32),0) -> 1 | K32: =IFERROR(IF(ISBLANK(H32),"",H32/C32),0) -> 1 | L32: =IFERROR(IF(ISBLANK(I32),"",I32/C32),0) -> 0.98113514 | M32: =IFERROR(L32-K32,"") -> -0.018864863 | N32: =IFERROR(L32/J32,"") -> 0.98113514 | O32: =+Progress!K27 -> 1532 | P32: =IF(ISBLANK(O32),"",O32/$O$38) -> 0.031886773 | Q32: =Progress!M27 -> 0 | R32: =Progress!N27 -> 0 | S32: =IFERROR(IF(ISBLANK(Q32),"",Q32/O32),0) -> 0 | T32: =IFERROR(IF(ISBLANK(R32),"",R32/O32),0) -> 0 | U32: =Progress!O27 -> 1532 | V32: =Progress!P27 -> 1511 | W32: =IFERROR(IF(ISBLANK(U32),"",U32/O32),0) -> 1 | X32: =IFERROR(IF(ISBLANK(V32),"",V32/O32),0) -> 0.98629243 | Y32: =IFERROR(X32-W32,"") -> -0.013707572 | Z32: =IFERROR(X32/W32,"") -> 0.98629243
A33: =Progress!A28 -> Z11 | C33: =Progress!C28 -> 201779.17 | D33: =Progress!D28 -> 0.00063106303 | E33: =Progress!E28 -> 0 | F33: =Progress!F28 -> 0 | G33: =Progress!G28 -> 201779.17 | H33: =Progress!H28 -> 201779.17 | I33: =Progress!I28 -> 192096.05 | J33: =IFERROR(IF(ISBLANK(G33),"",G33/C33),0) -> 1 | K33: =IFERROR(IF(ISBLANK(H33),"",H33/C33),0) -> 1 | L33: =IFERROR(IF(ISBLANK(I33),"",I33/C33),0) -> 0.9520113 | M33: =IFERROR(L33-K33,"") -> -0.0479887 | N33: =IFERROR(L33/J33,"") -> 0.9520113 | O33: =+Progress!K28 -> 314 | P33: =IF(ISBLANK(O33),"",O33/$O$38) -> 0.0065355396 | Q33: =Progress!M28 -> 0 | R33: =Progress!N28 -> 0 | S33: =IFERROR(IF(ISBLANK(Q33),"",Q33/O33),0) -> 0 | T33: =IFERROR(IF(ISBLANK(R33),"",R33/O33),0) -> 0 | U33: =Progress!O28 -> 314 | V33: =Progress!P28 -> 313 | W33: =IFERROR(IF(ISBLANK(U33),"",U33/O33),0) -> 1 | X33: =IFERROR(IF(ISBLANK(V33),"",V33/O33),0) -> 0.99681529 | Y33: =IFERROR(X33-W33,"") -> -0.0031847134 | Z33: =IFERROR(X33/W33,"") -> 0.99681529
A34: =Progress!A29 -> Z13 | C34: =Progress!C29 -> 5395935.5 | D34: =Progress!D29 -> 0.016875753 | E34: =Progress!E29 -> 0 | F34: =Progress!F29 -> 0 | G34: =Progress!G29 -> 5395935.5 | H34: =Progress!H29 -> 5395935.5 | I34: =Progress!I29 -> 5395935.5 | J34: =IFERROR(IF(ISBLANK(G34),"",G34/C34),0) -> 1 | K34: =IFERROR(IF(ISBLANK(H34),"",H34/C34),0) -> 1 | L34: =IFERROR(IF(ISBLANK(I34),"",I34/C34),0) -> 1 | M34: =IFERROR(L34-K34,"") -> 0 | N34: =IFERROR(L34/J34,"") -> 1 | O34: =+Progress!K29 -> 526 | P34: =IF(ISBLANK(O34),"",O34/$O$38) -> 0.01094807 | Q34: =Progress!M29 -> 0 | R34: =Progress!N29 -> 0 | S34: =IFERROR(IF(ISBLANK(Q34),"",Q34/O34),0) -> 0 | T34: =IFERROR(IF(ISBLANK(R34),"",R34/O34),0) -> 0 | U34: =Progress!O29 -> 526 | V34: =Progress!P29 -> 526 | W34: =IFERROR(IF(ISBLANK(U34),"",U34/O34),0) -> 1 | X34: =IFERROR(IF(ISBLANK(V34),"",V34/O34),0) -> 1 | Y34: =IFERROR(X34-W34,"") -> 0 | Z34: =IFERROR(X34/W34,"") -> 1
A35: =Progress!A30 -> CCTV | C35: =Progress!C30 -> 5075749.7 | D35: =Progress!D30 -> 0.015874374 | E35: =Progress!E30 -> 0 | F35: =Progress!F30 -> 0 | G35: =Progress!G30 -> 5075749.7 | H35: =Progress!H30 -> 5075749.7 | I35: =Progress!I30 -> 5075749.7 | J35: =IFERROR(IF(ISBLANK(G35),"",G35/C35),0) -> 1 | K35: =IFERROR(IF(ISBLANK(H35),"",H35/C35),0) -> 1 | L35: =IFERROR(IF(ISBLANK(I35),"",I35/C35),0) -> 1 | M35: =IFERROR(L35-K35,"") -> 0 | N35: =IFERROR(L35/J35,"") -> 1 | O35: =+Progress!K30 -> 9 | P35: =IF(ISBLANK(O35),"",O35/$O$38) -> 0.00018732438 | Q35: =Progress!M30 -> 0 | R35: =Progress!N30 -> 0 | S35: =IFERROR(IF(ISBLANK(Q35),"",Q35/O35),0) -> 0 | T35: =IFERROR(IF(ISBLANK(R35),"",R35/O35),0) -> 0 | U35: =Progress!O30 -> 9 | V35: =Progress!P30 -> 9 | W35: =IFERROR(IF(ISBLANK(U35),"",U35/O35),0) -> 1 | X35: =IFERROR(IF(ISBLANK(V35),"",V35/O35),0) -> 1 | Y35: =IFERROR(X35-W35,"") -> 0 | Z35: =IFERROR(X35/W35,"") -> 1
A36: =Progress!A31 -> New Scope | C36: =Progress!C31 -> 1920841.2 | D36: =Progress!D31 -> 0.0060074181 | E36: =Progress!E31 -> 0 | F36: =Progress!F31 -> 9073.11 | G36: =Progress!G31 -> 1920841.2 | H36: =Progress!H31 -> 1920841.2 | I36: =Progress!I31 -> 1881472.1 | J36: =IFERROR(IF(ISBLANK(G36),"",G36/C36),0) -> 1 | K36: =IFERROR(IF(ISBLANK(H36),"",H36/C36),0) -> 1 | L36: =IFERROR(IF(ISBLANK(I36),"",I36/C36),0) -> 0.97950423 | M36: =IFERROR(L36-K36,"") -> -0.020495766 | N36: =IFERROR(L36/J36,"") -> 0.97950423 | O36: =+Progress!K31 -> 617 | P36: =IF(ISBLANK(O36),"",O36/$O$38) -> 0.012842127 | Q36: =Progress!M31 -> 0 | R36: =Progress!N31 -> 3 | S36: =IFERROR(IF(ISBLANK(Q36),"",Q36/O36),0) -> 0 | T36: =IFERROR(IF(ISBLANK(R36),"",R36/O36),0) -> 0.0048622366 | U36: =Progress!O31 -> 617 | V36: =Progress!P31 -> 595 | W36: =IFERROR(IF(ISBLANK(U36),"",U36/O36),0) -> 1 | X36: =IFERROR(IF(ISBLANK(V36),"",V36/O36),0) -> 0.9643436 | Y36: =IFERROR(X36-W36,"") -> -0.035656402 | Z36: =IFERROR(X36/W36,"") -> 0.9643436
A37: =Progress!A32 -> JDH3-02-008-Close Out | C37: =Progress!C32 -> 31974488 | D37: =Progress!D32 -> 0.1 | E37: =Progress!E32 -> 0 | F37: =Progress!F32 -> 221749.97 | G37: =Progress!G32 -> 31974488 | H37: =Progress!H32 -> 31974488 | I37: =Progress!I32 -> 30357173 | J37: =IFERROR(IF(ISBLANK(G37),"",G37/C37),0) -> 1 | K37: =IFERROR(IF(ISBLANK(H37),"",H37/C37),0) -> 1 | L37: =IFERROR(IF(ISBLANK(I37),"",I37/C37),0) -> 0.9494186 | M37: =IFERROR(L37-K37,"") -> -0.050581395 | N37: =IFERROR(L37/J37,"") -> 0.9494186 | O37: =+Progress!K32 -> 0 | P37: =IF(ISBLANK(O37),"",O37/$O$38) -> 0 | Q37: =Progress!M32 -> 0 | R37: =Progress!N32 -> 0 | S37: =IFERROR(IF(ISBLANK(Q37),"",Q37/O37),0) -> 0 | T37: =IFERROR(IF(ISBLANK(R37),"",R37/O37),0) -> 0 | U37: =Progress!O32 -> 0 | V37: =Progress!P32 -> 0 | W37: =IFERROR(IF(ISBLANK(U37),"",U37/O37),0) -> 0 | X37: =IFERROR(IF(ISBLANK(V37),"",V37/O37),0) -> 0 | Y37: =IFERROR(X37-W37,"") -> 0 | Z37: =IFERROR(X37/W37,"")
B38: Total | C38: =C12+C13+C14+C15+C37 -> 3.1974488e+08 | D38: =D12+D13+D14+D15+D37 -> 1 | E38: =E12+E13+E14+E15+E37 -> 0 | F38: =F12+F13+F14+F15+F37 -> 467114.68 | G38: =G12+G13+G14+G15+G37 -> 3.1974488e+08 | H38: =H12+H13+H14+H15+H37 -> 3.1974488e+08 | I38: =I12+I13+I14+I15+I37 -> 3.1576701e+08 | J38: =G38/C38 -> 1 | K38: =H38/C38 -> 1 | L38: =I38/C38 -> 0.98755924 | M38: =+L38-J38 -> -0.012440759 | N38: =IFERROR(L38/J38,"") -> 0.98755924 | O38: =O12+O13+O14+O15+O37 -> 48045 | P38: =P12+P13+P14+P15+P37 -> 1 | Q38: =Q12+Q13+Q14+Q15+Q37 -> 0 | R38: =R12+R13+R14+R15+R37 -> 39 | S38: =IFERROR(IF(ISBLANK(Q38),"",Q38/O38),0) -> 0 | T38: =IFERROR(IF(ISBLANK(R38),"",R38/O38),0) -> 0.00081173899 | U38: =U12+U13+U14+U15+U37 -> 48012 | V38: =V12+V13+V14+V15+V37 -> 47522 | W38: =IFERROR(IF(ISBLANK(U38),"",U38/O38),0) -> 0.99931314 | X38: =IFERROR(IF(ISBLANK(V38),"",V38/O38),0) -> 0.98911437 | Y38: =+X38-W38 -> -0.010198772 | Z38: =X38/W38 -> 0.98979422
AA39: Construction Milestones
AA40: Item No. | AB40: Milestones | AD40: Original (Baseline) | AE40: Latest Plan | AF40: Forecast | AG40: Status | AH40: Days Change
AA41: =+Milestones!A4 -> 1 | AB41: =+Milestones!B4 -> Award Date | AD41: =+Milestones!C4 -> 45469 | AE41: =+Milestones!D4 -> 45469 | AF41: =+Milestones!E4 -> 45469 | AG41: =+Milestones!F4 -> A | AH41: =+Milestones!G4 -> 0
AA42: =+Milestones!A5 -> 2 | AB42: =+Milestones!B5 -> Contract Sign Date | AD42: =+Milestones!C5 -> 45495 | AE42: =+Milestones!D5 -> 45495 | AF42: =+Milestones!E5 -> 45495 | AG42: =+Milestones!F5 -> A | AH42: =+Milestones!G5 -> 0
AA43: =+Milestones!A6 -> 3 | AB43: =+Milestones!B6 -> Site Handover Date | AD43: =+Milestones!C6 -> 45502 | AE43: =+Milestones!D6 -> 45502 | AF43: =+Milestones!E6 -> 45502 | AG43: =+Milestones!F6 -> A | AH43: =+Milestones!G6 -> 0
AA44: =+Milestones!A7 -> 4 | AB44: =+Milestones!B7 -> Complete Mobilization | AD44: =+Milestones!C7 -> 45538 | AE44: =+Milestones!D7 -> 45538 | AF44: =+Milestones!E7 -> 45591 | AG44: =+Milestones!F7 -> A | AH44: =+Milestones!G7 -> 0
AA45: =+Milestones!A8 -> 5 | AB45: =+Milestones!B8 -> Complete existing condition survey, submission of Final Reports | AD45: =+Milestones!C8 -> 45907 | AE45: =+Milestones!D8 -> 45861 | AF45: =+Milestones!E8 -> 45861 | AG45: =+Milestones!F8 -> A | AH45: =+Milestones!G8 -> 0
AA46: =+Milestones!A9 -> 6 | AB46: =+Milestones!B9 -> Complete Earthworks | AD46: =+Milestones!C9 -> 46210 | AE46: =+Milestones!D9 -> 46208 | AF46: =+Milestones!E9 -> 46205 | AG46: =+Milestones!F9 -> F | AH46: =+Milestones!G9 -> 3
G47: 20000000 | AA47: =+Milestones!A10 -> 7 | AB47: =+Milestones!B10 -> Complete steel structure errection for all blocks | AD47: =+Milestones!C10 -> 46205 | AE47: =+Milestones!D10 -> 46117 | AF47: =+Milestones!E10 -> 46078 | AG47: =+Milestones!F10 -> F | AH47: =+Milestones!G10 -> 39
AA48: =+Milestones!A11 -> 8 | AB48: =+Milestones!B11 -> Complete all Civil Works | AD48: =+Milestones!C11 -> 46210 | AE48: =+Milestones!D11 -> 46208 | AF48: =+Milestones!E11 -> 46205 | AG48: =+Milestones!F11 -> F | AH48: =+Milestones!G11 -> 3
AA49: =+Milestones!A12 -> 9 | AB49: =+Milestones!B12 -> Complete Mechanical Works | AD49: =+Milestones!C12 -> 45931 | AE49: =+Milestones!D12 -> 46208 | AF49: =+Milestones!E12 -> 46200 | AG49: =+Milestones!F12 -> F | AH49: =+Milestones!G12 -> 8
A65: Performance overview
A66: Submittals Status | L66: Quality | W66: Safety
A67: Shop Drawings | L67: Quality Reports | W67: Safety Statistics | AE67: Proactive Vs Reactive Actions Taken
A68: Item Per WBS | C68: Total | D68: Total Submitted Drawings | I68: Remaining | J68: Pending | K68: Total Submittals | L68: Quality Reports | N68: Issued | O68: Closed | P68: Pending | Q68: Avg. Closing (Days) | R68: Pending | W68: Category | X68: Item | Z68: This Week | AB68: This Month | AC68: Year to Date | AD68: Cumulative
D69: A | E69: B | F69: C | G69: D | H69: Processed | R69: 0-10 Days | S69: 11-20 Days | T69: 21-30 Days | U69: 31-60 Days | V69: > 60 Days
A70: Road | C70: =IF('Quality-Stat'!D13="","",'Quality-Stat'!D13) -> 1940 | D70: =IF('Quality-Stat'!E13="","",'Quality-Stat'!E13) -> 84 | E70: =IF('Quality-Stat'!F13="","",'Quality-Stat'!F13) -> 1700 | F70: =IF('Quality-Stat'!G13="","",'Quality-Stat'!G13) -> 4 | G70: =IF('Quality-Stat'!H13="","",'Quality-Stat'!H13) -> 138 | H70: =IF('Quality-Stat'!I13="","",'Quality-Stat'!I13) -> 14 | I70: =IF('Quality-Stat'!J13="","",'Quality-Stat'!J13) -> 0 | J70: =IF('Quality-Stat'!K13="","",'Quality-Stat'!K13) -> 14 | K70: =IF('Quality-Stat'!L13="","",'Quality-Stat'!L13) -> 1940 | W70: General | X70: ='HSE-Stat'!B4 -> Total Hours Worked | Z70: ='HSE-Stat'!D4 -> 22920 | AB70: ='HSE-Stat'!E4 -> 97050 | AC70: ='HSE-Stat'!F4 -> 1866079 | AD70: ='HSE-Stat'!G4 -> 2210362 | AG70: Proactive | AH70: =+SUM(AD81:AD85) -> 3736
A71: Infrastructure | C71: =IF('Quality-Stat'!D14="","",'Quality-Stat'!D14) -> 437 | D71: =IF('Quality-Stat'!E14="","",'Quality-Stat'!E14) -> 4 | E71: =IF('Quality-Stat'!F14="","",'Quality-Stat'!F14) -> 423 | F71: =IF('Quality-Stat'!G14="","",'Quality-Stat'!G14) -> 8 | G71: =IF('Quality-Stat'!H14="","",'Quality-Stat'!H14) -> 2 | H71: =IF('Quality-Stat'!I14="","",'Quality-Stat'!I14) -> 0 | I71: =IF('Quality-Stat'!J14="","",'Quality-Stat'!J14) -> 0 | J71: =IF('Quality-Stat'!K14="","",'Quality-Stat'!K14) -> 0 | K71: =IF('Quality-Stat'!L14="","",'Quality-Stat'!L14) -> 437 | L71: Non Conformance (NCR) | N71: ='Quality-Stat'!C5 -> 102 | O71: ='Quality-Stat'!D5 -> 99 | P71: ='Quality-Stat'!E5 -> 3 | Q71: ='Quality-Stat'!F5 -> 7 | R71: ='Quality-Stat'!G5 -> 1 | S71: ='Quality-Stat'!H5 -> 0 | T71: ='Quality-Stat'!I5 -> 0 | U71: ='Quality-Stat'!J5 -> 0 | V71: ='Quality-Stat'!K5 -> 0 | X71: ='HSE-Stat'!B5 -> Safe Hours Worked | Z71: ='HSE-Stat'!D5 -> 22920 | AB71: ='HSE-Stat'!E5 -> 97050 | AC71: ='HSE-Stat'!F5 -> 1866079 | AD71: ='HSE-Stat'!G5 -> 2210362 | AG71: Reactive | AH71: =SUM(AD72:AD80) -> 12
A72: Electrical | C72: =IF('Quality-Stat'!D15="","",'Quality-Stat'!D15) -> 158 | D72: =IF('Quality-Stat'!E15="","",'Quality-Stat'!E15) -> 21 | E72: =IF('Quality-Stat'!F15="","",'Quality-Stat'!F15) -> 111 | F72: =IF('Quality-Stat'!G15="","",'Quality-Stat'!G15) -> 2 | G72: =IF('Quality-Stat'!H15="","",'Quality-Stat'!H15) -> 0 | H72: =IF('Quality-Stat'!I15="","",'Quality-Stat'!I15) -> 0 | I72: =IF('Quality-Stat'!J15="","",'Quality-Stat'!J15) -> 24 | J72: =IF('Quality-Stat'!K15="","",'Quality-Stat'!K15) -> 0 | K72: =IF('Quality-Stat'!L15="","",'Quality-Stat'!L15) -> 134 | L72: Site Instruction (SIR) | N72: ='Quality-Stat'!C6 -> 187 | O72: ='Quality-Stat'!D6 -> 177 | P72: ='Quality-Stat'!E6 -> 10 | Q72: ='Quality-Stat'!F6 -> 5 | R72: ='Quality-Stat'!G6 -> 1 | S72: ='Quality-Stat'!H6 -> 0 | T72: ='Quality-Stat'!I6 -> 0 | U72: ='Quality-Stat'!J6 -> 0 | V72: ='Quality-Stat'!K6 -> 0 | W72: Reactive | X72: ='HSE-Stat'!B6 -> LTI | Z72: ='HSE-Stat'!D6 -> 0 | AB72: ='HSE-Stat'!E6 -> 0 | AC72: ='HSE-Stat'!F6 -> 0 | AD72: ='HSE-Stat'!G6 -> 0
C73: =IF('Quality-Stat'!D16="","",'Quality-Stat'!D16) -> 3 | D73: =IF('Quality-Stat'!E16="","",'Quality-Stat'!E16) -> 0 | E73: =IF('Quality-Stat'!F16="","",'Quality-Stat'!F16) -> 3 | F73: =IF('Quality-Stat'!G16="","",'Quality-Stat'!G16) -> 0 | G73: =IF('Quality-Stat'!H16="","",'Quality-Stat'!H16) -> 0 | H73: =IF('Quality-Stat'!I16="","",'Quality-Stat'!I16) -> 0 | I73: =IF('Quality-Stat'!J16="","",'Quality-Stat'!J16) | J73: =IF('Quality-Stat'!K16="","",'Quality-Stat'!K16) -> 0 | K73: =IF('Quality-Stat'!L16="","",'Quality-Stat'!L16) -> 3 | L73: Material Inspection (MIR) | N73: ='Quality-Stat'!C7 -> 357 | O73: ='Quality-Stat'!D7 -> 355 | P73: ='Quality-Stat'!E7 -> 2 | Q73: ='Quality-Stat'!F7 -> 0 | R73: ='Quality-Stat'!G7 -> 0 | S73: ='Quality-Stat'!H7 -> 0 | T73: ='Quality-Stat'!I7 -> 0 | U73: ='Quality-Stat'!J7 -> 0 | V73: ='Quality-Stat'!K7 -> 0 | X73: ='HSE-Stat'!B7 -> MTC (Healed w/o Disability) | Z73: ='HSE-Stat'!D7 -> 0 | AB73: ='HSE-Stat'!E7 -> 0 | AC73: ='HSE-Stat'!F7 -> 0 | AD73: ='HSE-Stat'!G7 -> 0
C74: =IF('Quality-Stat'!D17="","",'Quality-Stat'!D17) -> 1 | D74: =IF('Quality-Stat'!E17="","",'Quality-Stat'!E17) -> 0 | E74: =IF('Quality-Stat'!F17="","",'Quality-Stat'!F17) -> 1 | F74: =IF('Quality-Stat'!G17="","",'Quality-Stat'!G17) -> 3 | G74: =IF('Quality-Stat'!H17="","",'Quality-Stat'!H17) -> 0 | H74: =IF('Quality-Stat'!I17="","",'Quality-Stat'!I17) -> 0 | I74: =IF('Quality-Stat'!J17="","",'Quality-Stat'!J17) | J74: =IF('Quality-Stat'!K17="","",'Quality-Stat'!K17) -> 0 | K74: =IF('Quality-Stat'!L17="","",'Quality-Stat'!L17) -> 4 | L74: Field Inspection (FIR) | N74: ='Quality-Stat'!C8 -> 30963 | O74: ='Quality-Stat'!D8 -> 30863 | P74: ='Quality-Stat'!E8 -> 100 | Q74: ='Quality-Stat'!F8 -> 0 | R74: ='Quality-Stat'!G8 -> 0 | S74: ='Quality-Stat'!H8 -> 0 | T74: ='Quality-Stat'!I8 -> 0 | U74: ='Quality-Stat'!J8 -> 0 | V74: ='Quality-Stat'!K8 -> 0 | X74: ='HSE-Stat'!B8 -> MTC (Healed w/ Disability) | Z74: ='HSE-Stat'!D8 -> 0 | AB74: ='HSE-Stat'!E8 -> 0 | AC74: ='HSE-Stat'!F8 -> 0 | AD74: ='HSE-Stat'!G8 -> 0
A75: TOTAL | C75: =SUM(C70:C74) -> 2539 | D75: =SUM(D70:D74) -> 109 | E75: =SUM(E70:E74) -> 2238 | F75: =SUM(F70:F74) -> 17 | G75: =SUM(G70:G74) -> 140 | H75: =SUM(H70:H74) -> 14 | I75: =SUM(I70:I74) -> 24 | J75: =SUM(J70:J74) -> 14 | K75: =SUM(K70:K74) -> 2518 | L75: Key Submittals Approval Status | X75: ='HSE-Stat'!B9 -> Near Miss | Z75: ='HSE-Stat'!D9 -> 0 | AB75: ='HSE-Stat'!E9 -> 0 | AC75: ='HSE-Stat'!F9 -> 9 | AD75: ='HSE-Stat'!G9 -> 11
A76: Material Approval | L76: 1 Quality Plan Approval | O76: ='General Information'!C27 -> 45654 | Q76: 6 Baseline Approval | U76: ='General Information'!C39 -> 45533 | X76: ='HSE-Stat'!B10 -> First Aid Cases | Z76: ='HSE-Stat'!D10 -> 0 | AB76: ='HSE-Stat'!E10 -> 0 | AC76: ='HSE-Stat'!F10 -> 0 | AD76: ='HSE-Stat'!G10 -> 0 | AE76: Total Hours Worked Vs Safe Hours Worked
A77: Item Per WBS | C77: Total | D77: Total Submitted Material | I77: Remaining to approve | J77: Pending | K77: Total Submittals | L77: 2 Quality Plan Last Up | O77: ='General Information'!C28 -> 45654 | Q77: 7 No of Approved Version of Schedule | U77: ='General Information'!C40 -> 3 | X77: ='HSE-Stat'!B11 -> Fatality | Z77: ='HSE-Stat'!D11 -> 0 | AB77: ='HSE-Stat'!E11 -> 0 | AC77: ='HSE-Stat'!F11 -> 0 | AD77: ='HSE-Stat'!G11 -> 0
D78: A | E78: B | F78: C | G78: D | H78: Processed | I78: with Designer | L78: 3 Safety Plan Approval | O78: ='General Information'!C31 -> 45523 | Q78: 8 Last Approved Schedule | U78: ='General Information'!C41 -> 45586 | X78: ='HSE-Stat'!B12 -> Fire Incident Cases | Z78: ='HSE-Stat'!D12 -> 0 | AB78: ='HSE-Stat'!E12 -> 0 | AC78: ='HSE-Stat'!F12 -> 0 | AD78: ='HSE-Stat'!G12 -> 0
A79: Road | C79: =IF('Quality-Stat'!D24="","",'Quality-Stat'!D24) -> 35 | D79: =IF('Quality-Stat'!E24="","",'Quality-Stat'!E24) -> 1 | E79: =IF('Quality-Stat'!F24="","",'Quality-Stat'!F24) -> 6 | F79: =IF('Quality-Stat'!G24="","",'Quality-Stat'!G24) -> 2 | G79: =IF('Quality-Stat'!H24="","",'Quality-Stat'!H24) -> 0 | H79: =IF('Quality-Stat'!I24="","",'Quality-Stat'!I24) -> 26 | I79: =IF('Quality-Stat'!J24="","",'Quality-Stat'!J24) -> 0 | J79: =IF('Quality-Stat'!K24="","",'Quality-Stat'!K24) -> 26 | K79: =IF('Quality-Stat'!L24="","",'Quality-Stat'!L24) -> 35 | L79: 4 Safety Plan Last Up | O79: ='General Information'!C32 -> 45582 | Q79: 9 BOQ Approval Date | U79: ='General Information'!C44 -> 45538 | X79: ='HSE-Stat'!B13 -> Vehicle Incident | Z79: ='HSE-Stat'!D13 -> 0 | AB79: ='HSE-Stat'!E13 -> 0 | AC79: ='HSE-Stat'!F13 -> 1 | AD79: ='HSE-Stat'!G13 -> 1
A80: Infrastructure | C80: =IF('Quality-Stat'!D25="","",'Quality-Stat'!D25) -> 23 | D80: =IF('Quality-Stat'!E25="","",'Quality-Stat'!E25) -> 14 | E80: =IF('Quality-Stat'!F25="","",'Quality-Stat'!F25) -> 7 | F80: =IF('Quality-Stat'!G25="","",'Quality-Stat'!G25) -> 1 | G80: =IF('Quality-Stat'!H25="","",'Quality-Stat'!H25) -> 0 | H80: =IF('Quality-Stat'!I25="","",'Quality-Stat'!I25) -> 1 | I80: =IF('Quality-Stat'!J25="","",'Quality-Stat'!J25) -> 0 | J80: =IF('Quality-Stat'!K25="","",'Quality-Stat'!K25) -> 1 | K80: =IF('Quality-Stat'!L25="","",'Quality-Stat'!L25) -> 23 | L80: 5 Construction Plan Approval | O80: ='General Information'!C48 -> 45743 | Q80: 10 No of Approved Version of BOQ | U80: ='General Information'!C45 -> 1 | X80: ='HSE-Stat'!B14 -> Property Damages | Z80: ='HSE-Stat'!D14 -> 0 | AB80: ='HSE-Stat'!E14 -> 0 | AC80: ='HSE-Stat'!F14 -> 0 | AD80: ='HSE-Stat'!G14 -> 0
A81: Electrical | C81: =IF('Quality-Stat'!D26="","",'Quality-Stat'!D26) -> 20 | D81: =IF('Quality-Stat'!E26="","",'Quality-Stat'!E26) -> 1 | E81: =IF('Quality-Stat'!F26="","",'Quality-Stat'!F26) -> 9 | F81: =IF('Quality-Stat'!G26="","",'Quality-Stat'!G26) -> 1 | G81: =IF('Quality-Stat'!H26="","",'Quality-Stat'!H26) -> 0 | H81: =IF('Quality-Stat'!I26="","",'Quality-Stat'!I26) -> 9 | I81: =IF('Quality-Stat'!J26="","",'Quality-Stat'!J26) -> 0 | J81: =IF('Quality-Stat'!K26="","",'Quality-Stat'!K26) -> 9 | K81: =IF('Quality-Stat'!L26="","",'Quality-Stat'!L26) -> 20 | L81: Invoices Summary | W81: Proactive | X81: ='HSE-Stat'!B15 -> Induction Training | Z81: ='HSE-Stat'!D15 -> 0 | AB81: ='HSE-Stat'!E15 -> 0 | AC81: ='HSE-Stat'!F15 -> 96 | AD81: ='HSE-Stat'!G15 -> 223
C82: =IF('Quality-Stat'!D27="","",'Quality-Stat'!D27) | D82: =IF('Quality-Stat'!E27="","",'Quality-Stat'!E27) | E82: =IF('Quality-Stat'!F27="","",'Quality-Stat'!F27) | F82: =IF('Quality-Stat'!G27="","",'Quality-Stat'!G27) | G82: =IF('Quality-Stat'!H27="","",'Quality-Stat'!H27) | H82: =IF('Quality-Stat'!I27="","",'Quality-Stat'!I27) | I82: =IF('Quality-Stat'!J27="","",'Quality-Stat'!J27) | J82: =IF('Quality-Stat'!K27="","",'Quality-Stat'!K27) -> 0 | K82: =IF('Quality-Stat'!L27="","",'Quality-Stat'!L27) | L82: Total Submitted Invoices | N82: ='Invoice Log'!V3 -> 0 | O82: Submitted Invoices (SAR) | R82: ='Invoice Log'!Z3 -> 2.5021413e+08 | T82: Contract Value (SR) | U82: =O4 -> 3.1974488e+08 | X82: ='HSE-Stat'!B16 -> No.of Internal Training | Z82: ='HSE-Stat'!D16 -> 2 | AB82: ='HSE-Stat'!E16 -> 7 | AC82: ='HSE-Stat'!F16 -> 145 | AD82: ='HSE-Stat'!G16 -> 178
C83: =IF('Quality-Stat'!D28="","",'Quality-Stat'!D28) | D83: =IF('Quality-Stat'!E28="","",'Quality-Stat'!E28) | E83: =IF('Quality-Stat'!F28="","",'Quality-Stat'!F28) | F83: =IF('Quality-Stat'!G28="","",'Quality-Stat'!G28) | G83: =IF('Quality-Stat'!H28="","",'Quality-Stat'!H28) | H83: =IF('Quality-Stat'!I28="","",'Quality-Stat'!I28) | I83: =IF('Quality-Stat'!J28="","",'Quality-Stat'!J28) | J83: =IF('Quality-Stat'!K28="","",'Quality-Stat'!K28) | K83: =IF('Quality-Stat'!L28="","",'Quality-Stat'!L28) | L83: PM Approved Invoices | N83: ='Invoice Log'!V5 -> 23 | O83: PM Approved Invoices (SAR) | R83: ='Invoice Log'!Z5 -> 2.465379e+08 | T83: Planned Value (SR) | U83: =H38 -> 3.1974488e+08 | X83: ='HSE-Stat'!B17 -> No.of Internal Audit | Z83: ='HSE-Stat'!D17 -> 0 | AB83: ='HSE-Stat'!E17 -> 0 | AC83: ='HSE-Stat'!F17 -> 0 | AD83: ='HSE-Stat'!G17 -> 0
A84: TOTAL | C84: =SUM(C79:C83) -> 78 | D84: =SUM(D79:D83) -> 16 | E84: =SUM(E79:E83) -> 22 | F84: =SUM(F79:F83) -> 4 | G84: =SUM(G79:G83) -> 0 | H84: =SUM(H79:H83) -> 36 | I84: =SUM(I79:I83) -> 0 | J84: =SUM(J79:J83) -> 36 | K84: =SUM(K79:K83) -> 78 | L84: No of Paid Invoices | N84: ='Invoice Log'!V6 -> 0 | O84: Paid Invoices (SAR) | R84: ='Invoice Log'!Z6 -> 0 | T84: Earned Value (SR) | U84: =I38 -> 3.1576701e+08 | X84: ='HSE-Stat'!B18 -> No. of Toolbox Talks | Z84: ='HSE-Stat'!D18 -> 8 | AB84: ='HSE-Stat'!E18 -> 34 | AC84: ='HSE-Stat'!F18 -> 3181 | AD84: ='HSE-Stat'!G18 -> 3335
A85: Procurement Summary | L85: No of Pending Invoices | N85: =+N82-N84 -> 0 | O85: Last Submitted Period | R85: ='Invoice Log'!AC3 -> 46265 | T85: Submitted (SAR) | U85: =R82 -> 2.5021413e+08 | X85: ='HSE-Stat'!B19 -> Safety Awards/Incentives | Z85: ='HSE-Stat'!D19 -> 0 | AB85: ='HSE-Stat'!E19 -> 0 | AC85: ='HSE-Stat'!F19 -> 0 | AD85: ='HSE-Stat'!G19 -> 0
A86: Item Per WBS | C86: Total Materials | D86: Total Number of P.O. | E86: Actual P.O. To Date | F86: Remaining P.O | G86: Material on Site | H86: Remaining Materials | I86: Material Delivery Completion (Date) | L86: Advance Payment % | N86: ='Invoice Log'!N3 -> 0.1 | O86: Advance Payment (SAR) | R86: ='Invoice Log'!R3 -> 31974488 | T86: PM Approved (SAR) | U86: =R83 -> 2.465379e+08 | W86: Latest Contract Change Order Log
D87: A | E87: B | F87: C | G87: D | H87: Processed | L87: Retention % | N87: ='Invoice Log'!N4 -> 0 | O87: Retention (SAR) | R87: ='Invoice Log'!R4 -> 0 | T87: Total Paid (SAR) | U87: =R84 -> 0
A88: Road | C88: =IF('Quality-Stat'!D34="","",'Quality-Stat'!D34) -> 4 | D88: =IF('Quality-Stat'!E34="","",'Quality-Stat'!E34) -> 4 | E88: =IF('Quality-Stat'!F34="","",'Quality-Stat'!F34) -> 3 | F88: =IF('Quality-Stat'!G34="","",'Quality-Stat'!G34) -> 1 | G88: =IF('Quality-Stat'!H34="","",'Quality-Stat'!H34) -> 3 | H88: =IF('Quality-Stat'!I34="","",'Quality-Stat'!I34) | L88: Deduction / Penalties % | N88: ='Invoice Log'!N5 -> 0.00081314829 | O88: Deduction / Penalties (SAR) | R88: ='Invoice Log'!N6 -> -260000 | W88: CCO No. | X88: Date Added | Y88: Description of Change | AD88: Status | AE88: Cost | AF88: Sch Impact (Months) | AG88: Date Approved | AH88: Duration
A89: Infrastructure | C89: =IF('Quality-Stat'!D35="","",'Quality-Stat'!D35) -> 8 | D89: =IF('Quality-Stat'!E35="","",'Quality-Stat'!E35) -> 8 | E89: =IF('Quality-Stat'!F35="","",'Quality-Stat'!F35) -> 7 | F89: =IF('Quality-Stat'!G35="","",'Quality-Stat'!G35) -> 1 | G89: =IF('Quality-Stat'!H35="","",'Quality-Stat'!H35) -> 7 | H89: =IF('Quality-Stat'!I35="","",'Quality-Stat'!I35) | L89: Resources at Site
A90: Electrical | C90: =IF('Quality-Stat'!D36="","",'Quality-Stat'!D36) -> 8 | D90: =IF('Quality-Stat'!E36="","",'Quality-Stat'!E36) -> 8 | E90: =IF('Quality-Stat'!F36="","",'Quality-Stat'!F36) -> 2 | F90: =IF('Quality-Stat'!G36="","",'Quality-Stat'!G36) -> 6 | G90: =IF('Quality-Stat'!H36="","",'Quality-Stat'!H36) | H90: =IF('Quality-Stat'!I36="","",'Quality-Stat'!I36) | L90: Head Count - Manual | P90: Head Count - Non Manual | T90: Total Head Count | W90: =CCO!A3 -> 1 | X90: =CCO!B3 -> 45854 | Y90: =CCO!C3 -> Revised BOQ | AD90: =CCO!D3 -> Completed | AE90: =CCO!E3 -> - | AF90: =CCO!F3 -> - | AG90: =CCO!G3 -> 45861 | AH90: =CCO!H3 -> -
C91: =IF('Quality-Stat'!D37="","",'Quality-Stat'!D37) | D91: =IF('Quality-Stat'!E37="","",'Quality-Stat'!E37) | E91: =IF('Quality-Stat'!F37="","",'Quality-Stat'!F37) | F91: =IF('Quality-Stat'!G37="","",'Quality-Stat'!G37) | G91: =IF('Quality-Stat'!H37="","",'Quality-Stat'!H37) | H91: =IF('Quality-Stat'!I37="","",'Quality-Stat'!I37) | L91: Planned | M91: Actual | N91: Next Month Forecast | O91: Saudi Staff | P91: Planned | Q91: Actual | R91: Next Month Forecast | S91: Saudi Staff | T91: Total Plan | U91: Total Actual | V91: Variance
C92: =IF('Quality-Stat'!D38="","",'Quality-Stat'!D38) | D92: =IF('Quality-Stat'!E38="","",'Quality-Stat'!E38) | E92: =IF('Quality-Stat'!F38="","",'Quality-Stat'!F38) | F92: =IF('Quality-Stat'!G38="","",'Quality-Stat'!G38) | G92: =IF('Quality-Stat'!H38="","",'Quality-Stat'!H38) | H92: =IF('Quality-Stat'!I38="","",'Quality-Stat'!I38) | L92: =Manpower!A20 -> 0 | M92: =Manpower!B20 -> 1092 | N92: =Manpower!F20 -> 0 | O92: =Manpower!H24 -> 0 | P92: =Manpower!A24 -> 0 | Q92: =Manpower!B24 -> 92 | R92: =Manpower!F24 -> 0 | S92: =Manpower!H24 -> 0 | T92: =L92+P92 -> 0 | U92: =M92+Q92+S92 -> 1184 | V92: =+U92-T92 -> 1184
A93: TOTAL | C93: =IF('Quality-Stat'!D39="","",'Quality-Stat'!D39) -> 20 | D93: =IF('Quality-Stat'!E39="","",'Quality-Stat'!E39) -> 20 | E93: =IF('Quality-Stat'!F39="","",'Quality-Stat'!F39) -> 12 | F93: =IF('Quality-Stat'!G39="","",'Quality-Stat'!G39) -> 8 | G93: =IF('Quality-Stat'!H39="","",'Quality-Stat'!H39) -> 10 | H93: =IF('Quality-Stat'!I39="","",'Quality-Stat'!I39) -> 0 | I93: =MAX(I88:I92) -> 0 | L93: Manpower Breakdown by Trade | S93: Major Equipment
A94: =Schedule!A1 -> Primavera P6 Schedule Status | L94: Key Trade | M94: Planned | N94: Actual | S94: Type | T94: Planned | U94: Actual | V94: Idle
A95: =Schedule!A2 -> Project Activities Overview | L95: =+Manpower!N23 -> General Labor | M95: =Manpower!N24 -> 288 | N95: =Manpower!N25 -> 139 | S95: =+Manpower!$B$49 -> Excavator | T95: =+Manpower!B50 -> 55 | U95: =+Manpower!B51 -> 49 | V95: =+Manpower!B52 -> 1
A96: =Schedule!A3 -> Schedule Statistics | F96: =Schedule!F3 -> Active Schedule Activities | L96: =+Manpower!P23 -> Carpenter | M96: =Manpower!P24 -> 42 | N96: =Manpower!P25 -> 39 | S96: =+Manpower!$D$49 -> Loader | T96: =+Manpower!D50 -> 5 | U96: =+Manpower!D51 -> 4 | V96: =+Manpower!D52 -> 0 | W96: Major Quantity Trackers
A97: =Schedule!A4 -> Total Act. | B97: =Schedule!B4 -> Not Started | C97: =Schedule!C4 -> In Progress | D97: =Schedule!D4 -> Completed | E97: =Schedule!E4 -> % | F97: =Schedule!F4 -> Active | G97: =Schedule!G4 -> Ahead | H97: =Schedule!H4 -> On | ... K97: =Schedule!K4 -> 0 | L97: =+Manpower!R23 -> Plumber | M97: =+Manpower!R24 -> 26 | N97: =Manpower!R25 -> 39 | S97: =+Manpower!$F$49 -> Dozer | T97: =+Manpower!F50 -> 2 | U97: =+Manpower!F51 -> 1 | V97: =+Manpower!F52 -> 0 | W97: Unit | X97: Material | AC97: Original BOQ Qty | AD97: Revised BOQ Qty (Under Review) | AE97: Delivered Qty | AF97: Remaining | AG97: Delivery % | AH97: Installed QTY
A98: =Schedule!A5 -> 9236 | B98: =Schedule!B5 -> 141 | C98: =Schedule!C5 -> 75 | D98: =Schedule!D5 -> 9020 | E98: =Schedule!E5 -> 0.97661325 | F98: =Schedule!F5 -> 75 | G98: =Schedule!G5 -> 9020 | H98: =Schedule!H5 -> 75 | ... J98: =Schedule!J5 -> 9029 | L98: =+Manpower!T23 -> Electrician | M98: =Manpower!T24 -> 0 | N98: =Manpower!T25 -> 0 | S98: =+Manpower!$H$49 -> Dumper | T98: =+Manpower!H50 -> 50 | U98: =+Manpower!H51 -> 37 | V98: =+Manpower!H52 -> 1 | W98: ='Major Quantities'!B9 -> m | X98: ='Major Quantities'!A9 -> UPVC 300 mm Dia | AC98: ='Major Quantities'!C9 -> 28700 | AD98: ='Major Quantities'!D9 -> 29079.778 | AE98: ='Major Quantities'!E9 -> 29079.778 | AF98: =+AD98-AE98 -> 0 | AG98: ='Major Quantities'!F9 -> 1 | AH98: ='Major Quantities'!G9 -> 29079.778
A99: =Schedule!A6 -> Critical Path Activities | D99: =Schedule!D6 -> Free Float Management (Total) | H99: =Schedule!H6 -> Failed Start Activities | L99: =+Manpower!V23 -> Steel Fixer | M99: =+Manpower!V24 -> 36 | N99: =+Manpower!V25 -> 39 | S99: =+Manpower!$J$49 -> Fork lift | T99: =+Manpower!J50 -> 2 | U99: =+Manpower!J51 -> 1 | V99: =+Manpower!J52 -> 0 | W99: ='Major Quantities'!B10 -> m | X99: ='Major Quantities'!A10 -> GRP– 400 Dia | AC99: ='Major Quantities'!C10 -> 4770 | AD99: ='Major Quantities'!D10 -> 11757.93 | AE99: ='Major Quantities'!E10 -> 11757.93 | AF99: =+AD99-AE99 -> 0 | AG99: ='Major Quantities'!F10 -> 1 | AH99: ='Major Quantities'!G10 -> 11757.93
D100: =Schedule!D7 -> Greater Than 14 Days | F100: =Schedule!F7 -> Less Than 14 Days | L100: =+Manpower!X23 -> Mason | M100: =+Manpower!X24 -> 38 | N100: =+Manpower!X25 -> 0 | S100: =+Manpower!$L$49 -> Grader | T100: =+Manpower!L50 -> 1 | U100: =+Manpower!L51 -> 0 | V100: =+Manpower!L52 -> 0 | W100: ='Major Quantities'!B11 -> m | X100: ='Major Quantities'!A11 -> GRP– 500 Dia | AC100: ='Major Quantities'!C11 -> 4350 | AD100: ='Major Quantities'!D11 -> 4240.12 | AE100: ='Major Quantities'!E11 -> 4240.12 | AF100: =+AD100-AE100 -> 0 | AG100: ='Major Quantities'!F11 -> 1 | AH100: ='Major Quantities'!G11 -> 4240.12
A101: =Schedule!A8 -> Last Week | B101: =Schedule!B8 -> This Week | C101: =Schedule!C8 -> Diff | D101: =Schedule!D8 -> Last Week | E101: =Schedule!E8 -> This Week | F101: =Schedule!F8 -> Last Week | G101: =Schedule!G8 -> This Week | H101: =Schedule!H8 -> Last Week | ... K101: =Schedule!K8 -> 0 | L101: =+Manpower!Z23 -> Others | M101: =+Manpower!Z24 -> 172 | N101: =+Manpower!Z25 -> 133 | S101: =+Manpower!$N$49 -> Other | T101: =+Manpower!N50 -> 52 | U101: =+Manpower!N51 -> 43 | V101: =+Manpower!N52 -> 1 | W101: ='Major Quantities'!B12 -> m | X101: ='Major Quantities'!A12 -> GRP– 600 Dia | AC101: ='Major Quantities'!C12 -> 5050 | AD101: ='Major Quantities'!D12 -> 5965.71 | AE101: ='Major Quantities'!E12 -> 5965.71 | AF101: =+AD101-AE101 -> 0 | AG101: ='Major Quantities'!F12 -> 1 | AH101: ='Major Quantities'!G12 -> 5965.71
A102: =Schedule!A9 -> 215 | B102: =Schedule!B9 -> 216 | C102: =Schedule!C9 -> -1 | D102: =Schedule!D9 -> 240 | E102: =Schedule!E9 -> 267 | F102: =Schedule!F9 -> 2934 | G102: =Schedule!G9 -> 2812 | H102: =Schedule!H9 -> 366 | ... J102: =Schedule!J9 -> 42 | L102: Total | M102: =SUM(M95:M101) -> 602 | N102: =SUM(N95:N101) -> 389 | S102: Total | T102: =SUM(T95:T101) -> 167 | U102: =SUM(U95:U101) -> 135 | V102: =SUM(V95:V101) -> 3 | W102: ='Major Quantities'!B13 -> m | X102: ='Major Quantities'!A13 -> GRP– 700 Dia | AC102: ='Major Quantities'!C13 -> 5550 | AD102: ='Major Quantities'!D13 -> 5347.16 | AE102: ='Major Quantities'!E13 -> 5347.16 | AF102: =+AD102-AE102 -> 0 | AG102: ='Major Quantities'!F13 -> 1 | AH102: ='Major Quantities'!G13 -> 5347.16
A103: Testing And Commissioning | Q103: Top Issues and Risks
Q104: Top 5 Issues
A105: Item | B105: Planned Start Date | D105: Planned Finish Date | F105: Forecast Start Date | H105: Forecast Finish Date | J105: Actual Start Date | L105: Actual Finish Date | N105: % Completed | O105: Open Comments | P105: Closed Comments | Q105: Issue No | R105: Date Identified | S105: Issue Description | W105: Responsible | X105: Action Taken | AA105: Mitigation | AF105: Current Status | AG105: Expected/Actual Closure | AH105: Duration Elapsed
A106: =Testing!A3 -> Mechanical System | B106: =IF(Testing!B3=""," ",Testing!B3) -> 45684 | D106: =IF(Testing!C3=""," ",Testing!C3) -> 45993 | F106: =IF(Testing!D3=""," ",Testing!D3) -> 45738 | H106: =IF(Testing!E3=""," ",Testing!E3) -> 46047 | J106: =IF(Testing!F3=""," ",Testing!F3) | L106: =IF(Testing!G3=""," ",Testing!G3) | N106: =IF(Testing!H3=""," ",Testing!H3) -> 0 | O106: =IF(Testing!I3=""," ",Testing!I3) -> 0 | P106: =IF(Testing!J3=""," ",Testing!J3) -> 0 | Q106: =IF(+Issues!B11="","",+Issues!B11) -> 1 | R106: =IF(+Issues!C11="","",+Issues!C11) -> 45552 | S106: =IF(+Issues!D11="","",+Issues!D11) -> The surveying in the project was initially conducted by taking random points until an email was sent by the owner on August 27, 2024, stating the need to change the method of collecting survey points. As a result, the work had to be redone, leading to an increase in the workload beyond what was planned, which caused a delay in the project. | W106: =IF(+Issues!E11="","",+Issues!E11) -> Modon | X106: =IF(+Issues!F11="","",+Issues!F11) -> The work is ongoing according to Madon's requirements. | AF106: =IF(+Issues!H11="","",+Issues!H11) -> Closed | AG106: =IF(+Issues!I11="","",+Issues!I11) -> 45531 | AH106: =IF(+Issues!J11="","",+Issues!J11) -> 29
A107: =Testing!A4 -> Electrical System | B107: =IF(Testing!B4=""," ",Testing!B4) -> 45729 | D107: =IF(Testing!C4=""," ",Testing!C4) -> 45875 | H107: =IF(Testing!E4=""," ",Testing!E4) -> 45929 | J107: =IF(Testing!F4=""," ",Testing!F4) | L107: =IF(Testing!G4=""," ",Testing!G4) | N107: =IF(Testing!H4=""," ",Testing!H4) -> 0 | O107: =IF(Testing!I4=""," ",Testing!I4) -> 0 | P107: =IF(Testing!J4=""," ",Testing!J4) -> 0 | Q107: =IF(+Issues!B12="","",+Issues!B12) -> 2 | R107: =IF(+Issues!C12="","",+Issues!C12) -> 45552 | S107: =IF(+Issues!D12="","",+Issues!D12) -> GPS device signal was disconnecting because of bad weather conditions and strong winds, there were delays in the surveying work . | W107: =IF(+Issues!E12="","",+Issues!E12) -> Other | X107: =IF(+Issues!F12="","",+Issues!F12) -> Waiting until the weather improves | AF107: =IF(+Issues!H12="","",+Issues!H12) -> Closed | AG107: =IF(+Issues!I12="","",+Issues!I12) | AH107: =IF(+Issues!J12="","",+Issues!J12)
A108: =Testing!A5 -> Fire System | B108: =IF(Testing!B5=""," ",Testing!B5) | D108: =IF(Testing!C5=""," ",Testing!C5) | F108: =IF(Testing!D5=""," ",Testing!D5) | H108: =IF(Testing!E5=""," ",Testing!E5) | J108: =IF(Testing!F5=""," ",Testing!F5) | L108: =IF(Testing!G5=""," ",Testing!G5) | N108: =IF(Testing!H5=""," ",Testing!H5) -> 0 | O108: =IF(Testing!I5=""," ",Testing!I5) -> 0 | P108: =IF(Testing!J5=""," ",Testing!J5) -> 0 | Q108: =IF(+Issues!B13="","",+Issues!B13) -> 3 | R108: =IF(+Issues!C13="","",+Issues!C13) -> 45552 | S108: =IF(+Issues!D13="","",+Issues!D13) -> RFI There is an issue with the official response, as we have not received all the replies except for some matters related to electricity. | W108: =IF(+Issues!E13="","",+Issues!E13) -> Modon | X108: =IF(+Issues!F13="","",+Issues!F13) -> Acclerate official response | AF108: =IF(+Issues!H13="","",+Issues!H13) -> Closed | AG108: =IF(+Issues!I13="","",+Issues!I13) | AH108: =IF(+Issues!J13="","",+Issues!J13)
A109: =Testing!A6 -> Other Testing (Manhole Testing) | B109: =IF(Testing!B6=""," ",Testing!B6) | D109: =IF(Testing!C6=""," ",Testing!C6) | F109: =IF(Testing!D6=""," ",Testing!D6) | H109: =IF(Testing!E6=""," ",Testing!E6) | J109: =IF(Testing!F6=""," ",Testing!F6) | L109: =IF(Testing!G6=""," ",Testing!G6) | N109: =IF(Testing!H6=""," ",Testing!H6) -> 0 | O109: =IF(Testing!I6=""," ",Testing!I6) -> 0 | P109: =IF(Testing!J6=""," ",Testing!J6) -> 0 | Q109: =IF(+Issues!B14="","",+Issues!B14) -> 4 | R109: =IF(+Issues!C14="","",+Issues!C14) -> 45559 | S109: =IF(+Issues!D14="","",+Issues!D14) -> The As-Built drawings do not match the actual site conditions, which requires excavation with Equipments across the connection area. | W109: =IF(+Issues!E14="","",+Issues!E14) -> Modon | X109: =IF(+Issues!F14="","",+Issues!F14) -> A report on the As-Built status was submitted to the consultant on 19th August 2024 | AF109: =IF(+Issues!H14="","",+Issues!H14) -> Active | AG109: =IF(+Issues!I14="","",+Issues!I14) -> 45565 | AH109: =IF(+Issues!J14="","",+Issues!J14) -> 42
A110: =Testing!A7 -> Total | B110: =IF(Testing!B7=""," ",Testing!B7) | D110: =IF(Testing!C7=""," ",Testing!C7) | F110: =IF(Testing!D7=""," ",Testing!D7) | H110: =IF(Testing!E7=""," ",Testing!E7) | J110: =IF(Testing!F7=""," ",Testing!F7) | L110: =IF(Testing!G7=""," ",Testing!G7) | N110: =IF(Testing!H7=""," ",Testing!H7) -> 0 | O110: =IF(Testing!I7=""," ",Testing!I7) -> 0 | P110: =IF(Testing!J7=""," ",Testing!J7) -> 0 | Q110: =IF(+Issues!B15="","",+Issues!B15) -> 5 | R110: =IF(+Issues!C15="","",+Issues!C15) -> 45559 | S110: =IF(+Issues!D15="","",+Issues!D15) -> There was a delay in responding to the RFI. | W110: =IF(+Issues!E15="","",+Issues!E15) -> Modon | X110: =IF(+Issues!F15="","",+Issues!F15) -> There was a delay in responding to the inquiries, which were officially submitted to the consultant via emails starting from 10th August 2024. The inquiries were fully addressed by 12th September 2024 through online meetings. However, we have only received official responses for 51 out of 56 inquiries | AF110: =IF(+Issues!H15="","",+Issues!H15) -> Closed | AG110: =IF(+Issues!I15="","",+Issues!I15) -> 45565 | AH110: =IF(+Issues!J15="","",+Issues!J15) -> 51

Sheet General Information
A1: Weekly Progress Report - Construction Projects | K1: Data Date | L1: {=_xlfn.TEXTBEFORE(_xlfn.TEXTAFTER(_xlfn.TEXTBEFORE(_xlfn.TEXTAFTER(CELL("filename",A1),"["),"]"),"Report "),".")} -> 11-10-2026
A2: Contract General Information
A3: Project Name | C3: Completion Of The Infrastructure Development Of The First Phase In The Third Industrial City In Jeddah | L3: {=_xlfn.TEXTBEFORE(_xlfn.TEXTAFTER(_xlfn.TEXTBEFORE(_xlfn.TEXTAFTER(CELL("filename",A1),"["),"]"),"Report "),".xlsx")} -> 11-10-2026
A4: Project ID | C4: JDH3 - 02 - 008
A5: Contractor | C5: ALRAWAF CONTRACTING | P5: =+L1-C14+1 -> 805 | Q5: =+C15-C14+1+60 -> 790
A6: Consultant | C6: egis
A7: Stage | C7: Construction | P7: =+P5/790 -> 1.0189873
A8: Status | C8: Active
A9: Modon PM | C9: Shuaib A.Alshuaibi
A11: Key Dates
A12: Contract Award Date | C12: =Milestones!E4 -> 45469 | M12: تاريخ تسليم الموقع | R12: تاريخ تسليم الموقع
A13: Contract Sign Date | C13: =Milestones!E5 -> 45495 | M13: إجمالي قيمة المصروف | R13: إجمالي قيمة المصروف
A14: Site Handover Date | C14: =Milestones!E6 -> 45502 | M14: شامل ضريبة القيمة المضافة | R14: شامل ضريبة القيمة المضافة
A15: Original Completion | C15: =Milestones!C13 -> 46231 | M15: الحاجة لأوامر تغيير | R15: الحاجة لأوامر تغيير
A16: Contract Award Date (Hijri) | C16: 20-12-1445 | M16: مدة المشروع المستهدفة | R16: مدة المشروع المستهدفة
A17: Contract Sign Date (Hijri) | C17: 16-1-1446 | M17: تاريخ نهاية المشروع المستهدفة | R17: تاريخ نهاية المشروع المستهدفة
A18: Site Handover Date (Hijri) | C18: 23-1-1446 | M18: نسبة المدة المنقضية المستهدفة | R18: نسبة المدة المنقضية المستهدفة
A19: Original Completion (Hijri) | C19: 14-2-1448 | M19: نسبة إنجاز المشروع الفعلية | R19: نسبة إنجاز المشروع الفعلية
A20: Revised Completion Date | C20: =C15+60 -> 46291 | M20: النسبة المستهدفة للربع القادم | R20: النسبة المستهدفة للربع القادم
A21: Committed Completion Date | C21: =C20 -> 46291
A22: Forecast Completion | C22: 46341 | O22: =Q22/1.15 -> 3.1974488e+08 | Q22: 3.6770661e+08
A23: Variance | C23: =C20-C22 -> -50 | Q23: =+Q22*0.85 -> 3.1255062e+08 | S23: 3.1974488e+08 | T23: =+S23*0.15 -> 47961731
Q24: 997065.03 | S24: =+T23+S23 -> 3.6770661e+08
A25: Key Project Submittals | C25: Submission Date | D25: Days taken to approve orginal plan from site handover date
A26: Quality Plan submission | C26: 45524 | D26: =C26-C14 -> 22
A27: Quality Plan approval | C27: 45654
A28: Quality Plan Last Update | C28: 45654
A30: Safety Plan submission | C30: 45509 | D30: =C30-C14 -> 7
A31: Safety Plan approval | C31: 45523
A32: Safety Plan Last Update | C32: 45582
A34: Risk Management Plan submission | C34: 45524 | D34: =C34-C14 -> 22
A35: Risk Management Plan approval | C35: 45538
A36: Risk Management Plan Last Update | C36: 45585
A38: Baseline Schedule submission | C38: 45521 | D38: =C38-C14 -> 19
A39: Baseline Schedule approval | C39: 45533
A40: No of Schedule Versions | C40: 3
A41: Last Revised Schedule Approval Date | C41: 45586
A43: BOQ submission | C43: 45524 | D43: =C43-C14 -> 22
A44: BOQ approval | C44: 45538
A45: No of Approved Version of BOQ | C45: 1
A47: Construction Plan submission | C47: 45538 | D47: =C47-C14 -> 36
A48: Construction Plan Approval | C48: 45743

Sheet Progress
A1: Project Scope Statement | B1: The project includes Completion of works construction of Sewage piping network with manhole Construction.Construction of a Stormwater piping network with catch basins and manholes which will be connected to pond. Construction of Irrigation Network, inculding pipes, valve chambers. Potable water piping network including pipes and valve chambers. 13.8 KV medium voltage cable. Installation of street lighting poles along main roads.Execution of the communication network, including the installation of underground ducts and the extension of communication cables to provide telecom and data services to the site. Completion and preparation of internal and external roads, including asphalt layers and sidewalks.
AA3: Activity ID | AB3: Activity Name | AC3: Budgeted Total Cost | AD3: Earned Value Cost | AE3: Actual Labor Units | AF3: Budgeted Labor Units | AG3: Planned Value Labor Units | AH3: Planned Value Cost | AI3: Performance % Complete | AJ3: Schedule % Complete | AK3: Total Float | AL3: Start | AM3: Finish | AN3: BL Project Start | AO3: BL Project Finish
A4: Earned Value Progress (SAR) | K4: Physical Progress (Effort) | AA4: Completion of the Infrastructure development of the 1st phase in the 3rd industrial city in Jeddah | AC4: 3.1974488e+08 | AD4: 3.1529989e+08 | AE4: 47483 | AF4: 48045 | AG4: 48012 | AH4: 3.1974488e+08 | AI4: 0.9861 | AJ4: 1 | AK4: -59 | AL4: 29-Jul-24 A | AM4: 46350 | AN4: 45502 | AO4: 46291
A5: WBS | C5: BOQ Value (SAR) | D5: % Wt. | E5: Weekly (SAR) | H5: To Date (SAR) | K5: Budgeted | L5: % Wt. | M5: Weekly Physical Progress | O5: To Date Physical Progress | AA5: JDH3-02-008-Milestones - MI | AC5: 0 | AD5: 0 | AE5: 0 | AF5: 0 | AG5: 0 | AH5: 0 | AI5: 0 | AJ5: 0 | AK5: -59 | AL5: 29-Jul-24 A | AM5: 46350 | AN5: 45502 | AO5: 46291
E6: Planned | F6: Earned | G6: Revised Plan | H6: Revised Plan | I6: Earned | K6: (Manhours) | M6: Planned | N6: Earned | O6: Planned | P6: Earned | T6: 0 | U6: =Progress!AG7 -> 0 | V6: 0 | W6: =Progress!AE7 -> 0 | Y6: Planned Value Cost | Z6: Earned Value Cost | AA6: JDH3-02-008-Mobilization - Mob | AC6: 0 | AD6: 0 | AE6: 0 | AF6: 0 | AG6: 0 | AH6: 0 | AI6: 0 | AJ6: 0 | AL6: 29-Jul-24 A | AM6: 01-Feb-25 A | AN6: 45502 | AO6: 45689
A7: =Progress!W44 -> JDH3-02-008-Authorities Permits & Approval - AT | C7: =Progress!Y44 -> 0 | D7: =C7/$C$33 -> 0 | E7: =Progress!Y7 -> 0 | F7: =Progress!Z7 -> 0 | G7: =Progress!AD44 -> 0 | H7: =G7 -> 0 | I7: =Progress!Z44 -> 0 | K7: =Progress!AB44 -> 0 | L7: =K7/$K$33 -> 0 | M7: =Progress!T7 -> 0 | N7: =Progress!V7 -> 0 | O7: =Progress!AC44 -> 0 | P7: =Progress!AA44 -> 0 | R7: JDH3-02-008-Authorities Permits & Approval - AT | T7: =+O7-U7 -> 0 | U7: =Progress!AG8 -> 0 | V7: =+AA44-W7 -> 0 | W7: =Progress!AE8 -> 0 | Y7: =+AD44-AH7 -> 0 | Z7: =Z44-AD7 -> 0 | AA7: JDH3-02-008-Authorities Permits & Approval - AT | AC7: 0 | AD7: 0 | AE7: 0 | AF7: 0 | AG7: 0 | AH7: 0 | AI7: 0 | AJ7: 0 | AL7: 21-Oct-24 A | AM7: 19-Sep-26 A | AN7: 45586 | AO7: 46279
A8: =Progress!W45 -> JDH3-02-008-Engineering | C8: =Progress!Y45 -> 9592346.3 | D8: =C8/$C$33 -> 0.03 | E8: =Progress!Y8 -> 0 | F8: =Progress!Z8 -> 0 | G8: =Progress!AD45 -> 9592346.3 | H8: =G8 -> 9592346.3 | I8: =Progress!Z45 -> 9592346.3 | K8: =Progress!AB45 -> 0 | L8: =K8/$K$33 -> 0 | M8: =Progress!T8 -> 0 | N8: =Progress!V8 -> 0 | O8: =Progress!AC45 -> 0 | P8: =Progress!AA45 -> 0 | R8: JDH3-02-008-Engineering | T8: =+O8-U8 -> 0 | U8: =AG8 -> 0 | V8: =+AA45-W8 -> 0 | W8: =AE8 -> 0 | X8: JDH3-02-008-Engineering | Y8: =+AD45-AH8 -> 0 | Z8: =Z45-AD8 -> 0 | AA8: JDH3-02-008-Engineering | AC8: 9592346.3 | AD8: 9592346.3 | AE8: 0 | AF8: 0 | AG8: 0 | AH8: 9592346.3 | AI8: 1 | AJ8: 1 | AK8: -13 | AL8: 05-Aug-24 A | AM8: 46306 | AN8: 45509 | AO8: 46207
A9: =Progress!W46 -> JDH3-02-008-Procurement | C9: =Progress!Y46 -> 63948975 | D9: =C9/$C$33 -> 0.2 | E9: =Progress!Y9 -> 0 | F9: =Progress!Z9 -> 0 | G9: =Progress!AD46 -> 63948975 | H9: =G9 -> 63948975 | I9: =Progress!Z46 -> 63948975 | K9: =Progress!AB46 -> 0 | L9: =K9/$K$33 -> 0 | M9: =Progress!T9 -> 0 | N9: =Progress!V9 -> 0 | O9: =Progress!AC46 -> 0 | P9: =Progress!AA46 -> 0 | R9: JDH3-02-008-Procurement | T9: =+O9-U9 -> 0 | U9: =AG9 -> 0 | V9: =+AA46-W9 -> 0 | W9: =AE9 -> 0 | X9: JDH3-02-008-Procurement | Y9: =+AD46-AH9 -> 0 | Z9: =Z46-AD9 -> 0 | AA9: JDH3-02-008-Procurement | AC9: 63948975 | AD9: 63948975 | AE9: 0 | AF9: 0 | AG9: 0 | AH9: 63948975 | AI9: 1 | AJ9: 1 | AL9: 10-Oct-24 A | AM9: 26-Sep-26 A | AN9: 45575 | AO9: 46230
A10: =Progress!W47 -> JDH3-02-008-Construction | C10: =Progress!Y47 -> 2.1422907e+08 | D10: =C10/$C$33 -> 0.67 | E10: =Progress!Y10 -> 0 | F10: =Progress!Z10 -> 245364.71 | G10: =Progress!AD47 -> 2.1422907e+08 | H10: =G10 -> 2.1422907e+08 | I10: =Progress!Z47 -> 2.1186851e+08 | K10: =Progress!AB47 -> 48045 | L10: =K10/$K$33 -> 1 | M10: =Progress!T10 -> 0 | N10: =Progress!V10 -> 39 | O10: =Progress!AC47 -> 48012 | P10: =Progress!AA47 -> 47522 | R10: JDH3-02-008-Construction | T10: =+O10-U10 -> 0 | U10: =AG10 -> 48012 | V10: =+AA47-W10 -> 39 | W10: =AE10 -> 47483 | X10: JDH3-02-008-Construction | Y10: =+AD47-AH10 -> 0 | Z10: =Z47-AD10 -> 245364.71 | AA10: JDH3-02-008-Construction | AC10: 2.1422907e+08 | AD10: 2.1162315e+08 | AE10: 47483 | AF10: 48045 | AG10: 48012 | AH10: 2.1422907e+08 | AI10: 0.9878 | AJ10: 1 | AK10: -31 | AL10: 16-Aug-24 A | AM10: 46322 | AN10: 45521 | AO10: 46291
A11: =Progress!W48 -> Pond and Swales - PS | C11: =Progress!Y48 -> 27026698 | D11: =C11/$C$33 -> 0.084525819 | E11: =Progress!Y11 -> 0 | F11: =Progress!Z11 -> 0 | G11: =Progress!AD48 -> 27026698 | H11: =G11 -> 27026698 | I11: =Progress!Z48 -> 27026698 | K11: =Progress!AB48 -> 3720 | L11: =K11/$K$33 -> 0.077427412 | M11: =Progress!T11 -> 0 | N11: =Progress!V11 -> 0 | O11: =Progress!AC48 -> 3720 | P11: =Progress!AA48 -> 3720 | R11: Pond and Swales - PS | T11: =+O11-U11 -> 0 | U11: =AG11 -> 3720 | V11: =+AA48-W11 -> 0 | W11: =AE11 -> 3720 | X11: Pond and Swales - PS | Y11: =+AD48-AH11 -> 0 | Z11: =Z48-AD11 -> 0 | AA11: Pond and Swales - PS | AC11: 27026698 | AD11: 27026698 | AE11: 3720 | AF11: 3720 | AG11: 3720 | AH11: 27026698 | AI11: 1 | AJ11: 1 | AL11: 28-Sep-24 A | AM11: 25-Dec-25 A | AN11: 45563 | AO11: 46016
A12: =Progress!W49 -> High Mast | C12: =Progress!Y49 -> 2003227.7 | D12: =C12/$C$33 -> 0.0062650814 | E12: =Progress!Y12 -> 0 | F12: =Progress!Z12 -> 0 | G12: =Progress!AD49 -> 2003227.7 | H12: =G12 -> 2003227.7 | I12: =Progress!Z49 -> 2003227.7 | K12: =Progress!AB49 -> 1222 | L12: =K12/$K$33 -> 0.025434489 | M12: =Progress!T12 -> 0 | N12: =Progress!V12 -> 0 | O12: =Progress!AC49 -> 1222 | P12: =Progress!AA49 -> 1222 | R12: High Mast | T12: =+O12-U12 -> 0 | U12: =AG12 -> 1222 | V12: =+AA49-W12 -> 0 | W12: =AE12 -> 1222 | X12: High Mast | Y12: =+AD49-AH12 -> 0 | Z12: =Z49-AD12 -> 0 | AA12: High Mast | AC12: 2003227.7 | AD12: 2003227.7 | AE12: 1222 | AF12: 1222 | AG12: 1222 | AH12: 2003227.7 | AI12: 1 | AJ12: 1 | AK12: -8 | AL12: 20-Aug-25 A | AM12: 46299 | AN12: 45889 | AO12: 46232
A13: =Progress!W50 -> ELDREES | C13: =Progress!Y50 -> 353857.85 | D13: =C13/$C$33 -> 0.0011066881 | E13: =Progress!Y13 -> 0 | F13: =Progress!Z13 -> 0 | G13: =Progress!AD50 -> 353857.85 | H13: =G13 -> 353857.85 | I13: =Progress!Z50 -> 353857.85 | K13: =Progress!AB50 -> 125 | L13: =K13/$K$33 -> 0.0026017275 | M13: =Progress!T13 -> 0 | N13: =Progress!V13 -> 0 | O13: =Progress!AC50 -> 125 | P13: =Progress!AA50 -> 125 | R13: ELDREES | T13: =+O13-U13 -> 0 | U13: =AG13 -> 125 | V13: =+AA50-W13 -> 0 | W13: =AE13 -> 125 | X13: ELDREES | Y13: =+AD50-AH13 -> 0 | Z13: =Z50-AD13 -> 0 | AA13: ELDREES | AC13: 353857.85 | AD13: 353857.85 | AE13: 125 | AF13: 125 | AG13: 125 | AH13: 353857.85 | AI13: 1 | AJ13: 1 | AL13: 10-Jan-26 A | AM13: 09-Sep-26 A | AN13: 46032 | AO13: 46215
A14: =Progress!W51 -> MR | C14: =Progress!Y51 -> 73833427 | D14: =C14/$C$33 -> 0.23091356 | E14: =Progress!Y14 -> 0 | F14: =Progress!Z14 -> 0 | G14: =Progress!AD51 -> 73833427 | H14: =G14 -> 73833427 | I14: =Progress!Z51 -> 73419907 | K14: =Progress!AB51 -> 17520 | L14: =K14/$K$33 -> 0.36465813 | M14: =Progress!T14 -> 0 | N14: =Progress!V14 -> 0 | O14: =Progress!AC51 -> 17507 | P14: =Progress!AA51 -> 17409 | R14: MR | T14: =+O14-U14 -> 0 | U14: =AG14 -> 17507 | V14: =+AA51-W14 -> 0 | W14: =AE14 -> 17409 | X14: MR | Y14: =+AD51-AH14 -> 0 | Z14: =Z51-AD14 -> 0 | AA14: MR | AC14: 73833427 | AD14: 73419907 | AE14: 17409 | AF14: 17520 | AG14: 17507 | AH14: 73833427 | AI14: 0.9944 | AJ14: 1 | AK14: -14 | AL14: 12-Oct-24 A | AM14: 46305 | AN14: 45577 | AO14: 46291
A15: =Progress!W52 -> Z01 | C15: =Progress!Y52 -> 12724319 | D15: =C15/$C$33 -> 0.039795223 | E15: =Progress!Y15 -> 0 | F15: =Progress!Z15 -> 0 | G15: =Progress!AD52 -> 12724319 | H15: =G15 -> 12724319 | I15: =Progress!Z52 -> 12724319 | K15: =Progress!AB52 -> 2771 | L15: =K15/$K$33 -> 0.057675096 | M15: =Progress!T15 -> 0 | N15: =Progress!V15 -> 0 | O15: =Progress!AC52 -> 2770 | P15: =Progress!AA52 -> 2771 | R15: Z01 | T15: =+O15-U15 -> 0 | U15: =AG15 -> 2770 | V15: =+AA52-W15 -> 0 | W15: =AE15 -> 2771 | X15: Z01 | Y15: =+AD52-AH15 -> 0 | Z15: =Z52-AD15 -> 0 | AA15: Z01 | AC15: 12724319 | AD15: 12724319 | AE15: 2771 | AF15: 2771 | AG15: 2770 | AH15: 12724319 | AI15: 1 | AJ15: 1 | AK15: -8 | AL15: 14-Sep-24 A | AM15: 46299 | AN15: 45549 | AO15: 46290
A16: =Progress!W53 -> Z02 | C16: =Progress!Y53 -> 1453405.8 | D16: =C16/$C$33 -> 0.0045455172 | E16: =Progress!Y16 -> 0 | F16: =Progress!Z16 -> 74152.78 | G16: =Progress!AD53 -> 1453405.8 | H16: =G16 -> 1453405.8 | I16: =Progress!Z53 -> 1268023.9 | K16: =Progress!AB53 -> 484 | L16: =K16/$K$33 -> 0.010073889 | M16: =Progress!T16 -> 0 | N16: =Progress!V16 -> 11 | O16: =Progress!AC53 -> 484 | P16: =Progress!AA53 -> 457 | R16: Z02 | T16: =+O16-U16 -> 0 | U16: =AG16 -> 484 | V16: =+AA53-W16 -> 11 | W16: =AE16 -> 446 | X16: Z02 | Y16: =+AD53-AH16 -> 0 | Z16: =Z53-AD16 -> 74152.78 | AA16: Z02 | AC16: 1453405.8 | AD16: 1193871.1 | AE16: 446 | AF16: 484 | AG16: 484 | AH16: 1453405.8 | AI16: 0.8214 | AJ16: 1 | AK16: -14 | AL16: 16-Aug-25 A | AM16: 46305 | AN16: 45885 | AO16: 46260
A17: =Progress!W54 -> Z02-1 | C17: =Progress!Y54 -> 10584846 | D17: =C17/$C$33 -> 0.033104036 | E17: =Progress!Y17 -> 0 | F17: =Progress!Z17 -> 0 | G17: =Progress!AD54 -> 10584846 | H17: =G17 -> 10584846 | I17: =Progress!Z54 -> 10584846 | K17: =Progress!AB54 -> 2709 | L17: =K17/$K$33 -> 0.056384639 | M17: =Progress!T17 -> 0 | N17: =Progress!V17 -> 0 | O17: =Progress!AC54 -> 2693 | P17: =Progress!AA54 -> 2709 | R17: Z02-1 | T17: =+O17-U17 -> 0 | U17: =AG17 -> 2693 | V17: =+AA54-W17 -> 0 | W17: =AE17 -> 2709 | X17: Z02-1 | Y17: =+AD54-AH17 -> 0 | Z17: =Z54-AD17 -> 0 | AA17: Z02-1 | AC17: 10584846 | AD17: 10584846 | AE17: 2709 | AF17: 2709 | AG17: 2693 | AH17: 10584846 | AI17: 1 | AJ17: 1 | AK17: -16 | AL17: 02-Sep-24 A | AM17: 46307 | AN17: 45537 | AO17: 46268
A18: =Progress!W55 -> Z02-2 | C18: =Progress!Y55 -> 11951477 | D18: =C18/$C$33 -> 0.037378164 | E18: =Progress!Y18 -> 0 | F18: =Progress!Z18 -> 0 | G18: =Progress!AD55 -> 11951477 | H18: =G18 -> 11951477 | I18: =Progress!Z55 -> 11951477 | K18: =Progress!AB55 -> 3089 | L18: =K18/$K$33 -> 0.064293891 | M18: =Progress!T18 -> 0 | N18: =Progress!V18 -> 0 | O18: =Progress!AC55 -> 3089 | P18: =Progress!AA55 -> 3089 | R18: Z02-2 | T18: =+O18-U18 -> 0 | U18: =AG18 -> 3089 | V18: =+AA55-W18 -> 0 | W18: =AE18 -> 3089 | X18: Z02-2 | Y18: =+AD55-AH18 -> 0 | Z18: =Z55-AD18 -> 0 | AA18: Z02-2 | AC18: 11951477 | AD18: 11951477 | AE18: 3089 | AF18: 3089 | AG18: 3089 | AH18: 11951477 | AI18: 1 | AJ18: 1 | AK18: -8 | AL18: 11-Sep-24 A | AM18: 46299 | AN18: 45546 | AO18: 46277
A19: =Progress!W56 -> Z03 | C19: =Progress!Y56 -> 709820.88 | D19: =C19/$C$33 -> 0.0022199601 | E19: =Progress!Y19 -> 0 | F19: =Progress!Z19 -> 0 | G19: =Progress!AD56 -> 709820.88 | H19: =G19 -> 709820.88 | I19: =Progress!Z56 -> 709820.88 | K19: =Progress!AB56 -> 378 | L19: =K19/$K$33 -> 0.0078676241 | M19: =Progress!T19 -> 0 | N19: =Progress!V19 -> 0 | O19: =Progress!AC56 -> 378 | P19: =Progress!AA56 -> 378 | R19: Z03 | T19: =+O19-U19 -> 0 | U19: =AG19 -> 378 | V19: =+AA56-W19 -> 0 | W19: =AE19 -> 378 | X19: Z03 | Y19: =+AD56-AH19 -> 0 | Z19: =Z56-AD19 -> 0 | AA19: Z03 | AC19: 709820.88 | AD19: 709820.88 | AE19: 378 | AF19: 378 | AG19: 378 | AH19: 709820.88 | AI19: 1 | AJ19: 1 | AK19: -8 | AL19: 03-Nov-24 A | AM19: 46299 | AN19: 45599 | AO19: 46257
A20: =Progress!W57 -> Z04 | C20: =Progress!Y57 -> 791520.69 | D20: =C20/$C$33 -> 0.0024754758 | E20: =Progress!Y20 -> 0 | F20: =Progress!Z20 -> 0 | G20: =Progress!AD57 -> 791520.69 | H20: =G20 -> 791520.69 | I20: =Progress!Z57 -> 582653.1 | K20: =Progress!AB57 -> 337 | L20: =K20/$K$33 -> 0.0070142575 | M20: =Progress!T20 -> 0 | N20: =Progress!V20 -> 0 | O20: =Progress!AC57 -> 337 | P20: =Progress!AA57 -> 310 | R20: Z04 | T20: =+O20-U20 -> 0 | U20: =AG20 -> 337 | V20: =+AA57-W20 -> 0 | W20: =AE20 -> 310 | X20: Z04 | Y20: =+AD57-AH20 -> 0 | Z20: =Z57-AD20 -> 0 | AA20: Z04 | AC20: 791520.69 | AD20: 582653.1 | AE20: 310 | AF20: 337 | AG20: 337 | AH20: 791520.69 | AI20: 0.7361 | AJ20: 1 | AK20: -24 | AL20: 19-Oct-24 A | AM20: 46315 | AN20: 45584 | AO20: 46257
A21: =Progress!W58 -> Z05 | C21: =Progress!Y58 -> 6381167 | D21: =C21/$C$33 -> 0.019957058 | E21: =Progress!Y21 -> 0 | F21: =Progress!Z21 -> 102028.39 | G21: =Progress!AD58 -> 6381167 | H21: =G21 -> 6381167 | I21: =Progress!Z58 -> 5519896.3 | K21: =Progress!AB58 -> 3703 | L21: =K21/$K$33 -> 0.077073577 | M21: =Progress!T21 -> 0 | N21: =Progress!V21 -> 13 | O21: =Progress!AC58 -> 3703 | P21: =Progress!AA58 -> 3458 | R21: Z05 | T21: =+O21-U21 -> 0 | U21: =AG21 -> 3703 | V21: =+AA58-W21 -> 13 | W21: =AE21 -> 3445 | X21: Z05 | Y21: =+AD58-AH21 -> 0 | Z21: =Z58-AD21 -> 102028.39 | AA21: Z05 | AC21: 6381167 | AD21: 5417867.9 | AE21: 3445 | AF21: 3703 | AG21: 3703 | AH21: 6381167 | AI21: 0.849 | AJ21: 1 | AK21: -25 | AL21: 25-Jun-25 A | AM21: 46316 | AN21: 45833 | AO21: 46272
A22: =Progress!W59 -> Z06 | C22: =Progress!Y59 -> 15215702 | D22: =C22/$C$33 -> 0.047587008 | E22: =Progress!Y22 -> 0 | F22: =Progress!Z22 -> 43378.29 | G22: =Progress!AD59 -> 15215702 | H22: =G22 -> 15215702 | I22: =Progress!Z59 -> 15151456 | K22: =Progress!AB59 -> 3016 | L22: =K22/$K$33 -> 0.062774482 | M22: =Progress!T22 -> 0 | N22: =Progress!V22 -> 8 | O22: =Progress!AC59 -> 3016 | P22: =Progress!AA59 -> 3004 | R22: Z06 | T22: =+O22-U22 -> 0 | U22: =AG22 -> 3016 | V22: =+AA59-W22 -> 8 | W22: =AE22 -> 2996 | X22: Z06 | Y22: =+AD59-AH22 -> 0 | Z22: =Z59-AD22 -> 43378.29 | AA22: Z06 | AC22: 15215702 | AD22: 15108078 | AE22: 2996 | AF22: 3016 | AG22: 3016 | AH22: 15215702 | AI22: 0.9929 | AJ22: 1 | AK22: -17 | AL22: 16-Aug-24 A | AM22: 46308 | AN22: 45521 | AO22: 46291
A23: =Progress!W60 -> Z07 | C23: =Progress!Y60 -> 14082635 | D23: =C23/$C$33 -> 0.044043347 | E23: =Progress!Y23 -> 0 | F23: =Progress!Z23 -> 0 | G23: =Progress!AD60 -> 14082635 | H23: =G23 -> 14082635 | I23: =Progress!Z60 -> 14082635 | K23: =Progress!AB60 -> 2682 | L23: =K23/$K$33 -> 0.055822666 | M23: =Progress!T23 -> 0 | N23: =Progress!V23 -> 0 | O23: =Progress!AC60 -> 2682 | P23: =Progress!AA60 -> 2682 | R23: Z07 | T23: =+O23-U23 -> 0 | U23: =AG23 -> 2682 | V23: =+AA60-W23 -> 0 | W23: =AE23 -> 2682 | X23: Z07 | Y23: =+AD60-AH23 -> 0 | Z23: =Z60-AD23 -> 0 | AA23: Z07 | AC23: 14082635 | AD23: 14082635 | AE23: 2682 | AF23: 2682 | AG23: 2682 | AH23: 14082635 | AI23: 1 | AJ23: 1 | AL23: 20-Aug-24 A | AM23: 27-Sep-26 A | AN23: 45524 | AO23: 46280
A24: =Progress!W61 -> Z07-1 | C24: =Progress!Y61 -> 9569376.8 | D24: =C24/$C$33 -> 0.029928163 | E24: =Progress!Y24 -> 0 | F24: =Progress!Z24 -> 0 | G24: =Progress!AD61 -> 9569376.8 | H24: =G24 -> 9569376.8 | I24: =Progress!Z61 -> 9569376.8 | K24: =Progress!AB61 -> 2065 | L24: =K24/$K$33 -> 0.042980539 | M24: =Progress!T24 -> 0 | N24: =Progress!V24 -> 0 | O24: =Progress!AC61 -> 2065 | P24: =Progress!AA61 -> 2065 | R24: Z07-1 | T24: =+O24-U24 -> 0 | U24: =AG24 -> 2065 | V24: =+AA61-W24 -> 0 | W24: =AE24 -> 2065 | X24: Z07-1 | Y24: =+AD61-AH24 -> 0 | Z24: =Z61-AD24 -> 0 | AA24: Z07-1 | AC24: 9569376.8 | AD24: 9569376.8 | AE24: 2065 | AF24: 2065 | AG24: 2065 | AH24: 9569376.8 | AI24: 1 | AJ24: 1 | AK24: -8 | AL24: 04-Sep-24 A | AM24: 46299 | AN24: 45539 | AO24: 46263
A25: =Progress!W62 -> Z08 | C25: =Progress!Y62 -> 1069834.5 | D25: =C25/$C$33 -> 0.0033459005 | E25: =Progress!Y25 -> 0 | F25: =Progress!Z25 -> 0 | G25: =Progress!AD62 -> 1069834.5 | H25: =G25 -> 1069834.5 | I25: =Progress!Z62 -> 744135.82 | K25: =Progress!AB62 -> 339 | L25: =K25/$K$33 -> 0.0070558851 | M25: =Progress!T25 -> 0 | N25: =Progress!V25 -> 0 | O25: =Progress!AC62 -> 339 | P25: =Progress!AA62 -> 296 | R25: Z08 | T25: =+O25-U25 -> 0 | U25: =AG25 -> 339 | V25: =+AA62-W25 -> 0 | W25: =AE25 -> 296 | X25: Z08 | Y25: =+AD62-AH25 -> 0 | Z25: =Z62-AD25 -> 0 | AA25: Z08 | AC25: 1069834.5 | AD25: 744135.82 | AE25: 296 | AF25: 339 | AG25: 339 | AH25: 1069834.5 | AI25: 0.6956 | AJ25: 1 | AK25: -31 | AL25: 05-Oct-24 A | AM25: 46322 | AN25: 45570 | AO25: 46286
A26: =Progress!W63 -> Z09 | C26: =Progress!Y63 -> 5049850.4 | D26: =C26/$C$33 -> 0.015793374 | E26: =Progress!Y26 -> 0 | F26: =Progress!Z26 -> 16732.15 | G26: =Progress!AD63 -> 5049850.4 | H26: =G26 -> 5049850.4 | I26: =Progress!Z63 -> 4963978.2 | K26: =Progress!AB63 -> 886 | L26: =K26/$K$33 -> 0.018441045 | M26: =Progress!T26 -> 0 | N26: =Progress!V26 -> 3 | O26: =Progress!AC63 -> 884 | P26: =Progress!AA63 -> 872 | R26: Z09 | T26: =+O26-U26 -> 0 | U26: =AG26 -> 884 | V26: =+AA63-W26 -> 3 | W26: =AE26 -> 869 | X26: Z09 | Y26: =+AD63-AH26 -> 0 | Z26: =Z63-AD26 -> 16732.15 | AA26: Z09 | AC26: 5049850.4 | AD26: 4947246 | AE26: 869 | AF26: 886 | AG26: 884 | AH26: 5049850.4 | AI26: 0.9797 | AJ26: 1 | AK26: -24 | AL26: 15-Nov-25 A | AM26: 46315 | AN26: 45976 | AO26: 46272
A27: =Progress!W64 -> Z10 | C27: =Progress!Y64 -> 8833596.8 | D27: =C27/$C$33 -> 0.027627016 | E27: =Progress!Y27 -> 0 | F27: =Progress!Z27 -> 0 | G27: =Progress!AD64 -> 8833596.8 | H27: =G27 -> 8833596.8 | I27: =Progress!Z64 -> 8666952.3 | K27: =Progress!AB64 -> 1532 | L27: =K27/$K$33 -> 0.031886773 | M27: =Progress!T27 -> 0 | N27: =Progress!V27 -> 0 | O27: =Progress!AC64 -> 1532 | P27: =Progress!AA64 -> 1511 | R27: Z10 | T27: =+O27-U27 -> 0 | U27: =AG27 -> 1532 | V27: =+AA64-W27 -> 0 | W27: =AE27 -> 1511 | X27: Z10 | Y27: =+AD64-AH27 -> 0 | Z27: =Z64-AD27 -> 0 | AA27: Z10 | AC27: 8833596.8 | AD27: 8666952.3 | AE27: 1511 | AF27: 1532 | AG27: 1532 | AH27: 8833596.8 | AI27: 0.9811 | AJ27: 1 | AK27: -11 | AL27: 28-Jun-25 A | AM27: 46302 | AN27: 45836 | AO27: 46286
A28: =Progress!W65 -> Z11 | C28: =Progress!Y65 -> 201779.17 | D28: =C28/$C$33 -> 0.00063106303 | E28: =Progress!Y28 -> 0 | F28: =Progress!Z28 -> 0 | G28: =Progress!AD65 -> 201779.17 | H28: =G28 -> 201779.17 | I28: =Progress!Z65 -> 192096.05 | K28: =Progress!AB65 -> 314 | L28: =K28/$K$33 -> 0.0065355396 | M28: =Progress!T28 -> 0 | N28: =Progress!V28 -> 0 | O28: =Progress!AC65 -> 314 | P28: =Progress!AA65 -> 313 | R28: Z11 | T28: =+O28-U28 -> 0 | U28: =AG28 -> 314 | V28: =+AA65-W28 -> 0 | W28: =AE28 -> 313 | X28: Z11 | Y28: =+AD65-AH28 -> 0 | Z28: =Z65-AD28 -> 0 | AA28: Z11 | AC28: 201779.17 | AD28: 192096.05 | AE28: 313 | AF28: 314 | AG28: 314 | AH28: 201779.17 | AI28: 0.952 | AJ28: 1 | AK28: -28 | AL28: 02-Nov-24 A | AM28: 46314 | AN28: 45598 | AO28: 46286
A29: =Progress!W66 -> Z13 | C29: =Progress!Y66 -> 5395935.5 | D29: =C29/$C$33 -> 0.016875753 | E29: =Progress!Y29 -> 0 | F29: =Progress!Z29 -> 0 | G29: =Progress!AD66 -> 5395935.5 | H29: =G29 -> 5395935.5 | I29: =Progress!Z66 -> 5395935.5 | K29: =Progress!AB66 -> 526 | L29: =K29/$K$33 -> 0.01094807 | M29: =Progress!T29 -> 0 | N29: =Progress!V29 -> 0 | O29: =Progress!AC66 -> 526 | P29: =Progress!AA66 -> 526 | R29: Z13 | T29: =+O29-U29 -> 0 | U29: =AG29 -> 526 | V29: =+AA66-W29 -> 0 | W29: =AE29 -> 526 | X29: Z13 | Y29: =+AD66-AH29 -> 0 | Z29: =Z66-AD29 -> 0 | AA29: Z13 | AC29: 5395935.5 | AD29: 5395935.5 | AE29: 526 | AF29: 526 | AG29: 526 | AH29: 5395935.5 | AI29: 1 | AJ29: 1 | AK29: -8 | AL29: 28-Apr-25 A | AM29: 46299 | AN29: 45775 | AO29: 46270
A30: CCTV | C30: =Progress!Y67 -> 5075749.7 | D30: =C30/$C$33 -> 0.015874374 | E30: =Progress!Y30 -> 0 | F30: =Progress!Z30 -> 0 | G30: =Progress!AD67 -> 5075749.7 | H30: =G30 -> 5075749.7 | I30: =Progress!Z67 -> 5075749.7 | K30: =Progress!AB67 -> 9 | L30: =K30/$K$33 -> 0.00018732438 | M30: =Progress!T30 -> 0 | N30: =Progress!V30 -> 0 | O30: =Progress!AC67 -> 9 | P30: =Progress!AA67 -> 9 | R30: CCTV | T30: =+O30-U30 -> 0 | U30: =AG30 -> 9 | V30: =+AA67-W30 -> 0 | W30: =AE30 -> 9 | X30: CCTV | Y30: =+AD67-AH30 -> 0 | Z30: =Z67-AD30 -> 0 | AA30: CCTV | AC30: 5075749.7 | AD30: 5075749.7 | AE30: 9 | AF30: 9 | AG30: 9 | AH30: 5075749.7 | AI30: 1 | AJ30: 1 | AL30: 08-Oct-25 A | AM30: 22-Jan-26 A | AN30: 45938 | AO30: 46044
A31: New Scope | C31: =Progress!Y68 -> 1920841.2 | D31: =C31/$C$33 -> 0.0060074181 | E31: =Progress!Y31 -> 0 | F31: =Progress!Z31 -> 9073.11 | G31: =Progress!AD68 -> 1920841.2 | H31: =G31 -> 1920841.2 | I31: =Progress!Z68 -> 1881472.1 | K31: =Progress!AB68 -> 617 | L31: =K31/$K$33 -> 0.012842127 | M31: =Progress!T31 -> 0 | N31: =Progress!V31 -> 3 | O31: =Progress!AC68 -> 617 | P31: =Progress!AA68 -> 595 | R31: New Scope | T31: =+O31-U31 -> 0 | U31: =AG31 -> 617 | V31: =+AA68-W31 -> 3 | W31: =AE31 -> 592 | X31: New Scope | Y31: =+AD68-AH31 -> 0 | Z31: =Z68-AD31 -> 9073.11 | AA31: New Scope | AC31: 1920841.2 | AD31: 1872398.9 | AE31: 592 | AF31: 617 | AG31: 617 | AH31: 1920841.2 | AI31: 0.9748 | AJ31: 1 | AK31: -13 | AL31: 12-Jul-26 A | AM31: 46304 | AN31: 46205 | AO31: 46289
A32: JDH3-02-008-Close Out | C32: =Progress!Y69 -> 31974488 | D32: =C32/$C$33 -> 0.1 | E32: =Progress!Y32 -> 0 | F32: =Progress!Z32 -> 221749.97 | G32: =Progress!AD69 -> 31974488 | H32: =G32 -> 31974488 | I32: =Progress!Z69 -> 30357173 | K32: =Progress!AB69 -> 0 | L32: =K32/$K$33 -> 0 | M32: =Progress!T32 -> 0 | N32: =Progress!V32 -> 0 | O32: =Progress!AC69 -> 0 | P32: =Progress!AA69 -> 0 | R32: JDH3-02-008-Close Out | T32: =+O32-U32 -> 0 | U32: =AG32 -> 0 | V32: =+AA69-W32 -> 0 | W32: =AE32 -> 0 | X32: JDH3-02-008-Close Out | Y32: =+AD69-AH32 -> 0 | Z32: =Z69-AD32 -> 221749.97 | AA32: JDH3-02-008-Close Out | AC32: 31974488 | AD32: 30135423 | AE32: 0 | AF32: 0 | AG32: 0 | AH32: 31974488 | AI32: 0.9425 | AJ32: 1 | AK32: -51 | AL32: 15-Oct-25 A | AM32: 46350 | AN32: 45945 | AO32: 46291
A33: Total | B33: Total | C33: =C7+C8+C9+C10+C32 -> 3.1974488e+08 | D33: =D7+D8+D9+D10+D32 -> 1 | E33: =E7+E8+E9+E10+E32 -> 0 | F33: =F7+F8+F9+F10+F32 -> 467114.68 | G33: =G7+G8+G9+G10+G32 -> 3.1974488e+08 | H33: =H7+H8+H9+H10+H32 -> 3.1974488e+08 | I33: =I7+I8+I9+I10+I32 -> 3.1576701e+08 | J33: =J7+J8+J9+J10+J32 -> 0 | ... P33: =P7+P8+P9+P10+P32 -> 47522
H34: =H33/C33 -> 1 | I34: =I33/C33 -> 0.98755924 | O34: =O33/K33 -> 0.99931314 | P34: =P33/K33 -> 0.98911437
W40: Activity ID | X40: Activity Name | Y40: Budgeted Total Cost | Z40: Earned Value Cost | AA40: Actual Labor Units | AB40: Budgeted Labor Units | AC40: Planned Value Labor Units | AD40: Planned Value Cost | AE40: Performance % Complete | AF40: Schedule % Complete | AG40: Total Float | AH40: Start | AI40: Finish | AJ40: BL Project Start | AK40: BL Project Finish
W41: Completion of the Infrastructure development of the 1st phase in the 3rd industrial city in Jeddah | Y41: 3.1974488e+08 | Z41: 3.1576701e+08 | AA41: 47522 | AB41: 48045 | AC41: 48012 | AD41: 3.1974488e+08 | AE41: 0.9876 | AF41: 1 | AG41: -66 | AH41: 29-Jul-24 A | AI41: 46357 | AJ41: 45502 | AK41: 46291
W42: JDH3-02-008-Milestones - MI | Y42: 0 | Z42: 0 | AA42: 0 | AB42: 0 | AC42: 0 | AD42: 0 | AE42: 0 | AF42: 0 | AG42: -66 | AH42: 29-Jul-24 A | AI42: 46357 | AJ42: 45502 | AK42: 46291
W43: JDH3-02-008-Mobilization - Mob | Y43: 0 | Z43: 0 | AA43: 0 | AB43: 0 | AC43: 0 | AD43: 0 | AE43: 0 | AF43: 0 | AH43: 29-Jul-24 A | AI43: 01-Feb-25 A | AJ43: 45502 | AK43: 45689
W44: JDH3-02-008-Authorities Permits & Approval - AT | Y44: 0 | Z44: 0 | AA44: 0 | AB44: 0 | AC44: 0 | AD44: 0 | AE44: 0 | AF44: 0 | AH44: 21-Oct-24 A | AI44: 19-Sep-26 A | AJ44: 45586 | AK44: 46279
W45: JDH3-02-008-Engineering | Y45: 9592346.3 | Z45: 9592346.3 | AA45: 0 | AB45: 0 | AC45: 0 | AD45: 9592346.3 | AE45: 1 | AF45: 1 | AG45: -19 | AH45: 05-Aug-24 A | AI45: 46313 | AJ45: 45509 | AK45: 46207
W46: JDH3-02-008-Procurement | Y46: 63948975 | Z46: 63948975 | AA46: 0 | AB46: 0 | AC46: 0 | AD46: 63948975 | AE46: 1 | AF46: 1 | AH46: 10-Oct-24 A | AI46: 26-Sep-26 A | AJ46: 45575 | AK46: 46230
W47: JDH3-02-008-Construction | Y47: 2.1422907e+08 | Z47: 2.1186851e+08 | AA47: 47522 | AB47: 48045 | AC47: 48012 | AD47: 2.1422907e+08 | AE47: 0.989 | AF47: 1 | AG47: -38 | AH47: 16-Aug-24 A | AI47: 46329 | AJ47: 45521 | AK47: 46291
W48: Pond and Swales - PS | Y48: 27026698 | Z48: 27026698 | AA48: 3720 | AB48: 3720 | AC48: 3720 | AD48: 27026698 | AE48: 1 | AF48: 1 | AH48: 28-Sep-24 A | AI48: 25-Dec-25 A | AJ48: 45563 | AK48: 46016
W49: High Mast | Y49: 2003227.7 | Z49: 2003227.7 | AA49: 1222 | AB49: 1222 | AC49: 1222 | AD49: 2003227.7 | AE49: 1 | AF49: 1 | AG49: -15 | AH49: 20-Aug-25 A | AI49: 46306 | AJ49: 45889 | AK49: 46232
W50: ELDREES | Y50: 353857.85 | Z50: 353857.85 | AA50: 125 | AB50: 125 | AC50: 125 | AD50: 353857.85 | AE50: 1 | AF50: 1 | AH50: 10-Jan-26 A | AI50: 09-Sep-26 A | AJ50: 46032 | AK50: 46215
W51: MR | Y51: 73833427 | Z51: 73419907 | AA51: 17409 | AB51: 17520 | AC51: 17507 | AD51: 73833427 | AE51: 0.9944 | AF51: 1 | AG51: -21 | AH51: 12-Oct-24 A | AI51: 46312 | AJ51: 45577 | AK51: 46291
W52: Z01 | Y52: 12724319 | Z52: 12724319 | AA52: 2771 | AB52: 2771 | AC52: 2770 | AD52: 12724319 | AE52: 1 | AF52: 1 | AG52: -15 | AH52: 14-Sep-24 A | AI52: 46306 | AJ52: 45549 | AK52: 46290
W53: Z02 | Y53: 1453405.8 | Z53: 1268023.9 | AA53: 457 | AB53: 484 | AC53: 484 | AD53: 1453405.8 | AE53: 0.8724 | AF53: 1 | AG53: -21 | AH53: 16-Aug-25 A | AI53: 46312 | AJ53: 45885 | AK53: 46260
W54: Z02-1 | Y54: 10584846 | Z54: 10584846 | AA54: 2709 | AB54: 2709 | AC54: 2693 | AD54: 10584846 | AE54: 1 | AF54: 1 | AG54: -23 | AH54: 02-Sep-24 A | AI54: 46314 | AJ54: 45537 | AK54: 46268
W55: Z02-2 | Y55: 11951477 | Z55: 11951477 | AA55: 3089 | AB55: 3089 | AC55: 3089 | AD55: 11951477 | AE55: 1 | AF55: 1 | AG55: -15 | AH55: 11-Sep-24 A | AI55: 46306 | AJ55: 45546 | AK55: 46277
W56: Z03 | Y56: 709820.88 | Z56: 709820.88 | AA56: 378 | AB56: 378 | AC56: 378 | AD56: 709820.88 | AE56: 1 | AF56: 1 | AG56: -15 | AH56: 03-Nov-24 A | AI56: 46306 | AJ56: 45599 | AK56: 46257
W57: Z04 | Y57: 791520.69 | Z57: 582653.1 | AA57: 310 | AB57: 337 | AC57: 337 | AD57: 791520.69 | AE57: 0.7361 | AF57: 1 | AG57: -31 | AH57: 19-Oct-24 A | AI57: 46322 | AJ57: 45584 | AK57: 46257
W58: Z05 | Y58: 6381167 | Z58: 5519896.3 | AA58: 3458 | AB58: 3703 | AC58: 3703 | AD58: 6381167 | AE58: 0.865 | AF58: 1 | AG58: -32 | AH58: 25-Jun-25 A | AI58: 46323 | AJ58: 45833 | AK58: 46272
W59: Z06 | Y59: 15215702 | Z59: 15151456 | AA59: 3004 | AB59: 3016 | AC59: 3016 | AD59: 15215702 | AE59: 0.9958 | AF59: 1 | AG59: -19 | AH59: 16-Aug-24 A | AI59: 46310 | AJ59: 45521 | AK59: 46291
W60: Z07 | Y60: 14082635 | Z60: 14082635 | AA60: 2682 | AB60: 2682 | AC60: 2682 | AD60: 14082635 | AE60: 1 | AF60: 1 | AH60: 20-Aug-24 A | AI60: 27-Sep-26 A | AJ60: 45524 | AK60: 46280
W61: Z07-1 | Y61: 9569376.8 | Z61: 9569376.8 | AA61: 2065 | AB61: 2065 | AC61: 2065 | AD61: 9569376.8 | AE61: 1 | AF61: 1 | AG61: -15 | AH61: 04-Sep-24 A | AI61: 46306 | AJ61: 45539 | AK61: 46263
W62: Z08 | Y62: 1069834.5 | Z62: 744135.82 | AA62: 296 | AB62: 339 | AC62: 339 | AD62: 1069834.5 | AE62: 0.6956 | AF62: 1 | AG62: -38 | AH62: 05-Oct-24 A | AI62: 46329 | AJ62: 45570 | AK62: 46286
W63: Z09 | Y63: 5049850.4 | Z63: 4963978.2 | AA63: 872 | AB63: 886 | AC63: 884 | AD63: 5049850.4 | AE63: 0.983 | AF63: 1 | AG63: -31 | AH63: 15-Nov-25 A | AI63: 46322 | AJ63: 45976 | AK63: 46272
W64: Z10 | Y64: 8833596.8 | Z64: 8666952.3 | AA64: 1511 | AB64: 1532 | AC64: 1532 | AD64: 8833596.8 | AE64: 0.9811 | AF64: 1 | AG64: -18 | AH64: 28-Jun-25 A | AI64: 46309 | AJ64: 45836 | AK64: 46286
W65: Z11 | Y65: 201779.17 | Z65: 192096.05 | AA65: 313 | AB65: 314 | AC65: 314 | AD65: 201779.17 | AE65: 0.952 | AF65: 1 | AG65: -35 | AH65: 02-Nov-24 A | AI65: 46321 | AJ65: 45598 | AK65: 46286
W66: Z13 | Y66: 5395935.5 | Z66: 5395935.5 | AA66: 526 | AB66: 526 | AC66: 526 | AD66: 5395935.5 | AE66: 1 | AF66: 1 | AG66: -15 | AH66: 28-Apr-25 A | AI66: 46306 | AJ66: 45775 | AK66: 46270
W67: CCTV | Y67: 5075749.7 | Z67: 5075749.7 | AA67: 9 | AB67: 9 | AC67: 9 | AD67: 5075749.7 | AE67: 1 | AF67: 1 | AH67: 08-Oct-25 A | AI67: 22-Jan-26 A | AJ67: 45938 | AK67: 46044
W68: New Scope | Y68: 1920841.2 | Z68: 1881472.1 | AA68: 595 | AB68: 617 | AC68: 617 | AD68: 1920841.2 | AE68: 0.9795 | AF68: 1 | AG68: -20 | AH68: 12-Jul-26 A | AI68: 46311 | AJ68: 46205 | AK68: 46289
W69: JDH3-02-008-Close Out | Y69: 31974488 | Z69: 30357173 | AA69: 0 | AB69: 0 | AC69: 0 | AD69: 31974488 | AE69: 0.9494 | AF69: 1 | AG69: -57 | AH69: 15-Oct-25 A | AI69: 46357 | AJ69: 45945 | AK69: 46291
AA73: 1.01

Sheet Invoice progress 
A1: Type of work | B1: This week progress | H1: Total | I1: 7422216.3
A2: Storm | B2: =(I7+I8+I4)*F13 -> 498812.4 | H2: Sewage Network | I2: 0
A3: Box culvert | B3: =I5*0.9 -> 0 | F3: =+B2+Table1[[#This Row],[This week progress]]+B4 -> 498812.4 | H3: Storm Network | I3: 1000000
A4: Open channel | B4: =I6*F13 -> 0 | F4: =I3*0.9 -> 900000 | H4: Ponds | I4: 0
A5: Sewer | B5: =I2*F13 -> 0 | H5: Box Culvert | I5: 0
A6: Irrigation | B6: =I9*F13 -> 27733.5 | H6: Swales
A7: Potable Water | B7: =I10*F13 -> 0 | E7: 1288421 | H7: Network
A8: Electrical | B8: =F13*(I12+I11) -> 0 | H8: Catch Basin | I8: 554236
A9: Roads | B9: =I13*F13 -> 36473.4 | H9: TSE Network | I9: 30815
A10: CCTV Works | B10: =I14*F13 -> 0 | H10: Potable Water Network
A11: Total | B11: =SUBTOTAL(109,B2:B10) -> 563019.3 | H11: Street Lighting Network
H12: Telecommunications Network
F13: 0.9 | H13: Road Works | I13: 40526
H14: CCTV Works | I14: 0

Sheet Weekly Photos
V1: Data Date | W1: ='General Information'!L1 -> 11-10-2026
B2: Aggregate Base Coarse at Zone 2-2 | L2: Laying of Asphalt at Zone 2-2
B21: Storm pipe installation at Zone 13 | L21: Potable water pipe installation at Zone 13
B40: Pond excavation at Zone 6 | L40: Pond excavation at Zone 12
B59: Potable water pipe installation at Zone 2-2 | L59: Irrigation line 450mm backilling at Zone 2-2
B79: Open channel rip rap works at Zone 2-1 | L79: Open channel rip rap works at Zone 7
B99: Sewer network excavation at Zone 2-1 L72 | L99: Open channel rip rap works at Zone 01

Sheet Quality
B2: QC OBSERVATIONS CHECKLIST
B6: Project No. | E6: JDH3-02-008 | K6: OBS No. | U6: Inspection Day: | X6: ='General Information'!$L$1 -> 11-10-2026
B8: Project | E8: Completion of the Infrastructure Development of the 1st Phase in the 3rd Industrial City in Jeddah | O8: Contractor: Consultant: | U8: Al-Rawaf Contracting
B10: 4 | D10: Excellent | G10: Quality Management System is being practiced and applies to MODON System | Z10: 90 - 100 | AB10: QC Overall Score | AC10: =Q49 -> 0.90551724 | AN10: =SUM(Z10:Z13) -> 0 | AO10: 100 | AP10: 0.22883295
B11: 3 | D11: Good | G11: Evidence of compliance with plans and procedures. | Z11: 80 - 89 | AN11: =SUM(Y10:Y14) -> 0 | AO11: 89 | AP11: 0.20366133
B12: 2 | D12: Average | G12: Indication level of compliance with standards but there is room for improvement | Z12: 70 - 79 | AO12: 79 | AP12: 0.18077803
B13: 1 | D13: Improve | G13: Quality and Control is NOT being managed effectively. Needs Improvement | Z13: ≤ 69 | AO13: 69 | AP13: 0.15789474
B14: 0 | D14: N/A | G14: Item was not applicable or this item was not reviewed during the inspection. | Z14: Zero | AO14: 100 | AP14: 0.22883295
B16: No. | C16: Topic | K16: E (4) | L16: G (3) | M16: A (2) | N16: I (1) | O16: N/A (0) | Q16: No. | R16: Topic | Z16: E (4) | AA16: G (3) | AB16: A (2) | AC16: I (1) | AD16: N/A (0) | AO16: =SUM(AO10:AO15) -> 437
K17: 1 | L17: 0.89 | M17: 0.79 | N17: 0.69 | O17: 1 | Z17: 1 | AA17: 0.89 | AB17: 0.79 | AC17: 0.69 | AD17: 1 | AF17: =SUM(AF18:AG46)/COUNT(AF18:AG46) -> 0.90551724
B18: 1 | C18: Control of Access to Site/Office | L18: 1 | Q18: 30 | R18: QC of Excavation | AA18: 1 | AC18: 0 | AF18: =SUMPRODUCT($K$17:$O$17,K18:O18) -> 0.89 | AG18: =SUMPRODUCT($Z$17:$AD$17,Z18:AD18) -> 0.89 | AV18: Item Count | AW18: Score | AX18: Distributtion
B19: 2 | C19: Document Control Administration | K19: 1 | L19: 0 | Q19: 31 | R19: QC of Roads/Round about | AA19: 1 | AB19: 0 | AD19: 0 | AF19: =SUMPRODUCT($K$17:$O$17,K19:O19) -> 1 | AG19: =SUMPRODUCT($Z$17:$AD$17,Z19:AD19) -> 0.89 | AX19: Overall | AY19: Relevant
B20: 3 | C20: Project Documents and Progress | L20: 1 | Q20: 32 | R20: QC of Interlock & Curbstone | AB20: 1 | AC20: 0 | AD20: 0 | AF20: =SUMPRODUCT($K$17:$O$17,K20:O20) -> 0.89 | AG20: =SUMPRODUCT($Z$17:$AD$17,Z20:AD20) -> 0.79 | AM20: 4 | AN20: =58 -> 58 | AO20: counts | AQ20: 4 | AR20: Excellent | AV20: =SUM(Z18:Z46,K18:K46) -> 2 | AW20: =AQ20*AV20 -> 8 | AX20: =AV20/$AV$25 -> 0.034482759 | AY20: =AV20/SUM($AV$20:$AV$23) -> 0.05
B21: 4 | C21: Contractor's Quality Plan/CM (Updated and Reviewed) | L21: 1 | M21: 0 | Q21: 33 | R21: Layers/Backfilling Sampling | AA21: 1 | AB21: 0 | AF21: =SUMPRODUCT($K$17:$O$17,K21:O21) -> 0.89 | AG21: =SUMPRODUCT($Z$17:$AD$17,Z21:AD21) -> 0.89 | AM21: 3 | AN21: =58 -> 58 | AO21: counts | AQ21: 3 | AR21: Good | AV21: =SUM(L18:L46,AA18:AA46) -> 25 | AW21: =AQ21*AV21 -> 75 | AX21: =AV21/$AV$25 -> 0.43103448 | AY21: =AV21/SUM($AV$20:$AV$23) -> 0.625
B22: 5 | C22: MS Log and Paperwork | L22: 1 | Q22: 34 | R22: Pump Stations Units | AD22: 1 | AF22: =SUMPRODUCT($K$17:$O$17,K22:O22) -> 0.89 | AG22: =SUMPRODUCT($Z$17:$AD$17,Z22:AD22) -> 1 | AM22: 2 | AN22: =58 -> 58 | AO22: counts | AQ22: 2 | AR22: Average | AV22: =SUM(M18:M46,AB18:AB46) -> 13 | AW22: =AQ22*AV22 -> 26 | AX22: =AV22/$AV$25 -> 0.22413793 | AY22: =AV22/SUM($AV$20:$AV$23) -> 0.325
B23: 6 | C23: RFI, FIR, & MIR Procedure | L23: 1 | Q23: 35 | R23: Quality of Form Work | AA23: 1 | AB23: 0 | AD23: 0 | AF23: =SUMPRODUCT($K$17:$O$17,K23:O23) -> 0.89 | AG23: =SUMPRODUCT($Z$17:$AD$17,Z23:AD23) -> 0.89 | AM23: 1 | AN23: =58 -> 58 | AO23: counts | AQ23: 1 | AR23: Improve | AV23: =SUM(N18:N46,AC18:AC46) -> 0 | AW23: =AQ23*AV23 -> 0 | AX23: =AV23/$AV$25 -> 0 | AY23: =AV23/SUM($AV$20:$AV$23) -> 0
B24: 7 | C24: RFI, FIR, & MIR Inventory system | L24: 1 | Q24: 36 | R24: Design Change List | AB24: 1 | AD24: 0 | AF24: =SUMPRODUCT($K$17:$O$17,K24:O24) -> 0.89 | AG24: =SUMPRODUCT($Z$17:$AD$17,Z24:AD24) -> 0.79 | AM24: 0 | AN24: =58 -> 58 | AO24: counts | AQ24: 0 | AR24: N/A | AV24: =SUM(O18:O46,AD18:AD46) -> 18 | AW24: =AQ24*AV24 -> 0 | AX24: =AV24/$AV$25 -> 0.31034483 | AY24: -
B25: 8 | C25: NCRs Control & Procedure | L25: 1 | M25: 0 | Q25: 37 | R25: Quality of Concrete Placing | AB25: 1 | AD25: 0 | AF25: =SUMPRODUCT($K$17:$O$17,K25:O25) -> 0.89 | AG25: =SUMPRODUCT($Z$17:$AD$17,Z25:AD25) -> 0.79 | AR25: Total | AV25: =SUM(AV20:AV24) -> 58 | AW25: =SUM(AW20:AW24) -> 109 | AX25: =SUM(AX20:AX24) -> 1 | AY25: =SUM(AY20:AY24) -> 1
B26: 9 | C26: NCR Log | L26: 1 | Q26: 38 | R26: Concrete Surface Finishing | AB26: 1 | AD26: 0 | AF26: =SUMPRODUCT($K$17:$O$17,K26:O26) -> 0.89 | AG26: =SUMPRODUCT($Z$17:$AD$17,Z26:AD26) -> 0.79
B27: 10 | C27: MODON Standard* | L27: 1 | M27: 0 | Q27: 39 | R27: Pedestals/Columns/Beams Alignment | AD27: 1 | AF27: =SUMPRODUCT($K$17:$O$17,K27:O27) -> 0.89 | AG27: =SUMPRODUCT($Z$17:$AD$17,Z27:AD27) -> 1 | AV27: Maz Score Available: | AW27: =SUM(AV20:AV23)*AQ20 -> 160 | AX27: <- Excludes N/A items
B28: 11 | C28: Project Risk Plan/Management* | M28: 1 | Q28: 40 | R28: Siporex Lifting & Unloading | AD28: 1 | AF28: =SUMPRODUCT($K$17:$O$17,K28:O28) -> 0.79 | AG28: =SUMPRODUCT($Z$17:$AD$17,Z28:AD28) -> 1
B29: 12 | C29: Monthly Quality Reports* | L29: 1 | M29: 0 | Q29: 41 | R29: Siporex Quality Pre-installation | AD29: 1 | AF29: =SUMPRODUCT($K$17:$O$17,K29:O29) -> 0.89 | AG29: =SUMPRODUCT($Z$17:$AD$17,Z29:AD29) -> 1
B30: 13 | C30: ITP | L30: 1 | M30: 0 | Q30: 42 | R30: Siporex Finishing Quality | AD30: 1 | AF30: =SUMPRODUCT($K$17:$O$17,K30:O30) -> 0.89 | AG30: =SUMPRODUCT($Z$17:$AD$17,Z30:AD30) -> 1 | AR30: Total Score | AW30: Percentage (%)
B31: 14 | C31: MODON Weekly Report | L31: 1 | Q31: 43 | R31: Roads / Parking Markings | AA31: 1 | AD31: 0 | AF31: =SUMPRODUCT($K$17:$O$17,K31:O31) -> 0.89 | AG31: =SUMPRODUCT($Z$17:$AD$17,Z31:AD31) -> 0.89 | AN31: =MAX(AN20:AN24) -> 58 | AR31: =AW25 -> 109 | AW31: =SUM(100/AR33*AR31) -> 68.125 | AY31: %
B32: 15 | C32: Design Change Official Paperwork* | O32: 1 | Q32: 44 | R32: QC of Finishing Outdoors | AD32: 1 | AF32: =SUMPRODUCT($K$17:$O$17,K32:O32) -> 1 | AG32: =SUMPRODUCT($Z$17:$AD$17,Z32:AD32) -> 1 | AR32: Max Score Available
B33: 16 | C33: Design Change was Applied* | O33: 1 | Q33: 45 | R33: Quality of Finishing Indoors | AD33: 1 | AF33: =SUMPRODUCT($K$17:$O$17,K33:O33) -> 1 | AG33: =SUMPRODUCT($Z$17:$AD$17,Z33:AD33) -> 1 | AR33: =AW27 -> 160
B34: 17 | C34: Material List | K34: 0 | L34: 1 | M34: 0 | Q34: 46 | R34: Stairs Quality | AD34: 1 | AF34: =SUMPRODUCT($K$17:$O$17,K34:O34) -> 0.89 | AG34: =SUMPRODUCT($Z$17:$AD$17,Z34:AD34) -> 1
B35: 18 | C35: Pending Material Status | L35: 1 | M35: 0 | Q35: 47 | R35: Tanks Method Statement Work | AD35: 1 | AF35: =SUMPRODUCT($K$17:$O$17,K35:O35) -> 0.89 | AG35: =SUMPRODUCT($Z$17:$AD$17,Z35:AD35) -> 1
B36: 19 | C36: Lifting Plan* | M36: 1 | O36: 0 | Q36: 48 | R36: Electric Rooms | AD36: 1 | AF36: =SUMPRODUCT($K$17:$O$17,K36:O36) -> 0.79 | AG36: =SUMPRODUCT($Z$17:$AD$17,Z36:AD36) -> 1
B37: 20 | C37: DWG Log | L37: 1 | M37: 0 | Q37: 49 | R37: QC of MCC/ATS Plant Units | AB37: 1 | AF37: =SUMPRODUCT($K$17:$O$17,K37:O37) -> 0.89 | AG37: =SUMPRODUCT($Z$17:$AD$17,Z37:AD37) -> 0.79
B38: 21 | C38: Invoice Status | O38: 1 | Q38: 50 | R38: Qualified Subcontractor | AB38: 1 | AC38: 0 | AD38: 0 | AF38: =SUMPRODUCT($K$17:$O$17,K38:O38) -> 1 | AG38: =SUMPRODUCT($Z$17:$AD$17,Z38:AD38) -> 0.79
B39: 22 | C39: Site Handover Letter | O39: 1 | Q39: 51 | R39: Scaffold/Ladders/Slope/Bridge Compliance | AD39: 1 | AF39: =SUMPRODUCT($K$17:$O$17,K39:O39) -> 1 | AG39: =SUMPRODUCT($Z$17:$AD$17,Z39:AD39) -> 1
B40: 23 | C40: Material Testing Results & Certification | L40: 1 | M40: 0 | Q40: 52 | R40: Protection Applied to Completed Work | AD40: 1 | AF40: =SUMPRODUCT($K$17:$O$17,K40:O40) -> 0.89 | AG40: =SUMPRODUCT($Z$17:$AD$17,Z40:AD40) -> 1
B41: 24 | C41: As Build Drawings Status* | M41: 1 | O41: 0 | Q41: 53 | R41: Storage Management in/out Control | AA41: 1 | AF41: =SUMPRODUCT($K$17:$O$17,K41:O41) -> 0.79 | AG41: =SUMPRODUCT($Z$17:$AD$17,Z41:AD41) -> 0.89
B42: 25 | C42: Calibrated Lab Tools & Equipment | K42: 1 | L42: 0 | Q42: 54 | R42: Material Control | AA42: 1 | AB42: 0 | AF42: =SUMPRODUCT($K$17:$O$17,K42:O42) -> 1 | AG42: =SUMPRODUCT($Z$17:$AD$17,Z42:AD42) -> 0.89
B43: 26 | C43: Storage Inventory System | M43: 1 | O43: 0 | Q43: 55 | R43: Manholes Storing and Quality | AA43: 1 | AB43: 0 | AD43: 0 | AF43: =SUMPRODUCT($K$17:$O$17,K43:O43) -> 0.79 | AG43: =SUMPRODUCT($Z$17:$AD$17,Z43:AD43) -> 0.89
B44: 27 | C44: Logistics Plan | L44: 0 | O44: 1 | Q44: 56 | R44: Reinforced Steel Quality | AB44: 1 | AD44: 0 | AF44: =SUMPRODUCT($K$17:$O$17,K44:O44) -> 1 | AG44: =SUMPRODUCT($Z$17:$AD$17,Z44:AD44) -> 0.79
B45: 28 | C45: Project Progress Planview | M45: 1 | Q45: 57 | R45: Safety Overview | AB45: 1 | AF45: =SUMPRODUCT($K$17:$O$17,K45:O45) -> 0.79 | AG45: =SUMPRODUCT($Z$17:$AD$17,Z45:AD45) -> 0.79
B46: 29 | C46: Sufficient Number of QC Inspectors | L46: 1 | M46: 0 | N46: 0 | Q46: 58 | R46: Waste Management Control | AA46: 0 | AD46: 1 | AF46: =SUMPRODUCT($K$17:$O$17,K46:O46) -> 0.89 | AG46: =SUMPRODUCT($Z$17:$AD$17,Z46:AD46) -> 1
O47: 0
I48: Score
M49: *QC % | Q49: =AF17 -> 0.90551724
B51: Prepared by: | G51: Eng.Hassan El Shorbagy(Quality Representative) | Q51: Issued to PM: | V51: Eng. Mohammed AL-Naggar (PM)
B53: *QC Observations refer only to the practices and documentation observed at time of inspection. The responsibility of the CM and Contractor is to ensure that aspects of Quality are suitably managed. *Scores are a reflection of the general site conditions based upon the findings at the time of the walk through *If Applicable

Sheet Quality-Stat
A1: Quality Reports | P1: SUMMARY | X1: SUMMARY
A2: Item | C2: Issued | D2: Closed | E2: Pending | F2: Avg. Closing (Days) | G2: Pending | P2: PLANS | X2: RFI
G3: 0-10 Days | H3: 11-20 Days | I3: 21-30 Days | J3: 31-60 Days | K3: > 60 Days | P3: ITEM | Q3: ALL | R3: A | S3: B | T3: C | U3: D | V3: UR | X3: ITEM | Y3: ALL | Z3: Closed | AA3: Open
P4: PLANS | Q4: 32 | R4: 1 | S4: 27 | T4: 2 | U4: 1 | V4: 1 | X4: RFI CVL | Y4: 186 | Z4: 186 | AA4: 0
A5: Non Conforomance Report (NCR) | C5: =Y44 -> 102 | D5: =C5-E5 -> 99 | E5: =AD44+AE44 -> 3 | F5: 7 | G5: 1 | P5: TOTAL | Q5: 32 | R5: 1 | S5: 27 | T5: 2 | U5: 1 | V5: 1 | X5: RFI ELE | Y5: 24 | Z5: 24 | AA5: 0
A6: Site Instruction (SI) | C6: =Y35 -> 187 | D6: =C6-E6 -> 177 | E6: =AE35+AD35 -> 10 | F6: 5 | G6: 1 | X6: RFI MEC | Y6: 24 | Z6: 24 | AA6: 0
A7: Material Inspection Report (MIR) | C7: =Y27 -> 357 | D7: =C7-E7 -> 355 | E7: =AD27+AB27 -> 2 | P7: PQA SUBCONTRACTOR | X7: RFI GEN | Y7: 4 | Z7: 4 | AA7: 0
A8: Work Inspection Report (WIR) | C8: =Y19 -> 30963 | D8: =C8-E8 -> 30863 | E8: =AD19 -> 100 | P8: ITEM | Q8: ALL | R8: A | S8: B | T8: C | U8: D | V8: UR | X8: TOTAL | Y8: 238 | Z8: 238 | AA8: 0
Q9: 31 | R9: 0 | S9: 20 | T9: 9 | U9: 2 | V9: 0
A10: Shop Drawings | P10: TOTAL | Q10: 31 | R10: 0 | S10: 20 | T10: 9 | U10: 2 | V10: 0
A11: Item Per WBS | D11: Total | E11: Total Drawings Submitted | J11: Remaining Drawings | K11: Pending | L11: Total Submittals
E12: A | F12: B | G12: C | H12: D | I12: Processed | J12: with Designer | K12: Submittals With Consultant
A13: Road | D13: =Q31 -> 1940 | E13: =R31 -> 84 | F13: =S31 -> 1700 | G13: =T31 -> 4 | H13: =U31 -> 138 | I13: =V31 -> 14 | J13: 0 | K13: ='Quality-Stat'!I13 -> 14 | L13: =+K13+E13+F13+G13+H13 -> 1940 | M13: =+L13/D13 -> 1 | P13: PQA | X13: FIR
A14: infrastructure | C14: Structural | D14: =Q34 -> 437 | E14: =R34 -> 4 | F14: =S34 -> 423 | G14: =T34 -> 8 | H14: =U34 -> 2 | I14: =V34 -> 0 | J14: 0 | K14: ='Quality-Stat'!I14 -> 0 | L14: =+K14+E14+F14+G14+H14 -> 437 | M14: =+L14/D14 -> 1 | P14: ITEM | Q14: ALL | R14: A | S14: B | T14: C | U14: D | V14: UR | X14: ITEM | Y14: ALL | Z14: A | AA14: B | AB14: C | AC14: D | AD14: UR
A15: Electrical & Telecommunication | D15: =Q32 -> 158 | E15: =R32 -> 21 | F15: =S32 -> 111 | G15: =T32 -> 2 | H15: =U32 -> 0 | I15: =V32 -> 0 | J15: =+D15-E15-F15-G15-H15-K15 -> 24 | K15: ='Quality-Stat'!I15 -> 0 | L15: =+K15+E15+F15+G15+H15 -> 134 | M15: =+L15/D15 -> 0.84810127 | P15: CVL | Q15: 60 | R15: 12 | S15: 40 | T15: 5 | U15: 3 | V15: 0 | X15: CVL | Y15: 14998 | Z15: 4727 | AA15: 9693 | AB15: 182 | AC15: 19 | AD15: 78
A16: General | D16: =Q33 -> 3 | E16: =R33 -> 0 | F16: =S33 -> 3 | G16: =T33 -> 0 | H16: =U33 -> 0 | I16: =V33 -> 0 | K16: ='Quality-Stat'!I16 -> 0 | L16: =+K16+E16+F16+G16+H16 -> 3 | M16: =+L16/D16 -> 1 | P16: ELE | Q16: 21 | R16: 1 | S16: 15 | T16: 1 | U16: 4 | V16: 0 | X16: ELE | Y16: 349 | Z16: 125 | AA16: 208 | AB16: 8 | AC16: 7 | AD16: 0
A17: SVY | D17: =Q35 -> 1 | E17: =R35 -> 0 | F17: =S35 -> 1 | G17: =T35 -> 3 | H17: =U35 -> 0 | I17: =V35 -> 0 | K17: ='Quality-Stat'!I17 -> 0 | L17: =+K17+E17+F17+G17+H17 -> 4 | M17: =+L17/D17 -> 4 | P17: GEN | Q17: 0 | R17: 0 | S17: 0 | T17: 0 | U17: 0 | V17: 0 | X17: MEC | Y17: 2759 | Z17: 1079 | AA17: 1598 | AB17: 29 | AC17: 15 | AD17: 1
A18: TOTAL | D18: =SUBTOTAL(9,D13:D17) -> 2539 | E18: =SUBTOTAL(9,E13:E17) -> 109 | F18: =SUBTOTAL(9,F13:F17) -> 2238 | G18: =SUBTOTAL(9,G13:G17) -> 17 | H18: =SUBTOTAL(9,H13:H17) -> 140 | I18: =SUBTOTAL(9,I13:I17) -> 14 | J18: =SUBTOTAL(9,J13:J17) -> 24 | K18: =SUBTOTAL(9,K13:K17) -> 14 | L18: =SUM(L13:L17) -> 2518 | P18: MEC | Q18: 24 | R18: 16 | S18: 7 | T18: 1 | U18: 0 | V18: 0 | X18: SVY | Y18: 12857 | Z18: 42 | AA18: 11563 | AB18: 664 | AC18: 14 | AD18: 21
P19: TOTAL | Q19: 105 | R19: 29 | S19: 62 | T19: 7 | U19: 7 | V19: 0 | X19: TOTAL | Y19: 30963 | Z19: 5973 | AA19: 23062 | AB19: 883 | AC19: 55 | AD19: 100
A21: Material Approval | P21: MST | X21: MIR
A22: Item Per WBS | D22: Total | E22: Total Materials Submitted | J22: Remaining to approve | K22: Pending | L22: Total Submittals | P22: ITEM | Q22: ALL | R22: A | S22: B | T22: C | U22: D | V22: UR | X22: ITEM | Y22: ALL | Z22: A | AA22: B | AB22: C | AC22: D | AD22: UR
E23: A | F23: B | G23: C | H23: D | I23: Processed | J23: with Designer | K23: Submittals With Consultant | P23: CVL | Q23: 9 | R23: 0 | S23: 0 | T23: 0 | U23: 1 | V23: 8 | X23: CVL | Y23: 125 | Z23: 123 | AA23: 0 | AB23: 2 | AC23: 0 | AD23: 0
A24: Road | D24: =Q40 -> 35 | E24: =R40 -> 1 | F24: =S40 -> 6 | G24: =T40 -> 2 | H24: =U40 -> 0 | I24: =V40 -> 26 | J24: =+D24-E24-F24-G24-H24-K24 -> 0 | K24: ='Quality-Stat'!I24 -> 26 | L24: =+K24+E24+F24+G24+H24 -> 35 | M24: =+L24/D24 -> 1 | P24: ELE | Q24: 3 | R24: 0 | S24: 0 | T24: 0 | U24: 0 | V24: 3 | X24: ELE | Y24: 27 | Z24: 27 | AA24: 0 | AB24: 0 | AC24: 0 | AD24: 0
A25: infrastructure | C25: Structural | D25: =Q42 -> 23 | E25: =R42 -> 14 | F25: =S42 -> 7 | G25: =T42 -> 1 | H25: =U42 -> 0 | I25: =V42 -> 1 | J25: =+D25-E25-F25-G25-H25-K25 -> 0 | K25: ='Quality-Stat'!I25 -> 1 | L25: =+K25+E25+F25+G25+H25 -> 23 | M25: =+L25/D25 -> 1 | P25: MEC | Q25: 5 | R25: 0 | S25: 0 | T25: 0 | U25: 1 | V25: 4 | X25: MEC | Y25: 205 | Z25: 205 | AA25: 0 | AB25: 0 | AC25: 0 | AD25: 0
A26: Electrical | D26: =Q41 -> 20 | E26: =R41 -> 1 | F26: =S41 -> 9 | G26: =T41 -> 1 | H26: =U41 -> 0 | I26: =V41 -> 9 | J26: =+D26-E26-F26-G26-H26-K26 -> 0 | K26: ='Quality-Stat'!I26 -> 9 | L26: =+K26+E26+F26+G26+H26 -> 20 | M26: =+L26/D26 -> 1
K27: ='Quality-Stat'!I27 -> 0 | P27: TOTAL | Q27: 17 | R27: 0 | S27: 0 | T27: 0 | U27: 2 | V27: 15 | X27: TOTAL | Y27: 357 | Z27: 355 | AA27: 0 | AB27: 2 | AC27: 0 | AD27: 0
A29: TOTAL | D29: =SUBTOTAL(9,D24:D28) -> 78 | E29: =SUBTOTAL(9,E24:E28) -> 16 | F29: =SUBTOTAL(9,F24:F28) -> 22 | G29: =SUBTOTAL(9,G24:G28) -> 4 | H29: =SUBTOTAL(9,H24:H28) -> 0 | I29: =SUBTOTAL(9,I24:I28) -> 36 | J29: =SUBTOTAL(9,J24:J28) -> 0 | K29: =SUBTOTAL(9,K24:K28) -> 36 | L29: =SUM(L24:L28) -> 78 | M29: =+L29/D29 -> 1 | P29: SDW | X29: INS
P30: ITEM | Q30: ALL | R30: A | S30: B | T30: C | U30: D | V30: UR | X30: ITEM | Y30: ALL | Z30: A | AA30: B | AB30: C | AC30: D | AD30: UR | AE30: Not Respond
A31: Procurement Summary | P31: CVL | Q31: 1940 | R31: 84 | S31: 1700 | T31: 4 | U31: 138 | V31: 14 | X31: CVL | Y31: 7 | Z31: 1 | AA31: 6 | AB31: 0 | AC31: 0 | AD31: 0 | AE31: 0
A32: Item Per WBS | D32: Total Materials | E32: Total Number of P.O. | F32: Actual P.O. To Date | G32: Remaining P.O | H32: Actual Material on Site | I32: Remaining Materials | J32: Material Delivery Completion (Date) | P32: ELE | Q32: 158 | R32: 21 | S32: 111 | T32: 2 | U32: 0 | V32: 0 | W32: 24 Returned | X32: HSF | Y32: 95 | Z32: 2 | AA32: 84 | AB32: 0 | AC32: 0 | AD32: 9 | AE32: 0
E33: A | F33: B | G33: C | H33: D | I33: Processed | P33: GEN | Q33: 3 | R33: 0 | S33: 3 | T33: 0 | U33: 0 | V33: 0 | X33: QAC | Y33: 85 | Z33: 32 | AA33: 52 | AB33: 0 | AC33: 0 | AD33: 1 | AE33: 0
A34: Road | D34: 4 | E34: 4 | F34: 3 | G34: =+D34-F34 -> 1 | H34: 3 | J34: 45990 | P34: MEC | Q34: 437 | R34: 4 | S34: 423 | T34: 8 | U34: 2 | V34: 0
A35: infrastructure | C35: Structural | D35: 8 | E35: 8 | F35: 7 | G35: =+D35-F35 -> 1 | H35: 7 | J35: 46119 | P35: SVY | Q35: 1 | R35: 0 | S35: 1 | T35: 3 | U35: 0 | V35: 0 | X35: TOTAL | Y35: 187 | Z35: 35 | AA35: 142 | AB35: 0 | AC35: 0 | AD35: 10 | AE35: 0
A36: Electrical | D36: 8 | E36: 8 | F36: 2 | G36: =+D36-F36 -> 6 | J36: 46078 | P36: TOTAL | Q36: 2539 | R36: 109 | S36: 2238 | T36: 17 | U36: 140 | V36: 14
P38: MAC | X38: NCR
A39: TOTAL | D39: =SUBTOTAL(9,D34:D38) -> 20 | E39: =SUBTOTAL(9,E34:E38) -> 20 | F39: =SUBTOTAL(9,F34:F38) -> 12 | G39: =SUBTOTAL(9,G34:G38) -> 8 | H39: =SUBTOTAL(9,H34:H38) -> 10 | I39: =SUBTOTAL(9,I34:I38) -> 0 | P39: ITEM | Q39: ALL | R39: A | S39: B | T39: C | U39: D | V39: UR | X39: ITEM | Y39: ALL | Z39: A | AA39: B | AB39: C | AC39: D | AD39: UR | AE39: Not Respond
P40: CVL | Q40: 35 | R40: 1 | S40: 6 | T40: 2 | U40: 0 | V40: 26 | X40: Cont | Y40: 4 | Z40: 0 | AA40: 4 | AB40: 0 | AC40: 0 | AD40: 0 | AE40: 0
A41: Consultant Quality Inspections / Observations (Weekly Basis) | I41: Overall Average | J41: =AVERAGE(E43:E824) -> #DIV/0! | L41: Average Closing | M41: =AVERAGE(G43:G113) -> #DIV/0! | P41: ELE | Q41: 20 | R41: 1 | S41: 9 | T41: 1 | U41: 0 | V41: 9 | X41: HSF | Y41: 53 | Z41: 1 | AA41: 47 | AB41: 0 | AC41: 0 | AD41: 0 | AE41: 0
A42: Week Number | B42: Date of Audit | C42: Date Issued | D42: Numbers Of Comments | E42: Quality Score | F42: Date Closed | G42: Closure Duration | I42: This Week Score | J42: =#REF! -> #REF! | L42: Average Number of Comments Per Audit | M42: =AVERAGE(D43:D113) -> #DIV/0! | P42: MEC | Q42: 23 | R42: 14 | S42: 7 | T42: 1 | U42: 0 | V42: 1 | X42: QAC | Y42: 45 | Z42: 17 | AA42: 25 | AB42: 0 | AC42: 0 | AD42: 3 | AE42: 0
P43: TOTAL | Q43: 78 | R43: 16 | S43: 22 | T43: 4 | U43: 0 | V43: 36
X44: TOTAL | Y44: 102 | Z44: 18 | AA44: 76 | AB44: 0 | AC44: 0 | AD44: 3 | AE44: 0
P45: ITP
P46: ITEM | Q46: ALL | R46: A | S46: B | T46: C | U46: D | V46: UR | X46: ASB
P47: CVL | Q47: 8 | R47: 0 | S47: 0 | T47: 0 | U47: 0 | V47: 8 | X47: ITEM | Y47: ALL | Z47: A | AA47: B | AB47: C | AC47: D | AD47: UR
P48: ELE | Q48: 3 | R48: 0 | S48: 0 | T48: 0 | U48: 0 | V48: 3 | X48: CVL | Y48: 165 | Z48: 122 | AA48: 23 | AB48: 8 | AC48: 7 | AD48: 3
P49: MEC | Q49: 4 | R49: 0 | S49: 0 | T49: 0 | U49: 0 | V49: 4 | X49: ELE | Y49: 56 | Z49: 56 | AA49: 0 | AB49: 0 | AC49: 0 | AD49: 0
P50: TOTAL | Q50: 15 | R50: 0 | S50: 0 | T50: 0 | U50: 0 | V50: 15 | X50: GEN | Y50: 0 | Z50: 0 | AA50: 0 | AB50: 0 | AC50: 0 | AD50: 0
X51: MEC | Y51: 393 | Z51: 309 | AA51: 52 | AB51: 4 | AC51: 2 | AD51: 21
X52: TOTAL | Y52: 614 | Z52: 487 | AA52: 75 | AB52: 12 | AC52: 9 | AD52: 24

Sheet HSE
B1: MODON HSE Site Inspection Report
B2: Date | E2: 46229 | L2: Inspected By:
B4: Project ID. | E4: JDH3-02-008-MOD-1-HSE-REP-03 | L4: Report No. | P4: 00080 | W4: MODON PM Name
B6: Project Name: | E6: completion of the infrastructure development in the 3rd industrial city in Jeddah | L6: Contractor: | R6: Alrawaf | X6: Safety Performance | AE6: =(((COUNTIF(L13:Q25,"1")+COUNTIF(AC13:AH25,"1"))*AR13)+(COUNTIF(L13:Q25,"2")+COUNTIF(AC13:AH25,"2"))*AR14+(COUNTIF(L13:Q25,"3")+COUNTIF(AC13:AH25,"3"))*AR15)/((COUNT(L13:Q25)+COUNT(AC13:AH25))*100) -> 0.81818182
B8: Inspections are a snapshot in time and refer only to the practices and documentation observed at the time of the Inspection. It remains the responsibility of the Consultant and Contractor to ensure that all aspects of Health & Safety are suitably managed.
B9: 1 | D9: Good Practice | H9: 2 | I9: Need Improvement | T9: 3 | U9: Fail (Life Threatening Activity) / Comliance with Plan & Procedures | X9: N/A | Y9: Atcitty Not Applicable for this Site Inspection Report
B11: No. | C11: Topic | K11: Wt. | L11: HSE Compliance | S11: No. | T11: Topic | AB11: Wt. | AC11: HSE Compliance
BA12: 45502
B13: 1 | C13: Access and Egress - (General access to site, segregated from vehicles, / Overhead protection, while entering into the building /Adequate lighting provided when dark or overnight work) | K13: 0.05 | L13: 1 | S13: 14 | T13: Work at Height - (PPE/Fall Protection(Same level, above and blow) / Training / Fall restraint / competency /Safe access & egress to and from work at height / Ladders / Openings (floor/shafts/Provision of emergency rescue) | AB13: 0.05 | AC13: N/A | AP13: 1 | AR13: 100 | AU13: 1 | BA13: 45579 | BC13: =+BA13-BA12+1 -> 78 | BE13: =+BC13/BC15 -> 0.10684932
B14: 2 | C14: Traffic Management - (Loading/unloading/sheeting/temp. routes/speed/parking/competence) | K14: 0.03 | L14: 2 | S14: 15 | T14: Scaffolding - (Temp. Scaffolding Work-platform (All types) - qualified scaffolder / Inspection / Tagged / Safe Access/egress / PTW/Falsework & Formwork) | AB14: 0.04 | AC14: N/A | AP14: 2 | AR14: 75 | AU14: 2
B15: 3 | C15: Site Signage - (Project Notice Board & General Signage) | K15: 0.02 | L15: 2 | S15: 16 | T15: Mobile Elevated Work platform (MEWP) - (PTW/competence requirements/conditions/inspections/tagged/training/Full-body harness) | AB15: 0.04 | AC15: N/A | AP15: 3 | AR15: 0 | AU15: 3 | BA15: 46231 | BC15: =+BA15-BA12+1 -> 730
B16: 4 | C16: PPE Compliance - (Use, storage, stock, handling & checks - Head, Foot, Eye, Hearing) | K16: 0.05 | L16: 2 | S16: 17 | T16: Excavation & Trenches - (PTW/Edge protection/buffer zone/Slope/Benching/Shoring/Geo-tech report/Atmospheric hazards/Acess&egress/Emergency management / MS&RA/H.E) | AB16: 0.03 | AC16: 1 | AU16: N/A
B17: 5 | C17: Housekeeping - (Material correctly stored/Rubbish cleaned & removed daily/slips & trips hazards) | K17: 0.03 | L17: 2 | S17: 18 | T17: Confined Space - (PTW/Training/competence/Emergency Management/MS & RA/Safe access/egress) | AB17: 0.05 | AC17: 2
B18: 6 | C18: Storage of Materials - (Transporting, storage, training and use - Combustible / Flammable / Hazardous substances (COSHH) | L18: 2 | S18: 19 | T18: Fire Protection - (Flammable/Oxy. LPG /Combustible separated/FE's/Flashback arrestor/Sparks & slags/Smoking area/PTW/Generators/MS & RA/Emergency Management) | AC18: 1 | AL18: Red | AM18: Serious injury or death (immediately)
B19: 7 | C19: Site Waste Management - (Hazardous waste /Combustible waste / Human waste / Construction waste - asphalt, cable, timber, paving roof sheeting tiles, plastic & bricks) | L19: 2 | S19: 20 | T19: Health & Welfare - (Adequate drinking water/shaded - eating & rest area/washing & sanitary facilities/Certified FA/FA Box & Stock/adequate toilets/Ambulance) | AC19: 3 | AL19: Yellow | AM19: Minor or near miss (3 days to comply)
B20: 8 | C20: Health Surveillance - (Expose to excessive noise/vibration/dust/silica/CO/cement/radiation/extreme weather condition) | K20: 0.03 | L20: 1 | S20: 21 | T20: Environmental Incident Measures - (Spill/ Leakage / Concrete wash / vehicle & eqpts. wash / waste disposal/Sewers and drains/emissions/Emergency Management/Training/site run-off water) | AB20: 0.05 | AC20: 2 | AL20: Green | AM20: No issues
B21: 9 | C21: Electrical Safety - (Electrical qualified /RCD/GFCI/Industrial Cocket/LOTO/Cable-overhung or buried/Cords in good condition/current inspection tag) | K21: 0.05 | L21: 1 | S21: 22 | T21: HSE Communications & Meetings - (Schedule HSE Meetings/Safety Committee meetings/Alerts / Lesson learned/Safety Bulletin contains latest HSE KPI) | AB21: 0.05 | AC21: 1
B22: 10 | C22: Tools & Equipment - (Includes, powered, hydraulic & pneumatic/Guards in place/Properly stored/RCD Protection/Earthed/Good condition & tagged) | K22: 0.03 | L22: 2 | S22: 23 | T22: HSE Plan & Associated Procedures - (Approved updated HSE Plan/ CEMP/HAZComm/Procedures/Standards/Project Safety Risk Register) | AB22: 0.03 | AC22: 1 | AL22: 26 points > 4 minors then is it’s a serious issue
B23: 11 | C23: Manual Handling - (Lifting/loading/pulling/pushing/twisting/awkward posture/repetitive task/frequent and prolong physical effort/Reasonable practicable use of mechanical aid) | K23: 0.03 | L23: 1 | S23: 24 | T23: Health, Safety & Environment Incident reporting - (Review of HSE Statistics, Reporting of Unsafe Act & Conditions/ Reporting of Near Miss incident/Reporting of FA cases/Record MT cases) | AB23: 0.03 | AC23: 2
B24: 12 | C24: Vehicle and mobile equipment / Plant - (dumpers; excavators, cranes, piling rigs, grader, roller, loaders/condition/KSA License/certification) | K24: 0.05 | L24: 2 | S24: 25 | T24: HSE Awareness, Training & Competence - (Policy /Objective & targets/Information, training/Climatic condition awareness/Reponses in emergency situation/ Safety Behavior Observation) | AB24: 0.04 | AC24: 2
B25: 13 | C25: Lifting Operations & Rigging - (Lifting Plan/Lifting devices & gears/PTW/Condition/3rd party certification/bank-man/rigger/slingers/man-basket/inspection record/tagged) | L25: N/A | S25: 26 | T25: Project Leadership Site Tours - (Provide evidence of proactive safety performance/Deficient discovered discussed/Positive feedback/Workers resolving safety issues) | AC25: 1
B27: Prepared by: | G27: Mohamed Ali | S27: Sent to MODON PM:
B28: Safety Results
B29: 1 | D29: =COUNTIF(L13:Q26,"1")+COUNTIF(AB13:AG26,"1") -> 9 | I29: 2 | L29: =COUNTIF(L13:Q26,"2")+COUNTIF(AB13:AG26,"2") -> 12 | U29: 3 | W29: =COUNTIF(L13:Q26,"3")+COUNTIF(AB13:AG26,"3") -> 1

Sheet HSE-Stat
A1: Safety Statistics
A3: Category | B3: Item | D3: This Week | E3: This Month | F3: Year to Date | G3: Cumulative
A4: Category | B4: Total Hours Worked | D4: 22920 | E4: 97050 | F4: 1866079 | G4: 2210362
B5: Safe Hours Worked | D5: =D4 -> 22920 | E5: =E4 -> 97050 | F5: =F4 -> 1866079 | G5: =G4 -> 2210362
B6: LTI | D6: 0 | E6: 0 | F6: 0 | G6: 0
B7: MTC (Healed w/o Disability) | D7: 0 | E7: 0 | F7: 0 | G7: 0
B8: MTC (Healed w/ Disability) | D8: 0 | E8: 0 | F8: 0 | G8: 0
B9: Near Miss | D9: 0 | E9: 0 | F9: =((5+1+2+1)+0)+0 -> 9 | G9: 11
B10: First Aid Cases | D10: 0 | E10: 0 | F10: 0 | G10: 0 | P10: =16*4 -> 64
B11: Fatality | D11: 0 | E11: 0 | F11: 0 | G11: 0
B12: Fire Incident Cases | D12: 0 | E12: 0 | F12: 0 | G12: 0
B13: Vehicle Incident | D13: 0 | E13: 0 | F13: 1 | G13: 1
B14: Property Damages | D14: 0 | E14: 0 | F14: 0 | G14: 0
A15: Proactive | B15: Induction Training | D15: 0 | E15: 0 | F15: 96 | G15: 223
B16: No.of Internal Training | D16: 2 | E16: 7 | F16: 145 | G16: 178
B17: No.of Internal Audit | D17: 0 | E17: 0 | F17: 0 | G17: 0
B18: No. of Toolbox Talks | D18: 8 | E18: 34 | F18: 3181 | G18: 3335
B19: Safety Awards/Incentives | D19: 0 | E19: 0 | F19: 0 | G19: 0
I20: Category | J20: Item | L20: This Week | M20: This Month | N20: Year to Date | O20: Cumulative
A22: Consultant Safety Inspection (Weekly Basis) | I22: Overall Average | J22: =AVERAGE(E24:E292) -> #DIV/0!
A23: Week Number | B23: Date of Audit | C23: Date Issued | D23: Numbers Of Comments | E23: Overall Score | F23: Date Closed | G23: Closure Duration | I23: This Week Score | J23: =HSE!AE6 -> 0.81818182

Sheet Major Quantities
A1: Material | B1: Unit | C1: Original BOQ Qty | D1: Revised BOQ | E1: Delivered Qty | F1: Delivery % | G1: Installed Qty | H1: Installed Qty %
A2: Sewage Network
A3: GRP–200 Dia | B3: m | C3: 29181 | D3: 21379.41 | E3: =D3 -> 21379.41 | F3: 1 | G3: =E3 -> 21379.41 | H3: =IFERROR(G3/(D3),"") -> 1
A4: GRP–250 Dia | B4: m | C4: 380 | D4: 4579.41 | E4: =D4 -> 4579.41 | F4: 1 | G4: =E4 -> 4579.41 | H4: =IFERROR(G4/(D4),"") -> 1
A5: GRP–300 Dia | B5: m | C5: 0 | D5: 204.61 | E5: =D5 -> 204.61 | F5: 1 | G5: =E5 -> 204.61 | H5: =IFERROR(G5/(D5),"") -> 1
A6: GRP–400 Dia | B6: m | C6: 0 | D6: 531.89 | E6: =D6 -> 531.89 | F6: 1 | G6: =E6 -> 531.89 | H6: =IFERROR(G6/(D6),"") -> 1
A7: Sewage Manholes | B7: Nr | C7: 361 | D7: 355 | E7: =D7 -> 355 | F7: 1 | G7: =E7 -> 355 | H7: =IFERROR(G7/(D7),"") -> 1
A8: Storm Network
A9: UPVC 300 mm Dia | B9: m | C9: 28700 | D9: 29079.778 | E9: =D9 -> 29079.778 | F9: 1 | G9: =E9 -> 29079.778 | H9: =IFERROR(G9/(D9),"") -> 1
A10: GRP– 400 Dia | B10: m | C10: 4770 | D10: 11757.93 | E10: =D10 -> 11757.93 | F10: 1 | G10: =E10 -> 11757.93 | H10: =IFERROR(G10/(D10),"") -> 1
A11: GRP– 500 Dia | B11: m | C11: 4350 | D11: 4240.12 | E11: =D11 -> 4240.12 | F11: 1 | G11: =E11 -> 4240.12 | H11: =IFERROR(G11/(D11),"") -> 1
A12: GRP– 600 Dia | B12: m | C12: 5050 | D12: 5965.71 | E12: =D12 -> 5965.71 | F12: 1 | G12: =E12 -> 5965.71 | H12: =IFERROR(G12/(D12),"") -> 1
A13: GRP– 700 Dia | B13: m | C13: 5550 | D13: 5347.16 | E13: =D13 -> 5347.16 | F13: 1 | G13: =E13 -> 5347.16 | H13: =IFERROR(G13/(D13),"") -> 1
A14: GRP– 800 Dia | B14: m | C14: 6900 | D14: 6312.41 | E14: =D14 -> 6312.41 | F14: 1 | G14: =E14 -> 6312.41 | H14: =IFERROR(G14/(D14),"") -> 1
A15: GRP– 900 Dia | B15: m | C15: 8250 | D15: 7735.76 | E15: =D15 -> 7735.76 | F15: 1 | G15: =E15 -> 7735.76 | H15: =IFERROR(G15/(D15),"") -> 1
A16: GRP– 1000 Dia | B16: m | C16: 3200 | D16: 2855.86 | E16: =D16 -> 2855.86 | F16: 1 | G16: =E16 -> 2855.86 | H16: =IFERROR(G16/(D16),"") -> 1
A17: GRP– 1100 Dia | B17: m | C17: 2370 | D17: 1771.08 | E17: =D17 -> 1771.08 | F17: 1 | G17: =E17 -> 1771.08 | H17: =IFERROR(G17/(D17),"") -> 1
A18: GRP– 1200 Dia | B18: m | C18: 3900 | D18: 8971.96 | E18: =D18 -> 8971.96 | F18: 1 | G18: =E18 -> 8971.96 | H18: =IFERROR(G18/(D18),"") -> 1
A19: GRP– 1400 Dia | B19: m | C19: 0 | D19: 425.38 | E19: =D19 -> 425.38 | F19: 1 | G19: =E19 -> 425.38 | H19: =IFERROR(G19/(D19),"") -> 1
A20: Manhole– 1200 Dia | B20: Nr | C20: 75 | D20: 203 | E20: =D20 -> 203 | F20: 1 | G20: =E20 -> 203 | H20: =IFERROR(G20/(D20),"") -> 1
... A24: Catch Basin Double | B24: Nr | C24: 630 | D24: 761 | E24: =D24 -> 761 | F24: 1 | G24: =E24 -> 761 | H24: =IFERROR(G24/(D24),"") -> 1
A25: Potable Water Network
A26: HDPE PIPE DN 160 | B26: m | C26: 17812 | D26: 8045 | E26: =D26 -> 8045 | F26: 1 | G26: =E26 -> 8045 | H26: =IFERROR(G26/(D26),"") -> 1
A27: HDPE PIPE DN 225 | B27: m | C27: 5660 | D27: 2000 | E27: =D27 -> 2000 | F27: 1 | G27: =E27 -> 2000 | H27: =IFERROR(G27/(D27),"") -> 1
A28: HDPE PIPE DN 315 | B28: m | C28: 270 | D28: 215 | E28: =D28 -> 215 | F28: 1 | G28: =E28 -> 215 | H28: =IFERROR(G28/(D28),"") -> 1
A29: HDPE PIPE DN 450 | B29: m | C29: 0 | D29: 1890 | E29: =D29 -> 1890 | F29: 1 | G29: =E29 -> 1890 | H29: =IFERROR(G29/(D29),"") -> 1
A30: Buried Gate Valves 150 | B30: Nr | C30: 68 | D30: 68 | E30: =D30 -> 68 | F30: 1 | G30: =E30 -> 68 | H30: =IFERROR(G30/(D30),"") -> 1
A31: Buried Gate Valves 200 | B31: Nr | C31: 9 | D31: 9 | E31: =D31 -> 9 | F31: 1 | G31: =E31 -> 9 | H31: =IFERROR(G31/(D31),"") -> 1
A32: Butterfly Valves 300 | B32: Nr | C32: 239 | D32: 2 | E32: =D32 -> 2 | F32: 1 | G32: =E32 -> 2 | H32: =IFERROR(G32/(D32),"") -> 1
A33: Wash-out Valves 100 | B33: Nr | C33: 2 | D33: 3 | E33: =D33 -> 3 | F33: 1 | G33: =E33 -> 3 | H33: =IFERROR(G33/(D33),"") -> 1
A34: Air Valves 50 | B34: Nr | C34: 7 | D34: 1 | E34: =D34 -> 1 | F34: 1 | G34: =E34 -> 1 | H34: =IFERROR(G34/(D34),"") -> 1
A35: Fire hydrant | B35: Nr | C35: 2 | D35: 193 | E35: =D35 -> 193 | F35: 1 | G35: =E35 -> 193 | H35: =IFERROR(G35/(D35),"") -> 1
A36: Fire hydrant ULFM 150 | B36: Nr | C36: 218 | D36: 193 | E36: =D36 -> 193 | F36: 1 | G36: =E36 -> 193 | H36: =IFERROR(G36/(D36),"") -> 1
A37: Irrigation Network
A38: HDPE PIPE DN 125 | B38: m | C38: 9460 | D38: 24479 | E38: =D38 -> 24479 | F38: 1 | G38: =E38 -> 24479 | H38: =IFERROR(G38/(D38),"") -> 1
A39: HDPE PIPE DN 250 | B39: m | C39: 38800 | D39: 28362 | E39: =D39 -> 28362 | F39: 1 | G39: =E39 -> 28362 | H39: =IFERROR(G39/(D39),"") -> 1
A40: HDPE PIPE DN 315 | B40: m | C40: 10249 | D40: 7061 | E40: =D40 -> 7061 | F40: 1 | G40: =E40 -> 7061 | H40: =IFERROR(G40/(D40),"") -> 1
A41: HDPE PIPE DN 450 | B41: m | C41: 8462 | D41: 8870 | E41: =D41 -> 8870 | F41: 1 | G41: =E41 -> 8870 | H41: =IFERROR(G41/(D41),"") -> 1
A42: HDPE PIPE DN 630 | B42: m | C42: 3014 | D42: 2221 | E42: =D42 -> 2221 | F42: 1 | G42: =E42 -> 2221 | H42: =IFERROR(G42/(D42),"") -> 1
A43: GRP PIPE DN 800 | B43: m | C43: =D43 -> 1340 | D43: 1340 | E43: =D43 -> 1340 | F43: 1 | G43: =E43 -> 1340 | H43: =IFERROR(G43/(D43),"") -> 1
A44: Buried Gate Valves 100 | B44: Nr | C44: =D44 -> 314 | D44: 314 | E44: =D44 -> 314 | F44: 1 | G44: =E44 -> 314 | H44: =IFERROR(G44/(D44),"") -> 1
A45: Buried Gate Valves 250 | B45: Nr | C45: =D45 -> 141 | D45: 141 | E45: =D45 -> 141 | F45: 1 | G45: =E45 -> 141 | H45: =IFERROR(G45/(D45),"") -> 1
A46: Butterfly Valves 300 | B46: Nr | C46: =D46 -> 20 | D46: 20 | E46: =D46 -> 20 | F46: 1 | G46: =E46 -> 20 | H46: =IFERROR(G46/(D46),"") -> 1
A47: Butterfly Valves 400 | B47: Nr | C47: =D47 -> 30 | D47: 30 | E47: =D47 -> 30 | F47: 1 | G47: =E47 -> 30 | H47: =IFERROR(G47/(D47),"") -> 1
A48: Butterfly Valves 600 | B48: Nr | C48: =D48 -> 9 | D48: 9 | E48: =D48 -> 9 | F48: 1 | G48: =E48 -> 9 | H48: =IFERROR(G48/(D48),"") -> 1
A49: Butterfly Valves 800 | B49: Nr | C49: =D49 -> 2 | D49: 2 | E49: =D49 -> 2 | F49: 1 | G49: =E49 -> 2 | H49: =IFERROR(G49/(D49),"") -> 1
A50: Wash-out Valves 100 | B50: Nr | C50: 998 | D50: 22 | E50: =D50 -> 22 | F50: 1 | G50: =E50 -> 22 | H50: =IFERROR(G50/(D50),"") -> 1
A51: Wash-out Valves 150 | B51: Nr | C51: 736 | D51: 6 | E51: =D51 -> 6 | F51: 1 | G51: =E51 -> 6 | H51: =IFERROR(G51/(D51),"") -> 1
A52: Wash-out Valves 200 | B52: Nr | C52: 103 | D52: 1 | E52: =D52 -> 1 | F52: 1 | G52: =E52 -> 1 | H52: =IFERROR(G52/(D52),"") -> 1
A53: Air Valves 50 | B53: Nr | C53: 46 | D53: 33 | E53: =D53 -> 33 | F53: 1 | G53: =E53 -> 33 | H53: =IFERROR(G53/(D53),"") -> 1
A54: Air Valves 65 | B54: Nr | C54: 82 | D54: 11 | E54: =D54 -> 11 | F54: 1 | G54: =E54 -> 11 | H54: =IFERROR(G54/(D54),"") -> 1
A55: Road works
A56: Bituminous base course (Grading I - Class A), including Prime Coat (MC1) | B56: m3 | C56: 2255 | D56: 1735 | E56: =D56 -> 1735 | F56: 1 | G56: =E56 -> 1735 | H56: =IFERROR(G56/(D56),"") -> 1
A57: Bituminous concrete wearing course, (Grading I - Class A), including tack coat (RC2) | B57: m3 | C57: 63689 | D57: 1240 | E57: =D57 -> 1240 | F57: 1 | G57: =E57 -> 1240 | H57: =IFERROR(G57/(D57),"") -> 1
A58: Precast Concrete Kerb, Type K1-D | B58: m | C58: 187209 | D58: 15100 | E58: =D58 -> 15100 | F58: 1 | G58: =E58 -> 15100 | H58: =IFERROR(G58/(D58),"") -> 1
A59: Precast Concrete Kerb, Type L1 | B59: m | C59: 123805 | D59: 1972.25 | E59: =D59 -> 1972.25 | F59: 1 | G59: =E59 -> 1972.25 | H59: =IFERROR(G59/(D59),"") -> 1
A60: Depressed curbs Type K2 | B60: m | C60: 2850 | D60: 750 | E60: =D60 -> 750 | F60: 1 | G60: =E60 -> 750 | H60: =IFERROR(G60/(D60),"") -> 1
A61: Interlock | B61: m2 | C61: 59537.282 | D61: 1576 | E61: =D61 -> 1576 | F61: 1 | G61: =E61 -> 1576 | H61: =IFERROR(G61/(D61),"") -> 1
A62: Traffic signs, ground mounted, Sheet Alumenium, (breakaway)Single post, with all accessories | B62: unit | C62: 1295 | D62: 31 | E62: =D62 -> 31 | F62: 1 | G62: =E62 -> 31 | H62: =IFERROR(G62/(D62),"") -> 1
A63: Traffic signs, ground mounted, Sheet Alumenium, (breakaway) Double post with all accessories | B63: unit | C63: 113 | D63: 4 | E63: =D63 -> 4 | F63: 1 | G63: =E63 -> 4 | H63: =IFERROR(G63/(D63),"") -> 1
A64: Electrical network
A65: MEDIUM VOLTAGE CABLES DUCT BANKS | E65: =D65 -> 0 | F65: =IFERROR(E65/(D65),"") | G65: =E65 -> 0
A66: Duct bank for (4) cables | B66: m | C66: 950 | D66: 0 | E66: =D66 -> 0 | F66: =IFERROR(E66/(D66),"") | G66: =E66 -> 0 | H66: =IFERROR(#REF!/G66,"")
A67: MEDIUM VOLTAGE CABLES | E67: =D67 -> 0 | F67: =IFERROR(E67/(D67),"") | G67: =E67 -> 0
A68: 3 Core AL . Cable 13.8 kV 3Cx500 mm² AL./XLPE /PVC. Unarmored | B68: m | C68: 30720 | D68: 0 | E68: =D68 -> 0 | F68: =IFERROR(E68/(D68),"") | G68: =E68 -> 0 | H68: =IFERROR(#REF!/G68,"")
A69: Straight joints cables for 13.8 kv 3Cx 500 mm², Al /XLPE/LLDPE | B69: unit | C69: 70 | D69: 0 | E69: =D69 -> 0 | F69: =IFERROR(E69/(D69),"") | G69: =E69 -> 0 | H69: =IFERROR(#REF!/G69,"")
A70: Cable Termination for 13.8 kv 3Cx 500 mm², Al /XLPE/LLDPE | B70: unit | C70: 8 | D70: 0 | E70: =D70 -> 0 | F70: =IFERROR(E70/(D70),"") | G70: =E70 -> 0 | H70: =IFERROR(#REF!/G70,"")
A71: MEDIUM VOLTAGE SWITCHGEARS | E71: =D71 -> 0 | F71: =IFERROR(E71/(D71),"") | G71: =E71 -> 0
A72: Nrrmally Open Point (R M U) 13.8 kv for Outdoor type according to the Saudi Electric Company specifications and requirements | B72: unit | C72: 2 | D72: 0 | E72: =D72 -> 0 | F72: =IFERROR(E72/(D72),"") | G72: =E72 -> 0 | H72: =IFERROR(#REF!/G72,"")
A73: Street Lighting
A74: STREET LIGHTING SUB-STATION | E74: =D74 -> 0 | F74: =IFERROR(E74/(D74),"") | G74: =E74 -> 0 | H74: =IFERROR(#REF!/G74,"")
A75: Unit Substation 13.8/0.4 K V, 500kVA ,Including concrete foundations and fencing, And all accorciess of cables , terminations , lugs , ...., According to the specifications and standards of SEC | B75: Unit | C75: 3 | D75: 0 | E75: =D75 -> 0 | F75: =IFERROR(E75/(D75),"") | G75: =E75 -> 0 | H75: =IFERROR(#REF!/G75,"")
A76: Ring Main Unit RMU, 13.8KV, According to the specifications and standards of SEC | B76: Unit | C76: 3 | D76: 0 | E76: =D76 -> 0 | F76: =IFERROR(E76/(D76),"") | G76: =E76 -> 0 | H76: =IFERROR(#REF!/G76,"")
A77: LOW VOLTAGE CABLES | E77: =D77 -> 0 | F77: =IFERROR(E77/(D77),"") | G77: =E77 -> 0
A78: Stranded armored Cables, Copper, 4Cx6 mm² XLPE /PVC/SWA | B78: m | C78: 3065 | D78: 1826 | E78: =D78 -> 1826 | F78: 1 | G78: =E78 -> 1826 | H78: =IFERROR(#REF!/G78,"")
A79: Stranded armored Cables, Copper, 4Cx10 mm² XLPE /PVC/SWA | B79: m | C79: 2890 | D79: 2092 | E79: =D79 -> 2092 | F79: 1 | G79: =E79 -> 2092 | H79: =IFERROR(#REF!/G79,"")
A80: Stranded armored Cables, Copper, 4Cx16 mm² XLPE /PVC/SWA | B80: m | C80: 1712 | D80: 896 | E80: =D80 -> 896 | F80: 1 | G80: =E80 -> 896 | H80: =IFERROR(#REF!/G80,"")
A81: Stranded armored Cables, Copper, 4Cx25 mm² XLPE /PVC/SWA | B81: m | C81: 15218 | D81: 7396 | E81: =D81 -> 7396 | F81: 1 | G81: =E81 -> 7396 | H81: =IFERROR(G81/(D81),"") -> 1
A82: Stranded armored Cables, Copper, 4Cx35 mm² XLPE /PVC/SWA | B82: m | C82: 1150 | D82: 11757 | E82: =D82 -> 11757 | F82: 1 | G82: =E82 -> 11757 | H82: =IFERROR(G82/(D82),"") -> 1
A83: Stranded armored Cables, Copper, 4Cx50 mm² XLPE /PVC/SWA | B83: m | C83: 120 | D83: 120 | E83: =D83 -> 120 | F83: 1 | G83: =E83 -> 120 | H83: =IFERROR(#REF!/G83,"")
A84: Stranded armored Cables, Copper, 4Cx150 mm² XLPE /PVC/SWA | B84: m | C84: 0 | D84: 1500 | E84: =D84 -> 1500 | F84: 1 | G84: =E84 -> 1500 | H84: =IFERROR(#REF!/G84,"")
A85: Supply and install single core PVC insulated copper conductor cables for circuit protective conductor (CPC) / ECC, size 6 mm² | B85: m | C85: 930 | D85: 4208 | E85: =D85 -> 4208 | F85: 1 | G85: =E85 -> 4208 | H85: =IFERROR(#REF!/G85,"")
A86: Supply and install single core PVC insulated copper conductor cables for circuit protective conductor (CPC) / ECC, size 16 mm² | B86: m | C86: 1270 | D86: 20049 | E86: =D86 -> 20049 | F86: 1 | G86: =E86 -> 20049 | H86: =IFERROR(#REF!/G86,"")
A87: Supply and install single core PVC insulated copper conductor cables for circuit protective conductor (CPC) / ECC, size 70 mm² | B87: m | D87: 2700 | E87: =D87 -> 2700 | F87: 1 | G87: =E87 -> 2700 | H87: =IFERROR(#REF!/G87,"")
A88: Supply and install single core PVC insulated copper conductor cables for circuit protective conductor (CPC) / ECC, size 70 mm² | B88: m | D88: 2700 | E88: =D88 -> 2700 | F88: 1 | G88: =E88 -> 2700 | H88: =IFERROR(#REF!/G88,"")
A89: LIGHTING POLES | E89: =D89 -> 0 | F89: =IFERROR(E89/(D89),"") | G89: =E89 -> 0
A90: Lighting poles with 2 arms, height of ( 12 ) meters, including the power distribution box, cables , and RCC foundation. | B90: Unit | C90: 10 | D90: 10 | E90: =D90 -> 10 | F90: 1 | G90: =E90 -> 10 | H90: =IFERROR(G90/(D90),"") -> 1
A91: Lighting poles with 1 arm, height of ( 12 ) meters, including the power distribution box, cables , and RCC foundation. | B91: Unit | C91: 255 | D91: 220 | E91: =D91 -> 220 | F91: 1 | G91: =E91 -> 220 | H91: =IFERROR(G91/(D91),"") -> 1
A92: STREET LIGHTING LUMINAIRE | E92: =D92 -> 0 | F92: =IFERROR(E92/(D92),"") | G92: =E92 -> 0
A93: Street Lighting( LED ) Luminaire complete with control gear and lamp, (150) WATT. | B93: Unit | C93: 275 | D93: 240 | E93: =D93 -> 240 | F93: 1 | G93: =E93 -> 240 | H93: =IFERROR(G93/(D93),"") -> 1
A94: Light fixtures LED 342 watts | B94: Unit | D94: 88 | E94: =D94 -> 88 | F94: 1 | G94: =E94 -> 88 | H94: =IFERROR(G94/(D94),"") -> 1
A95: Light fixtures LED 208 watts | B95: Unit | D95: 102 | E95: =D95 -> 102 | F95: 1 | G95: =E95 -> 102 | H95: =IFERROR(G95/(D95),"") -> 1
A96: EARTHING SYSTEM | E96: =D96 -> 0 | F96: =IFERROR(E96/(D96),"") | G96: =E96 -> 0
A97: Including earthing of lighting poles ,masts. feeder pillars , unit substations, L.V feeders and KWH meter. | B97: Unit | C97: 20 | D97: 20 | E97: =D97 -> 20 | F97: 1 | G97: =E97 -> 20 | H97: =IFERROR(#REF!/G97,"")
A98: ROAD CROSSING DUCTS | E98: =D98 -> 0 | F98: =IFERROR(E98/(D98),"") | G98: =E98 -> 0
A99: ROAD CROSSING DUCT مواسير 160مم UPVC | B99: m | C99: 1440 | D99: 1116 | E99: =D99 -> 1116 | F99: 1 | G99: =E99 -> 1116 | H99: =IFERROR(#REF!/G99,"")
A100: DRAWPITS | E100: =D100 -> 0 | F100: =IFERROR(E100/(D100),"") | G100: =E100 -> 0
A101: Drawpit with medium duty steel cover, size600x600x1000mm | B101: Unit | C101: 2 | D101: 783 | E101: =D101 -> 783 | F101: 1 | G101: =E101 -> 783 | H101: =IFERROR(G101/(D101),"") -> 1
A102: Drawpit with medium duty steel cover, size900x900x1200mm | B102: Unit | C102: 46 | D102: 151 | E102: =D102 -> 151 | F102: 1 | G102: =E102 -> 151 | H102: =IFERROR(#REF!/G102,"")
A103: Drawpit with medium duty steel cover, size 900x1800x1200mm | B103: Unit | C103: 4 | D103: 18 | E103: =D103 -> 18 | F103: 1 | G103: =E103 -> 18 | H103: =IFERROR(#REF!/G103,"")
...

Sheet Invoice Log
B1: Weekly Progress Report - Invoice Log | AK1: Y
B2: Project Value | L2: Payment Status | T2: Invoices Summary | AD2: Average Invoices durations | AK2: N
B3: Original Contract Value | F3: 3.1974488e+08 | H3: O&M Value | J3: 0 | L3: Advance Payment % | N3: 0.1 | P3: Advance Payment (SAR) | R3: =F3*N3 -> 31974488 | T3: No of Submitted Invoices | V3: =MAX($C$9:$C$46) -> 0 | X3: Submitted Invoices (SAR) | Z3: =SUM(F9:F46) -> 2.5021413e+08 | AB3: Submiited Invoice Peroid | AC3: =MAX(M9:M46) -> 46265 | AD3: CM / PgM Average Approval duration | AF3: =AVERAGE(Q9:Q59) -> 0.56521739 | AH3: Average Invoice Value | AI3: =AVERAGE(F9:F58) -> 10425589
B4: Revised Contract Value | F4: 3.1974488e+08 | H4: Revised O&M Value | J4: 0 | L4: Retention % | N4: 0 | P4: Retention (SAR) | R4: =F3*N4 -> 0 | T4: No of Approved Invoices (CM) | V4: =COUNTIF($O$9:$O$59,"Y") -> 23 | X4: Approved Invoices (CM) (SAR) | Z4: =SUMIF($O$9:$O$46,"Y",$K$9:$K$46) -> 2.465379e+08 | AD4: MODON PM & Accounts Average Approval duration | AF4: =AVERAGE(X9:X59) -> #DIV/0!
B5: Estimate At Completion Value | F5: 3.1974488e+08 | H5: Submitted Invoices (Gross Value) | J5: =Z3 -> 2.5021413e+08 | L5: Penalties and deduction % | N5: =ABS(N6/F3) -> 0.00081314829 | P5: AP Recovery (SAR) | R5: =SUM(G9:G58) -> -25021413 | T5: No of Approved Invoices (PM) | V5: =COUNTIF($S$9:$S$59,"Y") -> 23 | X5: Approved Invoices (PM) (SAR) | Z5: =SUMIF($S$9:$S$46,"Y",$K$9:$K$46) -> 2.465379e+08 | AB5: Invoice Submitted Compared to Contract Value | AC5: =Z3/F4 -> 0.78254306 | AD5: Payments Average Duration | AF5: =AVERAGE(AB9:AB59) -> #DIV/0!
B6: Potential Changes | F6: =F4-F5 -> 0 | H6: Total Deduction | J6: =N6+R6+R5 -> -25281413 | L6: Penalties and deduction (SAR) | N6: =SUM(J9:J58) -> -260000 | P6: Retention Cumulative (SAR) | R6: =SUM(H9:H58) -> 0 | T6: No of Paid Invoices | V6: =COUNTA(Y9:Y59) -> 0 | X6: Paid Invoices (SAR) | Z6: =SUM(Z9:Z46) -> 0 | AD6: Invoices Average total Duration | AF6: =IFERROR(AVERAGE(AD9:AD59),"")
B7: Invoice Reference | F7: Invoice Value | K7: Period Covered | N7: CM / PgM Approval Timeline | R7: Modon PM & Accounts Approval | Y7: Payment Status | AD7: Total Invoice Duration | AE7: Remarks
B8: # | C8: Invoice No. | D8: Doc Control reference | E8: Submittal Rev. # | F8: Gross Value | G8: AP Recovery | H8: Retention | I8: VAT 5%/15% | J8: Deduction / Penalties | K8: Amount (net) | L8: Start Date | M8: End Date | N8: Date to CM / PgM | O8: CM / PgM Approval (Yes/No) | P8: CM / PgM Reply Date | Q8: Days Elapsed | R8: Date to PM | S8: PM Approval (Yes/No) | T8: PM Reply Date | U8: Date to Accounts | V8: Accounts Approval (Yes/No) | W8: Accounts Approval Date | X8: Days Elapsed | Y8: Date Paid | Z8: Amount Paid | AA8: Paid % | AB8: Payment Period (d) | AC8: Amount Pending
B9: 1 | C9: #01 | D9: JDH3-02-008-RWF-TS9-1-GEN-IPC-0120-00 | E9: 0 | F9: 3023610.1 | G9: =IF(ISBLANK(F9),"",-F9*$N$3) -> -302361.01 | H9: =IF(ISBLANK(F9),"",-F9*$N$4) -> 0 | I9: =SUM(F9:G9)*0.15 -> 408187.36 | K9: =IF(ISBLANK(F9),"",SUM(F9:J9)) -> 3129436.4 | L9: 45502 | M9: 45594 | N9: 45594 | O9: Y | P9: 45594 | Q9: =IF(ISBLANK(P9),"",P9-N9) -> 0 | R9: 45594 | S9: Y | T9: 45595 | X9: =IF(ISBLANK(W9),"",W9-R9) | Z9: =IF(ISBLANK(Y9),"",K9) | AA9: =IF(ISBLANK(Y9),"",Z9/K9) | AB9: =IF(ISBLANK(W9),"",Y9-W9) | AC9: =IF(ISBLANK(Y9),"",(K9-Z9)) | AD9: =IF(ISBLANK(Y9),"",Y9-N9)
B10: 2 | C10: #02 | D10: JDH3-02-008-RWF-TS9-1-GEN-IPC-0162-00 | E10: 0 | F10: 1950678.2 | G10: =IF(ISBLANK(F10),"",-F10*$N$3) -> -195067.82 | H10: =IF(ISBLANK(F10),"",-F10*$N$4) -> 0 | I10: =SUM(F10:G10)*0.15 -> 263341.55 | K10: =IF(ISBLANK(F10),"",SUM(F10:J10)) -> 2018951.9 | L10: 45595 | M10: 45621 | N10: 45621 | O10: Y | P10: 45621 | Q10: =IF(ISBLANK(P10),"",P10-N10) -> 0 | R10: 45621 | S10: Y | T10: 45623 | X10: =IF(ISBLANK(W10),"",W10-R10) | Z10: =IF(ISBLANK(Y10),"",K10) | AA10: =IF(ISBLANK(Y10),"",Z10/K10) | AB10: =IF(ISBLANK(W10),"",Y10-W10) | AC10: =IF(ISBLANK(Y10),"",(K10-Z10)) | AD10: =IF(ISBLANK(Y10),"",Y10-N10) | AI10: format if no, make shaded
B11: 3 | C11: #03 | D11: JDH3-02-008-RWF-TS9-1-GEN-IPC-0196-00 | E11: 0 | F11: 6773509.5 | G11: =IF(ISBLANK(F11),"",-F11*$N$3) -> -677350.95 | H11: =IF(ISBLANK(F11),"",-F11*$N$4) -> 0 | I11: =SUM(F11:G11)*0.15 -> 914423.78 | J11: -58000 | K11: =IF(ISBLANK(F11),"",SUM(F11:J11)) -> 6952582.3 | L11: 45622 | M11: 45647 | N11: 45648 | O11: Y | P11: 45648 | Q11: =IF(ISBLANK(P11),"",P11-N11) -> 0 | R11: 45648 | S11: Y | T11: 45649 | X11: =IF(ISBLANK(W11),"",W11-R11) | Z11: =IF(ISBLANK(Y11),"",K11) | AA11: =IF(ISBLANK(Y11),"",Z11/K11) | AB11: =IF(ISBLANK(W11),"",Y11-W11) | AC11: =IF(ISBLANK(Y11),"",(K11-Z11)) | AD11: =IF(ISBLANK(Y11),"",Y11-N11)
B12: 4 | C12: #04 | D12: JDH3-02-008-RWF-TS9-1-GEN-IPC-0216-00 | E12: 0 | F12: 2399993.3 | G12: =IF(ISBLANK(F12),"",-F12*$N$3) -> -239999.33 | H12: =IF(ISBLANK(F12),"",-F12*$N$4) -> 0 | I12: =SUM(F12:G12)*0.15 -> 323999.1 | K12: =IF(ISBLANK(F12),"",SUM(F12:J12)) -> 2483993.1 | L12: 45648 | M12: 45657 | N12: 45658 | O12: Y | P12: 45658 | Q12: =IF(ISBLANK(P12),"",P12-N12) -> 0 | R12: 45658 | S12: Y | T12: 45658 | X12: =IF(ISBLANK(W12),"",W12-R12) | Z12: =IF(ISBLANK(Y12),"",K12) | AA12: =IF(ISBLANK(Y12),"",Z12/K12) | AB12: =IF(ISBLANK(W12),"",Y12-W12) | AC12: =IF(ISBLANK(Y12),"",(K12-Z12)) | AD12: =IF(ISBLANK(Y12),"",Y12-N12)
B13: 5 | C13: #05 | D13: JDH3-02-008-RWF-TS9-1-GEN-IPC-0250-00 | E13: 0 | F13: 5065410.2 | G13: =IF(ISBLANK(F13),"",-F13*$N$3) -> -506541.02 | H13: =IF(ISBLANK(F13),"",-F13*$N$4) -> 0 | I13: =SUM(F13:G13)*0.15 -> 683830.38 | J13: -125000 | K13: =IF(ISBLANK(F13),"",SUM(F13:J13)) -> 5117699.6 | L13: 45658 | M13: 45684 | N13: 45684 | O13: Y | P13: 45684 | Q13: =IF(ISBLANK(P13),"",P13-N13) -> 0 | R13: 45684 | S13: Y | T13: 45684 | X13: =IF(ISBLANK(W13),"",W13-R13) | Z13: =IF(ISBLANK(Y13),"",K13) | AA13: =IF(ISBLANK(Y13),"",Z13/K13) | AB13: =IF(ISBLANK(W13),"",Y13-W13) | AC13: =IF(ISBLANK(Y13),"",(K13-Z13)) | AD13: =IF(ISBLANK(Y13),"",Y13-N13)
B14: 6 | C14: #06 | D14: JDH3-02-008-RWF-TS9-1-GEN-IPC-0328-00 | E14: 0 | F14: 4209873.5 | G14: =IF(ISBLANK(F14),"",-F14*$N$3) -> -420987.35 | H14: =IF(ISBLANK(F14),"",-F14*$N$4) -> 0 | I14: =SUM(F14:G14)*0.15 -> 568332.93 | K14: =IF(ISBLANK(F14),"",SUM(F14:J14)) -> 4357219.1 | L14: 45685 | M14: 45717 | N14: 45719 | O14: Y | P14: 45719 | Q14: =IF(ISBLANK(P14),"",P14-N14) -> 0 | R14: 45719 | S14: Y | T14: 45719 | X14: =IF(ISBLANK(W14),"",W14-R14) | Z14: =IF(ISBLANK(Y14),"",K14) | AA14: =IF(ISBLANK(Y14),"",Z14/K14) | AB14: =IF(ISBLANK(W14),"",Y14-W14) | AC14: =IF(ISBLANK(Y14),"",(K14-Z14)) | AD14: =IF(ISBLANK(Y14),"",Y14-N14)
B15: 7 | C15: #07 | D15: JDH3-02-008-RWF-TS9-1-GEN-IPC-0348-00 | E15: 0 | F15: 2256432.9 | G15: =IF(ISBLANK(F15),"",-F15*$N$3) -> -225643.29 | H15: =IF(ISBLANK(F15),"",-F15*$N$4) -> 0 | I15: =SUM(F15:G15)*0.15 -> 304618.44 | K15: =IF(ISBLANK(F15),"",SUM(F15:J15)) -> 2335408.1 | L15: 45718 | M15: 45741 | N15: 45741 | O15: Y | P15: 45741 | Q15: =IF(ISBLANK(P15),"",P15-N15) -> 0 | R15: 45741 | S15: Y | T15: 45741 | X15: =IF(ISBLANK(W15),"",W15-R15) | Z15: =IF(ISBLANK(Y15),"",K15) | AA15: =IF(ISBLANK(Y15),"",Z15/K15) | AB15: =IF(ISBLANK(W15),"",Y15-W15) | AC15: =IF(ISBLANK(Y15),"",(K15-Z15)) | AD15: =IF(ISBLANK(Y15),"",Y15-N15)
B16: 8 | C16: #08 | D16: JDH3-02-008-RWF-TS9-1-GEN-IPC-0403-00 | E16: 0 | F16: 5913349.9 | G16: =IF(ISBLANK(F16),"",-F16*$N$3) -> -591334.99 | H16: =IF(ISBLANK(F16),"",-F16*$N$4) -> 0 | I16: =SUM(F16:G16)*0.15 -> 798302.23 | K16: =IF(ISBLANK(F16),"",SUM(F16:J16)) -> 6120317.1 | L16: 45742 | M16: 45776 | N16: 45777 | O16: Y | P16: 45777 | Q16: =IF(ISBLANK(P16),"",P16-N16) -> 0 | R16: 45777 | S16: Y | T16: 45777 | X16: =IF(ISBLANK(W16),"",W16-R16) | Z16: =IF(ISBLANK(Y16),"",K16) | AA16: =IF(ISBLANK(Y16),"",Z16/K16) | AB16: =IF(ISBLANK(W16),"",Y16-W16) | AC16: =IF(ISBLANK(Y16),"",(K16-Z16)) | AD16: =IF(ISBLANK(Y16),"",Y16-N16)
B17: 9 | C17: #09 | D17: JDH3-02-008-RWF-TS9-1-GEN-IPC-0455-00 | E17: 0 | F17: 5666519.8 | G17: =IF(ISBLANK(F17),"",-F17*$N$3) -> -566651.98 | H17: =IF(ISBLANK(F17),"",-F17*$N$4) -> 0 | I17: =SUM(F17:G17)*0.15 -> 764980.17 | K17: =IF(ISBLANK(F17),"",SUM(F17:J17)) -> 5864847.9 | L17: 45777 | M17: 45808 | N17: 45809 | O17: Y | P17: 45809 | Q17: =IF(ISBLANK(P17),"",P17-N17) -> 0 | R17: 45809 | S17: Y | T17: 45809 | X17: =IF(ISBLANK(W17),"",W17-R17) | Z17: =IF(ISBLANK(Y17),"",K17) | AA17: =IF(ISBLANK(Y17),"",Z17/K17) | AB17: =IF(ISBLANK(W17),"",Y17-W17) | AC17: =IF(ISBLANK(Y17),"",(K17-Z17)) | AD17: =IF(ISBLANK(Y17),"",Y17-N17)
B18: 10 | C18: #10 | D18: JDH3-02-008-RWF-TS9-1-GEN-IPC-0484-00 | E18: 0 | F18: 4491831 | G18: =IF(ISBLANK(F18),"",-F18*$N$3) -> -449183.1 | H18: =IF(ISBLANK(F18),"",-F18*$N$4) -> 0 | I18: =SUM(F18:G18)*0.15 -> 606397.19 | K18: =IF(ISBLANK(F18),"",SUM(F18:J18)) -> 4649045.1 | L18: 45809 | M18: 45837 | N18: 45839 | O18: Y | P18: 45839 | Q18: =IF(ISBLANK(P18),"",P18-N18) -> 0 | R18: 45839 | S18: Y | T18: 45839 | X18: =IF(ISBLANK(W18),"",W18-R18) | Z18: =IF(ISBLANK(Y18),"",K18) | AA18: =IF(ISBLANK(Y18),"",Z18/K18) | AB18: =IF(ISBLANK(W18),"",Y18-W18) | AC18: =IF(ISBLANK(Y18),"",(K18-Z18)) | AD18: =IF(ISBLANK(Y18),"",Y18-N18)
B19: 11 | C19: #11 | D19: JDH3-02-008-RWF-TS9-1-GEN-IPC-0504-00 | E19: 0 | F19: 30018472 | G19: =IF(ISBLANK(F19),"",-F19*$N$3) -> -3001847.2 | H19: =IF(ISBLANK(F19),"",-F19*$N$4) -> 0 | I19: =SUM(F19:G19)*0.15 -> 4052493.7 | K19: =IF(ISBLANK(F19),"",SUM(F19:J19)) -> 31069119 | L19: 45838 | M19: 45866 | N19: 45867 | O19: Y | P19: 45867 | Q19: =IF(ISBLANK(P19),"",P19-N19) -> 0 | R19: 45867 | S19: Y | T19: 45867 | X19: =IF(ISBLANK(W19),"",W19-R19) | Z19: =IF(ISBLANK(Y19),"",K19) | AA19: =IF(ISBLANK(Y19),"",Z19/K19) | AB19: =IF(ISBLANK(W19),"",Y19-W19) | AC19: =IF(ISBLANK(Y19),"",(K19-Z19)) | AD19: =IF(ISBLANK(Y19),"",Y19-N19)
B20: 12 | C20: #12 | D20: JDH3-02-008-RWF-TS9-1-GEN-IPC-0573-00 | E20: 0 | F20: 20138175 | G20: =IF(ISBLANK(F20),"",-F20*$N$3) -> -2013817.5 | H20: =IF(ISBLANK(F20),"",-F20*$N$4) -> 0 | I20: =SUM(F20:G20)*0.15 -> 2718653.6 | K20: =IF(ISBLANK(F20),"",SUM(F20:J20)) -> 20843011 | L20: 45867 | M20: 45902 | N20: 45903 | O20: Y | P20: 45903 | Q20: =IF(ISBLANK(P20),"",P20-N20) -> 0 | R20: 45903 | S20: Y | T20: 45903 | X20: =IF(ISBLANK(W20),"",W20-R20) | Z20: =IF(ISBLANK(Y20),"",K20) | AA20: =IF(ISBLANK(Y20),"",Z20/K20) | AB20: =IF(ISBLANK(W20),"",Y20-W20) | AC20: =IF(ISBLANK(Y20),"",(K20-Z20)) | AD20: =IF(ISBLANK(Y20),"",Y20-N20)
B21: 13 | C21: #13 | D21: JDH3-02-008-RWF-TS9-1-GEN-IPC-0609-00 | E21: 0 | F21: 19138829 | G21: =IF(ISBLANK(F21),"",-F21*$N$3) -> -1913882.9 | H21: =IF(ISBLANK(F21),"",-F21*$N$4) -> 0 | I21: =SUM(F21:G21)*0.15 -> 2583742 | K21: =IF(ISBLANK(F21),"",SUM(F21:J21)) -> 19808689 | L21: 45903 | M21: 45931 | N21: 45932 | O21: Y | P21: 45932 | Q21: =IF(ISBLANK(P21),"",P21-N21) -> 0 | R21: 45932 | S21: Y | T21: 45932 | X21: =IF(ISBLANK(W21),"",W21-R21) | Z21: =IF(ISBLANK(Y21),"",K21) | AA21: =IF(ISBLANK(Y21),"",Z21/K21) | AB21: =IF(ISBLANK(W21),"",Y21-W21) | AC21: =IF(ISBLANK(Y21),"",(K21-Z21)) | AD21: =IF(ISBLANK(Y21),"",Y21-N21)
B22: 14 | C22: #14 | D22: JDH3-02-008-RWF-TS9-1-GEN-IPC-0645-00 | E22: 0 | F22: 17166097 | G22: =IF(ISBLANK(F22),"",-F22*$N$3) -> -1716609.7 | H22: =IF(ISBLANK(F22),"",-F22*$N$4) -> 0 | I22: =SUM(F22:G22)*0.15 -> 2317423.1 | K22: =IF(ISBLANK(F22),"",SUM(F22:J22)) -> 17766910 | L22: 45932 | M22: 45964 | N22: 45965 | O22: Y | P22: 45965 | Q22: =IF(ISBLANK(P22),"",P22-N22) -> 0 | R22: 45965 | S22: Y | T22: 45965 | X22: =IF(ISBLANK(W22),"",W22-R22) | Z22: =IF(ISBLANK(Y22),"",K22) | AA22: =IF(ISBLANK(Y22),"",Z22/K22) | AB22: =IF(ISBLANK(W22),"",Y22-W22) | AC22: =IF(ISBLANK(Y22),"",(K22-Z22)) | AD22: =IF(ISBLANK(Y22),"",Y22-N22)
B23: 15 | C23: #15 | D23: JDH3-02-008-RWF-TS9-1-GEN-IPC-0667-00 | E23: 0 | F23: 16969912 | G23: =IF(ISBLANK(F23),"",-F23*$N$3) -> -1696991.2 | H23: =IF(ISBLANK(F23),"",-F23*$N$4) -> 0 | I23: =SUM(F23:G23)*0.15 -> 2290938.2 | K23: =IF(ISBLANK(F23),"",SUM(F23:J23)) -> 17563859 | L23: 45965 | M23: 45991 | N23: 45992 | O23: Y | P23: 45992 | Q23: =IF(ISBLANK(P23),"",P23-N23) -> 0 | R23: 45992 | S23: Y | T23: 45992 | X23: =IF(ISBLANK(W23),"",W23-R23) | Z23: =IF(ISBLANK(Y23),"",K23) | AA23: =IF(ISBLANK(Y23),"",Z23/K23) | AB23: =IF(ISBLANK(W23),"",Y23-W23) | AC23: =IF(ISBLANK(Y23),"",(K23-Z23)) | AD23: =IF(ISBLANK(Y23),"",Y23-N23)
B24: 16 | C24: #16 | D24: JDH3-02-008-RWF-TS9-1-GEN-IPC-0707-00 | E24: 0 | F24: 21074977 | G24: =IF(ISBLANK(F24),"",-F24*$N$3) -> -2107497.7 | H24: =IF(ISBLANK(F24),"",-F24*$N$4) -> 0 | I24: =SUM(F24:G24)*0.15 -> 2845121.9 | K24: =IF(ISBLANK(F24),"",SUM(F24:J24)) -> 21812601 | L24: 45992 | M24: 46024 | N24: 46025 | O24: Y | P24: 46025 | Q24: =IF(ISBLANK(P24),"",P24-N24) -> 0 | R24: 46025 | S24: Y | T24: 46025 | X24: =IF(ISBLANK(W24),"",W24-R24) | Z24: =IF(ISBLANK(Y24),"",K24) | AA24: =IF(ISBLANK(Y24),"",Z24/K24) | AB24: =IF(ISBLANK(W24),"",Y24-W24) | AC24: =IF(ISBLANK(Y24),"",(K24-Z24)) | AD24: =IF(ISBLANK(Y24),"",Y24-N24)
B25: 17 | C25: #17 | D25: JDH3-02-008-RWF-TS9-1-GEN-IPC-0743-00 | E25: 0 | F25: 19156497 | G25: =IF(ISBLANK(F25),"",-F25*$N$3) -> -1915649.7 | H25: =IF(ISBLANK(F25),"",-F25*$N$4) -> 0 | I25: =SUM(F25:G25)*0.15 -> 2586127 | K25: =IF(ISBLANK(F25),"",SUM(F25:J25)) -> 19826974 | L25: 46023 | M25: 46056 | N25: 46057 | O25: Y | P25: 46057 | Q25: =IF(ISBLANK(P25),"",P25-N25) -> 0 | R25: 46057 | S25: Y | T25: 46057 | X25: =IF(ISBLANK(W25),"",W25-R25) | Z25: =IF(ISBLANK(Y25),"",K25) | AA25: =IF(ISBLANK(Y25),"",Z25/K25) | AB25: =IF(ISBLANK(W25),"",Y25-W25) | AC25: =IF(ISBLANK(Y25),"",(K25-Z25)) | AD25: =IF(ISBLANK(Y25),"",Y25-N25)
B26: 18 | C26: #18 | D26: JDH3-02-008-RWF-TS9-1-GEN-IPC-0791-00 | E26: 0 | F26: 8008551.6 | G26: =IF(ISBLANK(F26),"",-F26*$N$3) -> -800855.16 | H26: =IF(ISBLANK(F26),"",-F26*$N$4) -> 0 | I26: =SUM(F26:G26)*0.15 -> 1081154.5 | K26: =IF(ISBLANK(F26),"",SUM(F26:J26)) -> 8288850.9 | L26: 46057 | M26: 46081 | N26: 46098 | O26: Y | P26: 46105 | Q26: =IF(ISBLANK(P26),"",P26-N26) -> 7 | R26: 46105 | S26: Y | T26: 46106 | X26: =IF(ISBLANK(W26),"",W26-R26) | Z26: =IF(ISBLANK(Y26),"",K26) | AA26: =IF(ISBLANK(Y26),"",Z26/K26) | AB26: =IF(ISBLANK(W26),"",Y26-W26) | AC26: =IF(ISBLANK(Y26),"",(K26-Z26)) | AD26: =IF(ISBLANK(Y26),"",Y26-N26)
B27: 19 | C27: #19 | D27: JDH3-02-008-RWF-TS9-1-GEN-IPC-0793-00 | E27: 0 | F27: 7771884.8 | G27: =IF(ISBLANK(F27),"",-F27*$N$3) -> -777188.48 | H27: =IF(ISBLANK(F27),"",-F27*$N$4) -> 0 | I27: =SUM(F27:G27)*0.15 -> 1049204.4 | K27: =IF(ISBLANK(F27),"",SUM(F27:J27)) -> 8043900.8 | L27: 46082 | M27: 46112 | N27: 46117 | O27: Y | P27: 46117 | Q27: =IF(ISBLANK(P27),"",P27-N27) -> 0 | R27: 46119 | S27: Y | T27: 46119 | X27: =IF(ISBLANK(W27),"",W27-R27) | Z27: =IF(ISBLANK(Y27),"",K27) | AA27: =IF(ISBLANK(Y27),"",Z27/K27) | AB27: =IF(ISBLANK(W27),"",Y27-W27) | AC27: =IF(ISBLANK(Y27),"",(K27-Z27))
B28: 20 | C28: #20 | D28: JDH3-02-008-RWF-TS9-1-GEN-IPC-0808-00 | E28: 0 | F28: 9252098 | G28: =IF(ISBLANK(F28),"",-F28*$N$3) -> -925209.8 | H28: =IF(ISBLANK(F28),"",-F28*$N$4) -> 0 | I28: =SUM(F28:G28)*0.15 -> 1249033.2 | J28: -77000 | K28: =IF(ISBLANK(F28),"",SUM(F28:J28)) -> 9498921.4 | L28: 46113 | M28: 46142 | N28: 46144 | O28: Y | P28: 46147 | Q28: =IF(ISBLANK(P28),"",P28-N28) -> 3 | R28: 46148 | S28: Y | T28: 46148 | X28: =IF(ISBLANK(W28),"",W28-R28) | Z28: =IF(ISBLANK(Y28),"",K28) | AA28: =IF(ISBLANK(Y28),"",Z28/K28) | AB28: =IF(ISBLANK(W28),"",Y28-W28) | AC28: =IF(ISBLANK(Y28),"",(K28-Z28)) | AD28: =IF(ISBLANK(Y28),"",Y28-N28)
B29: 21 | C29: #21 | D29: JDH3-02-008-RWF-TS9-1-GEN-IPC-0850-00 | E29: 0 | F29: 11034645 | G29: =IF(ISBLANK(F29),"",-F29*$N$3) -> -1103464.5 | H29: =IF(ISBLANK(F29),"",-F29*$N$4) -> 0 | I29: =SUM(F29:G29)*0.15 -> 1489677.1 | K29: =IF(ISBLANK(F29),"",SUM(F29:J29)) -> 11420858 | L29: 46143 | M29: 46173 | N29: 46175 | O29: Y | P29: 46178 | Q29: =IF(ISBLANK(P29),"",P29-N29) -> 3 | R29: 46179 | S29: Y | T29: 46179 | X29: =IF(ISBLANK(W29),"",W29-R29) | Z29: =IF(ISBLANK(Y29),"",K29) | AA29: =IF(ISBLANK(Y29),"",Z29/K29) | AB29: =IF(ISBLANK(W29),"",Y29-W29) | AC29: =IF(ISBLANK(Y29),"",(K29-Z29)) | AD29: =IF(ISBLANK(Y29),"",Y29-N29)
B30: 22 | C30: #22 | D30: JDH3-02-008-RWF-TS9-1-GEN-IPC-0890-00 | E30: 0 | F30: 7785923.9 | G30: =IF(ISBLANK(F30),"",-F30*$N$3) -> -778592.39 | H30: =IF(ISBLANK(F30),"",-F30*$N$4) -> 0 | I30: =SUM(F30:G30)*0.15 -> 1051099.7 | K30: =IF(ISBLANK(F30),"",SUM(F30:J30)) -> 8058431.3 | L30: 46174 | M30: 46203 | N30: 46207 | O30: Y | P30: 46207 | Q30: =IF(ISBLANK(P30),"",P30-N30) -> 0 | R30: 46208 | S30: Y | T30: 46208 | X30: =IF(ISBLANK(W30),"",W30-R30) | Z30: =IF(ISBLANK(Y30),"",K30) | AA30: =IF(ISBLANK(Y30),"",Z30/K30) | AB30: =IF(ISBLANK(W30),"",Y30-W30) | AC30: =IF(ISBLANK(Y30),"",(K30-Z30)) | AD30: =IF(ISBLANK(Y30),"",Y30-N30) | AE30: Under Review
B31: 23 | C31: #23 | D31: JDH3-02-008-RWF-TS9-1-GEN-IPC-0892-00 | E31: 0 | F31: 9184809.6 | G31: =IF(ISBLANK(F31),"",-F31*$N$3) -> -918480.96 | H31: =IF(ISBLANK(F31),"",-F31*$N$4) -> 0 | I31: =SUM(F31:G31)*0.15 -> 1239949.3 | K31: =IF(ISBLANK(F31),"",SUM(F31:J31)) -> 9506277.9 | L31: 46204 | M31: 46234 | N31: 46235 | O31: Y | P31: 46235 | Q31: =IF(ISBLANK(P31),"",P31-N31) -> 0 | R31: 46238 | S31: Y | T31: 46238 | X31: =IF(ISBLANK(W31),"",W31-R31) | Z31: =IF(ISBLANK(Y31),"",K31) | AA31: =IF(ISBLANK(Y31),"",Z31/K31) | AB31: =IF(ISBLANK(W31),"",Y31-W31) | AC31: =IF(ISBLANK(Y31),"",(K31-Z31)) | AD31: =IF(ISBLANK(Y31),"",Y31-N31) | AE31: Under Review
B32: 24 | C32: #24 | D32: JDH3-02-008-RWF-TS9-1-GEN-IPC-0903-00 | E32: 0 | F32: 11762053 | G32: =IF(ISBLANK(F32),"",-F32*$N$3) -> -1176205.3 | H32: =IF(ISBLANK(F32),"",-F32*$N$4) -> 0 | I32: =SUM(F32:G32)*0.15 -> 1587877.1 | K32: =IF(ISBLANK(F32),"",SUM(F32:J32)) -> 12173724 | L32: 46235 | M32: 46265 | Q32: =IF(ISBLANK(P32),"",P32-N32) | X32: =IF(ISBLANK(W32),"",W32-R32) | Z32: =IF(ISBLANK(Y32),"",K32) | AA32: =IF(ISBLANK(Y32),"",Z32/K32) | AB32: =IF(ISBLANK(W32),"",Y32-W32) | AC32: =IF(ISBLANK(Y32),"",(K32-Z32)) | AD32: =IF(ISBLANK(Y32),"",Y32-N32)
B33: 25 | G33: =IF(ISBLANK(F33),"",-F33*$N$3) | H33: =IF(ISBLANK(F33),"",-F33*$N$4) | K33: =IF(ISBLANK(F33),"",SUM(F33:J33)) | Q33: =IF(ISBLANK(P33),"",P33-N33) | X33: =IF(ISBLANK(W33),"",W33-R33) | Z33: =IF(ISBLANK(Y33),"",K33) | AA33: =IF(ISBLANK(Y33),"",Z33/K33) | AB33: =IF(ISBLANK(W33),"",Y33-W33) | AC33: =IF(ISBLANK(Y33),"",(K33-Z33)) | AD33: =IF(ISBLANK(Y33),"",Y33-N33)
B34: 27 | G34: =IF(ISBLANK(F34),"",-F34*$N$3) | H34: =IF(ISBLANK(F34),"",-F34*$N$4) | K34: =IF(ISBLANK(F34),"",SUM(F34:J34)) | Q34: =IF(ISBLANK(P34),"",P34-N34) | X34: =IF(ISBLANK(W34),"",W34-R34) | Z34: =IF(ISBLANK(Y34),"",K34) | AA34: =IF(ISBLANK(Y34),"",Z34/K34) | AB34: =IF(ISBLANK(W34),"",Y34-W34) | AC34: =IF(ISBLANK(Y34),"",(K34-Z34)) | AD34: =IF(ISBLANK(Y34),"",Y34-N34)
B35: 28 | G35: =IF(ISBLANK(F35),"",-F35*$N$3) | H35: =IF(ISBLANK(F35),"",-F35*$N$4) | K35: =IF(ISBLANK(F35),"",SUM(F35:J35)) | Q35: =IF(ISBLANK(P35),"",P35-N35) | X35: =IF(ISBLANK(W35),"",W35-R35) | Z35: =IF(ISBLANK(Y35),"",K35) | AA35: =IF(ISBLANK(Y35),"",Z35/K35) | AB35: =IF(ISBLANK(W35),"",Y35-W35) | AC35: =IF(ISBLANK(Y35),"",(K35-Z35)) | AD35: =IF(ISBLANK(Y35),"",Y35-N35)
B36: 29 | G36: =IF(ISBLANK(F36),"",-F36*$N$3) | H36: =IF(ISBLANK(F36),"",-F36*$N$4) | K36: =IF(ISBLANK(F36),"",SUM(F36:J36)) | Q36: =IF(ISBLANK(P36),"",P36-N36) | X36: =IF(ISBLANK(W36),"",W36-R36) | Z36: =IF(ISBLANK(Y36),"",K36) | AA36: =IF(ISBLANK(Y36),"",Z36/K36) | AB36: =IF(ISBLANK(W36),"",Y36-W36) | AC36: =IF(ISBLANK(Y36),"",(K36-Z36)) | AD36: =IF(ISBLANK(Y36),"",Y36-N36)
B37: 30 | G37: =IF(ISBLANK(F37),"",-F37*$N$3) | H37: =IF(ISBLANK(F37),"",-F37*$N$4) | K37: =IF(ISBLANK(F37),"",SUM(F37:J37)) | Q37: =IF(ISBLANK(P37),"",P37-N37) | X37: =IF(ISBLANK(W37),"",W37-R37) | Z37: =IF(ISBLANK(Y37),"",K37) | AA37: =IF(ISBLANK(Y37),"",Z37/K37) | AB37: =IF(ISBLANK(W37),"",Y37-W37) | AC37: =IF(ISBLANK(Y37),"",(K37-Z37)) | AD37: =IF(ISBLANK(Y37),"",Y37-N37)
B38: 31 | G38: =IF(ISBLANK(F38),"",-F38*$N$3) | H38: =IF(ISBLANK(F38),"",-F38*$N$4) | K38: =IF(ISBLANK(F38),"",SUM(F38:J38)) | Q38: =IF(ISBLANK(P38),"",P38-N38) | X38: =IF(ISBLANK(W38),"",W38-R38) | Z38: =IF(ISBLANK(Y38),"",K38) | AA38: =IF(ISBLANK(Y38),"",Z38/K38) | AB38: =IF(ISBLANK(W38),"",Y38-W38) | AC38: =IF(ISBLANK(Y38),"",(K38-Z38)) | AD38: =IF(ISBLANK(Y38),"",Y38-N38)
B39: 32 | G39: =IF(ISBLANK(F39),"",-F39*$N$3) | H39: =IF(ISBLANK(F39),"",-F39*$N$4) | K39: =IF(ISBLANK(F39),"",SUM(F39:J39)) | Q39: =IF(ISBLANK(P39),"",P39-N39) | X39: =IF(ISBLANK(W39),"",W39-R39) | Z39: =IF(ISBLANK(Y39),"",K39) | AA39: =IF(ISBLANK(Y39),"",Z39/K39) | AB39: =IF(ISBLANK(W39),"",Y39-W39) | AC39: =IF(ISBLANK(Y39),"",(K39-Z39)) | AD39: =IF(ISBLANK(Y39),"",Y39-N39)
B40: 33 | G40: =IF(ISBLANK(F40),"",-F40*$N$3) | H40: =IF(ISBLANK(F40),"",-F40*$N$4) | K40: =IF(ISBLANK(F40),"",SUM(F40:J40)) | Q40: =IF(ISBLANK(P40),"",P40-N40) | X40: =IF(ISBLANK(W40),"",W40-R40) | Z40: =IF(ISBLANK(Y40),"",K40) | AA40: =IF(ISBLANK(Y40),"",Z40/K40) | AB40: =IF(ISBLANK(W40),"",Y40-W40) | AC40: =IF(ISBLANK(Y40),"",(K40-Z40)) | AD40: =IF(ISBLANK(Y40),"",Y40-N40)
B41: 34 | G41: =IF(ISBLANK(F41),"",-F41*$N$3) | H41: =IF(ISBLANK(F41),"",-F41*$N$4) | K41: =IF(ISBLANK(F41),"",SUM(F41:J41)) | Q41: =IF(ISBLANK(P41),"",P41-N41) | X41: =IF(ISBLANK(W41),"",W41-R41) | Z41: =IF(ISBLANK(Y41),"",K41) | AA41: =IF(ISBLANK(Y41),"",Z41/K41) | AB41: =IF(ISBLANK(W41),"",Y41-W41) | AC41: =IF(ISBLANK(Y41),"",(K41-Z41)) | AD41: =IF(ISBLANK(Y41),"",Y41-N41)
B42: 35 | G42: =IF(ISBLANK(F42),"",-F42*$N$3) | H42: =IF(ISBLANK(F42),"",-F42*$N$4) | K42: =IF(ISBLANK(F42),"",SUM(F42:J42)) | Q42: =IF(ISBLANK(P42),"",P42-N42) | X42: =IF(ISBLANK(W42),"",W42-R42) | Z42: =IF(ISBLANK(Y42),"",K42) | AA42: =IF(ISBLANK(Y42),"",Z42/K42) | AB42: =IF(ISBLANK(W42),"",Y42-W42) | AC42: =IF(ISBLANK(Y42),"",(K42-Z42)) | AD42: =IF(ISBLANK(Y42),"",Y42-N42)
B43: 36 | G43: =IF(ISBLANK(F43),"",-F43*$N$3) | H43: =IF(ISBLANK(F43),"",-F43*$N$4) | K43: =IF(ISBLANK(F43),"",SUM(F43:J43)) | Q43: =IF(ISBLANK(P43),"",P43-N43) | X43: =IF(ISBLANK(W43),"",W43-R43) | Z43: =IF(ISBLANK(Y43),"",K43) | AA43: =IF(ISBLANK(Y43),"",Z43/K43) | AB43: =IF(ISBLANK(W43),"",Y43-W43) | AC43: =IF(ISBLANK(Y43),"",(K43-Z43)) | AD43: =IF(ISBLANK(Y43),"",Y43-N43)
B44: 37 | G44: =IF(ISBLANK(F44),"",-F44*$N$3) | H44: =IF(ISBLANK(F44),"",-F44*$N$4) | K44: =IF(ISBLANK(F44),"",SUM(F44:J44)) | Q44: =IF(ISBLANK(P44),"",P44-N44) | X44: =IF(ISBLANK(W44),"",W44-R44) | Z44: =IF(ISBLANK(Y44),"",K44) | AA44: =IF(ISBLANK(Y44),"",Z44/K44) | AB44: =IF(ISBLANK(W44),"",Y44-W44) | AC44: =IF(ISBLANK(Y44),"",(K44-Z44)) | AD44: =IF(ISBLANK(Y44),"",Y44-N44)
... B46: 39 | G46: =IF(ISBLANK(F46),"",-F46*$N$3) | H46: =IF(ISBLANK(F46),"",-F46*$N$4) | K46: =IF(ISBLANK(F46),"",SUM(F46:J46)) | Q46: =IF(ISBLANK(P46),"",P46-N46) | X46: =IF(ISBLANK(W46),"",W46-R46) | Z46: =IF(ISBLANK(Y46),"",K46) | AA46: =IF(ISBLANK(Y46),"",Z46/K46) | AB46: =IF(ISBLANK(W46),"",Y46-W46) | AC46: =IF(ISBLANK(Y46),"",(K46-Z46)) | AD46: =IF(ISBLANK(Y46),"",Y46-N46)
B47: 40 | G47: =IF(ISBLANK(F47),"",-F47*$N$3) | H47: =IF(ISBLANK(F47),"",-F47*$N$4) | Z47: =IF(ISBLANK(Y47),"",K47) | AA47: =IF(ISBLANK(Y47),"",Z47/K47) | AB47: =IF(ISBLANK(W47),"",Y47-W47) | AC47: =IF(ISBLANK(Y47),"",(K47-Z47))
B48: 41 | G48: =IF(ISBLANK(F48),"",-F48*$N$3) | H48: =IF(ISBLANK(F48),"",-F48*$N$4) | Z48: =IF(ISBLANK(Y48),"",K48) | AA48: =IF(ISBLANK(Y48),"",Z48/K48) | AB48: =IF(ISBLANK(W48),"",Y48-W48) | AC48: =IF(ISBLANK(Y48),"",(K48-Z48))
B49: 42 | G49: =IF(ISBLANK(F49),"",-F49*$N$3) | H49: =IF(ISBLANK(F49),"",-F49*$N$4) | Z49: =IF(ISBLANK(Y49),"",K49) | AA49: =IF(ISBLANK(Y49),"",Z49/K49) | AB49: =IF(ISBLANK(W49),"",Y49-W49) | AC49: =IF(ISBLANK(Y49),"",(K49-Z49))
B50: 43 | G50: =IF(ISBLANK(F50),"",-F50*$N$3) | H50: =IF(ISBLANK(F50),"",-F50*$N$4) | Z50: =IF(ISBLANK(Y50),"",K50) | AA50: =IF(ISBLANK(Y50),"",Z50/K50) | AB50: =IF(ISBLANK(W50),"",Y50-W50) | AC50: =IF(ISBLANK(Y50),"",(K50-Z50))
B51: 44 | G51: =IF(ISBLANK(F51),"",-F51*$N$3) | H51: =IF(ISBLANK(F51),"",-F51*$N$4) | Z51: =IF(ISBLANK(Y51),"",K51) | AA51: =IF(ISBLANK(Y51),"",Z51/K51) | AB51: =IF(ISBLANK(W51),"",Y51-W51) | AC51: =IF(ISBLANK(Y51),"",(K51-Z51))
B52: 45 | G52: =IF(ISBLANK(F52),"",-F52*$N$3) | H52: =IF(ISBLANK(F52),"",-F52*$N$4) | Z52: =IF(ISBLANK(Y52),"",K52) | AA52: =IF(ISBLANK(Y52),"",Z52/K52) | AB52: =IF(ISBLANK(W52),"",Y52-W52) | AC52: =IF(ISBLANK(Y52),"",(K52-Z52))
B53: 46 | G53: =IF(ISBLANK(F53),"",-F53*$N$3) | H53: =IF(ISBLANK(F53),"",-F53*$N$4) | Z53: =IF(ISBLANK(Y53),"",K53) | AA53: =IF(ISBLANK(Y53),"",Z53/K53) | AB53: =IF(ISBLANK(W53),"",Y53-W53) | AC53: =IF(ISBLANK(Y53),"",(K53-Z53))
B54: 47 | G54: =IF(ISBLANK(F54),"",-F54*$N$3) | H54: =IF(ISBLANK(F54),"",-F54*$N$4) | Z54: =IF(ISBLANK(Y54),"",K54) | AA54: =IF(ISBLANK(Y54),"",Z54/K54) | AB54: =IF(ISBLANK(W54),"",Y54-W54) | AC54: =IF(ISBLANK(Y54),"",(K54-Z54))
B55: 48 | G55: =IF(ISBLANK(F55),"",-F55*$N$3) | H55: =IF(ISBLANK(F55),"",-F55*$N$4) | Z55: =IF(ISBLANK(Y55),"",K55) | AA55: =IF(ISBLANK(Y55),"",Z55/K55) | AB55: =IF(ISBLANK(W55),"",Y55-W55) | AC55: =IF(ISBLANK(Y55),"",(K55-Z55))
B56: 49 | G56: =IF(ISBLANK(F56),"",-F56*$N$3) | H56: =IF(ISBLANK(F56),"",-F56*$N$4) | Z56: =IF(ISBLANK(Y56),"",K56) | AA56: =IF(ISBLANK(Y56),"",Z56/K56) | AB56: =IF(ISBLANK(W56),"",Y56-W56) | AC56: =IF(ISBLANK(Y56),"",(K56-Z56))
B57: 50 | G57: =IF(ISBLANK(F57),"",-F57*$N$3) | H57: =IF(ISBLANK(F57),"",-F57*$N$4) | Z57: =IF(ISBLANK(Y57),"",K57) | AA57: =IF(ISBLANK(Y57),"",Z57/K57) | AB57: =IF(ISBLANK(W57),"",Y57-W57) | AC57: =IF(ISBLANK(Y57),"",(K57-Z57))
B58: 51 | G58: =IF(ISBLANK(F58),"",-F58*$N$3) | H58: =IF(ISBLANK(F58),"",-F58*$N$4) | Z58: =IF(ISBLANK(Y58),"",K58) | AA58: =IF(ISBLANK(Y58),"",Z58/K58) | AB58: =IF(ISBLANK(W58),"",Y58-W58) | AC58: =IF(ISBLANK(Y58),"",(K58-Z58))
E59: TOTAL | F59: =SUM(F9:F58) -> 2.5021413e+08 | G59: =SUM(G9:G58) -> -25021413 | H59: =SUM(H9:H58) -> 0 | J59: =SUM(J9:J58) -> -260000 | K59: =SUM(K9:K58) -> 2.5871163e+08 | Q59: =IF(ISBLANK(P59),"",P59-N59) | X59: =IF(ISBLANK(W59),"",W59-R59) | Z59: =SUM(Z9:Z58) -> 0 | AB59: =IF(ISBLANK(Y59),"",Y59-W59) | AC59: =SUM(AC9:AC58) -> 0 | AD59: =IF(ISBLANK(Y59),"",Y59-N59)

Sheet Invoice Ammount FIR
A1: Weekly Report No. | B1: Date Of Report | C1: Time Intervals | D1: Cumulative | E1: Total Amount % (as Per Fir) | F1: 3.1974488e+08
A2: =ROW()-1 -> 1 | B2: 45551 | C2: 0 | D2: =C2 -> 0 | E2: =D2/$F$1 -> 0
A3: =ROW()-1 -> 2 | B3: 45558 | C3: 0 | D3: =C3+D2 -> 0 | E3: =D3/$F$1 -> 0
A4: =ROW()-1 -> 3 | B4: 45565 | C4: 0 | D4: =C4+D3 -> 0 | E4: =D4/$F$1 -> 0
A5: =ROW()-1 -> 4 | B5: 45572 | C5: 0 | D5: =C5+D4 -> 0 | E5: =D5/$F$1 -> 0
A6: =ROW()-1 -> 5 | B6: 45579 | C6: 1103925.1 | D6: =C6+D5 -> 1103925.1 | E6: =D6/$F$1 -> 0.0034525185
A7: =ROW()-1 -> 6 | B7: 45586 | C7: 1010342.3 | D7: =C7+D6 -> 2114267.4 | E7: =+D7/$F$1 -> 0.0066123574
A8: =ROW()-1 -> 7 | B8: 45593 | C8: 1519502.3 | D8: =C8+D7 -> 3633769.7 | E8: =+D8/$F$1 -> 0.011364591
A9: =ROW()-1 -> 8 | B9: 45600 | C9: 1370507.7 | D9: =C9+D8 -> 5004277.4 | E9: =+D9/$F$1 -> 0.015650845
A10: =ROW()-1 -> 9 | B10: 45607 | C10: 1097333.4 | D10: =C10+D9 -> 6101610.7 | E10: =+D10/$F$1 -> 0.019082747
A11: =ROW()-1 -> 10 | B11: 45614 | C11: 0 | D11: =C11+D10 -> 6101610.7 | E11: =+D11/$F$1 -> 0.019082747
A12: =ROW()-1 -> 11 | B12: 45621 | C12: 1143192.9 | D12: =C12+D11 -> 7244803.6 | E12: =+D12/$F$1 -> 0.022658076
A13: =ROW()-1 -> 12 | B13: 45628 | C13: 827265.67 | D13: =C13+D12 -> 8072069.3 | E13: =+D13/$F$1 -> 0.025245344
A14: =ROW()-1 -> 13 | B14: 45635 | C14: 1646697.4 | D14: =C14+D13 -> 9718766.7 | E14: =+D14/$F$1 -> 0.030395379
A15: =ROW()-1 -> 14 | B15: 45642 | C15: 1135896.9 | D15: =C15+D14 -> 10854664 | E15: =+D15/$F$1 -> 0.033947889
A16: =ROW()-1 -> 15 | B16: 45649 | C16: 1092701.6 | D16: =C16+D15 -> 11947365 | E16: =+D16/$F$1 -> 0.037365306
A17: =ROW()-1 -> 16 | B17: 45656 | C17: 2387944.3 | D17: =C17+D16 -> 14335309 | E17: =+D17/$F$1 -> 0.044833586
A18: =ROW()-1 -> 17 | B18: 45663 | C18: 1689182.2 | D18: =C18+D17 -> 16024492 | E18: =+D18/$F$1 -> 0.050116492
... A106: =ROW()-1 -> 105 | B106: 46306 | C106: 563019.3 | D106: =C106+D105 -> 2.777879e+08 | E106: =+D106/$F$1 -> 0.86877982

Sheet CCO
A1: CONTRACT CHANGE ORDER (CCO)
A2: CCO No. | B2: Date Added | C2: Description of Change | D2: Status | E2: SR | F2: Sch Impact (Months) | G2: Date Approved | H2: Duration (days)
A3: 1 | B3: 45854 | C3: Revised BOQ | D3: Completed | E3: - | F3: - | G3: 45861 | H3: -
A4: 2 | B4: 46208 | C4: EOT Approval | D4: Completed | E4: - | F4: 2 | G4: 46202 | H4: -

Sheet Procurement
A1: Sr. NO. | B1: Project ID | C1: ACT # in P6 | D1: Item Description | E1: Discipline | F1: (Long\Short) Lead Items | G1: BOQ. No. | H1: Unit | I1: Quantity | J1: Proc. Qty | K1: Required P.O Date | L1: Date of Pur. Order Issued | M1: Purchase Order No. | N1: Supplier | O1: Supplier Phone | P1: Method of Shipping | Q1: Required on Job | R1: E.D.A. to Site | S1: A.D.A. to Site | T1: Lead Time | U1: Approval Status | V1: The Impact (BOQ Cost) | W1: Delivered Qty | X1: Completion Rate | Y1: Remarks
A2: 1 | B2: JDH3-02-008 | C2: JDH3-02-008RRDPR733 | D2: Pavement Materials - Retroreflective Thermoplastic White Traffic lines- Retroreflective Thermoplastic Yellow, Traffic lines | E2: Road Marking | F2: Short Lead Iteam | G2: B1.32 17 23.01/B1.32 17 23.02 | H2: m² | I2: =15680+3350 -> 19030 | K2: 45717.708 | P2: Land | Q2: 45737.708 | V2: 1036754.4 | X2: =W2/I2 -> 0 | Y2: to be descoped. Needs to be revised as per revised BOQ
A3: 2 | B3: JDH3-02-008 | C3: JDH3-02-008RRDPR733 | D3: Pavement Materials -Straight Arrow -(Right/left ) Arrow- Right-left Arrow-Straight-Right Arrow- Straight-Left Arrow | E3: Road Marking | F3: Short Lead Iteam | G3: B1.32 17 23.03/B1.32 17 23.04//B1.32 17 23.05//B1.32 17 23.06//B1.32 17 23.07 | H3: nr | I3: 948.5 | K3: 45717.708 | P3: Land | Q3: 45737.708 | V3: 105852.6 | X3: =W3/I3 -> 0 | Y3: to be descoped. Needs to be revised as per revised BOQ
A4: 3 | B4: JDH3-02-008 | C4: JDH3-02-008RRDPR733 | D4: TRAFFIC SIGNAGE | E4: Signage | F4: Short Lead Iteam | G4: B1.10 14 53.01 / B1.10 14 53.02 | H4: unit | I4: 1408 | K4: 45717.708 | P4: Land | Q4: 45737.708 | V4: 2793028 | X4: =W4/I4 -> 0 | Y4: to be descoped. Needs to be revised as per revised BOQ
A5: 4 | B5: JDH3-02-008 | C5: JDH3-02-008RRDPR732 | D5: PRECAST CONCRETE CURB | E5: Kerbstone | F5: Short Lead Iteam | G5: B1.32 14 13.01/B1.32 14 13.02/B1.32 14 13.03 | H5: m | I5: 313864 | J5: =32820+24210 -> 57030 | K5: 45710.708 | L5: 45594 | M5: 24105611 | N5: Taiba Al Khair Development. Co | O5: +966 126946407 | P5: Land | Q5: 45730.708 | S5: 45607 | U5: Material Approved | V5: 20387468 | W5: 15084 | X5: =W5/I5 -> 0.048059032
A6: 5 | B6: JDH3-02-008 | C6: JDH3-02-008RRDPR732 | D6: PRECAST INTERLOCKING BLOCK PAVERS | E6: Interlock | F6: Short Lead Iteam | G6: B1.32 14 13.13.01 | H6: m² | I6: 59537.282 | J6: 25990 | K6: 45710.708 | L6: 45594 | M6: 24105611 | N6: Taiba Al Khair Development. Co | O6: +966 126946407 | P6: Land | Q6: 45730.708 | S6: 45607 | U6: Material Approved | V6: 3764542.3 | W6: 4088.24 | X6: =W6/I6 -> 0.06866689
A7: 6 | B7: JDH3-02-008 | C7: JDH3-02-008RRDPR731 | D7: EARTHWORKS AND SITE GRADING-300mm thick Subgrade AGGREGATE BASE COURSE-300mm thick Aggregate base course BITUMINOUS CONSTRUCTION-Bituminous concrete wearing course, (Grading I - Class A), including tack coat (RC2) | E7: Road work | F7: Short Lead Iteam | G7: B1.31 22 00.01/B1.32 11 23.01/B1.32 11 26.01 | H7: m3 | I7: 9021 | J7: 2520 | K7: 45703.708 | N7: Masharaf EL Torq | P7: Land | Q7: 45723.708 | U7: Material Approved | V7: 1688143.5 | W7: 2520 | X7: =W7/I7 -> 0.27934819
A8: 7 | B8: JDH3-02-008 | C8: JDH3-02-008RRDPR730 | D8: ASPHALT WEARING COURSE -Bituminous concrete wearing course, (Grading I - Class A), including tack coat (RC2) | E8: Road work | F8: Short Lead Iteam | G8: B1.32 12 16.01 | H8: m3 | I8: 63689 | K8: 45696.708 | N8: خلاطة الرواف | P8: Land | Q8: 45716.708 | V8: 37237048 | X8: =W8/I8 -> 0
A9: 8 | B9: JDH3-02-008 | C9: JDH3-02-008RELPR714 | D9: MEDIUM VOLTAGE CABLES DUCT BANKS | E9: MV | F9: Short Lead Iteam | G9: B2.33 71 19.01 | H9: m | I9: 950 | K9: 45670.708 | P9: Land | Q9: 45760.708 | V9: 383534 | X9: =W9/I9 -> 0 | Y9: to be descoped. Needs to be revised as per revised BOQ
A10: 9 | B10: JDH3-02-008 | C10: JDH3-02-008RELPR713 | D10: LOW VOLTAGE CABLES | E10: LV | F10: Short Lead Iteam | G10: B2.26 05 19.01/B2.26 05 19.02/B2.26 05 19.03/B2.26 05 19.04/B2.26 05 19.05/B2.26 05 19.06 / B2.26 05 19.07/B2.26 05 19.08 | H10: m | I10: 26353 | J10: 106000 | K10: 45684.708 | L10: 45635 | M10: 24106558 | N10: Jeddah cabels | O10: +9662 6644350 | P10: Land | Q10: 45774.708 | R10: 45787 | T10: =+R10-K10 -> 102.29167 | U10: Material Approved | V10: 1809503.3 | W10: 38238 | X10: =W10/J10 -> 0.36073585
A11: 10 | B11: JDH3-02-008 | C11: JDH3-02-008RELPR715 | D11: MEDIUM VOLTAGE CABLES - 3 Core AL . Cable 13.8 kV 3Cx500 mm² AL./XLPE /PVC. Unarmored | E11: MV | F11: Long Lead Iteam | G11: B2.26.05.13.16.01 | H11: m | I11: 30720 | K11: 45677.708 | P11: Land | Q11: 45767.708 | V11: 6574694.4 | X11: =W11/I11 -> 0 | Y11: to be descoped. Needs to be revised as per revised BOQ
A12: 11 | B12: JDH3-02-008 | C12: JDH3-02-008RELPR715 | D12: MEDIUM VOLTAGE CABLES -Straight joints cables for 13.8 kv 3Cx 500 mm², Al /XLPE/LLDPE -Cable Termination for 13.8 kv 3Cx 500 mm², Al /XLPE/LLDPE | E12: MV | F12: Long Lead Iteam | G12: B2.26.05.13.16.02/B2.26.05.13.16.03 | H12: unit | I12: 78 | K12: 45677.708 | P12: Land | Q12: 45767.708 | V12: 246611.04 | X12: =W12/I12 -> 0 | Y12: to be descoped. Needs to be revised as per revised BOQ
A13: 12 | B13: JDH3-02-008 | C13: JDH3-02-008RELPR712 | D13: MEDIUM VOLTAGE SWITCHGEARS - Normally Open Point (R M U) 13.8 kv for Outdoor type according to the Saudi Electric Company specifications and requirements | E13: MV | F13: Long Lead Iteam | G13: B2.26 13 00.01 | H13: unit | I13: 2 | K13: 45684.708 | P13: Land | Q13: 45774.708 | V13: 106864.94 | X13: =W13/I13 -> 0 | Y13: to be descoped. Needs to be revised as per revised BOQ
A14: 13 | B14: JDH3-02-008 | C14: JDH3-02-008RSLPR725 | D14: ROAD CROSSING DUCTS | E14: Ducts | F14: Short Lead Iteam | G14: B2.33 71 19.01.SL/B2.33 71 19.02/B2.33 71 19.03 | H14: m | I14: 580 | K14: 45684.708 | N14: National Kham Plastic Factory | P14: Land | Q14: 45704.708 | U14: Material Approved | V14: 100067.1 | X14: =W14/I14 -> 0
A15: 14 | B15: JDH3-02-008 | C15: JDH3-02-008RSLPR718 | D15: DRAWPITS | E15: Street Lighting | F15: Long Lead Iteam | G15: B2.33 71 19.13.01/B2.33 71 19.13.02/B2.33 71 19.13.03 | H15: Unit | I15: 52 | K15: 45684.708 | N15: FALCOM | P15: Land | Q15: 45774.708 | U15: Material Approved | V15: 12836.44 | X15: =W15/I15 -> 0
A16: 15 | B16: JDH3-02-008 | C16: JDH3-02-008RSLPR719 | D16: LIGHTING POLES | E16: Street Lighting | F16: Long Lead Iteam | G16: B2.26.56.19.01/ B2.26 56 19.02 | H16: Unit | I16: 265 | K16: 45677.708 | L16: 45782 | N16: Alyamama & Bantain | P16: Land | Q16: 45767.708 | R16: 45807 | T16: =+R16-K16 -> 129.29167 | U16: Material Approved | V16: 1417732.6 | X16: =W16/I16 -> 0
A17: 16 | B17: JDH3-02-008 | C17: JDH3-02-008RSLPR722 | D17: STREET LIGHTING LUMINAIRE | E17: Street Lighting | F17: Long Lead Iteam | G17: B2.26.56.19.01/B2.26.56.19.02/B2.26.56.19.03 | H17: Unit | I17: 370 | K17: 45663.708 | N17: SAUDI LIGHTING PHILIPS | P17: Land | Q17: 45753.708 | U17: Material Approved | V17: 401054 | X17: =W17/I17 -> 0
A18: 17 | B18: JDH3-02-008 | C18: JDH3-02-008RSLPR717 | D18: STREET LIGHTING SUB-STATION | E18: Street Lighting | F18: Long Lead Iteam | G18: B2.26 11 16.02 | H18: Unit | I18: 3 | K18: 45677.708 | P18: Land | Q18: 45767.708 | V18: 230183.31 | X18: =W18/I18 -> 0 | Y18: to be descoped. Needs to be revised as per revised BOQ
A19: 18 | B19: JDH3-02-008 | C19: JDH3-02-008RSLPR723 | D19: Ring Main Unit RMU, 13.8KV, According to the specifications and standards of SEC | E19: Street Lighting | F19: Long Lead Iteam | G19: B2.26 11 16.04 | H19: Unit | I19: 3 | K19: 45670.708 | P19: Land | Q19: 45760.708 | V19: 53432.47 | X19: =W19/I19 -> 0 | Y19: to be descoped. Needs to be revised as per revised BOQ
A20: 19 | B20: JDH3-02-008 | C20: JDH3-02-008RSLPR720 | D20: EARTHING SYSTEM | E20: Street Lighting | F20: Long Lead Iteam | G20: B2.26 05 26.01 | H20: Unit | I20: 20 | K20: 45656.708 | N20: Furse- Tabark Company | P20: Land | Q20: 45746.708 | U20: Material Approved | V20: 11284.8 | X20: =W20/I20 -> 0
A21: 20 | B21: JDH3-02-008 | C21: JDH3-02-008RSLPR721 | D21: Lighting panels | E21: Street Lighting | F21: Long Lead Iteam | G21: B2.26 24 16.01/B2.26 24 16.02 | H21: Unit | I21: 6 | K21: 45656.708 | P21: Land | Q21: 45746.708 | V21: 72465.81 | X21: =W21/I21 -> 0
A22: 21 | B22: JDH3-02-008 | C22: JDH3-02-008RTCPR727 | D22: TELECOMMUNICATIONS-DUCTS | E22: Ducts | F22: Short Lead Iteam | G22: B2.33 71 19.02.TEL | H22: m | I22: 8100 | K22: 45691.708 | N22: Alwasail Industrial Co | P22: Land | Q22: 45711.708 | U22: Material Approved | V22: 827415 | X22: =W22/I22 -> 0
A23: 22 | B23: JDH3-02-008 | C23: JDH3-02-008RTCPR728 | D23: TELECOMMUNICATIONS-MANHOLES | E23: Telecommunication | F23: Short Lead Iteam | G23: B2.33.71.19.13.01 | H23: nr | I23: 93 | K23: 45698.708 | N23: FALCOM | P23: Land | Q23: 45718.708 | U23: Material Approved | V23: 411654.48 | X23: =W23/I23 -> 0
A24: 23 | B24: JDH3-02-008 | C24: JDH3-02-008RWTPR697 | D24: PIPEWORK - VALVES | E24: Potable water | F24: Short Lead Iteam | G24: B3.33 14 19.01/B3.33 14 19.02/B3.33 14 19.03/B3.33 14 19.05/B3.33 14 19.06/B3.33 14 19.08 | H24: nr | I24: =250 -> 250 | J24: 178 | K24: 45670.708 | L24: 45592 | M24: 24105567 | N24: SPS | O24: +966504401239 | P24: Land | Q24: 45760.708 | S24: 45597 | U24: Material Approved | V24: 3767041.5 | W24: 178 | X24: =W24/I24 -> 0.712
A25: 24 | B25: JDH3-02-008 | C25: JDH3-02-008RWTPR694 | D25: POTABLE WATER -PIPEWORK-PIPES- High Density Polyethylene pipes PE 100 SDR 11 (PN 16 Bars) | E25: Potable water | F25: Short Lead Iteam | G25: B3.33 14 13.01/B3.33 14 13.02/B3.33 14 13.03/B3.33 14 13.04/B3.33 14 13.05 | H25: m | I25: 23742 | J25: 5520 | K25: 45656.708 | L25: 45621 | M25: 24106224 | N25: sps MUNIF | O25: +966504401239 +966507779468 | P25: Land | Q25: 45746.708 | S25: 45627 | U25: Material Approved | V25: 5352889.1 | W25: 5520 | X25: =W25/I25 -> 0.23249937
A26: 25 | B26: JDH3-02-008 | C26: JDH3-02-008RWTPR690 | D26: POTABLE WATER - PIPEWORK-Valve chambers - Civil Works | E26: Potable water | F26: Short Lead Iteam | G26: B3.33 14 13.011/B3.33 14 13.011/B3.33 14 13.10 | H26: nr | I26: 11 | K26: 45656.708 | N26: العربية الراجحي | P26: Land | Q26: 45746.708 | V26: 182271.65 | X26: =W26/I26 -> 0 | Y26: to be constructed at site
A27: 26 | B27: JDH3-02-008 | C27: JDH3-02-008RSEPR705 | D27: TSE NETWORK -High Density Polyethylene pipes PE 100 SDR 11 ( PN 16 Bars) | E27: TSE | F27: Short Lead Iteam | G27: B4.33 31 00.01/B4.33 31 00.02/B4.33 31 00.03/B4.33 31 00.04/B4.33 31 00.05/B4.33 31 00.06/B4.33 31 00.07/B4.33 31 00.08/B4.33 31 00.09/B4.33 31 00.10B4.33 31 00.11/B4.33 31 00.12/B4.33 31 00.13/B4.33 31 00.14/B4.33 31 00.15/B4.33 31 00.16/B4.33 31 00.17/B4.33 31 00.18 | H27: m | I27: 69985 | J27: 57408 | K27: 45586.708 | L27: 25-11-24 & 11-12-24 | M27: 24106224 & 24106620 | N27: sps MUNIF/ Al Wasail Industrial Company | O27: +966504401239 +966507779468 | P27: Land | Q27: 45676.708 | S27: 45627 | U27: Material Approved | V27: 37305017 | W27: 38800 | X27: =W27/I27 -> 0.55440452
A28: 27 | B28: JDH3-02-008 | C28: JDH3-02-008RSEPR704 | D28: TSE NETWORK -Glass Reinforced Plastic (GRP) Pipe | E28: TSE | F28: Short Lead Iteam | G28: B4.33 05 36.01/B4.33 05 36.02/B4.33 05 36.03/B4.33 05 36.04/B4.33 05 36.05/B4.33 05 36.06/B4.33 05 36.07 | H28: m | I28: 998 | K28: 45586.708 | N28: T- NAGADI | O28: +966564510408 | P28: Land | Q28: 45606.708 | U28: Material Approved | V28: 1705859.3 | X28: =W28/I28 -> 0
A29: 28 | B29: JDH3-02-008 | C29: JDH3-02-008RSEPR707 | D29: TSE NETWORK - PIPEWORK - VALVES | E29: TSE | F29: Long Lead Iteam | G29: B4.33 14 19.01/B4.33 14 19.02/B4.33 14 19.03/B4.33 14 19.04/B4.33 14 19.05/B4.33 14 19.06/B4.33 14 19.07/B4.33 14 19.08/B4.33 14 19.09/B4.33 14 19.15/B4.33 14 19.16/B4.33 14 19.17 | H29: nr | I29: 967 | K29: 45586.458 | N29: SPS | O29: +966504401239 | P29: Land | Q29: 45676.458 | U29: Material Approved | V29: 7069890.7 | X29: =W29/I29 -> 0
A30: 29 | B30: JDH3-02-008 | C30: JDH3-02-008RSEPR701 | D30: TSE NETWORK -PIPEWORK-Valve chambers - Civil Works | E30: TSE | F30: Short Lead Iteam | G30: B4.33 14 13.01/B4.33 14 13.02/B4.33 14 13.03/B4.33 14 13.06/B4.33 14 13.07/B4.33 14 13.08/B4.33 14 13.10/B4.33 14 13.11/B4.33 14 13.12 | H30: nr | I30: 231 | K30: 45586.708 | N30: العربية الراجحي | P30: Land | Q30: 45606.708 | V30: 2976403 | X30: =W30/I30 -> 0 | Y30: to be constructed at site
A31: 30 | B31: JDH3-02-008 | C31: JDH3-02-008RSSPR677 | D31: SEWERAGE NETWORK-Glass Reinforced Plastic (GRP): SN 5000 up to depth 3.5 m SN 10000 depth more than 3.5 m | E31: Sewer drainage | F31: Short Lead Iteam | G31: B5.33 31 00.03/B5.33 31 00.04/B5.33 31 00.05/B5.33 31 00.10/B5.33 31 00.11/B5.33 31 00.12/B5.33 31 00.13 | H31: m | I31: 29561 | J31: 10548 | K31: 45564.708 | L31: 45585 | M31: 3100000503 & 24105376 | N31: T- NAGADI | O31: +966564510408 | P31: Land | Q31: 45584.708 | S31: 45619 | U31: Material Approved | V31: 13012996 | W31: 10548 | X31: =W31/I31 -> 0.35682149
