Workbook
Name _____________ccr1: {#N/A,#N/A,TRUE,"Cover";#N/A,#N/A,TRUE,"Conts";#N/A,#N/A,TRUE,"VOS";#N/A,#N/A,TRUE,"Warrington";#N/A,#N/A,TRUE,"Widnes"}
Name _____________ccr1: {#N/A,#N/A,TRUE,"Cover";#N/A,#N/A,TRUE,"Conts";#N/A,#N/A,TRUE,"VOS";#N/A,#N/A,TRUE,"Warrington";#N/A,#N/A,TRUE,"Widnes"}
Name ___________ccr1: {#N/A,#N/A,TRUE,"Cover";#N/A,#N/A,TRUE,"Conts";#N/A,#N/A,TRUE,"VOS";#N/A,#N/A,TRUE,"Warrington";#N/A,#N/A,TRUE,"Widnes"}
Name ___________ccr1: {#N/A,#N/A,TRUE,"Cover";#N/A,#N/A,TRUE,"Conts";#N/A,#N/A,TRUE,"VOS";#N/A,#N/A,TRUE,"Warrington";#N/A,#N/A,TRUE,"Widnes"}
Name __________ccr1: {#N/A,#N/A,TRUE,"Cover";#N/A,#N/A,TRUE,"Conts";#N/A,#N/A,TRUE,"VOS";#N/A,#N/A,TRUE,"Warrington";#N/A,#N/A,TRUE,"Widnes"}
Name __________ccr1: {#N/A,#N/A,TRUE,"Cover";#N/A,#N/A,TRUE,"Conts";#N/A,#N/A,TRUE,"VOS";#N/A,#N/A,TRUE,"Warrington";#N/A,#N/A,TRUE,"Widnes"}
Name _________ccr1: {#N/A,#N/A,TRUE,"Cover";#N/A,#N/A,TRUE,"Conts";#N/A,#N/A,TRUE,"VOS";#N/A,#N/A,TRUE,"Warrington";#N/A,#N/A,TRUE,"Widnes"}
Name _________ccr1: {#N/A,#N/A,TRUE,"Cover";#N/A,#N/A,TRUE,"Conts";#N/A,#N/A,TRUE,"VOS";#N/A,#N/A,TRUE,"Warrington";#N/A,#N/A,TRUE,"Widnes"}
Name ________ccr1: {#N/A,#N/A,TRUE,"Cover";#N/A,#N/A,TRUE,"Conts";#N/A,#N/A,TRUE,"VOS";#N/A,#N/A,TRUE,"Warrington";#N/A,#N/A,TRUE,"Widnes"}
Name ________ccr1: {#N/A,#N/A,TRUE,"Cover";#N/A,#N/A,TRUE,"Conts";#N/A,#N/A,TRUE,"VOS";#N/A,#N/A,TRUE,"Warrington";#N/A,#N/A,TRUE,"Widnes"}
Name _______ccr1: {#N/A,#N/A,TRUE,"Cover";#N/A,#N/A,TRUE,"Conts";#N/A,#N/A,TRUE,"VOS";#N/A,#N/A,TRUE,"Warrington";#N/A,#N/A,TRUE,"Widnes"}
Name _______ccr1: {#N/A,#N/A,TRUE,"Cover";#N/A,#N/A,TRUE,"Conts";#N/A,#N/A,TRUE,"VOS";#N/A,#N/A,TRUE,"Warrington";#N/A,#N/A,TRUE,"Widnes"}
Name ______ccr1: {#N/A,#N/A,TRUE,"Cover";#N/A,#N/A,TRUE,"Conts";#N/A,#N/A,TRUE,"VOS";#N/A,#N/A,TRUE,"Warrington";#N/A,#N/A,TRUE,"Widnes"}
Name ______ccr1: {#N/A,#N/A,TRUE,"Cover";#N/A,#N/A,TRUE,"Conts";#N/A,#N/A,TRUE,"VOS";#N/A,#N/A,TRUE,"Warrington";#N/A,#N/A,TRUE,"Widnes"}
Name _____ccr1: {#N/A,#N/A,TRUE,"Cover";#N/A,#N/A,TRUE,"Conts";#N/A,#N/A,TRUE,"VOS";#N/A,#N/A,TRUE,"Warrington";#N/A,#N/A,TRUE,"Widnes"}
Name _____ccr1: {#N/A,#N/A,TRUE,"Cover";#N/A,#N/A,TRUE,"Conts";#N/A,#N/A,TRUE,"VOS";#N/A,#N/A,TRUE,"Warrington";#N/A,#N/A,TRUE,"Widnes"}
Name ____ccr1: {#N/A,#N/A,TRUE,"Cover";#N/A,#N/A,TRUE,"Conts";#N/A,#N/A,TRUE,"VOS";#N/A,#N/A,TRUE,"Warrington";#N/A,#N/A,TRUE,"Widnes"}
Name ____ccr1: {#N/A,#N/A,TRUE,"Cover";#N/A,#N/A,TRUE,"Conts";#N/A,#N/A,TRUE,"VOS";#N/A,#N/A,TRUE,"Warrington";#N/A,#N/A,TRUE,"Widnes"}
Name ____ccr2: {#N/A,#N/A,TRUE,"Cover";#N/A,#N/A,TRUE,"Conts";#N/A,#N/A,TRUE,"VOS";#N/A,#N/A,TRUE,"Warrington";#N/A,#N/A,TRUE,"Widnes"}
Name ____ccr2: {#N/A,#N/A,TRUE,"Cover";#N/A,#N/A,TRUE,"Conts";#N/A,#N/A,TRUE,"VOS";#N/A,#N/A,TRUE,"Warrington";#N/A,#N/A,TRUE,"Widnes"}
Name ___ccr1: {#N/A,#N/A,TRUE,"Cover";#N/A,#N/A,TRUE,"Conts";#N/A,#N/A,TRUE,"VOS";#N/A,#N/A,TRUE,"Warrington";#N/A,#N/A,TRUE,"Widnes"}
Name ___ccr1: {#N/A,#N/A,TRUE,"Cover";#N/A,#N/A,TRUE,"Conts";#N/A,#N/A,TRUE,"VOS";#N/A,#N/A,TRUE,"Warrington";#N/A,#N/A,TRUE,"Widnes"}
Name ___ccr2: {#N/A,#N/A,TRUE,"Cover";#N/A,#N/A,TRUE,"Conts";#N/A,#N/A,TRUE,"VOS";#N/A,#N/A,TRUE,"Warrington";#N/A,#N/A,TRUE,"Widnes"}
Name ___ccr2: {#N/A,#N/A,TRUE,"Cover";#N/A,#N/A,TRUE,"Conts";#N/A,#N/A,TRUE,"VOS";#N/A,#N/A,TRUE,"Warrington";#N/A,#N/A,TRUE,"Widnes"}
Name __ccr1: {#N/A,#N/A,TRUE,"Cover";#N/A,#N/A,TRUE,"Conts";#N/A,#N/A,TRUE,"VOS";#N/A,#N/A,TRUE,"Warrington";#N/A,#N/A,TRUE,"Widnes"}
Name __ccr1: {#N/A,#N/A,TRUE,"Cover";#N/A,#N/A,TRUE,"Conts";#N/A,#N/A,TRUE,"VOS";#N/A,#N/A,TRUE,"Warrington";#N/A,#N/A,TRUE,"Widnes"}
Name _1B.05.M.010.0010: #REF!
Name _1B.05.M.010.0010: #REF!
Name _1B.05.M.010.0010: #REF!
Name _1B.05.M.010.0010: #REF!
Name _1B.05.M.010.0050: #REF!
Name _1B.05.M.010.0050: #REF!
Name _1B.05.M.010.0050: #REF!
Name _1B.05.M.010.0050: #REF!
Name _1B.05.M.010.0050: #REF!
Name _1B.05.M.010.0050: #REF!
Name _1B.05.M.0100.0010: #REF!
Name _1B.05.M.0100.0010: #REF!
Name _1B.05.M.0100.0010: #REF!
Name _1B.05.M.0100.0010: #REF!
Name _1B.05.M.0100.0010: #REF!
Name _1B.05.M.020.0010: #REF!
Name _1B.05.M.020.0010: #REF!
Name _1B.05.M.020.0010: #REF!
Name _1B.05.M.020.0010: #REF!
Name _1B.05.M.020.0010: #REF!
Name _1B.05.M.020.0020: #REF!
Name _1B.05.M.020.0020: #REF!
Name _1B.05.M.020.0020: #REF!
Name _1B.05.M.020.0020: #REF!
Name _1B.05.M.020.0020: #REF!
Name _1B.05.M.020.0030: #REF!
Name _1B.05.M.020.0030: #REF!
Name _1B.05.M.020.0030: #REF!
Name _1B.05.M.020.0030: #REF!
Name _1B.05.M.020.0030: #REF!
Name _1B.05.M.020.0040: #REF!
Name _1B.05.M.020.0040: #REF!
Name _1B.05.M.020.0040: #REF!
Name _1B.05.M.020.0040: #REF!

Sheet DB
A1: ='Weekly Progress Report'!$A$1 -> MODON - Weekly Progress Report - Construction Projects
B2: ='Weekly Progress Report'!$A$2 -> Contract General Information | J2: ='Weekly Progress Report'!G2 -> Key Dates | U2: ='Weekly Progress Report'!$M$2 -> Cost Summary (SR) | AD2: ='Weekly Progress Report'!$U$2 -> Performance Summary | AP2: ='Weekly Progress Report'!A67 -> Shop Drawings | AT2: ='Weekly Progress Report'!A77 -> Material Approval | AW2: ='Weekly Progress Report'!A86 -> Procurement Summary | BD2: ='Weekly Progress Report'!L67 -> Quality Reports | BT2: ='Weekly Progress Report'!L75 -> Key Submittals Approval Status | CD2: ='Weekly Progress Report'!L81 -> Invoices Summary | CR2: ='Weekly Progress Report'!L89 -> Resources at Site | CY2: ='Weekly Progress Report'!W67 -> Safety Statistics | FK2: ='Weekly Progress Report'!A95 -> Primavera P6 Schedule Status | FS2: ='Weekly Progress Report'!A104 -> Testing And Commissioning
A3: ='Weekly Progress Report'!AF1 -> Data Date | B3: ='Weekly Progress Report'!A3 -> Project Name | C3: ='Weekly Progress Report'!A4 -> Project ID | D3: ='Weekly Progress Report'!A5 -> Contractor | E3: ='Weekly Progress Report'!A6 -> Consultant | F3: ='Weekly Progress Report'!D4 -> Stage | G3: ='Weekly Progress Report'!D5 -> Status | H3: ='Weekly Progress Report'!D6 -> Modon PM | I3: ='Weekly Progress Report'!AA2 -> Project Scope | J3: ='Weekly Progress Report'!G3 -> Contract Award | K3: ='Weekly Progress Report'!G4 -> Contract Sign | L3: ='Weekly Progress Report'!G5 -> Site Handover | M3: ='Weekly Progress Report'!G6 -> Original Completion | N3: ='Weekly Progress Report'!$I$3 -> Contract Award (Hijri) | O3: ='Weekly Progress Report'!$I$4 -> Contract Sign (Hijri) | P3: ='Weekly Progress Report'!$I$5 -> Site Handover (Hijri) | Q3: ='Weekly Progress Report'!$I$6 -> Original Completion (Hijri) | R3: ='Weekly Progress Report'!$K$3 -> Revised Completion | S3: ='Weekly Progress Report'!$K$4 -> Committed Completion | T3: ='Weekly Progress Report'!$K$5 -> Forecast Completion | U3: ='Weekly Progress Report'!$M$3 -> Original Contract Value | V3: ='Weekly Progress Report'!$M$4 -> Revised Contract Value | W3: ='Weekly Progress Report'!$M$5 -> Estimate At Completion Value | X3: ='Weekly Progress Report'!$M$6 -> Potential Changes | Y3: ='Weekly Progress Report'!$Q$3 -> O&M Value | Z3: ='Weekly Progress Report'!$Q$4 -> Revised O&M Value | AA3: ='Weekly Progress Report'!$Q$5 -> Submitted Invoices (Gross Value) | AB3: ='Weekly Progress Report'!$Q$6 -> Total Deduction | AC3: Original Plan Value | AD3: ='Weekly Progress Report'!$U$3 -> Plan Value | AE3: ='Weekly Progress Report'!$U$4 -> Earn Value | AF3: ='Weekly Progress Report'!$W$3 -> Phys. Plan Value | AG3: ='Weekly Progress Report'!$W$4 -> Phys. Earn Value | AH3: ='Weekly Progress Report'!$Y$3 -> Quality Score | AI3: ='Weekly Progress Report'!$Y$5 -> Safety Score | AJ3: Weekly PV (SAR) | AK3: Weekly EV (SAR) | AL3: Weekly PV % | AM3: Weekly PV % | AN3: Weekly Phys PV% | AO3: Weekly Phys PV% | AP3: Total SD Planned | AQ3: SD Remaining | AR3: SD Pending | AS3: Total SD Submittals | AT3: Planned Materials Approv | AU3: Material Pending Approval | AV3: Materila Total Submittals | AW3: ='Weekly Progress Report'!C87 -> Total Materials Planned | AX3: ='Weekly Progress Report'!D87 -> Total Number of P.O. | AY3: ='Weekly Progress Report'!E87 -> Actual P.O. To Date | AZ3: ='Weekly Progress Report'!F87 -> Remaining P.O | BA3: ='Weekly Progress Report'!G87 -> Actual Material on Site | BB3: ='Weekly Progress Report'!H87 -> Remaining Materials | BC3: ='Weekly Progress Report'!I87 -> Material Delivery Completion (Date) | BD3: ="NCR "&'Weekly Progress Report'!N68 -> NCR Issued | BE3: ="NCR "&'Weekly Progress Report'!O68 -> NCR Closed | BF3: ="NCR "&'Weekly Progress Report'!P68 -> NCR Pending | BG3: ="NCR "&'Weekly Progress Report'!Q68 -> NCR Avg. Closing (Days) | BH3: ="SIR "&'Weekly Progress Report'!N68 -> SIR Issued | BI3: ="SIR "&'Weekly Progress Report'!O68 -> SIR Closed | BJ3: ="SIR "&'Weekly Progress Report'!P68 -> SIR Pending | BK3: ="SIR "&'Weekly Progress Report'!Q68 -> SIR Avg. Closing (Days) | BL3: ="MIR "&'Weekly Progress Report'!N68 -> MIR Issued | BM3: ="MIR "&'Weekly Progress Report'!O68 -> MIR Closed | BN3: ="MIR "&'Weekly Progress Report'!P68 -> MIR Pending | BO3: ="MIR "&'Weekly Progress Report'!Q68 -> MIR Avg. Closing (Days) | BP3: ="FIR "&'Weekly Progress Report'!N68 -> FIR Issued | BQ3: ="FIR "&'Weekly Progress Report'!O68 -> FIR Closed | BR3: ="FIR "&'Weekly Progress Report'!P68 -> FIR Pending | BS3: ="FIR "&'Weekly Progress Report'!Q68 -> FIR Avg. Closing (Days) | BT3: ='Weekly Progress Report'!L76 -> 1 Quality Plan Approval | BU3: ='Weekly Progress Report'!L77 -> 2 Quality Plan Last Up | BV3: ='Weekly Progress Report'!L78 -> 3 Safety Plan Approval | BW3: ='Weekly Progress Report'!L79 -> 4 Safety Plan Last Up | BX3: ='Weekly Progress Report'!L80 -> 5 Construction Plan Approval | BY3: ='Weekly Progress Report'!Q76 -> 6 Baseline Approval | BZ3: ='Weekly Progress Report'!Q77 -> 7 No of Approved Version of Schedule | CA3: ='Weekly Progress Report'!Q78 -> 8 Last Approved Schedule | CB3: ='Weekly Progress Report'!Q79 -> 9 BOQ Approval Date | CC3: ='Weekly Progress Report'!Q80 -> 10 No of Approved Version of BOQ | CD3: ='Weekly Progress Report'!L82 -> Total Submitted Invoices | CE3: ='Weekly Progress Report'!L83 -> PM Approved Invoices | CF3: ='Weekly Progress Report'!L84 -> No of Paid Invoices | CG3: ='Weekly Progress Report'!L85 -> No of Pending Invoices | CH3: ='Weekly Progress Report'!L86 -> Advance Payment % | CI3: ='Weekly Progress Report'!L87 -> Retention % | CJ3: ='Weekly Progress Report'!L88 -> Deduction / Penalties % | CK3: ='Weekly Progress Report'!O82 -> Submitted Invoices (SAR) | CL3: ='Weekly Progress Report'!O83 -> PM Approved Invoices (SAR) | CM3: ='Weekly Progress Report'!O84 -> Paid Invoices (SAR) | CN3: ='Weekly Progress Report'!O85 -> Last Submitted Period | CO3: ='Weekly Progress Report'!O86 -> Advance Payment (SAR) | CP3: ='Weekly Progress Report'!O87 -> Retention (SAR) | CQ3: ='Weekly Progress Report'!O88 -> Deduction / Penalties (SAR) | CR3: Planned Head Count | CS3: Actual Head Count | CT3: Saudi Staff | CU3: Labor Planned | CV3: Labor Actual | CW3: Equipment Planned | CX3: Equipment Actual | CY3: ="This Week "&'Weekly Progress Report'!X70 -> This Week Total Hours Worked | CZ3: ="This Week "&'Weekly Progress Report'!X71 -> This Week Safe Hours Worked | DA3: ="This Week "&'Weekly Progress Report'!X72 -> This Week LTI | DB3: ="This Week "&'Weekly Progress Report'!X73 -> This Week MTC (Healed w/o Disability) | DC3: ="This Week "&'Weekly Progress Report'!X74 -> This Week MTC (Healed w/ Disability) | DD3: ="This Week "&'Weekly Progress Report'!X75 -> This Week Near Miss | DE3: ="This Week "&'Weekly Progress Report'!X76 -> This Week First Aid Cases | DF3: ="This Week "&'Weekly Progress Report'!X77 -> This Week Fatality | DG3: ="This Week "&'Weekly Progress Report'!X78 -> This Week Fire Incident Cases | DH3: ="This Week "&'Weekly Progress Report'!X79 -> This Week Vehicle Incident | DI3: ="This Week "&'Weekly Progress Report'!X80 -> This Week Property Damages | DJ3: ="This Week "&'Weekly Progress Report'!X81 -> This Week Induction Training | DK3: ="This Week "&'Weekly Progress Report'!X82 -> This Week No.of Internal Training | DL3: ="This Week "&'Weekly Progress Report'!X83 -> This Week No.of Internal Audit | DM3: ="This Week "&'Weekly Progress Report'!X84 -> This Week No. of Toolbox Talks | DN3: ="This Week "&'Weekly Progress Report'!X85 -> This Week Safety Awards/Incentives | DO3: ="This Month "&'Weekly Progress Report'!X70 -> This Month Total Hours Worked | DP3: ="This Month "&'Weekly Progress Report'!X71 -> This Month Safe Hours Worked | DQ3: ="This Month "&'Weekly Progress Report'!X72 -> This Month LTI | DR3: ="This Month "&'Weekly Progress Report'!X73 -> This Month MTC (Healed w/o Disability) | DS3: ="This Month "&'Weekly Progress Report'!X74 -> This Month MTC (Healed w/ Disability) | DT3: ="This Month "&'Weekly Progress Report'!X75 -> This Month Near Miss | DU3: ="This Month "&'Weekly Progress Report'!X76 -> This Month First Aid Cases | DV3: ="This Month "&'Weekly Progress Report'!X77 -> This Month Fatality | DW3: ="This Month "&'Weekly Progress Report'!X78 -> This Month Fire Incident Cases | DX3: ="This Month "&'Weekly Progress Report'!X79 -> This Month Vehicle Incident | DY3: ="This Month "&'Weekly Progress Report'!X80 -> This Month Property Damages | DZ3: ="This Month "&'Weekly Progress Report'!X81 -> This Month Induction Training | EA3: ="This Month "&'Weekly Progress Report'!X82 -> This Month No.of Internal Training | EB3: ="This Month "&'Weekly Progress Report'!X83 -> This Month No.of Internal Audit | EC3: ="This Month "&'Weekly Progress Report'!X84 -> This Month No. of Toolbox Talks | ED3: ="This Month "&'Weekly Progress Report'!X85 -> This Month Safety Awards/Incentives | EE3: ="YTD "&'Weekly Progress Report'!X70 -> YTD Total Hours Worked | EF3: ="YTD "&'Weekly Progress Report'!X71 -> YTD Safe Hours Worked | EG3: ="YTD "&'Weekly Progress Report'!X72 -> YTD LTI | EH3: ="YTD "&'Weekly Progress Report'!X73 -> YTD MTC (Healed w/o Disability) | EI3: ="YTD "&'Weekly Progress Report'!X74 -> YTD MTC (Healed w/ Disability) | EJ3: ="YTD "&'Weekly Progress Report'!X75 -> YTD Near Miss | EK3: ="YTD "&'Weekly Progress Report'!X76 -> YTD First Aid Cases | EL3: ="YTD "&'Weekly Progress Report'!X77 -> YTD Fatality | EM3: ="YTD "&'Weekly Progress Report'!X78 -> YTD Fire Incident Cases | EN3: ="YTD "&'Weekly Progress Report'!X79 -> YTD Vehicle Incident | EO3: ="YTD "&'Weekly Progress Report'!X80 -> YTD Property Damages | EP3: ="YTD "&'Weekly Progress Report'!X81 -> YTD Induction Training | EQ3: ="YTD "&'Weekly Progress Report'!X82 -> YTD No.of Internal Training | ER3: ="YTD "&'Weekly Progress Report'!X83 -> YTD No.of Internal Audit | ES3: ="YTD "&'Weekly Progress Report'!X84 -> YTD No. of Toolbox Talks | ET3: ="YTD "&'Weekly Progress Report'!X85 -> YTD Safety Awards/Incentives | EU3: ="Cum "&'Weekly Progress Report'!X70 -> Cum Total Hours Worked | EV3: ="Cum "&'Weekly Progress Report'!X71 -> Cum Safe Hours Worked | EW3: ="Cum "&'Weekly Progress Report'!X72 -> Cum LTI | EX3: ="Cum "&'Weekly Progress Report'!X73 -> Cum MTC (Healed w/o Disability) | EY3: ="Cum "&'Weekly Progress Report'!X74 -> Cum MTC (Healed w/ Disability) | EZ3: ="Cum "&'Weekly Progress Report'!X75 -> Cum Near Miss | FA3: ="Cum "&'Weekly Progress Report'!X76 -> Cum First Aid Cases | FB3: ="Cum "&'Weekly Progress Report'!X77 -> Cum Fatality | FC3: ="Cum "&'Weekly Progress Report'!X78 -> Cum Fire Incident Cases | FD3: ="Cum "&'Weekly Progress Report'!X79 -> Cum Vehicle Incident | FE3: ="Cum "&'Weekly Progress Report'!X80 -> Cum Property Damages | FF3: ="Cum "&'Weekly Progress Report'!X81 -> Cum Induction Training | FG3: ="Cum "&'Weekly Progress Report'!X82 -> Cum No.of Internal Training | FH3: ="Cum "&'Weekly Progress Report'!X83 -> Cum No.of Internal Audit | FI3: ="Cum "&'Weekly Progress Report'!X84 -> Cum No. of Toolbox Talks | FJ3: ="Cum "&'Weekly Progress Report'!X85 -> Cum Safety Awards/Incentives | FK3: ='Weekly Progress Report'!A98 -> Total Act. | FL3: ='Weekly Progress Report'!B98 -> Not Started | FM3: ='Weekly Progress Report'!C98 -> In Progress | FN3: ='Weekly Progress Report'!D98 -> Completed | FO3: Critical Path Act.Last Week | FP3: Critical Path Act.This Week | FQ3: Failed start Last Week | FR3: Failed start This Week | FS3: ='Weekly Progress Report'!B106 -> Planned Start Date | FT3: ='Weekly Progress Report'!D106 -> Planned Finish Date | FU3: ='Weekly Progress Report'!F106 -> Forecast Start Date | FV3: ='Weekly Progress Report'!H106 -> Forecast Finish Date | FW3: ='Weekly Progress Report'!J106 -> Actual Start Date | FX3: ='Weekly Progress Report'!L106 -> Actual Finish Date | FY3: ='Weekly Progress Report'!M106 -> % Completed | FZ3: ='Weekly Progress Report'!N106 -> Open Comments | GA3: ='Weekly Progress Report'!O106 -> Closed Comments
A4: ='Weekly Progress Report'!AG1 -> 46314 | B4: ='Weekly Progress Report'!B3 -> Playground Initiative for Western Region (Asir - Jazan - Jeddah) | C4: ='Weekly Progress Report'!B4 -> MLTX-02-004 | D4: ='Weekly Progress Report'!B5 -> Profast Company Ltd. | E4: ='Weekly Progress Report'!B6 -> Saudi Arabia Consulting Engineering Company "EGIS" | F4: ='Weekly Progress Report'!E4 -> Construction | G4: ='Weekly Progress Report'!E5 -> Active | H4: ='Weekly Progress Report'!E6 -> Engr.Yazeed Al Ragabh | I4: ='Weekly Progress Report'!AA3 -> The Scope of Works for the Playground Initiative for Western Region (ASIR - JAZAN – JEDDAH) according to the following contents. - Playground Area (Padel – Basketball – football) - Service & Toilet Building - Land Scape Works - Bike & Walking Paths - Parking | J4: ='Weekly Progress Report'!H3 -> 46057 | K4: ='Weekly Progress Report'!H4 -> 46085 | L4: ='Weekly Progress Report'!H5 -> 46107 | M4: ='Weekly Progress Report'!H6 -> 46412 | N4: ='Weekly Progress Report'!$J$3 -> 46057 | O4: ='Weekly Progress Report'!$J$4 -> 46085 | P4: ='Weekly Progress Report'!$J$5 -> 46107 | Q4: ='Weekly Progress Report'!$J$6 -> 46412 | R4: ='Weekly Progress Report'!$L$3 -> 46412 | S4: ='Weekly Progress Report'!$L$4 -> 46412 | T4: ='Weekly Progress Report'!$L$5 -> 46516 | U4: ='Weekly Progress Report'!$O$3 -> 33997787 | V4: ='Weekly Progress Report'!$O$4 -> 33793604 | W4: ='Weekly Progress Report'!$O$5 -> 33997787 | X4: ='Weekly Progress Report'!$O$6 -> -204182.66 | Y4: ='Weekly Progress Report'!$S$3 -> 0 | Z4: ='Weekly Progress Report'!$S$4 -> 0 | AA4: ='Weekly Progress Report'!$S$5 -> 4943710.6 | AB4: ='Weekly Progress Report'!$S$6 -> 11000 | AC4: ='Weekly Progress Report'!$J$28 -> 0.10537503 | AD4: ='Weekly Progress Report'!$V$3 -> 0.39130844 | AE4: ='Weekly Progress Report'!$V$4 -> 0.35390468 | AF4: ='Weekly Progress Report'!$X$3 -> 0.5102606 | AG4: ='Weekly Progress Report'!$X$4 -> 0.42411367 | AH4: ='Weekly Progress Report'!$Z$3 -> 0.85706897 | AI4: ='Weekly Progress Report'!$Z$5 -> 0.8375 | AJ4: ='Weekly Progress Report'!$E$28 -> 3299377 | AK4: ='Weekly Progress Report'!$F$28 -> 1643974.8 | AL4: =AJ4/V4 -> 0.097633177 | AM4: =AK4/V4 -> 0.048647512 | AN4: ='Weekly Progress Report'!S28 -> 0.040575427 | AO4: ='Weekly Progress Report'!T28 -> 0.034185672 | AP4: ='Weekly Progress Report'!C76 -> 140 | AQ4: ='Weekly Progress Report'!I76 -> 0 | AR4: ='Weekly Progress Report'!J76 -> 4 | AS4: ='Weekly Progress Report'!K76 -> 141 | AT4: ='Weekly Progress Report'!C85 -> 147 | AU4: ='Weekly Progress Report'!J85 -> 2 | AV4: ='Weekly Progress Report'!K85 -> 147 | AW4: ='Weekly Progress Report'!C94 -> 117 | AX4: ='Weekly Progress Report'!D94 -> 76 | AY4: ='Weekly Progress Report'!E94 -> 35 | AZ4: ='Weekly Progress Report'!F94 -> 41 | BA4: ='Weekly Progress Report'!G94 -> 22 | BB4: ='Weekly Progress Report'!H94 -> 54 | BC4: ='Weekly Progress Report'!I94 -> 0 | BD4: ='Weekly Progress Report'!N71 -> 20 | BE4: ='Weekly Progress Report'!O71 -> 20 | BF4: ='Weekly Progress Report'!P71 -> 0 | BG4: ='Weekly Progress Report'!Q71 -> 0 | BH4: ='Weekly Progress Report'!N72 -> 25 | BI4: ='Weekly Progress Report'!O72 -> 25 | BJ4: ='Weekly Progress Report'!P72 -> 0 | BK4: ='Weekly Progress Report'!Q72 -> 0 | BL4: ='Weekly Progress Report'!N73 -> 102 | BM4: ='Weekly Progress Report'!O73 -> 99 | BN4: ='Weekly Progress Report'!P73 -> 2 | BO4: ='Weekly Progress Report'!Q73 -> 0 | BP4: ='Weekly Progress Report'!N74 -> 657 | BQ4: ='Weekly Progress Report'!O74 -> 634 | BR4: ='Weekly Progress Report'!P74 -> 22 | BS4: ='Weekly Progress Report'!Q74 -> 0 | BT4: ='Weekly Progress Report'!O76 -> 46142 | BU4: ='Weekly Progress Report'!O77 -> - | BV4: ='Weekly Progress Report'!O78 -> 46184 | BW4: ='Weekly Progress Report'!O79 -> - | BX4: ='Weekly Progress Report'!O80 -> 46155 | BY4: ='Weekly Progress Report'!U76 -> 46140 | BZ4: ='Weekly Progress Report'!U77 -> - | CA4: ='Weekly Progress Report'!U78 -> - | CB4: ='Weekly Progress Report'!U79 -> 45918 | CC4: ='Weekly Progress Report'!U80 -> 0 | CD4: ='Weekly Progress Report'!N82 -> 5 | CE4: ='Weekly Progress Report'!N83 -> 0 | CF4: ='Weekly Progress Report'!N84 -> 0 | CG4: ='Weekly Progress Report'!N85 -> 5 | CH4: ='Weekly Progress Report'!N86 -> 0 | CI4: ='Weekly Progress Report'!N87 -> 0 | CJ4: ='Weekly Progress Report'!N88 -> 0.00032355047 | CK4: ='Weekly Progress Report'!R82 -> 4943710.6 | CL4: ='Weekly Progress Report'!R83 -> 0 | CM4: ='Weekly Progress Report'!R84 -> 0 | CN4: ='Weekly Progress Report'!R85 -> 46303 | CO4: ='Weekly Progress Report'!R86 -> 0 | CP4: ='Weekly Progress Report'!R87 -> 0 | CQ4: ='Weekly Progress Report'!R88 -> 11000 | CR4: ='Weekly Progress Report'!L92 -> 175 | CS4: ='Weekly Progress Report'!M92 -> 70 | CT4: ='Weekly Progress Report'!O92 -> 0 | CU4: ='Weekly Progress Report'!P92 -> 19 | CV4: ='Weekly Progress Report'!Q92 -> 30 | CW4: ='Weekly Progress Report'!T102 -> 9 | CX4: ='Weekly Progress Report'!U102 -> 5 | CY4: ='Weekly Progress Report'!Z70 -> 6480 | CZ4: ='Weekly Progress Report'!Z71 -> 6480 | DA4: ='Weekly Progress Report'!Z72 -> 0 | DB4: ='Weekly Progress Report'!Z73 -> 0 | DC4: ='Weekly Progress Report'!Z74 -> 0 | DD4: ='Weekly Progress Report'!Z75 -> 0 | DE4: ='Weekly Progress Report'!Z76 -> 0 | DF4: ='Weekly Progress Report'!Z77 -> 0 | DG4: ='Weekly Progress Report'!Z78 -> 0 | DH4: ='Weekly Progress Report'!Z79 -> 0 | DI4: ='Weekly Progress Report'!Z80 -> 0 | DJ4: ='Weekly Progress Report'!Z81 -> 0 | DK4: ='Weekly Progress Report'!Z82 -> 1 | DL4: ='Weekly Progress Report'!Z83 -> 0 | DM4: ='Weekly Progress Report'!Z84 -> 4 | DN4: ='Weekly Progress Report'!Z85 -> 0 | DO4: ='Weekly Progress Report'!AB70 -> 6480 | DP4: ='Weekly Progress Report'!AB71 -> 6480 | DQ4: ='Weekly Progress Report'!AB72 -> 0 | DR4: ='Weekly Progress Report'!AB73 -> 0 | DS4: ='Weekly Progress Report'!AB74 -> 0 | DT4: ='Weekly Progress Report'!AB75 -> 0 | DU4: ='Weekly Progress Report'!AB76 -> 0 | DV4: ='Weekly Progress Report'!AB77 -> 0 | DW4: ='Weekly Progress Report'!AB78 -> 0 | DX4: ='Weekly Progress Report'!AB79 -> 0 | DY4: ='Weekly Progress Report'!AB80 -> 0 | DZ4: ='Weekly Progress Report'!AB81 -> 18 | EA4: ='Weekly Progress Report'!AB82 -> 04 Session | EB4: ='Weekly Progress Report'!AB83 -> 0 | EC4: ='Weekly Progress Report'!AB84 -> 4 Sessions | ED4: ='Weekly Progress Report'!AB85 -> 0 | EE4: ='Weekly Progress Report'!AC70 -> 132050 | EF4: ='Weekly Progress Report'!AC71 -> 132050 | EG4: ='Weekly Progress Report'!AC72 -> 0 | EH4: ='Weekly Progress Report'!AC73 -> 0 | EI4: ='Weekly Progress Report'!AC74 -> 0 | EJ4: ='Weekly Progress Report'!AC75 -> 0 | EK4: ='Weekly Progress Report'!AC76 -> 0 | EL4: ='Weekly Progress Report'!AC77 -> 0 | EM4: ='Weekly Progress Report'!AC78 -> 0 | EN4: ='Weekly Progress Report'!AC79 -> 0 | EO4: ='Weekly Progress Report'!AC80 -> 0 | EP4: ='Weekly Progress Report'!AC81 -> 160 | EQ4: ='Weekly Progress Report'!AC82 -> 17 Session | ER4: ='Weekly Progress Report'!AC83 -> 0 | ES4: ='Weekly Progress Report'!AC84 -> 156 sessions | ET4: ='Weekly Progress Report'!AC85 -> 0 | EU4: ='Weekly Progress Report'!AD70 -> 132050 | EV4: ='Weekly Progress Report'!AD71 -> 132050 | EW4: ='Weekly Progress Report'!AD72 -> 0 | EX4: ='Weekly Progress Report'!AD73 -> 0 | EY4: ='Weekly Progress Report'!AD74 -> 0 | EZ4: ='Weekly Progress Report'!AD75 -> 0 | FA4: ='Weekly Progress Report'!AD76 -> 0 | FB4: ='Weekly Progress Report'!AD77 -> 0 | FC4: ='Weekly Progress Report'!AD78 -> 0 | FD4: ='Weekly Progress Report'!AD79 -> 0 | FE4: ='Weekly Progress Report'!AD80 -> 0 | FF4: ='Weekly Progress Report'!AD81 -> 160 | FG4: ='Weekly Progress Report'!AD82 -> 17 Session | FH4: ='Weekly Progress Report'!AD83 -> 0 | FI4: ='Weekly Progress Report'!AD84 -> 156 sessions | FJ4: ='Weekly Progress Report'!AD85 -> 0 | FK4: ='Weekly Progress Report'!A99 -> 2134 | FL4: ='Weekly Progress Report'!B99 -> 385 | FM4: ='Weekly Progress Report'!C99 -> 21 | FN4: ='Weekly Progress Report'!D99 -> 1728 | FO4: ='Weekly Progress Report'!A103 -> 373 | FP4: ='Weekly Progress Report'!B103 -> 331 | FQ4: ='Weekly Progress Report'!H103 -> 266 | FR4: ='Weekly Progress Report'!I103 -> 240 | FS4: ='Weekly Progress Report'!B111 -> 0 | FT4: ='Weekly Progress Report'!D111 -> 0 | FU4: ='Weekly Progress Report'!F111 -> 0 | FV4: ='Weekly Progress Report'!H111 -> 0 | FW4: ='Weekly Progress Report'!J111 -> 0 | FX4: ='Weekly Progress Report'!L111 -> 0 | FY4: ='Weekly Progress Report'!M111 -> 0 | FZ4: ='Weekly Progress Report'!N111 -> 0 | GA4: ='Weekly Progress Report'!O111 -> 0

Sheet Weekly Progress Report
A1: MODON - Weekly Progress Report - Construction Projects | AF1: Data Date | AG1: ='General Information'!L1 -> 46314
A2: Contract General Information | G2: Key Dates | M2: Cost Summary (SR) | U2: Performance Summary | AA2: Project Scope
A3: Project Name | B3: ='General Information'!C3 -> Playground Initiative for Western Region (Asir - Jazan - Jeddah) | G3: Contract Award | H3: ='General Information'!C12 -> 46057 | I3: Contract Award (Hijri) | J3: ='General Information'!C16 -> 46057 | K3: Revised Completion | L3: ='General Information'!C20 -> 46412 | M3: Original Contract Value | O3: ='Invoice Log'!F3 -> 33997787 | Q3: O&M Value | S3: ='Invoice Log'!J3 -> 0 | T3: EAC | U3: Plan Value | V3: =K28 -> 0.39130844 | W3: Phys. Plan Value | X3: =W28 -> 0.5102606 | Y3: Quality Score | Z3: =+[44]Quality!AC11 -> 0.85706897 | AA3: The Scope of Works for the Playground Initiative for Western Region (ASIR - JAZAN – JEDDAH) according to the following contents. - Playground Area (Padel – Basketball – football) - Service & Toilet Building - Land Scape Works - Bike & Walking Paths - Parking
A4: Project ID | B4: ='General Information'!C4 -> MLTX-02-004 | D4: Stage | E4: ='General Information'!C7 -> Construction | G4: Contract Sign | H4: ='General Information'!C13 -> 46085 | I4: Contract Sign (Hijri) | J4: ='General Information'!C17 -> 46085 | K4: Committed Completion | L4: ='General Information'!C21 -> 46412 | M4: Revised Contract Value | O4: ='Invoice Log'!F4 -> 33793604 | P4: EAC | Q4: Revised O&M Value | S4: ='Invoice Log'!J4 -> 0 | T4: =+#REF!+#REF!+S4 -> #REF! | U4: Earn Value | V4: =L28 -> 0.35390468 | W4: Phys. Earn Value | X4: =X28 -> 0.42411367 | Z4: =REPT("¢",IF(INT(+Z3*10)>5,5,INT(+Z3*10)))&REPT("£",IF(INT(+Z3*10)>5,0,5-INT(+Z3*10)))&CHAR(10)&REPT("¢",+IF(INT(+Z3*10)>5,-5+INT(+Z3*10),0))&REPT("£",IF(INT(+Z3*10)>5,10-INT(+Z3*10),5)) -> ¢¢¢¢¢ ¢¢¢££
A5: Contractor | B5: ='General Information'!C5 -> Profast Company Ltd. | D5: Status | E5: ='General Information'!C8 -> Active | G5: Site Handover | H5: ='General Information'!C14 -> 46107 | I5: Site Handover (Hijri) | J5: ='General Information'!C18 -> 46107 | K5: Forecast Completion | L5: ='General Information'!C22 -> 46516 | M5: Estimate At Completion Value | O5: ='Invoice Log'!F5 -> 33997787 | P5: =+#REF!+#REF!+O5 -> #REF! | Q5: Submitted Invoices (Gross Value) | S5: ='Invoice Log'!J5 -> 4943710.6 | U5: Variance | V5: =V4-V3 -> -0.037403761 | W5: Variance | X5: =X4-X3 -> -0.086146927 | Y5: Safety Score | Z5: =[44]HSE!$AE$6 -> 0.8375
A6: Consultant | B6: ='General Information'!C6 -> Saudi Arabia Consulting Engineering Company "EGIS" | D6: Modon PM | E6: ='General Information'!C9 -> Engr.Yazeed Al Ragabh | G6: Original Completion | H6: ='General Information'!C15 -> 46412 | I6: Original Completion (Hijri) | J6: ='General Information'!C19 -> 46412 | K6: Variance | L6: ='General Information'!C23 -> -104 | M6: Potential Changes | O6: =O4-O5 -> -204182.66 | Q6: Total Deduction | S6: ='Invoice Log'!J6 -> 11000 | U6: SPI | V6: =V4/V3 -> 0.90441361 | W6: SPI | X6: =X4/X3 -> 0.83117072 | Z6: =REPT("¢",IF(INT(+Z5*10)>5,5,INT(+Z5*10)))&REPT("£",IF(INT(+Z5*10)>5,0,5-INT(+Z5*10)))&CHAR(10)&REPT("¢",+IF(INT(+Z5*10)>5,-5+INT(+Z5*10),0))&REPT("£",IF(INT(+Z5*10)>5,10-INT(+Z5*10),5)) -> ¢¢¢¢¢ ¢¢¢££
A8: Progress Overview
A9: Earned Value Progress (SAR) | O9: Physical Progress (Effort) | AA9: Earned Value Progress (%)
A10: WBS | C10: BOQ Value (SAR) | D10: % Wt. | E10: Weekly (SAR) | G10: To Date (SAR) | O10: Budgeted | P10: % Wt. | Q10: Weekly Physical Progress | U10: To Date Physical Progress
E11: Planned | F11: Earned | G11: Original Plan | H11: Revised Planned | I11: Earned | J11: Original Plan % | K11: Revised Planned % | L11: Earned % | M11: Variance | N11: SPI | O11: (Manhours) | Q11: Planned | R11: Earned | S11: Plan % | T11: Earned % | U11: Planned | V11: Earned | W11: Plan % | X11: Earned % | Y11: Variance | Z11: SPI
C12: =Progress!C7 -> 0 | D12: =Progress!D7 -> 0 | E12: =Progress!E18 -> 0 | F12: =Progress!F18 -> 0 | G12: =Progress!G18 -> 0 | H12: =Progress!H18 -> 0 | I12: =Progress!I18 -> 0 | J12: =IFERROR(IF(ISBLANK(G12),"",G12/C12),0) -> 0 | K12: =IFERROR(IF(ISBLANK(H12),"",H12/C12),0) -> 0 | L12: =IFERROR(IF(ISBLANK(I12),"",I12/C12),0) -> 0 | M12: =IFERROR(L12-K12,"") -> 0 | N12: =IFERROR(L12/K12,"") | P12: =IF(ISBLANK(O12),"",O12/$O$28)
A13: =Progress!A7 -> Moblization | C13: =Progress!C7 -> 0 | D13: =Progress!D7 -> 0 | E13: =Progress!E7 -> 0 | F13: =Progress!F7 -> 0 | G13: =Progress!G7 -> 0 | H13: =Progress!H7 -> 0 | I13: =Progress!I7 -> 0 | J13: =IFERROR(IF(ISBLANK(G13),"",G13/C13),0) -> 0 | K13: =IFERROR(IF(ISBLANK(H13),"",H13/C13),0) -> 0 | L13: =IFERROR(IF(ISBLANK(I13),"",I13/C13),0) -> 0 | M13: =IFERROR(L13-K13,"") -> 0 | N13: =IFERROR(L13/K13,"") | O13: =Progress!L7 -> 12659 | P13: =IF(ISBLANK(O13),"",O13/$O$28) -> 0.031160232 | Q13: =Progress!N7 -> 0 | R13: =Progress!O7 -> 0 | S13: =IFERROR(IF(ISBLANK(Q13),"",Q13/O13),0) -> 0 | T13: =IFERROR(IF(ISBLANK(R13),"",R13/O13),0) -> 0 | U13: =Progress!P7 -> 12658.6 | V13: =Progress!Q7 -> 12658.6 | W13: =IFERROR(IF(ISBLANK(U13),"",U13/O13),0) -> 0.9999684 | X13: =IFERROR(IF(ISBLANK(V13),"",V13/O13),0) -> 0.9999684 | Y13: =IFERROR(X13-W13,"") -> 0 | Z13: =IFERROR(X13/W13,"") -> 1
A14: =Progress!A8 -> Engineering | C14: =Progress!C8 -> 0 | D14: =Progress!D8 -> 0 | E14: =Progress!E8 -> 0 | F14: =Progress!F8 -> 0 | G14: =Progress!G8 -> 0 | H14: =Progress!H8 -> 0 | I14: =Progress!I8 -> 0 | J14: =IFERROR(IF(ISBLANK(G14),"",G14/C14),0) -> 0 | K14: =IFERROR(IF(ISBLANK(H14),"",H14/C14),0) -> 0 | L14: =IFERROR(IF(ISBLANK(I14),"",I14/C14),0) -> 0 | M14: =IFERROR(L14-K14,"") -> 0 | N14: =IFERROR(L14/K14,"") | O14: =Progress!L8 -> 21299 | P14: =IF(ISBLANK(O14),"",O14/$O$28) -> 0.052427662 | Q14: =Progress!N8 -> 0 | R14: =Progress!O8 -> 80.5 | S14: =IFERROR(IF(ISBLANK(Q14),"",Q14/O14),0) -> 0 | T14: =IFERROR(IF(ISBLANK(R14),"",R14/O14),0) -> 0.0037795202 | U14: =Progress!P8 -> 21299.5 | V14: =Progress!Q8 -> 21009.7 | W14: =IFERROR(IF(ISBLANK(U14),"",U14/O14),0) -> 1.0000235 | X14: =IFERROR(IF(ISBLANK(V14),"",V14/O14),0) -> 0.9864172 | Y14: =IFERROR(X14-W14,"") -> -0.013606273 | Z14: =IFERROR(X14/W14,"") -> 0.98639405
A15: =Progress!A9 -> Procurment | C15: =Progress!C9 -> 0 | D15: =Progress!D9 -> 0 | E15: =Progress!E9 -> 0 | F15: =Progress!F9 -> 0 | G15: =Progress!G9 -> 0 | H15: =Progress!H9 -> 0 | I15: =Progress!I9 -> 0 | J15: =IFERROR(IF(ISBLANK(G15),"",G15/C15),0) -> 0 | K15: =IFERROR(IF(ISBLANK(H15),"",H15/C15),0) -> 0 | L15: =IFERROR(IF(ISBLANK(I15),"",I15/C15),0) -> 0 | M15: =IFERROR(L15-K15,"") -> 0 | N15: =IFERROR(L15/K15,"") | O15: =Progress!L9 -> 51273 | P15: =IF(ISBLANK(O15),"",O15/$O$28) -> 0.12620891 | Q15: =Progress!N9 -> 296.71 | R15: =Progress!O9 -> 5000 | S15: =IFERROR(IF(ISBLANK(Q15),"",Q15/O15),0) -> 0.0057868664 | T15: =IFERROR(IF(ISBLANK(R15),"",R15/O15),0) -> 0.097517212 | U15: =Progress!P9 -> 50732.3 | V15: =Progress!Q9 -> 31870.4 | W15: =IFERROR(IF(ISBLANK(U15),"",U15/O15),0) -> 0.98945449 | X15: =IFERROR(IF(ISBLANK(V15),"",V15/O15),0) -> 0.62158251 | Y15: =IFERROR(X15-W15,"") -> -0.36787198 | Z15: =IFERROR(X15/W15,"") -> 0.62820728
A16: =Progress!A10 -> Construction | C16: =Progress!C10 -> 33793604 | D16: =Progress!D10 -> 1 | E16: =Progress!E10 -> 1649688.5 | F16: =Progress!F10 -> 821987.39 | G16: =Progress!G10 -> 3561002.2 | H16: =Progress!H10 -> 13223723 | I16: =Progress!I10 -> 11959715 | J16: =IFERROR(IF(ISBLANK(G16),"",G16/C16),0) -> 0.10537503 | K16: =IFERROR(IF(ISBLANK(H16),"",H16/C16),0) -> 0.39130844 | L16: =IFERROR(IF(ISBLANK(I16),"",I16/C16),0) -> 0.35390468 | M16: =IFERROR(L16-K16,"") -> -0.037403761 | N16: =IFERROR(L16/K16,"") -> 0.90441361 | O16: =Progress!L10 -> 299660 | P16: =IF(ISBLANK(O16),"",O16/$O$28) -> 0.73761554 | Q16: =Progress!N10 -> 16187.26 | R16: =Progress!O10 -> 8807.6 | S16: =IFERROR(IF(ISBLANK(Q16),"",Q16/O16),0) -> 0.054018755 | T16: =IFERROR(IF(ISBLANK(R16),"",R16/O16),0) -> 0.029391978 | U16: =Progress!P10 -> 122605.52 | V16: =Progress!Q10 -> 106759.6 | W16: =IFERROR(IF(ISBLANK(U16),"",U16/O16),0) -> 0.40914877 | X16: =IFERROR(IF(ISBLANK(V16),"",V16/O16),0) -> 0.3562691 | Y16: =IFERROR(X16-W16,"") -> -0.052879664 | Z16: =IFERROR(X16/W16,"") -> 0.87075688
A17: =Progress!A11 -> Jazan Region | C17: =Progress!C11 -> 10680072 | D17: =Progress!D11 -> 0.31603825 | E17: =Progress!E11 -> 401113.04 | F17: =Progress!F11 -> 199957.72 | G17: =Progress!G11 -> 794325.94 | H17: =Progress!H11 -> 3951358.3 | I17: =Progress!I11 -> 2669083.7 | J17: =IFERROR(IF(ISBLANK(G17),"",G17/C17),0) -> 0.07437459 | K17: =IFERROR(IF(ISBLANK(H17),"",H17/C17),0) -> 0.36997489 | L17: =IFERROR(IF(ISBLANK(I17),"",I17/C17),0) -> 0.24991253 | M17: =IFERROR(L17-K17,"") -> -0.12006236 | N17: =IFERROR(L17/K17,"") -> 0.67548512 | O17: =Progress!L11 -> 102280 | P17: =IF(ISBLANK(O17),"",O17/$O$28) -> 0.25176306 | Q17: =Progress!N11 -> 5152.78 | R17: =Progress!O11 -> 4475.4 | S17: =IFERROR(IF(ISBLANK(Q17),"",Q17/O17),0) -> 0.050379155 | T17: =IFERROR(IF(ISBLANK(R17),"",R17/O17),0) -> 0.043756355 | U17: =Progress!P11 -> 45532.83 | V17: =Progress!Q11 -> 24825.4 | W17: =IFERROR(IF(ISBLANK(U17),"",U17/O17),0) -> 0.44517824 | X17: =IFERROR(IF(ISBLANK(V17),"",V17/O17),0) -> 0.24271998 | Y17: =IFERROR(X17-W17,"") -> -0.20245825 | Z17: =IFERROR(X17/W17,"") -> 0.54521979
A18: =Progress!A12 -> Asir Region | C18: =Progress!C12 -> 10578073 | D18: =Progress!D12 -> 0.31301997 | E18: =Progress!E12 -> 617430.85 | F18: =Progress!F12 -> 300428.38 | G18: =Progress!G12 -> 1310370.1 | H18: =Progress!H12 -> 3063276.7 | I18: =Progress!I12 -> 4049399.2 | J18: =IFERROR(IF(ISBLANK(G18),"",G18/C18),0) -> 0.12387607 | K18: =IFERROR(IF(ISBLANK(H18),"",H18/C18),0) -> 0.2895874 | L18: =IFERROR(IF(ISBLANK(I18),"",I18/C18),0) -> 0.38281067 | M18: =IFERROR(L18-K18,"") -> 0.093223271 | N18: =IFERROR(L18/K18,"") -> 1.3219176 | O18: =Progress!L12 -> 96810 | P18: =IF(ISBLANK(O18),"",O18/$O$28) -> 0.23829861 | Q18: =Progress!N12 -> 7222.43 | R18: =Progress!O12 -> 1151.2 | S18: =IFERROR(IF(ISBLANK(Q18),"",Q18/O18),0) -> 0.074604173 | T18: =IFERROR(IF(ISBLANK(R18),"",R18/O18),0) -> 0.011891334 | U18: =Progress!P12 -> 40471.12 | V18: =Progress!Q12 -> 39573.2 | W18: =IFERROR(IF(ISBLANK(U18),"",U18/O18),0) -> 0.4180469 | X18: =IFERROR(IF(ISBLANK(V18),"",V18/O18),0) -> 0.40877182 | Y18: =IFERROR(X18-W18,"") -> -0.0092750749 | Z18: =IFERROR(X18/W18,"") -> 0.97781331
A19: =Progress!A13 -> Jeddah Region | C19: =Progress!C13 -> 12535460 | D19: =Progress!D13 -> 0.37094178 | E19: =Progress!E13 -> 631144.59 | F19: =Progress!F13 -> 321601.29 | G19: =Progress!G13 -> 1456306.1 | H19: =Progress!H13 -> 6209087.6 | I19: =Progress!I13 -> 5241231.7 | J19: =IFERROR(IF(ISBLANK(G19),"",G19/C19),0) -> 0.11617493 | K19: =IFERROR(IF(ISBLANK(H19),"",H19/C19),0) -> 0.49532189 | L19: =IFERROR(IF(ISBLANK(I19),"",I19/C19),0) -> 0.41811244 | M19: =IFERROR(L19-K19,"") -> -0.077209447 | N19: =IFERROR(L19/K19,"") -> 0.84412268 | O19: =Progress!L13 -> 100570 | P19: =IF(ISBLANK(O19),"",O19/$O$28) -> 0.24755388 | Q19: =Progress!N13 -> 3812.05 | R19: =Progress!O13 -> 3181 | S19: =IFERROR(IF(ISBLANK(Q19),"",Q19/O19),0) -> 0.037904445 | T19: =IFERROR(IF(ISBLANK(R19),"",R19/O19),0) -> 0.031629711 | U19: =Progress!P13 -> 36601.57 | V19: =Progress!Q13 -> 42361 | W19: =IFERROR(IF(ISBLANK(U19),"",U19/O19),0) -> 0.36394123 | X19: =IFERROR(IF(ISBLANK(V19),"",V19/O19),0) -> 0.42120911 | Y19: =IFERROR(X19-W19,"") -> 0.057267873 | Z19: =IFERROR(X19/W19,"") -> 1.1573547
A20: =Progress!A14 -> Testing & Commissioning | C20: =Progress!C14 -> 0 | D20: =Progress!D14 -> 0 | E20: =Progress!E14 -> 0 | F20: =Progress!F14 -> 0 | G20: =Progress!G14 -> 0 | H20: =Progress!H14 -> 0 | I20: =Progress!I14 -> 0 | J20: =IFERROR(IF(ISBLANK(G20),"",G20/C20),0) -> 0 | K20: =IFERROR(IF(ISBLANK(H20),"",H20/C20),0) -> 0 | L20: =IFERROR(IF(ISBLANK(I20),"",I20/C20),0) -> 0 | M20: =IFERROR(L20-K20,"") -> 0 | N20: =IFERROR(L20/K20,"") | O20: =Progress!L14 -> 12818 | P20: =IF(ISBLANK(O20),"",O20/$O$28) -> 0.031551612 | Q20: =Progress!N14 -> 0 | R20: =Progress!O14 -> 0 | S20: =IFERROR(IF(ISBLANK(Q20),"",Q20/O20),0) -> 0 | T20: =IFERROR(IF(ISBLANK(R20),"",R20/O20),0) -> 0 | U20: =Progress!P14 -> 0 | V20: =Progress!Q14 -> 0 | W20: =IFERROR(IF(ISBLANK(U20),"",U20/O20),0) -> 0 | X20: =IFERROR(IF(ISBLANK(V20),"",V20/O20),0) -> 0 | Y20: =IFERROR(X20-W20,"") -> 0 | Z20: =IFERROR(X20/W20,"")
A21: =Progress!A15 -> Close-Out | C21: =Progress!C15 -> 0 | D21: =Progress!D15 -> 0 | E21: =Progress!E15 -> 0 | F21: =Progress!F15 -> 0 | G21: =Progress!G15 -> 0 | H21: =Progress!H15 -> 0 | I21: =Progress!I15 -> 0 | J21: =IFERROR(IF(ISBLANK(G21),"",G21/C21),0) -> 0 | K21: =IFERROR(IF(ISBLANK(H21),"",H21/C21),0) -> 0 | L21: =IFERROR(IF(ISBLANK(I21),"",I21/C21),0) -> 0 | M21: =IFERROR(L21-K21,"") -> 0 | N21: =IFERROR(L21/K21,"") | O21: =Progress!L15 -> 8546 | P21: =IF(ISBLANK(O21),"",O21/$O$28) -> 0.021036049 | Q21: =Progress!N15 -> 0 | R21: =Progress!O15 -> 0 | S21: =IFERROR(IF(ISBLANK(Q21),"",Q21/O21),0) -> 0 | T21: =IFERROR(IF(ISBLANK(R21),"",R21/O21),0) -> 0 | U21: =Progress!P15 -> 0 | V21: =Progress!Q15 -> 0 | W21: =IFERROR(IF(ISBLANK(U21),"",U21/O21),0) -> 0 | X21: =IFERROR(IF(ISBLANK(V21),"",V21/O21),0) -> 0 | Y21: =IFERROR(X21-W21,"") -> 0 | Z21: =IFERROR(X21/W21,"")
C22: =Progress!C16 -> 0 | D22: =Progress!D16 -> 0 | E22: =Progress!E16 -> 0 | F22: =Progress!F16 -> 0 | G22: =Progress!G16 -> 0 | H22: =Progress!H16 -> 0 | I22: =Progress!I16 -> 0 | J22: =IFERROR(IF(ISBLANK(G22),"",G22/C22),0) -> 0 | K22: =IFERROR(IF(ISBLANK(H22),"",H22/C22),0) -> 0 | L22: =IFERROR(IF(ISBLANK(I22),"",I22/C22),0) -> 0 | M22: =IFERROR(L22-K22,"") -> 0 | N22: =IFERROR(L22/K22,"") | O22: =Progress!L16 -> 0 | P22: =IF(ISBLANK(O22),"",O22/$O$28) -> 0 | Q22: =Progress!N16 -> 0 | R22: =Progress!O16 -> 0 | S22: =IFERROR(IF(ISBLANK(Q22),"",Q22/O22),0) -> 0 | T22: =IFERROR(IF(ISBLANK(R22),"",R22/O22),0) -> 0 | U22: =Progress!P16 -> 0 | V22: =Progress!Q16 -> 0 | W22: =IFERROR(IF(ISBLANK(U22),"",U22/O22),0) -> 0 | X22: =IFERROR(IF(ISBLANK(V22),"",V22/O22),0) -> 0 | Y22: =IFERROR(X22-W22,"") -> 0 | Z22: =IFERROR(X22/W22,"")
C23: =Progress!C17 -> 0 | D23: =Progress!D17 -> 0 | E23: =Progress!E17 -> 0 | F23: =Progress!F17 -> 0 | G23: =Progress!G17 -> 0 | H23: =Progress!H17 -> 0 | I23: =Progress!I17 -> 0 | J23: =IFERROR(IF(ISBLANK(G23),"",G23/C23),0) -> 0 | K23: =IFERROR(IF(ISBLANK(H23),"",H23/C23),0) -> 0 | L23: =IFERROR(IF(ISBLANK(I23),"",I23/C23),0) -> 0 | M23: =IFERROR(L23-K23,"") -> 0 | N23: =IFERROR(L23/K23,"") | O23: =Progress!L17 -> 0 | P23: =IF(ISBLANK(O23),"",O23/$O$28) -> 0 | Q23: =Progress!N17 -> 0 | R23: =Progress!O17 -> 0 | S23: =IFERROR(IF(ISBLANK(Q23),"",Q23/O23),0) -> 0 | T23: =IFERROR(IF(ISBLANK(R23),"",R23/O23),0) -> 0 | U23: =Progress!P17 -> 0 | V23: =Progress!Q17 -> 0 | W23: =IFERROR(IF(ISBLANK(U23),"",U23/O23),0) -> 0 | X23: =IFERROR(IF(ISBLANK(V23),"",V23/O23),0) -> 0 | Y23: =IFERROR(X23-W23,"") -> 0 | Z23: =IFERROR(X23/W23,"")
C24: =Progress!C18 -> 0 | D24: =Progress!D18 -> 0 | E24: =Progress!E18 -> 0 | F24: =Progress!F18 -> 0 | G24: =Progress!G18 -> 0 | H24: =Progress!H18 -> 0 | I24: =Progress!I18 -> 0 | J24: =IFERROR(IF(ISBLANK(G24),"",G24/C24),0) -> 0 | K24: =IFERROR(IF(ISBLANK(H24),"",H24/C24),0) -> 0 | L24: =IFERROR(IF(ISBLANK(I24),"",I24/C24),0) -> 0 | M24: =IFERROR(L24-K24,"") -> 0 | N24: =IFERROR(L24/K24,"") | O24: =Progress!L18 -> 0 | P24: =IF(ISBLANK(O24),"",O24/$O$28) -> 0 | Q24: =Progress!N18 -> 0 | R24: =Progress!O18 -> 0 | S24: =IFERROR(IF(ISBLANK(Q24),"",Q24/O24),0) -> 0 | T24: =IFERROR(IF(ISBLANK(R24),"",R24/O24),0) -> 0 | U24: =Progress!P18 -> 0 | V24: =Progress!Q18 -> 0 | W24: =IFERROR(IF(ISBLANK(U24),"",U24/O24),0) -> 0 | X24: =IFERROR(IF(ISBLANK(V24),"",V24/O24),0) -> 0 | Y24: =IFERROR(X24-W24,"") -> 0 | Z24: =IFERROR(X24/W24,"")
C25: =Progress!C19 -> 0 | D25: =Progress!D19 -> 0 | E25: =Progress!E19 -> 0 | F25: =Progress!F19 -> 0 | G25: =Progress!G19 -> 0 | H25: =Progress!H19 -> 0 | I25: =Progress!I19 -> 0 | J25: =IFERROR(IF(ISBLANK(G25),"",G25/C25),0) -> 0 | K25: =IFERROR(IF(ISBLANK(H25),"",H25/C25),0) -> 0 | L25: =IFERROR(IF(ISBLANK(I25),"",I25/C25),0) -> 0 | M25: =IFERROR(L25-K25,"") -> 0 | N25: =IFERROR(L25/K25,"") | O25: =Progress!L19 -> 0 | P25: =IF(ISBLANK(O25),"",O25/$O$28) -> 0 | Q25: =Progress!N19 -> 0 | R25: =Progress!O19 -> 0 | S25: =IFERROR(IF(ISBLANK(Q25),"",Q25/O25),0) -> 0 | T25: =IFERROR(IF(ISBLANK(R25),"",R25/O25),0) -> 0 | U25: =Progress!P19 -> 0 | V25: =Progress!Q19 -> 0 | W25: =IFERROR(IF(ISBLANK(U25),"",U25/O25),0) -> 0 | X25: =IFERROR(IF(ISBLANK(V25),"",V25/O25),0) -> 0 | Y25: =IFERROR(X25-W25,"") -> 0 | Z25: =IFERROR(X25/W25,"")
C26: =Progress!C20 -> 0 | D26: =Progress!D20 -> 0 | E26: =Progress!E20 -> 0 | F26: =Progress!F20 -> 0 | G26: =Progress!G20 -> 0 | H26: =Progress!H20 -> 0 | I26: =Progress!I20 -> 0 | J26: =IFERROR(IF(ISBLANK(G26),"",G26/C26),0) -> 0 | K26: =IFERROR(IF(ISBLANK(H26),"",H26/C26),0) -> 0 | L26: =IFERROR(IF(ISBLANK(I26),"",I26/C26),0) -> 0 | M26: =IFERROR(L26-K26,"") -> 0 | N26: =IFERROR(L26/K26,"") | O26: =Progress!L20 -> 0 | P26: =IF(ISBLANK(O26),"",O26/$O$28) -> 0 | Q26: =Progress!N20 -> 0 | R26: =Progress!O20 -> 0 | S26: =IFERROR(IF(ISBLANK(Q26),"",Q26/O26),0) -> 0 | T26: =IFERROR(IF(ISBLANK(R26),"",R26/O26),0) -> 0 | U26: =Progress!P20 -> 0 | V26: =Progress!Q20 -> 0 | W26: =IFERROR(IF(ISBLANK(U26),"",U26/O26),0) -> 0 | X26: =IFERROR(IF(ISBLANK(V26),"",V26/O26),0) -> 0 | Y26: =IFERROR(X26-W26,"") -> 0 | Z26: =IFERROR(X26/W26,"")
C27: =Progress!C21 -> 0 | D27: =Progress!D21 -> 0 | E27: =Progress!E21 -> 0 | F27: =Progress!F21 -> 0 | G27: =Progress!G21 -> 0 | H27: =Progress!H21 -> 0 | I27: =Progress!I21 -> 0 | J27: =IFERROR(IF(ISBLANK(G27),"",G27/C27),0) -> 0 | K27: =IFERROR(IF(ISBLANK(H27),"",H27/C27),0) -> 0 | L27: =IFERROR(IF(ISBLANK(I27),"",I27/C27),0) -> 0 | M27: =IFERROR(L27-K27,"") -> 0 | N27: =IFERROR(L27/K27,"") | O27: =Progress!L21 -> 0 | P27: =IF(ISBLANK(O27),"",O27/$O$28) -> 0 | Q27: =Progress!N21 -> 0 | R27: =Progress!O21 -> 0 | S27: =IFERROR(IF(ISBLANK(Q27),"",Q27/O27),0) -> 0 | T27: =IFERROR(IF(ISBLANK(R27),"",R27/O27),0) -> 0 | U27: =Progress!P21 -> 0 | V27: =Progress!Q21 -> 0 | W27: =IFERROR(IF(ISBLANK(U27),"",U27/O27),0) -> 0 | X27: =IFERROR(IF(ISBLANK(V27),"",V27/O27),0) -> 0 | Y27: =IFERROR(X27-W27,"") -> 0 | Z27: =IFERROR(X27/W27,"")
B28: Total | C28: =Progress!C25 -> 33793604 | D28: =Progress!D25 -> 1 | E28: =SUM(E12:E22) -> 3299377 | F28: =SUM(F12:F22) -> 1643974.8 | G28: =Progress!G25 -> 3561002.2 | H28: =Progress!H25 -> 13223723 | I28: =Progress!I25 -> 11959715 | J28: =IFERROR(IF(ISBLANK(G28),"",G28/C28),0) -> 0.10537503 | K28: =IFERROR(IF(ISBLANK(H28),"",H28/C28),0) -> 0.39130844 | L28: =IFERROR(IF(ISBLANK(I28),"",I28/C28),0) -> 0.35390468 | M28: =+L28-K28 -> -0.037403761 | N28: =L28/K28 -> 0.90441361 | O28: =Progress!L25 -> 406255 | P28: =Progress!M25 -> 1 | Q28: =Progress!N25 -> 16483.97 | R28: =Progress!O25 -> 13888.1 | S28: =IFERROR(IF(ISBLANK(Q28),"",Q28/O28),0) -> 0.040575427 | T28: =IFERROR(IF(ISBLANK(R28),"",R28/O28),0) -> 0.034185672 | U28: =Progress!P25 -> 207295.92 | V28: =Progress!Q25 -> 172298.3 | W28: =IFERROR(IF(ISBLANK(U28),"",U28/O28),0) -> 0.5102606 | X28: =IFERROR(IF(ISBLANK(V28),"",V28/O28),0) -> 0.42411367 | Y28: =+X28-W28 -> -0.086146927 | Z28: =X28/W28 -> 0.83117072
AA29: Construction Milestones
AA30: Item No. | AB30: Milestones | AD30: Original (Baseline) | AE30: Latest Plan | AF30: Forecast | AG30: Status | AH30: Days Change
AA31: =+Milestones!A4 -> 1 | AB31: =+Milestones!B4 -> Project Finish | AD31: =+Milestones!D4 -> 46412 | AE31: =+Milestones!E4 -> 46516 | AF31: =+Milestones!E4 -> 46516 | AG31: =+Milestones!F4 -> F | AH31: =+Milestones!G4 -> -104
Z32: =+Milestones!#REF! -> #REF! | AA32: =+Milestones!A5 -> 2 | AB32: =+Milestones!B5 -> Project Start | AD32: =+Milestones!D5 -> 46107 | AE32: =+Milestones!E5 -> 46107 | AF32: =+Milestones!E5 -> 46107 | AG32: =+Milestones!F5 -> A | AH32: =+Milestones!G5 -> 0
Z33: =+Milestones!#REF! -> #REF! | AA33: =+Milestones!A6 -> 3 | AB33: =+Milestones!B6 -> Baseline Programme Approval | AD33: =+Milestones!D6 -> 46141 | AE33: =+Milestones!E6 -> 46141 | AF33: =+Milestones!E6 -> 46141 | AG33: =+Milestones!F6 -> A | AH33: =+Milestones!G6 -> 0
Z34: =+Milestones!#REF! -> #REF! | AA34: =+Milestones!A7 -> 4 | AB34: =+Milestones!B7 -> Completion of Mobilization | AD34: =+Milestones!D7 -> 46175 | AE34: =+Milestones!E7 -> 46175 | AF34: =+Milestones!E7 -> 46175 | AG34: =+Milestones!F7 -> A | AH34: =+Milestones!G7 -> 0
Z35: =+Milestones!#REF! -> #REF! | AA35: =+Milestones!A8 -> 5 | AB35: =+Milestones!B8 -> Completion of Levelling Works | AD35: =+Milestones!D8 -> 46225 | AE35: =+Milestones!E8 -> 46315 | AF35: =+Milestones!E8 -> 46315 | AG35: =+Milestones!F8 -> F | AH35: =+Milestones!G8 -> -90
Z36: =+Milestones!#REF! -> #REF! | AA36: =+Milestones!A9 -> 6 | AB36: =+Milestones!B9 -> Completion of Engineering | AD36: =+Milestones!D9 -> 46406 | AE36: =+Milestones!E9 -> 46331 | AF36: =+Milestones!E9 -> 46331 | AG36: =+Milestones!F9 -> F | AH36: =+Milestones!G9 -> 75
G37: 20000000 | Z37: =+Milestones!#REF! -> #REF! | AA37: =+Milestones!A10 -> 7 | AB37: =+Milestones!B10 -> Completion of Toilet Building | AD37: =+Milestones!D10 -> 46243 | AE37: =+Milestones!E10 -> 46391 | AF37: =+Milestones!E10 -> 46391 | AG37: =+Milestones!F10 -> F | AH37: =+Milestones!G10 -> -148
AA38: =+Milestones!A11 -> 8 | AB38: =+Milestones!B11 -> Completion of Natural Landscape Works | AD38: =+Milestones!D11 -> 46403 | AE38: =+Milestones!E11 -> 46454 | AF38: =+Milestones!E11 -> 46454 | AG38: =+Milestones!F11 -> F | AH38: =+Milestones!G11 -> -51
AA39: =+Milestones!A12 -> 9 | AB39: =+Milestones!B12 -> Completion of Playground Area | AD39: =+Milestones!D12 -> 46356 | AE39: =+Milestones!E12 -> 46506 | AF39: =+Milestones!E12 -> 46506 | AG39: =+Milestones!F12 -> F | AH39: =+Milestones!G12 -> -150
Z40: =+Milestones!#REF! -> #REF! | AA40: =+Milestones!A13 -> 10 | AB40: =+Milestones!B13 -> Completion of Asir Works | AD40: =+Milestones!D13 -> 46369 | AE40: =+Milestones!E13 -> 46475 | AF40: =+Milestones!E13 -> 46475 | AG40: =+Milestones!F13 -> F | AH40: =+Milestones!G13 -> -106
Z41: =+Milestones!#REF! -> #REF!
Z42: =+Milestones!#REF! -> #REF! | AG42: This Week
Z43: =+Milestones!#REF! -> #REF!
Z44: =+Milestones!#REF! -> #REF!
G45: 20000000 | Z45: =+Milestones!#REF! -> #REF!
Z48: =+Milestones!#REF! -> #REF!
Z49: =+Milestones!#REF! -> #REF!
A65: Performance overview
A66: Submittals Status | L66: Quality | W66: Safety
A67: Shop Drawings | L67: Quality Reports | W67: Safety Statistics | AE67: Proactive Vs Reactive Actions Taken
A68: Item Per WBS | C68: Total | D68: Total Submitted Drawings | I68: Remaining | J68: Pending | K68: Total Submittals | L68: Quality Reports | N68: Issued | O68: Closed | P68: Pending | Q68: Avg. Closing (Days) | R68: Pending | W68: Category | X68: Item | AB68: This Month | AC68: Year to Date | AD68: Cumulative
D69: A | E69: B | F69: C | G69: D | H69: Processed | R69: 0-10 Days | S69: 11-20 Days | T69: 21-30 Days | U69: 31-60 Days | V69: > 60 Days
A70: ='Quality-Stat '!A13 -> Civil/Structure | C70: ='Quality-Stat '!D13 -> 36 | D70: ='Quality-Stat '!E13 -> 6 | E70: ='Quality-Stat '!F13 -> 24 | F70: ='Quality-Stat '!G13 -> 1 | G70: ='Quality-Stat '!H13 -> 3 | H70: ='Quality-Stat '!I13 -> 34 | I70: ='Quality-Stat '!J13 -> 0 | J70: ='Quality-Stat '!K13 -> 3 | K70: ='Quality-Stat '!L13 -> 37 | W70: General | X70: Total Hours Worked | Z70: ='[44]HSE-Stat'!D4 -> 6480 | AB70: ='[44]HSE-Stat'!E4 -> 6480 | AC70: ='[44]HSE-Stat'!F4 -> 132050 | AD70: ='[44]HSE-Stat'!G4 -> 132050 | AG70: Proactive | AH70: =+SUM(AD81:AD85) -> 160
A71: ='Quality-Stat '!A14 -> Architecture | C71: ='Quality-Stat '!D14 -> 19 | D71: ='Quality-Stat '!E14 -> 4 | E71: ='Quality-Stat '!F14 -> 14 | F71: ='Quality-Stat '!G14 -> 1 | G71: ='Quality-Stat '!H14 -> 0 | H71: ='Quality-Stat '!I14 -> 19 | I71: ='Quality-Stat '!J14 -> 0 | J71: ='Quality-Stat '!K14 -> 0 | K71: ='Quality-Stat '!L14 -> 19 | L71: Non Conformance (NCR) | N71: ='Quality-Stat '!D5 -> 20 | O71: ='Quality-Stat '!E5 -> 20 | P71: ='Quality-Stat '!F5 -> 0 | Q71: ='Quality-Stat '!G5 -> 0 | R71: ='Quality-Stat '!H5 -> 2 | S71: ='Quality-Stat '!I5 -> 0 | T71: ='Quality-Stat '!J5 -> 0 | U71: ='Quality-Stat '!K5 -> 0 | V71: ='Quality-Stat '!L5 -> 0 | X71: Safe Hours Worked | Z71: ='[44]HSE-Stat'!D5 -> 6480 | AB71: ='[44]HSE-Stat'!E5 -> 6480 | AC71: ='[44]HSE-Stat'!F5 -> 132050 | AD71: ='[44]HSE-Stat'!G5 -> 132050 | AG71: Reactive | AH71: =SUM(AD72:AD80) -> 0
A72: ='Quality-Stat '!A15 -> Mechanical | C72: ='Quality-Stat '!D15 -> 25 | D72: ='Quality-Stat '!E15 -> 0 | E72: ='Quality-Stat '!F15 -> 18 | F72: ='Quality-Stat '!G15 -> 6 | G72: ='Quality-Stat '!H15 -> 0 | H72: ='Quality-Stat '!I15 -> 24 | I72: ='Quality-Stat '!J15 -> 0 | J72: ='Quality-Stat '!K15 -> 1 | K72: ='Quality-Stat '!L15 -> 25 | L72: Site Instruction (SIR) | N72: ='Quality-Stat '!D6 -> 25 | O72: ='Quality-Stat '!E6 -> 25 | P72: ='Quality-Stat '!F6 -> 0 | Q72: ='Quality-Stat '!G6 -> 0 | R72: ='Quality-Stat '!H6 -> 0 | S72: ='Quality-Stat '!I6 -> 3 | T72: ='Quality-Stat '!J6 -> 0 | U72: ='Quality-Stat '!K6 -> 0 | V72: ='Quality-Stat '!L6 -> 0 | W72: Reactive | X72: LTI | Z72: ='[44]HSE-Stat'!D6 -> 0 | AB72: ='[44]HSE-Stat'!E6 -> 0 | AC72: ='[44]HSE-Stat'!F6 -> 0 | AD72: ='[44]HSE-Stat'!G6 -> 0
A73: ='Quality-Stat '!A16 -> Electrical | C73: ='Quality-Stat '!D16 -> 37 | D73: ='Quality-Stat '!E16 -> 0 | E73: ='Quality-Stat '!F16 -> 34 | F73: ='Quality-Stat '!G16 -> 0 | G73: ='Quality-Stat '!H16 -> 3 | H73: ='Quality-Stat '!I16 -> 37 | I73: ='Quality-Stat '!J16 -> 0 | J73: ='Quality-Stat '!K16 -> 0 | K73: ='Quality-Stat '!L16 -> 37 | L73: Material Inspection (MIR) | N73: ='Quality-Stat '!D7 -> 102 | O73: ='Quality-Stat '!E7 -> 99 | P73: ='Quality-Stat '!F7 -> 2 | Q73: ='Quality-Stat '!G7 -> 0 | R73: ='Quality-Stat '!H7 -> 11 | S73: ='Quality-Stat '!I7 -> 0 | T73: ='Quality-Stat '!J7 -> 0 | U73: ='Quality-Stat '!K7 -> 0 | V73: ='Quality-Stat '!L7 -> 0 | X73: MTC (Healed w/o Disability) | Z73: ='[44]HSE-Stat'!D7 -> 0 | AB73: ='[44]HSE-Stat'!E7 -> 0 | AC73: ='[44]HSE-Stat'!F7 -> 0 | AD73: ='[44]HSE-Stat'!G7 -> 0
A74: ='Quality-Stat '!A17 -> Landscape | C74: ='Quality-Stat '!D17 -> 23 | D74: ='Quality-Stat '!E17 -> 7 | E74: ='Quality-Stat '!F17 -> 14 | F74: ='Quality-Stat '!G17 -> 2 | G74: ='Quality-Stat '!H17 -> 0 | H74: ='Quality-Stat '!I17 -> 23 | I74: ='Quality-Stat '!J17 -> 0 | J74: ='Quality-Stat '!K17 -> 0 | K74: ='Quality-Stat '!L17 -> 23 | L74: Field Inspection (FIR) | N74: ='Quality-Stat '!D8 -> 657 | O74: ='Quality-Stat '!E8 -> 634 | P74: ='Quality-Stat '!F8 -> 22 | Q74: ='Quality-Stat '!G8 -> 0 | R74: ='Quality-Stat '!H8 -> 46 | S74: ='Quality-Stat '!I8 -> 0 | T74: ='Quality-Stat '!J8 -> 0 | U74: ='Quality-Stat '!K8 -> 0 | V74: ='Quality-Stat '!L8 -> 0 | X74: MTC (Healed w/ Disability) | Z74: ='[44]HSE-Stat'!D8 -> 0 | AB74: ='[44]HSE-Stat'!E8 -> 0 | AC74: ='[44]HSE-Stat'!F8 -> 0 | AD74: ='[44]HSE-Stat'!G8 -> 0
L75: Key Submittals Approval Status | X75: Near Miss | Z75: ='[44]HSE-Stat'!D9 -> 0 | AB75: ='[44]HSE-Stat'!E9 -> 0 | AC75: ='[44]HSE-Stat'!F9 -> 0 | AD75: ='[44]HSE-Stat'!G9 -> 0
A76: TOTAL | C76: ='Quality-Stat '!D18 -> 140 | D76: ='Quality-Stat '!E18 -> 17 | E76: ='Quality-Stat '!F18 -> 104 | F76: ='Quality-Stat '!G18 -> 10 | G76: ='Quality-Stat '!H18 -> 6 | H76: ='Quality-Stat '!I18 -> 137 | I76: ='Quality-Stat '!J18 -> 0 | J76: ='Quality-Stat '!K18 -> 4 | K76: ='Quality-Stat '!L18 -> 141 | L76: 1 Quality Plan Approval | O76: ='General Information'!C27 -> 46142 | Q76: 6 Baseline Approval | U76: ='General Information'!C39 -> 46140 | X76: First Aid Cases | Z76: ='[44]HSE-Stat'!D10 -> 0 | AB76: ='[44]HSE-Stat'!E10 -> 0 | AC76: ='[44]HSE-Stat'!F10 -> 0 | AD76: ='[44]HSE-Stat'!G10 -> 0 | AE76: Total Hours Worked Vs Safe Hours Worked
A77: Material Approval | L77: 2 Quality Plan Last Up | O77: ='General Information'!C28 -> - | Q77: 7 No of Approved Version of Schedule | U77: ='General Information'!C40 -> - | X77: Fatality | Z77: ='[44]HSE-Stat'!D11 -> 0 | AB77: ='[44]HSE-Stat'!E11 -> 0 | AC77: ='[44]HSE-Stat'!F11 -> 0 | AD77: ='[44]HSE-Stat'!G11 -> 0
A78: Item Per WBS | C78: Total | D78: Total Submitted Material | I78: Remaining to approve | J78: Pending | K78: Total Submittals | L78: 3 Safety Plan Approval | O78: ='General Information'!C31 -> 46184 | Q78: 8 Last Approved Schedule | U78: ='General Information'!C41 -> - | X78: Fire Incident Cases | Z78: ='[44]HSE-Stat'!D12 -> 0 | AB78: ='[44]HSE-Stat'!E12 -> 0 | AC78: ='[44]HSE-Stat'!F12 -> 0 | AD78: ='[44]HSE-Stat'!G12 -> 0
D79: A | E79: B | F79: C | G79: D | H79: Processed | I79: with Designer | L79: 4 Safety Plan Last Up | O79: ='General Information'!C32 -> - | Q79: 9 BOQ Approval Date | U79: ='General Information'!C44 -> 45918 | X79: Vehicle Incident | Z79: ='[44]HSE-Stat'!D13 -> 0 | AB79: ='[44]HSE-Stat'!E13 -> 0 | AC79: ='[44]HSE-Stat'!F13 -> 0 | AD79: ='[44]HSE-Stat'!G13 -> 0
A80: ='Quality-Stat '!A23 -> Civil/Structure | C80: ='Quality-Stat '!D23 -> 52 | D80: ='Quality-Stat '!E23 -> 2 | E80: ='Quality-Stat '!F23 -> 40 | F80: ='Quality-Stat '!G23 -> 7 | G80: ='Quality-Stat '!H23 -> 2 | H80: ='Quality-Stat '!I23 -> 42 | I80: ='Quality-Stat '!J23 -> 0 | J80: ='Quality-Stat '!K23 -> 1 | K80: ='Quality-Stat '!L23 -> 51 | L80: 5 Construction Plan Approval | O80: ='General Information'!C48 -> 46155 | Q80: 10 No of Approved Version of BOQ | U80: ='General Information'!C45 -> 0 | X80: Property Damages | Z80: ='[44]HSE-Stat'!D14 -> 0 | AB80: ='[44]HSE-Stat'!E14 -> 0 | AC80: ='[44]HSE-Stat'!F14 -> 0 | AD80: ='[44]HSE-Stat'!G14 -> 0
A81: ='Quality-Stat '!A24 -> Architecture | C81: ='Quality-Stat '!D24 -> 26 | D81: ='Quality-Stat '!E24 -> 2 | E81: ='Quality-Stat '!F24 -> 24 | F81: ='Quality-Stat '!G24 -> 0 | G81: ='Quality-Stat '!H24 -> 0 | H81: ='Quality-Stat '!I24 -> 26 | I81: ='Quality-Stat '!J24 -> 0 | J81: ='Quality-Stat '!K24 -> 0 | K81: ='Quality-Stat '!L24 -> 26 | L81: Invoices Summary | W81: Proactive | X81: Induction Training | Z81: ='[44]HSE-Stat'!D15 -> 0 | AB81: ='[44]HSE-Stat'!E15 -> 18 | AC81: ='[44]HSE-Stat'!F15 -> 160 | AD81: ='[44]HSE-Stat'!G15 -> 160
A82: ='Quality-Stat '!A25 -> Mechanical | C82: ='Quality-Stat '!D25 -> 33 | D82: ='Quality-Stat '!E25 -> 0 | E82: ='Quality-Stat '!F25 -> 31 | F82: ='Quality-Stat '!G25 -> 2 | G82: ='Quality-Stat '!H25 -> 0 | H82: ='Quality-Stat '!I25 -> 31 | I82: ='Quality-Stat '!J25 -> 0 | J82: ='Quality-Stat '!K25 -> 0 | K82: ='Quality-Stat '!L25 -> 33 | L82: Total Submitted Invoices | N82: ='Invoice Log'!V3 -> 5 | O82: Submitted Invoices (SAR) | R82: ='Invoice Log'!Z3 -> 4943710.6 | T82: Contract Value (SR) | U82: =O4 -> 33793604 | X82: No.of Internal Training | Z82: ='[44]HSE-Stat'!D16 -> 1 | AB82: ='[44]HSE-Stat'!E16 -> 04 Session | AC82: ='[44]HSE-Stat'!F16 -> 17 Session | AD82: ='[44]HSE-Stat'!G16 -> 17 Session
A83: ='Quality-Stat '!A26 -> Electrical | C83: ='Quality-Stat '!D26 -> 36 | D83: ='Quality-Stat '!E26 -> 0 | E83: ='Quality-Stat '!F26 -> 31 | F83: ='Quality-Stat '!G26 -> 4 | G83: ='Quality-Stat '!H26 -> 1 | H83: ='Quality-Stat '!I26 -> 31 | I83: ='Quality-Stat '!J26 -> 0 | J83: ='Quality-Stat '!K26 -> 1 | K83: ='Quality-Stat '!L26 -> 37 | L83: PM Approved Invoices | N83: ='Invoice Log'!V5 -> 0 | O83: PM Approved Invoices (SAR) | R83: ='Invoice Log'!Z5 -> 0 | T83: Planned Value (SR) | U83: =H28 -> 13223723 | X83: No.of Internal Audit | Z83: ='[44]HSE-Stat'!D17 -> 0 | AB83: ='[44]HSE-Stat'!E17 -> 0 | AC83: ='[44]HSE-Stat'!F17 -> 0 | AD83: ='[44]HSE-Stat'!G17 -> 0
L84: No of Paid Invoices | N84: ='Invoice Log'!V6 -> 0 | O84: Paid Invoices (SAR) | R84: ='Invoice Log'!Z6 -> 0 | T84: Earned Value (SR) | U84: =I28 -> 11959715 | X84: No. of Toolbox Talks | Z84: ='[44]HSE-Stat'!D18 -> 4 | AB84: ='[44]HSE-Stat'!E18 -> 4 Sessions | AC84: ='[44]HSE-Stat'!F18 -> 156 sessions | AD84: ='[44]HSE-Stat'!G18 -> 156 sessions
A85: TOTAL | C85: ='Quality-Stat '!D28 -> 147 | D85: ='Quality-Stat '!E28 -> 4 | E85: ='Quality-Stat '!F28 -> 126 | F85: ='Quality-Stat '!G28 -> 13 | G85: ='Quality-Stat '!H28 -> 3 | H85: ='Quality-Stat '!I28 -> 130 | I85: ='Quality-Stat '!J28 -> 0 | J85: ='Quality-Stat '!K28 -> 2 | K85: ='Quality-Stat '!L28 -> 147 | L85: No of Pending Invoices | N85: =+N82-N84 -> 5 | O85: Last Submitted Period | R85: ='Invoice Log'!AC3 -> 46303 | T85: Submitted (SAR) | U85: =R82 -> 4943710.6 | X85: Safety Awards/Incentives | Z85: ='[44]HSE-Stat'!D19 -> 0 | AB85: ='[44]HSE-Stat'!E19 -> 0 | AC85: ='[44]HSE-Stat'!F19 -> 0 | AD85: ='[44]HSE-Stat'!G19 -> 0
A86: Procurement Summary | L86: Advance Payment % | N86: ='Invoice Log'!N3 -> 0 | O86: Advance Payment (SAR) | R86: ='Invoice Log'!R3 -> 0 | T86: PM Approved (SAR) | U86: =R83 -> 0 | W86: Latest Contract Change Order Log
A87: Item Per WBS | C87: Total Materials Planned | D87: Total Number of P.O. | E87: Actual P.O. To Date | F87: Remaining P.O | G87: Actual Material on Site | H87: Remaining Materials | I87: Material Delivery Completion (Date) | L87: Retention % | N87: ='Invoice Log'!N4 -> 0 | O87: Retention (SAR) | R87: ='Invoice Log'!R4 -> 0 | T87: Total Paid (SAR) | U87: =R84 -> 0
D88: A | E88: B | F88: C | G88: D | H88: Processed | L88: Deduction / Penalties % | N88: ='Invoice Log'!N5 -> 0.00032355047 | O88: Deduction / Penalties (SAR) | R88: ='Invoice Log'!N6 -> 11000 | W88: CCO No. | X88: Date Added | Y88: Description of Change | AD88: Status | AE88: Cost | AF88: Sch Impact (Months) | AG88: Date Approved | AH88: Duration
A89: ='Quality-Stat '!A33 -> Civil/Structure | C89: ='Quality-Stat '!D33 -> 22 | D89: ='Quality-Stat '!E33 -> 27 | E89: ='Quality-Stat '!F33 -> 5 | F89: ='Quality-Stat '!G33 -> 22 | G89: ='Quality-Stat '!H33 -> 5 | H89: ='Quality-Stat '!I33 -> 22 | I89: ='Quality-Stat '!J33 -> 0 | J89: ='Quality-Stat '!K33 -> 0 | K89: ='Quality-Stat '!L33 -> 0 | L89: Resources at Site
A90: ='Quality-Stat '!A34 -> Architecture | C90: ='Quality-Stat '!D34 -> 30 | D90: ='Quality-Stat '!E34 -> 18 | E90: ='Quality-Stat '!F34 -> 14 | F90: ='Quality-Stat '!G34 -> 4 | G90: ='Quality-Stat '!H34 -> 7 | H90: ='Quality-Stat '!I34 -> 11 | I90: ='Quality-Stat '!J34 -> 0 | J90: ='Quality-Stat '!K34 -> 0 | K90: ='Quality-Stat '!L34 -> 0 | L90: Head Count - Manual | P90: Head Count - Non Manual | T90: Total Head Count | W90: =CCO!A3 -> - | X90: =CCO!B3 -> - | Y90: =CCO!C3 -> - | AD90: =CCO!D3 -> - | AE90: =CCO!E3 -> - | AF90: =CCO!F3 -> - | AG90: =CCO!G3 -> - | AH90: =CCO!H3 -> -
A91: ='Quality-Stat '!A35 -> Mechanical | C91: ='Quality-Stat '!D35 -> 30 | D91: ='Quality-Stat '!E35 -> 18 | E91: ='Quality-Stat '!F35 -> 10 | F91: ='Quality-Stat '!G35 -> 8 | G91: ='Quality-Stat '!H35 -> 7 | H91: ='Quality-Stat '!I35 -> 11 | I91: ='Quality-Stat '!J35 -> 0 | J91: ='Quality-Stat '!K35 -> 0 | K91: ='Quality-Stat '!L35 -> 0 | L91: Planned | M91: Actual | N91: Next Month Forecast | O91: Saudi Staff | P91: Planned | Q91: Actual | R91: Next Month Forecast | S91: Saudi Staff | T91: Total Plan | U91: Total Actual | V91: Variance
A92: ='Quality-Stat '!A36 -> Electrical | C92: ='Quality-Stat '!D36 -> 35 | D92: ='Quality-Stat '!E36 -> 13 | E92: ='Quality-Stat '!F36 -> 6 | F92: ='Quality-Stat '!G36 -> 7 | G92: ='Quality-Stat '!H36 -> 3 | H92: ='Quality-Stat '!I36 -> 10 | I92: ='Quality-Stat '!J36 -> 0 | J92: ='Quality-Stat '!K36 -> 0 | K92: ='Quality-Stat '!L36 -> 0 | L92: =Manpower!A24 -> 175 | M92: =Manpower!B24 -> 70 | N92: =Manpower!F24 -> 140 | O92: =Manpower!H24 -> 0 | P92: =Manpower!A20 -> 19 | Q92: =Manpower!B20 -> 30 | R92: =Manpower!F20 -> 25 | S92: =Manpower!H20 -> 0 | T92: =L92+P92 -> 194 | U92: =M92+Q92 -> 100 | V92: =+U92-T92 -> -94
L93: Manpower Breakdown by Trade | S93: Major Equipment
A94: TOTAL | C94: ='Quality-Stat '!D38 -> 117 | D94: ='Quality-Stat '!E38 -> 76 | E94: ='Quality-Stat '!F38 -> 35 | F94: ='Quality-Stat '!G38 -> 41 | G94: ='Quality-Stat '!H38 -> 22 | H94: ='Quality-Stat '!I38 -> 54 | I94: =MAX(I89:K92) -> 0 | L94: Key Trade | M94: Planned | N94: Actual | S94: Type | T94: Planned | U94: Actual | V94: Idle
A95: =Schedule!A1 -> Primavera P6 Schedule Status | L95: =+Manpower!N23 -> Labor | M95: =Manpower!N24 -> 65 | N95: =Manpower!N25 -> 15 | S95: =+Manpower!$B$49 -> Excavator | T95: =+Manpower!B50 -> 3 | U95: =+Manpower!B51 -> 3 | V95: =+Manpower!B52 -> 0
A96: =Schedule!A2 -> Project Activities Overview | L96: =+Manpower!P23 -> Skilled Labor | M96: =Manpower!P24 -> 25 | N96: =Manpower!P25 -> 10 | S96: =+Manpower!$D$49 -> Bulldozer | T96: =+Manpower!D50 -> 2 | U96: =+Manpower!D51 -> 0 | V96: =+Manpower!D52 -> 0 | W96: Major Quantity Trackers
A97: =Schedule!A3 -> Schedule Statistics | F97: =Schedule!F3 -> Active Schedule Activities | L97: =+Manpower!R23 -> Driver / Operator | M97: =+Manpower!R24 -> 27 | N97: =Manpower!R25 -> 12 | S97: =+Manpower!$F$49 -> Grader | T97: =+Manpower!F50 -> 3 | U97: =+Manpower!F51 -> 0 | V97: =+Manpower!F52 -> 0 | W97: BOQ N0. | X97: Item Description | AC97: Total Qty | AD97: Measu Unit | AE97: Plan to Date | AF97: Act to Date | AG97: Remaining | AH97: Variance
A98: =Schedule!A4 -> Total Act. | B98: =Schedule!B4 -> Not Started | C98: =Schedule!C4 -> In Progress | D98: =Schedule!D4 -> Completed | E98: =Schedule!E4 -> % | F98: =Schedule!F4 -> Active | G98: =Schedule!G4 -> Ahead | H98: =Schedule!H4 -> On | ... K98: =Schedule!K4 -> 0 | L98: =+Manpower!T23 -> Carpenter | M98: =Manpower!T24 -> 0 | N98: =Manpower!T25 -> 6 | S98: =+Manpower!$H$49 -> Road Roller | T98: =+Manpower!H50 -> 1 | U98: =+Manpower!H51 -> 0 | V98: =+Manpower!H52 -> 0 | W98: ='Major Quantities'!A3 -> 2.3.1 | X98: ='Major Quantities'!B4 -> Supply and plant trees | AC98: ='Major Quantities'!C4 -> 895 | AD98: ='Major Quantities'!D4 -> Nos. | AE98: ='Major Quantities'!E3 -> 0 | AF98: ='Major Quantities'!F3 -> 0 | AG98: ='Major Quantities'!G3 -> 30380 | AH98: ='Major Quantities'!H3 -> 0
A99: =Schedule!A5 -> 2134 | B99: =Schedule!B5 -> 385 | C99: =Schedule!C5 -> 21 | D99: =Schedule!D5 -> 1728 | E99: =Schedule!E5 -> 0.80974695 | F99: =Schedule!F5 -> 21 | G99: =Schedule!G5 -> 40 | H99: =Schedule!H5 -> 145 | ... J99: =Schedule!J5 -> -36 | L99: =+Manpower!V23 -> Steel Fixer | M99: =+Manpower!V24 -> 26 | N99: =+Manpower!V25 -> 6 | S99: =+Manpower!$J$49 -> Crane | T99: =+Manpower!J50 -> 0 | U99: =+Manpower!J51 -> 0 | V99: =+Manpower!J52 -> 0 | W99: ='Major Quantities'!A6 -> 2.3.10 | X99: ='Major Quantities'!B7 -> Supply and cast Concrete | AC99: ='Major Quantities'!C7 -> 145 | AD99: ='Major Quantities'!D7 -> m³ | AE99: ='Major Quantities'!E6 -> 0 | AF99: ='Major Quantities'!F6 -> 0 | AG99: ='Major Quantities'!G6 -> 248 | AH99: ='Major Quantities'!H6 -> 0
A100: =Schedule!A6 -> Critical Path Activities | D100: =Schedule!D6 -> Free Float Management (Total) | H100: =Schedule!H6 -> Failed Start Activities | L100: =+Manpower!X23 -> Mason | M100: =+Manpower!X24 -> 0 | N100: =+Manpower!X25 -> 0 | S100: =+Manpower!$L$49 -> Bobcat | T100: =+Manpower!L50 -> 0 | U100: =+Manpower!L51 -> 2 | V100: =+Manpower!L52 -> 0 | W100: ='Major Quantities'!A8 -> 9.1.1 | X100: ='Major Quantities'!B9 -> CEILING FINISHES | AC100: ='Major Quantities'!C9 -> 207 | AD100: ='Major Quantities'!D9 -> m² | AE100: ='Major Quantities'!E8 -> 0 | AF100: ='Major Quantities'!F8 -> 0 | AG100: ='Major Quantities'!G8 -> 219 | AH100: ='Major Quantities'!H8 -> 0
D101: =Schedule!D7 -> Greater Than 14 Days | F101: =Schedule!F7 -> Less Than 14 Days | L101: =Manpower!Z23 -> Plumber | M101: =Manpower!Z24 -> 0 | N101: =Manpower!Z25 -> 3 | S101: =+Manpower!$N$49 -> Other | T101: =+Manpower!N50 -> 0 | U101: =+Manpower!N51 -> 0 | V101: =+Manpower!N52 -> 0 | W101: ='Major Quantities'!A9 -> 9.3 | X101: ='Major Quantities'!B10 -> WATER SUPPLY SYSTEM for cold and hot water supply piping | AC101: ='Major Quantities'!C10 -> 138 | AD101: ='Major Quantities'!D10 -> Lm | AE101: ='Major Quantities'!E9 -> 0 | AF101: ='Major Quantities'!F9 -> 0 | AG101: ='Major Quantities'!G9 -> 207 | AH101: ='Major Quantities'!H9 -> 0
A102: =Schedule!A8 -> Last Week | B102: =Schedule!B8 -> This Week | C102: =Schedule!C8 -> Diff | D102: =Schedule!D8 -> Last Week | E102: =Schedule!E8 -> This Week | F102: =Schedule!F8 -> Last Week | G102: =Schedule!G8 -> This Week | H102: =Schedule!H8 -> Last Week | ... K102: =Schedule!K8 -> 0 | L102: Total | M102: =Manpower!AF24 -> 175 | N102: =Manpower!AF25 -> 70 | S102: Total | T102: =SUM(T95:T101) -> 9 | U102: =SUM(U95:U101) -> 5 | V102: =SUM(V95:V101) -> 0 | W102: ='Major Quantities'!A10 -> 15.2.1 | X102: ='Major Quantities'!B11 -> SEWER AND DRAINAGE PIPE | AC102: ='Major Quantities'!C11 -> 177 | AD102: ='Major Quantities'!D11 -> Lm | AE102: ='Major Quantities'!E10 -> 0 | AF102: ='Major Quantities'!F10 -> 14 | AG102: ='Major Quantities'!G10 -> 124 | AH102: ='Major Quantities'!H10 -> 14
A103: =Schedule!A9 -> 373 | B103: =Schedule!B9 -> 331 | C103: =Schedule!C9 -> 42 | D103: =Schedule!D9 -> 80 | E103: =Schedule!E9 -> 66 | F103: =Schedule!F9 -> 374 | G103: =Schedule!G9 -> 340 | H103: =Schedule!H9 -> 266 | ... J103: =Schedule!J9 -> 26
A104: Testing And Commissioning | P104: Top Issues and Risks
Q105: Top 5 Issues
A106: Item | B106: Planned Start Date | D106: Planned Finish Date | F106: Forecast Start Date | H106: Forecast Finish Date | J106: Actual Start Date | L106: Actual Finish Date | M106: % Completed | N106: Open Comments | O106: Closed Comments | P106: Issue No | R106: Date Identified | S106: Issue Description | V106: Responsible | X106: Action Taken | AC106: Mitigation | AF106: Current Status | AG106: Expected/Actual Closure | AH106: Duration Elapsed
P107: =IF(+Issues!B11="","",+Issues!B11) -> 1 | R107: =IF(+Issues!C11="","",+Issues!C11) | S107: =IF(+Issues!D11="","",+Issues!D11) -> Connection of the project to the drainage channel on the eastern side.(Jeddah) | V107: =IF(+Issues!E11="","",+Issues!E11) -> Contractor | X107: =IF(+Issues!F11="","",+Issues!F11) -> Coordination between the Municipality (City Management) and the infrastructure contractor. | AF107: =IF(+Issues!H11="","",+Issues!H11) -> Completed | AG107: =IF(+Issues!I11="","",+Issues!I11) -> 46163
P108: =IF(+Issues!B12="","",+Issues!B12) -> 2 | R108: =IF(+Issues!C12="","",+Issues!C12) | S108: =IF(+Issues!D12="","",+Issues!D12) -> drainage pipe was encountered during site excavation.(Jeddah) | V108: =IF(+Issues!E12="","",+Issues!E12) -> Owner | X108: =IF(+Issues!F12="","",+Issues!F12) -> The required calculations and slope analysis have been completed. | AF108: =IF(+Issues!H12="","",+Issues!H12) -> Completed | AG108: =IF(+Issues!I12="","",+Issues!I12) -> 46163
P109: =IF(+Issues!B13="","",+Issues!B13) -> 3 | R109: =IF(+Issues!C13="","",+Issues!C13) -> 46147 | S109: =IF(+Issues!D13="","",+Issues!D13) -> Based on the visit by Modon management, it was noted that the project level can be raised to match the external road level in front of the parking area.(Jeddah) | V109: =IF(+Issues!E13="","",+Issues!E13) -> Owner | X109: =IF(+Issues!F13="","",+Issues!F13) -> The required filling quantity was estimated at 59,000 m³ | AF109: =IF(+Issues!H13="","",+Issues!H13) -> Completed | AG109: =IF(+Issues!I13="","",+Issues!I13) -> 46163
P110: =IF(+Issues!B14="","",+Issues!B14) -> 4 | R110: =IF(+Issues!C14="","",+Issues!C14) | S110: =IF(+Issues!D14="","",+Issues!D14) -> Increase the sewage tank capacity for the Asir project to serve the administration building and playgrounds. | V110: =IF(+Issues!E14="","",+Issues!E14) -> Contractor | X110: =IF(+Issues!F14="","",+Issues!F14) -> Waiting for clarification of the project savings/cost reductions. | AF110: =IF(+Issues!H14="","",+Issues!H14) -> Completed | AG110: =IF(+Issues!I14="","",+Issues!I14) -> 46152
P111: =IF(+Issues!B15="","",+Issues!B15) -> 5 | R111: =IF(+Issues!C15="","",+Issues!C15) -> 46163 | S111: =IF(+Issues!D15="","",+Issues!D15) -> Difficulty accessing the parking area due to a level difference- Jazan | V111: =IF(+Issues!E15="","",+Issues!E15) -> Consultant | X111: =IF(+Issues!F15="","",+Issues!F15) -> Relocating the parking area to the far left side. | AF111: =IF(+Issues!H15="","",+Issues!H15) -> Completed | AG111: =IF(+Issues!I15="","",+Issues!I15) -> 46158
P112: =IF(+Issues!B16="","",+Issues!B16) -> 6 | R112: =IF(+Issues!C16="","",+Issues!C16) -> 13-05-2026 | S112: =IF(+Issues!D16="","",+Issues!D16) -> Road shoulder overlap at the Jeddah site | V112: =IF(+Issues!E16="","",+Issues!E16) -> Consultant | X112: =IF(+Issues!F16="","",+Issues!F16) -> A proposal has been submitted to the consultant. | AF112: =IF(+Issues!H16="","",+Issues!H16) -> Completed | AG112: =IF(+Issues!I16="","",+Issues!I16) -> 46296
A113: =Testing!A3 -> TESTING & COMMISSIONING JEDDAH | B113: =IF(Testing!B3=""," ",Testing!B3) -> 46357 | D113: =IF(Testing!C3=""," ",Testing!C3) -> 46405 | F113: =IF(Testing!D3=""," ",Testing!D3) -> 46357 | H113: =IF(Testing!E3=""," ",Testing!E3) -> 46471 | J113: =IF(Testing!H3=""," ",Testing!H3) | L113: =IF(Testing!G3=""," ",Testing!G3) | M113: =IF(Testing!H3=""," ",Testing!H3) | N113: =IF(Testing!I3=""," ",Testing!I3) | O113: =IF(Testing!J3=""," ",Testing!J3) | P113: =IF(+Issues!B17="","",+Issues!B17) -> 7 | R113: =IF(+Issues!C17="","",+Issues!C17) -> 46059 | S113: =IF(+Issues!D17="","",+Issues!D17) -> Trees located within Asir site. | V113: =IF(+Issues!E17="","",+Issues!E17) -> Owner | X113: =IF(+Issues!F17="","",+Issues!F17) -> Waiting for tree removal by the landscaping contractor. | AF113: =IF(+Issues!H17="","",+Issues!H17) -> Completed | AG113: =IF(+Issues!I17="","",+Issues!I17) -> 46158
A114: =Testing!A4 -> TESTING & COMMISSIONING ASIR | B114: =IF(Testing!B4=""," ",Testing!B4) -> 46331 | D114: =IF(Testing!C4=""," ",Testing!C4) -> 46399 | F114: =IF(Testing!D4=""," ",Testing!D4) -> 46410 | H114: =IF(Testing!E4=""," ",Testing!E4) -> 46488 | J114: =IF(Testing!H4=""," ",Testing!H4) | L114: =IF(Testing!G4=""," ",Testing!G4) | M114: =IF(Testing!H4=""," ",Testing!H4) | N114: =IF(Testing!I4=""," ",Testing!I4) | O114: =IF(Testing!J4=""," ",Testing!J4) | R114: =IF(+Issues!C18="","",+Issues!C18) -> 46305 | S114: =IF(+Issues!D18="","",+Issues!D18) -> Medium voltage cables on excavation way | V114: =IF(+Issues!E18="","",+Issues!E18) -> Owner | X114: =IF(+Issues!F18="","",+Issues!F18) -> Medium voltage cables are conflicting with the excavation route. Assessment and coordination with relevant stakeholders are ongoing to determine the required mitigation actions. Risk remains open. | AF114: =IF(+Issues!H18="","",+Issues!H18) -> Open | AG114: =IF(+Issues!J18="","",+Issues!J18)
A115: =Testing!A5 -> TESTING & COMMISSIONING JAZAN | B115: =IF(Testing!B5=""," ",Testing!B5) -> 46343 | D115: =IF(Testing!C5=""," ",Testing!C5) -> 46406 | F115: =IF(Testing!D5=""," ",Testing!D5) -> 46408 | H115: =IF(Testing!E5=""," ",Testing!E5) -> 46485 | J115: =IF(Testing!H5=""," ",Testing!H5) | L115: =IF(Testing!G5=""," ",Testing!G5) | M115: =IF(Testing!H5=""," ",Testing!H5) | N115: =IF(Testing!I5=""," ",Testing!I5) | O115: =IF(Testing!J5=""," ",Testing!J5) | R115: =IF(+Issues!C19="","",+Issues!C19) | S115: =IF(+Issues!D19="","",+Issues!D19) | V115: =IF(+Issues!E19="","",+Issues!E19) | X115: =IF(+Issues!F19="","",+Issues!F19) | AF115: =IF(+Issues!H19="","",+Issues!H19) | AG115: =IF(+Issues!J19="","",+Issues!J19)
R116: =IF(+Issues!C20="","",+Issues!C20) | S116: =IF(+Issues!D20="","",+Issues!D20) | V116: =IF(+Issues!E20="","",+Issues!E20) | X116: =IF(+Issues!F20="","",+Issues!F20) | AF116: =IF(+Issues!H20="","",+Issues!H20) | AG116: =IF(+Issues!J20="","",+Issues!J20)
P117: =IF(+Issues!B21="","",+Issues!B21) | R117: =IF(+Issues!C21="","",+Issues!C21) | S117: =IF(+Issues!D21="","",+Issues!D21) | V117: =IF(+Issues!E21="","",+Issues!E21) | X117: =IF(+Issues!F21="","",+Issues!F21) | AF117: =IF(+Issues!H21="","",+Issues!H21) | AG117: =IF(+Issues!J21="","",+Issues!J21)
P118: =IF(+Issues!B22="","",+Issues!B22) | R118: =IF(+Issues!C22="","",+Issues!C22) | S118: =IF(+Issues!D22="","",+Issues!D22) | V118: =IF(+Issues!E22="","",+Issues!E22) | X118: =IF(+Issues!F22="","",+Issues!F22) | AF118: =IF(+Issues!H22="","",+Issues!H22) | AG118: =IF(+Issues!J22="","",+Issues!J22)
...

Sheet General Information
A1: Weekly Progress Report - Construction Projects | K1: Data Date | L1: 46314
A2: Contract General Information
A3: Project Name | C3: Playground Initiative for Western Region (Asir - Jazan - Jeddah)
A4: Project ID | C4: MLTX-02-004
A5: Contractor | C5: Profast Company Ltd.
A6: Consultant | C6: Saudi Arabia Consulting Engineering Company "EGIS"
A7: Stage | C7: Construction
A8: Status | C8: Active
A9: Modon PM | C9: Engr.Yazeed Al Ragabh
A11: Key Dates
A12: Contract Award Date | C12: 46057
A13: Contract Sign Date | C13: 46085
A14: Site Handover Date | C14: 46107
A15: Original Completion | C15: 46412
A16: Contract Award Date (Hijri) | C16: =C12 -> 46057
A17: Contract Sign Date (Hijri) | C17: =C13 -> 46085
A18: Site Handover Date (Hijri) | C18: =C14 -> 46107
A19: Original Completion (Hijri) | C19: =C15 -> 46412
A20: Revised Completion Date | C20: 46412
A21: Committed Completion Date | C21: 46412
A22: Forecast Completion | C22: 46516
A23: Variance | C23: =C20-C22 -> -104
A25: Key Project Submittals | C25: Submission Date | D25: Days taken to approve orginal plan from site handover date
A26: Quality Plan submission | C26: 46123 | D26: =C26-C14 -> 16
A27: Quality Plan approval | C27: 46142
A28: Quality Plan Last Update | C28: -
A30: Safety Plan submission | C30: 46123 | D30: =C30-C14 -> 16
A31: Safety Plan approval | C31: 46184
A32: Safety Plan Last Update | C32: -
A34: Risk Management Plan submission | C34: 46141 | D34: =C34-C14 -> 34
A35: Risk Management Plan approval
A36: Risk Management Plan Last Update | C36: -
A38: Baseline Schedule submission | C38: 46140 | D38: =C38-C14 -> 33
A39: Baseline Schedule approval | C39: 46140
A40: No of Schedule Versions | C40: -
A41: Last Revised Schedule Approval Date | C41: -
A43: BOQ submission | C43: 45918 | D43: =C43-C14 -> -189
A44: BOQ approval | C44: 45918
A45: No of Approved Version of BOQ
A47: Execution Plan submission | C47: 46142 | D47: =C47-C14 -> 35
A48: Execution Plan Approval | C48: 46155

Sheet Milestones
A1: Project Name
A2: Item No. | B2: Milestones | C2: Original (Baseline) | D2: Latest | E2: Forecast | G2: Days Change
D3: =(D4-D5)/7 -> 43.571429 | E3: =(E4-E5)/7 -> 58.428571 | G3: =(D3-E3)*7 -> -104
A4: 1 | B4: Project Finish | C4: 46412 | D4: 46412 | E4: 46516 | F4: F | G4: =(D4-E4) -> -104
A5: 2 | B5: Project Start | C5: 46107 | D5: 46107 | E5: =D5 -> 46107 | F5: A | G5: =(D5-E5) -> 0
A6: 3 | B6: Baseline Programme Approval | C6: 46175 | D6: 46141 | E6: 46141 | F6: A | G6: =(D6-E6) -> 0
A7: 4 | B7: Completion of Mobilization | C7: 46412 | D7: 46175 | E7: 46175 | F7: A | G7: =D7-E7 -> 0
A8: 5 | B8: Completion of Levelling Works | C8: 46225 | D8: 46225 | E8: 46315 | F8: F | G8: =D8-E8 -> -90
A9: 6 | B9: Completion of Engineering | C9: 46406 | D9: 46406 | E9: 46331 | F9: F | G9: =D9-E9 -> 75
A10: 7 | B10: Completion of Toilet Building | C10: 46243 | D10: 46243 | E10: 46391 | F10: F | G10: =D10-E10 -> -148 | J10: 46141
A11: 8 | B11: Completion of Natural Landscape Works | C11: 46403 | D11: 46403 | E11: 46454 | F11: F | G11: =D11-E11 -> -51
A12: 9 | B12: Completion of Playground Area | C12: 46356 | D12: 46356 | E12: 46506 | F12: F | G12: =D12-E12 -> -150
A13: 10 | B13: Completion of Asir Works | C13: 46369 | D13: 46369 | E13: 46475 | F13: F | G13: =D13-E13 -> -106
A14: 11 | B14: Completion of Jazan Works | C14: 46406 | D14: 46406 | E14: 46516 | F14: F | G14: =D14-E14 -> -110
A15: 12 | B15: Completion of Jeddah Works | C15: 46412 | D15: 46412 | E15: 46471 | F15: F | G15: =D15-E15 -> -59
A16: 13 | B16: Completion of Testing & Commissioning | C16: 46141 | D16: 46141 | E16: 46488 | F16: F | G16: =D16-E16 -> -347
A24: Activity ID | B24: Activity Name | C24: Activity Status | D24: Original Duration | E24: Duration % Complete | F24: Schedule % Complete | G24: Performance % Complete | H24: Earned Value Cost | I24: Planned Value Cost | J24: Start | K24: Finish | L24: BL1 Start | M24: BL1 Finish | N24: Budgeted Total Cost
A25: MLTX-02-004 - Playground Initiative for Western Region (Asir - Jazan - Jeddah) - Updating 02-06-2026 | D25: 310 | E25: 0.1806 | F25: 0.0576 | G25: 0.0534 | H25: 1816335.3 | I25: 1958160.7 | J25: 26-Mar-26 A | K25: 46477 | L25: 46107 | M25: 46477 | N25: 33997787
A26: KEY MILESTONES | D26: 310 | E26: 0.2129 | F26: 0 | G26: 0 | H26: 0 | I26: 0 | J26: 26-Mar-26 A | K26: 46477 | L26: 46107 | M26: 46477 | N26: 0
A27: GENERAL MILESTONES | D27: 310 | E27: 1 | F27: 0 | G27: 0 | H27: 0 | I27: 0 | J27: 26-Mar-26 A | K27: 46477 | L27: 46107 | M27: 46477 | N27: 0
A28: MLTX-02-004-MS-1010 | B28: Project Commencement Date | C28: Completed | D28: 0 | E28: 1 | F28: 1 | G28: 1 | H28: 0 | I28: 0 | J28: 26-Mar-26 A | L28: 46107 | N28: 0
A29: MLTX-02-004-MS-1030 | B29: Project Completion | C29: Not Started | D29: 0 | E29: 0 | F29: 0 | G29: 0 | H29: 0 | I29: 0 | K29: 46477 | M29: 46477 | N29: 0
A30: CONTRACTUAL MILESTONE | D30: 271 | E30: 0.1328 | F30: 0 | G30: 0 | H30: 0 | I30: 0 | J30: 29-Apr-26 A | K30: 46467 | L30: 46141 | M30: 46467 | N30: 0
A31: MLTX-02-004-MS-1060 | B31: Baseline Programme Approval | C31: Completed | D31: 0 | E31: 1 | F31: 1 | G31: 1 | H31: 0 | I31: 0 | K31: 29-Apr-26 A | M31: 46141 | N31: 0
A32: MLTX-02-004-MS-1050 | B32: Completion of Mobilization | C32: Completed | D32: 0 | E32: 1 | F32: 1 | G32: 1 | H32: 0 | I32: 0 | K32: 02-Jun-26 A | M32: 46184 | N32: 0
A33: MLTX-02-004-MS-1120 | B33: Completion of Levelling Works | C33: Not Started | D33: 0 | E33: 0 | F33: 1 | G33: 0 | H33: 0 | I33: 0 | K33: 46187 | M33: 46187 | N33: 0
A34: MLTX-02-004-MS-1100 | B34: Completion of Engineering | C34: Not Started | D34: 0 | E34: 0 | F34: 1 | G34: 0 | H34: 0 | I34: 0 | K34: 46202 | M34: 46202 | N34: 0
A35: MLTX-02-004-MS-1130 | B35: Completion of Toilet Building | C35: Not Started | D35: 0 | E35: 0 | F35: 0 | G35: 0 | H35: 0 | I35: 0 | K35: 46292 | M35: 46292 | N35: 0
A36: MLTX-02-004-MS-1150 | B36: Completion of Natural Landscape Works | C36: Not Started | D36: 0 | E36: 0 | F36: 0 | G36: 0 | H36: 0 | I36: 0 | K36: 46413 | M36: 46413 | N36: 0
A37: MLTX-02-004-MS-1140 | B37: Completion of Playground Area | C37: Not Started | D37: 0 | E37: 0 | F37: 0 | G37: 0 | H37: 0 | I37: 0 | K37: 46445 | M37: 46445 | N37: 0
A38: MLTX-02-004-MS-1160 | B38: Completion of Asir Works | C38: Not Started | D38: 0 | E38: 0 | F38: 0 | G38: 0 | H38: 0 | I38: 0 | K38: 46467 | M38: 46467 | N38: 0
A39: MLTX-02-004-MS-1170 | B39: Completion of Jazan Works | C39: Not Started | D39: 0 | E39: 0 | F39: 0 | G39: 0 | H39: 0 | I39: 0 | K39: 46467 | M39: 46467 | N39: 0
A40: MLTX-02-004-MS-1180 | B40: Completion of Jeddah Works | C40: Not Started | D40: 0 | E40: 0 | F40: 0 | G40: 0 | H40: 0 | I40: 0 | K40: 46467 | M40: 46467 | N40: 0
A41: MLTX-02-004-MS-1070 | B41: Completion of Testing & Commissioning | C41: Not Started | D41: 0 | E41: 0 | F41: 0 | G41: 0 | H41: 0 | I41: 0 | K41: 46467 | M41: 46467 | N41: 0

Sheet Progress
A1: Project Scope Statement | B1: Playground Initiative for Western Region (Asir - Jazan - Jeddah)
A4: Earned Value Progress (SAR) | L4: Physical Progress (Effort)
A5: WBS | C5: BOQ Value (SAR) | D5: % Wt. | E5: Weekly (SAR) | H5: To Date (SAR) | J5: Actual % | L5: Budgeted | M5: % Wt. | N5: Weekly Physical Progress | P5: To Date Physical Progress | T5: Last Week Cost (SAR) | V5: Last Week Physical Progress
E6: Planned | F6: Earned | G6: Original Plan | H6: Planned | I6: Earned | L6: (Manhours) | N6: Planned | O6: Earned | P6: Planned | Q6: Earned | T6: Planned | U6: Earned | V6: Planned | W6: Earned
A7: Moblization | C7: 0 | E7: 0 | F7: =I7-U7 -> 0 | G7: 0 | H7: 0 | I7: 0 | J7: =I7/$C$25 -> 0 | L7: 12659 | M7: =L7/$L$25 -> 0.031160232 | N7: =P7-V7 -> 0 | O7: =Q7-W7 -> 0 | P7: =O48 -> 12658.6 | Q7: =N48 -> 12658.6 | T7: 0 | U7: 0 | V7: =O34 -> 12658.6 | W7: =N34 -> 12658.6
A8: Engineering | C8: 0 | D8: =C8/$C$25 -> 0 | E8: =H8-T8 -> 0 | F8: =I8-U8 -> 0 | G8: 0 | H8: 0 | I8: 0 | J8: =I8/$C$25 -> 0 | L8: 21299 | M8: =L8/$L$25 -> 0.052427662 | N8: =P8-V8 -> 0 | O8: =Q8-W8 -> 80.5 | P8: =O49 -> 21299.5 | Q8: =N49 -> 21009.7 | V8: =O35 -> 21299.5 | W8: =N35 -> 20929.2
A9: Procurment | C9: 0 | D9: =C9/$C$25 -> 0 | E9: =H9-T9 -> 0 | F9: =I9-U9 -> 0 | G9: 0 | H9: 0 | I9: 0 | J9: =I9/$C$25 -> 0 | L9: 51273 | M9: =L9/$L$25 -> 0.12620891 | N9: =P9-V9 -> 296.71 | O9: =Q9-W9 -> 5000 | P9: =O50 -> 50732.3 | Q9: =N50 -> 31870.4 | V9: =O36 -> 50435.59 | W9: =N36 -> 26870.4 | Z9: =W9-Q9 -> -5000
A10: Construction | C10: 33793604 | D10: =C10/$C$25 -> 1 | E10: =H10-T10 -> 1649688.5 | F10: =I10-U10 -> 821987.39 | G10: 3561002.2 | H10: =L51 -> 13223723 | I10: =K51 -> 11959715 | J10: =I10/$C$25 -> 0.35390468 | L10: 299660 | M10: =L10/$L$25 -> 0.73761554 | N10: =P10-V10 -> 16187.26 | O10: =Q10-W10 -> 8807.6 | P10: =O51 -> 122605.52 | Q10: =N51 -> 106759.6 | T10: =L37 -> 11574034 | U10: =K37 -> 11137727 | V10: =O37 -> 106418.26 | W10: =N37 -> 97952
A11: Jazan Region | C11: 10680072 | D11: =C11/$C$25 -> 0.31603825 | E11: =H11-T11 -> 401113.04 | F11: =I11-U11 -> 199957.72 | G11: 794325.94 | H11: =L52 -> 3951358.3 | I11: =K52 -> 2669083.7 | J11: =I11/$C$25 -> 0.07898192 | L11: 102280 | M11: =L11/$L$25 -> 0.25176306 | N11: =P11-V11 -> 5152.78 | O11: =Q11-W11 -> 4475.4 | P11: =O52 -> 45532.83 | Q11: =N52 -> 24825.4 | T11: =L38 -> 3550245.3 | U11: =K38 -> 2469126 | V11: =O38 -> 40380.05 | W11: =N38 -> 20350
A12: Asir Region | C12: 10578073 | D12: =C12/$C$25 -> 0.31301997 | E12: =H12-T12 -> 617430.85 | F12: =I12-U12 -> 300428.38 | G12: 1310370.1 | H12: =L53 -> 3063276.7 | I12: =K53 -> 4049399.2 | J12: =I12/$C$25 -> 0.11982738 | L12: 96810 | M12: =L12/$L$25 -> 0.23829861 | N12: =P12-V12 -> 7222.43 | O12: =Q12-W12 -> 1151.2 | P12: =O53 -> 40471.12 | Q12: =N53 -> 39573.2 | T12: =L39 -> 2445845.8 | U12: =K39 -> 3748970.9 | V12: =O39 -> 33248.69 | W12: =N39 -> 38422
A13: Jeddah Region | C13: 12535460 | D13: =C13/$C$25 -> 0.37094178 | E13: =H13-T13 -> 631144.59 | F13: =I13-U13 -> 321601.29 | G13: 1456306.1 | H13: =L54 -> 6209087.6 | I13: =K54 -> 5241231.7 | J13: =I13/$C$25 -> 0.15509537 | L13: 100570 | M13: =L13/$L$25 -> 0.24755388 | N13: =P13-V13 -> 3812.05 | O13: =Q13-W13 -> 3181 | P13: =O54 -> 36601.57 | Q13: =N54 -> 42361 | T13: =L40 -> 5577943 | U13: =K40 -> 4919630.4 | V13: =O40 -> 32789.52 | W13: =N40 -> 39180
A14: Testing & Commissioning | C14: 0 | D14: =C14/$C$25 -> 0 | E14: =H14-T14 -> 0 | F14: =I14-U14 -> 0 | G14: 0 | H14: 0 | I14: 0 | J14: =I14/$C$25 -> 0 | L14: 12818 | M14: =L14/$L$25 -> 0.031551612 | N14: =P14-V14 -> 0 | O14: =Q14-W14 -> 0 | P14: =O55 -> 0 | Q14: =N55 -> 0 | T14: 0 | V14: 0 | W14: 0
A15: Close-Out | C15: 0 | D15: =C15/$C$25 -> 0 | E15: =H15-T15 -> 0 | F15: =I15-U15 -> 0 | G15: 0 | H15: 0 | I15: 0 | J15: =I15/$C$25 -> 0 | L15: 8546 | M15: =L15/$L$25 -> 0.021036049 | N15: =P15-V15 -> 0 | O15: =Q15-W15 -> 0 | P15: =O56 -> 0 | Q15: =N56 -> 0 | V15: 0 | W15: 0
O16: =Q16-W16 -> 0 | P16: =O57 -> 0 | Q16: =N57 -> 0
O17: =Q17-W17 -> 0
O18: =Q18-W18 -> 0
O19: =Q19-W19 -> 0
O20: =Q20-W20 -> 0
O21: =Q21-W21 -> 0
E22: =H22-T22 -> 0 | F22: =I22-U22 -> 0 | N22: =P22-V22 -> 0 | O22: =Q22-W22 -> 0
E23: =H23-T23 -> 0 | F23: =I23-U23 -> 0 | N23: =P23-V23 -> 0 | O23: =Q23-W23 -> 0
E24: =H24-T24 -> 0 | F24: =I24-U24 -> 0 | N24: =P24-V24 -> 0 | O24: =Q24-W24 -> 0
B25: Total | C25: =C7+C8+C9+C11+C12+C13+C14+C15+C16+C17+C18+C19+C20+C21 -> 33793604 | D25: =D7+D8+D9+D11+D12+D13+D14+D15+D16+D17+D18+D19+D20+D21 -> 1 | E25: =E7+E8+E9+E11+E12+E13+E14+E15+E16+E17+E18+E19+E20+E21 -> 1649688.5 | F25: =F7+F8+F9+F11+F12+F13+F14+F15+F16+F17+F18+F19+F20+F21 -> 821987.39 | G25: =G7+G8+G9+G11+G12+G13+G14+G15+G16+G17+G18+G19+G20+G21 -> 3561002.2 | H25: =H7+H8+H9+H11+H12+H13+H14+H15+H16+H17+H18+H19+H20+H21 -> 13223723 | I25: =I7+I8+I9+I11+I12+I13+I14+I15+I16+I17+I18+I19+I20+I21 -> 11959715 | J25: =I25/$C$25 -> 0.35390468 | L25: =L7+L8+L9+L11+L12+L13+L14+L15+L16+L17+L18+L19+L20+L21 -> 406255 | M25: =M7+M8+M9+M11+M12+M13+M14+M15+M16+M17+M18+M19+M20+M21 -> 1 | N25: =N7+N8+N9+N11+N12+N13+N14+N15+N16+N17+N18+N19+N20+N21 -> 16483.97 | O25: =O7+O8+O9+O11+O12+O13+O14+O15+O16+O17+O18+O19+O20+O21 -> 13888.1 | P25: =P7+P8+P9+P11+P12+P13+P14+P15+P16+P17+P18+P19+P20+P21 -> 207295.92 | Q25: =Q7+Q8+Q9+Q11+Q12+Q13+Q14+Q15+Q16+Q17+Q18+Q19+Q20+Q21 -> 172298.3 | T25: =T7+T8+T9+T11+T12+T13+T14+T15+T16+T17+T18+T19+T20+T21 -> 11574034 | U25: =U7+U8+U9+U11+U12+U13+U14+U15+U16+U17+U18+U19+U20+U21 -> 11137727 | V25: =V7+V8+V9+V11+V12+V13+V14+V15+V16+V17+V18+V19+V20+V21 -> 190811.95 | W25: =W7+W8+W9+W11+W12+W13+W14+W15+W16+W17+W18+W19+W20+W21 -> 158410.2
G26: =G25/C25 -> 0.10537503 | H26: =H25/C25 -> 0.39130844 | I26: =I25/C25 -> 0.35390468 | P26: =P25/L25 -> 0.5102606 | Q26: =Q25/L25 -> 0.42411367
I27: =H26-I26 -> 0.037403761
A33: Activity ID | B33: Activity Name | C33: Activity Status | D33: Activity % Complete | E33: Duration % Complete | F33: Physical % Complete | G33: Units % Complete | H33: Schedule % Complete | I33: Performance % Complete | J33: Actual Total Cost | K33: Earned Value Cost | L33: Planned Value Cost | M33: Actual Labor Units | N33: Earned Value Labor Units | O33: Planned Value Labor Units | P33: Original Duration | Q33: Start | R33: Finish | S33: BL Project Start | T33: BL Project Finish | U33: Budgeted Total Cost | V33: Budgeted Labor Units | W33: Remaining Duration | X33: Actual Nonlabor Units | Y33: Remaining Nonlabor Units | Z33: Variance - BL Project Nonlabor Units | AA33: Variance - BL Project Labor Cost | AB33: Schedule Performance Index | AC33: Total Float | AD33: % Variance
A34: Moblization | E34: 1 | G34: 1 | H34: 0 | I34: 0 | J34: 0 | K34: 0 | L34: 0 | M34: 12658.6 | N34: 12658.6 | O34: 12658.6 | P34: 63 | Q34: 26-Mar-26 A | R34: 10-Jun-26 A | S34: 46107 | T34: 46183 | U34: 0 | V34: 12658.6 | W34: 0 | X34: 0 | Y34: 0 | Z34: 0 | AA34: 0 | AB34: 0 | AD34: -405
A35: Engineering | E35: 0.7628 | G35: 0.9826 | H35: 0 | I35: 0 | J35: 0 | K35: 0 | L35: 0 | M35: 20929.2 | N35: 20929.2 | O35: 21299.5 | P35: 215 | Q35: 31-Mar-26 A | R35: 46366 | S35: 46112 | T35: 46267 | U35: 0 | V35: 21299.5 | W35: 51 | X35: 0 | Y35: 0 | Z35: 0 | AA35: 0 | AB35: 0 | AC35: 39 | AD35: -43720
A36: Procurment | E36: 0.5754 | G36: 0.5241 | H36: 0 | I36: 0 | J36: 0 | K36: 0 | L36: 0 | M36: 26870.4 | N36: 26870.4 | O36: 50435.59 | P36: 252 | Q36: 06-May-26 A | R36: 46432 | S36: 46148 | T36: 46363 | U36: 0 | V36: 51273.3 | W36: 107 | X36: 0 | Y36: 0 | Z36: 0 | AA36: 0 | AB36: 0 | AC36: -43 | AD36: -6715.38
A37: Construction | E37: 0.4583 | G37: 0.2959 | H37: 0.3425 | I37: 0.3296 | J37: 7472734.8 | K37: 11137727 | L37: 11574034 | M37: 85000 | N37: 97952 | O37: 106418.26 | P37: 312 | Q37: 25-Apr-26 A | R37: 46509 | S37: 46137 | T37: 46412 | U37: 33793604 | V37: 299659.7 | W37: 169 | X37: 16420 | Y37: 26680 | Z37: 0 | AA37: 0 | AB37: 0.96 | AC37: -79 | AD37: -2645.55
A38: Jazan Region | E38: 0.4477 | G38: 0.1683 | H38: 0.3324 | I38: 0.2312 | J38: 1364443.7 | K38: 2469126 | L38: 3550245.3 | M38: 16500 | N38: 20350 | O38: 40380.05 | P38: 306 | Q38: 02-May-26 A | R38: 46509 | S38: 46144 | T38: 46412 | U38: 10680072 | V38: 102279.9 | W38: 169 | X38: 3210 | Y38: 11620 | Z38: 0 | AA38: 0 | AB38: 0.7 | AC38: -79 | AD38: -959.18
A39: Asir Region | E39: 0.493 | G39: 0.3622 | H39: 0.2312 | I39: 0.3544 | J39: 2696845.9 | K39: 3748970.9 | L39: 2445845.8 | M39: 33350 | N39: 38422 | O39: 33248.69 | P39: 286 | Q39: 27-Apr-26 A | R39: 46481 | S39: 46139 | T39: 46411 | U39: 10578073 | V39: 96809.9 | W39: 145 | X39: 6740 | Y39: 7130 | Z39: 0 | AA39: 0 | AB39: 1.53 | AC39: -55 | AD39: -858.18
A40: Jeddah Region | E40: 0.4931 | G40: 0.362 | H40: 0.445 | I40: 0.3925 | J40: 3411445.2 | K40: 4919630.4 | L40: 5577943 | M40: 35150 | N40: 39180 | O40: 32789.52 | P40: 290 | Q40: 25-Apr-26 A | R40: 46483 | S40: 46137 | T40: 46412 | U40: 12535460 | V40: 100569.9 | W40: 147 | X40: 6470 | Y40: 7930 | Z40: 0 | AA40: 0 | AB40: 0.88 | AC40: -57 | AD40: -828.18
A41: Testing & Commissioning | E41: 0 | G41: 0 | H41: 0 | I41: 0 | J41: 0 | K41: 0 | L41: 0 | M41: 0 | N41: 0 | O41: 0 | P41: 96 | Q41: 46369 | R41: 46484 | S41: 46331 | T41: 46406 | U41: 0 | V41: 12818.4 | W41: 96 | X41: 0 | Y41: 0 | Z41: 0 | AA41: 0 | AB41: 0 | AC41: -63 | AD41: 0
A42: Close-Out | E42: 0 | G42: 0 | H42: 0 | I42: 0 | J42: 0 | K42: 0 | L42: 0 | M42: 0 | N42: 0 | O42: 0 | P42: 21 | Q42: 46473 | R42: 46496 | S42: 46401 | T42: 46412 | U42: 0 | V42: 8545.6 | W42: 21 | X42: 0 | Y42: 360 | Z42: 0 | AA42: 0 | AB42: 0 | AC42: -68 | AD42: 0
A43: No WBS-Project | E43: 0.4985 | G43: 0 | H43: 0 | I43: 0 | J43: 0 | K43: 0 | L43: 0 | M43: 0 | N43: 0 | O43: 0 | P43: 337 | Q43: 26-Mar-26 A | R43: 46509 | S43: 46107 | T43: 46412 | U43: 0 | V43: 0 | W43: 169 | X43: 0 | Y43: 0 | Z43: 0 | AA43: 0 | AB43: 0 | AC43: -79 | AD43: -200
A47: Activity ID | B47: Activity Name | C47: Activity Status | D47: Activity % Complete | E47: Duration % Complete | F47: Physical % Complete | G47: Units % Complete | H47: Schedule % Complete | I47: Performance % Complete | J47: Actual Total Cost | K47: Earned Value Cost | L47: Planned Value Cost | M47: Actual Labor Units | N47: Earned Value Labor Units | O47: Planned Value Labor Units | P47: Original Duration | Q47: Start | R47: Finish | S47: BL Project Start | T47: BL Project Finish | U47: Budgeted Total Cost | V47: Budgeted Labor Units | W47: Remaining Duration | X47: Actual Nonlabor Units | Y47: Remaining Nonlabor Units | Z47: Variance - BL Project Nonlabor Units | AA47: Variance - BL Project Labor Cost | AB47: Schedule Performance Index | AC47: Total Float | AD47: % Variance
A48: Moblization | E48: 1 | G48: 1 | H48: 0 | I48: 0 | J48: 0 | K48: 0 | L48: 0 | M48: 12658.6 | N48: 12658.6 | O48: 12658.6 | P48: 63 | Q48: 26-Mar-26 A | R48: 10-Jun-26 A | S48: 46107 | T48: 46183 | U48: 0 | V48: 12658.6 | W48: 0 | X48: 0 | Y48: 0 | Z48: 0 | AA48: 0 | AB48: 0 | AD48: -405
A49: Engineering | E49: 0.8252 | G49: 0.9864 | H49: 0 | I49: 0 | J49: 0 | K49: 0 | L49: 0 | M49: 21009.7 | N49: 21009.7 | O49: 21299.5 | P49: 206 | Q49: 31-Mar-26 A | R49: 46356 | S49: 46112 | T49: 46267 | U49: 0 | V49: 21299.5 | W49: 36 | X49: 0 | Y49: 0 | Z49: 0 | AA49: 0 | AB49: 0 | AC49: 48 | AD49: -43720
A50: Procurment | E50: 0.5754 | G50: 0.6216 | H50: 0 | I50: 0 | J50: 0 | K50: 0 | L50: 0 | M50: 31870.4 | N50: 31870.4 | O50: 50732.3 | P50: 252 | Q50: 20-Apr-26 A | R50: 46439 | S50: 46148 | T50: 46363 | U50: 0 | V50: 51273.3 | W50: 107 | X50: 0 | Y50: 0 | Z50: 0 | AA50: 0 | AB50: 0 | AC50: -23 | AD50: -6715.38
A51: Construction | E51: 0.4686 | G51: 0.3221 | H51: 0.3913 | I51: 0.3539 | J51: 7843741.4 | K51: 11959715 | L51: 13223723 | M51: 93040 | N51: 106759.6 | O51: 122605.52 | P51: 318 | Q51: 25-Apr-26 A | R51: 46516 | S51: 46137 | T51: 46412 | U51: 33793604 | V51: 299659.7 | W51: 169 | X51: 17360 | Y51: 25740 | Z51: 0 | AA51: 0 | AB51: 0.9 | AC51: -85 | AD51: -2645.55
A52: Jazan Region | E52: 0.4583 | G52: 0.2076 | H52: 0.37 | I52: 0.2499 | J52: 1555475.9 | K52: 2669083.7 | L52: 3951358.3 | M52: 20610 | N52: 24825.4 | O52: 45532.83 | P52: 312 | Q52: 02-May-26 A | R52: 46516 | S52: 46144 | T52: 46412 | U52: 10680072 | V52: 102279.9 | W52: 169 | X52: 3700 | Y52: 11130 | Z52: 0 | AA52: 0 | AB52: 0.68 | AC52: -85 | AD52: -959.18
A53: Asir Region | E53: 0.5069 | G53: 0.3803 | H53: 0.2896 | I53: 0.3828 | J53: 2824315.9 | K53: 4049399.2 | L53: 3063276.7 | M53: 35050 | N53: 39573.2 | O53: 40471.12 | P53: 290 | Q53: 27-Apr-26 A | R53: 46485 | S53: 46139 | T53: 46411 | U53: 10578073 | V53: 96809.9 | W53: 143 | X53: 7040 | Y53: 6830 | Z53: 0 | AA53: 0 | AB53: 1.32 | AC53: -59 | AD53: -858.18
A54: Jeddah Region | E54: 0.5371 | G54: 0.3827 | H54: 0.4953 | I54: 0.4181 | J54: 3463949.6 | K54: 5241231.7 | L54: 6209087.6 | M54: 37380 | N54: 42361 | O54: 36601.57 | P54: 283 | Q54: 25-Apr-26 A | R54: 46471 | S54: 46137 | T54: 46412 | U54: 12535460 | V54: 100569.9 | W54: 131 | X54: 6620 | Y54: 7780 | Z54: 0 | AA54: 0 | AB54: 0.84 | AC54: -47 | AD54: -828.18
A55: Testing & Commissioning | E55: 0 | G55: 0 | H55: 0 | I55: 0 | J55: 0 | K55: 0 | L55: 0 | M55: 0 | N55: 0 | O55: 0 | P55: 109 | Q55: 46357 | R55: 46488 | S55: 46331 | T55: 46406 | U55: 0 | V55: 12818.4 | W55: 109 | X55: 0 | Y55: 0 | Z55: 0 | AA55: 0 | AB55: 0 | AC55: -66 | AD55: 0
A56: Close-Out | E56: 0 | G56: 0 | H56: 0 | I56: 0 | J56: 0 | K56: 0 | L56: 0 | M56: 0 | N56: 0 | O56: 0 | P56: 28 | Q56: 46468 | R56: 46499 | S56: 46401 | T56: 46412 | U56: 0 | V56: 8545.6 | W56: 28 | X56: 0 | Y56: 360 | Z56: 0 | AA56: 0 | AB56: 0 | AC56: -71 | AD56: 0
A57: No WBS-Project | E57: 0.5073 | G57: 0 | H57: 0 | I57: 0 | J57: 0 | K57: 0 | L57: 0 | M57: 0 | N57: 0 | O57: 0 | P57: 343 | Q57: 26-Mar-26 A | R57: 46516 | S57: 46107 | T57: 46412 | U57: 0 | V57: 0 | W57: 169 | X57: 0 | Y57: 0 | Z57: 0 | AA57: 0 | AB57: 0 | AC57: -85 | AD57: -200
A66: Activity ID | B66: Activity Name | C66: Activity Status | D66: Activity % Complete | E66: Duration % Complete | F66: Physical % Complete | G66: Units % Complete | H66: Schedule % Complete | I66: Performance % Complete | J66: Actual Total Cost | K66: Earned Value Cost | L66: Planned Value Cost | M66: Actual Labor Units | N66: Earned Value Labor Units | O66: Planned Value Labor Units | P66: Original Duration | Q66: Start | R66: Finish | S66: BL Project Start | T66: BL Project Finish | U66: Budgeted Total Cost | V66: Budgeted Labor Units | W66: Remaining Duration | X66: Actual Nonlabor Units | Y66: Remaining Nonlabor Units | Z66: Variance - BL Project Nonlabor Units | AA66: Variance - BL Project Labor Cost | AB66: Schedule Performance Index | AC66: Total Float | AD66: % Variance
A67: Total | E67: 0.5073 | G67: 0.3912 | H67: 0.3913 | I67: 0.3539 | J67: 7843741.4 | K67: 11959715 | L67: 13223723 | M67: 158578.7 | N67: 172298.3 | O67: 207295.92 | P67: 343 | Q67: 26-Mar-26 A | R67: 46516 | S67: 46107 | T67: 46412 | U67: 33793604 | V67: 406255.1 | W67: 169 | X67: 17360 | Y67: 26100 | Z67: 0 | AA67: 0 | AB67: 0.9 | AC67: -85 | AD67: -53685.93
A68: Moblization | E68: 1 | G68: 1 | H68: 0 | I68: 0 | J68: 0 | K68: 0 | L68: 0 | M68: 12658.6 | N68: 12658.6 | O68: 12658.6 | P68: 63 | Q68: 26-Mar-26 A | R68: 10-Jun-26 A | S68: 46107 | T68: 46183 | U68: 0 | V68: 12658.6 | W68: 0 | X68: 0 | Y68: 0 | Z68: 0 | AA68: 0 | AB68: 0 | AD68: -405
A69: Engineering | E69: 0.8252 | G69: 0.9864 | H69: 0 | I69: 0 | J69: 0 | K69: 0 | L69: 0 | M69: 21009.7 | N69: 21009.7 | O69: 21299.5 | P69: 206 | Q69: 31-Mar-26 A | R69: 46356 | S69: 46112 | T69: 46267 | U69: 0 | V69: 21299.5 | W69: 36 | X69: 0 | Y69: 0 | Z69: 0 | AA69: 0 | AB69: 0 | AC69: 48 | AD69: -43720
A70: Procurment | E70: 0.5754 | G70: 0.6216 | H70: 0 | I70: 0 | J70: 0 | K70: 0 | L70: 0 | M70: 31870.4 | N70: 31870.4 | O70: 50732.3 | P70: 252 | Q70: 20-Apr-26 A | R70: 46439 | S70: 46148 | T70: 46363 | U70: 0 | V70: 51273.3 | W70: 107 | X70: 0 | Y70: 0 | Z70: 0 | AA70: 0 | AB70: 0 | AC70: -23 | AD70: -6715.38
A71: Construction | E71: 0.4686 | G71: 0.3221 | H71: 0.3913 | I71: 0.3539 | J71: 7843741.4 | K71: 11959715 | L71: 13223723 | M71: 93040 | N71: 106759.6 | O71: 122605.52 | P71: 318 | Q71: 25-Apr-26 A | R71: 46516 | S71: 46137 | T71: 46412 | U71: 33793604 | V71: 299659.7 | W71: 169 | X71: 17360 | Y71: 25740 | Z71: 0 | AA71: 0 | AB71: 0.9 | AC71: -85 | AD71: -2645.55
A72: Jazan Region | E72: 0.4583 | G72: 0.2076 | H72: 0.37 | I72: 0.2499 | J72: 1555475.9 | K72: 2669083.7 | L72: 3951358.3 | M72: 20610 | N72: 24825.4 | O72: 45532.83 | P72: 312 | Q72: 02-May-26 A | R72: 46516 | S72: 46144 | T72: 46412 | U72: 10680072 | V72: 102279.9 | W72: 169 | X72: 3700 | Y72: 11130 | Z72: 0 | AA72: 0 | AB72: 0.68 | AC72: -85 | AD72: -959.18
A73: Asir Region | E73: 0.5069 | G73: 0.3803 | H73: 0.2896 | I73: 0.3828 | J73: 2824315.9 | K73: 4049399.2 | L73: 3063276.7 | M73: 35050 | N73: 39573.2 | O73: 40471.12 | P73: 290 | Q73: 27-Apr-26 A | R73: 46485 | S73: 46139 | T73: 46411 | U73: 10578073 | V73: 96809.9 | W73: 143 | X73: 7040 | Y73: 6830 | Z73: 0 | AA73: 0 | AB73: 1.32 | AC73: -59 | AD73: -858.18
A74: Jeddah Region | E74: 0.5371 | G74: 0.3827 | H74: 0.4953 | I74: 0.4181 | J74: 3463949.6 | K74: 5241231.7 | L74: 6209087.6 | M74: 37380 | N74: 42361 | O74: 36601.57 | P74: 283 | Q74: 25-Apr-26 A | R74: 46471 | S74: 46137 | T74: 46412 | U74: 12535460 | V74: 100569.9 | W74: 131 | X74: 6620 | Y74: 7780 | Z74: 0 | AA74: 0 | AB74: 0.84 | AC74: -47 | AD74: -828.18
A75: Testing & Commissioning | E75: 0 | G75: 0 | H75: 0 | I75: 0 | J75: 0 | K75: 0 | L75: 0 | M75: 0 | N75: 0 | O75: 0 | P75: 109 | Q75: 46357 | R75: 46488 | S75: 46331 | T75: 46406 | U75: 0 | V75: 12818.4 | W75: 109 | X75: 0 | Y75: 0 | Z75: 0 | AA75: 0 | AB75: 0 | AC75: -66 | AD75: 0
A76: Close-Out | E76: 0 | G76: 0 | H76: 0 | I76: 0 | J76: 0 | K76: 0 | L76: 0 | M76: 0 | N76: 0 | O76: 0 | P76: 28 | Q76: 46468 | R76: 46499 | S76: 46401 | T76: 46412 | U76: 0 | V76: 8545.6 | W76: 28 | X76: 0 | Y76: 360 | Z76: 0 | AA76: 0 | AB76: 0 | AC76: -71 | AD76: 0
A77: No WBS-Project | E77: 0.5073 | G77: 0 | H77: 0 | I77: 0 | J77: 0 | K77: 0 | L77: 0 | M77: 0 | N77: 0 | O77: 0 | P77: 343 | Q77: 26-Mar-26 A | R77: 46516 | S77: 46107 | T77: 46412 | U77: 0 | V77: 0 | W77: 169 | X77: 0 | Y77: 0 | Z77: 0 | AA77: 0 | AB77: 0 | AC77: -85 | AD77: -200
A84: Activity ID | B84: Activity Name | C84: Activity Status | D84: Activity % Complete | E84: Duration % Complete | F84: Physical % Complete | G84: Units % Complete | H84: Schedule % Complete | I84: Performance % Complete | J84: Actual Total Cost | K84: Earned Value Cost | L84: Planned Value Cost | M84: Actual Labor Units | N84: Earned Value Labor Units | O84: Planned Value Labor Units | P84: Original Duration | Q84: Start | R84: Finish | S84: BL Project Start | T84: BL Project Finish | U84: Budgeted Total Cost | V84: Budgeted Labor Units | W84: Remaining Duration | X84: Actual Nonlabor Units | Y84: Remaining Nonlabor Units | Z84: Variance - BL Project Nonlabor Units | AA84: Variance - BL Project Labor Cost | AB84: Schedule Performance Index | AC84: Total Float | AD84: % Variance
A85: Total | E85: 0.5073 | G85: 0.3912 | H85: 0.3913 | I85: 0.3539 | J85: 7843741.4 | K85: 11959715 | L85: 13223723 | M85: 158578.7 | N85: 172298.3 | O85: 207295.92 | P85: 343 | Q85: 26-Mar-26 A | R85: 46516 | S85: 46107 | T85: 46412 | U85: 33793604 | V85: 406255.1 | W85: 169 | X85: 17360 | Y85: 26100 | Z85: 0 | AA85: 0 | AB85: 0.9 | AC85: -85 | AD85: -53685.93
A86: Construction | E86: 0.4686 | G86: 0.3221 | H86: 0.3913 | I86: 0.3539 | J86: 7843741.4 | K86: 11959715 | L86: 13223723 | M86: 93040 | N86: 106759.6 | O86: 122605.52 | P86: 318 | Q86: 25-Apr-26 A | R86: 46516 | S86: 46137 | T86: 46412 | U86: 33793604 | V86: 299659.7 | W86: 169 | X86: 17360 | Y86: 25740 | Z86: 0 | AA86: 0 | AB86: 0.9 | AC86: -85 | AD86: -2645.55
A87: Jazan Region | E87: 0.4583 | G87: 0.2076 | H87: 0.37 | I87: 0.2499 | J87: 1555475.9 | K87: 2669083.7 | L87: 3951358.3 | M87: 20610 | N87: 24825.4 | O87: 45532.83 | P87: 312 | Q87: 02-May-26 A | R87: 46516 | S87: 46144 | T87: 46412 | U87: 10680072 | V87: 102279.9 | W87: 169 | X87: 3700 | Y87: 11130 | Z87: 0 | AA87: 0 | AB87: 0.68 | AC87: -85 | AD87: -959.18
A88: Asir Region | E88: 0.5069 | G88: 0.3803 | H88: 0.2896 | I88: 0.3828 | J88: 2824315.9 | K88: 4049399.2 | L88: 3063276.7 | M88: 35050 | N88: 39573.2 | O88: 40471.12 | P88: 290 | Q88: 27-Apr-26 A | R88: 46485 | S88: 46139 | T88: 46411 | U88: 10578073 | V88: 96809.9 | W88: 143 | X88: 7040 | Y88: 6830 | Z88: 0 | AA88: 0 | AB88: 1.32 | AC88: -59 | AD88: -858.18
A89: Jeddah Region | E89: 0.5371 | G89: 0.3827 | H89: 0.4953 | I89: 0.4181 | J89: 3463949.6 | K89: 5241231.7 | L89: 6209087.6 | M89: 37380 | N89: 42361 | O89: 36601.57 | P89: 283 | Q89: 25-Apr-26 A | R89: 46471 | S89: 46137 | T89: 46412 | U89: 12535460 | V89: 100569.9 | W89: 131 | X89: 6620 | Y89: 7780 | Z89: 0 | AA89: 0 | AB89: 0.84 | AC89: -47 | AD89: -828.18
A90: No W-Construction | E90: 0.5073 | G90: 0.6128 | H90: 0 | I90: 0 | J90: 0 | K90: 0 | L90: 0 | M90: 65538.7 | N90: 65538.7 | O90: 84690.4 | P90: 343 | Q90: 26-Mar-26 A | R90: 46516 | S90: 46107 | T90: 46412 | U90: 0 | V90: 106595.4 | W90: 169 | X90: 0 | Y90: 360 | Z90: 0 | AA90: 0 | AB90: 0 | AC90: -85 | AD90: -51040.38

Sheet EV-Chart Data
B2: Baseline Plan | E2: Revised / Recovery Plan | H2: Earned Value | K2: Gross Paid Value | N2: Forecast | Q2: Actual/Fcst vs Plan
A3: Month | B3: Monthly | C3: Cum | D3: % | E3: Monthly | F3: Cum | G3: % | H3: Monthly | I3: Cum | J3: % | K3: Monthly | L3: Cum | M3: % | N3: Monthly | O3: C um | Q3: Month | R3: Cum | AD3: Done
A4: 46096 | B4: 0 | C4: =B4 -> 0 | D4: =C4/$C$14 -> 0 | E4: 0 | F4: =E4 -> 0 | G4: =F4/$C$14 -> 0 | H4: 0 | I4: 0 | J4: =I4/$C$14 -> 0 | K4: 0 | L4: =K4 -> 0 | M4: =L4/$C$14 -> 0 | Q4: =(H4+N4)-E4 -> 0 | R4: =Q4 -> 0 | T4: Actuals thru previous month
A5: 46127 | B5: 199694.67 | C5: =B5 -> 199694.67 | D5: =C5/$C$14 -> 0.005873755 | E5: 205818.85 | F5: =E5 -> 205818.85 | G5: =F5/$F$14 -> 0.0060904675 | H5: 205818.85 | I5: =H5 -> 205818.85 | J5: =I5/$F$14 -> 0.0060904675 | K5: 0 | L5: =L4+K5 -> 0 | M5: =L5/$C$14 -> 0 | Q5: =(H5+N5)-E5 -> 0 | R5: =Q5+R4 -> 0
A6: 46157 | B6: 1723647.9 | C6: =B6+C5 -> 1923342.6 | D6: =C6/$C$14 -> 0.056572582 | E6: 1267322.6 | F6: =E6+F5 -> 1473141.5 | G6: =F6/$F$14 -> 0.043592316 | H6: 1252747.1 | I6: =H6+I5 -> 1458565.9 | J6: =I6/$F$14 -> 0.043161005 | K6: 0 | L6: =L5+K6 -> 0 | M6: =L6/$C$14 -> 0 | Q6: =(H6+N6)-E6 -> -14575.56 | R6: =Q6+R5 -> -14575.56 | AC6: 85712.66
A7: 46188 | B7: 2762137.8 | C7: =B7+C6 -> 4685480.4 | D7: =C7/$C$14 -> 0.13781722 | E7: 896200.52 | F7: =E7+F6 -> 2369342 | G7: =F7/$F$14 -> 0.070112143 | H7: 910089.8 | I7: =H7+I6 -> 2368655.7 | J7: =I7/$F$14 -> 0.070091835 | K7: 634329.39 | L7: =L6+K7 -> 634329.39 | M7: =L7/$C$14 -> 0.018657961 | Q7: =(H7+N7)-E7 -> 13889.28 | R7: =Q7+R6 -> -686.28 | AC7: 1597179.4
A8: 46218 | B8: 5604940.2 | C8: =B8+C7 -> 10290421 | D8: =C8/$C$14 -> 0.30267913 | E8: 1308159.9 | F8: =E8+F7 -> 3677501.9 | G8: =F8/$F$14 -> 0.10882242 | H8: 1106584.4 | I8: =H8+I7 -> 3475240.1 | J8: =I8/$F$14 -> 0.10283721 | K8: ='Invoice Log'!F10 -> 887817 | L8: =L7+K8 -> 1522146.4 | M8: =L8/$C$14 -> 0.044771926 | Q8: =(H8+N8)-E8 -> -201575.5 | R8: =Q8+R7 -> -202261.78 | T8: Forecast current and future months | AC8: 2973246.1
A9: 46249 | B9: 6742263.3 | C9: =B9+C8 -> 17032684 | D9: =C9/$C$14 -> 0.5009939 | E9: 924766.73 | F9: =E9+F8 -> 4602268.6 | G9: =F9/$F$14 -> 0.13618756 | H9: =I9-I8 -> 2749566.2 | I9: 6224806.3 | J9: =I9/$F$14 -> 0.18420072 | Q9: =(H9+N9)-E9 -> 1824799.5 | R9: =Q9+R8 -> 1622537.7 | AC9: 4807122
A10: 46280 | B10: 5043935.1 | C10: =B10+C9 -> 22076619 | D10: =C10/$C$14 -> 0.64935459 | E10: 5023017.7 | F10: =E10+F9 -> 9625286.3 | G10: =F10/$F$14 -> 0.28482568 | H10: =I10-I9 -> 2886879.1 | I10: 9111685.4 | J10: =I10/$F$14 -> 0.26962751 | Q10: =(H10+N10)-E10 -> -2136138.7 | R10: =Q10+R9 -> -513600.95 | AC10: 5879972.1
A11: 46310 | B11: 4651952.8 | C11: =B11+C10 -> 26728572 | D11: =C11/$C$14 -> 0.78618563 | E11: 6221852.6 | F11: =E11+F10 -> 15847139 | G11: =F11/$F$14 -> 0.468939 | H11: =I11-I10 -> 2848029.3 | I11: 11959715 | J11: 0.35390468 | Q11: =(H11+N11)-E11 -> -3373823.3 | R11: =Q11+R10 -> -3887424.2 | AC11: 5517468.5
A12: 46341 | B12: 3823943.2 | C12: =B12+C11 -> 30552515 | D12: =C12/$C$14 -> 0.89866187 | E12: 7294516.7 | F12: =E12+F11 -> 23141656 | G12: =F12/$F$14 -> 0.68479395 | Q12: =(H12+N12)-E12 -> -7294516.7 | R12: =Q12+R11 -> -11181941 | AC12: 4787653.5
A13: 46371 | B13: 2333735.3 | C13: =B13+C12 -> 32886250 | D13: =C13/$C$14 -> 0.96730561 | E13: 8882697.8 | F13: =E13+F12 -> 32024353 | G13: =F13/$F$14 -> 0.94764539 | Q13: =(H13+N13)-E13 -> -8882697.8 | R13: =Q13+R12 -> -20064639 | AC13: 4115781.3
A14: 46402 | B14: 1111536.8 | C14: =B14+C13 -> 33997787 | D14: =C14/$C$14 -> 1 | E14: 1769250.9 | F14: =E14+F13 -> 33793604 | G14: =F14/$F$14 -> 1 | Q14: =(H14+N14)-E14 -> -1769250.9 | R14: =Q14+R13 -> -21833890 | AC14: 2188790.5
A15: 46433 | Q15: =(H15+N15)-E15 -> 0 | R15: =Q15+R14 -> -21833890 | AC15: 1764236.5
AC16: 2138770.7 | AD16: 5614010.8 | AE16: 0.16612643
AC17: 2749566.2 | AD17: 6224806.3 | AE17: 0.18420072
AC18: 212768.9 | AD18: 6437575.2 | AE18: 0.19049685
AC19: 1149500.2 | AD19: 7374306.6 | AE19: 0.21821604
AC20: 2886879.1 | AD20: 9111685.4 | AE20: 0.26962751
AC21: 1299288 | AD21: 10410973 | AE21: 0.30807526
U22: Extended Duration
B39: UPDATE ONLY YELLOW PORTION FROM PRIMAVERA EXPORT, IF NEEDED, EXTEND YELLOW PORTION BASED ON SCHEDULE.
A47: Spreadsheet Field | B47: 46082 | C47: 46113 | D47: 46143 | E47: 46174 | F47: 46204 | G47: 46235 | H47: 46266 | I47: 46296 | J47: 46327 | K47: 46357 | L47: 46388 | M47: 46419
A48: Earned Value Cost | C48: 205818.85 | D48: 1252747.1 | E48: 910089.8 | F48: 1106584.4 | G48: 300732.48
A49: Planned Value Cost | C49: 205818.85 | D49: 1267322.6 | E49: 896200.52 | F49: 1308159.9 | G49: 924766.73 | H49: 5023017.7 | I49: 6221852.6 | J49: 7294516.7 | K49: 8882697.8 | L49: 1769250.9
A50: Remaining Total Cost | G50: 2565414.7 | H50: 2407360.4 | I50: 5270139 | J50: 4429466.5 | K50: 9838447.7 | L50: 5002146.7 | M50: 504657.34
A51: Budgeted Total Cost | C51: 205818.85 | D51: 1267322.6 | E51: 896200.52 | F51: 542878.66 | G51: 2830241.5 | H51: 2950222.5 | I51: 5326201.5 | J51: 4429466.5 | K51: 9838447.7 | L51: 5002146.7 | M51: 504657.34
A52: Actual Labor Units | B52: 1526 | C52: 18717 | D52: 22356 | E52: 27882 | F52: 21077 | G52: 1966
A53: Remaining Labor Units | G53: 38935 | H53: 28718 | I53: 54537 | J53: 47465 | K53: 63925 | L53: 57143 | M53: 22009
A54: Budgeted Labor Units | B54: 1526 | C54: 18717 | D54: 22356 | E54: 27882 | F54: 14212 | G54: 46384 | H54: 30044 | I54: 54593 | J54: 47465 | K54: 63925 | L54: 57143 | M54: 22009
A55: Earned Value Cost
A56: Planned Value Cost
A57: Remaining Total Cost
A58: Budgeted Total Cost
A59: Actual Labor Units | B59: 1377 | C59: 7487 | D59: 3417 | E59: 378
A60: Remaining Labor Units
A61: Budgeted Labor Units | B61: 1377 | C61: 7487 | D61: 3417 | E61: 378

Sheet Physical-Chart Data
B2: Baseline Plan | E2: Revised / Recovery Plan | H2: Earned Effort % | K2: Forecast | N2: Achieved/Fcst vs Plan
A3: Week | B3: Monthly Effort | C3: Cum Effort | D3: Plan Wt.% | E3: MonthlyEffort | F3: Cum Effort | G3: Plan Wt.% | H3: Monthly Wt. | I3: Cum Wt. | J3: Achieved Wt.% | K3: Monthly Wt. | L3: Cum Wt. | M3: Wt.% | N3: Monthly Wt. | O3: Cum Wt.
A4: 46096 | B4: 2126 | C4: =B4 -> 2126 | D4: =C4/$C$14 -> 0.0049775239 | E4: 1526 | F4: =E4 -> 1526 | G4: =F4/$F$14 -> 0.0037562615 | H4: 1526 | I4: =H4 -> 1526 | J4: =I4/$F$14 -> 0.0037562615 | N4: =H4-E4 -> 0 | O4: =N4 -> 0 | Q4: Actuals thru previous month
A5: 46127 | B5: 38413 | C5: =B5+C4 -> 40539 | D5: =C5/$C$14 -> 0.094912437 | E5: 18717 | F5: =E5+F4 -> 20243 | G5: =F5/$F$14 -> 0.04982831 | H5: 18717 | I5: =H5+I4 -> 20243 | J5: =I5/$F$14 -> 0.04982831 | N5: =(K5+H5)-E5 -> 0 | O5: =O4+N5 -> 0
A6: 46157 | B6: 30926 | C6: =B6+C5 -> 71465 | D6: =C6/$C$14 -> 0.16731832 | E6: 22356 | F6: =E6+F5 -> 42599 | G6: =F6/$F$14 -> 0.10485779 | H6: 22356 | I6: =H6+I5 -> 42599 | J6: =I6/$F$14 -> 0.10485779 | N6: =(K6+H6)-E6 -> 0 | O6: =O5+N6 -> 0 | AB6: Done
A7: 46188 | B7: 60339 | C7: =B7+C6 -> 131804 | D7: =C7/$C$14 -> 0.30858775 | E7: 27882 | F7: =E7+F6 -> 70481 | G7: =F7/$F$14 -> 0.17348956 | H7: 27882 | I7: =H7+I6 -> 70481 | J7: =I7/$F$14 -> 0.17348956 | N7: =(K7+H7)-E7 -> 0 | O7: =O6+N7 -> 0
A8: 46218 | B8: 50656 | C8: =B8+C7 -> 182460 | D8: =C8/$C$14 -> 0.42718674 | E8: 36166 | F8: =E8+F7 -> 106647 | G8: =F8/$F$14 -> 0.26251246 | H8: 21077 | I8: =H8+I7 -> 91558 | J8: =I8/$F$14 -> 0.22537076 | N8: =(K8+H8)-E8 -> -15089 | O8: =O7+N8 -> -15089 | Q8: Forecast current and future months
A9: 46249 | B9: 39250 | C9: =B9+C8 -> 221710 | D9: =C9/$C$14 -> 0.51908129 | E9: 28032 | F9: =E9+F8 -> 134679 | G9: =F9/$F$14 -> 0.33151346 | H9: =I9-I8 -> 38316 | I9: 129874 | J9: =I9/$F$14 -> 0.31968591 | N9: =(K9+H9)-E9 -> 10284 | O9: =O8+N9 -> -4805
A10: 46280 | B10: 48023 | C10: =B10+C9 -> 269733 | D10: =C10/$C$14 -> 0.63151573 | E10: 34666 | F10: =E10+F9 -> 169345 | G10: =F10/$F$14 -> 0.4168441 | H10: =I10-I9 -> 13807 | I10: 143681 | J10: =I10/$F$14 -> 0.35367195 | N10: =(K10+H10)-E10 -> -20859 | O10: =O9+N10 -> -25664
A11: 46310 | B11: 51145 | C11: =B11+C10 -> 320878 | D11: =C11/$C$14 -> 0.7512596 | E11: 65304 | F11: =E11+F10 -> 234649 | G11: =F11/$F$14 -> 0.57759043 | H11: =I11-I10 -> 28617.3 | I11: 172298.3 | J11: 0.42411367 | N11: =(K11+H11)-E11 -> -36686.7 | O11: =O10+N11 -> -62350.7
A12: 46341 | B12: 41901 | C12: =B12+C11 -> 362779 | D12: =C12/$C$14 -> 0.84936084 | E12: 53879 | F12: =E12+F11 -> 288528 | G12: =F12/$F$14 -> 0.71021403 | N12: =(K12+H12)-E12 -> -53879 | O12: =O11+N12 -> -116229.7 | Z12: 37220 | AA12: 128778 | AB12: 0.3169881
A13: 46371 | B13: 39788 | C13: =B13+C12 -> 402567 | D13: =C13/$C$14 -> 0.94251498 | E13: 77888 | F13: =E13+F12 -> 366416 | G13: =F13/$F$14 -> 0.90193598 | N13: =(K13+H13)-E13 -> -77888 | O13: =O12+N13 -> -194117.7 | Z13: 461 | AA13: 144781 | AB13: 0.35637961
A14: 46402 | B14: 24553 | C14: =B14+C13 -> 427120 | D14: =C14/$C$14 -> 1 | E14: 39839 | F14: =E14+F13 -> 406255 | G14: =F14/$F$14 -> 1 | N14: =(K14+H14)-E14 -> -39839 | O14: =O13+N14 -> -233956.7 | Z14: 13807 | AA14: 143681 | AB14: 0.35367195
A15: 46433 | N15: =(K15+H15)-E15 -> 0 | O15: =O14+N15 -> -233956.7 | Z15: 7812 | AA15: 151493 | AB15: 0.37290126
A16: 46461
A17: 46492
R22: Extended Duration
B39: UPDATE ONLY YELLOW PORTION FROM PRIMAVERA EXPORT, IF NEEDED, EXTEND YELLOW PORTION BASED ON SCHEDULE.

Sheet Weekly Photos
V1: Data Date | W1: ='General Information'!L1 -> 46314
B2: waterproofing works Jazan | L2: door works for service building Jazan
B21: Warning tape for cables works (Jeddah) | L21: backfilling & laying for lighting poles cables & foundation (Jeddah)
B41: waterproofing works for wet areas ASIR | L41: Steel Fixing for Air Dome Entrance Raft ASIR

Sheet Procurement
K1: Plan | Q1: Plan | R1: Forcast | S1: Actual
A2: Sr. NO. | B2: Project ID | C2: ACT#inP6 | D2: Item Description | E2: Discipline | F2: (Long \Short) Lead Items | G2: BOQ. No. | H2: Unit | I2: Quantity | J2: Proc. Qty | K2: Required P.O Date | L2: Date of Pur. Order Issued | M2: Purchase Order No. | N2: Supplier | O2: Supplier Phone | P2: Method of Shipping | Q2: Required on Job | R2: E.D.A. to Site | S2: A.D.A. to Site | T2: Lead Time | U2: Approval Status | V2: Completion Rate | W2: The Impact (BOQ Cost) | X2: Remarks
A3: 1 | B3: MLTX-02-004 | C3: ______________ | D3: AAC panels | E3: Architectural | F3: Long Lead | G3: 3.4 | H3: m² | I3: 680.43 | J3: 748.473 | L3: 46139 | M3: HQ01-PO-26-0015 | N3: ESPAC | O3: 592880434 | P3: Local | Q3: 46132 | T3: Long Lead | U3: Approved | X3: Delivered Of Site | AA3: =IF(K3<'General Information'!$L$1,1,0) -> 1
A4: 2 | B4: MLTX-02-004 | C4: _____________ | D4: Structural Glass | E4: Architectural | F4: short Lead | G4: 8.2.1 | H4: Sets | I4: 3 | J4: 3 | L4: 46140 | M4: HQ01-PO-26-0221 | N4: Dreametal | O4: 538882626 | P4: Local | Q4: 46208 | T4: short Lead | U4: Approved | X4: PO Issued | AA4: =IF(K4<'General Information'!$L$1,1,0) -> 1
A5: 3 | B5: MLTX-02-004 | C5: _____________ | D5: Frosted glass partition + door ( 12 mm thk. ) | E5: Architectural | F5: short Lead | G5: 9.2.9 | H5: m² | I5: 18.72 | J5: 20.592 | L5: 46140 | M5: HQ01-PO-26-0221 | N5: Dreametal | O5: 538882626 | P5: Local | Q5: 46208 | T5: short Lead | U5: Approved | X5: PO Issued | AA5: =IF(K5<'General Information'!$L$1,1,0) -> 1
A6: 4 | B6: MLTX-02-004 | C6: _____________ | D6: CNC aluminum cladding plates ( 3mm thk. ) | E6: Architectural | F6: short Lead | G6: 9.2.7 | H6: item | I6: 1 | J6: 1 | L6: 46140 | M6: HQ01-PO-26-0221 | N6: Dreametal | O6: 538882626 | P6: Local | Q6: 46208 | T6: short Lead | U6: Approved | X6: PO Issued | AA6: =IF(K6<'General Information'!$L$1,1,0) -> 1
A7: 5 | B7: MLTX-02-004 | C7: _____________ | D7: Anti slip ceramic ( floor 60*60 & 30*30 ) | E7: Architectural | F7: short Lead | G7: 9.1.1.1 9.1.1.2 | H7: m² | I7: 178.77 | J7: 196.647 | L7: 46131 | M7: PR. 4 | N7: Saudi Ceramics | O7: +966 2 001 1124 | P7: Local | Q7: 46202 | T7: short Lead | Y7: =IF(AND(L7="",K7<TODAY()),"Delay","") | AA7: =IF(K7<'General Information'!$L$1,1,0) -> 1
A8: 6 | B8: MLTX-02-004 | C8: _____________ | D8: Anti slip ceramic ( wall 30*30 ) | E8: Architectural | F8: short Lead | G8: 9.2.1 | H8: m² | I8: 355.68 | J8: 391.248 | L8: 46131 | M8: PR. 4 | N8: Saudi Ceramics | O8: +966 2 001 1124 | P8: Local | Q8: 46202 | T8: short Lead | Y8: =IF(AND(L8="",K8<TODAY()),"Delay","") | AA8: =IF(K8<'General Information'!$L$1,1,0) -> 1
A9: 7 | B9: MLTX-02-004 | C9: _____________ | D9: Anti slip ceramic ( skirting 60*100*10 ) | E9: Architectural | F9: short Lead | G9: 9.1.2.1 | H9: L.M | I9: 27.72 | J9: 30.492 | L9: 46131 | M9: PR. 4 | N9: Saudi Ceramics | O9: +966 2 001 1124 | P9: Local | Q9: 46202 | T9: short Lead | Y9: =IF(AND(L9="",K9<TODAY()),"Delay","") | AA9: =IF(K9<'General Information'!$L$1,1,0) -> 1
A10: 8 | B10: MLTX-02-004 | C10: _____________ | D10: Artificial Marble (Corian) | E10: Architectural | F10: short Lead | G10: 15.3.8.5 | H10: Nos. | I10: 3 | J10: 3.3 | N10: AFIFI | P10: Local | Q10: 46202 | T10: short Lead | Y10: =IF(AND(L10="",K10<TODAY()),"Delay","") -> Delay | AA10: =IF(K10<'General Information'!$L$1,1,0) -> 1
A11: 9 | B11: MLTX-02-004 | C11: _____________ | D11: Granite ( floor , treshold , coping ) | E11: Architectural | F11: short Lead | G11: 9.1.1.3 9.2.10 | H11: m² | I11: 121.8 | J11: 133.98 | L11: 46131 | M11: PR. 4 | N11: Saudi Ceramics | O11: +966 2 001 1124 | P11: Local | Q11: 46202 | T11: short Lead | Y11: =IF(AND(L11="",K11<TODAY()),"Delay","") | AA11: =IF(K11<'General Information'!$L$1,1,0) -> 1
A12: 10 | B12: MLTX-02-004 | C12: _____________ | D12: Acrylic paint (walls , ceilings , elevations) | E12: Architectural | F12: short Lead | G12: 9.2.3 9.2.4 9.3.3 | H12: m² | I12: 685 | J12: 753.5 | L12: 46128 | M12: PR. 2 | N12: Jazeera Paints | O12: +966 2 000 0085 | P12: Local | Q12: 46215 | T12: short Lead | U12: Approved | X12: PO Issued | Y12: =IF(AND(L12="",K12<TODAY()),"Delay","") | AA12: =IF(K12<'General Information'!$L$1,1,0) -> 1
A13: 11 | B13: MLTX-02-004 | C13: _____________ | D13: Decorative profile paint | E13: Architectural | F13: short Lead | G13: 9.2.6 | H13: item | I13: 3 | J13: 3 | L13: 46128 | M13: PR. 2 | N13: Jazeera Paints | O13: +966 2 000 0085 | P13: Local | Q13: 46215 | T13: short Lead | U13: Approved | X13: PO Issued | Y13: =IF(AND(L13="",K13<TODAY()),"Delay","") | AA13: =IF(K13<'General Information'!$L$1,1,0) -> 1
A14: 12 | B14: MLTX-02-004 | C14: _____________ | D14: Epoxy paint { (sport flooring (pike & walking paths )} | E14: Architectural | F14: short Lead | G14: 9.1.1.4 | H14: m² | I14: 16.56 | J14: 18.216 | L14: 46152 | M14: HQ01-SCC-CND-0027 | N14: First Roshin | O14: 966539293693 | P14: Local | Q14: 46215 | T14: short Lead | U14: Approved | X14: PO Issued | Y14: =IF(AND(L14="",K14<TODAY()),"Delay","") | AA14: =IF(K14<'General Information'!$L$1,1,0) -> 1
A15: 13 | B15: MLTX-02-004 | C15: _____________ | D15: Stone cladding 300*600 | E15: Architectural | F15: short Lead | G15: 9.2.5 | H15: m² | I15: 140 | J15: 168 | P15: Local | Q15: 46228 | T15: short Lead | Y15: =IF(AND(L15="",K15<TODAY()),"Delay","") -> Delay | AA15: =IF(K15<'General Information'!$L$1,1,0) -> 1
A16: 14 | B16: MLTX-02-004 | C16: Suspend Ceiling | D16: Gypsum board ( RG. & MR. ) 12.5 LL THK. | E16: Architectural | F16: short Lead | G16: 9.3.1 9.3.2 | H16: m² | I16: 164.4 | J16: 180.84 | L16: 46127 | M16: PR. 1 | N16: MADA | O16: +966 4 325 2411 | P16: Local | Q16: 46215 | T16: short Lead | Y16: =IF(AND(L16="",K16<TODAY()),"Delay","") | AA16: =IF(K16<'General Information'!$L$1,1,0) -> 1
A17: 15 | B17: MLTX-02-004 | C17: _____________ | D17: PHENOLIC TOILETS PARTITION & PHENOLIC LOCKER | E17: Architectural | F17: short Lead | G17: 9.2.8 10.1.2.1 10.1.2.2 | H17: m² | I17: 120.96 + 3 Item | J17: 139.104 + 3Item | L17: 10-May-26 | M17: HQ01-SCC-CND-0030 | N17: Perfect Doors | O17: 550840114 | P17: Local | Q17: 46202 | T17: short Lead | Y17: =IF(AND(L17="",K17<TODAY()),"Delay","") | Z17: تحويل عتد م.اسلام عبدالسميع | AA17: =IF(K17<'General Information'!$L$1,1,0) -> 1
A18: 16 | B18: MLTX-02-004 | C18: Grass/Trees | D18: Trees (Cassia Glauca+Plumeria Alba+Neem) | E18: Architectural | F18: Long Lead | G18: 2.3.4.1 | H18: Nos. | I18: 850 | J18: 850 | L18: 17-May-26 | M18: HQ01-SCC-CND-26-0027 | N18: Sana Al-Andalus | O18: +966 56 006 6003 | P18: Local | Q18: 46283 | T18: Long Lead | Y18: =IF(AND(L18="",K18<TODAY()),"Delay","") | AA18: =IF(K18<'General Information'!$L$1,1,0) -> 1
A19: 17 | B19: MLTX-02-004 | C19: _____________ | D19: Ground Covers -Lawn | E19: Architectural | F19: short Lead | G19: 2.3.4.2.1 | H19: m2 | I19: 13600 | J19: 14000 | L19: 17-May-26 | M19: HQ01-SCC-CND-26-0027 | N19: Sana Al-Andalus | O19: +966 56 006 6003 | P19: Local | Q19: 46180 | T19: short Lead | Y19: =IF(AND(L19="",K19<TODAY()),"Delay","") | AA19: =IF(K19<'General Information'!$L$1,1,0) -> 1
A20: 18 | B20: MLTX-02-004 | C20: Padel Glass | D20: padel playground fence - Glass | E20: Architectural | F20: Long Lead | G20: 2.3.7 | H20: Item | I20: 3 | J20: 3 | L20: 46152 | M20: HQ01-SCC-CND-0027 | N20: First Roshin | O20: 966539293693 | P20: Local | Q20: 46150 | T20: Long Lead | U20: Approved | X20: PO Issued | Y20: =IF(AND(L20="",K20<TODAY()),"Delay","") | AA20: =IF(K20<'General Information'!$L$1,1,0) -> 1
A21: 19 | B21: MLTX-02-004 | C21: _________________ | D21: Damproofinig paint | E21: Architectural | F21: Short Lead | G21: 7.3 | H21: m² | I21: 146.7 | J21: 150 | L21: 46142 | M21: PR.15 | N21: Awazel | O21: +966 2 660 1740 | P21: Local | Q21: 46167 | T21: Short Lead | X21: PO Issued | Y21: =IF(AND(L21="",K21<TODAY()),"Delay","") | AA21: =IF(K21<'General Information'!$L$1,1,0) -> 1
A22: 20 | B22: MLTX-02-004 | C22: _________________ | D22: 4mm thick layer APP modified bituminous membrane | E22: Architectural | F22: Short Lead | G22: 7.5 | H22: m² | I22: 236.16 | J22: 300 | L22: 46142 | M22: PR.15 | N22: Awazel | O22: +966 2 660 1740 | P22: Local | Q22: 46154 | T22: Short Lead | U22: Approved | V22: 0.3 | X22: Delivered Of Site | Y22: =IF(AND(L22="",K22<TODAY()),"Delay","") | AA22: =IF(K22<'General Information'!$L$1,1,0) -> 1
A23: 21 | B23: MLTX-02-004 | C23: _____________ | D23: Geotextile sheet | E23: Architectural | F23: Short Lead | G23: _______ | H23: _____ | I23: _____ | J23: _____ | L23: 46142 | M23: PR.15 | N23: Awazel | O23: +966 2 660 1740 | P23: Local | Q23: 46154 | T23: Short Lead | X23: Delivered Of Site | Y23: =IF(AND(L23="",K23<TODAY()),"Delay","") | Z23: تحويل عتد م.اسلام عبدالسميع | AA23: =IF(K23<'General Information'!$L$1,1,0) -> 1
A24: 22 | B24: MLTX-02-004 | C24: _____________ | D24: 50 mm thk rigid insulation (extruded polystyrene XPS) Density 35 kg/m3 | E24: Architectural | F24: Short Lead | G24: 7.4.4 | H24: m² | I24: 211.41 | J24: 232.551 | L24: 46142 | M24: PR.15 | N24: Awazel | O24: +966 2 660 1740 | P24: Local | Q24: 46154 | T24: Short Lead | X24: PO Issued | Y24: =IF(AND(L24="",K24<TODAY()),"Delay","") | AA24: =IF(K24<'General Information'!$L$1,1,0) -> 1
A25: 23 | B25: MLTX-02-004 | C25: _____________ | D25: Water proofing system | E25: Architectural | F25: Short Lead | G25: 7.4.1 7.4.2 7.4.5 7.4.6 | H25: m² | I25: 211.41 | J25: 232.551 | L25: 46142 | M25: PR.15 | N25: Awazel | O25: +966 2 660 1740 | P25: Local | Q25: 46154 | T25: Short Lead | X25: Delivered Of Site | Y25: =IF(AND(L25="",K25<TODAY()),"Delay","") | Z25: تحويل عتد م.اسلام عبدالسميع | AA25: =IF(K25<'General Information'!$L$1,1,0) -> 1
A26: 24 | B26: MLTX-02-004 | C26: _____________ | D26: epoxy 2 coating | E26: Architectural | F26: Short Lead | G26: 7.6 | H26: m² | I26: 172 | J26: 200 | L26: 46142 | M26: PR.15 | N26: Awazel | O26: +966 2 660 1740 | P26: Local | Q26: 46154 | T26: Short Lead | X26: Delivered Of Site | Y26: =IF(AND(L26="",K26<TODAY()),"Delay","") | Z26: تحويل عتد م.اسلام عبدالسميع | AA26: =IF(K26<'General Information'!$L$1,1,0) -> 1
A27: 25 | B27: MLTX-02-004 | C27: _____________ | D27: Precast conc. Seats ( rect. & circle ) | E27: Architectural | F27: Long Lead | G27: 2.3.10.1 2.3.10.2 2.3.10.3 | H27: Nos. | I27: 201 | J27: 241.2 | L27: 46135 | M27: PR.8 | N27: Al-Hasaniah | P27: Local | Q27: 46206 | T27: Long Lead | X27: PO Issued | Y27: =IF(AND(L27="",K27<TODAY()),"Delay","") | Z27: تحويل عتد م.اسلام عبدالسميع | AA27: =IF(K27<'General Information'!$L$1,1,0) -> 1
A28: 26 | B28: MLTX-02-004 | C28: _____________ | D28: Precast connc. Trash pin | E28: Architectural | F28: Long Lead | G28: 2.3.10.4 | H28: Nos. | I28: 38 | J28: 38 | L28: 46135 | M28: PR.8 | N28: Al-Hasaniah | P28: Local | Q28: 46206 | T28: Long Lead | X28: PO Issued | Y28: =IF(AND(L28="",K28<TODAY()),"Delay","") | Z28: تحويل عتد م.اسلام عبدالسميع | AA28: =IF(K28<'General Information'!$L$1,1,0) -> 1
A29: 27 | B29: MLTX-02-004 | C29: _____________ | D29: Air dome ( Full system )2 | E29: Architectural | F29: Long Lead | G29: 2.3.9 | H29: Item | I29: 3 | J29: 3 | N29: Global Sport Gate | O29: 551707700 | P29: Local | Q29: 46196 | T29: Long Lead | Y29: =IF(AND(L29="",K29<TODAY()),"Delay","") -> Delay | Z29: تحويل عتد م.اسلام عبدالسميع | AA29: =IF(K29<'General Information'!$L$1,1,0) -> 1
A30: 28 | B30: MLTX-02-004 | C30: Interlocking Block Pavers | D30: Curbstone & Interlock -01 | E30: Architectural | F30: Short Lead | G30: 2.2.1 2.3.1.1 2.3.2 | H30: m² L.M | I30: 1994.57 17350.00 | J30: 2194 19085 | L30: 29-4-2026 | M30: HQ01-PO-26-010 | N30: 33564116 | O30: 598283830 | P30: Local | Q30: 46205 | T30: Short Lead | U30: Approved | X30: PO Issued | Y30: =IF(AND(L30="",K30<TODAY()),"Delay","") | Z30: تحويل عتد م.اسلام عبدالسميع | AA30: =IF(K30<'General Information'!$L$1,1,0) -> 1
A31: 29 | B31: MLTX-02-004 | C31: Interlocking Block Pavers | D31: Curbstone & Interlock -02 | E31: Architectural | F31: Short Lead | G31: 2.2.1 2.3.1.1 2.3.2 | H31: m² L.M | I31: 1994.57 17350.00 | J31: 2194 19085 | L31: 22-4-2026 | M31: HQ01-PO-CND-9-26-04-20 | N31: AL_taj | O31: 555103330 | P31: Local | Q31: 46205 | T31: Short Lead | U31: Approved | X31: PO Issued | Y31: =IF(AND(L31="",K31<TODAY()),"Delay","") | AA31: =IF(K31<'General Information'!$L$1,1,0) -> 1
A32: 30 | B32: MLTX-02-004 | C32: Interlocking Block Pavers | D32: Curbstone & Interlock -03 | E32: Architectural | F32: Short Lead | G32: 2.2.1 2.3.1.1 2.3.2 | H32: m² L.M | I32: 1994.57 17350.00 | J32: 2194 19085 | L32: 22-4-2026 | M32: HQ01-PO-CND-11-26-04-20 | N32: Bin OTOT | O32: 507738308 | P32: Local | Q32: 46187 | T32: Short Lead | U32: Approved | X32: PO Issued | Y32: =IF(AND(L32="",K32<TODAY()),"Delay","") | AA32: =IF(K32<'General Information'!$L$1,1,0) -> 1
A33: 31 | B33: MLTX-02-004 | C33: _____________ | D33: galvanized block ladder mesh | E33: Civil | F33: Short Lead | G33: 4.1.1 | H33: Item | I33: 3 | J33: 3 | L33: 46144 | M33: PR. 19 | N33: Unitech | O33: +966 2 627 8222 | P33: Local | Q33: 46141 | T33: Short Lead | Y33: =IF(AND(L33="",K33<TODAY()),"Delay","") | AA33: =IF(K33<'General Information'!$L$1,1,0) -> 1
A34: 32 | B34: MLTX-02-004 | C34: _____________ | D34: galvanized block angle | E34: Civil | F34: Short Lead | G34: 4.1.1 | H34: Item | I34: 3 | J34: 3 | L34: 46144 | M34: PR. 19 | N34: Unitech | O34: +966 2 627 8222 | P34: Local | Q34: 46141 | T34: Short Lead | AA34: =IF(K34<'General Information'!$L$1,1,0) -> 1
A35: 33 | B35: MLTX-02-004 | C35: _____________ | D35: Plastering Accessories | E35: Civil | F35: Short Lead | G35: 9.2.2 | H35: Item | I35: 3 | J35: 3 | L35: 46144 | M35: PR. 19 | N35: Unitech | O35: +966 2 627 8222 | P35: Local | Q35: 46141 | T35: Short Lead | AA35: =IF(K35<'General Information'!$L$1,1,0) -> 1
A36: 34 | B36: MLTX-02-004 | C36: _____________ | D36: Metal doors | E36: Civil | F36: Short Lead | G36: 8 | H36: Nos. | I36: 3 | J36: 3 | N36: Anfal | O36: 545969350 | P36: Local | Q36: 46173 | T36: Short Lead | Y36: =IF(AND(L36="",K36<TODAY()),"Delay","") -> Delay | AA36: =IF(K36<'General Information'!$L$1,1,0) -> 1
A37: 35 | B37: MLTX-02-004 | C37: Aggregate Base Course | D37: CRUSHERS ( backfilling materials )1 | E37: Civil | F37: short Lead | G37: 2.1.2 | H37: m³ | I37: 3068.6667 | J37: 3375.5333 | L37: 26-4-2026 | M37: HQ01-PO-26-001 | N37: Alazm uniited company | P37: Local | Q37: 46173 | T37: short Lead | U37: Approved | X37: Delivered Of Site | Y37: =IF(AND(L37="",K37<TODAY()),"Delay","") | AA37: =IF(K37<'General Information'!$L$1,1,0) -> 1
A38: 36 | B38: MLTX-02-004 | C38: Aggregate Base Course | D38: CRUSHERS ( backfilling materials )2 | E38: Civil | F38: short Lead | G38: 2.1.2 | H38: m³ | I38: 3068.6667 | J38: 3375.5333 | L38: 22-4-2026 | M38: HQ7-PO01-26-04-20 | N38: EEAC | P38: Local | Q38: 46173 | T38: short Lead | U38: Approved | X38: Delivered Of Site | Y38: =IF(AND(L38="",K38<TODAY()),"Delay","") | AA38: =IF(K38<'General Information'!$L$1,1,0) -> 1
A39: 37 | B39: MLTX-02-004 | C39: Aggregate Base Course | D39: CRUSHERS ( backfilling materials )3 | E39: Civil | F39: short Lead | G39: 2.1.2 | H39: m³ | I39: 3068.6667 | J39: 3375.5333 | L39: 22-4-2026 | M39: HQ10-26-04-20CND-PO01- | N39: Star Towers Contracting Company | P39: Local | Q39: 46173 | T39: short Lead | U39: Approved | X39: Delivered Of Site | Y39: =IF(AND(L39="",K39<TODAY()),"Delay","") | AA39: =IF(K39<'General Information'!$L$1,1,0) -> 1
A40: 38 | B40: MLTX-02-004 | C40: _____________ | D40: polyethylene sheet | E40: Civil | F40: Short Lead | G40: 7.1 7.4.3 | H40: m² | I40: 499.29 | J40: 500 | L40: 29-4-2026 | M40: PR. 14 | N40: Unitech | O40: +966 2 627 8222 | P40: Local | Q40: 46215 | R40: 46175 | S40: 46175 | T40: Short Lead | U40: Approved | V40: 1 | X40: Delivered Of Site | Y40: =IF(AND(L40="",K40<TODAY()),"Delay","") | Z40: تحويل عند م اسلام عبدالسميع | AA40: =IF(K40<'General Information'!$L$1,1,0) -> 1
A41: 39 | B41: MLTX-02-004 | C41: _____________ | D41: Anti termite | E41: Civil | F41: Short Lead | G41: 7.2 | H41: m² | I41: 287.88 | J41: 300 | L41: 27-4-2026 | M41: PR.12 | N41: Trap kill | O41: +966 56 657 7862 | P41: Local | Q41: 46157 | R41: 46176 | S41: 46176 | T41: Short Lead | U41: Approved | V41: 0.3 | X41: Delivered Ongoing | Y41: =IF(AND(L41="",K41<TODAY()),"Delay","") | AA41: =IF(K41<'General Information'!$L$1,1,0) -> 1
A42: 40 | B42: MLTX-02-004 | C42: Concrete Blocks | D42: 01- Concrete & Masonry block for walls 10 cm | E42: Civil | F42: Short Lead | G42: 3 4.1.1 | H42: m3 m² | I42: 843.37 176.53 | J42: 900 180 | L42: 19-4-2026 | M42: HQ01-PO-CND 4 -26-04-18 | N42: Rhino | O42: 597224822 | P42: Local | Q42: 46135 | T42: Short Lead | U42: Approved | X42: PO Issued | Y42: =IF(AND(L42="",K42<TODAY()),"Delay","") | AA42: =IF(K42<'General Information'!$L$1,1,0) -> 1
A43: 41 | B43: MLTX-02-004 | C43: Concrete Blocks | D43: 02 -Concrete & Masonry block for walls 10 cm | E43: Civil | F43: Short Lead | G43: 3 4.1.1 | H43: m3 m² | I43: 843.37 176.53 | J43: 900 180 | L43: 22-4-2026 | M43: HQ01-PO-CND-9-26-04-20 | N43: Al Taj | O43: 555103330 | P43: Local | Q43: 46135 | T43: Short Lead | U43: Approved | X43: Delivered Ongoing | Y43: =IF(AND(L43="",K43<TODAY()),"Delay","") | AA43: =IF(K43<'General Information'!$L$1,1,0) -> 1
A44: 42 | B44: MLTX-02-004 | C44: Concrete Blocks | D44: 03- Concrete & Masonry block for walls 10 cm | E44: Civil | F44: Short Lead | G44: 3 4.1.1 | H44: m3 m² | I44: 843.37 176.53 | J44: 900 180 | L44: 24-4-2026 | M44: HQ01-PO-CND-11-26-04-20 | N44: Bin OTOT | O44: 507738308 | P44: Local | Q44: 46135 | T44: Short Lead | U44: Approved | X44: Delivered Ongoing | Y44: =IF(AND(L44="",K44<TODAY()),"Delay","") | AA44: =IF(K44<'General Information'!$L$1,1,0) -> 1
A45: 43 | B45: MLTX-02-004 | C45: Steel Reincement | D45: Reinforcement Steel 1 | E45: Civil | F45: Short Lead | G45: 43.5 | H45: Ton | I45: 30 | J45: 22.5 | L45: 46132 | M45: PR.5 | N45: ALRAJHI | O45: 542264279 | P45: Local | Q45: 46154 | R45: 25-05-2026 | S45: 25-05-2026 | T45: Short Lead | U45: Approved | V45: 0.75 | X45: Delivered Ongoing | Y45: =IF(AND(L45="",K45<TODAY()),"Delay","") | AA45: =IF(K45<'General Information'!$L$1,1,0) -> 1
A46: 44 | B46: MLTX-02-004 | C46: Steel Reincement | D46: Reinforcement Steel 2 | E46: Civil | F46: Short Lead | G46: 43.5 | H46: Ton | I46: __ | J46: __ | N46: AL-ITTEFAQ | P46: Local | Q46: 46154 | T46: Short Lead | Y46: =IF(AND(L46="",K46<TODAY()),"Delay","") -> Delay | AA46: =IF(K46<'General Information'!$L$1,1,0) -> 1
A47: 45 | B47: MLTX-02-004 | C47: Pavement Markings | D47: Road markings | E47: Civil | F47: Short Lead | G47: 2.2.5 | H47: Lot | I47: 3 | N47: SHAWAHID | O47: 541767351 | P47: Local | Q47: 46194 | T47: Short Lead | AA47: =IF(K47<'General Information'!$L$1,1,0) -> 1
A48: 46 | B48: MLTX-02-004 | C48: Traffic Signs | D48: Aluminum traffic breakaway signs | E48: Civil | F48: Short Lead | G48: 2.3.3.1 | H48: Nos. | I48: 6 | N48: SHAWAHID | O48: 541767351 | P48: Local | Q48: 46289 | T48: Short Lead | AA48: =IF(K48<'General Information'!$L$1,1,0) -> 1
A49: 47 | B49: MLTX-02-004 | C49: Track Surface Artificial TURF | D49: Tartan floors system (EPDM Granules + Polyurethane ) & Playground Flooring & Asphalt | E49: Civil | F49: Short Lead | G49: 2.3.1.2 2.3.1.3 2.3.1.5 2.3.1.6 2.3.5 | H49: m2 | I49: 11874.26 | L49: 46152 | M49: HQ01-SCC-CND-0027 | N49: First Roshin | O49: 966539293693 | P49: Local | Q49: 46180 | T49: Short Lead | U49: Approved | X49: PO Issued | AA49: =IF(K49<'General Information'!$L$1,1,0) -> 1
A50: 48 | B50: MLTX-02-004 | C50: _____________ | D50: Steel ladder with safety cage | E50: Civil | F50: Short Lead | G50: 5.1 | H50: Nos. | I50: 3 | N50: Judff | P50: Local | Q50: 46234 | T50: Short Lead | AA50: =IF(K50<'General Information'!$L$1,1,0) -> 1
A51: 49 | B51: MLTX-02-004 | D51: Low Voltage Cable -Wiring | E51: Electrical | F51: Long Lead | G51: 16.9 | H51: _____ | I51: _____ | N51: Bahra Electric | O51: 920011127 | P51: Local | T51: Long Lead | AA51: =IF(K51<'General Information'!$L$1,1,0) -> 1
A52: 50 | B52: MLTX-02-004 | C52: Cables - Landscape | D52: Low Voltage Cable -600/1000volt | E52: Electrical | F52: Long Lead | G52: _______ | H52: _____ | I52: _____ | N52: Jeddah Cable Company | O52: +966 055 289 3405 | P52: Local | Q52: 46234 | T52: Long Lead | AA52: =IF(K52<'General Information'!$L$1,1,0) -> 1
A53: 51 | B53: MLTX-02-004 | C53: _____________ | D53: BACK & JUNCTION BOXES | E53: Electrical | F53: Short Lead | G53: _______ | H53: _____ | I53: _____ | J53: _____ | L53: 24-05-2026 | M53: PO-Ele-01 | N53: ALFANAR | O53: 800-124-1333 | P53: Local | Q53: 46204 | R53: 46181 | S53: 46181 | T53: Short Lead | U53: Approved | V53: 0.4 | X53: Delivered Ongoing | Y53: =IF(AND(L53="",K53<TODAY()),"Delay","") | AA53: =IF(K53<'General Information'!$L$1,1,0) -> 1
A54: 52 | B54: MLTX-02-004 | C54: _____________ | D54: CONDUITS & FITTINGS & Accessories for PVC | E54: Electrical | F54: Short Lead | G54: _______ | H54: _____ | I54: _____ | L54: 24-05-2026 | M54: PR-Ele-01 | N54: Khereiji Showrooms Company (MK ) | O54: +966 56 686 6706 | P54: Local | Q54: 46204 | R54: 46181 | S54: 46194 | T54: Short Lead | U54: Approved | V54: 0.1 | X54: Delivered Ongoing | Y54: =IF(AND(L54="",K54<TODAY()),"Delay","") | AA54: =IF(K54<'General Information'!$L$1,1,0) -> 1
A55: 53 | B55: MLTX-02-004 | C55: _____________ | D55: EMT/RSC CONDUITS – LIQUDTIGHT FLEXIBLE CONDUIT- METAL FLEXIBLE CONDUIT | E55: Electrical | F55: Short Lead | G55: _______ | H55: _____ | I55: _____ | L55: 24-05-2026 | M55: PO-Ele-01 | N55: ITCC | O55: +966 12 288 9198 | P55: Local | Q55: 46204 | R55: 46181 | S55: 46181 | T55: Short Lead | U55: Approved | V55: 0.1 | X55: Delivered Ongoing | Y55: =IF(AND(L55="",K55<TODAY()),"Delay","") | AA55: =IF(K55<'General Information'!$L$1,1,0) -> 1
A56: 54 | B56: MLTX-02-004 | C56: Earthing System | D56: GROUNDING/ LIGHTNING PROTECTION SYSTEM | E56: Electrical | F56: Short Lead | G56: 16.6 16.7 | H56: Nos. | I56: 12 | J56: 6 | L56: 24-05-2026 | M56: PO-Ele-01 | N56: Jeddah Cable Company | O56: +966 56 686 6706 | P56: Local | Q56: 46154 | R56: 46181 | S56: 46181 | T56: Short Lead | U56: Approved | V56: 0.25 | X56: Delivered Ongoing | Y56: =IF(AND(L56="",K56<TODAY()),"Delay","") | AA56: =IF(K56<'General Information'!$L$1,1,0) -> 1
A57: 55 | B57: MLTX-02-004 | C57: Switches/Sockets - Toilet wer Outlets/Switches - Playground | D57: WIRING DEVICES | E57: Electrical | F57: Short Lead | G57: 16.9 | H57: Nos. | I57: 66 | N57: Khereiji Showrooms Company (MK) | O57: +966 56 686 6706 | P57: Local | T57: Short Lead | Y57: =IF(AND(L57="",K57<TODAY()),"Delay","") -> Delay | AA57: =IF(K57<'General Information'!$L$1,1,0) -> 1
A58: 56 | B58: MLTX-02-004 | C58: ____________ | D58: Disconnect switch | E58: Electrical | F58: Short Lead | G58: 16.9.10 | H58: Nos. | I58: 3 | N58: ABB | O58: +966 92 001 0301 | P58: Local | Q58: 46234 | T58: Short Lead | Y58: =IF(AND(L58="",K58<TODAY()),"Delay","") -> Delay | Z58: Material Submite 2-10-2025 | AA58: =IF(K58<'General Information'!$L$1,1,0) -> 1
A59: 57 | B59: MLTX-02-004 | C59: Distribution Panels - Toilet Distribution Boards - Playground | D59: LV PANEL BOARDS | E59: Electrical | F59: Short Lead | G59: 16.1 | H59: Nos. | I59: 8 | N59: Al-Babtain Power | O59: +966 11 250 6900 | P59: Local | T59: Short Lead | Y59: =IF(AND(L59="",K59<TODAY()),"Delay","") -> Delay | Z59: Material Submite 2-10-2025 | AA59: =IF(K59<'General Information'!$L$1,1,0) -> 1
A60: 58 | B60: MLTX-02-004 | C60: Light Fixtures - playground | D60: Roadway/ street lights – Lighting Poles | E60: Electrical | F60: Short Lead | G60: 16.2 | H60: Nos. | I60: 322 | J60: 322 | L60: 46176 | M60: PO2026-283 | N60: Al-Babtain Power | O60: +966 11 250 6900 | P60: Local | Q60: 46210 | T60: Short Lead | X60: Delivered Of Site | Y60: =IF(AND(L60="",K60<TODAY()),"Delay","") | AA60: =IF(K60<'General Information'!$L$1,1,0) -> 1
A61: 59 | B61: MLTX-02-004 | C61: Lighting Fixtures- toilet | D61: Interior Lighting | E61: Electrical | F61: Short Lead | G61: 16.3 | H61: Nos. | I61: 144 | N61: Nassli led Lights | O61: +966 59 406 6470 | P61: Local | Q61: 46198 | T61: Short Lead | Y61: =IF(AND(L61="",K61<TODAY()),"Delay","") -> Delay | AA61: =IF(K61<'General Information'!$L$1,1,0) -> 1
A62: 60 | B62: MLTX-02-004 | C62: _____________ | D62: Fire Alarm System | E62: Electrical | F62: Short Lead | G62: 16.8 | H62: Nos. | I62: 45 | N62: Gent | O62: 966112650555 | P62: Local | Q62: 46254 | T62: Short Lead | Y62: =IF(AND(L62="",K62<TODAY()),"Delay","") -> Delay | AA62: =IF(K62<'General Information'!$L$1,1,0) -> 1
A63: 61 | B63: MLTX-02-004 | C63: _____________ | D63: Telecommunications & Data System | E63: Electrical | F63: Short Lead | G63: 16.4 | H63: Nos. | I63: 27 | N63: Mesc | O63: 96611434711 | P63: Local | Q63: 46254 | T63: Short Lead | Y63: =IF(AND(L63="",K63<TODAY()),"Delay","") -> Delay | AA63: =IF(K63<'General Information'!$L$1,1,0) -> 1
A64: 62 | B64: MLTX-02-004 | C64: CCTV | D64: Security and Access Control System - CCTV | E64: Electrical | F64: Short Lead | G64: 16.5 | H64: Nos. | I64: 42 | P64: Local | Q64: 46215 | T64: Short Lead | Y64: =IF(AND(L64="",K64<TODAY()),"Delay","") -> Delay | AA64: =IF(K64<'General Information'!$L$1,1,0) -> 1
A65: 63 | B65: MLTX-02-004 | C65: Sewage/Drainage Pipes | D65: UPVC Pipes | E65: Mechanical | F65: Short Lead | G65: 15.3.1 15.3.7 | H65: Lm | I65: 454 | J65: 460 | L65: 21-05-2026 | M65: PR 26 | N65: AL MUNIF | O65: +966 2 000 0357 | P65: Local | Q65: 46128 | R65: 46178 | S65: 46178 | T65: Short Lead | U65: Approved | V65: 1 | X65: Delivered Of Site | Y65: =IF(AND(L65="",K65<TODAY()),"Delay","") | AA65: =IF(K65<'General Information'!$L$1,1,0) -> 1
A66: 64 | B66: MLTX-02-004 | C66: AC Split - Toilet | D66: Split Type Air Conditioner | E66: Mechanical | F66: Short Lead | G66: 15.4.5 | H66: Nos. | I66: 3 | J66: 3 | L66: 46118 | M66: Profast-PO2026-286 | N66: ZAMIL | O66: +966 2 234 3630 | P66: Local | Q66: 46192 | T66: Short Lead | X66: PO Issued | Y66: =IF(AND(L66="",K66<TODAY()),"Delay","") | AA66: =IF(K66<'General Information'!$L$1,1,0) -> 1
A67: 65 | B67: MLTX-02-004 | C67: _____________ | D67: Fire Extinguisher | E67: Mechanical | F67: Short Lead | G67: 15.1 | H67: Nos. | I67: 6 | L67: 46201 | M67: PR 31 | N67: SFFECO | O67: +966 12 670 6009 | P67: Local | Q67: 46252 | T67: Short Lead | X67: PO Issued | Y67: =IF(AND(L67="",K67<TODAY()),"Delay","") | AA67: =IF(K67<'General Information'!$L$1,1,0) -> 1
A68: 66 | B68: MLTX-02-004 | C68: Sanitary Fixtures | D68: Sanitary Fixtures ( water heater , soap dispenser , tissue holder , mirrors , grap bar , mixer & tissue dispenser , WC , lav. ….. ) | E68: Mechanical | F68: Short Lead | G68: 15.3.3 15.3.4 15.3.8 | H68: Nos. | I68: 3 | J68: 3 | L68: 46180 | M68: PR 26 | N68: Saudi Ceramics | O68: +966 2 001 1124 | P68: Local | Q68: 46186 | T68: Short Lead | X68: PO Issued | Y68: =IF(AND(L68="",K68<TODAY()),"Delay","") | AA68: =IF(K68<'General Information'!$L$1,1,0) -> 1
A69: 67 | B69: MLTX-02-004 | C69: Irrigation Pipes/Sprinkles | D69: Land scape & i irrigation system materials (main and sub-main irrigation pipelines, fittings, valve boxes and sprinklers) | E69: Mechanical | F69: Long Lead | G69: 15.4.1.9 15.5.3 | H69: Item | I69: 3 | J69: 3 | L69: 17-05-2026 | M69: HQ01-SCC-CND-26-0027 | N69: Sana Al-Andalus | O69: +966 56 006 6003 | P69: Local | Q69: 46234 | T69: Long Lead | X69: PO Issued | Y69: =IF(AND(L69="",K69<TODAY()),"Delay","") | AA69: =IF(K69<'General Information'!$L$1,1,0) -> 1
A70: 68 | B70: MLTX-02-004 | C70: Exhaust Fans | D70: Inline Exhaust Fans | E70: Mechanical | F70: Short Lead | G70: 15.4.1 | H70: Nos. | I70: 18 | J70: 20 | L70: 18-05-2026 | M70: PR 27 | N70: Saudi Fan | O70: +966 2 283 2295 | P70: Local | Q70: 46192 | T70: Short Lead | X70: PO Issued | Y70: =IF(AND(L70="",K70<TODAY()),"Delay","") | AA70: =IF(K70<'General Information'!$L$1,1,0) -> 1
A71: 69 | B71: MLTX-02-004 | C71: _____________ | D71: HDPE PIPES & FITTINGS | E71: Mechanical | F71: Short Lead | G71: 15.2.2 | H71: m | I71: 300 | J71: 300 | L71: 28-06-2026 | M71: PR 33 | N71: AL MUNIF | O71: +966 2 000 0357 | P71: Local | Q71: 46252 | T71: Short Lead | X71: PO Issued | Y71: =IF(AND(L71="",K71<TODAY()),"Delay","") | AA71: =IF(K71<'General Information'!$L$1,1,0) -> 1
A72: 70 | B72: MLTX-02-004 | C72: Water Supply Pipes | D72: PPR PIPES & FITTINGS | E72: Mechanical | F72: Short Lead | G72: 15.2.1 | H72: Lm | I72: 256.5 | J72: 285 | L72: 46271 | M72: PR 30 | N72: AL MUNIF | O72: +966 2 000 0357 | P72: Local | Q72: 46177 | R72: 13-06-2026 | S72: 13-06-2026 | T72: Short Lead | U72: Approved | V72: 1 | X72: Delivered Of Site | Y72: =IF(AND(L72="",K72<TODAY()),"Delay","") | AA72: =IF(K72<'General Information'!$L$1,1,0) -> 1
A73: 71 | B73: MLTX-02-004 | C73: Exhaust Fans | D73: Square Exhaust Diffuser | E73: Mechanical | F73: Short Lead | G73: 14.4.2.1 | H73: Nos. | I73: 18 | L73: 46176 | M73: Profast-PO2026-280 | N73: Rabie Al Takyeef | O73: +966 59 255 5240 | P73: Local | Q73: 46192 | T73: Short Lead | Y73: =IF(AND(L73="",K73<TODAY()),"Delay","") | AA73: =IF(K73<'General Information'!$L$1,1,0) -> 1
A74: 72 | B74: MLTX-02-004 | C74: _____________ | D74: Copper Pipe for AC | E74: Mechanical | F74: Short Lead | G74: _______ | H74: Nos. | I74: 3 | N74: Al-Sayed Center A/C | O74: +966 2 261 6246 | P74: Local | Q74: 46192 | T74: Short Lead | Y74: =IF(AND(L74="",K74<TODAY()),"Delay","") -> Delay | AA74: =IF(K74<'General Information'!$L$1,1,0) -> 1
A75: 73 | B75: MLTX-02-004 | C75: _____________ | D75: Copper Pipe Insulation | E75: Mechanical | F75: Short Lead | G75: _______ | H75: Nos. | I75: 3 | N75: KIMMCO-ISOVER | O75: +966 3 847 1450 | P75: Local | Q75: 46192 | T75: Short Lead | Y75: =IF(AND(L75="",K75<TODAY()),"Delay","") -> Delay | AA75: =IF(K75<'General Information'!$L$1,1,0) -> 1
A76: 74 | B76: MLTX-02-004 | C76: _____________ | D76: Valves, check valves strainers and air vent | E76: Mechanical | F76: Long Lead | G76: _______ | H76: Nos. | I76: 43 | J76: 43 | L76: 46203 | M76: PR 37 | N76: ZAMIL | O76: +966 2 234 3630 | P76: Local | Q76: 46283 | T76: Long Lead | X76: PO Issued | Y76: =IF(AND(L76="",K76<TODAY()),"Delay","") | AA76: =IF(K76<'General Information'!$L$1,1,0) -> 1
A77: 75 | B77: MLTX-02-004 | C77: _____________ | D77: Afico Insulation | E77: Mechanical | F77: Short Lead | G77: _______ | H77: Nos. | I77: 3 | N77: Afico | O77: +966 3 331 3333 | P77: Local | Q77: 46196 | T77: Short Lead | Y77: =IF(AND(L77="",K77<TODAY()),"Delay","") -> Delay | AA77: =IF(K77<'General Information'!$L$1,1,0) -> 1
A78: 76 | B78: MLTX-02-004 | C78: _____________ | D78: Water Supply Booster Pumps | E78: Mechanical | F78: Long Lead | G78: 15.2.3 | H78: Set | I78: 2 | J78: 2 | L78: 17-05-2026 | M78: HQ01-SCC-CND-26-0027 | N78: KSB | O78: +966 1 227 7060 | P78: Local | Q78: 46252 | T78: Long Lead | X78: PO Issued | Y78: =IF(AND(L78="",K78<TODAY()),"Delay","") | AA78: =IF(K78<'General Information'!$L$1,1,0) -> 1
A79: 77 | B79: MLTX-02-004 | C79: _____________ | D79: Roof Drain & Steel roof scupper | E79: Mechanical | F79: Short Lead | G79: 5.2 | H79: Nos. | I79: 3 | J79: 3 | L79: 4/25/2026 6/28/2026 | M79: PR.10 PR.31 | N79: Saudi Cast | O79: +966 1 448 0107 | P79: Local | Q79: 46234 | T79: Short Lead | X79: PO Issued | Y79: =IF(AND(L79="",K79<TODAY()),"Delay","") | AA79: =IF(K79<'General Information'!$L$1,1,0) -> 1
A80: 78 | B80: MLTX-02-004 | C80: _____________ | D80: Hot Press GRP Sectional Panel Water Tanks | E80: Mechanical | F80: Long Lead | G80: 15.2.4.1 | H80: Set | I80: 2 | J80: 2 | L80: 46208 | M80: PROFAST-PO-2026-277 | N80: AL-MUHAIDEB | O80: +966 92 002 8545 | P80: Local | Q80: 46196 | T80: Long Lead | X80: PO Issued | AA80: =IF(K80<'General Information'!$L$1,1,0) -> 1
A81: 79 | B81: MLTX-02-004 | C81: Galvanized Duct | D81: ductwork as per SMACNA Standards | E81: Mechanical | F81: Short Lead | G81: 15.4.3 | H81: K G | I81: 183 | N81: Rabie Al Takyeef | O81: +966 59 255 5240 | P81: Local | Q81: 46196 | T81: Short Lead | AA81: =IF(K81<'General Information'!$L$1,1,0) -> 1
A82: 80 | B82: MLTX-02-004 | C82: _____________ | D82: Manhole Cover | E82: Mechanical | F82: Short Lead | G82: 15.3.5 15.3.6 | H82: Nos. | I82: 6 | J82: 6 | L82: 46201 | M82: PR.43 | N82: Judff | P82: Local | Q82: 46252 | T82: Short Lead | X82: PO Issued
A1048473: Y

Sheet Major Quantities
A1: BOQ Number | B1: Description of Item | C1: Total Quantity | D1: Unit of Measurement | E1: Plan To Date | F1: Actual To Date | G1: Remaining Total | H1: Variance
A2: 2.1 | B2: EARTHWORK (Excavation & Backfilling) | C2: 68051.54 | D2: m³ | E2: 57843.809 | F2: 57000 | G2: =C2-F2 -> 11051.54 | H2: =F2-E2 -> -843.809
A3: 2.3.1 | B3: Supply and install hardscape works | C3: 30380 | D3: m2 | E3: 0 | F3: 0 | G3: =C3-F3 -> 30380 | H3: =F3-E3 -> 0
A4: 2.3.4 | B4: Supply and plant trees | C4: 895 | D4: Nos. | E4: 0 | F4: 0 | G4: =C4-F4 -> 895 | H4: =F4-E4 -> 0
A5: 2.3.9 | B5: Design, supply, install, testing and commissioning of air dome | C5: 3 | D5: Item | E5: 0 | F5: 0 | G5: =C5-F5 -> 3 | H5: =F5-E5 -> 0
A6: 2.3.10 | B6: Supply and install site furniture | C6: 248 | D6: Nos | E6: 0 | F6: 0 | G6: =C6-F6 -> 248 | H6: =F6-E6 -> 0
A7: 3 | B7: Supply and cast Concrete | C7: 145 | D7: m³ | E7: 145 | F7: 145 | G7: =C7-F7 -> 0 | H7: =F7-E7 -> 0
A8: 9.1.1 | B8: Supply and install tiles Ceramic tiles | C8: 219 | D8: m² | E8: 0 | F8: 0 | G8: =C8-F8 -> 219 | H8: =F8-E8 -> 0
A9: 9.3 | B9: CEILING FINISHES | C9: 207 | D9: m² | E9: 0 | F9: 0 | G9: =C9-F9 -> 207 | H9: =F9-E9 -> 0
A10: 15.2.1 | B10: WATER SUPPLY SYSTEM for cold and hot water supply piping | C10: 138 | D10: Lm | E10: 0 | F10: 14 | G10: =C10-F10 -> 124 | H10: =F10-E10 -> 14
A11: 15.3.1 | B11: SEWER AND DRAINAGE PIPE | C11: 177 | D11: Lm | E11: 177 | F11: 55 | G11: =C11-F11 -> 122 | H11: =F11-E11 -> -122
A12: 15.3.7 | B12: Supply and install 150 mm uPVC pipes | C12: 300 | D12: m | E12: 150 | F12: 50 | G12: =C12-F12 -> 250 | H12: =F12-E12 -> -100
A13: 15.5.1 | B13: IRRIGATION SYSTEM HDPE Pipes | C13: 7150 | D13: m | E13: 0 | F13: 0 | G13: =C13-F13 -> 7150 | H13: =F13-E13 -> 0
A14: 16.3 | B14: Lighting Fixtures | C14: 129 | D14: Nos. | E14: 0 | F14: 0 | G14: =C14-F14 -> 129 | H14: =F14-E14 -> 0
A15: 16.2 | B15: Site Lighting Poles | C15: 322 | D15: Nos. | E15: 0 | F15: 0 | G15: =C15-F15 -> 322 | H15: =F15-E15 -> 0

Sheet Invoice Log
B1: Weekly Progress Report - Invoice Log | AK1: Y
B2: Project Value | L2: Payment Status | T2: Invoices Summary | AD2: Average Invoices durations | AK2: N
B3: Original Contract Value | F3: 33997787 | H3: O&M Value | J3: 0 | L3: Advance Payment % | N3: 0 | P3: Advance Payment (SAR) | R3: =F3*N3 -> 0 | T3: No of Submitted Invoices | V3: =MAX($C$9:$C$46) -> 5 | X3: Submitted Invoices (SAR) | Z3: =SUM(F9:F46) -> 4943710.6 | AB3: Submiited Invoice Peroid | AC3: =MAX(M9:M46) -> 46303 | AD3: CM / PgM Average Approval duration | AF3: =IFERROR(AVERAGE(Q9:Q59),0) -> 2.5 | AH3: Average Invoice Value | AI3: =IFERROR(AVERAGE(F9:F58),0) -> 988742.13
B4: Revised Contract Value | F4: 33793604 | H4: Revised O&M Value | J4: 0 | L4: Retention % | N4: 0 | P4: Retention (SAR) | R4: =F3*N4 -> 0 | T4: No of Approved Invoices (CM) | V4: =COUNTIF($O$9:$O$59,"Y") -> 47 | X4: Approved Invoices (CM) (SAR) | Z4: =SUMIF($O$9:$O$46,"Y",$K$9:$K$46) -> 5674267.2 | AD4: MODON PM & Accounts Average Approval duration | AF4: =IFERROR(AVERAGE(X9:X59),0) -> 0
B5: Estimate At Completion Value | F5: 33997787 | H5: Submitted Invoices (Gross Value) | J5: =SUM(F9:F58) -> 4943710.6 | L5: Penalties and deduction % | N5: =IFERROR(J6/F3,0) -> 0.00032355047 | P5: AP Recovery (SAR) | R5: =SUM(G9:G58) -> 0 | T5: No of Approved Invoices (PM) | V5: =COUNTIF($S$9:$S$59,"Y") -> 0 | X5: Approved Invoices (PM) (SAR) | Z5: =SUMIF($S$9:$S$46,"Y",$K$9:$K$46) -> 0 | AB5: Invoice Submitted Compared to Contract Value | AC5: =Z3/F4 -> 0.14629131 | AD5: Payments Average Duration | AF5: =IFERROR(AVERAGE(AB9:AB59),0) -> 0
B6: Potential Changes | F6: =F4-F5 -> -204182.66 | H6: Total Deduction | J6: =G59+H59+J59 -> 11000 | L6: Penalties and deduction (SAR) | N6: =SUM(J9:J58) -> 11000 | P6: Retention Cumulative (SAR) | R6: =SUM(H9:H58) -> 0 | T6: No of Paid Invoices | V6: =COUNTA(Y9:Y59) -> 0 | X6: Paid Invoices (SAR) | Z6: =SUM(Z9:Z46) -> 0 | AD6: Invoices Average total Duration | AF6: =IFERROR(AVERAGE(AD9:AD59),"")
B7: Invoice Reference | F7: Invoice Value | K7: Period Covered | N7: CM / PgM Approval Timeline | R7: Modon PM & Accounts Approval | Y7: Payment Status | AD7: Total Invoice Duration | AE7: Remarks
B8: # | C8: Invoice No. | D8: Doc Control reference | E8: Submittal Rev. # | F8: Gross Value | G8: AP Recovery | H8: Retention | I8: VAT /15% | J8: Deduction / Penalties | K8: Amount (net) | L8: Start Date | M8: End Date | N8: Date to CM / PgM | O8: CM / PgM Approval (Yes/No) | P8: CM / PgM Reply Date | Q8: Days Elapsed | R8: Date to PM | S8: PM Approval (Yes/No) | T8: PM Reply Date | U8: Date to Accounts | V8: Accounts Approval (Yes/No) | W8: Accounts Approval Date | X8: Days Elapsed | Y8: Date Paid | Z8: Amount Paid | AA8: Paid % | AB8: Payment Period (d) | AC8: Amount Pending | AH8: Done
B9: 1 | C9: 1 | D9: MLTX-02-004-PRO-TS9-1-DSF-GEN-0002-00 | E9: 0 | F9: 634329.39 | G9: =IF(ISBLANK(F9),"",-F9*$N$3) -> 0 | H9: =IF(ISBLANK(F9),"",-F9*$N$4) -> 0 | I9: =IFERROR((F9+G9)*0.15,0) -> 95149.409 | J9: 11000 | K9: =IF(ISBLANK(F9),"",F9-J9+I9) -> 718478.8 | L9: 46107 | M9: 46186 | N9: 46186 | O9: Y | P9: 46189 | Q9: =IF(ISBLANK(P9),"",P9-N9) -> 3 | X9: =IF(ISBLANK(W9),"",W9-R9) | Z9: =IF(ISBLANK(Y9),"",K9) | AA9: =IF(ISBLANK(Y9),"",Z9/K9) | AB9: =IF(ISBLANK(W9),"",Y9-W9) | AC9: =IF(ISBLANK(Y9),"",(K9-Z9)) | AD9: =IF(ISBLANK(Y9),"",Y9-N9)
B10: 2 | C10: 2 | D10: MLTX-02-004-PRO-TS9-1-DSF-GEN-0003-00 | E10: 0 | F10: 887817 | G10: =IF(ISBLANK(F10),"",-F10*$N$3) -> 0 | H10: =IF(ISBLANK(F10),"",-F10*$N$4) -> 0 | I10: =IFERROR((F10+G10)*0.15,0) -> 133172.55 | J10: 0 | K10: =IF(ISBLANK(F10),"",SUM(F10:J10)) -> 1020989.6 | L10: 46187 | M10: 46207 | N10: 46207 | O10: Y | P10: 46208 | Q10: =IF(ISBLANK(P10),"",P10-N10) -> 1 | X10: =IF(ISBLANK(W10),"",W10-R10) | Z10: =IF(ISBLANK(Y10),"",K10) | AB10: =IF(ISBLANK(W10),"",Y10-W10) | AC10: =IF(ISBLANK(Y10),"",(K10-Z10)) | AD10: =IF(ISBLANK(Y10),"",Y10-N11) | AI10: format if no, make shaded
B11: 3 | C11: 3 | D11: MLTX-02-004-PRO-TS9-1-DSF-GEN-0005-01 | E11: 1 | F11: 1120100 | G11: =IF(ISBLANK(F11),"",-F11*$N$3) -> 0 | H11: =IF(ISBLANK(F11),"",-F11*$N$4) -> 0 | I11: =IFERROR((F11+G11)*0.15,0) -> 168015 | J11: 0 | K11: =IF(ISBLANK(F11),"",SUM(F11:J11)) -> 1288115 | L11: 46208 | M11: 46242 | N11: 46242 | O11: Y | P11: 46245 | Q11: =IF(ISBLANK(P11),"",P11-N11) -> 3 | X11: =IF(ISBLANK(W11),"",W11-R11) | Z11: =IF(ISBLANK(Y11),"",K11) | AA11: =IF(ISBLANK(Y11),"",Z11/K11) | AB11: =IF(ISBLANK(W11),"",Y11-W11) | AC11: =IF(ISBLANK(Y11),"",(K11-Z11)) | AD11: =IF(ISBLANK(Y11),"",Y11-N11)
B12: 4 | C12: 4 | D12: MLTX-02-004-PRO-TS9-1-GEN-IPC-0004-00 | E12: 0 | F12: 1024958.8 | G12: =IF(ISBLANK(F12),"",-F12*$N$3) -> 0 | H12: =IF(ISBLANK(F12),"",-F12*$N$4) -> 0 | I12: =IFERROR((F12+G12)*0.15,0) -> 153743.82 | J12: 0 | K12: =IF(ISBLANK(F12),"",SUM(F12:J12)) -> 1178702.6 | L12: 46243 | M12: 46258 | N12: 46258 | O12: Y | P12: 46261 | Q12: =IF(ISBLANK(P12),"",P12-N12) -> 3 | X12: =IF(ISBLANK(W12),"",W12-R12) | Z12: =IF(ISBLANK(Y12),"",K12) | AA12: =IF(ISBLANK(Y12),"",Z12/K12) | AB12: =IF(ISBLANK(W12),"",Y12-W12) | AC12: =IF(ISBLANK(Y12),"",(K12-Z12)) | AD12: =IF(ISBLANK(Y12),"",Y12-N12)
B13: 5 | C13: 5 | D13: MLTX-02-004-PRO-TS9-1-GEN-IPC-00005-00 | E13: 0 | F13: 1276505.4 | G13: =IF(ISBLANK(F13),"",-F13*$N$3) -> 0 | H13: =IF(ISBLANK(F13),"",-F13*$N$4) -> 0 | I13: =IFERROR((F13+G13)*0.15,0) -> 191475.82 | J13: 0 | K13: =IF(ISBLANK(F13),"",SUM(F13:J13)) -> 1467981.3 | L13: 46259 | M13: 46303 | N13: 46303 | O13: Y | Q13: =IF(ISBLANK(P13),"",P13-N13) | X13: =IF(ISBLANK(W13),"",W13-R13) | Z13: =IF(ISBLANK(Y13),"",K13) | AA13: =IF(ISBLANK(Y13),"",Z13/K13) | AB13: =IF(ISBLANK(W13),"",Y13-W13) | AC13: =IF(ISBLANK(Y13),"",(K13-Z13)) | AD13: =IF(ISBLANK(Y13),"",Y13-N13)
B14: 6 | G14: =IF(ISBLANK(F14),"",-F14*$N$3) | H14: =IF(ISBLANK(F14),"",-F14*$N$4) | K14: =IF(ISBLANK(F14),"",SUM(F14:J14)) | O14: Y | Q14: =IF(ISBLANK(P14),"",P14-N14) | X14: =IF(ISBLANK(W14),"",W14-R14) | Z14: =IF(ISBLANK(Y14),"",K14) | AA14: =IF(ISBLANK(Y14),"",Z14/K14) | AB14: =IF(ISBLANK(W14),"",Y14-W14) | AC14: =IF(ISBLANK(Y14),"",(K14-Z14)) | AD14: =IF(ISBLANK(Y14),"",Y14-N14)
B15: 7 | G15: =IF(ISBLANK(F15),"",-F15*$N$3) | H15: =IF(ISBLANK(F15),"",-F15*$N$4) | K15: =IF(ISBLANK(F15),"",SUM(F15:J15)) | O15: Y | Q15: =IF(ISBLANK(P15),"",P15-N15) | X15: =IF(ISBLANK(W15),"",W15-R15) | Z15: =IF(ISBLANK(Y15),"",K15) | AA15: =IF(ISBLANK(Y15),"",Z15/K15) | AB15: =IF(ISBLANK(W15),"",Y15-W15) | AC15: =IF(ISBLANK(Y15),"",(K15-Z15)) | AD15: =IF(ISBLANK(Y15),"",Y15-N15)
B16: 8 | G16: =IF(ISBLANK(F16),"",-F16*$N$3) | H16: =IF(ISBLANK(F16),"",-F16*$N$4) | K16: =IF(ISBLANK(F16),"",SUM(F16:J16)) | O16: Y | Q16: =IF(ISBLANK(P16),"",P16-N16) | X16: =IF(ISBLANK(W16),"",W16-R16) | Z16: =IF(ISBLANK(Y16),"",K16) | AA16: =IF(ISBLANK(Y16),"",Z16/K16) | AB16: =IF(ISBLANK(W16),"",Y16-W16) | AC16: =IF(ISBLANK(Y16),"",(K16-Z16)) | AD16: =IF(ISBLANK(Y16),"",Y16-N16)
B17: 9 | O17: Y
B18: 10 | O18: Y
B19: 11 | O19: Y
B20: 12 | K20: =IF(ISBLANK(F20),"",SUM(F20:J20)) | O20: Y | Q20: =IF(ISBLANK(P20),"",P20-N20) | X20: =IF(ISBLANK(W20),"",W20-R20) | Z20: =IF(ISBLANK(Y20),"",K20) | AA20: =IF(ISBLANK(Y20),"",Z20/K20) | AB20: =IF(ISBLANK(W20),"",Y20-W20) | AC20: =IF(ISBLANK(Y20),"",(K20-Z20)) | AD20: =IF(ISBLANK(Y20),"",Y20-N20)
B21: 13 | K21: =IF(ISBLANK(F21),"",SUM(F21:J21)) | O21: Y | Q21: =IF(ISBLANK(P21),"",P21-N21) | X21: =IF(ISBLANK(W21),"",W21-R21) | Z21: =IF(ISBLANK(Y21),"",K21) | AA21: =IF(ISBLANK(Y21),"",Z21/K21) | AB21: =IF(ISBLANK(W21),"",Y21-W21) | AC21: =IF(ISBLANK(Y21),"",(K21-Z21)) | AD21: =IF(ISBLANK(Y21),"",Y21-N21)
B22: 14 | K22: =IF(ISBLANK(F22),"",SUM(F22:J22)) | O22: Y | Q22: =IF(ISBLANK(P22),"",P22-N22) | X22: =IF(ISBLANK(W22),"",W22-R22) | Z22: =IF(ISBLANK(Y22),"",K22) | AA22: =IF(ISBLANK(Y22),"",Z22/K22) | AB22: =IF(ISBLANK(W22),"",Y22-W22) | AC22: =IF(ISBLANK(Y22),"",(K22-Z22)) | AD22: =IF(ISBLANK(Y22),"",Y22-N22)
B23: 15 | K23: =IF(ISBLANK(F23),"",SUM(F23:J23)) | O23: Y | Q23: =IF(ISBLANK(P23),"",P23-N23) | X23: =IF(ISBLANK(W23),"",W23-R23) | Z23: =IF(ISBLANK(Y23),"",K23) | AA23: =IF(ISBLANK(Y23),"",Z23/K23) | AB23: =IF(ISBLANK(W23),"",Y23-W23) | AC23: =IF(ISBLANK(Y23),"",(K23-Z23)) | AD23: =IF(ISBLANK(Y23),"",Y23-N23)
B24: 16 | K24: =IF(ISBLANK(F24),"",SUM(F24:J24)) | O24: Y | Q24: =IF(ISBLANK(P24),"",P24-N24) | X24: =IF(ISBLANK(W24),"",W24-R24) | Z24: =IF(ISBLANK(Y24),"",K24) | AA24: =IF(ISBLANK(Y24),"",Z24/K24) | AB24: =IF(ISBLANK(W24),"",Y24-W24) | AC24: =IF(ISBLANK(Y24),"",(K24-Z24)) | AD24: =IF(ISBLANK(Y24),"",Y24-N24)
B25: 17 | K25: =IF(ISBLANK(F25),"",SUM(F25:J25)) | O25: Y | Q25: =IF(ISBLANK(P25),"",P25-N25) | X25: =IF(ISBLANK(W25),"",W25-R25) | Z25: =IF(ISBLANK(Y25),"",K25) | AA25: =IF(ISBLANK(Y25),"",Z25/K25) | AB25: =IF(ISBLANK(W25),"",Y25-W25) | AC25: =IF(ISBLANK(Y25),"",(K25-Z25)) | AD25: =IF(ISBLANK(Y25),"",Y25-N25)
B26: 18 | K26: =IF(ISBLANK(F26),"",SUM(F26:J26)) | O26: Y | Q26: =IF(ISBLANK(P26),"",P26-N26) | X26: =IF(ISBLANK(W26),"",W26-R26) | Z26: =IF(ISBLANK(Y26),"",K26) | AA26: =IF(ISBLANK(Y26),"",Z26/K26) | AB26: =IF(ISBLANK(W26),"",Y26-W26) | AC26: =IF(ISBLANK(Y26),"",(K26-Z26)) | AD26: =IF(ISBLANK(Y26),"",Y26-N26)
B27: 19 | K27: =IF(ISBLANK(F27),"",SUM(F27:J27)) | O27: Y | Q27: =IF(ISBLANK(P27),"",P27-N27) | X27: =IF(ISBLANK(W27),"",W27-R27) | Z27: =IF(ISBLANK(Y27),"",K27) | AA27: =IF(ISBLANK(Y27),"",Z27/K27) | AB27: =IF(ISBLANK(W27),"",Y27-W27) | AC27: =IF(ISBLANK(Y27),"",(K27-Z27))
B28: 20 | G28: =IF(ISBLANK(F28),"",-F28*$N$3) | H28: =IF(ISBLANK(F28),"",-F28*$N$4) | K28: =IF(ISBLANK(F28),"",SUM(F28:J28)) | O28: Y | Q28: =IF(ISBLANK(P28),"",P28-N28) | X28: =IF(ISBLANK(W28),"",W28-R28) | Z28: =IF(ISBLANK(Y28),"",K28) | AA28: =IF(ISBLANK(Y28),"",Z28/K28) | AB28: =IF(ISBLANK(W28),"",Y28-W28) | AC28: =IF(ISBLANK(Y28),"",(K28-Z28)) | AD28: =IF(ISBLANK(Y28),"",Y28-N28)
B29: 21 | G29: =IF(ISBLANK(F29),"",-F29*$N$3) | H29: =IF(ISBLANK(F29),"",-F29*$N$4) | K29: =IF(ISBLANK(F29),"",SUM(F29:J29)) | O29: Y | Q29: =IF(ISBLANK(P29),"",P29-N29) | X29: =IF(ISBLANK(W29),"",W29-R29) | Z29: =IF(ISBLANK(Y29),"",K29) | AA29: =IF(ISBLANK(Y29),"",Z29/K29) | AB29: =IF(ISBLANK(W29),"",Y29-W29) | AC29: =IF(ISBLANK(Y29),"",(K29-Z29)) | AD29: =IF(ISBLANK(Y29),"",Y29-N29)
B30: 22 | G30: =IF(ISBLANK(F30),"",-F30*$N$3) | H30: =IF(ISBLANK(F30),"",-F30*$N$4) | K30: =IF(ISBLANK(F30),"",SUM(F30:J30)) | O30: Y | Q30: =IF(ISBLANK(P30),"",P30-N30) | X30: =IF(ISBLANK(W30),"",W30-R30) | Z30: =IF(ISBLANK(Y30),"",K30) | AA30: =IF(ISBLANK(Y30),"",Z30/K30) | AB30: =IF(ISBLANK(W30),"",Y30-W30) | AC30: =IF(ISBLANK(Y30),"",(K30-Z30)) | AD30: =IF(ISBLANK(Y30),"",Y30-N30)
B31: 23 | G31: =IF(ISBLANK(F31),"",-F31*$N$3) | H31: =IF(ISBLANK(F31),"",-F31*$N$4) | K31: =IF(ISBLANK(F31),"",SUM(F31:J31)) | O31: Y | Q31: =IF(ISBLANK(P31),"",P31-N31) | X31: =IF(ISBLANK(W31),"",W31-R31) | Z31: =IF(ISBLANK(Y31),"",K31) | AA31: =IF(ISBLANK(Y31),"",Z31/K31) | AB31: =IF(ISBLANK(W31),"",Y31-W31) | AC31: =IF(ISBLANK(Y31),"",(K31-Z31)) | AD31: =IF(ISBLANK(Y31),"",Y31-N31)
B32: 24 | G32: =IF(ISBLANK(F32),"",-F32*$N$3) | H32: =IF(ISBLANK(F32),"",-F32*$N$4) | K32: =IF(ISBLANK(F32),"",SUM(F32:J32)) | O32: Y | Q32: =IF(ISBLANK(P32),"",P32-N32) | X32: =IF(ISBLANK(W32),"",W32-R32) | Z32: =IF(ISBLANK(Y32),"",K32) | AA32: =IF(ISBLANK(Y32),"",Z32/K32) | AB32: =IF(ISBLANK(W32),"",Y32-W32) | AC32: =IF(ISBLANK(Y32),"",(K32-Z32)) | AD32: =IF(ISBLANK(Y32),"",Y32-N32)
B33: 25 | G33: =IF(ISBLANK(F33),"",-F33*$N$3) | H33: =IF(ISBLANK(F33),"",-F33*$N$4) | K33: =IF(ISBLANK(F33),"",SUM(F33:J33)) | O33: Y | Q33: =IF(ISBLANK(P33),"",P33-N33) | X33: =IF(ISBLANK(W33),"",W33-R33) | Z33: =IF(ISBLANK(Y33),"",K33) | AA33: =IF(ISBLANK(Y33),"",Z33/K33) | AB33: =IF(ISBLANK(W33),"",Y33-W33) | AC33: =IF(ISBLANK(Y33),"",(K33-Z33)) | AD33: =IF(ISBLANK(Y33),"",Y33-N33)
B34: 26 | G34: =IF(ISBLANK(F34),"",-F34*$N$3) | H34: =IF(ISBLANK(F34),"",-F34*$N$4) | K34: =IF(ISBLANK(F34),"",SUM(F34:J34)) | O34: Y | Q34: =IF(ISBLANK(P34),"",P34-N34) | X34: =IF(ISBLANK(W34),"",W34-R34) | Z34: =IF(ISBLANK(Y34),"",K34) | AA34: =IF(ISBLANK(Y34),"",Z34/K34) | AB34: =IF(ISBLANK(W34),"",Y34-W34) | AC34: =IF(ISBLANK(Y34),"",(K34-Z34)) | AD34: =IF(ISBLANK(Y34),"",Y34-N34)
B35: 27 | G35: =IF(ISBLANK(F35),"",-F35*$N$3) | H35: =IF(ISBLANK(F35),"",-F35*$N$4) | K35: =IF(ISBLANK(F35),"",SUM(F35:J35)) | O35: Y | Q35: =IF(ISBLANK(P35),"",P35-N35) | X35: =IF(ISBLANK(W35),"",W35-R35) | Z35: =IF(ISBLANK(Y35),"",K35) | AA35: =IF(ISBLANK(Y35),"",Z35/K35) | AB35: =IF(ISBLANK(W35),"",Y35-W35) | AC35: =IF(ISBLANK(Y35),"",(K35-Z35)) | AD35: =IF(ISBLANK(Y35),"",Y35-N35)
B36: 28 | G36: =IF(ISBLANK(F36),"",-F36*$N$3) | H36: =IF(ISBLANK(F36),"",-F36*$N$4) | K36: =IF(ISBLANK(F36),"",SUM(F36:J36)) | O36: Y | Q36: =IF(ISBLANK(P36),"",P36-N36) | X36: =IF(ISBLANK(W36),"",W36-R36) | Z36: =IF(ISBLANK(Y36),"",K36) | AA36: =IF(ISBLANK(Y36),"",Z36/K36) | AB36: =IF(ISBLANK(W36),"",Y36-W36) | AC36: =IF(ISBLANK(Y36),"",(K36-Z36)) | AD36: =IF(ISBLANK(Y36),"",Y36-N36)
B37: 29 | G37: =IF(ISBLANK(F37),"",-F37*$N$3) | H37: =IF(ISBLANK(F37),"",-F37*$N$4) | K37: =IF(ISBLANK(F37),"",SUM(F37:J37)) | O37: Y | Q37: =IF(ISBLANK(P37),"",P37-N37) | X37: =IF(ISBLANK(W37),"",W37-R37) | Z37: =IF(ISBLANK(Y37),"",K37) | AA37: =IF(ISBLANK(Y37),"",Z37/K37) | AB37: =IF(ISBLANK(W37),"",Y37-W37) | AC37: =IF(ISBLANK(Y37),"",(K37-Z37)) | AD37: =IF(ISBLANK(Y37),"",Y37-N37)
B38: 30 | G38: =IF(ISBLANK(F38),"",-F38*$N$3) | H38: =IF(ISBLANK(F38),"",-F38*$N$4) | K38: =IF(ISBLANK(F38),"",SUM(F38:J38)) | O38: Y | Q38: =IF(ISBLANK(P38),"",P38-N38) | X38: =IF(ISBLANK(W38),"",W38-R38) | Z38: =IF(ISBLANK(Y38),"",K38) | AA38: =IF(ISBLANK(Y38),"",Z38/K38) | AB38: =IF(ISBLANK(W38),"",Y38-W38) | AC38: =IF(ISBLANK(Y38),"",(K38-Z38)) | AD38: =IF(ISBLANK(Y38),"",Y38-N38)
B39: 31 | G39: =IF(ISBLANK(F39),"",-F39*$N$3) | H39: =IF(ISBLANK(F39),"",-F39*$N$4) | K39: =IF(ISBLANK(F39),"",SUM(F39:J39)) | O39: Y | Q39: =IF(ISBLANK(P39),"",P39-N39) | X39: =IF(ISBLANK(W39),"",W39-R39) | Z39: =IF(ISBLANK(Y39),"",K39) | AA39: =IF(ISBLANK(Y39),"",Z39/K39) | AB39: =IF(ISBLANK(W39),"",Y39-W39) | AC39: =IF(ISBLANK(Y39),"",(K39-Z39)) | AD39: =IF(ISBLANK(Y39),"",Y39-N39)
... B46: 38 | G46: =IF(ISBLANK(F46),"",-F46*$N$3) | H46: =IF(ISBLANK(F46),"",-F46*$N$4) | K46: =IF(ISBLANK(F46),"",SUM(F46:J46)) | O46: Y | Q46: =IF(ISBLANK(P46),"",P46-N46) | X46: =IF(ISBLANK(W46),"",W46-R46) | Z46: =IF(ISBLANK(Y46),"",K46) | AA46: =IF(ISBLANK(Y46),"",Z46/K46) | AB46: =IF(ISBLANK(W46),"",Y46-W46) | AC46: =IF(ISBLANK(Y46),"",(K46-Z46)) | AD46: =IF(ISBLANK(Y46),"",Y46-N46)
B47: 39 | G47: =IF(ISBLANK(F47),"",-F47*$N$3) | H47: =IF(ISBLANK(F47),"",-F47*$N$4) | O47: Y | Z47: =IF(ISBLANK(Y47),"",K47) | AA47: =IF(ISBLANK(Y47),"",Z47/K47) | AB47: =IF(ISBLANK(W47),"",Y47-W47) | AC47: =IF(ISBLANK(Y47),"",(K47-Z47))
B48: 40 | G48: =IF(ISBLANK(F48),"",-F48*$N$3) | H48: =IF(ISBLANK(F48),"",-F48*$N$4) | O48: Y | Z48: =IF(ISBLANK(Y48),"",K48) | AA48: =IF(ISBLANK(Y48),"",Z48/K48) | AB48: =IF(ISBLANK(W48),"",Y48-W48) | AC48: =IF(ISBLANK(Y48),"",(K48-Z48))
B49: 41 | G49: =IF(ISBLANK(F49),"",-F49*$N$3) | H49: =IF(ISBLANK(F49),"",-F49*$N$4) | O49: Y | Z49: =IF(ISBLANK(Y49),"",K49) | AA49: =IF(ISBLANK(Y49),"",Z49/K49) | AB49: =IF(ISBLANK(W49),"",Y49-W49) | AC49: =IF(ISBLANK(Y49),"",(K49-Z49))
B50: 42 | G50: =IF(ISBLANK(F50),"",-F50*$N$3) | H50: =IF(ISBLANK(F50),"",-F50*$N$4) | O50: Y | Z50: =IF(ISBLANK(Y50),"",K50) | AA50: =IF(ISBLANK(Y50),"",Z50/K50) | AB50: =IF(ISBLANK(W50),"",Y50-W50) | AC50: =IF(ISBLANK(Y50),"",(K50-Z50))
B51: 43 | G51: =IF(ISBLANK(F51),"",-F51*$N$3) | H51: =IF(ISBLANK(F51),"",-F51*$N$4) | O51: Y | Z51: =IF(ISBLANK(Y51),"",K51) | AA51: =IF(ISBLANK(Y51),"",Z51/K51) | AB51: =IF(ISBLANK(W51),"",Y51-W51) | AC51: =IF(ISBLANK(Y51),"",(K51-Z51))
B52: 44 | G52: =IF(ISBLANK(F52),"",-F52*$N$3) | H52: =IF(ISBLANK(F52),"",-F52*$N$4) | O52: Y | Z52: =IF(ISBLANK(Y52),"",K52) | AA52: =IF(ISBLANK(Y52),"",Z52/K52) | AB52: =IF(ISBLANK(W52),"",Y52-W52) | AC52: =IF(ISBLANK(Y52),"",(K52-Z52))
B53: 45 | G53: =IF(ISBLANK(F53),"",-F53*$N$3) | H53: =IF(ISBLANK(F53),"",-F53*$N$4) | O53: Y | Z53: =IF(ISBLANK(Y53),"",K53) | AA53: =IF(ISBLANK(Y53),"",Z53/K53) | AB53: =IF(ISBLANK(W53),"",Y53-W53) | AC53: =IF(ISBLANK(Y53),"",(K53-Z53))
B54: 46 | G54: =IF(ISBLANK(F54),"",-F54*$N$3) | H54: =IF(ISBLANK(F54),"",-F54*$N$4) | O54: Y | Z54: =IF(ISBLANK(Y54),"",K54) | AA54: =IF(ISBLANK(Y54),"",Z54/K54) | AB54: =IF(ISBLANK(W54),"",Y54-W54) | AC54: =IF(ISBLANK(Y54),"",(K54-Z54))
B55: 47 | G55: =IF(ISBLANK(F55),"",-F55*$N$3) | H55: =IF(ISBLANK(F55),"",-F55*$N$4) | O55: Y | Z55: =IF(ISBLANK(Y55),"",K55) | AA55: =IF(ISBLANK(Y55),"",Z55/K55) | AB55: =IF(ISBLANK(W55),"",Y55-W55) | AC55: =IF(ISBLANK(Y55),"",(K55-Z55))
B56: 48 | G56: =IF(ISBLANK(F56),"",-F56*$N$3) | H56: =IF(ISBLANK(F56),"",-F56*$N$4) | Z56: =IF(ISBLANK(Y56),"",K56) | AA56: =IF(ISBLANK(Y56),"",Z56/K56) | AB56: =IF(ISBLANK(W56),"",Y56-W56) | AC56: =IF(ISBLANK(Y56),"",(K56-Z56))
B57: 49 | G57: =IF(ISBLANK(F57),"",-F57*$N$3) | H57: =IF(ISBLANK(F57),"",-F57*$N$4) | Z57: =IF(ISBLANK(Y57),"",K57) | AA57: =IF(ISBLANK(Y57),"",Z57/K57) | AB57: =IF(ISBLANK(W57),"",Y57-W57) | AC57: =IF(ISBLANK(Y57),"",(K57-Z57))
B58: 50 | G58: =IF(ISBLANK(F58),"",-F58*$N$3) | H58: =IF(ISBLANK(F58),"",-F58*$N$4) | Z58: =IF(ISBLANK(Y58),"",K58) | AA58: =IF(ISBLANK(Y58),"",Z58/K58) | AB58: =IF(ISBLANK(W58),"",Y58-W58) | AC58: =IF(ISBLANK(Y58),"",(K58-Z58))
E59: TOTAL | F59: =SUM(F9:F58) -> 4943710.6 | G59: =SUM(G9:G58) -> 0 | H59: =SUM(H9:H58) -> 0 | J59: =SUM(J9:J58) -> 11000 | K59: =SUM(K9:K58) -> 5674267.2 | Q59: =IF(ISBLANK(P59),"",P59-N59) | X59: =IF(ISBLANK(W59),"",W59-R59) | Z59: =SUM(Z9:Z58) -> 0 | AB59: =IF(ISBLANK(Y59),"",Y59-W59) | AC59: =SUM(AC9:AC58) -> 0 | AD59: =IF(ISBLANK(Y59),"",Y59-N59)
F63: =F59/0.9 -> 5493011.8
F65: =F63/F4 -> 0.1625459
F66: =F65*100 -> 16.25459

Sheet CCO
A1: CONTRACT CHANGE ORDER (CCO)
A2: CCO No. | B2: Date Added | C2: Description of Change | D2: Status | E2: SR | F2: Sch Impact (Months) | G2: Date Approved | H2: Duration (days)
A3: - | B3: - | C3: - | D3: - | E3: - | F3: - | G3: - | H3: -

Sheet Schedule
A1: Primavera P6 Schedule Status
A2: Project Activities Overview
A3: Schedule Statistics | F3: Active Schedule Activities
A4: Total Act. | B4: Not Started | C4: In Progress | D4: Completed | E4: % | F4: Active | G4: Ahead | H4: On | I4: Behind | J4: Flag
A5: 2134 | B5: 385 | C5: 21 | D5: 1728 | E5: =D5/A5 -> 0.80974695 | F5: 21 | G5: 40 | H5: 145 | I5: 221 | J5: =+G5+H5-I5 -> -36
A6: Critical Path Activities | D6: Free Float Management (Total) | H6: Failed Start Activities | P6: Done
D7: Greater Than 14 Days | F7: Less Than 14 Days
A8: Last Week | B8: This Week | C8: Diff | D8: Last Week | E8: This Week | F8: Last Week | G8: This Week | H8: Last Week | I8: This Week | J8: Flag
A9: 373 | B9: 331 | C9: =A9-B9 -> 42 | D9: 80 | E9: 66 | F9: 374 | G9: 340 | H9: 266 | I9: 240 | J9: =H9-I9 -> 26

Sheet LOOK AHEAD 
A1: مستهدف الربع
A2: # | B2: القطاع | C2: المبادرة | D2: Project ID | E2: اسم المشروع | F2: مدير المشروع | G2: المقاول | H2: بداية المشروع | I2: نهاية المشروع التعاقدية | J2: مدة المشروع (أشهر) | K2: نهاية المشروع المتوقعة/ الالتزام | L2: قيمة المشروع | M2: المخطط /الفعلي | N2: Mobilization المخطط | O2: Mobilization المنفذ | P2: Procurement (Long Lead Items) توريد المواد طويلة الأجل (المخطط) | Q2: Procurement (Long Lead Items) توريد المواد طويلة الأجل (المنفذ) | R2: Civil Work الأعمال المدنيه (المخطط) | S2: Civil Work الأعمال المدنيه (المنفذ) | T2: Mechnical Work أعمال الميكانيكا (المخطط) | U2: Mechnical Work أعمال الميكانيكا (المنفذ) | V2: Mechnical Work أعمال الكهرباء (المخطط) | W2: Mechnical Work أعمال الكهرباء (المنفذ) | X2: تأثير التأخير (إن وجد) على المبادرات في الربع | Y2: نسبة الانجاز المستهدفة بنهاية الربع | Z2: نسبة الانجاز المحققة بنهاية الربع | AA2: مجموع المبالغ المفوترة المستهدفة بنهاية الربع | AB2: مجموع المبالغ المفوترة المحققة بنهاية الربع | AC2: نهاية المشروع المتوقعة
A3: 1 | B3: الغربي | C3: - | D3: MLTX-02-004 | E3: Playground Initiative for Western Region (Asir - Jazan - Jeddah) | F3: Eng.Yazeed Al Ragabh | G3: Profast Company Ltd. | H3: 46107 | I3: 46412 | J3: 10 | K3: 46412 | L3: 33793604 | M3: المخطط=39.13%% الفعلى =35.39% | N3: 1 | O3: 1 | P3: 1- 100% Steel Tension Cables 2- 100% Emergency Doors 3- 100% Pressure Units 4- 100% Lock Doors | Q3: 1- 0% Steel Tension Cables 2- 0% Emergency Doors 3- 0% Pressure Units 4- 0% Lock Doors | R3: 1- الانتهاء من اعمال القواعد للحمامات 100% 2-الانتهاء من أعمال خرسانات الخزانات الارضية 100% 3-الانتهاء من تركيب جدران واسقف الحمامات 100% 4-الانتهاء من أعمال العزل 100% 5- الانتهاء من أعمال تركيب الابواب والشبابيك 100% | S3: 1- الانتهاء من اعمال القواعد للحمامات 100% 2-الانتهاء من أعمال قواعد الخزانات الارضية 100% 3-الانتهاء من تركيب جدران واسقف الحمامات 100% 4-الانتهاء من أعمال العزل 95% 5- الانتهاء من أعمال تركيب الابواب والشبابيك 10% | T3: 1- الانتهاء من أعمال تمديدات الميكانيك للحمامات 100% | U3: 1- الانتهاء من أعمال تمديدات الميكانيك للحمامات 75% | V3: 1- الانتهاء من تركيبات وحدات الانارة (الحمامات) 100% 2- الانتهاء من تركيب الافياش والمفاتيح (الحمامات) 100% | W3: 1- الانتهاء من تركيبات وحدات الانارة 0% 2- الانتهاء من تركيب الافياش والمفاتيح 50% | Y3: 0.4596 | Z3: 0.3539 | AA3: 15533188 | AB3: 5674267.2 | AC3: 46412

Sheet Conclusion
A1: مبادرة الملاعب للمنطقة الغربية (عسير - جازان - جدة) MLTX-02-004
A2: معلومات المشروع | F2: نطاق المشروع | L2: موقع المشروع ( جدة - عسير - جازان )
A3: المقاول | B3: شركة البروفاست المحدودة | C3: الاستشاري | D3: شركة ايجيس السعودية للاستشارات | F3: البند | G3: الكمية الكلية | H3: الكمية المنفذة | I3: الكمية المتبقية | J3: نسبة المنفذ | U3: Playground Initiative for Western Region (Asir - Jazan - Jeddah)
A4: تاريخ استلام الموقع | B4: 26/03/2026 | C4: مدة التنفيذ | D4: 10 شهرًا ميلاديًا | F4: الاعمال الترابية | G4: 1 | H4: 0.9 | I4: =G4-H4 -> 0.1 | J4: =H4 -> 0.9
A5: بداية العقد | B5: من تاريخ استلام الموقع | C5: قيمة العقد (شامل ضريبة القيمة المضافة) | D5: {='Weekly Progress Report'!$O$5:$P$5} -> 33997787 | E5: #REF! | F5: أعمال الخرسانات والبلوك | G5: 1 | H5: 0.9 | I5: =G5-H5 -> 0.1 | J5: =H5 -> 0.9
A6: نسبة الإنجاز المخطط له | B6: 0.3913 | C6: نسبة الإنجاز الفعلي | D6: 0.3539 | F6: أعمال الملاعب | G6: 1 | H6: 0.3 | I6: =G6-H6 -> 0.7 | J6: =H6 -> 0.3
A7: ملخص جدول الكميات | F7: أعمال مناظر الطبيعية | G7: 1 | H7: 0 | I7: =G7-H7 -> 1 | J7: =H7 -> 0
A8: مكونات المشروع | C8: التكلفة (غير شامل ضريبة القيمة المضافة) | D8: النسبة الاجمالية | F8: أعمال توريد الاشجار | G8: 1 | H8: 0 | I8: =G8-H8 -> 1 | J8: =H8 -> 0 | R8: =D5*1.15 -> 39097455
A9: الاعمال الترابية | C9: 1906125 | D9: =C9/$R$8 -> 0.048753173 | F9: أعمال القبة الهوائية | G9: 1 | H9: 0.12 | I9: =G9-H9 -> 0.88 | J9: =H9 -> 0.12
A10: أعمال المواقف | C10: 370012.5 | D10: =C10/$R$8 -> 0.0094638513 | F10: اعمال مواسير الصرف الصحي | G10: 1 | H10: 0.5 | I10: =G10-H10 -> 0.5 | J10: =H10 -> 0.5 | Q10: 20865877 | R10: =Q10*(1-0.0212) -> 20423520
A11: أعمال المناظر الطبيعية والملاعب | C11: 28692664 | D11: =C11/$R$8 -> 0.73387549 | F11: اعمال مواسير التغذية | G11: 1 | H11: 0.5 | I11: =G11-H11 -> 0.5 | J11: =H11 -> 0.5 | Q11: 10508920 | R11: =Q11*(1-0.0212) -> 10286131
A12: أعمال الخرسانات والبلوك | C12: 551991.95 | D12: =C12/$R$8 -> 0.01411836 | F12: اعمال شبكة مياه الري | G12: 1 | H12: 0.1 | I12: =G12-H12 -> 0.9 | J12: =H12 -> 0.1 | Q12: 23728460 | R12: =Q12*(1-0.0212) -> 23225417
A13: الاعمال المعدنية | C13: 47092.5 | D13: =C13/$R$8 -> 0.0012044902 | F13: وحدات الانارة | G13: 1 | H13: 0.2 | I13: =G13-H13 -> 0.8 | J13: =H13 -> 0.2 | Q13: 7970089 | R13: =Q13*(1-0.0212) -> 7801123.1
A14: أعمال نظام العزل | C14: 155034.95 | D14: =C14/$R$8 -> 0.0039653463 | F14: ملخص التوريدات | Q14: 8842925 | R14: =Q14*(1-0.0212) -> 8655455
A15: أعمال الابواب والشبابيك | C15: 235462.5 | D15: =C15/$R$8 -> 0.0060224508 | F15: البند | G15: الكمية الكلية | H15: الكمية المورده | I15: الكمية المتبقية | J15: نسبة التوريد
A16: الاعمال الخاصة والتشطيبات | C16: 742862.05 | D16: =C16/$R$8 -> 0.019000266 | F16: الحوائط الخفيفة للحمامات | G16: 753 | H16: 753 | I16: =G16-H16 -> 0 | J16: =IFERROR(H16/G16,0) -> 1
A17: الاعمال الميكانيكية | C17: 2664969.8 | D17: =C17/$R$8 -> 0.068162231 | F17: حديد التسليح | G17: 25 | H17: 25 | I17: =G17-H17 -> 0 | J17: =IFERROR(H17/G17,0) -> 1
A18: الاعمال الكهربائية | C18: 3731239.4 | D18: =C18/$R$8 -> 0.095434329 | F18: توريد كابلات القبة السماوية | G18: 3 | H18: 0 | I18: =G18-H18 -> 3 | J18: =IFERROR(H18/G18,0) -> 0 | U18: 5041
A19: معالم البرنامج الزمني | F19: توريد الوحدات الصحية للحمامات | G19: 3 | H19: 0.5 | I19: =G19-H19 -> 2.5 | J19: =IFERROR(H19/G19,0) -> 0.16666667 | U19: 12075.28
A20: البند | C20: التاريخ حسب الجدول الزمني | D20: ملاحظة | F20: توريد الخرسانات | G20: 100 | H20: 90 | I20: =G20-H20 -> 10 | J20: =IFERROR(H20/G20,0) -> 0.9 | U20: 8502
A21: نهاية الشروع | C21: 46047 | F21: توريد الانترلوك | G21: =4400+2000 -> 6400 | I21: =G21-H21 -> 6400 | J21: =IFERROR(H21/G21,0) -> 0 | U21: 5775.1
A22: بداية المشروع | C22: 46107 | D22: تم الانتهاء | F22: توريد البردورات | G22: 17550 | I22: =G22-H22 -> 17550 | J22: =IFERROR(H22/G22,0) -> 0
A23: الانتهاء من تجهيزات الموقع. | C23: 46137 | D23: تم الانتهاء | L23: تقدم أعمال layout
A24: تقديم خطة العمل والبرنامج الزمني | C24: 46135 | D24: تم الانتهاء
A25: تقديم واعتماد المخططات والمواد | C25: 46225 | D25: جاري
A26: الانتهاء من الاعمال الترابية | C26: 46243 | D26: جاري
A27: الانتهاء من أعمال الحمامات | C27: 46356 | D27: جاري | F27: التحديات والعوائق
A28: الانتهاء من المناطق الخضراء | C28: 46369 | D28: جاري
A29: الانتهاء من تنفيذ الملاعب | C29: 46038 | D29: جاري
A30: الانتهاء من كامل الأعمال لموقع عسير | C30: 46406 | D30: لم يبدأ
A31: الانتهاء من كامل الأعمال لموقع جازان | C31: 46412 | D31: لم يبدأ
A32: الانتهاء من كامل الأعمال لموقع جدة | C32: 46412 | D32: لم يبدأ
A33: الانتهاء من الاختبار والتشغيل | C33: 46406 | D33: لم يبدأ
Q36: 1-التصريف السطحي على القناة المفتوحة بالجهة الشرقية بمشروع جدة 2-التصريف السطحي للطريق بالجهة الشرقية بمشروع عسير 3-وجود تربة صخرية أثناء الحفر بموقع عسير 4- تغيير اماكن مواقف انتظار سيارات بموقع جازان 5- اقتراح امكانية رفع منسوب مشروع موقع جدة

Sheet Issues
M3: ='General Information'!L1 -> 46314 | N3: Status | O3: Responsibility
N4: Open | O4: Contractor
N5: Closed | O5: Consultant
O6: Modon
O7: Third Party
O8: Other
B9: Issue Log
B10: Issue No | C10: Date Identified | D10: Issue Description | E10: Responsibility | F10: Action Taken | H10: Current Status | I10: Expected/Actual Closure | J10: Duration Elapsed
B11: 1 | D11: Connection of the project to the drainage channel on the eastern side.(Jeddah) | E11: Contractor | F11: Coordination between the Municipality (City Management) and the infrastructure contractor. | H11: Completed | I11: 46163 | L11: Owner
B12: 2 | D12: drainage pipe was encountered during site excavation.(Jeddah) | E12: Owner | F12: The required calculations and slope analysis have been completed. | H12: Completed | I12: 46163 | L12: Contractor
B13: 3 | C13: 46147 | D13: Based on the visit by Modon management, it was noted that the project level can be raised to match the external road level in front of the parking area.(Jeddah) | E13: Owner | F13: The required filling quantity was estimated at 59,000 m³ | H13: Completed | I13: 46163 | L13: Consultant | P13: closed
B14: 4 | D14: Increase the sewage tank capacity for the Asir project to serve the administration building and playgrounds. | E14: Contractor | F14: Waiting for clarification of the project savings/cost reductions. | H14: Completed | I14: 46152
B15: 5 | C15: 46163 | D15: Difficulty accessing the parking area due to a level difference- Jazan | E15: Consultant | F15: Relocating the parking area to the far left side. | H15: Completed | I15: 46158
B16: 6 | C16: 13-05-2026 | D16: Road shoulder overlap at the Jeddah site | E16: Consultant | F16: A proposal has been submitted to the consultant. | H16: Completed | I16: 46296
B17: 7 | C17: 46059 | D17: Trees located within Asir site. | E17: Owner | F17: Waiting for tree removal by the landscaping contractor. | H17: Completed | I17: 46158
B18: 8 | C18: 46305 | D18: Medium voltage cables on excavation way | E18: Owner | F18: Medium voltage cables are conflicting with the excavation route. Assessment and coordination with relevant stakeholders are ongoing to determine the required mitigation actions. Risk remains open. | H18: Open | I18: 46312
B19: 9
B20: 10
B59: 48
B60: 49
B61: 50
B62: 13 | D62: MV Network | H62: Open

Sheet Testing
A1: Testing and Commissioning
A2: Item | B2: Planned Start Date | C2: Planned Finish Date | D2: Forecast Start Date | E2: Forecast Finish Date | F2: Actual Start Date | G2: Actual Finish Date | H2: % Completed | I2: Open Comments | J2: Closed Comments
A3: TESTING & COMMISSIONING JEDDAH | B3: 46357 | C3: 46405 | D3: 46357 | E3: 46471
A4: TESTING & COMMISSIONING ASIR | B4: 46331 | C4: 46399 | D4: 46410 | E4: 46488
A5: TESTING & COMMISSIONING JAZAN | B5: 46343 | C5: 46406 | D5: 46408 | E5: 46485
D6: =#REF! -> #REF! | E6: =#REF! -> #REF!
A18: TESTING & COMMISSIONING JEDDAH | C18: 46357 | D18: 46471 | E18: 46357 | F18: 46405
A19: TESTING & COMMISSIONING ASIR | C19: 46410 | D19: 46488 | E19: 46331 | F19: 46399
A20: TESTING & COMMISSIONING JAZAN | C20: 46408 | D20: 46485 | E20: 46343 | F20: 46406

Sheet Manpower
A1: Head-Count ( Non Manual)
A2: MONTHS | B2: 46082 | C2: 46113 | D2: 46143 | E2: 46174 | F2: 46204 | G2: 46235 | H2: 46266 | I2: 46296 | J2: 46327 | K2: 46357 | L2: 46388 | AM2: non direct | BQ2: Jazan | CJ2: Asir | DG2: Jeddah
A3: Plan - Monthly | B3: 19 | C3: 19 | D3: 19 | E3: 19 | F3: 19 | G3: 19 | H3: 19 | I3: 19 | J3: 19 | K3: 19 | L3: 19 | BI3: CONTRACTOR STAFF | BU3: CONTRACTOR LABOUR | CG3: CONTRACTOR STAFF | CS3: CONTRACTOR LABOUR | DE3: CONTRACTOR STAFF | DQ3: CONTRACTOR LABOUR
A4: Planned - Cumulative | B4: =B3 -> 19 | C4: =B4+C3 -> 38 | D4: =C4+D3 -> 57 | E4: =D4+E3 -> 76 | F4: =E4+F3 -> 95 | G4: =F4+G3 -> 114 | H4: =G4+H3 -> 133 | I4: =H4+I3 -> 152 | J4: =I4+J3 -> 171 | ... L4: =K4+L3 -> 209 | BI4: POSITION | BP4: Expats | BR4: Saudi | BU4: TRADE | CA4: Expats | CC4: Saudi | CG4: POSITION | CN4: Expats | CP4: Saudi | CS4: TRADE | CY4: Expats | DA4: Saudi | DE4: POSITION | DL4: Expats | DN4: Saudi | DQ4: TRADE | DW4: Expats | DY4: Saudi
A5: Actual - Monthly | B5: 10 | C5: 15 | D5: 22 | E5: 32 | F5: 31 | G5: 30 | H5: 30 | I5: 30 | AM5: daily report | BI5: Project Manager | BU5: General Labor / Helper | CA5: 2 | CG5: Project Manager | CS5: General Labor / Helper | CY5: 4 | DE5: Project Manager | DL5: 2 | DQ5: General Labor / Helper | DW5: 10
A6: Actual Cumulative | B6: =B5 -> 10 | C6: =B6+C5 -> 25 | D6: =C6+D5 -> 47 | E6: =D6+E5 -> 79 | F6: =E6+F5 -> 110 | G6: =F6+G5 -> 140 | H6: =G6+H5 -> 170 | I6: =H6+I5 -> 200 | BI6: Civil Engineer | BP6: 2 | BU6: Carpenter | CG6: Civil Engineer | CN6: 2 | CS6: Carpenter | DE6: Civil Engineer | DL6: 4 | DQ6: Carpenter
A7: Forecast - Monthly | H7: 20 | I7: 20 | J7: 20 | K7: 20 | L7: 20 | BI7: Technical office manager | BU7: Steel Fixer | CG7: Technical office manager | CS7: Steel Fixer | CY7: 6 | DE7: Technical office manager | DL7: 2 | DQ7: Steel Fixer | DW7: 4
A8: Saudi Monthly - Actual | BI8: Quality Engineer | BU8: Concreting Labor | CG8: Quality Engineer | CS8: Concreting Labor | CY8: 4 | DE8: Quality Engineer | DQ8: Concreting Labor | DW8: 4
A9: Head-Count (Manual) | AM9: direct | BI9: HSE Engineer | BU9: Plumber | CG9: HSE Engineer | CS9: Plumber | DE9: HSE Engineer | DQ9: Plumber
A10: MONTHS | B10: 46082 | C10: 46113 | D10: 46143 | E10: 46174 | F10: 46204 | G10: 46235 | H10: 46266 | I10: 46296 | J10: 46327 | K10: 46357 | L10: 46388 | BI10: Planning Engineer | BU10: Electricial | CG10: Planning Engineer | CS10: Electricial | DE10: Planning Engineer | DL10: 2 | DQ10: Electricial
A11: Plan - Monthly | B11: 4 | C11: 35 | D11: 79 | E11: 165 | F11: 159 | G11: 140 | H11: 177 | I11: 175 | J11: 159 | K11: 150 | L11: 64 | BI11: Surveyor Engineer | BP11: 2 | BU11: Equipment Operator | CG11: Surveyor Engineer | CS11: Equipment Operator | DE11: Surveyor Engineer | DL11: 2 | DQ11: Equipment Operator
A12: Planned - Cumulative | B12: =B11 -> 4 | C12: =C11+B12 -> 39 | D12: =D11+C12 -> 118 | E12: =D12+E11 -> 283 | F12: =E12+F11 -> 442 | G12: =F12+G11 -> 582 | H12: =G12+H11 -> 759 | I12: =H12+I11 -> 934 | J12: =I12+J11 -> 1093 | K12: =J12+K11 -> 1243 | L12: =K12+L11 -> 1307 | BI12: Electrical Engineer | BU12: Glass & aluminum technical | CG12: Electrical Engineer | CS12: Glass & aluminum technical | DE12: Electrical Engineer | DQ12: Glass & aluminum technical
A13: Actual - Monthly | B13: 4 | C13: 30 | D13: =56+18 -> 74 | E13: 123 | F13: 63 | G13: 72 | H13: 64 | I13: 70 | AM13: daily report | AQ13: =W2-V2 -> 0 | BI13: Mechanical Engineer | BU13: OTHER | CG13: Mechanical Engineer | CS13: OTHER | DE13: Mechanical Engineer | DQ13: OTHER
A14: Actual Cumulative | B14: =B13 -> 4 | C14: =B14+C13 -> 34 | D14: =C14+D13 -> 108 | E14: =D14+E13 -> 231 | F14: =E14+F13 -> 294 | G14: =F14+G13 -> 366 | H14: =G14+H13 -> 430 | I14: =H14+I13 -> 500 | BI14: Agriculture Engineer | BU14: curbstone worker | CG14: Agriculture Engineer | CS14: curbstone worker | DE14: Agriculture Engineer | DQ14: curbstone worker
A15: Forecast - Monthly | I15: =I11 -> 175 | J15: =J11 -> 159 | K15: =K11 -> 150 | L15: =L11 -> 64 | BI15: Quantity Surveyor Engineer | BU15: Water proofing labor | CG15: Quantity Surveyor Engineer | CS15: Water proofing labor | DE15: Quantity Surveyor Engineer | DQ15: Water proofing labor
A16: Saudi - Actual | BI16: HSE Officer | BP16: 2 | BU16: PLASTER WORKER | CG16: HSE Officer | CN16: 2 | CS16: PLASTER WORKER | DE16: HSE Officer | DL16: 2 | DQ16: PLASTER WORKER
BI17: Surveyor | BU17: SHUTERR DOOR WORKER | CG17: Surveyor | CN17: 2 | CS17: SHUTERR DOOR WORKER | DE17: Surveyor | DL17: 2 | DQ17: SHUTERR DOOR WORKER
A18: Head-Count (Non-Manual) | L18: =D13+D5 -> 96 | AG18: Month | AI18: =EOMONTH('General Information'!$L$1,0) -> 46326 | AM18: =EOMONTH(AI18,1) -> 46356 | BI18: Document Controller | BU18: steel stu worker | CG18: Document Controller | CS18: steel stu worker | DE18: Document Controller | DL18: 2 | DQ18: steel stu worker
A19: Planned | B19: Actual | D19: Variance | F19: Forecast Next Month | H19: Saudi Staff | BI19: Supervisor | BP19: 2 | BU19: epoxy worker | CG19: Supervisor | CN19: 4 | CS19: epoxy worker | DE19: Supervisor | DL19: 2 | DQ19: epoxy worker
A20: 19 | B20: =G5 -> 30 | D20: =B20-A20 -> 11 | F20: 25 | H20: 0 | BU20: ASPHALT WORKER | CS20: ASPHALT WORKER | DE20: Labor | DL20: 2 | DQ20: ASPHALT WORKER
BU21: paint workers | CS21: paint workers | DQ21: paint workers
A22: Head-Count (Manual) | L22: Man Power by Trade | BU22: TANKS workers | CS22: TANKS workers | DQ22: TANKS workers
A23: Planned | B23: Actual | D23: Variance | F23: Forecast Next Month | H23: Saudi Staff | L23: Key Trade | N23: Labor | P23: Skilled Labor | R23: Driver / Operator | T23: Carpenter | V23: Steel Fixer | X23: Mason | Z23: Plumber | AB23: Electrician | AD23: Others | AF23: Total | AV23: 46082 | AW23: 46113 | AX23: 46143 | AY23: 46174 | AZ23: 46204 | BA23: 46235 | BB23: 46266 | BC23: 46296 | BD23: 46327 | BE23: 46357 | BF23: 46388 | BU23: fire worker | CS23: fire worker | DQ23: fire worker
A24: 175 | B24: 70 | D24: =B24-A24 -> -105 | F24: 140 | H24: 0 | L24: Plan | N24: 65 | P24: 25 | R24: 27 | T24: 0 | V24: 26 | X24: 0 | Z24: 0 | AB24: 0 | AD24: 32 | AF24: =SUM(N24:AE24) -> 175 | BU24: Celing worker | CS24: Celing worker | DQ24: Celing worker
L25: Actual | N25: 15 | P25: 10 | R25: 12 | T25: 6 | V25: 6 | X25: 0 | Z25: 3 | AB25: 3 | AD25: 15 | AF25: =SUM(N25:AE25) -> 70 | BU25: Air conditioning technician | CS25: Air conditioning technician | DQ25: Air conditioning technician
BU26: TOTAL | CA26: =SUM(CA5:CD21) -> 2 | CS26: TOTAL | CY26: =SUM(CY5:DB21) -> 14 | DQ26: TOTAL | DW26: =SUM(DW5:DZ21) -> 18
BU28: SUB-CONTRACTORS LABOURS | CS28: SUB-CONTRACTORS LABOURS | DQ28: SUB-CONTRACTORS LABOURS
BU29: DESCRIPTION | CA29: Expats | CC29: Saudi | CS29: DESCRIPTION | CY29: Expats | DA29: Saudi | DQ29: DESCRIPTION | DW29: Expats | DY29: Saudi
BU30: Carpenter | CS30: Carpenter | DQ30: Carpenter
BU31: Steel Fixers | CS31: Steel Fixers | DQ31: Steel Fixers
A32: Equipment | BU32: Labors | CS32: Labors | DQ32: Labors
A33: MONTHS | B33: 46082 | C33: 46113 | D33: 46143 | E33: 46174 | F33: 46204 | G33: 46235 | H33: 46266 | I33: 46296 | J33: 46327 | K33: 46357 | L33: 46388 | BU33: Drivers | CS33: Drivers | DQ33: Drivers
A34: Plan - Monthly | B34: 0 | C34: 10 | D34: 25 | E34: 29 | F34: 25 | G34: 24 | H34: 19 | I34: 27 | J34: 16 | K34: 20 | L34: 12 | BU34: TOTAL | CA34: =SUM(CA30:CD33) -> 0 | CS34: TOTAL | CY34: =SUM(CY30:DB33) -> 0 | DQ34: TOTAL | DW34: =SUM(DW30:DZ33) -> 0
A35: Planned - Cumulative | B35: =B34 -> 0 | C35: =B35+C34 -> 10 | D35: =C35+D34 -> 35 | E35: =D35+E34 -> 64 | F35: =E35+F34 -> 89 | G35: =F35+G34 -> 113 | H35: =G35+H34 -> 132 | I35: =H35+I34 -> 159 | J35: =I35+J34 -> 175 | ... L35: =K35+L34 -> 207 | BI35: TOTAL CONTRACTOR STAFF | BP35: =SUM(BP5:BS34) -> 8 | BU35: TOTAL PLANNED DIRECT MANPOWER | CG35: TOTAL CONTRACTOR STAFF | CN35: =SUM(CN5:CQ34) -> 10 | CS35: TOTAL PLANNED DIRECT MANPOWER | DE35: TOTAL CONTRACTOR STAFF | DL35: =SUM(DL5:DO34) -> 22 | DQ35: TOTAL PLANNED DIRECT MANPOWER
A36: Actual - Monthly | B36: 0 | C36: 10 | D36: =CA128 -> 25 | E36: 44 | F36: 44 | G36: 36 | H36: 30 | I36: 21 | BU36: TOTAL ACTUAL DIRECT MANPOWER | CC36: =SUM(CA34,CA26) -> 2 | CS36: TOTAL ACTUAL DIRECT MANPOWER | DA36: =SUM(CY34,CY26) -> 14 | DQ36: TOTAL ACTUAL DIRECT MANPOWER | DY36: =SUM(DW34,DW26) -> 18
A37: Actual Cumulative | B37: =B36 -> 0 | C37: =B37+C36 -> 10 | D37: =C37+D36 -> 35 | E37: =D37+E36 -> 79 | F37: =E37+F36 -> 123 | G37: =F37+G36 -> 159 | H37: =G37+H36 -> 189 | I37: =H37+I36 -> 210 | BI37: CONSULTANT STAFF | CG37: CONSULTANT STAFF | DE37: CONSULTANT STAFF
A38: Forecast - Monthly | G38: 30 | H38: =H34 -> 19 | I38: =I34 -> 27 | J38: =J34 -> 16 | K38: =K34 -> 20 | L38: =L34 -> 12 | BI38: POSITION | BP38: Expats | BR38: Saudi | BU38: EQUIPMENT AVAILABLE AT SITE TODAY | CG38: POSITION | CN38: Expats | CP38: Saudi | CS38: EQUIPMENT AVAILABLE AT SITE TODAY | DE38: POSITION | DL38: Expats | DN38: Saudi | DQ38: EQUIPMENT AVAILABLE AT SITE TODAY
BI39: Project Engineer | BP39: 0 | BU39: TYPE | CA39: Working | CC39: Idle | CG39: Project Engineer | CN39: 0 | CS39: TYPE | CY39: Working | DA39: Idle | DE39: Project Engineer | DL39: 2 | DQ39: TYPE | DW39: Working | DY39: Idle
BI40: Control / Schedule Engineer | BP40: 0 | BU40: Buldozer | CA40: 0 | CG40: Control / Schedule Engineer | CN40: 0 | CS40: Buldozer | CY40: 0 | DE40: Control / Schedule Engineer | DL40: 2 | DQ40: Buldozer | DW40: 0
A41: Equipment Count | BI41: Quality Engineer | BP41: 0 | BU41: Grader Machine | CA41: 0 | CG41: Quality Engineer | CN41: 0 | CS41: Grader Machine | CY41: 0 | DE41: Quality Engineer | DL41: 2 | DQ41: Grader Machine | DW41: 2
A42: Planned | B42: Actual | D42: Idle | F42: Variance | H42: Forecast Next Month | BI42: HSE Engineer | BP42: 0 | BU42: Roller Compactor | CA42: 0 | CG42: HSE Engineer | CN42: 0 | CS42: Roller Compactor | CY42: 0 | DE42: HSE Engineer | DL42: 2 | DQ42: Roller Compactor | DW42: 0
A43: 27 | B43: 21 | D43: =O52 -> 0 | F43: =B43-A43 -> -6 | H43: 20 | BI43: Mechanical Engineer | BP43: 0 | BU43: Shevol Loader | CA43: 2 | CG43: Mechanical Engineer | CN43: 0 | CS43: Shevol Loader | CY43: 2 | DE43: Mechanical Engineer | DL43: 2 | DQ43: Shevol Loader | DW43: 4
BI44: Electrical Engineer | BP44: 0 | BU44: Water Tank | CA44: 0 | CG44: Electrical Engineer | CN44: 0 | CS44: Water Tank | CY44: 0 | DE44: Electrical Engineer | DL44: 2 | DQ44: Water Tank | DW44: 0
BI45: Planning Engineer | BP45: 0 | BU45: Dump Truck | CA45: 0 | CG45: Planning Engineer | CN45: 0 | CS45: Dump Truck | CY45: 10 | DE45: Planning Engineer | DL45: 2 | DQ45: Dump Truck | DW45: 8
BI46: Civil Engineer - Structure/Buildings | BP46: 0 | BU46: Poclain Excavator | CA46: 6 | CG46: Civil Engineer - Structure/Buildings | CN46: 0 | CS46: Poclain Excavator | CY46: 2 | DE46: Civil Engineer - Structure/Buildings | DL46: 2 | DQ46: Poclain Excavator | DW46: 2
BI47: Civil Engineer - Wet Utilities | BP47: 0 | BU47: Bobcat | CA47: 0 | CG47: Civil Engineer - Wet Utilities | CN47: 0 | CS47: Bobcat | CY47: 0 | DE47: Civil Engineer - Wet Utilities | DL47: 2 | DQ47: Bobcat | DW47: 0
BI48: Architect | BP48: 0 | BU48: Truck | CA48: 12 | CG48: Architect | CN48: 0 | DE48: Architect | DL48: 2
A49: Type | B49: Excavator | C49: Loader | D49: Bulldozer | E49: Water Tanker | F49: Grader | G49: Truck | H49: Road Roller | I49: Asphalt Paver | J49: Crane | K49: Bobcat | L49: Bobcat | M49: Compactor | N49: Other | O49: Total | BI49: Surveyor | BP49: 2 | BU49: Crane | CA49: 0 | CG49: Surveyor | CN49: 0 | DE49: Surveyor | DL49: 2
A50: Plan | B50: 3 | C50: 5 | D50: 2 | E50: 5 | F50: 3 | G50: 5 | H50: 1 | I50: 0 | J50: 0 | K50: 0 | L50: 0 | M50: 3 | N50: 0 | O50: =SUM(B50:N50) -> 27 | BI50: Quality Engineer | BP50: 0 | CG50: Quality Engineer | CN50: 0 | DE50: Quality Engineer | DL50: 2
A51: Actual | B51: 3 | C51: 3 | D51: 0 | E51: 4 | F51: 0 | G51: 3 | H51: 0 | I51: 0 | J51: 0 | K51: 0 | L51: 2 | M51: 6 | N51: 0 | O51: =SUM(B51:N51) -> 21 | BI51: Document Controller | BP51: 0 | CG51: Document Controller | CN51: 2 | DE51: Document Controller | DL51: 2
A52: Idle | B52: 0 | C52: 0 | D52: 0 | E52: 0 | F52: 0 | G52: 0 | H52: 0 | I52: 0 | J52: 0 | K52: 0 | L52: 0 | M52: 0 | N52: 0 | O52: =SUM(B52:N52) -> 0 | BI52: Office Boy | BP52: 0 | CG52: Office Boy | CN52: 0 | DE52: Office Boy | DL52: 2
BI53: TOTAL CONSULTANT STAFF | BP53: =SUM(BP39:BS52) -> 2 | CG53: TOTAL CONSULTANT STAFF | CN53: =SUM(CN39:CQ52) -> 2 | DE53: TOTAL CONSULTANT STAFF | DL53: =SUM(DL39:DO52) -> 28
BI54: TOTAL STAFF AT SITE | BP54: =BP35+BP53 -> 10 | CG54: ` | CN54: =CN35+CN53 -> 12 | DE54: TOTAL STAFF AT SITE | DL54: =DL35+DL53 -> 50
BI55: TOTAL IMMUNE STAFF | CG55: TOTAL IMMUNE STAFF | DE55: TOTAL IMMUNE STAFF
BI57: MATERIAL RECEIVED AT SITE TODAY (MIR) | CG57: MATERIAL RECEIVED AT SITE TODAY (MIR) | DE57: MATERIAL RECEIVED AT SITE TODAY (MIR)
BI58: BOQ No. | BK58: DESCRIPTION | BR58: QTY | BS58: UNIT | CG58: BOQ No. | CI58: DESCRIPTION | CP58: QTY | CQ58: UNIT | DE58: BOQ No. | DG58: DESCRIPTION | DN58: QTY | DO58: UNIT
BK59: - | BU59: TOTAL PLANNED | CI59: - | CS59: TOTAL PLANNED | DG59: - | DQ59: TOTAL PLANNED
BK60: - | BU60: TOTAL ACTUAL | CA60: =SUM(CA40:CB58) -> 20 | CC60: =SUM(CC40:CD58) -> 0 | CI60: - | CS60: TOTAL ACTUAL | CY60: =SUM(CY40:CZ58) -> 14 | DA60: =SUM(DA40:DB58) -> 0 | DG60: - | DQ60: TOTAL ACTUAL | DW60: =SUM(DW40:DX58) -> 16 | DY60: =SUM(DY40:DZ58) -> 0
BI68: ALL Sites
BI71: CONTRACTOR STAFF | BU71: CONTRACTOR LABOUR
BI72: POSITION | BP72: Expats | BR72: Saudi | BU72: TRADE | CA72: Expats | CC72: Saudi
BI73: Project Manager | BU73: General Labor / Helper | CA73: =(CA5+CY5+DW5)/2 -> 8
BI74: Civil Engineer | BP74: =(BP6+CN6+DL6)/2 -> 4 | BU74: Carpenter | CA74: =(CA6+CY6+DW6)/2 -> 0
BI75: Technical office manager | BP75: =(BP7+CN7+DL7)/2 -> 1 | BU75: Steel Fixer | CA75: =(CA7+CY7+DW7)/2 -> 5
BI76: Quality Engineer | BP76: =(BP8+CN8+DL8)/2 -> 0 | BU76: Concreting Labor | CA76: =(CA8+CY8+DW8)/2 -> 4
BI77: HSE Engineer | BP77: =(BP9+CN9+DL9)/2 -> 0 | BU77: Plumber | CA77: =(CA9+CY9+DW9)/2 -> 0
BI78: Planning Engineer | BP78: =(BP10+CN10+DL10)/2 -> 1 | BU78: Electricial | CA78: =(CA10+CY10+DW10)/2 -> 0
BI79: Surveyor Engineer | BP79: =(BP11+CN11+DL11)/2 -> 2 | BU79: Equipment Operator | CA79: =(CA11+CY11+DW11)/2 -> 0
BI80: Electrical Engineer | BP80: =(BP12+CN12+DL12)/2 -> 0 | BU80: Glass & aluminum technical | CA80: =(CA12+CY12+DW12)/2 -> 0
BI81: Mechanical Engineer | BP81: =(BP13+CN13+DL13)/2 -> 0 | BU81: OTHER | CA81: =(CA13+CY13+DW13)/2 -> 0
BI82: Agriculture Engineer | BP82: =(BP14+CN14+DL14)/2 -> 0 | BU82: curbstone worker | CA82: =(CA14+CY14+DW14)/2 -> 0
BI83: Quantity Surveyor Engineer | BP83: =(BP15+CN15+DL15)/2 -> 0 | BU83: Water proofing labor | CA83: =(CA15+CY15+DW15)/2 -> 0
BI84: HSE Officer | BP84: =(BP16+CN16+DL16)/2 -> 3 | BU84: PLASTER WORKER | CA84: =(CA16+CY16+DW16)/2 -> 0
BI85: Surveyor | BP85: =(BP17+CN17+DL17)/2 -> 2 | BU85: SHUTERR DOOR WORKER | CA85: =(CA17+CY17+DW17)/2 -> 0
... BI87: Supervisor | BP87: =(BP19+CN19+DL19)/2 -> 4 | BU87: epoxy worker | CA87: =(CA19+CY19+DW19)/2 -> 0
BU88: ASPHALT WORKER | CA88: =(CA20+CY20+DW20)/2 -> 0
BU89: paint workers | CA89: =(CA21+CY21+DW21)/2 -> 0
BU90: TANKS workers | CA90: =(CA22+CY22+DW22)/2 -> 0
BU91: fire worker | CA91: =(CA23+CY23+DW23)/2 -> 0
BU92: Celing worker | CA92: =(CA24+CY24+DW24)/2 -> 0
BU93: Air conditioning technician | CA93: =(CA25+CY25+DW25)/2 -> 0
BU94: TOTAL | CA94: =SUM(CA73:CD89) -> 17
BU96: SUB-CONTRACTORS LABOURS
BU97: DESCRIPTION | CA97: Expats | CC97: Saudi
BU98: Carpenter
BU99: Steel Fixers
BU100: Labors
BU101: Drivers
BU102: TOTAL | CA102: =SUM(CA98:CD101) -> 0
BI103: TOTAL CONTRACTOR STAFF | BP103: =SUM(BP73:BS102) -> 18 | BU103: TOTAL PLANNED DIRECT MANPOWER
BU104: TOTAL ACTUAL DIRECT MANPOWER | CC104: =SUM(CA102,CA94) -> 17
BI105: CONSULTANT STAFF
BI106: POSITION | BP106: Expats | BR106: Saudi | BU106: EQUIPMENT AVAILABLE AT SITE TODAY
BI107: Project Engineer | BP107: =(BP39+CN39+DL39)/2 -> 1 | BU107: TYPE | CA107: Working | CC107: Idle
BI108: Control / Schedule Engineer | BP108: =(BP40+CN40+DL40)/2 -> 1 | BU108: Buldozer | CA108: =(CA40+CY40+DW40)/2 -> 0
BI109: Quality Engineer | BP109: =(BP41+CN41+DL41)/2 -> 1 | BU109: Grader Machine | CA109: =(CA41+CY41+DW41)/2 -> 1
BI110: HSE Engineer | BP110: =(BP42+CN42+DL42)/2 -> 1 | BU110: Roller Compactor | CA110: =(CA42+CY42+DW42)/2 -> 0
BI111: Mechanical Engineer | BP111: =(BP43+CN43+DL43)/2 -> 1 | BU111: Shevol Loader | CA111: =(CA43+CY43+DW43)/2 -> 4
BI112: Electrical Engineer | BP112: =(BP44+CN44+DL44)/2 -> 1 | BU112: Water Tank | CA112: =(CA44+CY44+DW44)/2 -> 0
BI113: Planning Engineer | BP113: =(BP45+CN45+DL45)/2 -> 1 | BU113: Dump Truck | CA113: =(CA45+CY45+DW45)/2 -> 9
...

Sheet HSE-Stat
A1: Safety Statistics (06-Oct-2026 to 13-October-2026)
A3: Category | B3: Item | D3: This Week | E3: This Month | F3: Year to Date | G3: Cumulative | O3: Item | Q3: This Week | R3: This Month | S3: Year to Date | T3: Cumulative
A4: Lagging Indicators | B4: Total Hours Worked | D4: 5220 | E4: 11700 | F4: 137270 | G4: 137270 | O4: Total Hours Worked | Q4: 4620 | R4: 14280 | S4: 40050 | T4: 40050
B5: Safe Hours Worked | D5: 5220 | E5: =E4 -> 11700 | F5: =F4 -> 137270 | G5: =G4 -> 137270 | O5: Safe Hours Worked | Q5: 4620 | R5: 14280 | S5: 40050 | T5: 40050
B6: LTI | D6: 0 | E6: 0 | F6: 0 | G6: 0 | I6: =L7*10*6 -> 5220 | K6: 32 | L6: 55 | O6: LTI | Q6: 0 | R6: 0 | S6: 0 | T6: 0
B7: MTC (Healed w/o Disability) | D7: 0 | E7: 0 | F7: 0 | G7: 0 | L7: =L6+K6 -> 87 | O7: MTC (Healed w/o Disability) | Q7: 0 | R7: 0 | S7: 0 | T7: 0
B8: MTC (Healed w/ Disability) | D8: 0 | E8: 0 | F8: 0 | G8: 0 | K8: Indirect Contractor Staff | L8: Final Direct Manpower | O8: MTC (Healed w/ Disability) | Q8: 0 | R8: 0 | S8: 0 | T8: 0
B9: Near Miss | D9: 0 | E9: 0 | F9: 0 | G9: 0 | O9: Near Miss | Q9: 0 | R9: 0 | S9: 0 | T9: 0
B10: First Aid Cases | D10: 0 | E10: 0 | F10: 0 | G10: 0 | O10: First Aid Cases | Q10: 0 | R10: 0 | S10: 0 | T10: 0
B11: Fatality | D11: 0 | E11: 0 | F11: 0 | G11: 0 | O11: Fatality | Q11: 0 | R11: 0 | S11: 0 | T11: 0
B12: Fire Incident Cases | D12: 0 | E12: 0 | F12: 0 | G12: 0 | O12: Fire Incident Cases | Q12: 0 | R12: 0 | S12: 0 | T12: 0
B13: Vehicle Incident | D13: 0 | E13: 0 | F13: 0 | G13: 0 | O13: Vehicle Incident | Q13: 0 | R13: 0 | S13: 0 | T13: 0
B14: Property Damages | D14: 0 | E14: 0 | F14: 0 | G14: 0 | O14: Property Damages | Q14: 0 | R14: 0 | S14: 0 | T14: 0
A15: Proactive | B15: Induction Training | D15: 0 | E15: 18 | F15: 160 | G15: 160 | O15: Induction Training | Q15: 5 | R15: 115 | S15: 115 | T15: 115
B16: No.of Internal Training | D16: 0 | E16: 04 Session | F16: 17 Session | G16: 17 Session | O16: No.of Internal Training | Q16: 1 | R16: 3 Session | S16: 6 Session | T16: 6 Session
B17: No.of Internal Audit | D17: 0 | E17: 0 | F17: 0 | G17: 0 | O17: No.of Internal Audit | Q17: 0 | R17: 0 | S17: 0 | T17: 0
B18: No. of Toolbox Talks | D18: 3 | E18: 7 Sessions | F18: 159 sessions | G18: 159 sessions | O18: No. of Toolbox Talks | Q18: 3 | R18: 6 sessions | S18: 18 sessions | T18: 18 sessions
B19: Safety Awards/Incentives | D19: 0 | E19: 0 | F19: 0 | G19: 0 | O19: Safety Awards/Incentives | Q19: 0 | R19: 0 | S19: 0 | T19: 0
I20: Category | J20: Item | L20: This Week | M20: This Month | N20: Year to Date | O20: Cumulative
A22: Consultant Safety Inspection (Weekly Basis) | I22: Overall Average | J22: =AVERAGE(E24:E293) -> 0.93333333
A23: Week Number | B23: Date of Audit | C23: Date Issued | D23: Numbers Of Comments | E23: Overall Score | F23: Date Closed | G23: Closure Duration | I23: This Week Score | J23: 0.77631579
A24: Week-1 | B24: 46140 | C24: 46140 | D24: 9 | E24: 0.8 | F24: 46147 | G24: =F24-C24+1 -> 8
A25: Week-2 | B25: 46146 | C25: 46155 | D25: 10 | E25: 0.8 | F25: 46155 | G25: =F25-C25+1 -> 1
A26: Week-3 | B26: 46147 | C26: 46147 | D26: 2 | E26: 1 | F26: NA | G26: NA
A27: Week-4 | B27: 46148 | C27: 46148 | D27: 10 | E27: 1 | F27: 46183 | G27: 34
A28: Week-5 | B28: 46156 | C28: 14-05-2026 | D28: 11 | E28: 1 | F28: 46205 | G28: NA
A29: Week-6 | B29: 46181 | C29: 46181 | D29: 10 | E29: 1 | F29: 46205 | G29: NA
A30: Week-7 | B30: 20-06-2026 | C30: 20-06-2026 | D30: 7 | E30: 1 | F30: 46205 | G30: NA
A31: Week-8 | B31: 46211 | C31: 46211 | D31: 7 | E31: 0.8 | F31: 21-08-2026 | G31: NA
A32: Week-9 | B32: 27-07-2026 | C32: 27-07-2026 | D32: 17 | E32: 1 | F32: 21-08-2026 | G32: NA
A33: Week-10
A34: Week-11
A35: Week-12
A36: Week-13
A37: Week-14
A38: Week-15
A39: Week-16
A40: Week-17
A41: Week-18
A42: Week-19
A43: Week-20
A44: Week-21
... A91: week-67

Sheet HSE
B1: MODON HSE Site Inspection Report
B2: Date | E2: 46308 | L2: Inspected By: | T2: PMO
B4: Project ID. | E4: MLTX-02-004 | L4: Report No. | P4: 13 | W4: MODON PM Name | Y4: Engr.Yazeed Al Ragabh
B6: Project Name: | E6: Playground Initiative Western Region | L6: Contractor: | R6: PROFAST | X6: Safety Performance | AA6: =IF(W29>0,3,IF(L29>6,2,IF(D29>0,2,1)*1)*1) -> 2 | AE6: =(((COUNTIF(L13:Q25,"1")+COUNTIF(AC13:AH25,"1"))*AR13)+(COUNTIF(L13:Q25,"2")+COUNTIF(AC13:AH25,"2"))*AR14+(COUNTIF(L13:Q25,"3")+COUNTIF(AC13:AH25,"3"))*AR15)/((COUNT(L13:Q25)+COUNT(AC13:AH25))*100) -> 0.8375
B8: Inspections are a snapshot in time and refer only to the practices and documentation observed at the time of the Inspection. It remains the responsibility of the Consultant and Contractor to ensure that all aspects of Health & Safety are suitably managed.
B9: 1 | D9: Good Practice | H9: 2 | I9: Need Improvement | T9: 3 | U9: Fail (Life Threatening Activity) / Comliance with Plan & Procedures | X9: N/A | Y9: Atcitty Not Applicable for this Site Inspection Report
B11: No. | C11: Topic | K11: Wt. | L11: HSE Compliance | S11: No. | T11: Topic | AB11: Wt. | AC11: HSE Compliance
B13: 1 | C13: Access and Egress - (General access to site, segregated from vehicles, / Overhead protection, while entering into the building /Adequate lighting provided when dark or overnight work) | K13: 0.05 | L13: 2 | S13: 14 | T13: Work at Height - (PPE/Fall Protection(Same level, above and blow) / Training / Fall restraint / competency /Safe access & egress to and from work at height / Ladders / Openings (floor/shafts/Provision of emergency rescue)_x000D_ | AB13: 0.05 | AC13: 2 | AP13: 1 | AR13: 100 | AU13: 1
B14: 2 | C14: Traffic Management - (Loading/unloading/sheeting/temp. routes/speed/parking/competence) | K14: 0.03 | L14: 2 | S14: 15 | T14: Scaffolding - (Temp. Scaffolding Work-platform (All types) - qualified scaffolder / Inspection / Tagged / Safe Access/egress / PTW/Falsework & Formwork) | AB14: 0.04 | AC14: N/A | AP14: 2 | AR14: 75 | AU14: 2
B15: 3 | C15: Site Signage - (Project Notice Board & General Signage) | K15: 0.02 | L15: 1 | S15: 16 | T15: Mobile Elevated Work platform (MEWP) - (PTW/competence requirements/conditions/inspections/tagged/training/Full-body harness) | AB15: 0.04 | AC15: N/A | AP15: 3 | AR15: 0 | AU15: 3
B16: 4 | C16: PPE Compliance - (Use, storage, stock, handling & checks - Head, Foot, Eye, Hearing) | K16: 0.05 | L16: 1 | S16: 17 | T16: Excavation & Trenches - (PTW/Edge protection/buffer zone/Slope/Benching/Shoring/Geo-tech report/Atmospheric hazards/Acess&egress/Emergency management / MS&RA/H.E) | AB16: 0.03 | AC16: 1 | AU16: N/A
B17: 5 | C17: Housekeeping - (Material correctly stored/Rubbish cleaned & removed daily/slips & trips hazards) | K17: 0.03 | L17: 2 | S17: 18 | T17: Confined Space - (PTW/Training/competence/Emergency Management/MS & RA/Safe access/egress) | AB17: 0.05 | AC17: N/A
B18: 6 | C18: Storage of Materials - (Transporting, storage, training and use - Combustible / Flammable / Hazardous substances (COSHH) | L18: N/A | S18: 19 | T18: Fire Protection - (Flammable/Oxy. LPG /Combustible separated/FE's/Flashback arrestor/Sparks & slags/Smoking area/PTW/Generators/MS & RA/Emergency Management) | AC18: N/A | AL18: Red | AM18: Serious injury or death (immediately)
B19: 7 | C19: Site Waste Management - (Hazardous waste /Combustible waste / Human waste / Construction waste - asphalt, cable, timber, paving roof sheeting tiles, plastic & bricks) | L19: 1 | S19: 20 | T19: Health & Welfare - (Adequate drinking water/shaded - eating & rest area/washing & sanitary facilities/Certified FA/FA Box & Stock/adequate toilets/Ambulance) | AC19: 2 | AL19: Yellow | AM19: Minor or near miss (3 days to comply)
B20: 8 | C20: Health Surveillance - (Expose to excessive noise/vibration/dust/silica/CO/cement/radiation/extreme weather condition) | K20: 0.03 | L20: 2 | S20: 21 | T20: Environmental Incident Measures - (Spill/ Leakage / Concrete wash / vehicle & eqpts. wash / waste disposal/Sewers and drains/emissions/Emergency Management/Training/site run-off water) | AB20: 0.05 | AC20: 2 | AL20: Green | AM20: No issues
B21: 9 | C21: Electrical Safety - (Electrical qualified /RCD/GFCI/Industrial Cocket/LOTO/Cable-overhung or buried/Cords in good condition/current inspection tag) | K21: 0.05 | L21: 1 | S21: 22 | T21: HSE Communications & Meetings - (Schedule HSE Meetings/Safety Committee meetings/Alerts / Lesson learned/Safety Bulletin contains latest HSE KPI) | AB21: 0.05 | AC21: 1
B22: 10 | C22: Tools & Equipment - (Includes, powered, hydraulic & pneumatic/Guards in place/Properly stored/RCD Protection/Earthed/Good condition & tagged) | K22: 0.03 | L22: 2 | S22: 23 | T22: HSE Plan & Associated Procedures - (Approved updated HSE Plan/ CEMP/HAZComm/Procedures/Standards/Project Safety Risk Register) | AB22: 0.03 | AC22: 2 | AL22: 26 points > 4 minors then is it’s a serious issue
