Workbook
Name \A: #REF!
Name \B: #REF!
Name \C: #REF!
Name \E: #REF!
Name \G: #REF!
Name \H: #REF!
Name \I: #REF!
Name \J: #REF!
Name \K: #REF!
Name \L: #REF!
Name \M: #REF!
Name \N: #REF!
Name \O: #REF!
Name \P: #REF!
Name \Q: #REF!
Name \S: #REF!
Name \T: #REF!
Name \U: #REF!
Name \V: #REF!
Name \W: #REF!
Name \X: #REF!
Name _________________________________HRS15: #REF!
Name _________________________________SUB15: #REF!
Name ________________________________HRS15: #REF!
Name ________________________________SUB15: #REF!
Name _______________________________HRS15: #REF!
Name _______________________________SUB15: #REF!
Name ______________________________HRS15: #REF!
Name ______________________________SUB15: #REF!
Name _____________________________HRS15: #REF!
Name _____________________________SUB15: #REF!
Name ____________________________HRS15: #REF!
Name ____________________________SUB15: #REF!
Name ___________________________HRS15: #REF!
Name ___________________________SUB15: #REF!
Name __________________________HRS15: #REF!
Name __________________________SUB15: #REF!
Name _________________________HRS15: #REF!
Name _________________________SUB15: #REF!
Name ________________________HRS15: #REF!
Name ________________________SUB15: #REF!
Name _______________________HRS15: #REF!
Name _______________________SUB15: #REF!
Name ______________________HRS15: #REF!
Name ______________________SUB15: #REF!
Name _____________________HRS15: #REF!
Name _____________________SUB15: #REF!
Name ____________________HRS15: #REF!
Name ____________________SUB15: #REF!
Name ___________________HRS15: #REF!
Name ___________________SUB15: #REF!
Name __________________HRS15: #REF!
Name __________________SUB15: #REF!
Name _________________HRS15: #REF!
Name _________________SUB15: #REF!
Name ________________HRS15: #REF!
Name ________________SUB15: #REF!
Name _______________HRS15: #REF!
Name _______________SUB15: #REF!
Name ______________HRS15: #REF!

Sheet General Information
C3: Weekly Progress Report - Construction Projects | E3: 46307
C4: Contract General Information
C5: Project Name | D5: Development Industrial City-Alkharj
C6: Project ID | D6: 3121
C7: Contractor | D7: Moffreh Group
C8: Consultant | D8: EGIS
C9: Stage | D9: 44th Week
C10: Modon PM | D10: Rakan Alotaibi
C11: Key Dates
C12: Contract Award Date | D12: 45970
C13: Contract Sign Date | D13: 45977
C14: Site Handover Date | D14: 45994
C15: Original Completion | D15: 46723
C16: Contract Award Date (Hijri) | D16: =D12 -> 45970
C17: Contract Sign Date (Hijri) | D17: =D13 -> 45977
C18: Site Handover Date (Hijri) | D18: =D14 -> 45994
C19: Original Completion (Hijri) | D19: =D15 -> 46723
C20: Revised Completion Date | D20: 46723
C21: Committed Completion Date | D21: 46723
C22: Forecast Completion | D22: 46723
C23: Variance | D23: =D20-D22 -> 0

Sheet Weekly Progress Report
C3: MODON - Weekly Progress Report - Construction Projects | AG3: Data Date | AH3: ='General Information'!E3 -> 46307
C4: Contract General Information | I4: Key Dates | O4: Cost Summary (SR) | W4: Performance Summary | AC4: Project Scope
C5: Project Name | D5: Development Industrial City-Alkharj | I5: Contract Award | J5: ='General Information'!D12 -> 45970 | K5: Contract Award (Hijri) | L5: ='General Information'!D16 -> 45970 | M5: Revised Completion | N5: ='General Information'!D20 -> 46723 | O5: Original Contract Value | Q5: ='Invoice Log'!G5 -> 307891320 | S5: O&M Value (if any) | U5: ='Invoice Log'!K5 -> 0 | V5: EAC | W5: Plan Value | X5: =M19 -> 0.3327 | Y5: Phys. Plan Value | Z5: =Y19 -> 0.5138 | AA5: Quality Score | AB5: =+Quality!AC10 -> 0.91 | AC5: =+Progress!D3 -> Development of infrastructure networks in Al-Kharj industrial city, which is located almost 100 kilometers southeast of Riyadh, The project is comprised of two zones (A , B and Labor Community Area ), which have a total area of approximately 3.50 square kilometers
C6: Project ID | D6: ='General Information'!D6 -> 3121 | F6: Stage | G6: 1 | I6: Contract Sign | J6: ='General Information'!D13 -> 45977 | K6: Contract Sign (Hijri) | L6: ='General Information'!D17 -> 45977 | M6: Committed Completion | N6: 46723 | O6: Revised Contract Value | Q6: ='Invoice Log'!G6 -> 307891320 | S6: Submitted Invoices (Gross Value) | U6: ='Invoice Log'!K7 -> 49710656 | W6: Earned Value | X6: =N19 -> 0.344 | Y6: Phys. Earn Value | Z6: =Z19 -> 0.4573
C7: Contractor | D7: ='General Information'!D7 -> Moffreh Group | F7: Status | G7: 32 | I7: Site Handover | J7: 45994 | K7: Site Handover (Hijri) | L7: ='General Information'!D18 -> 45994 | M7: Forecast Completion | N7: 46723 | O7: Estimate At Completion Value | Q7: ='Invoice Log'!G7 -> 307891320 | S7: Penalities & Retention | U7: ='Invoice Log'!K8 -> 5082066 | W7: Variance | X7: =X6-X5 -> 0.011 | Y7: Variance | Z7: =AA19 -> -0.057 | AA7: Safety Score | AB7: =HSE!AF6 -> 0.93
C8: Consultant | D8: ='General Information'!D8 -> EGIS | F8: Modon PM | G8: ='General Information'!D10 -> Rakan Alotaibi | I8: Original Completion | J8: 46723 | K8: Original Completion (Hijri) | L8: ='General Information'!D19 -> 46723 | M8: Variance | N8: =N6-N7 -> 0 | O8: Potential Changes | Q8: ='Invoice Log'!G8 -> 0 | S8: FIR Value (up To date) | U8: =U6+12000000 -> 61710656 | W8: FIR % | X8: =U8/Q5 -> 0.2 | Y8: Invoiced % | Z8: =U6/Q5 -> 0.16146
C10: Progress Overview
C11: Earned Value Progress (SAR) | Q11: Physical Progress (Effort) | AC11: Earned Value Progress (%)
C12: WBS | E12: BOQ Value (SAR) | F12: % Wt. | G12: Weekly (SAR) | I12: To Date (SAR) | Q12: Budgeted | R12: % Wt. | S12: Weekly Physical Progress | W12: To Date Physical Progress
G13: Planned | H13: Earned | I13: Original Plan | J13: Revised Planned | K13: Earned | L13: Original Plan % | M13: Revised Planned % | N13: Earned % | O13: Variance | P13: SPI | Q13: (Manhours) | S13: Planned | T13: Earned | U13: Plan % | V13: Earned % | W13: Planned | X13: Earned | Y13: Plan % | Z13: Earned % | AA13: Variance | AB13: SPI
C14: =+Progress!C9 -> Engineering | E14: =+Progress!D9 -> 0 | F14: =IF(ISBLANK(E14),"",E14/$E$19) -> 0 | G14: =+Progress!F9 -> 0 | H14: =+Progress!G9 -> 0 | I14: =Progress!H9 -> 0 | J14: =Progress!I9 -> 0 | K14: =+Progress!J9 -> 0 | L14: =IFERROR(IF(ISBLANK(I14),"",I14/E14),0) -> 0 | M14: =IFERROR(IF(ISBLANK(J14),"",J14/E14),0) -> 0 | N14: =IFERROR(IF(ISBLANK(K14),"",K14/E14),0) -> 0 | O14: =IFERROR(N14-M14,"") -> 0 | P14: =IFERROR(N14/M14,"") | Q14: =+Progress!K9 -> 8031948 | R14: =+Progress!L9 -> 0.03 | S14: =+Progress!M9 -> 0 | T14: =+Progress!N9 -> 0 | U14: =IFERROR(Progress!F9/Progress!D9,0) -> 0 | V14: =IFERROR(Progress!G9/Progress!D9,0) -> 0 | W14: =+Progress!O9 -> 8031948 | X14: =+Progress!P9 -> 8031948 | Y14: =IFERROR(IF(ISBLANK(W14),"",W14/Q14),0) -> 1 | Z14: =IFERROR(IF(ISBLANK(X14),"",X14/Q14),0) -> 1 | AA14: =Z14-Y14 -> 0 | AB14: =Z14/Y14 -> 1
C15: =+Progress!C10 -> Procurement | E15: =+Progress!D10 -> 0 | F15: =IF(ISBLANK(E15),"",E15/$E$19) -> 0 | G15: =+Progress!F10 -> 0 | H15: =+Progress!G10 -> 0 | I15: =Progress!H10 -> 0 | J15: =Progress!I10 -> 0 | K15: =+Progress!J10 -> 0 | L15: =IFERROR(IF(ISBLANK(I15),"",I15/E15),0) -> 0 | M15: =IFERROR(IF(ISBLANK(J15),"",J15/E15),0) -> 0 | N15: =IFERROR(IF(ISBLANK(K15),"",K15/E15),0) -> 0 | O15: =IFERROR(N15-M15,"") -> 0 | P15: =IFERROR(N15/M15,"") | Q15: =+Progress!K10 -> 53546316 | R15: =+Progress!L10 -> 0.2 | S15: =+Progress!M10 -> 1540097 | T15: =+Progress!N10 -> 4058810 | U15: =IFERROR(Progress!F10/Progress!D10,0) -> 0 | V15: =IFERROR(Progress!G10/Progress!D10,0) -> 0 | W15: =+Progress!O10 -> 46066045 | X15: =+Progress!P10 -> 35040709 | Y15: =IFERROR(IF(ISBLANK(W15),"",W15/Q15),0) -> 0.86 | Z15: =IFERROR(IF(ISBLANK(X15),"",X15/Q15),0) -> 0.654 | AA15: =Z15-Y15 -> -0.206 | AB15: =Z15/Y15 -> 0.76046512
C16: =+Progress!C11 -> Construction | E16: =+Progress!D11 -> 239411880 | F16: =IF(ISBLANK(E16),"",E16/$E$19) -> 0.778 | G16: =+Progress!F11 -> 2537765.9 | H16: =+Progress!G11 -> 2801119 | I16: =Progress!H11 -> 173573613 | J16: =Progress!I11 -> 1.0244434e+08 | K16: =+Progress!J11 -> 1.0591582e+08 | L16: =IFERROR(IF(ISBLANK(I16),"",I16/E16),0) -> 0.725 | M16: =IFERROR(IF(ISBLANK(J16),"",J16/E16),0) -> 0.428 | N16: =IFERROR(IF(ISBLANK(K16),"",K16/E16),0) -> 0.442 | O16: =IFERROR(N16-M16,"") -> 0.014 | P16: =IFERROR(N16/M16,"") -> 1.03 | Q16: =+Progress!K11 -> 179380160 | R16: =+Progress!L11 -> 0.67 | S16: =+Progress!M11 -> 1914427 | T16: =+Progress!N11 -> 2098748 | U16: =Progress!F11/Progress!D11 -> 0.011 | V16: =Progress!G11/Progress!D11 -> 0.012 | W16: =+Progress!O11 -> 76761914 | X16: =+Progress!P11 -> 79357783 | Y16: =IFERROR(IF(ISBLANK(W16),"",W16/Q16),0) -> 0.428 | Z16: =IFERROR(IF(ISBLANK(X16),"",X16/Q16),0) -> 0.442 | AA16: =Z16-Y16 -> 0.014 | AB16: =Z16/Y16 -> 1.0327103
C17: =+Progress!C12 -> Testing & Commissioning | E17: =+Progress!D12 -> 0 | F17: =IF(ISBLANK(E17),"",E17/$E$19) -> 0 | G17: =+Progress!F12 -> 0 | H17: =+Progress!G12 -> 0 | I17: =Progress!H12 -> 0 | J17: =Progress!I12 -> 0 | K17: =+Progress!J12 -> 0 | L17: =IFERROR(IF(ISBLANK(I17),"",I17/E17),0) -> 0 | M17: =IFERROR(IF(ISBLANK(J17),"",J17/E17),0) -> 0 | N17: =IFERROR(IF(ISBLANK(K17),"",K17/E17),0) -> 0 | O17: =IFERROR(N17-M17,"") -> 0 | P17: =IFERROR(N17/M17,"") | Q17: =+Progress!K12 -> 26773158 | R17: =+Progress!L12 -> 0.1 | S17: =+Progress!M12 -> 0 | T17: =+Progress!N12 -> 0 | U17: =IFERROR(Progress!F12/Progress!D12,0) -> 0 | V17: =IFERROR(Progress!G12/Progress!D12,0) -> 0 | W17: =+Progress!O12 -> 6693290 | X17: =+Progress!P12 -> 0 | Y17: =IFERROR(IF(ISBLANK(W17),"",W17/Q17),0) -> 0.25 | Z17: =IFERROR(IF(ISBLANK(X17),"",X17/Q17),0) -> 0 | AA17: =Z17-Y17 -> -0.25 | AB17: 0
C18: =+Progress!C13 -> Close Out | E18: =+Progress!D13 -> 68479440 | F18: =IF(ISBLANK(E18),"",E18/$E$19) -> 0.222 | G18: =+Progress!F13 -> 0 | H18: =+Progress!G13 -> 0 | I18: =Progress!H13 -> 0 | J18: =Progress!I13 -> 0 | K18: =+Progress!J13 -> 0 | L18: =IFERROR(IF(ISBLANK(I18),"",I18/E18),0) -> 0 | M18: =IFERROR(IF(ISBLANK(J18),"",J18/E18),0) -> 0 | N18: =IFERROR(IF(ISBLANK(K18),"",K18/E18),0) -> 0 | O18: =IFERROR(N18-M18,"") -> 0 | P18: =IFERROR(N18/M18,"") | Q18: =+Progress!K13 -> 0 | R18: =+Progress!L13 -> 0 | S18: =+Progress!M13 -> 0 | T18: =+Progress!N13 -> 0 | U18: 0 | V18: 0 | W18: =+Progress!O13 -> 0 | X18: =+Progress!P13 -> 0 | Y18: =IFERROR(IF(ISBLANK(W18),"",W18/Q18),0) -> 0 | Z18: =IFERROR(IF(ISBLANK(X18),"",X18/Q18),0) -> 0 | AA18: =Z18-Y18 -> 0 | AB18: 0
D19: Total | E19: =SUM(E14:E18) -> 307891320 | F19: =SUM(F14:F18) -> 1 | G19: =SUM(G14:G18) -> 2537765.9 | H19: =SUM(H14:H18) -> 2801119 | I19: =SUM(I14:I18) -> 173573613 | J19: =SUM(J14:J18) -> 1.0244434e+08 | K19: =SUM(K14:K18) -> 1.0591582e+08 | L19: =IFERROR(IF(ISBLANK(I19),"",I19/E19),0) -> 0.5637 | M19: =IFERROR(IF(ISBLANK(J19),"",J19/E19),0) -> 0.3327 | N19: =IFERROR(IF(ISBLANK(K19),"",K19/E19),0) -> 0.344 | O19: =+N19-M19 -> 0.0113 | P19: =N19/M19 -> 1.03 | Q19: =SUM(Q14:Q18) -> 267731582 | R19: =SUM(R14:R18) -> 1 | S19: =SUM(S14:S18) -> 3454524 | T19: =SUM(T14:T18) -> 6157558 | U19: =IFERROR(IF(ISBLANK(S19),"",S19/Q19),0) -> 0.0129 | V19: =IFERROR(IF(ISBLANK(T19),"",T19/Q19),0) -> 0.023 | W19: =SUM(W14:W18) -> 137553197 | X19: =SUM(X14:X18) -> 122430440 | Y19: =IFERROR(IF(ISBLANK(W19),"",W19/Q19),0) -> 0.5138 | Z19: =IFERROR(IF(ISBLANK(X19),"",X19/Q19),0) -> 0.4573 | AA19: =+Z19-Y19 -> -0.0565 | AB19: =Z19/Y19 -> 0.89
AC20: Construction Milestones
AC21: Item No. | AD21: Milestones | AF21: Original (Baseline) | AG21: Latest Plan | AH21: Forecast | AI21: Days Change
AC22: =+Milestones!C5 -> 1 | AD22: =+Milestones!D5 -> Site Handover Date | AF22: =+Milestones!E5 -> 45994 | AG22: =AF22 -> 45994 | AH22: =AF22 -> 45994 | AI22: =+Milestones!H5 -> 0
AC23: =+Milestones!C6 -> 2 | AD23: =+Milestones!D6 -> Complete Mobilization | AF23: =+Milestones!E6 -> 46024 | AG23: =AF23 -> 46024 | AH23: =AF23 -> 46024 | AI23: =+Milestones!H6 -> 0
AC24: =+Milestones!C7 -> 3 | AD24: =+Milestones!D7 -> Road works | AF24: =+Milestones!E7 -> 46297 | AG24: =AF24 -> 46297 | AH24: =AF24 -> 46297 | AI24: =+Milestones!H7 -> -36
AC25: =+Milestones!C8 -> 4 | AD25: =+Milestones!D8 -> Medium voltage network | AF25: =+Milestones!E8 -> 46297 | AG25: =AF25 -> 46297 | AH25: =AF25 -> 46297 | AI25: =+Milestones!H8 -> -29
AC26: =+Milestones!C9 -> 5 | AD26: =+Milestones!D9 -> All Networks | AF26: =+Milestones!E9 -> 46420 | AG26: =AF26 -> 46420 | AH26: =AF26 -> 46420 | AI26: =+Milestones!H9 -> 0
AC27: =+Milestones!C10 -> 6 | AD27: =+Milestones!D10 -> Project Handover | AF27: =+Milestones!E10 -> 46723 | AG27: =AF27 -> 46723 | AH27: =AF27 -> 46723 | AI27: =+Milestones!H10 -> 0
C43: Performance overview
C44: Submittals Status | N44: Quality | Y44: Safety
C45: Design | N45: Quality Reports | Y45: Safety Statistics | AG45: Proactive Vs Reactive Actions Taken
C46: Item Per WBS | E46: Total | F46: Total Submitted Drawings | K46: Remaining | L46: Pending | M46: Total Submittals | N46: Quality Reports | P46: Issued | Q46: Closed | R46: Pending | S46: Avg. Closing (Days) | T46: Pending | Y46: Category | Z46: Item | AB46: This Week | AD46: This Month | AE46: Year to Date | AF46: Cumulative
F47: A | G47: B | H47: C | I47: D | J47: Processed | T47: 0-10 Days | U47: 11-20 Days | V47: 21-30 Days | W47: 31-60 Days | X47: > 60 Days
C48: =#REF! -> #REF! | E48: =IF(#REF!="","",#REF!) -> #REF! | F48: =IF(#REF!="","",#REF!) -> #REF! | G48: =IF(#REF!="","",#REF!) -> #REF! | H48: =IF(#REF!="","",#REF!) -> #REF! | I48: =IF(#REF!="","",#REF!) -> #REF! | J48: =IF(#REF!="","",#REF!) -> #REF! | K48: =IF(#REF!="","",#REF!) -> #REF! | L48: =IF(#REF!="","",#REF!) -> #REF! | M48: =IF(#REF!="","",#REF!) -> #REF! | Y48: General | Z48: =#REF! -> #REF! | AB48: =#REF! -> #REF! | AD48: =#REF! -> #REF! | AE48: =#REF! -> #REF! | AF48: =#REF! -> #REF! | AI48: =+SUM(AF59:AF63) -> #REF!
C49: =#REF! -> #REF! | E49: =IF(#REF!="","",#REF!) -> #REF! | F49: =IF(#REF!="","",#REF!) -> #REF! | G49: =IF(#REF!="","",#REF!) -> #REF! | H49: =IF(#REF!="","",#REF!) -> #REF! | I49: =IF(#REF!="","",#REF!) -> #REF! | J49: =IF(#REF!="","",#REF!) -> #REF! | K49: =IF(#REF!="","",#REF!) -> #REF! | L49: =IF(#REF!="","",#REF!) -> #REF! | M49: =IF(#REF!="","",#REF!) -> #REF! | N49: Non Conformance (NCR) | P49: 3 | Q49: 3 | R49: 0 | S49: =#REF! -> #REF! | T49: 0 | U49: =#REF! -> #REF! | V49: =#REF! -> #REF! | W49: =#REF! -> #REF! | X49: =#REF! -> #REF! | Z49: =#REF! -> #REF! | AB49: =#REF! -> #REF! | AD49: =#REF! -> #REF! | AE49: =#REF! -> #REF! | AF49: =#REF! -> #REF! | AI49: =SUM(AF50:AF58) -> #REF!
C50: =#REF! -> #REF! | E50: =IF(#REF!="","",#REF!) -> #REF! | F50: =IF(#REF!="","",#REF!) -> #REF! | G50: =IF(#REF!="","",#REF!) -> #REF! | H50: =IF(#REF!="","",#REF!) -> #REF! | I50: =IF(#REF!="","",#REF!) -> #REF! | J50: =IF(#REF!="","",#REF!) -> #REF! | K50: =IF(#REF!="","",#REF!) -> #REF! | L50: =IF(#REF!="","",#REF!) -> #REF! | M50: =IF(#REF!="","",#REF!) -> #REF! | N50: Site Instruction (SIR) | P50: =#REF! -> #REF! | Q50: =#REF! -> #REF! | R50: =#REF! -> #REF! | S50: =#REF! -> #REF! | T50: =#REF! -> #REF! | U50: =#REF! -> #REF! | V50: =#REF! -> #REF! | W50: =#REF! -> #REF! | X50: =#REF! -> #REF! | Y50: Reactive | Z50: =#REF! -> #REF! | AB50: =#REF! -> #REF! | AD50: =#REF! -> #REF! | AE50: =#REF! -> #REF! | AF50: =#REF! -> #REF!
C51: =#REF! -> #REF! | E51: =IF(#REF!="","",#REF!) -> #REF! | F51: =IF(#REF!="","",#REF!) -> #REF! | G51: =IF(#REF!="","",#REF!) -> #REF! | H51: =IF(#REF!="","",#REF!) -> #REF! | I51: =IF(#REF!="","",#REF!) -> #REF! | J51: =IF(#REF!="","",#REF!) -> #REF! | K51: =IF(#REF!="","",#REF!) -> #REF! | L51: =IF(#REF!="","",#REF!) -> #REF! | M51: =IF(#REF!="","",#REF!) -> #REF! | N51: Material Inspection (MIR) | P51: =#REF! -> #REF! | Q51: =#REF! -> #REF! | R51: =#REF! -> #REF! | S51: =#REF! -> #REF! | T51: =#REF! -> #REF! | U51: =#REF! -> #REF! | V51: =#REF! -> #REF! | W51: =#REF! -> #REF! | X51: =#REF! -> #REF! | Z51: =#REF! -> #REF! | AB51: =#REF! -> #REF! | AD51: =#REF! -> #REF! | AE51: =#REF! -> #REF! | AF51: =#REF! -> #REF!
C52: =#REF! -> #REF! | E52: =IF(#REF!="","",#REF!) -> #REF! | F52: =IF(#REF!="","",#REF!) -> #REF! | G52: =IF(#REF!="","",#REF!) -> #REF! | H52: =IF(#REF!="","",#REF!) -> #REF! | I52: =IF(#REF!="","",#REF!) -> #REF! | J52: =IF(#REF!="","",#REF!) -> #REF! | K52: =IF(#REF!="","",#REF!) -> #REF! | L52: =IF(#REF!="","",#REF!) -> #REF! | M52: =IF(#REF!="","",#REF!) -> #REF! | N52: Field Inspection (FIR) | P52: =#REF! -> #REF! | Q52: =#REF! -> #REF! | R52: =#REF! -> #REF! | S52: =#REF! -> #REF! | T52: =#REF! -> #REF! | U52: =#REF! -> #REF! | V52: =#REF! -> #REF! | W52: =#REF! -> #REF! | X52: =#REF! -> #REF! | Z52: =#REF! -> #REF! | AB52: =#REF! -> #REF! | AD52: =#REF! -> #REF! | AE52: =#REF! -> #REF! | AF52: =#REF! -> #REF!
C53: TOTAL | E53: =SUM(E48:E52) -> #REF! | F53: =SUM(F48:F52) -> #REF! | G53: =SUM(G48:G52) -> #REF! | H53: =SUM(H48:H52) -> #REF! | I53: =SUM(I48:I52) -> #REF! | J53: =SUM(J48:J52) -> #REF! | K53: =SUM(K48:K52) -> #REF! | L53: =SUM(L48:L52) -> #REF! | M53: =SUM(M48:M52) -> #REF! | N53: Key Submittals Approval Status | Z53: =#REF! -> #REF! | AB53: =#REF! -> #REF! | AD53: =#REF! -> #REF! | AE53: =#REF! -> #REF! | AF53: =#REF! -> #REF!
C54: Material Approval | N54: 1 Quality Plan Approval | Q54: ='General Information'!#REF! -> #REF! | S54: 6 Baseline Approval | W54: ='General Information'!#REF! -> #REF! | Z54: =#REF! -> #REF! | AB54: =#REF! -> #REF! | AD54: =#REF! -> #REF! | AE54: =#REF! -> #REF! | AF54: =#REF! -> #REF! | AG54: Total Hours Worked Vs Safe Hours Worked
C55: Item Per WBS | E55: Total | F55: Total Submitted Material | K55: Remaining to approve | L55: Pending | M55: Total Submittals | N55: 2 Quality Plan Last Up | Q55: ='General Information'!#REF! -> #REF! | S55: 7 No of Approved Version of Schedule | W55: ='General Information'!#REF! -> #REF! | Z55: =#REF! -> #REF! | AB55: =#REF! -> #REF! | AD55: =#REF! -> #REF! | AE55: =#REF! -> #REF! | AF55: =#REF! -> #REF!
F56: A | G56: B | H56: C | I56: D | J56: Processed | K56: with Designer | N56: 3 Safety Plan Approval | Q56: ='General Information'!#REF! -> #REF! | S56: 8 Last Approved Schedule | W56: ='General Information'!#REF! -> #REF! | Z56: =#REF! -> #REF! | AB56: =#REF! -> #REF! | AD56: =#REF! -> #REF! | AE56: =#REF! -> #REF! | AF56: =#REF! -> #REF!
C57: =#REF! -> #REF! | E57: =IF(#REF!="","",#REF!) -> #REF! | F57: =IF(#REF!="","",#REF!) -> #REF! | G57: =IF(#REF!="","",#REF!) -> #REF! | H57: =IF(#REF!="","",#REF!) -> #REF! | I57: =IF(#REF!="","",#REF!) -> #REF! | J57: =IF(#REF!="","",#REF!) -> #REF! | K57: =IF(#REF!="","",#REF!) -> #REF! | L57: =IF(#REF!="","",#REF!) -> #REF! | M57: =IF(#REF!="","",#REF!) -> #REF! | N57: 4 Safety Plan Last Up | Q57: ='General Information'!#REF! -> #REF! | S57: 9 BOQ Approval Date | W57: ='General Information'!#REF! -> #REF! | Z57: =#REF! -> #REF! | AB57: =#REF! -> #REF! | AD57: =#REF! -> #REF! | AE57: =#REF! -> #REF! | AF57: =#REF! -> #REF!
C58: =#REF! -> #REF! | E58: =IF(#REF!="","",#REF!) -> #REF! | F58: =IF(#REF!="","",#REF!) -> #REF! | G58: =IF(#REF!="","",#REF!) -> #REF! | H58: =IF(#REF!="","",#REF!) -> #REF! | I58: =IF(#REF!="","",#REF!) -> #REF! | J58: =IF(#REF!="","",#REF!) -> #REF! | K58: =IF(#REF!="","",#REF!) -> #REF! | L58: =IF(#REF!="","",#REF!) -> #REF! | M58: =IF(#REF!="","",#REF!) -> #REF! | N58: 5 Construction Plan Approval | Q58: ='General Information'!#REF! -> #REF! | S58: 10 No of Approved Version of BOQ | W58: ='General Information'!#REF! -> #REF! | Z58: =#REF! -> #REF! | AB58: =#REF! -> #REF! | AD58: =#REF! -> #REF! | AE58: =#REF! -> #REF! | AF58: =#REF! -> #REF!
C59: =#REF! -> #REF! | E59: =IF(#REF!="","",#REF!) -> #REF! | F59: =IF(#REF!="","",#REF!) -> #REF! | G59: =IF(#REF!="","",#REF!) -> #REF! | H59: =IF(#REF!="","",#REF!) -> #REF! | I59: =IF(#REF!="","",#REF!) -> #REF! | J59: =IF(#REF!="","",#REF!) -> #REF! | K59: =IF(#REF!="","",#REF!) -> #REF! | L59: =IF(#REF!="","",#REF!) -> #REF! | M59: =IF(#REF!="","",#REF!) -> #REF! | N59: Invoices Summary | Y59: Proactive | Z59: =#REF! -> #REF! | AB59: 0 | AD59: 22(28) | AE59: =#REF! -> #REF! | AF59: =#REF! -> #REF!
C60: =#REF! -> #REF! | E60: =IF(#REF!="","",#REF!) -> #REF! | F60: =IF(#REF!="","",#REF!) -> #REF! | G60: =IF(#REF!="","",#REF!) -> #REF! | H60: =IF(#REF!="","",#REF!) -> #REF! | I60: =IF(#REF!="","",#REF!) -> #REF! | J60: =IF(#REF!="","",#REF!) -> #REF! | K60: =IF(#REF!="","",#REF!) -> #REF! | L60: =IF(#REF!="","",#REF!) -> #REF! | M60: =IF(#REF!="","",#REF!) -> #REF! | N60: Total Submitted Invoices | P60: ='Invoice Log'!W5 -> 0 | Q60: Submitted Invoices (SAR) | T60: ='Invoice Log'!AA5 -> 49710656 | V60: Contract Value (SR) | W60: =Q6 -> 307891320 | Z60: =#REF! -> #REF! | AB60: =#REF! -> #REF! | AD60: =#REF! -> #REF! | AE60: =#REF! -> #REF! | AF60: =#REF! -> #REF!
C61: =#REF! -> #REF! | E61: =IF(#REF!="","",#REF!) -> #REF! | F61: =IF(#REF!="","",#REF!) -> #REF! | G61: =IF(#REF!="","",#REF!) -> #REF! | H61: =IF(#REF!="","",#REF!) -> #REF! | I61: =IF(#REF!="","",#REF!) -> #REF! | J61: =IF(#REF!="","",#REF!) -> #REF! | K61: =IF(#REF!="","",#REF!) -> #REF! | L61: =IF(#REF!="","",#REF!) -> #REF! | M61: =IF(#REF!="","",#REF!) -> #REF! | N61: PM Approved Invoices | P61: ='Invoice Log'!W7 -> 0 | Q61: PM Approved Invoices (SAR) | T61: ='Invoice Log'!AA7 -> 0 | V61: Planned Value (SR) | W61: =J19 -> 102444343 | Z61: =#REF! -> #REF! | AB61: =#REF! -> #REF! | AD61: =#REF! -> #REF! | AE61: =#REF! -> #REF! | AF61: =#REF! -> #REF!
C62: TOTAL | E62: =SUM(E57:E61) -> #REF! | F62: =SUM(F57:F61) -> #REF! | G62: =SUM(G57:G61) -> #REF! | H62: =SUM(H57:H61) -> #REF! | I62: =SUM(I57:I61) -> #REF! | J62: =SUM(J57:J61) -> #REF! | K62: =SUM(K57:K61) -> #REF! | L62: =SUM(L57:L61) -> #REF! | M62: =SUM(M57:M61) -> #REF! | N62: No of Paid Invoices | P62: ='Invoice Log'!W8 -> 0 | Q62: Paid Invoices (SAR) | T62: ='Invoice Log'!AA8 -> 0 | V62: Earned Value (SR) | W62: =K19 -> 105915816 | Z62: =#REF! -> #REF! | AB62: =#REF! -> #REF! | AD62: =#REF! -> #REF! | AE62: =#REF! -> #REF! | AF62: =#REF! -> #REF!
C63: Procurement Summary | N63: No of Pending Invoices | P63: =P61-P62 -> 0 | Q63: Last Submitted Period | T63: ='Invoice Log'!AD5 -> 46295 | V63: Submitted (SAR) | W63: =T60 -> 49710656 | Z63: =#REF! -> #REF! | AB63: =#REF! -> #REF! | AD63: =#REF! -> #REF! | AE63: =#REF! -> #REF! | AF63: =#REF! -> #REF!
C64: Item Per WBS | E64: Total Materials | F64: Total Number of P.O. | G64: Actual P.O. To Date | H64: Remaining P.O | I64: Material on Site | J64: Remaining Materials | K64: Material Delivery Completion (Date) | N64: Advance Payment % | P64: ='Invoice Log'!O5 -> 0 | Q64: Advance Payment (SAR) | T64: ='Invoice Log'!S5 -> 0 | V64: PM Approved (SAR) | W64: =T61 -> 0 | Y64: Latest Contract Change Order Log
F65: A | G65: B | H65: C | I65: D | J65: Processed | N65: Retention % | P65: ='Invoice Log'!O6 -> 0 | Q65: Retention (SAR) | T65: ='Invoice Log'!S6 -> 0 | V65: Total Paid (SAR) | W65: =T62 -> 0
C66: =#REF! -> #REF! | E66: =IF(#REF!="","",#REF!) -> #REF! | F66: =IF(#REF!="","",#REF!) -> #REF! | G66: =IF(#REF!="","",#REF!) -> #REF! | H66: =IF(#REF!="","",#REF!) -> #REF! | I66: =IF(#REF!="","",#REF!) -> #REF! | J66: =IF(#REF!="","",#REF!) -> #REF! | K66: =#REF! -> #REF! | N66: Deduction / Penalties % | P66: ='Invoice Log'!O7 -> 0 | Q66: Deduction / Penalties (SAR) | T66: ='Invoice Log'!O8 -> 111000 | Y66: CCO No. | Z66: Date Added | AA66: Description of Change | AF66: Status | AG66: Cost | AH66: Sch Impact (Months) | AI66: Duration
C67: =#REF! -> #REF! | E67: =IF(#REF!="","",#REF!) -> #REF! | F67: =IF(#REF!="","",#REF!) -> #REF! | G67: =IF(#REF!="","",#REF!) -> #REF! | H67: =IF(#REF!="","",#REF!) -> #REF! | I67: =IF(#REF!="","",#REF!) -> #REF! | J67: =IF(#REF!="","",#REF!) -> #REF! | K67: =#REF! -> #REF! | N67: Resources at Site
C68: =#REF! -> #REF! | E68: =IF(#REF!="","",#REF!) -> #REF! | F68: =IF(#REF!="","",#REF!) -> #REF! | G68: =IF(#REF!="","",#REF!) -> #REF! | H68: =IF(#REF!="","",#REF!) -> #REF! | I68: =IF(#REF!="","",#REF!) -> #REF! | J68: =IF(#REF!="","",#REF!) -> #REF! | K68: =#REF! -> #REF! | N68: Head Count - Non Manual | R68: Head Count - Manual | V68: Total Head Count | Y68: =CCO!C6 -> 0 | Z68: =CCO!D6 -> NA | AA68: =CCO!E6 -> 0 | AF68: =CCO!F6 -> 0 | AG68: =CCO!G6 -> 0 | AH68: =CCO!H6 -> 0 | AI68: =CCO!J6 -> 0
C69: =#REF! -> #REF! | E69: =IF(#REF!="","",#REF!) -> #REF! | F69: =IF(#REF!="","",#REF!) -> #REF! | G69: =IF(#REF!="","",#REF!) -> #REF! | H69: =IF(#REF!="","",#REF!) -> #REF! | I69: =IF(#REF!="","",#REF!) -> #REF! | J69: =IF(#REF!="","",#REF!) -> #REF! | K69: =#REF! -> #REF! | N69: Planned | O69: Actual | P69: Next Month Forecast | Q69: Saudi Staff | R69: Planned | S69: Actual | T69: Next Month Forecast | U69: Saudi Staff | V69: Total Plan | W69: Total Actual | X69: Variance
C70: =#REF! -> #REF! | E70: =IF(#REF!="","",#REF!) -> #REF! | F70: =IF(#REF!="","",#REF!) -> #REF! | G70: =IF(#REF!="","",#REF!) -> #REF! | H70: =IF(#REF!="","",#REF!) -> #REF! | I70: =IF(#REF!="","",#REF!) -> #REF! | J70: =IF(#REF!="","",#REF!) -> #REF! | K70: =#REF! -> #REF! | N70: =Manpower!#REF! -> #REF! | O70: =Manpower!#REF! -> #REF! | P70: =Manpower!#REF! -> #REF! | Q70: 4 | R70: =O80 -> #REF! | S70: =P80 -> #REF! | T70: =Manpower!#REF! -> #REF! | U70: =Manpower!#REF! -> #REF! | V70: =N70+R70 -> #REF! | W70: =O70+S70 -> #REF! | X70: =+W70-V70 -> #REF! | Y70: =CCO!C7 | Z70: =CCO!D7 -> NA | AA70: =CCO!E7 | AF70: =IF(CCO!F7="","",CCO!F7) | AG70: =CCO!G7 | AH70: =CCO!H7 | AI70: =CCO!J7
C71: TOTAL | E71: =IF(#REF!="","",#REF!) -> #REF! | F71: =IF(#REF!="","",#REF!) -> #REF! | G71: =IF(#REF!="","",#REF!) -> #REF! | H71: =IF(#REF!="","",#REF!) -> #REF! | I71: =IF(#REF!="","",#REF!) -> #REF! | J71: =IF(#REF!="","",#REF!) -> #REF! | K71: =MAX(K66:K70) -> #REF! | N71: Manpower Breakdown by Trade | U71: Major Equipment
C72: =#REF! -> #REF! | N72: Key Trade | O72: Planned | P72: Actual | U72: Type | V72: Planned | W72: Actual | X72: Idle | Y72: =CCO!C12 | Z72: =CCO!D12 -> NA | AA72: =CCO!E12 | AF72: =IF(CCO!F12="","",CCO!F12) | AG72: =CCO!G12 | AH72: =CCO!H12 | AI72: =CCO!J12
C73: =#REF! -> #REF! | N73: =+Manpower!#REF! -> #REF! | O73: =Manpower!#REF! -> #REF! | P73: =Manpower!#REF! -> #REF! | U73: =+Manpower!#REF! -> #REF! | V73: =+Manpower!#REF! -> #REF! | W73: =+Manpower!#REF! -> #REF! | X73: =+Manpower!#REF! -> #REF!
C74: =#REF! -> #REF! | H74: =#REF! -> #REF! | N74: =+Manpower!#REF! -> #REF! | O74: =Manpower!#REF! -> #REF! | P74: =Manpower!#REF! -> #REF! | U74: =+Manpower!#REF! -> #REF! | V74: =+Manpower!#REF! -> #REF! | W74: =+Manpower!#REF! -> #REF! | X74: =+Manpower!#REF! -> #REF! | Y74: Major Quantity Trackers
C75: =#REF! -> #REF! | D75: =#REF! -> #REF! | E75: =#REF! -> #REF! | F75: =#REF! -> #REF! | G75: =#REF! -> #REF! | H75: =#REF! -> #REF! | I75: =#REF! -> #REF! | J75: =#REF! -> #REF! | ... M75: =#REF! -> #REF! | N75: =+Manpower!#REF! -> #REF! | O75: =+Manpower!#REF! -> #REF! | P75: =Manpower!#REF! -> #REF! | U75: =+Manpower!#REF! -> #REF! | V75: =+Manpower!#REF! -> #REF! | W75: =+Manpower!#REF! -> #REF! | X75: =+Manpower!#REF! -> #REF! | Y75: BOQ N0. | Z75: Item Description | AE75: Total Qty | AF75: Measu Unit | AG75: Plan to Date | AH75: Act to Date | AI75: Variance
C76: =#REF! -> #REF! | D76: 372 | E76: =#REF! -> #REF! | F76: =#REF! -> #REF! | G76: =#REF! -> #REF! | H76: =#REF! -> #REF! | I76: =#REF! -> #REF! | J76: =#REF! -> #REF! | K76: =#REF! -> #REF! | L76: =#REF! -> #REF! | N76: =+Manpower!#REF! -> #REF! | O76: =Manpower!#REF! -> #REF! | P76: =Manpower!#REF! -> #REF! | U76: =+Manpower!#REF! -> #REF! | V76: =+Manpower!#REF! -> #REF! | W76: =+Manpower!#REF! -> #REF! | X76: =+Manpower!#REF! -> #REF! | Y76: =#REF! -> #REF! | Z76: =#REF! -> #REF! | AE76: =VLOOKUP(Z76,#REF!,2,FALSE) -> #REF! | AF76: =VLOOKUP(Z76,#REF!,3,FALSE) -> #REF! | AG76: =VLOOKUP(Z76,#REF!,4,FALSE) -> #REF! | AH76: =VLOOKUP(Z76,#REF!,5,FALSE) -> #REF! | AI76: =VLOOKUP(Z76,#REF!,7,FALSE) -> #REF!
C77: =#REF! -> #REF! | F77: =#REF! -> #REF! | J77: =#REF! -> #REF! | N77: =+Manpower!#REF! -> #REF! | O77: =+Manpower!#REF! -> #REF! | P77: =Manpower!#REF! -> #REF! | U77: =+Manpower!#REF! -> #REF! | V77: =+Manpower!#REF! -> #REF! | W77: =+Manpower!#REF! -> #REF! | X77: =+Manpower!#REF! -> #REF! | Y77: =#REF! -> #REF! | Z77: =#REF! -> #REF! | AE77: =VLOOKUP(Z77,#REF!,2,FALSE) -> #REF! | AF77: =VLOOKUP(Z77,#REF!,3,FALSE) -> #REF! | AG77: =VLOOKUP(Z77,#REF!,4,FALSE) -> #REF! | AH77: =VLOOKUP(Z77,#REF!,5,FALSE) -> #REF! | AI77: =VLOOKUP(Z77,#REF!,7,FALSE) -> #REF!
F78: =#REF! -> #REF! | H78: =#REF! -> #REF! | N78: =+Manpower!#REF! -> #REF! | O78: =+Manpower!#REF! -> #REF! | P78: =Manpower!#REF! -> #REF! | U78: =+Manpower!#REF! -> #REF! | V78: =+Manpower!#REF! -> #REF! | W78: =+Manpower!#REF! -> #REF! | X78: =+Manpower!#REF! -> #REF! | Y78: =#REF! -> #REF! | Z78: =#REF! -> #REF! | AE78: =VLOOKUP(Z78,#REF!,2,FALSE) -> #REF! | AF78: =VLOOKUP(Z78,#REF!,3,FALSE) -> #REF! | AG78: =VLOOKUP(Z78,#REF!,4,FALSE) -> #REF! | AH78: =VLOOKUP(Z78,#REF!,5,FALSE) -> #REF! | AI78: =VLOOKUP(Z78,#REF!,7,FALSE) -> #REF!
C79: =#REF! -> #REF! | D79: =#REF! -> #REF! | E79: =#REF! -> #REF! | F79: =#REF! -> #REF! | G79: =#REF! -> #REF! | H79: =#REF! -> #REF! | I79: =#REF! -> #REF! | J79: =#REF! -> #REF! | ... M79: =#REF! -> #REF! | N79: =+Manpower!#REF! -> #REF! | O79: =+Manpower!#REF! -> #REF! | P79: =Manpower!#REF! -> #REF! | U79: =+Manpower!#REF! -> #REF! | V79: =+Manpower!#REF! -> #REF! | W79: =+Manpower!#REF! -> #REF! | X79: =+Manpower!#REF! -> #REF! | Y79: =#REF! -> #REF! | Z79: =#REF! -> #REF! | AE79: =VLOOKUP(Z79,#REF!,2,FALSE) -> #REF! | AF79: =VLOOKUP(Z79,#REF!,3,FALSE) -> #REF! | AG79: =VLOOKUP(Z79,#REF!,4,FALSE) -> #REF! | AH79: =VLOOKUP(Z79,#REF!,5,FALSE) -> #REF! | AI79: =VLOOKUP(Z79,#REF!,7,FALSE) -> #REF!
C80: =#REF! -> #REF! | D80: =#REF! -> #REF! | E80: =#REF! -> #REF! | F80: =#REF! -> #REF! | G80: =#REF! -> #REF! | H80: =#REF! -> #REF! | I80: =#REF! -> #REF! | J80: =#REF! -> #REF! | ... L80: =#REF! -> #REF! | N80: Total | O80: =SUM(O73:O79) -> #REF! | P80: =SUM(P73:P79) -> #REF! | U80: Total | V80: =SUM(V73:V79) -> #REF! | W80: =SUM(W73:W79) -> #REF! | X80: =SUM(X73:X79) -> #REF! | Y80: =#REF! -> #REF! | Z80: =#REF! -> #REF! | AE80: =VLOOKUP(Z80,#REF!,2,FALSE) -> #REF! | AF80: =VLOOKUP(Z80,#REF!,3,FALSE) -> #REF! | AG80: =VLOOKUP(Z80,#REF!,4,FALSE) -> #REF! | AH80: =VLOOKUP(Z80,#REF!,5,FALSE) -> #REF! | AI80: =VLOOKUP(Z80,#REF!,7,FALSE) -> #REF!
Y81: =#REF! -> #REF! | Z81: =#REF! -> #REF! | AE81: =VLOOKUP(Z81,#REF!,2,FALSE) -> #REF! | AF81: =VLOOKUP(Z81,#REF!,3,FALSE) -> #REF! | AG81: =VLOOKUP(Z81,#REF!,4,FALSE) -> #REF! | AH81: =VLOOKUP(Z81,#REF!,5,FALSE) -> #REF! | AI81: =VLOOKUP(Z81,#REF!,7,FALSE) -> #REF!
Y82: =#REF! -> #REF! | Z82: =#REF! -> #REF! | AE82: =VLOOKUP(Z82,#REF!,2,FALSE) -> #REF! | AF82: =VLOOKUP(Z82,#REF!,3,FALSE) -> #REF! | AG82: =VLOOKUP(Z82,#REF!,4,FALSE) -> #REF! | AH82: =VLOOKUP(Z82,#REF!,5,FALSE) -> #REF! | AI82: =VLOOKUP(Z82,#REF!,7,FALSE) -> #REF!
Y83: =#REF! -> #REF! | Z83: =#REF! -> #REF! | AE83: =VLOOKUP(Z83,#REF!,2,FALSE) -> #REF! | AF83: =VLOOKUP(Z83,#REF!,3,FALSE) -> #REF! | AG83: =VLOOKUP(Z83,#REF!,4,FALSE) -> #REF! | AH83: =VLOOKUP(Z83,#REF!,5,FALSE) -> #REF! | AI83: =VLOOKUP(Z83,#REF!,7,FALSE) -> #REF!
Y84: =#REF! -> #REF! | Z84: =#REF! -> #REF! | AE84: =VLOOKUP(Z84,#REF!,2,FALSE) -> #REF! | AF84: =VLOOKUP(Z84,#REF!,3,FALSE) -> #REF! | AG84: =VLOOKUP(Z84,#REF!,4,FALSE) -> #REF! | AH84: =VLOOKUP(Z84,#REF!,5,FALSE) -> #REF! | AI84: =VLOOKUP(Z84,#REF!,7,FALSE) -> #REF!
C85: Weekly Prgoress Photos | S85: Top Issues and Risks
C86: ='[61]Weekly Photos'!B23 -> Concrete barriers delivery | H86: ='[61]Weekly Photos'!H23 -> Temporary mobilization Area | N86: ='[61]Weekly Photos'!B4 -> Start works in Area A | S86: Top 5 Issues
S87: Issue No | T87: Date Identified | U87: Issue Description | Y87: Responsible | Z87: Action Taken | AC87: Mitigation | AH87: Current Status | AI87: Duration Elapsed
S88: =IF(+#REF!="","",+#REF!) -> #REF! | T88: =IF(+#REF!="","",+#REF!) -> #REF! | AI88: =IF(+#REF!="","",+#REF!) -> #REF!
S89: =IF(+#REF!="","",+#REF!) -> #REF! | T89: =IF(+#REF!="","",+#REF!) -> #REF! | AI89: =IF(+#REF!="","",+#REF!) -> #REF!
S90: =IF(+#REF!="","",+#REF!) -> #REF! | T90: =IF(+#REF!="","",+#REF!) -> #REF! | AI90: =IF(+#REF!="","",+#REF!) -> #REF!
S91: =IF(+#REF!="","",+#REF!) -> #REF! | T91: =IF(+#REF!="","",+#REF!) -> #REF! | U91: =IF(+#REF!="","",+#REF!) -> #REF! | Y91: =IF(+#REF!="","",+#REF!) -> #REF! | Z91: =IF(+#REF!="","",+#REF!) -> #REF! | AH91: =IF(+#REF!="","",+#REF!) -> #REF! | AI91: =IF(+#REF!="","",+#REF!) -> #REF!
S92: =IF(+#REF!="","",+#REF!) -> #REF! | T92: =IF(+#REF!="","",+#REF!) -> #REF! | U92: =IF(+#REF!="","",+#REF!) -> #REF! | Y92: =IF(+#REF!="","",+#REF!) -> #REF! | Z92: =IF(+#REF!="","",+#REF!) -> #REF! | AH92: =IF(+#REF!="","",+#REF!) -> #REF! | AI92: =IF(+#REF!="","",+#REF!) -> #REF!

Sheet SPI
C3: SPI Weekly Interval
D5: Week 1 14.Sep.2026 | E5: Week 2 21.Sep.2026 | F5: Week 3 28.Sep.2026 | G5: Week 4 05.Oct.2026 | H5: Week 5 012.Oct.2026
C6: Planned % | D6: 0.297 | E6: 0.31 | F6: 0.319 | G6: 0.325 | H6: =+'Weekly Progress Report'!M19 -> 0.333
C7: Earned % | D7: 0.309 | E7: 0.32 | F7: 0.329 | G7: 0.335 | H7: =+'Weekly Progress Report'!N19 -> 0.344 | L7: =+H7-G7 -> 0.009
C8: SPI | D8: 1.04 | E8: 1.03 | F8: 1.03 | G8: 1.03 | H8: =H7/H6 -> 1.03 | N8: =+G7-F7 -> 0.006
C31: Activity Name | D31: Start | E31: Finish | F31: Spreadsheet Field | G31: 46025 | H31: 46032 | I31: 46039 | J31: 46046 | K31: 46053 | L31: 46060 | M31: 46067 | N31: 46074 | O31: 46081 | P31: 46088 | Q31: 46095 | R31: 46102 | S31: 46109 | T31: 46116 | U31: 46123 | V31: 46130 | W31: 46137 | X31: 46144 | Y31: 46151 | Z31: 46158 | AA31: 46165 | AB31: 46172 | AC31: 46179 | AD31: 46186 | AE31: 46193 | AF31: 46200 | AG31: 46207 | AH31: 46214 | AI31: 46221 | AJ31: 46228 | AK31: 46235 | AL31: 46242 | AM31: 46249 | AN31: 46256 | AO31: 46263 | AP31: 46270 | AQ31: 46277 | AR31: 46284 | AS31: 46291 | AT31: 46298 | AU31: 46305 | AV31: 46312 | AW31: 46319 | AX31: 46326 | AY31: 46333 | AZ31: 46340 | BA31: 46347 | BB31: 46354 | BC31: 46361 | BD31: 46368 | BE31: 46375 | BF31: 46382 | BG31: 46389 | BH31: 46396 | BI31: 46403 | BJ31: 46410 | BK31: 46417 | BL31: 46424 | BM31: 46431 | BN31: 46438 | BO31: 46445 | BP31: 46452 | BQ31: 46459 | BR31: 46466 | BS31: 46473 | BT31: 46480 | BU31: 46487 | BV31: 46494 | BW31: 46501 | BX31: 46508 | BY31: 46515 | BZ31: 46522 | CA31: 46529 | CB31: 46536 | CC31: 46543 | CD31: 46550 | CE31: 46557 | CF31: 46564 | CG31: 46571 | CH31: 46578 | CI31: 46585 | CJ31: 46592 | CK31: 46599 | CL31: 46606 | CM31: 46613 | CN31: 46620 | CO31: 46627 | CP31: 46634 | CQ31: 46641 | CR31: 46648 | CS31: 46655 | CT31: 46662 | CU31: 46669 | CV31: 46676 | CW31: 46683 | CX31: 46690 | CY31: 46697 | CZ31: 46704 | DA31: 46711 | DB31: 46718
C32: ICKMO1-cost unite | D32: 46025 | E32: 46723 | F32: Budgeted Units | G32: 629778.8 | H32: 817900.7 | I32: 1117672.1 | J32: 1784116.5 | K32: 2205084.5 | L32: 3042911.7 | M32: 3538639.3 | N32: 2840366.4 | O32: 3077668.8 | P32: 2799539 | Q32: 2407878.9 | R32: 1910111.4 | S32: 2315821.6 | T32: 2136115.2 | U32: 1765470.3 | V32: 2035664.2 | W32: 2793013.9 | X32: 1763311.5 | Y32: 1890899.8 | Z32: 1102104.9 | AA32: 918553.47 | AB32: 1121640.6 | AC32: 817572.93 | AD32: 642466.71 | AE32: 1008995.6 | AF32: 1174931 | AG32: 1435794.4 | AH32: 2239774.9 | AI32: 2646690 | AJ32: 3094901 | AK32: 3129603.4 | AL32: 3592896.7 | AM32: 4072913.6 | AN32: 4283580 | AO32: 4325302.1 | AP32: 3073364.6 | AQ32: 3471431.7 | AR32: 1517990.5 | AS32: 2124434.9 | AT32: 2116641.5 | AU32: 2766161.8 | AV32: 3036723.7 | AW32: 2980679.1 | AX32: 3154463.8 | AY32: 3361260.2 | AZ32: 3092750.6 | BA32: 2820097.4 | BB32: 1936116.4 | BC32: 1689048.5 | BD32: 1631346.6 | BE32: 1526831.3 | BF32: 1100100.4 | BG32: 669938.63 | BH32: 595679.44 | BI32: 1867307 | BJ32: 2399894.4 | BK32: 1702100.4 | BL32: 4419281.2 | BM32: 5394379.9 | BN32: 4040128.2 | BO32: 5770854.6 | BP32: 5412649.6 | BQ32: 6058633.8 | BR32: 5925758.5 | BS32: 6146311.5 | BT32: 4098294 | BU32: 2791974.4 | BV32: 2393701.3 | BW32: 2013645.3 | BX32: 1392043.1 | BY32: 1109050.6 | BZ32: 1148278.6 | CA32: 1150798.1 | CB32: 917220.47 | CC32: 1953712.5 | CD32: 2600851.4 | CE32: 1922527.9 | CF32: 2010710.9 | CG32: 1876874.4 | CH32: 1711927.2 | CI32: 2346170.6 | CJ32: 1162975.6 | CK32: 1496899.5 | CL32: 2137249.3 | CM32: 1766195 | CN32: 576780.31 | CO32: 457950 | CP32: 429942.57 | CQ32: 203059.3 | CR32: 154448.87 | CS32: 70202.61 | CT32: 8712.77 | DA32: 19849113 | DB32: 39698226
G33: =+G32+F33 -> 629778.8 | H33: =+H32+G33 -> 1447679.5 | I33: =+I32+H33 -> 2565351.6 | J33: =+J32+I33 -> 4349468.1 | K33: =+K32+J33 -> 6554552.6 | L33: =+L32+K33 -> 9597464.3 | M33: =+M32+L33 -> 13136104 | N33: =+N32+M33 -> 15976470 | ... DB33: =+DB32+DA33 -> 2.6773158e+08
G34: =+G33/267731582 -> 0.0023522768 | H34: =+H33/267731582 -> 0.0054072048 | I34: =+I33/267731582 -> 0.0095818042 | J34: =+J33/267731582 -> 0.01624563 | K34: =+K33/267731582 -> 0.024481806 | L34: =+L33/267731582 -> 0.035847337 | M34: =+M33/267731582 -> 0.049064453 | N34: =+N33/267731582 -> 0.05967346 | ... DB34: =+DB33/267731582 -> 1

Sheet Weekly Progress Photos
C3: Weekly Progress Photos | J3: Date | K3: ='General Information'!E3 -> 46307

Sheet HSE
C3: MODON HSE Site Inspection Report
C4: Date | F4: =+'General Information'!E3 -> 46307 | M4: Inspected By | X4: MODON PM Name | AB4: Eng\Rakan
C5: Project ID. | F5: KH1-02-007 | M5: Report No. | T5: KHJ1-02-007-MAH-ST9-1-SUV-FIR-37-00
C6: Project Name: | F6: Development of infrastructure in Kharj Industrial City | M6: Contractor | T6: MOFARREH GROUP | Y6: Safety Performance | AB6: =IF(X29>0,3,IF(M29>6,AD133,IF(E29>0,2,1)*1)*1) -> 2 | AF6: =(((COUNTIF(M13:R25,"1")+COUNTIF(AD13:AI25,"1"))*AS13)+(COUNTIF(M13:R25,"2")+COUNTIF(AD13:AI25,"2"))*AS14+(COUNTIF(M13:R25,"3")+COUNTIF(AD13:AI25,"3"))*AS15)/((COUNT(M13:R25)+COUNT(AD13:AI25))*100) -> 0.93
C8: Inspections are a snapshot in time and refer only to the practices and documentation observed at the time of the Inspection. It remains the responsibility of the Consultant and Contractor to ensure that all aspects of Health & Safety are suitably managed.
C9: 1 | E9: Good Practice | I9: 2 | J9: Need Improvement | U9: 3 | V9: Fail (Life Threatening Activity) / Comliance with Plan & Procedures | Y9: N/A | Z9: Atcitty Not Applicable for this Site Inspection Report
C11: No. | D11: Topic | L11: Wt. | M11: HSE Compliance | T11: No. | U11: Topi+U11:AB15c | AC11: Wt. | AD11: HSE Compliance
C13: 1 | D13: Access and Egress - (General access to site, segregated from vehicles, / Overhead protection, while entering into the building /Adequate lighting provided when dark or overnight work) | L13: 0.05 | M13: 2 | T13: 14 | U13: Scaffolding - (Temp. Scaffolding Work-platform (All types) - qualified scaffolder / Inspection / Tagged / Safe Access/egress / PTW/Falsework & Formwork) | AC13: 0.05 | AD13: 1 | AQ13: 1 | AS13: 100 | AV13: 1
C14: 2 | D14: Traffic Management - (Loading/unloading/sheeting/temp. routes/speed/parking/competence) | L14: 0.02 | M14: 1 | T14: 15 | U14: Scaffolding - (Temp. Scaffolding Work-platform (All types) - qualified scaffolder / Inspection / Tagged / Safe Access/egress / PTW/Falsework & Formwork) | AC14: 0.04 | AD14: N/A | AQ14: 2 | AS14: 75 | AV14: 2
C15: 3 | D15: Site Signage - (Project Notice Board & General Signage) | L15: 0.02 | M15: 1 | T15: 16 | U15: Mobile Elevated Work platform (MEWP) - (PTW/competence requirements/conditions/inspections/tagged/training/Full-body harness) | AC15: 0.04 | AD15: N/A | AQ15: 3 | AS15: 0 | AV15: 3
C16: 4 | D16: PPE Compliance - (Use, storage, stock, handling & checks - Head, Foot, Eye, Hearing) | L16: 0.05 | M16: 1 | T16: 17 | U16: Excavation & Trenches - (PTW/Edge protection/buffer zone/Slope/Benching/Shoring/Geo-tech report/Atmospheric hazards/Acess&egress/Emergency management / MS&RA/H.E) | AC16: 0.03 | AD16: 2 | AV16: N/A
C17: 5 | D17: Housekeeping - (Material correctly stored/Rubbish cleaned & removed daily/slips & trips hazards) | L17: 0.03 | M17: 1 | T17: 18 | U17: Confined Space - (PTW/Training/competence/Emergency Management/MS & RA/Safe access/egress) | AC17: 0.05 | AD17: N/A
C18: 6 | D18: Storage of Materials - (Transporting, storage, training and use - Combustible / Flammable / Hazardous substances (COSHH) | M18: N/A | T18: 19 | U18: Fire Protection - (Flammable/Oxy. LPG /Combustible separated/FE's/Flashback arrestor/Sparks & slags/Smoking area/PTW/Generators/MS & RA/Emergency Management) | AD18: 1 | AM18: Red | AN18: Serious injury or death (immediately)
C19: 7 | D19: Site Waste Management - (Hazardous waste /Combustible waste / Human waste / Construction waste - asphalt, cable, timber, paving roof sheeting tiles, plastic & bricks) | L19: 0.03 | M19: 1 | T19: 20 | U19: Health & Welfare - (Adequate drinking water/shaded - eating & rest area/washing & sanitary facilities/Certified FA/FA Box & Stock/adequate toilets/Ambulance) | AD19: 2 | AM19: Yellow | AN19: Minor or near miss (3 days to comply)
C20: 8 | D20: Health Surveillance - (Expose to excessive noise/vibration/dust/silica/CO/cement/radiation/extreme weather condition) | L20: 0.03 | M20: 1 | T20: 21 | U20: Environmental Incident Measures - (Spill/ Leakage / Concrete wash / vehicle & eqpts. wash / waste disposal/Sewers and drains/emissions/Emergency Management/Training/site run-off water) | AC20: 0.05 | AD20: 2 | AM20: Green | AN20: No issues
C21: 9 | D21: Electrical Safety - (Electrical qualified /RCD/GFCI/Industrial Cocket/LOTO/Cable-overhung or buried/Cords in good condition/current inspection tag) | L21: 0.03 | M21: 1 | T21: 22 | U21: HSE Communications & Meetings - (Schedule HSE Meetings/Safety Committee meetings/Alerts / Lesson learned/Safety Bulletin contains latest HSE KPI) | AC21: 0.05 | AD21: 1
C22: 10 | D22: Tools & Equipment - (Includes, powered, hydraulic & pneumatic/Guards in place/Properly stored/RCD Protection/Earthed/Good condition & tagged) | L22: 0.03 | M22: 2 | T22: 23 | U22: HSE Plan & Associated Procedures - (Approved updated HSE Plan/ CEMP/HAZComm/Procedures/Standards/Project Safety Risk Register) | AC22: 0.03 | AD22: 1 | AM22: 26 points > 4 minors then is it’s a serious issue
C23: 11 | D23: Manual Handling - (Lifting/loading/pulling/pushing/twisting/awkward posture/repetitive task/frequent and prolong physical effort/Reasonable practicable use of mechanical aid) | L23: 0.03 | M23: 1 | T23: 24 | U23: Health, Safety & Environment Incident reporting - (Review of HSE Statistics, Reporting of Unsafe Act & Conditions/ Reporting of Near Miss incident/Reporting of FA cases/Record MT cases) | AC23: 0.03 | AD23: N/A
C24: 12 | D24: Vehicle and mobile equipment / Plant - (dumpers; excavators, cranes, piling rigs, grader, roller, loaders/condition/KSA License/certification) | L24: 0.03 | M24: 1 | T24: 25 | U24: HSE Awareness, Training & Competence - (Policy /Objective & targets/Information, training/Climatic condition awareness/Reponses in emergency situation/ Safety Behavior Observation) | AC24: 0.04 | AD24: 1
C25: 13 | D25: Lifting Operations & Rigging - (Lifting Plan/Lifting devices & gears/PTW/Condition/3rd party certification/bank-man/rigger/slingers/man-basket/inspection record/tagged) | L25: 0.03 | M25: 1 | T25: 26 | U25: Project Leadership Site Tours - (Provide evidence of proactive safety performance/Deficient discovered discussed/Positive feedback/Workers resolving safety issues) | AD25: 2
C27: Prepared by: | H27: Mohamed Adel | T27: Sent to MODON PM: | Y27: =AB4 -> Eng\Rakan
C28: Safety Results
C29: 1 | E29: =COUNTIF(M13:R26,"1")+COUNTIF(AC13:AH26,"1") -> 15 | J29: 2 | M29: =COUNTIF(M13:R26,"2")+COUNTIF(AC13:AH26,"2") -> 6 | V29: 3 | X29: =COUNTIF(M13:R26,"3")+COUNTIF(AC13:AH26,"3") -> 0

Sheet HSE-Stat
C3: WEEKLY SAFETY STATISTICS REPORT
C5: Category | D5: Item | F5: This Week | G5: This Month | H5: Year to Date | I5: Cumulative
C6: Reactive | D6: Total Hours Worked | F6: 32130 | G6: 32130 | H6: 1073075 | I6: 1073075
D7: Safe Hours Worked | F7: 32130 | G7: 32130 | H7: 1073075 | I7: 1073075
D8: LTI | F8: 0 | G8: 0 | H8: 0 | I8: 0
D9: MTC (Healed w/o Disability) | F9: 0 | G9: 0 | H9: 0 | I9: 0
D10: MTC (Healed w/ Disability) | F10: 0 | G10: 0 | H10: 0 | I10: 0
D11: Near Miss | F11: 0 | G11: 0 | H11: 2 | I11: 2
D12: First Aid Cases | F12: 0 | G12: 1 | H12: 6 | I12: 6
D13: Fatality | F13: 0 | G13: 0 | H13: 0 | I13: 0
D14: Fire Incident Cases | F14: 0 | G14: 0 | H14: 0 | I14: 0
D15: Vehicle Incident | F15: 0 | G15: 0 | H15: 0 | I15: 0
D16: Property Damages | F16: 0 | G16: 0 | H16: 3 | I16: 3
C17: Proactive | D17: Induction Training | F17: 23 | G17: 23 | H17: 1881 | I17: 1881
D18: No.of Internal Training | F18: 1 | G18: 1 | H18: 66 | I18: 66
D19: No.of Internal Audit | F19: 0 | G19: 0 | H19: 0 | I19: 0
D20: No. of Toolbox Talks | F20: 1 | G20: 1 | H20: 215 | I20: 215
D21: Safety Awards/Incentives | F21: 0 | G21: 0 | H21: 9 | I21: 9

Sheet Quality
B2: QC OBSERVATIONS CHECKLIST
BB4: ='[62]General Information'!C14 -> 45720
B6: Project No. | E6: KHJ1-02-007 | K6: OBS No. | O6: 44 | U6: Inspection Day: | X6: 04-October-2026 to 10-October-2026
B8: Project | E8: DEVELOPMENT OF INFRASTRUCTURE NETWORKS, AL KHARJ INDUSTRIAL CITY (MODON), RIYADH | O8: Contractor: Consultant: | U8: MOFFAREH ALHARBI & PARTNERS Egis Saudi Egnieering
B10: 4 | D10: Excellent | G10: Quality Management System is being practiced and applies to MODON System | Z10: 90 - 100 | AB10: QC Overall Score | AC10: =Q49 -> 0.91 | AN10: =SUM(Z10:Z13) -> 0 | AO10: 100 | AP10: 0.22883295
B11: 3 | D11: Good | G11: Evidence of compliance with plans and procedures. | Z11: 80 - 89 | AN11: =SUM(Y10:Y14) -> 0 | AO11: 89 | AP11: 0.20366133
B12: 2 | D12: Average | G12: Indication level of compliance with standards but there is room for improvement | Z12: 70 - 79 | AO12: 79 | AP12: 0.18077803
B13: 1 | D13: Improve | G13: Quality and Control is NOT being managed effectively. Needs Improvement | Z13: ≤ 69 | AO13: 69 | AP13: 0.15789474
B14: 0 | D14: N/A | G14: Item was not applicable or this item was not reviewed during the inspection. | Z14: Zero | AO14: 100 | AP14: 0.22883295
B16: No. | C16: Topic | K16: E (4) | L16: G (3) | M16: A (2) | N16: I (1) | O16: N/A (0) | Q16: No. | R16: Topic | Z16: E (4) | AA16: G (3) | AB16: A (2) | AC16: I (1) | AD16: N/A (0) | AO16: =SUM(AO10:AO15) -> 437
K17: 1 | L17: 0.89 | M17: 0.79 | N17: 0.69 | O17: 1 | Z17: 1 | AA17: 0.89 | AB17: 0.79 | AC17: 0.69 | AD17: 1 | AF17: =SUM(AF18:AG46)/COUNT(AF18:AG46) -> 0.91
B18: 1 | C18: Control of Access to Site/Office | L18: 1 | Q18: 30 | R18: QC of Excavation | AA18: 1 | AF18: =SUMPRODUCT($K$17:$O$17,K18:O18) -> 0.89 | AG18: =SUMPRODUCT($Z$17:$AD$17,Z18:AD18) -> 0.89 | AV18: Item Count | AW18: Score | AX18: Distributtion
B19: 2 | C19: Document Control Administration | L19: 1 | Q19: 31 | R19: QC of Roads/Round about | AA19: 1 | AF19: =SUMPRODUCT($K$17:$O$17,K19:O19) -> 0.89 | AG19: =SUMPRODUCT($Z$17:$AD$17,Z19:AD19) -> 0.89 | AX19: Overall | AY19: Relevant
B20: 3 | C20: Project Documents and Progress | L20: 1 | Q20: 32 | R20: QC of Interlock & Curbstone | AA20: 1 | AF20: =SUMPRODUCT($K$17:$O$17,K20:O20) -> 0.89 | AG20: =SUMPRODUCT($Z$17:$AD$17,Z20:AD20) -> 0.89 | AM20: 4 | AN20: =58 -> 58 | AO20: counts | AQ20: 4 | AR20: Excellent | AV20: =SUM(Z18:Z46,K18:K46) -> 1 | AW20: =AQ20*AV20 -> 4 | AX20: =AV20/$AV$25 -> 0.0172 | AY20: =AV20/SUM($AV$20:$AV$23) -> 0.0213
B21: 4 | C21: Contractor's Quality Plan/CM (Updated and Reviewed) | L21: 1 | Q21: 33 | R21: Layers/Backfilling Sampling | AA21: 1 | AF21: =SUMPRODUCT($K$17:$O$17,K21:O21) -> 0.89 | AG21: =SUMPRODUCT($Z$17:$AD$17,Z21:AD21) -> 0.89 | AM21: 3 | AN21: =58 -> 58 | AO21: counts | AQ21: 3 | AR21: Good | AV21: =SUM(L18:L46,AA18:AA46) -> 43 | AW21: =AQ21*AV21 -> 129 | AX21: =AV21/$AV$25 -> 0.7414 | AY21: =AV21/SUM($AV$20:$AV$23) -> 0.9149
B22: 5 | C22: MS Log and Paperwork | L22: 1 | Q22: 34 | R22: Pump Stations Units | AD22: 1 | AF22: =SUMPRODUCT($K$17:$O$17,K22:O22) -> 0.89 | AG22: =SUMPRODUCT($Z$17:$AD$17,Z22:AD22) -> 1 | AM22: 2 | AN22: =58 -> 58 | AO22: counts | AQ22: 2 | AR22: Average | AV22: =SUM(M18:M46,AB18:AB46) -> 3 | AW22: =AQ22*AV22 -> 6 | AX22: =AV22/$AV$25 -> 0.0517 | AY22: =AV22/SUM($AV$20:$AV$23) -> 0.0638 | BC22: NB: Insert 1, or 0 in the required cell only.
B23: 6 | C23: RFI, FIR, & MIR Procedure | L23: 1 | Q23: 35 | R23: Quality of Form Work | AA23: 1 | AF23: =SUMPRODUCT($K$17:$O$17,K23:O23) -> 0.89 | AG23: =SUMPRODUCT($Z$17:$AD$17,Z23:AD23) -> 0.89 | AM23: 1 | AN23: =58 -> 58 | AO23: counts | AQ23: 1 | AR23: Improve | AV23: =SUM(N18:N46,AC18:AC46) -> 0 | AW23: =AQ23*AV23 -> 0 | AX23: =AV23/$AV$25 -> 0 | AY23: =AV23/SUM($AV$20:$AV$23) -> 0
B24: 7 | C24: RFI, FIR, & MIR Inventory system | L24: 1 | Q24: 36 | R24: Design Change List | AD24: 1 | AF24: =SUMPRODUCT($K$17:$O$17,K24:O24) -> 0.89 | AG24: =SUMPRODUCT($Z$17:$AD$17,Z24:AD24) -> 1 | AM24: 0 | AN24: =58 -> 58 | AO24: counts | AQ24: 0 | AR24: N/A | AV24: =SUM(O18:O46,AD18:AD46) -> 11 | AW24: =AQ24*AV24 -> 0 | AX24: =AV24/$AV$25 -> 0.1897 | AY24: -
B25: 8 | C25: NCRs Control & Procedure | L25: 1 | Q25: 37 | R25: Quality of Concrete Placing | AA25: 1 | AF25: =SUMPRODUCT($K$17:$O$17,K25:O25) -> 0.89 | AG25: =SUMPRODUCT($Z$17:$AD$17,Z25:AD25) -> 0.89 | AR25: Total | AV25: =SUM(AV20:AV24) -> 58 | AW25: =SUM(AW20:AW24) -> 139 | AX25: =SUM(AX20:AX24) -> 1 | AY25: =SUM(AY20:AY24) -> 1
B26: 9 | C26: NCR Log | L26: 1 | Q26: 38 | R26: Concrete Surface Finishing | AA26: 1 | AF26: =SUMPRODUCT($K$17:$O$17,K26:O26) -> 0.89 | AG26: =SUMPRODUCT($Z$17:$AD$17,Z26:AD26) -> 0.89
B27: 10 | C27: MODON Standard* | L27: 1 | Q27: 39 | R27: Pedestals/Columns/Beams Alignment | AA27: 1 | AF27: =SUMPRODUCT($K$17:$O$17,K27:O27) -> 0.89 | AG27: =SUMPRODUCT($Z$17:$AD$17,Z27:AD27) -> 0.89 | AV27: Maz Score Available: | AW27: =SUM(AV20:AV23)*AQ20 -> 188 | AX27: <- Excludes N/A items
B28: 11 | C28: Project Risk Plan/Management* | L28: 1 | Q28: 40 | R28: Siporex Lifting & Unloading | AB28: 1 | AF28: =SUMPRODUCT($K$17:$O$17,K28:O28) -> 0.89 | AG28: =SUMPRODUCT($Z$17:$AD$17,Z28:AD28) -> 0.79
B29: 12 | C29: Monthly Quality Reports* | L29: 1 | Q29: 41 | R29: Siporex Quality Pre-installation | AD29: 1 | AF29: =SUMPRODUCT($K$17:$O$17,K29:O29) -> 0.89 | AG29: =SUMPRODUCT($Z$17:$AD$17,Z29:AD29) -> 1
B30: 13 | C30: ITP | K30: 1 | Q30: 42 | R30: Siporex Finishing Quality | AD30: 1 | AF30: =SUMPRODUCT($K$17:$O$17,K30:O30) -> 1 | AG30: =SUMPRODUCT($Z$17:$AD$17,Z30:AD30) -> 1 | AR30: Total Score | AW30: Percentage (%)
B31: 14 | C31: MODON Weekly Report | L31: 1 | Q31: 43 | R31: Roads / Parking Markings | AD31: 1 | AF31: =SUMPRODUCT($K$17:$O$17,K31:O31) -> 0.89 | AG31: =SUMPRODUCT($Z$17:$AD$17,Z31:AD31) -> 1 | AN31: =MAX(AN20:AN24) -> 58 | AR31: =AW25 -> 139 | AW31: =SUM(100/AR33*AR31) -> 73.94 | AY31: %
B32: 15 | C32: Design Change Official Paperwork* | M32: 1 | Q32: 44 | R32: QC of Finishing Outdoors | AD32: 1 | AF32: =SUMPRODUCT($K$17:$O$17,K32:O32) -> 0.79 | AG32: =SUMPRODUCT($Z$17:$AD$17,Z32:AD32) -> 1 | AR32: Max Score Available | BP32: 31
B33: 16 | C33: Design Change was Applied* | L33: 1 | Q33: 45 | R33: Quality of Finishing Indoors | AA33: 1 | AF33: =SUMPRODUCT($K$17:$O$17,K33:O33) -> 0.89 | AG33: =SUMPRODUCT($Z$17:$AD$17,Z33:AD33) -> 0.89 | AR33: =AW27 -> 188 | BP33: 32
B34: 17 | C34: Material List | L34: 1 | Q34: 46 | R34: Stairs Quality | AD34: 1 | AF34: =SUMPRODUCT($K$17:$O$17,K34:O34) -> 0.89 | AG34: =SUMPRODUCT($Z$17:$AD$17,Z34:AD34) -> 1 | BP34: 33
B35: 18 | C35: Pending Material Status | L35: 1 | Q35: 47 | R35: Tanks Method Statement Work | AD35: 1 | AF35: =SUMPRODUCT($K$17:$O$17,K35:O35) -> 0.89 | AG35: =SUMPRODUCT($Z$17:$AD$17,Z35:AD35) -> 1 | BP35: 34
B36: 19 | C36: Lifting Plan* | L36: 1 | Q36: 48 | R36: Electric Rooms | AD36: 1 | AF36: =SUMPRODUCT($K$17:$O$17,K36:O36) -> 0.89 | AG36: =SUMPRODUCT($Z$17:$AD$17,Z36:AD36) -> 1 | BP36: 35
B37: 20 | C37: DWG Log | L37: 1 | Q37: 49 | R37: QC of MCC/ATS Plant Units | AA37: 1 | AF37: =SUMPRODUCT($K$17:$O$17,K37:O37) -> 0.89 | AG37: =SUMPRODUCT($Z$17:$AD$17,Z37:AD37) -> 0.89 | BP37: 36
B38: 21 | C38: Invoice Status | M38: 1 | Q38: 50 | R38: Qualified Subcontractor | AA38: 1 | AF38: =SUMPRODUCT($K$17:$O$17,K38:O38) -> 0.79 | AG38: =SUMPRODUCT($Z$17:$AD$17,Z38:AD38) -> 0.89 | BP38: 37
B39: 22 | C39: Site Handover Letter | O39: 1 | Q39: 51 | R39: Scaffold/Ladders/Slope/Bridge Compliance | AA39: 1 | AF39: =SUMPRODUCT($K$17:$O$17,K39:O39) -> 1 | AG39: =SUMPRODUCT($Z$17:$AD$17,Z39:AD39) -> 0.89 | BP39: 38
B40: 23 | C40: Material Testing Results & Certification | L40: 1 | Q40: 52 | R40: Protection Applied to Completed Work | AA40: 1 | AF40: =SUMPRODUCT($K$17:$O$17,K40:O40) -> 0.89 | AG40: =SUMPRODUCT($Z$17:$AD$17,Z40:AD40) -> 0.89
B41: 24 | C41: As Build Drawings Status* | O41: 1 | Q41: 53 | R41: Storage Management in/out Control | AA41: 1 | AF41: =SUMPRODUCT($K$17:$O$17,K41:O41) -> 1 | AG41: =SUMPRODUCT($Z$17:$AD$17,Z41:AD41) -> 0.89
B42: 25 | C42: Calibrated Lab Tools & Equipment | L42: 1 | Q42: 54 | R42: Material Control | AA42: 1 | AF42: =SUMPRODUCT($K$17:$O$17,K42:O42) -> 0.89 | AG42: =SUMPRODUCT($Z$17:$AD$17,Z42:AD42) -> 0.89
B43: 26 | C43: Storage Inventory System | L43: 1 | Q43: 55 | R43: Manholes Storing and Quality | AA43: 1 | AF43: =SUMPRODUCT($K$17:$O$17,K43:O43) -> 0.89 | AG43: =SUMPRODUCT($Z$17:$AD$17,Z43:AD43) -> 0.89
B44: 27 | C44: Logistics Plan | L44: 1 | Q44: 56 | R44: Reinforced Steel Quality | AA44: 1 | AF44: =SUMPRODUCT($K$17:$O$17,K44:O44) -> 0.89 | AG44: =SUMPRODUCT($Z$17:$AD$17,Z44:AD44) -> 0.89
B45: 28 | C45: Project Progress Planview | L45: 1 | Q45: 57 | R45: Safety Overview | AA45: 1 | AF45: =SUMPRODUCT($K$17:$O$17,K45:O45) -> 0.89 | AG45: =SUMPRODUCT($Z$17:$AD$17,Z45:AD45) -> 0.89
B46: 29 | C46: Sufficient Number of QC Inspectors | L46: 1 | Q46: 58 | R46: Waste Management Control | AA46: 1 | AF46: =SUMPRODUCT($K$17:$O$17,K46:O46) -> 0.89 | AG46: =SUMPRODUCT($Z$17:$AD$17,Z46:AD46) -> 0.89
I48: Score
M49: *QC % | Q49: =AF17 -> 0.91
B51: Prepared by: | G51: Engr. Adil Ghafoor Sulehria | Q51: Issued to PM:
B53: *QC Observations refer only to the practices and documentation observed at time of inspection. The responsibility of the CM and Contractor is to ensure that aspects of Quality are suitably managed. *Scores are a reflection of the general site conditions based upon the findings at the time of the walk through *If Applicable

Sheet Quality-Stat
D3: Project ID: | E3: KHJ1-02-007 | G3: WEEKLY QUALITY STATISTICS REPORT (WQSR)
D4: Project Name: | E4: DEVELOPMENT OF INFRASTRUCTURE NETWORKS, AL KHARJ INDUSTRIAL CITY (MODON), RIYADH
C5: Contractor: MOFFAREH ALHARBI & PARTNERS | D5: For the Week of: | E5: 04-October-2026 to 10-October-2026
C6: Document Ref. Number | D6: QWR-0044
C7: The Following facts (provided as guideline) in figures indicate the current trends of Quality highlights improvement and areas of concerns as well towards overall site Quality aspects of this project.
C9: GENERAL | D9: Previous Week | E9: This Week | F9: Cumulative | G9: Brief Description/Comment
C10: Planned Project Progress | D10: 31.87 | E10: 0.6 | F10: 32.45 | G10: As Pre Revised Schedule
C11: Actual Project Progress | D11: 32.88 | E11: 0.6 | F11: 33.49
C12: QAC Leading Indicators | G12: Brief Description/Comment
C13: No. of Quality Induction conducted | D13: 1 | E13: =F13-D13 -> 0 | F13: 1
C14: No. of Quality Training Delivered* | D14: 10 | E14: 0 | F14: 10
C15: No. of Approved Field Inspection Report (FIR) | D15: 52983 | E15: 224 | F15: 53207
C16: No. of Rejected Field Inspection Report (FIR) | D16: 0 | E16: 29 | F16: 29
C17: No. of under review Field Inspection Report (FIR) | D17: 0 | E17: 31 | F17: 31
C18: No. of Approved Material Inspection Request (MIR) | D18: 206 | E18: 7 | F18: 213
C19: No. of Rejected Material Inspection Request (MIR) | D19: 0 | E19: 0 | F19: 0
C20: No. of Request For Information (RFI) - Open | D20: 1 | E20: 2 | F20: 3
C21: No. of Request For Information (RFI) - Closed | D21: 118 | E21: 3 | F21: 121
C22: No. of Approved Material Received Inspection Report (MRIR) | D22: 103 | E22: 0 | F22: 103
C23: No. of Rejected Material Received Inspection Report (MRIR) | D23: 0 | E23: 0 | F23: 0
C24: No. of Review/Approved Shop drawings | D24: 2031 | E24: 56 | F24: 2087
C25: No. of Rejected Shop drawings | D25: 0 | E25: 0 | F25: 0
... C31: No. of Non-Conformance Report (NCR) issued* | D31: 37 | E31: 0 | F31: 37
C32: Type & No. of Test performed* | D32: 2177 | E32: 93 | F32: 2270 | G32: Compaction-Soil Sampling-Borehole-Concrete Compressive Test
C33: Amount & No.of Penalties/Fines Applied* | D33: 7 | E33: 0 | F33: 7
C34: No. of Change/ Variation Request | D34: 0 | E34: =F34-D34 -> 0 | F34: 0
C35: No. of critical long lead iteams and status* | D35: 0 | E35: =F35-D35 -> 0 | F35: 0
C36: No. of Internal/External Audit Conducted | D36: 5 | E36: 0 | F36: 5
C38: Work Done this week
C39: E.g. 1 - Quality Toolbox Meeting for Borehole Geotechnical Investigation, Drilling and Sampling Activities. 2 - Quality inspections/Site walkthrough performed. 3 - Internal weekly MOM done.
C42: Name: Adil Ghafoor | G42: Approved By:
C43: Position: QA QC Manager | G43: Position:
C44: Signature: | G44: Signature:

Sheet Weekly Quality
A1: DEVELOPMENT OF INFRASTRUCTURE NETWORKS, AL KHARJ INDUSTRIAL CITY (MODON), RIYADH | AC1: DEVELOPMENT OF INFRASTRUCTURE NETWORKS, AL KHARJ INDUSTRIAL CITY (MODON), RIYADH
A2: The Contractor : MOFFAREH ALHARBI & PARTNERS | AC2: The Contractor : MOFFAREH ALHARBI & PARTNERS
A3: Report Number:KHJ1-02-007-MAH-TS9-1-QMS-QWR-0043-00 Contractors’ Submittal -27-September-2026 to 03-October-2026) | AC3: 04-October-2026 to 10-October-2026
B4: FIR Detail | L4: NCR Detail | T4: MAR Detail | AD4: Shop Drawing | AN4: ITP ( Inspection Test Plan) | AX4: MES ( Method statement)
C5: Received | F5: Code A | G5: Code B | H5: Code C/D | I5: UR | J5: KPI % | M5: Issued/Received | P5: Closed | Q5: OPEN | R5: KPI % | U5: Received | X5: Code A | Y5: Code B | Z5: Code C/D | AA5: UR | AB5: KPI % | AE5: Received | AH5: Code A | AI5: Code B | AJ5: Code C/D | AK5: UR | AL5: KPI % | AO5: Received | AR5: Code A | AS5: Code B | AT5: Code C/D | AU5: UR | AV5: KPI % | AY5: Received | BB5: Code A | BC5: Code B | BD5: Code C/D | BE5: UR | BF5: KPI %
C6: Previous | D6: Current | E6: Cumulative | M6: Previous | N6: Current | O6: Cumulative | U6: Previous | V6: Current | W6: Cumulative | AA6: UR | AE6: Previous | AF6: Current | AG6: Cumulative | AO6: Previous | AP6: Current | AQ6: Cumulative | AY6: Previous | AZ6: Current | BA6: Cumulative
B7: CIV | D7: 3 | F7: 0 | G7: 0 | H7: 0 | I7: 3 | L7: CIV | N7: 0 | P7: 0 | Q7: 0 | T7: CIV | V7: 0 | X7: 0 | Y7: 0 | Z7: 0 | AA7: 0 | AD7: CIV | AF7: 0 | AH7: 0 | AI7: 0 | AJ7: 0 | AK7: 0 | AN7: CIVIL | AP7: 0 | AR7: 0 | AS7: 0 | AT7: 0 | AU7: 0 | AX7: CIVIL | AZ7: 1 | BB7: 1 | BC7: 0 | BD7: 0 | BE7: 0
B8: Road | D8: 80 | F8: 15 | G8: 64 | H8: 1 | I8: 0 | L8: Electrical | N8: =O8-M8 -> 0 | P8: 0 | Q8: =O8-P8 -> 0 | T8: Electrical | V8: 0 | X8: 0 | Y8: 0 | Z8: 0 | AA8: 0 | AD8: Electrical | AF8: 6 | AH8: 4 | AI8: 0 | AJ8: 0 | AK8: 2 | AN8: MEP | AP8: 0 | AR8: 0 | AS8: 0 | AT8: 0 | AU8: 0 | AX8: MEP | AZ8: 0 | BB8: 0 | BC8: 0 | BD8: 0 | BE8: 1
B9: CBC | D9: 4 | F9: 2 | G9: 2 | H9: 0 | I9: 0 | L9: Mechanical | N9: 1 | P9: 0 | Q9: 1 | T9: Mechanical | V9: 0 | X9: 0 | Y9: 0 | Z9: 0 | AA9: 0 | AD9: Mechanical | AF9: 0 | AH9: 0 | AI9: 0 | AJ9: 0 | AK9: 0 | AN9: ELECTRICAL | AP9: 0 | AR9: 0 | AS9: 0 | AT9: 0 | AU9: 0 | AX9: ELECTRICAL | AZ9: 0 | BB9: 0 | BC9: 0 | BD9: 0 | BE9: 0
B10: MEC | D10: 0 | F10: 0 | G10: 0 | H10: 0 | I10: 0 | L10: Sewer | N10: 0 | P10: 0 | Q10: 0 | T10: Arc | V10: 0 | X10: 0 | Y10: 0 | Z10: 0 | AA10: 0 | AD10: General | AF10: 0 | AH10: 0 | AI10: 0 | AJ10: 0 | AK10: 0 | AN10: ROD | AP10: 0 | AR10: 0 | AS10: 0 | AT10: 0 | AU10: 0 | AX10: ARC | AZ10: 0 | BB10: 0 | BC10: 0 | BD10: 0 | BE10: 0
B11: Sewer | D11: 80 | F11: 0 | G11: 47 | H11: 19 | I11: 4 | L11: General | N11: 0 | P11: 0 | Q11: 0 | T11: IRI | V11: 0 | X11: 0 | Y11: 0 | Z11: 0 | AA11: 0 | AD11: Arch | AF11: 0 | AH11: 0 | AI11: 0 | AJ11: 0 | AK11: 0 | AN11: TEL | AP11: 0 | AR11: 0 | AS11: 0 | AT11: 0 | AU11: 0 | AX11: TEL | AZ11: 0 | BB11: 0 | BC11: 0 | BD11: 0 | BE11: 0
B12: Storm | D12: 44 | F12: 0 | G12: 39 | H12: 4 | I12: 1 | T12: LSC | V12: 0 | X12: 0 | Y12: 0 | Z12: 0 | AA12: 0 | AD12: ROAD | AF12: 1 | AH12: 1 | AI12: 0 | AJ12: 0 | AK12: 0 | AN12: Arc | AP12: 0 | AR12: 0 | AS12: 0 | AT12: 0 | AU12: 0
B13: Electrical | D13: 20 | F13: 7 | G13: 12 | H13: 0 | I13: 1 | AD13: SEW | AF13: 0 | AH13: 0 | AI13: 0 | AJ13: 0 | AK13: 0 | AN13: 0
B14: TEL | D14: 11 | F14: 3 | G14: 7 | H14: 1 | I14: 0 | AD14: TEL | AF14: 0 | AH14: 0 | AI14: 0 | AJ14: 0 | AK14: 0
B15: IRR | D15: 17 | F15: 1 | G15: 13 | H15: 3 | I15: 0 | AD15: ST | AF15: 20 | AH15: 0 | AI15: 20 | AJ15: 0 | AK15: 0
B16: Survey | D16: 0 | F16: 0 | G16: 0 | H16: 0 | I16: 0 | AD16: CBC | AF16: 0 | AH16: 0 | AI16: 0 | AJ16: 0 | AK16: 0
B17: POT | D17: 16 | F17: 0 | G17: 12 | H17: 1 | I17: 3 | AD17: LSC | AF17: 20 | AH17: 0 | AI17: 20 | AJ17: 0 | AK17: 0
AD18: IRR | AF18: 0 | AH18: 0 | AI18: 0 | AJ18: 0 | AK18: 0 | AM18: 81
AD19: POT | AF19: 0 | AH19: 0 | AI19: 0 | AJ19: 0 | AK19: 0
B20: TOTAL | D20: =SUM(D7:D19) -> 275 | F20: =SUM(F7:F19) -> 28 | G20: =SUM(G7:G19) -> 196 | H20: =SUM(H7:H19) -> 29 | I20: 31 | J20: 90 | L20: TOTAL | N20: 0 | P20: 0 | Q20: 0 | R20: 0 | T20: TOTAL | V20: 0 | X20: =SUM(X7:X15) -> 0 | Y20: 0 | Z20: =SUM(Z7:Z15) -> 0 | AA20: =SUM(AA7:AA15) -> 0 | AB20: 100 | AD20: MEP | AF20: 0 | AH20: 0 | AI20: 0 | AJ20: 0 | AK20: 0 | AN20: TOTAL | AP20: 0 | AR20: 0 | AS20: =SUM(AS7:AS15) -> 0 | AT20: =SUM(AT7:AT15) -> 0 | AU20: =SUM(AU7:AU15) -> 0 | AV20: 100 | AX20: TOTAL | AZ20: 1 | BB20: =SUM(BB7:BB15) -> 1 | BC20: =SUM(BC7:BC15) -> 0 | BD20: =SUM(BD7:BD15) -> 0 | BE20: 0 | BF20: 100
AD21: STR | AF21: 11 | AH21: 0 | AI21: 11 | AJ21: 0 | AK21: 0
AD22: TOTAL | AF22: 58 | AH22: 5 | AI22: 51 | AJ22: 0 | AK22: 2 | AL22: 100
B24: PQD (Prequalification Documents) | L24: SIR/SOR Detail | T24: MRIR | AD24: As built Drawing | AN24: MIR ( Material Receiving Inspection)
C25: Received | F25: Code A | G25: Code B | H25: Code C/D | I25: UR | J25: KPI % | M25: Issued/Received | P25: Closed | Q25: OPEN | R25: KPI % | U25: Received | X25: Code A | Y25: Code B | Z25: Code C/D | AA25: UR | AB25: KPI % | AE25: Received | AH25: Code A | AI25: Code B | AJ25: Code C/D | AK25: UR | AL25: KPI % | AO25: Received | AR25: Code A | AS25: Code B | AT25: Code C/D | AU25: UR | AV25: KPI %
C26: Previous | D26: Current | E26: Cumulative | M26: Previous | N26: Current | U26: Previous | V26: Current | W26: Cumulative | AE26: Previous | AF26: Current | AG26: Cumulative | AO26: Previous | AP26: Current | AQ26: Cumulative
B27: CIV | D27: 1 | F27: 0 | G27: 0 | H27: 1 | I27: 0 | L27: CIV | N27: 0 | P27: 0 | Q27: 0 | T27: CIV | V27: 0 | X27: 0 | Y27: 0 | Z27: 0 | AA27: 0 | AD27: CIV | AF27: 0 | AG27: 0 | AH27: 0 | AI27: 0 | AJ27: 0 | AK27: =AG27-AH27-AI27-AJ27 -> 0 | AN27: CIV/ROD | AP27: 2 | AR27: 2 | AS27: 0 | AT27: 0 | AU27: 0
B28: ARCH | D28: 1 | F28: 0 | G28: 0 | H28: 0 | I28: 1 | L28: ARCH | N28: 0 | P28: 0 | Q28: =O28-P28 -> 0 | T28: ARCH | V28: 0 | X28: 0 | Y28: 0 | Z28: 0 | AA28: 0 | AD28: ARCH | AF28: =AG28-AE28 -> 0 | AG28: 0 | AH28: 0 | AI28: 0 | AJ28: 0 | AK28: =AG28-AH28-AI28-AJ28 -> 0 | AN28: ARCH | AP28: =AQ28-AO28 -> 0 | AR28: 0 | AS28: 0 | AT28: 0 | AU28: =AQ28-AR28-AS28-AT28 -> 0
B29: Electrical | D29: 0 | F29: 0 | G29: 0 | H29: 0 | I29: 0 | L29: Electrical | N29: =O29-M29 -> 0 | P29: 0 | Q29: =O29-P29 -> 0 | T29: Electrical | V29: 0 | X29: 0 | Y29: 0 | Z29: 0 | AA29: 0 | AD29: Electrical | AF29: =AG29-AE29 -> 0 | AG29: 0 | AH29: 0 | AI29: 0 | AJ29: 0 | AK29: =AG29-AH29-AI29-AJ29 -> 0 | AN29: Electrical | AP29: 2 | AR29: 1 | AS29: 0 | AT29: 0 | AU29: 1
B30: Mechanical | D30: 0 | F30: 0 | G30: 0 | H30: 0 | I30: 0 | L30: Mechanical | N30: 0 | P30: 0 | Q30: 0 | T30: MEP | V30: 0 | X30: 0 | Y30: 0 | Z30: 0 | AA30: 0 | AD30: Mechanical | AF30: =AG30-AE30 -> 0 | AG30: 0 | AH30: 0 | AI30: 0 | AJ30: 0 | AK30: =AG30-AH30-AI30-AJ30 -> 0 | AN30: Mechanical | AP30: 4 | AR30: 4 | AS30: 0 | AT30: 0 | AU30: 0
B31: General | D31: 0 | F31: 0 | G31: 0 | H31: 0 | I31: 0 | L31: General | N31: 0 | P31: 0 | Q31: 0 | T31: Tel | V31: 0 | X31: 0 | Y31: 0 | Z31: 0 | AA31: 0 | AD31: General | AF31: =AG31-AE31 -> 0 | AG31: 0 | AH31: 0 | AI31: 0 | AJ31: 0 | AK31: =AG31-AH31-AI31-AJ31 -> 0 | AN31: Telecom | AP31: =AQ31-AO31 -> 0 | AR31: 0 | AS31: 0 | AT31: 0 | AU31: =AQ31-AR31-AS31-AT31 -> 0
T32: Storm | V32: 0 | X32: 0 | Y32: 0 | Z32: 0 | AA32: 0 | AN32: Storm | AP32: =AQ32-AO32 -> 0 | AR32: 0 | AS32: 0 | AT32: 0 | AU32: =AQ32-AR32-AS32-AT32 -> 0
T33: CBC | V33: 0 | X33: 0 | Y33: 0 | Z33: 0 | AA33: 0 | AN33: General | AP33: =AQ33-AO33 -> 0 | AR33: 0 | AS33: 0 | AT33: 0 | AU33: =AQ33-AR33-AS33-AT33 -> 0
T34: ROD | V34: 0 | X34: 9 | Y34: 0 | Z34: 0 | AA34: 0 | AN34: CBC | AP34: 0 | AR34: 0 | AS34: 0 | AT34: 0 | AU34: 0
B35: TOTAL | D35: =SUM(D26:D33) -> 2 | F35: =SUM(F26:F33) -> 0 | G35: =SUM(G26:G33) -> 0 | H35: =SUM(H26:H33) -> 1 | I35: =SUM(I26:I33) -> 1 | J35: 0 | T35: TOTAL | V35: =SUM(V26:V34) -> 0 | X35: 0 | Y35: =SUM(Y26:Y34) -> 0 | Z35: =SUM(Z26:Z34) -> 0 | AA35: 0 | AB35: 100 | AD35: TOTAL | AF35: =SUM(AF26:AF33) -> 0 | AH35: =SUM(AH26:AH33) -> 0 | AI35: =SUM(AI26:AI33) -> 0 | AJ35: =SUM(AJ26:AJ33) -> 0 | AK35: =SUM(AK26:AK33) -> 0 | AL35: 100 | AN35: LSC | AP35: =AQ35-AO35 -> 0 | AR35: 0 | AS35: 0 | AT35: 0 | AU35: =AQ35-AR35-AS35-AT35 -> 0
L36: TOTAL | N36: 0 | P36: =SUM(P27:P35) -> 0 | Q36: =SUM(Q27:Q35) -> 0 | R36: 100 | AN36: TOTAL | AP36: =SUM(AP27:AP35) -> 8 | AR36: 7 | AS36: =SUM(AS27:AS35) -> 0 | AT36: =SUM(AT27:AT35) -> 0 | AU36: 1 | AV36: 100

Sheet FIR Summary
C3: QC OBSERVATIONS CHECKLIST FIR Summary
C5: Serial # | D5: FIR # | E5: FIR Description | F5: Date | G5: Duration days | H5: Comments
C6: 1.Civil (CIV)
C8: 1 | D8: KHJ1-02-007-MAH-TS9-1-CIV-FIR-0096 | E8: Inspection for block masonry (CMU) Above the parapet between posts as per highlight in attached drawing Mosque (Mosque Area) | F8: 46295 | H8: UR-Under Review
C9: 2 | D9: KHJ1-02-007-MAH-TS9-1-CIV-FIR-0126 | E9: Inspection of Reinforcement Steel for Tie Beams Above the block masonry between posts as per highlight in attached drawing Mosque (Mosque Area). | F9: 46295 | H9: UR-Under Review
C10: 3 | D10: KHJ1-02-007-MAH-TS9-1-CIV-FIR-0137 | E10: Inspection of Concrete Pouring for Tie Beams Above the block masonry between posts as per highlight in attached drawing Mosque (Mosque Area). | F10: 46294 | H10: UR-Under Review
C11: 2.Road (ROD)
C12: 1 | D12: KHJ1-02-007-MAH-TS9-1-ROD-FIR-0849 | E12: Inspection for Sampling, Testing and Placement of 2nd Layer of Bituminous Base Course Left Side Remaining Area (5m) from Station 0+750 to 0+900 at Arterial Road - 01 Zone B. | F12: 46299 | H12: Accepted
C13: 2 | D13: KHJ1-02-007-MAH-TS9-1-ROD-FIR-0907 | E13: Inspection for Sampling, Testing and Placement of Bituminous Base Course (70mm) Station Station 0+062.5 to 0+275 at Local Road # 11 Zone A. | F13: 46299 | H13: Accepted
C14: 3 | D14: KHJ1-02-007-MAH-TS9-1-ROD-FIR-0910 | E14: Inspection for Sampling, Testing and Placement of Bituminous Base Course from Station 0+050 to 0+644 at Local Road - 25 Zone B. | F14: 46301 | H14: Accepted
C15: 4 | D15: KHJ1-02-007-MAH-TS9-1-ROD-FIR-0916 | E15: Inspection for Sampling, Testing and Placement of Bituminous Base Course Station 0+100 to 0+225 (70mm) at Local Road # 12 Zone A | F15: 46301 | H15: Accepted
C16: 5 | D16: KHJ1-02-007-MAH-TS9-1-ROD-FIR-0920 | E16: Inspection for Sampling, Testing and Placement of Bituminous Base Course from Station 0+025 to 0+100 at Local Road - 23 Zone B. | F16: 46301 | H16: Accepted
C17: 6 | D17: KHJ1-02-007-MAH-TS9-1-ROD-FIR-0925 | E17: Inspection for Installation of Curb Stone (K1A-187m) Median Right Side of Road from station 0+400 to 0+587 at Arterial Road # 01 Zone B. | F17: 46302 | H17: Accepted
C18: 7 | D18: KHJ1-02-007-MAH-TS9-1-ROD-FIR-0927 | E18: Core sampling Inspection for Bitumen Base course Station 0+062.5 to 0+275 (70mm) at Local Road # 11, 0+088 to 0+237 (70mm) at Local Road # 12 & 0+200 to 0+300 (150mm) (LHS) at Collector Road # 01 Zone A | F18: 46303 | H18: Accepted
C19: 8 | D19: KHJ1-02-007-MAH-TS9-1-ROD-FIR-0936 | E19: Inspection for Placement, Location, level and Compaction for 1st layer of Sub Grade from Station 0+550 to 0+625 at Local Road # 02 Zone B. | F19: 46303 | H19: Accepted
C20: 9 | D20: KHJ1-02-007-MAH-TS9-1-ROD-FIR-0937 | E20: Inspection for Placement, Location, level and Compaction for 1st layer of Sub Grade from Station 1+250 to 1+675 at Local Road # 02 Zone B. | F20: 46303 | H20: Accepted
C21: 10 | D21: KHJ1-02-007-MAH-TS9-1-ROD-FIR-0940 | E21: Inspection for Sampling, Testing and Placement of Bituminous Base Course Station 0+200 to 0+300 (150mm) (LHS) at Collector Road # 01 Zone A | F21: 46301 | H21: Accepted
C22: 11 | D22: KHJ1-02-007-MAH-TS9-1-ROD-FIR-0942 | E22: Inspection for Sampling, Testing and Placement of Bituminous Base Course Station 0+010 to 0+025 at Local Road # 13 Zone A. | F22: 46301 | H22: Accepted
C23: 12 | D23: KHJ1-02-007-MAH-TS9-1-ROD-FIR-0943 | E23: Inspection for Sampling, Testing and Placement of Bituminous Base Course Station 0+010 to 0+025 at Local Road # 14 Zone A. | F23: 46301 | H23: Accepted
... C93: 1 | D93: KHJ1-02-007-MAH-TS9-1-ROD-FIR-0957 | E93: Inspection for Placement, Location, level and Compaction of Aggregate Base Course(200mm) (A-1-a) from Station 0+010 to 0+075 at Local Road # 09 Zone A. | F93: 46303 | H93: Revised & Resubmit
C94: 3. Concrete Box Culvet (CBC)
C95: 1 | D95: KHJ1-02-007-MAH-TS9-1-CBC-FIR-0127 | E95: Inspection of Reinforcement for Base and Apron Slab Cast-in-Situ Part for Up stream and Down Stream at Culvert # 07 Local Road-24 Zone B. | F95: 46299 | H95: Accepted
C96: 2 | D96: KHJ1-02-007-MAH-TS9-1-CBC-FIR-0129 | E96: Inspection for Formwork and Concrete Pouring for Head Beam Cast-in-Situ Part for Up stream and Down Stream at Culvert # 04 Local Road-22 Zone B. | F96: 46300 | H96: Accepted
C98: 1 | D98: KHJ1-02-007-MAH-TS9-1-CBC-FIR-0128 | E98: Inspection for Formwork and Concrete Pouring for Top Slab and Vertical Walls Cast-in-Situ Part for Up stream and Down Stream at Culvert # 04 Local Road-22 Zone B. | F98: 46300 | H98: Accepted as Noted
C99: 2 | D99: KHJ1-02-007-MAH-TS9-1-CBC-FIR-0130 | E99: Inspection for Formwork and Concrete Pouring for Base and Apron Slab Cast-in-Situ Part for Up stream and Down Stream at Culvert # 05 Local Road-23 Zone B. | F99: 46300 | H99: Accepted as Noted
C100: 4.Mechanical(MEC)
C101: No FIR Submitted in Mechanical Decipline.
C102: 5.Sewer (SEW)
C103: 1 | D103: KHJ1-02-007-MAH-TS9-1-SEW-FIR-1634 | E103: Inspection for Excavation, Location, level and Compaction and Blinding Concrete Pouring for Sewer MH-2.32 at local road # 03 Zone-A. | F103: 46302 | H103: Accepted as Noted
C104: 2 | D104: KHJ1-02-007-MAH-TS9-1-SEW-FIR-1635 | E104: Inspection for Excavation, Location, level and Compaction and Blinding Concrete Pouring for Sewer MH-2.33 at local road # 03 Zone-A. | F104: 46302 | H104: Accepted as Noted
C105: 3 | D105: KHJ1-02-007-MAH-TS9-1-SEW-FIR-1636 | E105: Inspection for Excavation, Location, level and Compaction and Blinding Concrete Pouring for Sewer MH-2.31.1 at local road # 03 Zone-A. | F105: 46302 | H105: Accepted as Noted
C106: 4 | D106: KHJ1-02-007-MAH-TS9-1-SEW-FIR-1646 | E106: Sand Bedding and Installation of GRP Pipe (Dia200mm) ofSewer LinefromManhole MH-11to MH-12at localRoad #01inLabor Camp. | F106: 46302 | H106: Accepted as Noted
C107: 5 | D107: KHJ1-02-007-MAH-TS9-1-SEW-FIR-1649 | E107: Inspection for Excavation, Location, level and Compaction and Blinding Concrete Pouring for Sewer MH-2.29 at local road # 03 Zone-A. | F107: 46302 | H107: Accepted as Noted
C108: 6 | D108: KHJ1-02-007-MAH-TS9-1-SEW-FIR-1650 | E108: Inspection for Excavation, Location, level and Compaction and Blinding Concrete Pouring for Sewer MH-2.29.1 at local road # 03 Zone-A. | F108: 46302 | H108: Accepted as Noted
C109: 7 | D109: KHJ1-02-007-MAH-TS9-1-SEW-FIR-1651 | E109: Inspection for Excavation, Location, level and Compaction and Blinding Concrete Pouring for Sewer MH-2.30 at local road # 03 Zone-A. | F109: 46302 | H109: Accepted as Noted
C110: 8 | D110: KHJ1-02-007-MAH-TS9-1-SEW-FIR-1652 | E110: Inspection for Excavation, Location, level and Compaction and Blinding Concrete Pouring for Sewer MH-2.30.1 at local road # 03 Zone-A. | F110: 46302 | H110: Accepted as Noted
C111: 9 | D111: KHJ1-02-007-MAH-TS9-1-SEW-FIR-1653 | E111: Inspection for Blinding Concrete Pouring of Sewer MH-1 at labor camp road # 01 Zone A. | F111: 46302 | H111: Accepted as Noted
C112: 10 | D112: KHJ1-02-007-MAH-TS9-1-SEW-FIR-1654 | E112: Inspection for Blinding Concrete Pouring of Sewer MH-1-1, MH-1-2 & MH-1-3 at labor camp road # 01 Zone A. | F112: 46302 | H112: Accepted as Noted
C113: 11 | D113: KHJ1-02-007-MAH-TS9-1-SEW-FIR-1655 | E113: Inspection for Blinding Concrete Pouring of Sewer MH-1-4 & MH-1-5 at labor camp road # 01 Zone A. | F113: 46302 | H113: Accepted as Noted
C114: 12 | D114: KHJ1-02-007-MAH-TS9-1-SEW-FIR-1656 | E114: Inspection for Blinding Concrete Pouring of Sewer MH-1-6, MH-1-7 & MH-1-8 at labor camp road # 01 Zone A. | F114: 46302 | H114: Accepted as Noted
... C174: 4 | D174: KHJ1-02-007-MAH-TS9-1-SEW-FIR-1646 | E174: Leak Test of of GRP pipe (Dia 200mm) Sewer line 2.8 from MH-2.8.1 to MH-2.8 at local road # 06 Zone A | F174: 46305 | H174: UR-Under Review
C175: 6.Storm (STR)
C176: 1 | D176: KHJ1-02-007-MAH-TS9-1-STR-FIR-2538 | E176: Inspection for Excavation, Location, level & Blinding Concrete Pouring of Storm MH-32(A)_26 at Local Road # 03 Zone A. | F176: 46300 | H176: Accepted as Noted
C177: 2 | D177: KHJ1-02-007-MAH-TS9-1-STR-FIR-2545 | E177: Inspection for Excavation, Location, level & Blinding Concrete Pouring of Storm MH-32(A)_27 at Local Road # 03 Zone A. | F177: 46300 | H177: Accepted as Noted
C178: 3 | D178: KHJ1-02-007-MAH-TS9-1-STR-FIR-2548 | E178: Inspection for Excavation, Location, level & Blinding Concrete Pouring of Storm Catch Basin MH-32(A)_26-SCB-2 at Local Road # 03 Zone A. | F178: 46300 | H178: Accepted as Noted
C179: 4 | D179: KHJ1-02-007-MAH-TS9-1-STR-FIR-2549 | E179: Inspection for Excavation, Location, level & Blinding Concrete Pouring of Storm Catch Basin MH-32(A)_26-SCB-3 at Local Road # 03 Zone A. | F179: 46300 | H179: Accepted as Noted
C180: 5 | D180: KHJ1-02-007-MAH-TS9-1-STR-FIR-2550 | E180: Inspection for Excavation, level & Blinding Concrete Pouring of Storm Catch Basin MH-32(A)_26-DCB-1 at Local Road # 03 Zone A. | F180: 46300 | H180: Accepted as Noted
C181: 6 | D181: KHJ1-02-007-MAH-TS9-1-STR-FIR-2564 | E181: Excavation, Sand Bedding and Installation of GRP Pipe (Dia 400mm) of Storm Line from Manhole MH-5(L) to MH-O(L) at Collector Road #02 in Zone B | F181: 46300 | H181: Accepted as Noted
C182: 7 | D182: KHJ1-02-007-MAH-TS9-1-STR-FIR-2565 | E182: Inspection of Storm line Sand Backfill around & above of Storm Pipe to Bottom of Sub Grade & Laying of Warning Tape from MH-32(A)_16_5 to MH-32(A)_16_4 at Local Road # 4 Zone A. | F182: 46299 | H182: Accepted as Noted
C183: 8 | D183: KHJ1-02-007-MAH-TS9-1-STR-FIR-2566 | E183: Inspection of Storm line Sand Backfill around & above of Storm Pipe to Bottom of Sub Grade & Laying of Warning Tape from MH-32(A)_16_4 to MH-32(A)_16_3 at Local Road # 4 Zone A. | F183: 46299 | H183: Accepted as Noted
C184: 9 | D184: KHJ1-02-007-MAH-TS9-1-STR-FIR-2568 | E184: Inspection of Storm line Sand Backfill around & above of Storm Pipe to Bottom of Sub Grade & Laying of Warning Tape from MH-32(A)_16_1-SCB-1 to MH-32(A)_16_1 at Local Road # 4 Zone A. | F184: 46299 | H184: Accepted as Noted
C185: 10 | D185: KHJ1-02-007-MAH-TS9-1-STR-FIR-2570 | E185: Inspection of Storm line Sand Backfill around & above of Storm Pipe to Bottom of Sub Grade & Laying of Warning Tape from MH-32(A)_16_1-SCB-1 to MH-32(A)_16_1-DCB-2 at Local Road # 4 Zone A. | F185: 46299 | H185: Accepted as Noted
C186: 11 | D186: KHJ1-02-007-MAH-TS9-1-STR-FIR-2571 | E186: Inspection of Storm line Sand Backfill around & above of Storm Pipe to Bottom of Sub Grade & Laying of Warning Tape from MH-32(A)_16_3-SCB-4 to MH-32(A)_16_3-SCB-3 at Local Road #4 Zone A. | F186: 46299 | H186: Accepted as Noted
C187: 12 | D187: KHJ1-02-007-MAH-TS9-1-STR-FIR-2572 | E187: Inspection of Storm line Sand Backfill around & above of Storm Pipe to Bottom of Sub Grade & Laying of Warning Tape from MH-32(A)_16-SCB-5 to MH-32(A)_16-SCB-4 at Local Road # 4 Zone A. | F187: 46299 | H187: Accepted as Noted
... C221: 1 | D221: KHJ1-02-007-MAH-TS9-1-STR-FIR-2536 | E221: Inspection of Secondary line Sand Backfill around & above of Secondary Pipe to Bottom of Sub Grade layer and Laying of Warning Tape from MH-32(A)_14 MH-32(A)_13 at Collector Road # 01 Zone A. | F221: 46305 | H221: UR-Under Review
C222: 7.Electrical(ELE)
C223: 1 | D223: KHJ1-02-007-MAH-TS9-1-ELE-FIR-0198 | E223: Inspection for Excavation, Installation of Sleeve 2x110mm UPVC & Formwork and Concrete Pouring of Street Light Duct Bank at Station (RD-11 St. 0+035) Local Road # 11 Zone A. | F223: 46305 | H223: Accepted
C224: 2 | D224: KHJ1-02-007-MAH-TS9-1-ELE-FIR-0210 | E224: Installation of 120 mm² Bare Copper Ground Wire Around Mosque Building for Grounding System as per Attached Highlighted Drawing (Mosque Area) | F224: 46303 | H224: Accepted
C225: 3 | D225: KHJ1-02-007-MAH-TS9-1-ELE-FIR-0211 | E225: Excavation,Installation of Sleeve, Formwork and Concrete Pouring of Street Light Duct Bank Crossing at Station (CL-RD-02 St.2+225) Collector Road # 02 Zone B. | F225: 46301 | H225: Accepted
C226: 4 | D226: KHJ1-02-007-MAH-TS9-1-ELE-FIR-0212 | E226: Installation of 70 mm² Bare Copper Conductor for Lightning Protection System in Mosque Building as per Attached Highlighted Drawing (Mosque Area) | F226: 46303 | H226: Accepted
C227: 5 | D227: KHJ1-02-007-MAH-TS9-1-ELE-FIR-0213 | E227: Installation of Grounding Rods (2.4 m) around Mosque Building for Grounding & Lightning Protection System as per Attached Highlighted Drawing (Mosque Area) | F227: 46303 | H227: Accepted
C228: 6 | D228: KHJ1-02-007-MAH-TS9-1-ELE-FIR-0214 | E228: Exothermic Connection of Bare Copper Conductors (120mm2 & 70 mm2) for Grounding & Lightning Protection System as per Attached Highlighted Drawing (Mosque Area) | F228: 46303 | H228: Accepted
C229: 7 | D229: KHJ1-02-007-MAH-TS9-1-ELE-FIR-0215 | E229: Bonding Connection of 120 mm² & 70 mm² Bare Copper Conductors to Grounding Rods through Clamps for Grounding and Lightning Protection System around Mosque Building, as per Attached Highlighted Drawing (Mosque Area) | F229: 46303
C231: 1 | D231: KHJ1-02-007-MAH-TS9-1-ELE-FIR-0193 | E231: Inspection for Excavation, Installation of Sleeve 2x110mm UPVC Formwork and Concrete Pouring of Street Light Duct Bank at ation (RD-03 St. 0-674) Local Road # 03 Zone A. | F231: 46299 | H231: Accepted as Noted
C232: 2 | D232: KHJ1-02-007-MAH-TS9-1-ELE-FIR-0194 | E232: Inspection for Excavation, Installation of Sleeve 2x110mm UPVC & Formwork and Concrete Pouring of Street Light Duct Bank at Station (RD-03 St. 0+489) Local Road # 03 Zone A. | F232: 46299 | H232: Accepted as Noted
C233: 3 | D233: KHJ1-02-007-MAH-TS9-1-ELE-FIR-0199 | E233: Sand Backfill up to Bottom of Sub Grade and Laying of warning tape for Street Lighting Duct bank crossing at station (RD-04 STA. 0+048) at Local Road # 04 Zone A | F233: 46299 | H233: Accepted as Noted
C234: 4 | D234: KHJ1-02-007-MAH-TS9-1-ELE-FIR-0200 | E234: Sand Backfill up to Bottom of Sub Grade and Laying of warning tape for Street Lighting Duct bank crossing at station (RD-27 STA. 0+098) at Local Road # 27 Zone B | F234: 46299 | H234: Accepted as Noted
C235: 5 | D235: KHJ1-02-007-MAH-TS9-1-ELE-FIR-0204 | E235: Sand Backfill up to Bottom of Sub Grade and Laying of warning tape for Street Lighting Duct bank crossing at station (CL-RD-02 STA. 0+040) at Collector Road # 02 Zone B | F235: 46299 | H235: Accepted as Noted
C236: 6 | D236: KHJ1-02-007-MAH-TS9-1-ELE-FIR-0205 | E236: Sand Backfill up to Bottom of Sub Grade and Laying of warning tape for Street Lighting Duct bank crossing at station (CL-RD-02 STA. 0+050) at Collector Road # 02 Zone B | F236: 46299 | H236: Accepted as Noted
C237: 7 | D237: KHJ1-02-007-MAH-TS9-1-ELE-FIR-0206 | E237: Sand Backfill up to Bottom of Sub Grade and Laying of warning tape for Street Lighting Duct bank crossing at station (RD-07 STA. 0+020) at Local Road # 07 Zone A | F237: 46299 | H237: Accepted as Noted
C238: 8 | D238: KHJ1-02-007-MAH-TS9-1-ELE-FIR-0207 | E238: Sand Backfill up to Bottom of Sub Grade and Laying of warning tape for Street Lighting Duct bank crossing at station (RD-07 STA. 0+280) at Local Road # 07 Zone A | F238: 46299 | H238: Accepted as Noted
C239: 9 | D239: KHJ1-02-007-MAH-TS9-1-ELE-FIR-0208 | E239: Sand Backfill up to Bottom of Sub Grade and Laying of warning tape for Street Lighting Duct bank crossing at station (CL-RD-02 STA. 2+500) at Collector Road # 02 Zone B | F239: 46299 | H239: Accepted as Noted
C240: 10 | D240: KHJ1-02-007-MAH-TS9-1-ELE-FIR-0209 | E240: Sand Backfill up to Bottom of Sub Grade and Laying of warning tape for Street Lighting Duct bank crossing at station (CL-RD-02 STA. 2+540) at Collector Road # 02 Zone B | F240: 46299 | H240: Accepted as Noted
C241: 11 | D241: KHJ1-02-007-MAH-TS9-1-ELE-FIR-0218 | E241: Sand Backfill up to Bottom of Sub Grade and Laying of warning tape for Street Lighting Duct bank crossing at station (RD-08 STA. 0+020) at Local Road # 08 Zone A | F241: 46303 | H241: Accepted as Noted
C242: 12 | D242: KHJ1-02-007-MAH-TS9-1-ELE-FIR-0219 | E242: Sand Backfill up to Bottom of Sub Grade and Laying of warning tape for Street Lighting Duct bank crossing at station (RD-08 STA. 0+050) at Local Road # 08 Zone A | F242: 46303 | H242: Accepted as Noted
C244: 1 | D244: KHJ1-02-007-MAH-TS9-1-ELE-FIR-0216 | E244: Inspection for Excavation, Location, level, Installation & backfill of Street Lights Pole Foundations from (SLP-6/1/13/R - 6/2/12/B) (09 No's) at Local Road # 13 Zone A | F244: 46303 | H244: C-Revised & Resubmit
C245: 8.TELECOM(TEL)
C246: 1 | D246: KHJ1-02-007-MAH-TS9-1-TEL-FIR-0112 | E246: Inspection for Excavation, Installation of 6x50mm HDPE Sleeve & Formwork and Concrete Pouring of Telecom Network Duct TE-DB 6X50 Crossing at Station (RD-10 STA. 0+069) Local Road # 10 Zone A. | F246: 46300 | H246: Accepted
C247: 2 | D247: KHJ1-02-007-MAH-TS9-1-TEL-FIR-0119 | E247: Inspection for Excavation, Installation of 6x50mm HDPE Sleeve & Formwork and Concrete Pouring of Telecom Network Duct TE-DB 6X50 Crossing at Station (RD-02 STA. 0+245) Local Road # 02 Zone A. | F247: 46303 | H247: Accepted
C248: 3 | D248: KHJ1-02-007-MAH-TS9-1-TEL-FIR-0120 | E248: Excavation,Installation of Sleeve 6x50 HDPE,Formwork and Concrete Pouring of Telecom Duct Bank Crossing at Station (St.1+050) Collector Road # 02 Zone B. | F248: 46301 | H248: Accepted
C250: 1 | D250: KHJ1-02-007-MAH-TS9-1-TEL-FIR-0113 | E250: Inspection for Excavation, Installation of 6x50mm HDPE Sleeve & Formwork and Concrete Pouring of Telecom Network Duct TE-DB 6X50 Crossing at Station (RD-07 STA. 0+610) Local Road # 07 Zone A. | F250: 46300 | H250: Approved as Noted
C251: 2 | D251: KHJ1-02-007-MAH-TS9-1-TEL-FIR-0117 | E251: Laying of Warning Tape and Sand Backfilling up to Bottom of Sub Grade for Telecom Duct bank crossing at station (RD-07 STA. 0+120) at Local Road # 07 Zone A | F251: 46299 | H251: Approved as Noted
C252: 3 | D252: KHJ1-02-007-MAH-TS9-1-TEL-FIR-0118 | E252: Laying of Warning Tape and Sand Backfilling up to Bottom of Sub Grade for Telecom Duct bank crossing at station (RD-10 STA. 0+069) at Local Road # 10 Zone A | F252: 46299 | H252: Approved as Noted
C253: 4 | D253: KHJ1-02-007-MAH-TS9-1-TEL-FIR-0121 | E253: Excavation,Installation of Sleeve 6x50 HDPE,Formwork and Concrete Pouring of Telecom Duct Bank Crossing at Station (St.1+085) Collector Road # 02 Zone B. | F253: 46301 | H253: Approved as Noted
C254: 5 | D254: KHJ1-02-007-MAH-TS9-1-TEL-FIR-0122 | E254: Inspection for Excavation, Installation of 6x50mm HDPE Sleeve & Formwork and Concrete Pouring of Telecom Network Duct TE-DB 6X50 Crossing at Station (RD-03 STA. 1+004) Local Road # 03 Zone A. | F254: 46303 | H254: Approved as Noted
C255: 6 | D255: KHJ1-02-007-MAH-TS9-1-TEL-FIR-0123 | E255: Inspection for Excavation, Installation of 6x50mm HDPE Sleeve & Formwork and Concrete Pouring of Telecom Network Duct TE-DB 6X50 Crossing at Station (RD-01 STA. 0+245) Local Road # 01 Zone A | F255: 46303 | H255: Approved as Noted
C256: 7 | D256: KHJ1-02-007-MAH-TS9-1-TEL-FIR-0124 | E256: Sand Backfilling up to Bottom of Sub Grade and Laying of Warning Tape for Telecom Duct bank crossing at station (RD-08 STA. 0+060) at Local Road # 08 Zone A | F256: 46303 | H256: Approved as Noted
C258: 1 | D258: KHJ1-02-007-MAH-TS9-1-TEL-FIR-0115 | E258: Inspection for Excavation, Installation of 6x50mm HDPE Sleeve & Formwork and Concrete Pouring of Telecom Network Duct TE-DB 6X50 Crossing at Station (RD-03 STA. 0+787) Local Road # 03 Zone A. | F258: 46300 | H258: Revised & Resubmit
C259: 9.Irrigation (IRR)
C260: 1 | D260: KHJ1-02-007-MAH-TS9-1-IRR-FIR-0318 | E260: Inspection for Reinforcement of Chamber Walls - TSE Network Washout Chamber (B-9) at Station (0+937) Arterial Road # 01 Zone B. | F260: 46298 | H260: Accepted
C261: 2 | D261: KHJ1-02-007-MAH-TS9-1-IRR-FIR-0319 | E261: Inspection for Formwork and Concrete of Chamber Walls - TSE Network Washout Chamber (B-9) at Station (0+937) Arterial Road # 01 Zone B. | F261: 46298 | H261: Accepted
C263: 1 | D263: KHJ1-02-007-MAH-TS9-1-IRR-FIR-0309 | E263: Inspection of Sand Backfill around & above to Bottom of Sub Grade layer of HDPE Pipe (Dia 110mm) of TSE Irrigation line 22 from Station 0+050 to 0+450 at local road # 19 in Zone B | F263: 46292 | H263: Accepted as Noted
C264: 2 | D264: KHJ1-02-007-MAH-TS9-1-IRR-FIR-0310 | E264: Inspection of Sand Backfill around & above to Bottom of Sub Grade layer of HDPE Pipe (Dia 110mm) of Irrigation TSE Line-21 From Station 0+100 to 0+225 at local Road # 18 in Zone B | F264: 46292 | H264: Accepted as Noted
C265: 3 | D265: KHJ1-02-007-MAH-TS9-1-IRR-FIR-0311 | E265: Excavation, Sand Bedding and Installation of HDPE Pipe (Dia 160mm) of TSE Irrigation Crossing at BGV-B-46 station 1+555 at local road # 26 in Zone B | F265: 46293 | H265: Accepted as Noted
C266: 4 | D266: KHJ1-02-007-MAH-TS9-1-IRR-FIR-0312 | E266: Excavation, Sand Bedding and Installation of HDPE Pipe (Dia 160mm) of TSE Irrigation Line 29 from station 0+250 to 0+525 at local road # 26 in Zone B | F266: 46293 | H266: Accepted as Noted
C267: 5 | D267: KHJ1-02-007-MAH-TS9-1-IRR-FIR-0314 | E267: Inspection of Sand Backfill around & above of Potable Pipe to Bottom of Sub Grade & Laying of Warning Tape at HDPE pipe (Dia 110mm) TSE network crossing TSE-110-LINE- 2 TO BGV-90 at road # 3 Zone A | F267: 46292 | H267: Accepted as Noted
C268: 6 | D268: KHJ1-02-007-MAH-TS9-1-IRR-FIR-0317 | F268: 46298 | H268: Accepted as Noted
C269: 7 | D269: KHJ1-02-007-MAH-TS9-1-IRR-FIR-0320 | E269: Excavation, Sand bedding and Installation of HDPE pipe (Dia 110mm) TSE-110 Line-13 0+000 TO 0+025 crossing at Road #03 Zone A. | F269: 46294 | H269: Accepted as Noted
C270: 8 | D270: KHJ1-02-007-MAH-TS9-1-IRR-FIR-0321 | E270: Excavation, Sand bedding and Installation of HDPE pipe (Dia 110mm) TSE-110 Line-14 0+635 TO 0+660 crossing at Road #03 Zone A. | F270: 46294 | H270: Accepted as Noted
C271: 9 | D271: KHJ1-02-007-MAH-TS9-1-IRR-FIR-0322 | E271: Excavation, Sand bedding and Installation of HDPE pipe (Dia 110mm) TSE-110 Line-11 0+620 TO 0+645 crossing at Road #03 Zone A. | F271: 46294 | H271: Accepted as Noted
...

Sheet Procurement
C2: حالة المشتريات الرئيسية - مشروع الخرج
C3: اسم المشروع | D3: Parent Project ID | E3: القطاع | F3: مواد التوريدات | G3: المورد | H3: رقم التواصل مع المورد | I3: الموقف الحالي | J3: تاريخ بدء التوريد المجدول | K3: اجتماعات الموردين | L3: خارجي/ داخلي | M3: نسبة التوريد المحلي % | N3: نسبة التوريد الخارجي % | O3: اجمالي الكمية | P3: الكمية التي تم توريدها | Q3: وحدة القياس | R3: ملاحظات (حالة المادة - عوائق - تأخير - ظروف خارجية, التأخر بالدفع من المقاول أو المورد)
C4: DEVELOPMENT OF INFRASTRUCTURE NETWORKS, AL KHARJ INDUSTRIAL CITY | D4: KHJ1-02-007 | E4: مدن - الرياض | F4: Curb stone | G4: Sail Alreyadha Saudi Industrial Co (SIEFCO) | H4: Mr. MUSTAFA KADRI | I4: تحت التوريد | J4: يونيو 2026 | K4: تم الانتهاء | L4: داخلي | M4: 1 | N4: 0 | O4: 155879 | P4: 36336 | Q4: LM | R4: تم اعتماد العينة - التوريد جارى طبقا لاحتياجات الموقع | U4: داخلي
C5: DEVELOPMENT OF INFRASTRUCTURE NETWORKS, AL KHARJ INDUSTRIAL CITY | D5: KHJ1-02-007 | E5: مدن - الرياض | F5: Interlock | G5: Sail Alreyadha Saudi Industrial Co (SIEFCO) | H5: Mr. MUSTAFA KADRI | I5: تحت التوريد | J5: يونيو 2026 | K5: تم الانتهاء | L5: داخلي | M5: 1 | N5: 0 | O5: 129381 | P5: 0 | Q5: LM | R5: لم يتم اعتماد العينة - التوريد متوقف لحين الاعتماد
C6: DEVELOPMENT OF INFRASTRUCTURE NETWORKS, AL KHARJ INDUSTRIAL CITY | D6: KHJ1-02-007 | E6: مدن - الرياض | F6: Traffic signage | G6: Agyad Sign | H6: Mr. Amar Ashri | I6: تحت التوريد | J6: ابريل 2026 | K6: تم الانتهاء | L6: داخلي | M6: 1 | N6: 0 | O6: 981 | P6: 981 | Q6: NOS | R6: تم الانتهاء | U6: لم يقدم للإعتماد
C7: DEVELOPMENT OF INFRASTRUCTURE NETWORKS, AL KHARJ INDUSTRIAL CITY | D7: KHJ1-02-007 | E7: مدن - الرياض | F7: Manhole ( Storm) | G7: AL-BILAD CONCRETE PIPES CO. | H7: Mr. Mahmoud Attia | I7: تحت التوريد | J7: ابريل 2026 | K7: تم الانتهاء | L7: داخلي | M7: 1 | N7: 0 | O7: 300 | P7: 256 | Q7: NOS | R7: تم اعتماد العينة - الانتهاء فى التوريد اخر 20 oct | U7: جاري الإعتماد
C8: DEVELOPMENT OF INFRASTRUCTURE NETWORKS, AL KHARJ INDUSTRIAL CITY | D8: KHJ1-02-007 | E8: مدن - الرياض | F8: Manhole ( Sewage) | G8: T. Nagadi Preformed Concrete Factory | H8: Mr. Ahmed Eldeeb | I8: تحت التوريد | J8: ابريل 2026 | K8: تم الانتهاء | L8: داخلي | M8: 1 | N8: 0 | O8: 346 | P8: 340 | Q8: NOS | R8: تم اعتماد العينة - الانتهاء من التوريد 20 oct | U8: تم الإعتماد
C9: DEVELOPMENT OF INFRASTRUCTURE NETWORKS, AL KHARJ INDUSTRIAL CITY | D9: KHJ1-02-007 | E9: مدن - الرياض | F9: DI Cover & FRAME (Sewage & Storm&ICT CATCH BASIN ) | G9: UKC | H9: Mr. Mohammad Hany | I9: تحت التوريد | J9: ابريل 2026 | K9: تم الانتهاء | L9: داخلي | M9: 1 | N9: 0 | O9: 1768 | P9: 1205 | Q9: NOS | R9: تم اعتماد العينة - الانتهاء من التوريد 20 oct | U9: تم اصدار امر الشراء ولم يتم الدفع
C10: DEVELOPMENT OF INFRASTRUCTURE NETWORKS, AL KHARJ INDUSTRIAL CITY | D10: KHJ1-02-007 | E10: مدن - الرياض | F10: Concrete catch basin | G10: Kaayan advanced construction | H10: Mr. M salah | I10: تحت التوريد | J10: ابريل 2026 | K10: تم الانتهاء | L10: داخلي | M10: 1 | N10: 0 | O10: 666 | P10: 666 | Q10: NOS | R10: تم الانتهاء | U10: جاري التصنيع
C11: DEVELOPMENT OF INFRASTRUCTURE NETWORKS, AL KHARJ INDUSTRIAL CITY | D11: KHJ1-02-007 | E11: مدن - الرياض | F11: Precast Concrete Box Culverts/Conduits including the wing walls | G11: T. Nagadi Preformed Concrete Factory | H11: Mr. Ahmed Eldeeb | I11: تحت التوريد | J11: مارس 2026 | K11: تم الانتهاء | L11: داخلي | M11: 1 | N11: 0 | O11: 2914 | P11: 2570 | Q11: LM | R11: تم اعتماد العينة - الانتهاء فى التوريد اخر 20 Oct | U11: جاري التوريد
C12: DEVELOPMENT OF INFRASTRUCTURE NETWORKS, AL KHARJ INDUSTRIAL CITY | D12: KHJ1-02-007 | E12: مدن - الرياض | F12: Manhole (ICT) | G12: AL-BILAD CONCRETE PIPES CO. | H12: Mr. Mahmoud Attia | I12: تحت التوريد | J12: سبتمبر 2026 | K12: تم الانتهاء | L12: داخلي | M12: 1 | N12: 0 | O12: 214 | P12: 0 | Q12: NOS | R12: تم اعتماد العينة - جارى انتاج المواد - الانتهاء من التوريد 20 Nov | U12: تم التوريد
C13: DEVELOPMENT OF INFRASTRUCTURE NETWORKS, AL KHARJ INDUSTRIAL CITY | D13: KHJ1-02-007 | E13: مدن - الرياض | F13: Low Voltage Cables, Copper & Aluminium, | G13: Elsewedy | H13: Mr. Abdullah | I13: تحت التوريد | J13: يونيو 2026 | K13: تم الانتهاء | L13: داخلي | M13: 1 | N13: 0 | O13: 114893 | P13: 97030 | Q13: LM | R13: تم اعتماد العينة - جارى انتاج المواد - الانتهاء من التوريد 20 Nov
C14: DEVELOPMENT OF INFRASTRUCTURE NETWORKS, AL KHARJ INDUSTRIAL CITY | D14: KHJ1-02-007 | E14: مدن - الرياض | F14: MV cable, waiting for SEC to wave off FAT test to start delivery | H14: +966 53 484 9346 | J14: يونيو 2026 | K14: تم الانتهاء | L14: داخلي | M14: 1 | N14: 0 | O14: 72 | P14: 61 | Q14: Km | R14: تم اعتماد العينة - الانتهاء من التوريد اخر 20 Oct
C15: DEVELOPMENT OF INFRASTRUCTURE NETWORKS, AL KHARJ INDUSTRIAL CITY | D15: KHJ1-02-007 | E15: مدن - الرياض | F15: Ring Main unit-RMU | G15: Al Fanar | H15: Mr. Fahmi Zaitoon | I15: تم الانتهاء | J15: تم الانتهاء | K15: تم الانتهاء | L15: داخلي | M15: 1 | N15: 0 | O15: 5 | P15: 5 | Q15: NOS | R15: تم الانتهاء | U15: LM
C16: DEVELOPMENT OF INFRASTRUCTURE NETWORKS, AL KHARJ INDUSTRIAL CITY | D16: KHJ1-02-007 | E16: مدن - الرياض | F16: Unit Substation 13.8/0.4 kv , | H16: +966 56 596 1202 | I16: تم الانتهاء | J16: تم الانتهاء | K16: تم الانتهاء | L16: داخلي | M16: 1 | N16: 0 | O16: 5 | P16: 5 | Q16: NOS | R16: تم الانتهاء | U16: m2
C17: DEVELOPMENT OF INFRASTRUCTURE NETWORKS, AL KHARJ INDUSTRIAL CITY | D17: KHJ1-02-007 | E17: مدن - الرياض | F17: Street Lighting poles & Fixtures | G17: Al-Babtain Power & Telecom | H17: Mr. Reda Hegazy | I17: تحت التوريد | J17: يونيو 2026 | K17: تم الانتهاء | L17: داخلي | M17: 1 | N17: 0 | O17: 981 | P17: 863 | Q17: NOS | R17: تم اعتماد العينة - الانتهاء من التوريد اخر 20 Oct | U17: m3
C18: DEVELOPMENT OF INFRASTRUCTURE NETWORKS, AL KHARJ INDUSTRIAL CITY | D18: KHJ1-02-007 | E18: مدن - الرياض | H18: +966 58 128 6668 | O18: 1152 | P18: 970 | Q18: NOS | U18: NOS
C19: DEVELOPMENT OF INFRASTRUCTURE NETWORKS, AL KHARJ INDUSTRIAL CITY | D19: KHJ1-02-007 | E19: مدن - الرياض | F19: UPVC Pipes & Fittings | G19: National Kham Plastic Factory Co. | H19: Mr. M Rabie Elsaady | I19: تم الانتهاء | J19: تم الانتهاء | K19: تم الانتهاء | L19: داخلي | M19: 1 | N19: 0 | O19: 1026 | P19: 1026 | Q19: LM | R19: تم الانتهاء
C20: DEVELOPMENT OF INFRASTRUCTURE NETWORKS, AL KHARJ INDUSTRIAL CITY | D20: KHJ1-02-007 | E20: مدن - الرياض | F20: HDPE duct pipe | G20: UNION PIPES INDUSTRY CO. LTD | H20: Mr. Islam Ezzeldin | I20: تم الانتهاء | J20: تم الانتهاء | K20: تم الانتهاء | L20: داخلي | M20: 1 | N20: 0 | O20: 291380 | P20: 291380 | Q20: LM | R20: تم الانتهاء | U20: Km
C21: DEVELOPMENT OF INFRASTRUCTURE NETWORKS, AL KHARJ INDUSTRIAL CITY | D21: KHJ1-02-007 | E21: مدن - الرياض | F21: HDPE Pipe & Fittings | I21: تم الانتهاء | J21: تم الانتهاء | K21: تم الانتهاء | L21: داخلي | M21: 1 | N21: 0 | O21: 59088 | P21: 59088 | Q21: LM | R21: تم الانتهاء | U21: Ton
C22: DEVELOPMENT OF INFRASTRUCTURE NETWORKS, AL KHARJ INDUSTRIAL CITY | D22: KHJ1-02-007 | E22: مدن - الرياض | F22: potable Valve & accessories (Sluice) valves (Direct buried) | G22: AVK (Gaweea Global Trading Est.) | H22: Mr. Mohammad Sohail | I22: تحت التوريد | J22: يونيو 2026 | K22: تم الانتهاء | L22: داخلي | M22: 1 | N22: 0 | O22: 2723 | P22: 347 | Q22: EA | R22: تم اعتماد العينة - الانتهاء من ى التوريد ا 20 Oct
C23: DEVELOPMENT OF INFRASTRUCTURE NETWORKS, AL KHARJ INDUSTRIAL CITY | D23: KHJ1-02-007 | E23: مدن - الرياض | F23: Fire hydrant , Valve & Accessories | H23: +966 54 320 2000 | I23: تحت التوريد | J23: يونيو 2026 | K23: تم الانتهاء | L23: داخلي | M23: 1 | N23: 0 | O23: 310 | P23: 217 | Q23: EA | U23: set
C24: DEVELOPMENT OF INFRASTRUCTURE NETWORKS, AL KHARJ INDUSTRIAL CITY | D24: KHJ1-02-007 | E24: مدن - الرياض | F24: GRP Pipes & Fittings | G24: T. Nagadi Fiberglass Pipes Factory | H24: Mr. Ahmed Eldeeb | I24: تحت التوريد | J24: فبراير 2026 | K24: تم الانتهاء | L24: داخلي | M24: 1 | N24: 0 | O24: 49458 | P24: 48676 | Q24: LM | R24: تم اعتماد العينة - الانتهاء فى التوريد اخر 20 Oct
C25: DEVELOPMENT OF INFRASTRUCTURE NETWORKS, AL KHARJ INDUSTRIAL CITY | D25: KHJ1-02-007 | E25: مدن - الرياض | F25: Secondary Irrigation | G25: Gulf Bazar | H25: "Mr. Youseff | I25: تحت التوريد | J25: يونيو 2026 | K25: تم الانتهاء | L25: داخلي | M25: 1 | N25: 0 | O25: 1 | P25: 0.3 | Q25: LOT | R25: تم اعتماد العينة - جارى توريد المواد
C26: DEVELOPMENT OF INFRASTRUCTURE NETWORKS, AL KHARJ INDUSTRIAL CITY | D26: KHJ1-02-007 | E26: مدن - الرياض | F26: Plantataion & Shurbs | H26: +966 54 337 2517" | I26: تحت التوريد | J26: اكتبر 2026 | K26: تم الانتهاء | L26: داخلي | M26: 1 | N26: 0 | O26: 30556 | P26: 0 | Q26: M2 | R26: فى انتظار الاتفاق على الكمية النهائية

Sheet Material Status
C3: Procurement- Material Status | X3: Date | Y3: =+'General Information'!E3 -> 46307
C5: # | D5: Material Description | E5: Material Category | F5: BOQ Number | G5: Unit | H5: Total Quantity | I5: Long Lead Item | J5: PR Status | L5: PO Status | N5: Delivery Time Frame | Q5: Delivery Status | S5: MRIR Status | V5: MIR Status | Y5: Comments
E6: Civil/Mech/Elec/Arch | I6: Short/Long | J6: 0/1 | K6: Date | L6: 0/1 | M6: Date | N6: Duration/Days | O6: Start Date | P6: End Date | Q6: Quantity | R6: % | S6: 0/1 | T6: MRIR no. | U6: Date | V6: Yes / No | W6: MIR no. | X6: Date
C7: 1 | D7: GRP Pipes | E7: Mechanical | F7: B3.33 14 13.01
C8: 1.1 | D8: 150mm Diameter - SEWER | E8: Mechanical | G8: m | H8: 4288 | L8: 1 | M8: 15/3/2026 | N8: 80 | O8: 15/3/2026 | P8: 30/08/2026 | Q8: 4059.35 | R8: =Q8/H8 -> 0.95 | S8: yes | T8: KHJ1-02-007-MAH-TS9-1-MEC-MRIR-0026& 48 | U8: 46062 | W8: KHJ1-02-007-MAH-TS9-1-STR-MIR-0048,KHJ1-02-007-MAH-TS9-1-STR-MIR-0047,KHJ1-02-007-MAH-TS9-1-MEC-MIR-0119
C9: 1.2 | D9: 200mm Diameter - SEWER | E9: Mechanical | G9: m | H9: 12884 | L9: 1 | M9: 15/3/2026 | N9: 80 | O9: 15/3/2026 | P9: 30/08/2026 | Q9: 11985 | R9: =Q9/H9 -> 0.93 | S9: yes | T9: KHJ1-02-007-MAH-TS9-1-MEC-MRIR-0006,KHJ1-02-007-МАН-TS9-1-MEC-MRIR-0068 | U9: 46062 | W9: KHJ1-02-007-MAH-TS9-1-STR-MIR-0047
C10: 1.3 | D10: 250mm Diameter - SEWER | E10: Mechanical | G10: m | H10: 2310 | L10: 1 | M10: 15/3/2026 | N10: 80 | O10: 15/3/2026 | P10: 46030 | Q10: 2310 | R10: =Q10/H10 -> 1 | S10: yes | T10: KHJ1-02-007-MAH-TS9-1-MEC-MRIR-0018,KHJ1-02-007-MAH-TS9-1-MEC-MRIR-0037 | U10: 46062 | W10: KHJ1-02-007-MAH-TS9-1-MEC-MIR-0005
C11: 1.4 | D11: 300mm Diameter - SEWER | E11: Mechanical | G11: m | H11: 2700 | L11: 1 | M11: 15/3/2026 | N11: 80 | O11: 15/3/2026 | P11: 46030 | Q11: 2700 | R11: =Q11/H11 -> 1 | S11: yes | T11: KHJ1-02-007-MAH-TS9-1-MEC-MRIR-0001 | U11: 46062 | W11: KHJ1-02-007-MAH-TS9-1-MEC-MIR-0005
C12: 1.5 | D12: 400mm Diameter -STORM & SEWER | E12: Mechanical | G12: m | H12: 14097 | L12: 1 | M12: 15/3/2026 | N12: 80 | O12: 15/3/2026 | P12: 30/08/2026 | Q12: 11696 | R12: =Q12/H12 -> 0.83 | S12: yes | T12: KHJ1-02-007-MAH-TS9-1-MEC-MRIR-0068 | U12: 46062 | W12: KHJ1-02-007-MAH-TS9-1-STR-MIR-0047,KHJ1-02-007-MAH-TS9-1-STR-MIR-0103,KHJ1-02-007-MAH-TS9-1-MEC-MIR-0119
C13: 1.6 | D13: 500mm Diameter -STORM & SEWER | E13: Mechanical | G13: m | H13: 2389 | L13: 1 | M13: 15/3/2026 | N13: 80 | O13: 15/3/2026 | P13: 46030 | Q13: 2388 | R13: =Q13/H13 -> 1 | S13: yes | T13: KHJ1-02-007-MAH-TS9-1-MEC-MRIR-0015 & 48,KHJ1-02-007-MAH-TS9-1-STR-MIR-0047 | U13: 46062 | W13: KHJ1-02-007-MAH-TS9-1-MEC-MIR-0005,KHJ1-02-007-MAH-TS9-1-STR-MIR-0103,KHJ1-02-007-MAH-TS9-1-MEC-MIR-0119
C14: 1.7 | D14: 600mm Diameter -STORM & SEWER | E14: Mechanical | G14: m | H14: 4370 | L14: 1 | M14: 15/3/2026 | N14: 80 | O14: 15/3/2026 | P14: 46030 | Q14: 4370 | R14: =Q14/H14 -> 1 | S14: yes | T14: KHJ1-02-007-MAH-TS9-1-MEC-MRIR-0017,KHJ1-02-007-MAH-TS9-1-MEC-MRIR-0019,KHJ1-02-007-MAH-TS9-1-MEC-MRIR-0021 | U14: 46062 | W14: KHJ1-02-007-МАН-TS9-1-MEC-MRIR-0068,KHJ1-02-007-MAH-TS9-1-STR-MIR-0047
C15: 1.8 | D15: 700mm Diameter -STORM | E15: Mechanical | G15: m | H15: 1245 | L15: 1 | M15: 15/3/2026 | N15: 80 | O15: 15/3/2026 | P15: 30/08/2026 | Q15: 1245 | R15: =Q15/H15 -> 1 | S15: yes | T15: KHJ1-02-007-MAH-TS9-1-MEC-MRIR-0037,KHJ1-02-007-МАН-TS9-1-MEC-MRIR-0068 | U15: 46062 | W15: kHJ1-02-007-MAH-TS9-1-STR-MIR-0047,KHJ1-02-007-MAH-TS9-1-STR-MIR-0103
C16: 1.9 | D16: 800mm Diameter -STORM | E16: Mechanical | G16: m | H16: 1850 | L16: 1 | M16: 15/3/2026 | N16: 80 | O16: 15/3/2026 | P16: 30/08/2026 | Q16: 1800 | R16: =Q16/H16 -> 0.97 | S16: yes | T16: KHJ1-02-007-MAH-TS9-1-MEC-MRIR-0068 | U16: 46062 | W16: KHJ1-02-007-MAH-TS9-1-STR-MIR-0047,KHJ1-02-007-MAH-TS9-1-STR-MIR-0103
C17: 1.1 | D17: 900mm Diameter -STORM | E17: Mechanical | G17: m | H17: 870 | L17: 1 | M17: 15/3/2026 | N17: 80 | O17: 15/3/2026 | P17: 30/08/2026 | Q17: 804 | R17: =Q17/H17 -> 0.92 | S17: yes | T17: KHJ1-02-007-МАН-TS9-1-MEC-MRIR-0098 | U17: 46062 | W17: KHJ1-02-007-MAH-TS9-1-STR-MIR-0103
C18: 1.11 | D18: 1000mm Diameter -STORM | E18: Mechanical | G18: m | H18: 765 | L18: 1 | M18: 15/3/2026 | N18: 80 | O18: 15/3/2026 | P18: 30/08/2026 | Q18: 720 | R18: =Q18/H18 -> 0.94 | S18: yes | T18: KHJ1-02-007-MAH-TS9-1-MEC-MRIR-0001 | U18: 46062
C19: 1.12 | D19: 1200mm Diameter -STORM | E19: Mechanical | G19: m | H19: 1690 | L19: 1 | M19: 15/3/2026 | N19: 80 | O19: 15/3/2026 | P19: 46030 | Q19: 1690 | R19: 1 | S19: yes | T19: KHJ1-02-007-MAH-TS9-1-MEC-MRIR-0001& 48,KHJ1-02-007-МАН-TS9-1-MEC-MRIR-0064 | U19: 46062 | W19: KHJ1-02-007-MAH-TS9-1-STR-MIR-0047,KHJ1-02-007-MAH-TS9-1-MEC-MIR-0119
C20: 2 | D20: HDPE Pipes | E20: Mechanical
C21: 2.1 | D21: 32mm Diameter | E21: Mechanical | G21: m | H21: 66692 | L21: 1 | M21: 46026 | N21: 80 days | O21: 18/3/2026 | P21: 46030 | Q21: 66692 | R21: 1 | S21: YES | T21: KHJ1-02-007-MAH-TS9-1-MEC-MRIR-0002 & 004 | U21: 07 Feb & 14 FEB
C22: 2.2 | D22: 50mm Diameter | E22: Mechanical | G22: m | H22: 224688 | L22: 1 | M22: 46026 | N22: 80 days | O22: 18/3/2026 | P22: 46030 | Q22: 224688 | R22: 1 | S22: YES | T22: KHJ1-02-007-MAH-TS9-1-MEC-MRIR-0002 & 004 | U22: 07 Feb & 14 FEB | W22: KHJ1-02-007-МАН-TS9-1-TEL-MRIR-0082
C23: 2.3 | D23: 75 mm Diameter | E23: Mechanical | G23: m | L23: 1 | M23: 46026 | N23: 80 days | O23: 18/3/2026 | P23: 30/6/2026 | Q23: - | R23: 0 | S23: YES | T23: KHJ1-02-007-MAH-TS9-1-MEC-MRIR-0002 & 004 | U23: 07 Feb & 14 FEB
C24: 2.4 | D24: 90mm Diameter | E24: Mechanical | G24: m | H24: 900 | L24: 1 | M24: 46026 | N24: 80 days | O24: 18/3/2026 | P24: 46030 | Q24: 900 | R24: 1 | S24: YES | T24: KHJ1-02-007-MAH-TS9-1-MEC-MRIR-0002 & 004 | U24: 07 Feb & 14 FEB | W24: KHJ1-02-007-MAH-TS9-1-STR-MIR-0107
C25: 2.5 | D25: 110mm Diameter | E25: Mechanical | G25: m | H25: 27900 | L25: 1 | M25: 46026 | N25: 80 days | O25: 18/3/2026 | P25: 46030 | Q25: 27900 | R25: 1 | S25: YES | T25: KHJ1-02-007-MAH-TS9-1-MEC-MRIR-0002 & 004 | U25: 07 Feb & 14 FEB | W25: KHJ1-02-007-MAH-TS9-1-MEC-MRIR-0030
C26: 2.6 | D26: 160mm Diameter | E26: Mechanical | G26: m | H26: 9576 | L26: 1 | M26: 46026 | N26: 80 days | O26: 18/3/2026 | P26: 30/6/2026 | Q26: 9576 | R26: 1 | S26: YES | T26: KHJ1-02-007-MAH-TS9-1-MEC-MRIR-0002 & 004 | U26: 07 Feb & 14 FEB | W26: KHJ1-02-007-MAH-TS9-1-STR-MIR-0107,
C27: 2.7 | D27: 200mm Diameter | E27: Mechanical | G27: m | H27: 11496 | L27: 1 | M27: 46026 | N27: 80 days | O27: 18/3/2026 | P27: 46030 | Q27: 11496 | R27: 1 | S27: YES | T27: KHJ1-02-007-MAH-TS9-1-MEC-MRIR-0002 & 004 | U27: 07 Feb & 14 FEB | W27: KHJ1-02-007-MAH-TS9-1-STR-MIR-0107
C28: 2.8 | D28: 250mm Diameter | E28: Mechanical | G28: m | H28: 8772 | L28: 1 | M28: 46026 | N28: 80 days | O28: 18/3/2026 | P28: 46030 | Q28: 8772 | R28: 1 | S28: YES | T28: KHJ1-02-007-MAH-TS9-1-MEC-MRIR-0002 & 004 | U28: 07 Feb & 14 FEB | W28: KHJ1-02-007-MAH-TS9-1-CIV-MRIR-0030
C29: 2.9 | D29: 315mm Diameter | E29: Mechanical | G29: m | H29: 372 | L29: 1 | M29: 46026 | N29: 80 days | O29: 18/3/2026 | P29: 46030 | Q29: 372 | R29: 1 | S29: YES | T29: KHJ1-02-007-MAH-TS9-1-MEC-MRIR-0002 & 004 | U29: 07 Feb & 14 FEB | W29: KHJ1-02-007-MAH-TS9-1-CIV-MRIR-0030
C30: 2.1 | D30: 355mm Diameter | E30: Mechanical | G30: m | H30: 72 | L30: 1 | M30: 46026 | N30: 80 days | O30: 18/3/2026 | P30: 46030 | Q30: 72 | R30: 1 | S30: YES | T30: KHJ1-02-007-MAH-TS9-1-MEC-MRIR-0002 & 004 | U30: 07 Feb & 14 FEB | W30: KHJ1-02-007-MAH-TS9-1-CIV-MRIR-0030
C31: 3 | D31: UPVC Pipes | E31: Mechanical
D32: 110mm Diameter | G32: m | H32: 4800 | L32: 1 | M32: 46025 | N32: 60 days | O32: 15/3/2026 | P32: 46030 | Q32: 4320 | R32: =Q32/H32 -> 0.9 | S32: yes
C33: 2.1 | D33: 150mm Diameter | G33: m | H33: 9822 | L33: 1 | M33: 46025 | N33: 60 days | O33: 15/3/2026 | P33: 46030 | Q33: 9822 | R33: 1 | S33: yes | T33: KHJ1-02-007-МАН-TS9-1-MEC-MRIR-0063 | U33: 46062 | W33: KHJ1-02-007-MAH-TS9-1-STR-MIR-0107
C34: 2.2 | D34: 200mm Diameter | G34: m | H34: 1062 | L34: 1 | M34: 46025 | N34: 60 days | O34: 15/3/2026 | P34: 46030 | Q34: 1062 | R34: 1 | S34: yes | T34: KHJ1-02-007-MAH-TS9-1-MEC-MRIR-0003,KHJ1-02-007-MAH-TS9-1-MEC-MRIR-0025 | U34: 46062 | W34: KHJ1-02-007-MAH-TS9-1-STR-MIR-0102,KHJ1-02-007-MAH-TS9-1-MEC-MRIR-0025
C35: 2.4 | D35: 300mm Diameter | G35: m | H35: 13375 | L35: 1 | M35: 46025 | N35: 60 days | O35: 15/3/2026 | P35: 30/6/2026 | Q35: 13375 | R35: 1 | S35: yes | T35: KHJ1-02-007-MAH-TS9-1-MEC-MRIR-0003,KHJ1-02-007-MAH-TS9-1-MEC-MRIR-0007,KHJ1-02-007-MAH-TS9-1-MEC-MRIR-0033 | U35: 46062 | W35: KHJ1-02-007-MAH-TS9-1-STR-MIR-0102,KHJ1-02-007-MAH-TS9-1-CIV-MIR-0098
C36: 2.5 | D36: 400mm Diameter | G36: m | H36: 915 | L36: 1 | M36: 46025 | N36: 60 days | O36: 15/3/2026 | P36: 30/6/2026 | Q36: 915 | R36: 1 | S36: yes | T36: KHJ1-02-007-MAH-TS9-1-MEC-MRIR-0011 | U36: 46062 | W36: KHJ1-02-007-MAH-TS9-1-MEC-MRIR-0011
C37: 4 | D37: Back filling | G37: m3 | H37: 865580 | L37: 1 | M37: INREVIEW | N37: 90 days | O37: 46113 | P37: 46234 | Q37: 470000 | R37: =+Q37/H37 -> 0.54 | T37: KHJ1-02-007-MAH-TS9-1-MEC-MRIR-0046 & 47, 50 , 51 & 52 , 56
C38: 5 | D38: Subgrade | F38: B5.33 31 00.01 | G38: m3 | H38: 150796 | L38: 0 | N38: 90 | O38: 20/4/2026 | P38: 20/7/2026 | Q38: =+H38*75% -> 113097 | R38: =Q38/H38 -> 0.75 | S38: 1 | T38: KHJ1-02-007-MAH-TS9-1-ROD-MRIR-0038 KHJ1-02-007-MAH-TS9-1-ROD-MRIR-0049 KHJ1-02-007-MAH-TS9-1-ROD-MRIR-0053 | W38: KHJ1-02-007-MAH-TS9-1-CIV-MIR-0001 KHJ1-02-007-MAH-TS9-1-CIV-MIR-0002
C39: 6 | D39: Aggregate base course | G39: m3 | H39: 103310 | L39: 1 | M39: INREVIEW | N39: 90 | O39: 46028 | P39: 46265 | Q39: =+H39*55% -> 56820.5 | R39: =Q39/H39 -> 0.55
C40: 7 | D40: Waterproofing membrane | G40: lm | H40: HBS | L40: 1 | M40: 15/3/2026 | O40: as per site request to start
C41: 8 | D41: Curbstone | G41: EA | H41: 155879 | L41: 1 | M41: 15/3/2026 | N41: 90-100 | O41: as per site request to start | Q41: 36336 | R41: =Q41/H41 -> 0.2331
C42: 9 | D42: Block work Accessories | G42: m3 | H42: HBS | L42: 1 | M42: confirmed | N42: 10 days | O42: as per site request to start | P42: as per site request to start
C43: 10 | D43: Sand Cement Plaster for Internal Walls | G43: m3 | H43: HBS | L43: 1 | M43: confirmed | N43: 10 days | O43: as per site request to start | P43: as per site request to start
C44: 11 | D44: Paint INTERNAL & External Areas | G44: m2 | H44: HBS | L44: 1 | M44: 46025 | N44: 10 days | O44: as per site request to start | P44: as per site request to start
C45: 12 | D45: Concrete Mix for PC works | G45: m3 | H45: 2600 | L45: 1 | M45: confirmed | O45: as per site request to start | P45: as per site request to start | Q45: 1500 | R45: =Q45/H45 -> 0.5769 | T45: KHJ1-02-007-MAH-TS9-1-CIV-MAR-0054 & 54
C46: 13 | D46: Concrete Mix for RC works | G46: m3 | H46: 3300 | L46: 1 | M46: confirmed | N46: Done | O46: Done | P46: Done | Q46: 2000 | R46: =Q46/H46 -> 0.6061
C47: 14 | D47: Reinforcement Steel | G47: ton | H47: 470 | L47: 1 | M47: Done | N47: Done | O47: Done | P47: Done | Q47: 420 | R47: =Q47/H47 -> 0.89 | S47: 1 | T47: KHJ1-02-007-MAH-TS9-1-CIV-MAR-001-01KHJ1-02-007-MAH-TS9-1-CIV-MRIR-0029 KHJ1-02-007-MAH-TS9-1-CIV-MRIR-0036, | W47: KHJ1-02-007-MAH-TS9-1-CIV-MIR-0004
C48: 15 | D48: Paving blocks 200*100*60 mm | G48: EA | H48: 130000 | L48: 1 | M48: confirmed | N48: 20 days | O48: as per site request to start | R48: =Q48/H48 -> 0
C49: 16 | D49: Structural steeL for Prefab Portcabibn | G49: EA | H49: 4 | L49: 1 | M49: INREVIEW | Q49: 4 | R49: =Q49/H49 -> 1
C50: 17 | D50: Plaster for External Walls | G50: m2 | H50: HBS | L50: 1 | M50: confirmed | N50: 45 days | O50: AS PER SITE NEEDED
C51: 18 | D51: Porcelain Tiling | G51: m2 | H51: HBS | L51: 0 | M51: Sample has been submitted for approval
C52: 19 | D52: False Ceilings | G52: m2 | H52: HBS | L52: 1 | M52: confirmed | N52: 20 days | O52: as per site request to start
C53: 20 | D53: Access ladder | G53: EA | H53: HBS | L53: 0 | M53: confirmed under cancillation | N53: 30 days
C54: 21 | D54: Lighting Poles Precast Foundation & Bolt | G54: EA | H54: 981 | L54: 859 | M54: under process | Q54: 863 | R54: =Q54/H54 -> 0.88
C55: 22 | D55: Traffic signage | G55: EA | H55: 981 | L55: 1 | M55: 15/3/2026 | N55: 55 | O55: as per site request to start | Q55: 981 | R55: =Q55/H55 -> 1
C56: 23 | D56: Doors & Windows | G56: EA | H56: HBS | L56: 0 | M56: wait mock up sample from alumaco for approval
C57: 24 | D57: Granite, ceramic | G57: m2 | H57: HBS | L57: 0 | M57: Sample has been submitted for approval | N57: 30 days | O57: as per site request to start
C58: 25 | D58: Trees and Bushes-Landscape ( soft) | G58: EA | H58: HBS | L58: 1 | M58: confirmed | N58: 21 days | O58: as per site request to start
C59: 26 | D59: Asphalt | G59: m3 | H59: 75000 | L59: 1 | M59: under review | Q59: 25000 | R59: =+Q59/H59 -> 0.33
C60: 27 | D60: ICT Manholes Cover with frame | G60: EA | H60: 214 | L60: 1 | M60: 27/04/2026 | N60: 90 | O60: as per site request to start | Q60: 0
C61: 28 | D61: Telecome Manholes | G61: EA | H61: 214 | L61: 0 | N61: 15 | Q61: 0
C62: 29 | D62: Generator | G62: EA | H62: HBS | L62: 0 | M62: Pqd under review | N62: 30
C63: 30 | D63: MV Cables | G63: m | H63: 72000 | L63: 1 | M63: INREVIEW | N63: 84 DAYS | O63: 46029 | P63: 46031 | Q63: 56700 | R63: =+Q63/H63 -> 0.79
C64: 31 | D64: Public address System | G64: EA | H64: HBS | L64: 0 | M64: under process | N64: 7
C65: 32 | D65: Unit Substation & RMU | G65: EA | H65: 10 | L65: 1 | M65: 46026 | N65: 140 | O65: as per site request to start | Q65: 10 | R65: =+Q65/H65 -> 1
C66: 33 | D66: LV Cables | G66: m | H66: 114893 | L66: 1 | M66: INREVIEW | N66: 100 | O66: 15/5/2026 | P66: 15/7/2026 | Q66: 97030 | R66: =+Q66/H66 -> 0.84
C67: 35 | D67: Electrical Panels | G67: EA | H67: 13 | L67: 0 | M67: under process | N67: 30 days | Q67: 13 | R67: =+Q67/H67 -> 1
C68: 36 | D68: LV Conductors (part of the panels) | G68: EA | L68: 0 | M68: under process
C69: 38 | D69: Drain & Clean Out | G69: m | H69: HBS | L69: 0 | M69: under process
C70: 39 | D70: Split AC Package | G70: EA | H70: HBS | L70: 0 | M70: under process
C71: 40 | D71: Ventilation Unit-Fan | G71: EA | H71: HBS | L71: 0 | M71: under process | N71: 15
C72: 41 | D72: Fire Pump | G72: EA | H72: HBS | L72: 0 | N72: 120
C73: 42 | D73: Street Lights Lighting Fixtures | G73: EA | H73: 1090 | L73: 1 | M73: 27/4/2026 | N73: 70 | Q73: 970 | R73: =+Q73/H73 -> 0.89
C74: 43 | D74: Street Lighting Poles | G74: EA | H74: 981 | L74: 1 | M74: 27/04/2026 | N74: 70 | O74: 20/5/2026 | P74: 30/6/2026 | Q74: 863 | R74: =+Q74/H74 -> 0.88
C75: 44 | D75: PVC & EMT conduits | G75: EA | H75: HBS | L75: 1 | M75: INREVIEW | N75: 15
C76: 45 | D76: CCTV Pole | G76: EA | H76: HBS | L76: 0 | M76: under process
C77: 46 | D77: Underground Ducts-HDPE | G77: m | H77: HBS | L77: 1 | M77: 15/3/2026 | N77: 70 | O77: 28/3/2026 | P77: 30/7/2026 | S77: 1 | T77: KHJ1-02-007-MAH-TS9-1-ELE-MRIR-0042 KHJ1-02-007-MAH-TS9-1-ELE-MRIR-0040
C78: 47 | D78: LIGHTING FIXTURES (buildings Internal) | G78: EA | H78: HBS | L78: 0 | N78: 15
C79: 48 | D79: Earthing System | G79: EA | H79: 620 | L79: 1 | N79: 30 days | O79: 15/5/2026 | P79: 15/6/2026 | Q79: 620 | R79: =+Q79/H79 -> 1 | S79: 1 | T79: KHJ1-02-007-MAH-TS9-1-ELE-MRIR-0043
C80: 49 | D80: Cable glands, lugs and accessories | G80: EA | L80: 0 | M80: under process
C81: 50 | D81: Wiring Devices and Switches | G81: EA | H81: HBS | L81: 1 | N81: 15
C82: 51 | D82: DALI Cabinet (external lighting control) | G82: EA | H82: HBS | L82: 0 | M82: under process
C83: 52 | D83: GI duct work with insulation & Support | G83: EA | H83: HBS | L83: 0 | M83: under process
C84: 53 | D84: External Lighting Fixtures | G84: EA | H84: HBS | L84: 0 | M84: under process
C85: 54 | D85: Manhole Covers | G85: EA | H85: 1554 | L85: 1 | M85: 16/4/2026 | N85: 60 | O85: AS PER SITE NEEDED | Q85: 785 | R85: =+Q85/H85 -> 0.51
C86: 55 | D86: Sewer Manholes | G86: EA | H86: 346 | L86: 1 | M86: 15/3/2026 | N86: 46 | O86: AS PER SITE NEEDED | Q86: 340 | R86: =+Q86/H86 -> 0.98 | S86: 1 | T86: KHJ-1-02-007-MAH-TS9-1-MEC-MRIR-0010-00 KHJ-1-02-007-MAH-TS9-1-MEC-MRIR-0012-01,KHJ1-02-007-МАН-TS9-1-SEW-MRIR-0057 | W86: KHJ1-02-007-MAH-TS9-1-STR-MIR-0027,KHJ1-02-007-MAH-TS9-1-STR-MIR-0065-00
C87: 56 | D87: Storm Manholes | G87: EA | H87: 300 | L87: 1 | M87: 15/3/2026 | N87: 70 | O87: 15/3/2026 | P87: 46029 | Q87: 256 | R87: =+Q87/H87 -> 0.85 | S87: 1 | T87: KHJ-1-02-007-MAH-TS9-1-MEC-MRIR-0012-00 KHJ1-02-007-MAH-TS9-1-MEC-MRIR-0034,KHJ1-02-007-МАН-TS9-1-SEW-MRIR-0057 | W87: KHJ1-02-007-МАН-TS9-1-STR-MRIR-0104,KHJ1-02-007-MAH-TS9-1-STR -MIR-0031
C88: 57 | D88: Connection Chamber | G88: EA | H88: 23 | L88: 0 | M88: under process | Q88: 0
C89: 58 | D89: inspection Chambers | G89: EA | H89: 31 | L89: 0 | M89: under process | Q89: 0
C90: 59 | D90: Catch Basin | G90: EA | H90: 666 | L90: 1 | M90: 15/3/2026 | N90: 70 | O90: 46027 | P90: 46302 | Q90: 653 | R90: =+Q90/H90 -> 0.98 | T90: KHJ1-02-007-МАН-TS9-1-MEC-MRIR-0065,KHJ1-02-007-MAH-TS9-1-MEC-MRIR-0080,KHJ1-02-007-MAH-TS9-1-MEC-MRIR-0107 | W90: KHJ1-02-007-MAH-TS9-1-STR-MIR-0009,KHJ1-02-007-MAH-TS9-1-MEC-MIR-0023,KHJ1-02-007-MAH-TS9-1-STR-MIR-0051-00,KHJ1-02-007-MAH-TS9-1-STR-MIR-0066-00
C91: 61 | D91: Secondary Irrigation System | G91: EA | L91: 1 | M91: INREVIEW | N91: 90 | O91: 46028 | P91: 46031 | Q91: 0.67 | R91: 0.67
C92: 62 | D92: Sanitory Ware, Plumbing Fixtures, Toilet Accessories | G92: EA | H92: HBS | L92: 0 | N92: 15
C93: 63 | D93: Ductile Iron Valves & Fittings | G93: EA | H93: 810 | L93: 1 | M93: INREVIEW | N93: 130 | O93: 46027 | P93: 30/7/2026 | Q93: 394 | R93: =+Q93/H93 -> 0.49 | W93: KHJ1-02-007-MAH-TS9-1-MEC-MIR-0053,KHJ1-02-007-MAH-TS9-1-STR-MIR-0067
C94: 64 | D94: Hose Bib | G94: EA | L94: 0
C95: 65 | D95: PPR Pipes & Fittings | G95: EA | H95: HBS | L95: 1 | M95: INREVIEW | N95: 15 | O95: as per site request | Q95: 1 | R95: 1 | W95: KHJ1-02-007-MAH-TS9-1-STR-MIR-0078
C96: 66 | D96: Irrigation Manholes Cover with frame | G96: EA | H96: 20 | L96: 0 | M96: under process | Q96: 0
C97: 67 | D97: Potable Manholes Cover with frame | G97: EA | H97: 34 | L97: 0 | M97: under process | Q97: 0
C98: 68 | D98: Bitumen Paint (Bituminous Damp proofing) | G98: EA | H98: HBS | L98: 0 | M98: under process | S98: 1 | T98: KHJ1-02-007-MAH-TS9-1-MEC-MRIR-0041
C99: 69 | D99: Anti Termite & Pest Control | G99: EA | H99: HBS | L99: 1 | M99: 46024 | N99: FINISHED
C100: 70 | D100: OS & Y Gate valve | G100: EA | H100: HBS | L100: 0 | M100: under process
C101: 71 | D101: Termination Kits | G101: EA | H101: 182 | L101: 1 | M101: 27/04/2026 | N101: 60 days | O101: as per site request | Q101: 182 | R101: =Q101/H101 -> 1
C102: 72 | D102: Fire Hydrants | G102: EA | H102: 310 | L102: 1 | M102: 46057 | N102: 130 days | O102: 30/4/2026 | P102: 30/7/2026 | Q102: 217 | R102: =Q102/H102 -> 0.7 | W102: KHJ1-02-007-MAH-TS9-1-STR-MIR-0010
C103: 73 | D103: Fire Extinguisher | G103: EA | H103: HBS | L103: 0 | N103: 07 DAYS
...

Sheet Invoice Log
D3: Weekly Progress Report - Invoice Log
D4: Project Value | M4: Payment Status | U4: Invoices Summary | AE4: Average Invoices durations
D5: Original Contract Value | G5: 307891320 | I5: O&M Value | K5: 0 | L5: EAC | M5: Advance Payment % | Q5: Advance Payment (SAR) | S5: =G5*O5 -> 0 | U5: No of Submitted Invoices | W5: 0 | Y5: Submitted Invoices (SAR) | AA5: =SUM(H12:H20) -> 49710656 | AC5: Submiited Invoice Peroid | AD5: =MAX(N12:N20) -> 46295 | AE5: CM / PgM Average Approval duration | AG5: =AVERAGE(R12:R22) -> #DIV/0!
D6: Revised Contract Value | F6: 21100000 | G6: =G5 -> 307891320 | I6: Revised O&M Value | K6: 0 | L6: =+#REF!+#REF!+K6 -> #REF! | M6: Retention % | O6: 0 | Q6: Retention (SAR) | S6: 0 | U6: No of Approved Invoices (CM) | W6: =COUNTIF($P$12:$P$22,"Y") -> 0 | Y6: Approved Invoices (CM) (SAR) | AA6: =SUMIF($P$12:$P$20,"Y",$H$12:$H$20) -> 0 | AE6: MODON PM & Accounts Average Approval duration | AG6: -
D7: Estimate At Completion Value | F7: 20900000 | G7: =G6 -> 307891320 | I7: Submitted Invoices (Gross Value) | K7: =H22 -> 49710656 | M7: Penalties and deduction % | O7: =ABS(O8/G5) -> 0 | Q7: AP Recovery (SAR) | S7: =SUM(I12:I21) -> 4971066 | U7: No of Approved Invoices (PM) | W7: =COUNTIF($T$12:$T$22,"Y") -> 0 | Y7: Approved Invoices (PM) (SAR) | AA7: =SUMIF($T$12:$T$20,"Y",$H$12:$H$20) -> 0 | AC7: Invoice Submitted Compared to Contract Value | AD7: =AA5/G6 -> 0.1614552 | AE7: Payments Average Duration | AG7: -
D8: Potential Changes | F8: =F6-F7 -> 200000 | G8: =G6-G7 -> 0 | I8: Total Deduction | K8: =O8+S8 -> 5082066 | M8: Penalties and deduction (SAR) | O8: =K22 -> 111000 | Q8: Retention Cumulative (SAR) | S8: =I22 -> 4971066 | U8: No of Paid Invoices | W8: =COUNTA(Z12:Z22) -> 0 | Y8: Paid Invoices (SAR) | AA8: =SUM(AA12:AA20) -> 0 | AE8: Invoices Average total Duration | AG8: =IFERROR(AVERAGE(AE12:AE22),"")
D10: Invoice Reference | H10: Invoice Value | M10: Period Covered | O10: CM / PgM Approval Timeline | S10: Modon PM & Accounts Approval | Z10: Payment Status | AE10: Total Invoice Duration | AF10: Remarks
D11: # | E11: Invoice No. | F11: Doc Control reference | G11: Submittal Rev. # | H11: Gross Value | I11: Retention | J11: Amount After Retention | K11: Deduction / Penalties | L11: Amount (net) + VAT 15% | M11: Start Date | N11: End Date | O11: Date to CM / PgM | P11: CM / PgM Approval (Yes/No) | Q11: CM / PgM Reply Date | R11: Days Elapsed | S11: Date to PM | T11: PM Approval (Yes/No) | U11: PM Reply Date | V11: Date to Accounts | W11: Accounts Approval (Yes/No) | X11: Accounts Approval Date | Y11: Days Elapsed | Z11: Date Paid | AA11: Amount Paid | AB11: Paid % | AC11: Payment Period (d) | AD11: Amount Pending
D12: 1 | E12: 1 | F12: NA | G12: 1 | H12: 1681886.3 | I12: 168188.63 | J12: =H12-I12 -> 1513697.6 | K12: 34000 | L12: =(J12*1.15)-K12 -> 1706752.3 | M12: 46371 | N12: 46106 | O12: 46106 | P12: 46106 | Q12: 46106 | R12: - | S12: 46106 | T12: 46106 | U12: 46106
D13: 2 | E13: 2 | F13: NA | G13: 2 | H13: 5120873.8 | I13: 512087.38 | J13: =H13-I13 -> 4608786.4 | K13: 64000 | L13: =(J13*1.15)-K13 -> 5236104.4 | M13: 46106 | N13: 46177 | O13: 46177 | P13: 46177 | Q13: 46177 | R13: - | S13: 46177 | T13: 46177 | U13: 46177
D14: 3 | E14: 3 | F14: NA | G14: 3 | H14: 6277339.5 | I14: 627733.95 | J14: =H14-I14 -> 5649605.5 | K14: 0 | L14: =(J14*1.15)-K14 -> 6497046.3 | M14: 46178 | N14: 46230 | O14: 46230 | P14: 46230 | Q14: 46230 | R14: - | S14: 46230 | T14: 46230 | U14: 46230
D15: 4 | E15: 4 | F15: NA | G15: 4 | H15: =13181832.23/0.9 -> 14646480 | I15: =H15*10% -> 1464648 | J15: =H15-I15 -> 13181832 | K15: 13000 | L15: =(J15*1.15)-K15 -> 15146107 | M15: =+N14+1 -> 46231 | N15: 46265 | O15: 46265 | P15: 46265 | Q15: 46265 | S15: 46267 | T15: 46271 | U15: 46271
D16: 5 | F16: NA | G16: 5 | H16: =19785668.38/0.9 -> 21984076 | I16: =H16*10% -> 2198407.6 | J16: =H16-I16 -> 19785668 | K16: 0 | L16: =(J16*1.15)-K16 -> 22753519 | M16: =+N15+1 -> 46266 | N16: 46295 | O16: 46295 | P16: 46295 | Q16: 46295 | S16: 46298 | T16: 46303 | U16: 46303
D17: 6 | F17: NA
D18: 7 | F18: NA
D19: 8 | F19: NA
D20: 9 | F20: NA
D21: 10 | F21: NA | I21: =IF(ISBLANK(H21),"",-H21*$O$5) | J21: =IF(ISBLANK(H21),"",-H21*$O$6) | L21: =IF(ISBLANK(H21),"",(SUM(H21:K21)+(H21+I21)*0.15))
D22: TOTAL | H22: =SUM(H12:H21) -> 49710656 | I22: =SUM(I12:I21) -> 4971065.6 | J22: =SUM(J12:J21) -> 44739590 | K22: =SUM(K12:K21) -> 111000 | L22: =SUM(L12:L21) -> 51339529 | R22: =IF(ISBLANK(Q22),"",Q22-O22) | Y22: =IF(ISBLANK(X22),"",X22-S22) | AC22: =IF(ISBLANK(Z22),"",Z22-X22) | AD22: =SUM(AD12:AD21) -> 0 | AE22: =IF(ISBLANK(Z22),"",Z22-O22)

Sheet Milestones
C3: Contractiual Milestones
C4: Item No. | D4: Milestones | E4: Original (Baseline) | F4: Latest | G4: Forecast | H4: Days Change
C5: 1 | D5: Site Handover Date | E5: 45994 | F5: 45994 | G5: 45994 | H5: =F5-G5 -> 0
C6: 2 | D6: Complete Mobilization | E6: =E5+30 -> 46024 | F6: =F5+30 -> 46024 | G6: =G5+30 -> 46024 | H6: =F6-G6 -> 0
C7: 3 | D7: Road works | E7: 46297 | F7: 46297 | G7: 46333 | H7: =F7-G7 -> -36
C8: 4 | D8: Medium voltage network | E8: 46297 | F8: 46297 | G8: 46326 | H8: =F8-G8 -> -29
C9: 5 | D9: All Networks | E9: 46420 | F9: 46420 | G9: 46420 | H9: =F9-G9 -> 0
C10: 6 | D10: Project Handover | E10: 46723 | F10: 46723 | G10: 46723 | H10: =F10-G10 -> 0

Sheet Progress
C3: Project Scope Statement | D3: Development of infrastructure networks in Al-Kharj industrial city, which is located almost 100 kilometers southeast of Riyadh, The project is comprised of two zones (A , B and Labor Community Area ), which have a total area of approximately 3.50 square kilometers
C6: Earned Value Progress (SAR) | K6: Physical Progress (Effort)
C7: WBS | D7: BOQ Value (SAR) | E7: % Wt. | F7: Weekly (SAR) | H7: To Date (SAR) | K7: Budgeted | L7: % Wt. | M7: Weekly Physical Progress | O7: To Date Physical Progress
F8: Planned | G8: Actual | H8: Orignal Planned | I8: Revised Planned | J8: Actual | K8: (Manhours) | M8: Planned | N8: Earned | O8: Planned | P8: Earned
C9: Engineering | D9: 0 | E9: 0 | F9: 0 | G9: 0 | H9: =D9*100% -> 0 | I9: 0 | J9: =D9*100% -> 0 | K9: 8031947.5 | L9: 0.03 | M9: 0 | N9: =+P9-O21 -> 0 | O9: 8031948 | P9: =K9*100% -> 8031948 | S9: =+P9/$K$14 -> 0.03 | T9: =+O9 -> 8031948
C10: Procurement | D10: 0 | E10: 0 | F10: 0 | G10: 0 | H10: =D10*91.4% -> 0 | I10: 0 | J10: =D10*55% -> 0 | K10: 53546316 | L10: 0.2 | M10: =+O10-N22 -> 1540097 | N10: =+P10-O22 -> 4058810 | O10: 46066045 | P10: =K10*65.44% -> 35040709 | S10: =+P10/$K$14 -> 0.13 | T10: =46066044.78 -> 46066045
C11: Construction | D11: 239411880 | E11: =+D11/$D$14 -> 0.778 | F11: =+I11-I23 -> 2537765.9 | G11: =+J11-J23 -> 2801119 | H11: =D11*72.5% -> 173573613 | I11: =+D11*42.79% -> 1.0244434e+08 | J11: =D11*44.24% -> 1.0591582e+08 | K11: 1.7938016e+08 | L11: 0.67 | M11: =+O11-N23 -> 1914427 | N11: =+P11-O23 -> 2098748 | O11: 76761914 | P11: =K11*44.24% -> 79357783 | R11: =+P11/K11 -> 0.4424 | S11: =+P11/$K$14 -> 0.3 | T11: =76761914.22 -> 76761914 | U11: =+J11/1.15 -> 92100709
C12: Testing & Commissioning | D12: 0 | E12: 0 | F12: 0 | G12: 0 | H12: 0 | I12: =H12 -> 0 | J12: 0 | K12: 26773158 | L12: 0.1 | M12: =+O12-N24 -> 0 | N12: =G12 -> 0 | O12: 6693290 | P12: 0 | T12: =6693289.56 -> 6693289.6
C13: Close Out | D13: =59547339*1.15 -> 68479440 | E13: =+D13/$D$14 -> 0.222 | F13: 0 | G13: 0 | H13: 0 | I13: =H13 -> 0 | J13: 0 | K13: 0 | L13: 0 | M13: =F13 -> 0 | N13: =G13 -> 0 | O13: =N13 -> 0 | P13: 0
C14: Total | D14: =SUM(D9:D13) -> 307891320 | E14: =SUM(E9:E13) -> 1 | F14: =SUM(F9:F13) -> 2537765.9 | G14: =SUM(G9:G13) -> 2801119 | H14: =SUM(H9:H13) -> 173573613 | I14: =SUM(I9:I13) -> 1.0244434e+08 | J14: =SUM(J9:J13) -> 1.0591582e+08 | K14: =SUM(K9:K13) -> 267731582 | ... P14: =SUM(P9:P13) -> 122430440 | T14: =+O14/1.15 -> 1.1961148e+08
C15: Total | D15: =D14/1.15 -> 267731583 | F15: =F14/D14 -> 0.0082 | G15: =G14/D14 -> 0.0091 | H15: =H14/$D$14 -> 0.5637 | I15: =I14/$D$14 -> 0.3327 | J15: =J14/$D$14 -> 0.344 | K15: 1 | L15: =L14/$D$14 -> 0 | M15: =M14/$K$14 -> 0.0129 | N15: =N14/$K$14 -> 0.023 | O15: =O14/$K$14 -> 0.5138 | P15: =P14/$K$14 -> 0.4573 | S15: =+O15-P15 -> 0.0565
C19: 2.0818424e+08 | D19: =+D14*0.01/1.15 -> 2677315.8 | E19: 46300 | F19: =+J11/1.15 -> 92100709 | H19: To Date (SAR) | M19: To Date (SAR) | S19: =+J11/1.15 -> 92100709
F20: 54923877 | H20: Orignal Planned | I20: Revised Planned | J20: Actual | M20: Orignal Planned | N20: Revised Planned | O20: Actual
F21: =+F19-F20 -> 37176832 | H21: 0 | I21: 0 | J21: 0 | M21: 9236740 | N21: 8031947.5 | O21: 8031948
F22: =+F21/D11/1.15 -> 0.135 | H22: 0 | I22: 0 | J22: 0 | M22: 53480722 | N22: 44525948 | O22: 30981899
H23: 173573613 | I23: 99906578 | J23: 1.031147e+08 | K23: =+J23/1.15 -> 89664954 | M23: 1.078882e+08 | N23: 74847487 | O23: 77259035
E24: 46293 | F24: =+J23/1.15 -> 89664954 | H24: 0 | I24: 0 | J24: 0 | M24: 0 | N24: 6693289.6 | O24: 0
F25: 56008474 | H25: 0 | I25: 0 | J25: 0 | M25: 0 | N25: 0 | O25: 0
F26: =+F24-F25 -> 33656479 | H26: 173573613 | I26: 99906578 | J26: 1.031147e+08 | M26: 1.7340747e+08 | N26: 1.3409867e+08 | O26: 116272882
F27: =+F26/D11/1.15 -> 0.1222 | H27: 0.5637 | I27: 0.3245 | J27: 0.3349 | L27: =H15-M27 -> 0.0005 | M27: 0.5632 | N27: 0.5009 | O27: 0.4343 | P27: =J15-O27 -> -0.0903 | R27: =+N27-O27 -> 0.0666
O29: =+N27-O27 -> 0.0666
O30: =+O15-P15 -> 0.0565
C38: Activity Name | D38: Budgeted Cost | E38: Budgeted Units | F38: Spreadsheet Field | G38: 46032 | H38: 46039 | I38: 46046 | J38: 46053 | K38: 46060 | L38: 46067 | M38: 46074 | N38: 46081 | O38: 46088 | P38: 46095 | Q38: 46102 | R38: 46109 | S38: 46116 | T38: 46123 | U38: 46130 | V38: 46137 | W38: 46144 | X38: 46151 | Y38: 46158 | Z38: 46165 | AA38: 46172 | AB38: 46179 | AC38: 46186 | AD38: 46193 | AE38: 46200 | AF38: 46207 | AG38: 46214 | AH38: 46221 | AI38: 46228 | AJ38: 46235 | AK38: 46242 | AL38: 46249 | AM38: 46256 | AN38: 46263 | AO38: 46270 | AP38: 46277 | AQ38: 46284 | AR38: 46291 | AS38: 46298 | AT38: 46305 | AU38: 46312 | AV38: 46319 | AW38: 46326 | AX38: 46333 | AY38: 46340 | AZ38: 46347 | BA38: 46354 | BB38: 46361 | BC38: 46368 | BD38: 46375 | BE38: 46382 | BF38: 46389 | BG38: 46396 | BH38: 46403 | BI38: 46410 | BJ38: 46417 | BK38: 46424 | BL38: 46431 | BM38: 46438 | BN38: 46445 | BO38: 46452 | BP38: 46459 | BQ38: 46466 | BR38: 46473 | BS38: 46480 | BT38: 46487 | BU38: 46494 | BV38: 46501 | BW38: 46508 | BX38: 46515 | BY38: 46522 | BZ38: 46529 | CA38: 46536
C39: WBS: ICKM01-13.Sep.2026-3.PRO PROCUREMENT | D39: 0 | E39: 2622.73 | F39: Budgeted Units | G39: 2.73 | H39: 46.36 | I39: 72.27 | J39: 89.09 | K39: 93.64 | L39: 98.18 | M39: 100.91 | N39: 99.55 | O39: 95.45 | P39: 92.73 | Q39: 90 | R39: 87.27 | S39: 86.52 | T39: 82.27 | U39: 74.09 | V39: 71.36 | W39: 68.18 | X39: 64.09 | Y39: 60.45 | Z39: 58.18 | AA39: 53.18 | AB39: 35.91 | AC39: 31.33 | AD39: 22.16 | AE39: 20.34 | AF39: 19.43 | AG39: 19.43 | AH39: 19.43 | AI39: 19.43 | AJ39: 16.7 | AK39: 16.7 | AL39: 16.7 | AM39: 15.8 | AN39: 14.43 | AO39: 35.8 | AP39: 79.43 | AQ39: 81.27 | AR39: 81.27 | AS39: 79 | AT39: 56.73 | AU39: 45.82 | AV39: 43.09 | AW39: 37.64 | AX39: 37.64 | AY39: 20.73 | AZ39: 17.27 | BA39: 14.55 | BB39: 13.64 | BC39: 13.64 | BD39: 13.18 | BE39: 10.91 | BF39: 10.91 | BG39: 10.91 | BH39: 7.27 | BI39: 5.45 | BJ39: 5.45 | BK39: 5 | BL39: 2.73 | BM39: 2.73 | BN39: 2.73 | BO39: 2.73 | BP39: 2.73 | BQ39: 2.73 | BR39: 2.73 | BS39: 2.73 | BT39: 2.73 | BU39: 2.73 | BV39: 2.73 | BW39: 2.73 | BX39: 2.73 | BY39: 2.73 | BZ39: 2.73 | CA39: 0.91
G40: =+G39/$E$39 -> 0.0010409001 | H40: =+H39/$E$39 -> 0.017676238 | I40: =+I39/$E$39 -> 0.027555257 | J40: =+J39/$E$39 -> 0.033968422 | K40: =+K39/$E$39 -> 0.035703256 | L40: =+L39/$E$39 -> 0.037434276 | M40: =+M39/$E$39 -> 0.038475177 | N40: =+N39/$E$39 -> 0.037956633 | ... CA40: =+CA39/$E$39 -> 0.00034696671
G41: =+G40+F41 -> 0.0010409001 | H41: =+H40+G41 -> 0.018717138 | I41: =+I40+H41 -> 0.046272396 | J41: =+J40+I41 -> 0.080240818 | K41: =+K40+J41 -> 0.11594407 | L41: =+L40+K41 -> 0.15337835 | M41: =+M40+L41 -> 0.19185353 | N41: =+N40+M41 -> 0.22981016 | ... CA41: =+CA40+BZ41 -> 1.0000076
R47: Activity ID | S47: Activity Status | T47: Activity Name | U47: Original Duration | V47: Schedule % Complete | W47: Performance % Complete | X47: Cost % Complete | Y47: Activity % Complete | Z47: Duration % Complete | AA47: Budgeted Labor Units | AB47: Planned Value Labor Units | AC47: Labor Units % Complete | AD47: At Completion Total Cost | AE47: Budgeted Total Cost | AF47: Earned Value Cost | AG47: Actual Cost | AH47: Start | AI47: BL Project Start | AJ47: Finish | AK47: BL Project Finish | AL47: Spreadsheet Field | AM47: 45990 | AN47: 45997 | AO47: 46004 | AP47: 46011 | AQ47: 46018 | AR47: 46025 | AS47: 46032 | AT47: 46039 | AU47: 46046 | AV47: 46053 | AW47: 46060 | AX47: 46067 | AY47: 46074 | AZ47: 46081 | BA47: 46088 | BB47: 46095 | BC47: 46102 | BD47: 46109 | BE47: 46116 | BF47: 46123 | BG47: 46130 | BH47: 46137 | BI47: 46144 | BJ47: 46151 | BK47: 46158 | BL47: 46165 | BM47: 46172 | BN47: 46179 | BO47: 46186 | BP47: 46193 | BQ47: 46200 | BR47: 46207 | BS47: 46214 | BT47: 46221 | BU47: 46228 | BV47: 46235 | BW47: 46242 | BX47: 46249 | BY47: 46256 | BZ47: 46263 | CA47: 46270 | CB47: 46277 | CC47: 46284 | CD47: 46291 | CE47: 46298 | CF47: 46305 | CG47: 46312 | CH47: 46319 | CI47: 46326 | CJ47: 46333 | CK47: 46340 | CL47: 46347 | CM47: 46354 | CN47: 46361 | CO47: 46368 | CP47: 46375 | CQ47: 46382 | CR47: 46389 | CS47: 46396 | CT47: 46403 | CU47: 46410 | CV47: 46417 | CW47: 46424 | CX47: 46431 | CY47: 46438 | CZ47: 46445 | DA47: 46452 | DB47: 46459 | DC47: 46466 | DD47: 46473 | DE47: 46480 | DF47: 46487 | DG47: 46494 | DH47: 46501 | DI47: 46508 | DJ47: 46515 | DK47: 46522 | DL47: 46529 | DM47: 46536 | DN47: 46543 | DO47: 46550 | DP47: 46557 | DQ47: 46564 | DR47: 46571 | DS47: 46578 | DT47: 46585 | DU47: 46592 | DV47: 46599 | DW47: 46606 | DX47: 46613 | DY47: 46620 | DZ47: 46627 | EA47: 46634 | EB47: 46641 | EC47: 46648 | ED47: 46655 | EE47: 46662 | EF47: 46669 | EG47: 46676 | EH47: 46683 | EI47: 46690 | EJ47: 46697 | EK47: 46704 | EL47: 46711 | EM47: 46718 | EN47: 46725 | EO47: 46732 | EP47: 46739 | EQ47: 46746 | ER47: 46753 | ES47: 46760 | ET47: 46767 | EU47: 46774 | EV47: 46781 | EW47: 46788 | EX47: 46795 | EY47: 46802 | EZ47: 46809
R48: Industrial City in Alkharj - Modon (Revised Schedule) | U48: 678 | V48: 0.3187 | W48: 0.3288 | X48: 0.3288 | Z48: 0.4526 | AA48: 267731582 | AB48: 1.2782532e+08 | AC48: 0.4253 | AD48: 267731582 | AE48: 267731582 | AF48: 88029089 | AG48: 88029089 | AH48: 03-Dec-25 A | AI48: 45994 | AJ48: 46723 | AK48: 46723 | AL48: Budgeted Labor Units | AR48: 456116.26 | AS48: 590116.99 | AT48: 867106.42 | AU48: 1372995.2 | AV48: 1646081.2 | AW48: 2579239.9 | AX48: 2924452.3 | AY48: 2362980.2 | AZ48: 2419733.9 | BA48: 2338622.4 | BB48: 1513879.9 | BC48: 877578.11 | BD48: 741317.99 | BE48: 683405.96 | BF48: 605117.92 | BG48: 847808.09 | BH48: 770113.64 | BI48: 880362.95 | BJ48: 1034722.8 | BK48: 1857178.9 | BL48: 930251.67 | BM48: 1586349.9 | BN48: 602881.76 | BO48: 564034.04 | BP48: 533369.24 | BQ48: 722713.36 | BR48: 959053.79 | BS48: 1205693.8 | BT48: 1244219.9 | BU48: 1492117.7 | BV48: 1883221.4 | BW48: 2178015 | BX48: 2164868.5 | BY48: 1930226.8 | BZ48: 1445178.7 | CA48: 1265609.4 | CB48: 406812.88 | CC48: 1394911.9 | CD48: 7656082.2 | CE48: 6924855.6 | CF48: 5362910.8 | CG48: 4652425.4 | CH48: 3135100.1 | CI48: 2595860.5 | CJ48: 4328888.7 | CK48: 5004788.8 | CL48: 5124620.8 | CM48: 4525597 | CN48: 4585846.7 | CO48: 5136526.1 | CP48: 5677290 | CQ48: 3650383 | CR48: 4575558.1 | CS48: 3707799.3 | CT48: 5521403.7 | CU48: 4370072.4 | CV48: 2792077.5 | CW48: 1904808.1 | CX48: 2102923.6 | CY48: 3049505.3 | CZ48: 3223793.2 | DA48: 4801305.2 | DB48: 10515384 | DC48: 8867465.2 | DD48: 8569095.9 | DE48: 8089646.8 | DF48: 5276555.2 | DG48: 5319039.8 | DH48: 5859422.5 | DI48: 4903640 | DJ48: 4547376 | DK48: 4738647.7 | DL48: 5133384.3 | DM48: 6903467.5 | DN48: 3683411.4 | DO48: 2856118.9 | DP48: 3429934.1 | DQ48: 2407817.3 | DR48: 2197761.6 | DS48: 3162700.8 | DT48: 2136848.9 | DU48: 1603450.2 | DV48: 1040691.6 | DW48: 757298.96 | DX48: 508351.22 | DY48: 360818.82 | DZ48: 287396.56 | EA48: 218462.63 | EB48: 300912.17 | EC48: 289406.5 | ED48: 249302.9 | EE48: 237447.91 | EF48: 232533.5 | EG48: 85629.43 | EH48: 59495.75 | EI48: 59495.75 | EJ48: 149023.82 | EK48: 432220.57 | EL48: 581245.47 | EM48: 563153.22 | EN48: 673062.67 | EO48: 518193.1 | EP48: 429203.17 | EQ48: 767330.76 | ER48: 558296.13 | ES48: 559657.95 | ET48: 720150.44 | EU48: 1002295.1 | EV48: 629310.1 | EW48: 608648.76 | EX48: 206173.19 | EY48: 74253.49 | EZ48: 82069.65
R49: GENERAL | U49: 371 | V49: 0 | W49: 0 | X49: 0 | Z49: 0.2242 | AA49: 0 | AB49: 0 | AC49: 0 | AD49: 0 | AE49: 0 | AF49: 0 | AG49: 0 | AH49: 03-Dec-25 A | AI49: 45994 | AJ49: 46723 | AK49: 46723 | AL49: Budgeted Labor Units
R50: ENGINEERING | U50: 28 | V50: 0 | W50: 0 | X50: 0 | Z50: 1 | AA50: 8031947.5 | AB50: 8031947.5 | AC50: 1 | AD50: 0 | AE50: 0 | AF50: 0 | AG50: 0 | AH50: 06-Dec-25 A | AI50: 45994 | AJ50: 28-Sep-26 A | AK50: 46026 | AL50: Budgeted Labor Units | CD50: 2574000.5 | CE50: 2574000.5 | CF50: 1533315.6 | CG50: 1012973.2 | CH50: 337657.73
R51: PROCUREMENT | U51: 380 | V51: 0 | W51: 0 | X51: 0 | Z51: 0.7029 | AA51: 53546316 | AB51: 42916562 | AC51: 0.56 | AD51: 0 | AE51: 0 | AF51: 0 | AG51: 0 | AH51: 06-Dec-25 A | AI51: 46027 | AJ51: 46421 | AK51: 46537 | AL51: Budgeted Labor Units | CD51: 2333618.7 | CE51: 2336291.2 | CF51: 2278365.9 | CG51: 2211765.6 | CH51: 1945890.9 | CI51: 1583545.6 | CJ51: 3293998.9 | CK51: 3985689.6 | CL51: 4105572.1 | CM51: 3613165.4 | CN51: 3202754.5 | CO51: 2417375.3 | CP51: 2066707.9 | CQ51: 1591207.1 | CR51: 1342232 | CS51: 1059083.7 | CT51: 1035168.2 | CU51: 1049075.4 | CV51: 977278.48 | CW51: 654520.57 | CX51: 654520.57 | CY51: 628652.79 | CZ51: 615718.89 | DA51: 601907.34 | DB51: 543104.32 | DC51: 511924.4 | DD51: 419881.28 | DE51: 321722.27 | DF51: 328891.34 | DG51: 277357.17 | DH51: 194742.85 | DI51: 194742.85 | DJ51: 194742.85 | DK51: 194742.85 | DL51: 139496.65 | DM51: 111873.55 | DN51: 91156.23 | DO51: 63533.13 | DP51: 66295.44 | DQ51: 41434.65 | DR51: 471717.55 | DS51: 471717.55 | DT51: 471717.55 | DU51: 430144.32 | DV51: 346997.87 | DW51: 263851.41 | DX51: 263851.41 | DY51: 97558.51 | DZ51: 97558.51 | EA51: 97558.51 | EB51: 159918.35 | EC51: 208466.64 | ED51: 180843.54 | EE51: 180843.54 | EF51: 180843.54 | EG51: 76910.47 | EH51: 56123.86 | EI51: 56123.86 | EJ51: 45730.55 | EK51: 24943.94 | EL51: 24943.94 | EM51: 24943.94 | EN51: 24943.94 | EO51: 8314.65
R52: CONSTRUCTION | U52: 678 | V52: 0.4099 | W52: 0.4228 | X52: 0.4228 | Z52: 0.4634 | AA52: 1.7938016e+08 | AB52: 73530162 | AC52: 0.4228 | AD52: 208184243 | AE52: 208184243 | AF52: 88029089 | AG52: 88029089 | AH52: 06-Dec-25 A | AI52: 46025 | AJ52: 46714 | AK52: 46720 | AL52: Budgeted Labor Units | AR52: 456116.26 | AS52: 590116.99 | AT52: 867106.42 | AU52: 1372995.2 | AV52: 1646081.2 | AW52: 2579239.9 | AX52: 2924452.3 | AY52: 2362980.2 | AZ52: 2419733.9 | BA52: 2338622.4 | BB52: 1513879.9 | BC52: 877578.11 | BD52: 741317.99 | BE52: 683405.96 | BF52: 605117.92 | BG52: 847808.09 | BH52: 770113.64 | BI52: 880362.95 | BJ52: 1034722.8 | BK52: 1857178.9 | BL52: 930251.67 | BM52: 1586349.9 | BN52: 602881.76 | BO52: 564034.04 | BP52: 533369.24 | BQ52: 722713.36 | BR52: 959053.79 | BS52: 1205693.8 | BT52: 1244219.9 | BU52: 1492117.7 | BV52: 1883221.4 | BW52: 2178015 | BX52: 2164868.5 | BY52: 1930226.8 | BZ52: 1445178.7 | CA52: 1265609.4 | CB52: 406812.88 | CC52: 1394911.9 | CD52: 2748463 | CE52: 2014563.9 | CF52: 1551229.3 | CG52: 1427686.6 | CH52: 851551.42 | CI52: 1012314.9 | CJ52: 1034889.8 | CK52: 1019099.2 | CL52: 1019048.7 | CM52: 912431.56 | CN52: 1383092.2 | CO52: 1380493 | CP52: 1602595.3 | CQ52: 2059175.8 | CR52: 3233326.1 | CS52: 2648715.6 | CT52: 2589803.5 | CU52: 1870784.3 | CV52: 1814799 | CW52: 1250287.6 | CX52: 1448403 | CY52: 2420852.5 | CZ52: 2608074.3 | DA52: 3570228.6 | DB52: 4657807.5 | DC52: 4259247.6 | DD52: 4220253.6 | DE52: 5003596 | DF52: 4947663.8 | DG52: 5041682.6 | DH52: 5664679.6 | DI52: 4708897.2 | DJ52: 4352633.2 | DK52: 4543904.9 | DL52: 4538743.9 | DM52: 3900092.9 | DN52: 3592255.1 | DO52: 2792585.7 | DP52: 3363638.7 | DQ52: 2366382.6 | DR52: 1726044.1 | DS52: 2690983.3 | DT52: 1665131.4 | DU52: 1173305.9 | DV52: 693693.78 | DW52: 493447.54 | DX52: 244499.8 | DY52: 263260.32 | DZ52: 189838.05 | EA52: 120904.13 | EB52: 140993.83 | EC52: 80939.86 | ED52: 68459.37 | EE52: 56604.38 | EF52: 51689.96 | EG52: 8718.95 | EH52: 3371.89 | EI52: 3371.89 | EJ52: 103293.27 | EK52: 407276.63 | EL52: 556301.53 | EM52: 538209.28 | EN52: 648118.74 | EO52: 509878.46 | EP52: 429203.17 | EQ52: 767330.76 | ER52: 558296.13 | ES52: 559657.95 | ET52: 720150.44 | EU52: 1002295.1 | EV52: 629310.1 | EW52: 608648.76 | EX52: 206173.19 | EY52: 74253.49 | EZ52: 82069.65
R53: Testing & Commissionin | U53: 144 | V53: 0 | W53: 0 | X53: 0 | Z53: 0 | AA53: 26773158 | AB53: 3346644.8 | AC53: 0 | AD53: 0 | AE53: 0 | AF53: 0 | AG53: 0 | AH53: 46372 | AI53: 46281 | AJ53: 46540 | AK53: 46415 | AL53: Budgeted Labor Units | CO53: 1338657.9 | CP53: 2007986.9 | CT53: 1896432 | CU53: 1450212.7 | DA53: 629169.22 | DB53: 5314471.9 | DC53: 4096293.2 | DD53: 3928961 | DE53: 2764328.6 | DL53: 455143.69 | DM53: 2891501.1
R54: Close-out and Handover | U54: 65 | V54: 0 | W54: 0 | X54: 0 | Z54: 0 | AA54: 0 | AB54: 0 | AC54: 0 | AD54: 0 | AE54: 0 | AF54: 0 | AG54: 0 | AH54: 46648 | AI54: 46649 | AJ54: 46723 | AK54: 46723 | AL54: Budgeted Labor Units

Sheet Physical-Chart Data
D3: Baseline Plan | G3: Revised / Recovery Plan | J3: Earned Effort %
C4: Month | D4: Monthly Effort | E4: Cum Effort | F4: Plan Wt.% | G4: Monthly Effort | H4: Cum. Effort | I4: Plan Wt.% | J4: Monthly Effort | K4: Cum Effort | L4: Cum.Act. Wt.%
C5: 45992 | D5: 8419524 | E5: =D5 -> 8419524 | F5: =E5/$E$27 -> 0.027 | G5: =+H5 -> 0 | H5: 0 | I5: 0 | J5: 1338657.9 | K5: 1164050.4 | L5: =K5/$H$29 -> 0.004 | N5: 1.15
C6: =EOMONTH(C5,1) -> 46053 | D6: 2196489 | E6: =D6+E5 -> 10616013 | F6: =E6/$E$27 -> 0.034 | G6: =+H6-H5 -> 535463.17 | H6: 535463.17 | I6: 0.002 | J6: =K6-K5 -> 8846782.7 | K6: 10010833 | L6: =K6/$H$29 -> 0.037
C7: =EOMONTH(C6,1) -> 46081 | D7: 14420331 | E7: =D7+E6 -> 25036344 | F7: =E7/$E$27 -> 0.081 | G7: =+H7-H6 -> 6693289.6 | H7: 7228752.8 | I7: 0.027 | J7: =K7-K6 -> 7682732.4 | K7: 17693565 | L7: =K7/$H$29 -> 0.066
C8: =EOMONTH(C7,1) -> 46112 | D8: 33339297 | E8: =D8+E7 -> 58375641 | F8: =E8/$E$27 -> 0.19 | G8: =+H8-H7 -> 16599358 | H8: 23828111 | I8: 0.089 | J8: =K8-K7 -> 5587441.7 | K8: 23281007 | L8: =K8/$H$29 -> 0.087
C9: =EOMONTH(C8,1) -> 46142 | D9: 37611630 | E9: =D9+E8 -> 95987271 | F9: =E9/$E$27 -> 0.312 | G9: =+H9-H8 -> 18741211 | H9: 42569322 | I9: 0.159 | J9: 26211859 | K9: 46073928 | L9: =K9/$H$29 -> 0.1721
C10: =EOMONTH(C9,1) -> 46173 | D10: 22056707 | E10: =D10+E9 -> 118043978 | F10: =E10/$E$27 -> 0.383 | G10: =+H10-H9 -> 16599358 | H10: 59168680 | I10: 0.221 | J10: =K10-K9 -> 13596481 | K10: 59670409 | L10: =K10/$H$29 -> 0.223
C11: =EOMONTH(C10,1) -> 46203 | D11: 18108751 | E11: =D11+E10 -> 136152729 | F11: =E11/$E$27 -> 0.442 | G11: =+H11-H10 -> 18473479 | H11: 77642160 | I11: 0.29 | J11: =K11-K10 -> 18164517 | K11: 77834926 | L11: =K11/$H$29 -> 0.291
C12: =EOMONTH(C11,1) -> 46234 | D12: 24569297 | E12: =D12+E11 -> 160722026 | F12: =E12/$E$27 -> 0.522 | G12: =+H12-H11 -> 21418527 | H12: 99060687 | I12: 0.37 | J12: =K12-K11 -> 13780680 | K12: 91615606 | L12: =K12/$H$29 -> 0.342
C13: =EOMONTH(C12,1) -> 46265 | D13: 23526180 | E13: =D13+E12 -> 184248206 | F13: =E13/$E$27 -> 0.598 | G13: =+H13-H12 -> 17670285 | H13: 1.1673097e+08 | I13: 0.436 | J13: =K13-K12 -> 9003545.4 | K13: 1.0061915e+08 | L13: =K13/$H$29 -> 0.376
C14: =EOMONTH(C13,1) -> 46295 | D14: 48356422 | E14: =D14+E13 -> 232604628 | F14: =E14/$E$27 -> 0.755 | G14: =+H14-H13 -> 11512458 | H14: 1.2824343e+08 | I14: 0.479 | J14: =K14-K13 -> 15653731 | K14: 116272882 | L14: =K14/$H$29 -> 0.434 | O14: =+E14/1.15 -> 2.0226489e+08
C15: =EOMONTH(C14,1) -> 46326 | D15: 23001344 | E15: =D15+E14 -> 255605972 | F15: =E15/$E$27 -> 0.83 | G15: =+H15-H14 -> 26773159 | H15: 1.5501659e+08 | I15: 0.579 | J15: =K15-K14 -> 6157558 | K15: =+Progress!P14 -> 122430440 | L15: =K15/$H$29 -> 0.457
C16: =EOMONTH(C15,1) -> 46356 | D16: 12608740 | E16: =D16+E15 -> 268214712 | F16: =E16/$E$27 -> 0.871 | G16: =+H16-H15 -> 32663253 | H16: 1.8767984e+08 | I16: 0.701
C17: =EOMONTH(C16,1) -> 46387 | D17: 972462 | E17: =D17+E16 -> 269187174 | F17: =E17/$E$27 -> 0.874 | G17: =+H17-H16 -> 16599358 | H17: 2.042792e+08 | I17: 0.763
C18: =EOMONTH(C17,1) -> 46418 | D18: 12810602 | E18: =D18+E17 -> 281997776 | F18: =E18/$E$27 -> 0.916 | G18: =+H18-H17 -> 2141852.7 | H18: 2.0642105e+08 | I18: 0.771
C19: =EOMONTH(C18,1) -> 46446 | D19: 6202280 | E19: =D19+E18 -> 288200056 | F19: =E19/$E$27 -> 0.936 | G19: =+H19-H18 -> 15260700 | H19: 2.2168175e+08 | I19: 0.828
C20: =EOMONTH(C19,1) -> 46477 | D20: 5580537 | E20: =D20+E19 -> 293780593 | F20: =E20/$E$27 -> 0.954 | G20: =+H20-H19 -> 24363574 | H20: 2.4604533e+08 | I20: 0.919
C21: =EOMONTH(C20,1) -> 46507 | D21: 6212230 | E21: =D21+E20 -> 299992823 | F21: =E21/$E$27 -> 0.974 | G21: =+H21-H20 -> 6157826.5 | H21: 2.5220315e+08 | I21: 0.942
C22: =EOMONTH(C21,1) -> 46538 | D22: 2647466 | E22: =D22+E21 -> 302640289 | F22: =E22/$E$27 -> 0.983 | G22: =+H22-H21 -> 4551437 | H22: 2.5675459e+08 | I22: 0.959
C23: =EOMONTH(C22,1) -> 46568 | D23: 2923583 | E23: =D23+E22 -> 305563872 | F23: =E23/$E$27 -> 0.992 | G23: =+H23-H22 -> 6157826.5 | H23: 2.6291242e+08 | I23: 0.982
C24: =EOMONTH(C23,1) -> 46599 | D24: 1336381 | E24: =D24+E23 -> 306900253 | F24: =E24/$E$27 -> 0.997 | G24: =+H24-H23 -> 2945047.4 | H24: 2.6585746e+08 | I24: 0.993
C25: =EOMONTH(C24,1) -> 46630 | D25: 651250 | E25: =D25+E24 -> 307551503 | F25: =E25/$E$27 -> 0.999 | G25: =+H25-H24 -> 1606389.5 | H25: 2.6746385e+08 | I25: 0.999
C26: =EOMONTH(C25,1) -> 46660 | D26: 324742 | E26: =D26+E25 -> 307876245 | F26: =E26/$E$27 -> 1 | G26: =+H26-H25 -> 267728.37 | H26: 267731582 | I26: 1
C27: =EOMONTH(C26,1) -> 46691 | D27: 15078 | E27: =D27+E26 -> 307891323 | F27: =E27/$E$27 -> 1 | G27: =+H27-H26 -> 0 | H27: 267731582 | I27: 1
C28: =EOMONTH(C27,1) -> 46721 | G28: =+H28-H27 -> 0 | H28: 267731582 | I28: 1
C29: =EOMONTH(C28,1) -> 46752 | G29: =+H29-H28 -> 0 | H29: 267731582 | I29: 1

Sheet Manpower
D2: =+TEXT(D5,"mmm-yy") -> Dec-25 | E2: =+TEXT(E5,"mmm-yy") -> Jan-26 | F2: =+TEXT(F5,"mmm-yy") -> Feb-26 | G2: =+TEXT(G5,"mmm-yy") -> Mar-26 | H2: =+TEXT(H5,"mmm-yy") -> Apr-26 | I2: =+TEXT(I5,"mmm-yy") -> May-26 | J2: =+TEXT(J5,"mmm-yy") -> Jun-26 | K2: =+TEXT(K5,"mmm-yy") -> Jul-26 | ... AB2: =+TEXT(AB5,"mmm-yy") -> Dec-27
C4: Head-Count | AA4: ='General Information'!E3 -> 46307
C5: MONTHS | D5: 45992 | E5: =EOMONTH(D5,1) -> 46053 | F5: =EOMONTH(E5,1) -> 46081 | G5: =EOMONTH(F5,1) -> 46112 | H5: =EOMONTH(G5,1) -> 46142 | I5: =EOMONTH(H5,1) -> 46173 | J5: =EOMONTH(I5,1) -> 46203 | K5: =EOMONTH(J5,1) -> 46234 | L5: =EOMONTH(K5,1) -> 46265 | ... AB5: =EOMONTH(AA5,1) -> 46752
C6: Planned | D6: 2 | E6: 47 | F6: 201 | G6: 385 | H6: 544 | I6: 422 | J6: 413 | K6: 596 | L6: 642 | M6: 435 | N6: 677 | O6: 841 | P6: 554 | Q6: 106 | R6: 252 | S6: 689 | T6: 284 | U6: 76 | V6: 206 | W6: 110 | X6: 70 | Y6: 26 | Z6: 1 | AA6: 0 | AB6: 0
C7: Actual | D7: 20 | E7: 105 | F7: 190 | G7: 303 | H7: 428 | I7: 588 | J7: 650 | K7: 670 | L7: =575+84 -> 659 | M7: =575+84 -> 659 | N7: =445+84 -> 529
D31: =+D6/SUM($D$6:$AB$6) -> 0 | E31: =+E6/SUM($D$6:$AB$6) -> 0.01 | F31: =+F6/SUM($D$6:$AB$6) -> 0.03 | G31: =+G6/SUM($D$6:$AB$6) -> 0.05 | H31: =+H6/SUM($D$6:$AB$6) -> 0.07 | I31: =+I6/SUM($D$6:$AB$6) -> 0.06 | J31: =+J6/SUM($D$6:$AB$6) -> 0.05 | K31: =+K6/SUM($D$6:$AB$6) -> 0.08 | ... AB31: =+AB6/SUM($D$6:$AB$6) -> 0
C32: 0 | D32: =+D31+C32 -> 0 | E32: =+E31+D32 -> 0.01 | F32: =+F31+E32 -> 0.04 | G32: =+G31+F32 -> 0.09 | H32: =+H31+G32 -> 0.16 | I32: =+I31+H32 -> 0.22 | J32: =+J31+I32 -> 0.27 | K32: =+K31+J32 -> 0.35 | ... AB32: =+AB31+AA32 -> 0.99
A40: Activity Name | B40: Budgeted Units | C40: Spreadsheet Field | D40: 46025 | E40: 46032 | F40: 46039 | G40: 46046 | H40: 46053 | I40: 46060 | J40: 46067 | K40: 46074 | L40: 46081 | M40: 46088 | N40: 46095 | O40: 46102 | P40: 46109 | Q40: 46116 | R40: 46123 | S40: 46130 | T40: 46137 | U40: 46144 | V40: 46151 | W40: 46158 | X40: 46165 | Y40: 46172 | Z40: 46179 | AA40: 46186 | AB40: 46193 | AC40: 46200 | AD40: 46207 | AE40: 46214 | AF40: 46221 | AG40: 46228 | AH40: 46235 | AI40: 46242 | AJ40: 46249 | AK40: 46256 | AL40: 46263 | AM40: 46270 | AN40: 46277 | AO40: 46284 | AP40: 46291 | AQ40: 46298 | AR40: 46305 | AS40: 46312 | AT40: 46319 | AU40: 46326 | AV40: 46333 | AW40: 46340 | AX40: 46347 | AY40: 46354 | AZ40: 46361 | BA40: 46368 | BB40: 46375 | BC40: 46382 | BD40: 46389 | BE40: 46396 | BF40: 46403 | BG40: 46410 | BH40: 46417 | BI40: 46424 | BJ40: 46431 | BK40: 46438 | BL40: 46445 | BM40: 46452 | BN40: 46459 | BO40: 46466 | BP40: 46473 | BQ40: 46480 | BR40: 46487 | BS40: 46494 | BT40: 46501 | BU40: 46508 | BV40: 46515 | BW40: 46522 | BX40: 46529 | BY40: 46536 | BZ40: 46543 | CA40: 46550 | CB40: 46557 | CC40: 46564 | CD40: 46571 | CE40: 46578 | CF40: 46585 | CG40: 46592 | CH40: 46599 | CI40: 46606 | CJ40: 46613 | CK40: 46620 | CL40: 46627 | CM40: 46634 | CN40: 46641 | CO40: 46648 | CP40: 46655 | CQ40: 46662 | CR40: 46662
A41: Total | B41: 438870 | C41: Budgeted Units | D41: 366.57 | E41: 402 | F41: 939.76 | G41: 1640.43 | H41: 2420.86 | I41: 2994.67 | J41: 4137.43 | K41: 3390.86 | L41: 3969.29 | M41: 4335.12 | N41: 4958.12 | O41: 6138.48 | P41: 7085.33 | Q41: 7830.36 | R41: 7246.45 | S41: 7602.52 | T41: 6979 | U41: 6002.62 | V41: 5754.74 | W41: 5606.02 | X41: 5680.93 | Y41: 4778.64 | Z41: 4859.33 | AA41: 5284.1 | AB41: 5857.07 | AC41: 6779.79 | AD41: 7609.57 | AE41: 8197.24 | AF41: 8168.4 | AG41: 7819.24 | AH41: 7754.66 | AI41: 8665.22 | AJ41: 8681.3 | AK41: 7866 | AL41: 7370.44 | AM41: 6580.38 | AN41: 5683.47 | AO41: 4986.32 | AP41: 4728.68 | AQ41: 5953.26 | AR41: 8468.39 | AS41: 10786.19 | AT41: 10828.43 | AU41: 11658.1 | AV41: 11511.97 | AW41: 10653.86 | AX41: 10936.17 | AY41: 9666.28 | AZ41: 8329.5 | BA41: 7255.48 | BB41: 6892.17 | BC41: 4794.98 | BD41: 2918.56 | BE41: 1512.46 | BF41: 1012.33 | BG41: 492.14 | BH41: 325.9 | BI41: 1499.38 | BJ41: 4212.95 | BK41: 6067.24 | BL41: 7127.19 | BM41: 8262.24 | BN41: 10063.81 | BO41: 9736.19 | BP41: 7891.29 | BQ41: 6633.45 | BR41: 4024.88 | BS41: 2461.43 | BT41: 1913.24 | BU41: 1416.43 | BV41: 835.1 | BW41: 868.67 | BX41: 872.08 | BY41: 650.9 | BZ41: 4362.42 | CA41: 2582.76 | CB41: 2419.82 | CC41: 2437.59 | CD41: 2020.49 | CE41: 1446.04 | CF41: 1341.43 | CG41: 894.21 | CH41: 1181.87 | CI41: 1055.1 | CJ41: 794.44 | CK41: 712.57 | CL41: 619.5 | CM41: 422.67 | CN41: 360.16 | CO41: 286.41 | CP41: 217 | CQ41: 31.5 | CR41: 31.5
D42: =+C42+D41 -> 366.57 | E42: =+D42+E41 -> 768.57 | F42: =+E42+F41 -> 1708.33 | G42: =+F42+G41 -> 3348.76 | H42: =+G42+H41 -> 5769.62 | I42: =+H42+I41 -> 8764.29 | J42: =+I42+J41 -> 12901.72 | K42: =+J42+K41 -> 16292.58 | ... CR42: =+CQ42+CR41 -> 438901.53
D43: =+D42/$CR$42 -> 0.0008 | E43: =+E42/$CR$42 -> 0.0018 | F43: =+F42/$CR$42 -> 0.0039 | G43: =+G42/$CR$42 -> 0.0076 | H43: =+H42/$CR$42 -> 0.0131 | I43: =+I42/$CR$42 -> 0.02 | J43: =+J42/$CR$42 -> 0.0294 | K43: =+K42/$CR$42 -> 0.0371 | ... AO43: =+AO42/$CR$42 -> 0.484

Sheet Weekly Manpower
D2: =+TEXT(D5,"mmm-yy") -> Jan-26 | E2: =+TEXT(E5,"mmm-yy") -> Jan-26 | F2: =+TEXT(F5,"mmm-yy") -> Jan-26 | G2: =+TEXT(G5,"mmm-yy") -> Jan-26 | H2: =+TEXT(H5,"mmm-yy") -> Feb-26 | I2: =+TEXT(I5,"mmm-yy") -> Feb-26 | J2: =+TEXT(J5,"mmm-yy") -> Feb-26 | K2: =+TEXT(K5,"mmm-yy") -> Feb-26 | ... CT2: =+TEXT(CT5,"mmm-yy") -> Feb-28
C4: Head-Count | CS4: ='General Information'!E3 -> 46307
C5: Weeks | D5: 46032 | E5: 46039 | F5: 46046 | G5: 46053 | H5: 46060 | I5: 46067 | J5: 46074 | K5: 46081 | L5: 46088 | M5: 46095 | N5: 46102 | O5: 46109 | P5: 46116 | Q5: 46123 | R5: 46130 | S5: 46137 | T5: 46144 | U5: 46151 | V5: 46158 | W5: 46165 | X5: 46172 | Y5: 46179 | Z5: 46186 | AA5: 46193 | AB5: 46200 | AC5: 46207 | AD5: 46214 | AE5: 46221 | AF5: 46228 | AG5: 46235 | AH5: 46242 | AI5: 46249 | AJ5: 46256 | AK5: 46263 | AL5: 46270 | AM5: 46277 | AN5: 46284 | AO5: 46291 | AP5: 46298 | AQ5: 46305 | AR5: 46312 | AS5: 46319 | AT5: 46326 | AU5: 46333 | AV5: 46340 | AW5: 46347 | AX5: 46354 | AY5: 46361 | AZ5: 46368 | BA5: 46375 | BB5: 46382 | BC5: 46389 | BD5: 46396 | BE5: 46403 | BF5: 46410 | BG5: 46417 | BH5: 46424 | BI5: 46431 | BJ5: 46438 | BK5: 46445 | BL5: 46452 | BM5: 46459 | BN5: 46466 | BO5: 46473 | BP5: 46480 | BQ5: 46487 | BR5: 46494 | BS5: 46501 | BT5: 46508 | BU5: 46515 | BV5: 46522 | BW5: 46529 | BX5: 46536 | BY5: 46543 | BZ5: 46550 | CA5: 46557 | CB5: 46564 | CC5: 46571 | CD5: 46578 | CE5: 46585 | CF5: 46592 | CG5: 46599 | CH5: 46606 | CI5: 46613 | CJ5: 46620 | CK5: 46627 | CL5: 46634 | CM5: 46641 | CN5: 46648 | CO5: =+CN5+7 -> 46655 | CP5: =EOMONTH(CO5,1) -> 46691 | CQ5: =EOMONTH(CP5,1) -> 46721 | CR5: =EOMONTH(CQ5,1) -> 46752 | CS5: =EOMONTH(CR5,1) -> 46783 | CT5: =EOMONTH(CS5,1) -> 46812
C6: Planned | D6: 1 | E6: 8 | F6: 28 | G6: 86 | H6: 132 | I6: 218 | J6: 217 | K6: 233 | L6: 212 | M6: 420 | N6: 492 | O6: 544 | P6: 412 | Q6: 452 | R6: 384 | S6: 394 | T6: 393 | U6: 354 | V6: 391 | W6: 373 | X6: 376 | Y6: 387 | Z6: 431 | AA6: 443 | AB6: 504 | AC6: 480 | AD6: 521 | AE6: 465 | AF6: 477 | AG6: 435 | AH6: 406 | AI6: 387 | AJ6: 376 | AK6: 330 | AL6: 263 | AM6: 232 | AN6: 196 | AO6: 355 | AP6: 546 | AQ6: 589 | AR6: 612 | AS6: 726 | AT6: 680 | AU6: 793 | AV6: 908 | AW6: 687 | AX6: 549 | AY6: 492 | AZ6: 445 | BA6: 320 | BB6: 135 | BC6: 79 | BD6: 42 | BE6: 21 | BF6: 39 | BG6: 154 | BH6: 301 | BI6: 418 | BJ6: 471 | BK6: 600 | BL6: 620 | BM6: 587 | BN6: 485 | BO6: 384 | BP6: 217 | BQ6: 168 | BR6: 104 | BS6: 73 | BT6: 57 | BU6: 64 | BV6: 53 | BW6: 159 | BX6: 181 | BY6: 142 | BZ6: 146 | CA6: 148 | CB6: 111 | CC6: 88 | CD6: 63 | CE6: 53 | CF6: 63 | CG6: 54 | CH6: 49 | CI6: 43 | CJ6: 20 | CK6: 17 | CL6: 15 | CM6: 11 | CN6: 1 | CO6: 0 | CP6: 0 | CQ6: 0 | CR6: 0 | CS6: 0 | CT6: 0
C7: Actual | D7: =+HLOOKUP(D2,Manpower!$C$2:$AB$7,6,0) -> 105 | E7: =+HLOOKUP(E2,Manpower!$C$2:$AB$7,6,0) -> 105 | F7: =+HLOOKUP(F2,Manpower!$C$2:$AB$7,6,0) -> 105 | G7: =+HLOOKUP(G2,Manpower!$C$2:$AB$7,6,0) -> 105 | H7: =+HLOOKUP(H2,Manpower!$C$2:$AB$7,6,0) -> 190 | I7: =+HLOOKUP(I2,Manpower!$C$2:$AB$7,6,0) -> 190 | J7: =+HLOOKUP(J2,Manpower!$C$2:$AB$7,6,0) -> 190 | K7: =+HLOOKUP(K2,Manpower!$C$2:$AB$7,6,0) -> 190 | ... AP7: =+HLOOKUP(AP2,Manpower!$C$2:$AB$7,6,0) -> 529 | AQ7: =445+84 -> 529
D31: =+D6/SUM($D$6:$CT$6) -> 0 | E31: =+E6/SUM($D$6:$CT$6) -> 0 | F31: =+F6/SUM($D$6:$CT$6) -> 0 | G31: =+G6/SUM($D$6:$CT$6) -> 0 | H31: =+H6/SUM($D$6:$CT$6) -> 0 | I31: =+I6/SUM($D$6:$CT$6) -> 0.01 | J31: =+J6/SUM($D$6:$CT$6) -> 0.01 | K31: =+K6/SUM($D$6:$CT$6) -> 0.01 | ... V31: =+V6/SUM($D$6:$CT$6) -> 0.01 | W31: =+CO6/SUM($D$6:$CT$6) -> 0 | X31: =+CP6/SUM($D$6:$CT$6) -> 0 | Y31: =+CQ6/SUM($D$6:$CT$6) -> 0 | Z31: =+CR6/SUM($D$6:$CT$6) -> 0 | AA31: =+CS6/SUM($D$6:$CT$6) -> 0 | AB31: =+CT6/SUM($D$6:$CT$6) -> 0
C32: 0 | D32: =+D31+C32 -> 0 | E32: =+E31+D32 -> 0 | F32: =+F31+E32 -> 0 | G32: =+G31+F32 -> 0 | H32: =+H31+G32 -> 0 | I32: =+I31+H32 -> 0.01 | J32: =+J31+I32 -> 0.02 | K32: =+K31+J32 -> 0.03 | ... AB32: =+AB31+AA32 -> 0.19
A40: Activity Name | B40: Budgeted Units | C40: Spreadsheet Field | D40: 46025 | E40: 46032 | F40: 46039 | G40: 46046 | H40: 46053 | I40: 46060 | J40: 46067 | K40: 46074 | L40: 46081 | M40: 46088 | N40: 46095 | O40: 46102 | P40: 46109 | Q40: 46116 | R40: 46123 | S40: 46130 | T40: 46137 | U40: 46144 | V40: 46151 | W40: 46158 | X40: 46165 | Y40: 46172 | Z40: 46179 | AA40: 46186 | AB40: 46193 | AC40: 46200 | AD40: 46207 | AE40: 46214 | AF40: 46221 | AG40: 46228 | AH40: 46235 | AI40: 46242 | AJ40: 46249 | AK40: 46256 | AL40: 46263 | AM40: 46270 | AN40: 46277 | AO40: 46284 | AP40: 46291 | AQ40: 46298 | AR40: 46305 | AS40: 46312 | AT40: 46319 | AU40: 46326 | AV40: 46333 | AW40: 46340 | AX40: 46347 | AY40: 46354 | AZ40: 46361 | BA40: 46368 | BB40: 46375 | BC40: 46382 | BD40: 46389 | BE40: 46396 | BF40: 46403 | BG40: 46410 | BH40: 46417 | BI40: 46424 | BJ40: 46431 | BK40: 46438 | BL40: 46445 | BM40: 46452 | BN40: 46459 | BO40: 46466 | BP40: 46473 | BQ40: 46480 | BR40: 46487 | BS40: 46494 | BT40: 46501 | BU40: 46508 | BV40: 46515 | BW40: 46522 | BX40: 46529 | BY40: 46536 | BZ40: 46543 | CA40: 46550 | CB40: 46557 | CC40: 46564 | CD40: 46571 | CE40: 46578 | CF40: 46585 | CG40: 46592 | CH40: 46599 | CI40: 46606 | CJ40: 46613 | CK40: 46620 | CL40: 46627 | CM40: 46634 | CN40: 46641 | CO40: 46648 | CP40: 46655 | CQ40: 46662 | CR40: 46662
A41: Total | B41: 438870 | C41: Budgeted Units | D41: 366.57 | E41: 402 | F41: 939.76 | G41: 1640.43 | H41: 2420.86 | I41: 2994.67 | J41: 4137.43 | K41: 3390.86 | L41: 3969.29 | M41: 4335.12 | N41: 4958.12 | O41: 6138.48 | P41: 7085.33 | Q41: 7830.36 | R41: 7246.45 | S41: 7602.52 | T41: 6979 | U41: 6002.62 | V41: 5754.74 | W41: 5606.02 | X41: 5680.93 | Y41: 4778.64 | Z41: 4859.33 | AA41: 5284.1 | AB41: 5857.07 | AC41: 6779.79 | AD41: 7609.57 | AE41: 8197.24 | AF41: 8168.4 | AG41: 7819.24 | AH41: 7754.66 | AI41: 8665.22 | AJ41: 8681.3 | AK41: 7866 | AL41: 7370.44 | AM41: 6580.38 | AN41: 5683.47 | AO41: 4986.32 | AP41: 4728.68 | AQ41: 5953.26 | AR41: 8468.39 | AS41: 10786.19 | AT41: 10828.43 | AU41: 11658.1 | AV41: 11511.97 | AW41: 10653.86 | AX41: 10936.17 | AY41: 9666.28 | AZ41: 8329.5 | BA41: 7255.48 | BB41: 6892.17 | BC41: 4794.98 | BD41: 2918.56 | BE41: 1512.46 | BF41: 1012.33 | BG41: 492.14 | BH41: 325.9 | BI41: 1499.38 | BJ41: 4212.95 | BK41: 6067.24 | BL41: 7127.19 | BM41: 8262.24 | BN41: 10063.81 | BO41: 9736.19 | BP41: 7891.29 | BQ41: 6633.45 | BR41: 4024.88 | BS41: 2461.43 | BT41: 1913.24 | BU41: 1416.43 | BV41: 835.1 | BW41: 868.67 | BX41: 872.08 | BY41: 650.9 | BZ41: 4362.42 | CA41: 2582.76 | CB41: 2419.82 | CC41: 2437.59 | CD41: 2020.49 | CE41: 1446.04 | CF41: 1341.43 | CG41: 894.21 | CH41: 1181.87 | CI41: 1055.1 | CJ41: 794.44 | CK41: 712.57 | CL41: 619.5 | CM41: 422.67 | CN41: 360.16 | CO41: 286.41 | CP41: 217 | CQ41: 31.5 | CR41: 31.5
D42: =+C42+D41 -> 366.57 | E42: =+D42+E41 -> 768.57 | F42: =+E42+F41 -> 1708.33 | G42: =+F42+G41 -> 3348.76 | H42: =+G42+H41 -> 5769.62 | I42: =+H42+I41 -> 8764.29 | J42: =+I42+J41 -> 12901.72 | K42: =+J42+K41 -> 16292.58 | ... CR42: =+CQ42+CR41 -> 438901.53
D43: =+D42/$CR$42 -> 0.0008 | E43: =+E42/$CR$42 -> 0.0018 | F43: =+F42/$CR$42 -> 0.0039 | G43: =+G42/$CR$42 -> 0.0076 | H43: =+H42/$CR$42 -> 0.0131 | I43: =+I42/$CR$42 -> 0.02 | J43: =+J42/$CR$42 -> 0.0294 | K43: =+K42/$CR$42 -> 0.0371 | ... AO43: =+AO42/$CR$42 -> 0.484
E48: 6
A49: Activity Name | B49: Budgeted Cost | C49: Budgeted Units | D49: Spreadsheet Field | E49: 46032 | F49: 46039 | G49: 46046 | H49: 46053 | I49: 46060 | J49: 46067 | K49: 46074 | L49: 46081 | M49: 46088 | N49: 46095 | O49: 46102 | P49: 46109 | Q49: 46116 | R49: 46123 | S49: 46130 | T49: 46137 | U49: 46144 | V49: 46151 | W49: 46158 | X49: 46165 | Y49: 46172 | Z49: 46179 | AA49: 46186 | AB49: 46193 | AC49: 46200 | AD49: 46207 | AE49: 46214 | AF49: 46221 | AG49: 46228 | AH49: 46235 | AI49: 46242 | AJ49: 46249 | AK49: 46256 | AL49: 46263 | AM49: 46270 | AN49: 46277 | AO49: 46284 | AP49: 46291 | AQ49: 46298 | AR49: 46305 | AS49: 46312 | AT49: 46319 | AU49: 46326 | AV49: 46333 | AW49: 46340 | AX49: 46347 | AY49: 46354 | AZ49: 46361 | BA49: 46368 | BB49: 46375 | BC49: 46382 | BD49: 46389 | BE49: 46396 | BF49: 46403 | BG49: 46410 | BH49: 46417 | BI49: 46424 | BJ49: 46431 | BK49: 46438 | BL49: 46445 | BM49: 46452 | BN49: 46459 | BO49: 46466 | BP49: 46473 | BQ49: 46480 | BR49: 46487 | BS49: 46494 | BT49: 46501 | BU49: 46508 | BV49: 46515 | BW49: 46522 | BX49: 46529 | BY49: 46536 | BZ49: 46543 | CA49: 46550 | CB49: 46557 | CC49: 46564 | CD49: 46571 | CE49: 46578 | CF49: 46585 | CG49: 46592 | CH49: 46599 | CI49: 46606 | CJ49: 46613 | CK49: 46620 | CL49: 46627 | CM49: 46634 | CN49: 46641 | CO49: 46648
A50: labor | B50: 0 | C50: 159468.18 | D50: Budgeted Units | E50: 1 | F50: 8 | G50: 28 | H50: 86 | I50: 132 | J50: 218 | K50: 217 | L50: 233 | M50: 212 | N50: 420 | O50: 492 | P50: 544 | Q50: 412 | R50: 452 | S50: 384 | T50: 394 | U50: 393 | V50: 354 | W50: 391 | X50: 373 | Y50: 376 | Z50: 387 | AA50: 431 | AB50: 443 | AC50: 504 | AD50: 480 | AE50: 521 | AF50: 465 | AG50: 477 | AH50: 435 | AI50: 406 | AJ50: 387 | AK50: 376 | AL50: 330 | AM50: 263 | AN50: 232 | AO50: 196 | AP50: 355 | AQ50: 546 | AR50: 589 | AS50: 612 | AT50: 726 | AU50: 680 | AV50: 793 | AW50: 908 | AX50: 687 | AY50: 549 | AZ50: 492 | BA50: 445 | BB50: 320 | BC50: 135 | BD50: 79 | BE50: 42 | BF50: 21 | BG50: 39 | BH50: 154 | BI50: 301 | BJ50: 418 | BK50: 471 | BL50: 600 | BM50: 620 | BN50: 587 | BO50: 485 | BP50: 384 | BQ50: 217 | BR50: 168 | BS50: 104 | BT50: 73 | BU50: 57 | BV50: 64 | BW50: 53 | BX50: 159 | BY50: 181 | BZ50: 142 | CA50: 146 | CB50: 148 | CC50: 111 | CD50: 88 | CE50: 63 | CF50: 53 | CG50: 63 | CH50: 54 | CI50: 49 | CJ50: 43 | CK50: 20 | CL50: 17 | CM50: 15 | CN50: 11 | CO50: 1

Sheet Risk Register
C3: RISK Register
C6: Department:
C7: Program
C8: Project: | D8: Development Industrial City-Alkharj
C9: Project No.: | D9: 3121
C10: Project Location: | D10: Industrial City-Alkharj
C12: Risk Data | I12: Category | L12: Risk Description | O12: Risk Control Dates | Q12: Risk Manageability | R12: Risk Proximity | S12: Most Likely | V12: Risk Owner | W12: Risk Response & Treatment Action | AA12: Treatment Control Dates | AD12: Most Likely | AG12: Treatment Status
C13: Risk ID | D13: Region | E13: Section / Group | F13: City | G13: Project ID | H13: Risk Status | I13: T/O/I | J13: Internal/External | K13: Category | L13: Cause / Source | M13: Risk | N13: Consequence / Effect | O13: Identified | P13: Closed | S13: Liklihood | T13: Impact | U13: Risk Score | W13: Risk Response Strategy | X13: Treatment Action | Y13: Treatment Acton Description | Z13: Treatment Action Owner | AA13: Start | AB13: Due | AC13: Closed | AD13: Liklihood | AE13: Impact | AF13: Risk Score
C14: 1 | D14: Central | E14: Central | F14: Al Kharj | G14: KHJ1-02-007 | H14: Close | I14: Issue | J14: External | K14: Construction / Obstacle | L14: Site Obstacle | M14: Existing Site offices, fencing and work shop in zone B | N14: Project progress delay | O14: 31, Dec 2025 | P14: Closed | Q14: Moderate | R14: Distant | S14: High | T14: High | V14: Client | W14: Share | X14: Control | Y14: Email has been sent to the consultant, to advise and address this issue with stakeholder | Z14: Client | AA14: 31, Dec 2025 | AB14: 27, Jan 2026 | AD14: Medium | AE14: Medium | AG14: Open
C15: 2 | D15: Central | E15: Central | F15: Al Kharj | G15: KHJ1-02-007 | H15: Close | I15: Issue | J15: External | K15: Design / Planning | L15: Drawings | M15: Helipad Location and end user requirement | N15: Project progress delay | O15: 31, Dec 2025 | P15: Location Closed Pending Requirments | Q15: Moderate | R15: Distant | S15: High | T15: High | V15: Client | W15: Share | X15: Control | Y15: As discussed an RFI has been sent with all required to start working on a resoluation and open aprper communication channel with the end user | Z15: Client | AA15: 31, Dec 2025 | AB15: 15, Feb 2026 | AD15: Medium | AE15: Medium | AG15: Open
C16: 3 | D16: Central | E16: Central | F16: Al Kharj | G16: KHJ1-02-007 | H16: Open | I16: Issue | J16: Internal | K16: Authorities / Permits | L16: Drawings | M16: Portacabin services Tie-ins | N16: Project progress delay | O16: 31, Dec 2025 | P16: Closed | Q16: Moderate | R16: Distant | S16: Low | T16: Medium | V16: Client | W16: Share | X16: Control | Y16: Working on it with the client | Z16: Client | AA16: 31, Dec 2025 | AB16: 5, Feb 2026 | AD16: Low | AE16: Low | AG16: Open
C17: 4 | D17: Central | E17: Central | F17: Al Kharj | G17: KHJ1-02-007 | H17: Open | I17: Issue | J17: External | K17: Weather / Environmental | L17: Weather | M17: Rains/ Winds/ Dust/Hrash | N17: Project progress delay | O17: Expected | P17: Open | Q17: Hard | R17: Distant | S17: High | T17: High | V17: - | W17: Accept | X17: Mitigate | Y17: - | Z17: - | AA17: - | AB17: - | AD17: Medium | AE17: Medium | AG17: Open
C18: 5 | D18: Central | E18: Central | F18: Al Kharj | G18: KHJ1-02-007 | H18: Open | I18: Issue | J18: Internal | K18: Procurment / Logistic | L18: Procurement | M18: Subgrade Fill/Manholes/ Pipes | N18: Project progress delay | O18: 28, Dec. 2026 | P18: open | Q18: Moderate | R18: Distant | S18: High | T18: High | V18: MMAH | W18: Treat | X18: Mitigate | Y18: Working on it to resolve the delay and assign many suppliers | Z18: MMAH | AA18: 20, Dec 2025 | AB18: 15, Feb 2026 | AD18: Medium | AE18: Medium | AG18: Open
C19: 6 | D19: Central | E19: Central | F19: Al Kharj | G19: KHJ1-02-007 | H19: Open | I19: Issue | J19: Internal | K19: Safety / Quality | L19: Construction Work | M19: Deep Excavation | N19: Project progress delay | O19: Expected | P19: closed | Q19: Moderate | R19: Distant | S19: High | T19: High | V19: MMAH | W19: Treat | X19: Mitigate | Y19: Safety measures and plans | Z19: MMAH | AA19: 07, Feb 2026 | AB19: 15, Feb 2027 | AD19: Medium | AE19: Medium | AG19: Open
C20: 7 | D20: Central | E20: Central | F20: Al Kharj | G20: KHJ1-02-007 | H20: Open | I20: Issue | J20: Internal | K20: Interface / Communication | L20: Construction Work | M20: Existing Services & Roads | N20: Project progress delay | O20: Expected | P20: closed | Q20: Moderate | R20: Distant | S20: High | T20: High | V20: Client &MMAH | W20: Share | X20: Mitigate | Y20: it will be coordinate with the client and the EndUsers of those existing sevices | Z20: Client &MMAH | AA20: 07, Feb 2026 | AB20: 15, Feb 2027 | AD20: Medium | AE20: Medium | AG20: Open
C21: 8 | D21: Central | E21: Central | F21: Al Kharj | G21: KHJ1-02-007 | H21: Open | I21: Issue | J21: Internal | K21: Procurment / Logistic | L21: Procurement | M21: Delay in procurement of key materials | N21: Project progress delay | O21: Expected | P21: closed | Q21: Moderate | R21: Distant | S21: High | T21: High | V21: - | W21: Treat | X21: Mitigate | Y21: Working on it to resolve the delay and assign many suppliers | Z21: MMAH
C23: NOTES:
C24: Risk Status: 1.Open, 2.Closed, or 3.Realized
C25: T/O/I: 1.Threat, 2.Opportunity, or 3.Issue
C27: Category (select 1):
C28: 1. Political
C29: 2. Legal, Regulatory, Compliance
C30: 3. Funding, Finance, Budget
C31: 4. Management, Governance, Policies, KPI, Performance
C32: 5. Human Resources | Y32: `
C33: 6. Stakeholders, Authorities, Approvals, Permits
C34: 7. Requirements, Specifications, Scope, Procurement, Contract
C35: 8. Process, Tools, Technique, Technology
C36: 9. Design, Engineering
C37: 10. Construction, Execution
C38: 11. Testing, Commissioning, Handover
C39: 12. Operation, Maintenance
C41: Risk Description (add all 3):
C42: 1. Source/Cause
C43: 2. Event = Threat, Opportunity, or Issue
C44: 3. Consequence/Effect
C46: Risk Response Strategy for Threats: 1.Terminate, 2.Tolerate, 3.Transfer, or 4.Treat
... C51: Risk Level/Score: Likelihood x Highest Impact (Safety, Cost, Schedule, Environment, Quality, or Reputation. See Risk Scoring Matrix tab)

Sheet Issues
C4: Issues Log | I4: ='General Information'!E3 -> 46307
C5: Issue No | D5: Date Identified | E5: Issue Description | F5: Responsibility | G5: Action Taken | H5: Current Status | I5: Expected/Actual Closure | J5: Duration Elapsed
C6: 1 | E6: Site Obstacles | F6: Client | G6: An RFI has been sent with all required to start working on a resolution and open aprper communication channel with the end user : 1-Existing obstacles between the factory boundary and Local Roads 19 and 20 are preventing the commencement of the planned works. 2- Along Local Road 18, there are old rooms and a fenced storage area currently in use, in addition to installed signage. 3-A diesel tank is located within the affected area; clarification is required regarding the party responsible for its removal. 4- The crusher area must be officially handed over to MAH to proceed with surveying, as the existing NGL differs from the approved design levels. 5-An existing fenced storage area and site offices must be removed to allow access and ensure uninterrupted progress of the works) Action Taken : Meeting Held in Maddon Office and discussed the all challenges with all parties, and all challenges in process to be solved and removed . | H6: Closed | I6: 46068
C7: 2 | E7: Logistic / Procurement | F7: MG | G7: Logistics and Procurement services to be improved and expedited. | H7: Closed | I7: 46137
C8: 3 | E8: MV Network | F8: MG | G8: Finalize a deal with approved SEC contractor and Consultant to carry out the work and supervise it. | H8: Closed | I8: 46137
C9: 4 | E9: Contract Milestones | F9: MG | G9: MMAH Team Needs to recover and Put the follwing on track. 1- Engineering Work Completion. " Closed" 2- Procurement Work. " Closed" 3- Construction Work. " On Going" | H9: Open | I9: 46264
C10: 5 | D10: 20-Apr-2026 | E10: Overall delay against approved baseline | F10: MG | G10: Prepare & implement recovery plan, add resources, additional shifts " Closed" | H10: Closed | I10: 46142
C11: 6 | E11: Technical | F11: MG | G11: Identify and utilize potential financial/technical savings within the project | H11: Open
C12: 7 | E12: Construction | F12: MG | G12: Continue asphalt works without interruption | H12: Open
C13: 8 | E13: Construction | F13: MG | G13: The close proximity of the Medium Voltage (MV) network to the water and irrigation networks is preventing the commencement of internal MV network works | H13: Open
C14: 9 | E14: Construction | F14: MG | G14: Ongoing excavation in the box culvert area in Zone A for completion of the stormwater drainage network is conflicting with existing utilities, including Low Voltage (LV) and Medium Voltage (MV) cables, as well as water and irrigation pipelines | H14: Open

Sheet CCO
C3: CONTRACT CHANGE ORDER (CCO)
C5: CCO No. | D5: Date Added | E5: Description of Change | F5: Status | G5: SR | H5: Sch Impact (Months) | I5: Date Approved | J5: Duration (days)
D6: NA
D7: NA
D8: NA
D9: NA
D10: NA
D11: NA
D12: NA
D13: NA
D14: NA
D15: NA

Sheet Testing
C3: Testing and Commissioning
C4: Item | D4: Planned Start Date | E4: Planned Finish Date | F4: Forecast Start Date | G4: Forecast Finish Date | H4: Actual Start Date | I4: Actual Finish Date | J4: % Completed | K4: Open Comments | L4: Closed Comments
C5: Testing & Commissioning
C7: Total

Sheet KHARAJ CABLES TAKEOFF ZONE A
A2: ITEM | B2: TOTAL LENGTH | C2: NO. OF CABLES | D2: EXCAVATION LENGTH | E2: FACTOR | F2: FINAL EXCAVATION LENGTH | G2: ADJUSTMENT | H2: FINAL CABLE LENGTH
A3: 1 CABLE | B3: 14718.178 | C3: 1 | D3: =B3/C3 -> 14718.178 | E3: 1.05 | F3: =D3*E3 -> 15454.087 | G3: =INT(F3) -> 15454 | H3: =G3*C3 -> 15454
A4: 2 CABLES | B4: 4947.804 | C4: 2 | D4: =B4/C4 -> 2473.902 | E4: 1.05 | F4: =D4*E4 -> 2597.5971 | G4: =INT(F4) -> 2597 | H4: =G4*C4 -> 5194
A5: 3 CABLES | B5: 1455.314 | C5: 3 | D5: =B5/C5 -> 485.10467 | E5: 1.05 | F5: =D5*E5 -> 509.3599 | G5: =INT(F5) -> 509 | H5: =G5*C5 -> 1527
A6: 5 CABLES | B6: 726.669 | C6: 5 | D6: =B6/C6 -> 145.3338 | E6: 1.05 | F6: =D6*E6 -> 152.60049 | G6: =INT(F6) -> 152 | H6: =G6*C6 -> 760
A7: 6 CABLES | B7: 5936.842 | C7: 6 | D7: =B7/C7 -> 989.47367 | E7: 1.05 | F7: =D7*E7 -> 1038.9473 | G7: =INT(F7) -> 1038 | H7: =G7*C7 -> 6228
A8: Total | H8: =SUBTOTAL(109,Table2[FINAL CABLE LENGTH]) -> 29163
A12: No. of Cables | B12: DIM. | C12: EXCAVATION AREA | D12: EXCAVATION QTY. | E12: ADJUSTED EXCAVATION QTY.
A13: =A3 -> 1 CABLE | B13: 0.4 X 0.8 | C13: =0.4*0.8 -> 0.32 | D13: =G3*C13 -> 4945.28 | E13: =INT(D13) -> 4945
A14: =A4 -> 2 CABLES | B14: 0.6 X 0.8 | C14: =0.6*0.8 -> 0.48 | D14: =G4*C14 -> 1246.56 | E14: =INT(D14) -> 1246
A15: =A5 -> 3 CABLES | B15: 0.9 X 0.8 | C15: =0.8*0.9 -> 0.72 | D15: =G5*C15 -> 366.48 | E15: =INT(D15) -> 366
A16: =A6 -> 5 CABLES | B16: 1.5 X 0.8 | C16: =0.8*1.5 -> 1.2 | D16: =G6*C16 -> 182.4 | E16: =INT(D16) -> 182
A17: =A7 -> 6 CABLES | B17: 1.8 X 0.8 | C17: =1.8*0.8 -> 1.44 | D17: =G7*C17 -> 1494.72 | E17: =INT(D17) -> 1494

Sheet KHATRAJ ZONE B
A2: ITEM | B2: TOTAL LENGTH | C2: NO. OF CABLES | D2: EXCAVATION LENGTH | E2: FACTOR | F2: FINAL EXCAVATION LENGTH | G2: ADUSTED EXCAVATION | H2: FINAL CABLE LENGTH
A3: 1 CABLE | B3: 4837.863 | C3: 1 | D3: =B3/C3 -> 4837.863 | E3: 1.05 | F3: =D3*E3 -> 5079.7562 | G3: =INT(F3) -> 5079 | H3: =G3*C3 -> 5079
A4: 2 CABLES | B4: 11669.626 | C4: 2 | D4: =B4/C4 -> 5834.813 | E4: 1.05 | F4: =D4*E4 -> 6126.5536 | G4: =INT(F4) -> 6126 | H4: =G4*C4 -> 12252
A5: 3 CABLES | B5: 2142.739 | C5: 3 | D5: =B5/C5 -> 714.24633 | E5: 1.05 | F5: =D5*E5 -> 749.95865 | G5: =INT(F5) -> 749 | H5: =G5*C5 -> 2247
A6: 4 CABLES | B6: 1869.225 | C6: 4 | D6: =B6/C6 -> 467.30625 | E6: 1.05 | F6: =D6*E6 -> 490.67156 | G6: =INT(F6) -> 490 | H6: =G6*C6 -> 1960
A7: 8 CABLES | B7: 25123.545 | C7: 8 | D7: =B7/C7 -> 3140.4431 | E7: 1.05 | F7: =D7*E7 -> 3297.4653 | G7: =INT(F7) -> 3297 | H7: =G7*C7 -> 26376
A8: Total | H8: =SUBTOTAL(109,Table24[FINAL CABLE LENGTH]) -> 47914
A11: CABLE ITEM | B11: No. of Cables | C11: increment | D11: Cable excavation actual width
A12: =A24 -> 1 CABLE | B12: 1 | C12: 0.4 | D12: 0.4
A13: =A25 -> 2 CABLES | B13: 2 | C13: 0.3 | D13: =B13*C13 -> 0.6
A14: =A26 -> 3 CABLES | B14: 3 | C14: 0.3 | D14: =B14*C14 -> 0.9
A15: =A27 -> 4 CABLES | B15: 4 | C15: 0.3 | D15: =B15*C15 -> 1.2
A16: =A28 -> 8 CABLES | B16: 8 | C16: 0.3 | D16: =B16*C16 -> 2.4
A17: 5 CABLES | B17: 5 | C17: 0.3 | D17: =B17*C17 -> 1.5
A18: 6 CABLES | B18: 6 | C18: 0.3 | D18: =B18*C18 -> 1.8
A23: No. of Cables | B23: DIM. | C23: EXCAVATION AREA | D23: EXCAVATION QTY. | E23: ADJUSTED EXCAVATION QTY.
A24: =A3 -> 1 CABLE | B24: 0.4 X 0.8 | C24: =0.4*0.8 -> 0.32 | D24: =G3*C24 -> 1625.28 | E24: =INT(D24) -> 1625
A25: =A4 -> 2 CABLES | B25: 0.6 X 0.8 | C25: =0.6*0.8 -> 0.48 | D25: =G4*C25 -> 2940.48 | E25: =INT(D25) -> 2940
A26: =A5 -> 3 CABLES | B26: 0.9 X 0.8 | C26: =0.8*0.9 -> 0.72 | D26: =G5*C26 -> 539.28 | E26: =INT(D26) -> 539
A27: =A6 -> 4 CABLES | B27: 1.2 X 0.8 | C27: =1.2*0.8 -> 0.96 | D27: =G6*C27 -> 470.4 | E27: =INT(D27) -> 470
A28: =A7 -> 8 CABLES | B28: 2.4 X 0.8 | C28: =2.4*0.8 -> 1.92 | D28: =G7*C28 -> 6330.24 | E28: =INT(D28) -> 6330

Sheet TOTAL ITEMS FOR ZONE A&B
A2: ITEM | B2: TOTAL CABLE LENGTH | C2: EXCAVATION QTY.
A3: 1 CABLE | B3: =Table2[[#This Row],[FINAL CABLE LENGTH]]+Table24[[#This Row],[FINAL CABLE LENGTH]] -> 20533 | C3: ='KHARAJ CABLES TAKEOFF ZONE A'!E13+'KHATRAJ ZONE B'!E24 -> 6570
A4: 2 CABLES | B4: =Table2[[#This Row],[FINAL CABLE LENGTH]]+Table24[[#This Row],[FINAL CABLE LENGTH]] -> 17446 | C4: ='KHARAJ CABLES TAKEOFF ZONE A'!E14+'KHATRAJ ZONE B'!E25 -> 4186
A5: 3 CABLES | B5: =Table2[[#This Row],[FINAL CABLE LENGTH]]+Table24[[#This Row],[FINAL CABLE LENGTH]] -> 3774 | C5: ='KHARAJ CABLES TAKEOFF ZONE A'!E15+'KHATRAJ ZONE B'!E26 -> 905
A6: 4 CABLES | B6: =Table24[[#This Row],[FINAL CABLE LENGTH]] -> 1960 | C6: ='KHATRAJ ZONE B'!E27 -> 470
A7: 5 CABLES | B7: ='KHARAJ CABLES TAKEOFF ZONE A'!H6 -> 760 | C7: ='KHARAJ CABLES TAKEOFF ZONE A'!E16 -> 182
A8: 6 CABLES | B8: ='KHARAJ CABLES TAKEOFF ZONE A'!H7 -> 6228 | C8: ='KHARAJ CABLES TAKEOFF ZONE A'!E17 -> 1494
A9: 8 CABLES | B9: ='KHATRAJ ZONE B'!H7 -> 26376 | C9: ='KHATRAJ ZONE B'!E28 -> 6330
A10: Total | B10: =SUBTOTAL(109,'TOTAL ITEMS FOR ZONE A&B'!$B$3:$B$9) -> 77077

Sheet STANDBY BOQ
A1: =#REF! -> #REF! | H1: =#REF! -> #REF!
A2: جدول الكميات | H2: BILL OF QUANTITIES
A4: البند | B4: وصف البند | C4: الوحدة | D4: الكمية | E4: السعر (ريال سعودي) | F4: المبلغ (ريال سعودي) | G4: ITEM DESCRIPTION | H4: ITEM
C5: Unit | D5: QUANTITY | E5: PRICE (S.R) | F5: AMOUNT (S.R)
A6: أعمال الطرق | G6: ROAD WORKS
A7: =H7 -> 02 41 00 | B7: أعمال الهدم | G7: DEMOLITION | H7: 02 41 00
A8: =H8 -> B1.02 41 00.1 | B8: إزالة أسفلت قائم | C8: m2 | D8: 2200 | G8: Demolition of existing Asphalt | H8: B1.02 41 00.1
A9: =H9 -> B1.02 41 00.2 | B9: اعداد طبقة الاساس الحصوي القائمة | C9: m2 | D9: 2200 | G9: Compaction of existing aggregate base course layer | H9: B1.02 41 00.2
A10: =H10 -> B1.02 41 00.3 | B10: إزالة بردورات قائمه | C10: m | D10: 464 | G10: Demolition of existing Kerbs | H10: B1.02 41 00.3
A11: =H11 -> 31 22 00 | B11: الأعمال الترابية و التسوية | D11: 0 | G11: EARTHWORKS AND SITE GRADING | H11: 31 22 00
A12: =H12 -> B1.31 22 00.01 | B12: حفريات الطرق | C12: m3 | D12: 205106 | G12: Excavation for cuttings | H12: B1.31 22 00.01
A13: =H13 -> B1.31 22 00.02 | B13: ردميات الطرق | C13: m3 | D13: 1378709 | G13: Fill to the roads | H13: B1.31 22 00.02
A14: =H14 -> B1.31 22 00.03 | B14: طبقة القاعدة | C14: m3 | D14: 222337 | G14: Subgrade | H14: B1.31 22 00.03
A15: =H15 -> 32 11 23 | B15: طبقة أساس حصوية | D15: 0 | G15: AGGREGATE BASE COURSE | H15: 32 11 23
A16: =H16 -> B1.32 11 23.01 | B16: طبقة أساس حصوية | C16: m3 | D16: 145216 | G16: Aggregate base course | H16: B1.32 11 23.01
A17: =H17 -> 32 11 26 | B17: الإنشاء البيتوميني | D17: 0 | G17: BITUMINOUS CONSTRUCTION | H17: 32 11 26
A18: =H18 -> B1.32 11 26.02 | B18: الطبقة الأساس البيتومينية (تدرج 1 - صنف أ)، شاملاً الطبقة اللاصقة (MC1) & (RC2) . | C18: m3 | D18: 63389 | G18: Bituminous base course (Grading I - Class A), including Prime Coat (MC1) & (RC2). | H18: B1.32 11 26.02
A19: =H19 -> 32 12 16 | B19: طبقة السطح العليا | D19: 0 | G19: ASPHALT WEARING COURSE | H19: 32 12 16
A20: =H20 -> B1.32 12 16.01 | B20: طبقة السطح العليا من الخرسانة البيتومينية (تدرج 1 - صنف أ) شاملاً الطبقة اللاصقة (RC2) . | C20: m3 | D20: 36304 | G20: Bituminous concrete wearing course, (Grading I - Class A), including tack coat (RC2). | H20: B1.32 12 16.01
A21: =H21 -> 32 14 13 | B21: بردورات مسبقة الصب | D21: 0 | G21: PRECAST CONCRETE CURB | H21: 32 14 13
A22: =H22 -> B1.32 14 13.01 | B22: بردورات نوع (K1A) | C22: m | D22: 79448 | G22: Concrete curb, Type (K1A) | H22: B1.32 14 13.01
A23: =H23 -> B1.32 14 13.02 | B23: بردورات نوع (K1B) | C23: m | D23: 21624 | G23: Concrete curb, Type (K1B) | H23: B1.32 14 13.02
A24: =H24 -> B1.32 14 13.03 | B24: بردورات نوع (K2) | C24: m | D24: 2755 | G24: Concrete curb, Type (K2) | H24: B1.32 14 13.03
B32: يتم ترحيل الطرق - إلى التجميع | C32: ريال سعودي | F32: =SUM(F8:F24) -> 0 | G32: CARRIED TO ROADS - COLLECTION
A33: =H33 -> 32 17 23 | B33: العلامات الأرضية | G33: PAVEMENT MARKINGS | H33: 32 17 23
A34: =H34 -> 32 17 23.01 | B34: دهان ثرموبلاستيك (أبيض / أصفر) | G34: Thermoplastic pavement marking (White/Yellow) | H34: 32 17 23.01
A35: =H35 -> B1.32 17 23.01.01 | B35: دهانات مرورية بيضاء عاكسة بلاستيكية حرارية | C35: m² | D35: 18149 | G35: Retroreflective Thermoplastic White Traffic | H35: B1.32 17 23.01.01
A36: =H36 -> B1.32 17 23.01.02 | B36: دهانات مرورية صفراء عاكسة بلاستيكية حرارية | C36: m² | D36: 11771 | G36: Retroreflective Thermoplastic Yellow Traffic | H36: B1.32 17 23.01.02
A37: =H37 -> 10 14 53 | B37: اللوحات الإرشادية للطرق | D37: 0 | G37: TRAFFIC SIGNAGE | H37: 10 14 53
A38: =H38 -> B1.10 14 53.01 | B38: لوحات مرورية المثبتة بالأرض مصنوعة من ألواح ألومنيوم مع حواملها القابلة للإنفصال بالقاعدة مكونة من لوحة مروريه وعمود واحد مع كافة الاكسسورات وكل ما يلزم حسب المخططات والمواصفات. | C38: Unit | D38: 482 | G38: Traffic signs, ground mounted, 1 Sheet Alumenium, (breakaway) Single post, with all accessories according to the drawings and specifications. | H38: B1.10 14 53.01
A39: =H39 -> B1.10 14 53.02 | B39: لوحات مرورية المثبتة بالأرض مصنوعة من ألواح ألومنيوم مع حواملها القابلة للإنفصال بالقاعدة مكونة من لوحتين مروريتين وعمود واحد مع كافة الاكسسورات وكل ما يلزم حسب المخططات والمواصفات. | C39: Unit | D39: 275 | G39: Traffic signs, ground mounted, 2 Sheet Alumenium, (breakaway) Single post, with all accessories according to the drawings and specifications. | H39: B1.10 14 53.02
A40: =H40 -> B1.10 14 53.03 | B40: لوحات مرورية مصنوعة من ألواح الإلمنيوم مع حواملها (قابلة للانفصال بالقاعدة) مكونة من لوحه مروريه وعمودين مع كافات الاكسسورات، وكل ما يلزم حسب المخططات والمواصفات. | C40: Unit | D40: 45 | G40: Traffic signs, ground mounted, Sheet Alumenium, (breakaway) Double post with all accessories according to the drawings and specifications. | H40: B1.10 14 53.03
A41: =H41 -> B1.10 14 53.04 | B41: علامات أرضية بارزة عاكسة (نوع - أ) | C41: Unit | D41: 500 | G41: Retroreflective raised pavement markers (Type A) | H41: B1.10 14 53.04
A42: =H42 -> B1.10 14 53.05 | B42: علامات أرضية بارزة مصنوعة من السيراميك | C42: Unit | D42: 500 | G42: Ceramic raised pavement markers | H42: B1.10 14 53.05
A43: =H43 -> B1.10 14 53.06 | B43: علامات أرضية مضيئة تعمل بالطاقة الشمسية (عيون القط) | C43: Unit | D43: 500 | G43: Solar powered lighting cateyes pavement markers | H43: B1.10 14 53.06
F44: =E44+D44 -> 0
F45: =E45+D45 -> 0
F46: =E46+D46 -> 0
F50: =E50+D50 -> 0
F52: =E52+D52 -> 0
B53: يتم ترحيل الطرق - إلى التجميع | C53: ريال سعودي | F53: =E53+D53 -> 0 | G53: CARRIED TO ROADS - COLLECTION
A54: الأعمال الكهربائية | F54: =E54+D54 -> 0 | G54: ELECTRICAL WORKS
A55: =H55 -> 31 23 00 | B55: خندق كابل الجهد المتوسط | F55: =E55+D55 -> 0 | G55: MEDIUM VOLTAGE CABLE TRENCH | H55: 31 23 00
A56: =H56 -> B2.31 23 00.01 | B56: حفر خندق كابل بعرض 40 سم وعمق 80 سم يسع لعدد (1) كابل | C56: m³ | D56: 4945 | G56: Excavation for Trench size 40cm wide and 80cm deep (for 1 cable) | H56: B2.31 23 00.01
A57: =H57 -> B2.31 23 00.02 | B57: حفر خندق كابل بعرض 60 سم وعمق 80 سم يسع لعدد (2) كابل | C57: m³ | D57: 1246 | G57: Excavation for Trench size 60cm wide and 80cm deep ( for 2 cables) | H57: B2.31 23 00.02
A58: =H58 -> B2.31 23 00.03 | B58: حفر خندق كابل بعرض 90 سم وعمق 80 سم يسع لعدد (3) كابل | C58: m³ | D58: 325 | G58: Excavation for Trench size 90cm wide and 80cm deep ( for 3 cables) | H58: B2.31 23 00.03
A59: =H59 -> B2.31 23 00.04 | B59: حفر خندق كابل بعرض 150 سم وعمق 80 سم يسع لعدد (5) كابل | C59: m³ | D59: 182 | G59: Excavation for Trench size 150 cm wide and 80 cm deep ( for 5 cables) | H59: B2.31 23 00.04
A60: =H60 -> B2.31 23 00.05 | B60: حفر خندق كابل بعرض 180 سم وعمق 80 سم يسع لعدد (6) كابل | C60: m³ | D60: 1494 | G60: Excavation for Trench size 180 cm wide and 80 cm deep ( for 6 cables) | H60: B2.31 23 00.05
A61: =H61 -> 33 71 19 | B61: عبارات كابلات الجهد المتوسط | D61: 0 | G61: MEDIUM VOLTAGE CABLES DUCT BANKS | H61: 33 71 19
A62: =H62 -> B2.33 71 19.01 | B62: عبارة لعدد ( 2 ) ماسورة | C62: m | D62: 454 | G62: Duct bank 2 way | H62: B2.33 71 19.01
A63: =H63 -> B2.33 71 19.02 | B63: عبارة لعدد (4) ماسورة | C63: m | D63: 101 | G63: Duct bank 4 way | H63: B2.33 71 19.02
A64: =H64 -> 26 05 13.16 | B64: كيابل الجهد المتوسط | F64: =E64+D64 -> 0 | G64: MEDIUM VOLTAGE CABLES | H64: 26 05 13.16
A65: =H65 -> B2.26.05.13.16.01 | B65: كيبل جهد 15 ك.ف.500*3C مم2 AL/ XLPE/ LLDPE غير مسلح | C65: m | D65: 29163 | G65: Cable: 15KV 3Cx500mm² AL/XLPE/LLDPE unarmored | H65: B2.26.05.13.16.01
A66: =H66 -> B2.26.05.13.16.02 | B66: كابل نحاس أحادي القلب جهد 15 ك.ف غير مسلح (3x1Cx50mm²,Cu/LLDPE/PVC). | C66: m | D66: =15*3 -> 45 | G66: Single Core Cables, Copper, 15kV (3x1Cx50mm²,Cu/LLDPE/PVC). | H66: B2.26.05.13.16.02
A67: =H67 -> B2.26.05.13.16.03 | B67: وصلات كيابل مستقيمة جهد 15 ك.ف. 3C x 500 مم2 Al /XLPE/LLDPE غير مسلح | C67: Unit | D67: 66 | G67: Straight joints cables for 15KV 3x500mm² AL/XLPE/LLDPE unarmored | H67: B2.26.05.13.16.03
A68: =H68 -> B2.26.05.13.16.04 | B68: نهاية كابل جهد 15 ك.ف. 3C x 500 مم2 Al /XLPE/LLDPE | C68: Unit | D68: 24 | G68: Cable Termination for 15KV 3Cx500mm² AL/XLPE/LLDPE | H68: B2.26.05.13.16.04
B70: يتم ترحيل شبكة التوزيع الكهربائية - إلى التجميع | C70: ريال سعودي | F70: =E70+D70 -> 0 | G70: CARRIED TO ELECTRICAL DISTRIBUTION NETWORK - COLLECTION
A71: =H71 -> 26 13 00 | B71: مفاتيح الجهد المتوسط | F71: =E71+D71 -> 0 | G71: MEDIUM VOLTAGE SWITCHGEARS | H71: 26 13 00
A72: =H72 -> B2.26 13 00.01 | B72: مفتاح جهد متوسط (13.8 ك.ف) (وحدة الربط الحلقي) لنقاط الفتح بين المغذيات (NOP) من النوع الخارجي طبقاً لمواصفات الشركة السعودية للكهرباء ومتطلباتها | C72: Unit | D72: 6 | G72: Normally Open Point (R M U) 13.8 kv for Outdoor type according to the Saudi Electric Company specifications and requirements | H72: B2.26 13 00.01
B73: إنارة الطرق | F73: =E73+D73 -> 0 | G73: ROAD LIGHTING
A74: =H74 -> 26 11 16 | B74: محطات الإنارة | F74: =E74+D74 -> 0 | G74: STREET LIGHTING SUB-STATION | H74: 26 11 16
A75: =H75 -> B2.26 11 16.01 | B75: محطة مصندقة 13.8/0.4 ك ف ، 500 ك.ف .ا, شاملة القواعد الخرسانية والسياج .حسب مواصفات ومعايير شركة الكهرباء | C75: Unit | D75: 5 | G75: Unit Substation 13.8/0.4 K V, 500kVA ,Including concrete foundations and fencing, According to the specifications and standards of SEC | H75: B2.26 11 16.01
A76: =H76 -> B2.26 11 16.04 | B76: وحدة الجهد المتوسط الحلقية الالية 15 ك ف , RMU. حسب مواصفات ومعايير شركة الكهرباء | C76: Unit | D76: 5 | G76: Ring Main Unit RMU, 15 KV, According to the specifications and standards of SEC | H76: B2.26 11 16.04
A77: =H77 -> 26 05 19 | B77: كابلات الضغط المنخفض | F77: =E77+D77 -> 0 | G77: LOW VOLTAGE CABLES | H77: 26 05 19
A78: =H78 -> B2.26 05 19.01 | B78: كابل الومنيوم, (4Cx185mm²,AL/XLPE/PVC). | C78: m | D78: 100 | G78: Cables, Aluminium, (4Cx185mm²,AL/XLPE/PVC). | H78: B2.26 05 19.01
A79: =H79 -> B2.26 05 19.02 | B79: كابل نحاس, (4Cx50mm²,Cu/XLPE/SWA/PVC + 1x25mm² PVC/ECC). | C79: m | D79: 50 | G79: Cables, Copper, (4Cx50mm²,Cu/XLPE/SWA/PVC + 1x25mm² PVC/ECC). | H79: B2.26 05 19.02
A80: =H80 -> B2.26 05 19.03 | B80: كابل نحاس, (4Cx95mm²,Cu/XLPE/SWA/PVC + 1x50mm² PVC/ECC). | C80: m | D80: 7240 | G80: Cables, Copper, (4Cx95mm²,Cu/XLPE/SWA/PVC + 1x50mm² PVC/ECC). | H80: B2.26 05 19.03
A81: =H81 -> B2.26 05 19.04 | B81: كابل نحاس, (4Cx16mm²,Cu/XLPE/SWA/PVC +1x10mm² PVC/PVC) | C81: m | D81: 57370 | G81: Cables, Copper, (4Cx16mm²,Cu/XLPE/SWA/PVC +1x10mm² PVC/PVC) | H81: B2.26 05 19.04
A82: =H82 -> 26 27 33 | B82: لوحات توزيع الجهد المنخفض | F82: =E82+D82 -> 0 | G82: LOW VOLTAGE DISTRIBUTION PANEL | H82: 26 27 33
A83: =H83 -> B2.26 27 33.01 | B83: كابينه توزيع الجهد المنخفض Main: 100A, MCCB | C83: Unit | D83: 5 | G83: 100A MCCB Low Voltage Distribution Cabinet. | H83: B2.26 27 33.01
B89: يتم ترحيل شبكة التوزيع الكهربائية - إلى التجميع | C89: ريال سعودي | F89: =E89+D89 -> 0 | G89: CARRIED TO ELECTRICAL DISTRIBUTION NETWORK - COLLECTION
A90: =H90 -> 26 56 19 | B90: أعمدة إنارة | F90: =E90+D90 -> 0 | G90: LIGHTING POLES | H90: 26 56 19
A91: =H91 -> B2.26 56 19.01 | B91: أعمدة أنارة مع ذراعين ، إرتفاع 16 متر، تشمل علبة توزيع الطاقة والكوابل، والقاعدة الخرسانية | C91: Unit | D91: 107 | G91: Lighting poles with double arm, height of ( 16 ) meters, including the power distribution box, cables , and RCC foundation. | H91: B2.26 56 19.01
A92: =H92 -> B2.26 56 19.02 | B92: أعمدة أنارة مع ذراع واحد ، إرتفاع 16 متر، تشمل علبة توزيع الطاقة والكوابل، والقاعدة الخرسانية | C92: Unit | D92: 8 | G92: Lighting poles with single arm, height of ( 16 ) meters, including the power distribution box, cables , and RCC foundation. | H92: B2.26 56 19.02
A93: =H93 -> B2.26 56 19.03 | B93: أعمدة أنارة مع ذراع واحد ، إرتفاع 12 متر، تشمل علبة توزيع الطاقة والكوابل، والقاعدة الخرسانية | C93: Unit | D93: 748 | G93: Lighting poles with single arm, height of ( 12 ) meters, including the power distribution box, cables , and RCC foundation. | H93: B2.26 56 19.03
A94: =H94 -> 26 56 19 | B94: وحدات إنارة الشوارع | F94: =E94+D94 -> 0 | G94: STREET LIGHTING LUMINAIRE | H94: 26 56 19
A95: =H95 -> B2.26.56.19.04 | B95: وحدة إنارة LED نظام اضاءة بمخرج ≥ 50000 lumen كاملة مع جهاز التحكم والمصباح ، (305) واط, 230 فولت, 60 هرتز . | C95: Unit | D95: 70 | G95: Street Lighting ( LED) Luminaire,of Output≥ 50000 lumen complete with control gear and lamp, 305 WATT, 230 Volt, 60 HZ | H95: B2.26.56.19.04
A96: =H96 -> B2.26.56.19.05 | B96: وحدة إنارة LED نظام اضاءة بمخرج ≥ 26000 lumen كاملة مع جهاز التحكم والمصباح ، (154) واط, 230 فولت, 60 هرتز . | C96: Unit | D96: 214 | E96: =E93*2 -> 0 | G96: Street Lighting ( LED) Luminaire,of Output≥ 26000 lumen complete with control gear and lamp, 154 WATT, 230 Volt, 60 HZ | H96: B2.26.56.19.05
A97: =H97 -> B2.26.56.19.06 | B97: وحدة إنارة LED نظام اضاءة بمخرج ≥ 19000 lumen كاملة مع جهاز التحكم والمصباح ، (114) واط, 230 فولت, 60 هرتز . | C97: Unit | D97: 748 | E97: =E94 -> 0 | G97: Street Lighting ( LED) Luminaire,of Output≥ 19000 lumen complete with control gear and lamp, 114 WATT, 230 Volt, 60 HZ | H97: B2.26.56.19.06
A98: =H98 -> 26 05 26 | B98: نظام التاريض | F98: =E98+D98 -> 0 | G98: EARTHING SYSTEM | H98: 26 05 26
A99: =H99 -> B2.26 05 26.01 | B99: يشمل تأريض الأعمدة والصوارى وكبائن التغذية ومحطة التوزيع ووحدات الربط الحلقي ومغذيات الجهد المنخفض لدوائر الإنارة وعداد قياس الطاقة. | C99: Unit | D99: 86 | G99: Including earthing of lighting poles ,masts. feeder pillars , unit substations, RMU, L.V feeders and KWH meter. | H99: B2.26 05 26.01
A100: =H100 -> 33 71 19 | B100: عبارات عبور كابلات الطرق | D100: 0 | G100: ROAD CROSSING DUCTS | H100: 33 71 19
A101: =H101 -> B2.33 71 19.04 | B101: عبارة طرق لكابلات إنارة شوارع ذات أثنين منفذ من مواسير بوليفنيل الكلوريد (2x100 مم) | C101: m | D101: 5074 | G101: Road crossing ducts, 2 way (2 x 100mm PVC) | H101: B2.33 71 19.04
A102: =H102 -> 26 24 16 | B102: لوحات الانارة وكبائن التوزيع | D102: 0 | G102: LIGHTING PANELS | H102: 26 24 16
A103: =H103 -> B2.26 24 16.01 | B103: كبائن التوزيع لدوائر الانارة | C103: Unit | D103: 13 | G103: Street Lighting Feeder pillars | H103: B2.26 24 16.01
A104: =H104 -> B2.26 24 16.02 | B104: توريد وتركيب جدار مع الإطار لتركيب عداد قياس الطاقة من بلوك خرساني حسب معايير ومواصفات الشركة السعودية للكهرباء. | C104: Unit | D104: 5 | G104: Supply and installation of concrete block wall including the frame and the concrete block wall for installation of KWH meter according to the standards and specifications of SEC. | H104: B2.26 24 16.02
A105: =H105 -> 33 71 19.13 | B105: حفر سحب الكابلات | D105: 0 | G105: DRAWPITS | H105: 33 71 19.13
A106: =H106 -> B2.33 71 19.13.01 | B106: حفرة سحب مع غطاء حديد متوسط التحمل بأبعاد 600*600*1000 مم | C106: Unit | D106: 187 | G106: Drawpit with medium duty steel cover, size 600x600x1000mm | H106: B2.33 71 19.13.01
F109: =E109+D109 -> 0
B110: يتم ترحيل شبكة التوزيع الكهربائية - إلى التجميع | C110: ريال سعودي | F110: =E110+D110 -> 0 | G110: CARRIED TO ELECTRICAL DISTRIBUTION NETWORK - COLLECTION
B111: الاتصالات | F111: =E111+D111 -> 0 | G111: TELECOMMUNICATIONS
A112: =H112 -> 33 71 19 | B112: عبارات عبور كابلات الطرق من الخرسانة المسلحة | F112: =E112+D112 -> 0 | G112: ROAD CROSSING REINFORCED CONCRETE ENCASEMENT DUCTS | H112: 33 71 19
A113: =H113 -> B2.33 71 19.05 | B113: عبارات عبور الطريق من المواسير البولي ايثلين 6 خطوط بقطر 50 مم | C113: m | D113: 1700 | G113: 6 way 50mm HDPE duct | H113: B2.33 71 19.05
A114: =H114 -> 33 71 19 | B114: عبارات عبور كابلات الطرق من الخرسانة الغير مسلحة | D114: 0 | G114: UNREINFORCED CONCRETE DUCTS | H114: 33 71 19 | J114: 23380
A115: =H115 -> B2.33 71 19.06 | B115: عبارات عبور الطريق من المواسير البولي ايثلين 6 خطوط بقطر 50 مم | C115: m | D115: 34650 | G115: 6 way 50mm HDPE duct | H115: B2.33 71 19.06
A116: =H116 -> 33 71 19 | B116: العبارات | D116: 0 | G116: DUCTS | H116: 33 71 19 | J116: 370
A117: =H117 -> B2.33 71 19.07 | B117: المواسير من البولي ايثلين 2 خطوط بقطر 32 مم | C117: m | D117: 30590 | G117: 2 x 32 mm diameter HDPE ducts | H117: B2.33 71 19.07
A118: =H118 -> 33 71 19.13 | B118: غرف تفتيش (مانهولات) | D118: 0 | G118: MANHOLES | H118: 33 71 19.13
A119: =H119 -> B2.33.71.19.13.02 | B119: غرفة تقتيش (مانهول) من النوع 1 | C119: nr | D119: 79 | G119: Manhole type 1 | H119: B2.33.71.19.13.02
A120: =H120 -> B2.33.71.19.13.03 | B120: غرفة تقتيش (مانهول) من النوع 2 | C120: nr | D120: 103 | G120: Manhole type 2 | H120: B2.33.71.19.13.03
...

Sheet OLD BOQ
A1: =#REF! -> #REF! | H1: =#REF! -> #REF!
A2: جدول الكميات | H2: BILL OF QUANTITIES
A4: البند | B4: وصف البند | C4: الوحدة | D4: الكمية | E4: السعر (ريال سعودي) | F4: المبلغ (ريال سعودي) | G4: ITEM DESCRIPTION | H4: ITEM
C5: Unit | D5: QUANTITY | E5: PRICE (S.R) | F5: AMOUNT (S.R)
A6: أعمال الطرق | G6: ROAD WORKS
A7: =H7 -> 02 41 00 | B7: أعمال الهدم | G7: DEMOLITION | H7: 02 41 00
A8: =H8 -> B1.02 41 00.1 | B8: إزالة أسفلت قائم | C8: m2 | D8: 2200 | G8: Demolition of existing Asphalt | H8: B1.02 41 00.1
A9: =H9 -> B1.02 41 00.2 | B9: اعداد طبقة الاساس الحصوي القائمة | C9: m2 | D9: 2200 | G9: Compaction of existing aggregate base course layer | H9: B1.02 41 00.2
A10: =H10 -> B1.02 41 00.3 | B10: إزالة بردورات قائمه | C10: m | D10: 464 | G10: Demolition of existing Kerbs | H10: B1.02 41 00.3
A11: =H11 -> 31 22 00 | B11: الأعمال الترابية و التسوية | D11: 0 | G11: EARTHWORKS AND SITE GRADING | H11: 31 22 00
A12: =H12 -> B1.31 22 00.01 | B12: حفريات الطرق | C12: m3 | D12: 205106 | G12: Excavation for cuttings | H12: B1.31 22 00.01
A13: =H13 -> B1.31 22 00.02 | B13: ردميات الطرق | C13: m3 | D13: 1378709 | G13: Fill to the roads | H13: B1.31 22 00.02
A14: =H14 -> B1.31 22 00.03 | B14: طبقة القاعدة | C14: m3 | D14: 222337 | G14: Subgrade | H14: B1.31 22 00.03
A15: =H15 -> 32 11 23 | B15: طبقة أساس حصوية | D15: 0 | G15: AGGREGATE BASE COURSE | H15: 32 11 23
A16: =H16 -> B1.32 11 23.01 | B16: طبقة أساس حصوية | C16: m3 | D16: 145216 | G16: Aggregate base course | H16: B1.32 11 23.01
A17: =H17 -> 32 11 26 | B17: الإنشاء البيتوميني | D17: 0 | G17: BITUMINOUS CONSTRUCTION | H17: 32 11 26
A18: =H18 -> B1.32 11 26.02 | B18: الطبقة الأساس البيتومينية (تدرج 1 - صنف أ)، شاملاً الطبقة اللاصقة (MC1) & (RC2) . | C18: m3 | D18: 63389 | G18: Bituminous base course (Grading I - Class A), including Prime Coat (MC1) & (RC2). | H18: B1.32 11 26.02
A19: =H19 -> 32 12 16 | B19: طبقة السطح العليا | D19: 0 | G19: ASPHALT WEARING COURSE | H19: 32 12 16
A20: =H20 -> B1.32 12 16.01 | B20: طبقة السطح العليا من الخرسانة البيتومينية (تدرج 1 - صنف أ) شاملاً الطبقة اللاصقة (RC2) . | C20: m3 | D20: 36304 | G20: Bituminous concrete wearing course, (Grading I - Class A), including tack coat (RC2). | H20: B1.32 12 16.01
A21: =H21 -> 32 14 13 | B21: بردورات مسبقة الصب | D21: 0 | G21: PRECAST CONCRETE CURB | H21: 32 14 13
A22: =H22 -> B1.32 14 13.01 | B22: بردورات نوع (K1A) | C22: m | D22: 79448 | G22: Concrete curb, Type (K1A) | H22: B1.32 14 13.01
A23: =H23 -> B1.32 14 13.02 | B23: بردورات نوع (K1B) | C23: m | D23: 21624 | G23: Concrete curb, Type (K1B) | H23: B1.32 14 13.02
A24: =H24 -> B1.32 14 13.03 | B24: بردورات نوع (K2) | C24: m | D24: 2755 | G24: Concrete curb, Type (K2) | H24: B1.32 14 13.03
B32: يتم ترحيل الطرق - إلى التجميع | C32: ريال سعودي | F32: =SUM(F8:F24) -> 0 | G32: CARRIED TO ROADS - COLLECTION
A33: =H33 -> 32 17 23 | B33: العلامات الأرضية | G33: PAVEMENT MARKINGS | H33: 32 17 23
A34: =H34 -> 32 17 23.01 | B34: دهان ثرموبلاستيك (أبيض / أصفر) | G34: Thermoplastic pavement marking (White/Yellow) | H34: 32 17 23.01
A35: =H35 -> B1.32 17 23.01.01 | B35: دهانات مرورية بيضاء عاكسة بلاستيكية حرارية | C35: m² | D35: 18149 | G35: Retroreflective Thermoplastic White Traffic | H35: B1.32 17 23.01.01
A36: =H36 -> B1.32 17 23.01.02 | B36: دهانات مرورية صفراء عاكسة بلاستيكية حرارية | C36: m² | D36: 11771 | G36: Retroreflective Thermoplastic Yellow Traffic | H36: B1.32 17 23.01.02
A37: =H37 -> 10 14 53 | B37: اللوحات الإرشادية للطرق | D37: 0 | G37: TRAFFIC SIGNAGE | H37: 10 14 53
A38: =H38 -> B1.10 14 53.01 | B38: لوحات مرورية المثبتة بالأرض مصنوعة من ألواح ألومنيوم مع حواملها القابلة للإنفصال بالقاعدة مكونة من لوحة مروريه وعمود واحد مع كافة الاكسسورات وكل ما يلزم حسب المخططات والمواصفات. | C38: Unit | D38: 482 | G38: Traffic signs, ground mounted, 1 Sheet Alumenium, (breakaway) Single post, with all accessories according to the drawings and specifications. | H38: B1.10 14 53.01
A39: =H39 -> B1.10 14 53.02 | B39: لوحات مرورية المثبتة بالأرض مصنوعة من ألواح ألومنيوم مع حواملها القابلة للإنفصال بالقاعدة مكونة من لوحتين مروريتين وعمود واحد مع كافة الاكسسورات وكل ما يلزم حسب المخططات والمواصفات. | C39: Unit | D39: 275 | G39: Traffic signs, ground mounted, 2 Sheet Alumenium, (breakaway) Single post, with all accessories according to the drawings and specifications. | H39: B1.10 14 53.02
A40: =H40 -> B1.10 14 53.03 | B40: لوحات مرورية مصنوعة من ألواح الإلمنيوم مع حواملها (قابلة للانفصال بالقاعدة) مكونة من لوحه مروريه وعمودين مع كافات الاكسسورات، وكل ما يلزم حسب المخططات والمواصفات. | C40: Unit | D40: 45 | G40: Traffic signs, ground mounted, Sheet Alumenium, (breakaway) Double post with all accessories according to the drawings and specifications. | H40: B1.10 14 53.03
A41: =H41 -> B1.10 14 53.04 | B41: علامات أرضية بارزة عاكسة (نوع - أ) | C41: Unit | D41: 500 | G41: Retroreflective raised pavement markers (Type A) | H41: B1.10 14 53.04
A42: =H42 -> B1.10 14 53.05 | B42: علامات أرضية بارزة مصنوعة من السيراميك | C42: Unit | D42: 500 | G42: Ceramic raised pavement markers | H42: B1.10 14 53.05
A43: =H43 -> B1.10 14 53.06 | B43: علامات أرضية مضيئة تعمل بالطاقة الشمسية (عيون القط) | C43: Unit | D43: 500 | G43: Solar powered lighting cateyes pavement markers | H43: B1.10 14 53.06
F44: =E44+D44 -> 0
F45: =E45+D45 -> 0
F46: =E46+D46 -> 0
F50: =E50+D50 -> 0
F52: =E52+D52 -> 0
B53: يتم ترحيل الطرق - إلى التجميع | C53: ريال سعودي | F53: =E53+D53 -> 0 | G53: CARRIED TO ROADS - COLLECTION
A54: الأعمال الكهربائية | F54: =E54+D54 -> 0 | G54: ELECTRICAL WORKS
A55: =H55 -> 31 23 00 | B55: خندق كابل الجهد المتوسط | F55: =E55+D55 -> 0 | G55: MEDIUM VOLTAGE CABLE TRENCH | H55: 31 23 00
A56: =H56 -> B2.31 23 00.01 | B56: حفر خندق كابل عرض 2.4 م وعمق 80 سم | C56: m³ | D56: 4992 | G56: Excavation for Trench size 2.4m wide and 80cm deep | H56: B2.31 23 00.01
A57: =H57 -> B2.31 23 00.02 | B57: حفر خندق كابل عرض 1.2 م وعمق 80 سم | C57: m³ | D57: 1834 | G57: Excavation for Trench size 1.2m wide and 80cm deep | H57: B2.31 23 00.02
A58: =H58 -> B2.31 23 00.03 | B58: حفر خندق كابل عرض 0.9 م وعمق 80 سم | C58: m³ | D58: 568 | G58: Excavation for Trench size 0.9m wide and 80cm deep | H58: B2.31 23 00.03
A59: =H59 -> B2.31 23 00.04 | B59: حفر خندق كابل عرض 0.6 م وعمق 80 سم | C59: m³ | D59: 2294 | G59: Excavation for Trench size 0.6m wide and 80cm deep | H59: B2.31 23 00.04
A60: =H60 -> B2.31 23 00.05 | B60: حفر خندق كابل عرض 0.4 م وعمق 80 سم | C60: m³ | D60: 8008 | G60: Excavation for Trench size 0.4m wide and 80cm deep | H60: B2.31 23 00.05
A61: =H61 -> 33 71 19 | B61: عبارات كابلات الجهد المتوسط | D61: 0 | G61: MEDIUM VOLTAGE CABLES DUCT BANKS | H61: 33 71 19
A62: =H62 -> B2.33 71 19.01 | B62: عبارات كوابل 6 مسارات (6x150mm duct) | C62: m | D62: 225 | G62: 6-way Duct Bank (6x150mm duct) | H62: B2.33 71 19.01
A63: =H63 -> B2.33 71 19.02 | B63: عبارات كوابل 4 مسارات (4x150mm duct) | C63: m | D63: 330 | G63: 4-way Duct Bank (4x150mm duct) | H63: B2.33 71 19.02
A64: =H64 -> B2.33 71 19.03 | B64: عبارات كوابل 2 مسارات (2x150mm duct) | C64: m | D64: 677 | G64: 2-way Duct Bank (2x150mm duct) | H64: B2.33 71 19.03
A65: =H65 -> 26 05 13.16 | B65: كيابل الجهد المتوسط | F65: =E65+D65 -> 0 | G65: MEDIUM VOLTAGE CABLES | H65: 26 05 13.16
A66: =H66 -> B2.26.05.13.16.01 | B66: كيبل جهد 15 ك.ف.500*3C مم2 AL/ XLPE/ LLDPE غير مسلح | C66: m | D66: 41635 | G66: Cable: 15KV 3Cx500mm² AL/XLPE/LLDPE unarmored | H66: B2.26.05.13.16.01
A67: =H67 -> B2.26.05.13.16.02 | B67: كابل نحاس أحادي القلب جهد 15 ك.ف غير مسلح (3x1Cx50mm²,Cu/LLDPE/PVC). | C67: m | D67: =15*3 -> 45 | G67: Single Core Cables, Copper, 15kV (3x1Cx50mm²,Cu/LLDPE/PVC). | H67: B2.26.05.13.16.02
A68: =H68 -> B2.26.05.13.16.03 | B68: وصلات كيابل مستقيمة جهد 15 ك.ف. 3C x 500 مم2 Al /XLPE/LLDPE غير مسلح | C68: Unit | D68: =D66/500 -> 83 | G68: Straight joints cables for 15KV 3x500mm² AL/XLPE/LLDPE unarmored | H68: B2.26.05.13.16.03
A69: =H69 -> B2.26.05.13.16.04 | B69: نهاية كابل جهد 15 ك.ف. 3C x 500 مم2 Al /XLPE/LLDPE | C69: Unit | D69: =6*2+6*2+3*2 -> 30 | G69: Cable Termination for 15KV 3Cx500mm² AL/XLPE/LLDPE | H69: B2.26.05.13.16.04
A70: =H70 -> B2.26.05.13.16.05 | B70: كيبل جهد 36 ك.ف.400*3C مم2 AL/ XLPE/ LLDPE غير مسلح | C70: m | D70: 23760 | G70: Cable: 36KV 3Cx400mm² AL/XLPE/LLDPE unarmored | H70: B2.26.05.13.16.05
A71: =H71 -> B2.26.05.13.16.06 | B71: كابل نحاس أحادي القلب جهد 36 ك.ف غير مسلح (3x1Cx50mm²,Cu/LLDPE/PVC). | C71: m | D71: =15*2 -> 30 | G71: Single Core Cables, Copper, 36kV (3x1Cx50mm²,Cu/LLDPE/PVC). | H71: B2.26.05.13.16.06
A72: =H72 -> B2.26.05.13.16.07 | B72: وصلات كيابل مستقيمة جهد 36 ك.ف. 3C x 400 مم2 Al /XLPE/LLDPE غير مسلح | C72: Unit | D72: =D70/500 -> 48 | G72: Straight joints cables for 36KV 3x400mm² AL/XLPE/LLDPE unarmored | H72: B2.26.05.13.16.07
A73: =H73 -> B2.26.05.13.16.08 | B73: نهاية كابل جهد 36 ك.ف. 3C x 400 مم2 Al /XLPE/LLDPE | C73: Unit | D73: =6*2+6*2+2*2 -> 28 | G73: Cable Termination for 36KV 3Cx400mm² AL/XLPE/LLDPE | H73: B2.26.05.13.16.08
B75: يتم ترحيل شبكة التوزيع الكهربائية - إلى التجميع | C75: ريال سعودي | F75: =E75+D75 -> 0 | G75: CARRIED TO ELECTRICAL DISTRIBUTION NETWORK - COLLECTION
A76: =H76 -> 26 13 00 | B76: مفاتيح الجهد المتوسط | F76: =E76+D76 -> 0 | G76: MEDIUM VOLTAGE SWITCHGEARS | H76: 26 13 00
A77: =H77 -> B2.26 13 00.01 | B77: مفتاح جهد متوسط (13.8 ك.ف) (وحدة الربط الحلقي) لنقاط الفتح بين المغذيات (NOP) من النوع الخارجي طبقاً لمواصفات الشركة السعودية للكهرباء ومتطلباتها | C77: Unit | D77: 4 | G77: Normally Open Point (R M U) 13.8 kv for Outdoor type according to the Saudi Electric Company specifications and requirements | H77: B2.26 13 00.01
A78: =H78 -> B2.26 13 00.02 | B78: مفتاح جهد متوسط (33 ك.ف) (وحدة الربط الحلقي) لنقاط الفتح بين المغذيات (NOP) من النوع الخارجي طبقاً لمواصفات الشركة السعودية للكهرباء ومتطلباتها | C78: Unit | D78: 2 | G78: Normally Open Point (R M U) 33 kv for Outdoor type according to the Saudi Electric Company specifications and requirements | H78: B2.26 13 00.02
B79: إنارة الطرق | F79: =E79+D79 -> 0 | G79: ROAD LIGHTING
A80: =H80 -> 26 11 16 | B80: محطات الإنارة | F80: =E80+D80 -> 0 | G80: STREET LIGHTING SUB-STATION | H80: 26 11 16
A81: =H81 -> B2.26 11 16.01 | B81: محطة مصندقة 13.8/0.4 ك ف ، 500 ك.ف .ا, شاملة القواعد الخرسانية والسياج .حسب مواصفات ومعايير شركة الكهرباء | C81: Unit | D81: 3 | G81: Unit Substation 13.8/0.4 K V, 500kVA ,Including concrete foundations and fencing, According to the specifications and standards of SEC | H81: B2.26 11 16.01
A82: =H82 -> B2.26 11 16.02 | B82: وحدة الجهد المتوسط الحلقية الالية 13.8 ك ف , RMU. حسب مواصفات ومعايير شركة الكهرباء | C82: Unit | D82: =D81 -> 3 | G82: Ring Main Unit RMU, 13.8KV, According to the specifications and standards of SEC | H82: B2.26 11 16.02
A83: =H83 -> B2.26 11 16.03 | B83: محطة مصندقة 33/0.4 ك ف ، 500 ك.ف .ا, شاملة القواعد الخرسانية والسياج .حسب مواصفات ومعايير شركة الكهرباء | C83: Unit | D83: 2 | G83: Unit Substation 33/0.4 K V, 500kVA ,Including concrete foundations and fencing, According to the specifications and standards of SEC | H83: B2.26 11 16.03
A84: =H84 -> B2.26 11 16.04 | B84: وحدة الجهد المتوسط الحلقية الالية 33 ك ف , RMU. حسب مواصفات ومعايير شركة الكهرباء | C84: Unit | D84: =D83 -> 2 | G84: Ring Main Unit RMU, 33KV, According to the specifications and standards of SEC | H84: B2.26 11 16.04
A85: =H85 -> 26 05 19 | B85: كابلات الضغط المنخفض | F85: =E85+D85 -> 0 | G85: LOW VOLTAGE CABLES | H85: 26 05 19
A86: =H86 -> B2.26 05 19.01 | B86: كابل الومنيوم, (4Cx185mm²,AL/XLPE/PVC). | C86: m | D86: 100 | G86: Cables, Aluminium, (4Cx185mm²,AL/XLPE/PVC). | H86: B2.26 05 19.01
A87: =H87 -> B2.26 05 19.02 | B87: كابل نحاس, (4Cx50mm²,Cu/XLPE/SWA/PVC + 1x25mm² PVC/ECC). | C87: m | D87: 50 | G87: Cables, Copper, (4Cx50mm²,Cu/XLPE/SWA/PVC + 1x25mm² PVC/ECC). | H87: B2.26 05 19.02
A88: =H88 -> B2.26 05 19.03 | B88: كابل نحاس, (4Cx95mm²,Cu/XLPE/SWA/PVC + 1x50mm² PVC/ECC). | C88: m | D88: 7240 | G88: Cables, Copper, (4Cx95mm²,Cu/XLPE/SWA/PVC + 1x50mm² PVC/ECC). | H88: B2.26 05 19.03
A89: =H89 -> B2.26 05 19.04 | B89: كابل نحاس, (4Cx16mm²,Cu/XLPE/SWA/PVC +1x10mm² PVC/PVC) | C89: m | D89: 57370 | G89: Cables, Copper, (4Cx16mm²,Cu/XLPE/SWA/PVC +1x10mm² PVC/PVC) | H89: B2.26 05 19.04
A90: =H90 -> 26 27 33 | B90: لوحات توزيع الجهد المنخفض | F90: =E90+D90 -> 0 | G90: LOW VOLTAGE DISTRIBUTION PANEL | H90: 26 27 33
A91: =H91 -> B2.26 27 33.01 | B91: كابينه توزيع الجهد المنخفض Main: 100A, MCCB | C91: Unit | D91: 5 | G91: 100A MCCB Low Voltage Distribution Cabinet. | H91: B2.26 27 33.01
B97: يتم ترحيل شبكة التوزيع الكهربائية - إلى التجميع | C97: ريال سعودي | F97: =E97+D97 -> 0 | G97: CARRIED TO ELECTRICAL DISTRIBUTION NETWORK - COLLECTION
A98: =H98 -> 26 56 19 | B98: أعمدة إنارة | F98: =E98+D98 -> 0 | G98: LIGHTING POLES | H98: 26 56 19
A99: =H99 -> B2.26 56 19.01 | B99: أعمدة أنارة مع ذراعين ، إرتفاع 16 متر، تشمل علبة توزيع الطاقة والكوابل، والقاعدة الخرسانية | C99: Unit | D99: 107 | G99: Lighting poles with double arm, height of ( 16 ) meters, including the power distribution box, cables , and RCC foundation. | H99: B2.26 56 19.01
A100: =H100 -> B2.26 56 19.02 | B100: أعمدة أنارة مع ذراع واحد ، إرتفاع 16 متر، تشمل علبة توزيع الطاقة والكوابل، والقاعدة الخرسانية | C100: Unit | D100: 8 | G100: Lighting poles with single arm, height of ( 16 ) meters, including the power distribution box, cables , and RCC foundation. | H100: B2.26 56 19.02
